Workbook

Sheet Cover
B2: EVOLUTE
B4: Financial Model — 2027–2030
B6: Currency: EUR (€)
B7: Basis: monthly, aggregated to annual
B8: STRICTLY CONFIDENTIAL
B10: Contents
B11: Assumptions — all inputs & business drivers (edit here only)
B12: Revenue forecast — Growth Capital & M&A deal engine
B13: Personnel — headcount & salaries
B14: OPEX — operating costs
B15: Financial Statements — income statement
B16: Dashboard — annual summary

Sheet How to read me
B2: How to read this model
B4: STRUCTURE
B5: Assumptions → Revenue forecast → Personnel → OPEX → Financial Statements → Dashboard.
B6: Every tab is monthly (Jan 2027 – Dec 2030) with annual roll-up columns at the far right.
B8: HOW TO USE
B9: Change numbers ONLY on the Assumptions tab. All other tabs recalculate automatically.
B11: REVENUE LOGIC
B12: Two business lines: Growth Capital (retainer + success fee on ticket) and M&A (retainer + success fee on EV).
B13: Deals get bigger (M&A EV) and convert better over time; mix drifts 90/10 → 50/50.
B14: Industry partners source 25% of deals and take 25% of their retainer + fee.
B16: STAFFING
B17: 1 analyst per 3 live projects; associate at 10 live, 2nd at 15. Simon = delivery lead, Rob = partner + sales hire.

Sheet Assumptions
B1: Assumptions — Evolute (€) | C1: 2027 | D1: 2028 | E1: 2029 | F1: 2030
B2: GROWTH CAPITAL
B3: Retainer / month | C3: 7000 | D3: 7500 | E3: 8000 | F3: 8500 | G3: €/mo
B4: Avg engagement length | C4: 6 | D4: 6 | E4: 6 | F4: 6 | G4: months
B5: Success fee % | C5: 0.02 | D5: 0.02 | E5: 0.02 | F5: 0.02 | G5: %
B6: Ticket size | C6: 5000000 | D6: 7000000 | E6: 10000000 | F6: 15000000 | G6: €
B7: Close rate % | C7: 0.2 | D7: 0.25 | E7: 0.28 | F7: 0.32 | G7: %
B9: M&A
B10: Retainer / month | C10: 8000 | D10: 8500 | E10: 8500 | F10: 9000 | G10: €/mo
B11: Avg engagement length | C11: 7 | D11: 7 | E11: 7 | F11: 7 | G11: months
B12: Success fee % | C12: 0.02 | D12: 0.02 | E12: 0.02 | F12: 0.02 | G12: %
B13: Enterprise value | C13: 12000000 | D13: 18000000 | E13: 24000000 | F13: 30000000 | G13: €
B14: Close rate % | C14: 0.5 | D14: 0.56 | E14: 0.63 | F14: 0.7 | G14: %
B16: DEAL FLOW
B17: New deals started / yr | C17: 15 | D17: 20 | E17: 25 | F17: 30 | G17: #
B18: Growth Capital mix % | C18: 0.7 | D18: 0.6 | E18: 0.65 | F18: 0.5 | G18: % | H18: Explanation: The percentage of all new deals that are Growth Capital projects
B20: SOURCING & COMPENSATION
B21: Industry-partner: share of deals they source % | C21: 0.3 | D21: 0.35 | E21: 0.4 | F21: 0.45 | G21: % | H21: Explanation: The fraction of deals that are sourced by industry partners
B22: Sales-hire source share % | C22: 0.375 | D22: 0.4 | E22: 0.42 | F22: 0.44 | G22: % | H22: Explanation: The fraction of deals sourced by internal sales team
B23: Industry-partner: cut of those deals' revenue % | C23: 0.25 | D23: 0.25 | E23: 0.25 | F23: 0.25 | G23: % | H23: Explanation: When an industry partner refers a deal, they take 25% of the revenue on that deal (retainer + success fee)
B24: Success-fee bonus pool % | C24: 0.4 | D24: 0.4 | E24: 0.4 | F24: 0.4 | G24: % | H24: Explanation: 40% of success fees (after the partner cut when applicable) goes into the internal bonus pool for the team. The other 60% drops to the firm's bottom line
B26: PERSONNEL
B27: Rob salary / month | C27: =10000*(C$1-2026) -> 10000 | D27: =C27+2000 -> 12000 | E27: =D27+2000 -> 14000 | F27: =E27+2000 -> 16000 | G27: €/mo
B28: Simon salary / month | C28: 7500 | D28: =C28+2000 -> 9500 | E28: =D28+2000 -> 11500 | F28: =E28+2000 -> 13500 | G28: €/mo
B29: Associate salary / month | C29: 4500 | D29: =C29+250 -> 4750 | E29: =D29+250 -> 5000 | F29: =E29+250 -> 5250 | G29: €/mo
B30: Analyst salary / month | C30: 3000 | D30: =C30+250 -> 3250 | E30: =D30+250 -> 3500 | F30: =E30+250 -> 3750 | G30: €/mo
B31: Intern salary / month | C31: 500 | D31: 600 | E31: 700 | F31: 800 | G31: €/mo
B32: Marketing salary/ month | C32: 5000 | D32: =C32+500 -> 5500 | E32: =D32+500 -> 6000 | F32: =E32+500 -> 6500 | G32: €/mo
B33: Sales hire cost / month | C33: 6500 | D33: 7000 | E33: 7500 | F33: 8000 | G33: €/mo
B34: Holiday pay % | C34: 0.08 | D34: 0.08 | E34: 0.08 | F34: 0.08 | G34: %
B35: Employer tax % | C35: 0.19 | D35: 0.19 | E35: 0.19 | F35: 0.19 | G35: %
B36: Live projects per analyst | C36: 3 | D36: 3 | E36: 3 | F36: 3 | G36: #
B38: Hiring Triggers
B39: Associate trigger 1 (live proj) | C39: 10 | G39: #
B40: Associate trigger 2 (live proj) | C40: 15 | G40: #
B41: Interns (minimum) | C41: 2 | G41: #
B43: OPEX (monthly)
B44: Rent / FTE | C44: 600 | G44: €/FTE
B45: Software / FTE | C45: 120 | G45: €/FTE
B46: Database €/yr (FTE ≤6 / 7–9 / 10–15 / 16+) | C46: 35000 | D46: 40000 | E46: 60000 | F46: 70000 | G46: €/yr
B47: Hardware / FTE | C47: 40 | G47: €/FTE
B48: F&B / FTE | C48: 100 | G48: €/FTE
B49: Marketing & Sales (annual, spread monthly) | C49: 3000 | D49: 4000 | E49: 5000 | F49: 6000 | G49: €/yr
B50: Travel (annual, spread monthly) | C50: 6000 | D50: 6500 | E50: 7000 | F50: 7500 | G50: €/yr
B51: RX allocation (fixed) | C51: 1307 | G51: €/mo
B52: Other (fixed) | C52: 140 | G52: €/mo

Sheet Revenue forecast
B2: Revenue forecast — Monthly 2027–2030 (€)
E3: Unit | F3: 46388 | G3: 46419 | H3: 46447 | I3: 46478 | J3: 46508 | K3: 46539 | L3: 46569 | M3: 46600 | N3: 46631 | O3: 46661 | P3: 46692 | Q3: 46722 | R3: 46753 | S3: 46784 | T3: 46813 | U3: 46844 | V3: 46874 | W3: 46905 | X3: 46935 | Y3: 46966 | Z3: 46997 | AA3: 47027 | AB3: 47058 | AC3: 47088 | AD3: 47119 | AE3: 47150 | AF3: 47178 | AG3: 47209 | AH3: 47239 | AI3: 47270 | AJ3: 47300 | AK3: 47331 | AL3: 47362 | AM3: 47392 | AN3: 47423 | AO3: 47453 | AP3: 47484 | AQ3: 47515 | AR3: 47543 | AS3: 47574 | AT3: 47604 | AU3: 47635 | AV3: 47665 | AW3: 47696 | AX3: 47727 | AY3: 47757 | AZ3: 47788 | BA3: 47818 | BC3: 2027 | BD3: 2028 | BE3: 2029 | BF3: 2030
B6: GROWTH CAPITAL
B7: New deals started | E7: # | F7: {=ROUND((INDEX(Assumptions!$C$17:$F$17,MATCH(YEAR(F$3),Assumptions!$C$1:$F$1,0))*INDEX(Assumptions!$C$18:$F$18,MATCH(YEAR(F$3),Assumptions!$C$1:$F$1,0)))*MONTH(F$3)/12,0)-ROUND((INDEX(Assumptions!$C$17:$F$17,MATCH(YEAR(F$3),Assumptions!$C$1:$F$1,0))*INDEX(Assumptions!$C$18:$F$18,MATCH(YEAR(F$3),Assumptions!$C$1:$F$1,0)))*(MONTH(F$3)-1)/12,0)} -> 1 | G7: {=ROUND((INDEX(Assumptions!$C$17:$F$17,MATCH(YEAR(G$3),Assumptions!$C$1:$F$1,0))*INDEX(Assumptions!$C$18:$F$18,MATCH(YEAR(G$3),Assumptions!$C$1:$F$1,0)))*MONTH(G$3)/12,0)-ROUND((INDEX(Assumptions!$C$17:$F$17,MATCH(YEAR(G$3),Assumptions!$C$1:$F$1,0))*INDEX(Assumptions!$C$18:$F$18,MATCH(YEAR(G$3),Assumptions!$C$1:$F$1,0)))*(MONTH(G$3)-1)/12,0)} -> 1 | H7: {=ROUND((INDEX(Assumptions!$C$17:$F$17,MATCH(YEAR(H$3),Assumptions!$C$1:$F$1,0))*INDEX(Assumptions!$C$18:$F$18,MATCH(YEAR(H$3),Assumptions!$C$1:$F$1,0)))*MONTH(H$3)/12,0)-ROUND((INDEX(Assumptions!$C$17:$F$17,MATCH(YEAR(H$3),Assumptions!$C$1:$F$1,0))*INDEX(Assumptions!$C$18:$F$18,MATCH(YEAR(H$3),Assumptions!$C$1:$F$1,0)))*(MONTH(H$3)-1)/12,0)} -> 1 | I7: {=ROUND((INDEX(Assumptions!$C$17:$F$17,MATCH(YEAR(I$3),Assumptions!$C$1:$F$1,0))*INDEX(Assumptions!$C$18:$F$18,MATCH(YEAR(I$3),Assumptions!$C$1:$F$1,0)))*MONTH(I$3)/12,0)-ROUND((INDEX(Assumptions!$C$17:$F$17,MATCH(YEAR(I$3),Assumptions!$C$1:$F$1,0))*INDEX(Assumptions!$C$18:$F$18,MATCH(YEAR(I$3),Assumptions!$C$1:$F$1,0)))*(MONTH(I$3)-1)/12,0)} -> 1 | J7: {=ROUND((INDEX(Assumptions!$C$17:$F$17,MATCH(YEAR(J$3),Assumptions!$C$1:$F$1,0))*INDEX(Assumptions!$C$18:$F$18,MATCH(YEAR(J$3),Assumptions!$C$1:$F$1,0)))*MONTH(J$3)/12,0)-ROUND((INDEX(Assumptions!$C$17:$F$17,MATCH(YEAR(J$3),Assumptions!$C$1:$F$1,0))*INDEX(Assumptions!$C$18:$F$18,MATCH(YEAR(J$3),Assumptions!$C$1:$F$1,0)))*(MONTH(J$3)-1)/12,0)} -> 0 | K7: {=ROUND((INDEX(Assumptions!$C$17:$F$17,MATCH(YEAR(K$3),Assumptions!$C$1:$F$1,0))*INDEX(Assumptions!$C$18:$F$18,MATCH(YEAR(K$3),Assumptions!$C$1:$F$1,0)))*MONTH(K$3)/12,0)-ROUND((INDEX(Assumptions!$C$17:$F$17,MATCH(YEAR(K$3),Assumptions!$C$1:$F$1,0))*INDEX(Assumptions!$C$18:$F$18,MATCH(YEAR(K$3),Assumptions!$C$1:$F$1,0)))*(MONTH(K$3)-1)/12,0)} -> 1 | L7: {=ROUND((INDEX(Assumptions!$C$17:$F$17,MATCH(YEAR(L$3),Assumptions!$C$1:$F$1,0))*INDEX(Assumptions!$C$18:$F$18,MATCH(YEAR(L$3),Assumptions!$C$1:$F$1,0)))*MONTH(L$3)/12,0)-ROUND((INDEX(Assumptions!$C$17:$F$17,MATCH(YEAR(L$3),Assumptions!$C$1:$F$1,0))*INDEX(Assumptions!$C$18:$F$18,MATCH(YEAR(L$3),Assumptions!$C$1:$F$1,0)))*(MONTH(L$3)-1)/12,0)} -> 1 | M7: {=ROUND((INDEX(Assumptions!$C$17:$F$17,MATCH(YEAR(M$3),Assumptions!$C$1:$F$1,0))*INDEX(Assumptions!$C$18:$F$18,MATCH(YEAR(M$3),Assumptions!$C$1:$F$1,0)))*MONTH(M$3)/12,0)-ROUND((INDEX(Assumptions!$C$17:$F$17,MATCH(YEAR(M$3),Assumptions!$C$1:$F$1,0))*INDEX(Assumptions!$C$18:$F$18,MATCH(YEAR(M$3),Assumptions!$C$1:$F$1,0)))*(MONTH(M$3)-1)/12,0)} -> 1 | ... BA7: {=ROUND((INDEX(Assumptions!$C$17:$F$17,MATCH(YEAR(BA$3),Assumptions!$C$1:$F$1,0))*INDEX(Assumptions!$C$18:$F$18,MATCH(YEAR(BA$3),Assumptions!$C$1:$F$1,0)))*MONTH(BA$3)/12,0)-ROUND((INDEX(Assumptions!$C$17:$F$17,MATCH(YEAR(BA$3),Assumptions!$C$1:$F$1,0))*INDEX(Assumptions!$C$18:$F$18,MATCH(YEAR(BA$3),Assumptions!$C$1:$F$1,0)))*(MONTH(BA$3)-1)/12,0)} -> 1 | BC7: =SUMPRODUCT((YEAR($F$3:$BA$3)=BC$3)*$F7:$BA7) -> 11 | BD7: =SUMPRODUCT((YEAR($F$3:$BA$3)=BD$3)*$F7:$BA7) -> 12 | BE7: =SUMPRODUCT((YEAR($F$3:$BA$3)=BE$3)*$F7:$BA7) -> 16 | BF7: =SUMPRODUCT((YEAR($F$3:$BA$3)=BF$3)*$F7:$BA7) -> 15
B8: Live projects | E8: # | F8: =SUM(F7)+F33 -> 4 | G8: =SUM(F7:G7)+G33 -> 5 | H8: =SUM(F7:H7)+H33 -> 4 | I8: =SUM(F7:I7)+I33 -> 5 | J8: =SUM(F7:J7) -> 4 | K8: =SUM(G7:K7) -> 4 | L8: =SUM(H7:L7) -> 4 | M8: =SUM(I7:M7) -> 4 | N8: =SUM(J7:N7) -> 4 | O8: =SUM(K7:O7) -> 5 | P8: =SUM(L7:P7) -> 5 | Q8: =SUM(M7:Q7) -> 5 | ... BA8: =SUM(AW7:BA7) -> 6
B9: Retainer revenue | E9: € | F9: {=F8*INDEX(Assumptions!$C$3:$F$3,MATCH(YEAR(F$3),Assumptions!$C$1:$F$1,0))} -> 28000 | G9: {=G8*INDEX(Assumptions!$C$3:$F$3,MATCH(YEAR(G$3),Assumptions!$C$1:$F$1,0))} -> 35000 | H9: {=H8*INDEX(Assumptions!$C$3:$F$3,MATCH(YEAR(H$3),Assumptions!$C$1:$F$1,0))} -> 28000 | I9: {=I8*INDEX(Assumptions!$C$3:$F$3,MATCH(YEAR(I$3),Assumptions!$C$1:$F$1,0))} -> 35000 | J9: {=J8*INDEX(Assumptions!$C$3:$F$3,MATCH(YEAR(J$3),Assumptions!$C$1:$F$1,0))} -> 28000 | K9: {=K8*INDEX(Assumptions!$C$3:$F$3,MATCH(YEAR(K$3),Assumptions!$C$1:$F$1,0))} -> 28000 | L9: {=L8*INDEX(Assumptions!$C$3:$F$3,MATCH(YEAR(L$3),Assumptions!$C$1:$F$1,0))} -> 28000 | M9: {=M8*INDEX(Assumptions!$C$3:$F$3,MATCH(YEAR(M$3),Assumptions!$C$1:$F$1,0))} -> 28000 | ... BA9: {=BA8*INDEX(Assumptions!$C$3:$F$3,MATCH(YEAR(BA$3),Assumptions!$C$1:$F$1,0))} -> 51000 | BC9: =SUMPRODUCT((YEAR($F$3:$BA$3)=BC$3)*$F9:$BA9) -> 371000 | BD9: =SUMPRODUCT((YEAR($F$3:$BA$3)=BD$3)*$F9:$BA9) -> 450000 | BE9: =SUMPRODUCT((YEAR($F$3:$BA$3)=BE$3)*$F9:$BA9) -> 624000 | BF9: =SUMPRODUCT((YEAR($F$3:$BA$3)=BF$3)*$F9:$BA9) -> 637500
B10: Deals closed | E10: # | F10: 0 | G10: =G34 -> 1 | H10: 0 | I10: 0 | J10: 0 | K10: {=F7*INDEX(Assumptions!$C$7:$F$7,MATCH(YEAR(K$3),Assumptions!$C$1:$F$1,0))} -> 0.2 | L10: {=G7*INDEX(Assumptions!$C$7:$F$7,MATCH(YEAR(L$3),Assumptions!$C$1:$F$1,0))} -> 0.2 | M10: {=H7*INDEX(Assumptions!$C$7:$F$7,MATCH(YEAR(M$3),Assumptions!$C$1:$F$1,0))} -> 0.2 | N10: {=I7*INDEX(Assumptions!$C$7:$F$7,MATCH(YEAR(N$3),Assumptions!$C$1:$F$1,0))} -> 0.2 | O10: {=J7*INDEX(Assumptions!$C$7:$F$7,MATCH(YEAR(O$3),Assumptions!$C$1:$F$1,0))} -> 0 | P10: {=K7*INDEX(Assumptions!$C$7:$F$7,MATCH(YEAR(P$3),Assumptions!$C$1:$F$1,0))} -> 0.2 | Q10: {=L7*INDEX(Assumptions!$C$7:$F$7,MATCH(YEAR(Q$3),Assumptions!$C$1:$F$1,0))} -> 0.2 | R10: {=M7*INDEX(Assumptions!$C$7:$F$7,MATCH(YEAR(R$3),Assumptions!$C$1:$F$1,0))} -> 0.25 | ... BA10: {=AV7*INDEX(Assumptions!$C$7:$F$7,MATCH(YEAR(BA$3),Assumptions!$C$1:$F$1,0))} -> 0.32 | BC10: =SUMPRODUCT((YEAR($F$3:$BA$3)=BC$3)*$F10:$BA10) -> 2.2 | BD10: =SUMPRODUCT((YEAR($F$3:$BA$3)=BD$3)*$F10:$BA10) -> 3 | BE10: =SUMPRODUCT((YEAR($F$3:$BA$3)=BE$3)*$F10:$BA10) -> 3.92 | BF10: =SUMPRODUCT((YEAR($F$3:$BA$3)=BF$3)*$F10:$BA10) -> 5.12
B11: Success fees | E11: € | F11: {=F10*(INDEX(Assumptions!$C$6:$F$6,MATCH(YEAR(F$3),Assumptions!$C$1:$F$1,0))*Assumptions!$C$5)} -> 0 | G11: {=G10*(INDEX(Assumptions!$C$6:$F$6,MATCH(YEAR(G$3),Assumptions!$C$1:$F$1,0))*Assumptions!$C$5)} -> 100000 | H11: {=H10*(INDEX(Assumptions!$C$6:$F$6,MATCH(YEAR(H$3),Assumptions!$C$1:$F$1,0))*Assumptions!$C$5)} -> 0 | I11: {=I10*(INDEX(Assumptions!$C$6:$F$6,MATCH(YEAR(I$3),Assumptions!$C$1:$F$1,0))*Assumptions!$C$5)} -> 0 | J11: {=J10*(INDEX(Assumptions!$C$6:$F$6,MATCH(YEAR(J$3),Assumptions!$C$1:$F$1,0))*Assumptions!$C$5)} -> 0 | K11: {=K10*(INDEX(Assumptions!$C$6:$F$6,MATCH(YEAR(K$3),Assumptions!$C$1:$F$1,0))*Assumptions!$C$5)} -> 20000 | L11: {=L10*(INDEX(Assumptions!$C$6:$F$6,MATCH(YEAR(L$3),Assumptions!$C$1:$F$1,0))*Assumptions!$C$5)} -> 20000 | M11: {=M10*(INDEX(Assumptions!$C$6:$F$6,MATCH(YEAR(M$3),Assumptions!$C$1:$F$1,0))*Assumptions!$C$5)} -> 20000 | ... BA11: {=BA10*(INDEX(Assumptions!$C$6:$F$6,MATCH(YEAR(BA$3),Assumptions!$C$1:$F$1,0))*Assumptions!$C$5)} -> 96000 | BC11: =SUMPRODUCT((YEAR($F$3:$BA$3)=BC$3)*$F11:$BA11) -> 220000 | BD11: =SUMPRODUCT((YEAR($F$3:$BA$3)=BD$3)*$F11:$BA11) -> 420000 | BE11: =SUMPRODUCT((YEAR($F$3:$BA$3)=BE$3)*$F11:$BA11) -> 784000 | BF11: =SUMPRODUCT((YEAR($F$3:$BA$3)=BF$3)*$F11:$BA11) -> 1536000
B12: Total Growth revenue | E12: € | F12: =F9+F11 -> 28000 | G12: =G9+G11 -> 135000 | H12: =H9+H11 -> 28000 | I12: =I9+I11 -> 35000 | J12: =J9+J11 -> 28000 | K12: =K9+K11 -> 48000 | L12: =L9+L11 -> 48000 | M12: =M9+M11 -> 48000 | ... BA12: =BA9+BA11 -> 147000 | BC12: =SUMPRODUCT((YEAR($F$3:$BA$3)=BC$3)*$F12:$BA12) -> 591000 | BD12: =SUMPRODUCT((YEAR($F$3:$BA$3)=BD$3)*$F12:$BA12) -> 870000 | BE12: =SUMPRODUCT((YEAR($F$3:$BA$3)=BE$3)*$F12:$BA12) -> 1408000 | BF12: =SUMPRODUCT((YEAR($F$3:$BA$3)=BF$3)*$F12:$BA12) -> 2173500
B14: M&A
B15: New deals started | E15: # | F15: {=ROUND(INDEX(Assumptions!$C$17:$F$17,MATCH(YEAR(F$3),Assumptions!$C$1:$F$1,0))*MONTH(F$3)/12,0)-ROUND(INDEX(Assumptions!$C$17:$F$17,MATCH(YEAR(F$3),Assumptions!$C$1:$F$1,0))*(MONTH(F$3)-1)/12,0)-F7} -> 0 | G15: {=ROUND(INDEX(Assumptions!$C$17:$F$17,MATCH(YEAR(G$3),Assumptions!$C$1:$F$1,0))*MONTH(G$3)/12,0)-ROUND(INDEX(Assumptions!$C$17:$F$17,MATCH(YEAR(G$3),Assumptions!$C$1:$F$1,0))*(MONTH(G$3)-1)/12,0)-G7} -> 1 | H15: {=ROUND(INDEX(Assumptions!$C$17:$F$17,MATCH(YEAR(H$3),Assumptions!$C$1:$F$1,0))*MONTH(H$3)/12,0)-ROUND(INDEX(Assumptions!$C$17:$F$17,MATCH(YEAR(H$3),Assumptions!$C$1:$F$1,0))*(MONTH(H$3)-1)/12,0)-H7} -> 0 | I15: {=ROUND(INDEX(Assumptions!$C$17:$F$17,MATCH(YEAR(I$3),Assumptions!$C$1:$F$1,0))*MONTH(I$3)/12,0)-ROUND(INDEX(Assumptions!$C$17:$F$17,MATCH(YEAR(I$3),Assumptions!$C$1:$F$1,0))*(MONTH(I$3)-1)/12,0)-I7} -> 0 | J15: {=ROUND(INDEX(Assumptions!$C$17:$F$17,MATCH(YEAR(J$3),Assumptions!$C$1:$F$1,0))*MONTH(J$3)/12,0)-ROUND(INDEX(Assumptions!$C$17:$F$17,MATCH(YEAR(J$3),Assumptions!$C$1:$F$1,0))*(MONTH(J$3)-1)/12,0)-J7} -> 1 | K15: {=ROUND(INDEX(Assumptions!$C$17:$F$17,MATCH(YEAR(K$3),Assumptions!$C$1:$F$1,0))*MONTH(K$3)/12,0)-ROUND(INDEX(Assumptions!$C$17:$F$17,MATCH(YEAR(K$3),Assumptions!$C$1:$F$1,0))*(MONTH(K$3)-1)/12,0)-K7} -> 1 | L15: {=ROUND(INDEX(Assumptions!$C$17:$F$17,MATCH(YEAR(L$3),Assumptions!$C$1:$F$1,0))*MONTH(L$3)/12,0)-ROUND(INDEX(Assumptions!$C$17:$F$17,MATCH(YEAR(L$3),Assumptions!$C$1:$F$1,0))*(MONTH(L$3)-1)/12,0)-L7} -> 0 | M15: {=ROUND(INDEX(Assumptions!$C$17:$F$17,MATCH(YEAR(M$3),Assumptions!$C$1:$F$1,0))*MONTH(M$3)/12,0)-ROUND(INDEX(Assumptions!$C$17:$F$17,MATCH(YEAR(M$3),Assumptions!$C$1:$F$1,0))*(MONTH(M$3)-1)/12,0)-M7} -> 0 | ... BA15: {=ROUND(INDEX(Assumptions!$C$17:$F$17,MATCH(YEAR(BA$3),Assumptions!$C$1:$F$1,0))*MONTH(BA$3)/12,0)-ROUND(INDEX(Assumptions!$C$17:$F$17,MATCH(YEAR(BA$3),Assumptions!$C$1:$F$1,0))*(MONTH(BA$3)-1)/12,0)-BA7} -> 1 | BC15: =SUMPRODUCT((YEAR($F$3:$BA$3)=BC$3)*$F15:$BA15) -> 4 | BD15: =SUMPRODUCT((YEAR($F$3:$BA$3)=BD$3)*$F15:$BA15) -> 8 | BE15: =SUMPRODUCT((YEAR($F$3:$BA$3)=BE$3)*$F15:$BA15) -> 9 | BF15: =SUMPRODUCT((YEAR($F$3:$BA$3)=BF$3)*$F15:$BA15) -> 15
B16: Live projects | E16: # | F16: =SUM(F15) -> 0 | G16: =SUM(F15:G15) -> 1 | H16: =SUM(F15:H15) -> 1 | I16: =SUM(F15:I15) -> 1 | J16: =SUM(F15:J15) -> 2 | K16: =SUM(F15:K15) -> 3 | L16: =SUM(F15:L15) -> 3 | M16: =SUM(G15:M15) -> 3 | N16: =SUM(H15:N15) -> 2 | O16: =SUM(I15:O15) -> 3 | P16: =SUM(J15:P15) -> 3 | Q16: =SUM(K15:Q15) -> 2 | R16: =SUM(L15:R15) -> 2 | S16: =SUM(M15:S15) -> 2 | ... BA16: =SUM(AU15:BA15) -> 8
B17: Retainer revenue | E17: € | F17: {=F16*INDEX(Assumptions!$C$10:$F$10,MATCH(YEAR(F$3),Assumptions!$C$1:$F$1,0))} -> 0 | G17: {=G16*INDEX(Assumptions!$C$10:$F$10,MATCH(YEAR(G$3),Assumptions!$C$1:$F$1,0))} -> 8000 | H17: {=H16*INDEX(Assumptions!$C$10:$F$10,MATCH(YEAR(H$3),Assumptions!$C$1:$F$1,0))} -> 8000 | I17: {=I16*INDEX(Assumptions!$C$10:$F$10,MATCH(YEAR(I$3),Assumptions!$C$1:$F$1,0))} -> 8000 | J17: {=J16*INDEX(Assumptions!$C$10:$F$10,MATCH(YEAR(J$3),Assumptions!$C$1:$F$1,0))} -> 16000 | K17: {=K16*INDEX(Assumptions!$C$10:$F$10,MATCH(YEAR(K$3),Assumptions!$C$1:$F$1,0))} -> 24000 | L17: {=L16*INDEX(Assumptions!$C$10:$F$10,MATCH(YEAR(L$3),Assumptions!$C$1:$F$1,0))} -> 24000 | M17: {=M16*INDEX(Assumptions!$C$10:$F$10,MATCH(YEAR(M$3),Assumptions!$C$1:$F$1,0))} -> 24000 | ... BA17: {=BA16*INDEX(Assumptions!$C$10:$F$10,MATCH(YEAR(BA$3),Assumptions!$C$1:$F$1,0))} -> 72000 | BC17: =SUMPRODUCT((YEAR($F$3:$BA$3)=BC$3)*$F17:$BA17) -> 192000 | BD17: =SUMPRODUCT((YEAR($F$3:$BA$3)=BD$3)*$F17:$BA17) -> 391000 | BE17: =SUMPRODUCT((YEAR($F$3:$BA$3)=BE$3)*$F17:$BA17) -> 527000 | BF17: =SUMPRODUCT((YEAR($F$3:$BA$3)=BF$3)*$F17:$BA17) -> 846000
B18: Deals closed | E18: # | F18: 0 | G18: 0 | H18: 0 | I18: 0 | J18: 0 | K18: 0 | L18: 0 | M18: {=F15*INDEX(Assumptions!$C$14:$F$14,MATCH(YEAR(M$3),Assumptions!$C$1:$F$1,0))} -> 0 | N18: {=G15*INDEX(Assumptions!$C$14:$F$14,MATCH(YEAR(N$3),Assumptions!$C$1:$F$1,0))} -> 0.5 | O18: {=H15*INDEX(Assumptions!$C$14:$F$14,MATCH(YEAR(O$3),Assumptions!$C$1:$F$1,0))} -> 0 | P18: {=I15*INDEX(Assumptions!$C$14:$F$14,MATCH(YEAR(P$3),Assumptions!$C$1:$F$1,0))} -> 0 | Q18: {=J15*INDEX(Assumptions!$C$14:$F$14,MATCH(YEAR(Q$3),Assumptions!$C$1:$F$1,0))} -> 0.5 | R18: {=K15*INDEX(Assumptions!$C$14:$F$14,MATCH(YEAR(R$3),Assumptions!$C$1:$F$1,0))} -> 0.56 | S18: {=L15*INDEX(Assumptions!$C$14:$F$14,MATCH(YEAR(S$3),Assumptions!$C$1:$F$1,0))} -> 0 | T18: {=M15*INDEX(Assumptions!$C$14:$F$14,MATCH(YEAR(T$3),Assumptions!$C$1:$F$1,0))} -> 0 | ... BA18: {=AT15*INDEX(Assumptions!$C$14:$F$14,MATCH(YEAR(BA$3),Assumptions!$C$1:$F$1,0))} -> 1.4 | BC18: =SUMPRODUCT((YEAR($F$3:$BA$3)=BC$3)*$F18:$BA18) -> 1 | BD18: =SUMPRODUCT((YEAR($F$3:$BA$3)=BD$3)*$F18:$BA18) -> 2.8 | BE18: =SUMPRODUCT((YEAR($F$3:$BA$3)=BE$3)*$F18:$BA18) -> 5.04 | BF18: =SUMPRODUCT((YEAR($F$3:$BA$3)=BF$3)*$F18:$BA18) -> 9.1
B19: Success fees | E19: € | F19: {=F18*(INDEX(Assumptions!$C$13:$F$13,MATCH(YEAR(F$3),Assumptions!$C$1:$F$1,0))*Assumptions!$C$12)} -> 0 | G19: {=G18*(INDEX(Assumptions!$C$13:$F$13,MATCH(YEAR(G$3),Assumptions!$C$1:$F$1,0))*Assumptions!$C$12)} -> 0 | H19: {=H18*(INDEX(Assumptions!$C$13:$F$13,MATCH(YEAR(H$3),Assumptions!$C$1:$F$1,0))*Assumptions!$C$12)} -> 0 | I19: {=I18*(INDEX(Assumptions!$C$13:$F$13,MATCH(YEAR(I$3),Assumptions!$C$1:$F$1,0))*Assumptions!$C$12)} -> 0 | J19: {=J18*(INDEX(Assumptions!$C$13:$F$13,MATCH(YEAR(J$3),Assumptions!$C$1:$F$1,0))*Assumptions!$C$12)} -> 0 | K19: {=K18*(INDEX(Assumptions!$C$13:$F$13,MATCH(YEAR(K$3),Assumptions!$C$1:$F$1,0))*Assumptions!$C$12)} -> 0 | L19: {=L18*(INDEX(Assumptions!$C$13:$F$13,MATCH(YEAR(L$3),Assumptions!$C$1:$F$1,0))*Assumptions!$C$12)} -> 0 | M19: {=M18*(INDEX(Assumptions!$C$13:$F$13,MATCH(YEAR(M$3),Assumptions!$C$1:$F$1,0))*Assumptions!$C$12)} -> 0 | ... BA19: {=BA18*(INDEX(Assumptions!$C$13:$F$13,MATCH(YEAR(BA$3),Assumptions!$C$1:$F$1,0))*Assumptions!$C$12)} -> 840000 | BC19: =SUMPRODUCT((YEAR($F$3:$BA$3)=BC$3)*$F19:$BA19) -> 240000 | BD19: =SUMPRODUCT((YEAR($F$3:$BA$3)=BD$3)*$F19:$BA19) -> 1008000 | BE19: =SUMPRODUCT((YEAR($F$3:$BA$3)=BE$3)*$F19:$BA19) -> 2419200 | BF19: =SUMPRODUCT((YEAR($F$3:$BA$3)=BF$3)*$F19:$BA19) -> 5460000
B20: Total M&A revenue | E20: € | F20: =F17+F19 -> 0 | G20: =G17+G19 -> 8000 | H20: =H17+H19 -> 8000 | I20: =I17+I19 -> 8000 | J20: =J17+J19 -> 16000 | K20: =K17+K19 -> 24000 | L20: =L17+L19 -> 24000 | M20: =M17+M19 -> 24000 | ... BA20: =BA17+BA19 -> 912000 | BC20: =SUMPRODUCT((YEAR($F$3:$BA$3)=BC$3)*$F20:$BA20) -> 432000 | BD20: =SUMPRODUCT((YEAR($F$3:$BA$3)=BD$3)*$F20:$BA20) -> 1399000 | BE20: =SUMPRODUCT((YEAR($F$3:$BA$3)=BE$3)*$F20:$BA20) -> 2946200 | BF20: =SUMPRODUCT((YEAR($F$3:$BA$3)=BF$3)*$F20:$BA20) -> 6306000
B22: TOTAL REVENUE
B23: Total live projects (monthly only) | E23: # | F23: =F8+F16 -> 4 | G23: =G8+G16 -> 6 | H23: =H8+H16 -> 5 | I23: =I8+I16 -> 6 | J23: =J8+J16 -> 6 | K23: =K8+K16 -> 7 | L23: =L8+L16 -> 7 | M23: =M8+M16 -> 7 | ... BA23: =BA8+BA16 -> 14
B24: Total new deals started (annual only) | E24: # | BC24: =BC7+BC15 -> 15 | BD24: =BD7+BD15 -> 20 | BE24: =BE7+BE15 -> 25 | BF24: =BF7+BF15 -> 30
B25: Total retainer | E25: € | F25: =F9+F17 -> 28000 | G25: =G9+G17 -> 43000 | H25: =H9+H17 -> 36000 | I25: =I9+I17 -> 43000 | J25: =J9+J17 -> 44000 | K25: =K9+K17 -> 52000 | L25: =L9+L17 -> 52000 | M25: =M9+M17 -> 52000 | ... BA25: =BA9+BA17 -> 123000 | BC25: =SUMPRODUCT((YEAR($F$3:$BA$3)=BC$3)*$F25:$BA25) -> 563000 | BD25: =SUMPRODUCT((YEAR($F$3:$BA$3)=BD$3)*$F25:$BA25) -> 841000 | BE25: =SUMPRODUCT((YEAR($F$3:$BA$3)=BE$3)*$F25:$BA25) -> 1151000 | BF25: =SUMPRODUCT((YEAR($F$3:$BA$3)=BF$3)*$F25:$BA25) -> 1483500
B26: Total success fees | E26: € | F26: =F11+F19 -> 0 | G26: =G11+G19 -> 100000 | H26: =H11+H19 -> 0 | I26: =I11+I19 -> 0 | J26: =J11+J19 -> 0 | K26: =K11+K19 -> 20000 | L26: =L11+L19 -> 20000 | M26: =M11+M19 -> 20000 | ... BA26: =BA11+BA19 -> 936000 | BC26: =SUMPRODUCT((YEAR($F$3:$BA$3)=BC$3)*$F26:$BA26) -> 460000 | BD26: =SUMPRODUCT((YEAR($F$3:$BA$3)=BD$3)*$F26:$BA26) -> 1428000 | BE26: =SUMPRODUCT((YEAR($F$3:$BA$3)=BE$3)*$F26:$BA26) -> 3203200 | BF26: =SUMPRODUCT((YEAR($F$3:$BA$3)=BF$3)*$F26:$BA26) -> 6996000
B27: Total revenue (gross) | E27: € | F27: =F25+F26 -> 28000 | G27: =G25+G26 -> 143000 | H27: =H25+H26 -> 36000 | I27: =I25+I26 -> 43000 | J27: =J25+J26 -> 44000 | K27: =K25+K26 -> 72000 | L27: =L25+L26 -> 72000 | M27: =M25+M26 -> 72000 | ... BA27: =BA25+BA26 -> 1059000 | BC27: =SUMPRODUCT((YEAR($F$3:$BA$3)=BC$3)*$F27:$BA27) -> 1023000 | BD27: =SUMPRODUCT((YEAR($F$3:$BA$3)=BD$3)*$F27:$BA27) -> 2269000 | BE27: =SUMPRODUCT((YEAR($F$3:$BA$3)=BE$3)*$F27:$BA27) -> 4354200 | BF27: =SUMPRODUCT((YEAR($F$3:$BA$3)=BF$3)*$F27:$BA27) -> 8479500
B28: Less: industry-partner share | E28: € | F28: =-Assumptions!$C$21*Assumptions!$C$23*F27 -> -2100 | G28: =-Assumptions!$C$21*Assumptions!$C$23*G27 -> -10725 | H28: =-Assumptions!$C$21*Assumptions!$C$23*H27 -> -2700 | I28: =-Assumptions!$C$21*Assumptions!$C$23*I27 -> -3225 | J28: =-Assumptions!$C$21*Assumptions!$C$23*J27 -> -3300 | K28: =-Assumptions!$C$21*Assumptions!$C$23*K27 -> -5400 | L28: =-Assumptions!$C$21*Assumptions!$C$23*L27 -> -5400 | M28: =-Assumptions!$C$21*Assumptions!$C$23*M27 -> -5400 | ... BA28: =-Assumptions!$C$21*Assumptions!$C$23*BA27 -> -79425 | BC28: =SUMPRODUCT((YEAR($F$3:$BA$3)=BC$3)*$F28:$BA28) -> -76725 | BD28: =SUMPRODUCT((YEAR($F$3:$BA$3)=BD$3)*$F28:$BA28) -> -170175 | BE28: =SUMPRODUCT((YEAR($F$3:$BA$3)=BE$3)*$F28:$BA28) -> -326565 | BF28: =SUMPRODUCT((YEAR($F$3:$BA$3)=BF$3)*$F28:$BA28) -> -635962.5
B29: Net revenue | E29: € | F29: =F27+F28 -> 25900 | G29: =G27+G28 -> 132275 | H29: =H27+H28 -> 33300 | I29: =I27+I28 -> 39775 | J29: =J27+J28 -> 40700 | K29: =K27+K28 -> 66600 | L29: =L27+L28 -> 66600 | M29: =M27+M28 -> 66600 | ... BA29: =BA27+BA28 -> 979575 | BC29: =SUMPRODUCT((YEAR($F$3:$BA$3)=BC$3)*$F29:$BA29) -> 946275 | BD29: =SUMPRODUCT((YEAR($F$3:$BA$3)=BD$3)*$F29:$BA29) -> 2098825 | BE29: =SUMPRODUCT((YEAR($F$3:$BA$3)=BE$3)*$F29:$BA29) -> 4027635 | BF29: =SUMPRODUCT((YEAR($F$3:$BA$3)=BF$3)*$F29:$BA29) -> 7843537.5
B32: 2027 STARTING PROJECTS — Growth Capital opening pipeline
B33: Live projects (count) | E33: # | F33: 3 | G33: 3 | H33: 1 | I33: 1
B34: Deals closed | E34: # | G34: 1
B35: Success fee on close (memo) | E35: € | G35: {=INDEX(Assumptions!$C$6:$F$6,MATCH(2027,Assumptions!$C$1:$F$1,0))*Assumptions!$C$5} -> 100000
B36: Note: 1 of 3 deals is industry-partner-sourced — IP cut flows through the "Less: industry-partner share" line.

Sheet Personnel
B2: Personnel — Monthly 2027–2030 (€)
E3: Unit | F3: 46388 | G3: 46419 | H3: 46447 | I3: 46478 | J3: 46508 | K3: 46539 | L3: 46569 | M3: 46600 | N3: 46631 | O3: 46661 | P3: 46692 | Q3: 46722 | R3: 46753 | S3: 46784 | T3: 46813 | U3: 46844 | V3: 46874 | W3: 46905 | X3: 46935 | Y3: 46966 | Z3: 46997 | AA3: 47027 | AB3: 47058 | AC3: 47088 | AD3: 47119 | AE3: 47150 | AF3: 47178 | AG3: 47209 | AH3: 47239 | AI3: 47270 | AJ3: 47300 | AK3: 47331 | AL3: 47362 | AM3: 47392 | AN3: 47423 | AO3: 47453 | AP3: 47484 | AQ3: 47515 | AR3: 47543 | AS3: 47574 | AT3: 47604 | AU3: 47635 | AV3: 47665 | AW3: 47696 | AX3: 47727 | AY3: 47757 | AZ3: 47788 | BA3: 47818 | BC3: 2027 | BD3: 2028 | BE3: 2029 | BF3: 2030
B6: HEADCOUNT
B7: Live projects (total) | E7: # | F7: ='Revenue forecast'!F8+'Revenue forecast'!F16 -> 4 | G7: ='Revenue forecast'!G8+'Revenue forecast'!G16 -> 6 | H7: ='Revenue forecast'!H8+'Revenue forecast'!H16 -> 5 | I7: ='Revenue forecast'!I8+'Revenue forecast'!I16 -> 6 | J7: ='Revenue forecast'!J8+'Revenue forecast'!J16 -> 6 | K7: ='Revenue forecast'!K8+'Revenue forecast'!K16 -> 7 | L7: ='Revenue forecast'!L8+'Revenue forecast'!L16 -> 7 | M7: ='Revenue forecast'!M8+'Revenue forecast'!M16 -> 7 | ... BA7: ='Revenue forecast'!BA8+'Revenue forecast'!BA16 -> 14 | BC7: =Q7 -> 7 | BD7: =AC7 -> 10 | BE7: =AO7 -> 13 | BF7: =BA7 -> 14
B8: Analysts | E8: # | F8: {=MAX(1,CEILING(F7/INDEX(Assumptions!$C$36:$F$36,MATCH(YEAR(F$3),Assumptions!$C$1:$F$1,0)),1))} -> 2 | G8: {=MAX(F8,CEILING(G7/INDEX(Assumptions!$C$36:$F$36,MATCH(YEAR(G$3),Assumptions!$C$1:$F$1,0)),1))} -> 2 | H8: {=MAX(G8,CEILING(H7/INDEX(Assumptions!$C$36:$F$36,MATCH(YEAR(H$3),Assumptions!$C$1:$F$1,0)),1))} -> 2 | I8: {=MAX(H8,CEILING(I7/INDEX(Assumptions!$C$36:$F$36,MATCH(YEAR(I$3),Assumptions!$C$1:$F$1,0)),1))} -> 2 | J8: {=MAX(I8,CEILING(J7/INDEX(Assumptions!$C$36:$F$36,MATCH(YEAR(J$3),Assumptions!$C$1:$F$1,0)),1))} -> 2 | K8: {=MAX(J8,CEILING(K7/INDEX(Assumptions!$C$36:$F$36,MATCH(YEAR(K$3),Assumptions!$C$1:$F$1,0)),1))} -> 3 | L8: {=MAX(K8,CEILING(L7/INDEX(Assumptions!$C$36:$F$36,MATCH(YEAR(L$3),Assumptions!$C$1:$F$1,0)),1))} -> 3 | M8: {=MAX(L8,CEILING(M7/INDEX(Assumptions!$C$36:$F$36,MATCH(YEAR(M$3),Assumptions!$C$1:$F$1,0)),1))} -> 3 | N8: {=MAX(M8,CEILING(N7/INDEX(Assumptions!$C$36:$F$36,MATCH(YEAR(N$3),Assumptions!$C$1:$F$1,0)),1))} -> 3 | ... BA8: {=MAX(AZ8,CEILING(BA7/INDEX(Assumptions!$C$36:$F$36,MATCH(YEAR(BA$3),Assumptions!$C$1:$F$1,0)),1))} -> 6 | BC8: =Q8 -> 3 | BD8: =AC8 -> 4 | BE8: =AO8 -> 5 | BF8: =BA8 -> 6
B9: Associates | E9: # | F9: =IF(F7>=Assumptions!$C$40,2,IF(F7>=Assumptions!$C$39,1,0)) -> 0 | G9: =MAX(F9,IF(G7>=Assumptions!$C$40,2,IF(G7>=Assumptions!$C$39,1,0))) -> 0 | H9: =MAX(G9,IF(H7>=Assumptions!$C$40,2,IF(H7>=Assumptions!$C$39,1,0))) -> 0 | I9: =MAX(H9,IF(I7>=Assumptions!$C$40,2,IF(I7>=Assumptions!$C$39,1,0))) -> 0 | J9: =MAX(I9,IF(J7>=Assumptions!$C$40,2,IF(J7>=Assumptions!$C$39,1,0))) -> 0 | K9: =MAX(J9,IF(K7>=Assumptions!$C$40,2,IF(K7>=Assumptions!$C$39,1,0))) -> 0 | L9: =MAX(K9,IF(L7>=Assumptions!$C$40,2,IF(L7>=Assumptions!$C$39,1,0))) -> 0 | M9: =MAX(L9,IF(M7>=Assumptions!$C$40,2,IF(M7>=Assumptions!$C$39,1,0))) -> 0 | N9: =MAX(M9,IF(N7>=Assumptions!$C$40,2,IF(N7>=Assumptions!$C$39,1,0))) -> 0 | ... BA9: =MAX(AZ9,IF(BA7>=Assumptions!$C$40,2,IF(BA7>=Assumptions!$C$39,1,0))) -> 2 | BC9: =Q9 -> 0 | BD9: =AC9 -> 1 | BE9: =AO9 -> 1 | BF9: =BA9 -> 2
B10: Interns | E10: # | F10: =MAX(Assumptions!$C$41,ROUNDDOWN((F8+F9)/3,0)) -> 2 | G10: =MAX(Assumptions!$C$41,ROUNDDOWN((G8+G9)/3,0)) -> 2 | H10: =MAX(Assumptions!$C$41,ROUNDDOWN((H8+H9)/3,0)) -> 2 | I10: =MAX(Assumptions!$C$41,ROUNDDOWN((I8+I9)/3,0)) -> 2 | J10: =MAX(Assumptions!$C$41,ROUNDDOWN((J8+J9)/3,0)) -> 2 | K10: =MAX(Assumptions!$C$41,ROUNDDOWN((K8+K9)/3,0)) -> 2 | L10: =MAX(Assumptions!$C$41,ROUNDDOWN((L8+L9)/3,0)) -> 2 | M10: =MAX(Assumptions!$C$41,ROUNDDOWN((M8+M9)/3,0)) -> 2 | ... BA10: =MAX(Assumptions!$C$41,ROUNDDOWN((BA8+BA9)/3,0)) -> 2 | BC10: =Q10 -> 2 | BD10: =AC10 -> 2 | BE10: =AO10 -> 2 | BF10: =BA10 -> 2
B11: Sales hire | E11: # | F11: 1 | G11: 1 | H11: 1 | I11: 1 | J11: 1 | K11: 1 | L11: 1 | M11: 1 | N11: 1 | O11: 1 | P11: 1 | Q11: 1 | R11: 1 | S11: 1 | T11: 1 | U11: 1 | V11: 1 | W11: 1 | X11: 1 | Y11: 1 | Z11: 1 | AA11: 1 | AB11: 1 | AC11: 1 | AD11: 1 | AE11: 1 | AF11: 1 | AG11: 1 | AH11: 1 | AI11: 1 | AJ11: 1 | AK11: 1 | AL11: 1 | AM11: 1 | AN11: 1 | AO11: 1 | AP11: 1 | AQ11: 1 | AR11: 1 | AS11: 1 | AT11: 1 | AU11: 1 | AV11: 1 | AW11: 1 | AX11: 1 | AY11: 1 | AZ11: 1 | BA11: 1 | BC11: =Q11 -> 1 | BD11: =AC11 -> 1 | BE11: =AO11 -> 1 | BF11: =BA11 -> 1
B12: Marketing | E12: # | F12: 1 | G12: 1 | H12: 1 | I12: 1 | J12: 1 | K12: 1 | L12: 1 | M12: 1 | N12: 1 | O12: 1 | P12: 1 | Q12: 1 | R12: 1 | S12: 1 | T12: 1 | U12: 1 | V12: 1 | W12: 1 | X12: 1 | Y12: 1 | Z12: 1 | AA12: 1 | AB12: 1 | AC12: 1 | AD12: 1 | AE12: 1 | AF12: 1 | AG12: 1 | AH12: 1 | AI12: 1 | AJ12: 1 | AK12: 1 | AL12: 1 | AM12: 1 | AN12: 1 | AO12: 1 | AP12: 1 | AQ12: 1 | AR12: 1 | AS12: 1 | AT12: 1 | AU12: 1 | AV12: 1 | AW12: 1 | AX12: 1 | AY12: 1 | AZ12: 1 | BA12: 1 | BC12: =Q12 -> 1 | BD12: =AC12 -> 1 | BE12: =AO12 -> 1 | BF12: =BA12 -> 1
B13: Rob | E13: # | F13: 1 | G13: 1 | H13: 1 | I13: 1 | J13: 1 | K13: 1 | L13: 1 | M13: 1 | N13: 1 | O13: 1 | P13: 1 | Q13: 1 | R13: 1 | S13: 1 | T13: 1 | U13: 1 | V13: 1 | W13: 1 | X13: 1 | Y13: 1 | Z13: 1 | AA13: 1 | AB13: 1 | AC13: 1 | AD13: 1 | AE13: 1 | AF13: 1 | AG13: 1 | AH13: 1 | AI13: 1 | AJ13: 1 | AK13: 1 | AL13: 1 | AM13: 1 | AN13: 1 | AO13: 1 | AP13: 1 | AQ13: 1 | AR13: 1 | AS13: 1 | AT13: 1 | AU13: 1 | AV13: 1 | AW13: 1 | AX13: 1 | AY13: 1 | AZ13: 1 | BA13: 1 | BC13: =Q13 -> 1 | BD13: =AC13 -> 1 | BE13: =AO13 -> 1 | BF13: =BA13 -> 1
B14: Simon | E14: # | F14: 1 | G14: 1 | H14: 1 | I14: 1 | J14: 1 | K14: 1 | L14: 1 | M14: 1 | N14: 1 | O14: 1 | P14: 1 | Q14: 1 | R14: 1 | S14: 1 | T14: 1 | U14: 1 | V14: 1 | W14: 1 | X14: 1 | Y14: 1 | Z14: 1 | AA14: 1 | AB14: 1 | AC14: 1 | AD14: 1 | AE14: 1 | AF14: 1 | AG14: 1 | AH14: 1 | AI14: 1 | AJ14: 1 | AK14: 1 | AL14: 1 | AM14: 1 | AN14: 1 | AO14: 1 | AP14: 1 | AQ14: 1 | AR14: 1 | AS14: 1 | AT14: 1 | AU14: 1 | AV14: 1 | AW14: 1 | AX14: 1 | AY14: 1 | AZ14: 1 | BA14: 1 | BC14: =Q14 -> 1 | BD14: =AC14 -> 1 | BE14: =AO14 -> 1 | BF14: =BA14 -> 1
B15: Total FTE | E15: # | F15: =SUM(F8:F14) -> 8 | G15: =SUM(G8:G14) -> 8 | H15: =SUM(H8:H14) -> 8 | I15: =SUM(I8:I14) -> 8 | J15: =SUM(J8:J14) -> 8 | K15: =SUM(K8:K14) -> 9 | L15: =SUM(L8:L14) -> 9 | M15: =SUM(M8:M14) -> 9 | ... BA15: =SUM(BA8:BA14) -> 14 | BC15: =Q15 -> 9 | BD15: =AC15 -> 11 | BE15: =AO15 -> 12 | BF15: =BA15 -> 14
B17: PERSONNEL COSTS
B18: Gross salary | E18: € | F18: {=INDEX(Assumptions!$C$27:$F$27,MATCH(YEAR(F$3),Assumptions!$C$1:$F$1,0))*IF(ISNUMBER(SEARCH("yr",Assumptions!$G$27)),1/12,1)+INDEX(Assumptions!$C$28:$F$28,MATCH(YEAR(F$3),Assumptions!$C$1:$F$1,0))*IF(ISNUMBER(SEARCH("yr",Assumptions!$G$28)),1/12,1)+F8*INDEX(Assumptions!$C$30:$F$30,MATCH(YEAR(F$3),Assumptions!$C$1:$F$1,0))*IF(ISNUMBER(SEARCH("yr",Assumptions!$G$30)),1/12,1)+F9*INDEX(Assumptions!$C$29:$F$29,MATCH(YEAR(F$3),Assumptions!$C$1:$F$1,0))*IF(ISNUMBER(SEARCH("yr",Assumptions!$G$29)),1/12,1)+F10*INDEX(Assumptions!$C$31:$F$31,MATCH(YEAR(F$3),Assumptions!$C$1:$F$1,0))*IF(ISNUMBER(SEARCH("yr",Assumptions!$G$31)),1/12,1)+F12*INDEX(Assumptions!$C$32:$F$32,MATCH(YEAR(F$3),Assumptions!$C$1:$F$1,0))*IF(ISNUMBER(SEARCH("yr",Assumptions!$G$32)),1/12,1)} -> 29500 | G18: {=INDEX(Assumptions!$C$27:$F$27,MATCH(YEAR(G$3),Assumptions!$C$1:$F$1,0))*IF(ISNUMBER(SEARCH("yr",Assumptions!$G$27)),1/12,1)+INDEX(Assumptions!$C$28:$F$28,MATCH(YEAR(G$3),Assumptions!$C$1:$F$1,0))*IF(ISNUMBER(SEARCH("yr",Assumptions!$G$28)),1/12,1)+G8*INDEX(Assumptions!$C$30:$F$30,MATCH(YEAR(G$3),Assumptions!$C$1:$F$1,0))*IF(ISNUMBER(SEARCH("yr",Assumptions!$G$30)),1/12,1)+G9*INDEX(Assumptions!$C$29:$F$29,MATCH(YEAR(G$3),Assumptions!$C$1:$F$1,0))*IF(ISNUMBER(SEARCH("yr",Assumptions!$G$29)),1/12,1)+G10*INDEX(Assumptions!$C$31:$F$31,MATCH(YEAR(G$3),Assumptions!$C$1:$F$1,0))*IF(ISNUMBER(SEARCH("yr",Assumptions!$G$31)),1/12,1)+G12*INDEX(Assumptions!$C$32:$F$32,MATCH(YEAR(G$3),Assumptions!$C$1:$F$1,0))*IF(ISNUMBER(SEARCH("yr",Assumptions!$G$32)),1/12,1)} -> 29500 | H18: {=INDEX(Assumptions!$C$27:$F$27,MATCH(YEAR(H$3),Assumptions!$C$1:$F$1,0))*IF(ISNUMBER(SEARCH("yr",Assumptions!$G$27)),1/12,1)+INDEX(Assumptions!$C$28:$F$28,MATCH(YEAR(H$3),Assumptions!$C$1:$F$1,0))*IF(ISNUMBER(SEARCH("yr",Assumptions!$G$28)),1/12,1)+H8*INDEX(Assumptions!$C$30:$F$30,MATCH(YEAR(H$3),Assumptions!$C$1:$F$1,0))*IF(ISNUMBER(SEARCH("yr",Assumptions!$G$30)),1/12,1)+H9*INDEX(Assumptions!$C$29:$F$29,MATCH(YEAR(H$3),Assumptions!$C$1:$F$1,0))*IF(ISNUMBER(SEARCH("yr",Assumptions!$G$29)),1/12,1)+H10*INDEX(Assumptions!$C$31:$F$31,MATCH(YEAR(H$3),Assumptions!$C$1:$F$1,0))*IF(ISNUMBER(SEARCH("yr",Assumptions!$G$31)),1/12,1)+H12*INDEX(Assumptions!$C$32:$F$32,MATCH(YEAR(H$3),Assumptions!$C$1:$F$1,0))*IF(ISNUMBER(SEARCH("yr",Assumptions!$G$32)),1/12,1)} -> 29500 | I18: {=INDEX(Assumptions!$C$27:$F$27,MATCH(YEAR(I$3),Assumptions!$C$1:$F$1,0))*IF(ISNUMBER(SEARCH("yr",Assumptions!$G$27)),1/12,1)+INDEX(Assumptions!$C$28:$F$28,MATCH(YEAR(I$3),Assumptions!$C$1:$F$1,0))*IF(ISNUMBER(SEARCH("yr",Assumptions!$G$28)),1/12,1)+I8*INDEX(Assumptions!$C$30:$F$30,MATCH(YEAR(I$3),Assumptions!$C$1:$F$1,0))*IF(ISNUMBER(SEARCH("yr",Assumptions!$G$30)),1/12,1)+I9*INDEX(Assumptions!$C$29:$F$29,MATCH(YEAR(I$3),Assumptions!$C$1:$F$1,0))*IF(ISNUMBER(SEARCH("yr",Assumptions!$G$29)),1/12,1)+I10*INDEX(Assumptions!$C$31:$F$31,MATCH(YEAR(I$3),Assumptions!$C$1:$F$1,0))*IF(ISNUMBER(SEARCH("yr",Assumptions!$G$31)),1/12,1)+I12*INDEX(Assumptions!$C$32:$F$32,MATCH(YEAR(I$3),Assumptions!$C$1:$F$1,0))*IF(ISNUMBER(SEARCH("yr",Assumptions!$G$32)),1/12,1)} -> 29500 | J18: {=INDEX(Assumptions!$C$27:$F$27,MATCH(YEAR(J$3),Assumptions!$C$1:$F$1,0))*IF(ISNUMBER(SEARCH("yr",Assumptions!$G$27)),1/12,1)+INDEX(Assumptions!$C$28:$F$28,MATCH(YEAR(J$3),Assumptions!$C$1:$F$1,0))*IF(ISNUMBER(SEARCH("yr",Assumptions!$G$28)),1/12,1)+J8*INDEX(Assumptions!$C$30:$F$30,MATCH(YEAR(J$3),Assumptions!$C$1:$F$1,0))*IF(ISNUMBER(SEARCH("yr",Assumptions!$G$30)),1/12,1)+J9*INDEX(Assumptions!$C$29:$F$29,MATCH(YEAR(J$3),Assumptions!$C$1:$F$1,0))*IF(ISNUMBER(SEARCH("yr",Assumptions!$G$29)),1/12,1)+J10*INDEX(Assumptions!$C$31:$F$31,MATCH(YEAR(J$3),Assumptions!$C$1:$F$1,0))*IF(ISNUMBER(SEARCH("yr",Assumptions!$G$31)),1/12,1)+J12*INDEX(Assumptions!$C$32:$F$32,MATCH(YEAR(J$3),Assumptions!$C$1:$F$1,0))*IF(ISNUMBER(SEARCH("yr",Assumptions!$G$32)),1/12,1)} -> 29500 | K18: {=INDEX(Assumptions!$C$27:$F$27,MATCH(YEAR(K$3),Assumptions!$C$1:$F$1,0))*IF(ISNUMBER(SEARCH("yr",Assumptions!$G$27)),1/12,1)+INDEX(Assumptions!$C$28:$F$28,MATCH(YEAR(K$3),Assumptions!$C$1:$F$1,0))*IF(ISNUMBER(SEARCH("yr",Assumptions!$G$28)),1/12,1)+K8*INDEX(Assumptions!$C$30:$F$30,MATCH(YEAR(K$3),Assumptions!$C$1:$F$1,0))*IF(ISNUMBER(SEARCH("yr",Assumptions!$G$30)),1/12,1)+K9*INDEX(Assumptions!$C$29:$F$29,MATCH(YEAR(K$3),Assumptions!$C$1:$F$1,0))*IF(ISNUMBER(SEARCH("yr",Assumptions!$G$29)),1/12,1)+K10*INDEX(Assumptions!$C$31:$F$31,MATCH(YEAR(K$3),Assumptions!$C$1:$F$1,0))*IF(ISNUMBER(SEARCH("yr",Assumptions!$G$31)),1/12,1)+K12*INDEX(Assumptions!$C$32:$F$32,MATCH(YEAR(K$3),Assumptions!$C$1:$F$1,0))*IF(ISNUMBER(SEARCH("yr",Assumptions!$G$32)),1/12,1)} -> 32500 | L18: {=INDEX(Assumptions!$C$27:$F$27,MATCH(YEAR(L$3),Assumptions!$C$1:$F$1,0))*IF(ISNUMBER(SEARCH("yr",Assumptions!$G$27)),1/12,1)+INDEX(Assumptions!$C$28:$F$28,MATCH(YEAR(L$3),Assumptions!$C$1:$F$1,0))*IF(ISNUMBER(SEARCH("yr",Assumptions!$G$28)),1/12,1)+L8*INDEX(Assumptions!$C$30:$F$30,MATCH(YEAR(L$3),Assumptions!$C$1:$F$1,0))*IF(ISNUMBER(SEARCH("yr",Assumptions!$G$30)),1/12,1)+L9*INDEX(Assumptions!$C$29:$F$29,MATCH(YEAR(L$3),Assumptions!$C$1:$F$1,0))*IF(ISNUMBER(SEARCH("yr",Assumptions!$G$29)),1/12,1)+L10*INDEX(Assumptions!$C$31:$F$31,MATCH(YEAR(L$3),Assumptions!$C$1:$F$1,0))*IF(ISNUMBER(SEARCH("yr",Assumptions!$G$31)),1/12,1)+L12*INDEX(Assumptions!$C$32:$F$32,MATCH(YEAR(L$3),Assumptions!$C$1:$F$1,0))*IF(ISNUMBER(SEARCH("yr",Assumptions!$G$32)),1/12,1)} -> 32500 | M18: {=INDEX(Assumptions!$C$27:$F$27,MATCH(YEAR(M$3),Assumptions!$C$1:$F$1,0))*IF(ISNUMBER(SEARCH("yr",Assumptions!$G$27)),1/12,1)+INDEX(Assumptions!$C$28:$F$28,MATCH(YEAR(M$3),Assumptions!$C$1:$F$1,0))*IF(ISNUMBER(SEARCH("yr",Assumptions!$G$28)),1/12,1)+M8*INDEX(Assumptions!$C$30:$F$30,MATCH(YEAR(M$3),Assumptions!$C$1:$F$1,0))*IF(ISNUMBER(SEARCH("yr",Assumptions!$G$30)),1/12,1)+M9*INDEX(Assumptions!$C$29:$F$29,MATCH(YEAR(M$3),Assumptions!$C$1:$F$1,0))*IF(ISNUMBER(SEARCH("yr",Assumptions!$G$29)),1/12,1)+M10*INDEX(Assumptions!$C$31:$F$31,MATCH(YEAR(M$3),Assumptions!$C$1:$F$1,0))*IF(ISNUMBER(SEARCH("yr",Assumptions!$G$31)),1/12,1)+M12*INDEX(Assumptions!$C$32:$F$32,MATCH(YEAR(M$3),Assumptions!$C$1:$F$1,0))*IF(ISNUMBER(SEARCH("yr",Assumptions!$G$32)),1/12,1)} -> 32500 | ... BA18: {=INDEX(Assumptions!$C$27:$F$27,MATCH(YEAR(BA$3),Assumptions!$C$1:$F$1,0))*IF(ISNUMBER(SEARCH("yr",Assumptions!$G$27)),1/12,1)+INDEX(Assumptions!$C$28:$F$28,MATCH(YEAR(BA$3),Assumptions!$C$1:$F$1,0))*IF(ISNUMBER(SEARCH("yr",Assumptions!$G$28)),1/12,1)+BA8*INDEX(Assumptions!$C$30:$F$30,MATCH(YEAR(BA$3),Assumptions!$C$1:$F$1,0))*IF(ISNUMBER(SEARCH("yr",Assumptions!$G$30)),1/12,1)+BA9*INDEX(Assumptions!$C$29:$F$29,MATCH(YEAR(BA$3),Assumptions!$C$1:$F$1,0))*IF(ISNUMBER(SEARCH("yr",Assumptions!$G$29)),1/12,1)+BA10*INDEX(Assumptions!$C$31:$F$31,MATCH(YEAR(BA$3),Assumptions!$C$1:$F$1,0))*IF(ISNUMBER(SEARCH("yr",Assumptions!$G$31)),1/12,1)+BA12*INDEX(Assumptions!$C$32:$F$32,MATCH(YEAR(BA$3),Assumptions!$C$1:$F$1,0))*IF(ISNUMBER(SEARCH("yr",Assumptions!$G$32)),1/12,1)} -> 70600 | BC18: =SUMPRODUCT((YEAR($F$3:$BA$3)=BC$3)*$F18:$BA18) -> 375000 | BD18: =SUMPRODUCT((YEAR($F$3:$BA$3)=BD$3)*$F18:$BA18) -> 503400 | BE18: =SUMPRODUCT((YEAR($F$3:$BA$3)=BE$3)*$F18:$BA18) -> 647300 | BF18: =SUMPRODUCT((YEAR($F$3:$BA$3)=BF$3)*$F18:$BA18) -> 796200
B19: Holiday pay | E19: € | F19: =Assumptions!$C$34*F18 -> 2360 | G19: =Assumptions!$C$34*G18 -> 2360 | H19: =Assumptions!$C$34*H18 -> 2360 | I19: =Assumptions!$C$34*I18 -> 2360 | J19: =Assumptions!$C$34*J18 -> 2360 | K19: =Assumptions!$C$34*K18 -> 2600 | L19: =Assumptions!$C$34*L18 -> 2600 | M19: =Assumptions!$C$34*M18 -> 2600 | ... BA19: =Assumptions!$C$34*BA18 -> 5648 | BC19: =SUMPRODUCT((YEAR($F$3:$BA$3)=BC$3)*$F19:$BA19) -> 30000 | BD19: =SUMPRODUCT((YEAR($F$3:$BA$3)=BD$3)*$F19:$BA19) -> 40272 | BE19: =SUMPRODUCT((YEAR($F$3:$BA$3)=BE$3)*$F19:$BA19) -> 51784 | BF19: =SUMPRODUCT((YEAR($F$3:$BA$3)=BF$3)*$F19:$BA19) -> 63696
B20: Employer taxes | E20: € | F20: =Assumptions!$C$35*(F18+F19) -> 6053.4 | G20: =Assumptions!$C$35*(G18+G19) -> 6053.4 | H20: =Assumptions!$C$35*(H18+H19) -> 6053.4 | I20: =Assumptions!$C$35*(I18+I19) -> 6053.4 | J20: =Assumptions!$C$35*(J18+J19) -> 6053.4 | K20: =Assumptions!$C$35*(K18+K19) -> 6669 | L20: =Assumptions!$C$35*(L18+L19) -> 6669 | M20: =Assumptions!$C$35*(M18+M19) -> 6669 | ... BA20: =Assumptions!$C$35*(BA18+BA19) -> 14487.12 | BC20: =SUMPRODUCT((YEAR($F$3:$BA$3)=BC$3)*$F20:$BA20) -> 76950 | BD20: =SUMPRODUCT((YEAR($F$3:$BA$3)=BD$3)*$F20:$BA20) -> 103297.68 | BE20: =SUMPRODUCT((YEAR($F$3:$BA$3)=BE$3)*$F20:$BA20) -> 132825.96 | BF20: =SUMPRODUCT((YEAR($F$3:$BA$3)=BF$3)*$F20:$BA20) -> 163380.24
B21: Sales hire | E21: € | F21: {=INDEX(Assumptions!$C$33:$F$33,MATCH(YEAR(F$3),Assumptions!$C$1:$F$1,0))*IF(ISNUMBER(SEARCH("yr",Assumptions!$G$33)),1/12,1)} -> 6500 | G21: {=INDEX(Assumptions!$C$33:$F$33,MATCH(YEAR(G$3),Assumptions!$C$1:$F$1,0))*IF(ISNUMBER(SEARCH("yr",Assumptions!$G$33)),1/12,1)} -> 6500 | H21: {=INDEX(Assumptions!$C$33:$F$33,MATCH(YEAR(H$3),Assumptions!$C$1:$F$1,0))*IF(ISNUMBER(SEARCH("yr",Assumptions!$G$33)),1/12,1)} -> 6500 | I21: {=INDEX(Assumptions!$C$33:$F$33,MATCH(YEAR(I$3),Assumptions!$C$1:$F$1,0))*IF(ISNUMBER(SEARCH("yr",Assumptions!$G$33)),1/12,1)} -> 6500 | J21: {=INDEX(Assumptions!$C$33:$F$33,MATCH(YEAR(J$3),Assumptions!$C$1:$F$1,0))*IF(ISNUMBER(SEARCH("yr",Assumptions!$G$33)),1/12,1)} -> 6500 | K21: {=INDEX(Assumptions!$C$33:$F$33,MATCH(YEAR(K$3),Assumptions!$C$1:$F$1,0))*IF(ISNUMBER(SEARCH("yr",Assumptions!$G$33)),1/12,1)} -> 6500 | L21: {=INDEX(Assumptions!$C$33:$F$33,MATCH(YEAR(L$3),Assumptions!$C$1:$F$1,0))*IF(ISNUMBER(SEARCH("yr",Assumptions!$G$33)),1/12,1)} -> 6500 | M21: {=INDEX(Assumptions!$C$33:$F$33,MATCH(YEAR(M$3),Assumptions!$C$1:$F$1,0))*IF(ISNUMBER(SEARCH("yr",Assumptions!$G$33)),1/12,1)} -> 6500 | ... BA21: {=INDEX(Assumptions!$C$33:$F$33,MATCH(YEAR(BA$3),Assumptions!$C$1:$F$1,0))*IF(ISNUMBER(SEARCH("yr",Assumptions!$G$33)),1/12,1)} -> 8000 | BC21: =SUMPRODUCT((YEAR($F$3:$BA$3)=BC$3)*$F21:$BA21) -> 78000 | BD21: =SUMPRODUCT((YEAR($F$3:$BA$3)=BD$3)*$F21:$BA21) -> 84000 | BE21: =SUMPRODUCT((YEAR($F$3:$BA$3)=BE$3)*$F21:$BA21) -> 90000 | BF21: =SUMPRODUCT((YEAR($F$3:$BA$3)=BF$3)*$F21:$BA21) -> 96000
B22: Success-fee bonus | E22: € | F22: {='Revenue forecast'!F26*(1-Assumptions!$C$21*Assumptions!$C$23)*Assumptions!$C$24*(0.9+0.1*(Assumptions!$C$21+INDEX(Assumptions!$C$22:$F$22,MATCH(YEAR(F$3),Assumptions!$C$1:$F$1,0))))} -> 0 | G22: {='Revenue forecast'!G26*(1-Assumptions!$C$21*Assumptions!$C$23)*Assumptions!$C$24*(0.9+0.1*(Assumptions!$C$21+INDEX(Assumptions!$C$22:$F$22,MATCH(YEAR(G$3),Assumptions!$C$1:$F$1,0))))} -> 35797.5 | H22: {='Revenue forecast'!H26*(1-Assumptions!$C$21*Assumptions!$C$23)*Assumptions!$C$24*(0.9+0.1*(Assumptions!$C$21+INDEX(Assumptions!$C$22:$F$22,MATCH(YEAR(H$3),Assumptions!$C$1:$F$1,0))))} -> 0 | I22: {='Revenue forecast'!I26*(1-Assumptions!$C$21*Assumptions!$C$23)*Assumptions!$C$24*(0.9+0.1*(Assumptions!$C$21+INDEX(Assumptions!$C$22:$F$22,MATCH(YEAR(I$3),Assumptions!$C$1:$F$1,0))))} -> 0 | J22: {='Revenue forecast'!J26*(1-Assumptions!$C$21*Assumptions!$C$23)*Assumptions!$C$24*(0.9+0.1*(Assumptions!$C$21+INDEX(Assumptions!$C$22:$F$22,MATCH(YEAR(J$3),Assumptions!$C$1:$F$1,0))))} -> 0 | K22: {='Revenue forecast'!K26*(1-Assumptions!$C$21*Assumptions!$C$23)*Assumptions!$C$24*(0.9+0.1*(Assumptions!$C$21+INDEX(Assumptions!$C$22:$F$22,MATCH(YEAR(K$3),Assumptions!$C$1:$F$1,0))))} -> 7159.5 | L22: {='Revenue forecast'!L26*(1-Assumptions!$C$21*Assumptions!$C$23)*Assumptions!$C$24*(0.9+0.1*(Assumptions!$C$21+INDEX(Assumptions!$C$22:$F$22,MATCH(YEAR(L$3),Assumptions!$C$1:$F$1,0))))} -> 7159.5 | M22: {='Revenue forecast'!M26*(1-Assumptions!$C$21*Assumptions!$C$23)*Assumptions!$C$24*(0.9+0.1*(Assumptions!$C$21+INDEX(Assumptions!$C$22:$F$22,MATCH(YEAR(M$3),Assumptions!$C$1:$F$1,0))))} -> 7159.5 | ... BA22: {='Revenue forecast'!BA26*(1-Assumptions!$C$21*Assumptions!$C$23)*Assumptions!$C$24*(0.9+0.1*(Assumptions!$C$21+INDEX(Assumptions!$C$22:$F$22,MATCH(YEAR(BA$3),Assumptions!$C$1:$F$1,0))))} -> 337315.68 | BC22: =SUMPRODUCT((YEAR($F$3:$BA$3)=BC$3)*$F22:$BA22) -> 164668.5 | BD22: =SUMPRODUCT((YEAR($F$3:$BA$3)=BD$3)*$F22:$BA22) -> 512509.2 | BE22: =SUMPRODUCT((YEAR($F$3:$BA$3)=BE$3)*$F22:$BA22) -> 1151998.8 | BF22: =SUMPRODUCT((YEAR($F$3:$BA$3)=BF$3)*$F22:$BA22) -> 2521218.5
B23: Contractors / accountant | E23: € | F23: 450 | G23: 450 | H23: 450 | I23: 450 | J23: 450 | K23: 450 | L23: 450 | M23: 450 | N23: 450 | O23: 450 | P23: 450 | Q23: 450 | R23: 450 | S23: 450 | T23: 450 | U23: 450 | V23: 450 | W23: 450 | X23: 450 | Y23: 450 | Z23: 450 | AA23: 450 | AB23: 450 | AC23: 450 | AD23: 450 | AE23: 450 | AF23: 450 | AG23: 450 | AH23: 450 | AI23: 450 | AJ23: 450 | AK23: 450 | AL23: 450 | AM23: 450 | AN23: 450 | AO23: 450 | AP23: 450 | AQ23: 450 | AR23: 450 | AS23: 450 | AT23: 450 | AU23: 450 | AV23: 450 | AW23: 450 | AX23: 450 | AY23: 450 | AZ23: 450 | BA23: 450 | BC23: =SUMPRODUCT((YEAR($F$3:$BA$3)=BC$3)*$F23:$BA23) -> 5400 | BD23: =SUMPRODUCT((YEAR($F$3:$BA$3)=BD$3)*$F23:$BA23) -> 5400 | BE23: =SUMPRODUCT((YEAR($F$3:$BA$3)=BE$3)*$F23:$BA23) -> 5400 | BF23: =SUMPRODUCT((YEAR($F$3:$BA$3)=BF$3)*$F23:$BA23) -> 5400
B24: Other people costs | E24: € | F24: 267 | G24: 267 | H24: 267 | I24: 267 | J24: 267 | K24: 267 | L24: 267 | M24: 267 | N24: 267 | O24: 267 | P24: 267 | Q24: 267 | R24: 267 | S24: 267 | T24: 267 | U24: 267 | V24: 267 | W24: 267 | X24: 267 | Y24: 267 | Z24: 267 | AA24: 267 | AB24: 267 | AC24: 267 | AD24: 267 | AE24: 267 | AF24: 267 | AG24: 267 | AH24: 267 | AI24: 267 | AJ24: 267 | AK24: 267 | AL24: 267 | AM24: 267 | AN24: 267 | AO24: 267 | AP24: 267 | AQ24: 267 | AR24: 267 | AS24: 267 | AT24: 267 | AU24: 267 | AV24: 267 | AW24: 267 | AX24: 267 | AY24: 267 | AZ24: 267 | BA24: 267 | BC24: =SUMPRODUCT((YEAR($F$3:$BA$3)=BC$3)*$F24:$BA24) -> 3204 | BD24: =SUMPRODUCT((YEAR($F$3:$BA$3)=BD$3)*$F24:$BA24) -> 3204 | BE24: =SUMPRODUCT((YEAR($F$3:$BA$3)=BE$3)*$F24:$BA24) -> 3204 | BF24: =SUMPRODUCT((YEAR($F$3:$BA$3)=BF$3)*$F24:$BA24) -> 3204
B25: Total personnel | E25: € | F25: =SUM(F18:F24) -> 45130.4 | G25: =SUM(G18:G24) -> 80927.9 | H25: =SUM(H18:H24) -> 45130.4 | I25: =SUM(I18:I24) -> 45130.4 | J25: =SUM(J18:J24) -> 45130.4 | K25: =SUM(K18:K24) -> 56145.5 | L25: =SUM(L18:L24) -> 56145.5 | M25: =SUM(M18:M24) -> 56145.5 | ... BA25: =SUM(BA18:BA24) -> 436767.8 | BC25: =SUMPRODUCT((YEAR($F$3:$BA$3)=BC$3)*$F25:$BA25) -> 733222.5 | BD25: =SUMPRODUCT((YEAR($F$3:$BA$3)=BD$3)*$F25:$BA25) -> 1252082.9 | BE25: =SUMPRODUCT((YEAR($F$3:$BA$3)=BE$3)*$F25:$BA25) -> 2082512.8 | BF25: =SUMPRODUCT((YEAR($F$3:$BA$3)=BF$3)*$F25:$BA25) -> 3649098.7

Sheet OPEX
B2: OPEX — Monthly 2027–2030 (€)
E3: Unit | F3: 46388 | G3: 46419 | H3: 46447 | I3: 46478 | J3: 46508 | K3: 46539 | L3: 46569 | M3: 46600 | N3: 46631 | O3: 46661 | P3: 46692 | Q3: 46722 | R3: 46753 | S3: 46784 | T3: 46813 | U3: 46844 | V3: 46874 | W3: 46905 | X3: 46935 | Y3: 46966 | Z3: 46997 | AA3: 47027 | AB3: 47058 | AC3: 47088 | AD3: 47119 | AE3: 47150 | AF3: 47178 | AG3: 47209 | AH3: 47239 | AI3: 47270 | AJ3: 47300 | AK3: 47331 | AL3: 47362 | AM3: 47392 | AN3: 47423 | AO3: 47453 | AP3: 47484 | AQ3: 47515 | AR3: 47543 | AS3: 47574 | AT3: 47604 | AU3: 47635 | AV3: 47665 | AW3: 47696 | AX3: 47727 | AY3: 47757 | AZ3: 47788 | BA3: 47818 | BC3: 2027 | BD3: 2028 | BE3: 2029 | BF3: 2030
B6: OTHER OPEX
B7: Rent | E7: € | F7: =Personnel!F15*Assumptions!$C$44*IF(ISNUMBER(SEARCH("yr",Assumptions!$G$44)),1/12,1) -> 4800 | G7: =Personnel!G15*Assumptions!$C$44*IF(ISNUMBER(SEARCH("yr",Assumptions!$G$44)),1/12,1) -> 4800 | H7: =Personnel!H15*Assumptions!$C$44*IF(ISNUMBER(SEARCH("yr",Assumptions!$G$44)),1/12,1) -> 4800 | I7: =Personnel!I15*Assumptions!$C$44*IF(ISNUMBER(SEARCH("yr",Assumptions!$G$44)),1/12,1) -> 4800 | J7: =Personnel!J15*Assumptions!$C$44*IF(ISNUMBER(SEARCH("yr",Assumptions!$G$44)),1/12,1) -> 4800 | K7: =Personnel!K15*Assumptions!$C$44*IF(ISNUMBER(SEARCH("yr",Assumptions!$G$44)),1/12,1) -> 5400 | L7: =Personnel!L15*Assumptions!$C$44*IF(ISNUMBER(SEARCH("yr",Assumptions!$G$44)),1/12,1) -> 5400 | M7: =Personnel!M15*Assumptions!$C$44*IF(ISNUMBER(SEARCH("yr",Assumptions!$G$44)),1/12,1) -> 5400 | ... BA7: =Personnel!BA15*Assumptions!$C$44*IF(ISNUMBER(SEARCH("yr",Assumptions!$G$44)),1/12,1) -> 8400 | BC7: =SUMPRODUCT((YEAR($F$3:$BA$3)=BC$3)*$F7:$BA7) -> 61800 | BD7: =SUMPRODUCT((YEAR($F$3:$BA$3)=BD$3)*$F7:$BA7) -> 72000 | BE7: =SUMPRODUCT((YEAR($F$3:$BA$3)=BE$3)*$F7:$BA7) -> 83400 | BF7: =SUMPRODUCT((YEAR($F$3:$BA$3)=BF$3)*$F7:$BA7) -> 93600
B8: Software | E8: € | F8: =IF(Personnel!F15>=16,Assumptions!$F$46,IF(Personnel!F15>=10,Assumptions!$E$46,IF(Personnel!F15>=7,Assumptions!$D$46,Assumptions!$C$46)))*IF(ISNUMBER(SEARCH("yr",Assumptions!$G$46)),1/12,1)+Personnel!F15*Assumptions!$C$45*IF(ISNUMBER(SEARCH("yr",Assumptions!$G$45)),1/12,1) -> 4293.3333 | G8: =IF(Personnel!G15>=16,Assumptions!$F$46,IF(Personnel!G15>=10,Assumptions!$E$46,IF(Personnel!G15>=7,Assumptions!$D$46,Assumptions!$C$46)))*IF(ISNUMBER(SEARCH("yr",Assumptions!$G$46)),1/12,1)+Personnel!G15*Assumptions!$C$45*IF(ISNUMBER(SEARCH("yr",Assumptions!$G$45)),1/12,1) -> 4293.3333 | H8: =IF(Personnel!H15>=16,Assumptions!$F$46,IF(Personnel!H15>=10,Assumptions!$E$46,IF(Personnel!H15>=7,Assumptions!$D$46,Assumptions!$C$46)))*IF(ISNUMBER(SEARCH("yr",Assumptions!$G$46)),1/12,1)+Personnel!H15*Assumptions!$C$45*IF(ISNUMBER(SEARCH("yr",Assumptions!$G$45)),1/12,1) -> 4293.3333 | I8: =IF(Personnel!I15>=16,Assumptions!$F$46,IF(Personnel!I15>=10,Assumptions!$E$46,IF(Personnel!I15>=7,Assumptions!$D$46,Assumptions!$C$46)))*IF(ISNUMBER(SEARCH("yr",Assumptions!$G$46)),1/12,1)+Personnel!I15*Assumptions!$C$45*IF(ISNUMBER(SEARCH("yr",Assumptions!$G$45)),1/12,1) -> 4293.3333 | J8: =IF(Personnel!J15>=16,Assumptions!$F$46,IF(Personnel!J15>=10,Assumptions!$E$46,IF(Personnel!J15>=7,Assumptions!$D$46,Assumptions!$C$46)))*IF(ISNUMBER(SEARCH("yr",Assumptions!$G$46)),1/12,1)+Personnel!J15*Assumptions!$C$45*IF(ISNUMBER(SEARCH("yr",Assumptions!$G$45)),1/12,1) -> 4293.3333 | K8: =IF(Personnel!K15>=16,Assumptions!$F$46,IF(Personnel!K15>=10,Assumptions!$E$46,IF(Personnel!K15>=7,Assumptions!$D$46,Assumptions!$C$46)))*IF(ISNUMBER(SEARCH("yr",Assumptions!$G$46)),1/12,1)+Personnel!K15*Assumptions!$C$45*IF(ISNUMBER(SEARCH("yr",Assumptions!$G$45)),1/12,1) -> 4413.3333 | L8: =IF(Personnel!L15>=16,Assumptions!$F$46,IF(Personnel!L15>=10,Assumptions!$E$46,IF(Personnel!L15>=7,Assumptions!$D$46,Assumptions!$C$46)))*IF(ISNUMBER(SEARCH("yr",Assumptions!$G$46)),1/12,1)+Personnel!L15*Assumptions!$C$45*IF(ISNUMBER(SEARCH("yr",Assumptions!$G$45)),1/12,1) -> 4413.3333 | M8: =IF(Personnel!M15>=16,Assumptions!$F$46,IF(Personnel!M15>=10,Assumptions!$E$46,IF(Personnel!M15>=7,Assumptions!$D$46,Assumptions!$C$46)))*IF(ISNUMBER(SEARCH("yr",Assumptions!$G$46)),1/12,1)+Personnel!M15*Assumptions!$C$45*IF(ISNUMBER(SEARCH("yr",Assumptions!$G$45)),1/12,1) -> 4413.3333 | ... BA8: =IF(Personnel!BA15>=16,Assumptions!$F$46,IF(Personnel!BA15>=10,Assumptions!$E$46,IF(Personnel!BA15>=7,Assumptions!$D$46,Assumptions!$C$46)))*IF(ISNUMBER(SEARCH("yr",Assumptions!$G$46)),1/12,1)+Personnel!BA15*Assumptions!$C$45*IF(ISNUMBER(SEARCH("yr",Assumptions!$G$45)),1/12,1) -> 6680 | BC8: =SUMPRODUCT((YEAR($F$3:$BA$3)=BC$3)*$F8:$BA8) -> 52360 | BD8: =SUMPRODUCT((YEAR($F$3:$BA$3)=BD$3)*$F8:$BA8) -> 64400 | BE8: =SUMPRODUCT((YEAR($F$3:$BA$3)=BE$3)*$F8:$BA8) -> 76680 | BF8: =SUMPRODUCT((YEAR($F$3:$BA$3)=BF$3)*$F8:$BA8) -> 78720
B9: Office & hardware | E9: € | F9: =Personnel!F15*Assumptions!$C$47*IF(ISNUMBER(SEARCH("yr",Assumptions!$G$47)),1/12,1) -> 320 | G9: =Personnel!G15*Assumptions!$C$47*IF(ISNUMBER(SEARCH("yr",Assumptions!$G$47)),1/12,1) -> 320 | H9: =Personnel!H15*Assumptions!$C$47*IF(ISNUMBER(SEARCH("yr",Assumptions!$G$47)),1/12,1) -> 320 | I9: =Personnel!I15*Assumptions!$C$47*IF(ISNUMBER(SEARCH("yr",Assumptions!$G$47)),1/12,1) -> 320 | J9: =Personnel!J15*Assumptions!$C$47*IF(ISNUMBER(SEARCH("yr",Assumptions!$G$47)),1/12,1) -> 320 | K9: =Personnel!K15*Assumptions!$C$47*IF(ISNUMBER(SEARCH("yr",Assumptions!$G$47)),1/12,1) -> 360 | L9: =Personnel!L15*Assumptions!$C$47*IF(ISNUMBER(SEARCH("yr",Assumptions!$G$47)),1/12,1) -> 360 | M9: =Personnel!M15*Assumptions!$C$47*IF(ISNUMBER(SEARCH("yr",Assumptions!$G$47)),1/12,1) -> 360 | ... BA9: =Personnel!BA15*Assumptions!$C$47*IF(ISNUMBER(SEARCH("yr",Assumptions!$G$47)),1/12,1) -> 560 | BC9: =SUMPRODUCT((YEAR($F$3:$BA$3)=BC$3)*$F9:$BA9) -> 4120 | BD9: =SUMPRODUCT((YEAR($F$3:$BA$3)=BD$3)*$F9:$BA9) -> 4800 | BE9: =SUMPRODUCT((YEAR($F$3:$BA$3)=BE$3)*$F9:$BA9) -> 5560 | BF9: =SUMPRODUCT((YEAR($F$3:$BA$3)=BF$3)*$F9:$BA9) -> 6240
B10: Marketing & Sales | E10: € | F10: {=INDEX(Assumptions!$C$49:$F$49,MATCH(YEAR(F$3),Assumptions!$C$1:$F$1,0))*IF(ISNUMBER(SEARCH("yr",Assumptions!$G$49)),1/12,1)} -> 250 | G10: {=INDEX(Assumptions!$C$49:$F$49,MATCH(YEAR(G$3),Assumptions!$C$1:$F$1,0))*IF(ISNUMBER(SEARCH("yr",Assumptions!$G$49)),1/12,1)} -> 250 | H10: {=INDEX(Assumptions!$C$49:$F$49,MATCH(YEAR(H$3),Assumptions!$C$1:$F$1,0))*IF(ISNUMBER(SEARCH("yr",Assumptions!$G$49)),1/12,1)} -> 250 | I10: {=INDEX(Assumptions!$C$49:$F$49,MATCH(YEAR(I$3),Assumptions!$C$1:$F$1,0))*IF(ISNUMBER(SEARCH("yr",Assumptions!$G$49)),1/12,1)} -> 250 | J10: {=INDEX(Assumptions!$C$49:$F$49,MATCH(YEAR(J$3),Assumptions!$C$1:$F$1,0))*IF(ISNUMBER(SEARCH("yr",Assumptions!$G$49)),1/12,1)} -> 250 | K10: {=INDEX(Assumptions!$C$49:$F$49,MATCH(YEAR(K$3),Assumptions!$C$1:$F$1,0))*IF(ISNUMBER(SEARCH("yr",Assumptions!$G$49)),1/12,1)} -> 250 | L10: {=INDEX(Assumptions!$C$49:$F$49,MATCH(YEAR(L$3),Assumptions!$C$1:$F$1,0))*IF(ISNUMBER(SEARCH("yr",Assumptions!$G$49)),1/12,1)} -> 250 | M10: {=INDEX(Assumptions!$C$49:$F$49,MATCH(YEAR(M$3),Assumptions!$C$1:$F$1,0))*IF(ISNUMBER(SEARCH("yr",Assumptions!$G$49)),1/12,1)} -> 250 | ... BA10: {=INDEX(Assumptions!$C$49:$F$49,MATCH(YEAR(BA$3),Assumptions!$C$1:$F$1,0))*IF(ISNUMBER(SEARCH("yr",Assumptions!$G$49)),1/12,1)} -> 500 | BC10: =SUMPRODUCT((YEAR($F$3:$BA$3)=BC$3)*$F10:$BA10) -> 3000 | BD10: =SUMPRODUCT((YEAR($F$3:$BA$3)=BD$3)*$F10:$BA10) -> 4000 | BE10: =SUMPRODUCT((YEAR($F$3:$BA$3)=BE$3)*$F10:$BA10) -> 5000 | BF10: =SUMPRODUCT((YEAR($F$3:$BA$3)=BF$3)*$F10:$BA10) -> 6000
B11: Travel | E11: € | F11: {=INDEX(Assumptions!$C$50:$F$50,MATCH(YEAR(F$3),Assumptions!$C$1:$F$1,0))*IF(ISNUMBER(SEARCH("yr",Assumptions!$G$50)),1/12,1)} -> 500 | G11: {=INDEX(Assumptions!$C$50:$F$50,MATCH(YEAR(G$3),Assumptions!$C$1:$F$1,0))*IF(ISNUMBER(SEARCH("yr",Assumptions!$G$50)),1/12,1)} -> 500 | H11: {=INDEX(Assumptions!$C$50:$F$50,MATCH(YEAR(H$3),Assumptions!$C$1:$F$1,0))*IF(ISNUMBER(SEARCH("yr",Assumptions!$G$50)),1/12,1)} -> 500 | I11: {=INDEX(Assumptions!$C$50:$F$50,MATCH(YEAR(I$3),Assumptions!$C$1:$F$1,0))*IF(ISNUMBER(SEARCH("yr",Assumptions!$G$50)),1/12,1)} -> 500 | J11: {=INDEX(Assumptions!$C$50:$F$50,MATCH(YEAR(J$3),Assumptions!$C$1:$F$1,0))*IF(ISNUMBER(SEARCH("yr",Assumptions!$G$50)),1/12,1)} -> 500 | K11: {=INDEX(Assumptions!$C$50:$F$50,MATCH(YEAR(K$3),Assumptions!$C$1:$F$1,0))*IF(ISNUMBER(SEARCH("yr",Assumptions!$G$50)),1/12,1)} -> 500 | L11: {=INDEX(Assumptions!$C$50:$F$50,MATCH(YEAR(L$3),Assumptions!$C$1:$F$1,0))*IF(ISNUMBER(SEARCH("yr",Assumptions!$G$50)),1/12,1)} -> 500 | M11: {=INDEX(Assumptions!$C$50:$F$50,MATCH(YEAR(M$3),Assumptions!$C$1:$F$1,0))*IF(ISNUMBER(SEARCH("yr",Assumptions!$G$50)),1/12,1)} -> 500 | ... BA11: {=INDEX(Assumptions!$C$50:$F$50,MATCH(YEAR(BA$3),Assumptions!$C$1:$F$1,0))*IF(ISNUMBER(SEARCH("yr",Assumptions!$G$50)),1/12,1)} -> 625 | BC11: =SUMPRODUCT((YEAR($F$3:$BA$3)=BC$3)*$F11:$BA11) -> 6000 | BD11: =SUMPRODUCT((YEAR($F$3:$BA$3)=BD$3)*$F11:$BA11) -> 6500 | BE11: =SUMPRODUCT((YEAR($F$3:$BA$3)=BE$3)*$F11:$BA11) -> 7000 | BF11: =SUMPRODUCT((YEAR($F$3:$BA$3)=BF$3)*$F11:$BA11) -> 7500
B12: SG&A (F&B) | E12: € | F12: =Personnel!F15*Assumptions!$C$48*IF(ISNUMBER(SEARCH("yr",Assumptions!$G$48)),1/12,1) -> 800 | G12: =Personnel!G15*Assumptions!$C$48*IF(ISNUMBER(SEARCH("yr",Assumptions!$G$48)),1/12,1) -> 800 | H12: =Personnel!H15*Assumptions!$C$48*IF(ISNUMBER(SEARCH("yr",Assumptions!$G$48)),1/12,1) -> 800 | I12: =Personnel!I15*Assumptions!$C$48*IF(ISNUMBER(SEARCH("yr",Assumptions!$G$48)),1/12,1) -> 800 | J12: =Personnel!J15*Assumptions!$C$48*IF(ISNUMBER(SEARCH("yr",Assumptions!$G$48)),1/12,1) -> 800 | K12: =Personnel!K15*Assumptions!$C$48*IF(ISNUMBER(SEARCH("yr",Assumptions!$G$48)),1/12,1) -> 900 | L12: =Personnel!L15*Assumptions!$C$48*IF(ISNUMBER(SEARCH("yr",Assumptions!$G$48)),1/12,1) -> 900 | M12: =Personnel!M15*Assumptions!$C$48*IF(ISNUMBER(SEARCH("yr",Assumptions!$G$48)),1/12,1) -> 900 | ... BA12: =Personnel!BA15*Assumptions!$C$48*IF(ISNUMBER(SEARCH("yr",Assumptions!$G$48)),1/12,1) -> 1400 | BC12: =SUMPRODUCT((YEAR($F$3:$BA$3)=BC$3)*$F12:$BA12) -> 10300 | BD12: =SUMPRODUCT((YEAR($F$3:$BA$3)=BD$3)*$F12:$BA12) -> 12000 | BE12: =SUMPRODUCT((YEAR($F$3:$BA$3)=BE$3)*$F12:$BA12) -> 13900 | BF12: =SUMPRODUCT((YEAR($F$3:$BA$3)=BF$3)*$F12:$BA12) -> 15600
B13: Other | E13: € | F13: =Assumptions!$C$52*IF(ISNUMBER(SEARCH("yr",Assumptions!$G$52)),1/12,1) -> 140 | G13: =Assumptions!$C$52*IF(ISNUMBER(SEARCH("yr",Assumptions!$G$52)),1/12,1) -> 140 | H13: =Assumptions!$C$52*IF(ISNUMBER(SEARCH("yr",Assumptions!$G$52)),1/12,1) -> 140 | I13: =Assumptions!$C$52*IF(ISNUMBER(SEARCH("yr",Assumptions!$G$52)),1/12,1) -> 140 | J13: =Assumptions!$C$52*IF(ISNUMBER(SEARCH("yr",Assumptions!$G$52)),1/12,1) -> 140 | K13: =Assumptions!$C$52*IF(ISNUMBER(SEARCH("yr",Assumptions!$G$52)),1/12,1) -> 140 | L13: =Assumptions!$C$52*IF(ISNUMBER(SEARCH("yr",Assumptions!$G$52)),1/12,1) -> 140 | M13: =Assumptions!$C$52*IF(ISNUMBER(SEARCH("yr",Assumptions!$G$52)),1/12,1) -> 140 | ... BA13: =Assumptions!$C$52*IF(ISNUMBER(SEARCH("yr",Assumptions!$G$52)),1/12,1) -> 140 | BC13: =SUMPRODUCT((YEAR($F$3:$BA$3)=BC$3)*$F13:$BA13) -> 1680 | BD13: =SUMPRODUCT((YEAR($F$3:$BA$3)=BD$3)*$F13:$BA13) -> 1680 | BE13: =SUMPRODUCT((YEAR($F$3:$BA$3)=BE$3)*$F13:$BA13) -> 1680 | BF13: =SUMPRODUCT((YEAR($F$3:$BA$3)=BF$3)*$F13:$BA13) -> 1680
B14: RX allocation | E14: € | F14: =Assumptions!$C$51*IF(ISNUMBER(SEARCH("yr",Assumptions!$G$51)),1/12,1) -> 1307 | G14: =Assumptions!$C$51*IF(ISNUMBER(SEARCH("yr",Assumptions!$G$51)),1/12,1) -> 1307 | H14: =Assumptions!$C$51*IF(ISNUMBER(SEARCH("yr",Assumptions!$G$51)),1/12,1) -> 1307 | I14: =Assumptions!$C$51*IF(ISNUMBER(SEARCH("yr",Assumptions!$G$51)),1/12,1) -> 1307 | J14: =Assumptions!$C$51*IF(ISNUMBER(SEARCH("yr",Assumptions!$G$51)),1/12,1) -> 1307 | K14: =Assumptions!$C$51*IF(ISNUMBER(SEARCH("yr",Assumptions!$G$51)),1/12,1) -> 1307 | L14: =Assumptions!$C$51*IF(ISNUMBER(SEARCH("yr",Assumptions!$G$51)),1/12,1) -> 1307 | M14: =Assumptions!$C$51*IF(ISNUMBER(SEARCH("yr",Assumptions!$G$51)),1/12,1) -> 1307 | ... BA14: =Assumptions!$C$51*IF(ISNUMBER(SEARCH("yr",Assumptions!$G$51)),1/12,1) -> 1307 | BC14: =SUMPRODUCT((YEAR($F$3:$BA$3)=BC$3)*$F14:$BA14) -> 15684 | BD14: =SUMPRODUCT((YEAR($F$3:$BA$3)=BD$3)*$F14:$BA14) -> 15684 | BE14: =SUMPRODUCT((YEAR($F$3:$BA$3)=BE$3)*$F14:$BA14) -> 15684 | BF14: =SUMPRODUCT((YEAR($F$3:$BA$3)=BF$3)*$F14:$BA14) -> 15684
B15: Total other OPEX | E15: € | F15: =SUM(F7:F14) -> 12410.333 | G15: =SUM(G7:G14) -> 12410.333 | H15: =SUM(H7:H14) -> 12410.333 | I15: =SUM(I7:I14) -> 12410.333 | J15: =SUM(J7:J14) -> 12410.333 | K15: =SUM(K7:K14) -> 13270.333 | L15: =SUM(L7:L14) -> 13270.333 | M15: =SUM(M7:M14) -> 13270.333 | ... BA15: =SUM(BA7:BA14) -> 19612 | BC15: =SUMPRODUCT((YEAR($F$3:$BA$3)=BC$3)*$F15:$BA15) -> 154944 | BD15: =SUMPRODUCT((YEAR($F$3:$BA$3)=BD$3)*$F15:$BA15) -> 181064 | BE15: =SUMPRODUCT((YEAR($F$3:$BA$3)=BE$3)*$F15:$BA15) -> 208904 | BF15: =SUMPRODUCT((YEAR($F$3:$BA$3)=BF$3)*$F15:$BA15) -> 225024

Sheet Financial Statements
B1: Income Statement, 2027–2030 (€)
C2: 46388 | D2: 46419 | E2: 46447 | F2: 46478 | G2: 46508 | H2: 46539 | I2: 46569 | J2: 46600 | K2: 46631 | L2: 46661 | M2: 46692 | N2: 46722 | O2: 46753 | P2: 46784 | Q2: 46813 | R2: 46844 | S2: 46874 | T2: 46905 | U2: 46935 | V2: 46966 | W2: 46997 | X2: 47027 | Y2: 47058 | Z2: 47088 | AA2: 47119 | AB2: 47150 | AC2: 47178 | AD2: 47209 | AE2: 47239 | AF2: 47270 | AG2: 47300 | AH2: 47331 | AI2: 47362 | AJ2: 47392 | AK2: 47423 | AL2: 47453 | AM2: 47484 | AN2: 47515 | AO2: 47543 | AP2: 47574 | AQ2: 47604 | AR2: 47635 | AS2: 47665 | AT2: 47696 | AU2: 47727 | AV2: 47757 | AW2: 47788 | AX2: 47818 | AZ2: 2027 | BA2: 2028 | BB2: 2029 | BC2: 2030
B4: Revenues
B5: Retainer | C5: ='Revenue forecast'!F25 -> 28000 | D5: ='Revenue forecast'!G25 -> 43000 | E5: ='Revenue forecast'!H25 -> 36000 | F5: ='Revenue forecast'!I25 -> 43000 | G5: ='Revenue forecast'!J25 -> 44000 | H5: ='Revenue forecast'!K25 -> 52000 | I5: ='Revenue forecast'!L25 -> 52000 | J5: ='Revenue forecast'!M25 -> 52000 | ... AX5: ='Revenue forecast'!BA25 -> 123000 | AZ5: =SUMPRODUCT((YEAR($C$2:$AX$2)=AZ$2)*$C5:$AX5) -> 563000 | BA5: =SUMPRODUCT((YEAR($C$2:$AX$2)=BA$2)*$C5:$AX5) -> 841000 | BB5: =SUMPRODUCT((YEAR($C$2:$AX$2)=BB$2)*$C5:$AX5) -> 1151000 | BC5: =SUMPRODUCT((YEAR($C$2:$AX$2)=BC$2)*$C5:$AX5) -> 1483500
B6: Closing fees | C6: ='Revenue forecast'!F26 -> 0 | D6: ='Revenue forecast'!G26 -> 100000 | E6: ='Revenue forecast'!H26 -> 0 | F6: ='Revenue forecast'!I26 -> 0 | G6: ='Revenue forecast'!J26 -> 0 | H6: ='Revenue forecast'!K26 -> 20000 | I6: ='Revenue forecast'!L26 -> 20000 | J6: ='Revenue forecast'!M26 -> 20000 | ... AX6: ='Revenue forecast'!BA26 -> 936000 | AZ6: =SUMPRODUCT((YEAR($C$2:$AX$2)=AZ$2)*$C6:$AX6) -> 460000 | BA6: =SUMPRODUCT((YEAR($C$2:$AX$2)=BA$2)*$C6:$AX6) -> 1428000 | BB6: =SUMPRODUCT((YEAR($C$2:$AX$2)=BB$2)*$C6:$AX6) -> 3203200 | BC6: =SUMPRODUCT((YEAR($C$2:$AX$2)=BC$2)*$C6:$AX6) -> 6996000
B7: Less: industry-partner share | C7: ='Revenue forecast'!F28 -> -2100 | D7: ='Revenue forecast'!G28 -> -10725 | E7: ='Revenue forecast'!H28 -> -2700 | F7: ='Revenue forecast'!I28 -> -3225 | G7: ='Revenue forecast'!J28 -> -3300 | H7: ='Revenue forecast'!K28 -> -5400 | I7: ='Revenue forecast'!L28 -> -5400 | J7: ='Revenue forecast'!M28 -> -5400 | ... AX7: ='Revenue forecast'!BA28 -> -79425 | AZ7: =SUMPRODUCT((YEAR($C$2:$AX$2)=AZ$2)*$C7:$AX7) -> -76725 | BA7: =SUMPRODUCT((YEAR($C$2:$AX$2)=BA$2)*$C7:$AX7) -> -170175 | BB7: =SUMPRODUCT((YEAR($C$2:$AX$2)=BB$2)*$C7:$AX7) -> -326565 | BC7: =SUMPRODUCT((YEAR($C$2:$AX$2)=BC$2)*$C7:$AX7) -> -635962.5
B8: Total revenues | C8: =C5+C6+C7 -> 25900 | D8: =D5+D6+D7 -> 132275 | E8: =E5+E6+E7 -> 33300 | F8: =F5+F6+F7 -> 39775 | G8: =G5+G6+G7 -> 40700 | H8: =H5+H6+H7 -> 66600 | I8: =I5+I6+I7 -> 66600 | J8: =J5+J6+J7 -> 66600 | ... AX8: =AX5+AX6+AX7 -> 979575 | AZ8: =SUMPRODUCT((YEAR($C$2:$AX$2)=AZ$2)*$C8:$AX8) -> 946275 | BA8: =SUMPRODUCT((YEAR($C$2:$AX$2)=BA$2)*$C8:$AX8) -> 2098825 | BB8: =SUMPRODUCT((YEAR($C$2:$AX$2)=BB$2)*$C8:$AX8) -> 4027635 | BC8: =SUMPRODUCT((YEAR($C$2:$AX$2)=BC$2)*$C8:$AX8) -> 7843537.5
B10: Personnel
B11: Gross salary | C11: =Personnel!F18+Personnel!F21 -> 36000 | D11: =Personnel!G18+Personnel!G21 -> 36000 | E11: =Personnel!H18+Personnel!H21 -> 36000 | F11: =Personnel!I18+Personnel!I21 -> 36000 | G11: =Personnel!J18+Personnel!J21 -> 36000 | H11: =Personnel!K18+Personnel!K21 -> 39000 | I11: =Personnel!L18+Personnel!L21 -> 39000 | J11: =Personnel!M18+Personnel!M21 -> 39000 | ... AX11: =Personnel!BA18+Personnel!BA21 -> 78600 | AZ11: =SUMPRODUCT((YEAR($C$2:$AX$2)=AZ$2)*$C11:$AX11) -> 453000 | BA11: =SUMPRODUCT((YEAR($C$2:$AX$2)=BA$2)*$C11:$AX11) -> 587400 | BB11: =SUMPRODUCT((YEAR($C$2:$AX$2)=BB$2)*$C11:$AX11) -> 737300 | BC11: =SUMPRODUCT((YEAR($C$2:$AX$2)=BC$2)*$C11:$AX11) -> 892200
B12: Bonus | C12: =Personnel!F22 -> 0 | D12: =Personnel!G22 -> 35797.5 | E12: =Personnel!H22 -> 0 | F12: =Personnel!I22 -> 0 | G12: =Personnel!J22 -> 0 | H12: =Personnel!K22 -> 7159.5 | I12: =Personnel!L22 -> 7159.5 | J12: =Personnel!M22 -> 7159.5 | ... AX12: =Personnel!BA22 -> 337315.68 | AZ12: =SUMPRODUCT((YEAR($C$2:$AX$2)=AZ$2)*$C12:$AX12) -> 164668.5 | BA12: =SUMPRODUCT((YEAR($C$2:$AX$2)=BA$2)*$C12:$AX12) -> 512509.2 | BB12: =SUMPRODUCT((YEAR($C$2:$AX$2)=BB$2)*$C12:$AX12) -> 1151998.8 | BC12: =SUMPRODUCT((YEAR($C$2:$AX$2)=BC$2)*$C12:$AX12) -> 2521218.5
B13: Employer taxes | C13: =Personnel!F19+Personnel!F20 -> 8413.4 | D13: =Personnel!G19+Personnel!G20 -> 8413.4 | E13: =Personnel!H19+Personnel!H20 -> 8413.4 | F13: =Personnel!I19+Personnel!I20 -> 8413.4 | G13: =Personnel!J19+Personnel!J20 -> 8413.4 | H13: =Personnel!K19+Personnel!K20 -> 9269 | I13: =Personnel!L19+Personnel!L20 -> 9269 | J13: =Personnel!M19+Personnel!M20 -> 9269 | ... AX13: =Personnel!BA19+Personnel!BA20 -> 20135.12 | AZ13: =SUMPRODUCT((YEAR($C$2:$AX$2)=AZ$2)*$C13:$AX13) -> 106950 | BA13: =SUMPRODUCT((YEAR($C$2:$AX$2)=BA$2)*$C13:$AX13) -> 143569.68 | BB13: =SUMPRODUCT((YEAR($C$2:$AX$2)=BB$2)*$C13:$AX13) -> 184609.96 | BC13: =SUMPRODUCT((YEAR($C$2:$AX$2)=BC$2)*$C13:$AX13) -> 227076.24
B14: Contractors | C14: =Personnel!F23 -> 450 | D14: =Personnel!G23 -> 450 | E14: =Personnel!H23 -> 450 | F14: =Personnel!I23 -> 450 | G14: =Personnel!J23 -> 450 | H14: =Personnel!K23 -> 450 | I14: =Personnel!L23 -> 450 | J14: =Personnel!M23 -> 450 | ... AX14: =Personnel!BA23 -> 450 | AZ14: =SUMPRODUCT((YEAR($C$2:$AX$2)=AZ$2)*$C14:$AX14) -> 5400 | BA14: =SUMPRODUCT((YEAR($C$2:$AX$2)=BA$2)*$C14:$AX14) -> 5400 | BB14: =SUMPRODUCT((YEAR($C$2:$AX$2)=BB$2)*$C14:$AX14) -> 5400 | BC14: =SUMPRODUCT((YEAR($C$2:$AX$2)=BC$2)*$C14:$AX14) -> 5400
B15: Strategic Advisory costs | C15: 0 | D15: 0 | E15: 0 | F15: 0 | G15: 0 | H15: 0 | I15: 0 | J15: 0 | K15: 0 | L15: 0 | M15: 0 | N15: 0 | O15: 0 | P15: 0 | Q15: 0 | R15: 0 | S15: 0 | T15: 0 | U15: 0 | V15: 0 | W15: 0 | X15: 0 | Y15: 0 | Z15: 0 | AA15: 0 | AB15: 0 | AC15: 0 | AD15: 0 | AE15: 0 | AF15: 0 | AG15: 0 | AH15: 0 | AI15: 0 | AJ15: 0 | AK15: 0 | AL15: 0 | AM15: 0 | AN15: 0 | AO15: 0 | AP15: 0 | AQ15: 0 | AR15: 0 | AS15: 0 | AT15: 0 | AU15: 0 | AV15: 0 | AW15: 0 | AX15: 0 | AZ15: =SUMPRODUCT((YEAR($C$2:$AX$2)=AZ$2)*$C15:$AX15) -> 0 | BA15: =SUMPRODUCT((YEAR($C$2:$AX$2)=BA$2)*$C15:$AX15) -> 0 | BB15: =SUMPRODUCT((YEAR($C$2:$AX$2)=BB$2)*$C15:$AX15) -> 0 | BC15: =SUMPRODUCT((YEAR($C$2:$AX$2)=BC$2)*$C15:$AX15) -> 0
B16: Other people costs | C16: =Personnel!F24 -> 267 | D16: =Personnel!G24 -> 267 | E16: =Personnel!H24 -> 267 | F16: =Personnel!I24 -> 267 | G16: =Personnel!J24 -> 267 | H16: =Personnel!K24 -> 267 | I16: =Personnel!L24 -> 267 | J16: =Personnel!M24 -> 267 | ... AX16: =Personnel!BA24 -> 267 | AZ16: =SUMPRODUCT((YEAR($C$2:$AX$2)=AZ$2)*$C16:$AX16) -> 3204 | BA16: =SUMPRODUCT((YEAR($C$2:$AX$2)=BA$2)*$C16:$AX16) -> 3204 | BB16: =SUMPRODUCT((YEAR($C$2:$AX$2)=BB$2)*$C16:$AX16) -> 3204 | BC16: =SUMPRODUCT((YEAR($C$2:$AX$2)=BC$2)*$C16:$AX16) -> 3204
B17: Total personnel | C17: =SUM(C11:C16) -> 45130.4 | D17: =SUM(D11:D16) -> 80927.9 | E17: =SUM(E11:E16) -> 45130.4 | F17: =SUM(F11:F16) -> 45130.4 | G17: =SUM(G11:G16) -> 45130.4 | H17: =SUM(H11:H16) -> 56145.5 | I17: =SUM(I11:I16) -> 56145.5 | J17: =SUM(J11:J16) -> 56145.5 | ... AX17: =SUM(AX11:AX16) -> 436767.8 | AZ17: =SUMPRODUCT((YEAR($C$2:$AX$2)=AZ$2)*$C17:$AX17) -> 733222.5 | BA17: =SUMPRODUCT((YEAR($C$2:$AX$2)=BA$2)*$C17:$AX17) -> 1252082.9 | BB17: =SUMPRODUCT((YEAR($C$2:$AX$2)=BB$2)*$C17:$AX17) -> 2082512.8 | BC17: =SUMPRODUCT((YEAR($C$2:$AX$2)=BC$2)*$C17:$AX17) -> 3649098.7
B19: Gross profit | C19: =C8-C17 -> -19230.4 | D19: =D8-D17 -> 51347.1 | E19: =E8-E17 -> -11830.4 | F19: =F8-F17 -> -5355.4 | G19: =G8-G17 -> -4430.4 | H19: =H8-H17 -> 10454.5 | I19: =I8-I17 -> 10454.5 | J19: =J8-J17 -> 10454.5 | ... AX19: =AX8-AX17 -> 542807.2 | AZ19: =SUMPRODUCT((YEAR($C$2:$AX$2)=AZ$2)*$C19:$AX19) -> 213052.5 | BA19: =SUMPRODUCT((YEAR($C$2:$AX$2)=BA$2)*$C19:$AX19) -> 846742.12 | BB19: =SUMPRODUCT((YEAR($C$2:$AX$2)=BB$2)*$C19:$AX19) -> 1945122.2 | BC19: =SUMPRODUCT((YEAR($C$2:$AX$2)=BC$2)*$C19:$AX19) -> 4194438.8
B21: Other OPEX
B22: Rent | C22: =OPEX!F7 -> 4800 | D22: =OPEX!G7 -> 4800 | E22: =OPEX!H7 -> 4800 | F22: =OPEX!I7 -> 4800 | G22: =OPEX!J7 -> 4800 | H22: =OPEX!K7 -> 5400 | I22: =OPEX!L7 -> 5400 | J22: =OPEX!M7 -> 5400 | ... AX22: =OPEX!BA7 -> 8400 | AZ22: =SUMPRODUCT((YEAR($C$2:$AX$2)=AZ$2)*$C22:$AX22) -> 61800 | BA22: =SUMPRODUCT((YEAR($C$2:$AX$2)=BA$2)*$C22:$AX22) -> 72000 | BB22: =SUMPRODUCT((YEAR($C$2:$AX$2)=BB$2)*$C22:$AX22) -> 83400 | BC22: =SUMPRODUCT((YEAR($C$2:$AX$2)=BC$2)*$C22:$AX22) -> 93600
B23: Software | C23: =OPEX!F8 -> 4293.3333 | D23: =OPEX!G8 -> 4293.3333 | E23: =OPEX!H8 -> 4293.3333 | F23: =OPEX!I8 -> 4293.3333 | G23: =OPEX!J8 -> 4293.3333 | H23: =OPEX!K8 -> 4413.3333 | I23: =OPEX!L8 -> 4413.3333 | J23: =OPEX!M8 -> 4413.3333 | ... AX23: =OPEX!BA8 -> 6680 | AZ23: =SUMPRODUCT((YEAR($C$2:$AX$2)=AZ$2)*$C23:$AX23) -> 52360 | BA23: =SUMPRODUCT((YEAR($C$2:$AX$2)=BA$2)*$C23:$AX23) -> 64400 | BB23: =SUMPRODUCT((YEAR($C$2:$AX$2)=BB$2)*$C23:$AX23) -> 76680 | BC23: =SUMPRODUCT((YEAR($C$2:$AX$2)=BC$2)*$C23:$AX23) -> 78720
B24: Office | C24: =OPEX!F9 -> 320 | D24: =OPEX!G9 -> 320 | E24: =OPEX!H9 -> 320 | F24: =OPEX!I9 -> 320 | G24: =OPEX!J9 -> 320 | H24: =OPEX!K9 -> 360 | I24: =OPEX!L9 -> 360 | J24: =OPEX!M9 -> 360 | ... AX24: =OPEX!BA9 -> 560 | AZ24: =SUMPRODUCT((YEAR($C$2:$AX$2)=AZ$2)*$C24:$AX24) -> 4120 | BA24: =SUMPRODUCT((YEAR($C$2:$AX$2)=BA$2)*$C24:$AX24) -> 4800 | BB24: =SUMPRODUCT((YEAR($C$2:$AX$2)=BB$2)*$C24:$AX24) -> 5560 | BC24: =SUMPRODUCT((YEAR($C$2:$AX$2)=BC$2)*$C24:$AX24) -> 6240
B25: Marketing & Sales | C25: =OPEX!F10 -> 250 | D25: =OPEX!G10 -> 250 | E25: =OPEX!H10 -> 250 | F25: =OPEX!I10 -> 250 | G25: =OPEX!J10 -> 250 | H25: =OPEX!K10 -> 250 | I25: =OPEX!L10 -> 250 | J25: =OPEX!M10 -> 250 | ... AX25: =OPEX!BA10 -> 500 | AZ25: =SUMPRODUCT((YEAR($C$2:$AX$2)=AZ$2)*$C25:$AX25) -> 3000 | BA25: =SUMPRODUCT((YEAR($C$2:$AX$2)=BA$2)*$C25:$AX25) -> 4000 | BB25: =SUMPRODUCT((YEAR($C$2:$AX$2)=BB$2)*$C25:$AX25) -> 5000 | BC25: =SUMPRODUCT((YEAR($C$2:$AX$2)=BC$2)*$C25:$AX25) -> 6000
B26: Travel | C26: =OPEX!F11 -> 500 | D26: =OPEX!G11 -> 500 | E26: =OPEX!H11 -> 500 | F26: =OPEX!I11 -> 500 | G26: =OPEX!J11 -> 500 | H26: =OPEX!K11 -> 500 | I26: =OPEX!L11 -> 500 | J26: =OPEX!M11 -> 500 | ... AX26: =OPEX!BA11 -> 625 | AZ26: =SUMPRODUCT((YEAR($C$2:$AX$2)=AZ$2)*$C26:$AX26) -> 6000 | BA26: =SUMPRODUCT((YEAR($C$2:$AX$2)=BA$2)*$C26:$AX26) -> 6500 | BB26: =SUMPRODUCT((YEAR($C$2:$AX$2)=BB$2)*$C26:$AX26) -> 7000 | BC26: =SUMPRODUCT((YEAR($C$2:$AX$2)=BC$2)*$C26:$AX26) -> 7500
B27: SG&A | C27: =OPEX!F12 -> 800 | D27: =OPEX!G12 -> 800 | E27: =OPEX!H12 -> 800 | F27: =OPEX!I12 -> 800 | G27: =OPEX!J12 -> 800 | H27: =OPEX!K12 -> 900 | I27: =OPEX!L12 -> 900 | J27: =OPEX!M12 -> 900 | ... AX27: =OPEX!BA12 -> 1400 | AZ27: =SUMPRODUCT((YEAR($C$2:$AX$2)=AZ$2)*$C27:$AX27) -> 10300 | BA27: =SUMPRODUCT((YEAR($C$2:$AX$2)=BA$2)*$C27:$AX27) -> 12000 | BB27: =SUMPRODUCT((YEAR($C$2:$AX$2)=BB$2)*$C27:$AX27) -> 13900 | BC27: =SUMPRODUCT((YEAR($C$2:$AX$2)=BC$2)*$C27:$AX27) -> 15600
B28: Other | C28: =OPEX!F13 -> 140 | D28: =OPEX!G13 -> 140 | E28: =OPEX!H13 -> 140 | F28: =OPEX!I13 -> 140 | G28: =OPEX!J13 -> 140 | H28: =OPEX!K13 -> 140 | I28: =OPEX!L13 -> 140 | J28: =OPEX!M13 -> 140 | ... AX28: =OPEX!BA13 -> 140 | AZ28: =SUMPRODUCT((YEAR($C$2:$AX$2)=AZ$2)*$C28:$AX28) -> 1680 | BA28: =SUMPRODUCT((YEAR($C$2:$AX$2)=BA$2)*$C28:$AX28) -> 1680 | BB28: =SUMPRODUCT((YEAR($C$2:$AX$2)=BB$2)*$C28:$AX28) -> 1680 | BC28: =SUMPRODUCT((YEAR($C$2:$AX$2)=BC$2)*$C28:$AX28) -> 1680
B29: Total other OPEX | C29: =SUM(C22:C28) -> 11103.333 | D29: =SUM(D22:D28) -> 11103.333 | E29: =SUM(E22:E28) -> 11103.333 | F29: =SUM(F22:F28) -> 11103.333 | G29: =SUM(G22:G28) -> 11103.333 | H29: =SUM(H22:H28) -> 11963.333 | I29: =SUM(I22:I28) -> 11963.333 | J29: =SUM(J22:J28) -> 11963.333 | ... AX29: =SUM(AX22:AX28) -> 18305 | AZ29: =SUMPRODUCT((YEAR($C$2:$AX$2)=AZ$2)*$C29:$AX29) -> 139260 | BA29: =SUMPRODUCT((YEAR($C$2:$AX$2)=BA$2)*$C29:$AX29) -> 165380 | BB29: =SUMPRODUCT((YEAR($C$2:$AX$2)=BB$2)*$C29:$AX29) -> 193220 | BC29: =SUMPRODUCT((YEAR($C$2:$AX$2)=BC$2)*$C29:$AX29) -> 209340
B31: RX allocation | C31: =OPEX!F14 -> 1307 | D31: =OPEX!G14 -> 1307 | E31: =OPEX!H14 -> 1307 | F31: =OPEX!I14 -> 1307 | G31: =OPEX!J14 -> 1307 | H31: =OPEX!K14 -> 1307 | I31: =OPEX!L14 -> 1307 | J31: =OPEX!M14 -> 1307 | ... AX31: =OPEX!BA14 -> 1307 | AZ31: =SUMPRODUCT((YEAR($C$2:$AX$2)=AZ$2)*$C31:$AX31) -> 15684 | BA31: =SUMPRODUCT((YEAR($C$2:$AX$2)=BA$2)*$C31:$AX31) -> 15684 | BB31: =SUMPRODUCT((YEAR($C$2:$AX$2)=BB$2)*$C31:$AX31) -> 15684 | BC31: =SUMPRODUCT((YEAR($C$2:$AX$2)=BC$2)*$C31:$AX31) -> 15684
B33: Total costs | C33: =C17+C29+C31 -> 57540.733 | D33: =D17+D29+D31 -> 93338.233 | E33: =E17+E29+E31 -> 57540.733 | F33: =F17+F29+F31 -> 57540.733 | G33: =G17+G29+G31 -> 57540.733 | H33: =H17+H29+H31 -> 69415.833 | I33: =I17+I29+I31 -> 69415.833 | J33: =J17+J29+J31 -> 69415.833 | ... AX33: =AX17+AX29+AX31 -> 456379.8 | AZ33: =SUMPRODUCT((YEAR($C$2:$AX$2)=AZ$2)*$C33:$AX33) -> 888166.5 | BA33: =SUMPRODUCT((YEAR($C$2:$AX$2)=BA$2)*$C33:$AX33) -> 1433146.9 | BB33: =SUMPRODUCT((YEAR($C$2:$AX$2)=BB$2)*$C33:$AX33) -> 2291416.8 | BC33: =SUMPRODUCT((YEAR($C$2:$AX$2)=BC$2)*$C33:$AX33) -> 3874122.7
B35: EBITDA (total) | C35: =C8-C33 -> -31640.733 | D35: =D8-D33 -> 38936.767 | E35: =E8-E33 -> -24240.733 | F35: =F8-F33 -> -17765.733 | G35: =G8-G33 -> -16840.733 | H35: =H8-H33 -> -2815.8333 | I35: =I8-I33 -> -2815.8333 | J35: =J8-J33 -> -2815.8333 | ... AX35: =AX8-AX33 -> 523195.2 | AZ35: =SUMPRODUCT((YEAR($C$2:$AX$2)=AZ$2)*$C35:$AX35) -> 58108.5 | BA35: =SUMPRODUCT((YEAR($C$2:$AX$2)=BA$2)*$C35:$AX35) -> 665678.12 | BB35: =SUMPRODUCT((YEAR($C$2:$AX$2)=BB$2)*$C35:$AX35) -> 1736218.2 | BC35: =SUMPRODUCT((YEAR($C$2:$AX$2)=BC$2)*$C35:$AX35) -> 3969414.8
B36: EBITDA margin (total) | C36: =IF(C8=0,0,C35/C8) -> -1.2216499 | D36: =IF(D8=0,0,D35/D8) -> 0.29436225 | E36: =IF(E8=0,0,E35/E8) -> -0.72794995 | F36: =IF(F8=0,0,F35/F8) -> -0.44665577 | G36: =IF(G8=0,0,G35/G8) -> -0.41377723 | H36: =IF(H8=0,0,H35/H8) -> -0.04227978 | I36: =IF(I8=0,0,I35/I8) -> -0.04227978 | J36: =IF(J8=0,0,J35/J8) -> -0.04227978 | ... AX36: =IF(AX8=0,0,AX35/AX8) -> 0.53410428 | AZ36: =IF(AZ8=0,0,AZ35/AZ8) -> 0.061407625 | BA36: =IF(BA8=0,0,BA35/BA8) -> 0.31716704 | BB36: =IF(BB8=0,0,BB35/BB8) -> 0.43107635 | BC36: =IF(BC8=0,0,BC35/BC8) -> 0.50607456
B38: EBITDA (without success fee) | C38: =C5-C33+C12 -> -29540.733 | D38: =D5-D33+D12 -> -14540.733 | E38: =E5-E33+E12 -> -21540.733 | F38: =F5-F33+F12 -> -14540.733 | G38: =G5-G33+G12 -> -13540.733 | H38: =H5-H33+H12 -> -10256.333 | I38: =I5-I33+I12 -> -10256.333 | J38: =J5-J33+J12 -> -10256.333 | ... AX38: =AX5-AX33+AX12 -> 3935.88 | AZ38: =SUMPRODUCT((YEAR($C$2:$AX$2)=AZ$2)*$C38:$AX38) -> -160498 | BA38: =SUMPRODUCT((YEAR($C$2:$AX$2)=BA$2)*$C38:$AX38) -> -79637.68 | BB38: =SUMPRODUCT((YEAR($C$2:$AX$2)=BB$2)*$C38:$AX38) -> 11582.04 | BC38: =SUMPRODUCT((YEAR($C$2:$AX$2)=BC$2)*$C38:$AX38) -> 130595.76
B39: EBITDA margin (without success fee) | C39: =IF(C5=0,0,C38/C5) -> -1.0550262 | D39: =IF(D5=0,0,D38/D5) -> -0.33815659 | E39: =IF(E5=0,0,E38/E5) -> -0.5983537 | F39: =IF(F5=0,0,F38/F5) -> -0.33815659 | G39: =IF(G5=0,0,G38/G5) -> -0.30774394 | H39: =IF(H5=0,0,H38/H5) -> -0.19723718 | I39: =IF(I5=0,0,I38/I5) -> -0.19723718 | J39: =IF(J5=0,0,J38/J5) -> -0.19723718 | ... AX39: =IF(AX5=0,0,AX38/AX5) -> 0.031999024 | AZ39: =IF(AZ5=0,0,AZ38/AZ5) -> -0.28507638 | BA39: =IF(BA5=0,0,BA38/BA5) -> -0.094694031 | BB39: =IF(BB5=0,0,BB38/BB5) -> 0.010062589 | BC39: =IF(BC5=0,0,BC38/BC5) -> 0.088032194

Sheet Dashboard
B2: Dashboard — Annual Summary 2027–2030
C4: 2027 | D4: 2028 | E4: 2029 | F4: 2030
B5: Revenue (gross) | C5: ='Revenue forecast'!BC27 -> 1023000 | D5: ='Revenue forecast'!BD27 -> 2269000 | E5: ='Revenue forecast'!BE27 -> 4354200 | F5: ='Revenue forecast'!BF27 -> 8479500
B6: Net revenue | C6: ='Financial Statements'!AZ8 -> 946275 | D6: ='Financial Statements'!BA8 -> 2098825 | E6: ='Financial Statements'!BB8 -> 4027635 | F6: ='Financial Statements'!BC8 -> 7843537.5
B7: EBITDA | C7: ='Financial Statements'!AZ35 -> 58108.5 | D7: ='Financial Statements'!BA35 -> 665678.12 | E7: ='Financial Statements'!BB35 -> 1736218.2 | F7: ='Financial Statements'!BC35 -> 3969414.8
B8: EBITDA margin % | C8: ='Financial Statements'!AZ36 -> 0.061407625 | D8: ='Financial Statements'!BA36 -> 0.31716704 | E8: ='Financial Statements'!BB36 -> 0.43107635 | F8: ='Financial Statements'!BC36 -> 0.50607456
B9: New deals | C9: =Assumptions!C17 -> 15 | D9: =Assumptions!D17 -> 20 | E9: =Assumptions!E17 -> 25 | F9: =Assumptions!F17 -> 30
B10: Live projects (avg) | C10: =Personnel!BC7 -> 7 | D10: =Personnel!BD7 -> 10 | E10: =Personnel!BE7 -> 13 | F10: =Personnel!BF7 -> 14
B11: Total FTE | C11: =Personnel!BC15 -> 9 | D11: =Personnel!BD15 -> 11 | E11: =Personnel!BE15 -> 12 | F11: =Personnel!BF15 -> 14
B12: Revenue per FTE (net) | C12: =C6/C11 -> 105141.67 | D12: =D6/D11 -> 190802.27 | E12: =E6/E11 -> 335636.25 | F12: =F6/F11 -> 560252.68
