Workbook

Sheet Cover
B2: EVOLUTE
B4: Financial Model — 2027–2030
B6: Currency: EUR (€)
B7: Basis: monthly, aggregated to annual
B8: STRICTLY CONFIDENTIAL
B10: Contents
B11: Assumptions — all inputs & business drivers (edit here only)
B12: Revenue forecast — Growth Capital & M&A deal engine
B13: Personnel — headcount & salaries
B14: OPEX — operating costs
B15: Financial Statements — income statement
B16: Dashboard — annual summary

Sheet How to read me
B2: How to read this model
B4: STRUCTURE
B5: Assumptions → Revenue forecast → Personnel → OPEX → Financial Statements → Dashboard.
B6: Every tab is monthly (Jan 2027 – Dec 2030) with annual roll-up columns at the far right.
B8: HOW TO USE
B9: Change numbers ONLY on the Assumptions tab. All other tabs recalculate automatically.
B11: REVENUE LOGIC
B12: Two business lines: Growth Capital (retainer + success fee on ticket) and M&A (retainer + success fee on EV).
B13: Deals get bigger (M&A EV) and convert better over time; mix drifts 90/10 → 50/50.
B14: Industry partners source 25% of deals and take 25% of their retainer + fee.
B16: STAFFING
B17: 1 analyst per 3 live projects; associate at 10 live, 2nd at 15. Simon = delivery lead, Rob = partner + sales hire.

Sheet Assumptions
B1: Assumptions | C1: 2027 | D1: 2028 | E1: 2029 | F1: 2030
B2: GROWTH CAPITAL
B3: Retainer / month | C3: 7000 | D3: 7500 | E3: 8000 | F3: 8500 | G3: €/mo
B4: Avg engagement length | C4: 6 | D4: 6 | E4: 6 | F4: 6 | G4: months
B5: Success fee % | C5: 0.02 | D5: 0.02 | E5: 0.02 | F5: 0.02 | G5: %
B6: Ticket size | C6: 5000000 | D6: 7000000 | E6: 10000000 | F6: 15000000 | G6: €
B7: Close rate % | C7: 0.2 | D7: 0.25 | E7: 0.28 | F7: 0.32 | G7: %
B9: M&A
B10: Retainer / month | C10: 8000 | D10: 8500 | E10: 8500 | F10: 9000 | G10: €/mo
B11: Avg engagement length | C11: 7 | D11: 7 | E11: 7 | F11: 7 | G11: months
B12: Success fee % | C12: 0.02 | D12: 0.02 | E12: 0.02 | F12: 0.02 | G12: %
B13: Enterprise value | C13: 12000000 | D13: 18000000 | E13: 24000000 | F13: 30000000 | G13: €
B14: Close rate % | C14: 0.5 | D14: 0.56 | E14: 0.63 | F14: 0.7 | G14: %
B16: SOFTWARE
B17: Software price / month | C17: 500 | D17: 500 | E17: 500 | F17: 500 | G17: €/mo
B18: Post-engagement churn / yr | C18: 0.2 | G18: %/yr
B19: Monthly churn (computed) | C19: =1-(1-$C$18)^(1/12) -> 0.01842347 | G19: %/mo
B20: Software wins / rep / month | C20: 0 | D20: 0 | E20: 3 | F20: 4 | G20: #
B21: Direct churn / yr | C21: 0.3 | G21: %/yr
B22: Direct monthly churn (computed) | C22: =1-(1-$C$21)^(1/12) -> 0.02928553 | G22: %/mo
B23: Hosting / subscriber / month | C23: 20 | G23: €/mo
B24: Hosting fixed / month | C24: 500 | G24: €/mo
B26: DEAL FLOW
B27: New deals started / yr | C27: 15 | D27: 20 | E27: 25 | F27: 30 | G27: #
B28: Growth Capital mix % | C28: 0.7 | D28: 0.6 | E28: 0.65 | F28: 0.5 | G28: % | H28: Explanation: The percentage of all new deals that are Growth Capital projects
B30: SOURCING & COMPENSATION
B31: Industry-partner: share of deals they source % | C31: 0.3 | D31: 0.35 | E31: 0.4 | F31: 0.45 | G31: % | H31: Explanation: The fraction of deals that are sourced by industry partners
B32: Sales-hire source share % | C32: 0.375 | D32: 0.4 | E32: 0.42 | F32: 0.44 | G32: % | H32: Explanation: The fraction of deals sourced by internal sales team
B33: Industry-partner: cut of those deals' revenue % | C33: 0.25 | D33: 0.25 | E33: 0.25 | F33: 0.25 | G33: % | H33: Explanation: When an industry partner refers a deal, they take 25% of the revenue on that deal (retainer + success fee)
B34: Success-fee bonus pool % | C34: 0.4 | D34: 0.4 | E34: 0.4 | F34: 0.4 | G34: % | H34: Explanation: 40% of success fees (after the partner cut when applicable) goes into the internal bonus pool for the team. The other 60% drops to the firm's bottom line
B36: PERSONNEL
B37: Rob salary / month | C37: =10000*(C$1-2026) -> 10000 | D37: =C37+2000 -> 12000 | E37: =D37+2000 -> 14000 | F37: =E37+2000 -> 16000 | G37: €/mo
B38: Simon salary / month | C38: 7500 | D38: =C38+2000 -> 9500 | E38: =D38+2000 -> 11500 | F38: =E38+2000 -> 13500 | G38: €/mo
B39: Associate salary / month | C39: 4500 | D39: =C39+250 -> 4750 | E39: =D39+250 -> 5000 | F39: =E39+250 -> 5250 | G39: €/mo
B40: Analyst salary / month | C40: 3000 | D40: =C40+250 -> 3250 | E40: =D40+250 -> 3500 | F40: =E40+250 -> 3750 | G40: €/mo
B41: Intern salary / month | C41: 500 | D41: 600 | E41: 700 | F41: 800 | G41: €/mo
B42: Marketing salary/ month | C42: 5000 | D42: =C42+500 -> 5500 | E42: =D42+500 -> 6000 | F42: =E42+500 -> 6500 | G42: €/mo
B43: Sales hire cost / month | C43: 6500 | D43: 7000 | E43: 7500 | F43: 8000 | G43: €/mo
B44: Software sales salary / month | C44: 5000 | D44: 5500 | E44: 6000 | F44: 6500 | G44: €/mo
B45: Developer salary / month | C45: 5500 | D45: 6000 | E45: 6500 | F45: 7000 | G45: €/mo
B46: Holiday pay % | C46: 0.08 | D46: 0.08 | E46: 0.08 | F46: 0.08 | G46: %
B47: Employer tax % | C47: 0.19 | D47: 0.19 | E47: 0.19 | F47: 0.19 | G47: %
B48: Live projects per analyst | C48: 3 | D48: 3 | E48: 3 | F48: 3 | G48: #
B50: Hiring Triggers
B51: Associate trigger 1 (live proj) | C51: 10 | G51: #
B52: Associate trigger 2 (live proj) | C52: 15 | G52: #
B53: Interns (minimum) | C53: 2 | G53: #
B55: OPEX (monthly)
B56: Rent / FTE | C56: 600 | G56: €/FTE
B57: Software / FTE | C57: 120 | G57: €/FTE
B58: Database €/yr (FTE ≤6 / 7–9 / 10–15 / 16+) | C58: 35000 | D58: 40000 | E58: 60000 | F58: 70000 | G58: €/yr
B59: Hardware / FTE | C59: 40 | G59: €/FTE
B60: F&B / FTE | C60: 100 | G60: €/FTE
B61: Marketing & Sales (annual, spread monthly) | C61: 3000 | D61: 4000 | E61: 5000 | F61: 6000 | G61: €/yr
B62: Travel (annual, spread monthly) | C62: 6000 | D62: 6500 | E62: 7000 | F62: 7500 | G62: €/yr
B63: RX allocation (fixed) | C63: 1307 | G63: €/mo
B64: Other (fixed) | C64: 140 | G64: €/mo

Sheet Revenue forecast
B2: Revenue forecast — Monthly 2027–2030 (€)
E3: Unit | F3: 46388 | G3: 46419 | H3: 46447 | I3: 46478 | J3: 46508 | K3: 46539 | L3: 46569 | M3: 46600 | N3: 46631 | O3: 46661 | P3: 46692 | Q3: 46722 | R3: 46753 | S3: 46784 | T3: 46813 | U3: 46844 | V3: 46874 | W3: 46905 | X3: 46935 | Y3: 46966 | Z3: 46997 | AA3: 47027 | AB3: 47058 | AC3: 47088 | AD3: 47119 | AE3: 47150 | AF3: 47178 | AG3: 47209 | AH3: 47239 | AI3: 47270 | AJ3: 47300 | AK3: 47331 | AL3: 47362 | AM3: 47392 | AN3: 47423 | AO3: 47453 | AP3: 47484 | AQ3: 47515 | AR3: 47543 | AS3: 47574 | AT3: 47604 | AU3: 47635 | AV3: 47665 | AW3: 47696 | AX3: 47727 | AY3: 47757 | AZ3: 47788 | BA3: 47818 | BC3: 2027 | BD3: 2028 | BE3: 2029 | BF3: 2030
B6: GROWTH CAPITAL
B7: New deals started | E7: # | F7: {=ROUND((INDEX(Assumptions!$C$27:$F$27,MATCH(YEAR(F$3),Assumptions!$C$1:$F$1,0))*INDEX(Assumptions!$C$28:$F$28,MATCH(YEAR(F$3),Assumptions!$C$1:$F$1,0)))*MONTH(F$3)/12,0)-ROUND((INDEX(Assumptions!$C$27:$F$27,MATCH(YEAR(F$3),Assumptions!$C$1:$F$1,0))*INDEX(Assumptions!$C$28:$F$28,MATCH(YEAR(F$3),Assumptions!$C$1:$F$1,0)))*(MONTH(F$3)-1)/12,0)} -> 1 | G7: {=ROUND((INDEX(Assumptions!$C$27:$F$27,MATCH(YEAR(G$3),Assumptions!$C$1:$F$1,0))*INDEX(Assumptions!$C$28:$F$28,MATCH(YEAR(G$3),Assumptions!$C$1:$F$1,0)))*MONTH(G$3)/12,0)-ROUND((INDEX(Assumptions!$C$27:$F$27,MATCH(YEAR(G$3),Assumptions!$C$1:$F$1,0))*INDEX(Assumptions!$C$28:$F$28,MATCH(YEAR(G$3),Assumptions!$C$1:$F$1,0)))*(MONTH(G$3)-1)/12,0)} -> 1 | H7: {=ROUND((INDEX(Assumptions!$C$27:$F$27,MATCH(YEAR(H$3),Assumptions!$C$1:$F$1,0))*INDEX(Assumptions!$C$28:$F$28,MATCH(YEAR(H$3),Assumptions!$C$1:$F$1,0)))*MONTH(H$3)/12,0)-ROUND((INDEX(Assumptions!$C$27:$F$27,MATCH(YEAR(H$3),Assumptions!$C$1:$F$1,0))*INDEX(Assumptions!$C$28:$F$28,MATCH(YEAR(H$3),Assumptions!$C$1:$F$1,0)))*(MONTH(H$3)-1)/12,0)} -> 1 | I7: {=ROUND((INDEX(Assumptions!$C$27:$F$27,MATCH(YEAR(I$3),Assumptions!$C$1:$F$1,0))*INDEX(Assumptions!$C$28:$F$28,MATCH(YEAR(I$3),Assumptions!$C$1:$F$1,0)))*MONTH(I$3)/12,0)-ROUND((INDEX(Assumptions!$C$27:$F$27,MATCH(YEAR(I$3),Assumptions!$C$1:$F$1,0))*INDEX(Assumptions!$C$28:$F$28,MATCH(YEAR(I$3),Assumptions!$C$1:$F$1,0)))*(MONTH(I$3)-1)/12,0)} -> 1 | J7: {=ROUND((INDEX(Assumptions!$C$27:$F$27,MATCH(YEAR(J$3),Assumptions!$C$1:$F$1,0))*INDEX(Assumptions!$C$28:$F$28,MATCH(YEAR(J$3),Assumptions!$C$1:$F$1,0)))*MONTH(J$3)/12,0)-ROUND((INDEX(Assumptions!$C$27:$F$27,MATCH(YEAR(J$3),Assumptions!$C$1:$F$1,0))*INDEX(Assumptions!$C$28:$F$28,MATCH(YEAR(J$3),Assumptions!$C$1:$F$1,0)))*(MONTH(J$3)-1)/12,0)} -> 0 | K7: {=ROUND((INDEX(Assumptions!$C$27:$F$27,MATCH(YEAR(K$3),Assumptions!$C$1:$F$1,0))*INDEX(Assumptions!$C$28:$F$28,MATCH(YEAR(K$3),Assumptions!$C$1:$F$1,0)))*MONTH(K$3)/12,0)-ROUND((INDEX(Assumptions!$C$27:$F$27,MATCH(YEAR(K$3),Assumptions!$C$1:$F$1,0))*INDEX(Assumptions!$C$28:$F$28,MATCH(YEAR(K$3),Assumptions!$C$1:$F$1,0)))*(MONTH(K$3)-1)/12,0)} -> 1 | L7: {=ROUND((INDEX(Assumptions!$C$27:$F$27,MATCH(YEAR(L$3),Assumptions!$C$1:$F$1,0))*INDEX(Assumptions!$C$28:$F$28,MATCH(YEAR(L$3),Assumptions!$C$1:$F$1,0)))*MONTH(L$3)/12,0)-ROUND((INDEX(Assumptions!$C$27:$F$27,MATCH(YEAR(L$3),Assumptions!$C$1:$F$1,0))*INDEX(Assumptions!$C$28:$F$28,MATCH(YEAR(L$3),Assumptions!$C$1:$F$1,0)))*(MONTH(L$3)-1)/12,0)} -> 1 | M7: {=ROUND((INDEX(Assumptions!$C$27:$F$27,MATCH(YEAR(M$3),Assumptions!$C$1:$F$1,0))*INDEX(Assumptions!$C$28:$F$28,MATCH(YEAR(M$3),Assumptions!$C$1:$F$1,0)))*MONTH(M$3)/12,0)-ROUND((INDEX(Assumptions!$C$27:$F$27,MATCH(YEAR(M$3),Assumptions!$C$1:$F$1,0))*INDEX(Assumptions!$C$28:$F$28,MATCH(YEAR(M$3),Assumptions!$C$1:$F$1,0)))*(MONTH(M$3)-1)/12,0)} -> 1 | ... BA7: {=ROUND((INDEX(Assumptions!$C$27:$F$27,MATCH(YEAR(BA$3),Assumptions!$C$1:$F$1,0))*INDEX(Assumptions!$C$28:$F$28,MATCH(YEAR(BA$3),Assumptions!$C$1:$F$1,0)))*MONTH(BA$3)/12,0)-ROUND((INDEX(Assumptions!$C$27:$F$27,MATCH(YEAR(BA$3),Assumptions!$C$1:$F$1,0))*INDEX(Assumptions!$C$28:$F$28,MATCH(YEAR(BA$3),Assumptions!$C$1:$F$1,0)))*(MONTH(BA$3)-1)/12,0)} -> 1 | BC7: =SUMPRODUCT((YEAR($F$3:$BA$3)=BC$3)*$F7:$BA7) -> 11 | BD7: =SUMPRODUCT((YEAR($F$3:$BA$3)=BD$3)*$F7:$BA7) -> 12 | BE7: =SUMPRODUCT((YEAR($F$3:$BA$3)=BE$3)*$F7:$BA7) -> 16 | BF7: =SUMPRODUCT((YEAR($F$3:$BA$3)=BF$3)*$F7:$BA7) -> 15
B8: Live projects | E8: # | F8: =SUM(F7)+F43 -> 4 | G8: =SUM(F7:G7)+G43 -> 5 | H8: =SUM(F7:H7)+H43 -> 4 | I8: =SUM(F7:I7)+I43 -> 5 | J8: =SUM(F7:J7) -> 4 | K8: =SUM(G7:K7) -> 4 | L8: =SUM(H7:L7) -> 4 | M8: =SUM(I7:M7) -> 4 | N8: =SUM(J7:N7) -> 4 | O8: =SUM(K7:O7) -> 5 | P8: =SUM(L7:P7) -> 5 | Q8: =SUM(M7:Q7) -> 5 | ... BA8: =SUM(AW7:BA7) -> 6
B9: Retainer revenue | E9: € | F9: {=F8*(INDEX(Assumptions!$C$3:$F$3,MATCH(YEAR(F$3),Assumptions!$C$1:$F$1,0))-INDEX(Assumptions!$C$17:$F$17,MATCH(YEAR(F$3),Assumptions!$C$1:$F$1,0)))} -> 26000 | G9: {=G8*(INDEX(Assumptions!$C$3:$F$3,MATCH(YEAR(G$3),Assumptions!$C$1:$F$1,0))-INDEX(Assumptions!$C$17:$F$17,MATCH(YEAR(G$3),Assumptions!$C$1:$F$1,0)))} -> 32500 | H9: {=H8*(INDEX(Assumptions!$C$3:$F$3,MATCH(YEAR(H$3),Assumptions!$C$1:$F$1,0))-INDEX(Assumptions!$C$17:$F$17,MATCH(YEAR(H$3),Assumptions!$C$1:$F$1,0)))} -> 26000 | I9: {=I8*(INDEX(Assumptions!$C$3:$F$3,MATCH(YEAR(I$3),Assumptions!$C$1:$F$1,0))-INDEX(Assumptions!$C$17:$F$17,MATCH(YEAR(I$3),Assumptions!$C$1:$F$1,0)))} -> 32500 | J9: {=J8*(INDEX(Assumptions!$C$3:$F$3,MATCH(YEAR(J$3),Assumptions!$C$1:$F$1,0))-INDEX(Assumptions!$C$17:$F$17,MATCH(YEAR(J$3),Assumptions!$C$1:$F$1,0)))} -> 26000 | K9: {=K8*(INDEX(Assumptions!$C$3:$F$3,MATCH(YEAR(K$3),Assumptions!$C$1:$F$1,0))-INDEX(Assumptions!$C$17:$F$17,MATCH(YEAR(K$3),Assumptions!$C$1:$F$1,0)))} -> 26000 | L9: {=L8*(INDEX(Assumptions!$C$3:$F$3,MATCH(YEAR(L$3),Assumptions!$C$1:$F$1,0))-INDEX(Assumptions!$C$17:$F$17,MATCH(YEAR(L$3),Assumptions!$C$1:$F$1,0)))} -> 26000 | M9: {=M8*(INDEX(Assumptions!$C$3:$F$3,MATCH(YEAR(M$3),Assumptions!$C$1:$F$1,0))-INDEX(Assumptions!$C$17:$F$17,MATCH(YEAR(M$3),Assumptions!$C$1:$F$1,0)))} -> 26000 | ... BA9: {=BA8*(INDEX(Assumptions!$C$3:$F$3,MATCH(YEAR(BA$3),Assumptions!$C$1:$F$1,0))-INDEX(Assumptions!$C$17:$F$17,MATCH(YEAR(BA$3),Assumptions!$C$1:$F$1,0)))} -> 48000 | BC9: =SUMPRODUCT((YEAR($F$3:$BA$3)=BC$3)*$F9:$BA9) -> 344500 | BD9: =SUMPRODUCT((YEAR($F$3:$BA$3)=BD$3)*$F9:$BA9) -> 420000 | BE9: =SUMPRODUCT((YEAR($F$3:$BA$3)=BE$3)*$F9:$BA9) -> 585000 | BF9: =SUMPRODUCT((YEAR($F$3:$BA$3)=BF$3)*$F9:$BA9) -> 600000
B10: Deals closed | E10: # | F10: 0 | G10: =G44 -> 1 | H10: 0 | I10: 0 | J10: 0 | K10: {=F7*INDEX(Assumptions!$C$7:$F$7,MATCH(YEAR(K$3),Assumptions!$C$1:$F$1,0))} -> 0.2 | L10: {=G7*INDEX(Assumptions!$C$7:$F$7,MATCH(YEAR(L$3),Assumptions!$C$1:$F$1,0))} -> 0.2 | M10: {=H7*INDEX(Assumptions!$C$7:$F$7,MATCH(YEAR(M$3),Assumptions!$C$1:$F$1,0))} -> 0.2 | N10: {=I7*INDEX(Assumptions!$C$7:$F$7,MATCH(YEAR(N$3),Assumptions!$C$1:$F$1,0))} -> 0.2 | O10: {=J7*INDEX(Assumptions!$C$7:$F$7,MATCH(YEAR(O$3),Assumptions!$C$1:$F$1,0))} -> 0 | P10: {=K7*INDEX(Assumptions!$C$7:$F$7,MATCH(YEAR(P$3),Assumptions!$C$1:$F$1,0))} -> 0.2 | Q10: {=L7*INDEX(Assumptions!$C$7:$F$7,MATCH(YEAR(Q$3),Assumptions!$C$1:$F$1,0))} -> 0.2 | R10: {=M7*INDEX(Assumptions!$C$7:$F$7,MATCH(YEAR(R$3),Assumptions!$C$1:$F$1,0))} -> 0.25 | ... BA10: {=AV7*INDEX(Assumptions!$C$7:$F$7,MATCH(YEAR(BA$3),Assumptions!$C$1:$F$1,0))} -> 0.32 | BC10: =SUMPRODUCT((YEAR($F$3:$BA$3)=BC$3)*$F10:$BA10) -> 2.2 | BD10: =SUMPRODUCT((YEAR($F$3:$BA$3)=BD$3)*$F10:$BA10) -> 3 | BE10: =SUMPRODUCT((YEAR($F$3:$BA$3)=BE$3)*$F10:$BA10) -> 3.92 | BF10: =SUMPRODUCT((YEAR($F$3:$BA$3)=BF$3)*$F10:$BA10) -> 5.12
B11: Success fees | E11: € | F11: {=F10*(INDEX(Assumptions!$C$6:$F$6,MATCH(YEAR(F$3),Assumptions!$C$1:$F$1,0))*Assumptions!$C$5)} -> 0 | G11: {=G10*(INDEX(Assumptions!$C$6:$F$6,MATCH(YEAR(G$3),Assumptions!$C$1:$F$1,0))*Assumptions!$C$5)} -> 100000 | H11: {=H10*(INDEX(Assumptions!$C$6:$F$6,MATCH(YEAR(H$3),Assumptions!$C$1:$F$1,0))*Assumptions!$C$5)} -> 0 | I11: {=I10*(INDEX(Assumptions!$C$6:$F$6,MATCH(YEAR(I$3),Assumptions!$C$1:$F$1,0))*Assumptions!$C$5)} -> 0 | J11: {=J10*(INDEX(Assumptions!$C$6:$F$6,MATCH(YEAR(J$3),Assumptions!$C$1:$F$1,0))*Assumptions!$C$5)} -> 0 | K11: {=K10*(INDEX(Assumptions!$C$6:$F$6,MATCH(YEAR(K$3),Assumptions!$C$1:$F$1,0))*Assumptions!$C$5)} -> 20000 | L11: {=L10*(INDEX(Assumptions!$C$6:$F$6,MATCH(YEAR(L$3),Assumptions!$C$1:$F$1,0))*Assumptions!$C$5)} -> 20000 | M11: {=M10*(INDEX(Assumptions!$C$6:$F$6,MATCH(YEAR(M$3),Assumptions!$C$1:$F$1,0))*Assumptions!$C$5)} -> 20000 | ... BA11: {=BA10*(INDEX(Assumptions!$C$6:$F$6,MATCH(YEAR(BA$3),Assumptions!$C$1:$F$1,0))*Assumptions!$C$5)} -> 96000 | BC11: =SUMPRODUCT((YEAR($F$3:$BA$3)=BC$3)*$F11:$BA11) -> 220000 | BD11: =SUMPRODUCT((YEAR($F$3:$BA$3)=BD$3)*$F11:$BA11) -> 420000 | BE11: =SUMPRODUCT((YEAR($F$3:$BA$3)=BE$3)*$F11:$BA11) -> 784000 | BF11: =SUMPRODUCT((YEAR($F$3:$BA$3)=BF$3)*$F11:$BA11) -> 1536000
B12: Total Growth revenue | E12: € | F12: =F9+F11 -> 26000 | G12: =G9+G11 -> 132500 | H12: =H9+H11 -> 26000 | I12: =I9+I11 -> 32500 | J12: =J9+J11 -> 26000 | K12: =K9+K11 -> 46000 | L12: =L9+L11 -> 46000 | M12: =M9+M11 -> 46000 | ... BA12: =BA9+BA11 -> 144000 | BC12: =SUMPRODUCT((YEAR($F$3:$BA$3)=BC$3)*$F12:$BA12) -> 564500 | BD12: =SUMPRODUCT((YEAR($F$3:$BA$3)=BD$3)*$F12:$BA12) -> 840000 | BE12: =SUMPRODUCT((YEAR($F$3:$BA$3)=BE$3)*$F12:$BA12) -> 1369000 | BF12: =SUMPRODUCT((YEAR($F$3:$BA$3)=BF$3)*$F12:$BA12) -> 2136000
B14: M&A
B15: New deals started | E15: # | F15: {=ROUND(INDEX(Assumptions!$C$27:$F$27,MATCH(YEAR(F$3),Assumptions!$C$1:$F$1,0))*MONTH(F$3)/12,0)-ROUND(INDEX(Assumptions!$C$27:$F$27,MATCH(YEAR(F$3),Assumptions!$C$1:$F$1,0))*(MONTH(F$3)-1)/12,0)-F7} -> 0 | G15: {=ROUND(INDEX(Assumptions!$C$27:$F$27,MATCH(YEAR(G$3),Assumptions!$C$1:$F$1,0))*MONTH(G$3)/12,0)-ROUND(INDEX(Assumptions!$C$27:$F$27,MATCH(YEAR(G$3),Assumptions!$C$1:$F$1,0))*(MONTH(G$3)-1)/12,0)-G7} -> 1 | H15: {=ROUND(INDEX(Assumptions!$C$27:$F$27,MATCH(YEAR(H$3),Assumptions!$C$1:$F$1,0))*MONTH(H$3)/12,0)-ROUND(INDEX(Assumptions!$C$27:$F$27,MATCH(YEAR(H$3),Assumptions!$C$1:$F$1,0))*(MONTH(H$3)-1)/12,0)-H7} -> 0 | I15: {=ROUND(INDEX(Assumptions!$C$27:$F$27,MATCH(YEAR(I$3),Assumptions!$C$1:$F$1,0))*MONTH(I$3)/12,0)-ROUND(INDEX(Assumptions!$C$27:$F$27,MATCH(YEAR(I$3),Assumptions!$C$1:$F$1,0))*(MONTH(I$3)-1)/12,0)-I7} -> 0 | J15: {=ROUND(INDEX(Assumptions!$C$27:$F$27,MATCH(YEAR(J$3),Assumptions!$C$1:$F$1,0))*MONTH(J$3)/12,0)-ROUND(INDEX(Assumptions!$C$27:$F$27,MATCH(YEAR(J$3),Assumptions!$C$1:$F$1,0))*(MONTH(J$3)-1)/12,0)-J7} -> 1 | K15: {=ROUND(INDEX(Assumptions!$C$27:$F$27,MATCH(YEAR(K$3),Assumptions!$C$1:$F$1,0))*MONTH(K$3)/12,0)-ROUND(INDEX(Assumptions!$C$27:$F$27,MATCH(YEAR(K$3),Assumptions!$C$1:$F$1,0))*(MONTH(K$3)-1)/12,0)-K7} -> 1 | L15: {=ROUND(INDEX(Assumptions!$C$27:$F$27,MATCH(YEAR(L$3),Assumptions!$C$1:$F$1,0))*MONTH(L$3)/12,0)-ROUND(INDEX(Assumptions!$C$27:$F$27,MATCH(YEAR(L$3),Assumptions!$C$1:$F$1,0))*(MONTH(L$3)-1)/12,0)-L7} -> 0 | M15: {=ROUND(INDEX(Assumptions!$C$27:$F$27,MATCH(YEAR(M$3),Assumptions!$C$1:$F$1,0))*MONTH(M$3)/12,0)-ROUND(INDEX(Assumptions!$C$27:$F$27,MATCH(YEAR(M$3),Assumptions!$C$1:$F$1,0))*(MONTH(M$3)-1)/12,0)-M7} -> 0 | ... BA15: {=ROUND(INDEX(Assumptions!$C$27:$F$27,MATCH(YEAR(BA$3),Assumptions!$C$1:$F$1,0))*MONTH(BA$3)/12,0)-ROUND(INDEX(Assumptions!$C$27:$F$27,MATCH(YEAR(BA$3),Assumptions!$C$1:$F$1,0))*(MONTH(BA$3)-1)/12,0)-BA7} -> 1 | BC15: =SUMPRODUCT((YEAR($F$3:$BA$3)=BC$3)*$F15:$BA15) -> 4 | BD15: =SUMPRODUCT((YEAR($F$3:$BA$3)=BD$3)*$F15:$BA15) -> 8 | BE15: =SUMPRODUCT((YEAR($F$3:$BA$3)=BE$3)*$F15:$BA15) -> 9 | BF15: =SUMPRODUCT((YEAR($F$3:$BA$3)=BF$3)*$F15:$BA15) -> 15
B16: Live projects | E16: # | F16: =SUM(F15) -> 0 | G16: =SUM(F15:G15) -> 1 | H16: =SUM(F15:H15) -> 1 | I16: =SUM(F15:I15) -> 1 | J16: =SUM(F15:J15) -> 2 | K16: =SUM(F15:K15) -> 3 | L16: =SUM(F15:L15) -> 3 | M16: =SUM(G15:M15) -> 3 | N16: =SUM(H15:N15) -> 2 | O16: =SUM(I15:O15) -> 3 | P16: =SUM(J15:P15) -> 3 | Q16: =SUM(K15:Q15) -> 2 | R16: =SUM(L15:R15) -> 2 | S16: =SUM(M15:S15) -> 2 | ... BA16: =SUM(AU15:BA15) -> 8
B17: Retainer revenue | E17: € | F17: {=F16*(INDEX(Assumptions!$C$10:$F$10,MATCH(YEAR(F$3),Assumptions!$C$1:$F$1,0))-INDEX(Assumptions!$C$17:$F$17,MATCH(YEAR(F$3),Assumptions!$C$1:$F$1,0)))} -> 0 | G17: {=G16*(INDEX(Assumptions!$C$10:$F$10,MATCH(YEAR(G$3),Assumptions!$C$1:$F$1,0))-INDEX(Assumptions!$C$17:$F$17,MATCH(YEAR(G$3),Assumptions!$C$1:$F$1,0)))} -> 7500 | H17: {=H16*(INDEX(Assumptions!$C$10:$F$10,MATCH(YEAR(H$3),Assumptions!$C$1:$F$1,0))-INDEX(Assumptions!$C$17:$F$17,MATCH(YEAR(H$3),Assumptions!$C$1:$F$1,0)))} -> 7500 | I17: {=I16*(INDEX(Assumptions!$C$10:$F$10,MATCH(YEAR(I$3),Assumptions!$C$1:$F$1,0))-INDEX(Assumptions!$C$17:$F$17,MATCH(YEAR(I$3),Assumptions!$C$1:$F$1,0)))} -> 7500 | J17: {=J16*(INDEX(Assumptions!$C$10:$F$10,MATCH(YEAR(J$3),Assumptions!$C$1:$F$1,0))-INDEX(Assumptions!$C$17:$F$17,MATCH(YEAR(J$3),Assumptions!$C$1:$F$1,0)))} -> 15000 | K17: {=K16*(INDEX(Assumptions!$C$10:$F$10,MATCH(YEAR(K$3),Assumptions!$C$1:$F$1,0))-INDEX(Assumptions!$C$17:$F$17,MATCH(YEAR(K$3),Assumptions!$C$1:$F$1,0)))} -> 22500 | L17: {=L16*(INDEX(Assumptions!$C$10:$F$10,MATCH(YEAR(L$3),Assumptions!$C$1:$F$1,0))-INDEX(Assumptions!$C$17:$F$17,MATCH(YEAR(L$3),Assumptions!$C$1:$F$1,0)))} -> 22500 | M17: {=M16*(INDEX(Assumptions!$C$10:$F$10,MATCH(YEAR(M$3),Assumptions!$C$1:$F$1,0))-INDEX(Assumptions!$C$17:$F$17,MATCH(YEAR(M$3),Assumptions!$C$1:$F$1,0)))} -> 22500 | ... BA17: {=BA16*(INDEX(Assumptions!$C$10:$F$10,MATCH(YEAR(BA$3),Assumptions!$C$1:$F$1,0))-INDEX(Assumptions!$C$17:$F$17,MATCH(YEAR(BA$3),Assumptions!$C$1:$F$1,0)))} -> 68000 | BC17: =SUMPRODUCT((YEAR($F$3:$BA$3)=BC$3)*$F17:$BA17) -> 180000 | BD17: =SUMPRODUCT((YEAR($F$3:$BA$3)=BD$3)*$F17:$BA17) -> 368000 | BE17: =SUMPRODUCT((YEAR($F$3:$BA$3)=BE$3)*$F17:$BA17) -> 496000 | BF17: =SUMPRODUCT((YEAR($F$3:$BA$3)=BF$3)*$F17:$BA17) -> 799000
B18: Deals closed | E18: # | F18: 0 | G18: 0 | H18: 0 | I18: 0 | J18: 0 | K18: 0 | L18: 0 | M18: {=F15*INDEX(Assumptions!$C$14:$F$14,MATCH(YEAR(M$3),Assumptions!$C$1:$F$1,0))} -> 0 | N18: {=G15*INDEX(Assumptions!$C$14:$F$14,MATCH(YEAR(N$3),Assumptions!$C$1:$F$1,0))} -> 0.5 | O18: {=H15*INDEX(Assumptions!$C$14:$F$14,MATCH(YEAR(O$3),Assumptions!$C$1:$F$1,0))} -> 0 | P18: {=I15*INDEX(Assumptions!$C$14:$F$14,MATCH(YEAR(P$3),Assumptions!$C$1:$F$1,0))} -> 0 | Q18: {=J15*INDEX(Assumptions!$C$14:$F$14,MATCH(YEAR(Q$3),Assumptions!$C$1:$F$1,0))} -> 0.5 | R18: {=K15*INDEX(Assumptions!$C$14:$F$14,MATCH(YEAR(R$3),Assumptions!$C$1:$F$1,0))} -> 0.56 | S18: {=L15*INDEX(Assumptions!$C$14:$F$14,MATCH(YEAR(S$3),Assumptions!$C$1:$F$1,0))} -> 0 | T18: {=M15*INDEX(Assumptions!$C$14:$F$14,MATCH(YEAR(T$3),Assumptions!$C$1:$F$1,0))} -> 0 | ... BA18: {=AT15*INDEX(Assumptions!$C$14:$F$14,MATCH(YEAR(BA$3),Assumptions!$C$1:$F$1,0))} -> 1.4 | BC18: =SUMPRODUCT((YEAR($F$3:$BA$3)=BC$3)*$F18:$BA18) -> 1 | BD18: =SUMPRODUCT((YEAR($F$3:$BA$3)=BD$3)*$F18:$BA18) -> 2.8 | BE18: =SUMPRODUCT((YEAR($F$3:$BA$3)=BE$3)*$F18:$BA18) -> 5.04 | BF18: =SUMPRODUCT((YEAR($F$3:$BA$3)=BF$3)*$F18:$BA18) -> 9.1
B19: Success fees | E19: € | F19: {=F18*(INDEX(Assumptions!$C$13:$F$13,MATCH(YEAR(F$3),Assumptions!$C$1:$F$1,0))*Assumptions!$C$12)} -> 0 | G19: {=G18*(INDEX(Assumptions!$C$13:$F$13,MATCH(YEAR(G$3),Assumptions!$C$1:$F$1,0))*Assumptions!$C$12)} -> 0 | H19: {=H18*(INDEX(Assumptions!$C$13:$F$13,MATCH(YEAR(H$3),Assumptions!$C$1:$F$1,0))*Assumptions!$C$12)} -> 0 | I19: {=I18*(INDEX(Assumptions!$C$13:$F$13,MATCH(YEAR(I$3),Assumptions!$C$1:$F$1,0))*Assumptions!$C$12)} -> 0 | J19: {=J18*(INDEX(Assumptions!$C$13:$F$13,MATCH(YEAR(J$3),Assumptions!$C$1:$F$1,0))*Assumptions!$C$12)} -> 0 | K19: {=K18*(INDEX(Assumptions!$C$13:$F$13,MATCH(YEAR(K$3),Assumptions!$C$1:$F$1,0))*Assumptions!$C$12)} -> 0 | L19: {=L18*(INDEX(Assumptions!$C$13:$F$13,MATCH(YEAR(L$3),Assumptions!$C$1:$F$1,0))*Assumptions!$C$12)} -> 0 | M19: {=M18*(INDEX(Assumptions!$C$13:$F$13,MATCH(YEAR(M$3),Assumptions!$C$1:$F$1,0))*Assumptions!$C$12)} -> 0 | ... BA19: {=BA18*(INDEX(Assumptions!$C$13:$F$13,MATCH(YEAR(BA$3),Assumptions!$C$1:$F$1,0))*Assumptions!$C$12)} -> 840000 | BC19: =SUMPRODUCT((YEAR($F$3:$BA$3)=BC$3)*$F19:$BA19) -> 240000 | BD19: =SUMPRODUCT((YEAR($F$3:$BA$3)=BD$3)*$F19:$BA19) -> 1008000 | BE19: =SUMPRODUCT((YEAR($F$3:$BA$3)=BE$3)*$F19:$BA19) -> 2419200 | BF19: =SUMPRODUCT((YEAR($F$3:$BA$3)=BF$3)*$F19:$BA19) -> 5460000
B20: Total M&A revenue | E20: € | F20: =F17+F19 -> 0 | G20: =G17+G19 -> 7500 | H20: =H17+H19 -> 7500 | I20: =I17+I19 -> 7500 | J20: =J17+J19 -> 15000 | K20: =K17+K19 -> 22500 | L20: =L17+L19 -> 22500 | M20: =M17+M19 -> 22500 | ... BA20: =BA17+BA19 -> 908000 | BC20: =SUMPRODUCT((YEAR($F$3:$BA$3)=BC$3)*$F20:$BA20) -> 420000 | BD20: =SUMPRODUCT((YEAR($F$3:$BA$3)=BD$3)*$F20:$BA20) -> 1376000 | BE20: =SUMPRODUCT((YEAR($F$3:$BA$3)=BE$3)*$F20:$BA20) -> 2915200 | BF20: =SUMPRODUCT((YEAR($F$3:$BA$3)=BF$3)*$F20:$BA20) -> 6259000
B22: SOFTWARE
B23: Payers — in engagement | E23: # | F23: =F8+F16 -> 4 | G23: =G8+G16 -> 6 | H23: =H8+H16 -> 5 | I23: =I8+I16 -> 6 | J23: =J8+J16 -> 6 | K23: =K8+K16 -> 7 | L23: =L8+L16 -> 7 | M23: =M8+M16 -> 7 | ... BA23: =BA8+BA16 -> 14
B24: Graduates (engagements ending) | E24: # | F24: =0 -> 0 | G24: =MAX(0,F43-G43) -> 0 | H24: =MAX(0,G43-H43) -> 2 | I24: =MAX(0,H43-I43) -> 0 | J24: =MAX(0,I43-J43) -> 1 | K24: =F7+MAX(0,J43-K43) -> 1 | L24: =G7+MAX(0,K43-L43) -> 1 | M24: =H7+F15+MAX(0,L43-M43) -> 1 | N24: =I7+G15+MAX(0,M43-N43) -> 2 | O24: =J7+H15+MAX(0,N43-O43) -> 0 | P24: =K7+I15+MAX(0,O43-P43) -> 1 | Q24: =L7+J15+MAX(0,P43-Q43) -> 2 | R24: =M7+K15+MAX(0,Q43-R43) -> 2 | S24: =N7+L15+MAX(0,R43-S43) -> 1 | T24: =O7+M15+MAX(0,S43-T43) -> 1 | ... BA24: =AV7+AT15+MAX(0,AZ43-BA43) -> 3 | BC24: =SUMPRODUCT((YEAR($F$3:$BA$3)=BC$3)*$F24:$BA24) -> 11 | BD24: =SUMPRODUCT((YEAR($F$3:$BA$3)=BD$3)*$F24:$BA24) -> 17 | BE24: =SUMPRODUCT((YEAR($F$3:$BA$3)=BE$3)*$F24:$BA24) -> 22 | BF24: =SUMPRODUCT((YEAR($F$3:$BA$3)=BF$3)*$F24:$BA24) -> 29
B25: Subscribers — post-engagement | E25: # | F25: =F24 -> 0 | G25: =F25*(1-Assumptions!$C$19)+G24 -> 0 | H25: =G25*(1-Assumptions!$C$19)+H24 -> 2 | I25: =H25*(1-Assumptions!$C$19)+I24 -> 1.9631531 | J25: =I25*(1-Assumptions!$C$19)+J24 -> 2.926985 | K25: =J25*(1-Assumptions!$C$19)+K24 -> 3.8730597 | L25: =K25*(1-Assumptions!$C$19)+L24 -> 4.8017045 | M25: =L25*(1-Assumptions!$C$19)+M24 -> 5.7132405 | N25: =M25*(1-Assumptions!$C$19)+N24 -> 7.6079828 | ... BA25: =AZ25*(1-Assumptions!$C$19)+BA24 -> 57.303068
B26: New direct customers | E26: # | F26: {=Personnel!F13*INDEX(Assumptions!$C$20:$F$20,MATCH(YEAR(F$3),Assumptions!$C$1:$F$1,0))} -> 0 | G26: {=Personnel!G13*INDEX(Assumptions!$C$20:$F$20,MATCH(YEAR(G$3),Assumptions!$C$1:$F$1,0))} -> 0 | H26: {=Personnel!H13*INDEX(Assumptions!$C$20:$F$20,MATCH(YEAR(H$3),Assumptions!$C$1:$F$1,0))} -> 0 | I26: {=Personnel!I13*INDEX(Assumptions!$C$20:$F$20,MATCH(YEAR(I$3),Assumptions!$C$1:$F$1,0))} -> 0 | J26: {=Personnel!J13*INDEX(Assumptions!$C$20:$F$20,MATCH(YEAR(J$3),Assumptions!$C$1:$F$1,0))} -> 0 | K26: {=Personnel!K13*INDEX(Assumptions!$C$20:$F$20,MATCH(YEAR(K$3),Assumptions!$C$1:$F$1,0))} -> 0 | L26: {=Personnel!L13*INDEX(Assumptions!$C$20:$F$20,MATCH(YEAR(L$3),Assumptions!$C$1:$F$1,0))} -> 0 | M26: {=Personnel!M13*INDEX(Assumptions!$C$20:$F$20,MATCH(YEAR(M$3),Assumptions!$C$1:$F$1,0))} -> 0 | ... BA26: {=Personnel!BA13*INDEX(Assumptions!$C$20:$F$20,MATCH(YEAR(BA$3),Assumptions!$C$1:$F$1,0))} -> 4 | BC26: =SUMPRODUCT((YEAR($F$3:$BA$3)=BC$3)*$F26:$BA26) -> 0 | BD26: =SUMPRODUCT((YEAR($F$3:$BA$3)=BD$3)*$F26:$BA26) -> 0 | BE26: =SUMPRODUCT((YEAR($F$3:$BA$3)=BE$3)*$F26:$BA26) -> 36 | BF26: =SUMPRODUCT((YEAR($F$3:$BA$3)=BF$3)*$F26:$BA26) -> 48
B27: Direct subscribers | E27: # | F27: =F26 -> 0 | G27: =F27*(1-Assumptions!$C$22)+G26 -> 0 | H27: =G27*(1-Assumptions!$C$22)+H26 -> 0 | I27: =H27*(1-Assumptions!$C$22)+I26 -> 0 | J27: =I27*(1-Assumptions!$C$22)+J26 -> 0 | K27: =J27*(1-Assumptions!$C$22)+K26 -> 0 | L27: =K27*(1-Assumptions!$C$22)+L26 -> 0 | M27: =L27*(1-Assumptions!$C$22)+M26 -> 0 | N27: =M27*(1-Assumptions!$C$22)+N26 -> 0 | ... BA27: =AZ27*(1-Assumptions!$C$22)+BA26 -> 62.488197
B28: Total software payers | E28: # | F28: =F23+F25+F27 -> 4 | G28: =G23+G25+G27 -> 6 | H28: =H23+H25+H27 -> 7 | I28: =I23+I25+I27 -> 7.9631531 | J28: =J23+J25+J27 -> 8.926985 | K28: =K23+K25+K27 -> 10.87306 | L28: =L23+L25+L27 -> 11.801705 | M28: =M23+M25+M27 -> 12.71324 | ... BA28: =BA23+BA25+BA27 -> 133.79126
B29: Software revenue | E29: € | F29: {=F28*INDEX(Assumptions!$C$17:$F$17,MATCH(YEAR(F$3),Assumptions!$C$1:$F$1,0))} -> 2000 | G29: {=G28*INDEX(Assumptions!$C$17:$F$17,MATCH(YEAR(G$3),Assumptions!$C$1:$F$1,0))} -> 3000 | H29: {=H28*INDEX(Assumptions!$C$17:$F$17,MATCH(YEAR(H$3),Assumptions!$C$1:$F$1,0))} -> 3500 | I29: {=I28*INDEX(Assumptions!$C$17:$F$17,MATCH(YEAR(I$3),Assumptions!$C$1:$F$1,0))} -> 3981.5765 | J29: {=J28*INDEX(Assumptions!$C$17:$F$17,MATCH(YEAR(J$3),Assumptions!$C$1:$F$1,0))} -> 4463.4925 | K29: {=K28*INDEX(Assumptions!$C$17:$F$17,MATCH(YEAR(K$3),Assumptions!$C$1:$F$1,0))} -> 5436.5299 | L29: {=L28*INDEX(Assumptions!$C$17:$F$17,MATCH(YEAR(L$3),Assumptions!$C$1:$F$1,0))} -> 5900.8523 | M29: {=M28*INDEX(Assumptions!$C$17:$F$17,MATCH(YEAR(M$3),Assumptions!$C$1:$F$1,0))} -> 6356.6202 | ... BA29: {=BA28*INDEX(Assumptions!$C$17:$F$17,MATCH(YEAR(BA$3),Assumptions!$C$1:$F$1,0))} -> 66895.632 | BC29: =SUMPRODUCT((YEAR($F$3:$BA$3)=BC$3)*$F29:$BA29) -> 65930.47 | BD29: =SUMPRODUCT((YEAR($F$3:$BA$3)=BD$3)*$F29:$BA29) -> 157755.32 | BE29: =SUMPRODUCT((YEAR($F$3:$BA$3)=BE$3)*$F29:$BA29) -> 367793.02 | BF29: =SUMPRODUCT((YEAR($F$3:$BA$3)=BF$3)*$F29:$BA29) -> 670533.27
B31: TOTAL REVENUE
B32: Total live projects (monthly only) | E32: # | F32: =F8+F16 -> 4 | G32: =G8+G16 -> 6 | H32: =H8+H16 -> 5 | I32: =I8+I16 -> 6 | J32: =J8+J16 -> 6 | K32: =K8+K16 -> 7 | L32: =L8+L16 -> 7 | M32: =M8+M16 -> 7 | ... BA32: =BA8+BA16 -> 14
B33: Total new deals started (annual only) | E33: # | BC33: =BC7+BC15 -> 15 | BD33: =BD7+BD15 -> 20 | BE33: =BE7+BE15 -> 25 | BF33: =BF7+BF15 -> 30
B34: Total retainer | E34: € | F34: =F9+F17 -> 26000 | G34: =G9+G17 -> 40000 | H34: =H9+H17 -> 33500 | I34: =I9+I17 -> 40000 | J34: =J9+J17 -> 41000 | K34: =K9+K17 -> 48500 | L34: =L9+L17 -> 48500 | M34: =M9+M17 -> 48500 | ... BA34: =BA9+BA17 -> 116000 | BC34: =SUMPRODUCT((YEAR($F$3:$BA$3)=BC$3)*$F34:$BA34) -> 524500 | BD34: =SUMPRODUCT((YEAR($F$3:$BA$3)=BD$3)*$F34:$BA34) -> 788000 | BE34: =SUMPRODUCT((YEAR($F$3:$BA$3)=BE$3)*$F34:$BA34) -> 1081000 | BF34: =SUMPRODUCT((YEAR($F$3:$BA$3)=BF$3)*$F34:$BA34) -> 1399000
B35: Total success fees | E35: € | F35: =F11+F19 -> 0 | G35: =G11+G19 -> 100000 | H35: =H11+H19 -> 0 | I35: =I11+I19 -> 0 | J35: =J11+J19 -> 0 | K35: =K11+K19 -> 20000 | L35: =L11+L19 -> 20000 | M35: =M11+M19 -> 20000 | ... BA35: =BA11+BA19 -> 936000 | BC35: =SUMPRODUCT((YEAR($F$3:$BA$3)=BC$3)*$F35:$BA35) -> 460000 | BD35: =SUMPRODUCT((YEAR($F$3:$BA$3)=BD$3)*$F35:$BA35) -> 1428000 | BE35: =SUMPRODUCT((YEAR($F$3:$BA$3)=BE$3)*$F35:$BA35) -> 3203200 | BF35: =SUMPRODUCT((YEAR($F$3:$BA$3)=BF$3)*$F35:$BA35) -> 6996000
B36: Total software revenue | E36: € | F36: =F29 -> 2000 | G36: =G29 -> 3000 | H36: =H29 -> 3500 | I36: =I29 -> 3981.5765 | J36: =J29 -> 4463.4925 | K36: =K29 -> 5436.5299 | L36: =L29 -> 5900.8523 | M36: =M29 -> 6356.6202 | ... BA36: =BA29 -> 66895.632 | BC36: =SUMPRODUCT((YEAR($F$3:$BA$3)=BC$3)*$F36:$BA36) -> 65930.47 | BD36: =SUMPRODUCT((YEAR($F$3:$BA$3)=BD$3)*$F36:$BA36) -> 157755.32 | BE36: =SUMPRODUCT((YEAR($F$3:$BA$3)=BE$3)*$F36:$BA36) -> 367793.02 | BF36: =SUMPRODUCT((YEAR($F$3:$BA$3)=BF$3)*$F36:$BA36) -> 670533.27
B37: Total revenue (gross) | E37: € | F37: =F34+F35+F36 -> 28000 | G37: =G34+G35+G36 -> 143000 | H37: =H34+H35+H36 -> 37000 | I37: =I34+I35+I36 -> 43981.577 | J37: =J34+J35+J36 -> 45463.492 | K37: =K34+K35+K36 -> 73936.53 | L37: =L34+L35+L36 -> 74400.852 | M37: =M34+M35+M36 -> 74856.62 | ... BA37: =BA34+BA35+BA36 -> 1118895.6 | BC37: =SUMPRODUCT((YEAR($F$3:$BA$3)=BC$3)*$F37:$BA37) -> 1050430.5 | BD37: =SUMPRODUCT((YEAR($F$3:$BA$3)=BD$3)*$F37:$BA37) -> 2373755.3 | BE37: =SUMPRODUCT((YEAR($F$3:$BA$3)=BE$3)*$F37:$BA37) -> 4651993 | BF37: =SUMPRODUCT((YEAR($F$3:$BA$3)=BF$3)*$F37:$BA37) -> 9065533.3
B38: Less: industry-partner share | E38: € | F38: =-Assumptions!$C$31*Assumptions!$C$33*(F34+F35) -> -1950 | G38: =-Assumptions!$C$31*Assumptions!$C$33*(G34+G35) -> -10500 | H38: =-Assumptions!$C$31*Assumptions!$C$33*(H34+H35) -> -2512.5 | I38: =-Assumptions!$C$31*Assumptions!$C$33*(I34+I35) -> -3000 | J38: =-Assumptions!$C$31*Assumptions!$C$33*(J34+J35) -> -3075 | K38: =-Assumptions!$C$31*Assumptions!$C$33*(K34+K35) -> -5137.5 | L38: =-Assumptions!$C$31*Assumptions!$C$33*(L34+L35) -> -5137.5 | M38: =-Assumptions!$C$31*Assumptions!$C$33*(M34+M35) -> -5137.5 | ... BA38: =-Assumptions!$C$31*Assumptions!$C$33*(BA34+BA35) -> -78900 | BC38: =SUMPRODUCT((YEAR($F$3:$BA$3)=BC$3)*$F38:$BA38) -> -73837.5 | BD38: =SUMPRODUCT((YEAR($F$3:$BA$3)=BD$3)*$F38:$BA38) -> -166200 | BE38: =SUMPRODUCT((YEAR($F$3:$BA$3)=BE$3)*$F38:$BA38) -> -321315 | BF38: =SUMPRODUCT((YEAR($F$3:$BA$3)=BF$3)*$F38:$BA38) -> -629625
B39: Net revenue | E39: € | F39: =F37+F38 -> 26050 | G39: =G37+G38 -> 132500 | H39: =H37+H38 -> 34487.5 | I39: =I37+I38 -> 40981.577 | J39: =J37+J38 -> 42388.492 | K39: =K37+K38 -> 68799.03 | L39: =L37+L38 -> 69263.352 | M39: =M37+M38 -> 69719.12 | ... BA39: =BA37+BA38 -> 1039995.6 | BC39: =SUMPRODUCT((YEAR($F$3:$BA$3)=BC$3)*$F39:$BA39) -> 976592.97 | BD39: =SUMPRODUCT((YEAR($F$3:$BA$3)=BD$3)*$F39:$BA39) -> 2207555.3 | BE39: =SUMPRODUCT((YEAR($F$3:$BA$3)=BE$3)*$F39:$BA39) -> 4330678 | BF39: =SUMPRODUCT((YEAR($F$3:$BA$3)=BF$3)*$F39:$BA39) -> 8435908.3
B42: 2027 STARTING PROJECTS — Growth Capital opening pipeline
B43: Live projects (count) | E43: # | F43: 3 | G43: 3 | H43: 1 | I43: 1
B44: Deals closed | E44: # | G44: 1
B45: Success fee on close (memo) | E45: € | G45: {=INDEX(Assumptions!$C$6:$F$6,MATCH(2027,Assumptions!$C$1:$F$1,0))*Assumptions!$C$5} -> 100000
B46: Note: 1 of 3 deals is industry-partner-sourced — IP cut flows through the "Less: industry-partner share" line.

Sheet Personnel
B2: Personnel — Monthly 2027–2030 (€)
E3: Unit | F3: 46388 | G3: 46419 | H3: 46447 | I3: 46478 | J3: 46508 | K3: 46539 | L3: 46569 | M3: 46600 | N3: 46631 | O3: 46661 | P3: 46692 | Q3: 46722 | R3: 46753 | S3: 46784 | T3: 46813 | U3: 46844 | V3: 46874 | W3: 46905 | X3: 46935 | Y3: 46966 | Z3: 46997 | AA3: 47027 | AB3: 47058 | AC3: 47088 | AD3: 47119 | AE3: 47150 | AF3: 47178 | AG3: 47209 | AH3: 47239 | AI3: 47270 | AJ3: 47300 | AK3: 47331 | AL3: 47362 | AM3: 47392 | AN3: 47423 | AO3: 47453 | AP3: 47484 | AQ3: 47515 | AR3: 47543 | AS3: 47574 | AT3: 47604 | AU3: 47635 | AV3: 47665 | AW3: 47696 | AX3: 47727 | AY3: 47757 | AZ3: 47788 | BA3: 47818 | BC3: 2027 | BD3: 2028 | BE3: 2029 | BF3: 2030
B6: HEADCOUNT
B7: Live projects (total) | E7: # | F7: ='Revenue forecast'!F8+'Revenue forecast'!F16 -> 4 | G7: ='Revenue forecast'!G8+'Revenue forecast'!G16 -> 6 | H7: ='Revenue forecast'!H8+'Revenue forecast'!H16 -> 5 | I7: ='Revenue forecast'!I8+'Revenue forecast'!I16 -> 6 | J7: ='Revenue forecast'!J8+'Revenue forecast'!J16 -> 6 | K7: ='Revenue forecast'!K8+'Revenue forecast'!K16 -> 7 | L7: ='Revenue forecast'!L8+'Revenue forecast'!L16 -> 7 | M7: ='Revenue forecast'!M8+'Revenue forecast'!M16 -> 7 | ... BA7: ='Revenue forecast'!BA8+'Revenue forecast'!BA16 -> 14 | BC7: =Q7 -> 7 | BD7: =AC7 -> 10 | BE7: =AO7 -> 13 | BF7: =BA7 -> 14
B8: Analysts | E8: # | F8: {=MAX(1,CEILING(F7/INDEX(Assumptions!$C$48:$F$48,MATCH(YEAR(F$3),Assumptions!$C$1:$F$1,0)),1))} -> 2 | G8: {=MAX(F8,CEILING(G7/INDEX(Assumptions!$C$48:$F$48,MATCH(YEAR(G$3),Assumptions!$C$1:$F$1,0)),1))} -> 2 | H8: {=MAX(G8,CEILING(H7/INDEX(Assumptions!$C$48:$F$48,MATCH(YEAR(H$3),Assumptions!$C$1:$F$1,0)),1))} -> 2 | I8: {=MAX(H8,CEILING(I7/INDEX(Assumptions!$C$48:$F$48,MATCH(YEAR(I$3),Assumptions!$C$1:$F$1,0)),1))} -> 2 | J8: {=MAX(I8,CEILING(J7/INDEX(Assumptions!$C$48:$F$48,MATCH(YEAR(J$3),Assumptions!$C$1:$F$1,0)),1))} -> 2 | K8: {=MAX(J8,CEILING(K7/INDEX(Assumptions!$C$48:$F$48,MATCH(YEAR(K$3),Assumptions!$C$1:$F$1,0)),1))} -> 3 | L8: {=MAX(K8,CEILING(L7/INDEX(Assumptions!$C$48:$F$48,MATCH(YEAR(L$3),Assumptions!$C$1:$F$1,0)),1))} -> 3 | M8: {=MAX(L8,CEILING(M7/INDEX(Assumptions!$C$48:$F$48,MATCH(YEAR(M$3),Assumptions!$C$1:$F$1,0)),1))} -> 3 | N8: {=MAX(M8,CEILING(N7/INDEX(Assumptions!$C$48:$F$48,MATCH(YEAR(N$3),Assumptions!$C$1:$F$1,0)),1))} -> 3 | ... BA8: {=MAX(AZ8,CEILING(BA7/INDEX(Assumptions!$C$48:$F$48,MATCH(YEAR(BA$3),Assumptions!$C$1:$F$1,0)),1))} -> 6 | BC8: =Q8 -> 3 | BD8: =AC8 -> 4 | BE8: =AO8 -> 5 | BF8: =BA8 -> 6
B9: Associates | E9: # | F9: =IF(F7>=Assumptions!$C$52,2,IF(F7>=Assumptions!$C$51,1,0)) -> 0 | G9: =MAX(F9,IF(G7>=Assumptions!$C$52,2,IF(G7>=Assumptions!$C$51,1,0))) -> 0 | H9: =MAX(G9,IF(H7>=Assumptions!$C$52,2,IF(H7>=Assumptions!$C$51,1,0))) -> 0 | I9: =MAX(H9,IF(I7>=Assumptions!$C$52,2,IF(I7>=Assumptions!$C$51,1,0))) -> 0 | J9: =MAX(I9,IF(J7>=Assumptions!$C$52,2,IF(J7>=Assumptions!$C$51,1,0))) -> 0 | K9: =MAX(J9,IF(K7>=Assumptions!$C$52,2,IF(K7>=Assumptions!$C$51,1,0))) -> 0 | L9: =MAX(K9,IF(L7>=Assumptions!$C$52,2,IF(L7>=Assumptions!$C$51,1,0))) -> 0 | M9: =MAX(L9,IF(M7>=Assumptions!$C$52,2,IF(M7>=Assumptions!$C$51,1,0))) -> 0 | N9: =MAX(M9,IF(N7>=Assumptions!$C$52,2,IF(N7>=Assumptions!$C$51,1,0))) -> 0 | ... BA9: =MAX(AZ9,IF(BA7>=Assumptions!$C$52,2,IF(BA7>=Assumptions!$C$51,1,0))) -> 2 | BC9: =Q9 -> 0 | BD9: =AC9 -> 1 | BE9: =AO9 -> 1 | BF9: =BA9 -> 2
B10: Interns | E10: # | F10: =MAX(Assumptions!$C$53,ROUNDDOWN((F8+F9)/3,0)) -> 2 | G10: =MAX(Assumptions!$C$53,ROUNDDOWN((G8+G9)/3,0)) -> 2 | H10: =MAX(Assumptions!$C$53,ROUNDDOWN((H8+H9)/3,0)) -> 2 | I10: =MAX(Assumptions!$C$53,ROUNDDOWN((I8+I9)/3,0)) -> 2 | J10: =MAX(Assumptions!$C$53,ROUNDDOWN((J8+J9)/3,0)) -> 2 | K10: =MAX(Assumptions!$C$53,ROUNDDOWN((K8+K9)/3,0)) -> 2 | L10: =MAX(Assumptions!$C$53,ROUNDDOWN((L8+L9)/3,0)) -> 2 | M10: =MAX(Assumptions!$C$53,ROUNDDOWN((M8+M9)/3,0)) -> 2 | ... BA10: =MAX(Assumptions!$C$53,ROUNDDOWN((BA8+BA9)/3,0)) -> 2 | BC10: =Q10 -> 2 | BD10: =AC10 -> 2 | BE10: =AO10 -> 2 | BF10: =BA10 -> 2
B11: Sales hire | E11: # | F11: 1 | G11: 1 | H11: 1 | I11: 1 | J11: 1 | K11: 1 | L11: 1 | M11: 1 | N11: 1 | O11: 1 | P11: 1 | Q11: 1 | R11: 1 | S11: 1 | T11: 1 | U11: 1 | V11: 1 | W11: 1 | X11: 1 | Y11: 1 | Z11: 1 | AA11: 1 | AB11: 1 | AC11: 1 | AD11: 1 | AE11: 1 | AF11: 1 | AG11: 1 | AH11: 1 | AI11: 1 | AJ11: 1 | AK11: 1 | AL11: 1 | AM11: 1 | AN11: 1 | AO11: 1 | AP11: 1 | AQ11: 1 | AR11: 1 | AS11: 1 | AT11: 1 | AU11: 1 | AV11: 1 | AW11: 1 | AX11: 1 | AY11: 1 | AZ11: 1 | BA11: 1 | BC11: =Q11 -> 1 | BD11: =AC11 -> 1 | BE11: =AO11 -> 1 | BF11: =BA11 -> 1
B12: Marketing | E12: # | F12: 1 | G12: 1 | H12: 1 | I12: 1 | J12: 1 | K12: 1 | L12: 1 | M12: 1 | N12: 1 | O12: 1 | P12: 1 | Q12: 1 | R12: 1 | S12: 1 | T12: 1 | U12: 1 | V12: 1 | W12: 1 | X12: 1 | Y12: 1 | Z12: 1 | AA12: 1 | AB12: 1 | AC12: 1 | AD12: 1 | AE12: 1 | AF12: 1 | AG12: 1 | AH12: 1 | AI12: 1 | AJ12: 1 | AK12: 1 | AL12: 1 | AM12: 1 | AN12: 1 | AO12: 1 | AP12: 1 | AQ12: 1 | AR12: 1 | AS12: 1 | AT12: 1 | AU12: 1 | AV12: 1 | AW12: 1 | AX12: 1 | AY12: 1 | AZ12: 1 | BA12: 1 | BC12: =Q12 -> 1 | BD12: =AC12 -> 1 | BE12: =AO12 -> 1 | BF12: =BA12 -> 1
B13: Software sales | E13: # | F13: =IF(YEAR(F$3)>=2029,1,0) -> 0 | G13: =IF(YEAR(G$3)>=2029,1,0) -> 0 | H13: =IF(YEAR(H$3)>=2029,1,0) -> 0 | I13: =IF(YEAR(I$3)>=2029,1,0) -> 0 | J13: =IF(YEAR(J$3)>=2029,1,0) -> 0 | K13: =IF(YEAR(K$3)>=2029,1,0) -> 0 | L13: =IF(YEAR(L$3)>=2029,1,0) -> 0 | M13: =IF(YEAR(M$3)>=2029,1,0) -> 0 | ... BA13: =IF(YEAR(BA$3)>=2029,1,0) -> 1 | BC13: =Q13 -> 0 | BD13: =AC13 -> 0 | BE13: =AO13 -> 1 | BF13: =BA13 -> 1
B14: Developers | E14: # | F14: =IF(YEAR(F$3)>=2029,2,1) -> 1 | G14: =IF(YEAR(G$3)>=2029,2,1) -> 1 | H14: =IF(YEAR(H$3)>=2029,2,1) -> 1 | I14: =IF(YEAR(I$3)>=2029,2,1) -> 1 | J14: =IF(YEAR(J$3)>=2029,2,1) -> 1 | K14: =IF(YEAR(K$3)>=2029,2,1) -> 1 | L14: =IF(YEAR(L$3)>=2029,2,1) -> 1 | M14: =IF(YEAR(M$3)>=2029,2,1) -> 1 | ... BA14: =IF(YEAR(BA$3)>=2029,2,1) -> 2 | BC14: =Q14 -> 1 | BD14: =AC14 -> 1 | BE14: =AO14 -> 2 | BF14: =BA14 -> 2
B15: Rob | E15: # | F15: 1 | G15: 1 | H15: 1 | I15: 1 | J15: 1 | K15: 1 | L15: 1 | M15: 1 | N15: 1 | O15: 1 | P15: 1 | Q15: 1 | R15: 1 | S15: 1 | T15: 1 | U15: 1 | V15: 1 | W15: 1 | X15: 1 | Y15: 1 | Z15: 1 | AA15: 1 | AB15: 1 | AC15: 1 | AD15: 1 | AE15: 1 | AF15: 1 | AG15: 1 | AH15: 1 | AI15: 1 | AJ15: 1 | AK15: 1 | AL15: 1 | AM15: 1 | AN15: 1 | AO15: 1 | AP15: 1 | AQ15: 1 | AR15: 1 | AS15: 1 | AT15: 1 | AU15: 1 | AV15: 1 | AW15: 1 | AX15: 1 | AY15: 1 | AZ15: 1 | BA15: 1 | BC15: =Q15 -> 1 | BD15: =AC15 -> 1 | BE15: =AO15 -> 1 | BF15: =BA15 -> 1
B16: Simon | E16: # | F16: 1 | G16: 1 | H16: 1 | I16: 1 | J16: 1 | K16: 1 | L16: 1 | M16: 1 | N16: 1 | O16: 1 | P16: 1 | Q16: 1 | R16: 1 | S16: 1 | T16: 1 | U16: 1 | V16: 1 | W16: 1 | X16: 1 | Y16: 1 | Z16: 1 | AA16: 1 | AB16: 1 | AC16: 1 | AD16: 1 | AE16: 1 | AF16: 1 | AG16: 1 | AH16: 1 | AI16: 1 | AJ16: 1 | AK16: 1 | AL16: 1 | AM16: 1 | AN16: 1 | AO16: 1 | AP16: 1 | AQ16: 1 | AR16: 1 | AS16: 1 | AT16: 1 | AU16: 1 | AV16: 1 | AW16: 1 | AX16: 1 | AY16: 1 | AZ16: 1 | BA16: 1 | BC16: =Q16 -> 1 | BD16: =AC16 -> 1 | BE16: =AO16 -> 1 | BF16: =BA16 -> 1
B17: Total FTE | E17: # | F17: =SUM(F8:F16) -> 9 | G17: =SUM(G8:G16) -> 9 | H17: =SUM(H8:H16) -> 9 | I17: =SUM(I8:I16) -> 9 | J17: =SUM(J8:J16) -> 9 | K17: =SUM(K8:K16) -> 10 | L17: =SUM(L8:L16) -> 10 | M17: =SUM(M8:M16) -> 10 | ... BA17: =SUM(BA8:BA16) -> 17 | BC17: =Q17 -> 10 | BD17: =AC17 -> 12 | BE17: =AO17 -> 15 | BF17: =BA17 -> 17
B18: Consultancy FTE (ex-software team) | E18: # | F18: =F17-F13-F14 -> 8 | G18: =G17-G13-G14 -> 8 | H18: =H17-H13-H14 -> 8 | I18: =I17-I13-I14 -> 8 | J18: =J17-J13-J14 -> 8 | K18: =K17-K13-K14 -> 9 | L18: =L17-L13-L14 -> 9 | M18: =M17-M13-M14 -> 9 | ... BA18: =BA17-BA13-BA14 -> 14 | BC18: =Q18 -> 9 | BD18: =AC18 -> 11 | BE18: =AO18 -> 12 | BF18: =BA18 -> 14
B20: PERSONNEL COSTS
B21: Gross salary | E21: € | F21: {=INDEX(Assumptions!$C$37:$F$37,MATCH(YEAR(F$3),Assumptions!$C$1:$F$1,0))*IF(ISNUMBER(SEARCH("yr",Assumptions!$G$37)),1/12,1)+INDEX(Assumptions!$C$38:$F$38,MATCH(YEAR(F$3),Assumptions!$C$1:$F$1,0))*IF(ISNUMBER(SEARCH("yr",Assumptions!$G$38)),1/12,1)+F8*INDEX(Assumptions!$C$40:$F$40,MATCH(YEAR(F$3),Assumptions!$C$1:$F$1,0))*IF(ISNUMBER(SEARCH("yr",Assumptions!$G$40)),1/12,1)+F9*INDEX(Assumptions!$C$39:$F$39,MATCH(YEAR(F$3),Assumptions!$C$1:$F$1,0))*IF(ISNUMBER(SEARCH("yr",Assumptions!$G$39)),1/12,1)+F10*INDEX(Assumptions!$C$41:$F$41,MATCH(YEAR(F$3),Assumptions!$C$1:$F$1,0))*IF(ISNUMBER(SEARCH("yr",Assumptions!$G$41)),1/12,1)+F12*INDEX(Assumptions!$C$42:$F$42,MATCH(YEAR(F$3),Assumptions!$C$1:$F$1,0))*IF(ISNUMBER(SEARCH("yr",Assumptions!$G$42)),1/12,1)+F13*INDEX(Assumptions!$C$44:$F$44,MATCH(YEAR(F$3),Assumptions!$C$1:$F$1,0))*IF(ISNUMBER(SEARCH("yr",Assumptions!$G$44)),1/12,1)+F14*INDEX(Assumptions!$C$45:$F$45,MATCH(YEAR(F$3),Assumptions!$C$1:$F$1,0))*IF(ISNUMBER(SEARCH("yr",Assumptions!$G$45)),1/12,1)} -> 35000 | G21: {=INDEX(Assumptions!$C$37:$F$37,MATCH(YEAR(G$3),Assumptions!$C$1:$F$1,0))*IF(ISNUMBER(SEARCH("yr",Assumptions!$G$37)),1/12,1)+INDEX(Assumptions!$C$38:$F$38,MATCH(YEAR(G$3),Assumptions!$C$1:$F$1,0))*IF(ISNUMBER(SEARCH("yr",Assumptions!$G$38)),1/12,1)+G8*INDEX(Assumptions!$C$40:$F$40,MATCH(YEAR(G$3),Assumptions!$C$1:$F$1,0))*IF(ISNUMBER(SEARCH("yr",Assumptions!$G$40)),1/12,1)+G9*INDEX(Assumptions!$C$39:$F$39,MATCH(YEAR(G$3),Assumptions!$C$1:$F$1,0))*IF(ISNUMBER(SEARCH("yr",Assumptions!$G$39)),1/12,1)+G10*INDEX(Assumptions!$C$41:$F$41,MATCH(YEAR(G$3),Assumptions!$C$1:$F$1,0))*IF(ISNUMBER(SEARCH("yr",Assumptions!$G$41)),1/12,1)+G12*INDEX(Assumptions!$C$42:$F$42,MATCH(YEAR(G$3),Assumptions!$C$1:$F$1,0))*IF(ISNUMBER(SEARCH("yr",Assumptions!$G$42)),1/12,1)+G13*INDEX(Assumptions!$C$44:$F$44,MATCH(YEAR(G$3),Assumptions!$C$1:$F$1,0))*IF(ISNUMBER(SEARCH("yr",Assumptions!$G$44)),1/12,1)+G14*INDEX(Assumptions!$C$45:$F$45,MATCH(YEAR(G$3),Assumptions!$C$1:$F$1,0))*IF(ISNUMBER(SEARCH("yr",Assumptions!$G$45)),1/12,1)} -> 35000 | H21: {=INDEX(Assumptions!$C$37:$F$37,MATCH(YEAR(H$3),Assumptions!$C$1:$F$1,0))*IF(ISNUMBER(SEARCH("yr",Assumptions!$G$37)),1/12,1)+INDEX(Assumptions!$C$38:$F$38,MATCH(YEAR(H$3),Assumptions!$C$1:$F$1,0))*IF(ISNUMBER(SEARCH("yr",Assumptions!$G$38)),1/12,1)+H8*INDEX(Assumptions!$C$40:$F$40,MATCH(YEAR(H$3),Assumptions!$C$1:$F$1,0))*IF(ISNUMBER(SEARCH("yr",Assumptions!$G$40)),1/12,1)+H9*INDEX(Assumptions!$C$39:$F$39,MATCH(YEAR(H$3),Assumptions!$C$1:$F$1,0))*IF(ISNUMBER(SEARCH("yr",Assumptions!$G$39)),1/12,1)+H10*INDEX(Assumptions!$C$41:$F$41,MATCH(YEAR(H$3),Assumptions!$C$1:$F$1,0))*IF(ISNUMBER(SEARCH("yr",Assumptions!$G$41)),1/12,1)+H12*INDEX(Assumptions!$C$42:$F$42,MATCH(YEAR(H$3),Assumptions!$C$1:$F$1,0))*IF(ISNUMBER(SEARCH("yr",Assumptions!$G$42)),1/12,1)+H13*INDEX(Assumptions!$C$44:$F$44,MATCH(YEAR(H$3),Assumptions!$C$1:$F$1,0))*IF(ISNUMBER(SEARCH("yr",Assumptions!$G$44)),1/12,1)+H14*INDEX(Assumptions!$C$45:$F$45,MATCH(YEAR(H$3),Assumptions!$C$1:$F$1,0))*IF(ISNUMBER(SEARCH("yr",Assumptions!$G$45)),1/12,1)} -> 35000 | I21: {=INDEX(Assumptions!$C$37:$F$37,MATCH(YEAR(I$3),Assumptions!$C$1:$F$1,0))*IF(ISNUMBER(SEARCH("yr",Assumptions!$G$37)),1/12,1)+INDEX(Assumptions!$C$38:$F$38,MATCH(YEAR(I$3),Assumptions!$C$1:$F$1,0))*IF(ISNUMBER(SEARCH("yr",Assumptions!$G$38)),1/12,1)+I8*INDEX(Assumptions!$C$40:$F$40,MATCH(YEAR(I$3),Assumptions!$C$1:$F$1,0))*IF(ISNUMBER(SEARCH("yr",Assumptions!$G$40)),1/12,1)+I9*INDEX(Assumptions!$C$39:$F$39,MATCH(YEAR(I$3),Assumptions!$C$1:$F$1,0))*IF(ISNUMBER(SEARCH("yr",Assumptions!$G$39)),1/12,1)+I10*INDEX(Assumptions!$C$41:$F$41,MATCH(YEAR(I$3),Assumptions!$C$1:$F$1,0))*IF(ISNUMBER(SEARCH("yr",Assumptions!$G$41)),1/12,1)+I12*INDEX(Assumptions!$C$42:$F$42,MATCH(YEAR(I$3),Assumptions!$C$1:$F$1,0))*IF(ISNUMBER(SEARCH("yr",Assumptions!$G$42)),1/12,1)+I13*INDEX(Assumptions!$C$44:$F$44,MATCH(YEAR(I$3),Assumptions!$C$1:$F$1,0))*IF(ISNUMBER(SEARCH("yr",Assumptions!$G$44)),1/12,1)+I14*INDEX(Assumptions!$C$45:$F$45,MATCH(YEAR(I$3),Assumptions!$C$1:$F$1,0))*IF(ISNUMBER(SEARCH("yr",Assumptions!$G$45)),1/12,1)} -> 35000 | J21: {=INDEX(Assumptions!$C$37:$F$37,MATCH(YEAR(J$3),Assumptions!$C$1:$F$1,0))*IF(ISNUMBER(SEARCH("yr",Assumptions!$G$37)),1/12,1)+INDEX(Assumptions!$C$38:$F$38,MATCH(YEAR(J$3),Assumptions!$C$1:$F$1,0))*IF(ISNUMBER(SEARCH("yr",Assumptions!$G$38)),1/12,1)+J8*INDEX(Assumptions!$C$40:$F$40,MATCH(YEAR(J$3),Assumptions!$C$1:$F$1,0))*IF(ISNUMBER(SEARCH("yr",Assumptions!$G$40)),1/12,1)+J9*INDEX(Assumptions!$C$39:$F$39,MATCH(YEAR(J$3),Assumptions!$C$1:$F$1,0))*IF(ISNUMBER(SEARCH("yr",Assumptions!$G$39)),1/12,1)+J10*INDEX(Assumptions!$C$41:$F$41,MATCH(YEAR(J$3),Assumptions!$C$1:$F$1,0))*IF(ISNUMBER(SEARCH("yr",Assumptions!$G$41)),1/12,1)+J12*INDEX(Assumptions!$C$42:$F$42,MATCH(YEAR(J$3),Assumptions!$C$1:$F$1,0))*IF(ISNUMBER(SEARCH("yr",Assumptions!$G$42)),1/12,1)+J13*INDEX(Assumptions!$C$44:$F$44,MATCH(YEAR(J$3),Assumptions!$C$1:$F$1,0))*IF(ISNUMBER(SEARCH("yr",Assumptions!$G$44)),1/12,1)+J14*INDEX(Assumptions!$C$45:$F$45,MATCH(YEAR(J$3),Assumptions!$C$1:$F$1,0))*IF(ISNUMBER(SEARCH("yr",Assumptions!$G$45)),1/12,1)} -> 35000 | K21: {=INDEX(Assumptions!$C$37:$F$37,MATCH(YEAR(K$3),Assumptions!$C$1:$F$1,0))*IF(ISNUMBER(SEARCH("yr",Assumptions!$G$37)),1/12,1)+INDEX(Assumptions!$C$38:$F$38,MATCH(YEAR(K$3),Assumptions!$C$1:$F$1,0))*IF(ISNUMBER(SEARCH("yr",Assumptions!$G$38)),1/12,1)+K8*INDEX(Assumptions!$C$40:$F$40,MATCH(YEAR(K$3),Assumptions!$C$1:$F$1,0))*IF(ISNUMBER(SEARCH("yr",Assumptions!$G$40)),1/12,1)+K9*INDEX(Assumptions!$C$39:$F$39,MATCH(YEAR(K$3),Assumptions!$C$1:$F$1,0))*IF(ISNUMBER(SEARCH("yr",Assumptions!$G$39)),1/12,1)+K10*INDEX(Assumptions!$C$41:$F$41,MATCH(YEAR(K$3),Assumptions!$C$1:$F$1,0))*IF(ISNUMBER(SEARCH("yr",Assumptions!$G$41)),1/12,1)+K12*INDEX(Assumptions!$C$42:$F$42,MATCH(YEAR(K$3),Assumptions!$C$1:$F$1,0))*IF(ISNUMBER(SEARCH("yr",Assumptions!$G$42)),1/12,1)+K13*INDEX(Assumptions!$C$44:$F$44,MATCH(YEAR(K$3),Assumptions!$C$1:$F$1,0))*IF(ISNUMBER(SEARCH("yr",Assumptions!$G$44)),1/12,1)+K14*INDEX(Assumptions!$C$45:$F$45,MATCH(YEAR(K$3),Assumptions!$C$1:$F$1,0))*IF(ISNUMBER(SEARCH("yr",Assumptions!$G$45)),1/12,1)} -> 38000 | L21: {=INDEX(Assumptions!$C$37:$F$37,MATCH(YEAR(L$3),Assumptions!$C$1:$F$1,0))*IF(ISNUMBER(SEARCH("yr",Assumptions!$G$37)),1/12,1)+INDEX(Assumptions!$C$38:$F$38,MATCH(YEAR(L$3),Assumptions!$C$1:$F$1,0))*IF(ISNUMBER(SEARCH("yr",Assumptions!$G$38)),1/12,1)+L8*INDEX(Assumptions!$C$40:$F$40,MATCH(YEAR(L$3),Assumptions!$C$1:$F$1,0))*IF(ISNUMBER(SEARCH("yr",Assumptions!$G$40)),1/12,1)+L9*INDEX(Assumptions!$C$39:$F$39,MATCH(YEAR(L$3),Assumptions!$C$1:$F$1,0))*IF(ISNUMBER(SEARCH("yr",Assumptions!$G$39)),1/12,1)+L10*INDEX(Assumptions!$C$41:$F$41,MATCH(YEAR(L$3),Assumptions!$C$1:$F$1,0))*IF(ISNUMBER(SEARCH("yr",Assumptions!$G$41)),1/12,1)+L12*INDEX(Assumptions!$C$42:$F$42,MATCH(YEAR(L$3),Assumptions!$C$1:$F$1,0))*IF(ISNUMBER(SEARCH("yr",Assumptions!$G$42)),1/12,1)+L13*INDEX(Assumptions!$C$44:$F$44,MATCH(YEAR(L$3),Assumptions!$C$1:$F$1,0))*IF(ISNUMBER(SEARCH("yr",Assumptions!$G$44)),1/12,1)+L14*INDEX(Assumptions!$C$45:$F$45,MATCH(YEAR(L$3),Assumptions!$C$1:$F$1,0))*IF(ISNUMBER(SEARCH("yr",Assumptions!$G$45)),1/12,1)} -> 38000 | M21: {=INDEX(Assumptions!$C$37:$F$37,MATCH(YEAR(M$3),Assumptions!$C$1:$F$1,0))*IF(ISNUMBER(SEARCH("yr",Assumptions!$G$37)),1/12,1)+INDEX(Assumptions!$C$38:$F$38,MATCH(YEAR(M$3),Assumptions!$C$1:$F$1,0))*IF(ISNUMBER(SEARCH("yr",Assumptions!$G$38)),1/12,1)+M8*INDEX(Assumptions!$C$40:$F$40,MATCH(YEAR(M$3),Assumptions!$C$1:$F$1,0))*IF(ISNUMBER(SEARCH("yr",Assumptions!$G$40)),1/12,1)+M9*INDEX(Assumptions!$C$39:$F$39,MATCH(YEAR(M$3),Assumptions!$C$1:$F$1,0))*IF(ISNUMBER(SEARCH("yr",Assumptions!$G$39)),1/12,1)+M10*INDEX(Assumptions!$C$41:$F$41,MATCH(YEAR(M$3),Assumptions!$C$1:$F$1,0))*IF(ISNUMBER(SEARCH("yr",Assumptions!$G$41)),1/12,1)+M12*INDEX(Assumptions!$C$42:$F$42,MATCH(YEAR(M$3),Assumptions!$C$1:$F$1,0))*IF(ISNUMBER(SEARCH("yr",Assumptions!$G$42)),1/12,1)+M13*INDEX(Assumptions!$C$44:$F$44,MATCH(YEAR(M$3),Assumptions!$C$1:$F$1,0))*IF(ISNUMBER(SEARCH("yr",Assumptions!$G$44)),1/12,1)+M14*INDEX(Assumptions!$C$45:$F$45,MATCH(YEAR(M$3),Assumptions!$C$1:$F$1,0))*IF(ISNUMBER(SEARCH("yr",Assumptions!$G$45)),1/12,1)} -> 38000 | ... BA21: {=INDEX(Assumptions!$C$37:$F$37,MATCH(YEAR(BA$3),Assumptions!$C$1:$F$1,0))*IF(ISNUMBER(SEARCH("yr",Assumptions!$G$37)),1/12,1)+INDEX(Assumptions!$C$38:$F$38,MATCH(YEAR(BA$3),Assumptions!$C$1:$F$1,0))*IF(ISNUMBER(SEARCH("yr",Assumptions!$G$38)),1/12,1)+BA8*INDEX(Assumptions!$C$40:$F$40,MATCH(YEAR(BA$3),Assumptions!$C$1:$F$1,0))*IF(ISNUMBER(SEARCH("yr",Assumptions!$G$40)),1/12,1)+BA9*INDEX(Assumptions!$C$39:$F$39,MATCH(YEAR(BA$3),Assumptions!$C$1:$F$1,0))*IF(ISNUMBER(SEARCH("yr",Assumptions!$G$39)),1/12,1)+BA10*INDEX(Assumptions!$C$41:$F$41,MATCH(YEAR(BA$3),Assumptions!$C$1:$F$1,0))*IF(ISNUMBER(SEARCH("yr",Assumptions!$G$41)),1/12,1)+BA12*INDEX(Assumptions!$C$42:$F$42,MATCH(YEAR(BA$3),Assumptions!$C$1:$F$1,0))*IF(ISNUMBER(SEARCH("yr",Assumptions!$G$42)),1/12,1)+BA13*INDEX(Assumptions!$C$44:$F$44,MATCH(YEAR(BA$3),Assumptions!$C$1:$F$1,0))*IF(ISNUMBER(SEARCH("yr",Assumptions!$G$44)),1/12,1)+BA14*INDEX(Assumptions!$C$45:$F$45,MATCH(YEAR(BA$3),Assumptions!$C$1:$F$1,0))*IF(ISNUMBER(SEARCH("yr",Assumptions!$G$45)),1/12,1)} -> 91100 | BC21: =SUMPRODUCT((YEAR($F$3:$BA$3)=BC$3)*$F21:$BA21) -> 441000 | BD21: =SUMPRODUCT((YEAR($F$3:$BA$3)=BD$3)*$F21:$BA21) -> 575400 | BE21: =SUMPRODUCT((YEAR($F$3:$BA$3)=BE$3)*$F21:$BA21) -> 875300 | BF21: =SUMPRODUCT((YEAR($F$3:$BA$3)=BF$3)*$F21:$BA21) -> 1042200
B22: Holiday pay | E22: € | F22: =Assumptions!$C$46*F21 -> 2800 | G22: =Assumptions!$C$46*G21 -> 2800 | H22: =Assumptions!$C$46*H21 -> 2800 | I22: =Assumptions!$C$46*I21 -> 2800 | J22: =Assumptions!$C$46*J21 -> 2800 | K22: =Assumptions!$C$46*K21 -> 3040 | L22: =Assumptions!$C$46*L21 -> 3040 | M22: =Assumptions!$C$46*M21 -> 3040 | ... BA22: =Assumptions!$C$46*BA21 -> 7288 | BC22: =SUMPRODUCT((YEAR($F$3:$BA$3)=BC$3)*$F22:$BA22) -> 35280 | BD22: =SUMPRODUCT((YEAR($F$3:$BA$3)=BD$3)*$F22:$BA22) -> 46032 | BE22: =SUMPRODUCT((YEAR($F$3:$BA$3)=BE$3)*$F22:$BA22) -> 70024 | BF22: =SUMPRODUCT((YEAR($F$3:$BA$3)=BF$3)*$F22:$BA22) -> 83376
B23: Employer taxes | E23: € | F23: =Assumptions!$C$47*(F21+F22) -> 7182 | G23: =Assumptions!$C$47*(G21+G22) -> 7182 | H23: =Assumptions!$C$47*(H21+H22) -> 7182 | I23: =Assumptions!$C$47*(I21+I22) -> 7182 | J23: =Assumptions!$C$47*(J21+J22) -> 7182 | K23: =Assumptions!$C$47*(K21+K22) -> 7797.6 | L23: =Assumptions!$C$47*(L21+L22) -> 7797.6 | M23: =Assumptions!$C$47*(M21+M22) -> 7797.6 | ... BA23: =Assumptions!$C$47*(BA21+BA22) -> 18693.72 | BC23: =SUMPRODUCT((YEAR($F$3:$BA$3)=BC$3)*$F23:$BA23) -> 90493.2 | BD23: =SUMPRODUCT((YEAR($F$3:$BA$3)=BD$3)*$F23:$BA23) -> 118072.08 | BE23: =SUMPRODUCT((YEAR($F$3:$BA$3)=BE$3)*$F23:$BA23) -> 179611.56 | BF23: =SUMPRODUCT((YEAR($F$3:$BA$3)=BF$3)*$F23:$BA23) -> 213859.44
B24: Sales hire | E24: € | F24: {=INDEX(Assumptions!$C$43:$F$43,MATCH(YEAR(F$3),Assumptions!$C$1:$F$1,0))*IF(ISNUMBER(SEARCH("yr",Assumptions!$G$43)),1/12,1)} -> 6500 | G24: {=INDEX(Assumptions!$C$43:$F$43,MATCH(YEAR(G$3),Assumptions!$C$1:$F$1,0))*IF(ISNUMBER(SEARCH("yr",Assumptions!$G$43)),1/12,1)} -> 6500 | H24: {=INDEX(Assumptions!$C$43:$F$43,MATCH(YEAR(H$3),Assumptions!$C$1:$F$1,0))*IF(ISNUMBER(SEARCH("yr",Assumptions!$G$43)),1/12,1)} -> 6500 | I24: {=INDEX(Assumptions!$C$43:$F$43,MATCH(YEAR(I$3),Assumptions!$C$1:$F$1,0))*IF(ISNUMBER(SEARCH("yr",Assumptions!$G$43)),1/12,1)} -> 6500 | J24: {=INDEX(Assumptions!$C$43:$F$43,MATCH(YEAR(J$3),Assumptions!$C$1:$F$1,0))*IF(ISNUMBER(SEARCH("yr",Assumptions!$G$43)),1/12,1)} -> 6500 | K24: {=INDEX(Assumptions!$C$43:$F$43,MATCH(YEAR(K$3),Assumptions!$C$1:$F$1,0))*IF(ISNUMBER(SEARCH("yr",Assumptions!$G$43)),1/12,1)} -> 6500 | L24: {=INDEX(Assumptions!$C$43:$F$43,MATCH(YEAR(L$3),Assumptions!$C$1:$F$1,0))*IF(ISNUMBER(SEARCH("yr",Assumptions!$G$43)),1/12,1)} -> 6500 | M24: {=INDEX(Assumptions!$C$43:$F$43,MATCH(YEAR(M$3),Assumptions!$C$1:$F$1,0))*IF(ISNUMBER(SEARCH("yr",Assumptions!$G$43)),1/12,1)} -> 6500 | ... BA24: {=INDEX(Assumptions!$C$43:$F$43,MATCH(YEAR(BA$3),Assumptions!$C$1:$F$1,0))*IF(ISNUMBER(SEARCH("yr",Assumptions!$G$43)),1/12,1)} -> 8000 | BC24: =SUMPRODUCT((YEAR($F$3:$BA$3)=BC$3)*$F24:$BA24) -> 78000 | BD24: =SUMPRODUCT((YEAR($F$3:$BA$3)=BD$3)*$F24:$BA24) -> 84000 | BE24: =SUMPRODUCT((YEAR($F$3:$BA$3)=BE$3)*$F24:$BA24) -> 90000 | BF24: =SUMPRODUCT((YEAR($F$3:$BA$3)=BF$3)*$F24:$BA24) -> 96000
B25: Success-fee bonus | E25: € | F25: {='Revenue forecast'!F35*(1-Assumptions!$C$31*Assumptions!$C$33)*Assumptions!$C$34*(0.9+0.1*(Assumptions!$C$31+INDEX(Assumptions!$C$32:$F$32,MATCH(YEAR(F$3),Assumptions!$C$1:$F$1,0))))} -> 0 | G25: {='Revenue forecast'!G35*(1-Assumptions!$C$31*Assumptions!$C$33)*Assumptions!$C$34*(0.9+0.1*(Assumptions!$C$31+INDEX(Assumptions!$C$32:$F$32,MATCH(YEAR(G$3),Assumptions!$C$1:$F$1,0))))} -> 35797.5 | H25: {='Revenue forecast'!H35*(1-Assumptions!$C$31*Assumptions!$C$33)*Assumptions!$C$34*(0.9+0.1*(Assumptions!$C$31+INDEX(Assumptions!$C$32:$F$32,MATCH(YEAR(H$3),Assumptions!$C$1:$F$1,0))))} -> 0 | I25: {='Revenue forecast'!I35*(1-Assumptions!$C$31*Assumptions!$C$33)*Assumptions!$C$34*(0.9+0.1*(Assumptions!$C$31+INDEX(Assumptions!$C$32:$F$32,MATCH(YEAR(I$3),Assumptions!$C$1:$F$1,0))))} -> 0 | J25: {='Revenue forecast'!J35*(1-Assumptions!$C$31*Assumptions!$C$33)*Assumptions!$C$34*(0.9+0.1*(Assumptions!$C$31+INDEX(Assumptions!$C$32:$F$32,MATCH(YEAR(J$3),Assumptions!$C$1:$F$1,0))))} -> 0 | K25: {='Revenue forecast'!K35*(1-Assumptions!$C$31*Assumptions!$C$33)*Assumptions!$C$34*(0.9+0.1*(Assumptions!$C$31+INDEX(Assumptions!$C$32:$F$32,MATCH(YEAR(K$3),Assumptions!$C$1:$F$1,0))))} -> 7159.5 | L25: {='Revenue forecast'!L35*(1-Assumptions!$C$31*Assumptions!$C$33)*Assumptions!$C$34*(0.9+0.1*(Assumptions!$C$31+INDEX(Assumptions!$C$32:$F$32,MATCH(YEAR(L$3),Assumptions!$C$1:$F$1,0))))} -> 7159.5 | M25: {='Revenue forecast'!M35*(1-Assumptions!$C$31*Assumptions!$C$33)*Assumptions!$C$34*(0.9+0.1*(Assumptions!$C$31+INDEX(Assumptions!$C$32:$F$32,MATCH(YEAR(M$3),Assumptions!$C$1:$F$1,0))))} -> 7159.5 | ... BA25: {='Revenue forecast'!BA35*(1-Assumptions!$C$31*Assumptions!$C$33)*Assumptions!$C$34*(0.9+0.1*(Assumptions!$C$31+INDEX(Assumptions!$C$32:$F$32,MATCH(YEAR(BA$3),Assumptions!$C$1:$F$1,0))))} -> 337315.68 | BC25: =SUMPRODUCT((YEAR($F$3:$BA$3)=BC$3)*$F25:$BA25) -> 164668.5 | BD25: =SUMPRODUCT((YEAR($F$3:$BA$3)=BD$3)*$F25:$BA25) -> 512509.2 | BE25: =SUMPRODUCT((YEAR($F$3:$BA$3)=BE$3)*$F25:$BA25) -> 1151998.8 | BF25: =SUMPRODUCT((YEAR($F$3:$BA$3)=BF$3)*$F25:$BA25) -> 2521218.5
B26: Contractors / accountant | E26: € | F26: 0 | G26: 0 | H26: 0 | I26: 0 | J26: 0 | K26: 0 | L26: 0 | M26: 0 | N26: 0 | O26: 0 | P26: 0 | Q26: 0 | R26: 0 | S26: 0 | T26: 0 | U26: 0 | V26: 0 | W26: 0 | X26: 0 | Y26: 0 | Z26: 0 | AA26: 0 | AB26: 0 | AC26: 0 | AD26: 0 | AE26: 0 | AF26: 0 | AG26: 0 | AH26: 0 | AI26: 0 | AJ26: 0 | AK26: 0 | AL26: 0 | AM26: 0 | AN26: 0 | AO26: 0 | AP26: 0 | AQ26: 0 | AR26: 0 | AS26: 0 | AT26: 0 | AU26: 0 | AV26: 0 | AW26: 0 | AX26: 0 | AY26: 0 | AZ26: 0 | BA26: 0 | BC26: =SUMPRODUCT((YEAR($F$3:$BA$3)=BC$3)*$F26:$BA26) -> 0 | BD26: =SUMPRODUCT((YEAR($F$3:$BA$3)=BD$3)*$F26:$BA26) -> 0 | BE26: =SUMPRODUCT((YEAR($F$3:$BA$3)=BE$3)*$F26:$BA26) -> 0 | BF26: =SUMPRODUCT((YEAR($F$3:$BA$3)=BF$3)*$F26:$BA26) -> 0
B27: Other people costs | E27: € | F27: 267 | G27: 267 | H27: 267 | I27: 267 | J27: 267 | K27: 267 | L27: 267 | M27: 267 | N27: 267 | O27: 267 | P27: 267 | Q27: 267 | R27: 267 | S27: 267 | T27: 267 | U27: 267 | V27: 267 | W27: 267 | X27: 267 | Y27: 267 | Z27: 267 | AA27: 267 | AB27: 267 | AC27: 267 | AD27: 267 | AE27: 267 | AF27: 267 | AG27: 267 | AH27: 267 | AI27: 267 | AJ27: 267 | AK27: 267 | AL27: 267 | AM27: 267 | AN27: 267 | AO27: 267 | AP27: 267 | AQ27: 267 | AR27: 267 | AS27: 267 | AT27: 267 | AU27: 267 | AV27: 267 | AW27: 267 | AX27: 267 | AY27: 267 | AZ27: 267 | BA27: 267 | BC27: =SUMPRODUCT((YEAR($F$3:$BA$3)=BC$3)*$F27:$BA27) -> 3204 | BD27: =SUMPRODUCT((YEAR($F$3:$BA$3)=BD$3)*$F27:$BA27) -> 3204 | BE27: =SUMPRODUCT((YEAR($F$3:$BA$3)=BE$3)*$F27:$BA27) -> 3204 | BF27: =SUMPRODUCT((YEAR($F$3:$BA$3)=BF$3)*$F27:$BA27) -> 3204
B28: Total personnel | E28: € | F28: =SUM(F21:F27) -> 51749 | G28: =SUM(G21:G27) -> 87546.5 | H28: =SUM(H21:H27) -> 51749 | I28: =SUM(I21:I27) -> 51749 | J28: =SUM(J21:J27) -> 51749 | K28: =SUM(K21:K27) -> 62764.1 | L28: =SUM(L21:L27) -> 62764.1 | M28: =SUM(M21:M27) -> 62764.1 | ... BA28: =SUM(BA21:BA27) -> 462664.4 | BC28: =SUMPRODUCT((YEAR($F$3:$BA$3)=BC$3)*$F28:$BA28) -> 812645.7 | BD28: =SUMPRODUCT((YEAR($F$3:$BA$3)=BD$3)*$F28:$BA28) -> 1339217.3 | BE28: =SUMPRODUCT((YEAR($F$3:$BA$3)=BE$3)*$F28:$BA28) -> 2370138.4 | BF28: =SUMPRODUCT((YEAR($F$3:$BA$3)=BF$3)*$F28:$BA28) -> 3959857.9

Sheet OPEX
B2: OPEX — Monthly 2027–2030 (€)
E3: Unit | F3: 46388 | G3: 46419 | H3: 46447 | I3: 46478 | J3: 46508 | K3: 46539 | L3: 46569 | M3: 46600 | N3: 46631 | O3: 46661 | P3: 46692 | Q3: 46722 | R3: 46753 | S3: 46784 | T3: 46813 | U3: 46844 | V3: 46874 | W3: 46905 | X3: 46935 | Y3: 46966 | Z3: 46997 | AA3: 47027 | AB3: 47058 | AC3: 47088 | AD3: 47119 | AE3: 47150 | AF3: 47178 | AG3: 47209 | AH3: 47239 | AI3: 47270 | AJ3: 47300 | AK3: 47331 | AL3: 47362 | AM3: 47392 | AN3: 47423 | AO3: 47453 | AP3: 47484 | AQ3: 47515 | AR3: 47543 | AS3: 47574 | AT3: 47604 | AU3: 47635 | AV3: 47665 | AW3: 47696 | AX3: 47727 | AY3: 47757 | AZ3: 47788 | BA3: 47818 | BC3: 2027 | BD3: 2028 | BE3: 2029 | BF3: 2030
B6: OTHER OPEX
B7: Rent | E7: € | F7: =Personnel!F17*Assumptions!$C$56*IF(ISNUMBER(SEARCH("yr",Assumptions!$G$56)),1/12,1) -> 5400 | G7: =Personnel!G17*Assumptions!$C$56*IF(ISNUMBER(SEARCH("yr",Assumptions!$G$56)),1/12,1) -> 5400 | H7: =Personnel!H17*Assumptions!$C$56*IF(ISNUMBER(SEARCH("yr",Assumptions!$G$56)),1/12,1) -> 5400 | I7: =Personnel!I17*Assumptions!$C$56*IF(ISNUMBER(SEARCH("yr",Assumptions!$G$56)),1/12,1) -> 5400 | J7: =Personnel!J17*Assumptions!$C$56*IF(ISNUMBER(SEARCH("yr",Assumptions!$G$56)),1/12,1) -> 5400 | K7: =Personnel!K17*Assumptions!$C$56*IF(ISNUMBER(SEARCH("yr",Assumptions!$G$56)),1/12,1) -> 6000 | L7: =Personnel!L17*Assumptions!$C$56*IF(ISNUMBER(SEARCH("yr",Assumptions!$G$56)),1/12,1) -> 6000 | M7: =Personnel!M17*Assumptions!$C$56*IF(ISNUMBER(SEARCH("yr",Assumptions!$G$56)),1/12,1) -> 6000 | ... BA7: =Personnel!BA17*Assumptions!$C$56*IF(ISNUMBER(SEARCH("yr",Assumptions!$G$56)),1/12,1) -> 10200 | BC7: =SUMPRODUCT((YEAR($F$3:$BA$3)=BC$3)*$F7:$BA7) -> 69000 | BD7: =SUMPRODUCT((YEAR($F$3:$BA$3)=BD$3)*$F7:$BA7) -> 79200 | BE7: =SUMPRODUCT((YEAR($F$3:$BA$3)=BE$3)*$F7:$BA7) -> 105000 | BF7: =SUMPRODUCT((YEAR($F$3:$BA$3)=BF$3)*$F7:$BA7) -> 115200
B8: Software | E8: € | F8: =IF(Personnel!F18>=16,Assumptions!$F$58,IF(Personnel!F18>=10,Assumptions!$E$58,IF(Personnel!F18>=7,Assumptions!$D$58,Assumptions!$C$58)))*IF(ISNUMBER(SEARCH("yr",Assumptions!$G$58)),1/12,1)+Personnel!F17*Assumptions!$C$57*IF(ISNUMBER(SEARCH("yr",Assumptions!$G$57)),1/12,1) -> 4413.3333 | G8: =IF(Personnel!G18>=16,Assumptions!$F$58,IF(Personnel!G18>=10,Assumptions!$E$58,IF(Personnel!G18>=7,Assumptions!$D$58,Assumptions!$C$58)))*IF(ISNUMBER(SEARCH("yr",Assumptions!$G$58)),1/12,1)+Personnel!G17*Assumptions!$C$57*IF(ISNUMBER(SEARCH("yr",Assumptions!$G$57)),1/12,1) -> 4413.3333 | H8: =IF(Personnel!H18>=16,Assumptions!$F$58,IF(Personnel!H18>=10,Assumptions!$E$58,IF(Personnel!H18>=7,Assumptions!$D$58,Assumptions!$C$58)))*IF(ISNUMBER(SEARCH("yr",Assumptions!$G$58)),1/12,1)+Personnel!H17*Assumptions!$C$57*IF(ISNUMBER(SEARCH("yr",Assumptions!$G$57)),1/12,1) -> 4413.3333 | I8: =IF(Personnel!I18>=16,Assumptions!$F$58,IF(Personnel!I18>=10,Assumptions!$E$58,IF(Personnel!I18>=7,Assumptions!$D$58,Assumptions!$C$58)))*IF(ISNUMBER(SEARCH("yr",Assumptions!$G$58)),1/12,1)+Personnel!I17*Assumptions!$C$57*IF(ISNUMBER(SEARCH("yr",Assumptions!$G$57)),1/12,1) -> 4413.3333 | J8: =IF(Personnel!J18>=16,Assumptions!$F$58,IF(Personnel!J18>=10,Assumptions!$E$58,IF(Personnel!J18>=7,Assumptions!$D$58,Assumptions!$C$58)))*IF(ISNUMBER(SEARCH("yr",Assumptions!$G$58)),1/12,1)+Personnel!J17*Assumptions!$C$57*IF(ISNUMBER(SEARCH("yr",Assumptions!$G$57)),1/12,1) -> 4413.3333 | K8: =IF(Personnel!K18>=16,Assumptions!$F$58,IF(Personnel!K18>=10,Assumptions!$E$58,IF(Personnel!K18>=7,Assumptions!$D$58,Assumptions!$C$58)))*IF(ISNUMBER(SEARCH("yr",Assumptions!$G$58)),1/12,1)+Personnel!K17*Assumptions!$C$57*IF(ISNUMBER(SEARCH("yr",Assumptions!$G$57)),1/12,1) -> 4533.3333 | L8: =IF(Personnel!L18>=16,Assumptions!$F$58,IF(Personnel!L18>=10,Assumptions!$E$58,IF(Personnel!L18>=7,Assumptions!$D$58,Assumptions!$C$58)))*IF(ISNUMBER(SEARCH("yr",Assumptions!$G$58)),1/12,1)+Personnel!L17*Assumptions!$C$57*IF(ISNUMBER(SEARCH("yr",Assumptions!$G$57)),1/12,1) -> 4533.3333 | M8: =IF(Personnel!M18>=16,Assumptions!$F$58,IF(Personnel!M18>=10,Assumptions!$E$58,IF(Personnel!M18>=7,Assumptions!$D$58,Assumptions!$C$58)))*IF(ISNUMBER(SEARCH("yr",Assumptions!$G$58)),1/12,1)+Personnel!M17*Assumptions!$C$57*IF(ISNUMBER(SEARCH("yr",Assumptions!$G$57)),1/12,1) -> 4533.3333 | ... BA8: =IF(Personnel!BA18>=16,Assumptions!$F$58,IF(Personnel!BA18>=10,Assumptions!$E$58,IF(Personnel!BA18>=7,Assumptions!$D$58,Assumptions!$C$58)))*IF(ISNUMBER(SEARCH("yr",Assumptions!$G$58)),1/12,1)+Personnel!BA17*Assumptions!$C$57*IF(ISNUMBER(SEARCH("yr",Assumptions!$G$57)),1/12,1) -> 7040 | BC8: =SUMPRODUCT((YEAR($F$3:$BA$3)=BC$3)*$F8:$BA8) -> 53800 | BD8: =SUMPRODUCT((YEAR($F$3:$BA$3)=BD$3)*$F8:$BA8) -> 65840 | BE8: =SUMPRODUCT((YEAR($F$3:$BA$3)=BE$3)*$F8:$BA8) -> 81000 | BF8: =SUMPRODUCT((YEAR($F$3:$BA$3)=BF$3)*$F8:$BA8) -> 83040
B9: Office & hardware | E9: € | F9: =Personnel!F17*Assumptions!$C$59*IF(ISNUMBER(SEARCH("yr",Assumptions!$G$59)),1/12,1) -> 360 | G9: =Personnel!G17*Assumptions!$C$59*IF(ISNUMBER(SEARCH("yr",Assumptions!$G$59)),1/12,1) -> 360 | H9: =Personnel!H17*Assumptions!$C$59*IF(ISNUMBER(SEARCH("yr",Assumptions!$G$59)),1/12,1) -> 360 | I9: =Personnel!I17*Assumptions!$C$59*IF(ISNUMBER(SEARCH("yr",Assumptions!$G$59)),1/12,1) -> 360 | J9: =Personnel!J17*Assumptions!$C$59*IF(ISNUMBER(SEARCH("yr",Assumptions!$G$59)),1/12,1) -> 360 | K9: =Personnel!K17*Assumptions!$C$59*IF(ISNUMBER(SEARCH("yr",Assumptions!$G$59)),1/12,1) -> 400 | L9: =Personnel!L17*Assumptions!$C$59*IF(ISNUMBER(SEARCH("yr",Assumptions!$G$59)),1/12,1) -> 400 | M9: =Personnel!M17*Assumptions!$C$59*IF(ISNUMBER(SEARCH("yr",Assumptions!$G$59)),1/12,1) -> 400 | ... BA9: =Personnel!BA17*Assumptions!$C$59*IF(ISNUMBER(SEARCH("yr",Assumptions!$G$59)),1/12,1) -> 680 | BC9: =SUMPRODUCT((YEAR($F$3:$BA$3)=BC$3)*$F9:$BA9) -> 4600 | BD9: =SUMPRODUCT((YEAR($F$3:$BA$3)=BD$3)*$F9:$BA9) -> 5280 | BE9: =SUMPRODUCT((YEAR($F$3:$BA$3)=BE$3)*$F9:$BA9) -> 7000 | BF9: =SUMPRODUCT((YEAR($F$3:$BA$3)=BF$3)*$F9:$BA9) -> 7680
B10: Marketing & Sales | E10: € | F10: {=INDEX(Assumptions!$C$61:$F$61,MATCH(YEAR(F$3),Assumptions!$C$1:$F$1,0))*IF(ISNUMBER(SEARCH("yr",Assumptions!$G$61)),1/12,1)} -> 250 | G10: {=INDEX(Assumptions!$C$61:$F$61,MATCH(YEAR(G$3),Assumptions!$C$1:$F$1,0))*IF(ISNUMBER(SEARCH("yr",Assumptions!$G$61)),1/12,1)} -> 250 | H10: {=INDEX(Assumptions!$C$61:$F$61,MATCH(YEAR(H$3),Assumptions!$C$1:$F$1,0))*IF(ISNUMBER(SEARCH("yr",Assumptions!$G$61)),1/12,1)} -> 250 | I10: {=INDEX(Assumptions!$C$61:$F$61,MATCH(YEAR(I$3),Assumptions!$C$1:$F$1,0))*IF(ISNUMBER(SEARCH("yr",Assumptions!$G$61)),1/12,1)} -> 250 | J10: {=INDEX(Assumptions!$C$61:$F$61,MATCH(YEAR(J$3),Assumptions!$C$1:$F$1,0))*IF(ISNUMBER(SEARCH("yr",Assumptions!$G$61)),1/12,1)} -> 250 | K10: {=INDEX(Assumptions!$C$61:$F$61,MATCH(YEAR(K$3),Assumptions!$C$1:$F$1,0))*IF(ISNUMBER(SEARCH("yr",Assumptions!$G$61)),1/12,1)} -> 250 | L10: {=INDEX(Assumptions!$C$61:$F$61,MATCH(YEAR(L$3),Assumptions!$C$1:$F$1,0))*IF(ISNUMBER(SEARCH("yr",Assumptions!$G$61)),1/12,1)} -> 250 | M10: {=INDEX(Assumptions!$C$61:$F$61,MATCH(YEAR(M$3),Assumptions!$C$1:$F$1,0))*IF(ISNUMBER(SEARCH("yr",Assumptions!$G$61)),1/12,1)} -> 250 | ... BA10: {=INDEX(Assumptions!$C$61:$F$61,MATCH(YEAR(BA$3),Assumptions!$C$1:$F$1,0))*IF(ISNUMBER(SEARCH("yr",Assumptions!$G$61)),1/12,1)} -> 500 | BC10: =SUMPRODUCT((YEAR($F$3:$BA$3)=BC$3)*$F10:$BA10) -> 3000 | BD10: =SUMPRODUCT((YEAR($F$3:$BA$3)=BD$3)*$F10:$BA10) -> 4000 | BE10: =SUMPRODUCT((YEAR($F$3:$BA$3)=BE$3)*$F10:$BA10) -> 5000 | BF10: =SUMPRODUCT((YEAR($F$3:$BA$3)=BF$3)*$F10:$BA10) -> 6000
B11: Travel | E11: € | F11: {=INDEX(Assumptions!$C$62:$F$62,MATCH(YEAR(F$3),Assumptions!$C$1:$F$1,0))*IF(ISNUMBER(SEARCH("yr",Assumptions!$G$62)),1/12,1)} -> 500 | G11: {=INDEX(Assumptions!$C$62:$F$62,MATCH(YEAR(G$3),Assumptions!$C$1:$F$1,0))*IF(ISNUMBER(SEARCH("yr",Assumptions!$G$62)),1/12,1)} -> 500 | H11: {=INDEX(Assumptions!$C$62:$F$62,MATCH(YEAR(H$3),Assumptions!$C$1:$F$1,0))*IF(ISNUMBER(SEARCH("yr",Assumptions!$G$62)),1/12,1)} -> 500 | I11: {=INDEX(Assumptions!$C$62:$F$62,MATCH(YEAR(I$3),Assumptions!$C$1:$F$1,0))*IF(ISNUMBER(SEARCH("yr",Assumptions!$G$62)),1/12,1)} -> 500 | J11: {=INDEX(Assumptions!$C$62:$F$62,MATCH(YEAR(J$3),Assumptions!$C$1:$F$1,0))*IF(ISNUMBER(SEARCH("yr",Assumptions!$G$62)),1/12,1)} -> 500 | K11: {=INDEX(Assumptions!$C$62:$F$62,MATCH(YEAR(K$3),Assumptions!$C$1:$F$1,0))*IF(ISNUMBER(SEARCH("yr",Assumptions!$G$62)),1/12,1)} -> 500 | L11: {=INDEX(Assumptions!$C$62:$F$62,MATCH(YEAR(L$3),Assumptions!$C$1:$F$1,0))*IF(ISNUMBER(SEARCH("yr",Assumptions!$G$62)),1/12,1)} -> 500 | M11: {=INDEX(Assumptions!$C$62:$F$62,MATCH(YEAR(M$3),Assumptions!$C$1:$F$1,0))*IF(ISNUMBER(SEARCH("yr",Assumptions!$G$62)),1/12,1)} -> 500 | ... BA11: {=INDEX(Assumptions!$C$62:$F$62,MATCH(YEAR(BA$3),Assumptions!$C$1:$F$1,0))*IF(ISNUMBER(SEARCH("yr",Assumptions!$G$62)),1/12,1)} -> 625 | BC11: =SUMPRODUCT((YEAR($F$3:$BA$3)=BC$3)*$F11:$BA11) -> 6000 | BD11: =SUMPRODUCT((YEAR($F$3:$BA$3)=BD$3)*$F11:$BA11) -> 6500 | BE11: =SUMPRODUCT((YEAR($F$3:$BA$3)=BE$3)*$F11:$BA11) -> 7000 | BF11: =SUMPRODUCT((YEAR($F$3:$BA$3)=BF$3)*$F11:$BA11) -> 7500
B12: SG&A (F&B) | E12: € | F12: =Personnel!F17*Assumptions!$C$60*IF(ISNUMBER(SEARCH("yr",Assumptions!$G$60)),1/12,1) -> 900 | G12: =Personnel!G17*Assumptions!$C$60*IF(ISNUMBER(SEARCH("yr",Assumptions!$G$60)),1/12,1) -> 900 | H12: =Personnel!H17*Assumptions!$C$60*IF(ISNUMBER(SEARCH("yr",Assumptions!$G$60)),1/12,1) -> 900 | I12: =Personnel!I17*Assumptions!$C$60*IF(ISNUMBER(SEARCH("yr",Assumptions!$G$60)),1/12,1) -> 900 | J12: =Personnel!J17*Assumptions!$C$60*IF(ISNUMBER(SEARCH("yr",Assumptions!$G$60)),1/12,1) -> 900 | K12: =Personnel!K17*Assumptions!$C$60*IF(ISNUMBER(SEARCH("yr",Assumptions!$G$60)),1/12,1) -> 1000 | L12: =Personnel!L17*Assumptions!$C$60*IF(ISNUMBER(SEARCH("yr",Assumptions!$G$60)),1/12,1) -> 1000 | M12: =Personnel!M17*Assumptions!$C$60*IF(ISNUMBER(SEARCH("yr",Assumptions!$G$60)),1/12,1) -> 1000 | ... BA12: =Personnel!BA17*Assumptions!$C$60*IF(ISNUMBER(SEARCH("yr",Assumptions!$G$60)),1/12,1) -> 1700 | BC12: =SUMPRODUCT((YEAR($F$3:$BA$3)=BC$3)*$F12:$BA12) -> 11500 | BD12: =SUMPRODUCT((YEAR($F$3:$BA$3)=BD$3)*$F12:$BA12) -> 13200 | BE12: =SUMPRODUCT((YEAR($F$3:$BA$3)=BE$3)*$F12:$BA12) -> 17500 | BF12: =SUMPRODUCT((YEAR($F$3:$BA$3)=BF$3)*$F12:$BA12) -> 19200
B13: Hosting & product | E13: € | F13: ='Revenue forecast'!F28*Assumptions!$C$23+Assumptions!$C$24 -> 580 | G13: ='Revenue forecast'!G28*Assumptions!$C$23+Assumptions!$C$24 -> 620 | H13: ='Revenue forecast'!H28*Assumptions!$C$23+Assumptions!$C$24 -> 640 | I13: ='Revenue forecast'!I28*Assumptions!$C$23+Assumptions!$C$24 -> 659.26306 | J13: ='Revenue forecast'!J28*Assumptions!$C$23+Assumptions!$C$24 -> 678.5397 | K13: ='Revenue forecast'!K28*Assumptions!$C$23+Assumptions!$C$24 -> 717.46119 | L13: ='Revenue forecast'!L28*Assumptions!$C$23+Assumptions!$C$24 -> 736.03409 | M13: ='Revenue forecast'!M28*Assumptions!$C$23+Assumptions!$C$24 -> 754.26481 | ... BA13: ='Revenue forecast'!BA28*Assumptions!$C$23+Assumptions!$C$24 -> 3175.8253 | BC13: =SUMPRODUCT((YEAR($F$3:$BA$3)=BC$3)*$F13:$BA13) -> 8637.2188 | BD13: =SUMPRODUCT((YEAR($F$3:$BA$3)=BD$3)*$F13:$BA13) -> 12310.213 | BE13: =SUMPRODUCT((YEAR($F$3:$BA$3)=BE$3)*$F13:$BA13) -> 20711.721 | BF13: =SUMPRODUCT((YEAR($F$3:$BA$3)=BF$3)*$F13:$BA13) -> 32821.331
B14: Other | E14: € | F14: =Assumptions!$C$64*IF(ISNUMBER(SEARCH("yr",Assumptions!$G$64)),1/12,1) -> 140 | G14: =Assumptions!$C$64*IF(ISNUMBER(SEARCH("yr",Assumptions!$G$64)),1/12,1) -> 140 | H14: =Assumptions!$C$64*IF(ISNUMBER(SEARCH("yr",Assumptions!$G$64)),1/12,1) -> 140 | I14: =Assumptions!$C$64*IF(ISNUMBER(SEARCH("yr",Assumptions!$G$64)),1/12,1) -> 140 | J14: =Assumptions!$C$64*IF(ISNUMBER(SEARCH("yr",Assumptions!$G$64)),1/12,1) -> 140 | K14: =Assumptions!$C$64*IF(ISNUMBER(SEARCH("yr",Assumptions!$G$64)),1/12,1) -> 140 | L14: =Assumptions!$C$64*IF(ISNUMBER(SEARCH("yr",Assumptions!$G$64)),1/12,1) -> 140 | M14: =Assumptions!$C$64*IF(ISNUMBER(SEARCH("yr",Assumptions!$G$64)),1/12,1) -> 140 | ... BA14: =Assumptions!$C$64*IF(ISNUMBER(SEARCH("yr",Assumptions!$G$64)),1/12,1) -> 140 | BC14: =SUMPRODUCT((YEAR($F$3:$BA$3)=BC$3)*$F14:$BA14) -> 1680 | BD14: =SUMPRODUCT((YEAR($F$3:$BA$3)=BD$3)*$F14:$BA14) -> 1680 | BE14: =SUMPRODUCT((YEAR($F$3:$BA$3)=BE$3)*$F14:$BA14) -> 1680 | BF14: =SUMPRODUCT((YEAR($F$3:$BA$3)=BF$3)*$F14:$BA14) -> 1680
B15: RX allocation | E15: € | F15: =Assumptions!$C$63*IF(ISNUMBER(SEARCH("yr",Assumptions!$G$63)),1/12,1) -> 1307 | G15: =Assumptions!$C$63*IF(ISNUMBER(SEARCH("yr",Assumptions!$G$63)),1/12,1) -> 1307 | H15: =Assumptions!$C$63*IF(ISNUMBER(SEARCH("yr",Assumptions!$G$63)),1/12,1) -> 1307 | I15: =Assumptions!$C$63*IF(ISNUMBER(SEARCH("yr",Assumptions!$G$63)),1/12,1) -> 1307 | J15: =Assumptions!$C$63*IF(ISNUMBER(SEARCH("yr",Assumptions!$G$63)),1/12,1) -> 1307 | K15: =Assumptions!$C$63*IF(ISNUMBER(SEARCH("yr",Assumptions!$G$63)),1/12,1) -> 1307 | L15: =Assumptions!$C$63*IF(ISNUMBER(SEARCH("yr",Assumptions!$G$63)),1/12,1) -> 1307 | M15: =Assumptions!$C$63*IF(ISNUMBER(SEARCH("yr",Assumptions!$G$63)),1/12,1) -> 1307 | ... BA15: =Assumptions!$C$63*IF(ISNUMBER(SEARCH("yr",Assumptions!$G$63)),1/12,1) -> 1307 | BC15: =SUMPRODUCT((YEAR($F$3:$BA$3)=BC$3)*$F15:$BA15) -> 15684 | BD15: =SUMPRODUCT((YEAR($F$3:$BA$3)=BD$3)*$F15:$BA15) -> 15684 | BE15: =SUMPRODUCT((YEAR($F$3:$BA$3)=BE$3)*$F15:$BA15) -> 15684 | BF15: =SUMPRODUCT((YEAR($F$3:$BA$3)=BF$3)*$F15:$BA15) -> 15684
B16: Total other OPEX | E16: € | F16: =SUM(F7:F15) -> 13850.333 | G16: =SUM(G7:G15) -> 13890.333 | H16: =SUM(H7:H15) -> 13910.333 | I16: =SUM(I7:I15) -> 13929.596 | J16: =SUM(J7:J15) -> 13948.873 | K16: =SUM(K7:K15) -> 14847.795 | L16: =SUM(L7:L15) -> 14866.367 | M16: =SUM(M7:M15) -> 14884.598 | ... BA16: =SUM(BA7:BA15) -> 25367.825 | BC16: =SUMPRODUCT((YEAR($F$3:$BA$3)=BC$3)*$F16:$BA16) -> 173901.22 | BD16: =SUMPRODUCT((YEAR($F$3:$BA$3)=BD$3)*$F16:$BA16) -> 203694.21 | BE16: =SUMPRODUCT((YEAR($F$3:$BA$3)=BE$3)*$F16:$BA16) -> 260575.72 | BF16: =SUMPRODUCT((YEAR($F$3:$BA$3)=BF$3)*$F16:$BA16) -> 288805.33

Sheet Financial Statements
B1: Income Statement, 2027–2030 (€)
C2: 46388 | D2: 46419 | E2: 46447 | F2: 46478 | G2: 46508 | H2: 46539 | I2: 46569 | J2: 46600 | K2: 46631 | L2: 46661 | M2: 46692 | N2: 46722 | O2: 46753 | P2: 46784 | Q2: 46813 | R2: 46844 | S2: 46874 | T2: 46905 | U2: 46935 | V2: 46966 | W2: 46997 | X2: 47027 | Y2: 47058 | Z2: 47088 | AA2: 47119 | AB2: 47150 | AC2: 47178 | AD2: 47209 | AE2: 47239 | AF2: 47270 | AG2: 47300 | AH2: 47331 | AI2: 47362 | AJ2: 47392 | AK2: 47423 | AL2: 47453 | AM2: 47484 | AN2: 47515 | AO2: 47543 | AP2: 47574 | AQ2: 47604 | AR2: 47635 | AS2: 47665 | AT2: 47696 | AU2: 47727 | AV2: 47757 | AW2: 47788 | AX2: 47818 | AZ2: 2027 | BA2: 2028 | BB2: 2029 | BC2: 2030
B4: Revenues
B5: Retainer | C5: ='Revenue forecast'!F34 -> 26000 | D5: ='Revenue forecast'!G34 -> 40000 | E5: ='Revenue forecast'!H34 -> 33500 | F5: ='Revenue forecast'!I34 -> 40000 | G5: ='Revenue forecast'!J34 -> 41000 | H5: ='Revenue forecast'!K34 -> 48500 | I5: ='Revenue forecast'!L34 -> 48500 | J5: ='Revenue forecast'!M34 -> 48500 | ... AX5: ='Revenue forecast'!BA34 -> 116000 | AZ5: =SUMPRODUCT((YEAR($C$2:$AX$2)=AZ$2)*$C5:$AX5) -> 524500 | BA5: =SUMPRODUCT((YEAR($C$2:$AX$2)=BA$2)*$C5:$AX5) -> 788000 | BB5: =SUMPRODUCT((YEAR($C$2:$AX$2)=BB$2)*$C5:$AX5) -> 1081000 | BC5: =SUMPRODUCT((YEAR($C$2:$AX$2)=BC$2)*$C5:$AX5) -> 1399000
B6: Closing fees | C6: ='Revenue forecast'!F35 -> 0 | D6: ='Revenue forecast'!G35 -> 100000 | E6: ='Revenue forecast'!H35 -> 0 | F6: ='Revenue forecast'!I35 -> 0 | G6: ='Revenue forecast'!J35 -> 0 | H6: ='Revenue forecast'!K35 -> 20000 | I6: ='Revenue forecast'!L35 -> 20000 | J6: ='Revenue forecast'!M35 -> 20000 | ... AX6: ='Revenue forecast'!BA35 -> 936000 | AZ6: =SUMPRODUCT((YEAR($C$2:$AX$2)=AZ$2)*$C6:$AX6) -> 460000 | BA6: =SUMPRODUCT((YEAR($C$2:$AX$2)=BA$2)*$C6:$AX6) -> 1428000 | BB6: =SUMPRODUCT((YEAR($C$2:$AX$2)=BB$2)*$C6:$AX6) -> 3203200 | BC6: =SUMPRODUCT((YEAR($C$2:$AX$2)=BC$2)*$C6:$AX6) -> 6996000
B7: Software | C7: ='Revenue forecast'!F36 -> 2000 | D7: ='Revenue forecast'!G36 -> 3000 | E7: ='Revenue forecast'!H36 -> 3500 | F7: ='Revenue forecast'!I36 -> 3981.5765 | G7: ='Revenue forecast'!J36 -> 4463.4925 | H7: ='Revenue forecast'!K36 -> 5436.5299 | I7: ='Revenue forecast'!L36 -> 5900.8523 | J7: ='Revenue forecast'!M36 -> 6356.6202 | ... AX7: ='Revenue forecast'!BA36 -> 66895.632 | AZ7: =SUMPRODUCT((YEAR($C$2:$AX$2)=AZ$2)*$C7:$AX7) -> 65930.47 | BA7: =SUMPRODUCT((YEAR($C$2:$AX$2)=BA$2)*$C7:$AX7) -> 157755.32 | BB7: =SUMPRODUCT((YEAR($C$2:$AX$2)=BB$2)*$C7:$AX7) -> 367793.02 | BC7: =SUMPRODUCT((YEAR($C$2:$AX$2)=BC$2)*$C7:$AX7) -> 670533.27
B8: Less: industry-partner share | C8: ='Revenue forecast'!F38 -> -1950 | D8: ='Revenue forecast'!G38 -> -10500 | E8: ='Revenue forecast'!H38 -> -2512.5 | F8: ='Revenue forecast'!I38 -> -3000 | G8: ='Revenue forecast'!J38 -> -3075 | H8: ='Revenue forecast'!K38 -> -5137.5 | I8: ='Revenue forecast'!L38 -> -5137.5 | J8: ='Revenue forecast'!M38 -> -5137.5 | ... AX8: ='Revenue forecast'!BA38 -> -78900 | AZ8: =SUMPRODUCT((YEAR($C$2:$AX$2)=AZ$2)*$C8:$AX8) -> -73837.5 | BA8: =SUMPRODUCT((YEAR($C$2:$AX$2)=BA$2)*$C8:$AX8) -> -166200 | BB8: =SUMPRODUCT((YEAR($C$2:$AX$2)=BB$2)*$C8:$AX8) -> -321315 | BC8: =SUMPRODUCT((YEAR($C$2:$AX$2)=BC$2)*$C8:$AX8) -> -629625
B9: Total revenues | C9: =C5+C6+C7+C8 -> 26050 | D9: =D5+D6+D7+D8 -> 132500 | E9: =E5+E6+E7+E8 -> 34487.5 | F9: =F5+F6+F7+F8 -> 40981.577 | G9: =G5+G6+G7+G8 -> 42388.492 | H9: =H5+H6+H7+H8 -> 68799.03 | I9: =I5+I6+I7+I8 -> 69263.352 | J9: =J5+J6+J7+J8 -> 69719.12 | ... AX9: =AX5+AX6+AX7+AX8 -> 1039995.6 | AZ9: =AZ5+AZ6+AZ7+AZ8 -> 976592.97 | BA9: =BA5+BA6+BA7+BA8 -> 2207555.3 | BB9: =BB5+BB6+BB7+BB8 -> 4330678 | BC9: =BC5+BC6+BC7+BC8 -> 8435908.3
B11: Personnel
B12: Gross salary | C12: =Personnel!F21+Personnel!F24 -> 41500 | D12: =Personnel!G21+Personnel!G24 -> 41500 | E12: =Personnel!H21+Personnel!H24 -> 41500 | F12: =Personnel!I21+Personnel!I24 -> 41500 | G12: =Personnel!J21+Personnel!J24 -> 41500 | H12: =Personnel!K21+Personnel!K24 -> 44500 | I12: =Personnel!L21+Personnel!L24 -> 44500 | J12: =Personnel!M21+Personnel!M24 -> 44500 | ... AX12: =Personnel!BA21+Personnel!BA24 -> 99100 | AZ12: =SUMPRODUCT((YEAR($C$2:$AX$2)=AZ$2)*$C12:$AX12) -> 519000 | BA12: =SUMPRODUCT((YEAR($C$2:$AX$2)=BA$2)*$C12:$AX12) -> 659400 | BB12: =SUMPRODUCT((YEAR($C$2:$AX$2)=BB$2)*$C12:$AX12) -> 965300 | BC12: =SUMPRODUCT((YEAR($C$2:$AX$2)=BC$2)*$C12:$AX12) -> 1138200
B13: Bonus | C13: =Personnel!F25 -> 0 | D13: =Personnel!G25 -> 35797.5 | E13: =Personnel!H25 -> 0 | F13: =Personnel!I25 -> 0 | G13: =Personnel!J25 -> 0 | H13: =Personnel!K25 -> 7159.5 | I13: =Personnel!L25 -> 7159.5 | J13: =Personnel!M25 -> 7159.5 | ... AX13: =Personnel!BA25 -> 337315.68 | AZ13: =SUMPRODUCT((YEAR($C$2:$AX$2)=AZ$2)*$C13:$AX13) -> 164668.5 | BA13: =SUMPRODUCT((YEAR($C$2:$AX$2)=BA$2)*$C13:$AX13) -> 512509.2 | BB13: =SUMPRODUCT((YEAR($C$2:$AX$2)=BB$2)*$C13:$AX13) -> 1151998.8 | BC13: =SUMPRODUCT((YEAR($C$2:$AX$2)=BC$2)*$C13:$AX13) -> 2521218.5
B14: Employer taxes | C14: =Personnel!F22+Personnel!F23 -> 9982 | D14: =Personnel!G22+Personnel!G23 -> 9982 | E14: =Personnel!H22+Personnel!H23 -> 9982 | F14: =Personnel!I22+Personnel!I23 -> 9982 | G14: =Personnel!J22+Personnel!J23 -> 9982 | H14: =Personnel!K22+Personnel!K23 -> 10837.6 | I14: =Personnel!L22+Personnel!L23 -> 10837.6 | J14: =Personnel!M22+Personnel!M23 -> 10837.6 | ... AX14: =Personnel!BA22+Personnel!BA23 -> 25981.72 | AZ14: =SUMPRODUCT((YEAR($C$2:$AX$2)=AZ$2)*$C14:$AX14) -> 125773.2 | BA14: =SUMPRODUCT((YEAR($C$2:$AX$2)=BA$2)*$C14:$AX14) -> 164104.08 | BB14: =SUMPRODUCT((YEAR($C$2:$AX$2)=BB$2)*$C14:$AX14) -> 249635.56 | BC14: =SUMPRODUCT((YEAR($C$2:$AX$2)=BC$2)*$C14:$AX14) -> 297235.44
B15: Contractors | C15: =Personnel!F26 -> 0 | D15: =Personnel!G26 -> 0 | E15: =Personnel!H26 -> 0 | F15: =Personnel!I26 -> 0 | G15: =Personnel!J26 -> 0 | H15: =Personnel!K26 -> 0 | I15: =Personnel!L26 -> 0 | J15: =Personnel!M26 -> 0 | ... AX15: =Personnel!BA26 -> 0 | AZ15: =SUMPRODUCT((YEAR($C$2:$AX$2)=AZ$2)*$C15:$AX15) -> 0 | BA15: =SUMPRODUCT((YEAR($C$2:$AX$2)=BA$2)*$C15:$AX15) -> 0 | BB15: =SUMPRODUCT((YEAR($C$2:$AX$2)=BB$2)*$C15:$AX15) -> 0 | BC15: =SUMPRODUCT((YEAR($C$2:$AX$2)=BC$2)*$C15:$AX15) -> 0
B16: Strategic Advisory costs | C16: 0 | D16: 0 | E16: 0 | F16: 0 | G16: 0 | H16: 0 | I16: 0 | J16: 0 | K16: 0 | L16: 0 | M16: 0 | N16: 0 | O16: 0 | P16: 0 | Q16: 0 | R16: 0 | S16: 0 | T16: 0 | U16: 0 | V16: 0 | W16: 0 | X16: 0 | Y16: 0 | Z16: 0 | AA16: 0 | AB16: 0 | AC16: 0 | AD16: 0 | AE16: 0 | AF16: 0 | AG16: 0 | AH16: 0 | AI16: 0 | AJ16: 0 | AK16: 0 | AL16: 0 | AM16: 0 | AN16: 0 | AO16: 0 | AP16: 0 | AQ16: 0 | AR16: 0 | AS16: 0 | AT16: 0 | AU16: 0 | AV16: 0 | AW16: 0 | AX16: 0 | AZ16: =SUMPRODUCT((YEAR($C$2:$AX$2)=AZ$2)*$C16:$AX16) -> 0 | BA16: =SUMPRODUCT((YEAR($C$2:$AX$2)=BA$2)*$C16:$AX16) -> 0 | BB16: =SUMPRODUCT((YEAR($C$2:$AX$2)=BB$2)*$C16:$AX16) -> 0 | BC16: =SUMPRODUCT((YEAR($C$2:$AX$2)=BC$2)*$C16:$AX16) -> 0
B17: Other people costs | C17: =Personnel!F27 -> 267 | D17: =Personnel!G27 -> 267 | E17: =Personnel!H27 -> 267 | F17: =Personnel!I27 -> 267 | G17: =Personnel!J27 -> 267 | H17: =Personnel!K27 -> 267 | I17: =Personnel!L27 -> 267 | J17: =Personnel!M27 -> 267 | ... AX17: =Personnel!BA27 -> 267 | AZ17: =SUMPRODUCT((YEAR($C$2:$AX$2)=AZ$2)*$C17:$AX17) -> 3204 | BA17: =SUMPRODUCT((YEAR($C$2:$AX$2)=BA$2)*$C17:$AX17) -> 3204 | BB17: =SUMPRODUCT((YEAR($C$2:$AX$2)=BB$2)*$C17:$AX17) -> 3204 | BC17: =SUMPRODUCT((YEAR($C$2:$AX$2)=BC$2)*$C17:$AX17) -> 3204
B18: Total personnel | C18: =SUM(C12:C17) -> 51749 | D18: =SUM(D12:D17) -> 87546.5 | E18: =SUM(E12:E17) -> 51749 | F18: =SUM(F12:F17) -> 51749 | G18: =SUM(G12:G17) -> 51749 | H18: =SUM(H12:H17) -> 62764.1 | I18: =SUM(I12:I17) -> 62764.1 | J18: =SUM(J12:J17) -> 62764.1 | ... AX18: =SUM(AX12:AX17) -> 462664.4 | AZ18: =SUMPRODUCT((YEAR($C$2:$AX$2)=AZ$2)*$C18:$AX18) -> 812645.7 | BA18: =SUMPRODUCT((YEAR($C$2:$AX$2)=BA$2)*$C18:$AX18) -> 1339217.3 | BB18: =SUMPRODUCT((YEAR($C$2:$AX$2)=BB$2)*$C18:$AX18) -> 2370138.4 | BC18: =SUMPRODUCT((YEAR($C$2:$AX$2)=BC$2)*$C18:$AX18) -> 3959857.9
B20: Gross profit | C20: =C9-C18 -> -25699 | D20: =D9-D18 -> 44953.5 | E20: =E9-E18 -> -17261.5 | F20: =F9-F18 -> -10767.423 | G20: =G9-G18 -> -9360.5075 | H20: =H9-H18 -> 6034.9299 | I20: =I9-I18 -> 6499.2523 | J20: =J9-J18 -> 6955.0202 | ... AX20: =AX9-AX18 -> 577331.23 | AZ20: =SUMPRODUCT((YEAR($C$2:$AX$2)=AZ$2)*$C20:$AX20) -> 163947.27 | BA20: =SUMPRODUCT((YEAR($C$2:$AX$2)=BA$2)*$C20:$AX20) -> 868338.04 | BB20: =SUMPRODUCT((YEAR($C$2:$AX$2)=BB$2)*$C20:$AX20) -> 1960539.6 | BC20: =SUMPRODUCT((YEAR($C$2:$AX$2)=BC$2)*$C20:$AX20) -> 4476050.3
B22: Other OPEX
B23: Rent | C23: =OPEX!F7 -> 5400 | D23: =OPEX!G7 -> 5400 | E23: =OPEX!H7 -> 5400 | F23: =OPEX!I7 -> 5400 | G23: =OPEX!J7 -> 5400 | H23: =OPEX!K7 -> 6000 | I23: =OPEX!L7 -> 6000 | J23: =OPEX!M7 -> 6000 | ... AX23: =OPEX!BA7 -> 10200 | AZ23: =SUMPRODUCT((YEAR($C$2:$AX$2)=AZ$2)*$C23:$AX23) -> 69000 | BA23: =SUMPRODUCT((YEAR($C$2:$AX$2)=BA$2)*$C23:$AX23) -> 79200 | BB23: =SUMPRODUCT((YEAR($C$2:$AX$2)=BB$2)*$C23:$AX23) -> 105000 | BC23: =SUMPRODUCT((YEAR($C$2:$AX$2)=BC$2)*$C23:$AX23) -> 115200
B24: Software | C24: =OPEX!F8 -> 4413.3333 | D24: =OPEX!G8 -> 4413.3333 | E24: =OPEX!H8 -> 4413.3333 | F24: =OPEX!I8 -> 4413.3333 | G24: =OPEX!J8 -> 4413.3333 | H24: =OPEX!K8 -> 4533.3333 | I24: =OPEX!L8 -> 4533.3333 | J24: =OPEX!M8 -> 4533.3333 | ... AX24: =OPEX!BA8 -> 7040 | AZ24: =SUMPRODUCT((YEAR($C$2:$AX$2)=AZ$2)*$C24:$AX24) -> 53800 | BA24: =SUMPRODUCT((YEAR($C$2:$AX$2)=BA$2)*$C24:$AX24) -> 65840 | BB24: =SUMPRODUCT((YEAR($C$2:$AX$2)=BB$2)*$C24:$AX24) -> 81000 | BC24: =SUMPRODUCT((YEAR($C$2:$AX$2)=BC$2)*$C24:$AX24) -> 83040
B25: Office | C25: =OPEX!F9 -> 360 | D25: =OPEX!G9 -> 360 | E25: =OPEX!H9 -> 360 | F25: =OPEX!I9 -> 360 | G25: =OPEX!J9 -> 360 | H25: =OPEX!K9 -> 400 | I25: =OPEX!L9 -> 400 | J25: =OPEX!M9 -> 400 | ... AX25: =OPEX!BA9 -> 680 | AZ25: =SUMPRODUCT((YEAR($C$2:$AX$2)=AZ$2)*$C25:$AX25) -> 4600 | BA25: =SUMPRODUCT((YEAR($C$2:$AX$2)=BA$2)*$C25:$AX25) -> 5280 | BB25: =SUMPRODUCT((YEAR($C$2:$AX$2)=BB$2)*$C25:$AX25) -> 7000 | BC25: =SUMPRODUCT((YEAR($C$2:$AX$2)=BC$2)*$C25:$AX25) -> 7680
B26: Marketing & Sales | C26: =OPEX!F10 -> 250 | D26: =OPEX!G10 -> 250 | E26: =OPEX!H10 -> 250 | F26: =OPEX!I10 -> 250 | G26: =OPEX!J10 -> 250 | H26: =OPEX!K10 -> 250 | I26: =OPEX!L10 -> 250 | J26: =OPEX!M10 -> 250 | ... AX26: =OPEX!BA10 -> 500 | AZ26: =SUMPRODUCT((YEAR($C$2:$AX$2)=AZ$2)*$C26:$AX26) -> 3000 | BA26: =SUMPRODUCT((YEAR($C$2:$AX$2)=BA$2)*$C26:$AX26) -> 4000 | BB26: =SUMPRODUCT((YEAR($C$2:$AX$2)=BB$2)*$C26:$AX26) -> 5000 | BC26: =SUMPRODUCT((YEAR($C$2:$AX$2)=BC$2)*$C26:$AX26) -> 6000
B27: Travel | C27: =OPEX!F11 -> 500 | D27: =OPEX!G11 -> 500 | E27: =OPEX!H11 -> 500 | F27: =OPEX!I11 -> 500 | G27: =OPEX!J11 -> 500 | H27: =OPEX!K11 -> 500 | I27: =OPEX!L11 -> 500 | J27: =OPEX!M11 -> 500 | ... AX27: =OPEX!BA11 -> 625 | AZ27: =SUMPRODUCT((YEAR($C$2:$AX$2)=AZ$2)*$C27:$AX27) -> 6000 | BA27: =SUMPRODUCT((YEAR($C$2:$AX$2)=BA$2)*$C27:$AX27) -> 6500 | BB27: =SUMPRODUCT((YEAR($C$2:$AX$2)=BB$2)*$C27:$AX27) -> 7000 | BC27: =SUMPRODUCT((YEAR($C$2:$AX$2)=BC$2)*$C27:$AX27) -> 7500
B28: SG&A | C28: =OPEX!F12 -> 900 | D28: =OPEX!G12 -> 900 | E28: =OPEX!H12 -> 900 | F28: =OPEX!I12 -> 900 | G28: =OPEX!J12 -> 900 | H28: =OPEX!K12 -> 1000 | I28: =OPEX!L12 -> 1000 | J28: =OPEX!M12 -> 1000 | ... AX28: =OPEX!BA12 -> 1700 | AZ28: =SUMPRODUCT((YEAR($C$2:$AX$2)=AZ$2)*$C28:$AX28) -> 11500 | BA28: =SUMPRODUCT((YEAR($C$2:$AX$2)=BA$2)*$C28:$AX28) -> 13200 | BB28: =SUMPRODUCT((YEAR($C$2:$AX$2)=BB$2)*$C28:$AX28) -> 17500 | BC28: =SUMPRODUCT((YEAR($C$2:$AX$2)=BC$2)*$C28:$AX28) -> 19200
B29: Hosting & product | C29: =OPEX!F13 -> 580 | D29: =OPEX!G13 -> 620 | E29: =OPEX!H13 -> 640 | F29: =OPEX!I13 -> 659.26306 | G29: =OPEX!J13 -> 678.5397 | H29: =OPEX!K13 -> 717.46119 | I29: =OPEX!L13 -> 736.03409 | J29: =OPEX!M13 -> 754.26481 | ... AX29: =OPEX!BA13 -> 3175.8253 | AZ29: =SUMPRODUCT((YEAR($C$2:$AX$2)=AZ$2)*$C29:$AX29) -> 8637.2188 | BA29: =SUMPRODUCT((YEAR($C$2:$AX$2)=BA$2)*$C29:$AX29) -> 12310.213 | BB29: =SUMPRODUCT((YEAR($C$2:$AX$2)=BB$2)*$C29:$AX29) -> 20711.721 | BC29: =SUMPRODUCT((YEAR($C$2:$AX$2)=BC$2)*$C29:$AX29) -> 32821.331
B30: Other | C30: =OPEX!F14 -> 140 | D30: =OPEX!G14 -> 140 | E30: =OPEX!H14 -> 140 | F30: =OPEX!I14 -> 140 | G30: =OPEX!J14 -> 140 | H30: =OPEX!K14 -> 140 | I30: =OPEX!L14 -> 140 | J30: =OPEX!M14 -> 140 | ... AX30: =OPEX!BA14 -> 140 | AZ30: =SUMPRODUCT((YEAR($C$2:$AX$2)=AZ$2)*$C30:$AX30) -> 1680 | BA30: =SUMPRODUCT((YEAR($C$2:$AX$2)=BA$2)*$C30:$AX30) -> 1680 | BB30: =SUMPRODUCT((YEAR($C$2:$AX$2)=BB$2)*$C30:$AX30) -> 1680 | BC30: =SUMPRODUCT((YEAR($C$2:$AX$2)=BC$2)*$C30:$AX30) -> 1680
B31: Total other OPEX | C31: =SUM(C23:C30) -> 12543.333 | D31: =SUM(D23:D30) -> 12583.333 | E31: =SUM(E23:E30) -> 12603.333 | F31: =SUM(F23:F30) -> 12622.596 | G31: =SUM(G23:G30) -> 12641.873 | H31: =SUM(H23:H30) -> 13540.795 | I31: =SUM(I23:I30) -> 13559.367 | J31: =SUM(J23:J30) -> 13577.598 | ... AX31: =SUM(AX23:AX30) -> 24060.825 | AZ31: =SUMPRODUCT((YEAR($C$2:$AX$2)=AZ$2)*$C31:$AX31) -> 158217.22 | BA31: =SUMPRODUCT((YEAR($C$2:$AX$2)=BA$2)*$C31:$AX31) -> 188010.21 | BB31: =SUMPRODUCT((YEAR($C$2:$AX$2)=BB$2)*$C31:$AX31) -> 244891.72 | BC31: =SUMPRODUCT((YEAR($C$2:$AX$2)=BC$2)*$C31:$AX31) -> 273121.33
B33: RX allocation | C33: =OPEX!F15 -> 1307 | D33: =OPEX!G15 -> 1307 | E33: =OPEX!H15 -> 1307 | F33: =OPEX!I15 -> 1307 | G33: =OPEX!J15 -> 1307 | H33: =OPEX!K15 -> 1307 | I33: =OPEX!L15 -> 1307 | J33: =OPEX!M15 -> 1307 | ... AX33: =OPEX!BA15 -> 1307 | AZ33: =SUMPRODUCT((YEAR($C$2:$AX$2)=AZ$2)*$C33:$AX33) -> 15684 | BA33: =SUMPRODUCT((YEAR($C$2:$AX$2)=BA$2)*$C33:$AX33) -> 15684 | BB33: =SUMPRODUCT((YEAR($C$2:$AX$2)=BB$2)*$C33:$AX33) -> 15684 | BC33: =SUMPRODUCT((YEAR($C$2:$AX$2)=BC$2)*$C33:$AX33) -> 15684
B35: Total costs | C35: =C18+C31+C33 -> 65599.333 | D35: =D18+D31+D33 -> 101436.83 | E35: =E18+E31+E33 -> 65659.333 | F35: =F18+F31+F33 -> 65678.596 | G35: =G18+G31+G33 -> 65697.873 | H35: =H18+H31+H33 -> 77611.895 | I35: =I18+I31+I33 -> 77630.467 | J35: =J18+J31+J33 -> 77648.698 | ... AX35: =AX18+AX31+AX33 -> 488032.23 | AZ35: =SUMPRODUCT((YEAR($C$2:$AX$2)=AZ$2)*$C35:$AX35) -> 986546.92 | BA35: =SUMPRODUCT((YEAR($C$2:$AX$2)=BA$2)*$C35:$AX35) -> 1542911.5 | BB35: =SUMPRODUCT((YEAR($C$2:$AX$2)=BB$2)*$C35:$AX35) -> 2630714.1 | BC35: =SUMPRODUCT((YEAR($C$2:$AX$2)=BC$2)*$C35:$AX35) -> 4248663.3
B37: EBITDA (total) | C37: =C9-C35 -> -39549.333 | D37: =D9-D35 -> 31063.167 | E37: =E9-E35 -> -31171.833 | F37: =F9-F35 -> -24697.02 | G37: =G9-G35 -> -23309.381 | H37: =H9-H35 -> -8812.8647 | I37: =I9-I35 -> -8367.1152 | J37: =J9-J35 -> -7929.5779 | ... AX37: =AX9-AX35 -> 551963.41 | AZ37: =SUMPRODUCT((YEAR($C$2:$AX$2)=AZ$2)*$C37:$AX37) -> -9953.949 | BA37: =SUMPRODUCT((YEAR($C$2:$AX$2)=BA$2)*$C37:$AX37) -> 664643.83 | BB37: =SUMPRODUCT((YEAR($C$2:$AX$2)=BB$2)*$C37:$AX37) -> 1699963.9 | BC37: =SUMPRODUCT((YEAR($C$2:$AX$2)=BC$2)*$C37:$AX37) -> 4187245
B38: EBITDA margin (total) | C38: =IF(C9=0,0,C37/C9) -> -1.5182086 | D38: =IF(D9=0,0,D37/D9) -> 0.23443899 | E38: =IF(E9=0,0,E37/E9) -> -0.90385889 | F38: =IF(F9=0,0,F37/F9) -> -0.60263713 | G38: =IF(G9=0,0,G37/G9) -> -0.54989879 | H38: =IF(H9=0,0,H37/H9) -> -0.12809577 | I38: =IF(I9=0,0,I37/I9) -> -0.12080148 | J38: =IF(J9=0,0,J37/J9) -> -0.11373606 | ... AX38: =IF(AX9=0,0,AX37/AX9) -> 0.53073627 | AZ38: =IF(AZ9=0,0,AZ37/AZ9) -> -0.010192526 | BA38: =IF(BA9=0,0,BA37/BA9) -> 0.30107686 | BB38: =IF(BB9=0,0,BB37/BB9) -> 0.39253989 | BC38: =IF(BC9=0,0,BC37/BC9) -> 0.49635971
B40: EBITDA (without success fee) | C40: =C5+C7-C35+C13 -> -37599.333 | D40: =D5+D7-D35+D13 -> -22639.333 | E40: =E5+E7-E35+E13 -> -28659.333 | F40: =F5+F7-F35+F13 -> -21697.02 | G40: =G5+G7-G35+G13 -> -20234.381 | H40: =H5+H7-H35+H13 -> -16515.865 | I40: =I5+I7-I35+I13 -> -16070.115 | J40: =J5+J7-J35+J13 -> -15632.578 | ... AX40: =AX5+AX7-AX35+AX13 -> 32179.087 | AZ40: =AZ5+AZ7-AZ35+AZ13 -> -231447.95 | BA40: =BA5+BA7-BA35+BA13 -> -84646.97 | BB40: =BB5+BB7-BB35+BB13 -> -29922.262 | BC40: =BC5+BC7-BC35+BC13 -> 342088.5
B41: EBITDA margin (without success fee) | C41: =IF(C5=0,0,C40/C5) -> -1.4461282 | D41: =IF(D5=0,0,D40/D5) -> -0.56598333 | E41: =IF(E5=0,0,E40/E5) -> -0.85550249 | F41: =IF(F5=0,0,F40/F5) -> -0.5424255 | G41: =IF(G5=0,0,G40/G5) -> -0.49352148 | H41: =IF(H5=0,0,H40/H5) -> -0.34053329 | I41: =IF(I5=0,0,I40/I5) -> -0.33134258 | J41: =IF(J5=0,0,J40/J5) -> -0.32232119 | ... AX41: =IF(AX5=0,0,AX40/AX5) -> 0.27740592 | AZ41: =IF(AZ5=0,0,AZ40/AZ5) -> -0.4412735 | BA41: =IF(BA5=0,0,BA40/BA5) -> -0.10742001 | BB41: =IF(BB5=0,0,BB40/BB5) -> -0.027680168 | BC41: =IF(BC5=0,0,BC40/BC5) -> 0.24452359

Sheet Capital need
B1: Capital need — Evolute (€)
B2: Funding requirement · EBITDA-as-cash proxy · € · pre-model 2026 + FY2027–2030
B4: A · PRE-MODEL OUTLAYS (2026)
B5: Contract developer — rate / hour | C5: 120 | G5: €/hr
B6: days / week | C6: 2 | G6: days
B7: hours / day | C7: 8 | G7: hours
B8: weeks (job length) | C8: 13 | G8: weeks
B9: Contract developer cost | C9: =C5*C6*C7*C8 -> 24960 | G9: €
B10: Other pre-launch costs | G10: €
B11: Other pre-launch costs | G11: €
B12: Total pre-model outlays | C12: =C9+C10+C11 -> 24960 | G12: €
B14: B · OPERATING CASH NEED (2027+)
B15: EBITDA used as a cash proxy — no working capital or capex modelled; retainers bill monthly so WC drag is minimal.
E16: Unit | F16: ='Financial Statements'!C2 -> 46388 | G16: ='Financial Statements'!D2 -> 46419 | H16: ='Financial Statements'!E2 -> 46447 | I16: ='Financial Statements'!F2 -> 46478 | J16: ='Financial Statements'!G2 -> 46508 | K16: ='Financial Statements'!H2 -> 46539 | L16: ='Financial Statements'!I2 -> 46569 | M16: ='Financial Statements'!J2 -> 46600 | ... BA16: ='Financial Statements'!AX2 -> 47818
B17: Monthly EBITDA | E17: € | F17: ='Financial Statements'!C37 -> -39549.333 | G17: ='Financial Statements'!D37 -> 31063.167 | H17: ='Financial Statements'!E37 -> -31171.833 | I17: ='Financial Statements'!F37 -> -24697.02 | J17: ='Financial Statements'!G37 -> -23309.381 | K17: ='Financial Statements'!H37 -> -8812.8647 | L17: ='Financial Statements'!I37 -> -8367.1152 | M17: ='Financial Statements'!J37 -> -7929.5779 | ... BA17: ='Financial Statements'!AX37 -> 551963.41
B18: Cumulative EBITDA | E18: € | F18: =F17 -> -39549.333 | G18: =F18+G17 -> -8486.1667 | H18: =G18+H17 -> -39658 | I18: =H18+I17 -> -64355.02 | J18: =I18+J17 -> -87664.4 | K18: =J18+K17 -> -96477.265 | L18: =K18+L17 -> -104844.38 | M18: =L18+M17 -> -112773.96 | N18: =M18+N17 -> -59168.56 | ... BA18: =AZ18+BA17 -> 6541898.8
B19: Cumulative trough (min) | C19: =MIN(F18:BA18) -> -112773.96 | G19: €
B20: Trough month | C20: {=INDEX(F16:BA16,MATCH(C19,F18:BA18,0))} -> 46600
B22: C · CAPITAL NEED & RECOMMENDED RAISE
B23: Pre-model outlays | C23: =C12 -> 24960 | G23: €
B24: Operating trough (absolute) | C24: =MAX(0,-C19) -> 112773.96 | G24: €
B25: Total capital need | C25: =C23+C24 -> 137733.96 | G25: €
B26: Safety buffer % | C26: 0.3 | G26: %
B27: Recommended raise | C27: =CEILING(C25*(1+C26),25000) -> 200000 | G27: €

Sheet Dashboard
B2: Dashboard — Annual Summary 2027–2030
C4: 2027 | D4: 2028 | E4: 2029 | F4: 2030
B5: Revenue (gross) | C5: ='Revenue forecast'!BC37 -> 1050430.5 | D5: ='Revenue forecast'!BD37 -> 2373755.3 | E5: ='Revenue forecast'!BE37 -> 4651993 | F5: ='Revenue forecast'!BF37 -> 9065533.3
B6: Net revenue | C6: ='Financial Statements'!AZ9 -> 976592.97 | D6: ='Financial Statements'!BA9 -> 2207555.3 | E6: ='Financial Statements'!BB9 -> 4330678 | F6: ='Financial Statements'!BC9 -> 8435908.3
B7: EBITDA | C7: ='Financial Statements'!AZ37 -> -9953.949 | D7: ='Financial Statements'!BA37 -> 664643.83 | E7: ='Financial Statements'!BB37 -> 1699963.9 | F7: ='Financial Statements'!BC37 -> 4187245
B8: EBITDA margin % | C8: ='Financial Statements'!AZ38 -> -0.010192526 | D8: ='Financial Statements'!BA38 -> 0.30107686 | E8: ='Financial Statements'!BB38 -> 0.39253989 | F8: ='Financial Statements'!BC38 -> 0.49635971
B9: New deals | C9: =Assumptions!C27 -> 15 | D9: =Assumptions!D27 -> 20 | E9: =Assumptions!E27 -> 25 | F9: =Assumptions!F27 -> 30
B10: Live projects (avg) | C10: =Personnel!BC7 -> 7 | D10: =Personnel!BD7 -> 10 | E10: =Personnel!BE7 -> 13 | F10: =Personnel!BF7 -> 14
B11: Total FTE | C11: =Personnel!BC17 -> 10 | D11: =Personnel!BD17 -> 12 | E11: =Personnel!BE17 -> 15 | F11: =Personnel!BF17 -> 17
B12: Revenue per FTE (net) | C12: =C6/C11 -> 97659.297 | D12: =D6/D11 -> 183962.94 | E12: =E6/E11 -> 288711.87 | F12: =F6/F11 -> 496229.9
B13: SOFTWARE
B14: Software revenue | C14: ='Revenue forecast'!BC36 -> 65930.47 | D14: ='Revenue forecast'!BD36 -> 157755.32 | E14: ='Revenue forecast'!BE36 -> 367793.02 | F14: ='Revenue forecast'!BF36 -> 670533.27
B15: Software subscribers — total (year-end) | C15: ='Revenue forecast'!Q25+'Revenue forecast'!Q27 -> 10.176762 | D15: ='Revenue forecast'!AC25+'Revenue forecast'!AC27 -> 23.563479 | E15: ='Revenue forecast'!AO25+'Revenue forecast'!AO27 -> 69.482762 | F15: ='Revenue forecast'!BA25+'Revenue forecast'!BA27 -> 119.79126
B16: Software ARR — total (exit) | C16: ='Revenue forecast'!Q28*Assumptions!C17*12 -> 103060.57 | D16: ='Revenue forecast'!AC28*Assumptions!D17*12 -> 201380.87 | E16: ='Revenue forecast'!AO28*Assumptions!E17*12 -> 494896.57 | F16: ='Revenue forecast'!BA28*Assumptions!F17*12 -> 802747.59
B17: Software LTV — advisory | C17: =Assumptions!C17*((Assumptions!C28*Assumptions!C4+(1-Assumptions!C28)*Assumptions!C11)+1/Assumptions!$C$19) -> 30289.296 | D17: =Assumptions!D17*((Assumptions!D28*Assumptions!D4+(1-Assumptions!D28)*Assumptions!D11)+1/Assumptions!$C$19) -> 30339.296 | E17: =Assumptions!E17*((Assumptions!E28*Assumptions!E4+(1-Assumptions!E28)*Assumptions!E11)+1/Assumptions!$C$19) -> 30314.296 | F17: =Assumptions!F17*((Assumptions!F28*Assumptions!F4+(1-Assumptions!F28)*Assumptions!F11)+1/Assumptions!$C$19) -> 30389.296
B18: Software ARR — advisory (exit) | C18: =('Revenue forecast'!Q23+'Revenue forecast'!Q25)*Assumptions!C17*12 -> 103060.57 | D18: =('Revenue forecast'!AC23+'Revenue forecast'!AC25)*Assumptions!D17*12 -> 201380.87 | E18: =('Revenue forecast'!AO23+'Revenue forecast'!AO25)*Assumptions!E17*12 -> 310505.17 | F18: =('Revenue forecast'!BA23+'Revenue forecast'!BA25)*Assumptions!F17*12 -> 427818.41
B19: Software ARR — direct (exit) | C19: ='Revenue forecast'!Q27*Assumptions!C17*12 -> 0 | D19: ='Revenue forecast'!AC27*Assumptions!D17*12 -> 0 | E19: ='Revenue forecast'!AO27*Assumptions!E17*12 -> 184391.4 | F19: ='Revenue forecast'!BA27*Assumptions!F17*12 -> 374929.18
B20: Direct subscribers (year-end) | C20: ='Revenue forecast'!Q27 -> 0 | D20: ='Revenue forecast'!AC27 -> 0 | E20: ='Revenue forecast'!AO27 -> 30.7319 | F20: ='Revenue forecast'!BA27 -> 62.488197
B21: Software LTV — direct | C21: =Assumptions!C17*(1/Assumptions!$C$22) -> 17073.278 | D21: =Assumptions!D17*(1/Assumptions!$C$22) -> 17073.278 | E21: =Assumptions!E17*(1/Assumptions!$C$22) -> 17073.278 | F21: =Assumptions!F17*(1/Assumptions!$C$22) -> 17073.278
