Workbook

Sheet Cover
B15: Financial Model
B19: Currency: EUR (€)
B21: STRICTLY CONFIDENTIAL

Sheet How to read me
B1: Tarnoc — How to Read This Model
B3: COLOR CODING
B4: Sample | C4: Assumptions are hardcoded inputs (sourced from documents)
B5: Sample | C5: Hardcoded historicalsis actual data from source documents
B6: Sample | C6: Formula cells are calculated, not hardcoded
B7: Sample | C7: Subtotal / total rows
B8: Sample | C8: Section headers / grand totals
B9: Sample | C9: Subsection headers
B10: Sample | C10: Margin / ratio rows (grey)
B11: Sample | C11: Balance sheet check rows (must = 0)
B14: FORMULA ARCHITECTURE
B15: Assumptions → Revenue Forecast, COGS, OPEX, CAPEX, Personnel (all drivers sourced here)
B16: Revenue Forecast → Financial Statements (revenue lines via cross-sheet links)
B17: COGS → Financial Statements (cost lines via cross-sheet links)
B18: OPEX → Financial Statements (opex lines via cross-sheet links)
B20: To change a number: ONLY edit cells in the Assumptions tab (yellow/orange).
B21: All other tabs will recalculate automatically.
B24: FURTHER EXPLANATIONS
B25: Subsidies: Tarnoc is and has been eligible for a number of subsidies. We will consider application for large projects, however this model excludes the forecast of any subsidy financing foing forward.
B26: Installation revenues: This is modelled fully as pass through revenue for now, as we plan to charge a customer exactly what we pay the installation partner for these services. This is subject to change in the future.
B27: Tarnoc's main products are the TTK (turbineketel), the Combi and Combi+ (turbineketel + outdoor unit), and the Twincycle (in development for 2027). Every unit contains a turbineketel; the Combi and Combi+ differ only by their outdoor unit and installation. We also plan to sell various add-ons such as performance booster units, boilers for hybrid setups, and sound reduction units.
B28: Service Revenues: Service revenues are calculated relative to installed base. We assume a certain percentage (see assumptions) of customers will purchase our Service package, and are charged annually.
... B31: Revenues: Customer deposits have so far been collected at a TTK sales price of €8,099. We recently increased the list price to €8,925. For the purposes of this financial model, we assume an average selling price of €8,526, which we view as a conservative lower-bound assumption. Based on current market feedback, we believe the long-term market-clearing price is more likely to be approximately €9,000, although this will be validated over time as commercial sales progress.

Sheet Assumptions
B2: Drivers & Assumptions
B3: ASSUMPTIONS
B5: General Assumptions
B6: Opening Cash Balance (Jan 2024) | C6: 29538.9
B7: Annual salary increase (%) | C7: 0.08
B8: Employer cost basis | C8: Werkgeverlasten (incl. taxes)
B9: Holiday pay (%) | C9: 0.08
B10: Income tax rate | C10: 0.258
B11: Interst on WC loan | C11: 0.05
B13: Working Capital | H13: 20
B15: Days Sales Outstanding (DSO) | C15: days | D15: 20
B16: Days Payable Outstanding (DPO) | C16: days | D16: 45
B17: Days Inventory Outstanding (DIO) | C17: days | D17: 0
B18: Pre-payment | C18: %
B20: Revenue Build
B21: ~Units sold | D21: 1000 | E21: 3000 | F21: 6000 | G21: 12000
C22: 2026 | D22: 2027 | E22: 2028 | F22: 2029 | G22: 2030
B23: TTK | C23: 0 | D23: =D$21*$H23 -> 400 | E23: =E$21*$H23 -> 1200 | F23: =F$21*$H23 -> 2400 | G23: =G$21*$H23 -> 4800 | H23: 0.4
B24: Combi | C24: 0 | D24: =D$21*$H24 -> 300 | E24: =E$21*$H24 -> 900 | F24: =F$21*$H24 -> 1800 | G24: =G$21*$H24 -> 3600 | H24: 0.3
B25: Combi+ | C25: 0 | D25: =D$21*$H25 -> 300 | E25: =E$21*$H25 -> 900 | F25: =F$21*$H25 -> 1800 | G25: =G$21*$H25 -> 3600 | H25: 0.3
B28: Pricing
B29: PRICING — build-up (turbineketel + outdoor unit) | D29: (inc VAT)
B30: Turbineketel base price (all products) | C30: 8525.62 | D30: =C30*1.21 -> 10316
B31: Outdoor unit — Combi | C31: 2252.07 | D31: =C31*1.21 -> 2725.0047
B32: Outdoor unit — Combi+ | C32: 5309.92 | D32: =C32*1.21 -> 6425.0032
B33: Combi price (ketel + ODU) | C33: =C30+C31 -> 10777.69 | D33: =C33*1.21 -> 13041.005
B34: Combi+ price (ketel + ODU) | C34: =C30+C32 -> 13835.54 | D34: =C34*1.21 -> 16741.003
B35: INSTALLATION (PASS-THROUGH; REV=COST)
B36: Installation — TTK | C36: 2800
B37: Installation — Combi | C37: 3800
B38: Installation — Combi+ | C38: 3800
B39: COGS
B40: TTK
B41: Bill of Materials TTK supplier 1
B42: # | C42: Category | D42: Component | E42: 1,000 units | F42: 5,000 units | G42: 10,000 units | H42: Unit | I42: Source
B43: B1 | C43: Supplier 1 | D43: Compressor + VFD | E43: 6314 | F43: 4500 | G43: 2692.44 | H43: €/unit | I43: Source: BOM data provided
B44: B2 | C44: Supplier 1 | D44: Heat exchangers (set) | E44: 805.5 | F44: =E44*0.7 -> 563.85 | G44: =0.6*F44 -> 338.31 | H44: €/unit | I44: Source: BOM data provided
B45: B3 | C45: Supplier 1 | D45: Electronics & Power Electronics | E45: 632.92 | F45: =E45*0.7 -> 443.044 | G45: =0.6*F45 -> 265.8264 | H45: €/unit | I45: Source: BOM data provided
B46: B4 | C46: Supplier 1 | D46: Hydraulic Components (Pumps, Valves, etc.) | E46: 283.76 | F46: =E46*0.7 -> 198.632 | G46: =0.6*F46 -> 119.1792 | H46: €/unit | I46: Source: BOM data provided
B47: B5 | C47: Supplier 1 | D47: Silencer & Insulation | E47: 118.48 | F47: =E47*0.7 -> 82.936 | G47: =0.6*F47 -> 49.7616 | H47: €/unit | I47: Source: BOM data provided
B48: B6 | C48: Supplier 1 | D48: Enclosure (Sheet Metal & Coating) | E48: 653.03 | F48: =E48*0.7 -> 457.121 | G48: =0.6*F48 -> 274.2726 | H48: €/unit | I48: Source: BOM data provided
B49: B7 | C49: Supplier 1 | D49: Other Components | E49: 290 | F49: =E49*0.7 -> 203 | G49: 126 | H49: €/unit | I49: Source: BOM data provided
B50: B8 | C50: Supplier 1 | D50: Assembly & Final Testing | E50: 200 | F50: =E50*0.7 -> 140 | G50: =0.6*F50 -> 84 | H50: €/unit | I50: Source: BOM data provided
B51: B9 | C51: Supplier 1 | D51: Packaging & Inbound Logistics | E51: 395 | F51: =E51*0.7 -> 276.5 | G51: =0.6*F51 -> 165.9 | H51: €/unit | I51: Source: BOM data provided
B52: B10 | C52: Supplier 1 | D52: Yield Loss & Warranty Provision (~3%) | E52: 291.23 | F52: =E52*0.7 -> 203.861 | G52: =0.6*F52 -> 122.3166 | H52: €/unit | I52: Source: BOM data provided
B53: B11 | C53: Contingency/risk | D53: Contingency & Risk Reserve | E53: 0 | F53: 0 | G53: 760 | H53: €/unit | I53: Source: No source, added for risk purposes
B54: B-T | C54: Supplier 1 total | D54: Total COGS / unit (BOM) | E54: =SUM(E43:E53) -> 9983.92 | F54: =SUM(F43:F53) -> 7068.944 | G54: =round(SUM(G43:G53),0) -> 4998 | H54: €/unit
B56: Bill of Materials TTK supplier 2
B57: D1 | C57: Supplier 2 | D57: Compressor + VFD | E57: 2568 | F57: 2311.2 | G57: 2080.08 | H57: €/unit | I57: Source: BOM data provided
B58: D2 | C58: Supplier 2 | D58: Heat exchangers (set) | E58: 805.5 | F58: =E58*0.7 -> 563.85 | G58: =F58*0.6 -> 338.31 | H58: €/unit | I58: Source: BOM data provided
B59: D3 | C59: Supplier 2 | D59: Elektronica & vermogenselektronica | E59: 257.92 | F59: =E59*0.7 -> 180.544 | G59: =F59*0.6 -> 108.3264 | H59: €/unit | I59: Source: BOM data provided
B60: D4 | C60: Supplier 2 | D60: Hydraulisch (pompen/kleppen/etc.) | E60: 283.76 | F60: =E60*0.7 -> 198.632 | G60: =F60*0.6 -> 119.1792 | H60: €/unit | I60: Source: BOM data provided
B61: D5 | C61: Supplier 2 | D61: Silencer + isolatie | E61: 118.48 | F61: =E61*0.7 -> 82.936 | G61: =F61*0.6 -> 49.7616 | H61: €/unit | I61: Source: BOM data provided
B62: D6 | C62: Supplier 2 | D62: Enclosure (plaatwerk, coating) | E62: 653.03 | F62: =E62*0.7 -> 457.121 | G62: =F62*0.6 -> 274.2726 | H62: €/unit | I62: Source: BOM data provided
B63: D7 | C63: Supplier 2 | D63: Everything Else | E63: 300 | F63: =E63*0.7 -> 210 | G63: =F63*0.6 -> 126 | H63: €/unit | I63: Source: BOM data provided
B64: D8 | C64: Supplier 2 | D64: Assemblage & eindtest | E64: 200 | F64: =E64*0.7 -> 140 | G64: =F64*0.6 -> 84 | H64: €/unit | I64: Source: BOM data provided
B65: D9 | C65: Supplier 2 | D65: Verpakking & logistiek inkomend | E65: 400 | F65: =E65*0.7 -> 280 | G65: =F65*0.6 -> 168 | H65: €/unit | I65: Source: BOM data provided
B66: D10 | C66: Supplier 2 | D66: Yield / garantie-reserve (~3%) | E66: 236.81 | F66: =E66*0.7 -> 165.767 | G66: =F66*0.6 -> 99.4602 | H66: €/unit | I66: Source: BOM data provided
C67: Supplier 2 total | D67: Total COGS / unit (BOM) | E67: =SUM(E57:E66) -> 5823.5 | F67: =SUM(F57:F66) -> 4590.05 | G67: =SUM(G57:G66) -> 3447.39
B69: TTK Volume tier breakpoints
B70: Min Units (≥) | C70: Cost / unit | D70: Unit | E70: Note
B71: 0 | C71: =E54 -> 9983.92 | D71: €/unit | E71: Linked from BOM Total row above
B72: 5000 | C72: =F54 -> 7068.944 | D72: €/unit | E72: Linked from BOM Total row above
B73: 10000 | C73: =G54 -> 4998 | D73: €/unit | E73: Linked from BOM Total row above
B75: OUTDOOR UNIT COGS (Combi / Combi+) — volume tiers
B76: Component | E76: 1,000 units | F76: 5,000 units | G76: 10,000 units | H76: Unit | I76: Unit | J76: Source
B77: Outdoor unit — Combi | E77: 1178.36 | F77: 1060.52 | G77: 954.47 | H77: €/unit | I77: €/unit | J77: Source: BOM data
B78: Outdoor unit — Combi+ | E78: 1402.6 | F78: 1262.34 | G78: 1136.1 | H78: €/unit | I78: €/unit | J78: Source: BOM data
B79: Shipping (Combi & Combi+) | E79: 100 | F79: 100 | G79: 100 | H79: €/unit | I79: €/unit | J79: Source: BOM data
I80: €/unit | J80: Source: BOM data
B81: Outdoor Unit tier breakpoints (for COGS VLOOKUP) | I81: €/unit | J81: Source: BOM data provided
B82: Min Units (≥)
B83: 0 | C83: =E77 -> 1178.36 | E83: 0 | F83: =E78 -> 1402.6
B84: 5000 | C84: =F77 -> 1060.52 | E84: 5000 | F84: =F78 -> 1262.34
B85: 10000 | C85: =G77 -> 954.47 | E85: 10000 | F85: =G78 -> 1136.1
B91: Other operating expenditures | F91: Yearly increase: | G91: 0.35
C92: Category | D92: Note | E92: 2026 | F92: 2027 | G92: 2028 | H92: 2029 | I92: 2030
B93: Office rent (part of General) | C93: G&A | D93: ongoing | E93: 5000 | F93: =$E93*(1+$G$91) -> 6750 | G93: =F93*(1+$G$91) -> 9112.5 | H93: =G93*(1+$G$91) -> 12301.875 | I93: =H93*(1+$G$91) -> 16607.531
B94: Other General | C94: G&A | D94: ongoing | E94: 7000 | F94: =$E94*(1+$G$91) -> 9450 | G94: =F94*(1+$G$91) -> 12757.5 | H94: =G94*(1+$G$91) -> 17222.625 | I94: =H94*(1+$G$91) -> 23250.544
B95: Baseline Sales & Marketing | C95: S&M | D95: ongoing | E95: 14000 | F95: =$E95*(1+$G$91) -> 18900 | G95: =F95*(1+$G$91) -> 25515 | H95: =G95*(1+$G$91) -> 34445.25 | I95: =H95*(1+$G$91) -> 46501.088
B96: Finance & Legal etc. | C96: G&A | D96: ongoing | E96: 8000 | F96: =$E96*(1+$G$91) -> 10800 | G96: =F96*(1+$G$91) -> 14580 | H96: =G96*(1+$G$91) -> 19683 | I96: =H96*(1+$G$91) -> 26572.05
B97: Ongoing Development costs | C97: R&D | D97: ongoing | E97: 10000 | F97: =$E97*(1+$G$91) -> 13500 | G97: =F97*(1+$G$91) -> 18225 | H97: =G97*(1+$G$91) -> 24603.75 | I97: =H97*(1+$G$91) -> 33215.062
B98: Third party cost product development | C98: R&D | D98: ongoing | E98: 15000 | F98: =$E98*(1+$G$91) -> 20250 | G98: =F98*(1+$G$91) -> 27337.5 | H98: =G98*(1+$G$91) -> 36905.625 | I98: =H98*(1+$G$91) -> 49822.594
B99: Kicker Development Cost | C99: R&D | D99: one-off | E99: 168933
B100: Customer journey (third party) | C100: S&M | D100: one-off | E100: 10000
B101: Branding + Website (third party cost) | C101: S&M | D101: one-off | E101: 10000
B102: Assembly partner | C102: R&D | D102: one-off | E102: 100000
B103: Tooling Fisher (result: 2%-3%) | C103: R&D | D103: one-off | E103: 45000
B106: Assumptions for costs per unit sold (3rd parties or expenses (NO personell) | G106: Units sold | H106: S&M cost per unit | I106: Decrease | J106: Yearly costs
B107: Marketing spend per Customer | C107: S&M | E107: 600 | F107: third party | G107: 0 | H107: =E111 -> 800
B108: Closing costs per customer | C108: S&M | D108: (Calls, viewing location, etc) | E108: 150 | F108: third party | G108: 400 | H108: =E111 -> 800 | J108: =G108*H108 -> 320000
B109: Aftersales and support | C109: S&M | E109: 50 | F109: third party | G109: =G108*2 -> 800 | H109: =H108*I109 -> 720 | I109: 0.9 | J109: =G109*H109 -> 576000
G110: =G109*2 -> 1600 | H110: =H109*I110 -> 648 | I110: 0.9 | J110: =G110*H110 -> 1036800
B111: Cost per unit sold (cost down driven by volume) | C111: S&M | D111: costdown: S(n)=S(1)*n^-b, where b=0,2 | E111: =SUM(E107:E109) -> 800 | F111: S(1) | G111: =G110*2 -> 3200 | H111: =H110*I111 -> 583.2 | I111: 0.9 | J111: =G111*H111 -> 1866240
G112: =G111*2 -> 6400 | H112: =H111*I112 -> 524.88 | I112: 0.9 | J112: =G112*H112 -> 3359232
G113: =G112*2 -> 12800 | H113: =H112*I113 -> 472.392 | I113: 0.9 | J113: =G113*H113 -> 6046617.6
G114: =G113*2 -> 25600 | H114: =H113*I114 -> 425.1528 | I114: 0.9 | J114: =G114*H114 -> 10883912
B116: Product | C116: Upsell item | D116: Type | E116: Attach % | F116: Unit rev. (EX VAT) | G116: Unit COGS | H116: Gross profit | I116: avg. Value | J116: avg. profit
B117: TTK / Combi / Combi+ | C117: Boiler variant 50 | D117: One-time | E117: 0.49 | F117: 165.29 | G117: 80 | H117: =F117-G117 -> 85.29 | I117: =F117*E117 -> 80.9921 | J117: =H117*E117 -> 41.7921
B118: TTK / Combi / Combi+ | C118: Boiler variant 100 | D118: One-time | E118: 0.19 | F118: 330.58 | G118: 150 | H118: =F118-G118 -> 180.58 | I118: =F118*E118 -> 62.8102 | J118: =H118*E118 -> 34.3102
...

Sheet Financial Statements
B1: Tarnoc B.V. — Financial Statements (€)
E2: 2025 | Q2: 2026 | AC2: 2027 | AO2: 2028
E3: 45658 | F3: 45689 | G3: 45717 | H3: 45748 | I3: 45778 | J3: 45809 | K3: 45839 | L3: 45870 | M3: 45901 | N3: 45931 | O3: 45962 | P3: 45992 | Q3: 46023 | R3: 46054 | S3: 46082 | T3: 46113 | U3: 46143 | V3: 46174 | W3: 46204 | X3: 46235 | Y3: 46266 | Z3: 46296 | AA3: 46327 | AB3: 46357 | AC3: 46388 | AD3: 46419 | AE3: 46447 | AF3: 46478 | AG3: 46508 | AH3: 46539 | AI3: 46569 | AJ3: 46600 | AK3: 46631 | AL3: 46661 | AM3: 46692 | AN3: 46722 | AO3: 46753 | AP3: 46784 | AQ3: 46813 | AR3: 46844 | AS3: 46874 | AT3: 46905 | AU3: 46935 | AV3: 46966 | AW3: 46997 | AX3: 47027 | AY3: 47058 | AZ3: 47088 | BB3: 2025 | BC3: 2026 | BD3: 2027 | BE3: 2028 | BF3: 2029
B5: PROFIT & LOSS STATEMENT
B6: Revenues
B7: TTK | D7: € | M7: ='Revenue Forecast'!M9 | N7: ='Revenue Forecast'!N9 | O7: ='Revenue Forecast'!O9 | P7: ='Revenue Forecast'!P9 | Q7: ='Revenue Forecast'!Q9 -> 0 | R7: ='Revenue Forecast'!R9 -> 0 | S7: ='Revenue Forecast'!S9 -> 0 | T7: ='Revenue Forecast'!T9 -> 0 | ... AZ7: ='Revenue Forecast'!AZ9 -> 1408448.6 | BB7: =sum(E7:P7) -> 0 | BC7: =sum(Q7:AB7) -> 0 | BD7: =sum(AC7:AN7) -> 3611406.7 | BE7: =sum(AO7:AZ7) -> 10834220 | BF7: ='Revenue Forecast'!BF9 -> 21670840
B8: Combi | D8: € | M8: ='Revenue Forecast'!M15 | N8: ='Revenue Forecast'!N15 | O8: ='Revenue Forecast'!O15 | P8: ='Revenue Forecast'!P15 | Q8: ='Revenue Forecast'!Q15 -> 0 | R8: ='Revenue Forecast'!R15 -> 0 | S8: ='Revenue Forecast'!S15 -> 0 | T8: ='Revenue Forecast'!T15 -> 0 | ... AZ8: ='Revenue Forecast'!AZ15 -> 1331109.2 | BB8: =sum(E8:P8) -> 0 | BC8: =sum(Q8:AB8) -> 0 | BD8: =sum(AC8:AN8) -> 3384176 | BE8: =sum(AO8:AZ8) -> 10152528 | BF8: ='Revenue Forecast'!BF15 -> 20305056
B9: Combi+ | D9: € | Q9: ='Revenue Forecast'!Q21 -> 0 | R9: ='Revenue Forecast'!R21 -> 0 | S9: ='Revenue Forecast'!S21 -> 0 | T9: ='Revenue Forecast'!T21 -> 0 | U9: ='Revenue Forecast'!U21 -> 0 | V9: ='Revenue Forecast'!V21 -> 0 | W9: ='Revenue Forecast'!W21 -> 0 | X9: ='Revenue Forecast'!X21 -> 0 | ... AZ9: ='Revenue Forecast'!AZ21 -> 1691935.5 | BB9: ='Revenue Forecast'!BB21 -> 0 | BC9: ='Revenue Forecast'!BC21 -> 0 | BD9: ='Revenue Forecast'!BD21 -> 4301531 | BE9: ='Revenue Forecast'!BE21 -> 12904593 | BF9: ='Revenue Forecast'!BF21 -> 25809186
B10: Other | D10: € | M10: ='Revenue Forecast'!M25+'Revenue Forecast'!M31 -> 0 | N10: ='Revenue Forecast'!N25+'Revenue Forecast'!N31 -> 0 | O10: ='Revenue Forecast'!O25+'Revenue Forecast'!O31 -> 0 | P10: ='Revenue Forecast'!P25+'Revenue Forecast'!P31 -> 0 | Q10: ='Revenue Forecast'!Q25+'Revenue Forecast'!Q31 -> 0 | R10: ='Revenue Forecast'!R25+'Revenue Forecast'!R31 -> 0 | S10: ='Revenue Forecast'!S25+'Revenue Forecast'!S31 -> 0 | T10: ='Revenue Forecast'!T25+'Revenue Forecast'!T31 -> 0 | ... AZ10: ='Revenue Forecast'!AZ25+'Revenue Forecast'!AZ31 -> 1416757 | BB10: =sum(E10:P10) -> 0 | BC10: =sum(Q10:AB10) -> 0 | BD10: =sum(AC10:AN10) -> 3559000 | BE10: =sum(AO10:AZ10) -> 10836000 | BF10: ='Revenue Forecast'!BF25+'Revenue Forecast'!BF31 -> 21402177
B11: Subsidies & grants | D11: € | M11: ='Revenue Forecast'!M35 -> 0 | N11: ='Revenue Forecast'!N35 -> 19480 | O11: ='Revenue Forecast'!O35 -> 78000 | P11: ='Revenue Forecast'!P35 -> 0 | Q11: ='Revenue Forecast'!Q35 -> 0 | R11: ='Revenue Forecast'!R35 -> 0 | S11: ='Revenue Forecast'!S35 -> 0 | T11: 0 | U11: ='Revenue Forecast'!U35 -> 0 | V11: ='Revenue Forecast'!V35 -> 0 | W11: ='Revenue Forecast'!W35 -> 0 | X11: ='Revenue Forecast'!X35 -> 106782 | Y11: ='Revenue Forecast'!Y35 -> 0 | Z11: ='Revenue Forecast'!Z35 -> 0 | AA11: ='Revenue Forecast'!AA35 -> 0 | AB11: ='Revenue Forecast'!AB35 -> 0 | ... AZ11: ='Revenue Forecast'!AZ35 -> 0 | BB11: =sum(E11:P11) -> 97480 | BC11: =sum(Q11:AB11) -> 106782 | BD11: pm | BE11: pm | BF11: pm
B12: Total Revenue | D12: € | M12: ='Revenue Forecast'!M37 -> 0 | N12: ='Revenue Forecast'!N37 -> 19480 | O12: ='Revenue Forecast'!O37 -> 78000 | P12: ='Revenue Forecast'!P37 -> 0 | Q12: ='Revenue Forecast'!Q37 -> 0 | R12: ='Revenue Forecast'!R37 -> 0 | S12: ='Revenue Forecast'!S37 -> 0 | T12: ='Revenue Forecast'!T37 -> 0 | ... AZ12: ='Revenue Forecast'!AZ37 -> 5848250.4 | BB12: =sum(E12:P12) -> 97480 | BC12: =sum(Q12:AB12) -> 106782 | BD12: =sum(AC12:AN12) -> 14856114 | BE12: =sum(AO12:AZ12) -> 44727341 | BF12: =sum(BF7:BF11) -> 89187260
B14: Cost of goods sold
B15: TTK | D15: € | E15: =COGS!E9 | F15: =COGS!F9 | G15: =COGS!G9 | H15: =COGS!H9 | I15: =COGS!I9 | J15: =COGS!J9 | K15: =COGS!K9 | L15: =COGS!L9 | ... AZ15: =COGS!AZ9 -> 1136732.1 | BB15: =sum(E15:P15) -> 0 | BC15: =sum(Q15:AB15) -> 0 | BD15: =sum(AC15:AN15) -> 4080688 | BE15: =sum(AO15:AZ15) -> 8744092.8 | BF15: =COGS!BF9 -> 12517920
B16: Combi | D16: € | E16: =COGS!E14 | F16: =COGS!F14 | G16: =COGS!G14 | H16: =COGS!H14 | I16: =COGS!I14 | J16: =COGS!J14 | K16: =COGS!K14 | L16: =COGS!L14 | ... AZ16: =COGS!AZ14 -> 1010682.3 | BB16: =sum(E16:P16) -> 0 | BC16: =sum(Q16:AB16) -> 0 | BD16: =sum(AC16:AN16) -> 3444024 | BE16: =sum(AO16:AZ16) -> 7708593.6 | BF16: =COGS!BF14 -> 11477376
B17: Combi+ | D17: € | Q17: =COGS!Q19 -> 0 | R17: =COGS!R19 -> 0 | S17: =COGS!S19 -> 0 | T17: =COGS!T19 -> 0 | U17: =COGS!U19 -> 0 | V17: =COGS!V19 -> 0 | W17: =COGS!W19 -> 0 | X17: =COGS!X19 -> 0 | ... AZ17: =COGS!AZ19 -> 1037142.6 | BB17: =COGS!BB19 | BC17: =COGS!BC19 -> 0 | BD17: =COGS!BD19 -> 3511296 | BE17: =COGS!BE19 -> 7910409.6 | BF17: =COGS!BF19 -> 11840652
B18: Other | D18: € | E18: =COGS!E22 | F18: =COGS!F22 | G18: =COGS!G22 | H18: =COGS!H22 | I18: =COGS!I22 | J18: =COGS!J22 | K18: =COGS!K22 | L18: =COGS!L22 | ... P18: =COGS!P22 | Q18: =COGS!Q22+COGS!Q27 -> 0 | R18: =COGS!R22+COGS!R27 -> 0 | S18: =COGS!S22+COGS!S27 -> 0 | T18: =COGS!T22+COGS!T27 -> 0 | U18: =COGS!U22+COGS!U27 -> 0 | V18: =COGS!V22+COGS!V27 -> 0 | W18: =COGS!W22+COGS!W27 -> 0 | X18: =COGS!X22+COGS!X27 -> 0 | ... AZ18: =COGS!AZ22+COGS!AZ27 -> 1375178.5 | BB18: =sum(E18:P18) -> 0 | BC18: =sum(Q18:AB18) -> 0 | BD18: =sum(AC18:AN18) -> 3479500 | BE18: =sum(AO18:AZ18) -> 10518000 | BF18: =COGS!BF22 -> 20400000
B19: Total COGS | D19: € | M19: =COGS!M29 -> 0 | N19: =COGS!N29 -> 0 | O19: =COGS!O29 -> 0 | P19: =COGS!P29 -> 0 | Q19: =COGS!Q29 -> 0 | R19: =COGS!R29 -> 0 | S19: =COGS!S29 -> 0 | T19: =COGS!T29 -> 0 | ... AZ19: =COGS!AZ29 -> 4559735.4 | BB19: =sum(E19:P19) -> 0 | BC19: =sum(Q19:AB19) -> 0 | BD19: =sum(AC19:AN19) -> 14515508 | BE19: =sum(AO19:AZ19) -> 34881096 | BF19: =sum(BF15:BF18) -> 56235948
B21: Gross Profit
B22: TTK | D22: € | Q22: =Q7-Q15 -> 0 | R22: =R7-R15 -> 0 | S22: =S7-S15 -> 0 | T22: =T7-T15 -> 0 | U22: =U7-U15 -> 0 | V22: =V7-V15 -> 0 | W22: =W7-W15 -> 0 | X22: =X7-X15 -> 0 | ... AZ22: =AZ7-AZ15 -> 271716.56 | BC22: =BC7-BC15 -> 0 | BD22: =BD7-BD15 -> -469281.28 | BE22: =BE7-BE15 -> 2090127.4 | BF22: =BF7-BF15 -> 9152920.3
B23: Combi | D23: € | Q23: =Q8-Q16 -> 0 | R23: =R8-R16 -> 0 | S23: =S8-S16 -> 0 | T23: =T8-T16 -> 0 | U23: =U8-U16 -> 0 | V23: =V8-V16 -> 0 | W23: =W8-W16 -> 0 | X23: =X8-X16 -> 0 | ... AZ23: =AZ8-AZ16 -> 320426.97 | BC23: =BC8-BC16 -> 0 | BD23: =BD8-BD16 -> -59847.96 | BE23: =BE8-BE16 -> 2443934.5 | BF23: =BF8-BF16 -> 8827680.2
B24: Combi+ | D24: € | Q24: =Q9-Q17 -> 0 | R24: =R9-R17 -> 0 | S24: =S9-S17 -> 0 | T24: =T9-T17 -> 0 | U24: =U9-U17 -> 0 | V24: =V9-V17 -> 0 | W24: =W9-W17 -> 0 | X24: =X9-X17 -> 0 | ... AZ24: =AZ9-AZ17 -> 654792.95 | BC24: =BC9-BC17 -> 0 | BD24: =BD9-BD17 -> 790235.04 | BE24: =BE9-BE17 -> 4994183.5 | BF24: =BF9-BF17 -> 13968534
B25: Other | D25: € | Q25: =Q10-Q18 -> 0 | R25: =R10-R18 -> 0 | S25: =S10-S18 -> 0 | T25: =T10-T18 -> 0 | U25: =U10-U18 -> 0 | V25: =V10-V18 -> 0 | W25: =W10-W18 -> 0 | X25: =X10-X18 -> 0 | ... AZ25: =AZ10-AZ18 -> 41578.5 | BC25: =BC10-BC18 -> 0 | BD25: =BD10-BD18 -> 79500 | BE25: =BE10-BE18 -> 318000 | BF25: =BF10-BF18 -> 1002177
B26: Gross Profit | D26: € | M26: =M12-M19 -> 0 | N26: =N12-N19 -> 19480 | O26: =O12-O19 -> 78000 | P26: =P12-P19 -> 0 | Q26: =Q12-Q19 -> 0 | R26: =R12-R19 -> 0 | S26: =S12-S19 -> 0 | T26: =T12-T19 -> 0 | ... AZ26: =AZ12-AZ19 -> 1288515 | BB26: =sum(E26:P26) -> 97480 | BC26: =sum(Q26:AB26) -> 106782 | BD26: =sum(AC26:AN26) -> 340605.8 | BE26: =sum(AO26:AZ26) -> 9846245.4 | BF26: =BF12-BF19 -> 32951312
B27: Gross margin % | D27: % | BD27: =BD26/BD12 -> 0.022926978 | BE27: =BE26/BE12 -> 0.22013929 | BF27: =BF26/BF12 -> 0.36946209
B29: Operational expenses
B30: R&D | D30: € | M30: =OPEX!O38 -> 47500 | N30: =OPEX!P38 -> 47500 | O30: =OPEX!Q38 -> 47500 | P30: =OPEX!R38 -> 216433 | Q30: =OPEX!S38 -> 75700 | R30: =OPEX!T38 -> 75700 | S30: =OPEX!U38 -> 75700 | T30: =OPEX!V38 -> 75700 | ... AZ30: =OPEX!BB38 -> 155927.27 | BB30: =sum(E30:P30) -> 358933 | BC30: =sum(Q30:AB30) -> 1126160 | BD30: =sum(AC30:AN30) -> 1589655.2 | BE30: =sum(AO30:AZ30) -> 1858677.6 | BF30: =OPEX!BH38 -> 2628853.4
B31: S&M | D31: € | M31: =OPEX!O39 -> 0 | N31: =OPEX!P39 -> 0 | O31: =OPEX!Q39 -> 0 | P31: =OPEX!R39 -> 20000 | Q31: =OPEX!S39 -> 21000 | R31: =OPEX!T39 -> 31800 | S31: =OPEX!U39 -> 31800 | T31: =OPEX!V39 -> 31800 | ... AZ31: =OPEX!BB39 -> 299788.12 | BB31: =sum(E31:P31) -> 20000 | BC31: =sum(Q31:AB31) -> 464300 | BD31: =sum(AC31:AN31) -> 1261348 | BE31: =sum(AO31:AZ31) -> 2659678.2 | BF31: =OPEX!BH39 -> 4818295
B32: G&A | D32: € | M32: =OPEX!O40 -> 11500 | N32: =OPEX!P40 -> 11500 | O32: =OPEX!Q40 -> 11500 | P32: =OPEX!R40 -> 11500 | Q32: =OPEX!S40 -> 31820 | R32: =OPEX!T40 -> 31820 | S32: =OPEX!U40 -> 31820 | T32: =OPEX!V40 -> 31820 | ... AZ32: =OPEX!BB40 -> 98395.088 | BB32: =sum(E32:P32) -> 46000 | BC32: =sum(Q32:AB32) -> 462060 | BD32: =sum(AC32:AN32) -> 844843.2 | BE32: =sum(AO32:AZ32) -> 1109410.7 | BF32: =OPEX!BH40 -> 1357154.2
B33: Total OPEX | D33: € | M33: =(M32+M31+M30) -> 59000 | N33: =(N32+N31+N30) -> 59000 | O33: =(O32+O31+O30) -> 59000 | P33: =(P32+P31+P30) -> 247933 | Q33: =(Q32+Q31+Q30) -> 128520 | R33: =(R32+R31+R30) -> 139320 | S33: =(S32+S31+S30) -> 139320 | T33: =(T32+T31+T30) -> 139320 | ... AZ33: =(AZ32+AZ31+AZ30) -> 554110.48 | BB33: =sum(E33:P33) -> 424933 | BC33: =sum(Q33:AB33) -> 2052520 | BD33: =sum(AC33:AN33) -> 3695846.4 | BE33: =sum(AO33:AZ33) -> 5627766.5 | BF33: =sum(BF30:BF32) -> 8804302.6
B35: EBITDA | D35: € | M35: =M26-M33 -> -59000 | N35: =N26-N33 -> -39520 | O35: =O26-O33 -> 19000 | P35: =P26-P33 -> -247933 | Q35: =Q26-Q33 -> -128520 | R35: =R26-R33 -> -139320 | S35: =S26-S33 -> -139320 | T35: =T26-T33 -> -139320 | ... AZ35: =AZ26-AZ33 -> 734404.5 | BB35: =sum(E35:P35) -> -327453 | BC35: =sum(Q35:AB35) -> -1945738 | BD35: =sum(AC35:AN35) -> -3355240.6 | BE35: =sum(AO35:AZ35) -> 4218478.9 | BF35: =BF26-BF33 -> 24147009
B36: EBITDA margin % | D36: % | BE36: =BE35/BE12 -> 0.09431544 | BF36: =BF35/BF12 -> 0.27074505
B38: Depreciation & Amortisation | D38: € | M38: 0 | N38: 0 | O38: 0 | P38: 0 | Q38: 0 | R38: 0 | S38: 0 | T38: 0 | U38: 0 | V38: 0 | W38: 0 | X38: 0 | Y38: 0 | Z38: 0 | AA38: 0 | AB38: 0 | AC38: 0 | AD38: 0 | AE38: 0 | AF38: 0 | AG38: 0 | AH38: 0 | AI38: 0 | AJ38: 0 | AK38: 0 | AL38: 0 | AM38: 0 | AN38: 0 | AO38: 0 | AP38: 0 | AQ38: 0 | AR38: 0 | AS38: 0 | AT38: 0 | AU38: 0 | AV38: 0 | AW38: 0 | AX38: 0 | AY38: 0 | AZ38: 0 | BB38: =sum(E38:P38) -> 0 | BC38: =sum(Q38:AB38) -> 0 | BD38: =sum(AC38:AN38) -> 0 | BE38: =sum(AO38:AZ38) -> 0 | BF38: 0
B39: Interest payments | D39: € | M39: 0 | N39: 0 | O39: 0 | P39: 0 | Q39: =P85*Assumptions!$C$11/12 -> 0 | R39: =Q85*Assumptions!$C$11/12 -> 0 | S39: =R85*Assumptions!$C$11/12 -> 0 | T39: =S85*Assumptions!$C$11/12 -> 0 | U39: =T85*Assumptions!$C$11/12 -> 0 | V39: =U85*Assumptions!$C$11/12 -> 0 | W39: =V85*Assumptions!$C$11/12 -> 0 | X39: =W85*Assumptions!$C$11/12 -> 0 | ... AZ39: =AY85*Assumptions!$C$11/12 -> 2975 | BB39: =sum(E39:P39) -> 0 | BC39: =sum(Q39:AB39) -> 0 | BD39: =sum(AC39:AN39) -> 13164.375 | BE39: =sum(AO39:AZ39) -> 35700 | BF39: =BE85*0.05/12 -> 2975
B40: EBT | D40: € | M40: =M35-sum(M38:M39) -> -59000 | N40: =N35-sum(N38:N39) -> -39520 | O40: =O35-sum(O38:O39) -> 19000 | P40: =P35-sum(P38:P39) -> -247933 | Q40: =Q35-sum(Q38:Q39) -> -128520 | R40: =R35-sum(R38:R39) -> -139320 | S40: =S35-sum(S38:S39) -> -139320 | T40: =T35-sum(T38:T39) -> -139320 | ... AZ40: =AZ35-sum(AZ38:AZ39) -> 731429.5 | BB40: =sum(E40:P40) -> -327453 | BC40: =sum(Q40:AB40) -> -1945738 | BD40: =sum(AC40:AN40) -> -3368405 | BE40: =sum(AO40:AZ40) -> 4182778.9 | BF40: =BF35-sum(BF38:BF39) -> 24144034
BE41: =BE40/BE12 -> 0.093517271 | BF41: =BF40/BF12 -> 0.27071169
B43: Income tax | D43: € | M43: 0 | N43: 0 | O43: 0 | P43: 0 | Q43: 0 | R43: 0 | S43: 0 | T43: 0 | U43: 0 | V43: 0 | W43: 0 | X43: 0 | Y43: 0 | Z43: 0 | AA43: 0 | AB43: 0 | AC43: 0 | AD43: 0 | AE43: 0 | AF43: 0 | AG43: 0 | AH43: 0 | AI43: 0 | AJ43: 0 | AK43: 0 | AL43: 0 | AM43: 0 | AN43: 0 | AO43: 0 | AP43: 0 | AQ43: 0 | AR43: 0 | AS43: 0 | AT43: 0 | AU43: 0 | AV43: 0 | AW43: 0 | AX43: 0 | AY43: 0 | AZ43: 0 | BB43: =sum(E43:P43) -> 0 | BC43: =sum(Q43:AB43) -> 0 | BD43: =sum(AC43:AN43) -> 0 | BE43: =sum(AO43:AZ43) -> 0 | BF43: =(BF40-AZ47)*Assumptions!$C$10 -> 6108057.7
B44: NET INCOME | D44: € | M44: =M40-M43 -> -59000 | N44: =N40-N43 -> -39520 | O44: =O40-O43 -> 19000 | P44: =P40-P43 -> -247933 | Q44: =Q40-Q43 -> -128520 | R44: =R40-R43 -> -139320 | S44: =S40-S43 -> -139320 | T44: =T40-T43 -> -139320 | ... AZ44: =AZ40-AZ43 -> 731429.5 | BB44: =sum(E44:P44) -> -327453 | BC44: =sum(Q44:AB44) -> -1945738 | BD44: =sum(AC44:AN44) -> -3368405 | BE44: =sum(AO44:AZ44) -> 4182778.9 | BF44: =BF40-BF43 -> 18035976
B45: Profit margin % | BE45: =BE44/BE12 -> 0.093517271 | BF45: =BF44/BF12 -> 0.20222593
B47: Tax carry over to be applied | M47: 108239 | N47: =M47+(-N44*Assumptions!$C$10) -> 118435.16 | O47: =N47+(-O44*Assumptions!$C$10) -> 113533.16 | P47: =O47+(-P44*Assumptions!$C$10) -> 177499.87 | Q47: =P47+(-Q44*Assumptions!$C$10) -> 210658.03 | R47: =Q47+(-R44*Assumptions!$C$10) -> 246602.59 | S47: =R47+(-S44*Assumptions!$C$10) -> 282547.15 | T47: =S47+(-T44*Assumptions!$C$10) -> 318491.71 | U47: =T47+(-U44*Assumptions!$C$10) -> 357016.27 | ... AZ47: =AY47+(-AZ44*Assumptions!$C$10) -> 469391.81
B49: CASH FLOW STATEMENT
B50: Net income | D50: € | M50: =M44 -> -59000 | N50: =N44 -> -39520 | O50: =O44 -> 19000 | P50: =P44 -> -247933 | Q50: =Q44 -> -128520 | R50: =R44 -> -139320 | S50: =S44 -> -139320 | T50: =T44 -> -139320 | ... AZ50: =AZ44 -> 731429.5 | BB50: =sum(E50:P50) -> -327453 | BC50: =sum(Q50:AB50) -> -1945738 | BD50: =sum(AC50:AN50) -> -3368405 | BE50: =sum(AO50:AZ50) -> 4182778.9 | BF50: =BF44 -> 18035976
B51: Depreciation & amortisation | D51: € | M51: 0 | N51: 0 | O51: 0 | P51: 0 | Q51: 0 | R51: 0 | S51: 0 | T51: 0 | U51: 0 | V51: 0 | W51: 0 | X51: 0 | Y51: 0 | Z51: 0 | AA51: 0 | AB51: 0 | AC51: 0 | AD51: 0 | AE51: 0 | AF51: 0 | AG51: 0 | AH51: 0 | AI51: 0 | AJ51: 0 | AK51: 0 | AL51: 0 | AM51: 0 | AN51: 0 | AO51: 0 | AP51: 0 | AQ51: 0 | AR51: 0 | AS51: 0 | AT51: 0 | AU51: 0 | AV51: 0 | AW51: 0 | AX51: 0 | AY51: 0 | AZ51: 0 | BB51: =sum(E51:P51) -> 0 | BC51: =sum(Q51:AB51) -> 0 | BD51: =sum(AC51:AN51) -> 0 | BE51: =sum(AO51:AZ51) -> 0 | BF51: =BF38 -> 0
B52: Increase in accounts receivable (delta DSO) | D52: € | M52: 0 | N52: =-(N71-M71) -> -12986.667 | O52: =-(O71-N71) -> -39013.333 | P52: =-(P71-O71) -> 52000 | Q52: =-(Q71-P71) -> 0 | R52: =-(R71-Q71) -> 0 | S52: =-(S71-R71) -> 0 | T52: =-(T71-S71) -> 0 | U52: =-(U71-T71) -> 0 | ... AZ52: =-(AZ71-AY71) -> -320646.29 | BB52: =sum(E52:P52) -> 0 | BC52: =sum(Q52:AB52) -> 0 | BD52: =sum(AC52:AN52) -> -1295521.5 | BE52: =sum(AO52:AZ52) -> -2603312.1 | BF52: =-(BF71-BE71) -> -988139.54
B53: Increase in accounts payable (delta DPO) | D53: € | M53: 0 | N53: =(N80-M80) -> 0 | O53: =(O80-N80) -> 0 | P53: =(P80-O80) -> 0 | Q53: =(Q80-P80) -> 0 | R53: =(R80-Q80) -> 0 | S53: =(S80-R80) -> 0 | T53: =(T80-S80) -> 0 | U53: =(U80-T80) -> 0 | ... AZ53: =(AZ80-AY80) -> 561005.86 | BB53: =sum(E53:P53) -> 0 | BC53: =sum(Q53:AB53) -> 0 | BD53: =sum(AC53:AN53) -> 2850145.9 | BE53: =sum(AO53:AZ53) -> 3989457.3 | BF53: =BF80-BE80 -> 93595.926
B54: Change in inventory (delta DIO) | D54: € | M54: 0 | N54: =-(N72-M72) -> 0 | O54: =-(O72-N72) -> 0 | P54: =-(P72-O72) -> 0 | Q54: =-(Q72-P72) -> 0 | R54: =-(R72-Q72) -> 0 | S54: =-(S72-R72) -> 0 | T54: =-(T72-S72) -> 0 | U54: =-(U72-T72) -> 0 | ... AZ54: =-(AZ72-AY72) -> 0 | BB54: =sum(E54:P54) -> 0 | BC54: =sum(Q54:AB54) -> 0 | BD54: =sum(AC54:AN54) -> 0 | BE54: =sum(AO54:AZ54) -> 0 | BF54: 0
B55: Cash from Operations | D55: € | M55: =sum(M50:M54) -> -59000 | N55: =sum(N50:N54) -> -52506.667 | O55: =sum(O50:O54) -> -20013.333 | P55: =sum(P50:P54) -> -195933 | Q55: =sum(Q50:Q54) -> -128520 | R55: =sum(R50:R54) -> -139320 | S55: =sum(S50:S54) -> -139320 | T55: =sum(T50:T54) -> -139320 | ... AZ55: =sum(AZ50:AZ54) -> 971789.07 | BB55: =sum(E55:P55) -> -327453 | BC55: =sum(Q55:AB55) -> -1945738 | BD55: =sum(AC55:AN55) -> -1813780.6 | BE55: =sum(AO55:AZ55) -> 5568924.1 | BF55: =sum(BF50:BF54) -> 17141433
B56: CAPEX | D56: € | M56: 0 | N56: 0 | O56: 0 | P56: 0 | Q56: 0 | R56: 0 | S56: 0 | T56: 0 | U56: 0 | V56: 0 | W56: 0 | X56: 0 | Y56: 0 | Z56: 0 | AA56: 0 | AB56: 0 | AC56: 0 | AD56: 0 | AE56: 0 | AF56: 0 | AG56: 0 | AH56: 0 | AI56: 0 | AJ56: 0 | AK56: 0 | AL56: 0 | AM56: 0 | AN56: 0 | AO56: 0 | AP56: 0 | AQ56: 0 | AR56: 0 | AS56: 0 | AT56: 0 | AU56: 0 | AV56: 0 | AW56: 0 | AX56: 0 | AY56: 0 | AZ56: 0 | BB56: =sum(E56:P56) -> 0 | BC56: =sum(Q56:AB56) -> 0 | BD56: =sum(AC56:AN56) -> 0 | BE56: =sum(AO56:AZ56) -> 0 | BF56: 0
B57: Cash from Investing | M57: =M56 -> 0 | N57: =N56 -> 0 | O57: =O56 -> 0 | P57: =P56 -> 0 | Q57: =Q56 -> 0 | R57: =R56 -> 0 | S57: =S56 -> 0 | T57: =T56 -> 0 | ... AZ57: =AZ56 -> 0 | BB57: =sum(E57:P57) -> 0 | BC57: =sum(Q57:AB57) -> 0 | BD57: =sum(AC57:AN57) -> 0 | BE57: =sum(AO57:AZ57) -> 0 | BF57: =BF56 -> 0
B58: Equity injection | D58: € | S58: 0 | U58: 300000 | Z58: 2500000 | BB58: =sum(E58:P58) -> 0 | BC58: =sum(Q58:AB58) -> 2800000 | BD58: =sum(AC58:AN58) -> 0 | BE58: =sum(AO58:AZ58) -> 0 | BF58: 0
B59: Loan (CLA) | D59: € | W59: 300000 | BB59: =sum(E59:P59) -> 0 | BC59: =sum(Q59:AB59) -> 300000 | BD59: =sum(AC59:AN59) -> 0 | BE59: =sum(AO59:AZ59) -> 0 | BF59: 0
B60: Compressor WC loan (draw / repay) | E60: =E85 -> 0 | F60: =F85-E85 -> 0 | G60: =G85-F85 -> 0 | H60: =H85-G85 -> 0 | I60: =I85-H85 -> 0 | J60: =J85-I85 -> 0 | K60: =K85-J85 -> 0 | L60: =L85-K85 -> 0 | M60: =M85-L85 -> 0 | ... AZ60: =AZ85-AY85 -> 0 | BC60: =SUM(Q60:AB60) -> 0 | BD60: =SUM(AC60:AN60) -> 714000 | BE60: =SUM(AO60:AZ60) -> 0 | BF60: =BF85-BE85 -> -714000
B61: Cash from Financing | D61: € | E61: =E58+E59+E60 -> 0 | F61: =F58+F59+F60 -> 0 | G61: =G58+G59+G60 -> 0 | H61: =H58+H59+H60 -> 0 | I61: =I58+I59+I60 -> 0 | J61: =J58+J59+J60 -> 0 | K61: =K58+K59+K60 -> 0 | L61: =L58+L59+L60 -> 0 | ... AZ61: =AZ58+AZ59+AZ60 -> 0 | BB61: =sum(E61:P61) -> 0 | BC61: =sum(Q61:AB61) -> 3100000 | BD61: =sum(AC61:AN61) -> 714000 | BE61: =sum(AO61:AZ61) -> 0 | BF61: =BF58+BF59+BF60 -> -714000
B63: Total Change in Cash | D63: € | M63: =M55+M57+M61 -> -59000 | N63: =N55+N57+N61 -> -52506.667 | O63: =O55+O57+O61 -> -20013.333 | P63: =P55+P57+P61 -> -195933 | Q63: =Q55+Q57+Q61 -> -128520 | R63: =R55+R57+R61 -> -139320 | S63: =S55+S57+S61 -> -139320 | T63: =T55+T57+T61 -> -139320 | ... AZ63: =AZ55+AZ57+AZ61 -> 971789.07 | BB63: =BB61+BB57+BB55 -> -327453 | BC63: =BC61+BC57+BC55 -> 1154262 | BD63: =BD61+BD57+BD55 -> -1099780.6 | BE63: =BE61+BE57+BE55 -> 5568924.1 | BF63: =BF61+BF57+BF55 -> 16427433
B64: Beginning cash balance | D64: € | M64: 1111108 | N64: =M65 -> 1052108 | O64: =N65 -> 999601.33 | P64: =O65 -> 979588 | Q64: =P65 -> 783655 | R64: =Q65 -> 655135 | S64: =R65 -> 515815 | T64: =S65 -> 376495 | U64: =T65 -> 237175 | ... AZ64: =AY65 -> 5435271.4 | BB64: =BB63+BB65 -> 456202 | BC64: =Q64 -> 783655 | BD64: =AC64 -> 1937917 | BE64: =AO64 -> 838136.37 | BF64: =AZ65 -> 6407060.5
B65: Ending Cash Balance | D65: € | M65: =M63+M64 -> 1052108 | N65: =N64+N63 -> 999601.33 | O65: =O64+O63 -> 979588 | P65: =P64+P63 -> 783655 | Q65: =Q64+Q63 -> 655135 | R65: =R64+R63 -> 515815 | S65: =S64+S63 -> 376495 | T65: =T64+T63 -> 237175 | U65: =U64+U63 -> 387855 | ... AZ65: =AZ64+AZ63 -> 6407060.5 | BB65: =P65 -> 783655 | BC65: =BC63+BC64 -> 1937917 | BD65: =BD63+BD64 -> 838136.37 | BE65: =BE63+BE64 -> 6407060.5 | BF65: =BF63+BF64 -> 22834493
B67: BALANCE SHEET
B68: ASSETS
B69: Cash and cash equivalents | D69: € | M69: =M65 -> 1052108 | N69: =N65 -> 999601.33 | O69: =O65 -> 979588 | P69: =P65 -> 783655 | Q69: =Q65 -> 655135 | R69: =R65 -> 515815 | S69: =S65 -> 376495 | T69: =T65 -> 237175 | ... AZ69: =AZ65 -> 6407060.5 | BB69: =P69 -> 783655 | BC69: =AB69 -> 1937917 | BD69: =AN69 -> 838136.37 | BE69: =AZ69 -> 6407060.5 | BF69: =BF65 -> 22834493
B70: Deferred tax assest ("carry forward") | D70: € | M70: =M47 -> 108239 | N70: =N47 -> 118435.16 | O70: =O47 -> 113533.16 | P70: =P47 -> 177499.87 | Q70: =Q47 -> 210658.03 | R70: =R47 -> 246602.59 | S70: =S47 -> 282547.15 | T70: =T47 -> 318491.71 | ... AZ70: =AZ47 -> 469391.81 | BB70: =P70 -> 177499.87 | BC70: =AB70 -> 679500.28 | BD70: =AN70 -> 1548548.8 | BE70: =AZ70 -> 469391.81 | BF70: 0
B71: Accounts receivable (DSO-based) | D71: € | M71: =ABS(Assumptions!$D$15*(M12/30)) -> 0 | N71: =ABS(Assumptions!$D$15*(N12/30)) -> 12986.667 | O71: =ABS(Assumptions!$D$15*(O12/30)) -> 52000 | P71: =ABS(Assumptions!$D$15*(P12/30)) -> 0 | Q71: =ABS(Assumptions!$D$15*(Q12/30)) -> 0 | R71: =ABS(Assumptions!$D$15*(R12/30)) -> 0 | S71: =ABS(Assumptions!$D$15*(S12/30)) -> 0 | T71: =ABS(Assumptions!$D$15*(T12/30)) -> 0 | ... AZ71: =ABS(Assumptions!$D$15*(AZ12/30)) -> 3898833.6 | BB71: =P71 -> 0 | BC71: =AB71 -> 0 | BD71: =AN71 -> 1295521.5 | BE71: =AZ71 -> 3898833.6 | BF71: =Assumptions!$D$15/365*BF12 -> 4886973.1
B72: Inventory (DIO-based) | D72: € | M72: =ABS(Assumptions!$D$17*(M19/30)) -> 0 | N72: =ABS(Assumptions!$D$17*(N19/30)) -> 0 | O72: =ABS(Assumptions!$D$17*(O19/30)) -> 0 | P72: =ABS(Assumptions!$D$17*(P19/30)) -> 0 | Q72: =ABS(Assumptions!$D$17*(Q19/30)) -> 0 | R72: =ABS(Assumptions!$D$17*(R19/30)) -> 0 | S72: =ABS(Assumptions!$D$17*(S19/30)) -> 0 | T72: =ABS(Assumptions!$D$17*(T19/30)) -> 0 | ... AZ72: =ABS(Assumptions!$D$17*(AZ19/30)) -> 0 | BB72: =P72 -> 0 | BC72: =AB72 -> 0 | BD72: =AN72 -> 0 | BE72: =AZ72 -> 0 | BF72: 0
B73: Total Current Assets | D73: € | M73: =sum(M69:M72) -> 1160347 | N73: =sum(N69:N72) -> 1131023.2 | O73: =sum(O69:O72) -> 1145121.2 | P73: =sum(P69:P72) -> 961154.87 | Q73: =sum(Q69:Q72) -> 865793.03 | R73: =sum(R69:R72) -> 762417.59 | S73: =sum(S69:S72) -> 659042.15 | T73: =sum(T69:T72) -> 555666.71 | ... AZ73: =sum(AZ69:AZ72) -> 10775286 | BB73: =P73 -> 961154.87 | BC73: =AB73 -> 2617417.3 | BD73: =AN73 -> 3682206.7 | BE73: =AZ73 -> 10775286 | BF73: =BF69+BF71+BF72 -> 27721466
B75: Net PP&E | D75: € | M75: 0 | N75: 0 | O75: 0 | P75: 0 | Q75: 0 | R75: 0 | S75: 0 | T75: 0 | U75: 0 | V75: 0 | W75: 0 | X75: 0 | Y75: 0 | Z75: 0 | AA75: 0 | AB75: 0 | AC75: 0 | AD75: 0 | AE75: 0 | AF75: 0 | AG75: 0 | AH75: 0 | AI75: 0 | AJ75: 0 | AK75: 0 | AL75: 0 | AM75: 0 | AN75: 0 | AO75: 0 | AP75: 0 | AQ75: 0 | AR75: 0 | AS75: 0 | AT75: 0 | AU75: 0 | AV75: 0 | AW75: 0 | AX75: 0 | AY75: 0 | AZ75: 0 | BB75: =P75 -> 0 | BC75: =AB75 -> 0 | BD75: =AN75 -> 0 | BE75: =AZ75 -> 0 | BF75: 0
B76: Total Fixed Assets | D76: € | M76: =M75 -> 0 | N76: =N75 -> 0 | O76: =O75 -> 0 | P76: =P75 -> 0 | Q76: =Q75 -> 0 | R76: =R75 -> 0 | S76: =S75 -> 0 | T76: =T75 -> 0 | ... AZ76: =AZ75 -> 0 | BB76: =P76 -> 0 | BC76: =AB76 -> 0 | BD76: =AN76 -> 0 | BE76: =AZ76 -> 0 | BF76: =BF75 -> 0
B77: TOTAL ASSETS | D77: € | M77: =M73+M76 -> 1160347 | N77: =N73+N76 -> 1131023.2 | O77: =O73+O76 -> 1145121.2 | P77: =P73+P76 -> 961154.87 | Q77: =Q73+Q76 -> 865793.03 | R77: =R73+R76 -> 762417.59 | S77: =S73+S76 -> 659042.15 | T77: =T73+T76 -> 555666.71 | ... AZ77: =AZ73+AZ76 -> 10775286 | BB77: =P77 -> 961154.87 | BC77: =AB77 -> 2617417.3 | BD77: =AN77 -> 3682206.7 | BE77: =AZ77 -> 10775286 | BF77: =BF73+BF76 -> 27721466
B79: EQUITY & LIABILITIES
B80: Accounts payable (DPO-based) | D80: € | M80: =ABS(Assumptions!$D$16*(M19/30)) -> 0 | N80: =ABS(Assumptions!$D$16*(N19/30)) -> 0 | O80: =ABS(Assumptions!$D$16*(O19/30)) -> 0 | P80: =ABS(Assumptions!$D$16*(P19/30)) -> 0 | Q80: =ABS(Assumptions!$D$16*(Q19/30)) -> 0 | R80: =ABS(Assumptions!$D$16*(R19/30)) -> 0 | S80: =ABS(Assumptions!$D$16*(S19/30)) -> 0 | T80: =ABS(Assumptions!$D$16*(T19/30)) -> 0 | ... AZ80: =ABS(Assumptions!$D$16*(AZ19/30)) -> 6839603.1 | BB80: =P80 -> 0 | BC80: =AB80 -> 0 | BD80: =AN80 -> 2850145.9 | BE80: =AZ80 -> 6839603.1 | BF80: =Assumptions!$D$16/365*BF19 -> 6933199.1
B81: Total Current Liabilities | D81: € | M81: =sum(M80) -> 0 | N81: =sum(N80) -> 0 | O81: =sum(O80) -> 0 | P81: =sum(P80) -> 0 | Q81: =sum(Q80) -> 0 | R81: =sum(R80) -> 0 | S81: =sum(S80) -> 0 | T81: =sum(T80) -> 0 | ... AZ81: =sum(AZ80) -> 6839603.1 | BB81: =P81 -> 0 | BC81: =AB81 -> 0 | BD81: =AN81 -> 2850145.9 | BE81: =AZ81 -> 6839603.1 | BF81: =BF80 -> 6933199.1
B84: Loan (CLA) | D84: € | Q84: 0 | R84: 0 | S84: 0 | T84: 0 | U84: 0 | V84: =V59 | W84: =V84+W59 -> 300000 | X84: =W84 -> 300000 | Y84: =X84 -> 300000 | Z84: 0 | AA84: 0 | AB84: 0 | AC84: 0 | AD84: 0 | AE84: 0 | AF84: 0 | AG84: 0 | AH84: 0 | AI84: 0 | AJ84: 0 | AK84: 0 | AL84: 0 | AM84: 0 | AN84: 0 | AO84: 0 | AP84: 0 | AQ84: 0 | AR84: 0 | AS84: 0 | AT84: 0 | AU84: 0 | AV84: 0 | AW84: 0 | AX84: 0 | AY84: 0 | AZ84: 0 | BB84: 0 | BC84: =AB84 -> 0 | BD84: =AN84 -> 0 | BE84: =AZ84 -> 0 | BF84: 0
B85: Compressor WC loan (supplier financing) | E85: =MIN(E96,1000)*714 -> 0 | F85: =MIN(F96,1000)*714 -> 0 | G85: =MIN(G96,1000)*714 -> 0 | H85: =MIN(H96,1000)*714 -> 0 | I85: =MIN(I96,1000)*714 -> 0 | J85: =MIN(J96,1000)*714 -> 0 | K85: =MIN(K96,1000)*714 -> 0 | L85: =MIN(L96,1000)*714 -> 0 | ... AZ85: =MIN(AZ96,1000)*714 -> 714000 | BC85: =AB85 -> 0 | BD85: =AN85 -> 714000 | BE85: =AZ85 -> 714000 | BF85: 0
B86: Total Long-Term Liabilities | D86: € | E86: =E83+E84+E85 -> 0 | F86: =F83+F84+F85 -> 0 | G86: =G83+G84+G85 -> 0 | H86: =H83+H84+H85 -> 0 | I86: =I83+I84+I85 -> 0 | J86: =J83+J84+J85 -> 0 | K86: =K83+K84+K85 -> 0 | L86: =L83+L84+L85 -> 0 | ... AZ86: =AZ83+AZ84+AZ85 -> 714000 | BB86: =P86 -> 0 | BC86: =AB86 -> 0 | BD86: =AN86 -> 714000 | BE86: =AZ86 -> 714000 | BF86: =sum(BF83:BF85) -> 0
B88: Share capital + premium | D88: € | M88: =M64 -> 1111108 | N88: =M88 -> 1111108 | O88: =N88 -> 1111108 | P88: =O88 -> 1111108 | Q88: =P88 -> 1111108 | R88: =Q88 -> 1111108 | S88: =R88 -> 1111108 | T88: =S88 -> 1111108 | U88: =T88 -> 1111108 | ... Y88: =X88 -> 1111108 | Z88: =Y88+Y84 -> 1411108 | AA88: =Z88 -> 1411108 | AB88: =AA88 -> 1411108 | AC88: =AB88 -> 1411108 | AD88: =AC88 -> 1411108 | AE88: =AD88 -> 1411108 | AF88: =AE88 -> 1411108 | AG88: =AF88 -> 1411108 | AH88: =AG88 -> 1411108 | ... AZ88: =AY88 -> 1411108 | BB88: =P88 -> 1111108 | BC88: =AB88 -> 1411108 | BD88: =AN88 -> 1411108 | BE88: =AZ88 -> 1411108 | BF88: =BE88 -> 1411108
B89: Cumulative equity injections | D89: € | M89: =M58+M58 -> 0 | N89: =M89+N58 -> 0 | O89: =N89+O58 -> 0 | P89: =O89+P58 -> 0 | Q89: =P89+Q58 -> 0 | R89: =Q89+R58 -> 0 | S89: =R89+S58 -> 0 | T89: =S89+T58 -> 0 | U89: =T89+U58 -> 300000 | ... AZ89: =AY89+AZ58 -> 2800000 | BB89: =P89 -> 0 | BC89: =AB89 -> 2800000 | BD89: =AN89 -> 2800000 | BE89: =AZ89 -> 2800000 | BF89: =BE89 -> 2800000
B90: Retained earnings (cumulative net income) | D90: € | M90: =M50 -> -59000 | N90: =M90+N44 -> -98520 | O90: =N90+O44 -> -79520 | P90: =O90+P44 -> -327453 | Q90: =P90+Q44 -> -455973 | R90: =Q90+R44 -> -595293 | S90: =R90+S44 -> -734613 | T90: =S90+T44 -> -873933 | U90: =T90+U44 -> -1023253 | ... AZ90: =AY90+AZ44 -> -1458817.1 | BB90: =P90 -> -327453 | BC90: =AB90 -> -2273191 | BD90: =AN90 -> -5641596 | BE90: =AZ90 -> -1458817.1 | BF90: =BE90+BF44 -> 16577159
B91: Total Equity | D91: € | M91: =M88+M89+M90+M47 -> 1160347 | N91: =N88+N89+N90+N47 -> 1131023.2 | O91: =O88+O89+O90+O47 -> 1145121.2 | P91: =P88+P89+P90+P47 -> 961154.87 | Q91: =Q88+Q89+Q90+Q47 -> 865793.03 | R91: =R88+R89+R90+R47 -> 762417.59 | S91: =S88+S89+S90+S47 -> 659042.15 | T91: =T88+T89+T90+T47 -> 555666.71 | ... AZ91: =AZ88+AZ89+AZ90+AZ47 -> 3221682.7 | BB91: =P91 -> 961154.87 | BC91: =AB91 -> 2617417.3 | BD91: =AN91 -> 118060.79 | BE91: =AZ91 -> 3221682.7 | BF91: =sum(BF88:BF90) -> 20788267
B92: TOTAL EQUITY & LIABILITIES | D92: € | M92: =M81+M86+M91 -> 1160347 | N92: =N81+N86+N91 -> 1131023.2 | O92: =O81+O86+O91 -> 1145121.2 | P92: =P81+P86+P91 -> 961154.87 | Q92: =Q81+Q86+Q91 -> 865793.03 | R92: =R81+R86+R91 -> 762417.59 | S92: =S81+S86+S91 -> 659042.15 | T92: =T81+T86+T91 -> 555666.71 | ... AZ92: =AZ81+AZ86+AZ91 -> 10775286 | BB92: =P92 -> 961154.87 | BC92: =AB92 -> 2617417.3 | BD92: =AN92 -> 3682206.7 | BE92: =AZ92 -> 10775286 | BF92: =BF81+BF86+BF91 -> 27721466
B94: CHECK (Total Assets − Total E&L = 0) | M94: =M77-M92 -> 0 | N94: =N77-N92 -> 2.3283064e-10 | O94: =O77-O92 -> 0 | P94: =P77-P92 -> 0 | Q94: =Q77-Q92 -> 0 | R94: =R77-R92 -> 0 | S94: =S77-S92 -> 0 | T94: =T77-T92 -> 0 | ... AZ94: =AZ77-AZ92 -> -1.8626451e-09 | BB94: =BB77-BB92 -> 0 | BC94: =BC77-BC92 -> 0 | BD94: =BD77-BD92 -> -9.3132257e-10 | BE94: =BE77-BE92 -> -1.8626451e-09 | BF94: =BF77-BF92 -> 0
B96: Cumulative turbineketels (helper) | E96: ='Revenue Forecast'!E41 -> 0 | F96: =E96+'Revenue Forecast'!F41 -> 0 | G96: =F96+'Revenue Forecast'!G41 -> 0 | H96: =G96+'Revenue Forecast'!H41 -> 0 | I96: =H96+'Revenue Forecast'!I41 -> 0 | J96: =I96+'Revenue Forecast'!J41 -> 0 | K96: =J96+'Revenue Forecast'!K41 -> 0 | L96: =K96+'Revenue Forecast'!L41 -> 0 | M96: =L96+'Revenue Forecast'!M41 -> 0 | ... AZ96: =AY96+'Revenue Forecast'!AZ41 -> 4000

Sheet Revenue Forecast
B1: Tarnoc B.V. — Revenue Forecast (€, ex VAT unless noted)
E2: 2025 | Q2: 2026 | AC2: 2027 | AO2: 2028
E3: 45658 | F3: 45689 | G3: 45717 | H3: 45748 | I3: 45778 | J3: 45809 | K3: 45839 | L3: 45870 | M3: 45901 | N3: 45931 | O3: 45962 | P3: 45992 | Q3: 46023 | R3: 46054 | S3: 46082 | T3: 46113 | U3: 46143 | V3: 46174 | W3: 46204 | X3: 46235 | Y3: 46266 | Z3: 46296 | AA3: 46327 | AB3: 46357 | AC3: 46388 | AD3: 46419 | AE3: 46447 | AF3: 46478 | AG3: 46508 | AH3: 46539 | AI3: 46569 | AJ3: 46600 | AK3: 46631 | AL3: 46661 | AM3: 46692 | AN3: 46722 | AO3: 46753 | AP3: 46784 | AQ3: 46813 | AR3: 46844 | AS3: 46874 | AT3: 46905 | AU3: 46935 | AV3: 46966 | AW3: 46997 | AX3: 47027 | AY3: 47058 | AZ3: 47088 | BB3: 2025 | BC3: 2026 | BD3: 2027 | BE3: 2028 | BF3: 2029
AB4: 2 | AC4: 3 | AD4: 4 | AE4: 5 | AF4: 6 | AG4: 7 | AH4: 8 | AI4: 9 | AJ4: 10 | AK4: 11 | AL4: 12 | AM4: 13 | AN4: 14 | AO4: 15 | AP4: 16 | AQ4: 17 | AR4: 18 | AS4: 19 | AT4: 20 | AU4: 21 | AV4: 22 | AW4: 23 | AX4: 24 | AY4: 25 | AZ4: 26
B5: TURBINEKETEL (TTK)
B6: TTK units sold | D6: # | Q6: {=IF(YEAR(Q$3)=2026,0,ROUND(EXP((LN(Assumptions!$E$23/Assumptions!$D$23)/12)*((YEAR(Q$3)-2027)*12+MONTH(Q$3)-1))/SUMPRODUCT(EXP((LN(Assumptions!$E$23/Assumptions!$D$23)/12)*(ROW(INDIRECT("1:24"))-1)))*SUM(Assumptions!$D$23:$E$23),0))} -> 0 | R6: {=IF(YEAR(R$3)=2026,0,ROUND(EXP((LN(Assumptions!$E$23/Assumptions!$D$23)/12)*((YEAR(R$3)-2027)*12+MONTH(R$3)-1))/SUMPRODUCT(EXP((LN(Assumptions!$E$23/Assumptions!$D$23)/12)*(ROW(INDIRECT("1:24"))-1)))*SUM(Assumptions!$D$23:$E$23),0))} -> 0 | S6: {=IF(YEAR(S$3)=2026,0,ROUND(EXP((LN(Assumptions!$E$23/Assumptions!$D$23)/12)*((YEAR(S$3)-2027)*12+MONTH(S$3)-1))/SUMPRODUCT(EXP((LN(Assumptions!$E$23/Assumptions!$D$23)/12)*(ROW(INDIRECT("1:24"))-1)))*SUM(Assumptions!$D$23:$E$23),0))} -> 0 | T6: {=IF(YEAR(T$3)=2026,0,ROUND(EXP((LN(Assumptions!$E$23/Assumptions!$D$23)/12)*((YEAR(T$3)-2027)*12+MONTH(T$3)-1))/SUMPRODUCT(EXP((LN(Assumptions!$E$23/Assumptions!$D$23)/12)*(ROW(INDIRECT("1:24"))-1)))*SUM(Assumptions!$D$23:$E$23),0))} -> 0 | U6: {=IF(YEAR(U$3)=2026,0,ROUND(EXP((LN(Assumptions!$E$23/Assumptions!$D$23)/12)*((YEAR(U$3)-2027)*12+MONTH(U$3)-1))/SUMPRODUCT(EXP((LN(Assumptions!$E$23/Assumptions!$D$23)/12)*(ROW(INDIRECT("1:24"))-1)))*SUM(Assumptions!$D$23:$E$23),0))} -> 0 | V6: {=IF(YEAR(V$3)=2026,0,ROUND(EXP((LN(Assumptions!$E$23/Assumptions!$D$23)/12)*((YEAR(V$3)-2027)*12+MONTH(V$3)-1))/SUMPRODUCT(EXP((LN(Assumptions!$E$23/Assumptions!$D$23)/12)*(ROW(INDIRECT("1:24"))-1)))*SUM(Assumptions!$D$23:$E$23),0))} -> 0 | W6: {=IF(YEAR(W$3)=2026,0,ROUND(EXP((LN(Assumptions!$E$23/Assumptions!$D$23)/12)*((YEAR(W$3)-2027)*12+MONTH(W$3)-1))/SUMPRODUCT(EXP((LN(Assumptions!$E$23/Assumptions!$D$23)/12)*(ROW(INDIRECT("1:24"))-1)))*SUM(Assumptions!$D$23:$E$23),0))} -> 0 | X6: {=IF(YEAR(X$3)=2026,0,ROUND(EXP((LN(Assumptions!$E$23/Assumptions!$D$23)/12)*((YEAR(X$3)-2027)*12+MONTH(X$3)-1))/SUMPRODUCT(EXP((LN(Assumptions!$E$23/Assumptions!$D$23)/12)*(ROW(INDIRECT("1:24"))-1)))*SUM(Assumptions!$D$23:$E$23),0))} -> 0 | ... AM6: {=IF(YEAR(AM$3)=2026,0,ROUND(EXP((LN(Assumptions!$E$23/Assumptions!$D$23)/12)*((YEAR(AM$3)-2027)*12+MONTH(AM$3)-1))/SUMPRODUCT(EXP((LN(Assumptions!$E$23/Assumptions!$D$23)/12)*(ROW(INDIRECT("1:24"))-1)))*SUM(Assumptions!$D$23:$E$23),0))} -> 48 | AN6: =Assumptions!$D$23-SUM(AC6:AM6) -> 53 | AO6: {=IF(YEAR(AO$3)=2026,0,ROUND(EXP((LN(Assumptions!$E$23/Assumptions!$D$23)/12)*((YEAR(AO$3)-2027)*12+MONTH(AO$3)-1))/SUMPRODUCT(EXP((LN(Assumptions!$E$23/Assumptions!$D$23)/12)*(ROW(INDIRECT("1:24"))-1)))*SUM(Assumptions!$D$23:$E$23),0))} -> 58 | AP6: {=IF(YEAR(AP$3)=2026,0,ROUND(EXP((LN(Assumptions!$E$23/Assumptions!$D$23)/12)*((YEAR(AP$3)-2027)*12+MONTH(AP$3)-1))/SUMPRODUCT(EXP((LN(Assumptions!$E$23/Assumptions!$D$23)/12)*(ROW(INDIRECT("1:24"))-1)))*SUM(Assumptions!$D$23:$E$23),0))} -> 63 | AQ6: {=IF(YEAR(AQ$3)=2026,0,ROUND(EXP((LN(Assumptions!$E$23/Assumptions!$D$23)/12)*((YEAR(AQ$3)-2027)*12+MONTH(AQ$3)-1))/SUMPRODUCT(EXP((LN(Assumptions!$E$23/Assumptions!$D$23)/12)*(ROW(INDIRECT("1:24"))-1)))*SUM(Assumptions!$D$23:$E$23),0))} -> 69 | AR6: {=IF(YEAR(AR$3)=2026,0,ROUND(EXP((LN(Assumptions!$E$23/Assumptions!$D$23)/12)*((YEAR(AR$3)-2027)*12+MONTH(AR$3)-1))/SUMPRODUCT(EXP((LN(Assumptions!$E$23/Assumptions!$D$23)/12)*(ROW(INDIRECT("1:24"))-1)))*SUM(Assumptions!$D$23:$E$23),0))} -> 76 | AS6: {=IF(YEAR(AS$3)=2026,0,ROUND(EXP((LN(Assumptions!$E$23/Assumptions!$D$23)/12)*((YEAR(AS$3)-2027)*12+MONTH(AS$3)-1))/SUMPRODUCT(EXP((LN(Assumptions!$E$23/Assumptions!$D$23)/12)*(ROW(INDIRECT("1:24"))-1)))*SUM(Assumptions!$D$23:$E$23),0))} -> 83 | AT6: {=IF(YEAR(AT$3)=2026,0,ROUND(EXP((LN(Assumptions!$E$23/Assumptions!$D$23)/12)*((YEAR(AT$3)-2027)*12+MONTH(AT$3)-1))/SUMPRODUCT(EXP((LN(Assumptions!$E$23/Assumptions!$D$23)/12)*(ROW(INDIRECT("1:24"))-1)))*SUM(Assumptions!$D$23:$E$23),0))} -> 91 | AU6: {=IF(YEAR(AU$3)=2026,0,ROUND(EXP((LN(Assumptions!$E$23/Assumptions!$D$23)/12)*((YEAR(AU$3)-2027)*12+MONTH(AU$3)-1))/SUMPRODUCT(EXP((LN(Assumptions!$E$23/Assumptions!$D$23)/12)*(ROW(INDIRECT("1:24"))-1)))*SUM(Assumptions!$D$23:$E$23),0))} -> 100 | AV6: {=IF(YEAR(AV$3)=2026,0,ROUND(EXP((LN(Assumptions!$E$23/Assumptions!$D$23)/12)*((YEAR(AV$3)-2027)*12+MONTH(AV$3)-1))/SUMPRODUCT(EXP((LN(Assumptions!$E$23/Assumptions!$D$23)/12)*(ROW(INDIRECT("1:24"))-1)))*SUM(Assumptions!$D$23:$E$23),0))} -> 109 | ... AY6: {=IF(YEAR(AY$3)=2026,0,ROUND(EXP((LN(Assumptions!$E$23/Assumptions!$D$23)/12)*((YEAR(AY$3)-2027)*12+MONTH(AY$3)-1))/SUMPRODUCT(EXP((LN(Assumptions!$E$23/Assumptions!$D$23)/12)*(ROW(INDIRECT("1:24"))-1)))*SUM(Assumptions!$D$23:$E$23),0))} -> 144 | AZ6: =Assumptions!$E$23-SUM(AO6:AY6) -> 156 | BB6: =SUM(E6:P6) -> 0 | BC6: =SUM(Q6:AB6) -> 0 | BD6: =SUM(AC6:AN6) -> 400 | BE6: =SUM(AO6:AZ6) -> 1200 | BF6: =Assumptions!$F$23 -> 2400
B7: TTK Revenue | D7: € | Q7: =Q6*Assumptions!$C$30 -> 0 | R7: =R6*Assumptions!$C$30 -> 0 | S7: =S6*Assumptions!$C$30 -> 0 | T7: =T6*Assumptions!$C$30 -> 0 | U7: =U6*Assumptions!$C$30 -> 0 | V7: =V6*Assumptions!$C$30 -> 0 | W7: =W6*Assumptions!$C$30 -> 0 | X7: =X6*Assumptions!$C$30 -> 0 | ... AZ7: =AZ6*Assumptions!$C$30 -> 1329996.7 | BB7: =SUM(E7:P7) -> 0 | BC7: =SUM(Q7:AB7) -> 0 | BD7: =SUM(AC7:AN7) -> 3410248 | BE7: =SUM(AO7:AZ7) -> 10230744 | BF7: =BF6*Assumptions!$C$30 -> 20461488
B8: TTK upsell | D8: € | Q8: =Q6*SUMPRODUCT(Assumptions!$E$117:$F$119) -> 0 | R8: =R6*SUMPRODUCT(Assumptions!$E$117:$F$119) -> 0 | S8: =S6*SUMPRODUCT(Assumptions!$E$117:$F$119) -> 0 | T8: =T6*SUMPRODUCT(Assumptions!$E$117:$F$119) -> 0 | U8: =U6*SUMPRODUCT(Assumptions!$E$117:$F$119) -> 0 | V8: =V6*SUMPRODUCT(Assumptions!$E$117:$F$119) -> 0 | W8: =W6*SUMPRODUCT(Assumptions!$E$117:$F$119) -> 0 | X8: =X6*SUMPRODUCT(Assumptions!$E$117:$F$119) -> 0 | ... AB8: =AB6*SUMPRODUCT(Assumptions!$E$117:$F$119) -> 0 | AC8: =AC6*SUMPRODUCT(Assumptions!$E$117:$E$119,Assumptions!$F$117:$F$119) -> 9555.0392 | AD8: =AD6*SUMPRODUCT(Assumptions!$E$117:$E$119,Assumptions!$F$117:$F$119) -> 10560.833 | AE8: =AE6*SUMPRODUCT(Assumptions!$E$117:$E$119,Assumptions!$F$117:$F$119) -> 11566.626 | AF8: =AF6*SUMPRODUCT(Assumptions!$E$117:$E$119,Assumptions!$F$117:$F$119) -> 12572.42 | AG8: =AG6*SUMPRODUCT(Assumptions!$E$117:$E$119,Assumptions!$F$117:$F$119) -> 14081.11 | AH8: =AH6*SUMPRODUCT(Assumptions!$E$117:$E$119,Assumptions!$F$117:$F$119) -> 15086.904 | AI8: =AI6*SUMPRODUCT(Assumptions!$E$117:$E$119,Assumptions!$F$117:$F$119) -> 16595.594 | AJ8: =AJ6*SUMPRODUCT(Assumptions!$E$117:$E$119,Assumptions!$F$117:$F$119) -> 18104.285 | ... AZ8: =AZ6*SUMPRODUCT(Assumptions!$E$117:$E$119,Assumptions!$F$117:$F$119) -> 78451.901 | BB8: =SUM(E8:P8) -> 0 | BC8: =SUM(Q8:AB8) -> 0 | BD8: =SUM(AC8:AN8) -> 201158.72 | BE8: =SUM(AO8:AZ8) -> 603476.16 | BF8: =BF6*SUMPRODUCT(Assumptions!$E$117:$E$119,Assumptions!$F$117:$F$119) -> 1206952.3
B9: Total TTK Revenue | D9: € | Q9: =sum(Q7:Q8) -> 0 | R9: =sum(R7:R8) -> 0 | S9: =sum(S7:S8) -> 0 | T9: =sum(T7:T8) -> 0 | U9: =sum(U7:U8) -> 0 | V9: =sum(V7:V8) -> 0 | W9: =sum(W7:W8) -> 0 | X9: =sum(X7:X8) -> 0 | ... AZ9: =sum(AZ7:AZ8) -> 1408448.6 | BB9: =SUM(E9:P9) -> 0 | BC9: =SUM(Q9:AB9) -> 0 | BD9: =SUM(AC9:AN9) -> 3611406.7 | BE9: =SUM(AO9:AZ9) -> 10834220 | BF9: =SUM(BF6:BF8) -> 21670840
B11: COMBI
B12: Combi units sold | D12: # | Q12: {=IF(YEAR(Q$3)=2026,0,ROUND(EXP((LN(Assumptions!$E$24/Assumptions!$D$24)/12)*((YEAR(Q$3)-2027)*12+MONTH(Q$3)-1))/SUMPRODUCT(EXP((LN(Assumptions!$E$24/Assumptions!$D$24)/12)*(ROW(INDIRECT("1:24"))-1)))*SUM(Assumptions!$D$24:$E$24),0))} -> 0 | R12: {=IF(YEAR(R$3)=2026,0,ROUND(EXP((LN(Assumptions!$E$24/Assumptions!$D$24)/12)*((YEAR(R$3)-2027)*12+MONTH(R$3)-1))/SUMPRODUCT(EXP((LN(Assumptions!$E$24/Assumptions!$D$24)/12)*(ROW(INDIRECT("1:24"))-1)))*SUM(Assumptions!$D$24:$E$24),0))} -> 0 | S12: {=IF(YEAR(S$3)=2026,0,ROUND(EXP((LN(Assumptions!$E$24/Assumptions!$D$24)/12)*((YEAR(S$3)-2027)*12+MONTH(S$3)-1))/SUMPRODUCT(EXP((LN(Assumptions!$E$24/Assumptions!$D$24)/12)*(ROW(INDIRECT("1:24"))-1)))*SUM(Assumptions!$D$24:$E$24),0))} -> 0 | T12: {=IF(YEAR(T$3)=2026,0,ROUND(EXP((LN(Assumptions!$E$24/Assumptions!$D$24)/12)*((YEAR(T$3)-2027)*12+MONTH(T$3)-1))/SUMPRODUCT(EXP((LN(Assumptions!$E$24/Assumptions!$D$24)/12)*(ROW(INDIRECT("1:24"))-1)))*SUM(Assumptions!$D$24:$E$24),0))} -> 0 | U12: {=IF(YEAR(U$3)=2026,0,ROUND(EXP((LN(Assumptions!$E$24/Assumptions!$D$24)/12)*((YEAR(U$3)-2027)*12+MONTH(U$3)-1))/SUMPRODUCT(EXP((LN(Assumptions!$E$24/Assumptions!$D$24)/12)*(ROW(INDIRECT("1:24"))-1)))*SUM(Assumptions!$D$24:$E$24),0))} -> 0 | V12: {=IF(YEAR(V$3)=2026,0,ROUND(EXP((LN(Assumptions!$E$24/Assumptions!$D$24)/12)*((YEAR(V$3)-2027)*12+MONTH(V$3)-1))/SUMPRODUCT(EXP((LN(Assumptions!$E$24/Assumptions!$D$24)/12)*(ROW(INDIRECT("1:24"))-1)))*SUM(Assumptions!$D$24:$E$24),0))} -> 0 | W12: {=IF(YEAR(W$3)=2026,0,ROUND(EXP((LN(Assumptions!$E$24/Assumptions!$D$24)/12)*((YEAR(W$3)-2027)*12+MONTH(W$3)-1))/SUMPRODUCT(EXP((LN(Assumptions!$E$24/Assumptions!$D$24)/12)*(ROW(INDIRECT("1:24"))-1)))*SUM(Assumptions!$D$24:$E$24),0))} -> 0 | X12: {=IF(YEAR(X$3)=2026,0,ROUND(EXP((LN(Assumptions!$E$24/Assumptions!$D$24)/12)*((YEAR(X$3)-2027)*12+MONTH(X$3)-1))/SUMPRODUCT(EXP((LN(Assumptions!$E$24/Assumptions!$D$24)/12)*(ROW(INDIRECT("1:24"))-1)))*SUM(Assumptions!$D$24:$E$24),0))} -> 0 | ... AM12: {=IF(YEAR(AM$3)=2026,0,ROUND(EXP((LN(Assumptions!$E$24/Assumptions!$D$24)/12)*((YEAR(AM$3)-2027)*12+MONTH(AM$3)-1))/SUMPRODUCT(EXP((LN(Assumptions!$E$24/Assumptions!$D$24)/12)*(ROW(INDIRECT("1:24"))-1)))*SUM(Assumptions!$D$24:$E$24),0))} -> 36 | AN12: =Assumptions!$D$24-SUM(AC12:AM12) -> 39 | AO12: {=IF(YEAR(AO$3)=2026,0,ROUND(EXP((LN(Assumptions!$E$24/Assumptions!$D$24)/12)*((YEAR(AO$3)-2027)*12+MONTH(AO$3)-1))/SUMPRODUCT(EXP((LN(Assumptions!$E$24/Assumptions!$D$24)/12)*(ROW(INDIRECT("1:24"))-1)))*SUM(Assumptions!$D$24:$E$24),0))} -> 43 | AP12: {=IF(YEAR(AP$3)=2026,0,ROUND(EXP((LN(Assumptions!$E$24/Assumptions!$D$24)/12)*((YEAR(AP$3)-2027)*12+MONTH(AP$3)-1))/SUMPRODUCT(EXP((LN(Assumptions!$E$24/Assumptions!$D$24)/12)*(ROW(INDIRECT("1:24"))-1)))*SUM(Assumptions!$D$24:$E$24),0))} -> 47 | AQ12: {=IF(YEAR(AQ$3)=2026,0,ROUND(EXP((LN(Assumptions!$E$24/Assumptions!$D$24)/12)*((YEAR(AQ$3)-2027)*12+MONTH(AQ$3)-1))/SUMPRODUCT(EXP((LN(Assumptions!$E$24/Assumptions!$D$24)/12)*(ROW(INDIRECT("1:24"))-1)))*SUM(Assumptions!$D$24:$E$24),0))} -> 52 | AR12: {=IF(YEAR(AR$3)=2026,0,ROUND(EXP((LN(Assumptions!$E$24/Assumptions!$D$24)/12)*((YEAR(AR$3)-2027)*12+MONTH(AR$3)-1))/SUMPRODUCT(EXP((LN(Assumptions!$E$24/Assumptions!$D$24)/12)*(ROW(INDIRECT("1:24"))-1)))*SUM(Assumptions!$D$24:$E$24),0))} -> 57 | AS12: {=IF(YEAR(AS$3)=2026,0,ROUND(EXP((LN(Assumptions!$E$24/Assumptions!$D$24)/12)*((YEAR(AS$3)-2027)*12+MONTH(AS$3)-1))/SUMPRODUCT(EXP((LN(Assumptions!$E$24/Assumptions!$D$24)/12)*(ROW(INDIRECT("1:24"))-1)))*SUM(Assumptions!$D$24:$E$24),0))} -> 62 | AT12: {=IF(YEAR(AT$3)=2026,0,ROUND(EXP((LN(Assumptions!$E$24/Assumptions!$D$24)/12)*((YEAR(AT$3)-2027)*12+MONTH(AT$3)-1))/SUMPRODUCT(EXP((LN(Assumptions!$E$24/Assumptions!$D$24)/12)*(ROW(INDIRECT("1:24"))-1)))*SUM(Assumptions!$D$24:$E$24),0))} -> 68 | AU12: {=IF(YEAR(AU$3)=2026,0,ROUND(EXP((LN(Assumptions!$E$24/Assumptions!$D$24)/12)*((YEAR(AU$3)-2027)*12+MONTH(AU$3)-1))/SUMPRODUCT(EXP((LN(Assumptions!$E$24/Assumptions!$D$24)/12)*(ROW(INDIRECT("1:24"))-1)))*SUM(Assumptions!$D$24:$E$24),0))} -> 75 | AV12: {=IF(YEAR(AV$3)=2026,0,ROUND(EXP((LN(Assumptions!$E$24/Assumptions!$D$24)/12)*((YEAR(AV$3)-2027)*12+MONTH(AV$3)-1))/SUMPRODUCT(EXP((LN(Assumptions!$E$24/Assumptions!$D$24)/12)*(ROW(INDIRECT("1:24"))-1)))*SUM(Assumptions!$D$24:$E$24),0))} -> 82 | ... AY12: {=IF(YEAR(AY$3)=2026,0,ROUND(EXP((LN(Assumptions!$E$24/Assumptions!$D$24)/12)*((YEAR(AY$3)-2027)*12+MONTH(AY$3)-1))/SUMPRODUCT(EXP((LN(Assumptions!$E$24/Assumptions!$D$24)/12)*(ROW(INDIRECT("1:24"))-1)))*SUM(Assumptions!$D$24:$E$24),0))} -> 108 | AZ12: =Assumptions!$E$24-SUM(AO12:AY12) -> 118 | BB12: =SUM(E12:P12) -> 0 | BC12: =SUM(Q12:AB12) -> 0 | BD12: =SUM(AC12:AN12) -> 300 | BE12: =SUM(AO12:AZ12) -> 900 | BF12: =Assumptions!$F$24 -> 1800
B13: Combi Revenue | D13: € | Q13: =Q12*Assumptions!$C$33 -> 0 | R13: =R12*Assumptions!$C$33 -> 0 | S13: =S12*Assumptions!$C$33 -> 0 | T13: =T12*Assumptions!$C$33 -> 0 | U13: =U12*Assumptions!$C$33 -> 0 | V13: =V12*Assumptions!$C$33 -> 0 | W13: =W12*Assumptions!$C$33 -> 0 | X13: =X12*Assumptions!$C$33 -> 0 | ... AZ13: =AZ12*Assumptions!$C$33 -> 1271767.4 | BB13: =SUM(E13:P13) -> 0 | BC13: =SUM(Q13:AB13) -> 0 | BD13: =SUM(AC13:AN13) -> 3233307 | BE13: =SUM(AO13:AZ13) -> 9699921 | BF13: =BF12*Assumptions!$C$33 -> 19399842
B14: Combi upsell | D14: € | Q14: =Q12*SUMPRODUCT(Assumptions!$E$117:$E$119,Assumptions!$F$117:$F$119) -> 0 | R14: =R12*SUMPRODUCT(Assumptions!$E$117:$E$119,Assumptions!$F$117:$F$119) -> 0 | S14: =S12*SUMPRODUCT(Assumptions!$E$117:$E$119,Assumptions!$F$117:$F$119) -> 0 | T14: =T12*SUMPRODUCT(Assumptions!$E$117:$E$119,Assumptions!$F$117:$F$119) -> 0 | U14: =U12*SUMPRODUCT(Assumptions!$E$117:$E$119,Assumptions!$F$117:$F$119) -> 0 | V14: =V12*SUMPRODUCT(Assumptions!$E$117:$E$119,Assumptions!$F$117:$F$119) -> 0 | W14: =W12*SUMPRODUCT(Assumptions!$E$117:$E$119,Assumptions!$F$117:$F$119) -> 0 | X14: =X12*SUMPRODUCT(Assumptions!$E$117:$E$119,Assumptions!$F$117:$F$119) -> 0 | ... AZ14: =AZ12*SUMPRODUCT(Assumptions!$E$117:$E$119,Assumptions!$F$117:$F$119) -> 59341.822 | BB14: =SUM(E14:P14) -> 0 | BC14: =SUM(Q14:AB14) -> 0 | BD14: =SUM(AC14:AN14) -> 150869.04 | BE14: =SUM(AO14:AZ14) -> 452607.12 | BF14: =BF12*SUMPRODUCT(Assumptions!$E$117:$E$119,Assumptions!$F$117:$F$119) -> 905214.24
B15: Total Combi Revenue | D15: € | Q15: =sum(Q13:Q14) -> 0 | R15: =sum(R13:R14) -> 0 | S15: =sum(S13:S14) -> 0 | T15: =sum(T13:T14) -> 0 | U15: =sum(U13:U14) -> 0 | V15: =sum(V13:V14) -> 0 | W15: =sum(W13:W14) -> 0 | X15: =sum(X13:X14) -> 0 | ... AZ15: =sum(AZ13:AZ14) -> 1331109.2 | BB15: =SUM(E15:P15) -> 0 | BC15: =SUM(Q15:AB15) -> 0 | BD15: =SUM(AC15:AN15) -> 3384176 | BE15: =SUM(AO15:AZ15) -> 10152528 | BF15: =sum(BF13:BF14) -> 20305056
B17: COMBI+
B18: Combi+ units sold | D18: # | Q18: {=IF(YEAR(Q$3)=2026,0,ROUND(EXP((LN(Assumptions!$E$25/Assumptions!$D$25)/12)*((YEAR(Q$3)-2027)*12+MONTH(Q$3)-1))/SUMPRODUCT(EXP((LN(Assumptions!$E$25/Assumptions!$D$25)/12)*(ROW(INDIRECT("1:24"))-1)))*SUM(Assumptions!$D$25:$E$25),0))} -> 0 | R18: {=IF(YEAR(R$3)=2026,0,ROUND(EXP((LN(Assumptions!$E$25/Assumptions!$D$25)/12)*((YEAR(R$3)-2027)*12+MONTH(R$3)-1))/SUMPRODUCT(EXP((LN(Assumptions!$E$25/Assumptions!$D$25)/12)*(ROW(INDIRECT("1:24"))-1)))*SUM(Assumptions!$D$25:$E$25),0))} -> 0 | S18: {=IF(YEAR(S$3)=2026,0,ROUND(EXP((LN(Assumptions!$E$25/Assumptions!$D$25)/12)*((YEAR(S$3)-2027)*12+MONTH(S$3)-1))/SUMPRODUCT(EXP((LN(Assumptions!$E$25/Assumptions!$D$25)/12)*(ROW(INDIRECT("1:24"))-1)))*SUM(Assumptions!$D$25:$E$25),0))} -> 0 | T18: {=IF(YEAR(T$3)=2026,0,ROUND(EXP((LN(Assumptions!$E$25/Assumptions!$D$25)/12)*((YEAR(T$3)-2027)*12+MONTH(T$3)-1))/SUMPRODUCT(EXP((LN(Assumptions!$E$25/Assumptions!$D$25)/12)*(ROW(INDIRECT("1:24"))-1)))*SUM(Assumptions!$D$25:$E$25),0))} -> 0 | U18: {=IF(YEAR(U$3)=2026,0,ROUND(EXP((LN(Assumptions!$E$25/Assumptions!$D$25)/12)*((YEAR(U$3)-2027)*12+MONTH(U$3)-1))/SUMPRODUCT(EXP((LN(Assumptions!$E$25/Assumptions!$D$25)/12)*(ROW(INDIRECT("1:24"))-1)))*SUM(Assumptions!$D$25:$E$25),0))} -> 0 | V18: {=IF(YEAR(V$3)=2026,0,ROUND(EXP((LN(Assumptions!$E$25/Assumptions!$D$25)/12)*((YEAR(V$3)-2027)*12+MONTH(V$3)-1))/SUMPRODUCT(EXP((LN(Assumptions!$E$25/Assumptions!$D$25)/12)*(ROW(INDIRECT("1:24"))-1)))*SUM(Assumptions!$D$25:$E$25),0))} -> 0 | W18: {=IF(YEAR(W$3)=2026,0,ROUND(EXP((LN(Assumptions!$E$25/Assumptions!$D$25)/12)*((YEAR(W$3)-2027)*12+MONTH(W$3)-1))/SUMPRODUCT(EXP((LN(Assumptions!$E$25/Assumptions!$D$25)/12)*(ROW(INDIRECT("1:24"))-1)))*SUM(Assumptions!$D$25:$E$25),0))} -> 0 | X18: {=IF(YEAR(X$3)=2026,0,ROUND(EXP((LN(Assumptions!$E$25/Assumptions!$D$25)/12)*((YEAR(X$3)-2027)*12+MONTH(X$3)-1))/SUMPRODUCT(EXP((LN(Assumptions!$E$25/Assumptions!$D$25)/12)*(ROW(INDIRECT("1:24"))-1)))*SUM(Assumptions!$D$25:$E$25),0))} -> 0 | ... AM18: {=IF(YEAR(AM$3)=2026,0,ROUND(EXP((LN(Assumptions!$E$25/Assumptions!$D$25)/12)*((YEAR(AM$3)-2027)*12+MONTH(AM$3)-1))/SUMPRODUCT(EXP((LN(Assumptions!$E$25/Assumptions!$D$25)/12)*(ROW(INDIRECT("1:24"))-1)))*SUM(Assumptions!$D$25:$E$25),0))} -> 36 | AN18: =Assumptions!$D$25-SUM(AC18:AM18) -> 39 | AO18: {=IF(YEAR(AO$3)=2026,0,ROUND(EXP((LN(Assumptions!$E$25/Assumptions!$D$25)/12)*((YEAR(AO$3)-2027)*12+MONTH(AO$3)-1))/SUMPRODUCT(EXP((LN(Assumptions!$E$25/Assumptions!$D$25)/12)*(ROW(INDIRECT("1:24"))-1)))*SUM(Assumptions!$D$25:$E$25),0))} -> 43 | AP18: {=IF(YEAR(AP$3)=2026,0,ROUND(EXP((LN(Assumptions!$E$25/Assumptions!$D$25)/12)*((YEAR(AP$3)-2027)*12+MONTH(AP$3)-1))/SUMPRODUCT(EXP((LN(Assumptions!$E$25/Assumptions!$D$25)/12)*(ROW(INDIRECT("1:24"))-1)))*SUM(Assumptions!$D$25:$E$25),0))} -> 47 | AQ18: {=IF(YEAR(AQ$3)=2026,0,ROUND(EXP((LN(Assumptions!$E$25/Assumptions!$D$25)/12)*((YEAR(AQ$3)-2027)*12+MONTH(AQ$3)-1))/SUMPRODUCT(EXP((LN(Assumptions!$E$25/Assumptions!$D$25)/12)*(ROW(INDIRECT("1:24"))-1)))*SUM(Assumptions!$D$25:$E$25),0))} -> 52 | AR18: {=IF(YEAR(AR$3)=2026,0,ROUND(EXP((LN(Assumptions!$E$25/Assumptions!$D$25)/12)*((YEAR(AR$3)-2027)*12+MONTH(AR$3)-1))/SUMPRODUCT(EXP((LN(Assumptions!$E$25/Assumptions!$D$25)/12)*(ROW(INDIRECT("1:24"))-1)))*SUM(Assumptions!$D$25:$E$25),0))} -> 57 | AS18: {=IF(YEAR(AS$3)=2026,0,ROUND(EXP((LN(Assumptions!$E$25/Assumptions!$D$25)/12)*((YEAR(AS$3)-2027)*12+MONTH(AS$3)-1))/SUMPRODUCT(EXP((LN(Assumptions!$E$25/Assumptions!$D$25)/12)*(ROW(INDIRECT("1:24"))-1)))*SUM(Assumptions!$D$25:$E$25),0))} -> 62 | AT18: {=IF(YEAR(AT$3)=2026,0,ROUND(EXP((LN(Assumptions!$E$25/Assumptions!$D$25)/12)*((YEAR(AT$3)-2027)*12+MONTH(AT$3)-1))/SUMPRODUCT(EXP((LN(Assumptions!$E$25/Assumptions!$D$25)/12)*(ROW(INDIRECT("1:24"))-1)))*SUM(Assumptions!$D$25:$E$25),0))} -> 68 | AU18: {=IF(YEAR(AU$3)=2026,0,ROUND(EXP((LN(Assumptions!$E$25/Assumptions!$D$25)/12)*((YEAR(AU$3)-2027)*12+MONTH(AU$3)-1))/SUMPRODUCT(EXP((LN(Assumptions!$E$25/Assumptions!$D$25)/12)*(ROW(INDIRECT("1:24"))-1)))*SUM(Assumptions!$D$25:$E$25),0))} -> 75 | AV18: {=IF(YEAR(AV$3)=2026,0,ROUND(EXP((LN(Assumptions!$E$25/Assumptions!$D$25)/12)*((YEAR(AV$3)-2027)*12+MONTH(AV$3)-1))/SUMPRODUCT(EXP((LN(Assumptions!$E$25/Assumptions!$D$25)/12)*(ROW(INDIRECT("1:24"))-1)))*SUM(Assumptions!$D$25:$E$25),0))} -> 82 | ... AY18: {=IF(YEAR(AY$3)=2026,0,ROUND(EXP((LN(Assumptions!$E$25/Assumptions!$D$25)/12)*((YEAR(AY$3)-2027)*12+MONTH(AY$3)-1))/SUMPRODUCT(EXP((LN(Assumptions!$E$25/Assumptions!$D$25)/12)*(ROW(INDIRECT("1:24"))-1)))*SUM(Assumptions!$D$25:$E$25),0))} -> 108 | AZ18: =Assumptions!$E$25-SUM(AO18:AY18) -> 118 | BB18: =SUM(E18:P18) -> 0 | BC18: =SUM(Q18:AB18) -> 0 | BD18: =SUM(AC18:AN18) -> 300 | BE18: =SUM(AO18:AZ18) -> 900 | BF18: =Assumptions!$F$25 -> 1800
B19: Combi+ Revenue | D19: € | Q19: =Q18*Assumptions!$C$34 -> 0 | R19: =R18*Assumptions!$C$34 -> 0 | S19: =S18*Assumptions!$C$34 -> 0 | T19: =T18*Assumptions!$C$34 -> 0 | U19: =U18*Assumptions!$C$34 -> 0 | V19: =V18*Assumptions!$C$34 -> 0 | W19: =W18*Assumptions!$C$34 -> 0 | X19: =X18*Assumptions!$C$34 -> 0 | ... AZ19: =AZ18*Assumptions!$C$34 -> 1632593.7 | BB19: =SUM(E19:P19) -> 0 | BC19: =SUM(Q19:AB19) -> 0 | BD19: =SUM(AC19:AN19) -> 4150662 | BE19: =SUM(AO19:AZ19) -> 12451986 | BF19: =BF18*Assumptions!$C$34 -> 24903972
B20: Combi+ upsell | D20: € | Q20: =Q18*SUMPRODUCT(Assumptions!$E$117:$E$119,Assumptions!$F$117:$F$119) -> 0 | R20: =R18*SUMPRODUCT(Assumptions!$E$117:$E$119,Assumptions!$F$117:$F$119) -> 0 | S20: =S18*SUMPRODUCT(Assumptions!$E$117:$E$119,Assumptions!$F$117:$F$119) -> 0 | T20: =T18*SUMPRODUCT(Assumptions!$E$117:$E$119,Assumptions!$F$117:$F$119) -> 0 | U20: =U18*SUMPRODUCT(Assumptions!$E$117:$E$119,Assumptions!$F$117:$F$119) -> 0 | V20: =V18*SUMPRODUCT(Assumptions!$E$117:$E$119,Assumptions!$F$117:$F$119) -> 0 | W20: =W18*SUMPRODUCT(Assumptions!$E$117:$E$119,Assumptions!$F$117:$F$119) -> 0 | X20: =X18*SUMPRODUCT(Assumptions!$E$117:$E$119,Assumptions!$F$117:$F$119) -> 0 | ... AZ20: =AZ18*SUMPRODUCT(Assumptions!$E$117:$E$119,Assumptions!$F$117:$F$119) -> 59341.822 | BB20: =SUM(E20:P20) -> 0 | BC20: =SUM(Q20:AB20) -> 0 | BD20: =SUM(AC20:AN20) -> 150869.04 | BE20: =SUM(AO20:AZ20) -> 452607.12 | BF20: =BF18*SUMPRODUCT(Assumptions!$E$117:$E$119,Assumptions!$F$117:$F$119) -> 905214.24
B21: Total Combi+ Revenue | D21: € | Q21: =sum(Q19:Q20) -> 0 | R21: =sum(R19:R20) -> 0 | S21: =sum(S19:S20) -> 0 | T21: =sum(T19:T20) -> 0 | U21: =sum(U19:U20) -> 0 | V21: =sum(V19:V20) -> 0 | W21: =sum(W19:W20) -> 0 | X21: =sum(X19:X20) -> 0 | ... AZ21: =sum(AZ19:AZ20) -> 1691935.5 | BB21: =SUM(E21:P21) -> 0 | BC21: =SUM(Q21:AB21) -> 0 | BD21: =SUM(AC21:AN21) -> 4301531 | BE21: =SUM(AO21:AZ21) -> 12904593 | BF21: =sum(BF19:BF20) -> 25809186
B23: INSTALLATION REVENUES | D23: €
B24: Units installed | D24: # | E24: =E6+E12+E18 -> 0 | F24: =F6+F12+F18 -> 0 | G24: =G6+G12+G18 -> 0 | H24: =H6+H12+H18 -> 0 | I24: =I6+I12+I18 -> 0 | J24: =J6+J12+J18 -> 0 | K24: =K6+K12+K18 -> 0 | L24: =L6+L12+L18 -> 0 | ... AZ24: =AZ6+AZ12+AZ18 -> 392 | BB24: =SUM(E24:P24) -> 0 | BC24: =SUM(Q24:AB24) -> 0 | BD24: =SUM(AC24:AN24) -> 1000 | BE24: =SUM(AO24:AZ24) -> 3000 | BF24: =BF6+BF12+BF18 -> 6000
B25: Total Installation Revenue | D25: € | E25: =E6*Assumptions!$C$36+E12*Assumptions!$C$37+E18*Assumptions!$C$38 -> 0 | F25: =F6*Assumptions!$C$36+F12*Assumptions!$C$37+F18*Assumptions!$C$38 -> 0 | G25: =G6*Assumptions!$C$36+G12*Assumptions!$C$37+G18*Assumptions!$C$38 -> 0 | H25: =H6*Assumptions!$C$36+H12*Assumptions!$C$37+H18*Assumptions!$C$38 -> 0 | I25: =I6*Assumptions!$C$36+I12*Assumptions!$C$37+I18*Assumptions!$C$38 -> 0 | J25: =J6*Assumptions!$C$36+J12*Assumptions!$C$37+J18*Assumptions!$C$38 -> 0 | K25: =K6*Assumptions!$C$36+K12*Assumptions!$C$37+K18*Assumptions!$C$38 -> 0 | L25: =L6*Assumptions!$C$36+L12*Assumptions!$C$37+L18*Assumptions!$C$38 -> 0 | ... AZ25: =AZ6*Assumptions!$C$36+AZ12*Assumptions!$C$37+AZ18*Assumptions!$C$38 -> 1333600 | BB25: =SUM(E25:P25) -> 0 | BC25: =SUM(Q25:AB25) -> 0 | BD25: =SUM(AC25:AN25) -> 3400000 | BE25: =SUM(AO25:AZ25) -> 10200000 | BF25: =BF6*Assumptions!$C$36+BF12*Assumptions!$C$37+BF18*Assumptions!$C$38 -> 20400000
B27: SERVICE REVENUES
B28: Installed base (TTK) | D28: # | Q28: =Q6 -> 0 | R28: =R6 -> 0 | S28: =S6 -> 0 | T28: =T6 -> 0 | U28: =U6 -> 0 | V28: =V6 -> 0 | W28: =W6 -> 0 | X28: =X6 -> 0 | ... AC28: =AC6 -> 19 | AD28: =AC28+AD6 -> 40 | AE28: =AD28+AE6 -> 63 | AF28: =AE28+AF6 -> 88 | AG28: =AF28+AG6 -> 116 | AH28: =AG28+AH6 -> 146 | AI28: =AH28+AI6 -> 179 | AJ28: =AI28+AJ6 -> 215 | AK28: =AJ28+AK6 -> 255 | ... AZ28: =AY28+AZ6 -> 1600 | BB28: =SUM(E28:P28) -> 0 | BC28: =SUM(Q28:AB28) -> 0 | BD28: =AN28 -> 400 | BE28: =AZ28 -> 1600 | BF28: =BF24*0.5 -> 3000
B29: Installed base (Combi) | D29: # | Q29: =Q12 -> 0 | R29: =R12 -> 0 | S29: =S12 -> 0 | T29: =T12 -> 0 | U29: =U12 -> 0 | V29: =V12 -> 0 | W29: =W12 -> 0 | X29: =X12 -> 0 | ... AC29: =AC12 -> 14 | AD29: =AC29+AD12 -> 30 | AE29: =AD29+AE12 -> 47 | AF29: =AE29+AF12 -> 66 | AG29: =AF29+AG12 -> 87 | AH29: =AG29+AH12 -> 110 | AI29: =AH29+AI12 -> 135 | AJ29: =AI29+AJ12 -> 162 | AK29: =AJ29+AK12 -> 192 | ... AZ29: =AY29+AZ12 -> 1200 | BB29: =SUM(E29:P29) -> 0 | BC29: =SUM(Q29:AB29) -> 0 | BD29: =AN29 -> 300 | BE29: =AZ29 -> 1200 | BF29: =BF24*0.25 -> 1500
B30: Installed base (Combi+) | Q30: =Q18 -> 0 | R30: =R18 -> 0 | S30: =S18 -> 0 | T30: =T18 -> 0 | U30: =U18 -> 0 | V30: =V18 -> 0 | W30: =W18 -> 0 | X30: =X18 -> 0 | ... AC30: =AC18 -> 14 | AD30: =AC30+AD18 -> 30 | AE30: =AD30+AE18 -> 47 | AF30: =AE30+AF18 -> 66 | AG30: =AF30+AG18 -> 87 | AH30: =AG30+AH18 -> 110 | AI30: =AH30+AI18 -> 135 | AJ30: =AI30+AJ18 -> 162 | AK30: =AJ30+AK18 -> 192 | ... AZ30: =AY30+AZ18 -> 1200 | BB30: =SUM(E30:P30) -> 0 | BC30: =SUM(Q30:AB30) -> 0 | BD30: =AN30 -> 300 | BE30: =AZ30 -> 1200 | BF30: =BF24*0.25 -> 1500
B31: Total Service Revenue | D31: € | Q31: =Q41*SUMPRODUCT(Assumptions!$E$129:$E$130,Assumptions!$F$129:$F$130) -> 0 | R31: =R41*SUMPRODUCT(Assumptions!$E$129:$E$130,Assumptions!$F$129:$F$130) -> 0 | S31: =S41*SUMPRODUCT(Assumptions!$E$129:$E$130,Assumptions!$F$129:$F$130) -> 0 | T31: =T41*SUMPRODUCT(Assumptions!$E$129:$E$130,Assumptions!$F$129:$F$130) -> 0 | U31: =U41*SUMPRODUCT(Assumptions!$E$129:$E$130,Assumptions!$F$129:$F$130) -> 0 | V31: =V41*SUMPRODUCT(Assumptions!$E$129:$E$130,Assumptions!$F$129:$F$130) -> 0 | W31: =W41*SUMPRODUCT(Assumptions!$E$129:$E$130,Assumptions!$F$129:$F$130) -> 0 | X31: =X41*SUMPRODUCT(Assumptions!$E$129:$E$130,Assumptions!$F$129:$F$130) -> 0 | ... AB31: =AB41*SUMPRODUCT(Assumptions!$E$129:$E$130,Assumptions!$F$129:$F$130) -> 0 | AC31: =AC41*SUMPRODUCT(Assumptions!$E$129:$E$130,Assumptions!$F$129:$F$130)+Q31 -> 7473 | AD31: =AD41*SUMPRODUCT(Assumptions!$E$129:$E$130,Assumptions!$F$129:$F$130)+R31 -> 8427 | AE31: =AE41*SUMPRODUCT(Assumptions!$E$129:$E$130,Assumptions!$F$129:$F$130)+S31 -> 9063 | AF31: =AF41*SUMPRODUCT(Assumptions!$E$129:$E$130,Assumptions!$F$129:$F$130)+T31 -> 10017 | AG31: =AG41*SUMPRODUCT(Assumptions!$E$129:$E$130,Assumptions!$F$129:$F$130)+U31 -> 11130 | AH31: =AH41*SUMPRODUCT(Assumptions!$E$129:$E$130,Assumptions!$F$129:$F$130)+V31 -> 12084 | AI31: =AI41*SUMPRODUCT(Assumptions!$E$129:$E$130,Assumptions!$F$129:$F$130)+W31 -> 13197 | AJ31: =AJ41*SUMPRODUCT(Assumptions!$E$129:$E$130,Assumptions!$F$129:$F$130)+X31 -> 14310 | ... AZ31: =AZ41*SUMPRODUCT(Assumptions!$E$129:$E$130,Assumptions!$F$129:$F$130)+AN31 -> 83157 | BB31: =SUM(E31:P31) -> 0 | BC31: =SUM(Q31:AB31) -> 0 | BD31: =SUM(AC31:AN31) -> 159000 | BE31: =SUM(AO31:AZ31) -> 636000 | BF31: =BF41*SUMPRODUCT(Assumptions!$E$129:$E$130,Assumptions!$F$129:$F$130)+AT31 -> 1002177
B33: SUBSIDIES & GRANTS
B34: All other | D34: € | E34: 0 | F34: 0 | G34: 0 | H34: 0 | I34: 0 | J34: 0 | K34: 0 | L34: 0 | M34: 0 | N34: 19480 | O34: 78000 | P34: 0 | Q34: 0 | R34: 0 | S34: 0 | T34: 0 | U34: 0 | V34: 0 | W34: 0 | X34: 106782 | Y34: 0 | Z34: 0 | AA34: 0 | AB34: 0 | AC34: 0 | AD34: 0 | AE34: 0 | AF34: 0 | AG34: 0 | AH34: 0 | AI34: 0 | AJ34: 0 | AK34: 0 | AL34: 0 | AM34: 0 | AN34: 0 | AO34: 0 | AP34: 0 | AQ34: 0 | AR34: 0 | AS34: 0 | AT34: 0 | AU34: 0 | AV34: 0 | AW34: 0 | AX34: 0 | AY34: 0 | AZ34: 0 | BB34: =SUM(E34:P34) -> 97480 | BC34: =SUM(Q34:AB34) -> 106782 | BD34: =SUM(AC34:AN34) -> 0 | BE34: =SUM(AO34:AZ34) -> 0 | BF34: 0
B35: Total Subsidies & Grants | D35: € | E35: =sum(E34) -> 0 | F35: =sum(F34) -> 0 | G35: =sum(G34) -> 0 | H35: =sum(H34) -> 0 | I35: =sum(I34) -> 0 | J35: =sum(J34) -> 0 | K35: =sum(K34) -> 0 | L35: =sum(L34) -> 0 | ... AZ35: =sum(AZ34) -> 0 | BB35: =SUM(E35:P35) -> 97480 | BC35: =SUM(Q35:AB35) -> 106782 | BD35: =BD34 -> 0 | BE35: =BE34 -> 0 | BF35: =BF34 -> 0
B37: TOTAL REVENUE | E37: =E9+E15+E21+E25+E31+E35 -> 0 | F37: =F9+F15+F21+F25+F31+F35 -> 0 | G37: =G9+G15+G21+G25+G31+G35 -> 0 | H37: =H9+H15+H21+H25+H31+H35 -> 0 | I37: =I9+I15+I21+I25+I31+I35 -> 0 | J37: =J9+J15+J21+J25+J31+J35 -> 0 | K37: =K9+K15+K21+K25+K31+K35 -> 0 | L37: =L9+L15+L21+L25+L31+L35 -> 0 | ... AZ37: =AZ9+AZ15+AZ21+AZ25+AZ31+AZ35 -> 5848250.4 | BB37: =BB9+BB15+BB21+BB25+BB31+BB35 -> 97480 | BC37: =BC9+BC15+BC21+BC25+BC31+BC35 -> 106782 | BD37: =SUM(AC37:AN37) -> 14856114 | BE37: =SUM(AO37:AZ37) -> 44727341 | BF37: =BF9+BF15+BF21+BF25+BF31+BF35 -> 89187260
B40: Installed Base | E40: =sum(E28:E30) -> 0 | F40: =sum(F28:F30) -> 0 | G40: =sum(G28:G30) -> 0 | H40: =sum(H28:H30) -> 0 | I40: =sum(I28:I30) -> 0 | J40: =sum(J28:J30) -> 0 | K40: =sum(K28:K30) -> 0 | L40: =sum(L28:L30) -> 0 | ... AZ40: =sum(AZ28:AZ30) -> 4000 | BB40: =sum(BB28:BB30) -> 0 | BC40: =sum(BC28:BC30) -> 0 | BD40: =sum(BD28:BD30) -> 1000 | BE40: =sum(BE28:BE30) -> 4000 | BF40: =sum(BF28:BF30) -> 6000
B41: Units sold | D41: # | E41: =E6+E12+E18 -> 0 | F41: =F6+F12+F18 -> 0 | G41: =G6+G12+G18 -> 0 | H41: =H6+H12+H18 -> 0 | I41: =I6+I12+I18 -> 0 | J41: =J6+J12+J18 -> 0 | K41: =K6+K12+K18 -> 0 | L41: =L6+L12+L18 -> 0 | ... AZ41: =AZ6+AZ12+AZ18 -> 392 | BB41: 0 | BC41: 0 | BD41: =SUM(AC41:AN41) -> 1000 | BE41: =SUM(AO41:AZ41) -> 3000 | BF41: =BF24 -> 6000

Sheet COGS
B1: Tarnoc B.V. — COGS Schedule (€)
E2: 2025 | Q2: 2026 | AC2: 2027 | AO2: 2028
E3: 45658 | F3: 45689 | G3: 45717 | H3: 45748 | I3: 45778 | J3: 45809 | K3: 45839 | L3: 45870 | M3: 45901 | N3: 45931 | O3: 45962 | P3: 45992 | Q3: 46023 | R3: 46054 | S3: 46082 | T3: 46113 | U3: 46143 | V3: 46174 | W3: 46204 | X3: 46235 | Y3: 46266 | Z3: 46296 | AA3: 46327 | AB3: 46357 | AC3: 46388 | AD3: 46419 | AE3: 46447 | AF3: 46478 | AG3: 46508 | AH3: 46539 | AI3: 46569 | AJ3: 46600 | AK3: 46631 | AL3: 46661 | AM3: 46692 | AN3: 46722 | AO3: 46753 | AP3: 46784 | AQ3: 46813 | AR3: 46844 | AS3: 46874 | AT3: 46905 | AU3: 46935 | AV3: 46966 | AW3: 46997 | AX3: 47027 | AY3: 47058 | AZ3: 47088 | BB3: 2025 | BC3: 2026 | BD3: 2027 | BE3: 2028 | BF3: 2029
B6: TTK
B7: TTK | D7: € | Q7: =IFNA('Revenue Forecast'!Q6*VLOOKUP('Revenue Forecast'!$BC$41,Assumptions!$B$71:$C$73,2,TRUE),0) -> 0 | R7: =IFNA('Revenue Forecast'!R6*VLOOKUP('Revenue Forecast'!$BC$41,Assumptions!$B$71:$C$73,2,TRUE),0) -> 0 | S7: =IFNA('Revenue Forecast'!S6*VLOOKUP('Revenue Forecast'!$BC$41,Assumptions!$B$71:$C$73,2,TRUE),0) -> 0 | T7: =IFNA('Revenue Forecast'!T6*VLOOKUP('Revenue Forecast'!$BC$41,Assumptions!$B$71:$C$73,2,TRUE),0) -> 0 | U7: =IFNA('Revenue Forecast'!U6*VLOOKUP('Revenue Forecast'!$BC$41,Assumptions!$B$71:$C$73,2,TRUE),0) -> 0 | V7: =IFNA('Revenue Forecast'!V6*VLOOKUP('Revenue Forecast'!$BC$41,Assumptions!$B$71:$C$73,2,TRUE),0) -> 0 | W7: =IFNA('Revenue Forecast'!W6*VLOOKUP('Revenue Forecast'!$BC$41,Assumptions!$B$71:$C$73,2,TRUE),0) -> 0 | X7: =IFNA('Revenue Forecast'!X6*VLOOKUP('Revenue Forecast'!$BC$41,Assumptions!$B$71:$C$73,2,TRUE),0) -> 0 | ... AB7: =IFNA('Revenue Forecast'!AB6*VLOOKUP('Revenue Forecast'!$BC$41,Assumptions!$B$71:$C$73,2,TRUE),0) -> 0 | AC7: =IFNA('Revenue Forecast'!AC6*VLOOKUP('Revenue Forecast'!$BD$41,Assumptions!$B$71:$C$73,2,TRUE),0) -> 189694.48 | AD7: =IFNA('Revenue Forecast'!AD6*VLOOKUP('Revenue Forecast'!$BD$41,Assumptions!$B$71:$C$73,2,TRUE),0) -> 209662.32 | AE7: =IFNA('Revenue Forecast'!AE6*VLOOKUP('Revenue Forecast'!$BD$41,Assumptions!$B$71:$C$73,2,TRUE),0) -> 229630.16 | AF7: =IFNA('Revenue Forecast'!AF6*VLOOKUP('Revenue Forecast'!$BD$41,Assumptions!$B$71:$C$73,2,TRUE),0) -> 249598 | AG7: =IFNA('Revenue Forecast'!AG6*VLOOKUP('Revenue Forecast'!$BD$41,Assumptions!$B$71:$C$73,2,TRUE),0) -> 279549.76 | AH7: =IFNA('Revenue Forecast'!AH6*VLOOKUP('Revenue Forecast'!$BD$41,Assumptions!$B$71:$C$73,2,TRUE),0) -> 299517.6 | AI7: =IFNA('Revenue Forecast'!AI6*VLOOKUP('Revenue Forecast'!$BD$41,Assumptions!$B$71:$C$73,2,TRUE),0) -> 329469.36 | AJ7: =IFNA('Revenue Forecast'!AJ6*VLOOKUP('Revenue Forecast'!$BD$41,Assumptions!$B$71:$C$73,2,TRUE),0) -> 359421.12 | ... AN7: =IFNA('Revenue Forecast'!AN6*VLOOKUP('Revenue Forecast'!$BD$41,Assumptions!$B$71:$C$73,2,TRUE),0) -> 529147.76 | AO7: =IFNA('Revenue Forecast'!AO6*VLOOKUP('Revenue Forecast'!$BE$41+'Revenue Forecast'!$BF$41,Assumptions!$B$71:$C$73,2,TRUE),0) -> 409998.75 | AP7: =IFNA('Revenue Forecast'!AP6*VLOOKUP('Revenue Forecast'!$BE$41+'Revenue Forecast'!$BF$41,Assumptions!$B$71:$C$73,2,TRUE),0) -> 445343.47 | AQ7: =IFNA('Revenue Forecast'!AQ6*VLOOKUP('Revenue Forecast'!$BE$41+'Revenue Forecast'!$BF$41,Assumptions!$B$71:$C$73,2,TRUE),0) -> 487757.14 | AR7: =IFNA('Revenue Forecast'!AR6*VLOOKUP('Revenue Forecast'!$BE$41+'Revenue Forecast'!$BF$41,Assumptions!$B$71:$C$73,2,TRUE),0) -> 537239.74 | AS7: =IFNA('Revenue Forecast'!AS6*VLOOKUP('Revenue Forecast'!$BE$41+'Revenue Forecast'!$BF$41,Assumptions!$B$71:$C$73,2,TRUE),0) -> 586722.35 | AT7: =IFNA('Revenue Forecast'!AT6*VLOOKUP('Revenue Forecast'!$BE$41+'Revenue Forecast'!$BF$41,Assumptions!$B$71:$C$73,2,TRUE),0) -> 643273.9 | AU7: =IFNA('Revenue Forecast'!AU6*VLOOKUP('Revenue Forecast'!$BE$41+'Revenue Forecast'!$BF$41,Assumptions!$B$71:$C$73,2,TRUE),0) -> 706894.4 | AV7: =IFNA('Revenue Forecast'!AV6*VLOOKUP('Revenue Forecast'!$BE$41+'Revenue Forecast'!$BF$41,Assumptions!$B$71:$C$73,2,TRUE),0) -> 770514.9 | ... AZ7: =IFNA('Revenue Forecast'!AZ6*VLOOKUP('Revenue Forecast'!$BE$41+'Revenue Forecast'!$BF$41,Assumptions!$B$71:$C$73,2,TRUE),0) -> 1102755.3 | BC7: =SUM(Q7:AB7) -> 0 | BD7: =SUM(AC7:AN7) -> 3993568 | BE7: =SUM(AO7:AZ7) -> 8482732.8 | BF7: ='Revenue Forecast'!BF6*VLOOKUP('Revenue Forecast'!$BF$41+Assumptions!$G$21,Assumptions!$B$71:$C$73,2,TRUE) -> 11995200
B8: Upsell | D8: € | Q8: ='Revenue Forecast'!Q6*SUMPRODUCT(Assumptions!$E$117:$E$119,Assumptions!$G$117:$G$119) -> 0 | R8: ='Revenue Forecast'!R6*SUMPRODUCT(Assumptions!$E$117:$E$119,Assumptions!$G$117:$G$119) -> 0 | S8: ='Revenue Forecast'!S6*SUMPRODUCT(Assumptions!$E$117:$E$119,Assumptions!$G$117:$G$119) -> 0 | T8: ='Revenue Forecast'!T6*SUMPRODUCT(Assumptions!$E$117:$E$119,Assumptions!$G$117:$G$119) -> 0 | U8: ='Revenue Forecast'!U6*SUMPRODUCT(Assumptions!$E$117:$E$119,Assumptions!$G$117:$G$119) -> 0 | V8: ='Revenue Forecast'!V6*SUMPRODUCT(Assumptions!$E$117:$E$119,Assumptions!$G$117:$G$119) -> 0 | W8: ='Revenue Forecast'!W6*SUMPRODUCT(Assumptions!$E$117:$E$119,Assumptions!$G$117:$G$119) -> 0 | X8: ='Revenue Forecast'!X6*SUMPRODUCT(Assumptions!$E$117:$E$119,Assumptions!$G$117:$G$119) -> 0 | ... AZ8: ='Revenue Forecast'!AZ6*SUMPRODUCT(Assumptions!$E$117:$E$119,Assumptions!$G$117:$G$119) -> 33976.8 | BC8: =SUM(Q8:AB8) -> 0 | BD8: =SUM(AC8:AN8) -> 87120 | BE8: =SUM(AO8:AZ8) -> 261360 | BF8: ='Revenue Forecast'!BF6*SUMPRODUCT(Assumptions!$E$117:$E$119,Assumptions!$G$117:$G$119) -> 522720
B9: Total TTK COGS | D9: € | Q9: =sum(Q7:Q8) -> 0 | R9: =sum(R7:R8) -> 0 | S9: =sum(S7:S8) -> 0 | T9: =sum(T7:T8) -> 0 | U9: =sum(U7:U8) -> 0 | V9: =sum(V7:V8) -> 0 | W9: =sum(W7:W8) -> 0 | X9: =sum(X7:X8) -> 0 | ... AZ9: =sum(AZ7:AZ8) -> 1136732.1 | BB9: =SUM(E9:P9) -> 0 | BC9: =SUM(Q9:AB9) -> 0 | BD9: =SUM(AC9:AN9) -> 4080688 | BE9: =SUM(AO9:AZ9) -> 8744092.8 | BF9: =sum(BF7:BF8) -> 12517920
B11: COMBI
B12: Combi | D12: € | Q12: =IFNA('Revenue Forecast'!Q12*(VLOOKUP('Revenue Forecast'!$BC$41,Assumptions!$B$71:$C$73,2,TRUE)+VLOOKUP('Revenue Forecast'!$BC$12,Assumptions!$B$83:$C$85,2,TRUE)+Assumptions!$E$79),0) -> 0 | R12: =IFNA('Revenue Forecast'!R12*(VLOOKUP('Revenue Forecast'!$BC$41,Assumptions!$B$71:$C$73,2,TRUE)+VLOOKUP('Revenue Forecast'!$BC$12,Assumptions!$B$83:$C$85,2,TRUE)+Assumptions!$E$79),0) -> 0 | S12: =IFNA('Revenue Forecast'!S12*(VLOOKUP('Revenue Forecast'!$BC$41,Assumptions!$B$71:$C$73,2,TRUE)+VLOOKUP('Revenue Forecast'!$BC$12,Assumptions!$B$83:$C$85,2,TRUE)+Assumptions!$E$79),0) -> 0 | T12: =IFNA('Revenue Forecast'!T12*(VLOOKUP('Revenue Forecast'!$BC$41,Assumptions!$B$71:$C$73,2,TRUE)+VLOOKUP('Revenue Forecast'!$BC$12,Assumptions!$B$83:$C$85,2,TRUE)+Assumptions!$E$79),0) -> 0 | U12: =IFNA('Revenue Forecast'!U12*(VLOOKUP('Revenue Forecast'!$BC$41,Assumptions!$B$71:$C$73,2,TRUE)+VLOOKUP('Revenue Forecast'!$BC$12,Assumptions!$B$83:$C$85,2,TRUE)+Assumptions!$E$79),0) -> 0 | V12: =IFNA('Revenue Forecast'!V12*(VLOOKUP('Revenue Forecast'!$BC$41,Assumptions!$B$71:$C$73,2,TRUE)+VLOOKUP('Revenue Forecast'!$BC$12,Assumptions!$B$83:$C$85,2,TRUE)+Assumptions!$E$79),0) -> 0 | W12: =IFNA('Revenue Forecast'!W12*(VLOOKUP('Revenue Forecast'!$BC$41,Assumptions!$B$71:$C$73,2,TRUE)+VLOOKUP('Revenue Forecast'!$BC$12,Assumptions!$B$83:$C$85,2,TRUE)+Assumptions!$E$79),0) -> 0 | X12: =IFNA('Revenue Forecast'!X12*(VLOOKUP('Revenue Forecast'!$BC$41,Assumptions!$B$71:$C$73,2,TRUE)+VLOOKUP('Revenue Forecast'!$BC$12,Assumptions!$B$83:$C$85,2,TRUE)+Assumptions!$E$79),0) -> 0 | ... AB12: =IFNA('Revenue Forecast'!AB12*(VLOOKUP('Revenue Forecast'!$BC$41,Assumptions!$B$71:$C$73,2,TRUE)+VLOOKUP('Revenue Forecast'!$BC$12,Assumptions!$B$83:$C$85,2,TRUE)+Assumptions!$E$79),0) -> 0 | AC12: =IFNA('Revenue Forecast'!AC12*(VLOOKUP('Revenue Forecast'!$BD$41,Assumptions!$B$71:$C$73,2,TRUE)+VLOOKUP('Revenue Forecast'!$BD$12,Assumptions!$B$83:$C$85,2,TRUE)+Assumptions!$E$79),0) -> 157671.92 | AD12: =IFNA('Revenue Forecast'!AD12*(VLOOKUP('Revenue Forecast'!$BD$41,Assumptions!$B$71:$C$73,2,TRUE)+VLOOKUP('Revenue Forecast'!$BD$12,Assumptions!$B$83:$C$85,2,TRUE)+Assumptions!$E$79),0) -> 180196.48 | AE12: =IFNA('Revenue Forecast'!AE12*(VLOOKUP('Revenue Forecast'!$BD$41,Assumptions!$B$71:$C$73,2,TRUE)+VLOOKUP('Revenue Forecast'!$BD$12,Assumptions!$B$83:$C$85,2,TRUE)+Assumptions!$E$79),0) -> 191458.76 | AF12: =IFNA('Revenue Forecast'!AF12*(VLOOKUP('Revenue Forecast'!$BD$41,Assumptions!$B$71:$C$73,2,TRUE)+VLOOKUP('Revenue Forecast'!$BD$12,Assumptions!$B$83:$C$85,2,TRUE)+Assumptions!$E$79),0) -> 213983.32 | AG12: =IFNA('Revenue Forecast'!AG12*(VLOOKUP('Revenue Forecast'!$BD$41,Assumptions!$B$71:$C$73,2,TRUE)+VLOOKUP('Revenue Forecast'!$BD$12,Assumptions!$B$83:$C$85,2,TRUE)+Assumptions!$E$79),0) -> 236507.88 | AH12: =IFNA('Revenue Forecast'!AH12*(VLOOKUP('Revenue Forecast'!$BD$41,Assumptions!$B$71:$C$73,2,TRUE)+VLOOKUP('Revenue Forecast'!$BD$12,Assumptions!$B$83:$C$85,2,TRUE)+Assumptions!$E$79),0) -> 259032.44 | AI12: =IFNA('Revenue Forecast'!AI12*(VLOOKUP('Revenue Forecast'!$BD$41,Assumptions!$B$71:$C$73,2,TRUE)+VLOOKUP('Revenue Forecast'!$BD$12,Assumptions!$B$83:$C$85,2,TRUE)+Assumptions!$E$79),0) -> 281557 | AJ12: =IFNA('Revenue Forecast'!AJ12*(VLOOKUP('Revenue Forecast'!$BD$41,Assumptions!$B$71:$C$73,2,TRUE)+VLOOKUP('Revenue Forecast'!$BD$12,Assumptions!$B$83:$C$85,2,TRUE)+Assumptions!$E$79),0) -> 304081.56 | ... AN12: =IFNA('Revenue Forecast'!AN12*(VLOOKUP('Revenue Forecast'!$BD$41,Assumptions!$B$71:$C$73,2,TRUE)+VLOOKUP('Revenue Forecast'!$BD$12,Assumptions!$B$83:$C$85,2,TRUE)+Assumptions!$E$79),0) -> 439228.92 | AO12: =IFNA('Revenue Forecast'!AO12*(VLOOKUP('Revenue Forecast'!$BE$41+'Revenue Forecast'!$BF$41,Assumptions!$B$71:$C$73,2,TRUE)+VLOOKUP('Revenue Forecast'!$BE$12+'Revenue Forecast'!$BF$12,Assumptions!$B$83:$C$85,2,TRUE)+Assumptions!$E$79),0) -> 358934.07 | AP12: =IFNA('Revenue Forecast'!AP12*(VLOOKUP('Revenue Forecast'!$BE$41+'Revenue Forecast'!$BF$41,Assumptions!$B$71:$C$73,2,TRUE)+VLOOKUP('Revenue Forecast'!$BE$12+'Revenue Forecast'!$BF$12,Assumptions!$B$83:$C$85,2,TRUE)+Assumptions!$E$79),0) -> 392323.29 | AQ12: =IFNA('Revenue Forecast'!AQ12*(VLOOKUP('Revenue Forecast'!$BE$41+'Revenue Forecast'!$BF$41,Assumptions!$B$71:$C$73,2,TRUE)+VLOOKUP('Revenue Forecast'!$BE$12+'Revenue Forecast'!$BF$12,Assumptions!$B$83:$C$85,2,TRUE)+Assumptions!$E$79),0) -> 434059.81 | AR12: =IFNA('Revenue Forecast'!AR12*(VLOOKUP('Revenue Forecast'!$BE$41+'Revenue Forecast'!$BF$41,Assumptions!$B$71:$C$73,2,TRUE)+VLOOKUP('Revenue Forecast'!$BE$12+'Revenue Forecast'!$BF$12,Assumptions!$B$83:$C$85,2,TRUE)+Assumptions!$E$79),0) -> 475796.33 | AS12: =IFNA('Revenue Forecast'!AS12*(VLOOKUP('Revenue Forecast'!$BE$41+'Revenue Forecast'!$BF$41,Assumptions!$B$71:$C$73,2,TRUE)+VLOOKUP('Revenue Forecast'!$BE$12+'Revenue Forecast'!$BF$12,Assumptions!$B$83:$C$85,2,TRUE)+Assumptions!$E$79),0) -> 517532.85 | AT12: =IFNA('Revenue Forecast'!AT12*(VLOOKUP('Revenue Forecast'!$BE$41+'Revenue Forecast'!$BF$41,Assumptions!$B$71:$C$73,2,TRUE)+VLOOKUP('Revenue Forecast'!$BE$12+'Revenue Forecast'!$BF$12,Assumptions!$B$83:$C$85,2,TRUE)+Assumptions!$E$79),0) -> 567616.67 | AU12: =IFNA('Revenue Forecast'!AU12*(VLOOKUP('Revenue Forecast'!$BE$41+'Revenue Forecast'!$BF$41,Assumptions!$B$71:$C$73,2,TRUE)+VLOOKUP('Revenue Forecast'!$BE$12+'Revenue Forecast'!$BF$12,Assumptions!$B$83:$C$85,2,TRUE)+Assumptions!$E$79),0) -> 626047.8 | AV12: =IFNA('Revenue Forecast'!AV12*(VLOOKUP('Revenue Forecast'!$BE$41+'Revenue Forecast'!$BF$41,Assumptions!$B$71:$C$73,2,TRUE)+VLOOKUP('Revenue Forecast'!$BE$12+'Revenue Forecast'!$BF$12,Assumptions!$B$83:$C$85,2,TRUE)+Assumptions!$E$79),0) -> 684478.93 | ... AZ12: =IFNA('Revenue Forecast'!AZ12*(VLOOKUP('Revenue Forecast'!$BE$41+'Revenue Forecast'!$BF$41,Assumptions!$B$71:$C$73,2,TRUE)+VLOOKUP('Revenue Forecast'!$BE$12+'Revenue Forecast'!$BF$12,Assumptions!$B$83:$C$85,2,TRUE)+Assumptions!$E$79),0) -> 984981.87 | BC12: =SUM(Q12:AB12) -> 0 | BD12: =SUM(AC12:AN12) -> 3378684 | BE12: =SUM(AO12:AZ12) -> 7512573.6 | BF12: ='Revenue Forecast'!BF12*(VLOOKUP('Revenue Forecast'!$BF$41+Assumptions!$G$21,Assumptions!$B$71:$C$73,2,TRUE)+VLOOKUP('Revenue Forecast'!$BF$12+Assumptions!$G$24,Assumptions!$B$83:$C$85,2,TRUE)+Assumptions!$E$79) -> 11085336
B13: Upsell | D13: € | Q13: ='Revenue Forecast'!Q12*SUMPRODUCT(Assumptions!$E$117:$E$119,Assumptions!$G$117:$G$119) -> 0 | R13: ='Revenue Forecast'!R12*SUMPRODUCT(Assumptions!$E$117:$E$119,Assumptions!$G$117:$G$119) -> 0 | S13: ='Revenue Forecast'!S12*SUMPRODUCT(Assumptions!$E$117:$E$119,Assumptions!$G$117:$G$119) -> 0 | T13: ='Revenue Forecast'!T12*SUMPRODUCT(Assumptions!$E$117:$E$119,Assumptions!$G$117:$G$119) -> 0 | U13: ='Revenue Forecast'!U12*SUMPRODUCT(Assumptions!$E$117:$E$119,Assumptions!$G$117:$G$119) -> 0 | V13: ='Revenue Forecast'!V12*SUMPRODUCT(Assumptions!$E$117:$E$119,Assumptions!$G$117:$G$119) -> 0 | W13: ='Revenue Forecast'!W12*SUMPRODUCT(Assumptions!$E$117:$E$119,Assumptions!$G$117:$G$119) -> 0 | X13: ='Revenue Forecast'!X12*SUMPRODUCT(Assumptions!$E$117:$E$119,Assumptions!$G$117:$G$119) -> 0 | ... AZ13: ='Revenue Forecast'!AZ12*SUMPRODUCT(Assumptions!$E$117:$E$119,Assumptions!$G$117:$G$119) -> 25700.4 | BC13: =SUM(Q13:AB13) -> 0 | BD13: =SUM(AC13:AN13) -> 65340 | BE13: =SUM(AO13:AZ13) -> 196020 | BF13: ='Revenue Forecast'!BF12*SUMPRODUCT(Assumptions!$E$117:$E$119,Assumptions!$G$117:$G$119) -> 392040
B14: Total Combi COGS | D14: € | Q14: =sum(Q12:Q13) -> 0 | R14: =sum(R12:R13) -> 0 | S14: =sum(S12:S13) -> 0 | T14: =sum(T12:T13) -> 0 | U14: =sum(U12:U13) -> 0 | V14: =sum(V12:V13) -> 0 | W14: =sum(W12:W13) -> 0 | X14: =sum(X12:X13) -> 0 | ... AZ14: =sum(AZ12:AZ13) -> 1010682.3 | BB14: =SUM(E14:P14) -> 0 | BC14: =SUM(Q14:AB14) -> 0 | BD14: =SUM(AC14:AN14) -> 3444024 | BE14: =SUM(AO14:AZ14) -> 7708593.6 | BF14: =sum(BF12:BF13) -> 11477376
B16: COMBI+
B17: Combi+ | Q17: =IFNA('Revenue Forecast'!Q18*(VLOOKUP('Revenue Forecast'!$BC$41,Assumptions!$B$71:$C$73,2,TRUE)+VLOOKUP('Revenue Forecast'!$BC$18,Assumptions!$E$83:$F$85,2,TRUE)+Assumptions!$E$79),0) -> 0 | R17: =IFNA('Revenue Forecast'!R18*(VLOOKUP('Revenue Forecast'!$BC$41,Assumptions!$B$71:$C$73,2,TRUE)+VLOOKUP('Revenue Forecast'!$BC$18,Assumptions!$E$83:$F$85,2,TRUE)+Assumptions!$E$79),0) -> 0 | S17: =IFNA('Revenue Forecast'!S18*(VLOOKUP('Revenue Forecast'!$BC$41,Assumptions!$B$71:$C$73,2,TRUE)+VLOOKUP('Revenue Forecast'!$BC$18,Assumptions!$E$83:$F$85,2,TRUE)+Assumptions!$E$79),0) -> 0 | T17: =IFNA('Revenue Forecast'!T18*(VLOOKUP('Revenue Forecast'!$BC$41,Assumptions!$B$71:$C$73,2,TRUE)+VLOOKUP('Revenue Forecast'!$BC$18,Assumptions!$E$83:$F$85,2,TRUE)+Assumptions!$E$79),0) -> 0 | U17: =IFNA('Revenue Forecast'!U18*(VLOOKUP('Revenue Forecast'!$BC$41,Assumptions!$B$71:$C$73,2,TRUE)+VLOOKUP('Revenue Forecast'!$BC$18,Assumptions!$E$83:$F$85,2,TRUE)+Assumptions!$E$79),0) -> 0 | V17: =IFNA('Revenue Forecast'!V18*(VLOOKUP('Revenue Forecast'!$BC$41,Assumptions!$B$71:$C$73,2,TRUE)+VLOOKUP('Revenue Forecast'!$BC$18,Assumptions!$E$83:$F$85,2,TRUE)+Assumptions!$E$79),0) -> 0 | W17: =IFNA('Revenue Forecast'!W18*(VLOOKUP('Revenue Forecast'!$BC$41,Assumptions!$B$71:$C$73,2,TRUE)+VLOOKUP('Revenue Forecast'!$BC$18,Assumptions!$E$83:$F$85,2,TRUE)+Assumptions!$E$79),0) -> 0 | X17: =IFNA('Revenue Forecast'!X18*(VLOOKUP('Revenue Forecast'!$BC$41,Assumptions!$B$71:$C$73,2,TRUE)+VLOOKUP('Revenue Forecast'!$BC$18,Assumptions!$E$83:$F$85,2,TRUE)+Assumptions!$E$79),0) -> 0 | ... AB17: =IFNA('Revenue Forecast'!AB18*(VLOOKUP('Revenue Forecast'!$BC$41,Assumptions!$B$71:$C$73,2,TRUE)+VLOOKUP('Revenue Forecast'!$BC$18,Assumptions!$E$83:$F$85,2,TRUE)+Assumptions!$E$79),0) -> 0 | AC17: =IFNA('Revenue Forecast'!AC18*(VLOOKUP('Revenue Forecast'!$BD$41,Assumptions!$B$71:$C$73,2,TRUE)+VLOOKUP('Revenue Forecast'!$BD$18,Assumptions!$E$83:$F$85,2,TRUE)+Assumptions!$E$79),0) -> 160811.28 | AD17: =IFNA('Revenue Forecast'!AD18*(VLOOKUP('Revenue Forecast'!$BD$41,Assumptions!$B$71:$C$73,2,TRUE)+VLOOKUP('Revenue Forecast'!$BD$18,Assumptions!$E$83:$F$85,2,TRUE)+Assumptions!$E$79),0) -> 183784.32 | AE17: =IFNA('Revenue Forecast'!AE18*(VLOOKUP('Revenue Forecast'!$BD$41,Assumptions!$B$71:$C$73,2,TRUE)+VLOOKUP('Revenue Forecast'!$BD$18,Assumptions!$E$83:$F$85,2,TRUE)+Assumptions!$E$79),0) -> 195270.84 | AF17: =IFNA('Revenue Forecast'!AF18*(VLOOKUP('Revenue Forecast'!$BD$41,Assumptions!$B$71:$C$73,2,TRUE)+VLOOKUP('Revenue Forecast'!$BD$18,Assumptions!$E$83:$F$85,2,TRUE)+Assumptions!$E$79),0) -> 218243.88 | AG17: =IFNA('Revenue Forecast'!AG18*(VLOOKUP('Revenue Forecast'!$BD$41,Assumptions!$B$71:$C$73,2,TRUE)+VLOOKUP('Revenue Forecast'!$BD$18,Assumptions!$E$83:$F$85,2,TRUE)+Assumptions!$E$79),0) -> 241216.92 | AH17: =IFNA('Revenue Forecast'!AH18*(VLOOKUP('Revenue Forecast'!$BD$41,Assumptions!$B$71:$C$73,2,TRUE)+VLOOKUP('Revenue Forecast'!$BD$18,Assumptions!$E$83:$F$85,2,TRUE)+Assumptions!$E$79),0) -> 264189.96 | AI17: =IFNA('Revenue Forecast'!AI18*(VLOOKUP('Revenue Forecast'!$BD$41,Assumptions!$B$71:$C$73,2,TRUE)+VLOOKUP('Revenue Forecast'!$BD$18,Assumptions!$E$83:$F$85,2,TRUE)+Assumptions!$E$79),0) -> 287163 | AJ17: =IFNA('Revenue Forecast'!AJ18*(VLOOKUP('Revenue Forecast'!$BD$41,Assumptions!$B$71:$C$73,2,TRUE)+VLOOKUP('Revenue Forecast'!$BD$18,Assumptions!$E$83:$F$85,2,TRUE)+Assumptions!$E$79),0) -> 310136.04 | ... AN17: =IFNA('Revenue Forecast'!AN18*(VLOOKUP('Revenue Forecast'!$BD$41,Assumptions!$B$71:$C$73,2,TRUE)+VLOOKUP('Revenue Forecast'!$BD$18,Assumptions!$E$83:$F$85,2,TRUE)+Assumptions!$E$79),0) -> 447974.28 | AO17: =IFNA('Revenue Forecast'!AO18*(VLOOKUP('Revenue Forecast'!$BE$41+'Revenue Forecast'!$BF$41,Assumptions!$B$71:$C$73,2,TRUE)+VLOOKUP('Revenue Forecast'!$BE$18+'Revenue Forecast'!$BF$18,Assumptions!$E$83:$F$85,2,TRUE)+Assumptions!$E$79),0) -> 368576.39 | AP17: =IFNA('Revenue Forecast'!AP18*(VLOOKUP('Revenue Forecast'!$BE$41+'Revenue Forecast'!$BF$41,Assumptions!$B$71:$C$73,2,TRUE)+VLOOKUP('Revenue Forecast'!$BE$18+'Revenue Forecast'!$BF$18,Assumptions!$E$83:$F$85,2,TRUE)+Assumptions!$E$79),0) -> 402862.57 | AQ17: =IFNA('Revenue Forecast'!AQ18*(VLOOKUP('Revenue Forecast'!$BE$41+'Revenue Forecast'!$BF$41,Assumptions!$B$71:$C$73,2,TRUE)+VLOOKUP('Revenue Forecast'!$BE$18+'Revenue Forecast'!$BF$18,Assumptions!$E$83:$F$85,2,TRUE)+Assumptions!$E$79),0) -> 445720.29 | AR17: =IFNA('Revenue Forecast'!AR18*(VLOOKUP('Revenue Forecast'!$BE$41+'Revenue Forecast'!$BF$41,Assumptions!$B$71:$C$73,2,TRUE)+VLOOKUP('Revenue Forecast'!$BE$18+'Revenue Forecast'!$BF$18,Assumptions!$E$83:$F$85,2,TRUE)+Assumptions!$E$79),0) -> 488578.01 | AS17: =IFNA('Revenue Forecast'!AS18*(VLOOKUP('Revenue Forecast'!$BE$41+'Revenue Forecast'!$BF$41,Assumptions!$B$71:$C$73,2,TRUE)+VLOOKUP('Revenue Forecast'!$BE$18+'Revenue Forecast'!$BF$18,Assumptions!$E$83:$F$85,2,TRUE)+Assumptions!$E$79),0) -> 531435.73 | AT17: =IFNA('Revenue Forecast'!AT18*(VLOOKUP('Revenue Forecast'!$BE$41+'Revenue Forecast'!$BF$41,Assumptions!$B$71:$C$73,2,TRUE)+VLOOKUP('Revenue Forecast'!$BE$18+'Revenue Forecast'!$BF$18,Assumptions!$E$83:$F$85,2,TRUE)+Assumptions!$E$79),0) -> 582864.99 | AU17: =IFNA('Revenue Forecast'!AU18*(VLOOKUP('Revenue Forecast'!$BE$41+'Revenue Forecast'!$BF$41,Assumptions!$B$71:$C$73,2,TRUE)+VLOOKUP('Revenue Forecast'!$BE$18+'Revenue Forecast'!$BF$18,Assumptions!$E$83:$F$85,2,TRUE)+Assumptions!$E$79),0) -> 642865.8 | AV17: =IFNA('Revenue Forecast'!AV18*(VLOOKUP('Revenue Forecast'!$BE$41+'Revenue Forecast'!$BF$41,Assumptions!$B$71:$C$73,2,TRUE)+VLOOKUP('Revenue Forecast'!$BE$18+'Revenue Forecast'!$BF$18,Assumptions!$E$83:$F$85,2,TRUE)+Assumptions!$E$79),0) -> 702866.61 | ... AZ17: =IFNA('Revenue Forecast'!AZ18*(VLOOKUP('Revenue Forecast'!$BE$41+'Revenue Forecast'!$BF$41,Assumptions!$B$71:$C$73,2,TRUE)+VLOOKUP('Revenue Forecast'!$BE$18+'Revenue Forecast'!$BF$18,Assumptions!$E$83:$F$85,2,TRUE)+Assumptions!$E$79),0) -> 1011442.2 | BC17: =SUM(Q17:AB17) -> 0 | BD17: =SUM(AC17:AN17) -> 3445956 | BE17: =SUM(AO17:AZ17) -> 7714389.6 | BF17: ='Revenue Forecast'!BF18*(VLOOKUP('Revenue Forecast'!$BF$41+Assumptions!$G$21,Assumptions!$B$71:$C$73,2,TRUE)+VLOOKUP('Revenue Forecast'!$BF$18+Assumptions!$G$25,Assumptions!$E$83:$F$85,2,TRUE)+Assumptions!$E$79) -> 11448612
B18: Upsell | Q18: ='Revenue Forecast'!Q18*SUMPRODUCT(Assumptions!$E$117:$E$119,Assumptions!$G$117:$G$119) -> 0 | R18: ='Revenue Forecast'!R18*SUMPRODUCT(Assumptions!$E$117:$E$119,Assumptions!$G$117:$G$119) -> 0 | S18: ='Revenue Forecast'!S18*SUMPRODUCT(Assumptions!$E$117:$E$119,Assumptions!$G$117:$G$119) -> 0 | T18: ='Revenue Forecast'!T18*SUMPRODUCT(Assumptions!$E$117:$E$119,Assumptions!$G$117:$G$119) -> 0 | U18: ='Revenue Forecast'!U18*SUMPRODUCT(Assumptions!$E$117:$E$119,Assumptions!$G$117:$G$119) -> 0 | V18: ='Revenue Forecast'!V18*SUMPRODUCT(Assumptions!$E$117:$E$119,Assumptions!$G$117:$G$119) -> 0 | W18: ='Revenue Forecast'!W18*SUMPRODUCT(Assumptions!$E$117:$E$119,Assumptions!$G$117:$G$119) -> 0 | X18: ='Revenue Forecast'!X18*SUMPRODUCT(Assumptions!$E$117:$E$119,Assumptions!$G$117:$G$119) -> 0 | ... AZ18: ='Revenue Forecast'!AZ18*SUMPRODUCT(Assumptions!$E$117:$E$119,Assumptions!$G$117:$G$119) -> 25700.4 | BC18: =SUM(Q18:AB18) -> 0 | BD18: =SUM(AC18:AN18) -> 65340 | BE18: =SUM(AO18:AZ18) -> 196020 | BF18: ='Revenue Forecast'!BF18*SUMPRODUCT(Assumptions!$E$117:$E$119,Assumptions!$G$117:$G$119) -> 392040
B19: Total Combi+ COGS | Q19: =sum(Q17:Q18) -> 0 | R19: =sum(R17:R18) -> 0 | S19: =sum(S17:S18) -> 0 | T19: =sum(T17:T18) -> 0 | U19: =sum(U17:U18) -> 0 | V19: =sum(V17:V18) -> 0 | W19: =sum(W17:W18) -> 0 | X19: =sum(X17:X18) -> 0 | ... AZ19: =sum(AZ17:AZ18) -> 1037142.6 | BC19: =sum(BC17:BC18) -> 0 | BD19: =sum(BD17:BD18) -> 3511296 | BE19: =sum(BE17:BE18) -> 7910409.6 | BF19: =sum(BF17:BF18) -> 11840652
B21: INSTALLATION
B22: Installation COGS (pass-through, = installation revenue) | D22: € | Q22: ='Revenue Forecast'!Q25 -> 0 | R22: ='Revenue Forecast'!R25 -> 0 | S22: ='Revenue Forecast'!S25 -> 0 | T22: ='Revenue Forecast'!T25 -> 0 | U22: ='Revenue Forecast'!U25 -> 0 | V22: ='Revenue Forecast'!V25 -> 0 | W22: ='Revenue Forecast'!W25 -> 0 | X22: ='Revenue Forecast'!X25 -> 0 | ... AZ22: ='Revenue Forecast'!AZ25 -> 1333600 | BB22: ='Revenue Forecast'!BB25 -> 0 | BC22: ='Revenue Forecast'!BC25 -> 0 | BD22: ='Revenue Forecast'!BD25 -> 3400000 | BE22: ='Revenue Forecast'!BE25 -> 10200000 | BF22: ='Revenue Forecast'!BF25 -> 20400000
B24: SERVICE REVENUES
B25: Installed base (TTK) | D25: # | Q25: =Q4 | R25: =R4 | S25: =S4 | T25: =T4 | U25: =U4 | V25: =V4 | W25: =W4 | X25: =X4 | ... AB25: =AB4 | AC25: ='Revenue Forecast'!AC6 -> 19 | AD25: ='Revenue Forecast'!AD6+'Revenue Forecast'!AC28 -> 40 | AE25: ='Revenue Forecast'!AE6+'Revenue Forecast'!AD28 -> 63 | AF25: ='Revenue Forecast'!AF6+'Revenue Forecast'!AE28 -> 88 | AG25: ='Revenue Forecast'!AG6+'Revenue Forecast'!AF28 -> 116 | AH25: ='Revenue Forecast'!AH6+'Revenue Forecast'!AG28 -> 146 | AI25: ='Revenue Forecast'!AI6+'Revenue Forecast'!AH28 -> 179 | AJ25: ='Revenue Forecast'!AJ6+'Revenue Forecast'!AI28 -> 215 | AK25: ='Revenue Forecast'!AK6+'Revenue Forecast'!AJ28 -> 255 | ... AZ25: ='Revenue Forecast'!AZ6+'Revenue Forecast'!AY28 -> 1600 | BB25: =SUM(E25:P25) -> 0 | BC25: =SUM(Q25:AB25) -> 0 | BD25: =AN25 -> 400 | BE25: =AZ25 -> 1600 | BF25: ='Revenue Forecast'!BF28 -> 3000
B26: Installed base (Combi) | D26: # | Q26: =Q10 | R26: =R10 | S26: =S10 | T26: =T10 | U26: =U10 | V26: =V10 | W26: =W10 | X26: =X10 | ... AB26: =AB10 | AC26: ='Revenue Forecast'!AC12 -> 14 | AD26: ='Revenue Forecast'!AD12+'Revenue Forecast'!AC29 -> 30 | AE26: ='Revenue Forecast'!AE12+'Revenue Forecast'!AD29 -> 47 | AF26: ='Revenue Forecast'!AF12+'Revenue Forecast'!AE29 -> 66 | AG26: ='Revenue Forecast'!AG12+'Revenue Forecast'!AF29 -> 87 | AH26: ='Revenue Forecast'!AH12+'Revenue Forecast'!AG29 -> 110 | AI26: ='Revenue Forecast'!AI12+'Revenue Forecast'!AH29 -> 135 | AJ26: ='Revenue Forecast'!AJ12+'Revenue Forecast'!AI29 -> 162 | AK26: ='Revenue Forecast'!AK12+'Revenue Forecast'!AJ29 -> 192 | ... AZ26: ='Revenue Forecast'!AZ12+'Revenue Forecast'!AY29 -> 1200 | BB26: =SUM(E26:P26) -> 0 | BC26: =SUM(Q26:AB26) -> 0 | BD26: =AN26 -> 300 | BE26: =AZ26 -> 1200 | BF26: ='Revenue Forecast'!BF29 -> 1500
B27: Total Service Revenue | D27: € | Q27: ='Revenue Forecast'!Q41*SUMPRODUCT(Assumptions!$E$129:$E$130,Assumptions!$G$129:$G$130)+E27 -> 0 | R27: ='Revenue Forecast'!R41*SUMPRODUCT(Assumptions!$E$129:$E$130,Assumptions!$G$129:$G$130)+F27 -> 0 | S27: ='Revenue Forecast'!S41*SUMPRODUCT(Assumptions!$E$129:$E$130,Assumptions!$G$129:$G$130)+G27 -> 0 | T27: ='Revenue Forecast'!T41*SUMPRODUCT(Assumptions!$E$129:$E$130,Assumptions!$G$129:$G$130)+H27 -> 0 | U27: ='Revenue Forecast'!U41*SUMPRODUCT(Assumptions!$E$129:$E$130,Assumptions!$G$129:$G$130)+I27 -> 0 | V27: ='Revenue Forecast'!V41*SUMPRODUCT(Assumptions!$E$129:$E$130,Assumptions!$G$129:$G$130)+J27 -> 0 | W27: ='Revenue Forecast'!W41*SUMPRODUCT(Assumptions!$E$129:$E$130,Assumptions!$G$129:$G$130)+K27 -> 0 | X27: ='Revenue Forecast'!X41*SUMPRODUCT(Assumptions!$E$129:$E$130,Assumptions!$G$129:$G$130)+L27 -> 0 | ... AZ27: ='Revenue Forecast'!AZ41*SUMPRODUCT(Assumptions!$E$129:$E$130,Assumptions!$G$129:$G$130)+AN27 -> 41578.5 | BB27: =SUM(E27:P27) -> 0 | BC27: =SUM(Q27:AB27) -> 0 | BD27: =sum(AC27:AN27) -> 79500 | BE27: =sum(AO27:AZ27)+BD27 -> 397500 | BF27: =(BE27*2)+BE27 -> 1192500
B29: TOTAL COGS | M29: =M7+M12 -> 0 | N29: =N9+N14+N22+N27 -> 0 | O29: =O9+O14+O22+O27 -> 0 | P29: =P9+P14+P22+P27 -> 0 | Q29: =Q9+Q14+Q19+Q22+Q27 -> 0 | R29: =R9+R14+R19+R22+R27 -> 0 | S29: =S9+S14+S19+S22+S27 -> 0 | T29: =T9+T14+T19+T22+T27 -> 0 | U29: =U9+U14+U19+U22+U27 -> 0 | V29: =V9+V14+V19+V22+V27 -> 0 | W29: =W9+W14+W19+W22+W27 -> 0 | X29: =X9+X14+X19+X22+X27 -> 0 | ... AZ29: =AZ9+AZ14+AZ19+AZ22+AZ27 -> 4559735.4 | BB29: =BB9+BB14+BB19+BB22+BB27 -> 0 | BC29: =BC9+BC14+BC19+BC22+BC27 -> 0 | BD29: =BD9+BD14+BD19+BD22+BD27 -> 14515508 | BE29: =BE9+BE14+BE19+BE22+BE27 -> 34960596 | BF29: =BF9+BF14+BF19+BF22+BF27 -> 57428448

Sheet OPEX
B1: Tarnoc B.V. — OPEX Forecast (€, negative = cost) | U1: Actual | V1: Projected
G2: 2025 | S2: 2026 | AE2: 2027 | AQ2: 2028
G3: 45658 | H3: 45689 | I3: 45717 | J3: 45748 | K3: 45778 | L3: 45809 | M3: 45839 | N3: 45870 | O3: 45901 | P3: 45931 | Q3: 45962 | R3: 45992 | S3: 46023 | T3: 46054 | U3: 46082 | V3: 46113 | W3: 46143 | X3: 46174 | Y3: 46204 | Z3: 46235 | AA3: 46266 | AB3: 46296 | AC3: 46327 | AD3: 46357 | AE3: 46388 | AF3: 46419 | AG3: 46447 | AH3: 46478 | AI3: 46508 | AJ3: 46539 | AK3: 46569 | AL3: 46600 | AM3: 46631 | AN3: 46661 | AO3: 46692 | AP3: 46722 | AQ3: 46753 | AR3: 46784 | AS3: 46813 | AT3: 46844 | AU3: 46874 | AV3: 46905 | AW3: 46935 | AX3: 46966 | AY3: 46997 | AZ3: 47027 | BA3: 47058 | BB3: 47088 | BD3: 2025 | BE3: 2026 | BF3: 2027 | BG3: 2028 | BH3: 2029
B5: PERSONNEL
B6: R&D | D6: € | O6: =Personnel!Q62 -> 47500 | P6: =Personnel!R62 -> 47500 | Q6: =Personnel!S62 -> 47500 | R6: =Personnel!T62 -> 47500 | S6: =Personnel!U62 -> 50700 | T6: =Personnel!V62 -> 50700 | U6: =Personnel!W62 -> 50700 | V6: =Personnel!X62 -> 50700 | ... BB6: =Personnel!BD62 -> 110364.77 | BD6: =SUM(G6:R6) -> 190000 | BE6: =SUM(S6:AD6) -> 681160 | BF6: =SUM(AE6:AP6) -> 1184655.2 | BG6: =SUM(AQ6:BB6) -> 1311927.6 | BH6: =sum(Personnel!BE62:BP62) -> 1780381.8 | BI6: =BH6*('Financial Statements'!$BE$7/'Financial Statements'!$BD$7)^0.5 -> 3083711.8
B7: S&M | D7: € | O7: =Personnel!Q63 -> 0 | P7: =Personnel!R63 -> 0 | Q7: =Personnel!S63 -> 0 | R7: =Personnel!T63 -> 0 | S7: =Personnel!U63 -> 0 | T7: =Personnel!V63 -> 10800 | U7: =Personnel!W63 -> 10800 | V7: =Personnel!X63 -> 10800 | ... BB7: =Personnel!BD63 -> 114476.32 | BD7: =SUM(G7:R7) -> 0 | BE7: =SUM(S7:AD7) -> 183300 | BF7: =SUM(AE7:AP7) -> 488628 | BG7: =SUM(AQ7:BB7) -> 1017718.2 | BH7: =sum(Personnel!BE63:BP63) -> 1838535.7 | BI7: =BH7*('Financial Statements'!$BE$7/'Financial Statements'!$BD$7)^0.5 -> 3184437.2
B8: G&A | D8: € | O8: =Personnel!Q64 -> 11500 | P8: =Personnel!R64 -> 11500 | Q8: =Personnel!S64 -> 11500 | R8: =Personnel!T64 -> 11500 | S8: =Personnel!U64 -> 11820 | T8: =Personnel!V64 -> 11820 | U8: =Personnel!W64 -> 11820 | V8: =Personnel!X64 -> 11820 | ... BB8: =Personnel!BD64 -> 61945.088 | BD8: =SUM(G8:R8) -> 46000 | BE8: =SUM(S8:AD8) -> 222060 | BF8: =SUM(AE8:AP8) -> 520843.2 | BG8: =SUM(AQ8:BB8) -> 672010.66 | BH8: =sum(Personnel!BE64:BP64) -> 812271.51 | BI8: =BH8*('Financial Statements'!$BE$7/'Financial Statements'!$BD$7)^0.2 -> 1011871.7
B9: Total Personnel | D9: € | G9: =SUM(G6:G8) -> 0 | H9: =SUM(H6:H8) -> 0 | I9: =SUM(I6:I8) -> 0 | J9: =SUM(J6:J8) -> 0 | K9: =SUM(K6:K8) -> 0 | L9: =SUM(L6:L8) -> 0 | M9: =SUM(M6:M8) -> 0 | N9: =SUM(N6:N8) -> 0 | O9: =sum(O6:O8) -> 59000 | P9: =sum(P6:P8) -> 59000 | Q9: =sum(Q6:Q8) -> 59000 | R9: =sum(R6:R8) -> 59000 | S9: =sum(S6:S8) -> 62520 | T9: =sum(T6:T8) -> 73320 | U9: =sum(U6:U8) -> 73320 | V9: =sum(V6:V8) -> 73320 | ... BB9: =sum(BB6:BB8) -> 286786.18 | BD9: =SUM(G9:R9) -> 236000 | BE9: =SUM(S9:AD9) -> 1086520 | BF9: =SUM(AE9:AP9) -> 2194126.4 | BG9: =SUM(AQ9:BB9) -> 3001656.5 | BH9: =sum(BH6:BH8) -> 4431189
B11: NON-PERSONNEL
B13: R&D COSTS
B14: Kicker Development Cost | D14: € | R14: =Assumptions!E99 -> 168933 | BD14: =SUM(G14:R14) -> 168933 | BE14: =SUM(S14:AD14) -> 0 | BF14: =SUM(AE14:AP14) -> 0 | BG14: =SUM(AQ14:BB14) -> 0 | BH14: 0
B15: Ongoing Development costs | D15: € | S15: {=INDEX(Assumptions!$E$97:$I$97,MATCH(YEAR(S$3),Assumptions!$E$92:$I$92,0))} -> 10000 | T15: {=INDEX(Assumptions!$E$97:$I$97,MATCH(YEAR(T$3),Assumptions!$E$92:$I$92,0))} -> 10000 | U15: {=INDEX(Assumptions!$E$97:$I$97,MATCH(YEAR(U$3),Assumptions!$E$92:$I$92,0))} -> 10000 | V15: {=INDEX(Assumptions!$E$97:$I$97,MATCH(YEAR(V$3),Assumptions!$E$92:$I$92,0))} -> 10000 | W15: {=INDEX(Assumptions!$E$97:$I$97,MATCH(YEAR(W$3),Assumptions!$E$92:$I$92,0))} -> 10000 | X15: {=INDEX(Assumptions!$E$97:$I$97,MATCH(YEAR(X$3),Assumptions!$E$92:$I$92,0))} -> 10000 | Y15: {=INDEX(Assumptions!$E$97:$I$97,MATCH(YEAR(Y$3),Assumptions!$E$92:$I$92,0))} -> 10000 | Z15: {=INDEX(Assumptions!$E$97:$I$97,MATCH(YEAR(Z$3),Assumptions!$E$92:$I$92,0))} -> 10000 | ... BB15: {=INDEX(Assumptions!$E$97:$I$97,MATCH(YEAR(BB$3),Assumptions!$E$92:$I$92,0))} -> 18225 | BD15: =SUM(G15:R15) -> 0 | BE15: =SUM(S15:AD15) -> 120000 | BF15: =SUM(AE15:AP15) -> 162000 | BG15: =SUM(AQ15:BB15) -> 218700 | BH15: =BG15*('Financial Statements'!$BE$7/'Financial Statements'!$BD$7)^0.4 -> 339388.63
B16: Assembly partner | D16: € | AB16: =Assumptions!E102 -> 100000 | BD16: =SUM(G16:R16) -> 0 | BE16: =SUM(S16:AC16) -> 100000 | BF16: =SUM(AE16:AP16) -> 0 | BG16: =SUM(AQ16:BB16) -> 0 | BH16: 0
B17: Third party cost product development | D17: € | S17: {=INDEX(Assumptions!$E$98:$I$98,MATCH(YEAR(S$3),Assumptions!$E$92:$I$92,0))} -> 15000 | T17: {=INDEX(Assumptions!$E$98:$I$98,MATCH(YEAR(T$3),Assumptions!$E$92:$I$92,0))} -> 15000 | U17: {=INDEX(Assumptions!$E$98:$I$98,MATCH(YEAR(U$3),Assumptions!$E$92:$I$92,0))} -> 15000 | V17: {=INDEX(Assumptions!$E$98:$I$98,MATCH(YEAR(V$3),Assumptions!$E$92:$I$92,0))} -> 15000 | W17: {=INDEX(Assumptions!$E$98:$I$98,MATCH(YEAR(W$3),Assumptions!$E$92:$I$92,0))} -> 15000 | X17: {=INDEX(Assumptions!$E$98:$I$98,MATCH(YEAR(X$3),Assumptions!$E$92:$I$92,0))} -> 15000 | Y17: {=INDEX(Assumptions!$E$98:$I$98,MATCH(YEAR(Y$3),Assumptions!$E$92:$I$92,0))} -> 15000 | Z17: {=INDEX(Assumptions!$E$98:$I$98,MATCH(YEAR(Z$3),Assumptions!$E$92:$I$92,0))} -> 15000 | ... BB17: {=INDEX(Assumptions!$E$98:$I$98,MATCH(YEAR(BB$3),Assumptions!$E$92:$I$92,0))} -> 27337.5 | BD17: =SUM(G17:R17) -> 0 | BE17: =SUM(S17:AD17) -> 180000 | BF17: =SUM(AE17:AP17) -> 243000 | BG17: =SUM(AQ17:BB17) -> 328050 | BH17: =BG17*('Financial Statements'!$BE$7/'Financial Statements'!$BD$7)^0.4 -> 509082.94
B18: Tooling Fisher (result: 2%-3%) | D18: € | AC18: =Assumptions!E103 -> 45000 | BD18: =SUM(G18:R18) -> 0 | BE18: =SUM(S18:AC18) -> 45000 | BF18: =SUM(AE18:AP18) -> 0 | BG18: =SUM(AQ18:BB18) -> 0 | BH18: 0
B19: Total R&D | R19: =R14+R15+R16 -> 168933 | S19: =sum(S14:S18) -> 25000 | T19: =sum(T14:T18) -> 25000 | U19: =sum(U14:U18) -> 25000 | V19: =sum(V14:V18) -> 25000 | W19: =sum(W14:W18) -> 25000 | X19: =sum(X14:X18) -> 25000 | Y19: =sum(Y14:Y18) -> 25000 | Z19: =sum(Z14:Z18) -> 25000 | ... BB19: =sum(BB14:BB18) -> 45562.5 | BD19: =SUM(G19:R19) -> 168933 | BE19: =SUM(S19:AD19) -> 445000 | BF19: =SUM(AE19:AP19) -> 405000 | BG19: =SUM(AQ19:BB19) -> 546750 | BH19: =sum(BH14:BH18) -> 848471.57
BE20: =BE19/BD19-1 -> 1.6341804 | BF20: =BF19/BE19-1 -> -0.08988764 | BG20: =BG19/BF19-1 -> 0.35 | BH20: =BH19/BG19-1 -> 0.55184557
B21: SALES & MARKETING
B22: Baseline Sales & Marketting | S22: {=INDEX(Assumptions!$E$95:$I$95,MATCH(YEAR(S$3),Assumptions!$E$92:$I$92,0))} -> 14000 | T22: {=INDEX(Assumptions!$E$95:$I$95,MATCH(YEAR(T$3),Assumptions!$E$92:$I$92,0))} -> 14000 | U22: {=INDEX(Assumptions!$E$95:$I$95,MATCH(YEAR(U$3),Assumptions!$E$92:$I$92,0))} -> 14000 | V22: {=INDEX(Assumptions!$E$95:$I$95,MATCH(YEAR(V$3),Assumptions!$E$92:$I$92,0))} -> 14000 | W22: {=INDEX(Assumptions!$E$95:$I$95,MATCH(YEAR(W$3),Assumptions!$E$92:$I$92,0))} -> 14000 | X22: {=INDEX(Assumptions!$E$95:$I$95,MATCH(YEAR(X$3),Assumptions!$E$92:$I$92,0))} -> 14000 | Y22: {=INDEX(Assumptions!$E$95:$I$95,MATCH(YEAR(Y$3),Assumptions!$E$92:$I$92,0))} -> 14000 | Z22: {=INDEX(Assumptions!$E$95:$I$95,MATCH(YEAR(Z$3),Assumptions!$E$92:$I$92,0))} -> 14000 | ... BB22: {=INDEX(Assumptions!$E$95:$I$95,MATCH(YEAR(BB$3),Assumptions!$E$92:$I$92,0))} -> 25515 | BD22: =SUM(G22:R22) -> 0 | BE22: =SUM(S22:AD22) -> 168000 | BF22: =SUM(AE22:AP22) -> 226800 | BG22: =SUM(AQ22:BB22) -> 306180 | BH22: =BG22*('Financial Statements'!$BE$7/'Financial Statements'!$BD$7)^0.5 -> 530319.32
B23: Sales & Marketing (3rd party) | D23: € | S23: 7000 | T23: 7000 | U23: 7000 | V23: 7000 | W23: 7000 | X23: 7000 | Y23: 7000 | Z23: 7000 | AA23: 7000 | AB23: 10000 | AC23: 10000 | AD23: 10000 | AE23: =('Revenue Forecast'!AC6+'Revenue Forecast'!AC12)*VLOOKUP('Revenue Forecast'!AC40,Assumptions!$G$107:$H$114,2,TRUE) -> 26400 | AF23: =('Revenue Forecast'!AD6+'Revenue Forecast'!AD12)*VLOOKUP('Revenue Forecast'!AD40,Assumptions!$G$107:$H$114,2,TRUE) -> 29600 | AG23: =('Revenue Forecast'!AE6+'Revenue Forecast'!AE12)*VLOOKUP('Revenue Forecast'!AE40,Assumptions!$G$107:$H$114,2,TRUE) -> 32000 | AH23: =('Revenue Forecast'!AF6+'Revenue Forecast'!AF12)*VLOOKUP('Revenue Forecast'!AF40,Assumptions!$G$107:$H$114,2,TRUE) -> 35200 | AI23: =('Revenue Forecast'!AG6+'Revenue Forecast'!AG12)*VLOOKUP('Revenue Forecast'!AG40,Assumptions!$G$107:$H$114,2,TRUE) -> 39200 | AJ23: =('Revenue Forecast'!AH6+'Revenue Forecast'!AH12)*VLOOKUP('Revenue Forecast'!AH40,Assumptions!$G$107:$H$114,2,TRUE) -> 42400 | AK23: =('Revenue Forecast'!AI6+'Revenue Forecast'!AI12)*VLOOKUP('Revenue Forecast'!AI40,Assumptions!$G$107:$H$114,2,TRUE) -> 46400 | AL23: =('Revenue Forecast'!AJ6+'Revenue Forecast'!AJ12)*VLOOKUP('Revenue Forecast'!AJ40,Assumptions!$G$107:$H$114,2,TRUE) -> 50400 | ... BB23: =('Revenue Forecast'!AZ6+'Revenue Forecast'!AZ12)*VLOOKUP('Revenue Forecast'!AZ40,Assumptions!$G$107:$H$114,2,TRUE) -> 159796.8 | BD23: =SUM(G23:R23) -> 0 | BE23: =SUM(S23:AD23) -> 93000 | BF23: =SUM(AE23:AP23) -> 545920 | BG23: =SUM(AQ23:BB23) -> 1335780 | BH23: =('Revenue Forecast'!BF6+'Revenue Forecast'!BF12)*VLOOKUP('Revenue Forecast'!BF40,Assumptions!$G$107:$H$114,2,TRUE) -> 2449440
B24: Customer journey (third party) | D24: € | R24: =Assumptions!$E$100 -> 10000 | X24: =Assumptions!E100 -> 10000 | BD24: =SUM(G24:R24) -> 10000 | BE24: =SUM(T24:AC24) -> 10000 | BF24: =SUM(AE24:AP24) -> 0 | BG24: =SUM(AQ24:BB24) -> 0 | BH24: =BG24*('Financial Statements'!$BE$7/'Financial Statements'!$BD$7)^0.5 -> 0
B25: Branding + Website (third party cost) | D25: € | R25: =Assumptions!$E$101 -> 10000 | W25: =Assumptions!E101 -> 10000 | BD25: =SUM(G25:R25) -> 10000 | BE25: =SUM(S25:AH25) -> 10000 | BF25: =SUM(AE25:AP25) -> 0 | BG25: =SUM(AQ25:BB25) -> 0 | BH25: =BG25*('Financial Statements'!$BE$7/'Financial Statements'!$BD$7)^0.5 -> 0
B26: Total S&M | G26: =SUM(G23:G25) -> 0 | H26: =SUM(H23:H25) -> 0 | I26: =SUM(I23:I25) -> 0 | J26: =SUM(J23:J25) -> 0 | K26: =SUM(K23:K25) -> 0 | L26: =SUM(L23:L25) -> 0 | M26: =SUM(M23:M25) -> 0 | N26: =SUM(N23:N25) -> 0 | ... R26: =SUM(R23:R25) -> 20000 | S26: =sum(S22:S25) -> 21000 | T26: =sum(T22:T25) -> 21000 | U26: =sum(U22:U25) -> 21000 | V26: =sum(V22:V25) -> 21000 | W26: =sum(W22:W25) -> 31000 | X26: =sum(X22:X25) -> 31000 | Y26: =sum(Y22:Y25) -> 21000 | Z26: =sum(Z22:Z25) -> 21000 | ... BB26: =sum(BB22:BB25) -> 185311.8 | BD26: =SUM(G26:R26) -> 20000 | BE26: =SUM(S26:AD26) -> 281000 | BF26: =SUM(AE26:AP26) -> 772720 | BG26: =SUM(AQ26:BB26) -> 1641960 | BH26: =sum(BH22:BH25) -> 2979759.3
BE27: =BE26/BD26-1 -> 13.05 | BF27: =BF26/BE26-1 -> 1.7498932 | BG27: =BG26/BF26-1 -> 1.1249094 | BH27: =BH26/BG26-1 -> 0.81475756
B28: G&A (NON-LABOUR)
B29: Office rent (part of General) | D29: € | G29: =Assumptions!$E$93 -> 5000 | H29: =Assumptions!$E$93 -> 5000 | I29: =Assumptions!$E$93 -> 5000 | J29: =Assumptions!$E$93 -> 5000 | K29: =Assumptions!$E$93 -> 5000 | L29: =Assumptions!$E$93 -> 5000 | M29: =Assumptions!$E$93 -> 5000 | N29: =Assumptions!$E$93 -> 5000 | ... R29: =Assumptions!$E$93 -> 5000 | S29: {=INDEX(Assumptions!$E$93:$I$93,MATCH(YEAR(S$3),Assumptions!$E$92:$I$92,0))} -> 5000 | T29: {=INDEX(Assumptions!$E$93:$I$93,MATCH(YEAR(T$3),Assumptions!$E$92:$I$92,0))} -> 5000 | U29: {=INDEX(Assumptions!$E$93:$I$93,MATCH(YEAR(U$3),Assumptions!$E$92:$I$92,0))} -> 5000 | V29: {=INDEX(Assumptions!$E$93:$I$93,MATCH(YEAR(V$3),Assumptions!$E$92:$I$92,0))} -> 5000 | W29: {=INDEX(Assumptions!$E$93:$I$93,MATCH(YEAR(W$3),Assumptions!$E$92:$I$92,0))} -> 5000 | X29: {=INDEX(Assumptions!$E$93:$I$93,MATCH(YEAR(X$3),Assumptions!$E$92:$I$92,0))} -> 5000 | Y29: {=INDEX(Assumptions!$E$93:$I$93,MATCH(YEAR(Y$3),Assumptions!$E$92:$I$92,0))} -> 5000 | Z29: {=INDEX(Assumptions!$E$93:$I$93,MATCH(YEAR(Z$3),Assumptions!$E$92:$I$92,0))} -> 5000 | ... BB29: {=INDEX(Assumptions!$E$93:$I$93,MATCH(YEAR(BB$3),Assumptions!$E$92:$I$92,0))} -> 9112.5 | BD29: =SUM(G29:R29) -> 60000 | BE29: =SUM(S29:AD29) -> 60000 | BF29: =SUM(AE29:AP29) -> 81000 | BG29: =SUM(AQ29:BB29) -> 109350 | BH29: =BG29*('Financial Statements'!$BE$7/'Financial Statements'!$BD$7)^0.2 -> 136220.68
B30: Other General | D30: € | G30: =Assumptions!$E$94 -> 7000 | H30: =Assumptions!$E$94 -> 7000 | I30: =Assumptions!$E$94 -> 7000 | J30: =Assumptions!$E$94 -> 7000 | K30: =Assumptions!$E$94 -> 7000 | L30: =Assumptions!$E$94 -> 7000 | M30: =Assumptions!$E$94 -> 7000 | N30: =Assumptions!$E$94 -> 7000 | ... R30: =Assumptions!$E$94 -> 7000 | S30: {=INDEX(Assumptions!$E$94:$I$94,MATCH(YEAR(S$3),Assumptions!$E$92:$I$92,0))} -> 7000 | T30: {=INDEX(Assumptions!$E$94:$I$94,MATCH(YEAR(T$3),Assumptions!$E$92:$I$92,0))} -> 7000 | U30: {=INDEX(Assumptions!$E$94:$I$94,MATCH(YEAR(U$3),Assumptions!$E$92:$I$92,0))} -> 7000 | V30: {=INDEX(Assumptions!$E$94:$I$94,MATCH(YEAR(V$3),Assumptions!$E$92:$I$92,0))} -> 7000 | W30: {=INDEX(Assumptions!$E$94:$I$94,MATCH(YEAR(W$3),Assumptions!$E$92:$I$92,0))} -> 7000 | X30: {=INDEX(Assumptions!$E$94:$I$94,MATCH(YEAR(X$3),Assumptions!$E$92:$I$92,0))} -> 7000 | Y30: {=INDEX(Assumptions!$E$94:$I$94,MATCH(YEAR(Y$3),Assumptions!$E$92:$I$92,0))} -> 7000 | Z30: {=INDEX(Assumptions!$E$94:$I$94,MATCH(YEAR(Z$3),Assumptions!$E$92:$I$92,0))} -> 7000 | ... BB30: {=INDEX(Assumptions!$E$94:$I$94,MATCH(YEAR(BB$3),Assumptions!$E$92:$I$92,0))} -> 12757.5 | BD30: =SUM(G30:R30) -> 84000 | BE30: =SUM(S30:AD30) -> 84000 | BF30: =SUM(AE30:AP30) -> 113400 | BG30: =SUM(AQ30:BB30) -> 153090 | BH30: =BG30*('Financial Statements'!$BE$7/'Financial Statements'!$BD$7)^0.2 -> 190708.95
B31: Finance & Legal etc. | D31: € | G31: =Assumptions!$E$96 -> 8000 | H31: =Assumptions!$E$96 -> 8000 | I31: =Assumptions!$E$96 -> 8000 | J31: =Assumptions!$E$96 -> 8000 | K31: =Assumptions!$E$96 -> 8000 | L31: =Assumptions!$E$96 -> 8000 | M31: =Assumptions!$E$96 -> 8000 | N31: =Assumptions!$E$96 -> 8000 | ... R31: =Assumptions!$E$96 -> 8000 | S31: {=INDEX(Assumptions!$E$96:$I$96,MATCH(YEAR(S$3),Assumptions!$E$92:$I$92,0))} -> 8000 | T31: {=INDEX(Assumptions!$E$96:$I$96,MATCH(YEAR(T$3),Assumptions!$E$92:$I$92,0))} -> 8000 | U31: {=INDEX(Assumptions!$E$96:$I$96,MATCH(YEAR(U$3),Assumptions!$E$92:$I$92,0))} -> 8000 | V31: {=INDEX(Assumptions!$E$96:$I$96,MATCH(YEAR(V$3),Assumptions!$E$92:$I$92,0))} -> 8000 | W31: {=INDEX(Assumptions!$E$96:$I$96,MATCH(YEAR(W$3),Assumptions!$E$92:$I$92,0))} -> 8000 | X31: {=INDEX(Assumptions!$E$96:$I$96,MATCH(YEAR(X$3),Assumptions!$E$92:$I$92,0))} -> 8000 | Y31: {=INDEX(Assumptions!$E$96:$I$96,MATCH(YEAR(Y$3),Assumptions!$E$92:$I$92,0))} -> 8000 | Z31: {=INDEX(Assumptions!$E$96:$I$96,MATCH(YEAR(Z$3),Assumptions!$E$92:$I$92,0))} -> 8000 | ... BB31: {=INDEX(Assumptions!$E$96:$I$96,MATCH(YEAR(BB$3),Assumptions!$E$92:$I$92,0))} -> 14580 | BD31: =SUM(G31:R31) -> 96000 | BE31: =SUM(S31:AD31) -> 96000 | BF31: =SUM(AE31:AP31) -> 129600 | BG31: =SUM(AQ31:BB31) -> 174960 | BH31: =BG31*('Financial Statements'!$BE$7/'Financial Statements'!$BD$7)^0.2 -> 217953.09
B32: Total G&A | S32: =sum(S29:S31) -> 20000 | T32: =sum(T29:T31) -> 20000 | U32: =sum(U29:U31) -> 20000 | V32: =sum(V29:V31) -> 20000 | W32: =sum(W29:W31) -> 20000 | X32: =sum(X29:X31) -> 20000 | Y32: =sum(Y29:Y31) -> 20000 | Z32: =sum(Z29:Z31) -> 20000 | ... BB32: =sum(BB29:BB31) -> 36450 | BD32: =SUM(G32:R32) -> 0 | BE32: =SUM(S32:AD32) -> 240000 | BF32: =SUM(AE32:AP32) -> 324000 | BG32: =SUM(AQ32:BB32) -> 437400 | BH32: =sum(BH29:BH31) -> 544882.71
B34: Total non-personnell | D34: € | G34: =G32+G26+G19 -> 0 | H34: =H32+H26+H19 -> 0 | I34: =I32+I26+I19 -> 0 | J34: =J32+J26+J19 -> 0 | K34: =K32+K26+K19 -> 0 | L34: =L32+L26+L19 -> 0 | M34: =M32+M26+M19 -> 0 | N34: =N32+N26+N19 -> 0 | ... BB34: =BB32+BB26+BB19 -> 267324.3 | BD34: =SUM(G34:R34) -> 188933 | BE34: =SUM(S34:AD34) -> 966000 | BF34: =SUM(AE34:AP34) -> 1501720 | BG34: =SUM(AQ34:BB34) -> 2626110 | BH34: =BH32+BH26+BH19 -> 4373113.6
B36: TOTAL OPEX | D36: € | G36: =G34+G9 -> 0 | H36: =H34+H9 -> 0 | I36: =I34+I9 -> 0 | J36: =J34+J9 -> 0 | K36: =K34+K9 -> 0 | L36: =L34+L9 -> 0 | M36: =M34+M9 -> 0 | N36: =N34+N9 -> 0 | ... BB36: =BB34+BB9 -> 554110.48 | BD36: =SUM(G36:R36) -> 424933 | BE36: =SUM(S36:AD36) -> 2052520 | BF36: =SUM(AE36:AP36) -> 3695846.4 | BG36: =SUM(AQ36:BB36) -> 5627766.5 | BH36: =BH34+BH9 -> 8804302.6
B38: Total R&D | D38: € | G38: =G19+G6 -> 0 | H38: =H19+H6 -> 0 | I38: =I19+I6 -> 0 | J38: =J19+J6 -> 0 | K38: =K19+K6 -> 0 | L38: =L19+L6 -> 0 | M38: =M19+M6 -> 0 | N38: =N19+N6 -> 0 | ... BB38: =BB19+BB6 -> 155927.27 | BD38: =BD19+BD6 -> 358933 | BE38: =BE19+BE6 -> 1126160 | BF38: =BF19+BF6 -> 1589655.2 | BG38: =BG19+BG6 -> 1858677.6 | BH38: =BH19+BH6 -> 2628853.4
B39: Total S&M | D39: € | G39: =G26+G7 -> 0 | H39: =H26+H7 -> 0 | I39: =I26+I7 -> 0 | J39: =J26+J7 -> 0 | K39: =K26+K7 -> 0 | L39: =L26+L7 -> 0 | M39: =M26+M7 -> 0 | N39: =N26+N7 -> 0 | ... BB39: =BB26+BB7 -> 299788.12 | BD39: =BD26+BD7 -> 20000 | BE39: =BE26+BE7 -> 464300 | BF39: =BF26+BF7 -> 1261348 | BG39: =BG26+BG7 -> 2659678.2 | BH39: =BH26+BH7 -> 4818295
B40: Total G&A | D40: € | G40: =G32+G8 -> 0 | H40: =H32+H8 -> 0 | I40: =I32+I8 -> 0 | J40: =J32+J8 -> 0 | K40: =K32+K8 -> 0 | L40: =L32+L8 -> 0 | M40: =M32+M8 -> 0 | N40: =N32+N8 -> 0 | ... BB40: =BB32+BB8 -> 98395.088 | BD40: =BD32+BD8 -> 46000 | BE40: =BE32+BE8 -> 462060 | BF40: =BF32+BF8 -> 844843.2 | BG40: =BG32+BG8 -> 1109410.7 | BH40: =BH32+BH8 -> 1357154.2
B41: R&D % of Total OPEX | S41: =S38/S$36 -> 0.58901338 | T41: =T38/T$36 -> 0.54335343 | U41: =U38/U$36 -> 0.54335343 | V41: =V38/V$36 -> 0.54335343 | W41: =W38/W$36 -> 0.50696491 | X41: =X38/X$36 -> 0.50696491 | Y41: =Y38/Y$36 -> 0.54335343 | Z41: =Z38/Z$36 -> 0.50024492 | ... BB41: =BB38/BB$36 -> 0.28140105 | BD41: =BD38/BD$36 -> 0.8446814 | BE41: =BE38/BE$36 -> 0.54867188 | BF41: =BF38/BF$36 -> 0.43011939 | BG41: =BG38/BG$36 -> 0.33026914 | BH41: =BH38/BH$36 -> 0.29858735
B42: S&M % of Total OPEX | S42: =S39/S$36 -> 0.16339869 | T42: =T39/T$36 -> 0.22825151 | U42: =U39/U$36 -> 0.22825151 | V42: =V39/V$36 -> 0.22825151 | W42: =W39/W$36 -> 0.27993571 | X42: =X39/X$36 -> 0.27993571 | Y42: =Y39/Y$36 -> 0.22825151 | Z42: =Z39/Z$36 -> 0.24981631 | ... BB42: =BB39/BB$36 -> 0.5410259 | BD42: =BD39/BD$36 -> 0.047066243 | BE42: =BE39/BE$36 -> 0.22620973 | BF42: =BF39/BF$36 -> 0.34128799 | BG42: =BG39/BG$36 -> 0.47259925 | BH42: =BH39/BH$36 -> 0.54726595
B43: G&A % of Total OPEX | S43: =S40/S$36 -> 0.24758792 | T43: =T40/T$36 -> 0.22839506 | U43: =U40/U$36 -> 0.22839506 | V43: =V40/V$36 -> 0.22839506 | W43: =W40/W$36 -> 0.21309938 | X43: =X40/X$36 -> 0.21309938 | Y43: =Y40/Y$36 -> 0.22839506 | Z43: =Z40/Z$36 -> 0.24993877 | ... BB43: =BB40/BB$36 -> 0.17757305 | BD43: =BD40/BD$36 -> 0.10825236 | BE43: =BE40/BE$36 -> 0.22511839 | BF43: =BF40/BF$36 -> 0.22859262 | BG43: =BG40/BG$36 -> 0.19713161 | BH43: =BH40/BH$36 -> 0.1541467

Sheet Personnel
B1: PERSONNEL — Monthly Employer Cost (€)
A2: # | B2: Name | C2: Dept | D2: Role | E2: Type | F2: Start | G2: End | H2: Monthly Cost (€) | I2: 45658 | J2: 45689 | K2: 45717 | L2: 45748 | M2: 45778 | N2: 45809 | O2: 45839 | P2: 45870 | Q2: 45901 | R2: 45931 | S2: 45962 | T2: 45992 | U2: 46023 | V2: 46054 | W2: 46082 | X2: 46113 | Y2: 46143 | Z2: 46174 | AA2: 46204 | AB2: 46235 | AC2: 46266 | AD2: 46296 | AE2: 46327 | AF2: 46357 | AG2: 46388 | AH2: 46419 | AI2: 46447 | AJ2: 46478 | AK2: 46508 | AL2: 46539 | AM2: 46569 | AN2: 46600 | AO2: 46631 | AP2: 46661 | AQ2: 46692 | AR2: 46722 | AS2: 46753 | AT2: 46784 | AU2: 46813 | AV2: 46844 | AW2: 46874 | AX2: 46905 | AY2: 46935 | AZ2: 46966 | BA2: 46997 | BB2: 47027 | BC2: 47058 | BD2: 47088 | BE2: 47119 | BF2: 47150 | BG2: 47178 | BH2: 47209 | BI2: 47239 | BJ2: 47270 | BK2: 47300 | BL2: 47331 | BM2: 47362 | BN2: 47392 | BO2: 47423 | BP2: 47453
A3: 1 | B3: R&D Engineer | C3: R&D | D3: Field Engineer | E3: Current | F3: 45901 | H3: 5500 | I3: =IF(AND(F3<=DATE(2025,1,1),OR(G3="",G3>=DATE(2025,1,1))),H3*(1+Assumptions!$C$7)^0,0) -> 0 | J3: =IF(AND(F3<=DATE(2025,2,1),OR(G3="",G3>=DATE(2025,2,1))),H3*(1+Assumptions!$C$7)^0,0) -> 0 | K3: =IF(AND(F3<=DATE(2025,3,1),OR(G3="",G3>=DATE(2025,3,1))),H3*(1+Assumptions!$C$7)^0,0) -> 0 | L3: =IF(AND(F3<=DATE(2025,4,1),OR(G3="",G3>=DATE(2025,4,1))),H3*(1+Assumptions!$C$7)^0,0) -> 0 | M3: =IF(AND(F3<=DATE(2025,5,1),OR(G3="",G3>=DATE(2025,5,1))),H3*(1+Assumptions!$C$7)^0,0) -> 0 | N3: =IF(AND(F3<=DATE(2025,6,1),OR(G3="",G3>=DATE(2025,6,1))),H3*(1+Assumptions!$C$7)^0,0) -> 0 | O3: =IF(AND(F3<=DATE(2025,7,1),OR(G3="",G3>=DATE(2025,7,1))),H3*(1+Assumptions!$C$7)^0,0) -> 0 | P3: =IF(AND(F3<=DATE(2025,8,1),OR(G3="",G3>=DATE(2025,8,1))),H3*(1+Assumptions!$C$7)^0,0) -> 0 | Q3: =IF(AND(F3<=DATE(2025,9,1),OR(G3="",G3>=DATE(2025,9,1))),H3*(1+Assumptions!$C$7)^0,0) -> 5500 | R3: =IF(AND(F3<=DATE(2025,10,1),OR(G3="",G3>=DATE(2025,10,1))),H3*(1+Assumptions!$C$7)^0,0) -> 5500 | S3: =IF(AND(F3<=DATE(2025,11,1),OR(G3="",G3>=DATE(2025,11,1))),H3*(1+Assumptions!$C$7)^0,0) -> 5500 | T3: =IF(AND(F3<=DATE(2025,12,1),OR(G3="",G3>=DATE(2025,12,1))),H3*(1+Assumptions!$C$7)^0,0) -> 5500 | U3: =IF(AND(F3<=DATE(2026,1,1),OR(G3="",G3>=DATE(2026,1,1))),H3*(1+Assumptions!$C$7)^1,0) -> 5940 | V3: =IF(AND(F3<=DATE(2026,2,1),OR(G3="",G3>=DATE(2026,2,1))),H3*(1+Assumptions!$C$7)^1,0) -> 5940 | W3: =IF(AND(F3<=DATE(2026,3,1),OR(G3="",G3>=DATE(2026,3,1))),H3*(1+Assumptions!$C$7)^1,0) -> 5940 | X3: =IF(AND(F3<=DATE(2026,4,1),OR(G3="",G3>=DATE(2026,4,1))),H3*(1+Assumptions!$C$7)^1,0) -> 5940 | Y3: =IF(AND(F3<=DATE(2026,5,1),OR(G3="",G3>=DATE(2026,5,1))),H3*(1+Assumptions!$C$7)^1,0) -> 5940 | Z3: =IF(AND(F3<=DATE(2026,6,1),OR(G3="",G3>=DATE(2026,6,1))),H3*(1+Assumptions!$C$7)^1,0) -> 5940 | AA3: =IF(AND(F3<=DATE(2026,7,1),OR(G3="",G3>=DATE(2026,7,1))),H3*(1+Assumptions!$C$7)^1,0) -> 5940 | AB3: =IF(AND(F3<=DATE(2026,8,1),OR(G3="",G3>=DATE(2026,8,1))),H3*(1+Assumptions!$C$7)^1,0) -> 5940 | AC3: =IF(AND(F3<=DATE(2026,9,1),OR(G3="",G3>=DATE(2026,9,1))),H3*(1+Assumptions!$C$7)^1,0) -> 5940 | AD3: =IF(AND(F3<=DATE(2026,10,1),OR(G3="",G3>=DATE(2026,10,1))),H3*(1+Assumptions!$C$7)^1,0) -> 5940 | AE3: =IF(AND(F3<=DATE(2026,11,1),OR(G3="",G3>=DATE(2026,11,1))),H3*(1+Assumptions!$C$7)^1,0) -> 5940 | AF3: =IF(AND(F3<=DATE(2026,12,1),OR(G3="",G3>=DATE(2026,12,1))),H3*(1+Assumptions!$C$7)^1,0) -> 5940 | AG3: =IF(AND(F3<=DATE(2027,1,1),OR(G3="",G3>=DATE(2027,1,1))),H3*(1+Assumptions!$C$7)^2,0) -> 6415.2 | AH3: =IF(AND(F3<=DATE(2027,2,1),OR(G3="",G3>=DATE(2027,2,1))),H3*(1+Assumptions!$C$7)^2,0) -> 6415.2 | AI3: =IF(AND(F3<=DATE(2027,3,1),OR(G3="",G3>=DATE(2027,3,1))),H3*(1+Assumptions!$C$7)^2,0) -> 6415.2 | AJ3: =IF(AND(F3<=DATE(2027,4,1),OR(G3="",G3>=DATE(2027,4,1))),H3*(1+Assumptions!$C$7)^2,0) -> 6415.2 | AK3: =IF(AND(F3<=DATE(2027,5,1),OR(G3="",G3>=DATE(2027,5,1))),H3*(1+Assumptions!$C$7)^2,0) -> 6415.2 | AL3: =IF(AND(F3<=DATE(2027,6,1),OR(G3="",G3>=DATE(2027,6,1))),H3*(1+Assumptions!$C$7)^2,0) -> 6415.2 | AM3: =IF(AND(F3<=DATE(2027,7,1),OR(G3="",G3>=DATE(2027,7,1))),H3*(1+Assumptions!$C$7)^2,0) -> 6415.2 | AN3: =IF(AND(F3<=DATE(2027,8,1),OR(G3="",G3>=DATE(2027,8,1))),H3*(1+Assumptions!$C$7)^2,0) -> 6415.2 | AO3: =IF(AND(F3<=DATE(2027,9,1),OR(G3="",G3>=DATE(2027,9,1))),H3*(1+Assumptions!$C$7)^2,0) -> 6415.2 | AP3: =IF(AND(F3<=DATE(2027,10,1),OR(G3="",G3>=DATE(2027,10,1))),H3*(1+Assumptions!$C$7)^2,0) -> 6415.2 | AQ3: =IF(AND(F3<=DATE(2027,11,1),OR(G3="",G3>=DATE(2027,11,1))),H3*(1+Assumptions!$C$7)^2,0) -> 6415.2 | AR3: =IF(AND(F3<=DATE(2027,12,1),OR(G3="",G3>=DATE(2027,12,1))),H3*(1+Assumptions!$C$7)^2,0) -> 6415.2 | AS3: =IF(AND(F3<=DATE(2028,1,1),OR(G3="",G3>=DATE(2028,1,1))),H3*(1+Assumptions!$C$7)^3,0) -> 6928.416 | AT3: =IF(AND(F3<=DATE(2028,2,1),OR(G3="",G3>=DATE(2028,2,1))),H3*(1+Assumptions!$C$7)^3,0) -> 6928.416 | AU3: =IF(AND(F3<=DATE(2028,3,1),OR(G3="",G3>=DATE(2028,3,1))),H3*(1+Assumptions!$C$7)^3,0) -> 6928.416 | AV3: =IF(AND(F3<=DATE(2028,4,1),OR(G3="",G3>=DATE(2028,4,1))),H3*(1+Assumptions!$C$7)^3,0) -> 6928.416 | AW3: =IF(AND(F3<=DATE(2028,5,1),OR(G3="",G3>=DATE(2028,5,1))),H3*(1+Assumptions!$C$7)^3,0) -> 6928.416 | AX3: =IF(AND(F3<=DATE(2028,6,1),OR(G3="",G3>=DATE(2028,6,1))),H3*(1+Assumptions!$C$7)^3,0) -> 6928.416 | AY3: =IF(AND(F3<=DATE(2028,7,1),OR(G3="",G3>=DATE(2028,7,1))),H3*(1+Assumptions!$C$7)^3,0) -> 6928.416 | AZ3: =IF(AND(F3<=DATE(2028,8,1),OR(G3="",G3>=DATE(2028,8,1))),H3*(1+Assumptions!$C$7)^3,0) -> 6928.416 | BA3: =IF(AND(F3<=DATE(2028,9,1),OR(G3="",G3>=DATE(2028,9,1))),H3*(1+Assumptions!$C$7)^3,0) -> 6928.416 | BB3: =IF(AND(F3<=DATE(2028,10,1),OR(G3="",G3>=DATE(2028,10,1))),H3*(1+Assumptions!$C$7)^3,0) -> 6928.416 | BC3: =IF(AND(F3<=DATE(2028,11,1),OR(G3="",G3>=DATE(2028,11,1))),H3*(1+Assumptions!$C$7)^3,0) -> 6928.416 | BD3: =IF(AND(F3<=DATE(2028,12,1),OR(G3="",G3>=DATE(2028,12,1))),H3*(1+Assumptions!$C$7)^3,0) -> 6928.416 | BE3: =IF(AND(F3<=DATE(2029,1,1),OR(G3="",G3>=DATE(2029,1,1))),H3*(1+Assumptions!$C$7)^4,0) -> 7482.6893 | BF3: =IF(AND(F3<=DATE(2029,2,1),OR(G3="",G3>=DATE(2029,2,1))),H3*(1+Assumptions!$C$7)^4,0) -> 7482.6893 | BG3: =IF(AND(F3<=DATE(2029,3,1),OR(G3="",G3>=DATE(2029,3,1))),H3*(1+Assumptions!$C$7)^4,0) -> 7482.6893 | BH3: =IF(AND(F3<=DATE(2029,4,1),OR(G3="",G3>=DATE(2029,4,1))),H3*(1+Assumptions!$C$7)^4,0) -> 7482.6893 | BI3: =IF(AND(F3<=DATE(2029,5,1),OR(G3="",G3>=DATE(2029,5,1))),H3*(1+Assumptions!$C$7)^4,0) -> 7482.6893 | BJ3: =IF(AND(F3<=DATE(2029,6,1),OR(G3="",G3>=DATE(2029,6,1))),H3*(1+Assumptions!$C$7)^4,0) -> 7482.6893 | BK3: =IF(AND(F3<=DATE(2029,7,1),OR(G3="",G3>=DATE(2029,7,1))),H3*(1+Assumptions!$C$7)^4,0) -> 7482.6893 | BL3: =IF(AND(F3<=DATE(2029,8,1),OR(G3="",G3>=DATE(2029,8,1))),H3*(1+Assumptions!$C$7)^4,0) -> 7482.6893 | BM3: =IF(AND(F3<=DATE(2029,9,1),OR(G3="",G3>=DATE(2029,9,1))),H3*(1+Assumptions!$C$7)^4,0) -> 7482.6893 | BN3: =IF(AND(F3<=DATE(2029,10,1),OR(G3="",G3>=DATE(2029,10,1))),H3*(1+Assumptions!$C$7)^4,0) -> 7482.6893 | BO3: =IF(AND(F3<=DATE(2029,11,1),OR(G3="",G3>=DATE(2029,11,1))),H3*(1+Assumptions!$C$7)^4,0) -> 7482.6893 | BP3: =IF(AND(F3<=DATE(2029,12,1),OR(G3="",G3>=DATE(2029,12,1))),H3*(1+Assumptions!$C$7)^4,0) -> 7482.6893
A4: 2 | B4: Project manager | C4: R&D | D4: R&D Engineer | E4: Current | F4: 45901 | H4: 7500 | I4: =IF(AND(F4<=DATE(2025,1,1),OR(G4="",G4>=DATE(2025,1,1))),H4*(1+Assumptions!$C$7)^0,0) -> 0 | J4: =IF(AND(F4<=DATE(2025,2,1),OR(G4="",G4>=DATE(2025,2,1))),H4*(1+Assumptions!$C$7)^0,0) -> 0 | K4: =IF(AND(F4<=DATE(2025,3,1),OR(G4="",G4>=DATE(2025,3,1))),H4*(1+Assumptions!$C$7)^0,0) -> 0 | L4: =IF(AND(F4<=DATE(2025,4,1),OR(G4="",G4>=DATE(2025,4,1))),H4*(1+Assumptions!$C$7)^0,0) -> 0 | M4: =IF(AND(F4<=DATE(2025,5,1),OR(G4="",G4>=DATE(2025,5,1))),H4*(1+Assumptions!$C$7)^0,0) -> 0 | N4: =IF(AND(F4<=DATE(2025,6,1),OR(G4="",G4>=DATE(2025,6,1))),H4*(1+Assumptions!$C$7)^0,0) -> 0 | O4: =IF(AND(F4<=DATE(2025,7,1),OR(G4="",G4>=DATE(2025,7,1))),H4*(1+Assumptions!$C$7)^0,0) -> 0 | P4: =IF(AND(F4<=DATE(2025,8,1),OR(G4="",G4>=DATE(2025,8,1))),H4*(1+Assumptions!$C$7)^0,0) -> 0 | Q4: =IF(AND(F4<=DATE(2025,9,1),OR(G4="",G4>=DATE(2025,9,1))),H4*(1+Assumptions!$C$7)^0,0) -> 7500 | R4: =IF(AND(F4<=DATE(2025,10,1),OR(G4="",G4>=DATE(2025,10,1))),H4*(1+Assumptions!$C$7)^0,0) -> 7500 | S4: =IF(AND(F4<=DATE(2025,11,1),OR(G4="",G4>=DATE(2025,11,1))),H4*(1+Assumptions!$C$7)^0,0) -> 7500 | T4: =IF(AND(F4<=DATE(2025,12,1),OR(G4="",G4>=DATE(2025,12,1))),H4*(1+Assumptions!$C$7)^0,0) -> 7500 | U4: =IF(AND(F4<=DATE(2026,1,1),OR(G4="",G4>=DATE(2026,1,1))),H4*(1+Assumptions!$C$7)^1,0) -> 8100 | V4: =IF(AND(F4<=DATE(2026,2,1),OR(G4="",G4>=DATE(2026,2,1))),H4*(1+Assumptions!$C$7)^1,0) -> 8100 | W4: =IF(AND(F4<=DATE(2026,3,1),OR(G4="",G4>=DATE(2026,3,1))),H4*(1+Assumptions!$C$7)^1,0) -> 8100 | X4: =IF(AND(F4<=DATE(2026,4,1),OR(G4="",G4>=DATE(2026,4,1))),H4*(1+Assumptions!$C$7)^1,0) -> 8100 | Y4: =IF(AND(F4<=DATE(2026,5,1),OR(G4="",G4>=DATE(2026,5,1))),H4*(1+Assumptions!$C$7)^1,0) -> 8100 | Z4: =IF(AND(F4<=DATE(2026,6,1),OR(G4="",G4>=DATE(2026,6,1))),H4*(1+Assumptions!$C$7)^1,0) -> 8100 | AA4: =IF(AND(F4<=DATE(2026,7,1),OR(G4="",G4>=DATE(2026,7,1))),H4*(1+Assumptions!$C$7)^1,0) -> 8100 | AB4: =IF(AND(F4<=DATE(2026,8,1),OR(G4="",G4>=DATE(2026,8,1))),H4*(1+Assumptions!$C$7)^1,0) -> 8100 | AC4: =IF(AND(F4<=DATE(2026,9,1),OR(G4="",G4>=DATE(2026,9,1))),H4*(1+Assumptions!$C$7)^1,0) -> 8100 | AD4: =IF(AND(F4<=DATE(2026,10,1),OR(G4="",G4>=DATE(2026,10,1))),H4*(1+Assumptions!$C$7)^1,0) -> 8100 | AE4: =IF(AND(F4<=DATE(2026,11,1),OR(G4="",G4>=DATE(2026,11,1))),H4*(1+Assumptions!$C$7)^1,0) -> 8100 | AF4: =IF(AND(F4<=DATE(2026,12,1),OR(G4="",G4>=DATE(2026,12,1))),H4*(1+Assumptions!$C$7)^1,0) -> 8100 | AG4: =IF(AND(F4<=DATE(2027,1,1),OR(G4="",G4>=DATE(2027,1,1))),H4*(1+Assumptions!$C$7)^2,0) -> 8748 | AH4: =IF(AND(F4<=DATE(2027,2,1),OR(G4="",G4>=DATE(2027,2,1))),H4*(1+Assumptions!$C$7)^2,0) -> 8748 | AI4: =IF(AND(F4<=DATE(2027,3,1),OR(G4="",G4>=DATE(2027,3,1))),H4*(1+Assumptions!$C$7)^2,0) -> 8748 | AJ4: =IF(AND(F4<=DATE(2027,4,1),OR(G4="",G4>=DATE(2027,4,1))),H4*(1+Assumptions!$C$7)^2,0) -> 8748 | AK4: =IF(AND(F4<=DATE(2027,5,1),OR(G4="",G4>=DATE(2027,5,1))),H4*(1+Assumptions!$C$7)^2,0) -> 8748 | AL4: =IF(AND(F4<=DATE(2027,6,1),OR(G4="",G4>=DATE(2027,6,1))),H4*(1+Assumptions!$C$7)^2,0) -> 8748 | AM4: =IF(AND(F4<=DATE(2027,7,1),OR(G4="",G4>=DATE(2027,7,1))),H4*(1+Assumptions!$C$7)^2,0) -> 8748 | AN4: =IF(AND(F4<=DATE(2027,8,1),OR(G4="",G4>=DATE(2027,8,1))),H4*(1+Assumptions!$C$7)^2,0) -> 8748 | AO4: =IF(AND(F4<=DATE(2027,9,1),OR(G4="",G4>=DATE(2027,9,1))),H4*(1+Assumptions!$C$7)^2,0) -> 8748 | AP4: =IF(AND(F4<=DATE(2027,10,1),OR(G4="",G4>=DATE(2027,10,1))),H4*(1+Assumptions!$C$7)^2,0) -> 8748 | AQ4: =IF(AND(F4<=DATE(2027,11,1),OR(G4="",G4>=DATE(2027,11,1))),H4*(1+Assumptions!$C$7)^2,0) -> 8748 | AR4: =IF(AND(F4<=DATE(2027,12,1),OR(G4="",G4>=DATE(2027,12,1))),H4*(1+Assumptions!$C$7)^2,0) -> 8748 | AS4: =IF(AND(F4<=DATE(2028,1,1),OR(G4="",G4>=DATE(2028,1,1))),H4*(1+Assumptions!$C$7)^3,0) -> 9447.84 | AT4: =IF(AND(F4<=DATE(2028,2,1),OR(G4="",G4>=DATE(2028,2,1))),H4*(1+Assumptions!$C$7)^3,0) -> 9447.84 | AU4: =IF(AND(F4<=DATE(2028,3,1),OR(G4="",G4>=DATE(2028,3,1))),H4*(1+Assumptions!$C$7)^3,0) -> 9447.84 | AV4: =IF(AND(F4<=DATE(2028,4,1),OR(G4="",G4>=DATE(2028,4,1))),H4*(1+Assumptions!$C$7)^3,0) -> 9447.84 | AW4: =IF(AND(F4<=DATE(2028,5,1),OR(G4="",G4>=DATE(2028,5,1))),H4*(1+Assumptions!$C$7)^3,0) -> 9447.84 | AX4: =IF(AND(F4<=DATE(2028,6,1),OR(G4="",G4>=DATE(2028,6,1))),H4*(1+Assumptions!$C$7)^3,0) -> 9447.84 | AY4: =IF(AND(F4<=DATE(2028,7,1),OR(G4="",G4>=DATE(2028,7,1))),H4*(1+Assumptions!$C$7)^3,0) -> 9447.84 | AZ4: =IF(AND(F4<=DATE(2028,8,1),OR(G4="",G4>=DATE(2028,8,1))),H4*(1+Assumptions!$C$7)^3,0) -> 9447.84 | BA4: =IF(AND(F4<=DATE(2028,9,1),OR(G4="",G4>=DATE(2028,9,1))),H4*(1+Assumptions!$C$7)^3,0) -> 9447.84 | BB4: =IF(AND(F4<=DATE(2028,10,1),OR(G4="",G4>=DATE(2028,10,1))),H4*(1+Assumptions!$C$7)^3,0) -> 9447.84 | BC4: =IF(AND(F4<=DATE(2028,11,1),OR(G4="",G4>=DATE(2028,11,1))),H4*(1+Assumptions!$C$7)^3,0) -> 9447.84 | BD4: =IF(AND(F4<=DATE(2028,12,1),OR(G4="",G4>=DATE(2028,12,1))),H4*(1+Assumptions!$C$7)^3,0) -> 9447.84 | BE4: =IF(AND(F4<=DATE(2029,1,1),OR(G4="",G4>=DATE(2029,1,1))),H4*(1+Assumptions!$C$7)^4,0) -> 10203.667 | BF4: =IF(AND(F4<=DATE(2029,2,1),OR(G4="",G4>=DATE(2029,2,1))),H4*(1+Assumptions!$C$7)^4,0) -> 10203.667 | BG4: =IF(AND(F4<=DATE(2029,3,1),OR(G4="",G4>=DATE(2029,3,1))),H4*(1+Assumptions!$C$7)^4,0) -> 10203.667 | BH4: =IF(AND(F4<=DATE(2029,4,1),OR(G4="",G4>=DATE(2029,4,1))),H4*(1+Assumptions!$C$7)^4,0) -> 10203.667 | BI4: =IF(AND(F4<=DATE(2029,5,1),OR(G4="",G4>=DATE(2029,5,1))),H4*(1+Assumptions!$C$7)^4,0) -> 10203.667 | BJ4: =IF(AND(F4<=DATE(2029,6,1),OR(G4="",G4>=DATE(2029,6,1))),H4*(1+Assumptions!$C$7)^4,0) -> 10203.667 | BK4: =IF(AND(F4<=DATE(2029,7,1),OR(G4="",G4>=DATE(2029,7,1))),H4*(1+Assumptions!$C$7)^4,0) -> 10203.667 | BL4: =IF(AND(F4<=DATE(2029,8,1),OR(G4="",G4>=DATE(2029,8,1))),H4*(1+Assumptions!$C$7)^4,0) -> 10203.667 | BM4: =IF(AND(F4<=DATE(2029,9,1),OR(G4="",G4>=DATE(2029,9,1))),H4*(1+Assumptions!$C$7)^4,0) -> 10203.667 | BN4: =IF(AND(F4<=DATE(2029,10,1),OR(G4="",G4>=DATE(2029,10,1))),H4*(1+Assumptions!$C$7)^4,0) -> 10203.667 | BO4: =IF(AND(F4<=DATE(2029,11,1),OR(G4="",G4>=DATE(2029,11,1))),H4*(1+Assumptions!$C$7)^4,0) -> 10203.667 | BP4: =IF(AND(F4<=DATE(2029,12,1),OR(G4="",G4>=DATE(2029,12,1))),H4*(1+Assumptions!$C$7)^4,0) -> 10203.667
A5: 3 | B5: R&D Engineer | C5: R&D | D5: R&D Engineer | E5: Current | F5: 45901 | H5: 3000 | I5: =IF(AND(F5<=DATE(2025,1,1),OR(G5="",G5>=DATE(2025,1,1))),H5*(1+Assumptions!$C$7)^0,0) -> 0 | J5: =IF(AND(F5<=DATE(2025,2,1),OR(G5="",G5>=DATE(2025,2,1))),H5*(1+Assumptions!$C$7)^0,0) -> 0 | K5: =IF(AND(F5<=DATE(2025,3,1),OR(G5="",G5>=DATE(2025,3,1))),H5*(1+Assumptions!$C$7)^0,0) -> 0 | L5: =IF(AND(F5<=DATE(2025,4,1),OR(G5="",G5>=DATE(2025,4,1))),H5*(1+Assumptions!$C$7)^0,0) -> 0 | M5: =IF(AND(F5<=DATE(2025,5,1),OR(G5="",G5>=DATE(2025,5,1))),H5*(1+Assumptions!$C$7)^0,0) -> 0 | N5: =IF(AND(F5<=DATE(2025,6,1),OR(G5="",G5>=DATE(2025,6,1))),H5*(1+Assumptions!$C$7)^0,0) -> 0 | O5: =IF(AND(F5<=DATE(2025,7,1),OR(G5="",G5>=DATE(2025,7,1))),H5*(1+Assumptions!$C$7)^0,0) -> 0 | P5: =IF(AND(F5<=DATE(2025,8,1),OR(G5="",G5>=DATE(2025,8,1))),H5*(1+Assumptions!$C$7)^0,0) -> 0 | Q5: =IF(AND(F5<=DATE(2025,9,1),OR(G5="",G5>=DATE(2025,9,1))),H5*(1+Assumptions!$C$7)^0,0) -> 3000 | R5: =IF(AND(F5<=DATE(2025,10,1),OR(G5="",G5>=DATE(2025,10,1))),H5*(1+Assumptions!$C$7)^0,0) -> 3000 | S5: =IF(AND(F5<=DATE(2025,11,1),OR(G5="",G5>=DATE(2025,11,1))),H5*(1+Assumptions!$C$7)^0,0) -> 3000 | T5: =IF(AND(F5<=DATE(2025,12,1),OR(G5="",G5>=DATE(2025,12,1))),H5*(1+Assumptions!$C$7)^0,0) -> 3000 | U5: =IF(AND(F5<=DATE(2026,1,1),OR(G5="",G5>=DATE(2026,1,1))),H5*(1+Assumptions!$C$7)^1,0) -> 3240 | V5: =IF(AND(F5<=DATE(2026,2,1),OR(G5="",G5>=DATE(2026,2,1))),H5*(1+Assumptions!$C$7)^1,0) -> 3240 | W5: =IF(AND(F5<=DATE(2026,3,1),OR(G5="",G5>=DATE(2026,3,1))),H5*(1+Assumptions!$C$7)^1,0) -> 3240 | X5: =IF(AND(F5<=DATE(2026,4,1),OR(G5="",G5>=DATE(2026,4,1))),H5*(1+Assumptions!$C$7)^1,0) -> 3240 | Y5: =IF(AND(F5<=DATE(2026,5,1),OR(G5="",G5>=DATE(2026,5,1))),H5*(1+Assumptions!$C$7)^1,0) -> 3240 | Z5: =IF(AND(F5<=DATE(2026,6,1),OR(G5="",G5>=DATE(2026,6,1))),H5*(1+Assumptions!$C$7)^1,0) -> 3240 | AA5: =IF(AND(F5<=DATE(2026,7,1),OR(G5="",G5>=DATE(2026,7,1))),H5*(1+Assumptions!$C$7)^1,0) -> 3240 | AB5: =IF(AND(F5<=DATE(2026,8,1),OR(G5="",G5>=DATE(2026,8,1))),H5*(1+Assumptions!$C$7)^1,0) -> 3240 | AC5: =IF(AND(F5<=DATE(2026,9,1),OR(G5="",G5>=DATE(2026,9,1))),H5*(1+Assumptions!$C$7)^1,0) -> 3240 | AD5: =IF(AND(F5<=DATE(2026,10,1),OR(G5="",G5>=DATE(2026,10,1))),H5*(1+Assumptions!$C$7)^1,0) -> 3240 | AE5: =IF(AND(F5<=DATE(2026,11,1),OR(G5="",G5>=DATE(2026,11,1))),H5*(1+Assumptions!$C$7)^1,0) -> 3240 | AF5: =IF(AND(F5<=DATE(2026,12,1),OR(G5="",G5>=DATE(2026,12,1))),H5*(1+Assumptions!$C$7)^1,0) -> 3240 | AG5: =IF(AND(F5<=DATE(2027,1,1),OR(G5="",G5>=DATE(2027,1,1))),H5*(1+Assumptions!$C$7)^2,0) -> 3499.2 | AH5: =IF(AND(F5<=DATE(2027,2,1),OR(G5="",G5>=DATE(2027,2,1))),H5*(1+Assumptions!$C$7)^2,0) -> 3499.2 | AI5: =IF(AND(F5<=DATE(2027,3,1),OR(G5="",G5>=DATE(2027,3,1))),H5*(1+Assumptions!$C$7)^2,0) -> 3499.2 | AJ5: =IF(AND(F5<=DATE(2027,4,1),OR(G5="",G5>=DATE(2027,4,1))),H5*(1+Assumptions!$C$7)^2,0) -> 3499.2 | AK5: =IF(AND(F5<=DATE(2027,5,1),OR(G5="",G5>=DATE(2027,5,1))),H5*(1+Assumptions!$C$7)^2,0) -> 3499.2 | AL5: =IF(AND(F5<=DATE(2027,6,1),OR(G5="",G5>=DATE(2027,6,1))),H5*(1+Assumptions!$C$7)^2,0) -> 3499.2 | AM5: =IF(AND(F5<=DATE(2027,7,1),OR(G5="",G5>=DATE(2027,7,1))),H5*(1+Assumptions!$C$7)^2,0) -> 3499.2 | AN5: =IF(AND(F5<=DATE(2027,8,1),OR(G5="",G5>=DATE(2027,8,1))),H5*(1+Assumptions!$C$7)^2,0) -> 3499.2 | AO5: =IF(AND(F5<=DATE(2027,9,1),OR(G5="",G5>=DATE(2027,9,1))),H5*(1+Assumptions!$C$7)^2,0) -> 3499.2 | AP5: =IF(AND(F5<=DATE(2027,10,1),OR(G5="",G5>=DATE(2027,10,1))),H5*(1+Assumptions!$C$7)^2,0) -> 3499.2 | AQ5: =IF(AND(F5<=DATE(2027,11,1),OR(G5="",G5>=DATE(2027,11,1))),H5*(1+Assumptions!$C$7)^2,0) -> 3499.2 | AR5: =IF(AND(F5<=DATE(2027,12,1),OR(G5="",G5>=DATE(2027,12,1))),H5*(1+Assumptions!$C$7)^2,0) -> 3499.2 | AS5: =IF(AND(F5<=DATE(2028,1,1),OR(G5="",G5>=DATE(2028,1,1))),H5*(1+Assumptions!$C$7)^3,0) -> 3779.136 | AT5: =IF(AND(F5<=DATE(2028,2,1),OR(G5="",G5>=DATE(2028,2,1))),H5*(1+Assumptions!$C$7)^3,0) -> 3779.136 | AU5: =IF(AND(F5<=DATE(2028,3,1),OR(G5="",G5>=DATE(2028,3,1))),H5*(1+Assumptions!$C$7)^3,0) -> 3779.136 | AV5: =IF(AND(F5<=DATE(2028,4,1),OR(G5="",G5>=DATE(2028,4,1))),H5*(1+Assumptions!$C$7)^3,0) -> 3779.136 | AW5: =IF(AND(F5<=DATE(2028,5,1),OR(G5="",G5>=DATE(2028,5,1))),H5*(1+Assumptions!$C$7)^3,0) -> 3779.136 | AX5: =IF(AND(F5<=DATE(2028,6,1),OR(G5="",G5>=DATE(2028,6,1))),H5*(1+Assumptions!$C$7)^3,0) -> 3779.136 | AY5: =IF(AND(F5<=DATE(2028,7,1),OR(G5="",G5>=DATE(2028,7,1))),H5*(1+Assumptions!$C$7)^3,0) -> 3779.136 | AZ5: =IF(AND(F5<=DATE(2028,8,1),OR(G5="",G5>=DATE(2028,8,1))),H5*(1+Assumptions!$C$7)^3,0) -> 3779.136 | BA5: =IF(AND(F5<=DATE(2028,9,1),OR(G5="",G5>=DATE(2028,9,1))),H5*(1+Assumptions!$C$7)^3,0) -> 3779.136 | BB5: =IF(AND(F5<=DATE(2028,10,1),OR(G5="",G5>=DATE(2028,10,1))),H5*(1+Assumptions!$C$7)^3,0) -> 3779.136 | BC5: =IF(AND(F5<=DATE(2028,11,1),OR(G5="",G5>=DATE(2028,11,1))),H5*(1+Assumptions!$C$7)^3,0) -> 3779.136 | BD5: =IF(AND(F5<=DATE(2028,12,1),OR(G5="",G5>=DATE(2028,12,1))),H5*(1+Assumptions!$C$7)^3,0) -> 3779.136 | BE5: =IF(AND(F5<=DATE(2029,1,1),OR(G5="",G5>=DATE(2029,1,1))),H5*(1+Assumptions!$C$7)^4,0) -> 4081.4669 | BF5: =IF(AND(F5<=DATE(2029,2,1),OR(G5="",G5>=DATE(2029,2,1))),H5*(1+Assumptions!$C$7)^4,0) -> 4081.4669 | BG5: =IF(AND(F5<=DATE(2029,3,1),OR(G5="",G5>=DATE(2029,3,1))),H5*(1+Assumptions!$C$7)^4,0) -> 4081.4669 | BH5: =IF(AND(F5<=DATE(2029,4,1),OR(G5="",G5>=DATE(2029,4,1))),H5*(1+Assumptions!$C$7)^4,0) -> 4081.4669 | BI5: =IF(AND(F5<=DATE(2029,5,1),OR(G5="",G5>=DATE(2029,5,1))),H5*(1+Assumptions!$C$7)^4,0) -> 4081.4669 | BJ5: =IF(AND(F5<=DATE(2029,6,1),OR(G5="",G5>=DATE(2029,6,1))),H5*(1+Assumptions!$C$7)^4,0) -> 4081.4669 | BK5: =IF(AND(F5<=DATE(2029,7,1),OR(G5="",G5>=DATE(2029,7,1))),H5*(1+Assumptions!$C$7)^4,0) -> 4081.4669 | BL5: =IF(AND(F5<=DATE(2029,8,1),OR(G5="",G5>=DATE(2029,8,1))),H5*(1+Assumptions!$C$7)^4,0) -> 4081.4669 | BM5: =IF(AND(F5<=DATE(2029,9,1),OR(G5="",G5>=DATE(2029,9,1))),H5*(1+Assumptions!$C$7)^4,0) -> 4081.4669 | BN5: =IF(AND(F5<=DATE(2029,10,1),OR(G5="",G5>=DATE(2029,10,1))),H5*(1+Assumptions!$C$7)^4,0) -> 4081.4669 | BO5: =IF(AND(F5<=DATE(2029,11,1),OR(G5="",G5>=DATE(2029,11,1))),H5*(1+Assumptions!$C$7)^4,0) -> 4081.4669 | BP5: =IF(AND(F5<=DATE(2029,12,1),OR(G5="",G5>=DATE(2029,12,1))),H5*(1+Assumptions!$C$7)^4,0) -> 4081.4669
A6: 4 | B6: R&D Engineer | C6: R&D | D6: R&D Engineer | E6: Current | F6: 45901 | H6: 6000 | I6: =IF(AND(F6<=DATE(2025,1,1),OR(G6="",G6>=DATE(2025,1,1))),H6*(1+Assumptions!$C$7)^0,0) -> 0 | J6: =IF(AND(F6<=DATE(2025,2,1),OR(G6="",G6>=DATE(2025,2,1))),H6*(1+Assumptions!$C$7)^0,0) -> 0 | K6: =IF(AND(F6<=DATE(2025,3,1),OR(G6="",G6>=DATE(2025,3,1))),H6*(1+Assumptions!$C$7)^0,0) -> 0 | L6: =IF(AND(F6<=DATE(2025,4,1),OR(G6="",G6>=DATE(2025,4,1))),H6*(1+Assumptions!$C$7)^0,0) -> 0 | M6: =IF(AND(F6<=DATE(2025,5,1),OR(G6="",G6>=DATE(2025,5,1))),H6*(1+Assumptions!$C$7)^0,0) -> 0 | N6: =IF(AND(F6<=DATE(2025,6,1),OR(G6="",G6>=DATE(2025,6,1))),H6*(1+Assumptions!$C$7)^0,0) -> 0 | O6: =IF(AND(F6<=DATE(2025,7,1),OR(G6="",G6>=DATE(2025,7,1))),H6*(1+Assumptions!$C$7)^0,0) -> 0 | P6: =IF(AND(F6<=DATE(2025,8,1),OR(G6="",G6>=DATE(2025,8,1))),H6*(1+Assumptions!$C$7)^0,0) -> 0 | Q6: =IF(AND(F6<=DATE(2025,9,1),OR(G6="",G6>=DATE(2025,9,1))),H6*(1+Assumptions!$C$7)^0,0) -> 6000 | R6: =IF(AND(F6<=DATE(2025,10,1),OR(G6="",G6>=DATE(2025,10,1))),H6*(1+Assumptions!$C$7)^0,0) -> 6000 | S6: =IF(AND(F6<=DATE(2025,11,1),OR(G6="",G6>=DATE(2025,11,1))),H6*(1+Assumptions!$C$7)^0,0) -> 6000 | T6: =IF(AND(F6<=DATE(2025,12,1),OR(G6="",G6>=DATE(2025,12,1))),H6*(1+Assumptions!$C$7)^0,0) -> 6000 | U6: =IF(AND(F6<=DATE(2026,1,1),OR(G6="",G6>=DATE(2026,1,1))),H6*(1+Assumptions!$C$7)^1,0) -> 6480 | V6: =IF(AND(F6<=DATE(2026,2,1),OR(G6="",G6>=DATE(2026,2,1))),H6*(1+Assumptions!$C$7)^1,0) -> 6480 | W6: =IF(AND(F6<=DATE(2026,3,1),OR(G6="",G6>=DATE(2026,3,1))),H6*(1+Assumptions!$C$7)^1,0) -> 6480 | X6: =IF(AND(F6<=DATE(2026,4,1),OR(G6="",G6>=DATE(2026,4,1))),H6*(1+Assumptions!$C$7)^1,0) -> 6480 | Y6: =IF(AND(F6<=DATE(2026,5,1),OR(G6="",G6>=DATE(2026,5,1))),H6*(1+Assumptions!$C$7)^1,0) -> 6480 | Z6: =IF(AND(F6<=DATE(2026,6,1),OR(G6="",G6>=DATE(2026,6,1))),H6*(1+Assumptions!$C$7)^1,0) -> 6480 | AA6: =IF(AND(F6<=DATE(2026,7,1),OR(G6="",G6>=DATE(2026,7,1))),H6*(1+Assumptions!$C$7)^1,0) -> 6480 | AB6: =IF(AND(F6<=DATE(2026,8,1),OR(G6="",G6>=DATE(2026,8,1))),H6*(1+Assumptions!$C$7)^1,0) -> 6480 | AC6: =IF(AND(F6<=DATE(2026,9,1),OR(G6="",G6>=DATE(2026,9,1))),H6*(1+Assumptions!$C$7)^1,0) -> 6480 | AD6: =IF(AND(F6<=DATE(2026,10,1),OR(G6="",G6>=DATE(2026,10,1))),H6*(1+Assumptions!$C$7)^1,0) -> 6480 | AE6: =IF(AND(F6<=DATE(2026,11,1),OR(G6="",G6>=DATE(2026,11,1))),H6*(1+Assumptions!$C$7)^1,0) -> 6480 | AF6: =IF(AND(F6<=DATE(2026,12,1),OR(G6="",G6>=DATE(2026,12,1))),H6*(1+Assumptions!$C$7)^1,0) -> 6480 | AG6: =IF(AND(F6<=DATE(2027,1,1),OR(G6="",G6>=DATE(2027,1,1))),H6*(1+Assumptions!$C$7)^2,0) -> 6998.4 | AH6: =IF(AND(F6<=DATE(2027,2,1),OR(G6="",G6>=DATE(2027,2,1))),H6*(1+Assumptions!$C$7)^2,0) -> 6998.4 | AI6: =IF(AND(F6<=DATE(2027,3,1),OR(G6="",G6>=DATE(2027,3,1))),H6*(1+Assumptions!$C$7)^2,0) -> 6998.4 | AJ6: =IF(AND(F6<=DATE(2027,4,1),OR(G6="",G6>=DATE(2027,4,1))),H6*(1+Assumptions!$C$7)^2,0) -> 6998.4 | AK6: =IF(AND(F6<=DATE(2027,5,1),OR(G6="",G6>=DATE(2027,5,1))),H6*(1+Assumptions!$C$7)^2,0) -> 6998.4 | AL6: =IF(AND(F6<=DATE(2027,6,1),OR(G6="",G6>=DATE(2027,6,1))),H6*(1+Assumptions!$C$7)^2,0) -> 6998.4 | AM6: =IF(AND(F6<=DATE(2027,7,1),OR(G6="",G6>=DATE(2027,7,1))),H6*(1+Assumptions!$C$7)^2,0) -> 6998.4 | AN6: =IF(AND(F6<=DATE(2027,8,1),OR(G6="",G6>=DATE(2027,8,1))),H6*(1+Assumptions!$C$7)^2,0) -> 6998.4 | AO6: =IF(AND(F6<=DATE(2027,9,1),OR(G6="",G6>=DATE(2027,9,1))),H6*(1+Assumptions!$C$7)^2,0) -> 6998.4 | AP6: =IF(AND(F6<=DATE(2027,10,1),OR(G6="",G6>=DATE(2027,10,1))),H6*(1+Assumptions!$C$7)^2,0) -> 6998.4 | AQ6: =IF(AND(F6<=DATE(2027,11,1),OR(G6="",G6>=DATE(2027,11,1))),H6*(1+Assumptions!$C$7)^2,0) -> 6998.4 | AR6: =IF(AND(F6<=DATE(2027,12,1),OR(G6="",G6>=DATE(2027,12,1))),H6*(1+Assumptions!$C$7)^2,0) -> 6998.4 | AS6: =IF(AND(F6<=DATE(2028,1,1),OR(G6="",G6>=DATE(2028,1,1))),H6*(1+Assumptions!$C$7)^3,0) -> 7558.272 | AT6: =IF(AND(F6<=DATE(2028,2,1),OR(G6="",G6>=DATE(2028,2,1))),H6*(1+Assumptions!$C$7)^3,0) -> 7558.272 | AU6: =IF(AND(F6<=DATE(2028,3,1),OR(G6="",G6>=DATE(2028,3,1))),H6*(1+Assumptions!$C$7)^3,0) -> 7558.272 | AV6: =IF(AND(F6<=DATE(2028,4,1),OR(G6="",G6>=DATE(2028,4,1))),H6*(1+Assumptions!$C$7)^3,0) -> 7558.272 | AW6: =IF(AND(F6<=DATE(2028,5,1),OR(G6="",G6>=DATE(2028,5,1))),H6*(1+Assumptions!$C$7)^3,0) -> 7558.272 | AX6: =IF(AND(F6<=DATE(2028,6,1),OR(G6="",G6>=DATE(2028,6,1))),H6*(1+Assumptions!$C$7)^3,0) -> 7558.272 | AY6: =IF(AND(F6<=DATE(2028,7,1),OR(G6="",G6>=DATE(2028,7,1))),H6*(1+Assumptions!$C$7)^3,0) -> 7558.272 | AZ6: =IF(AND(F6<=DATE(2028,8,1),OR(G6="",G6>=DATE(2028,8,1))),H6*(1+Assumptions!$C$7)^3,0) -> 7558.272 | BA6: =IF(AND(F6<=DATE(2028,9,1),OR(G6="",G6>=DATE(2028,9,1))),H6*(1+Assumptions!$C$7)^3,0) -> 7558.272 | BB6: =IF(AND(F6<=DATE(2028,10,1),OR(G6="",G6>=DATE(2028,10,1))),H6*(1+Assumptions!$C$7)^3,0) -> 7558.272 | BC6: =IF(AND(F6<=DATE(2028,11,1),OR(G6="",G6>=DATE(2028,11,1))),H6*(1+Assumptions!$C$7)^3,0) -> 7558.272 | BD6: =IF(AND(F6<=DATE(2028,12,1),OR(G6="",G6>=DATE(2028,12,1))),H6*(1+Assumptions!$C$7)^3,0) -> 7558.272 | BE6: =IF(AND(F6<=DATE(2029,1,1),OR(G6="",G6>=DATE(2029,1,1))),H6*(1+Assumptions!$C$7)^4,0) -> 8162.9338 | BF6: =IF(AND(F6<=DATE(2029,2,1),OR(G6="",G6>=DATE(2029,2,1))),H6*(1+Assumptions!$C$7)^4,0) -> 8162.9338 | BG6: =IF(AND(F6<=DATE(2029,3,1),OR(G6="",G6>=DATE(2029,3,1))),H6*(1+Assumptions!$C$7)^4,0) -> 8162.9338 | BH6: =IF(AND(F6<=DATE(2029,4,1),OR(G6="",G6>=DATE(2029,4,1))),H6*(1+Assumptions!$C$7)^4,0) -> 8162.9338 | BI6: =IF(AND(F6<=DATE(2029,5,1),OR(G6="",G6>=DATE(2029,5,1))),H6*(1+Assumptions!$C$7)^4,0) -> 8162.9338 | BJ6: =IF(AND(F6<=DATE(2029,6,1),OR(G6="",G6>=DATE(2029,6,1))),H6*(1+Assumptions!$C$7)^4,0) -> 8162.9338 | BK6: =IF(AND(F6<=DATE(2029,7,1),OR(G6="",G6>=DATE(2029,7,1))),H6*(1+Assumptions!$C$7)^4,0) -> 8162.9338 | BL6: =IF(AND(F6<=DATE(2029,8,1),OR(G6="",G6>=DATE(2029,8,1))),H6*(1+Assumptions!$C$7)^4,0) -> 8162.9338 | BM6: =IF(AND(F6<=DATE(2029,9,1),OR(G6="",G6>=DATE(2029,9,1))),H6*(1+Assumptions!$C$7)^4,0) -> 8162.9338 | BN6: =IF(AND(F6<=DATE(2029,10,1),OR(G6="",G6>=DATE(2029,10,1))),H6*(1+Assumptions!$C$7)^4,0) -> 8162.9338 | BO6: =IF(AND(F6<=DATE(2029,11,1),OR(G6="",G6>=DATE(2029,11,1))),H6*(1+Assumptions!$C$7)^4,0) -> 8162.9338 | BP6: =IF(AND(F6<=DATE(2029,12,1),OR(G6="",G6>=DATE(2029,12,1))),H6*(1+Assumptions!$C$7)^4,0) -> 8162.9338
A7: 5 | B7: Firmware Engineer | C7: R&D | D7: R&D Engineer | E7: Current | F7: 45901 | H7: 7000 | I7: =IF(AND(F7<=DATE(2025,1,1),OR(G7="",G7>=DATE(2025,1,1))),H7*(1+Assumptions!$C$7)^0,0) -> 0 | J7: =IF(AND(F7<=DATE(2025,2,1),OR(G7="",G7>=DATE(2025,2,1))),H7*(1+Assumptions!$C$7)^0,0) -> 0 | K7: =IF(AND(F7<=DATE(2025,3,1),OR(G7="",G7>=DATE(2025,3,1))),H7*(1+Assumptions!$C$7)^0,0) -> 0 | L7: =IF(AND(F7<=DATE(2025,4,1),OR(G7="",G7>=DATE(2025,4,1))),H7*(1+Assumptions!$C$7)^0,0) -> 0 | M7: =IF(AND(F7<=DATE(2025,5,1),OR(G7="",G7>=DATE(2025,5,1))),H7*(1+Assumptions!$C$7)^0,0) -> 0 | N7: =IF(AND(F7<=DATE(2025,6,1),OR(G7="",G7>=DATE(2025,6,1))),H7*(1+Assumptions!$C$7)^0,0) -> 0 | O7: =IF(AND(F7<=DATE(2025,7,1),OR(G7="",G7>=DATE(2025,7,1))),H7*(1+Assumptions!$C$7)^0,0) -> 0 | P7: =IF(AND(F7<=DATE(2025,8,1),OR(G7="",G7>=DATE(2025,8,1))),H7*(1+Assumptions!$C$7)^0,0) -> 0 | Q7: =IF(AND(F7<=DATE(2025,9,1),OR(G7="",G7>=DATE(2025,9,1))),H7*(1+Assumptions!$C$7)^0,0) -> 7000 | R7: =IF(AND(F7<=DATE(2025,10,1),OR(G7="",G7>=DATE(2025,10,1))),H7*(1+Assumptions!$C$7)^0,0) -> 7000 | S7: =IF(AND(F7<=DATE(2025,11,1),OR(G7="",G7>=DATE(2025,11,1))),H7*(1+Assumptions!$C$7)^0,0) -> 7000 | T7: =IF(AND(F7<=DATE(2025,12,1),OR(G7="",G7>=DATE(2025,12,1))),H7*(1+Assumptions!$C$7)^0,0) -> 7000 | U7: =IF(AND(F7<=DATE(2026,1,1),OR(G7="",G7>=DATE(2026,1,1))),H7*(1+Assumptions!$C$7)^1,0) -> 7560 | V7: =IF(AND(F7<=DATE(2026,2,1),OR(G7="",G7>=DATE(2026,2,1))),H7*(1+Assumptions!$C$7)^1,0) -> 7560 | W7: =IF(AND(F7<=DATE(2026,3,1),OR(G7="",G7>=DATE(2026,3,1))),H7*(1+Assumptions!$C$7)^1,0) -> 7560 | X7: =IF(AND(F7<=DATE(2026,4,1),OR(G7="",G7>=DATE(2026,4,1))),H7*(1+Assumptions!$C$7)^1,0) -> 7560 | Y7: =IF(AND(F7<=DATE(2026,5,1),OR(G7="",G7>=DATE(2026,5,1))),H7*(1+Assumptions!$C$7)^1,0) -> 7560 | Z7: =IF(AND(F7<=DATE(2026,6,1),OR(G7="",G7>=DATE(2026,6,1))),H7*(1+Assumptions!$C$7)^1,0) -> 7560 | AA7: =IF(AND(F7<=DATE(2026,7,1),OR(G7="",G7>=DATE(2026,7,1))),H7*(1+Assumptions!$C$7)^1,0) -> 7560 | AB7: =IF(AND(F7<=DATE(2026,8,1),OR(G7="",G7>=DATE(2026,8,1))),H7*(1+Assumptions!$C$7)^1,0) -> 7560 | AC7: =IF(AND(F7<=DATE(2026,9,1),OR(G7="",G7>=DATE(2026,9,1))),H7*(1+Assumptions!$C$7)^1,0) -> 7560 | AD7: =IF(AND(F7<=DATE(2026,10,1),OR(G7="",G7>=DATE(2026,10,1))),H7*(1+Assumptions!$C$7)^1,0) -> 7560 | AE7: =IF(AND(F7<=DATE(2026,11,1),OR(G7="",G7>=DATE(2026,11,1))),H7*(1+Assumptions!$C$7)^1,0) -> 7560 | AF7: =IF(AND(F7<=DATE(2026,12,1),OR(G7="",G7>=DATE(2026,12,1))),H7*(1+Assumptions!$C$7)^1,0) -> 7560 | AG7: =IF(AND(F7<=DATE(2027,1,1),OR(G7="",G7>=DATE(2027,1,1))),H7*(1+Assumptions!$C$7)^2,0) -> 8164.8 | AH7: =IF(AND(F7<=DATE(2027,2,1),OR(G7="",G7>=DATE(2027,2,1))),H7*(1+Assumptions!$C$7)^2,0) -> 8164.8 | AI7: =IF(AND(F7<=DATE(2027,3,1),OR(G7="",G7>=DATE(2027,3,1))),H7*(1+Assumptions!$C$7)^2,0) -> 8164.8 | AJ7: =IF(AND(F7<=DATE(2027,4,1),OR(G7="",G7>=DATE(2027,4,1))),H7*(1+Assumptions!$C$7)^2,0) -> 8164.8 | AK7: =IF(AND(F7<=DATE(2027,5,1),OR(G7="",G7>=DATE(2027,5,1))),H7*(1+Assumptions!$C$7)^2,0) -> 8164.8 | AL7: =IF(AND(F7<=DATE(2027,6,1),OR(G7="",G7>=DATE(2027,6,1))),H7*(1+Assumptions!$C$7)^2,0) -> 8164.8 | AM7: =IF(AND(F7<=DATE(2027,7,1),OR(G7="",G7>=DATE(2027,7,1))),H7*(1+Assumptions!$C$7)^2,0) -> 8164.8 | AN7: =IF(AND(F7<=DATE(2027,8,1),OR(G7="",G7>=DATE(2027,8,1))),H7*(1+Assumptions!$C$7)^2,0) -> 8164.8 | AO7: =IF(AND(F7<=DATE(2027,9,1),OR(G7="",G7>=DATE(2027,9,1))),H7*(1+Assumptions!$C$7)^2,0) -> 8164.8 | AP7: =IF(AND(F7<=DATE(2027,10,1),OR(G7="",G7>=DATE(2027,10,1))),H7*(1+Assumptions!$C$7)^2,0) -> 8164.8 | AQ7: =IF(AND(F7<=DATE(2027,11,1),OR(G7="",G7>=DATE(2027,11,1))),H7*(1+Assumptions!$C$7)^2,0) -> 8164.8 | AR7: =IF(AND(F7<=DATE(2027,12,1),OR(G7="",G7>=DATE(2027,12,1))),H7*(1+Assumptions!$C$7)^2,0) -> 8164.8 | AS7: =IF(AND(F7<=DATE(2028,1,1),OR(G7="",G7>=DATE(2028,1,1))),H7*(1+Assumptions!$C$7)^3,0) -> 8817.984 | AT7: =IF(AND(F7<=DATE(2028,2,1),OR(G7="",G7>=DATE(2028,2,1))),H7*(1+Assumptions!$C$7)^3,0) -> 8817.984 | AU7: =IF(AND(F7<=DATE(2028,3,1),OR(G7="",G7>=DATE(2028,3,1))),H7*(1+Assumptions!$C$7)^3,0) -> 8817.984 | AV7: =IF(AND(F7<=DATE(2028,4,1),OR(G7="",G7>=DATE(2028,4,1))),H7*(1+Assumptions!$C$7)^3,0) -> 8817.984 | AW7: =IF(AND(F7<=DATE(2028,5,1),OR(G7="",G7>=DATE(2028,5,1))),H7*(1+Assumptions!$C$7)^3,0) -> 8817.984 | AX7: =IF(AND(F7<=DATE(2028,6,1),OR(G7="",G7>=DATE(2028,6,1))),H7*(1+Assumptions!$C$7)^3,0) -> 8817.984 | AY7: =IF(AND(F7<=DATE(2028,7,1),OR(G7="",G7>=DATE(2028,7,1))),H7*(1+Assumptions!$C$7)^3,0) -> 8817.984 | AZ7: =IF(AND(F7<=DATE(2028,8,1),OR(G7="",G7>=DATE(2028,8,1))),H7*(1+Assumptions!$C$7)^3,0) -> 8817.984 | BA7: =IF(AND(F7<=DATE(2028,9,1),OR(G7="",G7>=DATE(2028,9,1))),H7*(1+Assumptions!$C$7)^3,0) -> 8817.984 | BB7: =IF(AND(F7<=DATE(2028,10,1),OR(G7="",G7>=DATE(2028,10,1))),H7*(1+Assumptions!$C$7)^3,0) -> 8817.984 | BC7: =IF(AND(F7<=DATE(2028,11,1),OR(G7="",G7>=DATE(2028,11,1))),H7*(1+Assumptions!$C$7)^3,0) -> 8817.984 | BD7: =IF(AND(F7<=DATE(2028,12,1),OR(G7="",G7>=DATE(2028,12,1))),H7*(1+Assumptions!$C$7)^3,0) -> 8817.984 | BE7: =IF(AND(F7<=DATE(2029,1,1),OR(G7="",G7>=DATE(2029,1,1))),H7*(1+Assumptions!$C$7)^4,0) -> 9523.4227 | BF7: =IF(AND(F7<=DATE(2029,2,1),OR(G7="",G7>=DATE(2029,2,1))),H7*(1+Assumptions!$C$7)^4,0) -> 9523.4227 | BG7: =IF(AND(F7<=DATE(2029,3,1),OR(G7="",G7>=DATE(2029,3,1))),H7*(1+Assumptions!$C$7)^4,0) -> 9523.4227 | BH7: =IF(AND(F7<=DATE(2029,4,1),OR(G7="",G7>=DATE(2029,4,1))),H7*(1+Assumptions!$C$7)^4,0) -> 9523.4227 | BI7: =IF(AND(F7<=DATE(2029,5,1),OR(G7="",G7>=DATE(2029,5,1))),H7*(1+Assumptions!$C$7)^4,0) -> 9523.4227 | BJ7: =IF(AND(F7<=DATE(2029,6,1),OR(G7="",G7>=DATE(2029,6,1))),H7*(1+Assumptions!$C$7)^4,0) -> 9523.4227 | BK7: =IF(AND(F7<=DATE(2029,7,1),OR(G7="",G7>=DATE(2029,7,1))),H7*(1+Assumptions!$C$7)^4,0) -> 9523.4227 | BL7: =IF(AND(F7<=DATE(2029,8,1),OR(G7="",G7>=DATE(2029,8,1))),H7*(1+Assumptions!$C$7)^4,0) -> 9523.4227 | BM7: =IF(AND(F7<=DATE(2029,9,1),OR(G7="",G7>=DATE(2029,9,1))),H7*(1+Assumptions!$C$7)^4,0) -> 9523.4227 | BN7: =IF(AND(F7<=DATE(2029,10,1),OR(G7="",G7>=DATE(2029,10,1))),H7*(1+Assumptions!$C$7)^4,0) -> 9523.4227 | BO7: =IF(AND(F7<=DATE(2029,11,1),OR(G7="",G7>=DATE(2029,11,1))),H7*(1+Assumptions!$C$7)^4,0) -> 9523.4227 | BP7: =IF(AND(F7<=DATE(2029,12,1),OR(G7="",G7>=DATE(2029,12,1))),H7*(1+Assumptions!$C$7)^4,0) -> 9523.4227
A8: 6 | B8: Mechanical Engineer | C8: R&D | D8: R&D Engineer | E8: Current | F8: 45901 | H8: 5500 | I8: =IF(AND(F8<=DATE(2025,1,1),OR(G8="",G8>=DATE(2025,1,1))),H8*(1+Assumptions!$C$7)^0,0) -> 0 | J8: =IF(AND(F8<=DATE(2025,2,1),OR(G8="",G8>=DATE(2025,2,1))),H8*(1+Assumptions!$C$7)^0,0) -> 0 | K8: =IF(AND(F8<=DATE(2025,3,1),OR(G8="",G8>=DATE(2025,3,1))),H8*(1+Assumptions!$C$7)^0,0) -> 0 | L8: =IF(AND(F8<=DATE(2025,4,1),OR(G8="",G8>=DATE(2025,4,1))),H8*(1+Assumptions!$C$7)^0,0) -> 0 | M8: =IF(AND(F8<=DATE(2025,5,1),OR(G8="",G8>=DATE(2025,5,1))),H8*(1+Assumptions!$C$7)^0,0) -> 0 | N8: =IF(AND(F8<=DATE(2025,6,1),OR(G8="",G8>=DATE(2025,6,1))),H8*(1+Assumptions!$C$7)^0,0) -> 0 | O8: =IF(AND(F8<=DATE(2025,7,1),OR(G8="",G8>=DATE(2025,7,1))),H8*(1+Assumptions!$C$7)^0,0) -> 0 | P8: =IF(AND(F8<=DATE(2025,8,1),OR(G8="",G8>=DATE(2025,8,1))),H8*(1+Assumptions!$C$7)^0,0) -> 0 | Q8: =IF(AND(F8<=DATE(2025,9,1),OR(G8="",G8>=DATE(2025,9,1))),H8*(1+Assumptions!$C$7)^0,0) -> 5500 | R8: =IF(AND(F8<=DATE(2025,10,1),OR(G8="",G8>=DATE(2025,10,1))),H8*(1+Assumptions!$C$7)^0,0) -> 5500 | S8: =IF(AND(F8<=DATE(2025,11,1),OR(G8="",G8>=DATE(2025,11,1))),H8*(1+Assumptions!$C$7)^0,0) -> 5500 | T8: =IF(AND(F8<=DATE(2025,12,1),OR(G8="",G8>=DATE(2025,12,1))),H8*(1+Assumptions!$C$7)^0,0) -> 5500 | U8: =IF(AND(F8<=DATE(2026,1,1),OR(G8="",G8>=DATE(2026,1,1))),H8*(1+Assumptions!$C$7)^1,0) -> 5940 | V8: =IF(AND(F8<=DATE(2026,2,1),OR(G8="",G8>=DATE(2026,2,1))),H8*(1+Assumptions!$C$7)^1,0) -> 5940 | W8: =IF(AND(F8<=DATE(2026,3,1),OR(G8="",G8>=DATE(2026,3,1))),H8*(1+Assumptions!$C$7)^1,0) -> 5940 | X8: =IF(AND(F8<=DATE(2026,4,1),OR(G8="",G8>=DATE(2026,4,1))),H8*(1+Assumptions!$C$7)^1,0) -> 5940 | Y8: =IF(AND(F8<=DATE(2026,5,1),OR(G8="",G8>=DATE(2026,5,1))),H8*(1+Assumptions!$C$7)^1,0) -> 5940 | Z8: =IF(AND(F8<=DATE(2026,6,1),OR(G8="",G8>=DATE(2026,6,1))),H8*(1+Assumptions!$C$7)^1,0) -> 5940 | AA8: =IF(AND(F8<=DATE(2026,7,1),OR(G8="",G8>=DATE(2026,7,1))),H8*(1+Assumptions!$C$7)^1,0) -> 5940 | AB8: =IF(AND(F8<=DATE(2026,8,1),OR(G8="",G8>=DATE(2026,8,1))),H8*(1+Assumptions!$C$7)^1,0) -> 5940 | AC8: =IF(AND(F8<=DATE(2026,9,1),OR(G8="",G8>=DATE(2026,9,1))),H8*(1+Assumptions!$C$7)^1,0) -> 5940 | AD8: =IF(AND(F8<=DATE(2026,10,1),OR(G8="",G8>=DATE(2026,10,1))),H8*(1+Assumptions!$C$7)^1,0) -> 5940 | AE8: =IF(AND(F8<=DATE(2026,11,1),OR(G8="",G8>=DATE(2026,11,1))),H8*(1+Assumptions!$C$7)^1,0) -> 5940 | AF8: =IF(AND(F8<=DATE(2026,12,1),OR(G8="",G8>=DATE(2026,12,1))),H8*(1+Assumptions!$C$7)^1,0) -> 5940 | AG8: =IF(AND(F8<=DATE(2027,1,1),OR(G8="",G8>=DATE(2027,1,1))),H8*(1+Assumptions!$C$7)^2,0) -> 6415.2 | AH8: =IF(AND(F8<=DATE(2027,2,1),OR(G8="",G8>=DATE(2027,2,1))),H8*(1+Assumptions!$C$7)^2,0) -> 6415.2 | AI8: =IF(AND(F8<=DATE(2027,3,1),OR(G8="",G8>=DATE(2027,3,1))),H8*(1+Assumptions!$C$7)^2,0) -> 6415.2 | AJ8: =IF(AND(F8<=DATE(2027,4,1),OR(G8="",G8>=DATE(2027,4,1))),H8*(1+Assumptions!$C$7)^2,0) -> 6415.2 | AK8: =IF(AND(F8<=DATE(2027,5,1),OR(G8="",G8>=DATE(2027,5,1))),H8*(1+Assumptions!$C$7)^2,0) -> 6415.2 | AL8: =IF(AND(F8<=DATE(2027,6,1),OR(G8="",G8>=DATE(2027,6,1))),H8*(1+Assumptions!$C$7)^2,0) -> 6415.2 | AM8: =IF(AND(F8<=DATE(2027,7,1),OR(G8="",G8>=DATE(2027,7,1))),H8*(1+Assumptions!$C$7)^2,0) -> 6415.2 | AN8: =IF(AND(F8<=DATE(2027,8,1),OR(G8="",G8>=DATE(2027,8,1))),H8*(1+Assumptions!$C$7)^2,0) -> 6415.2 | AO8: =IF(AND(F8<=DATE(2027,9,1),OR(G8="",G8>=DATE(2027,9,1))),H8*(1+Assumptions!$C$7)^2,0) -> 6415.2 | AP8: =IF(AND(F8<=DATE(2027,10,1),OR(G8="",G8>=DATE(2027,10,1))),H8*(1+Assumptions!$C$7)^2,0) -> 6415.2 | AQ8: =IF(AND(F8<=DATE(2027,11,1),OR(G8="",G8>=DATE(2027,11,1))),H8*(1+Assumptions!$C$7)^2,0) -> 6415.2 | AR8: =IF(AND(F8<=DATE(2027,12,1),OR(G8="",G8>=DATE(2027,12,1))),H8*(1+Assumptions!$C$7)^2,0) -> 6415.2 | AS8: =IF(AND(F8<=DATE(2028,1,1),OR(G8="",G8>=DATE(2028,1,1))),H8*(1+Assumptions!$C$7)^3,0) -> 6928.416 | AT8: =IF(AND(F8<=DATE(2028,2,1),OR(G8="",G8>=DATE(2028,2,1))),H8*(1+Assumptions!$C$7)^3,0) -> 6928.416 | AU8: =IF(AND(F8<=DATE(2028,3,1),OR(G8="",G8>=DATE(2028,3,1))),H8*(1+Assumptions!$C$7)^3,0) -> 6928.416 | AV8: =IF(AND(F8<=DATE(2028,4,1),OR(G8="",G8>=DATE(2028,4,1))),H8*(1+Assumptions!$C$7)^3,0) -> 6928.416 | AW8: =IF(AND(F8<=DATE(2028,5,1),OR(G8="",G8>=DATE(2028,5,1))),H8*(1+Assumptions!$C$7)^3,0) -> 6928.416 | AX8: =IF(AND(F8<=DATE(2028,6,1),OR(G8="",G8>=DATE(2028,6,1))),H8*(1+Assumptions!$C$7)^3,0) -> 6928.416 | AY8: =IF(AND(F8<=DATE(2028,7,1),OR(G8="",G8>=DATE(2028,7,1))),H8*(1+Assumptions!$C$7)^3,0) -> 6928.416 | AZ8: =IF(AND(F8<=DATE(2028,8,1),OR(G8="",G8>=DATE(2028,8,1))),H8*(1+Assumptions!$C$7)^3,0) -> 6928.416 | BA8: =IF(AND(F8<=DATE(2028,9,1),OR(G8="",G8>=DATE(2028,9,1))),H8*(1+Assumptions!$C$7)^3,0) -> 6928.416 | BB8: =IF(AND(F8<=DATE(2028,10,1),OR(G8="",G8>=DATE(2028,10,1))),H8*(1+Assumptions!$C$7)^3,0) -> 6928.416 | BC8: =IF(AND(F8<=DATE(2028,11,1),OR(G8="",G8>=DATE(2028,11,1))),H8*(1+Assumptions!$C$7)^3,0) -> 6928.416 | BD8: =IF(AND(F8<=DATE(2028,12,1),OR(G8="",G8>=DATE(2028,12,1))),H8*(1+Assumptions!$C$7)^3,0) -> 6928.416 | BE8: =IF(AND(F8<=DATE(2029,1,1),OR(G8="",G8>=DATE(2029,1,1))),H8*(1+Assumptions!$C$7)^4,0) -> 7482.6893 | BF8: =IF(AND(F8<=DATE(2029,2,1),OR(G8="",G8>=DATE(2029,2,1))),H8*(1+Assumptions!$C$7)^4,0) -> 7482.6893 | BG8: =IF(AND(F8<=DATE(2029,3,1),OR(G8="",G8>=DATE(2029,3,1))),H8*(1+Assumptions!$C$7)^4,0) -> 7482.6893 | BH8: =IF(AND(F8<=DATE(2029,4,1),OR(G8="",G8>=DATE(2029,4,1))),H8*(1+Assumptions!$C$7)^4,0) -> 7482.6893 | BI8: =IF(AND(F8<=DATE(2029,5,1),OR(G8="",G8>=DATE(2029,5,1))),H8*(1+Assumptions!$C$7)^4,0) -> 7482.6893 | BJ8: =IF(AND(F8<=DATE(2029,6,1),OR(G8="",G8>=DATE(2029,6,1))),H8*(1+Assumptions!$C$7)^4,0) -> 7482.6893 | BK8: =IF(AND(F8<=DATE(2029,7,1),OR(G8="",G8>=DATE(2029,7,1))),H8*(1+Assumptions!$C$7)^4,0) -> 7482.6893 | BL8: =IF(AND(F8<=DATE(2029,8,1),OR(G8="",G8>=DATE(2029,8,1))),H8*(1+Assumptions!$C$7)^4,0) -> 7482.6893 | BM8: =IF(AND(F8<=DATE(2029,9,1),OR(G8="",G8>=DATE(2029,9,1))),H8*(1+Assumptions!$C$7)^4,0) -> 7482.6893 | BN8: =IF(AND(F8<=DATE(2029,10,1),OR(G8="",G8>=DATE(2029,10,1))),H8*(1+Assumptions!$C$7)^4,0) -> 7482.6893 | BO8: =IF(AND(F8<=DATE(2029,11,1),OR(G8="",G8>=DATE(2029,11,1))),H8*(1+Assumptions!$C$7)^4,0) -> 7482.6893 | BP8: =IF(AND(F8<=DATE(2029,12,1),OR(G8="",G8>=DATE(2029,12,1))),H8*(1+Assumptions!$C$7)^4,0) -> 7482.6893
A9: 7 | B9: Electrical Engineer | C9: R&D | D9: R&D Engineer | E9: Current | F9: 45901 | H9: 5500 | I9: =IF(AND(F9<=DATE(2025,1,1),OR(G9="",G9>=DATE(2025,1,1))),H9*(1+Assumptions!$C$7)^0,0) -> 0 | J9: =IF(AND(F9<=DATE(2025,2,1),OR(G9="",G9>=DATE(2025,2,1))),H9*(1+Assumptions!$C$7)^0,0) -> 0 | K9: =IF(AND(F9<=DATE(2025,3,1),OR(G9="",G9>=DATE(2025,3,1))),H9*(1+Assumptions!$C$7)^0,0) -> 0 | L9: =IF(AND(F9<=DATE(2025,4,1),OR(G9="",G9>=DATE(2025,4,1))),H9*(1+Assumptions!$C$7)^0,0) -> 0 | M9: =IF(AND(F9<=DATE(2025,5,1),OR(G9="",G9>=DATE(2025,5,1))),H9*(1+Assumptions!$C$7)^0,0) -> 0 | N9: =IF(AND(F9<=DATE(2025,6,1),OR(G9="",G9>=DATE(2025,6,1))),H9*(1+Assumptions!$C$7)^0,0) -> 0 | O9: =IF(AND(F9<=DATE(2025,7,1),OR(G9="",G9>=DATE(2025,7,1))),H9*(1+Assumptions!$C$7)^0,0) -> 0 | P9: =IF(AND(F9<=DATE(2025,8,1),OR(G9="",G9>=DATE(2025,8,1))),H9*(1+Assumptions!$C$7)^0,0) -> 0 | Q9: =IF(AND(F9<=DATE(2025,9,1),OR(G9="",G9>=DATE(2025,9,1))),H9*(1+Assumptions!$C$7)^0,0) -> 5500 | R9: =IF(AND(F9<=DATE(2025,10,1),OR(G9="",G9>=DATE(2025,10,1))),H9*(1+Assumptions!$C$7)^0,0) -> 5500 | S9: =IF(AND(F9<=DATE(2025,11,1),OR(G9="",G9>=DATE(2025,11,1))),H9*(1+Assumptions!$C$7)^0,0) -> 5500 | T9: =IF(AND(F9<=DATE(2025,12,1),OR(G9="",G9>=DATE(2025,12,1))),H9*(1+Assumptions!$C$7)^0,0) -> 5500 | U9: =IF(AND(F9<=DATE(2026,1,1),OR(G9="",G9>=DATE(2026,1,1))),H9*(1+Assumptions!$C$7)^1,0) -> 5940 | V9: =IF(AND(F9<=DATE(2026,2,1),OR(G9="",G9>=DATE(2026,2,1))),H9*(1+Assumptions!$C$7)^1,0) -> 5940 | W9: =IF(AND(F9<=DATE(2026,3,1),OR(G9="",G9>=DATE(2026,3,1))),H9*(1+Assumptions!$C$7)^1,0) -> 5940 | X9: =IF(AND(F9<=DATE(2026,4,1),OR(G9="",G9>=DATE(2026,4,1))),H9*(1+Assumptions!$C$7)^1,0) -> 5940 | Y9: =IF(AND(F9<=DATE(2026,5,1),OR(G9="",G9>=DATE(2026,5,1))),H9*(1+Assumptions!$C$7)^1,0) -> 5940 | Z9: =IF(AND(F9<=DATE(2026,6,1),OR(G9="",G9>=DATE(2026,6,1))),H9*(1+Assumptions!$C$7)^1,0) -> 5940 | AA9: =IF(AND(F9<=DATE(2026,7,1),OR(G9="",G9>=DATE(2026,7,1))),H9*(1+Assumptions!$C$7)^1,0) -> 5940 | AB9: =IF(AND(F9<=DATE(2026,8,1),OR(G9="",G9>=DATE(2026,8,1))),H9*(1+Assumptions!$C$7)^1,0) -> 5940 | AC9: =IF(AND(F9<=DATE(2026,9,1),OR(G9="",G9>=DATE(2026,9,1))),H9*(1+Assumptions!$C$7)^1,0) -> 5940 | AD9: =IF(AND(F9<=DATE(2026,10,1),OR(G9="",G9>=DATE(2026,10,1))),H9*(1+Assumptions!$C$7)^1,0) -> 5940 | AE9: =IF(AND(F9<=DATE(2026,11,1),OR(G9="",G9>=DATE(2026,11,1))),H9*(1+Assumptions!$C$7)^1,0) -> 5940 | AF9: =IF(AND(F9<=DATE(2026,12,1),OR(G9="",G9>=DATE(2026,12,1))),H9*(1+Assumptions!$C$7)^1,0) -> 5940 | AG9: =IF(AND(F9<=DATE(2027,1,1),OR(G9="",G9>=DATE(2027,1,1))),H9*(1+Assumptions!$C$7)^2,0) -> 6415.2 | AH9: =IF(AND(F9<=DATE(2027,2,1),OR(G9="",G9>=DATE(2027,2,1))),H9*(1+Assumptions!$C$7)^2,0) -> 6415.2 | AI9: =IF(AND(F9<=DATE(2027,3,1),OR(G9="",G9>=DATE(2027,3,1))),H9*(1+Assumptions!$C$7)^2,0) -> 6415.2 | AJ9: =IF(AND(F9<=DATE(2027,4,1),OR(G9="",G9>=DATE(2027,4,1))),H9*(1+Assumptions!$C$7)^2,0) -> 6415.2 | AK9: =IF(AND(F9<=DATE(2027,5,1),OR(G9="",G9>=DATE(2027,5,1))),H9*(1+Assumptions!$C$7)^2,0) -> 6415.2 | AL9: =IF(AND(F9<=DATE(2027,6,1),OR(G9="",G9>=DATE(2027,6,1))),H9*(1+Assumptions!$C$7)^2,0) -> 6415.2 | AM9: =IF(AND(F9<=DATE(2027,7,1),OR(G9="",G9>=DATE(2027,7,1))),H9*(1+Assumptions!$C$7)^2,0) -> 6415.2 | AN9: =IF(AND(F9<=DATE(2027,8,1),OR(G9="",G9>=DATE(2027,8,1))),H9*(1+Assumptions!$C$7)^2,0) -> 6415.2 | AO9: =IF(AND(F9<=DATE(2027,9,1),OR(G9="",G9>=DATE(2027,9,1))),H9*(1+Assumptions!$C$7)^2,0) -> 6415.2 | AP9: =IF(AND(F9<=DATE(2027,10,1),OR(G9="",G9>=DATE(2027,10,1))),H9*(1+Assumptions!$C$7)^2,0) -> 6415.2 | AQ9: =IF(AND(F9<=DATE(2027,11,1),OR(G9="",G9>=DATE(2027,11,1))),H9*(1+Assumptions!$C$7)^2,0) -> 6415.2 | AR9: =IF(AND(F9<=DATE(2027,12,1),OR(G9="",G9>=DATE(2027,12,1))),H9*(1+Assumptions!$C$7)^2,0) -> 6415.2 | AS9: =IF(AND(F9<=DATE(2028,1,1),OR(G9="",G9>=DATE(2028,1,1))),H9*(1+Assumptions!$C$7)^3,0) -> 6928.416 | AT9: =IF(AND(F9<=DATE(2028,2,1),OR(G9="",G9>=DATE(2028,2,1))),H9*(1+Assumptions!$C$7)^3,0) -> 6928.416 | AU9: =IF(AND(F9<=DATE(2028,3,1),OR(G9="",G9>=DATE(2028,3,1))),H9*(1+Assumptions!$C$7)^3,0) -> 6928.416 | AV9: =IF(AND(F9<=DATE(2028,4,1),OR(G9="",G9>=DATE(2028,4,1))),H9*(1+Assumptions!$C$7)^3,0) -> 6928.416 | AW9: =IF(AND(F9<=DATE(2028,5,1),OR(G9="",G9>=DATE(2028,5,1))),H9*(1+Assumptions!$C$7)^3,0) -> 6928.416 | AX9: =IF(AND(F9<=DATE(2028,6,1),OR(G9="",G9>=DATE(2028,6,1))),H9*(1+Assumptions!$C$7)^3,0) -> 6928.416 | AY9: =IF(AND(F9<=DATE(2028,7,1),OR(G9="",G9>=DATE(2028,7,1))),H9*(1+Assumptions!$C$7)^3,0) -> 6928.416 | AZ9: =IF(AND(F9<=DATE(2028,8,1),OR(G9="",G9>=DATE(2028,8,1))),H9*(1+Assumptions!$C$7)^3,0) -> 6928.416 | BA9: =IF(AND(F9<=DATE(2028,9,1),OR(G9="",G9>=DATE(2028,9,1))),H9*(1+Assumptions!$C$7)^3,0) -> 6928.416 | BB9: =IF(AND(F9<=DATE(2028,10,1),OR(G9="",G9>=DATE(2028,10,1))),H9*(1+Assumptions!$C$7)^3,0) -> 6928.416 | BC9: =IF(AND(F9<=DATE(2028,11,1),OR(G9="",G9>=DATE(2028,11,1))),H9*(1+Assumptions!$C$7)^3,0) -> 6928.416 | BD9: =IF(AND(F9<=DATE(2028,12,1),OR(G9="",G9>=DATE(2028,12,1))),H9*(1+Assumptions!$C$7)^3,0) -> 6928.416 | BE9: =IF(AND(F9<=DATE(2029,1,1),OR(G9="",G9>=DATE(2029,1,1))),H9*(1+Assumptions!$C$7)^4,0) -> 7482.6893 | BF9: =IF(AND(F9<=DATE(2029,2,1),OR(G9="",G9>=DATE(2029,2,1))),H9*(1+Assumptions!$C$7)^4,0) -> 7482.6893 | BG9: =IF(AND(F9<=DATE(2029,3,1),OR(G9="",G9>=DATE(2029,3,1))),H9*(1+Assumptions!$C$7)^4,0) -> 7482.6893 | BH9: =IF(AND(F9<=DATE(2029,4,1),OR(G9="",G9>=DATE(2029,4,1))),H9*(1+Assumptions!$C$7)^4,0) -> 7482.6893 | BI9: =IF(AND(F9<=DATE(2029,5,1),OR(G9="",G9>=DATE(2029,5,1))),H9*(1+Assumptions!$C$7)^4,0) -> 7482.6893 | BJ9: =IF(AND(F9<=DATE(2029,6,1),OR(G9="",G9>=DATE(2029,6,1))),H9*(1+Assumptions!$C$7)^4,0) -> 7482.6893 | BK9: =IF(AND(F9<=DATE(2029,7,1),OR(G9="",G9>=DATE(2029,7,1))),H9*(1+Assumptions!$C$7)^4,0) -> 7482.6893 | BL9: =IF(AND(F9<=DATE(2029,8,1),OR(G9="",G9>=DATE(2029,8,1))),H9*(1+Assumptions!$C$7)^4,0) -> 7482.6893 | BM9: =IF(AND(F9<=DATE(2029,9,1),OR(G9="",G9>=DATE(2029,9,1))),H9*(1+Assumptions!$C$7)^4,0) -> 7482.6893 | BN9: =IF(AND(F9<=DATE(2029,10,1),OR(G9="",G9>=DATE(2029,10,1))),H9*(1+Assumptions!$C$7)^4,0) -> 7482.6893 | BO9: =IF(AND(F9<=DATE(2029,11,1),OR(G9="",G9>=DATE(2029,11,1))),H9*(1+Assumptions!$C$7)^4,0) -> 7482.6893 | BP9: =IF(AND(F9<=DATE(2029,12,1),OR(G9="",G9>=DATE(2029,12,1))),H9*(1+Assumptions!$C$7)^4,0) -> 7482.6893
A10: 11 | B10: CFO (part time) | C10: G&A | D10: CFO | E10: Current | F10: 45901 | G10: 46266 | H10: 4000 | I10: =IF(AND(F10<=DATE(2025,1,1),OR(G10="",G10>=DATE(2025,1,1))),H10*(1+Assumptions!$C$7)^0,0) -> 0 | J10: =IF(AND(F10<=DATE(2025,2,1),OR(G10="",G10>=DATE(2025,2,1))),H10*(1+Assumptions!$C$7)^0,0) -> 0 | K10: =IF(AND(F10<=DATE(2025,3,1),OR(G10="",G10>=DATE(2025,3,1))),H10*(1+Assumptions!$C$7)^0,0) -> 0 | L10: =IF(AND(F10<=DATE(2025,4,1),OR(G10="",G10>=DATE(2025,4,1))),H10*(1+Assumptions!$C$7)^0,0) -> 0 | M10: =IF(AND(F10<=DATE(2025,5,1),OR(G10="",G10>=DATE(2025,5,1))),H10*(1+Assumptions!$C$7)^0,0) -> 0 | N10: =IF(AND(F10<=DATE(2025,6,1),OR(G10="",G10>=DATE(2025,6,1))),H10*(1+Assumptions!$C$7)^0,0) -> 0 | O10: =IF(AND(F10<=DATE(2025,7,1),OR(G10="",G10>=DATE(2025,7,1))),H10*(1+Assumptions!$C$7)^0,0) -> 0 | P10: =IF(AND(F10<=DATE(2025,8,1),OR(G10="",G10>=DATE(2025,8,1))),H10*(1+Assumptions!$C$7)^0,0) -> 0 | Q10: =IF(AND(F10<=DATE(2025,9,1),OR(G10="",G10>=DATE(2025,9,1))),H10*(1+Assumptions!$C$7)^0,0) -> 4000 | R10: =IF(AND(F10<=DATE(2025,10,1),OR(G10="",G10>=DATE(2025,10,1))),H10*(1+Assumptions!$C$7)^0,0) -> 4000 | S10: =IF(AND(F10<=DATE(2025,11,1),OR(G10="",G10>=DATE(2025,11,1))),H10*(1+Assumptions!$C$7)^0,0) -> 4000 | T10: =IF(AND(F10<=DATE(2025,12,1),OR(G10="",G10>=DATE(2025,12,1))),H10*(1+Assumptions!$C$7)^0,0) -> 4000 | U10: =IF(AND(F10<=DATE(2026,1,1),OR(G10="",G10>=DATE(2026,1,1))),H10*(1+Assumptions!$C$7)^1,0) -> 4320 | V10: =IF(AND(F10<=DATE(2026,2,1),OR(G10="",G10>=DATE(2026,2,1))),H10*(1+Assumptions!$C$7)^1,0) -> 4320 | W10: =IF(AND(F10<=DATE(2026,3,1),OR(G10="",G10>=DATE(2026,3,1))),H10*(1+Assumptions!$C$7)^1,0) -> 4320 | X10: =IF(AND(F10<=DATE(2026,4,1),OR(G10="",G10>=DATE(2026,4,1))),H10*(1+Assumptions!$C$7)^1,0) -> 4320 | Y10: =IF(AND(F10<=DATE(2026,5,1),OR(G10="",G10>=DATE(2026,5,1))),H10*(1+Assumptions!$C$7)^1,0) -> 4320 | Z10: =IF(AND(F10<=DATE(2026,6,1),OR(G10="",G10>=DATE(2026,6,1))),H10*(1+Assumptions!$C$7)^1,0) -> 4320 | AA10: =IF(AND(F10<=DATE(2026,7,1),OR(G10="",G10>=DATE(2026,7,1))),H10*(1+Assumptions!$C$7)^1,0) -> 4320 | AB10: =IF(AND(F10<=DATE(2026,8,1),OR(G10="",G10>=DATE(2026,8,1))),H10*(1+Assumptions!$C$7)^1,0) -> 4320 | AC10: =IF(AND(F10<=DATE(2026,9,1),OR(G10="",G10>=DATE(2026,9,1))),H10*(1+Assumptions!$C$7)^1,0) -> 4320 | AD10: =IF(AND(F10<=DATE(2026,10,1),OR(G10="",G10>=DATE(2026,10,1))),H10*(1+Assumptions!$C$7)^1,0) -> 0 | AE10: =IF(AND(F10<=DATE(2026,11,1),OR(G10="",G10>=DATE(2026,11,1))),H10*(1+Assumptions!$C$7)^1,0) -> 0 | AF10: =IF(AND(F10<=DATE(2026,12,1),OR(G10="",G10>=DATE(2026,12,1))),H10*(1+Assumptions!$C$7)^1,0) -> 0 | AG10: =IF(AND(F10<=DATE(2027,1,1),OR(G10="",G10>=DATE(2027,1,1))),H10*(1+Assumptions!$C$7)^2,0) -> 0 | AH10: =IF(AND(F10<=DATE(2027,2,1),OR(G10="",G10>=DATE(2027,2,1))),H10*(1+Assumptions!$C$7)^2,0) -> 0 | AI10: =IF(AND(F10<=DATE(2027,3,1),OR(G10="",G10>=DATE(2027,3,1))),H10*(1+Assumptions!$C$7)^2,0) -> 0 | AJ10: =IF(AND(F10<=DATE(2027,4,1),OR(G10="",G10>=DATE(2027,4,1))),H10*(1+Assumptions!$C$7)^2,0) -> 0 | AK10: =IF(AND(F10<=DATE(2027,5,1),OR(G10="",G10>=DATE(2027,5,1))),H10*(1+Assumptions!$C$7)^2,0) -> 0 | AL10: =IF(AND(F10<=DATE(2027,6,1),OR(G10="",G10>=DATE(2027,6,1))),H10*(1+Assumptions!$C$7)^2,0) -> 0 | AM10: =IF(AND(F10<=DATE(2027,7,1),OR(G10="",G10>=DATE(2027,7,1))),H10*(1+Assumptions!$C$7)^2,0) -> 0 | AN10: =IF(AND(F10<=DATE(2027,8,1),OR(G10="",G10>=DATE(2027,8,1))),H10*(1+Assumptions!$C$7)^2,0) -> 0 | AO10: =IF(AND(F10<=DATE(2027,9,1),OR(G10="",G10>=DATE(2027,9,1))),H10*(1+Assumptions!$C$7)^2,0) -> 0 | AP10: =IF(AND(F10<=DATE(2027,10,1),OR(G10="",G10>=DATE(2027,10,1))),H10*(1+Assumptions!$C$7)^2,0) -> 0 | AQ10: =IF(AND(F10<=DATE(2027,11,1),OR(G10="",G10>=DATE(2027,11,1))),H10*(1+Assumptions!$C$7)^2,0) -> 0 | AR10: =IF(AND(F10<=DATE(2027,12,1),OR(G10="",G10>=DATE(2027,12,1))),H10*(1+Assumptions!$C$7)^2,0) -> 0 | AS10: =IF(AND(F10<=DATE(2028,1,1),OR(G10="",G10>=DATE(2028,1,1))),H10*(1+Assumptions!$C$7)^3,0) -> 0 | AT10: =IF(AND(F10<=DATE(2028,2,1),OR(G10="",G10>=DATE(2028,2,1))),H10*(1+Assumptions!$C$7)^3,0) -> 0 | AU10: =IF(AND(F10<=DATE(2028,3,1),OR(G10="",G10>=DATE(2028,3,1))),H10*(1+Assumptions!$C$7)^3,0) -> 0 | AV10: =IF(AND(F10<=DATE(2028,4,1),OR(G10="",G10>=DATE(2028,4,1))),H10*(1+Assumptions!$C$7)^3,0) -> 0 | AW10: =IF(AND(F10<=DATE(2028,5,1),OR(G10="",G10>=DATE(2028,5,1))),H10*(1+Assumptions!$C$7)^3,0) -> 0 | AX10: =IF(AND(F10<=DATE(2028,6,1),OR(G10="",G10>=DATE(2028,6,1))),H10*(1+Assumptions!$C$7)^3,0) -> 0 | AY10: =IF(AND(F10<=DATE(2028,7,1),OR(G10="",G10>=DATE(2028,7,1))),H10*(1+Assumptions!$C$7)^3,0) -> 0 | AZ10: =IF(AND(F10<=DATE(2028,8,1),OR(G10="",G10>=DATE(2028,8,1))),H10*(1+Assumptions!$C$7)^3,0) -> 0 | BA10: =IF(AND(F10<=DATE(2028,9,1),OR(G10="",G10>=DATE(2028,9,1))),H10*(1+Assumptions!$C$7)^3,0) -> 0 | BB10: =IF(AND(F10<=DATE(2028,10,1),OR(G10="",G10>=DATE(2028,10,1))),H10*(1+Assumptions!$C$7)^3,0) -> 0 | BC10: =IF(AND(F10<=DATE(2028,11,1),OR(G10="",G10>=DATE(2028,11,1))),H10*(1+Assumptions!$C$7)^3,0) -> 0 | BD10: =IF(AND(F10<=DATE(2028,12,1),OR(G10="",G10>=DATE(2028,12,1))),H10*(1+Assumptions!$C$7)^3,0) -> 0 | BE10: =IF(AND(F10<=DATE(2029,1,1),OR(G10="",G10>=DATE(2029,1,1))),H10*(1+Assumptions!$C$7)^4,0) -> 0 | BF10: =IF(AND(F10<=DATE(2029,2,1),OR(G10="",G10>=DATE(2029,2,1))),H10*(1+Assumptions!$C$7)^4,0) -> 0 | BG10: =IF(AND(F10<=DATE(2029,3,1),OR(G10="",G10>=DATE(2029,3,1))),H10*(1+Assumptions!$C$7)^4,0) -> 0 | BH10: =IF(AND(F10<=DATE(2029,4,1),OR(G10="",G10>=DATE(2029,4,1))),H10*(1+Assumptions!$C$7)^4,0) -> 0 | BI10: =IF(AND(F10<=DATE(2029,5,1),OR(G10="",G10>=DATE(2029,5,1))),H10*(1+Assumptions!$C$7)^4,0) -> 0 | BJ10: =IF(AND(F10<=DATE(2029,6,1),OR(G10="",G10>=DATE(2029,6,1))),H10*(1+Assumptions!$C$7)^4,0) -> 0 | BK10: =IF(AND(F10<=DATE(2029,7,1),OR(G10="",G10>=DATE(2029,7,1))),H10*(1+Assumptions!$C$7)^4,0) -> 0 | BL10: =IF(AND(F10<=DATE(2029,8,1),OR(G10="",G10>=DATE(2029,8,1))),H10*(1+Assumptions!$C$7)^4,0) -> 0 | BM10: =IF(AND(F10<=DATE(2029,9,1),OR(G10="",G10>=DATE(2029,9,1))),H10*(1+Assumptions!$C$7)^4,0) -> 0 | BN10: =IF(AND(F10<=DATE(2029,10,1),OR(G10="",G10>=DATE(2029,10,1))),H10*(1+Assumptions!$C$7)^4,0) -> 0 | BO10: =IF(AND(F10<=DATE(2029,11,1),OR(G10="",G10>=DATE(2029,11,1))),H10*(1+Assumptions!$C$7)^4,0) -> 0 | BP10: =IF(AND(F10<=DATE(2029,12,1),OR(G10="",G10>=DATE(2029,12,1))),H10*(1+Assumptions!$C$7)^4,0) -> 0
A11: 8 | B11: CTO | C11: R&D | D11: CTO | E11: Current | F11: 46266 | H11: 11500 | I11: =IF(AND(F11<=DATE(2025,1,1),OR(G11="",G11>=DATE(2025,1,1))),H11*(1+Assumptions!$C$7)^0,0) -> 0 | J11: =IF(AND(F11<=DATE(2025,2,1),OR(G11="",G11>=DATE(2025,2,1))),H11*(1+Assumptions!$C$7)^0,0) -> 0 | K11: =IF(AND(F11<=DATE(2025,3,1),OR(G11="",G11>=DATE(2025,3,1))),H11*(1+Assumptions!$C$7)^0,0) -> 0 | L11: =IF(AND(F11<=DATE(2025,4,1),OR(G11="",G11>=DATE(2025,4,1))),H11*(1+Assumptions!$C$7)^0,0) -> 0 | M11: =IF(AND(F11<=DATE(2025,5,1),OR(G11="",G11>=DATE(2025,5,1))),H11*(1+Assumptions!$C$7)^0,0) -> 0 | N11: =IF(AND(F11<=DATE(2025,6,1),OR(G11="",G11>=DATE(2025,6,1))),H11*(1+Assumptions!$C$7)^0,0) -> 0 | O11: =IF(AND(F11<=DATE(2025,7,1),OR(G11="",G11>=DATE(2025,7,1))),H11*(1+Assumptions!$C$7)^0,0) -> 0 | P11: =IF(AND(F11<=DATE(2025,8,1),OR(G11="",G11>=DATE(2025,8,1))),H11*(1+Assumptions!$C$7)^0,0) -> 0 | Q11: 7500 | R11: 7500 | S11: 7500 | T11: 7500 | U11: 7500 | V11: 7500 | W11: 7500 | X11: 7500 | Y11: 7500 | Z11: 7500 | AA11: 7500 | AB11: 7500 | AC11: =IF(AND(F11<=DATE(2026,9,1),OR(G11="",G11>=DATE(2026,9,1))),H11) -> 11500 | AD11: =IF(AND(F11<=DATE(2026,10,1),OR(G11="",G11>=DATE(2026,10,1))),H11*(1+Assumptions!$C$7)^1,0) -> 12420 | AE11: =IF(AND(F11<=DATE(2026,11,1),OR(G11="",G11>=DATE(2026,11,1))),H11*(1+Assumptions!$C$7)^1,0) -> 12420 | AF11: =IF(AND(F11<=DATE(2026,12,1),OR(G11="",G11>=DATE(2026,12,1))),H11*(1+Assumptions!$C$7)^1,0) -> 12420 | AG11: =IF(AND(F11<=DATE(2027,1,1),OR(G11="",G11>=DATE(2027,1,1))),H11*(1+Assumptions!$C$7)^2,0) -> 13413.6 | AH11: =IF(AND(F11<=DATE(2027,2,1),OR(G11="",G11>=DATE(2027,2,1))),H11*(1+Assumptions!$C$7)^2,0) -> 13413.6 | AI11: =IF(AND(F11<=DATE(2027,3,1),OR(G11="",G11>=DATE(2027,3,1))),H11*(1+Assumptions!$C$7)^2,0) -> 13413.6 | AJ11: =IF(AND(F11<=DATE(2027,4,1),OR(G11="",G11>=DATE(2027,4,1))),H11*(1+Assumptions!$C$7)^2,0) -> 13413.6 | AK11: =IF(AND(F11<=DATE(2027,5,1),OR(G11="",G11>=DATE(2027,5,1))),H11*(1+Assumptions!$C$7)^2,0) -> 13413.6 | AL11: =IF(AND(F11<=DATE(2027,6,1),OR(G11="",G11>=DATE(2027,6,1))),H11*(1+Assumptions!$C$7)^2,0) -> 13413.6 | AM11: =IF(AND(F11<=DATE(2027,7,1),OR(G11="",G11>=DATE(2027,7,1))),H11*(1+Assumptions!$C$7)^2,0) -> 13413.6 | AN11: =IF(AND(F11<=DATE(2027,8,1),OR(G11="",G11>=DATE(2027,8,1))),H11*(1+Assumptions!$C$7)^2,0) -> 13413.6 | AO11: =IF(AND(F11<=DATE(2027,9,1),OR(G11="",G11>=DATE(2027,9,1))),H11*(1+Assumptions!$C$7)^2,0) -> 13413.6 | AP11: =IF(AND(F11<=DATE(2027,10,1),OR(G11="",G11>=DATE(2027,10,1))),H11*(1+Assumptions!$C$7)^2,0) -> 13413.6 | AQ11: =IF(AND(F11<=DATE(2027,11,1),OR(G11="",G11>=DATE(2027,11,1))),H11*(1+Assumptions!$C$7)^2,0) -> 13413.6 | AR11: =IF(AND(F11<=DATE(2027,12,1),OR(G11="",G11>=DATE(2027,12,1))),H11*(1+Assumptions!$C$7)^2,0) -> 13413.6 | AS11: =IF(AND(F11<=DATE(2028,1,1),OR(G11="",G11>=DATE(2028,1,1))),H11*(1+Assumptions!$C$7)^3,0) -> 14486.688 | AT11: =IF(AND(F11<=DATE(2028,2,1),OR(G11="",G11>=DATE(2028,2,1))),H11*(1+Assumptions!$C$7)^3,0) -> 14486.688 | AU11: =IF(AND(F11<=DATE(2028,3,1),OR(G11="",G11>=DATE(2028,3,1))),H11*(1+Assumptions!$C$7)^3,0) -> 14486.688 | AV11: =IF(AND(F11<=DATE(2028,4,1),OR(G11="",G11>=DATE(2028,4,1))),H11*(1+Assumptions!$C$7)^3,0) -> 14486.688 | AW11: =IF(AND(F11<=DATE(2028,5,1),OR(G11="",G11>=DATE(2028,5,1))),H11*(1+Assumptions!$C$7)^3,0) -> 14486.688 | AX11: =IF(AND(F11<=DATE(2028,6,1),OR(G11="",G11>=DATE(2028,6,1))),H11*(1+Assumptions!$C$7)^3,0) -> 14486.688 | AY11: =IF(AND(F11<=DATE(2028,7,1),OR(G11="",G11>=DATE(2028,7,1))),H11*(1+Assumptions!$C$7)^3,0) -> 14486.688 | AZ11: =IF(AND(F11<=DATE(2028,8,1),OR(G11="",G11>=DATE(2028,8,1))),H11*(1+Assumptions!$C$7)^3,0) -> 14486.688 | BA11: =IF(AND(F11<=DATE(2028,9,1),OR(G11="",G11>=DATE(2028,9,1))),H11*(1+Assumptions!$C$7)^3,0) -> 14486.688 | BB11: =IF(AND(F11<=DATE(2028,10,1),OR(G11="",G11>=DATE(2028,10,1))),H11*(1+Assumptions!$C$7)^3,0) -> 14486.688 | BC11: =IF(AND(F11<=DATE(2028,11,1),OR(G11="",G11>=DATE(2028,11,1))),H11*(1+Assumptions!$C$7)^3,0) -> 14486.688 | BD11: =IF(AND(F11<=DATE(2028,12,1),OR(G11="",G11>=DATE(2028,12,1))),H11*(1+Assumptions!$C$7)^3,0) -> 14486.688 | BE11: =IF(AND(F11<=DATE(2029,1,1),OR(G11="",G11>=DATE(2029,1,1))),H11*(1+Assumptions!$C$7)^4,0) -> 15645.623 | BF11: =IF(AND(F11<=DATE(2029,2,1),OR(G11="",G11>=DATE(2029,2,1))),H11*(1+Assumptions!$C$7)^4,0) -> 15645.623 | BG11: =IF(AND(F11<=DATE(2029,3,1),OR(G11="",G11>=DATE(2029,3,1))),H11*(1+Assumptions!$C$7)^4,0) -> 15645.623 | BH11: =IF(AND(F11<=DATE(2029,4,1),OR(G11="",G11>=DATE(2029,4,1))),H11*(1+Assumptions!$C$7)^4,0) -> 15645.623 | BI11: =IF(AND(F11<=DATE(2029,5,1),OR(G11="",G11>=DATE(2029,5,1))),H11*(1+Assumptions!$C$7)^4,0) -> 15645.623 | BJ11: =IF(AND(F11<=DATE(2029,6,1),OR(G11="",G11>=DATE(2029,6,1))),H11*(1+Assumptions!$C$7)^4,0) -> 15645.623 | BK11: =IF(AND(F11<=DATE(2029,7,1),OR(G11="",G11>=DATE(2029,7,1))),H11*(1+Assumptions!$C$7)^4,0) -> 15645.623 | BL11: =IF(AND(F11<=DATE(2029,8,1),OR(G11="",G11>=DATE(2029,8,1))),H11*(1+Assumptions!$C$7)^4,0) -> 15645.623 | BM11: =IF(AND(F11<=DATE(2029,9,1),OR(G11="",G11>=DATE(2029,9,1))),H11*(1+Assumptions!$C$7)^4,0) -> 15645.623 | BN11: =IF(AND(F11<=DATE(2029,10,1),OR(G11="",G11>=DATE(2029,10,1))),H11*(1+Assumptions!$C$7)^4,0) -> 15645.623 | BO11: =IF(AND(F11<=DATE(2029,11,1),OR(G11="",G11>=DATE(2029,11,1))),H11*(1+Assumptions!$C$7)^4,0) -> 15645.623 | BP11: =IF(AND(F11<=DATE(2029,12,1),OR(G11="",G11>=DATE(2029,12,1))),H11*(1+Assumptions!$C$7)^4,0) -> 15645.623
A12: 9 | B12: Head of Growth | C12: S&M | D12: Growth | E12: Current | F12: 46054 | H12: 10000 | I12: =IF(AND(F12<=DATE(2025,1,1),OR(G12="",G12>=DATE(2025,1,1))),H12*(1+Assumptions!$C$7)^0,0) -> 0 | J12: =IF(AND(F12<=DATE(2025,2,1),OR(G12="",G12>=DATE(2025,2,1))),H12*(1+Assumptions!$C$7)^0,0) -> 0 | K12: =IF(AND(F12<=DATE(2025,3,1),OR(G12="",G12>=DATE(2025,3,1))),H12*(1+Assumptions!$C$7)^0,0) -> 0 | L12: =IF(AND(F12<=DATE(2025,4,1),OR(G12="",G12>=DATE(2025,4,1))),H12*(1+Assumptions!$C$7)^0,0) -> 0 | M12: =IF(AND(F12<=DATE(2025,5,1),OR(G12="",G12>=DATE(2025,5,1))),H12*(1+Assumptions!$C$7)^0,0) -> 0 | N12: =IF(AND(F12<=DATE(2025,6,1),OR(G12="",G12>=DATE(2025,6,1))),H12*(1+Assumptions!$C$7)^0,0) -> 0 | O12: =IF(AND(F12<=DATE(2025,7,1),OR(G12="",G12>=DATE(2025,7,1))),H12*(1+Assumptions!$C$7)^0,0) -> 0 | P12: =IF(AND(F12<=DATE(2025,8,1),OR(G12="",G12>=DATE(2025,8,1))),H12*(1+Assumptions!$C$7)^0,0) -> 0 | Q12: =IF(AND(F12<=DATE(2025,9,1),OR(G12="",G12>=DATE(2025,9,1))),H12*(1+Assumptions!$C$7)^0,0) -> 0 | R12: =IF(AND(F12<=DATE(2025,10,1),OR(G12="",G12>=DATE(2025,10,1))),H12*(1+Assumptions!$C$7)^0,0) -> 0 | S12: =IF(AND(F12<=DATE(2025,11,1),OR(G12="",G12>=DATE(2025,11,1))),H12*(1+Assumptions!$C$7)^0,0) -> 0 | T12: =IF(AND(F12<=DATE(2025,12,1),OR(G12="",G12>=DATE(2025,12,1))),H12*(1+Assumptions!$C$7)^0,0) -> 0 | U12: =IF(AND(F12<=DATE(2026,1,1),OR(G12="",G12>=DATE(2026,1,1))),H12*(1+Assumptions!$C$7)^1,0) -> 0 | V12: =IF(AND(F12<=DATE(2026,2,1),OR(G12="",G12>=DATE(2026,2,1))),H12*(1+Assumptions!$C$7)^1,0) -> 10800 | W12: =IF(AND(F12<=DATE(2026,3,1),OR(G12="",G12>=DATE(2026,3,1))),H12*(1+Assumptions!$C$7)^1,0) -> 10800 | X12: =IF(AND(F12<=DATE(2026,4,1),OR(G12="",G12>=DATE(2026,4,1))),H12*(1+Assumptions!$C$7)^1,0) -> 10800 | Y12: =IF(AND(F12<=DATE(2026,5,1),OR(G12="",G12>=DATE(2026,5,1))),H12*(1+Assumptions!$C$7)^1,0) -> 10800 | Z12: =IF(AND(F12<=DATE(2026,6,1),OR(G12="",G12>=DATE(2026,6,1))),H12*(1+Assumptions!$C$7)^1,0) -> 10800 | AA12: =IF(AND(F12<=DATE(2026,7,1),OR(G12="",G12>=DATE(2026,7,1))),H12*(1+Assumptions!$C$7)^1,0) -> 10800 | AB12: =IF(AND(F12<=DATE(2026,8,1),OR(G12="",G12>=DATE(2026,8,1))),H12*(1+Assumptions!$C$7)^1,0) -> 10800 | AC12: =IF(AND(F12<=DATE(2026,9,1),OR(G12="",G12>=DATE(2026,9,1))),H12*(1+Assumptions!$C$7)^1,0) -> 10800 | AD12: =IF(AND(F12<=DATE(2026,10,1),OR(G12="",G12>=DATE(2026,10,1))),H12*(1+Assumptions!$C$7)^1,0) -> 10800 | AE12: =IF(AND(F12<=DATE(2026,11,1),OR(G12="",G12>=DATE(2026,11,1))),H12*(1+Assumptions!$C$7)^1,0) -> 10800 | AF12: =IF(AND(F12<=DATE(2026,12,1),OR(G12="",G12>=DATE(2026,12,1))),H12*(1+Assumptions!$C$7)^1,0) -> 10800 | AG12: =IF(AND(F12<=DATE(2027,1,1),OR(G12="",G12>=DATE(2027,1,1))),H12*(1+Assumptions!$C$7)^2,0) -> 11664 | AH12: =IF(AND(F12<=DATE(2027,2,1),OR(G12="",G12>=DATE(2027,2,1))),H12*(1+Assumptions!$C$7)^2,0) -> 11664 | AI12: =IF(AND(F12<=DATE(2027,3,1),OR(G12="",G12>=DATE(2027,3,1))),H12*(1+Assumptions!$C$7)^2,0) -> 11664 | AJ12: =IF(AND(F12<=DATE(2027,4,1),OR(G12="",G12>=DATE(2027,4,1))),H12*(1+Assumptions!$C$7)^2,0) -> 11664 | AK12: =IF(AND(F12<=DATE(2027,5,1),OR(G12="",G12>=DATE(2027,5,1))),H12*(1+Assumptions!$C$7)^2,0) -> 11664 | AL12: =IF(AND(F12<=DATE(2027,6,1),OR(G12="",G12>=DATE(2027,6,1))),H12*(1+Assumptions!$C$7)^2,0) -> 11664 | AM12: =IF(AND(F12<=DATE(2027,7,1),OR(G12="",G12>=DATE(2027,7,1))),H12*(1+Assumptions!$C$7)^2,0) -> 11664 | AN12: =IF(AND(F12<=DATE(2027,8,1),OR(G12="",G12>=DATE(2027,8,1))),H12*(1+Assumptions!$C$7)^2,0) -> 11664 | AO12: =IF(AND(F12<=DATE(2027,9,1),OR(G12="",G12>=DATE(2027,9,1))),H12*(1+Assumptions!$C$7)^2,0) -> 11664 | AP12: =IF(AND(F12<=DATE(2027,10,1),OR(G12="",G12>=DATE(2027,10,1))),H12*(1+Assumptions!$C$7)^2,0) -> 11664 | AQ12: =IF(AND(F12<=DATE(2027,11,1),OR(G12="",G12>=DATE(2027,11,1))),H12*(1+Assumptions!$C$7)^2,0) -> 11664 | AR12: =IF(AND(F12<=DATE(2027,12,1),OR(G12="",G12>=DATE(2027,12,1))),H12*(1+Assumptions!$C$7)^2,0) -> 11664 | AS12: =IF(AND(F12<=DATE(2028,1,1),OR(G12="",G12>=DATE(2028,1,1))),H12*(1+Assumptions!$C$7)^3,0) -> 12597.12 | AT12: =IF(AND(F12<=DATE(2028,2,1),OR(G12="",G12>=DATE(2028,2,1))),H12*(1+Assumptions!$C$7)^3,0) -> 12597.12 | AU12: =IF(AND(F12<=DATE(2028,3,1),OR(G12="",G12>=DATE(2028,3,1))),H12*(1+Assumptions!$C$7)^3,0) -> 12597.12 | AV12: =IF(AND(F12<=DATE(2028,4,1),OR(G12="",G12>=DATE(2028,4,1))),H12*(1+Assumptions!$C$7)^3,0) -> 12597.12 | AW12: =IF(AND(F12<=DATE(2028,5,1),OR(G12="",G12>=DATE(2028,5,1))),H12*(1+Assumptions!$C$7)^3,0) -> 12597.12 | AX12: =IF(AND(F12<=DATE(2028,6,1),OR(G12="",G12>=DATE(2028,6,1))),H12*(1+Assumptions!$C$7)^3,0) -> 12597.12 | AY12: =IF(AND(F12<=DATE(2028,7,1),OR(G12="",G12>=DATE(2028,7,1))),H12*(1+Assumptions!$C$7)^3,0) -> 12597.12 | AZ12: =IF(AND(F12<=DATE(2028,8,1),OR(G12="",G12>=DATE(2028,8,1))),H12*(1+Assumptions!$C$7)^3,0) -> 12597.12 | BA12: =IF(AND(F12<=DATE(2028,9,1),OR(G12="",G12>=DATE(2028,9,1))),H12*(1+Assumptions!$C$7)^3,0) -> 12597.12 | BB12: =IF(AND(F12<=DATE(2028,10,1),OR(G12="",G12>=DATE(2028,10,1))),H12*(1+Assumptions!$C$7)^3,0) -> 12597.12 | BC12: =IF(AND(F12<=DATE(2028,11,1),OR(G12="",G12>=DATE(2028,11,1))),H12*(1+Assumptions!$C$7)^3,0) -> 12597.12 | BD12: =IF(AND(F12<=DATE(2028,12,1),OR(G12="",G12>=DATE(2028,12,1))),H12*(1+Assumptions!$C$7)^3,0) -> 12597.12 | BE12: =IF(AND(F12<=DATE(2029,1,1),OR(G12="",G12>=DATE(2029,1,1))),H12*(1+Assumptions!$C$7)^4,0) -> 13604.89 | BF12: =IF(AND(F12<=DATE(2029,2,1),OR(G12="",G12>=DATE(2029,2,1))),H12*(1+Assumptions!$C$7)^4,0) -> 13604.89 | BG12: =IF(AND(F12<=DATE(2029,3,1),OR(G12="",G12>=DATE(2029,3,1))),H12*(1+Assumptions!$C$7)^4,0) -> 13604.89 | BH12: =IF(AND(F12<=DATE(2029,4,1),OR(G12="",G12>=DATE(2029,4,1))),H12*(1+Assumptions!$C$7)^4,0) -> 13604.89 | BI12: =IF(AND(F12<=DATE(2029,5,1),OR(G12="",G12>=DATE(2029,5,1))),H12*(1+Assumptions!$C$7)^4,0) -> 13604.89 | BJ12: =IF(AND(F12<=DATE(2029,6,1),OR(G12="",G12>=DATE(2029,6,1))),H12*(1+Assumptions!$C$7)^4,0) -> 13604.89 | BK12: =IF(AND(F12<=DATE(2029,7,1),OR(G12="",G12>=DATE(2029,7,1))),H12*(1+Assumptions!$C$7)^4,0) -> 13604.89 | BL12: =IF(AND(F12<=DATE(2029,8,1),OR(G12="",G12>=DATE(2029,8,1))),H12*(1+Assumptions!$C$7)^4,0) -> 13604.89 | BM12: =IF(AND(F12<=DATE(2029,9,1),OR(G12="",G12>=DATE(2029,9,1))),H12*(1+Assumptions!$C$7)^4,0) -> 13604.89 | BN12: =IF(AND(F12<=DATE(2029,10,1),OR(G12="",G12>=DATE(2029,10,1))),H12*(1+Assumptions!$C$7)^4,0) -> 13604.89 | BO12: =IF(AND(F12<=DATE(2029,11,1),OR(G12="",G12>=DATE(2029,11,1))),H12*(1+Assumptions!$C$7)^4,0) -> 13604.89 | BP12: =IF(AND(F12<=DATE(2029,12,1),OR(G12="",G12>=DATE(2029,12,1))),H12*(1+Assumptions!$C$7)^4,0) -> 13604.89
A13: 10 | B13: CEO | C13: G&A | D13: CEO | E13: Current | F13: 46266 | H13: 11500 | I13: =IF(AND(F13<=DATE(2025,1,1),OR(G13="",G13>=DATE(2025,1,1))),H13*(1+Assumptions!$C$7)^0,0) -> 0 | J13: =IF(AND(F13<=DATE(2025,2,1),OR(G13="",G13>=DATE(2025,2,1))),H13*(1+Assumptions!$C$7)^0,0) -> 0 | K13: =IF(AND(F13<=DATE(2025,3,1),OR(G13="",G13>=DATE(2025,3,1))),H13*(1+Assumptions!$C$7)^0,0) -> 0 | L13: =IF(AND(F13<=DATE(2025,4,1),OR(G13="",G13>=DATE(2025,4,1))),H13*(1+Assumptions!$C$7)^0,0) -> 0 | M13: =IF(AND(F13<=DATE(2025,5,1),OR(G13="",G13>=DATE(2025,5,1))),H13*(1+Assumptions!$C$7)^0,0) -> 0 | N13: =IF(AND(F13<=DATE(2025,6,1),OR(G13="",G13>=DATE(2025,6,1))),H13*(1+Assumptions!$C$7)^0,0) -> 0 | O13: =IF(AND(F13<=DATE(2025,7,1),OR(G13="",G13>=DATE(2025,7,1))),H13*(1+Assumptions!$C$7)^0,0) -> 0 | P13: =IF(AND(F13<=DATE(2025,8,1),OR(G13="",G13>=DATE(2025,8,1))),H13*(1+Assumptions!$C$7)^0,0) -> 0 | Q13: 7500 | R13: 7500 | S13: 7500 | T13: 7500 | U13: 7500 | V13: 7500 | W13: 7500 | X13: 7500 | Y13: 7500 | Z13: 7500 | AA13: 7500 | AB13: 7500 | AC13: =IF(AND(F13<=DATE(2026,9,1),OR(G13="",G13>=DATE(2026,9,1))),H13*(1+Assumptions!$C$7)^1,0) -> 12420 | AD13: =IF(AND(F13<=DATE(2026,10,1),OR(G13="",G13>=DATE(2026,10,1))),H13*(1+Assumptions!$C$7)^1,0) -> 12420 | AE13: =IF(AND(F13<=DATE(2026,11,1),OR(G13="",G13>=DATE(2026,11,1))),H13*(1+Assumptions!$C$7)^1,0) -> 12420 | AF13: =IF(AND(F13<=DATE(2026,12,1),OR(G13="",G13>=DATE(2026,12,1))),H13*(1+Assumptions!$C$7)^1,0) -> 12420 | AG13: =IF(AND(F13<=DATE(2027,1,1),OR(G13="",G13>=DATE(2027,1,1))),H13*(1+Assumptions!$C$7)^2,0) -> 13413.6 | AH13: =IF(AND(F13<=DATE(2027,2,1),OR(G13="",G13>=DATE(2027,2,1))),H13*(1+Assumptions!$C$7)^2,0) -> 13413.6 | AI13: =IF(AND(F13<=DATE(2027,3,1),OR(G13="",G13>=DATE(2027,3,1))),H13*(1+Assumptions!$C$7)^2,0) -> 13413.6 | AJ13: =IF(AND(F13<=DATE(2027,4,1),OR(G13="",G13>=DATE(2027,4,1))),H13*(1+Assumptions!$C$7)^2,0) -> 13413.6 | AK13: =IF(AND(F13<=DATE(2027,5,1),OR(G13="",G13>=DATE(2027,5,1))),H13*(1+Assumptions!$C$7)^2,0) -> 13413.6 | AL13: =IF(AND(F13<=DATE(2027,6,1),OR(G13="",G13>=DATE(2027,6,1))),H13*(1+Assumptions!$C$7)^2,0) -> 13413.6 | AM13: =IF(AND(F13<=DATE(2027,7,1),OR(G13="",G13>=DATE(2027,7,1))),H13*(1+Assumptions!$C$7)^2,0) -> 13413.6 | AN13: =IF(AND(F13<=DATE(2027,8,1),OR(G13="",G13>=DATE(2027,8,1))),H13*(1+Assumptions!$C$7)^2,0) -> 13413.6 | AO13: =IF(AND(F13<=DATE(2027,9,1),OR(G13="",G13>=DATE(2027,9,1))),H13*(1+Assumptions!$C$7)^2,0) -> 13413.6 | AP13: =IF(AND(F13<=DATE(2027,10,1),OR(G13="",G13>=DATE(2027,10,1))),H13*(1+Assumptions!$C$7)^2,0) -> 13413.6 | AQ13: =IF(AND(F13<=DATE(2027,11,1),OR(G13="",G13>=DATE(2027,11,1))),H13*(1+Assumptions!$C$7)^2,0) -> 13413.6 | AR13: =IF(AND(F13<=DATE(2027,12,1),OR(G13="",G13>=DATE(2027,12,1))),H13*(1+Assumptions!$C$7)^2,0) -> 13413.6 | AS13: =IF(AND(F13<=DATE(2028,1,1),OR(G13="",G13>=DATE(2028,1,1))),H13*(1+Assumptions!$C$7)^3,0) -> 14486.688 | AT13: =IF(AND(F13<=DATE(2028,2,1),OR(G13="",G13>=DATE(2028,2,1))),H13*(1+Assumptions!$C$7)^3,0) -> 14486.688 | AU13: =IF(AND(F13<=DATE(2028,3,1),OR(G13="",G13>=DATE(2028,3,1))),H13*(1+Assumptions!$C$7)^3,0) -> 14486.688 | AV13: =IF(AND(F13<=DATE(2028,4,1),OR(G13="",G13>=DATE(2028,4,1))),H13*(1+Assumptions!$C$7)^3,0) -> 14486.688 | AW13: =IF(AND(F13<=DATE(2028,5,1),OR(G13="",G13>=DATE(2028,5,1))),H13*(1+Assumptions!$C$7)^3,0) -> 14486.688 | AX13: =IF(AND(F13<=DATE(2028,6,1),OR(G13="",G13>=DATE(2028,6,1))),H13*(1+Assumptions!$C$7)^3,0) -> 14486.688 | AY13: =IF(AND(F13<=DATE(2028,7,1),OR(G13="",G13>=DATE(2028,7,1))),H13*(1+Assumptions!$C$7)^3,0) -> 14486.688 | AZ13: =IF(AND(F13<=DATE(2028,8,1),OR(G13="",G13>=DATE(2028,8,1))),H13*(1+Assumptions!$C$7)^3,0) -> 14486.688 | BA13: =IF(AND(F13<=DATE(2028,9,1),OR(G13="",G13>=DATE(2028,9,1))),H13*(1+Assumptions!$C$7)^3,0) -> 14486.688 | BB13: =IF(AND(F13<=DATE(2028,10,1),OR(G13="",G13>=DATE(2028,10,1))),H13*(1+Assumptions!$C$7)^3,0) -> 14486.688 | BC13: =IF(AND(F13<=DATE(2028,11,1),OR(G13="",G13>=DATE(2028,11,1))),H13*(1+Assumptions!$C$7)^3,0) -> 14486.688 | BD13: =IF(AND(F13<=DATE(2028,12,1),OR(G13="",G13>=DATE(2028,12,1))),H13*(1+Assumptions!$C$7)^3,0) -> 14486.688 | BE13: =IF(AND(F13<=DATE(2029,1,1),OR(G13="",G13>=DATE(2029,1,1))),H13*(1+Assumptions!$C$7)^4,0) -> 15645.623 | BF13: =IF(AND(F13<=DATE(2029,2,1),OR(G13="",G13>=DATE(2029,2,1))),H13*(1+Assumptions!$C$7)^4,0) -> 15645.623 | BG13: =IF(AND(F13<=DATE(2029,3,1),OR(G13="",G13>=DATE(2029,3,1))),H13*(1+Assumptions!$C$7)^4,0) -> 15645.623 | BH13: =IF(AND(F13<=DATE(2029,4,1),OR(G13="",G13>=DATE(2029,4,1))),H13*(1+Assumptions!$C$7)^4,0) -> 15645.623 | BI13: =IF(AND(F13<=DATE(2029,5,1),OR(G13="",G13>=DATE(2029,5,1))),H13*(1+Assumptions!$C$7)^4,0) -> 15645.623 | BJ13: =IF(AND(F13<=DATE(2029,6,1),OR(G13="",G13>=DATE(2029,6,1))),H13*(1+Assumptions!$C$7)^4,0) -> 15645.623 | BK13: =IF(AND(F13<=DATE(2029,7,1),OR(G13="",G13>=DATE(2029,7,1))),H13*(1+Assumptions!$C$7)^4,0) -> 15645.623 | BL13: =IF(AND(F13<=DATE(2029,8,1),OR(G13="",G13>=DATE(2029,8,1))),H13*(1+Assumptions!$C$7)^4,0) -> 15645.623 | BM13: =IF(AND(F13<=DATE(2029,9,1),OR(G13="",G13>=DATE(2029,9,1))),H13*(1+Assumptions!$C$7)^4,0) -> 15645.623 | BN13: =IF(AND(F13<=DATE(2029,10,1),OR(G13="",G13>=DATE(2029,10,1))),H13*(1+Assumptions!$C$7)^4,0) -> 15645.623 | BO13: =IF(AND(F13<=DATE(2029,11,1),OR(G13="",G13>=DATE(2029,11,1))),H13*(1+Assumptions!$C$7)^4,0) -> 15645.623 | BP13: =IF(AND(F13<=DATE(2029,12,1),OR(G13="",G13>=DATE(2029,12,1))),H13*(1+Assumptions!$C$7)^4,0) -> 15645.623
A15: # | B15: PLANNED HIRES
A16: 11 | B16: New hire | C16: R&D | D16: Software Engineer | E16: Planned | F16: 46296 | H16: 8000 | I16: =IF(AND($F16<=I$2, OR($G16="",$G16>=I$2)), $H16 * (1 + Assumptions!$C$7) ^ INT(((YEAR(I$2)-YEAR($F16))*12 + MONTH(I$2)-MONTH($F16)) / 12), 0) -> 0 | J16: =IF(AND($F16<=J$2, OR($G16="",$G16>=J$2)), $H16 * (1 + Assumptions!$C$7) ^ INT(((YEAR(J$2)-YEAR($F16))*12 + MONTH(J$2)-MONTH($F16)) / 12), 0) -> 0 | K16: =IF(AND($F16<=K$2, OR($G16="",$G16>=K$2)), $H16 * (1 + Assumptions!$C$7) ^ INT(((YEAR(K$2)-YEAR($F16))*12 + MONTH(K$2)-MONTH($F16)) / 12), 0) -> 0 | L16: =IF(AND($F16<=L$2, OR($G16="",$G16>=L$2)), $H16 * (1 + Assumptions!$C$7) ^ INT(((YEAR(L$2)-YEAR($F16))*12 + MONTH(L$2)-MONTH($F16)) / 12), 0) -> 0 | M16: =IF(AND($F16<=M$2, OR($G16="",$G16>=M$2)), $H16 * (1 + Assumptions!$C$7) ^ INT(((YEAR(M$2)-YEAR($F16))*12 + MONTH(M$2)-MONTH($F16)) / 12), 0) -> 0 | N16: =IF(AND($F16<=N$2, OR($G16="",$G16>=N$2)), $H16 * (1 + Assumptions!$C$7) ^ INT(((YEAR(N$2)-YEAR($F16))*12 + MONTH(N$2)-MONTH($F16)) / 12), 0) -> 0 | O16: =IF(AND($F16<=O$2, OR($G16="",$G16>=O$2)), $H16 * (1 + Assumptions!$C$7) ^ INT(((YEAR(O$2)-YEAR($F16))*12 + MONTH(O$2)-MONTH($F16)) / 12), 0) -> 0 | P16: =IF(AND($F16<=P$2, OR($G16="",$G16>=P$2)), $H16 * (1 + Assumptions!$C$7) ^ INT(((YEAR(P$2)-YEAR($F16))*12 + MONTH(P$2)-MONTH($F16)) / 12), 0) -> 0 | ... BP16: =IF(AND($F16<=BP$2, OR($G16="",$G16>=BP$2)), $H16 * (1 + Assumptions!$C$7) ^ INT(((YEAR(BP$2)-YEAR($F16))*12 + MONTH(BP$2)-MONTH($F16)) / 12), 0) -> 10077.696
A17: 12 | B17: New hire | C17: G&A | D17: COO | E17: Planned | F17: 46235 | H17: 9000 | I17: =IF(AND($F17<=I$2, OR($G17="",$G17>=I$2)), $H17 * (1 + Assumptions!$C$7) ^ INT(((YEAR(I$2)-YEAR($F17))*12 + MONTH(I$2)-MONTH($F17)) / 12), 0) -> 0 | J17: =IF(AND($F17<=J$2, OR($G17="",$G17>=J$2)), $H17 * (1 + Assumptions!$C$7) ^ INT(((YEAR(J$2)-YEAR($F17))*12 + MONTH(J$2)-MONTH($F17)) / 12), 0) -> 0 | K17: =IF(AND($F17<=K$2, OR($G17="",$G17>=K$2)), $H17 * (1 + Assumptions!$C$7) ^ INT(((YEAR(K$2)-YEAR($F17))*12 + MONTH(K$2)-MONTH($F17)) / 12), 0) -> 0 | L17: =IF(AND($F17<=L$2, OR($G17="",$G17>=L$2)), $H17 * (1 + Assumptions!$C$7) ^ INT(((YEAR(L$2)-YEAR($F17))*12 + MONTH(L$2)-MONTH($F17)) / 12), 0) -> 0 | M17: =IF(AND($F17<=M$2, OR($G17="",$G17>=M$2)), $H17 * (1 + Assumptions!$C$7) ^ INT(((YEAR(M$2)-YEAR($F17))*12 + MONTH(M$2)-MONTH($F17)) / 12), 0) -> 0 | N17: =IF(AND($F17<=N$2, OR($G17="",$G17>=N$2)), $H17 * (1 + Assumptions!$C$7) ^ INT(((YEAR(N$2)-YEAR($F17))*12 + MONTH(N$2)-MONTH($F17)) / 12), 0) -> 0 | O17: =IF(AND($F17<=O$2, OR($G17="",$G17>=O$2)), $H17 * (1 + Assumptions!$C$7) ^ INT(((YEAR(O$2)-YEAR($F17))*12 + MONTH(O$2)-MONTH($F17)) / 12), 0) -> 0 | P17: =IF(AND($F17<=P$2, OR($G17="",$G17>=P$2)), $H17 * (1 + Assumptions!$C$7) ^ INT(((YEAR(P$2)-YEAR($F17))*12 + MONTH(P$2)-MONTH($F17)) / 12), 0) -> 0 | ... BP17: =IF(AND($F17<=BP$2, OR($G17="",$G17>=BP$2)), $H17 * (1 + Assumptions!$C$7) ^ INT(((YEAR(BP$2)-YEAR($F17))*12 + MONTH(BP$2)-MONTH($F17)) / 12), 0) -> 11337.408
A18: 13 | B18: New hire | C18: R&D | D18: Maintenance Engineer | E18: Planned | F18: 46235 | H18: 6000 | I18: =IF(AND($F18<=I$2, OR($G18="",$G18>=I$2)), $H18 * (1 + Assumptions!$C$7) ^ INT(((YEAR(I$2)-YEAR($F18))*12 + MONTH(I$2)-MONTH($F18)) / 12), 0) -> 0 | J18: =IF(AND($F18<=J$2, OR($G18="",$G18>=J$2)), $H18 * (1 + Assumptions!$C$7) ^ INT(((YEAR(J$2)-YEAR($F18))*12 + MONTH(J$2)-MONTH($F18)) / 12), 0) -> 0 | K18: =IF(AND($F18<=K$2, OR($G18="",$G18>=K$2)), $H18 * (1 + Assumptions!$C$7) ^ INT(((YEAR(K$2)-YEAR($F18))*12 + MONTH(K$2)-MONTH($F18)) / 12), 0) -> 0 | L18: =IF(AND($F18<=L$2, OR($G18="",$G18>=L$2)), $H18 * (1 + Assumptions!$C$7) ^ INT(((YEAR(L$2)-YEAR($F18))*12 + MONTH(L$2)-MONTH($F18)) / 12), 0) -> 0 | M18: =IF(AND($F18<=M$2, OR($G18="",$G18>=M$2)), $H18 * (1 + Assumptions!$C$7) ^ INT(((YEAR(M$2)-YEAR($F18))*12 + MONTH(M$2)-MONTH($F18)) / 12), 0) -> 0 | N18: =IF(AND($F18<=N$2, OR($G18="",$G18>=N$2)), $H18 * (1 + Assumptions!$C$7) ^ INT(((YEAR(N$2)-YEAR($F18))*12 + MONTH(N$2)-MONTH($F18)) / 12), 0) -> 0 | O18: =IF(AND($F18<=O$2, OR($G18="",$G18>=O$2)), $H18 * (1 + Assumptions!$C$7) ^ INT(((YEAR(O$2)-YEAR($F18))*12 + MONTH(O$2)-MONTH($F18)) / 12), 0) -> 0 | P18: =IF(AND($F18<=P$2, OR($G18="",$G18>=P$2)), $H18 * (1 + Assumptions!$C$7) ^ INT(((YEAR(P$2)-YEAR($F18))*12 + MONTH(P$2)-MONTH($F18)) / 12), 0) -> 0 | ... BP18: =IF(AND($F18<=BP$2, OR($G18="",$G18>=BP$2)), $H18 * (1 + Assumptions!$C$7) ^ INT(((YEAR(BP$2)-YEAR($F18))*12 + MONTH(BP$2)-MONTH($F18)) / 12), 0) -> 7558.272
A19: 14 | B19: New hire | C19: S&M | D19: Marketing | E19: Planned | F19: 46235 | H19: 9000 | I19: =IF(AND($F19<=I$2, OR($G19="",$G19>=I$2)), $H19 * (1 + Assumptions!$C$7) ^ INT(((YEAR(I$2)-YEAR($F19))*12 + MONTH(I$2)-MONTH($F19)) / 12), 0) -> 0 | J19: =IF(AND($F19<=J$2, OR($G19="",$G19>=J$2)), $H19 * (1 + Assumptions!$C$7) ^ INT(((YEAR(J$2)-YEAR($F19))*12 + MONTH(J$2)-MONTH($F19)) / 12), 0) -> 0 | K19: =IF(AND($F19<=K$2, OR($G19="",$G19>=K$2)), $H19 * (1 + Assumptions!$C$7) ^ INT(((YEAR(K$2)-YEAR($F19))*12 + MONTH(K$2)-MONTH($F19)) / 12), 0) -> 0 | L19: =IF(AND($F19<=L$2, OR($G19="",$G19>=L$2)), $H19 * (1 + Assumptions!$C$7) ^ INT(((YEAR(L$2)-YEAR($F19))*12 + MONTH(L$2)-MONTH($F19)) / 12), 0) -> 0 | M19: =IF(AND($F19<=M$2, OR($G19="",$G19>=M$2)), $H19 * (1 + Assumptions!$C$7) ^ INT(((YEAR(M$2)-YEAR($F19))*12 + MONTH(M$2)-MONTH($F19)) / 12), 0) -> 0 | N19: =IF(AND($F19<=N$2, OR($G19="",$G19>=N$2)), $H19 * (1 + Assumptions!$C$7) ^ INT(((YEAR(N$2)-YEAR($F19))*12 + MONTH(N$2)-MONTH($F19)) / 12), 0) -> 0 | O19: =IF(AND($F19<=O$2, OR($G19="",$G19>=O$2)), $H19 * (1 + Assumptions!$C$7) ^ INT(((YEAR(O$2)-YEAR($F19))*12 + MONTH(O$2)-MONTH($F19)) / 12), 0) -> 0 | P19: =IF(AND($F19<=P$2, OR($G19="",$G19>=P$2)), $H19 * (1 + Assumptions!$C$7) ^ INT(((YEAR(P$2)-YEAR($F19))*12 + MONTH(P$2)-MONTH($F19)) / 12), 0) -> 0 | ... BP19: =IF(AND($F19<=BP$2, OR($G19="",$G19>=BP$2)), $H19 * (1 + Assumptions!$C$7) ^ INT(((YEAR(BP$2)-YEAR($F19))*12 + MONTH(BP$2)-MONTH($F19)) / 12), 0) -> 11337.408
A20: 15 | B20: New hire | C20: G&A | D20: CFO | E20: Planned | F20: 46296 | H20: 9500 | I20: =IF(AND($F20<=I$2, OR($G20="",$G20>=I$2)), $H20 * (1 + Assumptions!$C$7) ^ INT(((YEAR(I$2)-YEAR($F20))*12 + MONTH(I$2)-MONTH($F20)) / 12), 0) -> 0 | J20: =IF(AND($F20<=J$2, OR($G20="",$G20>=J$2)), $H20 * (1 + Assumptions!$C$7) ^ INT(((YEAR(J$2)-YEAR($F20))*12 + MONTH(J$2)-MONTH($F20)) / 12), 0) -> 0 | K20: =IF(AND($F20<=K$2, OR($G20="",$G20>=K$2)), $H20 * (1 + Assumptions!$C$7) ^ INT(((YEAR(K$2)-YEAR($F20))*12 + MONTH(K$2)-MONTH($F20)) / 12), 0) -> 0 | L20: =IF(AND($F20<=L$2, OR($G20="",$G20>=L$2)), $H20 * (1 + Assumptions!$C$7) ^ INT(((YEAR(L$2)-YEAR($F20))*12 + MONTH(L$2)-MONTH($F20)) / 12), 0) -> 0 | M20: =IF(AND($F20<=M$2, OR($G20="",$G20>=M$2)), $H20 * (1 + Assumptions!$C$7) ^ INT(((YEAR(M$2)-YEAR($F20))*12 + MONTH(M$2)-MONTH($F20)) / 12), 0) -> 0 | N20: =IF(AND($F20<=N$2, OR($G20="",$G20>=N$2)), $H20 * (1 + Assumptions!$C$7) ^ INT(((YEAR(N$2)-YEAR($F20))*12 + MONTH(N$2)-MONTH($F20)) / 12), 0) -> 0 | O20: =IF(AND($F20<=O$2, OR($G20="",$G20>=O$2)), $H20 * (1 + Assumptions!$C$7) ^ INT(((YEAR(O$2)-YEAR($F20))*12 + MONTH(O$2)-MONTH($F20)) / 12), 0) -> 0 | P20: =IF(AND($F20<=P$2, OR($G20="",$G20>=P$2)), $H20 * (1 + Assumptions!$C$7) ^ INT(((YEAR(P$2)-YEAR($F20))*12 + MONTH(P$2)-MONTH($F20)) / 12), 0) -> 0 | ... BP20: =IF(AND($F20<=BP$2, OR($G20="",$G20>=BP$2)), $H20 * (1 + Assumptions!$C$7) ^ INT(((YEAR(BP$2)-YEAR($F20))*12 + MONTH(BP$2)-MONTH($F20)) / 12), 0) -> 11967.264
A21: 16 | B21: New hire | C21: S&M | D21: Sales | E21: Planned | F21: 46296 | H21: 6500 | I21: =IF(AND($F21<=I$2, OR($G21="",$G21>=I$2)), $H21 * (1 + Assumptions!$C$7) ^ INT(((YEAR(I$2)-YEAR($F21))*12 + MONTH(I$2)-MONTH($F21)) / 12), 0) -> 0 | J21: =IF(AND($F21<=J$2, OR($G21="",$G21>=J$2)), $H21 * (1 + Assumptions!$C$7) ^ INT(((YEAR(J$2)-YEAR($F21))*12 + MONTH(J$2)-MONTH($F21)) / 12), 0) -> 0 | K21: =IF(AND($F21<=K$2, OR($G21="",$G21>=K$2)), $H21 * (1 + Assumptions!$C$7) ^ INT(((YEAR(K$2)-YEAR($F21))*12 + MONTH(K$2)-MONTH($F21)) / 12), 0) -> 0 | L21: =IF(AND($F21<=L$2, OR($G21="",$G21>=L$2)), $H21 * (1 + Assumptions!$C$7) ^ INT(((YEAR(L$2)-YEAR($F21))*12 + MONTH(L$2)-MONTH($F21)) / 12), 0) -> 0 | M21: =IF(AND($F21<=M$2, OR($G21="",$G21>=M$2)), $H21 * (1 + Assumptions!$C$7) ^ INT(((YEAR(M$2)-YEAR($F21))*12 + MONTH(M$2)-MONTH($F21)) / 12), 0) -> 0 | N21: =IF(AND($F21<=N$2, OR($G21="",$G21>=N$2)), $H21 * (1 + Assumptions!$C$7) ^ INT(((YEAR(N$2)-YEAR($F21))*12 + MONTH(N$2)-MONTH($F21)) / 12), 0) -> 0 | O21: =IF(AND($F21<=O$2, OR($G21="",$G21>=O$2)), $H21 * (1 + Assumptions!$C$7) ^ INT(((YEAR(O$2)-YEAR($F21))*12 + MONTH(O$2)-MONTH($F21)) / 12), 0) -> 0 | P21: =IF(AND($F21<=P$2, OR($G21="",$G21>=P$2)), $H21 * (1 + Assumptions!$C$7) ^ INT(((YEAR(P$2)-YEAR($F21))*12 + MONTH(P$2)-MONTH($F21)) / 12), 0) -> 0 | ... BP21: =IF(AND($F21<=BP$2, OR($G21="",$G21>=BP$2)), $H21 * (1 + Assumptions!$C$7) ^ INT(((YEAR(BP$2)-YEAR($F21))*12 + MONTH(BP$2)-MONTH($F21)) / 12), 0) -> 8188.128
A22: 17 | B22: New hire | C22: R&D | D22: R&D Engineer | E22: Planned | F22: 46388 | H22: 7500 | I22: =IF(AND($F22<=I$2, OR($G22="",$G22>=I$2)), $H22 * (1 + Assumptions!$C$7) ^ INT(((YEAR(I$2)-YEAR($F22))*12 + MONTH(I$2)-MONTH($F22)) / 12), 0) -> 0 | J22: =IF(AND($F22<=J$2, OR($G22="",$G22>=J$2)), $H22 * (1 + Assumptions!$C$7) ^ INT(((YEAR(J$2)-YEAR($F22))*12 + MONTH(J$2)-MONTH($F22)) / 12), 0) -> 0 | K22: =IF(AND($F22<=K$2, OR($G22="",$G22>=K$2)), $H22 * (1 + Assumptions!$C$7) ^ INT(((YEAR(K$2)-YEAR($F22))*12 + MONTH(K$2)-MONTH($F22)) / 12), 0) -> 0 | L22: =IF(AND($F22<=L$2, OR($G22="",$G22>=L$2)), $H22 * (1 + Assumptions!$C$7) ^ INT(((YEAR(L$2)-YEAR($F22))*12 + MONTH(L$2)-MONTH($F22)) / 12), 0) -> 0 | M22: =IF(AND($F22<=M$2, OR($G22="",$G22>=M$2)), $H22 * (1 + Assumptions!$C$7) ^ INT(((YEAR(M$2)-YEAR($F22))*12 + MONTH(M$2)-MONTH($F22)) / 12), 0) -> 0 | N22: =IF(AND($F22<=N$2, OR($G22="",$G22>=N$2)), $H22 * (1 + Assumptions!$C$7) ^ INT(((YEAR(N$2)-YEAR($F22))*12 + MONTH(N$2)-MONTH($F22)) / 12), 0) -> 0 | O22: =IF(AND($F22<=O$2, OR($G22="",$G22>=O$2)), $H22 * (1 + Assumptions!$C$7) ^ INT(((YEAR(O$2)-YEAR($F22))*12 + MONTH(O$2)-MONTH($F22)) / 12), 0) -> 0 | P22: =IF(AND($F22<=P$2, OR($G22="",$G22>=P$2)), $H22 * (1 + Assumptions!$C$7) ^ INT(((YEAR(P$2)-YEAR($F22))*12 + MONTH(P$2)-MONTH($F22)) / 12), 0) -> 0 | ... BP22: =IF(AND($F22<=BP$2, OR($G22="",$G22>=BP$2)), $H22 * (1 + Assumptions!$C$7) ^ INT(((YEAR(BP$2)-YEAR($F22))*12 + MONTH(BP$2)-MONTH($F22)) / 12), 0) -> 8748
A23: 18 | B23: New hire | C23: G&A | D23: Office Support | E23: Planned | F23: 46388 | H23: 4500 | I23: =IF(AND($F23<=I$2, OR($G23="",$G23>=I$2)), $H23 * (1 + Assumptions!$C$7) ^ INT(((YEAR(I$2)-YEAR($F23))*12 + MONTH(I$2)-MONTH($F23)) / 12), 0) -> 0 | J23: =IF(AND($F23<=J$2, OR($G23="",$G23>=J$2)), $H23 * (1 + Assumptions!$C$7) ^ INT(((YEAR(J$2)-YEAR($F23))*12 + MONTH(J$2)-MONTH($F23)) / 12), 0) -> 0 | K23: =IF(AND($F23<=K$2, OR($G23="",$G23>=K$2)), $H23 * (1 + Assumptions!$C$7) ^ INT(((YEAR(K$2)-YEAR($F23))*12 + MONTH(K$2)-MONTH($F23)) / 12), 0) -> 0 | L23: =IF(AND($F23<=L$2, OR($G23="",$G23>=L$2)), $H23 * (1 + Assumptions!$C$7) ^ INT(((YEAR(L$2)-YEAR($F23))*12 + MONTH(L$2)-MONTH($F23)) / 12), 0) -> 0 | M23: =IF(AND($F23<=M$2, OR($G23="",$G23>=M$2)), $H23 * (1 + Assumptions!$C$7) ^ INT(((YEAR(M$2)-YEAR($F23))*12 + MONTH(M$2)-MONTH($F23)) / 12), 0) -> 0 | N23: =IF(AND($F23<=N$2, OR($G23="",$G23>=N$2)), $H23 * (1 + Assumptions!$C$7) ^ INT(((YEAR(N$2)-YEAR($F23))*12 + MONTH(N$2)-MONTH($F23)) / 12), 0) -> 0 | O23: =IF(AND($F23<=O$2, OR($G23="",$G23>=O$2)), $H23 * (1 + Assumptions!$C$7) ^ INT(((YEAR(O$2)-YEAR($F23))*12 + MONTH(O$2)-MONTH($F23)) / 12), 0) -> 0 | P23: =IF(AND($F23<=P$2, OR($G23="",$G23>=P$2)), $H23 * (1 + Assumptions!$C$7) ^ INT(((YEAR(P$2)-YEAR($F23))*12 + MONTH(P$2)-MONTH($F23)) / 12), 0) -> 0 | ... BP23: =IF(AND($F23<=BP$2, OR($G23="",$G23>=BP$2)), $H23 * (1 + Assumptions!$C$7) ^ INT(((YEAR(BP$2)-YEAR($F23))*12 + MONTH(BP$2)-MONTH($F23)) / 12), 0) -> 5248.8
A24: 19 | B24: New hire | C24: R&D | D24: Product | E24: Planned | F24: 46388 | H24: 6500 | I24: =IF(AND($F24<=I$2, OR($G24="",$G24>=I$2)), $H24 * (1 + Assumptions!$C$7) ^ INT(((YEAR(I$2)-YEAR($F24))*12 + MONTH(I$2)-MONTH($F24)) / 12), 0) -> 0 | J24: =IF(AND($F24<=J$2, OR($G24="",$G24>=J$2)), $H24 * (1 + Assumptions!$C$7) ^ INT(((YEAR(J$2)-YEAR($F24))*12 + MONTH(J$2)-MONTH($F24)) / 12), 0) -> 0 | K24: =IF(AND($F24<=K$2, OR($G24="",$G24>=K$2)), $H24 * (1 + Assumptions!$C$7) ^ INT(((YEAR(K$2)-YEAR($F24))*12 + MONTH(K$2)-MONTH($F24)) / 12), 0) -> 0 | L24: =IF(AND($F24<=L$2, OR($G24="",$G24>=L$2)), $H24 * (1 + Assumptions!$C$7) ^ INT(((YEAR(L$2)-YEAR($F24))*12 + MONTH(L$2)-MONTH($F24)) / 12), 0) -> 0 | M24: =IF(AND($F24<=M$2, OR($G24="",$G24>=M$2)), $H24 * (1 + Assumptions!$C$7) ^ INT(((YEAR(M$2)-YEAR($F24))*12 + MONTH(M$2)-MONTH($F24)) / 12), 0) -> 0 | N24: =IF(AND($F24<=N$2, OR($G24="",$G24>=N$2)), $H24 * (1 + Assumptions!$C$7) ^ INT(((YEAR(N$2)-YEAR($F24))*12 + MONTH(N$2)-MONTH($F24)) / 12), 0) -> 0 | O24: =IF(AND($F24<=O$2, OR($G24="",$G24>=O$2)), $H24 * (1 + Assumptions!$C$7) ^ INT(((YEAR(O$2)-YEAR($F24))*12 + MONTH(O$2)-MONTH($F24)) / 12), 0) -> 0 | P24: =IF(AND($F24<=P$2, OR($G24="",$G24>=P$2)), $H24 * (1 + Assumptions!$C$7) ^ INT(((YEAR(P$2)-YEAR($F24))*12 + MONTH(P$2)-MONTH($F24)) / 12), 0) -> 0 | ... BP24: =IF(AND($F24<=BP$2, OR($G24="",$G24>=BP$2)), $H24 * (1 + Assumptions!$C$7) ^ INT(((YEAR(BP$2)-YEAR($F24))*12 + MONTH(BP$2)-MONTH($F24)) / 12), 0) -> 7581.6
