Workbook

Sheet Cover
B15: Financial Model
B19: Currency: EUR (€)
B21: STRICTLY CONFIDENTIAL

Sheet How to read me
B1: Tarnoc — How to Read This Model
B3: COLOR CODING
B4: Sample | C4: Assumptions are hardcoded inputs (sourced from documents)
B5: Sample | C5: Hardcoded historicalsis actual data from source documents
B6: Sample | C6: Formula cells are calculated, not hardcoded
B7: Sample | C7: Subtotal / total rows
B8: Sample | C8: Section headers / grand totals
B9: Sample | C9: Subsection headers
B10: Sample | C10: Margin / ratio rows (grey)
B11: Sample | C11: Balance sheet check rows (must = 0)
B14: FORMULA ARCHITECTURE
B15: Assumptions → Revenue Forecast, COGS, OPEX, CAPEX, Personnel (all drivers sourced here)
B16: Revenue Forecast → Financial Statements (revenue lines via cross-sheet links)
B17: COGS → Financial Statements (cost lines via cross-sheet links)
B18: OPEX → Financial Statements (opex lines via cross-sheet links)
B20: To change a number: ONLY edit cells in the Assumptions tab (yellow/orange).
B21: All other tabs will recalculate automatically.
B24: FURTHER EXPLANATIONS
B25: Subsidies: Tarnoc is and has been eligible for a number of subsidies. We will consider application for large projects, however this model excludes the forecast of any subsidy financing foing forward.
B26: Installation revenues: This is modelled fully as pass through revenue for now, as we plan to charge a customer exactly what we pay the installation partner for these services. This is subject to change in the future.
B27: Tarnoc's main products are the TTK (turbineketel), the Combi and Combi+ (turbineketel + outdoor unit), and the Twincycle (in development for 2027). Every unit contains a turbineketel; the Combi and Combi+ differ only by their outdoor unit and installation. We also plan to sell various add-ons such as performance booster units, boilers for hybrid setups, and sound reduction units.
B28: Service Revenues: Service revenues are calculated relative to installed base. We assume a certain percentage (see assumptions) of customers will purchase our Service package, and are charged annually.
... B30: Sales and Marketing costs are largely driven by permfomance marketing, and are calcualted on a volume and CPL basis. ]

Sheet Assumptions
B2: Drivers & Assumptions
B3: ASSUMPTIONS
B5: General Assumptions
B6: Opening Cash Balance (Jan 2024) | C6: 29538.9
B7: Annual salary increase (%) | C7: 0.08
B8: Employer cost basis | C8: Werkgeverlasten (incl. taxes)
B9: Holiday pay (%) | C9: 0.08
B10: Income tax rate | C10: 0.258
B12: Working Capital | H12: 20
B14: Days Sales Outstanding (DSO) | C14: days | D14: 20
B15: Days Payable Outstanding (DPO) | C15: days | D15: 45
B16: Days Inventory Outstanding (DIO) | C16: days | D16: 0
B17: Pre-payment | C17: %
B19: Revenue Build
B20: Units sold
C21: 2026 | D21: 2027 | E21: 2028 | F21: 2029 | G21: 2030
B22: TTK | C22: 0 | D22: 600 | E22: 2000 | F22: 4000 | G22: 8000
B23: Combi | C23: 0 | D23: 450 | E23: 1500 | F23: 3000 | G23: 6000
B24: Combi+ | C24: 0 | D24: 450 | E24: 1500 | F24: 3000 | G24: 6000
B25: Discounter | C25: 1 | D25: 1 | E25: 0.6
B27: Pricing
B28: PRICING — build-up (turbineketel + outdoor unit), ex VAT
B29: Turbineketel base price (all products) | C29: =10800/1.21 -> 8925.6198 | D29: Mgmt input — gross €10,800 incl VAT
B30: Outdoor unit — Combi | C30: =2725/1.21 -> 2252.0661 | D30: gross €2,725 incl VAT
B31: Outdoor unit — Combi+ | C31: =6425/1.21 -> 5309.9174 | D31: gross €6,425 incl VAT
B32: Combi price (ketel + ODU) | C32: =C29+C30 -> 11177.686 | D32: computed, ex VAT
B33: Combi+ price (ketel + ODU) | C33: =C29+C31 -> 14235.537 | D33: computed, ex VAT
B34: INSTALLATION (PASS-THROUGH; REV=COST)
B35: Installation — TTK | C35: =2800/1.21 -> 2314.0496 | D35: gross €2,800 incl VAT
B36: Installation — Combi | C36: =3800/1.21 -> 3140.4959 | D36: gross €3,800 incl VAT
B37: Installation — Combi+ | C37: =3800/1.21 -> 3140.4959 | D37: gross €3,800 incl VAT
B38: COGS
B39: TTK
B40: Bill of Materials TTK supplier 1
B41: # | C41: Category | D41: Component | E41: 1,000 units | F41: 5,000 units | G41: 10,000 units | H41: Unit | I41: Source
B42: B1 | C42: Supplier 1 | D42: Compressor + VFD | E42: 6314 | F42: 4500 | G42: 2692.44 | H42: €/unit | I42: Source: BOM data provided
B43: B2 | C43: Supplier 1 | D43: Heat exchangers (set) | E43: 805.5 | F43: =E43*0.7 -> 563.85 | G43: =0.6*F43 -> 338.31 | H43: €/unit | I43: Source: BOM data provided
B44: B3 | C44: Supplier 1 | D44: Electronics & Power Electronics | E44: 632.92 | F44: =E44*0.7 -> 443.044 | G44: =0.6*F44 -> 265.8264 | H44: €/unit | I44: Source: BOM data provided
B45: B4 | C45: Supplier 1 | D45: Hydraulic Components (Pumps, Valves, etc.) | E45: 283.76 | F45: =E45*0.7 -> 198.632 | G45: =0.6*F45 -> 119.1792 | H45: €/unit | I45: Source: BOM data provided
B46: B5 | C46: Supplier 1 | D46: Silencer & Insulation | E46: 118.48 | F46: =E46*0.7 -> 82.936 | G46: =0.6*F46 -> 49.7616 | H46: €/unit | I46: Source: BOM data provided
B47: B6 | C47: Supplier 1 | D47: Enclosure (Sheet Metal & Coating) | E47: 653.03 | F47: =E47*0.7 -> 457.121 | G47: =0.6*F47 -> 274.2726 | H47: €/unit | I47: Source: BOM data provided
B48: B7 | C48: Supplier 1 | D48: Other Components | E48: 300 | F48: =E48*0.7 -> 210 | G48: 126 | H48: €/unit | I48: Source: BOM data provided
B49: B8 | C49: Supplier 1 | D49: Assembly & Final Testing | E49: 200 | F49: =E49*0.7 -> 140 | G49: =0.6*F49 -> 84 | H49: €/unit | I49: Source: BOM data provided
B50: B9 | C50: Supplier 1 | D50: Packaging & Inbound Logistics | E50: 400 | F50: =E50*0.7 -> 280 | G50: =0.6*F50 -> 168 | H50: €/unit | I50: Source: BOM data provided
B51: B10 | C51: Supplier 1 | D51: Yield Loss & Warranty Provision (~3%) | E51: 291.23 | F51: =E51*0.7 -> 203.861 | G51: =0.6*F51 -> 122.3166 | H51: €/unit | I51: Source: BOM data provided
B52: B11 | C52: Contingency/risk | D52: Contingency & Risk Reserve | E52: 0 | F52: 0 | G52: 760 | H52: €/unit | I52: Source: No source, added for risk purposes
B53: B-T | C53: Supplier 1 total | D53: Total COGS / unit (BOM) | E53: =SUM(E42:E52) -> 9998.92 | F53: =SUM(F42:F52) -> 7079.444 | G53: =round(SUM(G42:G52),0) -> 5000 | H53: €/unit
B55: Bill of Materials TTK supplier 2
B56: D1 | C56: Supplier 2 | D56: Compressor + VFD | E56: 2568 | F56: 2311.2 | G56: 2080.08 | H56: €/unit | I56: Source: BOM data provided
B57: D2 | C57: Supplier 2 | D57: Heat exchangers (set) | E57: 805.5 | F57: =E57*0.7 -> 563.85 | G57: =F57*0.6 -> 338.31 | H57: €/unit | I57: Source: BOM data provided
B58: D3 | C58: Supplier 2 | D58: Elektronica & vermogenselektronica | E58: 257.92 | F58: =E58*0.7 -> 180.544 | G58: =F58*0.6 -> 108.3264 | H58: €/unit | I58: Source: BOM data provided
B59: D4 | C59: Supplier 2 | D59: Hydraulisch (pompen/kleppen/etc.) | E59: 283.76 | F59: =E59*0.7 -> 198.632 | G59: =F59*0.6 -> 119.1792 | H59: €/unit | I59: Source: BOM data provided
B60: D5 | C60: Supplier 2 | D60: Silencer + isolatie | E60: 118.48 | F60: =E60*0.7 -> 82.936 | G60: =F60*0.6 -> 49.7616 | H60: €/unit | I60: Source: BOM data provided
B61: D6 | C61: Supplier 2 | D61: Enclosure (plaatwerk, coating) | E61: 653.03 | F61: =E61*0.7 -> 457.121 | G61: =F61*0.6 -> 274.2726 | H61: €/unit | I61: Source: BOM data provided
B62: D7 | C62: Supplier 2 | D62: Everything Else | E62: 300 | F62: =E62*0.7 -> 210 | G62: =F62*0.6 -> 126 | H62: €/unit | I62: Source: BOM data provided
B63: D8 | C63: Supplier 2 | D63: Assemblage & eindtest | E63: 200 | F63: =E63*0.7 -> 140 | G63: =F63*0.6 -> 84 | H63: €/unit | I63: Source: BOM data provided
B64: D9 | C64: Supplier 2 | D64: Verpakking & logistiek inkomend | E64: 400 | F64: =E64*0.7 -> 280 | G64: =F64*0.6 -> 168 | H64: €/unit | I64: Source: BOM data provided
B65: D10 | C65: Supplier 2 | D65: Yield / garantie-reserve (~3%) | E65: 236.81 | F65: =E65*0.7 -> 165.767 | G65: =F65*0.6 -> 99.4602 | H65: €/unit | I65: Source: BOM data provided
C66: Supplier 2 total | D66: Total COGS / unit (BOM) | E66: =SUM(E56:E65) -> 5823.5 | F66: =SUM(F56:F65) -> 4590.05 | G66: =SUM(G56:G65) -> 3447.39
B68: TTK Volume tier breakpoints
B69: Min Units (≥) | C69: Cost / unit | D69: Unit | E69: Note
B70: 1000 | C70: =E53 -> 9998.92 | D70: €/unit | E70: Linked from BOM Total row above
B71: 5000 | C71: =F53 -> 7079.444 | D71: €/unit | E71: Linked from BOM Total row above
B72: 10000 | C72: =G53 -> 5000 | D72: €/unit | E72: Linked from BOM Total row above
B74: OUTDOOR UNIT COGS (Combi / Combi+) — volume tiers
B75: Component | E75: 1,000 units | F75: 5,000 units | G75: 10,000 units | H75: Unit | I75: Unit | J75: Source
B76: Outdoor unit — Combi | E76: 1178.36 | F76: 1060.52 | G76: 954.47 | H76: €/unit | I76: €/unit | J76: Source: BOM data
B77: Outdoor unit — Combi+ | E77: 1402.6 | F77: 1262.34 | G77: 1136.1 | H77: €/unit | I77: €/unit | J77: Source: BOM data
B78: Shipping (Combi & Combi+) | E78: 100 | F78: 100 | G78: 100 | H78: €/unit | I78: €/unit | J78: Source: BOM data
I79: €/unit | J79: Source: BOM data
B80: Outdoor Unit tier breakpoints (for COGS VLOOKUP) | I80: €/unit | J80: Source: BOM data provided
B81: Min Units (≥)
B82: 0 | C82: =E76 -> 1178.36 | E82: 0 | F82: =E77 -> 1402.6
B83: 5000 | C83: =F76 -> 1060.52 | E83: 5000 | F83: =F77 -> 1262.34
B84: 10000 | C84: =G76 -> 954.47 | E84: 10000 | F84: =G77 -> 1136.1
B90: Other operating expenditures | F90: Yearly increase: | G90: 0.3
C91: Category | D91: Note | E91: 2026 | F91: 2027 | G91: 2028 | H91: 2029 | I91: 2030
B92: Office rent (part of General) | C92: G&A | D92: ongoing | E92: 5000 | F92: =$E92*(1+$G$90) -> 6500 | G92: =F92*(1+$G$90) -> 8450 | H92: =G92*(1+$G$90) -> 10985 | I92: =H92*(1+$G$90) -> 14280.5
B93: Other General | C93: G&A | D93: ongoing | E93: 7000 | F93: =$E93*(1+$G$90) -> 9100 | G93: =F93*(1+$G$90) -> 11830 | H93: =G93*(1+$G$90) -> 15379 | I93: =H93*(1+$G$90) -> 19992.7
B94: Baseline Sales & Marketing | C94: S&M | D94: ongoing | E94: 14000 | F94: =$E94*(1+$G$90) -> 18200 | G94: =F94*(1+$G$90) -> 23660 | H94: =G94*(1+$G$90) -> 30758 | I94: =H94*(1+$G$90) -> 39985.4
B95: Finance & Legal etc. | C95: G&A | D95: ongoing | E95: 8000 | F95: =$E95*(1+$G$90) -> 10400 | G95: =F95*(1+$G$90) -> 13520 | H95: =G95*(1+$G$90) -> 17576 | I95: =H95*(1+$G$90) -> 22848.8
B96: Ongoing Development costs | C96: R&D | D96: ongoing | E96: 10000 | F96: =$E96*(1+$G$90) -> 13000 | G96: =F96*(1+$G$90) -> 16900 | H96: =G96*(1+$G$90) -> 21970 | I96: =H96*(1+$G$90) -> 28561
B97: Third party cost product development | C97: R&D | D97: ongoing | E97: 15000 | F97: =$E97*(1+$G$90) -> 19500 | G97: =F97*(1+$G$90) -> 25350 | H97: =G97*(1+$G$90) -> 32955 | I97: =H97*(1+$G$90) -> 42841.5
B98: Kicker Development Cost | C98: R&D | D98: one-off | E98: 168933
B99: Customer journey (third party) | C99: S&M | D99: one-off | E99: 10000
B100: Branding + Website (third party cost) | C100: S&M | D100: one-off | E100: 10000
B101: Assembly partner | C101: R&D | D101: one-off | E101: 100000
B102: Tooling Fisher (result: 2%-3%) | C102: R&D | D102: one-off | E102: 45000
B105: Assumptions for costs per unit sold (3rd parties or expenses (NO personell) | G105: Units sold | H105: S&M cost per unit | I105: Decrease | J105: Yearly costs
B106: Marketing spend per Customer | C106: S&M | D106: €80/lead with 20% closing rate | E106: 400 | F106: third party | G106: 0 | H106: 600
B107: Closing costs per customer | C107: S&M | D107: (Calls, viewing location, etc) | E107: 150 | F107: third party | G107: 400 | H107: =E110 -> 600 | J107: =G107*H107 -> 240000
B108: Aftersales and support | C108: S&M | E108: 50 | F108: third party | G108: =G107*2 -> 800 | H108: =H107*I108 -> 480 | I108: 0.8 | J108: =G108*H108 -> 384000
G109: =G108*2 -> 1600 | H109: =H108*I109 -> 384 | I109: 0.8 | J109: =G109*H109 -> 614400
B110: Cost per unit sold (cost down driven by volume) | C110: S&M | D110: costdown: S(n)=S(1)*n^-b, where b=0,2 | E110: =SUM(E106:E108) -> 600 | F110: S(1) | G110: =G109*2 -> 3200 | H110: =H109*I110 -> 307.2 | I110: 0.8 | J110: =G110*H110 -> 983040
G111: =G110*2 -> 6400 | H111: =H110*I111 -> 245.76 | I111: 0.8 | J111: =G111*H111 -> 1572864
G112: =G111*2 -> 12800 | H112: =H111*I112 -> 196.608 | I112: 0.8 | J112: =G112*H112 -> 2516582.4
G113: =G112*2 -> 25600 | H113: =H112*I113 -> 157.2864 | I113: 0.8 | J113: =G113*H113 -> 4026531.8
B115: Product | C115: Upsell item | D115: Type | E115: Attach % | F115: Unit rev. (EX VAT) | G115: Unit COGS | H115: Gross profit | I115: avg. Value | J115: avg. profit
B116: TTK / Combi / Combi+ | C116: Boiler variant 50 | D116: One-time | E116: 0.49 | F116: =200/1.21 -> 165.28926 | G116: 80 | H116: =F116-G116 -> 85.289256 | I116: =F116*E116 -> 80.991736 | J116: =H116*E116 -> 41.791736
B117: TTK / Combi / Combi+ | C117: Boiler variant 100 | D117: One-time | E117: 0.19 | F117: =400/1.21 -> 330.57851 | G117: 150 | H117: =F117-G117 -> 180.57851 | I117: =F117*E117 -> 62.809917 | J117: =H117*E117 -> 34.309917
...

Sheet Financial Statements
B1: Tarnoc B.V. — Financial Statements (€)
E2: 2025 | Q2: 2026 | AC2: 2027 | AO2: 2028
E3: 45658 | F3: 45689 | G3: 45717 | H3: 45748 | I3: 45778 | J3: 45809 | K3: 45839 | L3: 45870 | M3: 45901 | N3: 45931 | O3: 45962 | P3: 45992 | Q3: 46023 | R3: 46054 | S3: 46082 | T3: 46113 | U3: 46143 | V3: 46174 | W3: 46204 | X3: 46235 | Y3: 46266 | Z3: 46296 | AA3: 46327 | AB3: 46357 | AC3: 46388 | AD3: 46419 | AE3: 46447 | AF3: 46478 | AG3: 46508 | AH3: 46539 | AI3: 46569 | AJ3: 46600 | AK3: 46631 | AL3: 46661 | AM3: 46692 | AN3: 46722 | AO3: 46753 | AP3: 46784 | AQ3: 46813 | AR3: 46844 | AS3: 46874 | AT3: 46905 | AU3: 46935 | AV3: 46966 | AW3: 46997 | AX3: 47027 | AY3: 47058 | AZ3: 47088 | BB3: 2025 | BC3: 2026 | BD3: 2027 | BE3: 2028 | BF3: 2029
B5: PROFIT & LOSS STATEMENT
B6: Revenues
B7: TTK | D7: € | M7: ='Revenue Forecast'!M9 | N7: ='Revenue Forecast'!N9 | O7: ='Revenue Forecast'!O9 | P7: ='Revenue Forecast'!P9 | Q7: ='Revenue Forecast'!Q9 -> 0 | R7: ='Revenue Forecast'!R9 -> 0 | S7: ='Revenue Forecast'!S9 -> 0 | T7: ='Revenue Forecast'!T9 -> 0 | ... AZ7: ='Revenue Forecast'!AZ9 -> 2413699.2 | BB7: =sum(E7:P7) -> 0 | BC7: =sum(Q7:AB7) -> 0 | BD7: =sum(AC7:AN7) -> 6147390.1 | BE7: =sum(AO7:AZ7) -> 18366742 | BF7: ='Revenue Forecast'!BF9 -> 36733484
B8: Combi | D8: € | M8: ='Revenue Forecast'!M15 | N8: ='Revenue Forecast'!N15 | O8: ='Revenue Forecast'!O15 | P8: ='Revenue Forecast'!P15 | Q8: ='Revenue Forecast'!Q15 -> 0 | R8: ='Revenue Forecast'!R15 -> 0 | S8: ='Revenue Forecast'!S15 -> 0 | T8: ='Revenue Forecast'!T15 -> 0 | ... AZ8: ='Revenue Forecast'!AZ15 -> 2651491.3 | BB8: =sum(E8:P8) -> 0 | BC8: =sum(Q8:AB8) -> 0 | BD8: =sum(AC8:AN8) -> 4543745 | BE8: =sum(AO8:AZ8) -> 18210022 | BF8: ='Revenue Forecast'!BF15 -> 36420044
B9: Combi+ | Q9: ='Revenue Forecast'!Q21 -> 0 | R9: ='Revenue Forecast'!R21 -> 0 | S9: ='Revenue Forecast'!S21 -> 0 | T9: ='Revenue Forecast'!T21 -> 0 | U9: ='Revenue Forecast'!U21 -> 0 | V9: ='Revenue Forecast'!V21 -> 0 | W9: ='Revenue Forecast'!W21 -> 0 | X9: ='Revenue Forecast'!X21 -> 0 | ... AZ9: ='Revenue Forecast'!AZ21 -> 3345623.6 | BB9: ='Revenue Forecast'!BB21 -> 0 | BC9: ='Revenue Forecast'!BC21 -> 0 | BD9: ='Revenue Forecast'!BD21 -> 5733249.2 | BE9: ='Revenue Forecast'!BE21 -> 22977212 | BF9: ='Revenue Forecast'!BF21 -> 45954424
B10: Other | M10: ='Revenue Forecast'!M25+'Revenue Forecast'!M31 -> 0 | N10: ='Revenue Forecast'!N25+'Revenue Forecast'!N31 -> 0 | O10: ='Revenue Forecast'!O25+'Revenue Forecast'!O31 -> 0 | P10: ='Revenue Forecast'!P25+'Revenue Forecast'!P31 -> 0 | Q10: ='Revenue Forecast'!Q25+'Revenue Forecast'!Q31 -> 0 | R10: ='Revenue Forecast'!R25+'Revenue Forecast'!R31 -> 0 | S10: ='Revenue Forecast'!S25+'Revenue Forecast'!S31 -> 0 | T10: ='Revenue Forecast'!T25+'Revenue Forecast'!T31 -> 0 | ... AZ10: ='Revenue Forecast'!AZ25+'Revenue Forecast'!AZ31 -> 2080971.8 | BB10: =sum(E10:P10) -> 0 | BC10: =sum(Q10:AB10) -> 0 | BD10: =sum(AC10:AN10) -> 4050736.1 | BE10: =sum(AO10:AZ10) -> 14748059 | BF10: ='Revenue Forecast'!BF25+'Revenue Forecast'!BF31 -> 29944341
B11: Subsidies & grants | D11: € | M11: ='Revenue Forecast'!M35 -> 0 | N11: ='Revenue Forecast'!N35 -> 19480 | O11: ='Revenue Forecast'!O35 -> 78000 | P11: ='Revenue Forecast'!P35 -> 0 | Q11: ='Revenue Forecast'!Q35 -> 0 | R11: ='Revenue Forecast'!R35 -> 0 | S11: ='Revenue Forecast'!S35 -> 0 | T11: 0 | U11: ='Revenue Forecast'!U35 -> 0 | V11: 106782 | W11: ='Revenue Forecast'!W35 -> 0 | X11: ='Revenue Forecast'!X35 -> 0 | Y11: ='Revenue Forecast'!Y35 -> 0 | Z11: ='Revenue Forecast'!Z35 -> 0 | AA11: ='Revenue Forecast'!AA35 -> 0 | AB11: ='Revenue Forecast'!AB35 -> 0 | AC11: ='Revenue Forecast'!AC35 -> 0 | AD11: ='Revenue Forecast'!AD35 -> 0 | ... AZ11: ='Revenue Forecast'!AZ35 -> 0 | BB11: =sum(E11:P11) -> 97480 | BC11: =sum(Q11:AB11) -> 106782 | BD11: pm | BE11: pm | BF11: pm
B12: Total Revenue | D12: € | M12: ='Revenue Forecast'!M37 -> 0 | N12: ='Revenue Forecast'!N37 -> 19480 | O12: ='Revenue Forecast'!O37 -> 78000 | P12: ='Revenue Forecast'!P37 -> 0 | Q12: ='Revenue Forecast'!Q37 -> 0 | R12: ='Revenue Forecast'!R37 -> 0 | S12: ='Revenue Forecast'!S37 -> 0 | T12: ='Revenue Forecast'!T37 -> 0 | ... AZ12: ='Revenue Forecast'!AZ37 -> 10491786 | BB12: =sum(E12:P12) -> 97480 | BC12: =sum(Q12:AB12) -> 106782 | BD12: =sum(AC12:AN12) -> 20475120 | BE12: =sum(AO12:AZ12) -> 74302035 | BF12: =sum(BF7:BF11) -> 1.4905229e+08
B14: Cost of goods sold
B15: TTK | D15: € | E15: =COGS!E9 | F15: =COGS!F9 | G15: =COGS!G9 | H15: =COGS!H9 | I15: =COGS!I9 | J15: =COGS!J9 | K15: =COGS!K9 | L15: =COGS!L9 | ... AZ15: =COGS!AZ9 -> 1868094.5 | BB15: =sum(E15:P15) -> 0 | BC15: =sum(Q15:AB15) -> 0 | BD15: =sum(AC15:AN15) -> 4757803.1 | BE15: =sum(AO15:AZ15) -> 14215031 | BF15: =COGS!BF9 -> 20328549
B16: Combi | D16: € | E16: =COGS!E14 | F16: =COGS!F14 | G16: =COGS!G14 | H16: =COGS!H14 | I16: =COGS!I14 | J16: =COGS!J14 | K16: =COGS!K14 | L16: =COGS!L14 | ... AZ16: =COGS!AZ14 -> 1946662.1 | BB16: =sum(E16:P16) -> 0 | BC16: =sum(Q16:AB16) -> 0 | BD16: =sum(AC16:AN16) -> 3335910 | BE16: =sum(AO16:AZ16) -> 13369367 | BF16: =COGS!BF14 -> 19556938
B17: Combi+ | Q17: =COGS!Q19 -> 0 | R17: =COGS!R19 -> 0 | S17: =COGS!S19 -> 0 | T17: =COGS!T19 -> 0 | U17: =COGS!U19 -> 0 | V17: =COGS!V19 -> 0 | W17: =COGS!W19 -> 0 | X17: =COGS!X19 -> 0 | ... AZ17: =COGS!AZ19 -> 1997564.6 | BB17: =COGS!BB19 | BC17: =COGS!BC19 -> 0 | BD17: =COGS!BD19 -> 3423139.3 | BE17: =COGS!BE19 -> 13718957 | BF17: =COGS!BF19 -> 20123260
B18: Other | E18: =COGS!E22 | F18: =COGS!F22 | G18: =COGS!G22 | H18: =COGS!H22 | I18: =COGS!I22 | J18: =COGS!J22 | K18: =COGS!K22 | L18: =COGS!L22 | ... P18: =COGS!P22 | Q18: =COGS!Q22+COGS!Q27 -> 0 | R18: =COGS!R22+COGS!R27 -> 0 | S18: =COGS!S22+COGS!S27 -> 0 | T18: =COGS!T22+COGS!T27 -> 0 | U18: =COGS!U22+COGS!U27 -> 0 | V18: =COGS!V22+COGS!V27 -> 0 | W18: =COGS!W22+COGS!W27 -> 0 | X18: =COGS!X22+COGS!X27 -> 0 | ... AZ18: =COGS!AZ22+COGS!AZ27 -> 2047119.8 | BB18: =sum(E18:P18) -> 0 | BC18: =sum(Q18:AB18) -> 0 | BD18: =sum(AC18:AN18) -> 3997540.1 | BE18: =sum(AO18:AZ18) -> 14506408 | BF18: =COGS!BF22 -> 28599669
B19: Total COGS | D19: € | M19: =COGS!M29 -> 0 | N19: =COGS!N29 -> 0 | O19: =COGS!O29 -> 0 | P19: =COGS!P29 -> 0 | Q19: =COGS!Q29 -> 0 | R19: =COGS!R29 -> 0 | S19: =COGS!S29 -> 0 | T19: =COGS!T29 -> 0 | ... AZ19: =COGS!AZ29 -> 7859441 | BB19: =sum(E19:P19) -> 0 | BC19: =sum(Q19:AB19) -> 0 | BD19: =sum(AC19:AN19) -> 15514392 | BE19: =sum(AO19:AZ19) -> 55809762 | BF19: =sum(BF15:BF18) -> 88608416
B21: Gross Profit | M21: =M12-M19 -> 0 | N21: =N12-N19 -> 19480 | O21: =O12-O19 -> 78000 | P21: =P12-P19 -> 0 | Q21: =Q12-Q19 -> 0 | R21: =R12-R19 -> 0 | S21: =S12-S19 -> 0 | T21: =T12-T19 -> 0 | ... AZ21: =AZ12-AZ19 -> 2632344.9 | BB21: =sum(E21:P21) -> 97480 | BC21: =sum(Q21:AB21) -> 106782 | BD21: =sum(AC21:AN21) -> 4960727.9 | BE21: =sum(AO21:AZ21) -> 18492272 | BF21: =BF12-BF19 -> 60443877
B22: Gross margin % | D22: % | BE22: =BE21/BE12 -> 0.24887976 | BF22: =BF21/BF12 -> 0.40552128
B24: Operational expenses
B25: R&D | D25: € | M25: =OPEX!O38 -> 47500 | N25: =OPEX!P38 -> 47500 | O25: =OPEX!Q38 -> 47500 | P25: =OPEX!R38 -> 216433 | Q25: =OPEX!S38 -> 75700 | R25: =OPEX!T38 -> 75700 | S25: =OPEX!U38 -> 75700 | T25: =OPEX!V38 -> 75700 | ... AZ25: =OPEX!BB38 -> 152614.77 | BB25: =sum(E25:P25) -> 358933 | BC25: =sum(Q25:AB25) -> 1150160 | BD25: =sum(AC25:AN25) -> 1576575.2 | BE25: =sum(AO25:AZ25) -> 1821001.2 | BF25: =OPEX!BH38 -> 3056754.8
B26: S&M | D26: € | M26: =OPEX!O39 -> 0 | N26: =OPEX!P39 -> 0 | O26: =OPEX!Q39 -> 0 | P26: =OPEX!R39 -> 20000 | Q26: =OPEX!S39 -> 21000 | R26: =OPEX!T39 -> 31800 | S26: =OPEX!U39 -> 31800 | T26: =OPEX!V39 -> 31800 | ... AZ26: =OPEX!BB39 -> 195538.4 | BB26: =sum(E26:P26) -> 20000 | BC26: =sum(Q26:AB26) -> 464300 | BD26: =sum(AC26:AN26) -> 1115088 | BE26: =sum(AO26:AZ26) -> 2046330.7 | BF26: =OPEX!BH39 -> 3286395.4
B27: G&A | D27: € | M27: =OPEX!O40 -> 11500 | N27: =OPEX!P40 -> 11500 | O27: =OPEX!Q40 -> 11500 | P27: =OPEX!R40 -> 11500 | Q27: =OPEX!S40 -> 31820 | R27: =OPEX!T40 -> 31820 | S27: =OPEX!U40 -> 31820 | T27: =OPEX!V40 -> 31820 | ... AZ27: =OPEX!BB40 -> 89245.088 | BB27: =sum(E27:P27) -> 46000 | BC27: =sum(Q27:AB27) -> 462060 | BD27: =sum(AC27:AN27) -> 832843.2 | BE27: =sum(AO27:AZ27) -> 1050610.7 | BF27: =OPEX!BH40 -> 1307705.9
B28: Total OPEX | D28: € | M28: =(M27+M26+M25) -> 59000 | N28: =(N27+N26+N25) -> 59000 | O28: =(O27+O26+O25) -> 59000 | P28: =(P27+P26+P25) -> 247933 | Q28: =(Q27+Q26+Q25) -> 128520 | R28: =(R27+R26+R25) -> 139320 | S28: =(S27+S26+S25) -> 139320 | T28: =(T27+T26+T25) -> 139320 | ... AZ28: =(AZ27+AZ26+AZ25) -> 437398.26 | BB28: =sum(E28:P28) -> 424933 | BC28: =sum(Q28:AB28) -> 2076520 | BD28: =sum(AC28:AN28) -> 3524506.4 | BE28: =sum(AO28:AZ28) -> 4917942.6 | BF28: =sum(BF25:BF27) -> 7650856.1
B30: EBITDA | D30: € | M30: =M21-M28 -> -59000 | N30: =N21-N28 -> -39520 | O30: =O21-O28 -> 19000 | P30: =P21-P28 -> -247933 | Q30: =Q21-Q28 -> -128520 | R30: =R21-R28 -> -139320 | S30: =S21-S28 -> -139320 | T30: =T21-T28 -> -139320 | ... AZ30: =AZ21-AZ28 -> 2194946.6 | BB30: =sum(E30:P30) -> -327453 | BC30: =sum(Q30:AB30) -> -1969738 | BD30: =sum(AC30:AN30) -> 1436221.5 | BE30: =sum(AO30:AZ30) -> 13574330 | BF30: =BF21-BF28 -> 52793021
B31: EBITDA margin % | D31: % | BE31: =BE30/BE12 -> 0.18269123 | BF31: =BF30/BF12 -> 0.35419127
B33: Depreciation & Amortisation | D33: € | M33: 0 | N33: 0 | O33: 0 | P33: 0 | Q33: 0 | R33: 0 | S33: 0 | T33: 0 | U33: 0 | V33: 0 | W33: 0 | X33: 0 | Y33: 0 | Z33: 0 | AA33: 0 | AB33: 0 | AC33: 0 | AD33: 0 | AE33: 0 | AF33: 0 | AG33: 0 | AH33: 0 | AI33: 0 | AJ33: 0 | AK33: 0 | AL33: 0 | AM33: 0 | AN33: 0 | AO33: 0 | AP33: 0 | AQ33: 0 | AR33: 0 | AS33: 0 | AT33: 0 | AU33: 0 | AV33: 0 | AW33: 0 | AX33: 0 | AY33: 0 | AZ33: 0 | BB33: =sum(E33:P33) -> 0 | BC33: =sum(Q33:AB33) -> 0 | BD33: =sum(AC33:AN33) -> 0 | BE33: =sum(AO33:AZ33) -> 0 | BF33: 0
B34: Interst payments | D34: € | M34: 0 | N34: 0 | O34: 0 | P34: 0 | Q34: =P80*0.05/12 -> 0 | R34: =Q80*0.05/12 -> 0 | S34: =R80*0.05/12 -> 0 | T34: =S80*0.05/12 -> 0 | U34: =T80*0.05/12 -> 0 | V34: =U80*0.05/12 -> 0 | W34: =V80*0.05/12 -> 0 | X34: =W80*0.05/12 -> 0 | ... AZ34: =AY80*0.05/12 -> 2975 | BB34: =sum(E34:P34) -> 0 | BC34: =sum(Q34:AB34) -> 0 | BD34: =sum(AC34:AN34) -> 17382.925 | BE34: =sum(AO34:AZ34) -> 35700 | BF34: =BE80*0.05/12 -> 2975
B35: EBT | D35: € | M35: =M30-sum(M33:M34) -> -59000 | N35: =N30-sum(N33:N34) -> -39520 | O35: =O30-sum(O33:O34) -> 19000 | P35: =P30-sum(P33:P34) -> -247933 | Q35: =Q30-sum(Q33:Q34) -> -128520 | R35: =R30-sum(R33:R34) -> -139320 | S35: =S30-sum(S33:S34) -> -139320 | T35: =T30-sum(T33:T34) -> -139320 | ... AZ35: =AZ30-sum(AZ33:AZ34) -> 2191971.6 | BB35: =sum(E35:P35) -> -327453 | BC35: =sum(Q35:AB35) -> -1969738 | BD35: =sum(AC35:AN35) -> 1418838.6 | BE35: =sum(AO35:AZ35) -> 13538630 | BF35: =BF30-sum(BF33:BF34) -> 52790046
BE36: =BE35/BE12 -> 0.18221076 | BF36: =BF35/BF12 -> 0.35417131
B38: Income tax | D38: € | M38: 0 | N38: 0 | O38: 0 | P38: 0 | Q38: 0 | R38: 0 | S38: 0 | T38: 0 | U38: 0 | V38: 0 | W38: 0 | X38: 0 | Y38: 0 | Z38: 0 | AA38: 0 | AB38: 0 | AC38: 0 | AD38: 0 | AE38: 0 | AF38: 0 | AG38: 0 | AH38: 0 | AI38: 0 | AJ38: 0 | AK38: 0 | AL38: 0 | AM38: 0 | AN38: 0 | AO38: 0 | AP38: 0 | AQ38: 0 | AR38: 0 | AS38: 0 | AT38: 0 | AU38: 0 | AV38: 0 | AW38: 0 | AX38: 0 | AY38: 0 | AZ38: 0 | BB38: =sum(E38:P38) -> 0 | BC38: =sum(Q38:AB38) -> 0 | BD38: =sum(AC38:AN38) -> 0 | BE38: =sum(AO38:AZ38) -> 0 | BF38: =(BF35-AZ42)*Assumptions!$C$10 -> 14438552
B39: NET INCOME | D39: € | M39: =M35-M38 -> -59000 | N39: =N35-N38 -> -39520 | O39: =O35-O38 -> 19000 | P39: =P35-P38 -> -247933 | Q39: =Q35-Q38 -> -128520 | R39: =R35-R38 -> -139320 | S39: =S35-S38 -> -139320 | T39: =T35-T38 -> -139320 | ... AZ39: =AZ35-AZ38 -> 2191971.6 | BB39: =sum(E39:P39) -> -327453 | BC39: =sum(Q39:AB39) -> -1969738 | BD39: =sum(AC39:AN39) -> 1418838.6 | BE39: =sum(AO39:AZ39) -> 13538630 | BF39: =BF35-BF38 -> 38351494
B40: Profit margin % | BE40: =BE39/BE12 -> 0.18221076 | BF40: =BF39/BF12 -> 0.25730227
B42: Tax carry over to be applied | M42: 108239 | N42: =M42+(-N39*Assumptions!$C$10) -> 118435.16 | O42: =N42+(-O39*Assumptions!$C$10) -> 113533.16 | P42: =O42+(-P39*Assumptions!$C$10) -> 177499.87 | Q42: =P42+(-Q39*Assumptions!$C$10) -> 210658.03 | R42: =Q42+(-R39*Assumptions!$C$10) -> 246602.59 | S42: =R42+(-S39*Assumptions!$C$10) -> 282547.15 | T42: =S42+(-T39*Assumptions!$C$10) -> 318491.71 | U42: =T42+(-U39*Assumptions!$C$10) -> 357016.27 | ... AZ42: =AY42+(-AZ39*Assumptions!$C$10) -> -3173334.6
B44: CASH FLOW STATEMENT
B45: Net income | D45: € | M45: =M39 -> -59000 | N45: =N39 -> -39520 | O45: =O39 -> 19000 | P45: =P39 -> -247933 | Q45: =Q39 -> -128520 | R45: =R39 -> -139320 | S45: =S39 -> -139320 | T45: =T39 -> -139320 | ... AZ45: =AZ39 -> 2191971.6 | BB45: =sum(E45:P45) -> -327453 | BC45: =sum(Q45:AB45) -> -1969738 | BD45: =sum(AC45:AN45) -> 1418838.6 | BE45: =sum(AO45:AZ45) -> 13538630 | BF45: =BF39 -> 38351494
B46: Depreciation & amortisation | D46: € | M46: 0 | N46: 0 | O46: 0 | P46: 0 | Q46: 0 | R46: 0 | S46: 0 | T46: 0 | U46: 0 | V46: 0 | W46: 0 | X46: 0 | Y46: 0 | Z46: 0 | AA46: 0 | AB46: 0 | AC46: 0 | AD46: 0 | AE46: 0 | AF46: 0 | AG46: 0 | AH46: 0 | AI46: 0 | AJ46: 0 | AK46: 0 | AL46: 0 | AM46: 0 | AN46: 0 | AO46: 0 | AP46: 0 | AQ46: 0 | AR46: 0 | AS46: 0 | AT46: 0 | AU46: 0 | AV46: 0 | AW46: 0 | AX46: 0 | AY46: 0 | AZ46: 0 | BB46: =sum(E46:P46) -> 0 | BC46: =sum(Q46:AB46) -> 0 | BD46: =sum(AC46:AN46) -> 0 | BE46: =sum(AO46:AZ46) -> 0 | BF46: =BF33 -> 0
B47: Increase in accounts receivable (delta DSO) | D47: € | M47: 0 | N47: =-(N66-M66) -> -12986.667 | O47: =-(O66-N66) -> -39013.333 | P47: =-(P66-O66) -> 52000 | Q47: =-(Q66-P66) -> 0 | R47: =-(R66-Q66) -> 0 | S47: =-(S66-R66) -> 0 | T47: =-(T66-S66) -> 0 | U47: =-(U66-T66) -> 0 | ... AZ47: =-(AZ66-AY66) -> -729422.62 | BB47: =sum(E47:P47) -> 0 | BC47: =sum(Q47:AB47) -> 0 | BD47: =sum(AC47:AN47) -> -1925040.2 | BE47: =sum(AO47:AZ47) -> -5069483.7 | BF47: =-(BF66-BE66) -> -1172725
B48: Increase in accounts payable (delta DPO) | D48: € | M48: 0 | N48: =(N75-M75) -> 0 | O48: =(O75-N75) -> 0 | P48: =(P75-O75) -> 0 | Q48: =(Q75-P75) -> 0 | R48: =(R75-Q75) -> 0 | S48: =(S75-R75) -> 0 | T48: =(T75-S75) -> 0 | U48: =(U75-T75) -> 0 | ... AZ48: =(AZ75-AY75) -> 1223237.6 | BB48: =sum(E48:P48) -> 0 | BC48: =sum(Q48:AB48) -> 0 | BD48: =sum(AC48:AN48) -> 3272022.5 | BE48: =sum(AO48:AZ48) -> 8517139 | BF48: =BF75-BE75 -> -864836.17
B49: Change in inventory (delta DIO) | D49: € | M49: 0 | N49: =-(N67-M67) -> 0 | O49: =-(O67-N67) -> 0 | P49: =-(P67-O67) -> 0 | Q49: =-(Q67-P67) -> 0 | R49: =-(R67-Q67) -> 0 | S49: =-(S67-R67) -> 0 | T49: =-(T67-S67) -> 0 | U49: =-(U67-T67) -> 0 | ... AZ49: =-(AZ67-AY67) -> 0 | BB49: =sum(E49:P49) -> 0 | BC49: =sum(Q49:AB49) -> 0 | BD49: =sum(AC49:AN49) -> 0 | BE49: =sum(AO49:AZ49) -> 0 | BF49: 0
B50: Cash from Operations | D50: € | M50: =sum(M45:M49) -> -59000 | N50: =sum(N45:N49) -> -52506.667 | O50: =sum(O45:O49) -> -20013.333 | P50: =sum(P45:P49) -> -195933 | Q50: =sum(Q45:Q49) -> -128520 | R50: =sum(R45:R49) -> -139320 | S50: =sum(S45:S49) -> -139320 | T50: =sum(T45:T49) -> -139320 | ... AZ50: =sum(AZ45:AZ49) -> 2685786.6 | BB50: =sum(E50:P50) -> -327453 | BC50: =sum(Q50:AB50) -> -1969738 | BD50: =sum(AC50:AN50) -> 2765820.9 | BE50: =sum(AO50:AZ50) -> 16986285 | BF50: =sum(BF45:BF49) -> 36313933
B51: CAPEX | D51: € | M51: 0 | N51: 0 | O51: 0 | P51: 0 | Q51: 0 | R51: 0 | S51: 0 | T51: 0 | U51: 0 | V51: 0 | W51: 0 | X51: 0 | Y51: 0 | Z51: 0 | AA51: 0 | AB51: 0 | AC51: 0 | AD51: 0 | AE51: 0 | AF51: 0 | AG51: 0 | AH51: 0 | AI51: 0 | AJ51: 0 | AK51: 0 | AL51: 0 | AM51: 0 | AN51: 0 | AO51: 0 | AP51: 0 | AQ51: 0 | AR51: 0 | AS51: 0 | AT51: 0 | AU51: 0 | AV51: 0 | AW51: 0 | AX51: 0 | AY51: 0 | AZ51: 0 | BB51: =sum(E51:P51) -> 0 | BC51: =sum(Q51:AB51) -> 0 | BD51: =sum(AC51:AN51) -> 0 | BE51: =sum(AO51:AZ51) -> 0 | BF51: 0
B52: Cash from Investing | M52: =M51 -> 0 | N52: =N51 -> 0 | O52: =O51 -> 0 | P52: =P51 -> 0 | Q52: =Q51 -> 0 | R52: =R51 -> 0 | S52: =S51 -> 0 | T52: =T51 -> 0 | ... AZ52: =AZ51 -> 0 | BB52: =sum(E52:P52) -> 0 | BC52: =sum(Q52:AB52) -> 0 | BD52: =sum(AC52:AN52) -> 0 | BE52: =sum(AO52:AZ52) -> 0 | BF52: =BF51 -> 0
B53: Equity injection | D53: € | S53: 0 | U53: 300000 | Z53: 3250000 | BB53: =sum(E53:P53) -> 0 | BC53: =sum(Q53:AB53) -> 3550000 | BD53: =sum(AC53:AN53) -> 0 | BE53: =sum(AO53:AZ53) -> 0 | BF53: 0
B54: Loan (CLA) | D54: € | V54: 300000 | BB54: =sum(E54:P54) -> 0 | BC54: =sum(Q54:AB54) -> 300000 | BD54: =sum(AC54:AN54) -> 0 | BE54: =sum(AO54:AZ54) -> 0 | BF54: 0
B55: Compressor WC loan (draw / repay) | E55: =E80 -> 0 | F55: =F80-E80 -> 0 | G55: =G80-F80 -> 0 | H55: =H80-G80 -> 0 | I55: =I80-H80 -> 0 | J55: =J80-I80 -> 0 | K55: =K80-J80 -> 0 | L55: =L80-K80 -> 0 | M55: =M80-L80 -> 0 | ... AZ55: =AZ80-AY80 -> 0 | BC55: =SUM(Q55:AB55) -> 0 | BD55: =SUM(AC55:AN55) -> 714000 | BE55: =SUM(AO55:AZ55) -> 0 | BF55: =BF80-BE80 -> -714000
B56: Cash from Financing | D56: € | E56: =E53+E54+E55 -> 0 | F56: =F53+F54+F55 -> 0 | G56: =G53+G54+G55 -> 0 | H56: =H53+H54+H55 -> 0 | I56: =I53+I54+I55 -> 0 | J56: =J53+J54+J55 -> 0 | K56: =K53+K54+K55 -> 0 | L56: =L53+L54+L55 -> 0 | ... AZ56: =AZ53+AZ54+AZ55 -> 0 | BB56: =sum(E56:P56) -> 0 | BC56: =sum(Q56:AB56) -> 3850000 | BD56: =sum(AC56:AN56) -> 714000 | BE56: =sum(AO56:AZ56) -> 0 | BF56: =BF53+BF54+BF55 -> -714000
B58: Total Change in Cash | D58: € | M58: =M50+M52+M56 -> -59000 | N58: =N50+N52+N56 -> -52506.667 | O58: =O50+O52+O56 -> -20013.333 | P58: =P50+P52+P56 -> -195933 | Q58: =Q50+Q52+Q56 -> -128520 | R58: =R50+R52+R56 -> -139320 | S58: =S50+S52+S56 -> -139320 | T58: =T50+T52+T56 -> -139320 | ... AZ58: =AZ50+AZ52+AZ56 -> 2685786.6 | BB58: =BB56+BB52+BB50 -> -327453 | BC58: =BC56+BC52+BC50 -> 1880262 | BD58: =BD56+BD52+BD50 -> 3479820.9 | BE58: =BE56+BE52+BE50 -> 16986285 | BF58: =BF56+BF52+BF50 -> 35599933
B59: Beginning cash balance | D59: € | M59: 1111108 | N59: =M60 -> 1052108 | O59: =N60 -> 999601.33 | P59: =O60 -> 979588 | Q59: =P60 -> 783655 | R59: =Q60 -> 655135 | S59: =R60 -> 515815 | T59: =S60 -> 376495 | U59: =T60 -> 237175 | ... AZ59: =AY60 -> 20444236 | BB59: =BB58+BB60 -> 456202 | BC59: =Q59 -> 783655 | BD59: =AC59 -> 2663917 | BE59: =AO59 -> 6143737.9 | BF59: =AZ60 -> 23130023
B60: Ending Cash Balance | D60: € | M60: =M58+M59 -> 1052108 | N60: =N59+N58 -> 999601.33 | O60: =O59+O58 -> 979588 | P60: =P59+P58 -> 783655 | Q60: =Q59+Q58 -> 655135 | R60: =R59+R58 -> 515815 | S60: =S59+S58 -> 376495 | T60: =T59+T58 -> 237175 | U60: =U59+U58 -> 387855 | ... AZ60: =AZ59+AZ58 -> 23130023 | BB60: =P60 -> 783655 | BC60: =BC58+BC59 -> 2663917 | BD60: =BD58+BD59 -> 6143737.9 | BE60: =BE58+BE59 -> 23130023 | BF60: =BF58+BF59 -> 58729956
B62: BALANCE SHEET
B63: ASSETS
B64: Cash and cash equivalents | D64: € | M64: =M60 -> 1052108 | N64: =N60 -> 999601.33 | O64: =O60 -> 979588 | P64: =P60 -> 783655 | Q64: =Q60 -> 655135 | R64: =R60 -> 515815 | S64: =S60 -> 376495 | T64: =T60 -> 237175 | ... AZ64: =AZ60 -> 23130023 | BB64: =P64 -> 783655 | BC64: =AB64 -> 2663917 | BD64: =AN64 -> 6143737.9 | BE64: =AZ64 -> 23130023 | BF64: =BF60 -> 58729956
B65: Deferred tax assest ("carry forward") | D65: € | M65: =M42 -> 108239 | N65: =N42 -> 118435.16 | O65: =O42 -> 113533.16 | P65: =P42 -> 177499.87 | Q65: =Q42 -> 210658.03 | R65: =R42 -> 246602.59 | S65: =S42 -> 282547.15 | T65: =T42 -> 318491.71 | ... AZ65: =AZ42 -> -3173334.6 | BB65: =P65 -> 177499.87 | BC65: =AB65 -> 685692.28 | BD65: =AN65 -> 319631.92 | BE65: =AZ65 -> -3173334.6 | BF65: 0
B66: Accounts receivable (DSO-based) | D66: € | M66: =ABS(Assumptions!$D$14*(M12/30)) -> 0 | N66: =ABS(Assumptions!$D$14*(N12/30)) -> 12986.667 | O66: =ABS(Assumptions!$D$14*(O12/30)) -> 52000 | P66: =ABS(Assumptions!$D$14*(P12/30)) -> 0 | Q66: =ABS(Assumptions!$D$14*(Q12/30)) -> 0 | R66: =ABS(Assumptions!$D$14*(R12/30)) -> 0 | S66: =ABS(Assumptions!$D$14*(S12/30)) -> 0 | T66: =ABS(Assumptions!$D$14*(T12/30)) -> 0 | ... AZ66: =ABS(Assumptions!$D$14*(AZ12/30)) -> 6994523.9 | BB66: =P66 -> 0 | BC66: =AB66 -> 0 | BD66: =AN66 -> 1925040.2 | BE66: =AZ66 -> 6994523.9 | BF66: =Assumptions!$D$14/365*BF12 -> 8167249
B67: Inventory (DIO-based) | D67: € | M67: =ABS(Assumptions!$D$16*(M19/30)) -> 0 | N67: =ABS(Assumptions!$D$16*(N19/30)) -> 0 | O67: =ABS(Assumptions!$D$16*(O19/30)) -> 0 | P67: =ABS(Assumptions!$D$16*(P19/30)) -> 0 | Q67: =ABS(Assumptions!$D$16*(Q19/30)) -> 0 | R67: =ABS(Assumptions!$D$16*(R19/30)) -> 0 | S67: =ABS(Assumptions!$D$16*(S19/30)) -> 0 | T67: =ABS(Assumptions!$D$16*(T19/30)) -> 0 | ... AZ67: =ABS(Assumptions!$D$16*(AZ19/30)) -> 0 | BB67: =P67 -> 0 | BC67: =AB67 -> 0 | BD67: =AN67 -> 0 | BE67: =AZ67 -> 0 | BF67: 0
B68: Total Current Assets | D68: € | M68: =sum(M64:M67) -> 1160347 | N68: =sum(N64:N67) -> 1131023.2 | O68: =sum(O64:O67) -> 1145121.2 | P68: =sum(P64:P67) -> 961154.87 | Q68: =sum(Q64:Q67) -> 865793.03 | R68: =sum(R64:R67) -> 762417.59 | S68: =sum(S64:S67) -> 659042.15 | T68: =sum(T64:T67) -> 555666.71 | ... AZ68: =sum(AZ64:AZ67) -> 26951212 | BB68: =P68 -> 961154.87 | BC68: =AB68 -> 3349609.3 | BD68: =AN68 -> 8388410 | BE68: =AZ68 -> 26951212 | BF68: =BF64+BF66+BF67 -> 66897205
B70: Net PP&E | D70: € | M70: 0 | N70: 0 | O70: 0 | P70: 0 | Q70: 0 | R70: 0 | S70: 0 | T70: 0 | U70: 0 | V70: 0 | W70: 0 | X70: 0 | Y70: 0 | Z70: 0 | AA70: 0 | AB70: 0 | AC70: 0 | AD70: 0 | AE70: 0 | AF70: 0 | AG70: 0 | AH70: 0 | AI70: 0 | AJ70: 0 | AK70: 0 | AL70: 0 | AM70: 0 | AN70: 0 | AO70: 0 | AP70: 0 | AQ70: 0 | AR70: 0 | AS70: 0 | AT70: 0 | AU70: 0 | AV70: 0 | AW70: 0 | AX70: 0 | AY70: 0 | AZ70: 0 | BB70: =P70 -> 0 | BC70: =AB70 -> 0 | BD70: =AN70 -> 0 | BE70: =AZ70 -> 0 | BF70: 0
B71: Total Fixed Assets | D71: € | M71: =M70 -> 0 | N71: =N70 -> 0 | O71: =O70 -> 0 | P71: =P70 -> 0 | Q71: =Q70 -> 0 | R71: =R70 -> 0 | S71: =S70 -> 0 | T71: =T70 -> 0 | ... AZ71: =AZ70 -> 0 | BB71: =P71 -> 0 | BC71: =AB71 -> 0 | BD71: =AN71 -> 0 | BE71: =AZ71 -> 0 | BF71: =BF70 -> 0
B72: TOTAL ASSETS | D72: € | M72: =M68+M71 -> 1160347 | N72: =N68+N71 -> 1131023.2 | O72: =O68+O71 -> 1145121.2 | P72: =P68+P71 -> 961154.87 | Q72: =Q68+Q71 -> 865793.03 | R72: =R68+R71 -> 762417.59 | S72: =S68+S71 -> 659042.15 | T72: =T68+T71 -> 555666.71 | ... AZ72: =AZ68+AZ71 -> 26951212 | BB72: =P72 -> 961154.87 | BC72: =AB72 -> 3349609.3 | BD72: =AN72 -> 8388410 | BE72: =AZ72 -> 26951212 | BF72: =BF68+BF71 -> 66897205
B74: EQUITY & LIABILITIES
B75: Accounts payable (DPO-based) | D75: € | M75: =ABS(Assumptions!$D$15*(M19/30)) -> 0 | N75: =ABS(Assumptions!$D$15*(N19/30)) -> 0 | O75: =ABS(Assumptions!$D$15*(O19/30)) -> 0 | P75: =ABS(Assumptions!$D$15*(P19/30)) -> 0 | Q75: =ABS(Assumptions!$D$15*(Q19/30)) -> 0 | R75: =ABS(Assumptions!$D$15*(R19/30)) -> 0 | S75: =ABS(Assumptions!$D$15*(S19/30)) -> 0 | T75: =ABS(Assumptions!$D$15*(T19/30)) -> 0 | ... AZ75: =ABS(Assumptions!$D$15*(AZ19/30)) -> 11789161 | BB75: =P75 -> 0 | BC75: =AB75 -> 0 | BD75: =AN75 -> 3272022.5 | BE75: =AZ75 -> 11789161 | BF75: =Assumptions!$D$15/365*BF19 -> 10924325
B76: Total Current Liabilities | D76: € | M76: =sum(M75) -> 0 | N76: =sum(N75) -> 0 | O76: =sum(O75) -> 0 | P76: =sum(P75) -> 0 | Q76: =sum(Q75) -> 0 | R76: =sum(R75) -> 0 | S76: =sum(S75) -> 0 | T76: =sum(T75) -> 0 | ... AZ76: =sum(AZ75) -> 11789161 | BB76: =P76 -> 0 | BC76: =AB76 -> 0 | BD76: =AN76 -> 3272022.5 | BE76: =AZ76 -> 11789161 | BF76: =BF75 -> 10924325
B78: Innovation loan outstanding | D78: € | M78: 0 | N78: 0 | O78: 0 | P78: 0 | Q78: 0 | R78: 0 | S78: 0 | T78: 0 | U78: 0 | V78: 0 | W78: 0 | X78: 0 | Y78: 0 | Z78: 0 | AA78: 0 | AB78: 0 | AC78: 0 | AD78: 0 | AE78: 0 | AF78: 0 | AG78: 0 | AH78: 0 | AI78: 0 | AJ78: 0 | AK78: 0 | AL78: 0 | AM78: 0 | AN78: 0 | AO78: 0 | AP78: 0 | AQ78: 0 | AR78: 0 | AS78: 0 | AT78: 0 | AU78: 0 | AV78: 0 | AW78: 0 | AX78: 0 | AY78: 0 | AZ78: 0 | BB78: =P78 -> 0 | BC78: =AB78 -> 0 | BD78: =AN78 -> 0 | BE78: =AZ78 -> 0 | BF78: 0
B79: Loan (CLA) | D79: € | Q79: 0 | R79: 0 | S79: 0 | T79: 0 | U79: 0 | V79: =V54 -> 300000 | W79: =V79 -> 300000 | X79: =W79 -> 300000 | Y79: =X79 -> 300000 | Z79: 0 | AA79: 0 | AB79: 0 | AC79: 0 | AD79: 0 | AE79: 0 | AF79: 0 | AG79: 0 | AH79: 0 | AI79: 0 | AJ79: 0 | AK79: 0 | AL79: 0 | AM79: 0 | AN79: 0 | AO79: 0 | AP79: 0 | AQ79: 0 | AR79: 0 | AS79: 0 | AT79: 0 | AU79: 0 | AV79: 0 | AW79: 0 | AX79: 0 | AY79: 0 | AZ79: 0 | BB79: 0 | BC79: =AB79 -> 0 | BD79: =AN79 -> 0 | BE79: =AZ79 -> 0 | BF79: 0
B80: Compressor WC loan (supplier financing) | E80: =MIN(E91,1000)*714 -> 0 | F80: =MIN(F91,1000)*714 -> 0 | G80: =MIN(G91,1000)*714 -> 0 | H80: =MIN(H91,1000)*714 -> 0 | I80: =MIN(I91,1000)*714 -> 0 | J80: =MIN(J91,1000)*714 -> 0 | K80: =MIN(K91,1000)*714 -> 0 | L80: =MIN(L91,1000)*714 -> 0 | ... AZ80: =MIN(AZ91,1000)*714 -> 714000 | BC80: =AB80 -> 0 | BD80: =AN80 -> 714000 | BE80: =AZ80 -> 714000 | BF80: 0
B81: Total Long-Term Liabilities | D81: € | E81: =E78+E79+E80 -> 0 | F81: =F78+F79+F80 -> 0 | G81: =G78+G79+G80 -> 0 | H81: =H78+H79+H80 -> 0 | I81: =I78+I79+I80 -> 0 | J81: =J78+J79+J80 -> 0 | K81: =K78+K79+K80 -> 0 | L81: =L78+L79+L80 -> 0 | ... AZ81: =AZ78+AZ79+AZ80 -> 714000 | BB81: =P81 -> 0 | BC81: =AB81 -> 0 | BD81: =AN81 -> 714000 | BE81: =AZ81 -> 714000 | BF81: =sum(BF78:BF80) -> 0
B83: Share capital + premium | D83: € | M83: =M59 -> 1111108 | N83: =M83 -> 1111108 | O83: =N83 -> 1111108 | P83: =O83 -> 1111108 | Q83: =P83 -> 1111108 | R83: =Q83 -> 1111108 | S83: =R83 -> 1111108 | T83: =S83 -> 1111108 | U83: =T83 -> 1111108 | ... Y83: =X83 -> 1111108 | Z83: =Y83+Y79 -> 1411108 | AA83: =Z83 -> 1411108 | AB83: =AA83 -> 1411108 | AC83: =AB83 -> 1411108 | AD83: =AC83 -> 1411108 | AE83: =AD83 -> 1411108 | AF83: =AE83 -> 1411108 | AG83: =AF83 -> 1411108 | AH83: =AG83 -> 1411108 | ... AZ83: =AY83 -> 1411108 | BB83: =P83 -> 1111108 | BC83: =AB83 -> 1411108 | BD83: =AN83 -> 1411108 | BE83: =AZ83 -> 1411108 | BF83: =BE83 -> 1411108
B84: Cumulative equity injections | D84: € | M84: =M53+M53 -> 0 | N84: =M84+N53 -> 0 | O84: =N84+O53 -> 0 | P84: =O84+P53 -> 0 | Q84: =P84+Q53 -> 0 | R84: =Q84+R53 -> 0 | S84: =R84+S53 -> 0 | T84: =S84+T53 -> 0 | U84: =T84+U53 -> 300000 | ... AZ84: =AY84+AZ53 -> 3550000 | BB84: =P84 -> 0 | BC84: =AB84 -> 3550000 | BD84: =AN84 -> 3550000 | BE84: =AZ84 -> 3550000 | BF84: =BE84 -> 3550000
B85: Retained earnings (cumulative net income) | D85: € | M85: =M45 -> -59000 | N85: =M85+N39 -> -98520 | O85: =N85+O39 -> -79520 | P85: =O85+P39 -> -327453 | Q85: =P85+Q39 -> -455973 | R85: =Q85+R39 -> -595293 | S85: =R85+S39 -> -734613 | T85: =S85+T39 -> -873933 | U85: =T85+U39 -> -1023253 | ... AZ85: =AY85+AZ39 -> 12660278 | BB85: =P85 -> -327453 | BC85: =AB85 -> -2297191 | BD85: =AN85 -> -878352.39 | BE85: =AZ85 -> 12660278 | BF85: =BE85+BF39 -> 51011771
B86: Total Equity | D86: € | M86: =M83+M84+M85+M42 -> 1160347 | N86: =N83+N84+N85+N42 -> 1131023.2 | O86: =O83+O84+O85+O42 -> 1145121.2 | P86: =P83+P84+P85+P42 -> 961154.87 | Q86: =Q83+Q84+Q85+Q42 -> 865793.03 | R86: =R83+R84+R85+R42 -> 762417.59 | S86: =S83+S84+S85+S42 -> 659042.15 | T86: =T83+T84+T85+T42 -> 555666.71 | ... AZ86: =AZ83+AZ84+AZ85+AZ42 -> 14448051 | BB86: =P86 -> 961154.87 | BC86: =AB86 -> 3349609.3 | BD86: =AN86 -> 4402387.5 | BE86: =AZ86 -> 14448051 | BF86: =sum(BF83:BF85) -> 55972879
B87: TOTAL EQUITY & LIABILITIES | D87: € | M87: =M76+M81+M86 -> 1160347 | N87: =N76+N81+N86 -> 1131023.2 | O87: =O76+O81+O86 -> 1145121.2 | P87: =P76+P81+P86 -> 961154.87 | Q87: =Q76+Q81+Q86 -> 865793.03 | R87: =R76+R81+R86 -> 762417.59 | S87: =S76+S81+S86 -> 659042.15 | T87: =T76+T81+T86 -> 555666.71 | ... AZ87: =AZ76+AZ81+AZ86 -> 26951212 | BB87: =P87 -> 961154.87 | BC87: =AB87 -> 3349609.3 | BD87: =AN87 -> 8388410 | BE87: =AZ87 -> 26951212 | BF87: =BF76+BF81+BF86 -> 66897205
B89: CHECK (Total Assets − Total E&L = 0) | M89: =M72-M87 -> 0 | N89: =N72-N87 -> 2.3283064e-10 | O89: =O72-O87 -> 0 | P89: =P72-P87 -> 0 | Q89: =Q72-Q87 -> 0 | R89: =R72-R87 -> 0 | S89: =S72-S87 -> 0 | T89: =T72-T87 -> 0 | ... AZ89: =AZ72-AZ87 -> -3.7252903e-09 | BB89: =BB72-BB87 -> 0 | BC89: =BC72-BC87 -> 0 | BD89: =BD72-BD87 -> -9.3132257e-10 | BE89: =BE72-BE87 -> -3.7252903e-09 | BF89: =BF72-BF87 -> -7.4505806e-09
B91: Cumulative turbineketels (helper) | E91: ='Revenue Forecast'!E41 -> 0 | F91: =E91+'Revenue Forecast'!F41 -> 0 | G91: =F91+'Revenue Forecast'!G41 -> 0 | H91: =G91+'Revenue Forecast'!H41 -> 0 | I91: =H91+'Revenue Forecast'!I41 -> 0 | J91: =I91+'Revenue Forecast'!J41 -> 0 | K91: =J91+'Revenue Forecast'!K41 -> 0 | L91: =K91+'Revenue Forecast'!L41 -> 0 | M91: =L91+'Revenue Forecast'!M41 -> 0 | ... AZ91: =AY91+'Revenue Forecast'!AZ41 -> 6496

Sheet Revenue Forecast
B1: Tarnoc B.V. — Revenue Forecast (€, ex VAT unless noted)
E2: 2025 | Q2: 2026 | AC2: 2027 | AO2: 2028
E3: 45658 | F3: 45689 | G3: 45717 | H3: 45748 | I3: 45778 | J3: 45809 | K3: 45839 | L3: 45870 | M3: 45901 | N3: 45931 | O3: 45962 | P3: 45992 | Q3: 46023 | R3: 46054 | S3: 46082 | T3: 46113 | U3: 46143 | V3: 46174 | W3: 46204 | X3: 46235 | Y3: 46266 | Z3: 46296 | AA3: 46327 | AB3: 46357 | AC3: 46388 | AD3: 46419 | AE3: 46447 | AF3: 46478 | AG3: 46508 | AH3: 46539 | AI3: 46569 | AJ3: 46600 | AK3: 46631 | AL3: 46661 | AM3: 46692 | AN3: 46722 | AO3: 46753 | AP3: 46784 | AQ3: 46813 | AR3: 46844 | AS3: 46874 | AT3: 46905 | AU3: 46935 | AV3: 46966 | AW3: 46997 | AX3: 47027 | AY3: 47058 | AZ3: 47088 | BB3: 2025 | BC3: 2026 | BD3: 2027 | BE3: 2028 | BF3: 2029
AB4: 2 | AC4: 3 | AD4: 4 | AE4: 5 | AF4: 6 | AG4: 7 | AH4: 8 | AI4: 9 | AJ4: 10 | AK4: 11 | AL4: 12 | AM4: 13 | AN4: 14 | AO4: 15 | AP4: 16 | AQ4: 17 | AR4: 18 | AS4: 19 | AT4: 20 | AU4: 21 | AV4: 22 | AW4: 23 | AX4: 24 | AY4: 25 | AZ4: 26
B5: TURBINEKETEL (TTK)
B6: TTK units sold | D6: # | Q6: {=IF(YEAR(Q$3)=2026,0,ROUND(EXP(0.095*((YEAR(Q$3)-2027)*12+MONTH(Q$3)-1))/SUMPRODUCT(EXP(0.095*(ROW(INDIRECT("1:24"))-1)))*SUM(Assumptions!$D$22:$E$22),0))} -> 0 | R6: {=IF(YEAR(R$3)=2026,0,ROUND(EXP(0.095*((YEAR(R$3)-2027)*12+MONTH(R$3)-1))/SUMPRODUCT(EXP(0.095*(ROW(INDIRECT("1:24"))-1)))*SUM(Assumptions!$D$22:$E$22),0))} -> 0 | S6: {=IF(YEAR(S$3)=2026,0,ROUND(EXP(0.095*((YEAR(S$3)-2027)*12+MONTH(S$3)-1))/SUMPRODUCT(EXP(0.095*(ROW(INDIRECT("1:24"))-1)))*SUM(Assumptions!$D$22:$E$22),0))} -> 0 | T6: {=IF(YEAR(T$3)=2026,0,ROUND(EXP(0.095*((YEAR(T$3)-2027)*12+MONTH(T$3)-1))/SUMPRODUCT(EXP(0.095*(ROW(INDIRECT("1:24"))-1)))*SUM(Assumptions!$D$22:$E$22),0))} -> 0 | U6: {=IF(YEAR(U$3)=2026,0,ROUND(EXP(0.095*((YEAR(U$3)-2027)*12+MONTH(U$3)-1))/SUMPRODUCT(EXP(0.095*(ROW(INDIRECT("1:24"))-1)))*SUM(Assumptions!$D$22:$E$22),0))} -> 0 | V6: {=IF(YEAR(V$3)=2026,0,ROUND(EXP(0.095*((YEAR(V$3)-2027)*12+MONTH(V$3)-1))/SUMPRODUCT(EXP(0.095*(ROW(INDIRECT("1:24"))-1)))*SUM(Assumptions!$D$22:$E$22),0))} -> 0 | W6: {=IF(YEAR(W$3)=2026,0,ROUND(EXP(0.095*((YEAR(W$3)-2027)*12+MONTH(W$3)-1))/SUMPRODUCT(EXP(0.095*(ROW(INDIRECT("1:24"))-1)))*SUM(Assumptions!$D$22:$E$22),0))} -> 0 | X6: {=IF(YEAR(X$3)=2026,0,ROUND(EXP(0.095*((YEAR(X$3)-2027)*12+MONTH(X$3)-1))/SUMPRODUCT(EXP(0.095*(ROW(INDIRECT("1:24"))-1)))*SUM(Assumptions!$D$22:$E$22),0))} -> 0 | ... AB6: {=IF(YEAR(AB$3)=2026,0,ROUND(EXP(0.095*((YEAR(AB$3)-2027)*12+MONTH(AB$3)-1))/SUMPRODUCT(EXP(0.095*(ROW(INDIRECT("1:24"))-1)))*SUM(Assumptions!$D$22:$E$22),0))} -> 0 | AC6: {=IF(YEAR(AC$3)=2026,0,ROUND(EXP(0.091*((YEAR(AC$3)-2027)*12+MONTH(AC$3)-1))/SUMPRODUCT(EXP(0.091*(ROW(INDIRECT("1:24"))-1)))*SUM(Assumptions!$D$22:$E$22),0))} -> 31 | AD6: {=IF(YEAR(AD$3)=2026,0,ROUND(EXP(0.091*((YEAR(AD$3)-2027)*12+MONTH(AD$3)-1))/SUMPRODUCT(EXP(0.091*(ROW(INDIRECT("1:24"))-1)))*SUM(Assumptions!$D$22:$E$22),0))} -> 34 | AE6: {=IF(YEAR(AE$3)=2026,0,ROUND(EXP(0.091*((YEAR(AE$3)-2027)*12+MONTH(AE$3)-1))/SUMPRODUCT(EXP(0.091*(ROW(INDIRECT("1:24"))-1)))*SUM(Assumptions!$D$22:$E$22),0))} -> 38 | AF6: {=IF(YEAR(AF$3)=2026,0,ROUND(EXP(0.091*((YEAR(AF$3)-2027)*12+MONTH(AF$3)-1))/SUMPRODUCT(EXP(0.091*(ROW(INDIRECT("1:24"))-1)))*SUM(Assumptions!$D$22:$E$22),0))} -> 41 | AG6: {=IF(YEAR(AG$3)=2026,0,ROUND(EXP(0.091*((YEAR(AG$3)-2027)*12+MONTH(AG$3)-1))/SUMPRODUCT(EXP(0.091*(ROW(INDIRECT("1:24"))-1)))*SUM(Assumptions!$D$22:$E$22),0))} -> 45 | AH6: {=IF(YEAR(AH$3)=2026,0,ROUND(EXP(0.091*((YEAR(AH$3)-2027)*12+MONTH(AH$3)-1))/SUMPRODUCT(EXP(0.091*(ROW(INDIRECT("1:24"))-1)))*SUM(Assumptions!$D$22:$E$22),0))} -> 50 | AI6: {=IF(YEAR(AI$3)=2026,0,ROUND(EXP(0.091*((YEAR(AI$3)-2027)*12+MONTH(AI$3)-1))/SUMPRODUCT(EXP(0.091*(ROW(INDIRECT("1:24"))-1)))*SUM(Assumptions!$D$22:$E$22),0))} -> 54 | AJ6: {=IF(YEAR(AJ$3)=2026,0,ROUND(EXP(0.091*((YEAR(AJ$3)-2027)*12+MONTH(AJ$3)-1))/SUMPRODUCT(EXP(0.091*(ROW(INDIRECT("1:24"))-1)))*SUM(Assumptions!$D$22:$E$22),0))} -> 59 | ... AN6: {=IF(YEAR(AN$3)=2026,0,ROUND(EXP(0.091*((YEAR(AN$3)-2027)*12+MONTH(AN$3)-1))/SUMPRODUCT(EXP(0.091*(ROW(INDIRECT("1:24"))-1)))*SUM(Assumptions!$D$22:$E$22),0))} -> 86 | AO6: {=IF(YEAR(AO$3)=2026,0,ROUND(EXP(0.0915*((YEAR(AO$3)-2027)*12+MONTH(AO$3)-1))/SUMPRODUCT(EXP(0.0915*(ROW(INDIRECT("1:24"))-1)))*SUM(Assumptions!$D$22:$E$22),0))} -> 93 | AP6: {=IF(YEAR(AP$3)=2026,0,ROUND(EXP(0.0915*((YEAR(AP$3)-2027)*12+MONTH(AP$3)-1))/SUMPRODUCT(EXP(0.0915*(ROW(INDIRECT("1:24"))-1)))*SUM(Assumptions!$D$22:$E$22),0))} -> 102 | AQ6: {=IF(YEAR(AQ$3)=2026,0,ROUND(EXP(0.0915*((YEAR(AQ$3)-2027)*12+MONTH(AQ$3)-1))/SUMPRODUCT(EXP(0.0915*(ROW(INDIRECT("1:24"))-1)))*SUM(Assumptions!$D$22:$E$22),0))} -> 112 | AR6: {=IF(YEAR(AR$3)=2026,0,ROUND(EXP(0.0915*((YEAR(AR$3)-2027)*12+MONTH(AR$3)-1))/SUMPRODUCT(EXP(0.0915*(ROW(INDIRECT("1:24"))-1)))*SUM(Assumptions!$D$22:$E$22),0))} -> 123 | AS6: {=IF(YEAR(AS$3)=2026,0,ROUND(EXP(0.0915*((YEAR(AS$3)-2027)*12+MONTH(AS$3)-1))/SUMPRODUCT(EXP(0.0915*(ROW(INDIRECT("1:24"))-1)))*SUM(Assumptions!$D$22:$E$22),0))} -> 135 | AT6: {=IF(YEAR(AT$3)=2026,0,ROUND(EXP(0.0915*((YEAR(AT$3)-2027)*12+MONTH(AT$3)-1))/SUMPRODUCT(EXP(0.0915*(ROW(INDIRECT("1:24"))-1)))*SUM(Assumptions!$D$22:$E$22),0))} -> 148 | AU6: {=IF(YEAR(AU$3)=2026,0,ROUND(EXP(0.0915*((YEAR(AU$3)-2027)*12+MONTH(AU$3)-1))/SUMPRODUCT(EXP(0.0915*(ROW(INDIRECT("1:24"))-1)))*SUM(Assumptions!$D$22:$E$22),0))} -> 162 | AV6: {=IF(YEAR(AV$3)=2026,0,ROUND(EXP(0.0915*((YEAR(AV$3)-2027)*12+MONTH(AV$3)-1))/SUMPRODUCT(EXP(0.0915*(ROW(INDIRECT("1:24"))-1)))*SUM(Assumptions!$D$22:$E$22),0))} -> 177 | ... AZ6: {=IF(YEAR(AZ$3)=2026,0,ROUND(EXP(0.0915*((YEAR(AZ$3)-2027)*12+MONTH(AZ$3)-1))/SUMPRODUCT(EXP(0.0915*(ROW(INDIRECT("1:24"))-1)))*SUM(Assumptions!$D$22:$E$22),0))} -> 256 | BB6: =SUM(E6:P6) -> 0 | BC6: =SUM(Q6:AB6) -> 0 | BD6: =SUM(AC6:AN6) -> 652 | BE6: =SUM(AO6:AZ6) -> 1948 | BF6: =BE6*2 -> 3896
B7: TTK Revenue | D7: € | Q7: =Q6*Assumptions!$C$29 -> 0 | R7: =R6*Assumptions!$C$29 -> 0 | S7: =S6*Assumptions!$C$29 -> 0 | T7: =T6*Assumptions!$C$29 -> 0 | U7: =U6*Assumptions!$C$29 -> 0 | V7: =V6*Assumptions!$C$29 -> 0 | W7: =W6*Assumptions!$C$29 -> 0 | X7: =X6*Assumptions!$C$29 -> 0 | ... AZ7: =AZ6*Assumptions!$C$29 -> 2284958.7 | BB7: =SUM(E7:P7) -> 0 | BC7: =SUM(Q7:AB7) -> 0 | BD7: =SUM(AC7:AN7) -> 5819504.1 | BE7: =SUM(AO7:AZ7) -> 17387107 | BF7: =BF6*Assumptions!$C$29 -> 34774215
B8: TTK upsell | D8: € | Q8: =Q6*SUMPRODUCT(Assumptions!$E$116:$F$118) -> 0 | R8: =R6*SUMPRODUCT(Assumptions!$E$116:$F$118) -> 0 | S8: =S6*SUMPRODUCT(Assumptions!$E$116:$F$118) -> 0 | T8: =T6*SUMPRODUCT(Assumptions!$E$116:$F$118) -> 0 | U8: =U6*SUMPRODUCT(Assumptions!$E$116:$F$118) -> 0 | V8: =V6*SUMPRODUCT(Assumptions!$E$116:$F$118) -> 0 | W8: =W6*SUMPRODUCT(Assumptions!$E$116:$F$118) -> 0 | X8: =X6*SUMPRODUCT(Assumptions!$E$116:$F$118) -> 0 | ... AB8: =AB6*SUMPRODUCT(Assumptions!$E$116:$F$118) -> 0 | AC8: =AC6*SUMPRODUCT(Assumptions!$E$116:$E$118,Assumptions!$F$116:$F$118) -> 15589.669 | AD8: =AD6*SUMPRODUCT(Assumptions!$E$116:$E$118,Assumptions!$F$116:$F$118) -> 17098.347 | AE8: =AE6*SUMPRODUCT(Assumptions!$E$116:$E$118,Assumptions!$F$116:$F$118) -> 19109.917 | AF8: =AF6*SUMPRODUCT(Assumptions!$E$116:$E$118,Assumptions!$F$116:$F$118) -> 20618.595 | AG8: =AG6*SUMPRODUCT(Assumptions!$E$116:$E$118,Assumptions!$F$116:$F$118) -> 22630.165 | AH8: =AH6*SUMPRODUCT(Assumptions!$E$116:$E$118,Assumptions!$F$116:$F$118) -> 25144.628 | AI8: =AI6*SUMPRODUCT(Assumptions!$E$116:$E$118,Assumptions!$F$116:$F$118) -> 27156.198 | AJ8: =AJ6*SUMPRODUCT(Assumptions!$E$116:$E$118,Assumptions!$F$116:$F$118) -> 29670.661 | ... AZ8: =AZ6*SUMPRODUCT(Assumptions!$E$116:$E$118,Assumptions!$F$116:$F$118) -> 128740.5 | BB8: =SUM(E8:P8) -> 0 | BC8: =SUM(Q8:AB8) -> 0 | BD8: =SUM(AC8:AN8) -> 327885.95 | BE8: =SUM(AO8:AZ8) -> 979634.71 | BF8: =BF6*SUMPRODUCT(Assumptions!$E$116:$E$118,Assumptions!$F$116:$F$118) -> 1959269.4
B9: Total TTK Revenue | D9: € | Q9: =sum(Q7:Q8) -> 0 | R9: =sum(R7:R8) -> 0 | S9: =sum(S7:S8) -> 0 | T9: =sum(T7:T8) -> 0 | U9: =sum(U7:U8) -> 0 | V9: =sum(V7:V8) -> 0 | W9: =sum(W7:W8) -> 0 | X9: =sum(X7:X8) -> 0 | ... AZ9: =sum(AZ7:AZ8) -> 2413699.2 | BB9: =SUM(E9:P9) -> 0 | BC9: =SUM(Q9:AB9) -> 0 | BD9: =SUM(AC9:AN9) -> 6147390.1 | BE9: =SUM(AO9:AZ9) -> 18366742 | BF9: =BE9*2 -> 36733484
B11: COMBI
B12: Combi units sold | D12: # | Q12: {=IF(YEAR(Q$3)=2026,0,ROUND(EXP(0.11*((YEAR(Q$3)-2027)*12+MONTH(Q$3)-1))/SUMPRODUCT(EXP(0.11*(ROW(INDIRECT("1:24"))-1)))*SUM(Assumptions!$D$23:$E$23),0))} -> 0 | R12: {=IF(YEAR(R$3)=2026,0,ROUND(EXP(0.11*((YEAR(R$3)-2027)*12+MONTH(R$3)-1))/SUMPRODUCT(EXP(0.11*(ROW(INDIRECT("1:24"))-1)))*SUM(Assumptions!$D$23:$E$23),0))} -> 0 | S12: {=IF(YEAR(S$3)=2026,0,ROUND(EXP(0.11*((YEAR(S$3)-2027)*12+MONTH(S$3)-1))/SUMPRODUCT(EXP(0.11*(ROW(INDIRECT("1:24"))-1)))*SUM(Assumptions!$D$23:$E$23),0))} -> 0 | T12: {=IF(YEAR(T$3)=2026,0,ROUND(EXP(0.11*((YEAR(T$3)-2027)*12+MONTH(T$3)-1))/SUMPRODUCT(EXP(0.11*(ROW(INDIRECT("1:24"))-1)))*SUM(Assumptions!$D$23:$E$23),0))} -> 0 | U12: {=IF(YEAR(U$3)=2026,0,ROUND(EXP(0.11*((YEAR(U$3)-2027)*12+MONTH(U$3)-1))/SUMPRODUCT(EXP(0.11*(ROW(INDIRECT("1:24"))-1)))*SUM(Assumptions!$D$23:$E$23),0))} -> 0 | V12: {=IF(YEAR(V$3)=2026,0,ROUND(EXP(0.11*((YEAR(V$3)-2027)*12+MONTH(V$3)-1))/SUMPRODUCT(EXP(0.11*(ROW(INDIRECT("1:24"))-1)))*SUM(Assumptions!$D$23:$E$23),0))} -> 0 | W12: {=IF(YEAR(W$3)=2026,0,ROUND(EXP(0.11*((YEAR(W$3)-2027)*12+MONTH(W$3)-1))/SUMPRODUCT(EXP(0.11*(ROW(INDIRECT("1:24"))-1)))*SUM(Assumptions!$D$23:$E$23),0))} -> 0 | X12: {=IF(YEAR(X$3)=2026,0,ROUND(EXP(0.11*((YEAR(X$3)-2027)*12+MONTH(X$3)-1))/SUMPRODUCT(EXP(0.11*(ROW(INDIRECT("1:24"))-1)))*SUM(Assumptions!$D$23:$E$23),0))} -> 0 | ... AB12: {=IF(YEAR(AB$3)=2026,0,ROUND(EXP(0.11*((YEAR(AB$3)-2027)*12+MONTH(AB$3)-1))/SUMPRODUCT(EXP(0.11*(ROW(INDIRECT("1:24"))-1)))*SUM(Assumptions!$D$23:$E$23),0))} -> 0 | AC12: {=IF(YEAR(AC$3)=2026,0,ROUND(EXP(0.116*((YEAR(AC$3)-2027)*12+MONTH(AC$3)-1))/SUMPRODUCT(EXP(0.116*(ROW(INDIRECT("1:24"))-1)))*SUM(Assumptions!$D$23:$E$23),0))} -> 16 | AD12: {=IF(YEAR(AD$3)=2026,0,ROUND(EXP(0.116*((YEAR(AD$3)-2027)*12+MONTH(AD$3)-1))/SUMPRODUCT(EXP(0.116*(ROW(INDIRECT("1:24"))-1)))*SUM(Assumptions!$D$23:$E$23),0))} -> 18 | AE12: {=IF(YEAR(AE$3)=2026,0,ROUND(EXP(0.116*((YEAR(AE$3)-2027)*12+MONTH(AE$3)-1))/SUMPRODUCT(EXP(0.116*(ROW(INDIRECT("1:24"))-1)))*SUM(Assumptions!$D$23:$E$23),0))} -> 20 | AF12: {=IF(YEAR(AF$3)=2026,0,ROUND(EXP(0.116*((YEAR(AF$3)-2027)*12+MONTH(AF$3)-1))/SUMPRODUCT(EXP(0.116*(ROW(INDIRECT("1:24"))-1)))*SUM(Assumptions!$D$23:$E$23),0))} -> 22 | AG12: {=IF(YEAR(AG$3)=2026,0,ROUND(EXP(0.116*((YEAR(AG$3)-2027)*12+MONTH(AG$3)-1))/SUMPRODUCT(EXP(0.116*(ROW(INDIRECT("1:24"))-1)))*SUM(Assumptions!$D$23:$E$23),0))} -> 25 | AH12: {=IF(YEAR(AH$3)=2026,0,ROUND(EXP(0.116*((YEAR(AH$3)-2027)*12+MONTH(AH$3)-1))/SUMPRODUCT(EXP(0.116*(ROW(INDIRECT("1:24"))-1)))*SUM(Assumptions!$D$23:$E$23),0))} -> 28 | AI12: {=IF(YEAR(AI$3)=2026,0,ROUND(EXP(0.116*((YEAR(AI$3)-2027)*12+MONTH(AI$3)-1))/SUMPRODUCT(EXP(0.116*(ROW(INDIRECT("1:24"))-1)))*SUM(Assumptions!$D$23:$E$23),0))} -> 32 | AJ12: {=IF(YEAR(AJ$3)=2026,0,ROUND(EXP(0.116*((YEAR(AJ$3)-2027)*12+MONTH(AJ$3)-1))/SUMPRODUCT(EXP(0.116*(ROW(INDIRECT("1:24"))-1)))*SUM(Assumptions!$D$23:$E$23),0))} -> 36 | ... AN12: {=IF(YEAR(AN$3)=2026,0,ROUND(EXP(0.116*((YEAR(AN$3)-2027)*12+MONTH(AN$3)-1))/SUMPRODUCT(EXP(0.116*(ROW(INDIRECT("1:24"))-1)))*SUM(Assumptions!$D$23:$E$23),0))} -> 57 | AO12: {=IF(YEAR(AO$3)=2026,0,ROUND(EXP(0.1157*((YEAR(AO$3)-2027)*12+MONTH(AO$3)-1))/SUMPRODUCT(EXP(0.1157*(ROW(INDIRECT("1:24"))-1)))*SUM(Assumptions!$D$23:$E$23),0))} -> 64 | AP12: {=IF(YEAR(AP$3)=2026,0,ROUND(EXP(0.1157*((YEAR(AP$3)-2027)*12+MONTH(AP$3)-1))/SUMPRODUCT(EXP(0.1157*(ROW(INDIRECT("1:24"))-1)))*SUM(Assumptions!$D$23:$E$23),0))} -> 71 | AQ12: {=IF(YEAR(AQ$3)=2026,0,ROUND(EXP(0.1157*((YEAR(AQ$3)-2027)*12+MONTH(AQ$3)-1))/SUMPRODUCT(EXP(0.1157*(ROW(INDIRECT("1:24"))-1)))*SUM(Assumptions!$D$23:$E$23),0))} -> 80 | AR12: {=IF(YEAR(AR$3)=2026,0,ROUND(EXP(0.1157*((YEAR(AR$3)-2027)*12+MONTH(AR$3)-1))/SUMPRODUCT(EXP(0.1157*(ROW(INDIRECT("1:24"))-1)))*SUM(Assumptions!$D$23:$E$23),0))} -> 90 | AS12: {=IF(YEAR(AS$3)=2026,0,ROUND(EXP(0.1157*((YEAR(AS$3)-2027)*12+MONTH(AS$3)-1))/SUMPRODUCT(EXP(0.1157*(ROW(INDIRECT("1:24"))-1)))*SUM(Assumptions!$D$23:$E$23),0))} -> 101 | AT12: {=IF(YEAR(AT$3)=2026,0,ROUND(EXP(0.1157*((YEAR(AT$3)-2027)*12+MONTH(AT$3)-1))/SUMPRODUCT(EXP(0.1157*(ROW(INDIRECT("1:24"))-1)))*SUM(Assumptions!$D$23:$E$23),0))} -> 113 | AU12: {=IF(YEAR(AU$3)=2026,0,ROUND(EXP(0.1157*((YEAR(AU$3)-2027)*12+MONTH(AU$3)-1))/SUMPRODUCT(EXP(0.1157*(ROW(INDIRECT("1:24"))-1)))*SUM(Assumptions!$D$23:$E$23),0))} -> 127 | AV12: {=IF(YEAR(AV$3)=2026,0,ROUND(EXP(0.1157*((YEAR(AV$3)-2027)*12+MONTH(AV$3)-1))/SUMPRODUCT(EXP(0.1157*(ROW(INDIRECT("1:24"))-1)))*SUM(Assumptions!$D$23:$E$23),0))} -> 143 | ... AZ12: {=IF(YEAR(AZ$3)=2026,0,ROUND(EXP(0.1157*((YEAR(AZ$3)-2027)*12+MONTH(AZ$3)-1))/SUMPRODUCT(EXP(0.1157*(ROW(INDIRECT("1:24"))-1)))*SUM(Assumptions!$D$23:$E$23),0))} -> 227 | BB12: =SUM(E12:P12) -> 0 | BC12: =SUM(Q12:AB12) -> 0 | BD12: =SUM(AC12:AN12) -> 389 | BE12: =SUM(AO12:AZ12) -> 1559 | BF12: =BE12*2 -> 3118
B13: Combi Revenue | D13: € | Q13: =Q12*Assumptions!$C$32 -> 0 | R13: =R12*Assumptions!$C$32 -> 0 | S13: =S12*Assumptions!$C$32 -> 0 | T13: =T12*Assumptions!$C$32 -> 0 | U13: =U12*Assumptions!$C$32 -> 0 | V13: =V12*Assumptions!$C$32 -> 0 | W13: =W12*Assumptions!$C$32 -> 0 | X13: =X12*Assumptions!$C$32 -> 0 | ... AZ13: =AZ12*Assumptions!$C$32 -> 2537334.7 | BB13: =SUM(E13:P13) -> 0 | BC13: =SUM(Q13:AB13) -> 0 | BD13: =SUM(AC13:AN13) -> 4348119.8 | BE13: =SUM(AO13:AZ13) -> 17426012 | BF13: =BF12*Assumptions!$C$32 -> 34852025
B14: Combi upsell | D14: € | Q14: =Q12*SUMPRODUCT(Assumptions!$E$116:$E$118,Assumptions!$F$116:$F$118) -> 0 | R14: =R12*SUMPRODUCT(Assumptions!$E$116:$E$118,Assumptions!$F$116:$F$118) -> 0 | S14: =S12*SUMPRODUCT(Assumptions!$E$116:$E$118,Assumptions!$F$116:$F$118) -> 0 | T14: =T12*SUMPRODUCT(Assumptions!$E$116:$E$118,Assumptions!$F$116:$F$118) -> 0 | U14: =U12*SUMPRODUCT(Assumptions!$E$116:$E$118,Assumptions!$F$116:$F$118) -> 0 | V14: =V12*SUMPRODUCT(Assumptions!$E$116:$E$118,Assumptions!$F$116:$F$118) -> 0 | W14: =W12*SUMPRODUCT(Assumptions!$E$116:$E$118,Assumptions!$F$116:$F$118) -> 0 | X14: =X12*SUMPRODUCT(Assumptions!$E$116:$E$118,Assumptions!$F$116:$F$118) -> 0 | ... AZ14: =AZ12*SUMPRODUCT(Assumptions!$E$116:$E$118,Assumptions!$F$116:$F$118) -> 114156.61 | BB14: =SUM(E14:P14) -> 0 | BC14: =SUM(Q14:AB14) -> 0 | BD14: =SUM(AC14:AN14) -> 195625.21 | BE14: =SUM(AO14:AZ14) -> 784009.5 | BF14: =BF12*SUMPRODUCT(Assumptions!$E$116:$E$118,Assumptions!$F$116:$F$118) -> 1568019
B15: Total Combi Revenue | D15: € | Q15: =sum(Q13:Q14) -> 0 | R15: =sum(R13:R14) -> 0 | S15: =sum(S13:S14) -> 0 | T15: =sum(T13:T14) -> 0 | U15: =sum(U13:U14) -> 0 | V15: =sum(V13:V14) -> 0 | W15: =sum(W13:W14) -> 0 | X15: =sum(X13:X14) -> 0 | ... AZ15: =sum(AZ13:AZ14) -> 2651491.3 | BB15: =SUM(E15:P15) -> 0 | BC15: =SUM(Q15:AB15) -> 0 | BD15: =SUM(AC15:AN15) -> 4543745 | BE15: =SUM(AO15:AZ15) -> 18210022 | BF15: =BE15*2 -> 36420044
B17: COMBI+
B18: Combi+ units sold | D18: # | Q18: {=IF(YEAR(Q$3)=2026,0,ROUND(EXP(0.11*((YEAR(Q$3)-2027)*12+MONTH(Q$3)-1))/SUMPRODUCT(EXP(0.11*(ROW(INDIRECT("1:24"))-1)))*SUM(Assumptions!$D$24:$E$24),0))} -> 0 | R18: {=IF(YEAR(R$3)=2026,0,ROUND(EXP(0.11*((YEAR(R$3)-2027)*12+MONTH(R$3)-1))/SUMPRODUCT(EXP(0.11*(ROW(INDIRECT("1:24"))-1)))*SUM(Assumptions!$D$24:$E$24),0))} -> 0 | S18: {=IF(YEAR(S$3)=2026,0,ROUND(EXP(0.11*((YEAR(S$3)-2027)*12+MONTH(S$3)-1))/SUMPRODUCT(EXP(0.11*(ROW(INDIRECT("1:24"))-1)))*SUM(Assumptions!$D$24:$E$24),0))} -> 0 | T18: {=IF(YEAR(T$3)=2026,0,ROUND(EXP(0.11*((YEAR(T$3)-2027)*12+MONTH(T$3)-1))/SUMPRODUCT(EXP(0.11*(ROW(INDIRECT("1:24"))-1)))*SUM(Assumptions!$D$24:$E$24),0))} -> 0 | U18: {=IF(YEAR(U$3)=2026,0,ROUND(EXP(0.11*((YEAR(U$3)-2027)*12+MONTH(U$3)-1))/SUMPRODUCT(EXP(0.11*(ROW(INDIRECT("1:24"))-1)))*SUM(Assumptions!$D$24:$E$24),0))} -> 0 | V18: {=IF(YEAR(V$3)=2026,0,ROUND(EXP(0.11*((YEAR(V$3)-2027)*12+MONTH(V$3)-1))/SUMPRODUCT(EXP(0.11*(ROW(INDIRECT("1:24"))-1)))*SUM(Assumptions!$D$24:$E$24),0))} -> 0 | W18: {=IF(YEAR(W$3)=2026,0,ROUND(EXP(0.11*((YEAR(W$3)-2027)*12+MONTH(W$3)-1))/SUMPRODUCT(EXP(0.11*(ROW(INDIRECT("1:24"))-1)))*SUM(Assumptions!$D$24:$E$24),0))} -> 0 | X18: {=IF(YEAR(X$3)=2026,0,ROUND(EXP(0.11*((YEAR(X$3)-2027)*12+MONTH(X$3)-1))/SUMPRODUCT(EXP(0.11*(ROW(INDIRECT("1:24"))-1)))*SUM(Assumptions!$D$24:$E$24),0))} -> 0 | ... AB18: {=IF(YEAR(AB$3)=2026,0,ROUND(EXP(0.11*((YEAR(AB$3)-2027)*12+MONTH(AB$3)-1))/SUMPRODUCT(EXP(0.11*(ROW(INDIRECT("1:24"))-1)))*SUM(Assumptions!$D$24:$E$24),0))} -> 0 | AC18: {=IF(YEAR(AC$3)=2026,0,ROUND(EXP(0.116*((YEAR(AC$3)-2027)*12+MONTH(AC$3)-1))/SUMPRODUCT(EXP(0.116*(ROW(INDIRECT("1:24"))-1)))*SUM(Assumptions!$D$24:$E$24),0))} -> 16 | AD18: {=IF(YEAR(AD$3)=2026,0,ROUND(EXP(0.116*((YEAR(AD$3)-2027)*12+MONTH(AD$3)-1))/SUMPRODUCT(EXP(0.116*(ROW(INDIRECT("1:24"))-1)))*SUM(Assumptions!$D$24:$E$24),0))} -> 18 | AE18: {=IF(YEAR(AE$3)=2026,0,ROUND(EXP(0.116*((YEAR(AE$3)-2027)*12+MONTH(AE$3)-1))/SUMPRODUCT(EXP(0.116*(ROW(INDIRECT("1:24"))-1)))*SUM(Assumptions!$D$24:$E$24),0))} -> 20 | AF18: {=IF(YEAR(AF$3)=2026,0,ROUND(EXP(0.116*((YEAR(AF$3)-2027)*12+MONTH(AF$3)-1))/SUMPRODUCT(EXP(0.116*(ROW(INDIRECT("1:24"))-1)))*SUM(Assumptions!$D$24:$E$24),0))} -> 22 | AG18: {=IF(YEAR(AG$3)=2026,0,ROUND(EXP(0.116*((YEAR(AG$3)-2027)*12+MONTH(AG$3)-1))/SUMPRODUCT(EXP(0.116*(ROW(INDIRECT("1:24"))-1)))*SUM(Assumptions!$D$24:$E$24),0))} -> 25 | AH18: {=IF(YEAR(AH$3)=2026,0,ROUND(EXP(0.116*((YEAR(AH$3)-2027)*12+MONTH(AH$3)-1))/SUMPRODUCT(EXP(0.116*(ROW(INDIRECT("1:24"))-1)))*SUM(Assumptions!$D$24:$E$24),0))} -> 28 | AI18: {=IF(YEAR(AI$3)=2026,0,ROUND(EXP(0.116*((YEAR(AI$3)-2027)*12+MONTH(AI$3)-1))/SUMPRODUCT(EXP(0.116*(ROW(INDIRECT("1:24"))-1)))*SUM(Assumptions!$D$24:$E$24),0))} -> 32 | AJ18: {=IF(YEAR(AJ$3)=2026,0,ROUND(EXP(0.116*((YEAR(AJ$3)-2027)*12+MONTH(AJ$3)-1))/SUMPRODUCT(EXP(0.116*(ROW(INDIRECT("1:24"))-1)))*SUM(Assumptions!$D$24:$E$24),0))} -> 36 | ... AN18: {=IF(YEAR(AN$3)=2026,0,ROUND(EXP(0.116*((YEAR(AN$3)-2027)*12+MONTH(AN$3)-1))/SUMPRODUCT(EXP(0.116*(ROW(INDIRECT("1:24"))-1)))*SUM(Assumptions!$D$24:$E$24),0))} -> 57 | AO18: {=IF(YEAR(AO$3)=2026,0,ROUND(EXP(0.1157*((YEAR(AO$3)-2027)*12+MONTH(AO$3)-1))/SUMPRODUCT(EXP(0.1157*(ROW(INDIRECT("1:24"))-1)))*SUM(Assumptions!$D$24:$E$24),0))} -> 64 | AP18: {=IF(YEAR(AP$3)=2026,0,ROUND(EXP(0.1157*((YEAR(AP$3)-2027)*12+MONTH(AP$3)-1))/SUMPRODUCT(EXP(0.1157*(ROW(INDIRECT("1:24"))-1)))*SUM(Assumptions!$D$24:$E$24),0))} -> 71 | AQ18: {=IF(YEAR(AQ$3)=2026,0,ROUND(EXP(0.1157*((YEAR(AQ$3)-2027)*12+MONTH(AQ$3)-1))/SUMPRODUCT(EXP(0.1157*(ROW(INDIRECT("1:24"))-1)))*SUM(Assumptions!$D$24:$E$24),0))} -> 80 | AR18: {=IF(YEAR(AR$3)=2026,0,ROUND(EXP(0.1157*((YEAR(AR$3)-2027)*12+MONTH(AR$3)-1))/SUMPRODUCT(EXP(0.1157*(ROW(INDIRECT("1:24"))-1)))*SUM(Assumptions!$D$24:$E$24),0))} -> 90 | AS18: {=IF(YEAR(AS$3)=2026,0,ROUND(EXP(0.1157*((YEAR(AS$3)-2027)*12+MONTH(AS$3)-1))/SUMPRODUCT(EXP(0.1157*(ROW(INDIRECT("1:24"))-1)))*SUM(Assumptions!$D$24:$E$24),0))} -> 101 | AT18: {=IF(YEAR(AT$3)=2026,0,ROUND(EXP(0.1157*((YEAR(AT$3)-2027)*12+MONTH(AT$3)-1))/SUMPRODUCT(EXP(0.1157*(ROW(INDIRECT("1:24"))-1)))*SUM(Assumptions!$D$24:$E$24),0))} -> 113 | AU18: {=IF(YEAR(AU$3)=2026,0,ROUND(EXP(0.1157*((YEAR(AU$3)-2027)*12+MONTH(AU$3)-1))/SUMPRODUCT(EXP(0.1157*(ROW(INDIRECT("1:24"))-1)))*SUM(Assumptions!$D$24:$E$24),0))} -> 127 | AV18: {=IF(YEAR(AV$3)=2026,0,ROUND(EXP(0.1157*((YEAR(AV$3)-2027)*12+MONTH(AV$3)-1))/SUMPRODUCT(EXP(0.1157*(ROW(INDIRECT("1:24"))-1)))*SUM(Assumptions!$D$24:$E$24),0))} -> 143 | ... AZ18: {=IF(YEAR(AZ$3)=2026,0,ROUND(EXP(0.1157*((YEAR(AZ$3)-2027)*12+MONTH(AZ$3)-1))/SUMPRODUCT(EXP(0.1157*(ROW(INDIRECT("1:24"))-1)))*SUM(Assumptions!$D$24:$E$24),0))} -> 227 | BB18: =SUM(E18:P18) -> 0 | BC18: =SUM(Q18:AB18) -> 0 | BD18: =SUM(AC18:AN18) -> 389 | BE18: =SUM(AO18:AZ18) -> 1559 | BF18: =BE18*2 -> 3118
B19: Combi+ Revenue | D19: € | Q19: =Q18*Assumptions!$C$33 -> 0 | R19: =R18*Assumptions!$C$33 -> 0 | S19: =S18*Assumptions!$C$33 -> 0 | T19: =T18*Assumptions!$C$33 -> 0 | U19: =U18*Assumptions!$C$33 -> 0 | V19: =V18*Assumptions!$C$33 -> 0 | W19: =W18*Assumptions!$C$33 -> 0 | X19: =X18*Assumptions!$C$33 -> 0 | ... AZ19: =AZ18*Assumptions!$C$33 -> 3231466.9 | BB19: =SUM(E19:P19) -> 0 | BC19: =SUM(Q19:AB19) -> 0 | BD19: =SUM(AC19:AN19) -> 5537624 | BE19: =SUM(AO19:AZ19) -> 22193202 | BF19: =BF18*Assumptions!$C$33 -> 44386405
B20: Combi+ upsell | D20: € | Q20: =Q18*SUMPRODUCT(Assumptions!$E$116:$E$118,Assumptions!$F$116:$F$118) -> 0 | R20: =R18*SUMPRODUCT(Assumptions!$E$116:$E$118,Assumptions!$F$116:$F$118) -> 0 | S20: =S18*SUMPRODUCT(Assumptions!$E$116:$E$118,Assumptions!$F$116:$F$118) -> 0 | T20: =T18*SUMPRODUCT(Assumptions!$E$116:$E$118,Assumptions!$F$116:$F$118) -> 0 | U20: =U18*SUMPRODUCT(Assumptions!$E$116:$E$118,Assumptions!$F$116:$F$118) -> 0 | V20: =V18*SUMPRODUCT(Assumptions!$E$116:$E$118,Assumptions!$F$116:$F$118) -> 0 | W20: =W18*SUMPRODUCT(Assumptions!$E$116:$E$118,Assumptions!$F$116:$F$118) -> 0 | X20: =X18*SUMPRODUCT(Assumptions!$E$116:$E$118,Assumptions!$F$116:$F$118) -> 0 | ... AZ20: =AZ18*SUMPRODUCT(Assumptions!$E$116:$E$118,Assumptions!$F$116:$F$118) -> 114156.61 | BB20: =SUM(E20:P20) -> 0 | BC20: =SUM(Q20:AB20) -> 0 | BD20: =SUM(AC20:AN20) -> 195625.21 | BE20: =SUM(AO20:AZ20) -> 784009.5 | BF20: =BF18*SUMPRODUCT(Assumptions!$E$116:$E$118,Assumptions!$F$116:$F$118) -> 1568019
B21: Total Combi+ Revenue | D21: € | Q21: =sum(Q19:Q20) -> 0 | R21: =sum(R19:R20) -> 0 | S21: =sum(S19:S20) -> 0 | T21: =sum(T19:T20) -> 0 | U21: =sum(U19:U20) -> 0 | V21: =sum(V19:V20) -> 0 | W21: =sum(W19:W20) -> 0 | X21: =sum(X19:X20) -> 0 | ... AZ21: =sum(AZ19:AZ20) -> 3345623.6 | BB21: =SUM(E21:P21) -> 0 | BC21: =SUM(Q21:AB21) -> 0 | BD21: =SUM(AC21:AN21) -> 5733249.2 | BE21: =SUM(AO21:AZ21) -> 22977212 | BF21: =BE21*2 -> 45954424
B23: INSTALLATION REVENUES | D23: €
B24: Units installed | D24: # | E24: =E6+E12+E18 -> 0 | F24: =F6+F12+F18 -> 0 | G24: =G6+G12+G18 -> 0 | H24: =H6+H12+H18 -> 0 | I24: =I6+I12+I18 -> 0 | J24: =J6+J12+J18 -> 0 | K24: =K6+K12+K18 -> 0 | L24: =L6+L12+L18 -> 0 | ... AZ24: =AZ6+AZ12+AZ18 -> 710 | BB24: =SUM(E24:P24) -> 0 | BC24: =SUM(Q24:AB24) -> 0 | BD24: =SUM(AC24:AN24) -> 1430 | BE24: =SUM(AO24:AZ24) -> 5066 | BF24: =BF6+BF12+BF18 -> 10132
B25: Total Installation Revenue | D25: € | E25: =E6*Assumptions!$C$35+E12*Assumptions!$C$36+E18*Assumptions!$C$37 -> 0 | F25: =F6*Assumptions!$C$35+F12*Assumptions!$C$36+F18*Assumptions!$C$37 -> 0 | G25: =G6*Assumptions!$C$35+G12*Assumptions!$C$36+G18*Assumptions!$C$37 -> 0 | H25: =H6*Assumptions!$C$35+H12*Assumptions!$C$36+H18*Assumptions!$C$37 -> 0 | I25: =I6*Assumptions!$C$35+I12*Assumptions!$C$36+I18*Assumptions!$C$37 -> 0 | J25: =J6*Assumptions!$C$35+J12*Assumptions!$C$36+J18*Assumptions!$C$37 -> 0 | K25: =K6*Assumptions!$C$35+K12*Assumptions!$C$36+K18*Assumptions!$C$37 -> 0 | L25: =L6*Assumptions!$C$35+L12*Assumptions!$C$36+L18*Assumptions!$C$37 -> 0 | ... AZ25: =AZ6*Assumptions!$C$35+AZ12*Assumptions!$C$36+AZ18*Assumptions!$C$37 -> 2018181.8 | BB25: =SUM(E25:P25) -> 0 | BC25: =SUM(Q25:AB25) -> 0 | BD25: =SUM(AC25:AN25) -> 3952066.1 | BE25: =SUM(AO25:AZ25) -> 14299835 | BF25: =BE25*2 -> 28599669
B27: SERVICE REVENUES
B28: Installed base (TTK) | D28: # | Q28: =Q6 -> 0 | R28: =R6 -> 0 | S28: =S6 -> 0 | T28: =T6 -> 0 | U28: =U6 -> 0 | V28: =V6 -> 0 | W28: =W6 -> 0 | X28: =X6 -> 0 | ... AC28: =AC6 -> 31 | AD28: =AC28+AD6 -> 65 | AE28: =AD28+AE6 -> 103 | AF28: =AE28+AF6 -> 144 | AG28: =AF28+AG6 -> 189 | AH28: =AG28+AH6 -> 239 | AI28: =AH28+AI6 -> 293 | AJ28: =AI28+AJ6 -> 352 | AK28: =AJ28+AK6 -> 417 | ... AZ28: =AY28+AZ6 -> 2600 | BB28: =SUM(E28:P28) -> 0 | BC28: =SUM(Q28:AB28) -> 0 | BD28: =AN28 -> 652 | BE28: =AZ28 -> 2600 | BF28: =BF24*0.4 -> 4052.8
B29: Installed base (Combi) | D29: # | Q29: =Q12 -> 0 | R29: =R12 -> 0 | S29: =S12 -> 0 | T29: =T12 -> 0 | U29: =U12 -> 0 | V29: =V12 -> 0 | W29: =W12 -> 0 | X29: =X12 -> 0 | ... AC29: =AC12 -> 16 | AD29: =AC29+AD12 -> 34 | AE29: =AD29+AE12 -> 54 | AF29: =AE29+AF12 -> 76 | AG29: =AF29+AG12 -> 101 | AH29: =AG29+AH12 -> 129 | AI29: =AH29+AI12 -> 161 | AJ29: =AI29+AJ12 -> 197 | AK29: =AJ29+AK12 -> 237 | ... AZ29: =AY29+AZ12 -> 1948 | BB29: =SUM(E29:P29) -> 0 | BC29: =SUM(Q29:AB29) -> 0 | BD29: =AN29 -> 389 | BE29: =AZ29 -> 1948 | BF29: =BF24*0.3 -> 3039.6
B30: Installed base (Combi+) | Q30: =Q18 -> 0 | R30: =R18 -> 0 | S30: =S18 -> 0 | T30: =T18 -> 0 | U30: =U18 -> 0 | V30: =V18 -> 0 | W30: =W18 -> 0 | X30: =X18 -> 0 | ... AC30: =AC18 -> 16 | AD30: =AC30+AD18 -> 34 | AE30: =AD30+AE18 -> 54 | AF30: =AE30+AF18 -> 76 | AG30: =AF30+AG18 -> 101 | AH30: =AG30+AH18 -> 129 | AI30: =AH30+AI18 -> 161 | AJ30: =AI30+AJ18 -> 197 | AK30: =AJ30+AK18 -> 237 | ... AZ30: =AY30+AZ18 -> 1948 | BB30: =SUM(E30:P30) -> 0 | BC30: =SUM(Q30:AB30) -> 0 | BD30: =AN30 -> 389 | BE30: =AZ30 -> 1948 | BF30: =BF24*0.3 -> 3039.6
B31: Total Service Revenue | D31: € | Q31: =Q41*SUMPRODUCT(Assumptions!$E$128:$E$129,Assumptions!$F$128:$F$129) -> 0 | R31: =R41*SUMPRODUCT(Assumptions!$E$128:$E$129,Assumptions!$F$128:$F$129) -> 0 | S31: =S41*SUMPRODUCT(Assumptions!$E$128:$E$129,Assumptions!$F$128:$F$129) -> 0 | T31: =T41*SUMPRODUCT(Assumptions!$E$128:$E$129,Assumptions!$F$128:$F$129) -> 0 | U31: =U41*SUMPRODUCT(Assumptions!$E$128:$E$129,Assumptions!$F$128:$F$129) -> 0 | V31: =V41*SUMPRODUCT(Assumptions!$E$128:$E$129,Assumptions!$F$128:$F$129) -> 0 | W31: =W41*SUMPRODUCT(Assumptions!$E$128:$E$129,Assumptions!$F$128:$F$129) -> 0 | X31: =X41*SUMPRODUCT(Assumptions!$E$128:$E$129,Assumptions!$F$128:$F$129) -> 0 | ... AB31: =AB41*SUMPRODUCT(Assumptions!$E$128:$E$129,Assumptions!$F$128:$F$129) -> 0 | AC31: =AC41*SUMPRODUCT(Assumptions!$E$128:$E$129,Assumptions!$F$128:$F$129)+Q31 -> 4347 | AD31: =AD41*SUMPRODUCT(Assumptions!$E$128:$E$129,Assumptions!$F$128:$F$129)+R31 -> 4830 | AE31: =AE41*SUMPRODUCT(Assumptions!$E$128:$E$129,Assumptions!$F$128:$F$129)+S31 -> 5382 | AF31: =AF41*SUMPRODUCT(Assumptions!$E$128:$E$129,Assumptions!$F$128:$F$129)+T31 -> 5865 | AG31: =AG41*SUMPRODUCT(Assumptions!$E$128:$E$129,Assumptions!$F$128:$F$129)+U31 -> 6555 | AH31: =AH41*SUMPRODUCT(Assumptions!$E$128:$E$129,Assumptions!$F$128:$F$129)+V31 -> 7314 | AI31: =AI41*SUMPRODUCT(Assumptions!$E$128:$E$129,Assumptions!$F$128:$F$129)+W31 -> 8142 | AJ31: =AJ41*SUMPRODUCT(Assumptions!$E$128:$E$129,Assumptions!$F$128:$F$129)+X31 -> 9039 | ... AZ31: =AZ41*SUMPRODUCT(Assumptions!$E$128:$E$129,Assumptions!$F$128:$F$129)+AN31 -> 62790 | BB31: =SUM(E31:P31) -> 0 | BC31: =SUM(Q31:AB31) -> 0 | BD31: =SUM(AC31:AN31) -> 98670 | BE31: =SUM(AO31:AZ31) -> 448224 | BF31: =(BE31*2)+BE31 -> 1344672
B33: SUBSIDIES & GRANTS
B34: All other | D34: € | E34: 0 | F34: 0 | G34: 0 | H34: 0 | I34: 0 | J34: 0 | K34: 0 | L34: 0 | M34: 0 | N34: 19480 | O34: 78000 | P34: 0 | Q34: 0 | R34: 0 | S34: 0 | T34: 0 | U34: 0 | V34: 106782 | W34: 0 | X34: 0 | Y34: 0 | Z34: 0 | AA34: 0 | AB34: 0 | AC34: 0 | AD34: 0 | AE34: 0 | AF34: 0 | AG34: 0 | AH34: 0 | AI34: 0 | AJ34: 0 | AK34: 0 | AL34: 0 | AM34: 0 | AN34: 0 | AO34: 0 | AP34: 0 | AQ34: 0 | AR34: 0 | AS34: 0 | AT34: 0 | AU34: 0 | AV34: 0 | AW34: 0 | AX34: 0 | AY34: 0 | AZ34: 0 | BB34: =SUM(E34:P34) -> 97480 | BC34: =SUM(Q34:AB34) -> 106782 | BD34: =SUM(AC34:AN34) -> 0 | BE34: =SUM(AO34:AZ34) -> 0 | BF34: 0
B35: Total Subsidies & Grants | D35: € | E35: =sum(E34) -> 0 | F35: =sum(F34) -> 0 | G35: =sum(G34) -> 0 | H35: =sum(H34) -> 0 | I35: =sum(I34) -> 0 | J35: =sum(J34) -> 0 | K35: =sum(K34) -> 0 | L35: =sum(L34) -> 0 | ... AZ35: =sum(AZ34) -> 0 | BB35: =SUM(E35:P35) -> 97480 | BC35: =SUM(Q35:AB35) -> 106782 | BD35: =BD34 -> 0 | BE35: =BE34 -> 0 | BF35: =BF34 -> 0
B37: TOTAL REVENUE | E37: =E9+E15+E21+E25+E31+E35 -> 0 | F37: =F9+F15+F21+F25+F31+F35 -> 0 | G37: =G9+G15+G21+G25+G31+G35 -> 0 | H37: =H9+H15+H21+H25+H31+H35 -> 0 | I37: =I9+I15+I21+I25+I31+I35 -> 0 | J37: =J9+J15+J21+J25+J31+J35 -> 0 | K37: =K9+K15+K21+K25+K31+K35 -> 0 | L37: =L9+L15+L21+L25+L31+L35 -> 0 | ... AZ37: =AZ9+AZ15+AZ21+AZ25+AZ31+AZ35 -> 10491786 | BB37: =BB9+BB15+BB21+BB25+BB31+BB35 -> 97480 | BC37: =BC9+BC15+BC21+BC25+BC31+BC35 -> 106782 | BD37: =SUM(AC37:AN37) -> 20475120 | BE37: =SUM(AO37:AZ37) -> 74302035 | BF37: =BF9+BF15+BF21+BF25+BF31+BF35 -> 1.4905229e+08
B40: Installed Base | E40: =sum(E28:E30) -> 0 | F40: =sum(F28:F30) -> 0 | G40: =sum(G28:G30) -> 0 | H40: =sum(H28:H30) -> 0 | I40: =sum(I28:I30) -> 0 | J40: =sum(J28:J30) -> 0 | K40: =sum(K28:K30) -> 0 | L40: =sum(L28:L30) -> 0 | ... AZ40: =sum(AZ28:AZ30) -> 6496 | BB40: =sum(BB28:BB30) -> 0 | BC40: =sum(BC28:BC30) -> 0 | BD40: =sum(BD28:BD30) -> 1430 | BE40: =sum(BE28:BE30) -> 6496 | BF40: =sum(BF28:BF30) -> 10132
B41: Units sold | D41: # | E41: =E6+E12+E18 -> 0 | F41: =F6+F12+F18 -> 0 | G41: =G6+G12+G18 -> 0 | H41: =H6+H12+H18 -> 0 | I41: =I6+I12+I18 -> 0 | J41: =J6+J12+J18 -> 0 | K41: =K6+K12+K18 -> 0 | L41: =L6+L12+L18 -> 0 | ... AZ41: =AZ6+AZ12+AZ18 -> 710 | BB41: 0 | BC41: 0 | BD41: =SUM(AC41:AN41) -> 1430 | BE41: =SUM(AO41:AZ41) -> 5066 | BF41: =BF24 -> 10132

Sheet COGS
B1: Tarnoc B.V. — COGS Schedule (€)
E2: 2025 | Q2: 2026 | AC2: 2027 | AO2: 2028
E3: 45658 | F3: 45689 | G3: 45717 | H3: 45748 | I3: 45778 | J3: 45809 | K3: 45839 | L3: 45870 | M3: 45901 | N3: 45931 | O3: 45962 | P3: 45992 | Q3: 46023 | R3: 46054 | S3: 46082 | T3: 46113 | U3: 46143 | V3: 46174 | W3: 46204 | X3: 46235 | Y3: 46266 | Z3: 46296 | AA3: 46327 | AB3: 46357 | AC3: 46388 | AD3: 46419 | AE3: 46447 | AF3: 46478 | AG3: 46508 | AH3: 46539 | AI3: 46569 | AJ3: 46600 | AK3: 46631 | AL3: 46661 | AM3: 46692 | AN3: 46722 | AO3: 46753 | AP3: 46784 | AQ3: 46813 | AR3: 46844 | AS3: 46874 | AT3: 46905 | AU3: 46935 | AV3: 46966 | AW3: 46997 | AX3: 47027 | AY3: 47058 | AZ3: 47088 | BB3: 2025 | BC3: 2026 | BD3: 2027 | BE3: 2028 | BF3: 2029
B6: TTK
B7: TTK | D7: € | Q7: =IFNA('Revenue Forecast'!Q6*VLOOKUP('Revenue Forecast'!$BD$41+'Revenue Forecast'!$BE$41,Assumptions!$B$70:$C$72,2,TRUE),0) -> 0 | R7: =IFNA('Revenue Forecast'!R6*VLOOKUP('Revenue Forecast'!$BD$41+'Revenue Forecast'!$BE$41,Assumptions!$B$70:$C$72,2,TRUE),0) -> 0 | S7: =IFNA('Revenue Forecast'!S6*VLOOKUP('Revenue Forecast'!$BD$41+'Revenue Forecast'!$BE$41,Assumptions!$B$70:$C$72,2,TRUE),0) -> 0 | T7: =IFNA('Revenue Forecast'!T6*VLOOKUP('Revenue Forecast'!$BD$41+'Revenue Forecast'!$BE$41,Assumptions!$B$70:$C$72,2,TRUE),0) -> 0 | U7: =IFNA('Revenue Forecast'!U6*VLOOKUP('Revenue Forecast'!$BD$41+'Revenue Forecast'!$BE$41,Assumptions!$B$70:$C$72,2,TRUE),0) -> 0 | V7: =IFNA('Revenue Forecast'!V6*VLOOKUP('Revenue Forecast'!$BD$41+'Revenue Forecast'!$BE$41,Assumptions!$B$70:$C$72,2,TRUE),0) -> 0 | W7: =IFNA('Revenue Forecast'!W6*VLOOKUP('Revenue Forecast'!$BD$41+'Revenue Forecast'!$BE$41,Assumptions!$B$70:$C$72,2,TRUE),0) -> 0 | X7: =IFNA('Revenue Forecast'!X6*VLOOKUP('Revenue Forecast'!$BD$41+'Revenue Forecast'!$BE$41,Assumptions!$B$70:$C$72,2,TRUE),0) -> 0 | ... AZ7: =IFNA('Revenue Forecast'!AZ6*VLOOKUP('Revenue Forecast'!$BD$41+'Revenue Forecast'!$BE$41,Assumptions!$B$70:$C$72,2,TRUE),0) -> 1812337.7 | BC7: =SUM(Q7:AB7) -> 0 | BD7: =SUM(AC7:AN7) -> 4615797.5 | BE7: =SUM(AO7:AZ7) -> 13790757 | BF7: ='Revenue Forecast'!BF6*Assumptions!$G$53 -> 19480000
B8: Upsell | D8: € | Q8: ='Revenue Forecast'!Q6*SUMPRODUCT(Assumptions!$E$116:$E$118,Assumptions!$G$116:$G$118) -> 0 | R8: ='Revenue Forecast'!R6*SUMPRODUCT(Assumptions!$E$116:$E$118,Assumptions!$G$116:$G$118) -> 0 | S8: ='Revenue Forecast'!S6*SUMPRODUCT(Assumptions!$E$116:$E$118,Assumptions!$G$116:$G$118) -> 0 | T8: ='Revenue Forecast'!T6*SUMPRODUCT(Assumptions!$E$116:$E$118,Assumptions!$G$116:$G$118) -> 0 | U8: ='Revenue Forecast'!U6*SUMPRODUCT(Assumptions!$E$116:$E$118,Assumptions!$G$116:$G$118) -> 0 | V8: ='Revenue Forecast'!V6*SUMPRODUCT(Assumptions!$E$116:$E$118,Assumptions!$G$116:$G$118) -> 0 | W8: ='Revenue Forecast'!W6*SUMPRODUCT(Assumptions!$E$116:$E$118,Assumptions!$G$116:$G$118) -> 0 | X8: ='Revenue Forecast'!X6*SUMPRODUCT(Assumptions!$E$116:$E$118,Assumptions!$G$116:$G$118) -> 0 | ... AZ8: ='Revenue Forecast'!AZ6*SUMPRODUCT(Assumptions!$E$116:$E$118,Assumptions!$G$116:$G$118) -> 55756.8 | BC8: =SUM(Q8:AB8) -> 0 | BD8: =SUM(AC8:AN8) -> 142005.6 | BE8: =SUM(AO8:AZ8) -> 424274.4 | BF8: ='Revenue Forecast'!BF6*SUMPRODUCT(Assumptions!$E$116:$E$118,Assumptions!$G$116:$G$118) -> 848548.8
B9: Total TTK COGS | D9: € | Q9: =sum(Q7:Q8) -> 0 | R9: =sum(R7:R8) -> 0 | S9: =sum(S7:S8) -> 0 | T9: =sum(T7:T8) -> 0 | U9: =sum(U7:U8) -> 0 | V9: =sum(V7:V8) -> 0 | W9: =sum(W7:W8) -> 0 | X9: =sum(X7:X8) -> 0 | ... AZ9: =sum(AZ7:AZ8) -> 1868094.5 | BB9: =SUM(E9:P9) -> 0 | BC9: =SUM(Q9:AB9) -> 0 | BD9: =SUM(AC9:AN9) -> 4757803.1 | BE9: =SUM(AO9:AZ9) -> 14215031 | BF9: =sum(BF7:BF8) -> 20328549
B11: COMBI
B12: Total COGS Combi | D12: € | Q12: =IFNA('Revenue Forecast'!Q12*(VLOOKUP('Revenue Forecast'!$BD$41+'Revenue Forecast'!$BE$41,Assumptions!$B$70:$C$72,2,TRUE)+VLOOKUP('Revenue Forecast'!$BD$12+'Revenue Forecast'!$BE$12,Assumptions!$B$82:$C$84,2,TRUE)+Assumptions!$E$78),0) -> 0 | R12: =IFNA('Revenue Forecast'!R12*(VLOOKUP('Revenue Forecast'!$BD$41+'Revenue Forecast'!$BE$41,Assumptions!$B$70:$C$72,2,TRUE)+VLOOKUP('Revenue Forecast'!$BD$12+'Revenue Forecast'!$BE$12,Assumptions!$B$82:$C$84,2,TRUE)+Assumptions!$E$78),0) -> 0 | S12: =IFNA('Revenue Forecast'!S12*(VLOOKUP('Revenue Forecast'!$BD$41+'Revenue Forecast'!$BE$41,Assumptions!$B$70:$C$72,2,TRUE)+VLOOKUP('Revenue Forecast'!$BD$12+'Revenue Forecast'!$BE$12,Assumptions!$B$82:$C$84,2,TRUE)+Assumptions!$E$78),0) -> 0 | T12: =IFNA('Revenue Forecast'!T12*(VLOOKUP('Revenue Forecast'!$BD$41+'Revenue Forecast'!$BE$41,Assumptions!$B$70:$C$72,2,TRUE)+VLOOKUP('Revenue Forecast'!$BD$12+'Revenue Forecast'!$BE$12,Assumptions!$B$82:$C$84,2,TRUE)+Assumptions!$E$78),0) -> 0 | U12: =IFNA('Revenue Forecast'!U12*(VLOOKUP('Revenue Forecast'!$BD$41+'Revenue Forecast'!$BE$41,Assumptions!$B$70:$C$72,2,TRUE)+VLOOKUP('Revenue Forecast'!$BD$12+'Revenue Forecast'!$BE$12,Assumptions!$B$82:$C$84,2,TRUE)+Assumptions!$E$78),0) -> 0 | V12: =IFNA('Revenue Forecast'!V12*(VLOOKUP('Revenue Forecast'!$BD$41+'Revenue Forecast'!$BE$41,Assumptions!$B$70:$C$72,2,TRUE)+VLOOKUP('Revenue Forecast'!$BD$12+'Revenue Forecast'!$BE$12,Assumptions!$B$82:$C$84,2,TRUE)+Assumptions!$E$78),0) -> 0 | W12: =IFNA('Revenue Forecast'!W12*(VLOOKUP('Revenue Forecast'!$BD$41+'Revenue Forecast'!$BE$41,Assumptions!$B$70:$C$72,2,TRUE)+VLOOKUP('Revenue Forecast'!$BD$12+'Revenue Forecast'!$BE$12,Assumptions!$B$82:$C$84,2,TRUE)+Assumptions!$E$78),0) -> 0 | X12: =IFNA('Revenue Forecast'!X12*(VLOOKUP('Revenue Forecast'!$BD$41+'Revenue Forecast'!$BE$41,Assumptions!$B$70:$C$72,2,TRUE)+VLOOKUP('Revenue Forecast'!$BD$12+'Revenue Forecast'!$BE$12,Assumptions!$B$82:$C$84,2,TRUE)+Assumptions!$E$78),0) -> 0 | ... AZ12: =IFNA('Revenue Forecast'!AZ12*(VLOOKUP('Revenue Forecast'!$BD$41+'Revenue Forecast'!$BE$41,Assumptions!$B$70:$C$72,2,TRUE)+VLOOKUP('Revenue Forecast'!$BD$12+'Revenue Forecast'!$BE$12,Assumptions!$B$82:$C$84,2,TRUE)+Assumptions!$E$78),0) -> 1897221.5 | BC12: =SUM(Q12:AB12) -> 0 | BD12: =SUM(AC12:AN12) -> 3251185.8 | BE12: =SUM(AO12:AZ12) -> 13029816 | BF12: ='Revenue Forecast'!BF12*(Assumptions!$G$53+Assumptions!$C$84+Assumptions!$E$78) -> 18877837
B13: Upsell | D13: € | Q13: ='Revenue Forecast'!Q12*SUMPRODUCT(Assumptions!$E$116:$E$118,Assumptions!$G$116:$G$118) -> 0 | R13: ='Revenue Forecast'!R12*SUMPRODUCT(Assumptions!$E$116:$E$118,Assumptions!$G$116:$G$118) -> 0 | S13: ='Revenue Forecast'!S12*SUMPRODUCT(Assumptions!$E$116:$E$118,Assumptions!$G$116:$G$118) -> 0 | T13: ='Revenue Forecast'!T12*SUMPRODUCT(Assumptions!$E$116:$E$118,Assumptions!$G$116:$G$118) -> 0 | U13: ='Revenue Forecast'!U12*SUMPRODUCT(Assumptions!$E$116:$E$118,Assumptions!$G$116:$G$118) -> 0 | V13: ='Revenue Forecast'!V12*SUMPRODUCT(Assumptions!$E$116:$E$118,Assumptions!$G$116:$G$118) -> 0 | W13: ='Revenue Forecast'!W12*SUMPRODUCT(Assumptions!$E$116:$E$118,Assumptions!$G$116:$G$118) -> 0 | X13: ='Revenue Forecast'!X12*SUMPRODUCT(Assumptions!$E$116:$E$118,Assumptions!$G$116:$G$118) -> 0 | ... AZ13: ='Revenue Forecast'!AZ12*SUMPRODUCT(Assumptions!$E$116:$E$118,Assumptions!$G$116:$G$118) -> 49440.6 | BC13: =SUM(Q13:AB13) -> 0 | BD13: =SUM(AC13:AN13) -> 84724.2 | BE13: =SUM(AO13:AZ13) -> 339550.2 | BF13: ='Revenue Forecast'!BF12*SUMPRODUCT(Assumptions!$E$116:$E$118,Assumptions!$G$116:$G$118) -> 679100.4
B14: Total Combi COGS | D14: € | Q14: =sum(Q12:Q13) -> 0 | R14: =sum(R12:R13) -> 0 | S14: =sum(S12:S13) -> 0 | T14: =sum(T12:T13) -> 0 | U14: =sum(U12:U13) -> 0 | V14: =sum(V12:V13) -> 0 | W14: =sum(W12:W13) -> 0 | X14: =sum(X12:X13) -> 0 | ... AZ14: =sum(AZ12:AZ13) -> 1946662.1 | BB14: =SUM(E14:P14) -> 0 | BC14: =SUM(Q14:AB14) -> 0 | BD14: =SUM(AC14:AN14) -> 3335910 | BE14: =SUM(AO14:AZ14) -> 13369367 | BF14: =sum(BF12:BF13) -> 19556938
B16: COMBI+
B17: Total COGS Combi+ | Q17: =IFNA('Revenue Forecast'!Q18*(VLOOKUP('Revenue Forecast'!$BD$41+'Revenue Forecast'!$BE$41,Assumptions!$B$70:$C$72,2,TRUE)+VLOOKUP('Revenue Forecast'!$BD$18+'Revenue Forecast'!$BE$18,Assumptions!$E$82:$F$84,2,TRUE)+Assumptions!$E$78),0) -> 0 | R17: =IFNA('Revenue Forecast'!R18*(VLOOKUP('Revenue Forecast'!$BD$41+'Revenue Forecast'!$BE$41,Assumptions!$B$70:$C$72,2,TRUE)+VLOOKUP('Revenue Forecast'!$BD$18+'Revenue Forecast'!$BE$18,Assumptions!$E$82:$F$84,2,TRUE)+Assumptions!$E$78),0) -> 0 | S17: =IFNA('Revenue Forecast'!S18*(VLOOKUP('Revenue Forecast'!$BD$41+'Revenue Forecast'!$BE$41,Assumptions!$B$70:$C$72,2,TRUE)+VLOOKUP('Revenue Forecast'!$BD$18+'Revenue Forecast'!$BE$18,Assumptions!$E$82:$F$84,2,TRUE)+Assumptions!$E$78),0) -> 0 | T17: =IFNA('Revenue Forecast'!T18*(VLOOKUP('Revenue Forecast'!$BD$41+'Revenue Forecast'!$BE$41,Assumptions!$B$70:$C$72,2,TRUE)+VLOOKUP('Revenue Forecast'!$BD$18+'Revenue Forecast'!$BE$18,Assumptions!$E$82:$F$84,2,TRUE)+Assumptions!$E$78),0) -> 0 | U17: =IFNA('Revenue Forecast'!U18*(VLOOKUP('Revenue Forecast'!$BD$41+'Revenue Forecast'!$BE$41,Assumptions!$B$70:$C$72,2,TRUE)+VLOOKUP('Revenue Forecast'!$BD$18+'Revenue Forecast'!$BE$18,Assumptions!$E$82:$F$84,2,TRUE)+Assumptions!$E$78),0) -> 0 | V17: =IFNA('Revenue Forecast'!V18*(VLOOKUP('Revenue Forecast'!$BD$41+'Revenue Forecast'!$BE$41,Assumptions!$B$70:$C$72,2,TRUE)+VLOOKUP('Revenue Forecast'!$BD$18+'Revenue Forecast'!$BE$18,Assumptions!$E$82:$F$84,2,TRUE)+Assumptions!$E$78),0) -> 0 | W17: =IFNA('Revenue Forecast'!W18*(VLOOKUP('Revenue Forecast'!$BD$41+'Revenue Forecast'!$BE$41,Assumptions!$B$70:$C$72,2,TRUE)+VLOOKUP('Revenue Forecast'!$BD$18+'Revenue Forecast'!$BE$18,Assumptions!$E$82:$F$84,2,TRUE)+Assumptions!$E$78),0) -> 0 | X17: =IFNA('Revenue Forecast'!X18*(VLOOKUP('Revenue Forecast'!$BD$41+'Revenue Forecast'!$BE$41,Assumptions!$B$70:$C$72,2,TRUE)+VLOOKUP('Revenue Forecast'!$BD$18+'Revenue Forecast'!$BE$18,Assumptions!$E$82:$F$84,2,TRUE)+Assumptions!$E$78),0) -> 0 | ... AZ17: =IFNA('Revenue Forecast'!AZ18*(VLOOKUP('Revenue Forecast'!$BD$41+'Revenue Forecast'!$BE$41,Assumptions!$B$70:$C$72,2,TRUE)+VLOOKUP('Revenue Forecast'!$BD$18+'Revenue Forecast'!$BE$18,Assumptions!$E$82:$F$84,2,TRUE)+Assumptions!$E$78),0) -> 1948124 | BC17: =SUM(Q17:AB17) -> 0 | BD17: =SUM(AC17:AN17) -> 3338415.1 | BE17: =SUM(AO17:AZ17) -> 13379407 | BF17: ='Revenue Forecast'!BF18*(Assumptions!$G$53+Assumptions!$F$84+Assumptions!$E$78) -> 19444160
B18: Upsell | Q18: ='Revenue Forecast'!Q18*SUMPRODUCT(Assumptions!$E$116:$E$118,Assumptions!$G$116:$G$118) -> 0 | R18: ='Revenue Forecast'!R18*SUMPRODUCT(Assumptions!$E$116:$E$118,Assumptions!$G$116:$G$118) -> 0 | S18: ='Revenue Forecast'!S18*SUMPRODUCT(Assumptions!$E$116:$E$118,Assumptions!$G$116:$G$118) -> 0 | T18: ='Revenue Forecast'!T18*SUMPRODUCT(Assumptions!$E$116:$E$118,Assumptions!$G$116:$G$118) -> 0 | U18: ='Revenue Forecast'!U18*SUMPRODUCT(Assumptions!$E$116:$E$118,Assumptions!$G$116:$G$118) -> 0 | V18: ='Revenue Forecast'!V18*SUMPRODUCT(Assumptions!$E$116:$E$118,Assumptions!$G$116:$G$118) -> 0 | W18: ='Revenue Forecast'!W18*SUMPRODUCT(Assumptions!$E$116:$E$118,Assumptions!$G$116:$G$118) -> 0 | X18: ='Revenue Forecast'!X18*SUMPRODUCT(Assumptions!$E$116:$E$118,Assumptions!$G$116:$G$118) -> 0 | ... AZ18: ='Revenue Forecast'!AZ18*SUMPRODUCT(Assumptions!$E$116:$E$118,Assumptions!$G$116:$G$118) -> 49440.6 | BC18: =SUM(Q18:AB18) -> 0 | BD18: =SUM(AC18:AN18) -> 84724.2 | BE18: =SUM(AO18:AZ18) -> 339550.2 | BF18: ='Revenue Forecast'!BF18*SUMPRODUCT(Assumptions!$E$116:$E$118,Assumptions!$G$116:$G$118) -> 679100.4
B19: Total Combi+ COGS | Q19: =sum(Q17:Q18) -> 0 | R19: =sum(R17:R18) -> 0 | S19: =sum(S17:S18) -> 0 | T19: =sum(T17:T18) -> 0 | U19: =sum(U17:U18) -> 0 | V19: =sum(V17:V18) -> 0 | W19: =sum(W17:W18) -> 0 | X19: =sum(X17:X18) -> 0 | ... AZ19: =sum(AZ17:AZ18) -> 1997564.6 | BC19: =sum(BC17:BC18) -> 0 | BD19: =sum(BD17:BD18) -> 3423139.3 | BE19: =sum(BE17:BE18) -> 13718957 | BF19: =sum(BF17:BF18) -> 20123260
B21: INSTALLATION
B22: Installation COGS (pass-through, = installation revenue) | D22: € | Q22: ='Revenue Forecast'!Q25 -> 0 | R22: ='Revenue Forecast'!R25 -> 0 | S22: ='Revenue Forecast'!S25 -> 0 | T22: ='Revenue Forecast'!T25 -> 0 | U22: ='Revenue Forecast'!U25 -> 0 | V22: ='Revenue Forecast'!V25 -> 0 | W22: ='Revenue Forecast'!W25 -> 0 | X22: ='Revenue Forecast'!X25 -> 0 | ... AZ22: ='Revenue Forecast'!AZ25 -> 2018181.8 | BB22: ='Revenue Forecast'!BB25 -> 0 | BC22: ='Revenue Forecast'!BC25 -> 0 | BD22: ='Revenue Forecast'!BD25 -> 3952066.1 | BE22: ='Revenue Forecast'!BE25 -> 14299835 | BF22: ='Revenue Forecast'!BF25 -> 28599669
B24: SERVICE REVENUES
B25: Installed base (TTK) | D25: # | Q25: =Q4 | R25: =R4 | S25: =S4 | T25: =T4 | U25: =U4 | V25: =V4 | W25: =W4 | X25: =X4 | ... AB25: =AB4 | AC25: ='Revenue Forecast'!AC6 -> 31 | AD25: ='Revenue Forecast'!AD6+'Revenue Forecast'!AC28 -> 65 | AE25: ='Revenue Forecast'!AE6+'Revenue Forecast'!AD28 -> 103 | AF25: ='Revenue Forecast'!AF6+'Revenue Forecast'!AE28 -> 144 | AG25: ='Revenue Forecast'!AG6+'Revenue Forecast'!AF28 -> 189 | AH25: ='Revenue Forecast'!AH6+'Revenue Forecast'!AG28 -> 239 | AI25: ='Revenue Forecast'!AI6+'Revenue Forecast'!AH28 -> 293 | AJ25: ='Revenue Forecast'!AJ6+'Revenue Forecast'!AI28 -> 352 | AK25: ='Revenue Forecast'!AK6+'Revenue Forecast'!AJ28 -> 417 | ... AZ25: ='Revenue Forecast'!AZ6+'Revenue Forecast'!AY28 -> 2600 | BB25: =SUM(E25:P25) -> 0 | BC25: =SUM(Q25:AB25) -> 0 | BD25: =AN25 -> 652 | BE25: =AZ25 -> 2600 | BF25: ='Revenue Forecast'!BF28 -> 4052.8
B26: Installed base (Combi) | D26: # | Q26: =Q10 | R26: =R10 | S26: =S10 | T26: =T10 | U26: =U10 | V26: =V10 | W26: =W10 | X26: =X10 | ... AB26: =AB10 | AC26: ='Revenue Forecast'!AC12 -> 16 | AD26: ='Revenue Forecast'!AD12+'Revenue Forecast'!AC29 -> 34 | AE26: ='Revenue Forecast'!AE12+'Revenue Forecast'!AD29 -> 54 | AF26: ='Revenue Forecast'!AF12+'Revenue Forecast'!AE29 -> 76 | AG26: ='Revenue Forecast'!AG12+'Revenue Forecast'!AF29 -> 101 | AH26: ='Revenue Forecast'!AH12+'Revenue Forecast'!AG29 -> 129 | AI26: ='Revenue Forecast'!AI12+'Revenue Forecast'!AH29 -> 161 | AJ26: ='Revenue Forecast'!AJ12+'Revenue Forecast'!AI29 -> 197 | AK26: ='Revenue Forecast'!AK12+'Revenue Forecast'!AJ29 -> 237 | ... AZ26: ='Revenue Forecast'!AZ12+'Revenue Forecast'!AY29 -> 1948 | BB26: =SUM(E26:P26) -> 0 | BC26: =SUM(Q26:AB26) -> 0 | BD26: =AN26 -> 389 | BE26: =AZ26 -> 1948 | BF26: ='Revenue Forecast'!BF29 -> 3039.6
B27: Total Service Revenue | D27: € | Q27: ='Revenue Forecast'!Q41*SUMPRODUCT(Assumptions!$E$128:$E$129,Assumptions!$G$128:$G$129)+E27 -> 0 | R27: ='Revenue Forecast'!R41*SUMPRODUCT(Assumptions!$E$128:$E$129,Assumptions!$G$128:$G$129)+F27 -> 0 | S27: ='Revenue Forecast'!S41*SUMPRODUCT(Assumptions!$E$128:$E$129,Assumptions!$G$128:$G$129)+G27 -> 0 | T27: ='Revenue Forecast'!T41*SUMPRODUCT(Assumptions!$E$128:$E$129,Assumptions!$G$128:$G$129)+H27 -> 0 | U27: ='Revenue Forecast'!U41*SUMPRODUCT(Assumptions!$E$128:$E$129,Assumptions!$G$128:$G$129)+I27 -> 0 | V27: ='Revenue Forecast'!V41*SUMPRODUCT(Assumptions!$E$128:$E$129,Assumptions!$G$128:$G$129)+J27 -> 0 | W27: ='Revenue Forecast'!W41*SUMPRODUCT(Assumptions!$E$128:$E$129,Assumptions!$G$128:$G$129)+K27 -> 0 | X27: ='Revenue Forecast'!X41*SUMPRODUCT(Assumptions!$E$128:$E$129,Assumptions!$G$128:$G$129)+L27 -> 0 | ... AZ27: ='Revenue Forecast'!AZ41*SUMPRODUCT(Assumptions!$E$128:$E$129,Assumptions!$G$128:$G$129)+AN27 -> 28938 | BB27: =SUM(E27:P27) -> 0 | BC27: =SUM(Q27:AB27) -> 0 | BD27: =sum(AC27:AN27) -> 45474 | BE27: =sum(AO27:AZ27)+BD27 -> 252046.8 | BF27: =(BE27*2)+BE27 -> 756140.4
B29: TOTAL COGS | M29: =M7+M12 -> 0 | N29: =N9+N14+N22+N27 -> 0 | O29: =O9+O14+O22+O27 -> 0 | P29: =P9+P14+P22+P27 -> 0 | Q29: =Q9+Q14+Q19+Q22+Q27 -> 0 | R29: =R9+R14+R19+R22+R27 -> 0 | S29: =S9+S14+S19+S22+S27 -> 0 | T29: =T9+T14+T19+T22+T27 -> 0 | U29: =U9+U14+U19+U22+U27 -> 0 | V29: =V9+V14+V19+V22+V27 -> 0 | W29: =W9+W14+W19+W22+W27 -> 0 | X29: =X9+X14+X19+X22+X27 -> 0 | ... AZ29: =AZ9+AZ14+AZ19+AZ22+AZ27 -> 7859441 | BB29: =BB9+BB14+BB19+BB22+BB27 -> 0 | BC29: =BC9+BC14+BC19+BC22+BC27 -> 0 | BD29: =BD9+BD14+BD19+BD22+BD27 -> 15514392 | BE29: =BE9+BE14+BE19+BE22+BE27 -> 55855236 | BF29: =BF9+BF14+BF19+BF22+BF27 -> 89364557

Sheet OPEX
B1: Tarnoc B.V. — OPEX Forecast (€, negative = cost) | U1: Actual | V1: Projected
G2: 2025 | S2: 2026 | AE2: 2027 | AQ2: 2028
G3: 45658 | H3: 45689 | I3: 45717 | J3: 45748 | K3: 45778 | L3: 45809 | M3: 45839 | N3: 45870 | O3: 45901 | P3: 45931 | Q3: 45962 | R3: 45992 | S3: 46023 | T3: 46054 | U3: 46082 | V3: 46113 | W3: 46143 | X3: 46174 | Y3: 46204 | Z3: 46235 | AA3: 46266 | AB3: 46296 | AC3: 46327 | AD3: 46357 | AE3: 46388 | AF3: 46419 | AG3: 46447 | AH3: 46478 | AI3: 46508 | AJ3: 46539 | AK3: 46569 | AL3: 46600 | AM3: 46631 | AN3: 46661 | AO3: 46692 | AP3: 46722 | AQ3: 46753 | AR3: 46784 | AS3: 46813 | AT3: 46844 | AU3: 46874 | AV3: 46905 | AW3: 46935 | AX3: 46966 | AY3: 46997 | AZ3: 47027 | BA3: 47058 | BB3: 47088 | BD3: 2025 | BE3: 2026 | BF3: 2027 | BG3: 2028 | BH3: 2029
B5: PERSONNEL
B6: R&D | D6: € | O6: =Personnel!Q49 -> 47500 | P6: =Personnel!R49 -> 47500 | Q6: =Personnel!S49 -> 47500 | R6: =Personnel!T49 -> 47500 | S6: =Personnel!U49 -> 50700 | T6: =Personnel!V49 -> 50700 | U6: =Personnel!W49 -> 50700 | V6: =Personnel!X49 -> 50700 | ... BB6: =Personnel!BD49 -> 110364.77 | BD6: =SUM(G6:R6) -> 190000 | BE6: =SUM(S6:AD6) -> 705160 | BF6: =SUM(AE6:AP6) -> 1186575.2 | BG6: =SUM(AQ6:BB6) -> 1314001.2 | BH6: =BG6*('Financial Statements'!$BE$7/'Financial Statements'!$BD$7)^0.5 -> 2271257.9
B7: S&M | D7: € | O7: =Personnel!Q50 -> 0 | P7: =Personnel!R50 -> 0 | Q7: =Personnel!S50 -> 0 | R7: =Personnel!T50 -> 0 | S7: =Personnel!U50 -> 0 | T7: =Personnel!V50 -> 10800 | U7: =Personnel!W50 -> 10800 | V7: =Personnel!X50 -> 10800 | ... BB7: =Personnel!BD50 -> 53176.32 | BD7: =SUM(G7:R7) -> 0 | BE7: =SUM(S7:AD7) -> 183300 | BF7: =SUM(AE7:AP7) -> 331128 | BG7: =SUM(AQ7:BB7) -> 620118.24 | BH7: =BG7*('Financial Statements'!$BE$7/'Financial Statements'!$BD$7)^0.5 -> 1071877.6
B8: G&A | D8: € | O8: =Personnel!Q51 -> 11500 | P8: =Personnel!R51 -> 11500 | Q8: =Personnel!S51 -> 11500 | R8: =Personnel!T51 -> 11500 | S8: =Personnel!U51 -> 11820 | T8: =Personnel!V51 -> 11820 | U8: =Personnel!W51 -> 11820 | V8: =Personnel!X51 -> 11820 | ... BB8: =Personnel!BD51 -> 55445.088 | BD8: =SUM(G8:R8) -> 46000 | BE8: =SUM(S8:AD8) -> 222060 | BF8: =SUM(AE8:AP8) -> 520843.2 | BG8: =SUM(AQ8:BB8) -> 645010.66 | BH8: =BG8*('Financial Statements'!$BE$7/'Financial Statements'!$BD$7)^0.2 -> 802851.39
B9: Total Personnel | D9: € | G9: =SUM(G6:G8) -> 0 | H9: =SUM(H6:H8) -> 0 | I9: =SUM(I6:I8) -> 0 | J9: =SUM(J6:J8) -> 0 | K9: =SUM(K6:K8) -> 0 | L9: =SUM(L6:L8) -> 0 | M9: =SUM(M6:M8) -> 0 | N9: =SUM(N6:N8) -> 0 | O9: =sum(O6:O8) -> 59000 | P9: =sum(P6:P8) -> 59000 | Q9: =sum(Q6:Q8) -> 59000 | R9: =sum(R6:R8) -> 59000 | S9: =sum(S6:S8) -> 62520 | T9: =sum(T6:T8) -> 73320 | U9: =sum(U6:U8) -> 73320 | V9: =sum(V6:V8) -> 73320 | ... BB9: =sum(BB6:BB8) -> 218986.18 | BD9: =SUM(G9:R9) -> 236000 | BE9: =SUM(S9:AD9) -> 1110520 | BF9: =SUM(AE9:AP9) -> 2038546.4 | BG9: =SUM(AQ9:BB9) -> 2579130.1 | BH9: =sum(BH6:BH8) -> 4145986.8
B11: NON-PERSONNEL
B13: R&D COSTS
B14: Kicker Development Cost | D14: € | R14: =Assumptions!E98 -> 168933 | BD14: =SUM(G14:R14) -> 168933 | BE14: =SUM(S14:AD14) -> 0 | BF14: =SUM(AE14:AP14) -> 0 | BG14: =SUM(AQ14:BB14) -> 0 | BH14: 0
B15: Ongoing Development costs | D15: € | S15: {=INDEX(Assumptions!$E$96:$I$96,MATCH(YEAR(S$3),Assumptions!$E$91:$I$91,0))} -> 10000 | T15: {=INDEX(Assumptions!$E$96:$I$96,MATCH(YEAR(T$3),Assumptions!$E$91:$I$91,0))} -> 10000 | U15: {=INDEX(Assumptions!$E$96:$I$96,MATCH(YEAR(U$3),Assumptions!$E$91:$I$91,0))} -> 10000 | V15: {=INDEX(Assumptions!$E$96:$I$96,MATCH(YEAR(V$3),Assumptions!$E$91:$I$91,0))} -> 10000 | W15: {=INDEX(Assumptions!$E$96:$I$96,MATCH(YEAR(W$3),Assumptions!$E$91:$I$91,0))} -> 10000 | X15: {=INDEX(Assumptions!$E$96:$I$96,MATCH(YEAR(X$3),Assumptions!$E$91:$I$91,0))} -> 10000 | Y15: {=INDEX(Assumptions!$E$96:$I$96,MATCH(YEAR(Y$3),Assumptions!$E$91:$I$91,0))} -> 10000 | Z15: {=INDEX(Assumptions!$E$96:$I$96,MATCH(YEAR(Z$3),Assumptions!$E$91:$I$91,0))} -> 10000 | ... BB15: {=INDEX(Assumptions!$E$96:$I$96,MATCH(YEAR(BB$3),Assumptions!$E$91:$I$91,0))} -> 16900 | BD15: =SUM(G15:R15) -> 0 | BE15: =SUM(S15:AD15) -> 120000 | BF15: =SUM(AE15:AP15) -> 156000 | BG15: =SUM(AQ15:BB15) -> 202800 | BH15: =BG15*('Financial Statements'!$BE$7/'Financial Statements'!$BD$7)^0.4 -> 314198.78
B16: Assembly partner | D16: € | AB16: =Assumptions!E101 -> 100000 | BD16: =SUM(G16:R16) -> 0 | BE16: =SUM(S16:AC16) -> 100000 | BF16: =SUM(AE16:AP16) -> 0 | BG16: =SUM(AQ16:BB16) -> 0
B17: Third party cost product development | D17: € | S17: {=INDEX(Assumptions!$E$97:$I$97,MATCH(YEAR(S$3),Assumptions!$E$91:$I$91,0))} -> 15000 | T17: {=INDEX(Assumptions!$E$97:$I$97,MATCH(YEAR(T$3),Assumptions!$E$91:$I$91,0))} -> 15000 | U17: {=INDEX(Assumptions!$E$97:$I$97,MATCH(YEAR(U$3),Assumptions!$E$91:$I$91,0))} -> 15000 | V17: {=INDEX(Assumptions!$E$97:$I$97,MATCH(YEAR(V$3),Assumptions!$E$91:$I$91,0))} -> 15000 | W17: {=INDEX(Assumptions!$E$97:$I$97,MATCH(YEAR(W$3),Assumptions!$E$91:$I$91,0))} -> 15000 | X17: {=INDEX(Assumptions!$E$97:$I$97,MATCH(YEAR(X$3),Assumptions!$E$91:$I$91,0))} -> 15000 | Y17: {=INDEX(Assumptions!$E$97:$I$97,MATCH(YEAR(Y$3),Assumptions!$E$91:$I$91,0))} -> 15000 | Z17: {=INDEX(Assumptions!$E$97:$I$97,MATCH(YEAR(Z$3),Assumptions!$E$91:$I$91,0))} -> 15000 | ... BB17: {=INDEX(Assumptions!$E$97:$I$97,MATCH(YEAR(BB$3),Assumptions!$E$91:$I$91,0))} -> 25350 | BD17: =SUM(G17:R17) -> 0 | BE17: =SUM(S17:AD17) -> 180000 | BF17: =SUM(AE17:AP17) -> 234000 | BG17: =SUM(AQ17:BB17) -> 304200 | BH17: =BG17*('Financial Statements'!$BE$7/'Financial Statements'!$BD$7)^0.4 -> 471298.17
B18: Tooling Fisher (result: 2%-3%) | D18: € | AC18: =Assumptions!E102 -> 45000 | BD18: =SUM(G18:R18) -> 0 | BE18: =SUM(S18:AC18) -> 45000 | BF18: =SUM(AE18:AP18) -> 0 | BG18: =SUM(AQ18:BB18) -> 0 | BH18: 0
B19: Total R&D | R19: =R14+R15+R16 -> 168933 | S19: =sum(S14:S18) -> 25000 | T19: =sum(T14:T18) -> 25000 | U19: =sum(U14:U18) -> 25000 | V19: =sum(V14:V18) -> 25000 | W19: =sum(W14:W18) -> 25000 | X19: =sum(X14:X18) -> 25000 | Y19: =sum(Y14:Y18) -> 25000 | Z19: =sum(Z14:Z18) -> 25000 | ... BB19: =sum(BB14:BB18) -> 42250 | BD19: =SUM(G19:R19) -> 168933 | BE19: =SUM(S19:AD19) -> 445000 | BF19: =SUM(AE19:AP19) -> 390000 | BG19: =SUM(AQ19:BB19) -> 507000 | BH19: =sum(BH14:BH18) -> 785496.95
BE20: =BE19/BD19-1 -> 1.6341804 | BF20: =BF19/BE19-1 -> -0.12359551 | BG20: =BG19/BF19-1 -> 0.3 | BH20: =BH19/BG19-1 -> 0.54930365
B21: SALES & MARKETING
B22: Baseline Sales & Marketting | S22: {=INDEX(Assumptions!$E$94:$I$94,MATCH(YEAR(S$3),Assumptions!$E$91:$I$91,0))} -> 14000 | T22: {=INDEX(Assumptions!$E$94:$I$94,MATCH(YEAR(T$3),Assumptions!$E$91:$I$91,0))} -> 14000 | U22: {=INDEX(Assumptions!$E$94:$I$94,MATCH(YEAR(U$3),Assumptions!$E$91:$I$91,0))} -> 14000 | V22: {=INDEX(Assumptions!$E$94:$I$94,MATCH(YEAR(V$3),Assumptions!$E$91:$I$91,0))} -> 14000 | W22: {=INDEX(Assumptions!$E$94:$I$94,MATCH(YEAR(W$3),Assumptions!$E$91:$I$91,0))} -> 14000 | X22: {=INDEX(Assumptions!$E$94:$I$94,MATCH(YEAR(X$3),Assumptions!$E$91:$I$91,0))} -> 14000 | Y22: {=INDEX(Assumptions!$E$94:$I$94,MATCH(YEAR(Y$3),Assumptions!$E$91:$I$91,0))} -> 14000 | Z22: {=INDEX(Assumptions!$E$94:$I$94,MATCH(YEAR(Z$3),Assumptions!$E$91:$I$91,0))} -> 14000 | ... BB22: {=INDEX(Assumptions!$E$94:$I$94,MATCH(YEAR(BB$3),Assumptions!$E$91:$I$91,0))} -> 23660 | BD22: =SUM(G22:R22) -> 0 | BE22: =SUM(S22:AD22) -> 168000 | BF22: =SUM(AE22:AP22) -> 218400 | BG22: =SUM(AQ22:BB22) -> 283920 | BH22: =BG22*('Financial Statements'!$BE$7/'Financial Statements'!$BD$7)^0.5 -> 490757.18
B23: Sales & Marketing (3rd party) | D23: € | S23: 7000 | T23: 7000 | U23: 7000 | V23: 7000 | W23: 7000 | X23: 7000 | Y23: 7000 | Z23: 7000 | AA23: 7000 | AB23: 10000 | AC23: 10000 | AD23: 10000 | AE23: =('Revenue Forecast'!AC6+'Revenue Forecast'!AC12)*VLOOKUP('Revenue Forecast'!AC40,Assumptions!$G$106:$H$113,2,TRUE) -> 28200 | AF23: =('Revenue Forecast'!AD6+'Revenue Forecast'!AD12)*VLOOKUP('Revenue Forecast'!AD40,Assumptions!$G$106:$H$113,2,TRUE) -> 31200 | AG23: =('Revenue Forecast'!AE6+'Revenue Forecast'!AE12)*VLOOKUP('Revenue Forecast'!AE40,Assumptions!$G$106:$H$113,2,TRUE) -> 34800 | AH23: =('Revenue Forecast'!AF6+'Revenue Forecast'!AF12)*VLOOKUP('Revenue Forecast'!AF40,Assumptions!$G$106:$H$113,2,TRUE) -> 37800 | AI23: =('Revenue Forecast'!AG6+'Revenue Forecast'!AG12)*VLOOKUP('Revenue Forecast'!AG40,Assumptions!$G$106:$H$113,2,TRUE) -> 42000 | AJ23: =('Revenue Forecast'!AH6+'Revenue Forecast'!AH12)*VLOOKUP('Revenue Forecast'!AH40,Assumptions!$G$106:$H$113,2,TRUE) -> 46800 | AK23: =('Revenue Forecast'!AI6+'Revenue Forecast'!AI12)*VLOOKUP('Revenue Forecast'!AI40,Assumptions!$G$106:$H$113,2,TRUE) -> 51600 | AL23: =('Revenue Forecast'!AJ6+'Revenue Forecast'!AJ12)*VLOOKUP('Revenue Forecast'!AJ40,Assumptions!$G$106:$H$113,2,TRUE) -> 57000 | ... BB23: =('Revenue Forecast'!AZ6+'Revenue Forecast'!AZ12)*VLOOKUP('Revenue Forecast'!AZ40,Assumptions!$G$106:$H$113,2,TRUE) -> 118702.08 | BD23: =SUM(G23:R23) -> 0 | BE23: =SUM(S23:AD23) -> 93000 | BF23: =SUM(AE23:AP23) -> 565560 | BG23: =SUM(AQ23:BB23) -> 1142292.5 | BH23: =('Revenue Forecast'!BF6+'Revenue Forecast'!BF12)*VLOOKUP('Revenue Forecast'!BF40,Assumptions!$G$106:$H$113,2,TRUE) -> 1723760.6
B24: Customer journey (third party) | D24: € | R24: =Assumptions!$E$99 -> 10000 | X24: =Assumptions!E99 -> 10000 | BD24: =SUM(G24:R24) -> 10000 | BE24: =SUM(T24:AC24) -> 10000 | BF24: =SUM(AE24:AP24) -> 0 | BG24: =SUM(AQ24:BB24) -> 0 | BH24: =BG24*('Financial Statements'!$BE$7/'Financial Statements'!$BD$7)^0.5 -> 0
B25: Branding + Website (third party cost) | D25: € | R25: =Assumptions!$E$100 -> 10000 | W25: =Assumptions!E100 -> 10000 | BD25: =SUM(G25:R25) -> 10000 | BE25: =SUM(S25:AH25) -> 10000 | BF25: =SUM(AE25:AP25) -> 0 | BG25: =SUM(AQ25:BB25) -> 0 | BH25: =BG25*('Financial Statements'!$BE$7/'Financial Statements'!$BD$7)^0.5 -> 0
B26: Total S&M | G26: =SUM(G23:G25) -> 0 | H26: =SUM(H23:H25) -> 0 | I26: =SUM(I23:I25) -> 0 | J26: =SUM(J23:J25) -> 0 | K26: =SUM(K23:K25) -> 0 | L26: =SUM(L23:L25) -> 0 | M26: =SUM(M23:M25) -> 0 | N26: =SUM(N23:N25) -> 0 | ... R26: =SUM(R23:R25) -> 20000 | S26: =sum(S22:S25) -> 21000 | T26: =sum(T22:T25) -> 21000 | U26: =sum(U22:U25) -> 21000 | V26: =sum(V22:V25) -> 21000 | W26: =sum(W22:W25) -> 31000 | X26: =sum(X22:X25) -> 31000 | Y26: =sum(Y22:Y25) -> 21000 | Z26: =sum(Z22:Z25) -> 21000 | ... BB26: =sum(BB22:BB25) -> 142362.08 | BD26: =SUM(G26:R26) -> 20000 | BE26: =SUM(S26:AD26) -> 281000 | BF26: =SUM(AE26:AP26) -> 783960 | BG26: =SUM(AQ26:BB26) -> 1426212.5 | BH26: =sum(BH22:BH25) -> 2214517.8
BE27: =BE26/BD26-1 -> 13.05 | BF27: =BF26/BE26-1 -> 1.7898932 | BG27: =BG26/BF26-1 -> 0.81924139 | BH27: =BH26/BG26-1 -> 0.55272644
B28: G&A (NON-LABOUR)
B29: Office rent (part of General) | D29: € | G29: =Assumptions!$E$92 -> 5000 | H29: =Assumptions!$E$92 -> 5000 | I29: =Assumptions!$E$92 -> 5000 | J29: =Assumptions!$E$92 -> 5000 | K29: =Assumptions!$E$92 -> 5000 | L29: =Assumptions!$E$92 -> 5000 | M29: =Assumptions!$E$92 -> 5000 | N29: =Assumptions!$E$92 -> 5000 | ... R29: =Assumptions!$E$92 -> 5000 | S29: {=INDEX(Assumptions!$E$92:$I$92,MATCH(YEAR(S$3),Assumptions!$E$91:$I$91,0))} -> 5000 | T29: {=INDEX(Assumptions!$E$92:$I$92,MATCH(YEAR(T$3),Assumptions!$E$91:$I$91,0))} -> 5000 | U29: {=INDEX(Assumptions!$E$92:$I$92,MATCH(YEAR(U$3),Assumptions!$E$91:$I$91,0))} -> 5000 | V29: {=INDEX(Assumptions!$E$92:$I$92,MATCH(YEAR(V$3),Assumptions!$E$91:$I$91,0))} -> 5000 | W29: {=INDEX(Assumptions!$E$92:$I$92,MATCH(YEAR(W$3),Assumptions!$E$91:$I$91,0))} -> 5000 | X29: {=INDEX(Assumptions!$E$92:$I$92,MATCH(YEAR(X$3),Assumptions!$E$91:$I$91,0))} -> 5000 | Y29: {=INDEX(Assumptions!$E$92:$I$92,MATCH(YEAR(Y$3),Assumptions!$E$91:$I$91,0))} -> 5000 | Z29: {=INDEX(Assumptions!$E$92:$I$92,MATCH(YEAR(Z$3),Assumptions!$E$91:$I$91,0))} -> 5000 | ... BB29: {=INDEX(Assumptions!$E$92:$I$92,MATCH(YEAR(BB$3),Assumptions!$E$91:$I$91,0))} -> 8450 | BD29: =SUM(G29:R29) -> 60000 | BE29: =SUM(S29:AD29) -> 60000 | BF29: =SUM(AE29:AP29) -> 78000 | BG29: =SUM(AQ29:BB29) -> 101400 | BH29: =BG29*('Financial Statements'!$BE$7/'Financial Statements'!$BD$7)^0.2 -> 126213.62
B30: Other General | D30: € | G30: =Assumptions!$E$93 -> 7000 | H30: =Assumptions!$E$93 -> 7000 | I30: =Assumptions!$E$93 -> 7000 | J30: =Assumptions!$E$93 -> 7000 | K30: =Assumptions!$E$93 -> 7000 | L30: =Assumptions!$E$93 -> 7000 | M30: =Assumptions!$E$93 -> 7000 | N30: =Assumptions!$E$93 -> 7000 | ... R30: =Assumptions!$E$93 -> 7000 | S30: {=INDEX(Assumptions!$E$93:$I$93,MATCH(YEAR(S$3),Assumptions!$E$91:$I$91,0))} -> 7000 | T30: {=INDEX(Assumptions!$E$93:$I$93,MATCH(YEAR(T$3),Assumptions!$E$91:$I$91,0))} -> 7000 | U30: {=INDEX(Assumptions!$E$93:$I$93,MATCH(YEAR(U$3),Assumptions!$E$91:$I$91,0))} -> 7000 | V30: {=INDEX(Assumptions!$E$93:$I$93,MATCH(YEAR(V$3),Assumptions!$E$91:$I$91,0))} -> 7000 | W30: {=INDEX(Assumptions!$E$93:$I$93,MATCH(YEAR(W$3),Assumptions!$E$91:$I$91,0))} -> 7000 | X30: {=INDEX(Assumptions!$E$93:$I$93,MATCH(YEAR(X$3),Assumptions!$E$91:$I$91,0))} -> 7000 | Y30: {=INDEX(Assumptions!$E$93:$I$93,MATCH(YEAR(Y$3),Assumptions!$E$91:$I$91,0))} -> 7000 | Z30: {=INDEX(Assumptions!$E$93:$I$93,MATCH(YEAR(Z$3),Assumptions!$E$91:$I$91,0))} -> 7000 | ... BB30: {=INDEX(Assumptions!$E$93:$I$93,MATCH(YEAR(BB$3),Assumptions!$E$91:$I$91,0))} -> 11830 | BD30: =SUM(G30:R30) -> 84000 | BE30: =SUM(S30:AD30) -> 84000 | BF30: =SUM(AE30:AP30) -> 109200 | BG30: =SUM(AQ30:BB30) -> 141960 | BH30: =BG30*('Financial Statements'!$BE$7/'Financial Statements'!$BD$7)^0.2 -> 176699.07
B31: Finance & Legal etc. | D31: € | G31: =Assumptions!$E$95 -> 8000 | H31: =Assumptions!$E$95 -> 8000 | I31: =Assumptions!$E$95 -> 8000 | J31: =Assumptions!$E$95 -> 8000 | K31: =Assumptions!$E$95 -> 8000 | L31: =Assumptions!$E$95 -> 8000 | M31: =Assumptions!$E$95 -> 8000 | N31: =Assumptions!$E$95 -> 8000 | ... R31: =Assumptions!$E$95 -> 8000 | S31: {=INDEX(Assumptions!$E$95:$I$95,MATCH(YEAR(S$3),Assumptions!$E$91:$I$91,0))} -> 8000 | T31: {=INDEX(Assumptions!$E$95:$I$95,MATCH(YEAR(T$3),Assumptions!$E$91:$I$91,0))} -> 8000 | U31: {=INDEX(Assumptions!$E$95:$I$95,MATCH(YEAR(U$3),Assumptions!$E$91:$I$91,0))} -> 8000 | V31: {=INDEX(Assumptions!$E$95:$I$95,MATCH(YEAR(V$3),Assumptions!$E$91:$I$91,0))} -> 8000 | W31: {=INDEX(Assumptions!$E$95:$I$95,MATCH(YEAR(W$3),Assumptions!$E$91:$I$91,0))} -> 8000 | X31: {=INDEX(Assumptions!$E$95:$I$95,MATCH(YEAR(X$3),Assumptions!$E$91:$I$91,0))} -> 8000 | Y31: {=INDEX(Assumptions!$E$95:$I$95,MATCH(YEAR(Y$3),Assumptions!$E$91:$I$91,0))} -> 8000 | Z31: {=INDEX(Assumptions!$E$95:$I$95,MATCH(YEAR(Z$3),Assumptions!$E$91:$I$91,0))} -> 8000 | ... BB31: {=INDEX(Assumptions!$E$95:$I$95,MATCH(YEAR(BB$3),Assumptions!$E$91:$I$91,0))} -> 13520 | BD31: =SUM(G31:R31) -> 96000 | BE31: =SUM(S31:AD31) -> 96000 | BF31: =SUM(AE31:AP31) -> 124800 | BG31: =SUM(AQ31:BB31) -> 162240 | BH31: =BG31*('Financial Statements'!$BE$7/'Financial Statements'!$BD$7)^0.2 -> 201941.79
B32: Total G&A | S32: =sum(S29:S31) -> 20000 | T32: =sum(T29:T31) -> 20000 | U32: =sum(U29:U31) -> 20000 | V32: =sum(V29:V31) -> 20000 | W32: =sum(W29:W31) -> 20000 | X32: =sum(X29:X31) -> 20000 | Y32: =sum(Y29:Y31) -> 20000 | Z32: =sum(Z29:Z31) -> 20000 | ... BB32: =sum(BB29:BB31) -> 33800 | BD32: =SUM(G32:R32) -> 0 | BE32: =SUM(S32:AD32) -> 240000 | BF32: =SUM(AE32:AP32) -> 312000 | BG32: =SUM(AQ32:BB32) -> 405600 | BH32: =sum(BH29:BH31) -> 504854.48
B34: Total non-personnell | D34: € | G34: =G32+G26+G19 -> 0 | H34: =H32+H26+H19 -> 0 | I34: =I32+I26+I19 -> 0 | J34: =J32+J26+J19 -> 0 | K34: =K32+K26+K19 -> 0 | L34: =L32+L26+L19 -> 0 | M34: =M32+M26+M19 -> 0 | N34: =N32+N26+N19 -> 0 | ... BB34: =BB32+BB26+BB19 -> 218412.08 | BD34: =SUM(G34:R34) -> 188933 | BE34: =SUM(S34:AD34) -> 966000 | BF34: =SUM(AE34:AP34) -> 1485960 | BG34: =SUM(AQ34:BB34) -> 2338812.5 | BH34: =BH32+BH26+BH19 -> 3504869.3
B36: TOTAL OPEX | D36: € | G36: =G34+G9 -> 0 | H36: =H34+H9 -> 0 | I36: =I34+I9 -> 0 | J36: =J34+J9 -> 0 | K36: =K34+K9 -> 0 | L36: =L34+L9 -> 0 | M36: =M34+M9 -> 0 | N36: =N34+N9 -> 0 | ... BB36: =BB34+BB9 -> 437398.26 | BD36: =SUM(G36:R36) -> 424933 | BE36: =SUM(S36:AD36) -> 2076520 | BF36: =SUM(AE36:AP36) -> 3524506.4 | BG36: =SUM(AQ36:BB36) -> 4917942.6 | BH36: =BH34+BH9 -> 7650856.1
B38: Total R&D | D38: € | G38: =G19+G6 -> 0 | H38: =H19+H6 -> 0 | I38: =I19+I6 -> 0 | J38: =J19+J6 -> 0 | K38: =K19+K6 -> 0 | L38: =L19+L6 -> 0 | M38: =M19+M6 -> 0 | N38: =N19+N6 -> 0 | ... BB38: =BB19+BB6 -> 152614.77 | BD38: =BD19+BD6 -> 358933 | BE38: =BE19+BE6 -> 1150160 | BF38: =BF19+BF6 -> 1576575.2 | BG38: =BG19+BG6 -> 1821001.2 | BH38: =BH19+BH6 -> 3056754.8
B39: Total S&M | D39: € | G39: =G26+G7 -> 0 | H39: =H26+H7 -> 0 | I39: =I26+I7 -> 0 | J39: =J26+J7 -> 0 | K39: =K26+K7 -> 0 | L39: =L26+L7 -> 0 | M39: =M26+M7 -> 0 | N39: =N26+N7 -> 0 | ... BB39: =BB26+BB7 -> 195538.4 | BD39: =BD26+BD7 -> 20000 | BE39: =BE26+BE7 -> 464300 | BF39: =BF26+BF7 -> 1115088 | BG39: =BG26+BG7 -> 2046330.7 | BH39: =BH26+BH7 -> 3286395.4
B40: Total G&A | D40: € | G40: =G32+G8 -> 0 | H40: =H32+H8 -> 0 | I40: =I32+I8 -> 0 | J40: =J32+J8 -> 0 | K40: =K32+K8 -> 0 | L40: =L32+L8 -> 0 | M40: =M32+M8 -> 0 | N40: =N32+N8 -> 0 | ... BB40: =BB32+BB8 -> 89245.088 | BD40: =BD32+BD8 -> 46000 | BE40: =BE32+BE8 -> 462060 | BF40: =BF32+BF8 -> 832843.2 | BG40: =BG32+BG8 -> 1050610.7 | BH40: =BH32+BH8 -> 1307705.9
B41: R&D % of Total OPEX | S41: =S38/S$36 -> 0.58901338 | T41: =T38/T$36 -> 0.54335343 | U41: =U38/U$36 -> 0.54335343 | V41: =V38/V$36 -> 0.54335343 | W41: =W38/W$36 -> 0.50696491 | X41: =X38/X$36 -> 0.50696491 | Y41: =Y38/Y$36 -> 0.56815096 | Z41: =Z38/Z$36 -> 0.5235816 | ... BB41: =BB38/BB$36 -> 0.3489149 | BD41: =BD38/BD$36 -> 0.8446814 | BE41: =BE38/BE$36 -> 0.55388824 | BF41: =BF38/BF$36 -> 0.44731801 | BG41: =BG38/BG$36 -> 0.37027704 | BH41: =BH38/BH$36 -> 0.39953108
B42: S&M % of Total OPEX | S42: =S39/S$36 -> 0.16339869 | T42: =T39/T$36 -> 0.22825151 | U42: =U39/U$36 -> 0.22825151 | V42: =V39/V$36 -> 0.22825151 | W42: =W39/W$36 -> 0.27993571 | X42: =X39/X$36 -> 0.27993571 | Y42: =Y39/Y$36 -> 0.21585664 | Z42: =Z39/Z$36 -> 0.23815083 | ... BB42: =BB39/BB$36 -> 0.44704888 | BD42: =BD39/BD$36 -> 0.047066243 | BE42: =BE39/BE$36 -> 0.22359525 | BF42: =BF39/BF$36 -> 0.31638132 | BG42: =BG39/BG$36 -> 0.41609488 | BH42: =BH39/BH$36 -> 0.4295461
B43: G&A % of Total OPEX | S43: =S40/S$36 -> 0.24758792 | T43: =T40/T$36 -> 0.22839506 | U43: =U40/U$36 -> 0.22839506 | V43: =V40/V$36 -> 0.22839506 | W43: =W40/W$36 -> 0.21309938 | X43: =X40/X$36 -> 0.21309938 | Y43: =Y40/Y$36 -> 0.2159924 | Z43: =Z40/Z$36 -> 0.23826757 | ... BB43: =BB40/BB$36 -> 0.20403622 | BD43: =BD40/BD$36 -> 0.10825236 | BE43: =BE40/BE$36 -> 0.22251652 | BF43: =BF40/BF$36 -> 0.23630066 | BG43: =BG40/BG$36 -> 0.21362808 | BH43: =BH40/BH$36 -> 0.17092282

Sheet Personnel
B1: PERSONNEL — Monthly Employer Cost (€)
A2: # | B2: Name | C2: Dept | D2: Role | E2: Type | F2: Start | G2: End | H2: Monthly Cost (€) | I2: 45658 | J2: 45689 | K2: 45717 | L2: 45748 | M2: 45778 | N2: 45809 | O2: 45839 | P2: 45870 | Q2: 45901 | R2: 45931 | S2: 45962 | T2: 45992 | U2: 46023 | V2: 46054 | W2: 46082 | X2: 46113 | Y2: 46143 | Z2: 46174 | AA2: 46204 | AB2: 46235 | AC2: 46266 | AD2: 46296 | AE2: 46327 | AF2: 46357 | AG2: 46388 | AH2: 46419 | AI2: 46447 | AJ2: 46478 | AK2: 46508 | AL2: 46539 | AM2: 46569 | AN2: 46600 | AO2: 46631 | AP2: 46661 | AQ2: 46692 | AR2: 46722 | AS2: 46753 | AT2: 46784 | AU2: 46813 | AV2: 46844 | AW2: 46874 | AX2: 46905 | AY2: 46935 | AZ2: 46966 | BA2: 46997 | BB2: 47027 | BC2: 47058 | BD2: 47088 | BE2: 47119 | BF2: 47150 | BG2: 47178 | BH2: 47209 | BI2: 47239 | BJ2: 47270 | BK2: 47300 | BL2: 47331 | BM2: 47362 | BN2: 47392 | BO2: 47423 | BP2: 47453
A3: 1 | B3: R&D Engineer | C3: R&D | D3: Field Engineer | E3: Current | F3: 45901 | H3: 5500 | I3: =IF(AND(F3<=DATE(2025,1,1),OR(G3="",G3>=DATE(2025,1,1))),H3*(1+Assumptions!$C$7)^0,0) -> 0 | J3: =IF(AND(F3<=DATE(2025,2,1),OR(G3="",G3>=DATE(2025,2,1))),H3*(1+Assumptions!$C$7)^0,0) -> 0 | K3: =IF(AND(F3<=DATE(2025,3,1),OR(G3="",G3>=DATE(2025,3,1))),H3*(1+Assumptions!$C$7)^0,0) -> 0 | L3: =IF(AND(F3<=DATE(2025,4,1),OR(G3="",G3>=DATE(2025,4,1))),H3*(1+Assumptions!$C$7)^0,0) -> 0 | M3: =IF(AND(F3<=DATE(2025,5,1),OR(G3="",G3>=DATE(2025,5,1))),H3*(1+Assumptions!$C$7)^0,0) -> 0 | N3: =IF(AND(F3<=DATE(2025,6,1),OR(G3="",G3>=DATE(2025,6,1))),H3*(1+Assumptions!$C$7)^0,0) -> 0 | O3: =IF(AND(F3<=DATE(2025,7,1),OR(G3="",G3>=DATE(2025,7,1))),H3*(1+Assumptions!$C$7)^0,0) -> 0 | P3: =IF(AND(F3<=DATE(2025,8,1),OR(G3="",G3>=DATE(2025,8,1))),H3*(1+Assumptions!$C$7)^0,0) -> 0 | Q3: =IF(AND(F3<=DATE(2025,9,1),OR(G3="",G3>=DATE(2025,9,1))),H3*(1+Assumptions!$C$7)^0,0) -> 5500 | R3: =IF(AND(F3<=DATE(2025,10,1),OR(G3="",G3>=DATE(2025,10,1))),H3*(1+Assumptions!$C$7)^0,0) -> 5500 | S3: =IF(AND(F3<=DATE(2025,11,1),OR(G3="",G3>=DATE(2025,11,1))),H3*(1+Assumptions!$C$7)^0,0) -> 5500 | T3: =IF(AND(F3<=DATE(2025,12,1),OR(G3="",G3>=DATE(2025,12,1))),H3*(1+Assumptions!$C$7)^0,0) -> 5500 | U3: =IF(AND(F3<=DATE(2026,1,1),OR(G3="",G3>=DATE(2026,1,1))),H3*(1+Assumptions!$C$7)^1,0) -> 5940 | V3: =IF(AND(F3<=DATE(2026,2,1),OR(G3="",G3>=DATE(2026,2,1))),H3*(1+Assumptions!$C$7)^1,0) -> 5940 | W3: =IF(AND(F3<=DATE(2026,3,1),OR(G3="",G3>=DATE(2026,3,1))),H3*(1+Assumptions!$C$7)^1,0) -> 5940 | X3: =IF(AND(F3<=DATE(2026,4,1),OR(G3="",G3>=DATE(2026,4,1))),H3*(1+Assumptions!$C$7)^1,0) -> 5940 | Y3: =IF(AND(F3<=DATE(2026,5,1),OR(G3="",G3>=DATE(2026,5,1))),H3*(1+Assumptions!$C$7)^1,0) -> 5940 | Z3: =IF(AND(F3<=DATE(2026,6,1),OR(G3="",G3>=DATE(2026,6,1))),H3*(1+Assumptions!$C$7)^1,0) -> 5940 | AA3: =IF(AND(F3<=DATE(2026,7,1),OR(G3="",G3>=DATE(2026,7,1))),H3*(1+Assumptions!$C$7)^1,0) -> 5940 | AB3: =IF(AND(F3<=DATE(2026,8,1),OR(G3="",G3>=DATE(2026,8,1))),H3*(1+Assumptions!$C$7)^1,0) -> 5940 | AC3: =IF(AND(F3<=DATE(2026,9,1),OR(G3="",G3>=DATE(2026,9,1))),H3*(1+Assumptions!$C$7)^1,0) -> 5940 | AD3: =IF(AND(F3<=DATE(2026,10,1),OR(G3="",G3>=DATE(2026,10,1))),H3*(1+Assumptions!$C$7)^1,0) -> 5940 | AE3: =IF(AND(F3<=DATE(2026,11,1),OR(G3="",G3>=DATE(2026,11,1))),H3*(1+Assumptions!$C$7)^1,0) -> 5940 | AF3: =IF(AND(F3<=DATE(2026,12,1),OR(G3="",G3>=DATE(2026,12,1))),H3*(1+Assumptions!$C$7)^1,0) -> 5940 | AG3: =IF(AND(F3<=DATE(2027,1,1),OR(G3="",G3>=DATE(2027,1,1))),H3*(1+Assumptions!$C$7)^2,0) -> 6415.2 | AH3: =IF(AND(F3<=DATE(2027,2,1),OR(G3="",G3>=DATE(2027,2,1))),H3*(1+Assumptions!$C$7)^2,0) -> 6415.2 | AI3: =IF(AND(F3<=DATE(2027,3,1),OR(G3="",G3>=DATE(2027,3,1))),H3*(1+Assumptions!$C$7)^2,0) -> 6415.2 | AJ3: =IF(AND(F3<=DATE(2027,4,1),OR(G3="",G3>=DATE(2027,4,1))),H3*(1+Assumptions!$C$7)^2,0) -> 6415.2 | AK3: =IF(AND(F3<=DATE(2027,5,1),OR(G3="",G3>=DATE(2027,5,1))),H3*(1+Assumptions!$C$7)^2,0) -> 6415.2 | AL3: =IF(AND(F3<=DATE(2027,6,1),OR(G3="",G3>=DATE(2027,6,1))),H3*(1+Assumptions!$C$7)^2,0) -> 6415.2 | AM3: =IF(AND(F3<=DATE(2027,7,1),OR(G3="",G3>=DATE(2027,7,1))),H3*(1+Assumptions!$C$7)^2,0) -> 6415.2 | AN3: =IF(AND(F3<=DATE(2027,8,1),OR(G3="",G3>=DATE(2027,8,1))),H3*(1+Assumptions!$C$7)^2,0) -> 6415.2 | AO3: =IF(AND(F3<=DATE(2027,9,1),OR(G3="",G3>=DATE(2027,9,1))),H3*(1+Assumptions!$C$7)^2,0) -> 6415.2 | AP3: =IF(AND(F3<=DATE(2027,10,1),OR(G3="",G3>=DATE(2027,10,1))),H3*(1+Assumptions!$C$7)^2,0) -> 6415.2 | AQ3: =IF(AND(F3<=DATE(2027,11,1),OR(G3="",G3>=DATE(2027,11,1))),H3*(1+Assumptions!$C$7)^2,0) -> 6415.2 | AR3: =IF(AND(F3<=DATE(2027,12,1),OR(G3="",G3>=DATE(2027,12,1))),H3*(1+Assumptions!$C$7)^2,0) -> 6415.2 | AS3: =IF(AND(F3<=DATE(2028,1,1),OR(G3="",G3>=DATE(2028,1,1))),H3*(1+Assumptions!$C$7)^3,0) -> 6928.416 | AT3: =IF(AND(F3<=DATE(2028,2,1),OR(G3="",G3>=DATE(2028,2,1))),H3*(1+Assumptions!$C$7)^3,0) -> 6928.416 | AU3: =IF(AND(F3<=DATE(2028,3,1),OR(G3="",G3>=DATE(2028,3,1))),H3*(1+Assumptions!$C$7)^3,0) -> 6928.416 | AV3: =IF(AND(F3<=DATE(2028,4,1),OR(G3="",G3>=DATE(2028,4,1))),H3*(1+Assumptions!$C$7)^3,0) -> 6928.416 | AW3: =IF(AND(F3<=DATE(2028,5,1),OR(G3="",G3>=DATE(2028,5,1))),H3*(1+Assumptions!$C$7)^3,0) -> 6928.416 | AX3: =IF(AND(F3<=DATE(2028,6,1),OR(G3="",G3>=DATE(2028,6,1))),H3*(1+Assumptions!$C$7)^3,0) -> 6928.416 | AY3: =IF(AND(F3<=DATE(2028,7,1),OR(G3="",G3>=DATE(2028,7,1))),H3*(1+Assumptions!$C$7)^3,0) -> 6928.416 | AZ3: =IF(AND(F3<=DATE(2028,8,1),OR(G3="",G3>=DATE(2028,8,1))),H3*(1+Assumptions!$C$7)^3,0) -> 6928.416 | BA3: =IF(AND(F3<=DATE(2028,9,1),OR(G3="",G3>=DATE(2028,9,1))),H3*(1+Assumptions!$C$7)^3,0) -> 6928.416 | BB3: =IF(AND(F3<=DATE(2028,10,1),OR(G3="",G3>=DATE(2028,10,1))),H3*(1+Assumptions!$C$7)^3,0) -> 6928.416 | BC3: =IF(AND(F3<=DATE(2028,11,1),OR(G3="",G3>=DATE(2028,11,1))),H3*(1+Assumptions!$C$7)^3,0) -> 6928.416 | BD3: =IF(AND(F3<=DATE(2028,12,1),OR(G3="",G3>=DATE(2028,12,1))),H3*(1+Assumptions!$C$7)^3,0) -> 6928.416 | BE3: =IF(AND(G3<=DATE(2028,12,1),OR(H3="",H3>=DATE(2028,12,1))),I3*(1+Assumptions!$C$7)^3,0) -> 0 | BF3: =IF(AND(H3<=DATE(2028,12,1),OR(I3="",I3>=DATE(2028,12,1))),J3*(1+Assumptions!$C$7)^3,0) -> 0 | BG3: =IF(AND(I3<=DATE(2028,12,1),OR(J3="",J3>=DATE(2028,12,1))),K3*(1+Assumptions!$C$7)^3,0) -> 0 | BH3: =IF(AND(J3<=DATE(2028,12,1),OR(K3="",K3>=DATE(2028,12,1))),L3*(1+Assumptions!$C$7)^3,0) -> 0 | BI3: =IF(AND(K3<=DATE(2028,12,1),OR(L3="",L3>=DATE(2028,12,1))),M3*(1+Assumptions!$C$7)^3,0) -> 0 | BJ3: =IF(AND(L3<=DATE(2028,12,1),OR(M3="",M3>=DATE(2028,12,1))),N3*(1+Assumptions!$C$7)^3,0) -> 0 | BK3: =IF(AND(M3<=DATE(2028,12,1),OR(N3="",N3>=DATE(2028,12,1))),O3*(1+Assumptions!$C$7)^3,0) -> 0 | ... BP3: =IF(AND(R3<=DATE(2028,12,1),OR(S3="",S3>=DATE(2028,12,1))),T3*(1+Assumptions!$C$7)^3,0) -> 0
A4: 2 | B4: Project manager | C4: R&D | D4: R&D Engineer | E4: Current | F4: 45901 | H4: 7500 | I4: =IF(AND(F4<=DATE(2025,1,1),OR(G4="",G4>=DATE(2025,1,1))),H4*(1+Assumptions!$C$7)^0,0) -> 0 | J4: =IF(AND(F4<=DATE(2025,2,1),OR(G4="",G4>=DATE(2025,2,1))),H4*(1+Assumptions!$C$7)^0,0) -> 0 | K4: =IF(AND(F4<=DATE(2025,3,1),OR(G4="",G4>=DATE(2025,3,1))),H4*(1+Assumptions!$C$7)^0,0) -> 0 | L4: =IF(AND(F4<=DATE(2025,4,1),OR(G4="",G4>=DATE(2025,4,1))),H4*(1+Assumptions!$C$7)^0,0) -> 0 | M4: =IF(AND(F4<=DATE(2025,5,1),OR(G4="",G4>=DATE(2025,5,1))),H4*(1+Assumptions!$C$7)^0,0) -> 0 | N4: =IF(AND(F4<=DATE(2025,6,1),OR(G4="",G4>=DATE(2025,6,1))),H4*(1+Assumptions!$C$7)^0,0) -> 0 | O4: =IF(AND(F4<=DATE(2025,7,1),OR(G4="",G4>=DATE(2025,7,1))),H4*(1+Assumptions!$C$7)^0,0) -> 0 | P4: =IF(AND(F4<=DATE(2025,8,1),OR(G4="",G4>=DATE(2025,8,1))),H4*(1+Assumptions!$C$7)^0,0) -> 0 | Q4: =IF(AND(F4<=DATE(2025,9,1),OR(G4="",G4>=DATE(2025,9,1))),H4*(1+Assumptions!$C$7)^0,0) -> 7500 | R4: =IF(AND(F4<=DATE(2025,10,1),OR(G4="",G4>=DATE(2025,10,1))),H4*(1+Assumptions!$C$7)^0,0) -> 7500 | S4: =IF(AND(F4<=DATE(2025,11,1),OR(G4="",G4>=DATE(2025,11,1))),H4*(1+Assumptions!$C$7)^0,0) -> 7500 | T4: =IF(AND(F4<=DATE(2025,12,1),OR(G4="",G4>=DATE(2025,12,1))),H4*(1+Assumptions!$C$7)^0,0) -> 7500 | U4: =IF(AND(F4<=DATE(2026,1,1),OR(G4="",G4>=DATE(2026,1,1))),H4*(1+Assumptions!$C$7)^1,0) -> 8100 | V4: =IF(AND(F4<=DATE(2026,2,1),OR(G4="",G4>=DATE(2026,2,1))),H4*(1+Assumptions!$C$7)^1,0) -> 8100 | W4: =IF(AND(F4<=DATE(2026,3,1),OR(G4="",G4>=DATE(2026,3,1))),H4*(1+Assumptions!$C$7)^1,0) -> 8100 | X4: =IF(AND(F4<=DATE(2026,4,1),OR(G4="",G4>=DATE(2026,4,1))),H4*(1+Assumptions!$C$7)^1,0) -> 8100 | Y4: =IF(AND(F4<=DATE(2026,5,1),OR(G4="",G4>=DATE(2026,5,1))),H4*(1+Assumptions!$C$7)^1,0) -> 8100 | Z4: =IF(AND(F4<=DATE(2026,6,1),OR(G4="",G4>=DATE(2026,6,1))),H4*(1+Assumptions!$C$7)^1,0) -> 8100 | AA4: =IF(AND(F4<=DATE(2026,7,1),OR(G4="",G4>=DATE(2026,7,1))),H4*(1+Assumptions!$C$7)^1,0) -> 8100 | AB4: =IF(AND(F4<=DATE(2026,8,1),OR(G4="",G4>=DATE(2026,8,1))),H4*(1+Assumptions!$C$7)^1,0) -> 8100 | AC4: =IF(AND(F4<=DATE(2026,9,1),OR(G4="",G4>=DATE(2026,9,1))),H4*(1+Assumptions!$C$7)^1,0) -> 8100 | AD4: =IF(AND(F4<=DATE(2026,10,1),OR(G4="",G4>=DATE(2026,10,1))),H4*(1+Assumptions!$C$7)^1,0) -> 8100 | AE4: =IF(AND(F4<=DATE(2026,11,1),OR(G4="",G4>=DATE(2026,11,1))),H4*(1+Assumptions!$C$7)^1,0) -> 8100 | AF4: =IF(AND(F4<=DATE(2026,12,1),OR(G4="",G4>=DATE(2026,12,1))),H4*(1+Assumptions!$C$7)^1,0) -> 8100 | AG4: =IF(AND(F4<=DATE(2027,1,1),OR(G4="",G4>=DATE(2027,1,1))),H4*(1+Assumptions!$C$7)^2,0) -> 8748 | AH4: =IF(AND(F4<=DATE(2027,2,1),OR(G4="",G4>=DATE(2027,2,1))),H4*(1+Assumptions!$C$7)^2,0) -> 8748 | AI4: =IF(AND(F4<=DATE(2027,3,1),OR(G4="",G4>=DATE(2027,3,1))),H4*(1+Assumptions!$C$7)^2,0) -> 8748 | AJ4: =IF(AND(F4<=DATE(2027,4,1),OR(G4="",G4>=DATE(2027,4,1))),H4*(1+Assumptions!$C$7)^2,0) -> 8748 | AK4: =IF(AND(F4<=DATE(2027,5,1),OR(G4="",G4>=DATE(2027,5,1))),H4*(1+Assumptions!$C$7)^2,0) -> 8748 | AL4: =IF(AND(F4<=DATE(2027,6,1),OR(G4="",G4>=DATE(2027,6,1))),H4*(1+Assumptions!$C$7)^2,0) -> 8748 | AM4: =IF(AND(F4<=DATE(2027,7,1),OR(G4="",G4>=DATE(2027,7,1))),H4*(1+Assumptions!$C$7)^2,0) -> 8748 | AN4: =IF(AND(F4<=DATE(2027,8,1),OR(G4="",G4>=DATE(2027,8,1))),H4*(1+Assumptions!$C$7)^2,0) -> 8748 | AO4: =IF(AND(F4<=DATE(2027,9,1),OR(G4="",G4>=DATE(2027,9,1))),H4*(1+Assumptions!$C$7)^2,0) -> 8748 | AP4: =IF(AND(F4<=DATE(2027,10,1),OR(G4="",G4>=DATE(2027,10,1))),H4*(1+Assumptions!$C$7)^2,0) -> 8748 | AQ4: =IF(AND(F4<=DATE(2027,11,1),OR(G4="",G4>=DATE(2027,11,1))),H4*(1+Assumptions!$C$7)^2,0) -> 8748 | AR4: =IF(AND(F4<=DATE(2027,12,1),OR(G4="",G4>=DATE(2027,12,1))),H4*(1+Assumptions!$C$7)^2,0) -> 8748 | AS4: =IF(AND(F4<=DATE(2028,1,1),OR(G4="",G4>=DATE(2028,1,1))),H4*(1+Assumptions!$C$7)^3,0) -> 9447.84 | AT4: =IF(AND(F4<=DATE(2028,2,1),OR(G4="",G4>=DATE(2028,2,1))),H4*(1+Assumptions!$C$7)^3,0) -> 9447.84 | AU4: =IF(AND(F4<=DATE(2028,3,1),OR(G4="",G4>=DATE(2028,3,1))),H4*(1+Assumptions!$C$7)^3,0) -> 9447.84 | AV4: =IF(AND(F4<=DATE(2028,4,1),OR(G4="",G4>=DATE(2028,4,1))),H4*(1+Assumptions!$C$7)^3,0) -> 9447.84 | AW4: =IF(AND(F4<=DATE(2028,5,1),OR(G4="",G4>=DATE(2028,5,1))),H4*(1+Assumptions!$C$7)^3,0) -> 9447.84 | AX4: =IF(AND(F4<=DATE(2028,6,1),OR(G4="",G4>=DATE(2028,6,1))),H4*(1+Assumptions!$C$7)^3,0) -> 9447.84 | AY4: =IF(AND(F4<=DATE(2028,7,1),OR(G4="",G4>=DATE(2028,7,1))),H4*(1+Assumptions!$C$7)^3,0) -> 9447.84 | AZ4: =IF(AND(F4<=DATE(2028,8,1),OR(G4="",G4>=DATE(2028,8,1))),H4*(1+Assumptions!$C$7)^3,0) -> 9447.84 | BA4: =IF(AND(F4<=DATE(2028,9,1),OR(G4="",G4>=DATE(2028,9,1))),H4*(1+Assumptions!$C$7)^3,0) -> 9447.84 | BB4: =IF(AND(F4<=DATE(2028,10,1),OR(G4="",G4>=DATE(2028,10,1))),H4*(1+Assumptions!$C$7)^3,0) -> 9447.84 | BC4: =IF(AND(F4<=DATE(2028,11,1),OR(G4="",G4>=DATE(2028,11,1))),H4*(1+Assumptions!$C$7)^3,0) -> 9447.84 | BD4: =IF(AND(F4<=DATE(2028,12,1),OR(G4="",G4>=DATE(2028,12,1))),H4*(1+Assumptions!$C$7)^3,0) -> 9447.84 | BE4: =IF(AND(G4<=DATE(2028,12,1),OR(H4="",H4>=DATE(2028,12,1))),I4*(1+Assumptions!$C$7)^3,0) -> 0 | BF4: =IF(AND(H4<=DATE(2028,12,1),OR(I4="",I4>=DATE(2028,12,1))),J4*(1+Assumptions!$C$7)^3,0) -> 0 | BG4: =IF(AND(I4<=DATE(2028,12,1),OR(J4="",J4>=DATE(2028,12,1))),K4*(1+Assumptions!$C$7)^3,0) -> 0 | BH4: =IF(AND(J4<=DATE(2028,12,1),OR(K4="",K4>=DATE(2028,12,1))),L4*(1+Assumptions!$C$7)^3,0) -> 0 | BI4: =IF(AND(K4<=DATE(2028,12,1),OR(L4="",L4>=DATE(2028,12,1))),M4*(1+Assumptions!$C$7)^3,0) -> 0 | BJ4: =IF(AND(L4<=DATE(2028,12,1),OR(M4="",M4>=DATE(2028,12,1))),N4*(1+Assumptions!$C$7)^3,0) -> 0 | BK4: =IF(AND(M4<=DATE(2028,12,1),OR(N4="",N4>=DATE(2028,12,1))),O4*(1+Assumptions!$C$7)^3,0) -> 0 | ... BP4: =IF(AND(R4<=DATE(2028,12,1),OR(S4="",S4>=DATE(2028,12,1))),T4*(1+Assumptions!$C$7)^3,0) -> 0
A5: 3 | B5: R&D Engineer | C5: R&D | D5: R&D Engineer | E5: Current | F5: 45901 | H5: 3000 | I5: =IF(AND(F5<=DATE(2025,1,1),OR(G5="",G5>=DATE(2025,1,1))),H5*(1+Assumptions!$C$7)^0,0) -> 0 | J5: =IF(AND(F5<=DATE(2025,2,1),OR(G5="",G5>=DATE(2025,2,1))),H5*(1+Assumptions!$C$7)^0,0) -> 0 | K5: =IF(AND(F5<=DATE(2025,3,1),OR(G5="",G5>=DATE(2025,3,1))),H5*(1+Assumptions!$C$7)^0,0) -> 0 | L5: =IF(AND(F5<=DATE(2025,4,1),OR(G5="",G5>=DATE(2025,4,1))),H5*(1+Assumptions!$C$7)^0,0) -> 0 | M5: =IF(AND(F5<=DATE(2025,5,1),OR(G5="",G5>=DATE(2025,5,1))),H5*(1+Assumptions!$C$7)^0,0) -> 0 | N5: =IF(AND(F5<=DATE(2025,6,1),OR(G5="",G5>=DATE(2025,6,1))),H5*(1+Assumptions!$C$7)^0,0) -> 0 | O5: =IF(AND(F5<=DATE(2025,7,1),OR(G5="",G5>=DATE(2025,7,1))),H5*(1+Assumptions!$C$7)^0,0) -> 0 | P5: =IF(AND(F5<=DATE(2025,8,1),OR(G5="",G5>=DATE(2025,8,1))),H5*(1+Assumptions!$C$7)^0,0) -> 0 | Q5: =IF(AND(F5<=DATE(2025,9,1),OR(G5="",G5>=DATE(2025,9,1))),H5*(1+Assumptions!$C$7)^0,0) -> 3000 | R5: =IF(AND(F5<=DATE(2025,10,1),OR(G5="",G5>=DATE(2025,10,1))),H5*(1+Assumptions!$C$7)^0,0) -> 3000 | S5: =IF(AND(F5<=DATE(2025,11,1),OR(G5="",G5>=DATE(2025,11,1))),H5*(1+Assumptions!$C$7)^0,0) -> 3000 | T5: =IF(AND(F5<=DATE(2025,12,1),OR(G5="",G5>=DATE(2025,12,1))),H5*(1+Assumptions!$C$7)^0,0) -> 3000 | U5: =IF(AND(F5<=DATE(2026,1,1),OR(G5="",G5>=DATE(2026,1,1))),H5*(1+Assumptions!$C$7)^1,0) -> 3240 | V5: =IF(AND(F5<=DATE(2026,2,1),OR(G5="",G5>=DATE(2026,2,1))),H5*(1+Assumptions!$C$7)^1,0) -> 3240 | W5: =IF(AND(F5<=DATE(2026,3,1),OR(G5="",G5>=DATE(2026,3,1))),H5*(1+Assumptions!$C$7)^1,0) -> 3240 | X5: =IF(AND(F5<=DATE(2026,4,1),OR(G5="",G5>=DATE(2026,4,1))),H5*(1+Assumptions!$C$7)^1,0) -> 3240 | Y5: =IF(AND(F5<=DATE(2026,5,1),OR(G5="",G5>=DATE(2026,5,1))),H5*(1+Assumptions!$C$7)^1,0) -> 3240 | Z5: =IF(AND(F5<=DATE(2026,6,1),OR(G5="",G5>=DATE(2026,6,1))),H5*(1+Assumptions!$C$7)^1,0) -> 3240 | AA5: =IF(AND(F5<=DATE(2026,7,1),OR(G5="",G5>=DATE(2026,7,1))),H5*(1+Assumptions!$C$7)^1,0) -> 3240 | AB5: =IF(AND(F5<=DATE(2026,8,1),OR(G5="",G5>=DATE(2026,8,1))),H5*(1+Assumptions!$C$7)^1,0) -> 3240 | AC5: =IF(AND(F5<=DATE(2026,9,1),OR(G5="",G5>=DATE(2026,9,1))),H5*(1+Assumptions!$C$7)^1,0) -> 3240 | AD5: =IF(AND(F5<=DATE(2026,10,1),OR(G5="",G5>=DATE(2026,10,1))),H5*(1+Assumptions!$C$7)^1,0) -> 3240 | AE5: =IF(AND(F5<=DATE(2026,11,1),OR(G5="",G5>=DATE(2026,11,1))),H5*(1+Assumptions!$C$7)^1,0) -> 3240 | AF5: =IF(AND(F5<=DATE(2026,12,1),OR(G5="",G5>=DATE(2026,12,1))),H5*(1+Assumptions!$C$7)^1,0) -> 3240 | AG5: =IF(AND(F5<=DATE(2027,1,1),OR(G5="",G5>=DATE(2027,1,1))),H5*(1+Assumptions!$C$7)^2,0) -> 3499.2 | AH5: =IF(AND(F5<=DATE(2027,2,1),OR(G5="",G5>=DATE(2027,2,1))),H5*(1+Assumptions!$C$7)^2,0) -> 3499.2 | AI5: =IF(AND(F5<=DATE(2027,3,1),OR(G5="",G5>=DATE(2027,3,1))),H5*(1+Assumptions!$C$7)^2,0) -> 3499.2 | AJ5: =IF(AND(F5<=DATE(2027,4,1),OR(G5="",G5>=DATE(2027,4,1))),H5*(1+Assumptions!$C$7)^2,0) -> 3499.2 | AK5: =IF(AND(F5<=DATE(2027,5,1),OR(G5="",G5>=DATE(2027,5,1))),H5*(1+Assumptions!$C$7)^2,0) -> 3499.2 | AL5: =IF(AND(F5<=DATE(2027,6,1),OR(G5="",G5>=DATE(2027,6,1))),H5*(1+Assumptions!$C$7)^2,0) -> 3499.2 | AM5: =IF(AND(F5<=DATE(2027,7,1),OR(G5="",G5>=DATE(2027,7,1))),H5*(1+Assumptions!$C$7)^2,0) -> 3499.2 | AN5: =IF(AND(F5<=DATE(2027,8,1),OR(G5="",G5>=DATE(2027,8,1))),H5*(1+Assumptions!$C$7)^2,0) -> 3499.2 | AO5: =IF(AND(F5<=DATE(2027,9,1),OR(G5="",G5>=DATE(2027,9,1))),H5*(1+Assumptions!$C$7)^2,0) -> 3499.2 | AP5: =IF(AND(F5<=DATE(2027,10,1),OR(G5="",G5>=DATE(2027,10,1))),H5*(1+Assumptions!$C$7)^2,0) -> 3499.2 | AQ5: =IF(AND(F5<=DATE(2027,11,1),OR(G5="",G5>=DATE(2027,11,1))),H5*(1+Assumptions!$C$7)^2,0) -> 3499.2 | AR5: =IF(AND(F5<=DATE(2027,12,1),OR(G5="",G5>=DATE(2027,12,1))),H5*(1+Assumptions!$C$7)^2,0) -> 3499.2 | AS5: =IF(AND(F5<=DATE(2028,1,1),OR(G5="",G5>=DATE(2028,1,1))),H5*(1+Assumptions!$C$7)^3,0) -> 3779.136 | AT5: =IF(AND(F5<=DATE(2028,2,1),OR(G5="",G5>=DATE(2028,2,1))),H5*(1+Assumptions!$C$7)^3,0) -> 3779.136 | AU5: =IF(AND(F5<=DATE(2028,3,1),OR(G5="",G5>=DATE(2028,3,1))),H5*(1+Assumptions!$C$7)^3,0) -> 3779.136 | AV5: =IF(AND(F5<=DATE(2028,4,1),OR(G5="",G5>=DATE(2028,4,1))),H5*(1+Assumptions!$C$7)^3,0) -> 3779.136 | AW5: =IF(AND(F5<=DATE(2028,5,1),OR(G5="",G5>=DATE(2028,5,1))),H5*(1+Assumptions!$C$7)^3,0) -> 3779.136 | AX5: =IF(AND(F5<=DATE(2028,6,1),OR(G5="",G5>=DATE(2028,6,1))),H5*(1+Assumptions!$C$7)^3,0) -> 3779.136 | AY5: =IF(AND(F5<=DATE(2028,7,1),OR(G5="",G5>=DATE(2028,7,1))),H5*(1+Assumptions!$C$7)^3,0) -> 3779.136 | AZ5: =IF(AND(F5<=DATE(2028,8,1),OR(G5="",G5>=DATE(2028,8,1))),H5*(1+Assumptions!$C$7)^3,0) -> 3779.136 | BA5: =IF(AND(F5<=DATE(2028,9,1),OR(G5="",G5>=DATE(2028,9,1))),H5*(1+Assumptions!$C$7)^3,0) -> 3779.136 | BB5: =IF(AND(F5<=DATE(2028,10,1),OR(G5="",G5>=DATE(2028,10,1))),H5*(1+Assumptions!$C$7)^3,0) -> 3779.136 | BC5: =IF(AND(F5<=DATE(2028,11,1),OR(G5="",G5>=DATE(2028,11,1))),H5*(1+Assumptions!$C$7)^3,0) -> 3779.136 | BD5: =IF(AND(F5<=DATE(2028,12,1),OR(G5="",G5>=DATE(2028,12,1))),H5*(1+Assumptions!$C$7)^3,0) -> 3779.136 | BE5: =IF(AND(G5<=DATE(2028,12,1),OR(H5="",H5>=DATE(2028,12,1))),I5*(1+Assumptions!$C$7)^3,0) -> 0 | BF5: =IF(AND(H5<=DATE(2028,12,1),OR(I5="",I5>=DATE(2028,12,1))),J5*(1+Assumptions!$C$7)^3,0) -> 0 | BG5: =IF(AND(I5<=DATE(2028,12,1),OR(J5="",J5>=DATE(2028,12,1))),K5*(1+Assumptions!$C$7)^3,0) -> 0 | BH5: =IF(AND(J5<=DATE(2028,12,1),OR(K5="",K5>=DATE(2028,12,1))),L5*(1+Assumptions!$C$7)^3,0) -> 0 | BI5: =IF(AND(K5<=DATE(2028,12,1),OR(L5="",L5>=DATE(2028,12,1))),M5*(1+Assumptions!$C$7)^3,0) -> 0 | BJ5: =IF(AND(L5<=DATE(2028,12,1),OR(M5="",M5>=DATE(2028,12,1))),N5*(1+Assumptions!$C$7)^3,0) -> 0 | BK5: =IF(AND(M5<=DATE(2028,12,1),OR(N5="",N5>=DATE(2028,12,1))),O5*(1+Assumptions!$C$7)^3,0) -> 0 | ... BP5: =IF(AND(R5<=DATE(2028,12,1),OR(S5="",S5>=DATE(2028,12,1))),T5*(1+Assumptions!$C$7)^3,0) -> 0
A6: 4 | B6: R&D Engineer | C6: R&D | D6: R&D Engineer | E6: Current | F6: 45901 | H6: 6000 | I6: =IF(AND(F6<=DATE(2025,1,1),OR(G6="",G6>=DATE(2025,1,1))),H6*(1+Assumptions!$C$7)^0,0) -> 0 | J6: =IF(AND(F6<=DATE(2025,2,1),OR(G6="",G6>=DATE(2025,2,1))),H6*(1+Assumptions!$C$7)^0,0) -> 0 | K6: =IF(AND(F6<=DATE(2025,3,1),OR(G6="",G6>=DATE(2025,3,1))),H6*(1+Assumptions!$C$7)^0,0) -> 0 | L6: =IF(AND(F6<=DATE(2025,4,1),OR(G6="",G6>=DATE(2025,4,1))),H6*(1+Assumptions!$C$7)^0,0) -> 0 | M6: =IF(AND(F6<=DATE(2025,5,1),OR(G6="",G6>=DATE(2025,5,1))),H6*(1+Assumptions!$C$7)^0,0) -> 0 | N6: =IF(AND(F6<=DATE(2025,6,1),OR(G6="",G6>=DATE(2025,6,1))),H6*(1+Assumptions!$C$7)^0,0) -> 0 | O6: =IF(AND(F6<=DATE(2025,7,1),OR(G6="",G6>=DATE(2025,7,1))),H6*(1+Assumptions!$C$7)^0,0) -> 0 | P6: =IF(AND(F6<=DATE(2025,8,1),OR(G6="",G6>=DATE(2025,8,1))),H6*(1+Assumptions!$C$7)^0,0) -> 0 | Q6: =IF(AND(F6<=DATE(2025,9,1),OR(G6="",G6>=DATE(2025,9,1))),H6*(1+Assumptions!$C$7)^0,0) -> 6000 | R6: =IF(AND(F6<=DATE(2025,10,1),OR(G6="",G6>=DATE(2025,10,1))),H6*(1+Assumptions!$C$7)^0,0) -> 6000 | S6: =IF(AND(F6<=DATE(2025,11,1),OR(G6="",G6>=DATE(2025,11,1))),H6*(1+Assumptions!$C$7)^0,0) -> 6000 | T6: =IF(AND(F6<=DATE(2025,12,1),OR(G6="",G6>=DATE(2025,12,1))),H6*(1+Assumptions!$C$7)^0,0) -> 6000 | U6: =IF(AND(F6<=DATE(2026,1,1),OR(G6="",G6>=DATE(2026,1,1))),H6*(1+Assumptions!$C$7)^1,0) -> 6480 | V6: =IF(AND(F6<=DATE(2026,2,1),OR(G6="",G6>=DATE(2026,2,1))),H6*(1+Assumptions!$C$7)^1,0) -> 6480 | W6: =IF(AND(F6<=DATE(2026,3,1),OR(G6="",G6>=DATE(2026,3,1))),H6*(1+Assumptions!$C$7)^1,0) -> 6480 | X6: =IF(AND(F6<=DATE(2026,4,1),OR(G6="",G6>=DATE(2026,4,1))),H6*(1+Assumptions!$C$7)^1,0) -> 6480 | Y6: =IF(AND(F6<=DATE(2026,5,1),OR(G6="",G6>=DATE(2026,5,1))),H6*(1+Assumptions!$C$7)^1,0) -> 6480 | Z6: =IF(AND(F6<=DATE(2026,6,1),OR(G6="",G6>=DATE(2026,6,1))),H6*(1+Assumptions!$C$7)^1,0) -> 6480 | AA6: =IF(AND(F6<=DATE(2026,7,1),OR(G6="",G6>=DATE(2026,7,1))),H6*(1+Assumptions!$C$7)^1,0) -> 6480 | AB6: =IF(AND(F6<=DATE(2026,8,1),OR(G6="",G6>=DATE(2026,8,1))),H6*(1+Assumptions!$C$7)^1,0) -> 6480 | AC6: =IF(AND(F6<=DATE(2026,9,1),OR(G6="",G6>=DATE(2026,9,1))),H6*(1+Assumptions!$C$7)^1,0) -> 6480 | AD6: =IF(AND(F6<=DATE(2026,10,1),OR(G6="",G6>=DATE(2026,10,1))),H6*(1+Assumptions!$C$7)^1,0) -> 6480 | AE6: =IF(AND(F6<=DATE(2026,11,1),OR(G6="",G6>=DATE(2026,11,1))),H6*(1+Assumptions!$C$7)^1,0) -> 6480 | AF6: =IF(AND(F6<=DATE(2026,12,1),OR(G6="",G6>=DATE(2026,12,1))),H6*(1+Assumptions!$C$7)^1,0) -> 6480 | AG6: =IF(AND(F6<=DATE(2027,1,1),OR(G6="",G6>=DATE(2027,1,1))),H6*(1+Assumptions!$C$7)^2,0) -> 6998.4 | AH6: =IF(AND(F6<=DATE(2027,2,1),OR(G6="",G6>=DATE(2027,2,1))),H6*(1+Assumptions!$C$7)^2,0) -> 6998.4 | AI6: =IF(AND(F6<=DATE(2027,3,1),OR(G6="",G6>=DATE(2027,3,1))),H6*(1+Assumptions!$C$7)^2,0) -> 6998.4 | AJ6: =IF(AND(F6<=DATE(2027,4,1),OR(G6="",G6>=DATE(2027,4,1))),H6*(1+Assumptions!$C$7)^2,0) -> 6998.4 | AK6: =IF(AND(F6<=DATE(2027,5,1),OR(G6="",G6>=DATE(2027,5,1))),H6*(1+Assumptions!$C$7)^2,0) -> 6998.4 | AL6: =IF(AND(F6<=DATE(2027,6,1),OR(G6="",G6>=DATE(2027,6,1))),H6*(1+Assumptions!$C$7)^2,0) -> 6998.4 | AM6: =IF(AND(F6<=DATE(2027,7,1),OR(G6="",G6>=DATE(2027,7,1))),H6*(1+Assumptions!$C$7)^2,0) -> 6998.4 | AN6: =IF(AND(F6<=DATE(2027,8,1),OR(G6="",G6>=DATE(2027,8,1))),H6*(1+Assumptions!$C$7)^2,0) -> 6998.4 | AO6: =IF(AND(F6<=DATE(2027,9,1),OR(G6="",G6>=DATE(2027,9,1))),H6*(1+Assumptions!$C$7)^2,0) -> 6998.4 | AP6: =IF(AND(F6<=DATE(2027,10,1),OR(G6="",G6>=DATE(2027,10,1))),H6*(1+Assumptions!$C$7)^2,0) -> 6998.4 | AQ6: =IF(AND(F6<=DATE(2027,11,1),OR(G6="",G6>=DATE(2027,11,1))),H6*(1+Assumptions!$C$7)^2,0) -> 6998.4 | AR6: =IF(AND(F6<=DATE(2027,12,1),OR(G6="",G6>=DATE(2027,12,1))),H6*(1+Assumptions!$C$7)^2,0) -> 6998.4 | AS6: =IF(AND(F6<=DATE(2028,1,1),OR(G6="",G6>=DATE(2028,1,1))),H6*(1+Assumptions!$C$7)^3,0) -> 7558.272 | AT6: =IF(AND(F6<=DATE(2028,2,1),OR(G6="",G6>=DATE(2028,2,1))),H6*(1+Assumptions!$C$7)^3,0) -> 7558.272 | AU6: =IF(AND(F6<=DATE(2028,3,1),OR(G6="",G6>=DATE(2028,3,1))),H6*(1+Assumptions!$C$7)^3,0) -> 7558.272 | AV6: =IF(AND(F6<=DATE(2028,4,1),OR(G6="",G6>=DATE(2028,4,1))),H6*(1+Assumptions!$C$7)^3,0) -> 7558.272 | AW6: =IF(AND(F6<=DATE(2028,5,1),OR(G6="",G6>=DATE(2028,5,1))),H6*(1+Assumptions!$C$7)^3,0) -> 7558.272 | AX6: =IF(AND(F6<=DATE(2028,6,1),OR(G6="",G6>=DATE(2028,6,1))),H6*(1+Assumptions!$C$7)^3,0) -> 7558.272 | AY6: =IF(AND(F6<=DATE(2028,7,1),OR(G6="",G6>=DATE(2028,7,1))),H6*(1+Assumptions!$C$7)^3,0) -> 7558.272 | AZ6: =IF(AND(F6<=DATE(2028,8,1),OR(G6="",G6>=DATE(2028,8,1))),H6*(1+Assumptions!$C$7)^3,0) -> 7558.272 | BA6: =IF(AND(F6<=DATE(2028,9,1),OR(G6="",G6>=DATE(2028,9,1))),H6*(1+Assumptions!$C$7)^3,0) -> 7558.272 | BB6: =IF(AND(F6<=DATE(2028,10,1),OR(G6="",G6>=DATE(2028,10,1))),H6*(1+Assumptions!$C$7)^3,0) -> 7558.272 | BC6: =IF(AND(F6<=DATE(2028,11,1),OR(G6="",G6>=DATE(2028,11,1))),H6*(1+Assumptions!$C$7)^3,0) -> 7558.272 | BD6: =IF(AND(F6<=DATE(2028,12,1),OR(G6="",G6>=DATE(2028,12,1))),H6*(1+Assumptions!$C$7)^3,0) -> 7558.272 | BE6: =IF(AND(G6<=DATE(2028,12,1),OR(H6="",H6>=DATE(2028,12,1))),I6*(1+Assumptions!$C$7)^3,0) -> 0 | BF6: =IF(AND(H6<=DATE(2028,12,1),OR(I6="",I6>=DATE(2028,12,1))),J6*(1+Assumptions!$C$7)^3,0) -> 0 | BG6: =IF(AND(I6<=DATE(2028,12,1),OR(J6="",J6>=DATE(2028,12,1))),K6*(1+Assumptions!$C$7)^3,0) -> 0 | BH6: =IF(AND(J6<=DATE(2028,12,1),OR(K6="",K6>=DATE(2028,12,1))),L6*(1+Assumptions!$C$7)^3,0) -> 0 | BI6: =IF(AND(K6<=DATE(2028,12,1),OR(L6="",L6>=DATE(2028,12,1))),M6*(1+Assumptions!$C$7)^3,0) -> 0 | BJ6: =IF(AND(L6<=DATE(2028,12,1),OR(M6="",M6>=DATE(2028,12,1))),N6*(1+Assumptions!$C$7)^3,0) -> 0 | BK6: =IF(AND(M6<=DATE(2028,12,1),OR(N6="",N6>=DATE(2028,12,1))),O6*(1+Assumptions!$C$7)^3,0) -> 0 | ... BP6: =IF(AND(R6<=DATE(2028,12,1),OR(S6="",S6>=DATE(2028,12,1))),T6*(1+Assumptions!$C$7)^3,0) -> 0
A7: 5 | B7: Firmware Engineer | C7: R&D | D7: R&D Engineer | E7: Current | F7: 45901 | H7: 7000 | I7: =IF(AND(F7<=DATE(2025,1,1),OR(G7="",G7>=DATE(2025,1,1))),H7*(1+Assumptions!$C$7)^0,0) -> 0 | J7: =IF(AND(F7<=DATE(2025,2,1),OR(G7="",G7>=DATE(2025,2,1))),H7*(1+Assumptions!$C$7)^0,0) -> 0 | K7: =IF(AND(F7<=DATE(2025,3,1),OR(G7="",G7>=DATE(2025,3,1))),H7*(1+Assumptions!$C$7)^0,0) -> 0 | L7: =IF(AND(F7<=DATE(2025,4,1),OR(G7="",G7>=DATE(2025,4,1))),H7*(1+Assumptions!$C$7)^0,0) -> 0 | M7: =IF(AND(F7<=DATE(2025,5,1),OR(G7="",G7>=DATE(2025,5,1))),H7*(1+Assumptions!$C$7)^0,0) -> 0 | N7: =IF(AND(F7<=DATE(2025,6,1),OR(G7="",G7>=DATE(2025,6,1))),H7*(1+Assumptions!$C$7)^0,0) -> 0 | O7: =IF(AND(F7<=DATE(2025,7,1),OR(G7="",G7>=DATE(2025,7,1))),H7*(1+Assumptions!$C$7)^0,0) -> 0 | P7: =IF(AND(F7<=DATE(2025,8,1),OR(G7="",G7>=DATE(2025,8,1))),H7*(1+Assumptions!$C$7)^0,0) -> 0 | Q7: =IF(AND(F7<=DATE(2025,9,1),OR(G7="",G7>=DATE(2025,9,1))),H7*(1+Assumptions!$C$7)^0,0) -> 7000 | R7: =IF(AND(F7<=DATE(2025,10,1),OR(G7="",G7>=DATE(2025,10,1))),H7*(1+Assumptions!$C$7)^0,0) -> 7000 | S7: =IF(AND(F7<=DATE(2025,11,1),OR(G7="",G7>=DATE(2025,11,1))),H7*(1+Assumptions!$C$7)^0,0) -> 7000 | T7: =IF(AND(F7<=DATE(2025,12,1),OR(G7="",G7>=DATE(2025,12,1))),H7*(1+Assumptions!$C$7)^0,0) -> 7000 | U7: =IF(AND(F7<=DATE(2026,1,1),OR(G7="",G7>=DATE(2026,1,1))),H7*(1+Assumptions!$C$7)^1,0) -> 7560 | V7: =IF(AND(F7<=DATE(2026,2,1),OR(G7="",G7>=DATE(2026,2,1))),H7*(1+Assumptions!$C$7)^1,0) -> 7560 | W7: =IF(AND(F7<=DATE(2026,3,1),OR(G7="",G7>=DATE(2026,3,1))),H7*(1+Assumptions!$C$7)^1,0) -> 7560 | X7: =IF(AND(F7<=DATE(2026,4,1),OR(G7="",G7>=DATE(2026,4,1))),H7*(1+Assumptions!$C$7)^1,0) -> 7560 | Y7: =IF(AND(F7<=DATE(2026,5,1),OR(G7="",G7>=DATE(2026,5,1))),H7*(1+Assumptions!$C$7)^1,0) -> 7560 | Z7: =IF(AND(F7<=DATE(2026,6,1),OR(G7="",G7>=DATE(2026,6,1))),H7*(1+Assumptions!$C$7)^1,0) -> 7560 | AA7: =IF(AND(F7<=DATE(2026,7,1),OR(G7="",G7>=DATE(2026,7,1))),H7*(1+Assumptions!$C$7)^1,0) -> 7560 | AB7: =IF(AND(F7<=DATE(2026,8,1),OR(G7="",G7>=DATE(2026,8,1))),H7*(1+Assumptions!$C$7)^1,0) -> 7560 | AC7: =IF(AND(F7<=DATE(2026,9,1),OR(G7="",G7>=DATE(2026,9,1))),H7*(1+Assumptions!$C$7)^1,0) -> 7560 | AD7: =IF(AND(F7<=DATE(2026,10,1),OR(G7="",G7>=DATE(2026,10,1))),H7*(1+Assumptions!$C$7)^1,0) -> 7560 | AE7: =IF(AND(F7<=DATE(2026,11,1),OR(G7="",G7>=DATE(2026,11,1))),H7*(1+Assumptions!$C$7)^1,0) -> 7560 | AF7: =IF(AND(F7<=DATE(2026,12,1),OR(G7="",G7>=DATE(2026,12,1))),H7*(1+Assumptions!$C$7)^1,0) -> 7560 | AG7: =IF(AND(F7<=DATE(2027,1,1),OR(G7="",G7>=DATE(2027,1,1))),H7*(1+Assumptions!$C$7)^2,0) -> 8164.8 | AH7: =IF(AND(F7<=DATE(2027,2,1),OR(G7="",G7>=DATE(2027,2,1))),H7*(1+Assumptions!$C$7)^2,0) -> 8164.8 | AI7: =IF(AND(F7<=DATE(2027,3,1),OR(G7="",G7>=DATE(2027,3,1))),H7*(1+Assumptions!$C$7)^2,0) -> 8164.8 | AJ7: =IF(AND(F7<=DATE(2027,4,1),OR(G7="",G7>=DATE(2027,4,1))),H7*(1+Assumptions!$C$7)^2,0) -> 8164.8 | AK7: =IF(AND(F7<=DATE(2027,5,1),OR(G7="",G7>=DATE(2027,5,1))),H7*(1+Assumptions!$C$7)^2,0) -> 8164.8 | AL7: =IF(AND(F7<=DATE(2027,6,1),OR(G7="",G7>=DATE(2027,6,1))),H7*(1+Assumptions!$C$7)^2,0) -> 8164.8 | AM7: =IF(AND(F7<=DATE(2027,7,1),OR(G7="",G7>=DATE(2027,7,1))),H7*(1+Assumptions!$C$7)^2,0) -> 8164.8 | AN7: =IF(AND(F7<=DATE(2027,8,1),OR(G7="",G7>=DATE(2027,8,1))),H7*(1+Assumptions!$C$7)^2,0) -> 8164.8 | AO7: =IF(AND(F7<=DATE(2027,9,1),OR(G7="",G7>=DATE(2027,9,1))),H7*(1+Assumptions!$C$7)^2,0) -> 8164.8 | AP7: =IF(AND(F7<=DATE(2027,10,1),OR(G7="",G7>=DATE(2027,10,1))),H7*(1+Assumptions!$C$7)^2,0) -> 8164.8 | AQ7: =IF(AND(F7<=DATE(2027,11,1),OR(G7="",G7>=DATE(2027,11,1))),H7*(1+Assumptions!$C$7)^2,0) -> 8164.8 | AR7: =IF(AND(F7<=DATE(2027,12,1),OR(G7="",G7>=DATE(2027,12,1))),H7*(1+Assumptions!$C$7)^2,0) -> 8164.8 | AS7: =IF(AND(F7<=DATE(2028,1,1),OR(G7="",G7>=DATE(2028,1,1))),H7*(1+Assumptions!$C$7)^3,0) -> 8817.984 | AT7: =IF(AND(F7<=DATE(2028,2,1),OR(G7="",G7>=DATE(2028,2,1))),H7*(1+Assumptions!$C$7)^3,0) -> 8817.984 | AU7: =IF(AND(F7<=DATE(2028,3,1),OR(G7="",G7>=DATE(2028,3,1))),H7*(1+Assumptions!$C$7)^3,0) -> 8817.984 | AV7: =IF(AND(F7<=DATE(2028,4,1),OR(G7="",G7>=DATE(2028,4,1))),H7*(1+Assumptions!$C$7)^3,0) -> 8817.984 | AW7: =IF(AND(F7<=DATE(2028,5,1),OR(G7="",G7>=DATE(2028,5,1))),H7*(1+Assumptions!$C$7)^3,0) -> 8817.984 | AX7: =IF(AND(F7<=DATE(2028,6,1),OR(G7="",G7>=DATE(2028,6,1))),H7*(1+Assumptions!$C$7)^3,0) -> 8817.984 | AY7: =IF(AND(F7<=DATE(2028,7,1),OR(G7="",G7>=DATE(2028,7,1))),H7*(1+Assumptions!$C$7)^3,0) -> 8817.984 | AZ7: =IF(AND(F7<=DATE(2028,8,1),OR(G7="",G7>=DATE(2028,8,1))),H7*(1+Assumptions!$C$7)^3,0) -> 8817.984 | BA7: =IF(AND(F7<=DATE(2028,9,1),OR(G7="",G7>=DATE(2028,9,1))),H7*(1+Assumptions!$C$7)^3,0) -> 8817.984 | BB7: =IF(AND(F7<=DATE(2028,10,1),OR(G7="",G7>=DATE(2028,10,1))),H7*(1+Assumptions!$C$7)^3,0) -> 8817.984 | BC7: =IF(AND(F7<=DATE(2028,11,1),OR(G7="",G7>=DATE(2028,11,1))),H7*(1+Assumptions!$C$7)^3,0) -> 8817.984 | BD7: =IF(AND(F7<=DATE(2028,12,1),OR(G7="",G7>=DATE(2028,12,1))),H7*(1+Assumptions!$C$7)^3,0) -> 8817.984 | BE7: =IF(AND(G7<=DATE(2028,12,1),OR(H7="",H7>=DATE(2028,12,1))),I7*(1+Assumptions!$C$7)^3,0) -> 0 | BF7: =IF(AND(H7<=DATE(2028,12,1),OR(I7="",I7>=DATE(2028,12,1))),J7*(1+Assumptions!$C$7)^3,0) -> 0 | BG7: =IF(AND(I7<=DATE(2028,12,1),OR(J7="",J7>=DATE(2028,12,1))),K7*(1+Assumptions!$C$7)^3,0) -> 0 | BH7: =IF(AND(J7<=DATE(2028,12,1),OR(K7="",K7>=DATE(2028,12,1))),L7*(1+Assumptions!$C$7)^3,0) -> 0 | BI7: =IF(AND(K7<=DATE(2028,12,1),OR(L7="",L7>=DATE(2028,12,1))),M7*(1+Assumptions!$C$7)^3,0) -> 0 | BJ7: =IF(AND(L7<=DATE(2028,12,1),OR(M7="",M7>=DATE(2028,12,1))),N7*(1+Assumptions!$C$7)^3,0) -> 0 | BK7: =IF(AND(M7<=DATE(2028,12,1),OR(N7="",N7>=DATE(2028,12,1))),O7*(1+Assumptions!$C$7)^3,0) -> 0 | ... BP7: =IF(AND(R7<=DATE(2028,12,1),OR(S7="",S7>=DATE(2028,12,1))),T7*(1+Assumptions!$C$7)^3,0) -> 0
A8: 6 | B8: Mechanical Engineer | C8: R&D | D8: R&D Engineer | E8: Current | F8: 45901 | H8: 5500 | I8: =IF(AND(F8<=DATE(2025,1,1),OR(G8="",G8>=DATE(2025,1,1))),H8*(1+Assumptions!$C$7)^0,0) -> 0 | J8: =IF(AND(F8<=DATE(2025,2,1),OR(G8="",G8>=DATE(2025,2,1))),H8*(1+Assumptions!$C$7)^0,0) -> 0 | K8: =IF(AND(F8<=DATE(2025,3,1),OR(G8="",G8>=DATE(2025,3,1))),H8*(1+Assumptions!$C$7)^0,0) -> 0 | L8: =IF(AND(F8<=DATE(2025,4,1),OR(G8="",G8>=DATE(2025,4,1))),H8*(1+Assumptions!$C$7)^0,0) -> 0 | M8: =IF(AND(F8<=DATE(2025,5,1),OR(G8="",G8>=DATE(2025,5,1))),H8*(1+Assumptions!$C$7)^0,0) -> 0 | N8: =IF(AND(F8<=DATE(2025,6,1),OR(G8="",G8>=DATE(2025,6,1))),H8*(1+Assumptions!$C$7)^0,0) -> 0 | O8: =IF(AND(F8<=DATE(2025,7,1),OR(G8="",G8>=DATE(2025,7,1))),H8*(1+Assumptions!$C$7)^0,0) -> 0 | P8: =IF(AND(F8<=DATE(2025,8,1),OR(G8="",G8>=DATE(2025,8,1))),H8*(1+Assumptions!$C$7)^0,0) -> 0 | Q8: =IF(AND(F8<=DATE(2025,9,1),OR(G8="",G8>=DATE(2025,9,1))),H8*(1+Assumptions!$C$7)^0,0) -> 5500 | R8: =IF(AND(F8<=DATE(2025,10,1),OR(G8="",G8>=DATE(2025,10,1))),H8*(1+Assumptions!$C$7)^0,0) -> 5500 | S8: =IF(AND(F8<=DATE(2025,11,1),OR(G8="",G8>=DATE(2025,11,1))),H8*(1+Assumptions!$C$7)^0,0) -> 5500 | T8: =IF(AND(F8<=DATE(2025,12,1),OR(G8="",G8>=DATE(2025,12,1))),H8*(1+Assumptions!$C$7)^0,0) -> 5500 | U8: =IF(AND(F8<=DATE(2026,1,1),OR(G8="",G8>=DATE(2026,1,1))),H8*(1+Assumptions!$C$7)^1,0) -> 5940 | V8: =IF(AND(F8<=DATE(2026,2,1),OR(G8="",G8>=DATE(2026,2,1))),H8*(1+Assumptions!$C$7)^1,0) -> 5940 | W8: =IF(AND(F8<=DATE(2026,3,1),OR(G8="",G8>=DATE(2026,3,1))),H8*(1+Assumptions!$C$7)^1,0) -> 5940 | X8: =IF(AND(F8<=DATE(2026,4,1),OR(G8="",G8>=DATE(2026,4,1))),H8*(1+Assumptions!$C$7)^1,0) -> 5940 | Y8: =IF(AND(F8<=DATE(2026,5,1),OR(G8="",G8>=DATE(2026,5,1))),H8*(1+Assumptions!$C$7)^1,0) -> 5940 | Z8: =IF(AND(F8<=DATE(2026,6,1),OR(G8="",G8>=DATE(2026,6,1))),H8*(1+Assumptions!$C$7)^1,0) -> 5940 | AA8: =IF(AND(F8<=DATE(2026,7,1),OR(G8="",G8>=DATE(2026,7,1))),H8*(1+Assumptions!$C$7)^1,0) -> 5940 | AB8: =IF(AND(F8<=DATE(2026,8,1),OR(G8="",G8>=DATE(2026,8,1))),H8*(1+Assumptions!$C$7)^1,0) -> 5940 | AC8: =IF(AND(F8<=DATE(2026,9,1),OR(G8="",G8>=DATE(2026,9,1))),H8*(1+Assumptions!$C$7)^1,0) -> 5940 | AD8: =IF(AND(F8<=DATE(2026,10,1),OR(G8="",G8>=DATE(2026,10,1))),H8*(1+Assumptions!$C$7)^1,0) -> 5940 | AE8: =IF(AND(F8<=DATE(2026,11,1),OR(G8="",G8>=DATE(2026,11,1))),H8*(1+Assumptions!$C$7)^1,0) -> 5940 | AF8: =IF(AND(F8<=DATE(2026,12,1),OR(G8="",G8>=DATE(2026,12,1))),H8*(1+Assumptions!$C$7)^1,0) -> 5940 | AG8: =IF(AND(F8<=DATE(2027,1,1),OR(G8="",G8>=DATE(2027,1,1))),H8*(1+Assumptions!$C$7)^2,0) -> 6415.2 | AH8: =IF(AND(F8<=DATE(2027,2,1),OR(G8="",G8>=DATE(2027,2,1))),H8*(1+Assumptions!$C$7)^2,0) -> 6415.2 | AI8: =IF(AND(F8<=DATE(2027,3,1),OR(G8="",G8>=DATE(2027,3,1))),H8*(1+Assumptions!$C$7)^2,0) -> 6415.2 | AJ8: =IF(AND(F8<=DATE(2027,4,1),OR(G8="",G8>=DATE(2027,4,1))),H8*(1+Assumptions!$C$7)^2,0) -> 6415.2 | AK8: =IF(AND(F8<=DATE(2027,5,1),OR(G8="",G8>=DATE(2027,5,1))),H8*(1+Assumptions!$C$7)^2,0) -> 6415.2 | AL8: =IF(AND(F8<=DATE(2027,6,1),OR(G8="",G8>=DATE(2027,6,1))),H8*(1+Assumptions!$C$7)^2,0) -> 6415.2 | AM8: =IF(AND(F8<=DATE(2027,7,1),OR(G8="",G8>=DATE(2027,7,1))),H8*(1+Assumptions!$C$7)^2,0) -> 6415.2 | AN8: =IF(AND(F8<=DATE(2027,8,1),OR(G8="",G8>=DATE(2027,8,1))),H8*(1+Assumptions!$C$7)^2,0) -> 6415.2 | AO8: =IF(AND(F8<=DATE(2027,9,1),OR(G8="",G8>=DATE(2027,9,1))),H8*(1+Assumptions!$C$7)^2,0) -> 6415.2 | AP8: =IF(AND(F8<=DATE(2027,10,1),OR(G8="",G8>=DATE(2027,10,1))),H8*(1+Assumptions!$C$7)^2,0) -> 6415.2 | AQ8: =IF(AND(F8<=DATE(2027,11,1),OR(G8="",G8>=DATE(2027,11,1))),H8*(1+Assumptions!$C$7)^2,0) -> 6415.2 | AR8: =IF(AND(F8<=DATE(2027,12,1),OR(G8="",G8>=DATE(2027,12,1))),H8*(1+Assumptions!$C$7)^2,0) -> 6415.2 | AS8: =IF(AND(F8<=DATE(2028,1,1),OR(G8="",G8>=DATE(2028,1,1))),H8*(1+Assumptions!$C$7)^3,0) -> 6928.416 | AT8: =IF(AND(F8<=DATE(2028,2,1),OR(G8="",G8>=DATE(2028,2,1))),H8*(1+Assumptions!$C$7)^3,0) -> 6928.416 | AU8: =IF(AND(F8<=DATE(2028,3,1),OR(G8="",G8>=DATE(2028,3,1))),H8*(1+Assumptions!$C$7)^3,0) -> 6928.416 | AV8: =IF(AND(F8<=DATE(2028,4,1),OR(G8="",G8>=DATE(2028,4,1))),H8*(1+Assumptions!$C$7)^3,0) -> 6928.416 | AW8: =IF(AND(F8<=DATE(2028,5,1),OR(G8="",G8>=DATE(2028,5,1))),H8*(1+Assumptions!$C$7)^3,0) -> 6928.416 | AX8: =IF(AND(F8<=DATE(2028,6,1),OR(G8="",G8>=DATE(2028,6,1))),H8*(1+Assumptions!$C$7)^3,0) -> 6928.416 | AY8: =IF(AND(F8<=DATE(2028,7,1),OR(G8="",G8>=DATE(2028,7,1))),H8*(1+Assumptions!$C$7)^3,0) -> 6928.416 | AZ8: =IF(AND(F8<=DATE(2028,8,1),OR(G8="",G8>=DATE(2028,8,1))),H8*(1+Assumptions!$C$7)^3,0) -> 6928.416 | BA8: =IF(AND(F8<=DATE(2028,9,1),OR(G8="",G8>=DATE(2028,9,1))),H8*(1+Assumptions!$C$7)^3,0) -> 6928.416 | BB8: =IF(AND(F8<=DATE(2028,10,1),OR(G8="",G8>=DATE(2028,10,1))),H8*(1+Assumptions!$C$7)^3,0) -> 6928.416 | BC8: =IF(AND(F8<=DATE(2028,11,1),OR(G8="",G8>=DATE(2028,11,1))),H8*(1+Assumptions!$C$7)^3,0) -> 6928.416 | BD8: =IF(AND(F8<=DATE(2028,12,1),OR(G8="",G8>=DATE(2028,12,1))),H8*(1+Assumptions!$C$7)^3,0) -> 6928.416 | BE8: =IF(AND(G8<=DATE(2028,12,1),OR(H8="",H8>=DATE(2028,12,1))),I8*(1+Assumptions!$C$7)^3,0) -> 0 | BF8: =IF(AND(H8<=DATE(2028,12,1),OR(I8="",I8>=DATE(2028,12,1))),J8*(1+Assumptions!$C$7)^3,0) -> 0 | BG8: =IF(AND(I8<=DATE(2028,12,1),OR(J8="",J8>=DATE(2028,12,1))),K8*(1+Assumptions!$C$7)^3,0) -> 0 | BH8: =IF(AND(J8<=DATE(2028,12,1),OR(K8="",K8>=DATE(2028,12,1))),L8*(1+Assumptions!$C$7)^3,0) -> 0 | BI8: =IF(AND(K8<=DATE(2028,12,1),OR(L8="",L8>=DATE(2028,12,1))),M8*(1+Assumptions!$C$7)^3,0) -> 0 | BJ8: =IF(AND(L8<=DATE(2028,12,1),OR(M8="",M8>=DATE(2028,12,1))),N8*(1+Assumptions!$C$7)^3,0) -> 0 | BK8: =IF(AND(M8<=DATE(2028,12,1),OR(N8="",N8>=DATE(2028,12,1))),O8*(1+Assumptions!$C$7)^3,0) -> 0 | ... BP8: =IF(AND(R8<=DATE(2028,12,1),OR(S8="",S8>=DATE(2028,12,1))),T8*(1+Assumptions!$C$7)^3,0) -> 0
A9: 7 | B9: Electrical Engineer | C9: R&D | D9: R&D Engineer | E9: Current | F9: 45901 | H9: 5500 | I9: =IF(AND(F9<=DATE(2025,1,1),OR(G9="",G9>=DATE(2025,1,1))),H9*(1+Assumptions!$C$7)^0,0) -> 0 | J9: =IF(AND(F9<=DATE(2025,2,1),OR(G9="",G9>=DATE(2025,2,1))),H9*(1+Assumptions!$C$7)^0,0) -> 0 | K9: =IF(AND(F9<=DATE(2025,3,1),OR(G9="",G9>=DATE(2025,3,1))),H9*(1+Assumptions!$C$7)^0,0) -> 0 | L9: =IF(AND(F9<=DATE(2025,4,1),OR(G9="",G9>=DATE(2025,4,1))),H9*(1+Assumptions!$C$7)^0,0) -> 0 | M9: =IF(AND(F9<=DATE(2025,5,1),OR(G9="",G9>=DATE(2025,5,1))),H9*(1+Assumptions!$C$7)^0,0) -> 0 | N9: =IF(AND(F9<=DATE(2025,6,1),OR(G9="",G9>=DATE(2025,6,1))),H9*(1+Assumptions!$C$7)^0,0) -> 0 | O9: =IF(AND(F9<=DATE(2025,7,1),OR(G9="",G9>=DATE(2025,7,1))),H9*(1+Assumptions!$C$7)^0,0) -> 0 | P9: =IF(AND(F9<=DATE(2025,8,1),OR(G9="",G9>=DATE(2025,8,1))),H9*(1+Assumptions!$C$7)^0,0) -> 0 | Q9: =IF(AND(F9<=DATE(2025,9,1),OR(G9="",G9>=DATE(2025,9,1))),H9*(1+Assumptions!$C$7)^0,0) -> 5500 | R9: =IF(AND(F9<=DATE(2025,10,1),OR(G9="",G9>=DATE(2025,10,1))),H9*(1+Assumptions!$C$7)^0,0) -> 5500 | S9: =IF(AND(F9<=DATE(2025,11,1),OR(G9="",G9>=DATE(2025,11,1))),H9*(1+Assumptions!$C$7)^0,0) -> 5500 | T9: =IF(AND(F9<=DATE(2025,12,1),OR(G9="",G9>=DATE(2025,12,1))),H9*(1+Assumptions!$C$7)^0,0) -> 5500 | U9: =IF(AND(F9<=DATE(2026,1,1),OR(G9="",G9>=DATE(2026,1,1))),H9*(1+Assumptions!$C$7)^1,0) -> 5940 | V9: =IF(AND(F9<=DATE(2026,2,1),OR(G9="",G9>=DATE(2026,2,1))),H9*(1+Assumptions!$C$7)^1,0) -> 5940 | W9: =IF(AND(F9<=DATE(2026,3,1),OR(G9="",G9>=DATE(2026,3,1))),H9*(1+Assumptions!$C$7)^1,0) -> 5940 | X9: =IF(AND(F9<=DATE(2026,4,1),OR(G9="",G9>=DATE(2026,4,1))),H9*(1+Assumptions!$C$7)^1,0) -> 5940 | Y9: =IF(AND(F9<=DATE(2026,5,1),OR(G9="",G9>=DATE(2026,5,1))),H9*(1+Assumptions!$C$7)^1,0) -> 5940 | Z9: =IF(AND(F9<=DATE(2026,6,1),OR(G9="",G9>=DATE(2026,6,1))),H9*(1+Assumptions!$C$7)^1,0) -> 5940 | AA9: =IF(AND(F9<=DATE(2026,7,1),OR(G9="",G9>=DATE(2026,7,1))),H9*(1+Assumptions!$C$7)^1,0) -> 5940 | AB9: =IF(AND(F9<=DATE(2026,8,1),OR(G9="",G9>=DATE(2026,8,1))),H9*(1+Assumptions!$C$7)^1,0) -> 5940 | AC9: =IF(AND(F9<=DATE(2026,9,1),OR(G9="",G9>=DATE(2026,9,1))),H9*(1+Assumptions!$C$7)^1,0) -> 5940 | AD9: =IF(AND(F9<=DATE(2026,10,1),OR(G9="",G9>=DATE(2026,10,1))),H9*(1+Assumptions!$C$7)^1,0) -> 5940 | AE9: =IF(AND(F9<=DATE(2026,11,1),OR(G9="",G9>=DATE(2026,11,1))),H9*(1+Assumptions!$C$7)^1,0) -> 5940 | AF9: =IF(AND(F9<=DATE(2026,12,1),OR(G9="",G9>=DATE(2026,12,1))),H9*(1+Assumptions!$C$7)^1,0) -> 5940 | AG9: =IF(AND(F9<=DATE(2027,1,1),OR(G9="",G9>=DATE(2027,1,1))),H9*(1+Assumptions!$C$7)^2,0) -> 6415.2 | AH9: =IF(AND(F9<=DATE(2027,2,1),OR(G9="",G9>=DATE(2027,2,1))),H9*(1+Assumptions!$C$7)^2,0) -> 6415.2 | AI9: =IF(AND(F9<=DATE(2027,3,1),OR(G9="",G9>=DATE(2027,3,1))),H9*(1+Assumptions!$C$7)^2,0) -> 6415.2 | AJ9: =IF(AND(F9<=DATE(2027,4,1),OR(G9="",G9>=DATE(2027,4,1))),H9*(1+Assumptions!$C$7)^2,0) -> 6415.2 | AK9: =IF(AND(F9<=DATE(2027,5,1),OR(G9="",G9>=DATE(2027,5,1))),H9*(1+Assumptions!$C$7)^2,0) -> 6415.2 | AL9: =IF(AND(F9<=DATE(2027,6,1),OR(G9="",G9>=DATE(2027,6,1))),H9*(1+Assumptions!$C$7)^2,0) -> 6415.2 | AM9: =IF(AND(F9<=DATE(2027,7,1),OR(G9="",G9>=DATE(2027,7,1))),H9*(1+Assumptions!$C$7)^2,0) -> 6415.2 | AN9: =IF(AND(F9<=DATE(2027,8,1),OR(G9="",G9>=DATE(2027,8,1))),H9*(1+Assumptions!$C$7)^2,0) -> 6415.2 | AO9: =IF(AND(F9<=DATE(2027,9,1),OR(G9="",G9>=DATE(2027,9,1))),H9*(1+Assumptions!$C$7)^2,0) -> 6415.2 | AP9: =IF(AND(F9<=DATE(2027,10,1),OR(G9="",G9>=DATE(2027,10,1))),H9*(1+Assumptions!$C$7)^2,0) -> 6415.2 | AQ9: =IF(AND(F9<=DATE(2027,11,1),OR(G9="",G9>=DATE(2027,11,1))),H9*(1+Assumptions!$C$7)^2,0) -> 6415.2 | AR9: =IF(AND(F9<=DATE(2027,12,1),OR(G9="",G9>=DATE(2027,12,1))),H9*(1+Assumptions!$C$7)^2,0) -> 6415.2 | AS9: =IF(AND(F9<=DATE(2028,1,1),OR(G9="",G9>=DATE(2028,1,1))),H9*(1+Assumptions!$C$7)^3,0) -> 6928.416 | AT9: =IF(AND(F9<=DATE(2028,2,1),OR(G9="",G9>=DATE(2028,2,1))),H9*(1+Assumptions!$C$7)^3,0) -> 6928.416 | AU9: =IF(AND(F9<=DATE(2028,3,1),OR(G9="",G9>=DATE(2028,3,1))),H9*(1+Assumptions!$C$7)^3,0) -> 6928.416 | AV9: =IF(AND(F9<=DATE(2028,4,1),OR(G9="",G9>=DATE(2028,4,1))),H9*(1+Assumptions!$C$7)^3,0) -> 6928.416 | AW9: =IF(AND(F9<=DATE(2028,5,1),OR(G9="",G9>=DATE(2028,5,1))),H9*(1+Assumptions!$C$7)^3,0) -> 6928.416 | AX9: =IF(AND(F9<=DATE(2028,6,1),OR(G9="",G9>=DATE(2028,6,1))),H9*(1+Assumptions!$C$7)^3,0) -> 6928.416 | AY9: =IF(AND(F9<=DATE(2028,7,1),OR(G9="",G9>=DATE(2028,7,1))),H9*(1+Assumptions!$C$7)^3,0) -> 6928.416 | AZ9: =IF(AND(F9<=DATE(2028,8,1),OR(G9="",G9>=DATE(2028,8,1))),H9*(1+Assumptions!$C$7)^3,0) -> 6928.416 | BA9: =IF(AND(F9<=DATE(2028,9,1),OR(G9="",G9>=DATE(2028,9,1))),H9*(1+Assumptions!$C$7)^3,0) -> 6928.416 | BB9: =IF(AND(F9<=DATE(2028,10,1),OR(G9="",G9>=DATE(2028,10,1))),H9*(1+Assumptions!$C$7)^3,0) -> 6928.416 | BC9: =IF(AND(F9<=DATE(2028,11,1),OR(G9="",G9>=DATE(2028,11,1))),H9*(1+Assumptions!$C$7)^3,0) -> 6928.416 | BD9: =IF(AND(F9<=DATE(2028,12,1),OR(G9="",G9>=DATE(2028,12,1))),H9*(1+Assumptions!$C$7)^3,0) -> 6928.416 | BE9: =IF(AND(G9<=DATE(2028,12,1),OR(H9="",H9>=DATE(2028,12,1))),I9*(1+Assumptions!$C$7)^3,0) -> 0 | BF9: =IF(AND(H9<=DATE(2028,12,1),OR(I9="",I9>=DATE(2028,12,1))),J9*(1+Assumptions!$C$7)^3,0) -> 0 | BG9: =IF(AND(I9<=DATE(2028,12,1),OR(J9="",J9>=DATE(2028,12,1))),K9*(1+Assumptions!$C$7)^3,0) -> 0 | BH9: =IF(AND(J9<=DATE(2028,12,1),OR(K9="",K9>=DATE(2028,12,1))),L9*(1+Assumptions!$C$7)^3,0) -> 0 | BI9: =IF(AND(K9<=DATE(2028,12,1),OR(L9="",L9>=DATE(2028,12,1))),M9*(1+Assumptions!$C$7)^3,0) -> 0 | BJ9: =IF(AND(L9<=DATE(2028,12,1),OR(M9="",M9>=DATE(2028,12,1))),N9*(1+Assumptions!$C$7)^3,0) -> 0 | BK9: =IF(AND(M9<=DATE(2028,12,1),OR(N9="",N9>=DATE(2028,12,1))),O9*(1+Assumptions!$C$7)^3,0) -> 0 | ... BP9: =IF(AND(R9<=DATE(2028,12,1),OR(S9="",S9>=DATE(2028,12,1))),T9*(1+Assumptions!$C$7)^3,0) -> 0
A10: 11 | B10: CFO (part time) | C10: G&A | D10: CFO | E10: Current | F10: 45901 | G10: 46266 | H10: 4000 | I10: =IF(AND(F10<=DATE(2025,1,1),OR(G10="",G10>=DATE(2025,1,1))),H10*(1+Assumptions!$C$7)^0,0) -> 0 | J10: =IF(AND(F10<=DATE(2025,2,1),OR(G10="",G10>=DATE(2025,2,1))),H10*(1+Assumptions!$C$7)^0,0) -> 0 | K10: =IF(AND(F10<=DATE(2025,3,1),OR(G10="",G10>=DATE(2025,3,1))),H10*(1+Assumptions!$C$7)^0,0) -> 0 | L10: =IF(AND(F10<=DATE(2025,4,1),OR(G10="",G10>=DATE(2025,4,1))),H10*(1+Assumptions!$C$7)^0,0) -> 0 | M10: =IF(AND(F10<=DATE(2025,5,1),OR(G10="",G10>=DATE(2025,5,1))),H10*(1+Assumptions!$C$7)^0,0) -> 0 | N10: =IF(AND(F10<=DATE(2025,6,1),OR(G10="",G10>=DATE(2025,6,1))),H10*(1+Assumptions!$C$7)^0,0) -> 0 | O10: =IF(AND(F10<=DATE(2025,7,1),OR(G10="",G10>=DATE(2025,7,1))),H10*(1+Assumptions!$C$7)^0,0) -> 0 | P10: =IF(AND(F10<=DATE(2025,8,1),OR(G10="",G10>=DATE(2025,8,1))),H10*(1+Assumptions!$C$7)^0,0) -> 0 | Q10: =IF(AND(F10<=DATE(2025,9,1),OR(G10="",G10>=DATE(2025,9,1))),H10*(1+Assumptions!$C$7)^0,0) -> 4000 | R10: =IF(AND(F10<=DATE(2025,10,1),OR(G10="",G10>=DATE(2025,10,1))),H10*(1+Assumptions!$C$7)^0,0) -> 4000 | S10: =IF(AND(F10<=DATE(2025,11,1),OR(G10="",G10>=DATE(2025,11,1))),H10*(1+Assumptions!$C$7)^0,0) -> 4000 | T10: =IF(AND(F10<=DATE(2025,12,1),OR(G10="",G10>=DATE(2025,12,1))),H10*(1+Assumptions!$C$7)^0,0) -> 4000 | U10: =IF(AND(F10<=DATE(2026,1,1),OR(G10="",G10>=DATE(2026,1,1))),H10*(1+Assumptions!$C$7)^1,0) -> 4320 | V10: =IF(AND(F10<=DATE(2026,2,1),OR(G10="",G10>=DATE(2026,2,1))),H10*(1+Assumptions!$C$7)^1,0) -> 4320 | W10: =IF(AND(F10<=DATE(2026,3,1),OR(G10="",G10>=DATE(2026,3,1))),H10*(1+Assumptions!$C$7)^1,0) -> 4320 | X10: =IF(AND(F10<=DATE(2026,4,1),OR(G10="",G10>=DATE(2026,4,1))),H10*(1+Assumptions!$C$7)^1,0) -> 4320 | Y10: =IF(AND(F10<=DATE(2026,5,1),OR(G10="",G10>=DATE(2026,5,1))),H10*(1+Assumptions!$C$7)^1,0) -> 4320 | Z10: =IF(AND(F10<=DATE(2026,6,1),OR(G10="",G10>=DATE(2026,6,1))),H10*(1+Assumptions!$C$7)^1,0) -> 4320 | AA10: =IF(AND(F10<=DATE(2026,7,1),OR(G10="",G10>=DATE(2026,7,1))),H10*(1+Assumptions!$C$7)^1,0) -> 4320 | AB10: =IF(AND(F10<=DATE(2026,8,1),OR(G10="",G10>=DATE(2026,8,1))),H10*(1+Assumptions!$C$7)^1,0) -> 4320 | AC10: =IF(AND(F10<=DATE(2026,9,1),OR(G10="",G10>=DATE(2026,9,1))),H10*(1+Assumptions!$C$7)^1,0) -> 4320 | AD10: =IF(AND(F10<=DATE(2026,10,1),OR(G10="",G10>=DATE(2026,10,1))),H10*(1+Assumptions!$C$7)^1,0) -> 0 | AE10: =IF(AND(F10<=DATE(2026,11,1),OR(G10="",G10>=DATE(2026,11,1))),H10*(1+Assumptions!$C$7)^1,0) -> 0 | AF10: =IF(AND(F10<=DATE(2026,12,1),OR(G10="",G10>=DATE(2026,12,1))),H10*(1+Assumptions!$C$7)^1,0) -> 0 | AG10: =IF(AND(F10<=DATE(2027,1,1),OR(G10="",G10>=DATE(2027,1,1))),H10*(1+Assumptions!$C$7)^2,0) -> 0 | AH10: =IF(AND(F10<=DATE(2027,2,1),OR(G10="",G10>=DATE(2027,2,1))),H10*(1+Assumptions!$C$7)^2,0) -> 0 | AI10: =IF(AND(F10<=DATE(2027,3,1),OR(G10="",G10>=DATE(2027,3,1))),H10*(1+Assumptions!$C$7)^2,0) -> 0 | AJ10: =IF(AND(F10<=DATE(2027,4,1),OR(G10="",G10>=DATE(2027,4,1))),H10*(1+Assumptions!$C$7)^2,0) -> 0 | AK10: =IF(AND(F10<=DATE(2027,5,1),OR(G10="",G10>=DATE(2027,5,1))),H10*(1+Assumptions!$C$7)^2,0) -> 0 | AL10: =IF(AND(F10<=DATE(2027,6,1),OR(G10="",G10>=DATE(2027,6,1))),H10*(1+Assumptions!$C$7)^2,0) -> 0 | AM10: =IF(AND(F10<=DATE(2027,7,1),OR(G10="",G10>=DATE(2027,7,1))),H10*(1+Assumptions!$C$7)^2,0) -> 0 | AN10: =IF(AND(F10<=DATE(2027,8,1),OR(G10="",G10>=DATE(2027,8,1))),H10*(1+Assumptions!$C$7)^2,0) -> 0 | AO10: =IF(AND(F10<=DATE(2027,9,1),OR(G10="",G10>=DATE(2027,9,1))),H10*(1+Assumptions!$C$7)^2,0) -> 0 | AP10: =IF(AND(F10<=DATE(2027,10,1),OR(G10="",G10>=DATE(2027,10,1))),H10*(1+Assumptions!$C$7)^2,0) -> 0 | AQ10: =IF(AND(F10<=DATE(2027,11,1),OR(G10="",G10>=DATE(2027,11,1))),H10*(1+Assumptions!$C$7)^2,0) -> 0 | AR10: =IF(AND(F10<=DATE(2027,12,1),OR(G10="",G10>=DATE(2027,12,1))),H10*(1+Assumptions!$C$7)^2,0) -> 0 | AS10: =IF(AND(F10<=DATE(2028,1,1),OR(G10="",G10>=DATE(2028,1,1))),H10*(1+Assumptions!$C$7)^3,0) -> 0 | AT10: =IF(AND(F10<=DATE(2028,2,1),OR(G10="",G10>=DATE(2028,2,1))),H10*(1+Assumptions!$C$7)^3,0) -> 0 | AU10: =IF(AND(F10<=DATE(2028,3,1),OR(G10="",G10>=DATE(2028,3,1))),H10*(1+Assumptions!$C$7)^3,0) -> 0 | AV10: =IF(AND(F10<=DATE(2028,4,1),OR(G10="",G10>=DATE(2028,4,1))),H10*(1+Assumptions!$C$7)^3,0) -> 0 | AW10: =IF(AND(F10<=DATE(2028,5,1),OR(G10="",G10>=DATE(2028,5,1))),H10*(1+Assumptions!$C$7)^3,0) -> 0 | AX10: =IF(AND(F10<=DATE(2028,6,1),OR(G10="",G10>=DATE(2028,6,1))),H10*(1+Assumptions!$C$7)^3,0) -> 0 | AY10: =IF(AND(F10<=DATE(2028,7,1),OR(G10="",G10>=DATE(2028,7,1))),H10*(1+Assumptions!$C$7)^3,0) -> 0 | AZ10: =IF(AND(F10<=DATE(2028,8,1),OR(G10="",G10>=DATE(2028,8,1))),H10*(1+Assumptions!$C$7)^3,0) -> 0 | BA10: =IF(AND(F10<=DATE(2028,9,1),OR(G10="",G10>=DATE(2028,9,1))),H10*(1+Assumptions!$C$7)^3,0) -> 0 | BB10: =IF(AND(F10<=DATE(2028,10,1),OR(G10="",G10>=DATE(2028,10,1))),H10*(1+Assumptions!$C$7)^3,0) -> 0 | BC10: =IF(AND(F10<=DATE(2028,11,1),OR(G10="",G10>=DATE(2028,11,1))),H10*(1+Assumptions!$C$7)^3,0) -> 0 | BD10: =IF(AND(F10<=DATE(2028,12,1),OR(G10="",G10>=DATE(2028,12,1))),H10*(1+Assumptions!$C$7)^3,0) -> 0 | BE10: =IF(AND(G10<=DATE(2028,12,1),OR(H10="",H10>=DATE(2028,12,1))),I10*(1+Assumptions!$C$7)^3,0) -> 0 | BF10: =IF(AND(H10<=DATE(2028,12,1),OR(I10="",I10>=DATE(2028,12,1))),J10*(1+Assumptions!$C$7)^3,0) -> 0 | BG10: =IF(AND(I10<=DATE(2028,12,1),OR(J10="",J10>=DATE(2028,12,1))),K10*(1+Assumptions!$C$7)^3,0) -> 0 | BH10: =IF(AND(J10<=DATE(2028,12,1),OR(K10="",K10>=DATE(2028,12,1))),L10*(1+Assumptions!$C$7)^3,0) -> 0 | BI10: =IF(AND(K10<=DATE(2028,12,1),OR(L10="",L10>=DATE(2028,12,1))),M10*(1+Assumptions!$C$7)^3,0) -> 0 | BJ10: =IF(AND(L10<=DATE(2028,12,1),OR(M10="",M10>=DATE(2028,12,1))),N10*(1+Assumptions!$C$7)^3,0) -> 0 | BK10: =IF(AND(M10<=DATE(2028,12,1),OR(N10="",N10>=DATE(2028,12,1))),O10*(1+Assumptions!$C$7)^3,0) -> 0 | ... BP10: =IF(AND(R10<=DATE(2028,12,1),OR(S10="",S10>=DATE(2028,12,1))),T10*(1+Assumptions!$C$7)^3,0) -> 0
A11: 8 | B11: CTO | C11: R&D | D11: CTO | E11: Current | F11: 46266 | H11: 11500 | I11: =IF(AND(F11<=DATE(2025,1,1),OR(G11="",G11>=DATE(2025,1,1))),H11*(1+Assumptions!$C$7)^0,0) -> 0 | J11: =IF(AND(F11<=DATE(2025,2,1),OR(G11="",G11>=DATE(2025,2,1))),H11*(1+Assumptions!$C$7)^0,0) -> 0 | K11: =IF(AND(F11<=DATE(2025,3,1),OR(G11="",G11>=DATE(2025,3,1))),H11*(1+Assumptions!$C$7)^0,0) -> 0 | L11: =IF(AND(F11<=DATE(2025,4,1),OR(G11="",G11>=DATE(2025,4,1))),H11*(1+Assumptions!$C$7)^0,0) -> 0 | M11: =IF(AND(F11<=DATE(2025,5,1),OR(G11="",G11>=DATE(2025,5,1))),H11*(1+Assumptions!$C$7)^0,0) -> 0 | N11: =IF(AND(F11<=DATE(2025,6,1),OR(G11="",G11>=DATE(2025,6,1))),H11*(1+Assumptions!$C$7)^0,0) -> 0 | O11: =IF(AND(F11<=DATE(2025,7,1),OR(G11="",G11>=DATE(2025,7,1))),H11*(1+Assumptions!$C$7)^0,0) -> 0 | P11: =IF(AND(F11<=DATE(2025,8,1),OR(G11="",G11>=DATE(2025,8,1))),H11*(1+Assumptions!$C$7)^0,0) -> 0 | Q11: 7500 | R11: 7500 | S11: 7500 | T11: 7500 | U11: 7500 | V11: 7500 | W11: 7500 | X11: 7500 | Y11: 7500 | Z11: 7500 | AA11: 7500 | AB11: 7500 | AC11: =IF(AND(F11<=DATE(2026,9,1),OR(G11="",G11>=DATE(2026,9,1))),H11) -> 11500 | AD11: =IF(AND(F11<=DATE(2026,10,1),OR(G11="",G11>=DATE(2026,10,1))),H11*(1+Assumptions!$C$7)^1,0) -> 12420 | AE11: =IF(AND(F11<=DATE(2026,11,1),OR(G11="",G11>=DATE(2026,11,1))),H11*(1+Assumptions!$C$7)^1,0) -> 12420 | AF11: =IF(AND(F11<=DATE(2026,12,1),OR(G11="",G11>=DATE(2026,12,1))),H11*(1+Assumptions!$C$7)^1,0) -> 12420 | AG11: =IF(AND(F11<=DATE(2027,1,1),OR(G11="",G11>=DATE(2027,1,1))),H11*(1+Assumptions!$C$7)^2,0) -> 13413.6 | AH11: =IF(AND(F11<=DATE(2027,2,1),OR(G11="",G11>=DATE(2027,2,1))),H11*(1+Assumptions!$C$7)^2,0) -> 13413.6 | AI11: =IF(AND(F11<=DATE(2027,3,1),OR(G11="",G11>=DATE(2027,3,1))),H11*(1+Assumptions!$C$7)^2,0) -> 13413.6 | AJ11: =IF(AND(F11<=DATE(2027,4,1),OR(G11="",G11>=DATE(2027,4,1))),H11*(1+Assumptions!$C$7)^2,0) -> 13413.6 | AK11: =IF(AND(F11<=DATE(2027,5,1),OR(G11="",G11>=DATE(2027,5,1))),H11*(1+Assumptions!$C$7)^2,0) -> 13413.6 | AL11: =IF(AND(F11<=DATE(2027,6,1),OR(G11="",G11>=DATE(2027,6,1))),H11*(1+Assumptions!$C$7)^2,0) -> 13413.6 | AM11: =IF(AND(F11<=DATE(2027,7,1),OR(G11="",G11>=DATE(2027,7,1))),H11*(1+Assumptions!$C$7)^2,0) -> 13413.6 | AN11: =IF(AND(F11<=DATE(2027,8,1),OR(G11="",G11>=DATE(2027,8,1))),H11*(1+Assumptions!$C$7)^2,0) -> 13413.6 | AO11: =IF(AND(F11<=DATE(2027,9,1),OR(G11="",G11>=DATE(2027,9,1))),H11*(1+Assumptions!$C$7)^2,0) -> 13413.6 | AP11: =IF(AND(F11<=DATE(2027,10,1),OR(G11="",G11>=DATE(2027,10,1))),H11*(1+Assumptions!$C$7)^2,0) -> 13413.6 | AQ11: =IF(AND(F11<=DATE(2027,11,1),OR(G11="",G11>=DATE(2027,11,1))),H11*(1+Assumptions!$C$7)^2,0) -> 13413.6 | AR11: =IF(AND(F11<=DATE(2027,12,1),OR(G11="",G11>=DATE(2027,12,1))),H11*(1+Assumptions!$C$7)^2,0) -> 13413.6 | AS11: =IF(AND(F11<=DATE(2028,1,1),OR(G11="",G11>=DATE(2028,1,1))),H11*(1+Assumptions!$C$7)^3,0) -> 14486.688 | AT11: =IF(AND(F11<=DATE(2028,2,1),OR(G11="",G11>=DATE(2028,2,1))),H11*(1+Assumptions!$C$7)^3,0) -> 14486.688 | AU11: =IF(AND(F11<=DATE(2028,3,1),OR(G11="",G11>=DATE(2028,3,1))),H11*(1+Assumptions!$C$7)^3,0) -> 14486.688 | AV11: =IF(AND(F11<=DATE(2028,4,1),OR(G11="",G11>=DATE(2028,4,1))),H11*(1+Assumptions!$C$7)^3,0) -> 14486.688 | AW11: =IF(AND(F11<=DATE(2028,5,1),OR(G11="",G11>=DATE(2028,5,1))),H11*(1+Assumptions!$C$7)^3,0) -> 14486.688 | AX11: =IF(AND(F11<=DATE(2028,6,1),OR(G11="",G11>=DATE(2028,6,1))),H11*(1+Assumptions!$C$7)^3,0) -> 14486.688 | AY11: =IF(AND(F11<=DATE(2028,7,1),OR(G11="",G11>=DATE(2028,7,1))),H11*(1+Assumptions!$C$7)^3,0) -> 14486.688 | AZ11: =IF(AND(F11<=DATE(2028,8,1),OR(G11="",G11>=DATE(2028,8,1))),H11*(1+Assumptions!$C$7)^3,0) -> 14486.688 | BA11: =IF(AND(F11<=DATE(2028,9,1),OR(G11="",G11>=DATE(2028,9,1))),H11*(1+Assumptions!$C$7)^3,0) -> 14486.688 | BB11: =IF(AND(F11<=DATE(2028,10,1),OR(G11="",G11>=DATE(2028,10,1))),H11*(1+Assumptions!$C$7)^3,0) -> 14486.688 | BC11: =IF(AND(F11<=DATE(2028,11,1),OR(G11="",G11>=DATE(2028,11,1))),H11*(1+Assumptions!$C$7)^3,0) -> 14486.688 | BD11: =IF(AND(F11<=DATE(2028,12,1),OR(G11="",G11>=DATE(2028,12,1))),H11*(1+Assumptions!$C$7)^3,0) -> 14486.688 | BE11: =IF(AND(G11<=DATE(2028,12,1),OR(H11="",H11>=DATE(2028,12,1))),I11*(1+Assumptions!$C$7)^3,0) -> 0 | BF11: =IF(AND(H11<=DATE(2028,12,1),OR(I11="",I11>=DATE(2028,12,1))),J11*(1+Assumptions!$C$7)^3,0) -> 0 | BG11: =IF(AND(I11<=DATE(2028,12,1),OR(J11="",J11>=DATE(2028,12,1))),K11*(1+Assumptions!$C$7)^3,0) -> 0 | BH11: =IF(AND(J11<=DATE(2028,12,1),OR(K11="",K11>=DATE(2028,12,1))),L11*(1+Assumptions!$C$7)^3,0) -> 0 | BI11: =IF(AND(K11<=DATE(2028,12,1),OR(L11="",L11>=DATE(2028,12,1))),M11*(1+Assumptions!$C$7)^3,0) -> 0 | BJ11: =IF(AND(L11<=DATE(2028,12,1),OR(M11="",M11>=DATE(2028,12,1))),N11*(1+Assumptions!$C$7)^3,0) -> 0 | BK11: =IF(AND(M11<=DATE(2028,12,1),OR(N11="",N11>=DATE(2028,12,1))),O11*(1+Assumptions!$C$7)^3,0) -> 0 | ... BP11: =IF(AND(R11<=DATE(2028,12,1),OR(S11="",S11>=DATE(2028,12,1))),T11*(1+Assumptions!$C$7)^3,0) -> 0
A12: 9 | B12: Head of Growth | C12: S&M | D12: Growth | E12: Current | F12: 46054 | H12: 10000 | I12: =IF(AND(F12<=DATE(2025,1,1),OR(G12="",G12>=DATE(2025,1,1))),H12*(1+Assumptions!$C$7)^0,0) -> 0 | J12: =IF(AND(F12<=DATE(2025,2,1),OR(G12="",G12>=DATE(2025,2,1))),H12*(1+Assumptions!$C$7)^0,0) -> 0 | K12: =IF(AND(F12<=DATE(2025,3,1),OR(G12="",G12>=DATE(2025,3,1))),H12*(1+Assumptions!$C$7)^0,0) -> 0 | L12: =IF(AND(F12<=DATE(2025,4,1),OR(G12="",G12>=DATE(2025,4,1))),H12*(1+Assumptions!$C$7)^0,0) -> 0 | M12: =IF(AND(F12<=DATE(2025,5,1),OR(G12="",G12>=DATE(2025,5,1))),H12*(1+Assumptions!$C$7)^0,0) -> 0 | N12: =IF(AND(F12<=DATE(2025,6,1),OR(G12="",G12>=DATE(2025,6,1))),H12*(1+Assumptions!$C$7)^0,0) -> 0 | O12: =IF(AND(F12<=DATE(2025,7,1),OR(G12="",G12>=DATE(2025,7,1))),H12*(1+Assumptions!$C$7)^0,0) -> 0 | P12: =IF(AND(F12<=DATE(2025,8,1),OR(G12="",G12>=DATE(2025,8,1))),H12*(1+Assumptions!$C$7)^0,0) -> 0 | Q12: =IF(AND(F12<=DATE(2025,9,1),OR(G12="",G12>=DATE(2025,9,1))),H12*(1+Assumptions!$C$7)^0,0) -> 0 | R12: =IF(AND(F12<=DATE(2025,10,1),OR(G12="",G12>=DATE(2025,10,1))),H12*(1+Assumptions!$C$7)^0,0) -> 0 | S12: =IF(AND(F12<=DATE(2025,11,1),OR(G12="",G12>=DATE(2025,11,1))),H12*(1+Assumptions!$C$7)^0,0) -> 0 | T12: =IF(AND(F12<=DATE(2025,12,1),OR(G12="",G12>=DATE(2025,12,1))),H12*(1+Assumptions!$C$7)^0,0) -> 0 | U12: =IF(AND(F12<=DATE(2026,1,1),OR(G12="",G12>=DATE(2026,1,1))),H12*(1+Assumptions!$C$7)^1,0) -> 0 | V12: =IF(AND(F12<=DATE(2026,2,1),OR(G12="",G12>=DATE(2026,2,1))),H12*(1+Assumptions!$C$7)^1,0) -> 10800 | W12: =IF(AND(F12<=DATE(2026,3,1),OR(G12="",G12>=DATE(2026,3,1))),H12*(1+Assumptions!$C$7)^1,0) -> 10800 | X12: =IF(AND(F12<=DATE(2026,4,1),OR(G12="",G12>=DATE(2026,4,1))),H12*(1+Assumptions!$C$7)^1,0) -> 10800 | Y12: =IF(AND(F12<=DATE(2026,5,1),OR(G12="",G12>=DATE(2026,5,1))),H12*(1+Assumptions!$C$7)^1,0) -> 10800 | Z12: =IF(AND(F12<=DATE(2026,6,1),OR(G12="",G12>=DATE(2026,6,1))),H12*(1+Assumptions!$C$7)^1,0) -> 10800 | AA12: =IF(AND(F12<=DATE(2026,7,1),OR(G12="",G12>=DATE(2026,7,1))),H12*(1+Assumptions!$C$7)^1,0) -> 10800 | AB12: =IF(AND(F12<=DATE(2026,8,1),OR(G12="",G12>=DATE(2026,8,1))),H12*(1+Assumptions!$C$7)^1,0) -> 10800 | AC12: =IF(AND(F12<=DATE(2026,9,1),OR(G12="",G12>=DATE(2026,9,1))),H12*(1+Assumptions!$C$7)^1,0) -> 10800 | AD12: =IF(AND(F12<=DATE(2026,10,1),OR(G12="",G12>=DATE(2026,10,1))),H12*(1+Assumptions!$C$7)^1,0) -> 10800 | AE12: =IF(AND(F12<=DATE(2026,11,1),OR(G12="",G12>=DATE(2026,11,1))),H12*(1+Assumptions!$C$7)^1,0) -> 10800 | AF12: =IF(AND(F12<=DATE(2026,12,1),OR(G12="",G12>=DATE(2026,12,1))),H12*(1+Assumptions!$C$7)^1,0) -> 10800 | AG12: =IF(AND(F12<=DATE(2027,1,1),OR(G12="",G12>=DATE(2027,1,1))),H12*(1+Assumptions!$C$7)^2,0) -> 11664 | AH12: =IF(AND(F12<=DATE(2027,2,1),OR(G12="",G12>=DATE(2027,2,1))),H12*(1+Assumptions!$C$7)^2,0) -> 11664 | AI12: =IF(AND(F12<=DATE(2027,3,1),OR(G12="",G12>=DATE(2027,3,1))),H12*(1+Assumptions!$C$7)^2,0) -> 11664 | AJ12: =IF(AND(F12<=DATE(2027,4,1),OR(G12="",G12>=DATE(2027,4,1))),H12*(1+Assumptions!$C$7)^2,0) -> 11664 | AK12: =IF(AND(F12<=DATE(2027,5,1),OR(G12="",G12>=DATE(2027,5,1))),H12*(1+Assumptions!$C$7)^2,0) -> 11664 | AL12: =IF(AND(F12<=DATE(2027,6,1),OR(G12="",G12>=DATE(2027,6,1))),H12*(1+Assumptions!$C$7)^2,0) -> 11664 | AM12: =IF(AND(F12<=DATE(2027,7,1),OR(G12="",G12>=DATE(2027,7,1))),H12*(1+Assumptions!$C$7)^2,0) -> 11664 | AN12: =IF(AND(F12<=DATE(2027,8,1),OR(G12="",G12>=DATE(2027,8,1))),H12*(1+Assumptions!$C$7)^2,0) -> 11664 | AO12: =IF(AND(F12<=DATE(2027,9,1),OR(G12="",G12>=DATE(2027,9,1))),H12*(1+Assumptions!$C$7)^2,0) -> 11664 | AP12: =IF(AND(F12<=DATE(2027,10,1),OR(G12="",G12>=DATE(2027,10,1))),H12*(1+Assumptions!$C$7)^2,0) -> 11664 | AQ12: =IF(AND(F12<=DATE(2027,11,1),OR(G12="",G12>=DATE(2027,11,1))),H12*(1+Assumptions!$C$7)^2,0) -> 11664 | AR12: =IF(AND(F12<=DATE(2027,12,1),OR(G12="",G12>=DATE(2027,12,1))),H12*(1+Assumptions!$C$7)^2,0) -> 11664 | AS12: =IF(AND(F12<=DATE(2028,1,1),OR(G12="",G12>=DATE(2028,1,1))),H12*(1+Assumptions!$C$7)^3,0) -> 12597.12 | AT12: =IF(AND(F12<=DATE(2028,2,1),OR(G12="",G12>=DATE(2028,2,1))),H12*(1+Assumptions!$C$7)^3,0) -> 12597.12 | AU12: =IF(AND(F12<=DATE(2028,3,1),OR(G12="",G12>=DATE(2028,3,1))),H12*(1+Assumptions!$C$7)^3,0) -> 12597.12 | AV12: =IF(AND(F12<=DATE(2028,4,1),OR(G12="",G12>=DATE(2028,4,1))),H12*(1+Assumptions!$C$7)^3,0) -> 12597.12 | AW12: =IF(AND(F12<=DATE(2028,5,1),OR(G12="",G12>=DATE(2028,5,1))),H12*(1+Assumptions!$C$7)^3,0) -> 12597.12 | AX12: =IF(AND(F12<=DATE(2028,6,1),OR(G12="",G12>=DATE(2028,6,1))),H12*(1+Assumptions!$C$7)^3,0) -> 12597.12 | AY12: =IF(AND(F12<=DATE(2028,7,1),OR(G12="",G12>=DATE(2028,7,1))),H12*(1+Assumptions!$C$7)^3,0) -> 12597.12 | AZ12: =IF(AND(F12<=DATE(2028,8,1),OR(G12="",G12>=DATE(2028,8,1))),H12*(1+Assumptions!$C$7)^3,0) -> 12597.12 | BA12: =IF(AND(F12<=DATE(2028,9,1),OR(G12="",G12>=DATE(2028,9,1))),H12*(1+Assumptions!$C$7)^3,0) -> 12597.12 | BB12: =IF(AND(F12<=DATE(2028,10,1),OR(G12="",G12>=DATE(2028,10,1))),H12*(1+Assumptions!$C$7)^3,0) -> 12597.12 | BC12: =IF(AND(F12<=DATE(2028,11,1),OR(G12="",G12>=DATE(2028,11,1))),H12*(1+Assumptions!$C$7)^3,0) -> 12597.12 | BD12: =IF(AND(F12<=DATE(2028,12,1),OR(G12="",G12>=DATE(2028,12,1))),H12*(1+Assumptions!$C$7)^3,0) -> 12597.12 | BE12: =IF(AND(G12<=DATE(2028,12,1),OR(H12="",H12>=DATE(2028,12,1))),I12*(1+Assumptions!$C$7)^3,0) -> 0 | BF12: =IF(AND(H12<=DATE(2028,12,1),OR(I12="",I12>=DATE(2028,12,1))),J12*(1+Assumptions!$C$7)^3,0) -> 0 | BG12: =IF(AND(I12<=DATE(2028,12,1),OR(J12="",J12>=DATE(2028,12,1))),K12*(1+Assumptions!$C$7)^3,0) -> 0 | BH12: =IF(AND(J12<=DATE(2028,12,1),OR(K12="",K12>=DATE(2028,12,1))),L12*(1+Assumptions!$C$7)^3,0) -> 0 | BI12: =IF(AND(K12<=DATE(2028,12,1),OR(L12="",L12>=DATE(2028,12,1))),M12*(1+Assumptions!$C$7)^3,0) -> 0 | BJ12: =IF(AND(L12<=DATE(2028,12,1),OR(M12="",M12>=DATE(2028,12,1))),N12*(1+Assumptions!$C$7)^3,0) -> 0 | BK12: =IF(AND(M12<=DATE(2028,12,1),OR(N12="",N12>=DATE(2028,12,1))),O12*(1+Assumptions!$C$7)^3,0) -> 0 | ... BP12: =IF(AND(R12<=DATE(2028,12,1),OR(S12="",S12>=DATE(2028,12,1))),T12*(1+Assumptions!$C$7)^3,0) -> 0
A13: 10 | B13: CEO | C13: G&A | D13: CEO | E13: Current | F13: 46266 | H13: 11500 | I13: =IF(AND(F13<=DATE(2025,1,1),OR(G13="",G13>=DATE(2025,1,1))),H13*(1+Assumptions!$C$7)^0,0) -> 0 | J13: =IF(AND(F13<=DATE(2025,2,1),OR(G13="",G13>=DATE(2025,2,1))),H13*(1+Assumptions!$C$7)^0,0) -> 0 | K13: =IF(AND(F13<=DATE(2025,3,1),OR(G13="",G13>=DATE(2025,3,1))),H13*(1+Assumptions!$C$7)^0,0) -> 0 | L13: =IF(AND(F13<=DATE(2025,4,1),OR(G13="",G13>=DATE(2025,4,1))),H13*(1+Assumptions!$C$7)^0,0) -> 0 | M13: =IF(AND(F13<=DATE(2025,5,1),OR(G13="",G13>=DATE(2025,5,1))),H13*(1+Assumptions!$C$7)^0,0) -> 0 | N13: =IF(AND(F13<=DATE(2025,6,1),OR(G13="",G13>=DATE(2025,6,1))),H13*(1+Assumptions!$C$7)^0,0) -> 0 | O13: =IF(AND(F13<=DATE(2025,7,1),OR(G13="",G13>=DATE(2025,7,1))),H13*(1+Assumptions!$C$7)^0,0) -> 0 | P13: =IF(AND(F13<=DATE(2025,8,1),OR(G13="",G13>=DATE(2025,8,1))),H13*(1+Assumptions!$C$7)^0,0) -> 0 | Q13: 7500 | R13: 7500 | S13: 7500 | T13: 7500 | U13: 7500 | V13: 7500 | W13: 7500 | X13: 7500 | Y13: 7500 | Z13: 7500 | AA13: 7500 | AB13: 7500 | AC13: =IF(AND(F13<=DATE(2026,9,1),OR(G13="",G13>=DATE(2026,9,1))),H13*(1+Assumptions!$C$7)^1,0) -> 12420 | AD13: =IF(AND(F13<=DATE(2026,10,1),OR(G13="",G13>=DATE(2026,10,1))),H13*(1+Assumptions!$C$7)^1,0) -> 12420 | AE13: =IF(AND(F13<=DATE(2026,11,1),OR(G13="",G13>=DATE(2026,11,1))),H13*(1+Assumptions!$C$7)^1,0) -> 12420 | AF13: =IF(AND(F13<=DATE(2026,12,1),OR(G13="",G13>=DATE(2026,12,1))),H13*(1+Assumptions!$C$7)^1,0) -> 12420 | AG13: =IF(AND(F13<=DATE(2027,1,1),OR(G13="",G13>=DATE(2027,1,1))),H13*(1+Assumptions!$C$7)^2,0) -> 13413.6 | AH13: =IF(AND(F13<=DATE(2027,2,1),OR(G13="",G13>=DATE(2027,2,1))),H13*(1+Assumptions!$C$7)^2,0) -> 13413.6 | AI13: =IF(AND(F13<=DATE(2027,3,1),OR(G13="",G13>=DATE(2027,3,1))),H13*(1+Assumptions!$C$7)^2,0) -> 13413.6 | AJ13: =IF(AND(F13<=DATE(2027,4,1),OR(G13="",G13>=DATE(2027,4,1))),H13*(1+Assumptions!$C$7)^2,0) -> 13413.6 | AK13: =IF(AND(F13<=DATE(2027,5,1),OR(G13="",G13>=DATE(2027,5,1))),H13*(1+Assumptions!$C$7)^2,0) -> 13413.6 | AL13: =IF(AND(F13<=DATE(2027,6,1),OR(G13="",G13>=DATE(2027,6,1))),H13*(1+Assumptions!$C$7)^2,0) -> 13413.6 | AM13: =IF(AND(F13<=DATE(2027,7,1),OR(G13="",G13>=DATE(2027,7,1))),H13*(1+Assumptions!$C$7)^2,0) -> 13413.6 | AN13: =IF(AND(F13<=DATE(2027,8,1),OR(G13="",G13>=DATE(2027,8,1))),H13*(1+Assumptions!$C$7)^2,0) -> 13413.6 | AO13: =IF(AND(F13<=DATE(2027,9,1),OR(G13="",G13>=DATE(2027,9,1))),H13*(1+Assumptions!$C$7)^2,0) -> 13413.6 | AP13: =IF(AND(F13<=DATE(2027,10,1),OR(G13="",G13>=DATE(2027,10,1))),H13*(1+Assumptions!$C$7)^2,0) -> 13413.6 | AQ13: =IF(AND(F13<=DATE(2027,11,1),OR(G13="",G13>=DATE(2027,11,1))),H13*(1+Assumptions!$C$7)^2,0) -> 13413.6 | AR13: =IF(AND(F13<=DATE(2027,12,1),OR(G13="",G13>=DATE(2027,12,1))),H13*(1+Assumptions!$C$7)^2,0) -> 13413.6 | AS13: =IF(AND(F13<=DATE(2028,1,1),OR(G13="",G13>=DATE(2028,1,1))),H13*(1+Assumptions!$C$7)^3,0) -> 14486.688 | AT13: =IF(AND(F13<=DATE(2028,2,1),OR(G13="",G13>=DATE(2028,2,1))),H13*(1+Assumptions!$C$7)^3,0) -> 14486.688 | AU13: =IF(AND(F13<=DATE(2028,3,1),OR(G13="",G13>=DATE(2028,3,1))),H13*(1+Assumptions!$C$7)^3,0) -> 14486.688 | AV13: =IF(AND(F13<=DATE(2028,4,1),OR(G13="",G13>=DATE(2028,4,1))),H13*(1+Assumptions!$C$7)^3,0) -> 14486.688 | AW13: =IF(AND(F13<=DATE(2028,5,1),OR(G13="",G13>=DATE(2028,5,1))),H13*(1+Assumptions!$C$7)^3,0) -> 14486.688 | AX13: =IF(AND(F13<=DATE(2028,6,1),OR(G13="",G13>=DATE(2028,6,1))),H13*(1+Assumptions!$C$7)^3,0) -> 14486.688 | AY13: =IF(AND(F13<=DATE(2028,7,1),OR(G13="",G13>=DATE(2028,7,1))),H13*(1+Assumptions!$C$7)^3,0) -> 14486.688 | AZ13: =IF(AND(F13<=DATE(2028,8,1),OR(G13="",G13>=DATE(2028,8,1))),H13*(1+Assumptions!$C$7)^3,0) -> 14486.688 | BA13: =IF(AND(F13<=DATE(2028,9,1),OR(G13="",G13>=DATE(2028,9,1))),H13*(1+Assumptions!$C$7)^3,0) -> 14486.688 | BB13: =IF(AND(F13<=DATE(2028,10,1),OR(G13="",G13>=DATE(2028,10,1))),H13*(1+Assumptions!$C$7)^3,0) -> 14486.688 | BC13: =IF(AND(F13<=DATE(2028,11,1),OR(G13="",G13>=DATE(2028,11,1))),H13*(1+Assumptions!$C$7)^3,0) -> 14486.688 | BD13: =IF(AND(F13<=DATE(2028,12,1),OR(G13="",G13>=DATE(2028,12,1))),H13*(1+Assumptions!$C$7)^3,0) -> 14486.688 | BE13: =IF(AND(G13<=DATE(2028,12,1),OR(H13="",H13>=DATE(2028,12,1))),I13*(1+Assumptions!$C$7)^3,0) -> 0 | BF13: =IF(AND(H13<=DATE(2028,12,1),OR(I13="",I13>=DATE(2028,12,1))),J13*(1+Assumptions!$C$7)^3,0) -> 0 | BG13: =IF(AND(I13<=DATE(2028,12,1),OR(J13="",J13>=DATE(2028,12,1))),K13*(1+Assumptions!$C$7)^3,0) -> 0 | BH13: =IF(AND(J13<=DATE(2028,12,1),OR(K13="",K13>=DATE(2028,12,1))),L13*(1+Assumptions!$C$7)^3,0) -> 0 | BI13: =IF(AND(K13<=DATE(2028,12,1),OR(L13="",L13>=DATE(2028,12,1))),M13*(1+Assumptions!$C$7)^3,0) -> 0 | BJ13: =IF(AND(L13<=DATE(2028,12,1),OR(M13="",M13>=DATE(2028,12,1))),N13*(1+Assumptions!$C$7)^3,0) -> 0 | BK13: =IF(AND(M13<=DATE(2028,12,1),OR(N13="",N13>=DATE(2028,12,1))),O13*(1+Assumptions!$C$7)^3,0) -> 0 | ... BP13: =IF(AND(R13<=DATE(2028,12,1),OR(S13="",S13>=DATE(2028,12,1))),T13*(1+Assumptions!$C$7)^3,0) -> 0
A15: # | B15: PLANNED HIRES
A16: 12 | B16: New hire | C16: R&D | D16: Software Engineer | E16: Planned | F16: 46204 | H16: 8000 | I16: =IF(AND($F16<=I$2, OR($G16="",$G16>=I$2)), $H16 * (1 + Assumptions!$C$7) ^ INT(((YEAR(I$2)-YEAR($F16))*12 + MONTH(I$2)-MONTH($F16)) / 12), 0) -> 0 | J16: =IF(AND($F16<=J$2, OR($G16="",$G16>=J$2)), $H16 * (1 + Assumptions!$C$7) ^ INT(((YEAR(J$2)-YEAR($F16))*12 + MONTH(J$2)-MONTH($F16)) / 12), 0) -> 0 | K16: =IF(AND($F16<=K$2, OR($G16="",$G16>=K$2)), $H16 * (1 + Assumptions!$C$7) ^ INT(((YEAR(K$2)-YEAR($F16))*12 + MONTH(K$2)-MONTH($F16)) / 12), 0) -> 0 | L16: =IF(AND($F16<=L$2, OR($G16="",$G16>=L$2)), $H16 * (1 + Assumptions!$C$7) ^ INT(((YEAR(L$2)-YEAR($F16))*12 + MONTH(L$2)-MONTH($F16)) / 12), 0) -> 0 | M16: =IF(AND($F16<=M$2, OR($G16="",$G16>=M$2)), $H16 * (1 + Assumptions!$C$7) ^ INT(((YEAR(M$2)-YEAR($F16))*12 + MONTH(M$2)-MONTH($F16)) / 12), 0) -> 0 | N16: =IF(AND($F16<=N$2, OR($G16="",$G16>=N$2)), $H16 * (1 + Assumptions!$C$7) ^ INT(((YEAR(N$2)-YEAR($F16))*12 + MONTH(N$2)-MONTH($F16)) / 12), 0) -> 0 | O16: =IF(AND($F16<=O$2, OR($G16="",$G16>=O$2)), $H16 * (1 + Assumptions!$C$7) ^ INT(((YEAR(O$2)-YEAR($F16))*12 + MONTH(O$2)-MONTH($F16)) / 12), 0) -> 0 | P16: =IF(AND($F16<=P$2, OR($G16="",$G16>=P$2)), $H16 * (1 + Assumptions!$C$7) ^ INT(((YEAR(P$2)-YEAR($F16))*12 + MONTH(P$2)-MONTH($F16)) / 12), 0) -> 0 | ... BP16: =IF(AND($F16<=BP$2, OR($G16="",$G16>=BP$2)), $H16 * (1 + Assumptions!$C$7) ^ INT(((YEAR(BP$2)-YEAR($F16))*12 + MONTH(BP$2)-MONTH($F16)) / 12), 0) -> 10077.696
A17: 13 | B17: New hire | C17: G&A | D17: COO | E17: Planned | F17: 46235 | H17: 9000 | I17: =IF(AND($F17<=I$2, OR($G17="",$G17>=I$2)), $H17 * (1 + Assumptions!$C$7) ^ INT(((YEAR(I$2)-YEAR($F17))*12 + MONTH(I$2)-MONTH($F17)) / 12), 0) -> 0 | J17: =IF(AND($F17<=J$2, OR($G17="",$G17>=J$2)), $H17 * (1 + Assumptions!$C$7) ^ INT(((YEAR(J$2)-YEAR($F17))*12 + MONTH(J$2)-MONTH($F17)) / 12), 0) -> 0 | K17: =IF(AND($F17<=K$2, OR($G17="",$G17>=K$2)), $H17 * (1 + Assumptions!$C$7) ^ INT(((YEAR(K$2)-YEAR($F17))*12 + MONTH(K$2)-MONTH($F17)) / 12), 0) -> 0 | L17: =IF(AND($F17<=L$2, OR($G17="",$G17>=L$2)), $H17 * (1 + Assumptions!$C$7) ^ INT(((YEAR(L$2)-YEAR($F17))*12 + MONTH(L$2)-MONTH($F17)) / 12), 0) -> 0 | M17: =IF(AND($F17<=M$2, OR($G17="",$G17>=M$2)), $H17 * (1 + Assumptions!$C$7) ^ INT(((YEAR(M$2)-YEAR($F17))*12 + MONTH(M$2)-MONTH($F17)) / 12), 0) -> 0 | N17: =IF(AND($F17<=N$2, OR($G17="",$G17>=N$2)), $H17 * (1 + Assumptions!$C$7) ^ INT(((YEAR(N$2)-YEAR($F17))*12 + MONTH(N$2)-MONTH($F17)) / 12), 0) -> 0 | O17: =IF(AND($F17<=O$2, OR($G17="",$G17>=O$2)), $H17 * (1 + Assumptions!$C$7) ^ INT(((YEAR(O$2)-YEAR($F17))*12 + MONTH(O$2)-MONTH($F17)) / 12), 0) -> 0 | P17: =IF(AND($F17<=P$2, OR($G17="",$G17>=P$2)), $H17 * (1 + Assumptions!$C$7) ^ INT(((YEAR(P$2)-YEAR($F17))*12 + MONTH(P$2)-MONTH($F17)) / 12), 0) -> 0 | ... BP17: =IF(AND($F17<=BP$2, OR($G17="",$G17>=BP$2)), $H17 * (1 + Assumptions!$C$7) ^ INT(((YEAR(BP$2)-YEAR($F17))*12 + MONTH(BP$2)-MONTH($F17)) / 12), 0) -> 11337.408
A18: 14 | B18: New hire | C18: R&D | D18: Maintenance Engineer | E18: Planned | F18: 46235 | H18: 6000 | I18: =IF(AND($F18<=I$2, OR($G18="",$G18>=I$2)), $H18 * (1 + Assumptions!$C$7) ^ INT(((YEAR(I$2)-YEAR($F18))*12 + MONTH(I$2)-MONTH($F18)) / 12), 0) -> 0 | J18: =IF(AND($F18<=J$2, OR($G18="",$G18>=J$2)), $H18 * (1 + Assumptions!$C$7) ^ INT(((YEAR(J$2)-YEAR($F18))*12 + MONTH(J$2)-MONTH($F18)) / 12), 0) -> 0 | K18: =IF(AND($F18<=K$2, OR($G18="",$G18>=K$2)), $H18 * (1 + Assumptions!$C$7) ^ INT(((YEAR(K$2)-YEAR($F18))*12 + MONTH(K$2)-MONTH($F18)) / 12), 0) -> 0 | L18: =IF(AND($F18<=L$2, OR($G18="",$G18>=L$2)), $H18 * (1 + Assumptions!$C$7) ^ INT(((YEAR(L$2)-YEAR($F18))*12 + MONTH(L$2)-MONTH($F18)) / 12), 0) -> 0 | M18: =IF(AND($F18<=M$2, OR($G18="",$G18>=M$2)), $H18 * (1 + Assumptions!$C$7) ^ INT(((YEAR(M$2)-YEAR($F18))*12 + MONTH(M$2)-MONTH($F18)) / 12), 0) -> 0 | N18: =IF(AND($F18<=N$2, OR($G18="",$G18>=N$2)), $H18 * (1 + Assumptions!$C$7) ^ INT(((YEAR(N$2)-YEAR($F18))*12 + MONTH(N$2)-MONTH($F18)) / 12), 0) -> 0 | O18: =IF(AND($F18<=O$2, OR($G18="",$G18>=O$2)), $H18 * (1 + Assumptions!$C$7) ^ INT(((YEAR(O$2)-YEAR($F18))*12 + MONTH(O$2)-MONTH($F18)) / 12), 0) -> 0 | P18: =IF(AND($F18<=P$2, OR($G18="",$G18>=P$2)), $H18 * (1 + Assumptions!$C$7) ^ INT(((YEAR(P$2)-YEAR($F18))*12 + MONTH(P$2)-MONTH($F18)) / 12), 0) -> 0 | ... BP18: =IF(AND($F18<=BP$2, OR($G18="",$G18>=BP$2)), $H18 * (1 + Assumptions!$C$7) ^ INT(((YEAR(BP$2)-YEAR($F18))*12 + MONTH(BP$2)-MONTH($F18)) / 12), 0) -> 7558.272
A19: 15 | B19: New hire | C19: S&M | D19: Marketing | E19: Planned | F19: 46235 | H19: 9000 | I19: =IF(AND($F19<=I$2, OR($G19="",$G19>=I$2)), $H19 * (1 + Assumptions!$C$7) ^ INT(((YEAR(I$2)-YEAR($F19))*12 + MONTH(I$2)-MONTH($F19)) / 12), 0) -> 0 | J19: =IF(AND($F19<=J$2, OR($G19="",$G19>=J$2)), $H19 * (1 + Assumptions!$C$7) ^ INT(((YEAR(J$2)-YEAR($F19))*12 + MONTH(J$2)-MONTH($F19)) / 12), 0) -> 0 | K19: =IF(AND($F19<=K$2, OR($G19="",$G19>=K$2)), $H19 * (1 + Assumptions!$C$7) ^ INT(((YEAR(K$2)-YEAR($F19))*12 + MONTH(K$2)-MONTH($F19)) / 12), 0) -> 0 | L19: =IF(AND($F19<=L$2, OR($G19="",$G19>=L$2)), $H19 * (1 + Assumptions!$C$7) ^ INT(((YEAR(L$2)-YEAR($F19))*12 + MONTH(L$2)-MONTH($F19)) / 12), 0) -> 0 | M19: =IF(AND($F19<=M$2, OR($G19="",$G19>=M$2)), $H19 * (1 + Assumptions!$C$7) ^ INT(((YEAR(M$2)-YEAR($F19))*12 + MONTH(M$2)-MONTH($F19)) / 12), 0) -> 0 | N19: =IF(AND($F19<=N$2, OR($G19="",$G19>=N$2)), $H19 * (1 + Assumptions!$C$7) ^ INT(((YEAR(N$2)-YEAR($F19))*12 + MONTH(N$2)-MONTH($F19)) / 12), 0) -> 0 | O19: =IF(AND($F19<=O$2, OR($G19="",$G19>=O$2)), $H19 * (1 + Assumptions!$C$7) ^ INT(((YEAR(O$2)-YEAR($F19))*12 + MONTH(O$2)-MONTH($F19)) / 12), 0) -> 0 | P19: =IF(AND($F19<=P$2, OR($G19="",$G19>=P$2)), $H19 * (1 + Assumptions!$C$7) ^ INT(((YEAR(P$2)-YEAR($F19))*12 + MONTH(P$2)-MONTH($F19)) / 12), 0) -> 0 | ... BP19: =IF(AND($F19<=BP$2, OR($G19="",$G19>=BP$2)), $H19 * (1 + Assumptions!$C$7) ^ INT(((YEAR(BP$2)-YEAR($F19))*12 + MONTH(BP$2)-MONTH($F19)) / 12), 0) -> 11337.408
A20: 16 | B20: New hire | C20: G&A | D20: CFO | E20: Planned | F20: 46296 | H20: 9500 | I20: =IF(AND($F20<=I$2, OR($G20="",$G20>=I$2)), $H20 * (1 + Assumptions!$C$7) ^ INT(((YEAR(I$2)-YEAR($F20))*12 + MONTH(I$2)-MONTH($F20)) / 12), 0) -> 0 | J20: =IF(AND($F20<=J$2, OR($G20="",$G20>=J$2)), $H20 * (1 + Assumptions!$C$7) ^ INT(((YEAR(J$2)-YEAR($F20))*12 + MONTH(J$2)-MONTH($F20)) / 12), 0) -> 0 | K20: =IF(AND($F20<=K$2, OR($G20="",$G20>=K$2)), $H20 * (1 + Assumptions!$C$7) ^ INT(((YEAR(K$2)-YEAR($F20))*12 + MONTH(K$2)-MONTH($F20)) / 12), 0) -> 0 | L20: =IF(AND($F20<=L$2, OR($G20="",$G20>=L$2)), $H20 * (1 + Assumptions!$C$7) ^ INT(((YEAR(L$2)-YEAR($F20))*12 + MONTH(L$2)-MONTH($F20)) / 12), 0) -> 0 | M20: =IF(AND($F20<=M$2, OR($G20="",$G20>=M$2)), $H20 * (1 + Assumptions!$C$7) ^ INT(((YEAR(M$2)-YEAR($F20))*12 + MONTH(M$2)-MONTH($F20)) / 12), 0) -> 0 | N20: =IF(AND($F20<=N$2, OR($G20="",$G20>=N$2)), $H20 * (1 + Assumptions!$C$7) ^ INT(((YEAR(N$2)-YEAR($F20))*12 + MONTH(N$2)-MONTH($F20)) / 12), 0) -> 0 | O20: =IF(AND($F20<=O$2, OR($G20="",$G20>=O$2)), $H20 * (1 + Assumptions!$C$7) ^ INT(((YEAR(O$2)-YEAR($F20))*12 + MONTH(O$2)-MONTH($F20)) / 12), 0) -> 0 | P20: =IF(AND($F20<=P$2, OR($G20="",$G20>=P$2)), $H20 * (1 + Assumptions!$C$7) ^ INT(((YEAR(P$2)-YEAR($F20))*12 + MONTH(P$2)-MONTH($F20)) / 12), 0) -> 0 | ... BP20: =IF(AND($F20<=BP$2, OR($G20="",$G20>=BP$2)), $H20 * (1 + Assumptions!$C$7) ^ INT(((YEAR(BP$2)-YEAR($F20))*12 + MONTH(BP$2)-MONTH($F20)) / 12), 0) -> 11967.264
A21: 17 | B21: New hire | C21: S&M | D21: Sales | E21: Planned | F21: 46296 | H21: 6500 | I21: =IF(AND($F21<=I$2, OR($G21="",$G21>=I$2)), $H21 * (1 + Assumptions!$C$7) ^ INT(((YEAR(I$2)-YEAR($F21))*12 + MONTH(I$2)-MONTH($F21)) / 12), 0) -> 0 | J21: =IF(AND($F21<=J$2, OR($G21="",$G21>=J$2)), $H21 * (1 + Assumptions!$C$7) ^ INT(((YEAR(J$2)-YEAR($F21))*12 + MONTH(J$2)-MONTH($F21)) / 12), 0) -> 0 | K21: =IF(AND($F21<=K$2, OR($G21="",$G21>=K$2)), $H21 * (1 + Assumptions!$C$7) ^ INT(((YEAR(K$2)-YEAR($F21))*12 + MONTH(K$2)-MONTH($F21)) / 12), 0) -> 0 | L21: =IF(AND($F21<=L$2, OR($G21="",$G21>=L$2)), $H21 * (1 + Assumptions!$C$7) ^ INT(((YEAR(L$2)-YEAR($F21))*12 + MONTH(L$2)-MONTH($F21)) / 12), 0) -> 0 | M21: =IF(AND($F21<=M$2, OR($G21="",$G21>=M$2)), $H21 * (1 + Assumptions!$C$7) ^ INT(((YEAR(M$2)-YEAR($F21))*12 + MONTH(M$2)-MONTH($F21)) / 12), 0) -> 0 | N21: =IF(AND($F21<=N$2, OR($G21="",$G21>=N$2)), $H21 * (1 + Assumptions!$C$7) ^ INT(((YEAR(N$2)-YEAR($F21))*12 + MONTH(N$2)-MONTH($F21)) / 12), 0) -> 0 | O21: =IF(AND($F21<=O$2, OR($G21="",$G21>=O$2)), $H21 * (1 + Assumptions!$C$7) ^ INT(((YEAR(O$2)-YEAR($F21))*12 + MONTH(O$2)-MONTH($F21)) / 12), 0) -> 0 | P21: =IF(AND($F21<=P$2, OR($G21="",$G21>=P$2)), $H21 * (1 + Assumptions!$C$7) ^ INT(((YEAR(P$2)-YEAR($F21))*12 + MONTH(P$2)-MONTH($F21)) / 12), 0) -> 0 | ... BP21: =IF(AND($F21<=BP$2, OR($G21="",$G21>=BP$2)), $H21 * (1 + Assumptions!$C$7) ^ INT(((YEAR(BP$2)-YEAR($F21))*12 + MONTH(BP$2)-MONTH($F21)) / 12), 0) -> 8188.128
A22: 18 | B22: New hire | C22: R&D | D22: R&D Engineer | E22: Planned | F22: 46388 | H22: 7500 | I22: =IF(AND($F22<=I$2, OR($G22="",$G22>=I$2)), $H22 * (1 + Assumptions!$C$7) ^ INT(((YEAR(I$2)-YEAR($F22))*12 + MONTH(I$2)-MONTH($F22)) / 12), 0) -> 0 | J22: =IF(AND($F22<=J$2, OR($G22="",$G22>=J$2)), $H22 * (1 + Assumptions!$C$7) ^ INT(((YEAR(J$2)-YEAR($F22))*12 + MONTH(J$2)-MONTH($F22)) / 12), 0) -> 0 | K22: =IF(AND($F22<=K$2, OR($G22="",$G22>=K$2)), $H22 * (1 + Assumptions!$C$7) ^ INT(((YEAR(K$2)-YEAR($F22))*12 + MONTH(K$2)-MONTH($F22)) / 12), 0) -> 0 | L22: =IF(AND($F22<=L$2, OR($G22="",$G22>=L$2)), $H22 * (1 + Assumptions!$C$7) ^ INT(((YEAR(L$2)-YEAR($F22))*12 + MONTH(L$2)-MONTH($F22)) / 12), 0) -> 0 | M22: =IF(AND($F22<=M$2, OR($G22="",$G22>=M$2)), $H22 * (1 + Assumptions!$C$7) ^ INT(((YEAR(M$2)-YEAR($F22))*12 + MONTH(M$2)-MONTH($F22)) / 12), 0) -> 0 | N22: =IF(AND($F22<=N$2, OR($G22="",$G22>=N$2)), $H22 * (1 + Assumptions!$C$7) ^ INT(((YEAR(N$2)-YEAR($F22))*12 + MONTH(N$2)-MONTH($F22)) / 12), 0) -> 0 | O22: =IF(AND($F22<=O$2, OR($G22="",$G22>=O$2)), $H22 * (1 + Assumptions!$C$7) ^ INT(((YEAR(O$2)-YEAR($F22))*12 + MONTH(O$2)-MONTH($F22)) / 12), 0) -> 0 | P22: =IF(AND($F22<=P$2, OR($G22="",$G22>=P$2)), $H22 * (1 + Assumptions!$C$7) ^ INT(((YEAR(P$2)-YEAR($F22))*12 + MONTH(P$2)-MONTH($F22)) / 12), 0) -> 0 | ... BP22: =IF(AND($F22<=BP$2, OR($G22="",$G22>=BP$2)), $H22 * (1 + Assumptions!$C$7) ^ INT(((YEAR(BP$2)-YEAR($F22))*12 + MONTH(BP$2)-MONTH($F22)) / 12), 0) -> 8748
A23: 19 | B23: New hire | C23: G&A | D23: Office Support | E23: Planned | F23: 46388 | H23: 4500 | I23: =IF(AND($F23<=I$2, OR($G23="",$G23>=I$2)), $H23 * (1 + Assumptions!$C$7) ^ INT(((YEAR(I$2)-YEAR($F23))*12 + MONTH(I$2)-MONTH($F23)) / 12), 0) -> 0 | J23: =IF(AND($F23<=J$2, OR($G23="",$G23>=J$2)), $H23 * (1 + Assumptions!$C$7) ^ INT(((YEAR(J$2)-YEAR($F23))*12 + MONTH(J$2)-MONTH($F23)) / 12), 0) -> 0 | K23: =IF(AND($F23<=K$2, OR($G23="",$G23>=K$2)), $H23 * (1 + Assumptions!$C$7) ^ INT(((YEAR(K$2)-YEAR($F23))*12 + MONTH(K$2)-MONTH($F23)) / 12), 0) -> 0 | L23: =IF(AND($F23<=L$2, OR($G23="",$G23>=L$2)), $H23 * (1 + Assumptions!$C$7) ^ INT(((YEAR(L$2)-YEAR($F23))*12 + MONTH(L$2)-MONTH($F23)) / 12), 0) -> 0 | M23: =IF(AND($F23<=M$2, OR($G23="",$G23>=M$2)), $H23 * (1 + Assumptions!$C$7) ^ INT(((YEAR(M$2)-YEAR($F23))*12 + MONTH(M$2)-MONTH($F23)) / 12), 0) -> 0 | N23: =IF(AND($F23<=N$2, OR($G23="",$G23>=N$2)), $H23 * (1 + Assumptions!$C$7) ^ INT(((YEAR(N$2)-YEAR($F23))*12 + MONTH(N$2)-MONTH($F23)) / 12), 0) -> 0 | O23: =IF(AND($F23<=O$2, OR($G23="",$G23>=O$2)), $H23 * (1 + Assumptions!$C$7) ^ INT(((YEAR(O$2)-YEAR($F23))*12 + MONTH(O$2)-MONTH($F23)) / 12), 0) -> 0 | P23: =IF(AND($F23<=P$2, OR($G23="",$G23>=P$2)), $H23 * (1 + Assumptions!$C$7) ^ INT(((YEAR(P$2)-YEAR($F23))*12 + MONTH(P$2)-MONTH($F23)) / 12), 0) -> 0 | ... BP23: =IF(AND($F23<=BP$2, OR($G23="",$G23>=BP$2)), $H23 * (1 + Assumptions!$C$7) ^ INT(((YEAR(BP$2)-YEAR($F23))*12 + MONTH(BP$2)-MONTH($F23)) / 12), 0) -> 5248.8
A24: 20 | B24: New hire | C24: R&D | D24: Product | E24: Planned | F24: 46388 | H24: 6500 | I24: =IF(AND($F24<=I$2, OR($G24="",$G24>=I$2)), $H24 * (1 + Assumptions!$C$7) ^ INT(((YEAR(I$2)-YEAR($F24))*12 + MONTH(I$2)-MONTH($F24)) / 12), 0) -> 0 | J24: =IF(AND($F24<=J$2, OR($G24="",$G24>=J$2)), $H24 * (1 + Assumptions!$C$7) ^ INT(((YEAR(J$2)-YEAR($F24))*12 + MONTH(J$2)-MONTH($F24)) / 12), 0) -> 0 | K24: =IF(AND($F24<=K$2, OR($G24="",$G24>=K$2)), $H24 * (1 + Assumptions!$C$7) ^ INT(((YEAR(K$2)-YEAR($F24))*12 + MONTH(K$2)-MONTH($F24)) / 12), 0) -> 0 | L24: =IF(AND($F24<=L$2, OR($G24="",$G24>=L$2)), $H24 * (1 + Assumptions!$C$7) ^ INT(((YEAR(L$2)-YEAR($F24))*12 + MONTH(L$2)-MONTH($F24)) / 12), 0) -> 0 | M24: =IF(AND($F24<=M$2, OR($G24="",$G24>=M$2)), $H24 * (1 + Assumptions!$C$7) ^ INT(((YEAR(M$2)-YEAR($F24))*12 + MONTH(M$2)-MONTH($F24)) / 12), 0) -> 0 | N24: =IF(AND($F24<=N$2, OR($G24="",$G24>=N$2)), $H24 * (1 + Assumptions!$C$7) ^ INT(((YEAR(N$2)-YEAR($F24))*12 + MONTH(N$2)-MONTH($F24)) / 12), 0) -> 0 | O24: =IF(AND($F24<=O$2, OR($G24="",$G24>=O$2)), $H24 * (1 + Assumptions!$C$7) ^ INT(((YEAR(O$2)-YEAR($F24))*12 + MONTH(O$2)-MONTH($F24)) / 12), 0) -> 0 | P24: =IF(AND($F24<=P$2, OR($G24="",$G24>=P$2)), $H24 * (1 + Assumptions!$C$7) ^ INT(((YEAR(P$2)-YEAR($F24))*12 + MONTH(P$2)-MONTH($F24)) / 12), 0) -> 0 | ... BP24: =IF(AND($F24<=BP$2, OR($G24="",$G24>=BP$2)), $H24 * (1 + Assumptions!$C$7) ^ INT(((YEAR(BP$2)-YEAR($F24))*12 + MONTH(BP$2)-MONTH($F24)) / 12), 0) -> 7581.6
A25: 21 | B25: New hire | C25: G&A | D25: Logistics | E25: Planned | F25: 46388 | H25: 6500 | I25: =IF(AND($F25<=I$2, OR($G25="",$G25>=I$2)), $H25 * (1 + Assumptions!$C$7) ^ INT(((YEAR(I$2)-YEAR($F25))*12 + MONTH(I$2)-MONTH($F25)) / 12), 0) -> 0 | J25: =IF(AND($F25<=J$2, OR($G25="",$G25>=J$2)), $H25 * (1 + Assumptions!$C$7) ^ INT(((YEAR(J$2)-YEAR($F25))*12 + MONTH(J$2)-MONTH($F25)) / 12), 0) -> 0 | K25: =IF(AND($F25<=K$2, OR($G25="",$G25>=K$2)), $H25 * (1 + Assumptions!$C$7) ^ INT(((YEAR(K$2)-YEAR($F25))*12 + MONTH(K$2)-MONTH($F25)) / 12), 0) -> 0 | L25: =IF(AND($F25<=L$2, OR($G25="",$G25>=L$2)), $H25 * (1 + Assumptions!$C$7) ^ INT(((YEAR(L$2)-YEAR($F25))*12 + MONTH(L$2)-MONTH($F25)) / 12), 0) -> 0 | M25: =IF(AND($F25<=M$2, OR($G25="",$G25>=M$2)), $H25 * (1 + Assumptions!$C$7) ^ INT(((YEAR(M$2)-YEAR($F25))*12 + MONTH(M$2)-MONTH($F25)) / 12), 0) -> 0 | N25: =IF(AND($F25<=N$2, OR($G25="",$G25>=N$2)), $H25 * (1 + Assumptions!$C$7) ^ INT(((YEAR(N$2)-YEAR($F25))*12 + MONTH(N$2)-MONTH($F25)) / 12), 0) -> 0 | O25: =IF(AND($F25<=O$2, OR($G25="",$G25>=O$2)), $H25 * (1 + Assumptions!$C$7) ^ INT(((YEAR(O$2)-YEAR($F25))*12 + MONTH(O$2)-MONTH($F25)) / 12), 0) -> 0 | P25: =IF(AND($F25<=P$2, OR($G25="",$G25>=P$2)), $H25 * (1 + Assumptions!$C$7) ^ INT(((YEAR(P$2)-YEAR($F25))*12 + MONTH(P$2)-MONTH($F25)) / 12), 0) -> 0 | ... BP25: =IF(AND($F25<=BP$2, OR($G25="",$G25>=BP$2)), $H25 * (1 + Assumptions!$C$7) ^ INT(((YEAR(BP$2)-YEAR($F25))*12 + MONTH(BP$2)-MONTH($F25)) / 12), 0) -> 7581.6
A26: 22 | B26: New hire | C26: R&D | D26: Field Engineer | E26: Planned | F26: 46388 | H26: 6500 | I26: =IF(AND($F26<=I$2, OR($G26="",$G26>=I$2)), $H26 * (1 + Assumptions!$C$7) ^ INT(((YEAR(I$2)-YEAR($F26))*12 + MONTH(I$2)-MONTH($F26)) / 12), 0) -> 0 | J26: =IF(AND($F26<=J$2, OR($G26="",$G26>=J$2)), $H26 * (1 + Assumptions!$C$7) ^ INT(((YEAR(J$2)-YEAR($F26))*12 + MONTH(J$2)-MONTH($F26)) / 12), 0) -> 0 | K26: =IF(AND($F26<=K$2, OR($G26="",$G26>=K$2)), $H26 * (1 + Assumptions!$C$7) ^ INT(((YEAR(K$2)-YEAR($F26))*12 + MONTH(K$2)-MONTH($F26)) / 12), 0) -> 0 | L26: =IF(AND($F26<=L$2, OR($G26="",$G26>=L$2)), $H26 * (1 + Assumptions!$C$7) ^ INT(((YEAR(L$2)-YEAR($F26))*12 + MONTH(L$2)-MONTH($F26)) / 12), 0) -> 0 | M26: =IF(AND($F26<=M$2, OR($G26="",$G26>=M$2)), $H26 * (1 + Assumptions!$C$7) ^ INT(((YEAR(M$2)-YEAR($F26))*12 + MONTH(M$2)-MONTH($F26)) / 12), 0) -> 0 | N26: =IF(AND($F26<=N$2, OR($G26="",$G26>=N$2)), $H26 * (1 + Assumptions!$C$7) ^ INT(((YEAR(N$2)-YEAR($F26))*12 + MONTH(N$2)-MONTH($F26)) / 12), 0) -> 0 | O26: =IF(AND($F26<=O$2, OR($G26="",$G26>=O$2)), $H26 * (1 + Assumptions!$C$7) ^ INT(((YEAR(O$2)-YEAR($F26))*12 + MONTH(O$2)-MONTH($F26)) / 12), 0) -> 0 | P26: =IF(AND($F26<=P$2, OR($G26="",$G26>=P$2)), $H26 * (1 + Assumptions!$C$7) ^ INT(((YEAR(P$2)-YEAR($F26))*12 + MONTH(P$2)-MONTH($F26)) / 12), 0) -> 0 | ... BP26: =IF(AND($F26<=BP$2, OR($G26="",$G26>=BP$2)), $H26 * (1 + Assumptions!$C$7) ^ INT(((YEAR(BP$2)-YEAR($F26))*12 + MONTH(BP$2)-MONTH($F26)) / 12), 0) -> 7581.6
A27: 23 | B27: New hire | C27: R&D | D27: Field Engineer | E27: Planned | F27: 46539 | H27: 6500 | I27: =IF(AND($F27<=I$2, OR($G27="",$G27>=I$2)), $H27 * (1 + Assumptions!$C$7) ^ INT(((YEAR(I$2)-YEAR($F27))*12 + MONTH(I$2)-MONTH($F27)) / 12), 0) -> 0 | J27: =IF(AND($F27<=J$2, OR($G27="",$G27>=J$2)), $H27 * (1 + Assumptions!$C$7) ^ INT(((YEAR(J$2)-YEAR($F27))*12 + MONTH(J$2)-MONTH($F27)) / 12), 0) -> 0 | K27: =IF(AND($F27<=K$2, OR($G27="",$G27>=K$2)), $H27 * (1 + Assumptions!$C$7) ^ INT(((YEAR(K$2)-YEAR($F27))*12 + MONTH(K$2)-MONTH($F27)) / 12), 0) -> 0 | L27: =IF(AND($F27<=L$2, OR($G27="",$G27>=L$2)), $H27 * (1 + Assumptions!$C$7) ^ INT(((YEAR(L$2)-YEAR($F27))*12 + MONTH(L$2)-MONTH($F27)) / 12), 0) -> 0 | M27: =IF(AND($F27<=M$2, OR($G27="",$G27>=M$2)), $H27 * (1 + Assumptions!$C$7) ^ INT(((YEAR(M$2)-YEAR($F27))*12 + MONTH(M$2)-MONTH($F27)) / 12), 0) -> 0 | N27: =IF(AND($F27<=N$2, OR($G27="",$G27>=N$2)), $H27 * (1 + Assumptions!$C$7) ^ INT(((YEAR(N$2)-YEAR($F27))*12 + MONTH(N$2)-MONTH($F27)) / 12), 0) -> 0 | O27: =IF(AND($F27<=O$2, OR($G27="",$G27>=O$2)), $H27 * (1 + Assumptions!$C$7) ^ INT(((YEAR(O$2)-YEAR($F27))*12 + MONTH(O$2)-MONTH($F27)) / 12), 0) -> 0 | P27: =IF(AND($F27<=P$2, OR($G27="",$G27>=P$2)), $H27 * (1 + Assumptions!$C$7) ^ INT(((YEAR(P$2)-YEAR($F27))*12 + MONTH(P$2)-MONTH($F27)) / 12), 0) -> 0 | ... BP27: =IF(AND($F27<=BP$2, OR($G27="",$G27>=BP$2)), $H27 * (1 + Assumptions!$C$7) ^ INT(((YEAR(BP$2)-YEAR($F27))*12 + MONTH(BP$2)-MONTH($F27)) / 12), 0) -> 7581.6
... A43: 39 | B43: New hire | C43: G&A | D43: Finance | E43: Planned | F43: 47394 | H43: 7500 | I43: =IF(AND($F43<=I$2, OR($G43="",$G43>=I$2)), $H43 * (1 + Assumptions!$C$7) ^ INT(((YEAR(I$2)-YEAR($F43))*12 + MONTH(I$2)-MONTH($F43)) / 12), 0) -> 0 | J43: =IF(AND($F43<=J$2, OR($G43="",$G43>=J$2)), $H43 * (1 + Assumptions!$C$7) ^ INT(((YEAR(J$2)-YEAR($F43))*12 + MONTH(J$2)-MONTH($F43)) / 12), 0) -> 0 | K43: =IF(AND($F43<=K$2, OR($G43="",$G43>=K$2)), $H43 * (1 + Assumptions!$C$7) ^ INT(((YEAR(K$2)-YEAR($F43))*12 + MONTH(K$2)-MONTH($F43)) / 12), 0) -> 0 | L43: =IF(AND($F43<=L$2, OR($G43="",$G43>=L$2)), $H43 * (1 + Assumptions!$C$7) ^ INT(((YEAR(L$2)-YEAR($F43))*12 + MONTH(L$2)-MONTH($F43)) / 12), 0) -> 0 | M43: =IF(AND($F43<=M$2, OR($G43="",$G43>=M$2)), $H43 * (1 + Assumptions!$C$7) ^ INT(((YEAR(M$2)-YEAR($F43))*12 + MONTH(M$2)-MONTH($F43)) / 12), 0) -> 0 | N43: =IF(AND($F43<=N$2, OR($G43="",$G43>=N$2)), $H43 * (1 + Assumptions!$C$7) ^ INT(((YEAR(N$2)-YEAR($F43))*12 + MONTH(N$2)-MONTH($F43)) / 12), 0) -> 0 | O43: =IF(AND($F43<=O$2, OR($G43="",$G43>=O$2)), $H43 * (1 + Assumptions!$C$7) ^ INT(((YEAR(O$2)-YEAR($F43))*12 + MONTH(O$2)-MONTH($F43)) / 12), 0) -> 0 | P43: =IF(AND($F43<=P$2, OR($G43="",$G43>=P$2)), $H43 * (1 + Assumptions!$C$7) ^ INT(((YEAR(P$2)-YEAR($F43))*12 + MONTH(P$2)-MONTH($F43)) / 12), 0) -> 0 | ... BP43: =IF(AND($F43<=BP$2, OR($G43="",$G43>=BP$2)), $H43 * (1 + Assumptions!$C$7) ^ INT(((YEAR(BP$2)-YEAR($F43))*12 + MONTH(BP$2)-MONTH($F43)) / 12), 0) -> 7500
B45: How to use this section:
B46: When adding an employee, follow the structure above, filling in columns A through H. Then drag the formula from the row above in column H down, and accross. Additionally, add a new employee above row 38, as the formulas below will not capture the new employee.
B48: SUMMARY BY DEPARTMENT
B49: R&D | I49: =SUMIF($C$2:$C$37,"R&D",I2:I37) -> 0 | J49: =SUMIF($C$2:$C$37,"R&D",J2:J37) -> 0 | K49: =SUMIF($C$2:$C$37,"R&D",K2:K37) -> 0 | L49: =SUMIF($C$2:$C$37,"R&D",L2:L37) -> 0 | M49: =SUMIF($C$2:$C$37,"R&D",M2:M37) -> 0 | N49: =SUMIF($C$2:$C$37,"R&D",N2:N37) -> 0 | O49: =SUMIF($C$2:$C$37,"R&D",O2:O37) -> 0 | P49: =SUMIF($C$2:$C$37,"R&D",P2:P37) -> 0 | ... BD49: =SUMIF($C$2:$C$37,"R&D",BD2:BD37) -> 110364.77
B50: S&M | I50: =SUMIF($C$3:$C$37,"S&M",I3:I37) -> 0 | J50: =SUMIF($C$3:$C$37,"S&M",J3:J37) -> 0 | K50: =SUMIF($C$3:$C$37,"S&M",K3:K37) -> 0 | L50: =SUMIF($C$3:$C$37,"S&M",L3:L37) -> 0 | M50: =SUMIF($C$3:$C$37,"S&M",M3:M37) -> 0 | N50: =SUMIF($C$3:$C$37,"S&M",N3:N37) -> 0 | O50: =SUMIF($C$3:$C$37,"S&M",O3:O37) -> 0 | P50: =SUMIF($C$3:$C$37,"S&M",P3:P37) -> 0 | ... BD50: =SUMIF($C$3:$C$37,"S&M",BD3:BD37) -> 53176.32
B51: G&A | I51: =SUMIF($C$3:$C$37,"G&A",I3:I37) -> 0 | J51: =SUMIF($C$3:$C$37,"G&A",J3:J37) -> 0 | K51: =SUMIF($C$3:$C$37,"G&A",K3:K37) -> 0 | L51: =SUMIF($C$3:$C$37,"G&A",L3:L37) -> 0 | M51: =SUMIF($C$3:$C$37,"G&A",M3:M37) -> 0 | N51: =SUMIF($C$3:$C$37,"G&A",N3:N37) -> 0 | O51: =SUMIF($C$3:$C$37,"G&A",O3:O37) -> 0 | P51: =SUMIF($C$3:$C$37,"G&A",P3:P37) -> 0 | ... BD51: =SUMIF($C$3:$C$37,"G&A",BD3:BD37) -> 55445.088
B52: TOTAL | I52: =SUM(I49:I51) -> 0 | J52: =SUM(J49:J51) -> 0 | K52: =SUM(K49:K51) -> 0 | L52: =SUM(L49:L51) -> 0 | M52: =SUM(M49:M51) -> 0 | N52: =SUM(N49:N51) -> 0 | O52: =SUM(O49:O51) -> 0 | P52: =SUM(P49:P51) -> 0 | ... BD52: =SUM(BD49:BD51) -> 218986.18
B54: HEADCOUNT BY DEPARTMENT
B55: R&D | I55: =COUNTIFS($C$3:$C$37,"R&D",I3:I37,">0") -> 0 | J55: =COUNTIFS($C$3:$C$37,"R&D",J3:J37,">0") -> 0 | K55: =COUNTIFS($C$3:$C$37,"R&D",K3:K37,">0") -> 0 | L55: =COUNTIFS($C$3:$C$37,"R&D",L3:L37,">0") -> 0 | M55: =COUNTIFS($C$3:$C$37,"R&D",M3:M37,">0") -> 0 | N55: =COUNTIFS($C$3:$C$37,"R&D",N3:N37,">0") -> 0 | O55: =COUNTIFS($C$3:$C$37,"R&D",O3:O37,">0") -> 0 | P55: =COUNTIFS($C$3:$C$37,"R&D",P3:P37,">0") -> 0 | ... BD55: =COUNTIFS($C$3:$C$37,"R&D",BD3:BD37,">0") -> 14
B56: S&M | I56: =COUNTIFS($C$3:$C$37,"S&M",I3:I37,">0") -> 0 | J56: =COUNTIFS($C$3:$C$37,"S&M",J3:J37,">0") -> 0 | K56: =COUNTIFS($C$3:$C$37,"S&M",K3:K37,">0") -> 0 | L56: =COUNTIFS($C$3:$C$37,"S&M",L3:L37,">0") -> 0 | M56: =COUNTIFS($C$3:$C$37,"S&M",M3:M37,">0") -> 0 | N56: =COUNTIFS($C$3:$C$37,"S&M",N3:N37,">0") -> 0 | O56: =COUNTIFS($C$3:$C$37,"S&M",O3:O37,">0") -> 0 | P56: =COUNTIFS($C$3:$C$37,"S&M",P3:P37,">0") -> 0 | ... BD56: =COUNTIFS($C$3:$C$37,"S&M",BD3:BD37,">0") -> 6
B57: G&A | I57: =COUNTIFS($C$3:$C$37,"G&A",I3:I37,">0") -> 0 | J57: =COUNTIFS($C$3:$C$37,"G&A",J3:J37,">0") -> 0 | K57: =COUNTIFS($C$3:$C$37,"G&A",K3:K37,">0") -> 0 | L57: =COUNTIFS($C$3:$C$37,"G&A",L3:L37,">0") -> 0 | M57: =COUNTIFS($C$3:$C$37,"G&A",M3:M37,">0") -> 0 | N57: =COUNTIFS($C$3:$C$37,"G&A",N3:N37,">0") -> 0 | O57: =COUNTIFS($C$3:$C$37,"G&A",O3:O37,">0") -> 0 | P57: =COUNTIFS($C$3:$C$37,"G&A",P3:P37,">0") -> 0 | ... BD57: =COUNTIFS($C$3:$C$37,"G&A",BD3:BD37,">0") -> 6
B58: TOTAL HEADCOUNT | I58: =SUM(I55:I57) -> 0 | J58: =SUM(J55:J57) -> 0 | K58: =SUM(K55:K57) -> 0 | L58: =SUM(L55:L57) -> 0 | M58: =SUM(M55:M57) -> 0 | N58: =SUM(N55:N57) -> 0 | O58: =SUM(O55:O57) -> 0 | P58: =SUM(P55:P57) -> 0 | ... BD58: =SUM(BD55:BD57) -> 26

Sheet Dasboard (FOR PITCHDECK)
B2: Financials | C2: 2025 | D2: 2026 | E2: 2027 | F2: 2028 | G2: 2029 | H2: 2030 | M2: Units & Revenues | N2: 2027 | O2: 2028 | P2: 2029 | T2: 2027 | U2: 2028 | V2: 2029
B3: Revenues (€) | C3: ='Financial Statements'!BB12 -> 97480 | D3: ='Financial Statements'!BC12 -> 106782 | E3: ='Financial Statements'!BD12 -> 20475120 | F3: ='Financial Statements'!BE12 -> 74302035 | G3: ='Financial Statements'!BF12 -> 1.4905229e+08 | H3: =#REF! -> #REF! | M3: TTK units sold | N3: ='Revenue Forecast'!BD6 -> 652 | O3: ='Revenue Forecast'!BE6 -> 1948 | P3: ='Revenue Forecast'!BF6 -> 3896 | S3: TTK revenues | T3: 3035867.8 | U3: 11993554 | V3: 23987107
B4: COGS (€) | E4: =COGS!BD7 -> 4615797.5 | F4: =COGS!BE7 -> 13790757 | M4: Combi units sold | N4: ='Revenue Forecast'!BD12 -> 389 | O4: ='Revenue Forecast'!BE12 -> 1559 | P4: ='Revenue Forecast'!BF12 -> 3118 | S4: Combi revenues | T4: 332231.4 | U4: 2751983.5 | V4: 5503966.9
B5: OPEX (€) | D5: =OPEX!BE36 -> 2076520 | E5: =OPEX!BF36 -> 3524506.4 | F5: =OPEX!BG36 -> 4917942.6 | M5: TTK revenues (€) | N5: ='Revenue Forecast'!BD9 -> 6147390.1 | O5: ='Revenue Forecast'!BE9 -> 18366742 | P5: ='Revenue Forecast'!BF9 -> 36733484
M6: Combi revenues (€) | N6: ='Revenue Forecast'!BD15 -> 4543745 | O6: ='Revenue Forecast'!BE15 -> 18210022 | P6: ='Revenue Forecast'!BF15 -> 36420044 | S6: Distribution of funds | V6: Production/Aasembly | W6: Product development | X6: Sales & Marketing
M7: Combi+ units sold | N7: ='Revenue Forecast'!BD18 -> 389 | O7: ='Revenue Forecast'!BE18 -> 1559 | P7: ='Revenue Forecast'!BF18 -> 3118 | V7: 0.6 | W7: 0.15 | X7: 0.25
M8: Combi+ revenues (€) | N8: ='Revenue Forecast'!BD21 -> 5733249.2 | O8: ='Revenue Forecast'!BE21 -> 22977212 | P8: ='Revenue Forecast'!BF21 -> 45954424

Sheet Dashboard
B2: Financials | C2: 2025 | D2: 2026 | E2: 2027 | F2: 2028 | G2: 2029 | J2: Units & Revenues | L2: 2026 | M2: 2027 | N2: 2028 | O2: 2029 | U2: 2026 | V2: 2027 | W2: 2028 | X2: 2029
B3: REVENUES (€) | C3: ='Financial Statements'!BB12 -> 97480 | D3: ='Financial Statements'!BC12 -> 106782 | E3: ='Financial Statements'!BD12 -> 20475120 | F3: ='Financial Statements'!BE12 -> 74302035 | G3: ='Financial Statements'!BF12 -> 1.4905229e+08 | J3: TTK units sold | L3: ='Revenue Forecast'!BC6 -> 0 | M3: ='Revenue Forecast'!BD6 -> 652 | N3: ='Revenue Forecast'!BE6 -> 1948 | O3: ='Revenue Forecast'!BF6 -> 3896 | S3: Headcount | U3: =count(Personnel!F3:F21) -> 17 | V3: =count(Personnel!F3:F27) -> 23 | W3: =COUNT(Personnel!F3:F31) -> 27 | X3: =COUNT(Personnel!F3:F33) -> 29
B4: COGS (€) | D4: ='Financial Statements'!BC19 -> 0 | E4: ='Financial Statements'!BD19 -> 15514392 | F4: ='Financial Statements'!BE19 -> 55809762 | G4: ='Financial Statements'!BF19 -> 88608416 | J4: Combi units sold | L4: ='Revenue Forecast'!BC12 -> 0 | M4: ='Revenue Forecast'!BD12 -> 389 | N4: ='Revenue Forecast'!BE12 -> 1559 | O4: ='Revenue Forecast'!BF12 -> 3118 | S4: Revenue/FTE | U4: =D3/U3 -> 6281.2941 | V4: =E3/V3 -> 890222.63 | W4: =F3/W3 -> 2751927.2 | X4: =G3/X3 -> 5139734.3
B5: OPEX (€) | D5: ='Financial Statements'!BC28 -> 2076520 | E5: ='Financial Statements'!BD28 -> 3524506.4 | F5: ='Financial Statements'!BE28 -> 4917942.6 | G5: ='Financial Statements'!BF28 -> 7650856.1 | J5: TTK revenues | L5: ='Revenue Forecast'!BC9 -> 0 | M5: ='Revenue Forecast'!BD9 -> 6147390.1 | N5: ='Revenue Forecast'!BE9 -> 18366742 | O5: ='Revenue Forecast'!BF9 -> 36733484 | S5: EBITDA/FTE | U5: =D6/U3 -> -115866.94 | V5: =E6/V3 -> 62444.415 | W5: =F6/W3 -> 502752.96 | X5: =G6/X3 -> 1820449
B6: EBITDA (€) | D6: ='Financial Statements'!BC30 -> -1969738 | E6: ='Financial Statements'!BD30 -> 1436221.5 | F6: ='Financial Statements'!BE30 -> 13574330 | G6: ='Financial Statements'!BF30 -> 52793021 | J6: Combi revenues | L6: ='Revenue Forecast'!BC15 -> 0 | M6: ='Revenue Forecast'!BD15 -> 4543745 | N6: ='Revenue Forecast'!BE15 -> 18210022 | O6: ='Revenue Forecast'!BF15 -> 36420044 | S6: Seed Distribution of funds | X6: Production/Aasembly | Y6: Product development | Z6: Sales & Marketing
B7: EBT (€) | D7: ='Financial Statements'!BC35 -> -1969738 | E7: ='Financial Statements'!BD35 -> 1418838.6 | F7: ='Financial Statements'!BE35 -> 13538630 | G7: ='Financial Statements'!BF35 -> 52790046 | J7: Combi+ units sold | L7: ='Revenue Forecast'!BC18 -> 0 | M7: ='Revenue Forecast'!BD18 -> 389 | N7: ='Revenue Forecast'!BE18 -> 1559 | O7: ='Revenue Forecast'!BF18 -> 3118 | X7: 0.6 | Y7: 0.15 | Z7: 0.25
B8: NET INCOME (€) | D8: ='Financial Statements'!BC39 -> -1969738 | E8: ='Financial Statements'!BD39 -> 1418838.6 | F8: ='Financial Statements'!BE39 -> 13538630 | G8: ='Financial Statements'!BF39 -> 38351494 | J8: Combi+ revenues | L8: ='Revenue Forecast'!BC21 -> 0 | M8: ='Revenue Forecast'!BD21 -> 5733249.2 | N8: ='Revenue Forecast'!BE21 -> 22977212 | O8: ='Revenue Forecast'!BF21 -> 45954424
