Workbook

Sheet Cover
B15: Financial Model
B19: Currency: EUR (€)
B21: STRICTLY CONFIDENTIAL

Sheet How to read me
B1: Tarnoc — How to Read This Model
B3: COLOR CODING
B4: Sample | C4: Assumptions are hardcoded inputs (sourced from documents)
B5: Sample | C5: Hardcoded historicalsis actual data from source documents
B6: Sample | C6: Formula cells are calculated, not hardcoded
B7: Sample | C7: Subtotal / total rows
B8: Sample | C8: Section headers / grand totals
B9: Sample | C9: Subsection headers
B10: Sample | C10: Margin / ratio rows (grey)
B11: Sample | C11: Balance sheet check rows (must = 0)
B14: FORMULA ARCHITECTURE
B15: Assumptions → Revenue Forecast, COGS, OPEX, CAPEX, Personnel (all drivers sourced here)
B16: Revenue Forecast → Financial Statements (revenue lines via cross-sheet links)
B17: COGS → Financial Statements (cost lines via cross-sheet links)
B18: OPEX → Financial Statements (opex lines via cross-sheet links)
B20: To change a number: ONLY edit cells in the Assumptions tab (yellow/orange).
B21: All other tabs will recalculate automatically.
B24: FURTHER EXPLANATIONS
B25: Subsidies: Tarnoc is and has been eligible for a number of subsidies. We will consider application for large projects, however this model excludes the forecast of any subsidy financing foing forward.
B26: Installation revenues: This is modelled fully as pass through revenue for now, as we plan to charge a customer exactly what we pay the installation partner for these services. This is subject to change in the future.
B27: Tarnoc's main products are the TTK, Tarnoc Mini, and the Twinciycle (to be in development in 2027). We also plan to sell verious add-ons such as performance booster units, boilers for hybrid setups, and sound reduction units.
B28: Service Revenues: Service revenues are calculated relative to installed base. We assume a certain percentage (see assumptions) of customers will purchase our Service package, and are charged annually.
... B30: Sales and Marketing costs are largely driven by permfomance marketing, and are calcualted on a volume and CPL basis. ]

Sheet Assumptions
B2: Drivers & Assumptions
B3: ASSUMPTIONS
B5: General Assumptions
B6: Opening Cash Balance (Jan 2024) | C6: 29538.9
B7: Annual salary increase (%) | C7: 0.08
B8: Employer cost basis | C8: Werkgeverlasten (incl. taxes)
B9: Holiday pay (%) | C9: 0.08
B10: Income tax rate | C10: 0.258
B12: Working Capital | H12: 20
B14: Days Sales Outstanding (DSO) | C14: days | D14: 20
B15: Days Payable Outstanding (DPO) | C15: days | D15: 45
B16: Days Inventory Outstanding (DIO) | C16: days | D16: 0
B17: Pre-payment | C17: %
B19: Revenue Build
B20: Units sold
C21: 2026 | D21: 2027 | E21: 2028 | F21: 2029 | G21: 2030
B22: TTK | C22: 0 | D22: =1000*D24 -> 1000 | E22: =3000*D24 -> 3000 | F22: =6000*D24 -> 6000 | G22: =12000*D24 -> 12000
B23: Tarnoc Mini | C23: 0 | D23: =500*D24 -> 500 | E23: =2000*D24 -> 2000 | F23: =4000*D24 -> 4000 | G23: =8000*D24 -> 8000
B24: Discounter | C24: 1 | D24: 1 | E24: 0.6
B26: Pricing
B27: TTK PRICING
B28: TTK Price | C28: =9800/1.21 -> 8099.1736 | D28: Management input (excl. VAT)
B30: MINI PRICING
B31: Mini Price | C31: =3350/1.21 -> 2768.595 | D31: Management input (excl. BTW)
B33: INSTALLATION (PASS THROUGH; REV=COST) | C33: 3200 | D33: Management input (excl. BTW)
B35: COGS
B36: TTK
B37: Bill of Materials TTK supplier 1
B38: # | C38: Category | D38: Component | E38: 1,000 units | F38: 5,000 units | G38: 10,000 units | H38: Unit | I38: Source
B39: B1 | C39: Supplier 1 | D39: Compressor + VFD | E39: 6314 | F39: 4500 | G39: 2692.44 | H39: €/unit | I39: Source: BOM data provided
B40: B2 | C40: Supplier 1 | D40: Heat exchangers (set) | E40: 805.5 | F40: =E40*0.7 -> 563.85 | G40: =0.6*F40 -> 338.31 | H40: €/unit | I40: Source: BOM data provided
B41: B3 | C41: Supplier 1 | D41: Electronics & Power Electronics | E41: 632.92 | F41: =E41*0.7 -> 443.044 | G41: =0.6*F41 -> 265.8264 | H41: €/unit | I41: Source: BOM data provided
B42: B4 | C42: Supplier 1 | D42: Hydraulic Components (Pumps, Valves, etc.) | E42: 283.76 | F42: =E42*0.7 -> 198.632 | G42: =0.6*F42 -> 119.1792 | H42: €/unit | I42: Source: BOM data provided
B43: B5 | C43: Supplier 1 | D43: Silencer & Insulation | E43: 118.48 | F43: =E43*0.7 -> 82.936 | G43: =0.6*F43 -> 49.7616 | H43: €/unit | I43: Source: BOM data provided
B44: B6 | C44: Supplier 1 | D44: Enclosure (Sheet Metal & Coating) | E44: 653.03 | F44: =E44*0.7 -> 457.121 | G44: =0.6*F44 -> 274.2726 | H44: €/unit | I44: Source: BOM data provided
B45: B7 | C45: Supplier 1 | D45: Other Components | E45: 300 | F45: =E45*0.7 -> 210 | G45: 126 | H45: €/unit | I45: Source: BOM data provided
B46: B8 | C46: Supplier 1 | D46: Assembly & Final Testing | E46: 200 | F46: =E46*0.7 -> 140 | G46: =0.6*F46 -> 84 | H46: €/unit | I46: Source: BOM data provided
B47: B9 | C47: Supplier 1 | D47: Packaging & Inbound Logistics | E47: 400 | F47: =E47*0.7 -> 280 | G47: =0.6*F47 -> 168 | H47: €/unit | I47: Source: BOM data provided
B48: B10 | C48: Supplier 1 | D48: Yield Loss & Warranty Provision (~3%) | E48: 291.23 | F48: =E48*0.7 -> 203.861 | G48: =0.6*F48 -> 122.3166 | H48: €/unit | I48: Source: BOM data provided
B49: B11 | C49: Contingency/risk | D49: Contingency & Risk Reserve | E49: 0 | F49: 0 | G49: 760 | H49: €/unit | I49: Source: No source, added for risk purposes
B50: B-T | C50: Supplier 1 total | D50: Total COGS / unit (BOM) | E50: =SUM(E39:E49) -> 9998.92 | F50: =SUM(F39:F49) -> 7079.444 | G50: =round(SUM(G39:G49),0) -> 5000 | H50: €/unit
B52: Bill of Materials TTK supplier 2
B53: D1 | C53: Supplier 2 | D53: Compressor + VFD | E53: 2568 | F53: 2311.2 | G53: 2080.08 | H53: €/unit | I53: Source: BOM data provided
B54: D2 | C54: Supplier 2 | D54: Heat exchangers (set) | E54: 805.5 | F54: =E54*0.7 -> 563.85 | G54: =F54*0.6 -> 338.31 | H54: €/unit | I54: Source: BOM data provided
B55: D3 | C55: Supplier 2 | D55: Elektronica & vermogenselektronica | E55: 257.92 | F55: =E55*0.7 -> 180.544 | G55: =F55*0.6 -> 108.3264 | H55: €/unit | I55: Source: BOM data provided
B56: D4 | C56: Supplier 2 | D56: Hydraulisch (pompen/kleppen/etc.) | E56: 283.76 | F56: =E56*0.7 -> 198.632 | G56: =F56*0.6 -> 119.1792 | H56: €/unit | I56: Source: BOM data provided
B57: D5 | C57: Supplier 2 | D57: Silencer + isolatie | E57: 118.48 | F57: =E57*0.7 -> 82.936 | G57: =F57*0.6 -> 49.7616 | H57: €/unit | I57: Source: BOM data provided
B58: D6 | C58: Supplier 2 | D58: Enclosure (plaatwerk, coating) | E58: 653.03 | F58: =E58*0.7 -> 457.121 | G58: =F58*0.6 -> 274.2726 | H58: €/unit | I58: Source: BOM data provided
B59: D7 | C59: Supplier 2 | D59: Everything Else | E59: 300 | F59: =E59*0.7 -> 210 | G59: =F59*0.6 -> 126 | H59: €/unit | I59: Source: BOM data provided
B60: D8 | C60: Supplier 2 | D60: Assemblage & eindtest | E60: 200 | F60: =E60*0.7 -> 140 | G60: =F60*0.6 -> 84 | H60: €/unit | I60: Source: BOM data provided
B61: D9 | C61: Supplier 2 | D61: Verpakking & logistiek inkomend | E61: 400 | F61: =E61*0.7 -> 280 | G61: =F61*0.6 -> 168 | H61: €/unit | I61: Source: BOM data provided
B62: D10 | C62: Supplier 2 | D62: Yield / garantie-reserve (~3%) | E62: 236.81 | F62: =E62*0.7 -> 165.767 | G62: =F62*0.6 -> 99.4602 | H62: €/unit | I62: Source: BOM data provided
C63: Supplier 2 total | D63: Total COGS / unit (BOM) | E63: =SUM(E53:E62) -> 5823.5 | F63: =SUM(F53:F62) -> 4590.05 | G63: =SUM(G53:G62) -> 3447.39
B65: TTK Volume tier breakpoints
B66: Min Units (≥) | C66: Cost / unit | D66: Unit | E66: Note
B67: 1000 | C67: =E50 -> 9998.92 | D67: €/unit | E67: Linked from BOM Total row above
B68: 5000 | C68: =F50 -> 7079.444 | D68: €/unit | E68: Linked from BOM Total row above
B69: 10000 | C69: =G50 -> 5000 | D69: €/unit | E69: Linked from BOM Total row above
B71: Tarnoc Mini Tier Breakpoints
B72: # | C72: Category | D72: Component | E72: 500 units | F72: 1,000 units | G72: 5,000 units | H72: 10,000 units | I72: Unit | J72: Source
B73: H1 | C73: Mini BOM | D73: Heat pump | E73: 750 | F73: =E73*0.9 -> 675 | G73: =F73*0.9 -> 607.5 | H73: =G73*0.9 -> 546.75 | I73: €/unit | J73: Source: BOM data
B74: H2 | C74: Mini BOM | D74: Shipping | E74: 150 | F74: 150 | G74: 150 | H74: 150 | I74: €/unit | J74: Source: BOM data
B75: H3 | C75: Mini BOM | D75: Enclosure + tank | E75: 200 | F75: =E75*0.9 -> 180 | G75: =F75*0.9 -> 162 | H75: =G75*0.9 -> 145.8 | I75: €/unit | J75: Source: BOM data
B76: H4 | C76: Mini BOM | D76: Manufacturing | E76: 200 | F76: =E76*0.9 -> 180 | G76: =F76*0.9 -> 162 | H76: =G76*0.9 -> 145.8 | I76: €/unit | J76: Source: BOM data
B77: T | C77: Mini BOM | D77: Total COGS / unit — MINI | E77: =SUM(E73:E76) -> 1300 | F77: =SUM(F73:F76) -> 1185 | G77: =SUM(G73:G76) -> 1081.5 | H77: =SUM(H73:H76) -> 988.35 | I77: €/unit | J77: Source: BOM data provided
B78: I-T. MINI VOLUME TIER BREAKPOINTS
B79: Min Units (≥) | C79: Cost / unit | D79: Unit | E79: Source
B80: 0 | C80: =E77 -> 1300 | D80: €/unit | E80: Source: BOM data
B81: 500 | C81: =E77 -> 1300 | D81: €/unit | E81: Source: BOM data
B82: 1000 | C82: =F77 -> 1185 | D82: €/unit | E82: Source: BOM data
B83: 5000 | C83: =G77 -> 1081.5 | D83: €/unit | E83: Source: BOM data
B84: 10000 | C84: =H77 -> 988.35 | D84: €/unit | E84: Source: BOM data
B87: Other operating expenditures | F87: Yearly increase: | G87: 0.3
C88: Category | D88: Note | E88: 2026 | F88: 2027 | G88: 2028 | H88: 2029 | I88: 2030
B89: Office rent (part of General) | C89: G&A | D89: ongoing | E89: 5000 | F89: =$E89*(1+$G$87) -> 6500 | G89: =F89*(1+$G$87) -> 8450 | H89: =G89*(1+$G$87) -> 10985 | I89: =H89*(1+$G$87) -> 14280.5
B90: Other General | C90: G&A | D90: ongoing | E90: 7000 | F90: =$E90*(1+$G$87) -> 9100 | G90: =F90*(1+$G$87) -> 11830 | H90: =G90*(1+$G$87) -> 15379 | I90: =H90*(1+$G$87) -> 19992.7
B91: Baseline Sales & Marketing | C91: S&M | D91: ongoing | E91: 14000 | F91: =$E91*(1+$G$87) -> 18200 | G91: =F91*(1+$G$87) -> 23660 | H91: =G91*(1+$G$87) -> 30758 | I91: =H91*(1+$G$87) -> 39985.4
B92: Finance & Legal etc. | C92: G&A | D92: ongoing | E92: 8000 | F92: =$E92*(1+$G$87) -> 10400 | G92: =F92*(1+$G$87) -> 13520 | H92: =G92*(1+$G$87) -> 17576 | I92: =H92*(1+$G$87) -> 22848.8
B93: Ongoing Development costs | C93: R&D | D93: ongoing | E93: 10000 | F93: =$E93*(1+$G$87) -> 13000 | G93: =F93*(1+$G$87) -> 16900 | H93: =G93*(1+$G$87) -> 21970 | I93: =H93*(1+$G$87) -> 28561
B94: Third party cost product development | C94: R&D | D94: ongoing | E94: 15000 | F94: =$E94*(1+$G$87) -> 19500 | G94: =F94*(1+$G$87) -> 25350 | H94: =G94*(1+$G$87) -> 32955 | I94: =H94*(1+$G$87) -> 42841.5
B95: Kicker Development Cost | C95: R&D | D95: one-off | E95: 168933
B96: Customer journey (third party) | C96: S&M | D96: one-off | E96: 10000
B97: Branding + Website (third party cost) | C97: S&M | D97: one-off | E97: 10000
B98: Assembly partner | C98: R&D | D98: one-off | E98: 100000
B99: Tooling Fisher (result: 2%-3%) | C99: R&D | D99: one-off | E99: 45000
B102: Assumptions for costs per unit sold (3rd parties or expenses (NO personell) | G102: Units sold | H102: S&M cost per unit | I102: Decrease | J102: Yearly costs
B103: Marketing spend per Customer | C103: S&M | D103: €80/lead with 20% closing rate | E103: 400 | F103: third party | G103: 0 | H103: 600
B104: Closing costs per customer | C104: S&M | D104: (Calls, viewing location, etc) | E104: 150 | F104: third party | G104: 400 | H104: =E107 -> 600 | J104: =G104*H104 -> 240000
B105: Aftersales and support | C105: S&M | E105: 50 | F105: third party | G105: =G104*2 -> 800 | H105: =H104*I105 -> 480 | I105: 0.8 | J105: =G105*H105 -> 384000
G106: =G105*2 -> 1600 | H106: =H105*I106 -> 384 | I106: 0.8 | J106: =G106*H106 -> 614400
B107: Cost per unit sold (cost down driven by volume) | C107: S&M | D107: costdown: S(n)=S(1)*n^-b, where b=0,2 | E107: =SUM(E103:E105) -> 600 | F107: S(1) | G107: =G106*2 -> 3200 | H107: =H106*I107 -> 307.2 | I107: 0.8 | J107: =G107*H107 -> 983040
G108: =G107*2 -> 6400 | H108: =H107*I108 -> 245.76 | I108: 0.8 | J108: =G108*H108 -> 1572864
G109: =G108*2 -> 12800 | H109: =H108*I109 -> 196.608 | I109: 0.8 | J109: =G109*H109 -> 2516582.4
G110: =G109*2 -> 25600 | H110: =H109*I110 -> 157.2864 | I110: 0.8 | J110: =G110*H110 -> 4026531.8
B112: Product | C112: Upsell item | D112: Type | E112: Attach % | F112: Unit rev. (EX VAT) | G112: Unit COGS | H112: Gross profit | I112: avg. Value | J112: avg. profit
B113: Turbine Heat Pump | C113: Boiler variant 50 | D113: One-time | E113: 0.49 | F113: =200/1.21 -> 165.28926 | G113: 80 | H113: =F113-G113 -> 85.289256 | I113: =F113*E113 -> 80.991736 | J113: =H113*E113 -> 41.791736
B114: Turbine Heat Pump | C114: Boiler variant 100 | D114: One-time | E114: 0.19 | F114: =400/1.21 -> 330.57851 | G114: 150 | H114: =F114-G114 -> 180.57851 | I114: =F114*E114 -> 62.809917 | J114: =H114*E114 -> 34.309917
B115: Turbine Heat Pump | C115: Sound reduction | D115: One-time | E115: 0.79 | F115: =550/1.21 -> 454.54545 | G115: 190 | H115: =F115-G115 -> 264.54545 | I115: =F115*E115 -> 359.09091 | J115: =H115*E115 -> 208.99091
B116: Turbine Heat Pump | C116: Power Booster | D116: One-time | E116: 0.3 | F116: =6000/1.21 -> 4958.6777 | G116: 2500 | H116: =F116-G116 -> 2458.6777 | I116: =F116*E116 -> 1487.6033 | J116: =H116*E116 -> 737.60331
B117: Turbine Heat Pump subtotal | F117: =SUMPRODUCT(E113:E116,F113:F116) -> 1990.4959 | I117: =sum(I113:I116) -> 1990.4959 | J117: =sum(J113:J116) -> 1022.6959
...

Sheet Financial Statements
B1: Tarnoc B.V. — Financial Statements (€)
E2: 2025 | Q2: 2026 | AC2: 2027 | AO2: 2028
E3: 45658 | F3: 45689 | G3: 45717 | H3: 45748 | I3: 45778 | J3: 45809 | K3: 45839 | L3: 45870 | M3: 45901 | N3: 45931 | O3: 45962 | P3: 45992 | Q3: 46023 | R3: 46054 | S3: 46082 | T3: 46113 | U3: 46143 | V3: 46174 | W3: 46204 | X3: 46235 | Y3: 46266 | Z3: 46296 | AA3: 46327 | AB3: 46357 | AC3: 46388 | AD3: 46419 | AE3: 46447 | AF3: 46478 | AG3: 46508 | AH3: 46539 | AI3: 46569 | AJ3: 46600 | AK3: 46631 | AL3: 46661 | AM3: 46692 | AN3: 46722 | AO3: 46753 | AP3: 46784 | AQ3: 46813 | AR3: 46844 | AS3: 46874 | AT3: 46905 | AU3: 46935 | AV3: 46966 | AW3: 46997 | AX3: 47027 | AY3: 47058 | AZ3: 47088 | BB3: 2025 | BC3: 2026 | BD3: 2027 | BE3: 2028 | BF3: 2029
B5: PROFIT & LOSS STATEMENT
B6: Revenues
B7: TTK | D7: € | M7: ='Revenue Forecast'!M9 | N7: ='Revenue Forecast'!N9 | O7: ='Revenue Forecast'!O9 | P7: ='Revenue Forecast'!P9 | Q7: ='Revenue Forecast'!Q9 -> 0 | R7: ='Revenue Forecast'!R9 -> 0 | S7: ='Revenue Forecast'!S9 -> 0 | T7: ='Revenue Forecast'!T9 -> 0 | ... AZ7: ='Revenue Forecast'!AZ9 -> 3975329.8 | BB7: =sum(E7:P7) -> 0 | BC7: =sum(Q7:AB7) -> 0 | BD7: =sum(AC7:AN7) -> 10140118 | BE7: =sum(AO7:AZ7) -> 30269008 | BF7: ='Revenue Forecast'!BF9 -> 60538017
B8: Tarnoc Mini | D8: € | M8: ='Revenue Forecast'!M15 | N8: ='Revenue Forecast'!N15 | O8: ='Revenue Forecast'!O15 | P8: ='Revenue Forecast'!P15 | Q8: ='Revenue Forecast'!Q15 -> 0 | R8: ='Revenue Forecast'!R15 -> 0 | S8: ='Revenue Forecast'!S15 -> 0 | T8: ='Revenue Forecast'!T15 -> 0 | ... AZ8: ='Revenue Forecast'!AZ15 -> 845528.16 | BB8: =sum(E8:P8) -> 0 | BC8: =sum(Q8:AB8) -> 0 | BD8: =sum(AC8:AN8) -> 1452797.5 | BE8: =sum(AO8:AZ8) -> 5811190.1 | BF8: ='Revenue Forecast'!BF15 -> 11622380
B9: Other | M9: ='Revenue Forecast'!M19+'Revenue Forecast'!M24 -> 0 | N9: ='Revenue Forecast'!N19+'Revenue Forecast'!N24 -> 0 | O9: ='Revenue Forecast'!O19+'Revenue Forecast'!O24 -> 0 | P9: ='Revenue Forecast'!P19+'Revenue Forecast'!P24 -> 0 | Q9: ='Revenue Forecast'!Q19+'Revenue Forecast'!Q24 -> 0 | R9: ='Revenue Forecast'!R19+'Revenue Forecast'!R24 -> 0 | S9: ='Revenue Forecast'!S19+'Revenue Forecast'!S24 -> 0 | T9: ='Revenue Forecast'!T19+'Revenue Forecast'!T24 -> 0 | ... AZ9: ='Revenue Forecast'!AZ19+'Revenue Forecast'!AZ24 -> 2253410 | BB9: =sum(E9:P9) -> 0 | BC9: =sum(Q9:AB9) -> 0 | BD9: =sum(AC9:AN9) -> 4919845 | BE9: =sum(AO9:AZ9) -> 16448845 | BF9: ='Revenue Forecast'!BF19+'Revenue Forecast'!BF24 -> 33346535
B10: Subsidies & grants | D10: € | M10: ='Revenue Forecast'!M28 -> 0 | N10: ='Revenue Forecast'!N28 -> 19480 | O10: ='Revenue Forecast'!O28 -> 78000 | P10: ='Revenue Forecast'!P28 -> 0 | Q10: ='Revenue Forecast'!Q28 -> 0 | R10: ='Revenue Forecast'!R28 -> 0 | S10: ='Revenue Forecast'!S28 -> 0 | T10: 0 | U10: ='Revenue Forecast'!U28 -> 0 | V10: 106782 | W10: ='Revenue Forecast'!W28 -> 0 | X10: ='Revenue Forecast'!X28 -> 0 | Y10: ='Revenue Forecast'!Y28 -> 0 | Z10: ='Revenue Forecast'!Z28 -> 0 | AA10: ='Revenue Forecast'!AA28 -> 0 | AB10: ='Revenue Forecast'!AB28 -> 0 | AC10: ='Revenue Forecast'!AC28 -> 0 | AD10: ='Revenue Forecast'!AD28 -> 0 | ... AZ10: ='Revenue Forecast'!AZ28 -> 0 | BB10: =sum(E10:P10) -> 97480 | BC10: =sum(Q10:AB10) -> 106782 | BD10: pm | BE10: pm | BF10: pm
B11: Total Revenue | D11: € | M11: ='Revenue Forecast'!M30 -> 0 | N11: ='Revenue Forecast'!N30 -> 19480 | O11: ='Revenue Forecast'!O30 -> 78000 | P11: ='Revenue Forecast'!P30 -> 0 | Q11: ='Revenue Forecast'!Q30 -> 0 | R11: ='Revenue Forecast'!R30 -> 0 | S11: ='Revenue Forecast'!S30 -> 0 | T11: ='Revenue Forecast'!T30 -> 0 | ... AZ11: ='Revenue Forecast'!AZ30 -> 7074267.9 | BB11: =sum(E11:P11) -> 97480 | BC11: =sum(Q11:AB11) -> 106782 | BD11: =sum(AC11:AN11) -> 16512760 | BE11: =sum(AO11:AZ11) -> 52529043 | BF11: =sum(BF7:BF10) -> 1.0550693e+08
B13: Cost of goods sold
B14: TTK | D14: € | E14: =COGS!E9 | F14: =COGS!F9 | G14: =COGS!G9 | H14: =COGS!H9 | I14: =COGS!I9 | J14: =COGS!J9 | K14: =COGS!K9 | L14: =COGS!L9 | ... AZ14: =COGS!AZ9 -> 3170614.1 | BB14: =sum(E14:P14) -> 0 | BC14: =sum(Q14:AB14) -> 0 | BD14: =sum(AC14:AN14) -> 11021554 | BE14: =sum(AO14:AZ14) -> 24141732 | BF14: =COGS!BF9 -> 35806800
B15: Tarnoc Mini | D15: € | E15: =COGS!E14 | F15: =COGS!F14 | G15: =COGS!G14 | H15: =COGS!H14 | I15: =COGS!I14 | J15: =COGS!J14 | K15: =COGS!K14 | L15: =COGS!L14 | ... AZ15: =COGS!AZ14 -> 395760 | BB15: =sum(E15:P15) -> 0 | BC15: =sum(Q15:AB15) -> 0 | BD15: =sum(AC15:AN15) -> 680000 | BE15: =sum(AO15:AZ15) -> 2720000 | BF15: =COGS!BF14 -> 4193400
B16: Other | E16: =COGS!E17 | F16: =COGS!F17 | G16: =COGS!G17 | H16: =COGS!H17 | I16: =COGS!I17 | J16: =COGS!J17 | K16: =COGS!K17 | L16: =COGS!L17 | ... P16: =COGS!P17 | Q16: =COGS!Q17+COGS!Q22 -> 0 | R16: =COGS!R17+COGS!R22 -> 0 | S16: =COGS!S17+COGS!S22 -> 0 | T16: =COGS!T17+COGS!T22 -> 0 | U16: =COGS!U17+COGS!U22 -> 0 | V16: =COGS!V17+COGS!V22 -> 0 | W16: =COGS!W17+COGS!W22 -> 0 | X16: =COGS!X17+COGS!X22 -> 0 | ... AZ16: =COGS!AZ17+COGS!AZ22 -> 2220302 | BB16: =sum(E16:P16) -> 0 | BC16: =sum(Q16:AB16) -> 0 | BD16: =sum(AC16:AN16) -> 4863859 | BE16: =sum(AO16:AZ16) -> 16206859 | BF16: =COGS!BF17 -> 32000000
B17: Total COGS | D17: € | M17: =COGS!M24 -> 0 | N17: =COGS!N24 -> 0 | O17: =COGS!O24 -> 0 | P17: =COGS!P24 -> 0 | Q17: =COGS!Q24 -> 0 | R17: =COGS!R24 -> 0 | S17: =COGS!S24 -> 0 | T17: =COGS!T24 -> 0 | ... AZ17: =COGS!AZ24 -> 5786676.1 | BB17: =sum(E17:P17) -> 0 | BC17: =sum(Q17:AB17) -> 0 | BD17: =sum(AC17:AN17) -> 16565413 | BE17: =sum(AO17:AZ17) -> 43068591 | BF17: =sum(BF14:BF16) -> 72000200
B19: Gross Profit | M19: =M11-M17 -> 0 | N19: =N11-N17 -> 19480 | O19: =O11-O17 -> 78000 | P19: =P11-P17 -> 0 | Q19: =Q11-Q17 -> 0 | R19: =R11-R17 -> 0 | S19: =S11-S17 -> 0 | T19: =T11-T17 -> 0 | ... AZ19: =AZ11-AZ17 -> 1287591.8 | BB19: =sum(E19:P19) -> 97480 | BC19: =sum(Q19:AB19) -> 106782 | BD19: =sum(AC19:AN19) -> -52652.311 | BE19: =sum(AO19:AZ19) -> 9460452.3 | BF19: =BF11-BF17 -> 33506732
B20: Gross margin % | D20: % | BE20: =BE19/BE11 -> 0.18009946 | BF20: =BF19/BF11 -> 0.31757849
B22: Operational expenses
B23: R&D | D23: € | M23: =OPEX!O38 -> 47500 | N23: =OPEX!P38 -> 47500 | O23: =OPEX!Q38 -> 47500 | P23: =OPEX!R38 -> 216433 | Q23: =OPEX!S38 -> 75700 | R23: =OPEX!T38 -> 75700 | S23: =OPEX!U38 -> 75700 | T23: =OPEX!V38 -> 75700 | ... AZ23: =OPEX!BB38 -> 152614.77 | BB23: =sum(E23:P23) -> 358933 | BC23: =sum(Q23:AB23) -> 1150160 | BD23: =sum(AC23:AN23) -> 1576575.2 | BE23: =sum(AO23:AZ23) -> 1821001.2 | BF23: =OPEX!BH38 -> 3055465.9
B24: S&M | D24: € | M24: =OPEX!O39 -> 0 | N24: =OPEX!P39 -> 0 | O24: =OPEX!Q39 -> 0 | P24: =OPEX!R39 -> 20000 | Q24: =OPEX!S39 -> 21000 | R24: =OPEX!T39 -> 31800 | S24: =OPEX!U39 -> 31800 | T24: =OPEX!V39 -> 31800 | ... AZ24: =OPEX!BB39 -> 245181.92 | BB24: =sum(E24:P24) -> 20000 | BC24: =sum(Q24:AB24) -> 464300 | BD24: =sum(AC24:AN24) -> 1367448 | BE24: =sum(AO24:AZ24) -> 2504934.2 | BF24: =OPEX!BH39 -> 4019540.2
B25: G&A | D25: € | M25: =OPEX!O40 -> 11500 | N25: =OPEX!P40 -> 11500 | O25: =OPEX!Q40 -> 11500 | P25: =OPEX!R40 -> 11500 | Q25: =OPEX!S40 -> 31820 | R25: =OPEX!T40 -> 31820 | S25: =OPEX!U40 -> 31820 | T25: =OPEX!V40 -> 31820 | ... AZ25: =OPEX!BB40 -> 89245.088 | BB25: =sum(E25:P25) -> 46000 | BC25: =sum(Q25:AB25) -> 462060 | BD25: =sum(AC25:AN25) -> 832843.2 | BE25: =sum(AO25:AZ25) -> 1050610.7 | BF25: =OPEX!BH40 -> 1307473.3
B26: Total OPEX | D26: € | M26: =(M25+M24+M23) -> 59000 | N26: =(N25+N24+N23) -> 59000 | O26: =(O25+O24+O23) -> 59000 | P26: =(P25+P24+P23) -> 247933 | Q26: =(Q25+Q24+Q23) -> 128520 | R26: =(R25+R24+R23) -> 139320 | S26: =(S25+S24+S23) -> 139320 | T26: =(T25+T24+T23) -> 139320 | ... AZ26: =(AZ25+AZ24+AZ23) -> 487041.78 | BB26: =sum(E26:P26) -> 424933 | BC26: =sum(Q26:AB26) -> 2076520 | BD26: =sum(AC26:AN26) -> 3776866.4 | BE26: =sum(AO26:AZ26) -> 5376546.1 | BF26: =sum(BF23:BF25) -> 8382479.5
B28: EBITDA | D28: € | M28: =M19-M26 -> -59000 | N28: =N19-N26 -> -39520 | O28: =O19-O26 -> 19000 | P28: =P19-P26 -> -247933 | Q28: =Q19-Q26 -> -128520 | R28: =R19-R26 -> -139320 | S28: =S19-S26 -> -139320 | T28: =T19-T26 -> -139320 | ... AZ28: =AZ19-AZ26 -> 800550 | BB28: =sum(E28:P28) -> -327453 | BC28: =sum(Q28:AB28) -> -1969738 | BD28: =sum(AC28:AN28) -> -3829518.7 | BE28: =sum(AO28:AZ28) -> 4083906.2 | BF28: =BF19-BF26 -> 25124252
B29: EBITDA margin % | D29: % | BE29: =BE28/BE11 -> 0.077745681 | BF29: =BF28/BF11 -> 0.23812893
B31: Depreciation & Amortisation | D31: € | M31: 0 | N31: 0 | O31: 0 | P31: 0 | Q31: 0 | R31: 0 | S31: 0 | T31: 0 | U31: 0 | V31: 0 | W31: 0 | X31: 0 | Y31: 0 | Z31: 0 | AA31: 0 | AB31: 0 | AC31: 0 | AD31: 0 | AE31: 0 | AF31: 0 | AG31: 0 | AH31: 0 | AI31: 0 | AJ31: 0 | AK31: 0 | AL31: 0 | AM31: 0 | AN31: 0 | AO31: 0 | AP31: 0 | AQ31: 0 | AR31: 0 | AS31: 0 | AT31: 0 | AU31: 0 | AV31: 0 | AW31: 0 | AX31: 0 | AY31: 0 | AZ31: 0 | BB31: =sum(E31:P31) -> 0 | BC31: =sum(Q31:AB31) -> 0 | BD31: =sum(AC31:AN31) -> 0 | BE31: =sum(AO31:AZ31) -> 0 | BF31: 0
B32: Interst payments | D32: € | M32: 0 | N32: 0 | O32: 0 | P32: 0 | Q32: 0 | R32: 0 | S32: 0 | T32: 0 | U32: 0 | V32: 0 | W32: 0 | X32: 0 | Y32: 0 | Z32: 0 | AA32: 0 | AB32: 0 | AC32: 0 | AD32: 0 | AE32: 0 | AF32: 0 | AG32: 0 | AH32: 0 | AI32: 0 | AJ32: 0 | AK32: 0 | AL32: 0 | AM32: 0 | AN32: 0 | AO32: 0 | AP32: 0 | AQ32: 0 | AR32: 0 | AS32: 0 | AT32: 0 | AU32: 0 | AV32: 0 | AW32: 0 | AX32: 0 | AY32: 0 | AZ32: 0 | BB32: =sum(E32:P32) -> 0 | BC32: =sum(Q32:AB32) -> 0 | BD32: =sum(AC32:AN32) -> 0 | BE32: =sum(AO32:AZ32) -> 0 | BF32: 0
B33: EBT | D33: € | M33: =M28-sum(M31:M32) -> -59000 | N33: =N28-sum(N31:N32) -> -39520 | O33: =O28-sum(O31:O32) -> 19000 | P33: =P28-sum(P31:P32) -> -247933 | Q33: =Q28-sum(Q31:Q32) -> -128520 | R33: =R28-sum(R31:R32) -> -139320 | S33: =S28-sum(S31:S32) -> -139320 | T33: =T28-sum(T31:T32) -> -139320 | ... AZ33: =AZ28-sum(AZ31:AZ32) -> 800550 | BB33: =sum(E33:P33) -> -327453 | BC33: =sum(Q33:AB33) -> -1969738 | BD33: =sum(AC33:AN33) -> -3829518.7 | BE33: =sum(AO33:AZ33) -> 4083906.2 | BF33: =BF28-sum(BF31:BF32) -> 25124252
BE34: =BE33/BE11 -> 0.077745681 | BF34: =BF33/BF11 -> 0.23812893
B36: Income tax | D36: € | M36: 0 | N36: 0 | O36: 0 | P36: 0 | Q36: 0 | R36: 0 | S36: 0 | T36: 0 | U36: 0 | V36: 0 | W36: 0 | X36: 0 | Y36: 0 | Z36: 0 | AA36: 0 | AB36: 0 | AC36: 0 | AD36: 0 | AE36: 0 | AF36: 0 | AG36: 0 | AH36: 0 | AI36: 0 | AJ36: 0 | AK36: 0 | AL36: 0 | AM36: 0 | AN36: 0 | AO36: 0 | AP36: 0 | AQ36: 0 | AR36: 0 | AS36: 0 | AT36: 0 | AU36: 0 | AV36: 0 | AW36: 0 | AX36: 0 | AY36: 0 | AZ36: 0 | BB36: =sum(E36:P36) -> 0 | BC36: =sum(Q36:AB36) -> 0 | BD36: =sum(AC36:AN36) -> 0 | BE36: =sum(AO36:AZ36) -> 0 | BF36: =(BF33-AZ40)*Assumptions!$C$10 -> 6322081.5
B37: NET INCOME | D37: € | M37: =M33-M36 -> -59000 | N37: =N33-N36 -> -39520 | O37: =O33-O36 -> 19000 | P37: =P33-P36 -> -247933 | Q37: =Q33-Q36 -> -128520 | R37: =R33-R36 -> -139320 | S37: =S33-S36 -> -139320 | T37: =T33-T36 -> -139320 | ... AZ37: =AZ33-AZ36 -> 800550 | BB37: =sum(E37:P37) -> -327453 | BC37: =sum(Q37:AB37) -> -1969738 | BD37: =sum(AC37:AN37) -> -3829518.7 | BE37: =sum(AO37:AZ37) -> 4083906.2 | BF37: =BF33-BF36 -> 18802171
B38: Profit margin % | BE38: =BE37/BE11 -> 0.077745681 | BF38: =BF37/BF11 -> 0.17820792
B40: Tax carry over to be applied | M40: 108239 | N40: =M40+(-N37*Assumptions!$C$10) -> 118435.16 | O40: =N40+(-O37*Assumptions!$C$10) -> 113533.16 | P40: =O40+(-P37*Assumptions!$C$10) -> 177499.87 | Q40: =P40+(-Q37*Assumptions!$C$10) -> 210658.03 | R40: =Q40+(-R37*Assumptions!$C$10) -> 246602.59 | S40: =R40+(-S37*Assumptions!$C$10) -> 282547.15 | T40: =S40+(-T37*Assumptions!$C$10) -> 318491.71 | U40: =T40+(-U37*Assumptions!$C$10) -> 357016.27 | ... AZ40: =AY40+(-AZ37*Assumptions!$C$10) -> 620060.3
B42: CASH FLOW STATEMENT
B43: Net income | D43: € | M43: =M37 -> -59000 | N43: =N37 -> -39520 | O43: =O37 -> 19000 | P43: =P37 -> -247933 | Q43: =Q37 -> -128520 | R43: =R37 -> -139320 | S43: =S37 -> -139320 | T43: =T37 -> -139320 | ... AZ43: =AZ37 -> 800550 | BB43: =sum(E43:P43) -> -327453 | BC43: =sum(Q43:AB43) -> -1969738 | BD43: =sum(AC43:AN43) -> -3829518.7 | BE43: =sum(AO43:AZ43) -> 4083906.2 | BF43: =BF37 -> 18802171
B44: Depreciation & amortisation | D44: € | M44: 0 | N44: 0 | O44: 0 | P44: 0 | Q44: 0 | R44: 0 | S44: 0 | T44: 0 | U44: 0 | V44: 0 | W44: 0 | X44: 0 | Y44: 0 | Z44: 0 | AA44: 0 | AB44: 0 | AC44: 0 | AD44: 0 | AE44: 0 | AF44: 0 | AG44: 0 | AH44: 0 | AI44: 0 | AJ44: 0 | AK44: 0 | AL44: 0 | AM44: 0 | AN44: 0 | AO44: 0 | AP44: 0 | AQ44: 0 | AR44: 0 | AS44: 0 | AT44: 0 | AU44: 0 | AV44: 0 | AW44: 0 | AX44: 0 | AY44: 0 | AZ44: 0 | BB44: =sum(E44:P44) -> 0 | BC44: =sum(Q44:AB44) -> 0 | BD44: =sum(AC44:AN44) -> 0 | BE44: =sum(AO44:AZ44) -> 0 | BF44: =BF31 -> 0
B45: Increase in accounts receivable (delta DSO) | D45: € | M45: 0 | N45: =-(N63-M63) -> -12986.667 | O45: =-(O63-N63) -> -39013.333 | P45: =-(P63-O63) -> 52000 | Q45: =-(Q63-P63) -> 0 | R45: =-(R63-Q63) -> 0 | S45: =-(S63-R63) -> 0 | T45: =-(T63-S63) -> 0 | U45: =-(U63-T63) -> 0 | ... AZ45: =-(AZ63-AY63) -> -444346.98 | BB45: =sum(E45:P45) -> 0 | BC45: =sum(Q45:AB45) -> 0 | BD45: =sum(AC45:AN45) -> -1476059.9 | BE45: =sum(AO45:AZ45) -> -3240118.7 | BF45: =-(BF63-BE63) -> -1065023.1
B46: Increase in accounts payable (delta DPO) | D46: € | M46: 0 | N46: =(N72-M72) -> 0 | O46: =(O72-N72) -> 0 | P46: =(P72-O72) -> 0 | Q46: =(Q72-P72) -> 0 | R46: =(R72-Q72) -> 0 | S46: =(S72-R72) -> 0 | T46: =(T72-S72) -> 0 | U46: =(U72-T72) -> 0 | ... AZ46: =(AZ72-AY72) -> 813510.21 | BB46: =sum(E46:P46) -> 0 | BC46: =sum(Q46:AB46) -> 0 | BD46: =sum(AC46:AN46) -> 3314109.1 | BE46: =sum(AO46:AZ46) -> 5365905.1 | BF46: =BF72-BE72 -> 196722.78
B47: Change in inventory (delta DIO) | D47: € | M47: 0 | N47: =-(N64-M64) -> 0 | O47: =-(O64-N64) -> 0 | P47: =-(P64-O64) -> 0 | Q47: =-(Q64-P64) -> 0 | R47: =-(R64-Q64) -> 0 | S47: =-(S64-R64) -> 0 | T47: =-(T64-S64) -> 0 | U47: =-(U64-T64) -> 0 | ... AZ47: =-(AZ64-AY64) -> 0 | BB47: =sum(E47:P47) -> 0 | BC47: =sum(Q47:AB47) -> 0 | BD47: =sum(AC47:AN47) -> 0 | BE47: =sum(AO47:AZ47) -> 0 | BF47: 0
B48: Cash from Operations | D48: € | M48: =sum(M43:M47) -> -59000 | N48: =sum(N43:N47) -> -52506.667 | O48: =sum(O43:O47) -> -20013.333 | P48: =sum(P43:P47) -> -195933 | Q48: =sum(Q43:Q47) -> -128520 | R48: =sum(R43:R47) -> -139320 | S48: =sum(S43:S47) -> -139320 | T48: =sum(T43:T47) -> -139320 | ... AZ48: =sum(AZ43:AZ47) -> 1169713.2 | BB48: =sum(E48:P48) -> -327453 | BC48: =sum(Q48:AB48) -> -1969738 | BD48: =sum(AC48:AN48) -> -1991469.5 | BE48: =sum(AO48:AZ48) -> 6209692.6 | BF48: =sum(BF43:BF47) -> 17933870
B49: CAPEX | D49: € | M49: 0 | N49: 0 | O49: 0 | P49: 0 | Q49: 0 | R49: 0 | S49: 0 | T49: 0 | U49: 0 | V49: 0 | W49: 0 | X49: 0 | Y49: 0 | Z49: 0 | AA49: 0 | AB49: 0 | AC49: 0 | AD49: 0 | AE49: 0 | AF49: 0 | AG49: 0 | AH49: 0 | AI49: 0 | AJ49: 0 | AK49: 0 | AL49: 0 | AM49: 0 | AN49: 0 | AO49: 0 | AP49: 0 | AQ49: 0 | AR49: 0 | AS49: 0 | AT49: 0 | AU49: 0 | AV49: 0 | AW49: 0 | AX49: 0 | AY49: 0 | AZ49: 0 | BB49: =sum(E49:P49) -> 0 | BC49: =sum(Q49:AB49) -> 0 | BD49: =sum(AC49:AN49) -> 0 | BE49: =sum(AO49:AZ49) -> 0 | BF49: 0
B50: Cash from Investing | M50: =M49 -> 0 | N50: =N49 -> 0 | O50: =O49 -> 0 | P50: =P49 -> 0 | Q50: =Q49 -> 0 | R50: =R49 -> 0 | S50: =S49 -> 0 | T50: =T49 -> 0 | ... AZ50: =AZ49 -> 0 | BB50: =sum(E50:P50) -> 0 | BC50: =sum(Q50:AB50) -> 0 | BD50: =sum(AC50:AN50) -> 0 | BE50: =sum(AO50:AZ50) -> 0 | BF50: =BF49 -> 0
B51: Equity injection | D51: € | S51: 0 | U51: 300000 | Z51: 3250000 | BB51: =sum(E51:P51) -> 0 | BC51: =sum(Q51:AB51) -> 3550000 | BD51: =sum(AC51:AN51) -> 0 | BE51: =sum(AO51:AZ51) -> 0 | BF51: 0
B52: Loan (CLA) | D52: € | V52: 300000 | BB52: =sum(E52:P52) -> 0 | BC52: =sum(Q52:AB52) -> 300000 | BD52: =sum(AC52:AN52) -> 0 | BE52: =sum(AO52:AZ52) -> 0 | BF52: 0
B53: Cash from Financing | D53: € | M53: =M51+M52 -> 0 | N53: =N51+N52 -> 0 | O53: =O51+O52 -> 0 | P53: =P51+P52 -> 0 | Q53: =Q51+Q52 -> 0 | R53: =R51+R52 -> 0 | S53: =S51+S52 -> 0 | T53: =T51+T52 -> 0 | ... AZ53: =AZ51+AZ52 -> 0 | BB53: =sum(E53:P53) -> 0 | BC53: =sum(Q53:AB53) -> 3850000 | BD53: =sum(AC53:AN53) -> 0 | BE53: =sum(AO53:AZ53) -> 0 | BF53: 0
B55: Total Change in Cash | D55: € | M55: =M48+M50+M53 -> -59000 | N55: =N48+N50+N53 -> -52506.667 | O55: =O48+O50+O53 -> -20013.333 | P55: =P48+P50+P53 -> -195933 | Q55: =Q48+Q50+Q53 -> -128520 | R55: =R48+R50+R53 -> -139320 | S55: =S48+S50+S53 -> -139320 | T55: =T48+T50+T53 -> -139320 | ... AZ55: =AZ48+AZ50+AZ53 -> 1169713.2 | BB55: =BB53+BB50+BB48 -> -327453 | BC55: =BC53+BC50+BC48 -> 1880262 | BD55: =BD53+BD50+BD48 -> -1991469.5 | BE55: =BE53+BE50+BE48 -> 6209692.6 | BF55: =BF53+BF50+BF48 -> 17933870
B56: Beginning cash balance | D56: € | M56: 1111108 | N56: =M57 -> 1052108 | O56: =N57 -> 999601.33 | P56: =O57 -> 979588 | Q56: =P57 -> 783655 | R56: =Q57 -> 655135 | S56: =R57 -> 515815 | T56: =S57 -> 376495 | U56: =T57 -> 237175 | ... AZ56: =AY57 -> 5712426.9 | BB56: =BB55+BB57 -> 456202 | BC56: =Q56 -> 783655 | BD56: =AC56 -> 2663917 | BE56: =AO56 -> 672447.48 | BF56: =AZ57 -> 6882140.1
B57: Ending Cash Balance | D57: € | M57: =M55+M56 -> 1052108 | N57: =N56+N55 -> 999601.33 | O57: =O56+O55 -> 979588 | P57: =P56+P55 -> 783655 | Q57: =Q56+Q55 -> 655135 | R57: =R56+R55 -> 515815 | S57: =S56+S55 -> 376495 | T57: =T56+T55 -> 237175 | U57: =U56+U55 -> 387855 | ... AZ57: =AZ56+AZ55 -> 6882140.1 | BB57: =P57 -> 783655 | BC57: =BC55+BC56 -> 2663917 | BD57: =BD55+BD56 -> 672447.48 | BE57: =BE55+BE56 -> 6882140.1 | BF57: =BF55+BF56 -> 24816010
B59: BALANCE SHEET
B60: ASSETS
B61: Cash and cash equivalents | D61: € | M61: =M57 -> 1052108 | N61: =N57 -> 999601.33 | O61: =O57 -> 979588 | P61: =P57 -> 783655 | Q61: =Q57 -> 655135 | R61: =R57 -> 515815 | S61: =S57 -> 376495 | T61: =T57 -> 237175 | ... AZ61: =AZ57 -> 6882140.1 | BB61: =P61 -> 783655 | BC61: =AB61 -> 2663917 | BD61: =AN61 -> 672447.48 | BE61: =AZ61 -> 6882140.1 | BF61: =BF57 -> 24816010
B62: Deferred tax assest ("carry forward") | D62: € | M62: =M40 -> 108239 | N62: =N40 -> 118435.16 | O62: =O40 -> 113533.16 | P62: =P40 -> 177499.87 | Q62: =Q40 -> 210658.03 | R62: =R40 -> 246602.59 | S62: =S40 -> 282547.15 | T62: =T40 -> 318491.71 | ... AZ62: =AZ40 -> 620060.3 | BB62: =P62 -> 177499.87 | BC62: =AB62 -> 685692.28 | BD62: =AN62 -> 1673708.1 | BE62: =AZ62 -> 620060.3 | BF62: 0
B63: Accounts receivable (DSO-based) | D63: € | M63: =ABS(Assumptions!$D$14*(M11/30)) -> 0 | N63: =ABS(Assumptions!$D$14*(N11/30)) -> 12986.667 | O63: =ABS(Assumptions!$D$14*(O11/30)) -> 52000 | P63: =ABS(Assumptions!$D$14*(P11/30)) -> 0 | Q63: =ABS(Assumptions!$D$14*(Q11/30)) -> 0 | R63: =ABS(Assumptions!$D$14*(R11/30)) -> 0 | S63: =ABS(Assumptions!$D$14*(S11/30)) -> 0 | T63: =ABS(Assumptions!$D$14*(T11/30)) -> 0 | ... AZ63: =ABS(Assumptions!$D$14*(AZ11/30)) -> 4716178.6 | BB63: =P63 -> 0 | BC63: =AB63 -> 0 | BD63: =AN63 -> 1476059.9 | BE63: =AZ63 -> 4716178.6 | BF63: =Assumptions!$D$14/365*BF11 -> 5781201.7
B64: Inventory (DIO-based) | D64: € | M64: =ABS(Assumptions!$D$16*(M17/30)) -> 0 | N64: =ABS(Assumptions!$D$16*(N17/30)) -> 0 | O64: =ABS(Assumptions!$D$16*(O17/30)) -> 0 | P64: =ABS(Assumptions!$D$16*(P17/30)) -> 0 | Q64: =ABS(Assumptions!$D$16*(Q17/30)) -> 0 | R64: =ABS(Assumptions!$D$16*(R17/30)) -> 0 | S64: =ABS(Assumptions!$D$16*(S17/30)) -> 0 | T64: =ABS(Assumptions!$D$16*(T17/30)) -> 0 | ... AZ64: =ABS(Assumptions!$D$16*(AZ17/30)) -> 0 | BB64: =P64 -> 0 | BC64: =AB64 -> 0 | BD64: =AN64 -> 0 | BE64: =AZ64 -> 0 | BF64: 0
B65: Total Current Assets | D65: € | M65: =sum(M61:M64) -> 1160347 | N65: =sum(N61:N64) -> 1131023.2 | O65: =sum(O61:O64) -> 1145121.2 | P65: =sum(P61:P64) -> 961154.87 | Q65: =sum(Q61:Q64) -> 865793.03 | R65: =sum(R61:R64) -> 762417.59 | S65: =sum(S61:S64) -> 659042.15 | T65: =sum(T61:T64) -> 555666.71 | ... AZ65: =sum(AZ61:AZ64) -> 12218379 | BB65: =P65 -> 961154.87 | BC65: =AB65 -> 3349609.3 | BD65: =AN65 -> 3822215.5 | BE65: =AZ65 -> 12218379 | BF65: =BF61+BF63+BF64 -> 30597212
B67: Net PP&E | D67: € | M67: 0 | N67: 0 | O67: 0 | P67: 0 | Q67: 0 | R67: 0 | S67: 0 | T67: 0 | U67: 0 | V67: 0 | W67: 0 | X67: 0 | Y67: 0 | Z67: 0 | AA67: 0 | AB67: 0 | AC67: 0 | AD67: 0 | AE67: 0 | AF67: 0 | AG67: 0 | AH67: 0 | AI67: 0 | AJ67: 0 | AK67: 0 | AL67: 0 | AM67: 0 | AN67: 0 | AO67: 0 | AP67: 0 | AQ67: 0 | AR67: 0 | AS67: 0 | AT67: 0 | AU67: 0 | AV67: 0 | AW67: 0 | AX67: 0 | AY67: 0 | AZ67: 0 | BB67: =P67 -> 0 | BC67: =AB67 -> 0 | BD67: =AN67 -> 0 | BE67: =AZ67 -> 0 | BF67: 0
B68: Total Fixed Assets | D68: € | M68: =M67 -> 0 | N68: =N67 -> 0 | O68: =O67 -> 0 | P68: =P67 -> 0 | Q68: =Q67 -> 0 | R68: =R67 -> 0 | S68: =S67 -> 0 | T68: =T67 -> 0 | ... AZ68: =AZ67 -> 0 | BB68: =P68 -> 0 | BC68: =AB68 -> 0 | BD68: =AN68 -> 0 | BE68: =AZ68 -> 0 | BF68: =BF67 -> 0
B69: TOTAL ASSETS | D69: € | M69: =M65+M68 -> 1160347 | N69: =N65+N68 -> 1131023.2 | O69: =O65+O68 -> 1145121.2 | P69: =P65+P68 -> 961154.87 | Q69: =Q65+Q68 -> 865793.03 | R69: =R65+R68 -> 762417.59 | S69: =S65+S68 -> 659042.15 | T69: =T65+T68 -> 555666.71 | ... AZ69: =AZ65+AZ68 -> 12218379 | BB69: =P69 -> 961154.87 | BC69: =AB69 -> 3349609.3 | BD69: =AN69 -> 3822215.5 | BE69: =AZ69 -> 12218379 | BF69: =BF65+BF68 -> 30597212
B71: EQUITY & LIABILITIES
B72: Accounts payable (DPO-based) | D72: € | M72: =ABS(Assumptions!$D$15*(M17/30)) -> 0 | N72: =ABS(Assumptions!$D$15*(N17/30)) -> 0 | O72: =ABS(Assumptions!$D$15*(O17/30)) -> 0 | P72: =ABS(Assumptions!$D$15*(P17/30)) -> 0 | Q72: =ABS(Assumptions!$D$15*(Q17/30)) -> 0 | R72: =ABS(Assumptions!$D$15*(R17/30)) -> 0 | S72: =ABS(Assumptions!$D$15*(S17/30)) -> 0 | T72: =ABS(Assumptions!$D$15*(T17/30)) -> 0 | ... AZ72: =ABS(Assumptions!$D$15*(AZ17/30)) -> 8680014.2 | BB72: =P72 -> 0 | BC72: =AB72 -> 0 | BD72: =AN72 -> 3314109.1 | BE72: =AZ72 -> 8680014.2 | BF72: =Assumptions!$D$15/365*BF17 -> 8876737
B73: Total Current Liabilities | D73: € | M73: =sum(M72) -> 0 | N73: =sum(N72) -> 0 | O73: =sum(O72) -> 0 | P73: =sum(P72) -> 0 | Q73: =sum(Q72) -> 0 | R73: =sum(R72) -> 0 | S73: =sum(S72) -> 0 | T73: =sum(T72) -> 0 | ... AZ73: =sum(AZ72) -> 8680014.2 | BB73: =P73 -> 0 | BC73: =AB73 -> 0 | BD73: =AN73 -> 3314109.1 | BE73: =AZ73 -> 8680014.2 | BF73: =BF72 -> 8876737
B75: Innovation loan outstanding | D75: € | M75: 0 | N75: 0 | O75: 0 | P75: 0 | Q75: 0 | R75: 0 | S75: 0 | T75: 0 | U75: 0 | V75: 0 | W75: 0 | X75: 0 | Y75: 0 | Z75: 0 | AA75: 0 | AB75: 0 | AC75: 0 | AD75: 0 | AE75: 0 | AF75: 0 | AG75: 0 | AH75: 0 | AI75: 0 | AJ75: 0 | AK75: 0 | AL75: 0 | AM75: 0 | AN75: 0 | AO75: 0 | AP75: 0 | AQ75: 0 | AR75: 0 | AS75: 0 | AT75: 0 | AU75: 0 | AV75: 0 | AW75: 0 | AX75: 0 | AY75: 0 | AZ75: 0 | BB75: =P75 -> 0 | BC75: =AB75 -> 0 | BD75: =AN75 -> 0 | BE75: =AZ75 -> 0 | BF75: 0
B76: Loan (CLA) | D76: € | Q76: 0 | R76: 0 | S76: 0 | T76: 0 | U76: 0 | V76: =V52 -> 300000 | W76: =V76 -> 300000 | X76: =W76 -> 300000 | Y76: =X76 -> 300000 | Z76: 0 | AA76: 0 | AB76: 0 | AC76: 0 | AD76: 0 | AE76: 0 | AF76: 0 | AG76: 0 | AH76: 0 | AI76: 0 | AJ76: 0 | AK76: 0 | AL76: 0 | AM76: 0 | AN76: 0 | AO76: 0 | AP76: 0 | AQ76: 0 | AR76: 0 | AS76: 0 | AT76: 0 | AU76: 0 | AV76: 0 | AW76: 0 | AX76: 0 | AY76: 0 | AZ76: 0 | BB76: 0 | BC76: =AB76 -> 0 | BD76: =AN76 -> 0 | BE76: =AZ76 -> 0 | BF76: 0
B77: Total Long-Term Liabilities | D77: € | M77: =M75 -> 0 | N77: =N75 -> 0 | O77: =O75 -> 0 | P77: =P75 -> 0 | Q77: =Q75+Q76 -> 0 | R77: =R75+R76 -> 0 | S77: =S75+S76 -> 0 | T77: =T75+T76 -> 0 | U77: =U75+U76 -> 0 | V77: =V75+V76 -> 300000 | W77: =W75+W76 -> 300000 | X77: =X75+X76 -> 300000 | ... AZ77: =AZ75+AZ76 -> 0 | BB77: =P77 -> 0 | BC77: =AB77 -> 0 | BD77: =AN77 -> 0 | BE77: =AZ77 -> 0 | BF77: =sum(BF75:BF76) -> 0
B79: Share capital + premium | D79: € | M79: =M56 -> 1111108 | N79: =M79 -> 1111108 | O79: =N79 -> 1111108 | P79: =O79 -> 1111108 | Q79: =P79 -> 1111108 | R79: =Q79 -> 1111108 | S79: =R79 -> 1111108 | T79: =S79 -> 1111108 | U79: =T79 -> 1111108 | ... Y79: =X79 -> 1111108 | Z79: =Y79+Y76 -> 1411108 | AA79: =Z79 -> 1411108 | AB79: =AA79 -> 1411108 | AC79: =AB79 -> 1411108 | AD79: =AC79 -> 1411108 | AE79: =AD79 -> 1411108 | AF79: =AE79 -> 1411108 | AG79: =AF79 -> 1411108 | AH79: =AG79 -> 1411108 | ... AZ79: =AY79 -> 1411108 | BB79: =P79 -> 1111108 | BC79: =AB79 -> 1411108 | BD79: =AN79 -> 1411108 | BE79: =AZ79 -> 1411108 | BF79: =BE79 -> 1411108
B80: Cumulative equity injections | D80: € | M80: =M51+M51 -> 0 | N80: =M80+N51 -> 0 | O80: =N80+O51 -> 0 | P80: =O80+P51 -> 0 | Q80: =P80+Q51 -> 0 | R80: =Q80+R51 -> 0 | S80: =R80+S51 -> 0 | T80: =S80+T51 -> 0 | U80: =T80+U51 -> 300000 | ... AZ80: =AY80+AZ51 -> 3550000 | BB80: =P80 -> 0 | BC80: =AB80 -> 3550000 | BD80: =AN80 -> 3550000 | BE80: =AZ80 -> 3550000 | BF80: =BE80 -> 3550000
B81: Retained earnings (cumulative net income) | D81: € | M81: =M43 -> -59000 | N81: =M81+N37 -> -98520 | O81: =N81+O37 -> -79520 | P81: =O81+P37 -> -327453 | Q81: =P81+Q37 -> -455973 | R81: =Q81+R37 -> -595293 | S81: =R81+S37 -> -734613 | T81: =S81+T37 -> -873933 | U81: =T81+U37 -> -1023253 | ... AZ81: =AY81+AZ37 -> -2042803.5 | BB81: =P81 -> -327453 | BC81: =AB81 -> -2297191 | BD81: =AN81 -> -6126709.7 | BE81: =AZ81 -> -2042803.5 | BF81: =BE81+BF37 -> 16759367
B82: Total Equity | D82: € | M82: =M79+M80+M81+M40 -> 1160347 | N82: =N79+N80+N81+N40 -> 1131023.2 | O82: =O79+O80+O81+O40 -> 1145121.2 | P82: =P79+P80+P81+P40 -> 961154.87 | Q82: =Q79+Q80+Q81+Q40 -> 865793.03 | R82: =R79+R80+R81+R40 -> 762417.59 | S82: =S79+S80+S81+S40 -> 659042.15 | T82: =T79+T80+T81+T40 -> 555666.71 | ... AZ82: =AZ79+AZ80+AZ81+AZ40 -> 3538364.8 | BB82: =P82 -> 961154.87 | BC82: =AB82 -> 3349609.3 | BD82: =AN82 -> 508106.39 | BE82: =AZ82 -> 3538364.8 | BF82: =sum(BF79:BF81) -> 21720475
B83: TOTAL EQUITY & LIABILITIES | D83: € | M83: =M73+M77+M82 -> 1160347 | N83: =N73+N77+N82 -> 1131023.2 | O83: =O73+O77+O82 -> 1145121.2 | P83: =P73+P77+P82 -> 961154.87 | Q83: =Q73+Q77+Q82 -> 865793.03 | R83: =R73+R77+R82 -> 762417.59 | S83: =S73+S77+S82 -> 659042.15 | T83: =T73+T77+T82 -> 555666.71 | ... AZ83: =AZ73+AZ77+AZ82 -> 12218379 | BB83: =P83 -> 961154.87 | BC83: =AB83 -> 3349609.3 | BD83: =AN83 -> 3822215.5 | BE83: =AZ83 -> 12218379 | BF83: =BF73+BF77+BF82 -> 30597212
B85: CHECK (Total Assets − Total E&L = 0) | M85: =M69-M83 -> 0 | N85: =N69-N83 -> 2.3283064e-10 | O85: =O69-O83 -> 0 | P85: =P69-P83 -> 0 | Q85: =Q69-Q83 -> 0 | R85: =R69-R83 -> 0 | S85: =S69-S83 -> 0 | T85: =T69-T83 -> 0 | ... AZ85: =AZ69-AZ83 -> 0 | BB85: =BB69-BB83 -> 0 | BC85: =BC69-BC83 -> 0 | BD85: =BD69-BD83 -> 9.3132257e-10 | BE85: =BE69-BE83 -> 0 | BF85: =BF69-BF83 -> 0

Sheet Revenue Forecast
B1: Tarnoc B.V. — Revenue Forecast (€, ex VAT unless noted)
E2: 2025 | Q2: 2026 | AC2: 2027 | AO2: 2028
E3: 45658 | F3: 45689 | G3: 45717 | H3: 45748 | I3: 45778 | J3: 45809 | K3: 45839 | L3: 45870 | M3: 45901 | N3: 45931 | O3: 45962 | P3: 45992 | Q3: 46023 | R3: 46054 | S3: 46082 | T3: 46113 | U3: 46143 | V3: 46174 | W3: 46204 | X3: 46235 | Y3: 46266 | Z3: 46296 | AA3: 46327 | AB3: 46357 | AC3: 46388 | AD3: 46419 | AE3: 46447 | AF3: 46478 | AG3: 46508 | AH3: 46539 | AI3: 46569 | AJ3: 46600 | AK3: 46631 | AL3: 46661 | AM3: 46692 | AN3: 46722 | AO3: 46753 | AP3: 46784 | AQ3: 46813 | AR3: 46844 | AS3: 46874 | AT3: 46905 | AU3: 46935 | AV3: 46966 | AW3: 46997 | AX3: 47027 | AY3: 47058 | AZ3: 47088 | BB3: 2025 | BC3: 2026 | BD3: 2027 | BE3: 2028 | BF3: 2029
AB4: 2 | AC4: 3 | AD4: 4 | AE4: 5 | AF4: 6 | AG4: 7 | AH4: 8 | AI4: 9 | AJ4: 10 | AK4: 11 | AL4: 12 | AM4: 13 | AN4: 14 | AO4: 15 | AP4: 16 | AQ4: 17 | AR4: 18 | AS4: 19 | AT4: 20 | AU4: 21 | AV4: 22 | AW4: 23 | AX4: 24 | AY4: 25 | AZ4: 26
B5: TURBINEKETEL (TTK)
B6: TTK units sold | D6: # | Q6: {=IF(YEAR(Q$3)=2026,0,ROUND(EXP(0.095*((YEAR(Q$3)-2027)*12+MONTH(Q$3)-1))/SUMPRODUCT(EXP(0.095*(ROW(INDIRECT("1:24"))-1)))*SUM(Assumptions!$D$22:$E$22),0))} -> 0 | R6: {=IF(YEAR(R$3)=2026,0,ROUND(EXP(0.095*((YEAR(R$3)-2027)*12+MONTH(R$3)-1))/SUMPRODUCT(EXP(0.095*(ROW(INDIRECT("1:24"))-1)))*SUM(Assumptions!$D$22:$E$22),0))} -> 0 | S6: {=IF(YEAR(S$3)=2026,0,ROUND(EXP(0.095*((YEAR(S$3)-2027)*12+MONTH(S$3)-1))/SUMPRODUCT(EXP(0.095*(ROW(INDIRECT("1:24"))-1)))*SUM(Assumptions!$D$22:$E$22),0))} -> 0 | T6: {=IF(YEAR(T$3)=2026,0,ROUND(EXP(0.095*((YEAR(T$3)-2027)*12+MONTH(T$3)-1))/SUMPRODUCT(EXP(0.095*(ROW(INDIRECT("1:24"))-1)))*SUM(Assumptions!$D$22:$E$22),0))} -> 0 | U6: {=IF(YEAR(U$3)=2026,0,ROUND(EXP(0.095*((YEAR(U$3)-2027)*12+MONTH(U$3)-1))/SUMPRODUCT(EXP(0.095*(ROW(INDIRECT("1:24"))-1)))*SUM(Assumptions!$D$22:$E$22),0))} -> 0 | V6: {=IF(YEAR(V$3)=2026,0,ROUND(EXP(0.095*((YEAR(V$3)-2027)*12+MONTH(V$3)-1))/SUMPRODUCT(EXP(0.095*(ROW(INDIRECT("1:24"))-1)))*SUM(Assumptions!$D$22:$E$22),0))} -> 0 | W6: {=IF(YEAR(W$3)=2026,0,ROUND(EXP(0.095*((YEAR(W$3)-2027)*12+MONTH(W$3)-1))/SUMPRODUCT(EXP(0.095*(ROW(INDIRECT("1:24"))-1)))*SUM(Assumptions!$D$22:$E$22),0))} -> 0 | X6: {=IF(YEAR(X$3)=2026,0,ROUND(EXP(0.095*((YEAR(X$3)-2027)*12+MONTH(X$3)-1))/SUMPRODUCT(EXP(0.095*(ROW(INDIRECT("1:24"))-1)))*SUM(Assumptions!$D$22:$E$22),0))} -> 0 | ... AB6: {=IF(YEAR(AB$3)=2026,0,ROUND(EXP(0.095*((YEAR(AB$3)-2027)*12+MONTH(AB$3)-1))/SUMPRODUCT(EXP(0.095*(ROW(INDIRECT("1:24"))-1)))*SUM(Assumptions!$D$22:$E$22),0))} -> 0 | AC6: {=IF(YEAR(AC$3)=2026,0,ROUND(EXP(0.091*((YEAR(AC$3)-2027)*12+MONTH(AC$3)-1))/SUMPRODUCT(EXP(0.091*(ROW(INDIRECT("1:24"))-1)))*SUM(Assumptions!$D$22:$E$22),0))} -> 48 | AD6: {=IF(YEAR(AD$3)=2026,0,ROUND(EXP(0.091*((YEAR(AD$3)-2027)*12+MONTH(AD$3)-1))/SUMPRODUCT(EXP(0.091*(ROW(INDIRECT("1:24"))-1)))*SUM(Assumptions!$D$22:$E$22),0))} -> 53 | AE6: {=IF(YEAR(AE$3)=2026,0,ROUND(EXP(0.091*((YEAR(AE$3)-2027)*12+MONTH(AE$3)-1))/SUMPRODUCT(EXP(0.091*(ROW(INDIRECT("1:24"))-1)))*SUM(Assumptions!$D$22:$E$22),0))} -> 58 | AF6: {=IF(YEAR(AF$3)=2026,0,ROUND(EXP(0.091*((YEAR(AF$3)-2027)*12+MONTH(AF$3)-1))/SUMPRODUCT(EXP(0.091*(ROW(INDIRECT("1:24"))-1)))*SUM(Assumptions!$D$22:$E$22),0))} -> 64 | AG6: {=IF(YEAR(AG$3)=2026,0,ROUND(EXP(0.091*((YEAR(AG$3)-2027)*12+MONTH(AG$3)-1))/SUMPRODUCT(EXP(0.091*(ROW(INDIRECT("1:24"))-1)))*SUM(Assumptions!$D$22:$E$22),0))} -> 70 | AH6: {=IF(YEAR(AH$3)=2026,0,ROUND(EXP(0.091*((YEAR(AH$3)-2027)*12+MONTH(AH$3)-1))/SUMPRODUCT(EXP(0.091*(ROW(INDIRECT("1:24"))-1)))*SUM(Assumptions!$D$22:$E$22),0))} -> 76 | AI6: {=IF(YEAR(AI$3)=2026,0,ROUND(EXP(0.091*((YEAR(AI$3)-2027)*12+MONTH(AI$3)-1))/SUMPRODUCT(EXP(0.091*(ROW(INDIRECT("1:24"))-1)))*SUM(Assumptions!$D$22:$E$22),0))} -> 83 | AJ6: {=IF(YEAR(AJ$3)=2026,0,ROUND(EXP(0.091*((YEAR(AJ$3)-2027)*12+MONTH(AJ$3)-1))/SUMPRODUCT(EXP(0.091*(ROW(INDIRECT("1:24"))-1)))*SUM(Assumptions!$D$22:$E$22),0))} -> 91 | ... AN6: {=IF(YEAR(AN$3)=2026,0,ROUND(EXP(0.091*((YEAR(AN$3)-2027)*12+MONTH(AN$3)-1))/SUMPRODUCT(EXP(0.091*(ROW(INDIRECT("1:24"))-1)))*SUM(Assumptions!$D$22:$E$22),0))} -> 132 | AO6: {=IF(YEAR(AO$3)=2026,0,ROUND(EXP(0.0915*((YEAR(AO$3)-2027)*12+MONTH(AO$3)-1))/SUMPRODUCT(EXP(0.0915*(ROW(INDIRECT("1:24"))-1)))*SUM(Assumptions!$D$22:$E$22),0))} -> 144 | AP6: {=IF(YEAR(AP$3)=2026,0,ROUND(EXP(0.0915*((YEAR(AP$3)-2027)*12+MONTH(AP$3)-1))/SUMPRODUCT(EXP(0.0915*(ROW(INDIRECT("1:24"))-1)))*SUM(Assumptions!$D$22:$E$22),0))} -> 158 | AQ6: {=IF(YEAR(AQ$3)=2026,0,ROUND(EXP(0.0915*((YEAR(AQ$3)-2027)*12+MONTH(AQ$3)-1))/SUMPRODUCT(EXP(0.0915*(ROW(INDIRECT("1:24"))-1)))*SUM(Assumptions!$D$22:$E$22),0))} -> 173 | AR6: {=IF(YEAR(AR$3)=2026,0,ROUND(EXP(0.0915*((YEAR(AR$3)-2027)*12+MONTH(AR$3)-1))/SUMPRODUCT(EXP(0.0915*(ROW(INDIRECT("1:24"))-1)))*SUM(Assumptions!$D$22:$E$22),0))} -> 189 | AS6: {=IF(YEAR(AS$3)=2026,0,ROUND(EXP(0.0915*((YEAR(AS$3)-2027)*12+MONTH(AS$3)-1))/SUMPRODUCT(EXP(0.0915*(ROW(INDIRECT("1:24"))-1)))*SUM(Assumptions!$D$22:$E$22),0))} -> 207 | AT6: {=IF(YEAR(AT$3)=2026,0,ROUND(EXP(0.0915*((YEAR(AT$3)-2027)*12+MONTH(AT$3)-1))/SUMPRODUCT(EXP(0.0915*(ROW(INDIRECT("1:24"))-1)))*SUM(Assumptions!$D$22:$E$22),0))} -> 227 | AU6: {=IF(YEAR(AU$3)=2026,0,ROUND(EXP(0.0915*((YEAR(AU$3)-2027)*12+MONTH(AU$3)-1))/SUMPRODUCT(EXP(0.0915*(ROW(INDIRECT("1:24"))-1)))*SUM(Assumptions!$D$22:$E$22),0))} -> 249 | AV6: {=IF(YEAR(AV$3)=2026,0,ROUND(EXP(0.0915*((YEAR(AV$3)-2027)*12+MONTH(AV$3)-1))/SUMPRODUCT(EXP(0.0915*(ROW(INDIRECT("1:24"))-1)))*SUM(Assumptions!$D$22:$E$22),0))} -> 273 | ... AZ6: {=IF(YEAR(AZ$3)=2026,0,ROUND(EXP(0.0915*((YEAR(AZ$3)-2027)*12+MONTH(AZ$3)-1))/SUMPRODUCT(EXP(0.0915*(ROW(INDIRECT("1:24"))-1)))*SUM(Assumptions!$D$22:$E$22),0))} -> 394 | BB6: =SUM(E6:P6) -> 0 | BC6: =SUM(Q6:AB6) -> 0 | BD6: =SUM(AC6:AN6) -> 1005 | BE6: =SUM(AO6:AZ6) -> 3000 | BF6: =BE6*2 -> 6000
B7: TTK Revenue | D7: € | Q7: =Q6*Assumptions!$C$28 -> 0 | R7: =R6*Assumptions!$C$28 -> 0 | S7: =S6*Assumptions!$C$28 -> 0 | T7: =T6*Assumptions!$C$28 -> 0 | U7: =U6*Assumptions!$C$28 -> 0 | V7: =V6*Assumptions!$C$28 -> 0 | W7: =W6*Assumptions!$C$28 -> 0 | X7: =X6*Assumptions!$C$28 -> 0 | ... AZ7: =AZ6*Assumptions!$C$28 -> 3191074.4 | BB7: =SUM(E7:P7) -> 0 | BC7: =SUM(Q7:AB7) -> 0 | BD7: =SUM(AC7:AN7) -> 8139669.4 | BE7: =SUM(AO7:AZ7) -> 24297521 | BF7: =BF6*Assumptions!$C$28 -> 48595041
B8: TTK upsell | D8: € | Q8: =Q6*SUMPRODUCT(Assumptions!$E$113:$F$116) -> 0 | R8: =R6*SUMPRODUCT(Assumptions!$E$113:$F$116) -> 0 | S8: =S6*SUMPRODUCT(Assumptions!$E$113:$F$116) -> 0 | T8: =T6*SUMPRODUCT(Assumptions!$E$113:$F$116) -> 0 | U8: =U6*SUMPRODUCT(Assumptions!$E$113:$F$116) -> 0 | V8: =V6*SUMPRODUCT(Assumptions!$E$113:$F$116) -> 0 | W8: =W6*SUMPRODUCT(Assumptions!$E$113:$F$116) -> 0 | X8: =X6*SUMPRODUCT(Assumptions!$E$113:$F$116) -> 0 | ... AB8: =AB6*SUMPRODUCT(Assumptions!$E$113:$F$116) -> 0 | AC8: =AC6*SUMPRODUCT(Assumptions!$E$113:$E$116,Assumptions!$F$113:$F$116) -> 95543.802 | AD8: =AD6*SUMPRODUCT(Assumptions!$E$113:$E$116,Assumptions!$F$113:$F$116) -> 105496.28 | AE8: =AE6*SUMPRODUCT(Assumptions!$E$113:$E$116,Assumptions!$F$113:$F$116) -> 115448.76 | AF8: =AF6*SUMPRODUCT(Assumptions!$E$113:$E$116,Assumptions!$F$113:$F$116) -> 127391.74 | AG8: =AG6*SUMPRODUCT(Assumptions!$E$113:$E$116,Assumptions!$F$113:$F$116) -> 139334.71 | AH8: =AH6*SUMPRODUCT(Assumptions!$E$113:$E$116,Assumptions!$F$113:$F$116) -> 151277.69 | AI8: =AI6*SUMPRODUCT(Assumptions!$E$113:$E$116,Assumptions!$F$113:$F$116) -> 165211.16 | AJ8: =AJ6*SUMPRODUCT(Assumptions!$E$113:$E$116,Assumptions!$F$113:$F$116) -> 181135.12 | ... AZ8: =AZ6*SUMPRODUCT(Assumptions!$E$113:$E$116,Assumptions!$F$113:$F$116) -> 784255.37 | BB8: =SUM(E8:P8) -> 0 | BC8: =SUM(Q8:AB8) -> 0 | BD8: =SUM(AC8:AN8) -> 2000448.3 | BE8: =SUM(AO8:AZ8) -> 5971487.6 | BF8: =BF6*SUMPRODUCT(Assumptions!$E$113:$E$116,Assumptions!$F$113:$F$116) -> 11942975
B9: Total TTK Revenue | D9: € | Q9: =sum(Q7:Q8) -> 0 | R9: =sum(R7:R8) -> 0 | S9: =sum(S7:S8) -> 0 | T9: =sum(T7:T8) -> 0 | U9: =sum(U7:U8) -> 0 | V9: =sum(V7:V8) -> 0 | W9: =sum(W7:W8) -> 0 | X9: =sum(X7:X8) -> 0 | ... AZ9: =sum(AZ7:AZ8) -> 3975329.8 | BB9: =SUM(E9:P9) -> 0 | BC9: =SUM(Q9:AB9) -> 0 | BD9: =SUM(AC9:AN9) -> 10140118 | BE9: =SUM(AO9:AZ9) -> 30269008 | BF9: =BE9*2 -> 60538017
B11: TARNOC MINI
B12: Mini units sold | D12: # | Q12: {=IF(YEAR(Q$3)=2026,0,ROUND(EXP(0.11*((YEAR(Q$3)-2027)*12+MONTH(Q$3)-1))/SUMPRODUCT(EXP(0.11*(ROW(INDIRECT("1:24"))-1)))*SUM(Assumptions!$D$23:$E$23),0))} -> 0 | R12: {=IF(YEAR(R$3)=2026,0,ROUND(EXP(0.11*((YEAR(R$3)-2027)*12+MONTH(R$3)-1))/SUMPRODUCT(EXP(0.11*(ROW(INDIRECT("1:24"))-1)))*SUM(Assumptions!$D$23:$E$23),0))} -> 0 | S12: {=IF(YEAR(S$3)=2026,0,ROUND(EXP(0.11*((YEAR(S$3)-2027)*12+MONTH(S$3)-1))/SUMPRODUCT(EXP(0.11*(ROW(INDIRECT("1:24"))-1)))*SUM(Assumptions!$D$23:$E$23),0))} -> 0 | T12: {=IF(YEAR(T$3)=2026,0,ROUND(EXP(0.11*((YEAR(T$3)-2027)*12+MONTH(T$3)-1))/SUMPRODUCT(EXP(0.11*(ROW(INDIRECT("1:24"))-1)))*SUM(Assumptions!$D$23:$E$23),0))} -> 0 | U12: {=IF(YEAR(U$3)=2026,0,ROUND(EXP(0.11*((YEAR(U$3)-2027)*12+MONTH(U$3)-1))/SUMPRODUCT(EXP(0.11*(ROW(INDIRECT("1:24"))-1)))*SUM(Assumptions!$D$23:$E$23),0))} -> 0 | V12: {=IF(YEAR(V$3)=2026,0,ROUND(EXP(0.11*((YEAR(V$3)-2027)*12+MONTH(V$3)-1))/SUMPRODUCT(EXP(0.11*(ROW(INDIRECT("1:24"))-1)))*SUM(Assumptions!$D$23:$E$23),0))} -> 0 | W12: {=IF(YEAR(W$3)=2026,0,ROUND(EXP(0.11*((YEAR(W$3)-2027)*12+MONTH(W$3)-1))/SUMPRODUCT(EXP(0.11*(ROW(INDIRECT("1:24"))-1)))*SUM(Assumptions!$D$23:$E$23),0))} -> 0 | X12: {=IF(YEAR(X$3)=2026,0,ROUND(EXP(0.11*((YEAR(X$3)-2027)*12+MONTH(X$3)-1))/SUMPRODUCT(EXP(0.11*(ROW(INDIRECT("1:24"))-1)))*SUM(Assumptions!$D$23:$E$23),0))} -> 0 | ... AB12: {=IF(YEAR(AB$3)=2026,0,ROUND(EXP(0.11*((YEAR(AB$3)-2027)*12+MONTH(AB$3)-1))/SUMPRODUCT(EXP(0.11*(ROW(INDIRECT("1:24"))-1)))*SUM(Assumptions!$D$23:$E$23),0))} -> 0 | AC12: {=IF(YEAR(AC$3)=2026,0,ROUND(EXP(0.116*((YEAR(AC$3)-2027)*12+MONTH(AC$3)-1))/SUMPRODUCT(EXP(0.116*(ROW(INDIRECT("1:24"))-1)))*SUM(Assumptions!$D$23:$E$23),0))} -> 20 | AD12: {=IF(YEAR(AD$3)=2026,0,ROUND(EXP(0.116*((YEAR(AD$3)-2027)*12+MONTH(AD$3)-1))/SUMPRODUCT(EXP(0.116*(ROW(INDIRECT("1:24"))-1)))*SUM(Assumptions!$D$23:$E$23),0))} -> 23 | AE12: {=IF(YEAR(AE$3)=2026,0,ROUND(EXP(0.116*((YEAR(AE$3)-2027)*12+MONTH(AE$3)-1))/SUMPRODUCT(EXP(0.116*(ROW(INDIRECT("1:24"))-1)))*SUM(Assumptions!$D$23:$E$23),0))} -> 26 | AF12: {=IF(YEAR(AF$3)=2026,0,ROUND(EXP(0.116*((YEAR(AF$3)-2027)*12+MONTH(AF$3)-1))/SUMPRODUCT(EXP(0.116*(ROW(INDIRECT("1:24"))-1)))*SUM(Assumptions!$D$23:$E$23),0))} -> 29 | AG12: {=IF(YEAR(AG$3)=2026,0,ROUND(EXP(0.116*((YEAR(AG$3)-2027)*12+MONTH(AG$3)-1))/SUMPRODUCT(EXP(0.116*(ROW(INDIRECT("1:24"))-1)))*SUM(Assumptions!$D$23:$E$23),0))} -> 32 | AH12: {=IF(YEAR(AH$3)=2026,0,ROUND(EXP(0.116*((YEAR(AH$3)-2027)*12+MONTH(AH$3)-1))/SUMPRODUCT(EXP(0.116*(ROW(INDIRECT("1:24"))-1)))*SUM(Assumptions!$D$23:$E$23),0))} -> 36 | AI12: {=IF(YEAR(AI$3)=2026,0,ROUND(EXP(0.116*((YEAR(AI$3)-2027)*12+MONTH(AI$3)-1))/SUMPRODUCT(EXP(0.116*(ROW(INDIRECT("1:24"))-1)))*SUM(Assumptions!$D$23:$E$23),0))} -> 41 | AJ12: {=IF(YEAR(AJ$3)=2026,0,ROUND(EXP(0.116*((YEAR(AJ$3)-2027)*12+MONTH(AJ$3)-1))/SUMPRODUCT(EXP(0.116*(ROW(INDIRECT("1:24"))-1)))*SUM(Assumptions!$D$23:$E$23),0))} -> 46 | ... AN12: {=IF(YEAR(AN$3)=2026,0,ROUND(EXP(0.116*((YEAR(AN$3)-2027)*12+MONTH(AN$3)-1))/SUMPRODUCT(EXP(0.116*(ROW(INDIRECT("1:24"))-1)))*SUM(Assumptions!$D$23:$E$23),0))} -> 73 | AO12: {=IF(YEAR(AO$3)=2026,0,ROUND(EXP(0.1157*((YEAR(AO$3)-2027)*12+MONTH(AO$3)-1))/SUMPRODUCT(EXP(0.1157*(ROW(INDIRECT("1:24"))-1)))*SUM(Assumptions!$D$23:$E$23),0))} -> 82 | AP12: {=IF(YEAR(AP$3)=2026,0,ROUND(EXP(0.1157*((YEAR(AP$3)-2027)*12+MONTH(AP$3)-1))/SUMPRODUCT(EXP(0.1157*(ROW(INDIRECT("1:24"))-1)))*SUM(Assumptions!$D$23:$E$23),0))} -> 92 | AQ12: {=IF(YEAR(AQ$3)=2026,0,ROUND(EXP(0.1157*((YEAR(AQ$3)-2027)*12+MONTH(AQ$3)-1))/SUMPRODUCT(EXP(0.1157*(ROW(INDIRECT("1:24"))-1)))*SUM(Assumptions!$D$23:$E$23),0))} -> 103 | AR12: {=IF(YEAR(AR$3)=2026,0,ROUND(EXP(0.1157*((YEAR(AR$3)-2027)*12+MONTH(AR$3)-1))/SUMPRODUCT(EXP(0.1157*(ROW(INDIRECT("1:24"))-1)))*SUM(Assumptions!$D$23:$E$23),0))} -> 115 | AS12: {=IF(YEAR(AS$3)=2026,0,ROUND(EXP(0.1157*((YEAR(AS$3)-2027)*12+MONTH(AS$3)-1))/SUMPRODUCT(EXP(0.1157*(ROW(INDIRECT("1:24"))-1)))*SUM(Assumptions!$D$23:$E$23),0))} -> 130 | AT12: {=IF(YEAR(AT$3)=2026,0,ROUND(EXP(0.1157*((YEAR(AT$3)-2027)*12+MONTH(AT$3)-1))/SUMPRODUCT(EXP(0.1157*(ROW(INDIRECT("1:24"))-1)))*SUM(Assumptions!$D$23:$E$23),0))} -> 145 | AU12: {=IF(YEAR(AU$3)=2026,0,ROUND(EXP(0.1157*((YEAR(AU$3)-2027)*12+MONTH(AU$3)-1))/SUMPRODUCT(EXP(0.1157*(ROW(INDIRECT("1:24"))-1)))*SUM(Assumptions!$D$23:$E$23),0))} -> 163 | AV12: {=IF(YEAR(AV$3)=2026,0,ROUND(EXP(0.1157*((YEAR(AV$3)-2027)*12+MONTH(AV$3)-1))/SUMPRODUCT(EXP(0.1157*(ROW(INDIRECT("1:24"))-1)))*SUM(Assumptions!$D$23:$E$23),0))} -> 183 | ... AZ12: {=IF(YEAR(AZ$3)=2026,0,ROUND(EXP(0.1157*((YEAR(AZ$3)-2027)*12+MONTH(AZ$3)-1))/SUMPRODUCT(EXP(0.1157*(ROW(INDIRECT("1:24"))-1)))*SUM(Assumptions!$D$23:$E$23),0))} -> 291 | BB12: =SUM(E12:P12) -> 0 | BC12: =SUM(Q12:AB12) -> 0 | BD12: =SUM(AC12:AN12) -> 500 | BE12: =SUM(AO12:AZ12) -> 2000 | BF12: =BE12*2 -> 4000
B13: Mini Revenue | D13: € | Q13: =Q12*Assumptions!$C$31 -> 0 | R13: =R12*Assumptions!$C$31 -> 0 | S13: =S12*Assumptions!$C$31 -> 0 | T13: =T12*Assumptions!$C$31 -> 0 | U13: =U12*Assumptions!$C$31 -> 0 | V13: =V12*Assumptions!$C$31 -> 0 | W13: =W12*Assumptions!$C$31 -> 0 | X13: =X12*Assumptions!$C$31 -> 0 | ... AZ13: =AZ12*Assumptions!$C$31 -> 805661.16 | BB13: =SUM(E13:P13) -> 0 | BC13: =SUM(Q13:AB13) -> 0 | BD13: =SUM(AC13:AN13) -> 1384297.5 | BE13: =SUM(AO13:AZ13) -> 5537190.1 | BF13: =BF12*Assumptions!$C$31 -> 11074380
B14: Mini upsell | D14: € | Q14: =Q12*PRODUCT(Assumptions!$E$122:$F$122) -> 0 | R14: =R12*PRODUCT(Assumptions!$E$122:$F$122) -> 0 | S14: =S12*PRODUCT(Assumptions!$E$122:$F$122) -> 0 | T14: =T12*PRODUCT(Assumptions!$E$122:$F$122) -> 0 | U14: =U12*PRODUCT(Assumptions!$E$122:$F$122) -> 0 | V14: =V12*PRODUCT(Assumptions!$E$122:$F$122) -> 0 | W14: =W12*PRODUCT(Assumptions!$E$122:$F$122) -> 0 | X14: =X12*PRODUCT(Assumptions!$E$122:$F$122) -> 0 | ... AZ14: =AZ12*PRODUCT(Assumptions!$E$122:$F$122) -> 39867 | BB14: =SUM(E14:P14) -> 0 | BC14: =SUM(Q14:AB14) -> 0 | BD14: =SUM(AC14:AN14) -> 68500 | BE14: =SUM(AO14:AZ14) -> 274000 | BF14: =BF12*PRODUCT(Assumptions!$E$122:$F$122) -> 548000
B15: Total Mini Revenue | D15: € | Q15: =sum(Q13:Q14) -> 0 | R15: =sum(R13:R14) -> 0 | S15: =sum(S13:S14) -> 0 | T15: =sum(T13:T14) -> 0 | U15: =sum(U13:U14) -> 0 | V15: =sum(V13:V14) -> 0 | W15: =sum(W13:W14) -> 0 | X15: =sum(X13:X14) -> 0 | ... AZ15: =sum(AZ13:AZ14) -> 845528.16 | BB15: =SUM(E15:P15) -> 0 | BC15: =SUM(Q15:AB15) -> 0 | BD15: =SUM(AC15:AN15) -> 1452797.5 | BE15: =SUM(AO15:AZ15) -> 5811190.1 | BF15: =BE15*2 -> 11622380
B17: INSTALLATION REVENUES | D17: €
B18: Units installed | D18: # | Q18: =Q12+Q6 -> 0 | R18: =R12+R6 -> 0 | S18: =S12+S6 -> 0 | T18: =T12+T6 -> 0 | U18: =U12+U6 -> 0 | V18: =V12+V6 -> 0 | W18: =W12+W6 -> 0 | X18: =X12+X6 -> 0 | ... AZ18: =AZ12+AZ6 -> 685 | BB18: =SUM(E18:P18) -> 0 | BC18: =SUM(Q18:AB18) -> 0 | BD18: =SUM(AC18:AN18) -> 1505 | BE18: =SUM(AO18:AZ18) -> 5000 | BF18: =BF6+BF12 -> 10000
B19: Total Installation Revenue | D19: € | Q19: =Q18*Assumptions!$C$33 -> 0 | R19: =R18*Assumptions!$C$33 -> 0 | S19: =S18*Assumptions!$C$33 -> 0 | T19: =T18*Assumptions!$C$33 -> 0 | U19: =U18*Assumptions!$C$33 -> 0 | V19: =V18*Assumptions!$C$33 -> 0 | W19: =W18*Assumptions!$C$33 -> 0 | X19: =X18*Assumptions!$C$33 -> 0 | ... AZ19: =AZ18*Assumptions!$C$33 -> 2192000 | BB19: =SUM(E19:P19) -> 0 | BC19: =SUM(Q19:AB19) -> 0 | BD19: =SUM(AC19:AN19) -> 4816000 | BE19: =SUM(AO19:AZ19) -> 16000000 | BF19: =BE19*2 -> 32000000
B21: SERVICE REVENUES
B22: Installed base (TTK) | D22: # | Q22: =Q6 -> 0 | R22: =R6 -> 0 | S22: =S6 -> 0 | T22: =T6 -> 0 | U22: =U6 -> 0 | V22: =V6 -> 0 | W22: =W6 -> 0 | X22: =X6 -> 0 | ... AC22: =AC6 -> 48 | AD22: =AC22+AD6 -> 101 | AE22: =AD22+AE6 -> 159 | AF22: =AE22+AF6 -> 223 | AG22: =AF22+AG6 -> 293 | AH22: =AG22+AH6 -> 369 | AI22: =AH22+AI6 -> 452 | AJ22: =AI22+AJ6 -> 543 | AK22: =AJ22+AK6 -> 643 | ... AZ22: =AY22+AZ6 -> 4005 | BB22: =SUM(E22:P22) -> 0 | BC22: =SUM(Q22:AB22) -> 0 | BD22: =AN22 -> 1005 | BE22: =AZ22 -> 4005 | BF22: =BF18*55% -> 5500
B23: Installed base (Mini) | D23: # | Q23: =Q12 -> 0 | R23: =R12 -> 0 | S23: =S12 -> 0 | T23: =T12 -> 0 | U23: =U12 -> 0 | V23: =V12 -> 0 | W23: =W12 -> 0 | X23: =X12 -> 0 | ... AC23: =AC12 -> 20 | AD23: =AC23+AD12 -> 43 | AE23: =AD23+AE12 -> 69 | AF23: =AE23+AF12 -> 98 | AG23: =AF23+AG12 -> 130 | AH23: =AG23+AH12 -> 166 | AI23: =AH23+AI12 -> 207 | AJ23: =AI23+AJ12 -> 253 | AK23: =AJ23+AK12 -> 304 | ... AZ23: =AY23+AZ12 -> 2500 | BB23: =SUM(E23:P23) -> 0 | BC23: =SUM(Q23:AB23) -> 0 | BD23: =AN23 -> 500 | BE23: =AZ23 -> 2500 | BF23: =BF18*0.45 -> 4500
B24: Total Service Revenue | D24: € | Q24: =Q34*SUMPRODUCT(Assumptions!$E$126:$E$127,Assumptions!$F$126:$F$127) -> 0 | R24: =R34*SUMPRODUCT(Assumptions!$E$126:$E$127,Assumptions!$F$126:$F$127) -> 0 | S24: =S34*SUMPRODUCT(Assumptions!$E$126:$E$127,Assumptions!$F$126:$F$127) -> 0 | T24: =T34*SUMPRODUCT(Assumptions!$E$126:$E$127,Assumptions!$F$126:$F$127) -> 0 | U24: =U34*SUMPRODUCT(Assumptions!$E$126:$E$127,Assumptions!$F$126:$F$127) -> 0 | V24: =V34*SUMPRODUCT(Assumptions!$E$126:$E$127,Assumptions!$F$126:$F$127) -> 0 | W24: =W34*SUMPRODUCT(Assumptions!$E$126:$E$127,Assumptions!$F$126:$F$127) -> 0 | X24: =X34*SUMPRODUCT(Assumptions!$E$126:$E$127,Assumptions!$F$126:$F$127) -> 0 | ... AB24: =AB34*SUMPRODUCT(Assumptions!$E$126:$E$127,Assumptions!$F$126:$F$127) -> 0 | AC24: =AC34*SUMPRODUCT(Assumptions!$E$126:$E$127,Assumptions!$F$126:$F$127)+Q24 -> 4692 | AD24: =AD34*SUMPRODUCT(Assumptions!$E$126:$E$127,Assumptions!$F$126:$F$127)+R24 -> 5244 | AE24: =AE34*SUMPRODUCT(Assumptions!$E$126:$E$127,Assumptions!$F$126:$F$127)+S24 -> 5796 | AF24: =AF34*SUMPRODUCT(Assumptions!$E$126:$E$127,Assumptions!$F$126:$F$127)+T24 -> 6417 | AG24: =AG34*SUMPRODUCT(Assumptions!$E$126:$E$127,Assumptions!$F$126:$F$127)+U24 -> 7038 | AH24: =AH34*SUMPRODUCT(Assumptions!$E$126:$E$127,Assumptions!$F$126:$F$127)+V24 -> 7728 | AI24: =AI34*SUMPRODUCT(Assumptions!$E$126:$E$127,Assumptions!$F$126:$F$127)+W24 -> 8556 | AJ24: =AJ34*SUMPRODUCT(Assumptions!$E$126:$E$127,Assumptions!$F$126:$F$127)+X24 -> 9453 | ... AZ24: =AZ34*SUMPRODUCT(Assumptions!$E$126:$E$127,Assumptions!$F$126:$F$127)+AN24 -> 61410 | BB24: =SUM(E24:P24) -> 0 | BC24: =SUM(Q24:AB24) -> 0 | BD24: =SUM(AC24:AN24) -> 103845 | BE24: =SUM(AO24:AZ24) -> 448845 | BF24: =(BE24*2)+BE24 -> 1346535
B26: SUBSIDIES & GRANTS
B27: All other | D27: € | E27: 0 | F27: 0 | G27: 0 | H27: 0 | I27: 0 | J27: 0 | K27: 0 | L27: 0 | M27: 0 | N27: 19480 | O27: 78000 | P27: 0 | Q27: 0 | R27: 0 | S27: 0 | T27: 0 | U27: 0 | V27: 106782 | W27: 0 | X27: 0 | Y27: 0 | Z27: 0 | AA27: 0 | AB27: 0 | AC27: 0 | AD27: 0 | AE27: 0 | AF27: 0 | AG27: 0 | AH27: 0 | AI27: 0 | AJ27: 0 | AK27: 0 | AL27: 0 | AM27: 0 | AN27: 0 | AO27: 0 | AP27: 0 | AQ27: 0 | AR27: 0 | AS27: 0 | AT27: 0 | AU27: 0 | AV27: 0 | AW27: 0 | AX27: 0 | AY27: 0 | AZ27: 0 | BB27: =SUM(E27:P27) -> 97480 | BC27: =SUM(Q27:AB27) -> 106782 | BD27: =SUM(AC27:AN27) -> 0 | BE27: =SUM(AO27:AZ27) -> 0 | BF27: 0
B28: Total Subsidies & Grants | D28: € | E28: =sum(E27) -> 0 | F28: =sum(F27) -> 0 | G28: =sum(G27) -> 0 | H28: =sum(H27) -> 0 | I28: =sum(I27) -> 0 | J28: =sum(J27) -> 0 | K28: =sum(K27) -> 0 | L28: =sum(L27) -> 0 | ... AZ28: =sum(AZ27) -> 0 | BB28: =SUM(E28:P28) -> 97480 | BC28: =SUM(Q28:AB28) -> 106782 | BD28: =BD27 -> 0 | BE28: =BE27 -> 0 | BF28: =BF27 -> 0
B30: TOTAL REVENUE | E30: =E15+E9+E19+E24+E28 -> 0 | F30: =F15+F9+F19+F24+F28 -> 0 | G30: =G15+G9+G19+G24+G28 -> 0 | H30: =H15+H9+H19+H24+H28 -> 0 | I30: =I15+I9+I19+I24+I28 -> 0 | J30: =J15+J9+J19+J24+J28 -> 0 | K30: =K15+K9+K19+K24+K28 -> 0 | L30: =L15+L9+L19+L24+L28 -> 0 | ... AZ30: =AZ15+AZ9+AZ19+AZ24+AZ28 -> 7074267.9 | BB30: =BB9+BB15+BB28+BB19+BB24 -> 97480 | BC30: =BC9+BC15+BC28+BC19+BC24 -> 106782 | BD30: =SUM(AC30:AN30) -> 16512760 | BE30: =SUM(AO30:AZ30) -> 52529043 | BF30: =BF9+BF15+BF28+BF19+BF24 -> 1.0550693e+08
B33: Installed Base | AC33: =sum(AC22:AC23) -> 68 | AD33: =sum(AD22:AD23) -> 144 | AE33: =sum(AE22:AE23) -> 228 | AF33: =sum(AF22:AF23) -> 321 | AG33: =sum(AG22:AG23) -> 423 | AH33: =sum(AH22:AH23) -> 535 | AI33: =sum(AI22:AI23) -> 659 | AJ33: =sum(AJ22:AJ23) -> 796 | ... AZ33: =sum(AZ22:AZ23) -> 6505 | BB33: =sum(BB22:BB23) -> 0 | BC33: =sum(BC22:BC23) -> 0 | BD33: =sum(BD22:BD23) -> 1505 | BE33: =sum(BE22:BE23) -> 6505 | BF33: =sum(BF22:BF23) -> 10000
B34: Units sold | D34: # | Q34: =Q12+Q6 -> 0 | R34: =R12+R6 -> 0 | S34: =S12+S6 -> 0 | T34: =T12+T6 -> 0 | U34: =U12+U6 -> 0 | V34: =V12+V6 -> 0 | W34: =W12+W6 -> 0 | X34: =X12+X6 -> 0 | ... AZ34: =AZ12+AZ6 -> 685 | BB34: 0 | BC34: 0 | BD34: =SUM(AC34:AN34) -> 1505 | BE34: =SUM(AO34:AZ34) -> 5000 | BF34: =BF18 -> 10000

Sheet COGS
B1: Tarnoc B.V. — COGS Schedule (€)
E2: 2025 | Q2: 2026 | AC2: 2027 | AO2: 2028
E3: 45658 | F3: 45689 | G3: 45717 | H3: 45748 | I3: 45778 | J3: 45809 | K3: 45839 | L3: 45870 | M3: 45901 | N3: 45931 | O3: 45962 | P3: 45992 | Q3: 46023 | R3: 46054 | S3: 46082 | T3: 46113 | U3: 46143 | V3: 46174 | W3: 46204 | X3: 46235 | Y3: 46266 | Z3: 46296 | AA3: 46327 | AB3: 46357 | AC3: 46388 | AD3: 46419 | AE3: 46447 | AF3: 46478 | AG3: 46508 | AH3: 46539 | AI3: 46569 | AJ3: 46600 | AK3: 46631 | AL3: 46661 | AM3: 46692 | AN3: 46722 | AO3: 46753 | AP3: 46784 | AQ3: 46813 | AR3: 46844 | AS3: 46874 | AT3: 46905 | AU3: 46935 | AV3: 46966 | AW3: 46997 | AX3: 47027 | AY3: 47058 | AZ3: 47088 | BB3: 2025 | BC3: 2026 | BD3: 2027 | BE3: 2028 | BF3: 2029
B6: TTK
B7: TTK | D7: € | Q7: =IFNA('Revenue Forecast'!Q6 * VLOOKUP('Revenue Forecast'!$BC$6, Assumptions!$B$67:$C$69, 2, TRUE), 0) -> 0 | R7: =IFNA('Revenue Forecast'!R6 * VLOOKUP('Revenue Forecast'!$BC$6, Assumptions!$B$67:$C$69, 2, TRUE), 0) -> 0 | S7: =IFNA('Revenue Forecast'!S6 * VLOOKUP('Revenue Forecast'!$BC$6, Assumptions!$B$67:$C$69, 2, TRUE), 0) -> 0 | T7: =IFNA('Revenue Forecast'!T6 * VLOOKUP('Revenue Forecast'!$BC$6, Assumptions!$B$67:$C$69, 2, TRUE), 0) -> 0 | U7: =IFNA('Revenue Forecast'!U6 * VLOOKUP('Revenue Forecast'!$BC$6, Assumptions!$B$67:$C$69, 2, TRUE), 0) -> 0 | V7: =IFNA('Revenue Forecast'!V6 * VLOOKUP('Revenue Forecast'!$BC$6, Assumptions!$B$67:$C$69, 2, TRUE), 0) -> 0 | W7: =IFNA('Revenue Forecast'!W6 * VLOOKUP('Revenue Forecast'!$BC$6, Assumptions!$B$67:$C$69, 2, TRUE), 0) -> 0 | X7: =IFNA('Revenue Forecast'!X6 * VLOOKUP('Revenue Forecast'!$BC$6, Assumptions!$B$67:$C$69, 2, TRUE), 0) -> 0 | ... AB7: =IFNA('Revenue Forecast'!AB6 * VLOOKUP('Revenue Forecast'!$BC$6, Assumptions!$B$67:$C$69, 2, TRUE), 0) -> 0 | AC7: ='Revenue Forecast'!AC6*VLOOKUP('Revenue Forecast'!$BD$6+'Revenue Forecast'!$BE$6,Assumptions!$B$67:$C$69,2,TRUE) -> 479948.16 | AD7: ='Revenue Forecast'!AD6*VLOOKUP('Revenue Forecast'!$BD$6+'Revenue Forecast'!$BE$6,Assumptions!$B$67:$C$69,2,TRUE) -> 529942.76 | AE7: ='Revenue Forecast'!AE6*VLOOKUP('Revenue Forecast'!$BD$6+'Revenue Forecast'!$BE$6,Assumptions!$B$67:$C$69,2,TRUE) -> 579937.36 | AF7: ='Revenue Forecast'!AF6*VLOOKUP('Revenue Forecast'!$BD$6+'Revenue Forecast'!$BE$6,Assumptions!$B$67:$C$69,2,TRUE) -> 639930.88 | AG7: ='Revenue Forecast'!AG6*VLOOKUP('Revenue Forecast'!$BD$6+'Revenue Forecast'!$BE$6,Assumptions!$B$67:$C$69,2,TRUE) -> 699924.4 | AH7: ='Revenue Forecast'!AH6*VLOOKUP('Revenue Forecast'!$BD$6+'Revenue Forecast'!$BE$6,Assumptions!$B$67:$C$69,2,TRUE) -> 759917.92 | AI7: ='Revenue Forecast'!AI6*VLOOKUP('Revenue Forecast'!$BD$6+'Revenue Forecast'!$BE$6,Assumptions!$B$67:$C$69,2,TRUE) -> 829910.36 | AJ7: ='Revenue Forecast'!AJ6*VLOOKUP('Revenue Forecast'!$BD$6+'Revenue Forecast'!$BE$6,Assumptions!$B$67:$C$69,2,TRUE) -> 909901.72 | ... AN7: ='Revenue Forecast'!AN6*VLOOKUP('Revenue Forecast'!$BD$6+'Revenue Forecast'!$BE$6,Assumptions!$B$67:$C$69,2,TRUE) -> 1319857.4 | AO7: ='Revenue Forecast'!AO6*VLOOKUP('Revenue Forecast'!$BE$6+'Revenue Forecast'!$BF$6,Assumptions!$B$67:$C$69,2,TRUE) -> 1019439.9 | AP7: ='Revenue Forecast'!AP6*VLOOKUP('Revenue Forecast'!$BE$6+'Revenue Forecast'!$BF$6,Assumptions!$B$67:$C$69,2,TRUE) -> 1118552.2 | AQ7: ='Revenue Forecast'!AQ6*VLOOKUP('Revenue Forecast'!$BE$6+'Revenue Forecast'!$BF$6,Assumptions!$B$67:$C$69,2,TRUE) -> 1224743.8 | AR7: ='Revenue Forecast'!AR6*VLOOKUP('Revenue Forecast'!$BE$6+'Revenue Forecast'!$BF$6,Assumptions!$B$67:$C$69,2,TRUE) -> 1338014.9 | AS7: ='Revenue Forecast'!AS6*VLOOKUP('Revenue Forecast'!$BE$6+'Revenue Forecast'!$BF$6,Assumptions!$B$67:$C$69,2,TRUE) -> 1465444.9 | AT7: ='Revenue Forecast'!AT6*VLOOKUP('Revenue Forecast'!$BE$6+'Revenue Forecast'!$BF$6,Assumptions!$B$67:$C$69,2,TRUE) -> 1607033.8 | AU7: ='Revenue Forecast'!AU6*VLOOKUP('Revenue Forecast'!$BE$6+'Revenue Forecast'!$BF$6,Assumptions!$B$67:$C$69,2,TRUE) -> 1762781.6 | AV7: ='Revenue Forecast'!AV6*VLOOKUP('Revenue Forecast'!$BE$6+'Revenue Forecast'!$BF$6,Assumptions!$B$67:$C$69,2,TRUE) -> 1932688.2 | ... AZ7: ='Revenue Forecast'!AZ6*VLOOKUP('Revenue Forecast'!$BE$6+'Revenue Forecast'!$BF$6,Assumptions!$B$67:$C$69,2,TRUE) -> 2789300.9 | BC7: =SUM(Q7:AB7) -> 0 | BD7: =SUM(AC7:AN7) -> 10048915 | BE7: =SUM(AO7:AZ7) -> 21238332 | BF7: ='Revenue Forecast'!BF6*Assumptions!G50 -> 30000000
B8: Upsell | D8: € | Q8: ='Revenue Forecast'!Q6*SUMPRODUCT(Assumptions!$E$113:$E$116,Assumptions!$G$113:$G$116) -> 0 | R8: ='Revenue Forecast'!R6*SUMPRODUCT(Assumptions!$E$113:$E$116,Assumptions!$G$113:$G$116) -> 0 | S8: ='Revenue Forecast'!S6*SUMPRODUCT(Assumptions!$E$113:$E$116,Assumptions!$G$113:$G$116) -> 0 | T8: ='Revenue Forecast'!T6*SUMPRODUCT(Assumptions!$E$113:$E$116,Assumptions!$G$113:$G$116) -> 0 | U8: ='Revenue Forecast'!U6*SUMPRODUCT(Assumptions!$E$113:$E$116,Assumptions!$G$113:$G$116) -> 0 | V8: ='Revenue Forecast'!V6*SUMPRODUCT(Assumptions!$E$113:$E$116,Assumptions!$G$113:$G$116) -> 0 | W8: ='Revenue Forecast'!W6*SUMPRODUCT(Assumptions!$E$113:$E$116,Assumptions!$G$113:$G$116) -> 0 | X8: ='Revenue Forecast'!X6*SUMPRODUCT(Assumptions!$E$113:$E$116,Assumptions!$G$113:$G$116) -> 0 | ... AZ8: ='Revenue Forecast'!AZ6*SUMPRODUCT(Assumptions!$E$113:$E$116,Assumptions!$G$113:$G$116) -> 381313.2 | BC8: =SUM(Q8:AB8) -> 0 | BD8: =SUM(AC8:AN8) -> 972639 | BE8: =SUM(AO8:AZ8) -> 2903400 | BF8: ='Revenue Forecast'!BF6*SUMPRODUCT(Assumptions!$E$113:$E$116,Assumptions!$G$113:$G$116) -> 5806800
B9: Total TTK COGS | D9: € | Q9: =sum(Q7:Q8) -> 0 | R9: =sum(R7:R8) -> 0 | S9: =sum(S7:S8) -> 0 | T9: =sum(T7:T8) -> 0 | U9: =sum(U7:U8) -> 0 | V9: =sum(V7:V8) -> 0 | W9: =sum(W7:W8) -> 0 | X9: =sum(X7:X8) -> 0 | ... AZ9: =sum(AZ7:AZ8) -> 3170614.1 | BB9: =SUM(E9:P9) -> 0 | BC9: =SUM(Q9:AB9) -> 0 | BD9: =SUM(AC9:AN9) -> 11021554 | BE9: =SUM(AO9:AZ9) -> 24141732 | BF9: =sum(BF7:BF8) -> 35806800
B11: TARNOC MINI
B12: Total COGS Mini | D12: € | Q12: =IFNA('Revenue Forecast'!Q12*VLOOKUP('Revenue Forecast'!$BD$12,Assumptions!$B$81:$C$84,2,TRUE),0) -> 0 | R12: =IFNA('Revenue Forecast'!R12*VLOOKUP('Revenue Forecast'!$BD$12,Assumptions!$B$81:$C$84,2,TRUE),0) -> 0 | S12: =IFNA('Revenue Forecast'!S12*VLOOKUP('Revenue Forecast'!$BD$12,Assumptions!$B$81:$C$84,2,TRUE),0) -> 0 | T12: =IFNA('Revenue Forecast'!T12*VLOOKUP('Revenue Forecast'!$BD$12,Assumptions!$B$81:$C$84,2,TRUE),0) -> 0 | U12: =IFNA('Revenue Forecast'!U12*VLOOKUP('Revenue Forecast'!$BD$12,Assumptions!$B$81:$C$84,2,TRUE),0) -> 0 | V12: =IFNA('Revenue Forecast'!V12*VLOOKUP('Revenue Forecast'!$BD$12,Assumptions!$B$81:$C$84,2,TRUE),0) -> 0 | W12: =IFNA('Revenue Forecast'!W12*VLOOKUP('Revenue Forecast'!$BD$12,Assumptions!$B$81:$C$84,2,TRUE),0) -> 0 | X12: =IFNA('Revenue Forecast'!X12*VLOOKUP('Revenue Forecast'!$BD$12,Assumptions!$B$81:$C$84,2,TRUE),0) -> 0 | ... AB12: =IFNA('Revenue Forecast'!AB12*VLOOKUP('Revenue Forecast'!$BD$12,Assumptions!$B$81:$C$84,2,TRUE),0) -> 0 | AC12: ='Revenue Forecast'!AC12*VLOOKUP('Revenue Forecast'!$BD$12,Assumptions!$B$80:$C$84,2,TRUE) -> 26000 | AD12: ='Revenue Forecast'!AD12*VLOOKUP('Revenue Forecast'!$BD$12,Assumptions!$B$80:$C$84,2,TRUE) -> 29900 | AE12: ='Revenue Forecast'!AE12*VLOOKUP('Revenue Forecast'!$BD$12,Assumptions!$B$80:$C$84,2,TRUE) -> 33800 | AF12: ='Revenue Forecast'!AF12*VLOOKUP('Revenue Forecast'!$BD$12,Assumptions!$B$80:$C$84,2,TRUE) -> 37700 | AG12: ='Revenue Forecast'!AG12*VLOOKUP('Revenue Forecast'!$BD$12,Assumptions!$B$80:$C$84,2,TRUE) -> 41600 | AH12: ='Revenue Forecast'!AH12*VLOOKUP('Revenue Forecast'!$BD$12,Assumptions!$B$80:$C$84,2,TRUE) -> 46800 | AI12: ='Revenue Forecast'!AI12*VLOOKUP('Revenue Forecast'!$BD$12,Assumptions!$B$80:$C$84,2,TRUE) -> 53300 | AJ12: ='Revenue Forecast'!AJ12*VLOOKUP('Revenue Forecast'!$BD$12,Assumptions!$B$80:$C$84,2,TRUE) -> 59800 | ... AZ12: ='Revenue Forecast'!AZ12*VLOOKUP('Revenue Forecast'!$BD$12,Assumptions!$B$80:$C$84,2,TRUE) -> 378300 | BC12: =SUM(Q12:AB12) -> 0 | BD12: =SUM(AC12:AN12) -> 650000 | BE12: =SUM(AO12:AZ12) -> 2600000 | BF12: ='Revenue Forecast'!BF12*Assumptions!H77 -> 3953400
B13: Upsell | D13: € | Q13: ='Revenue Forecast'!Q12*PRODUCT(Assumptions!$E$122,Assumptions!$G$122) -> 0 | R13: ='Revenue Forecast'!R12*PRODUCT(Assumptions!$E$122,Assumptions!$G$122) -> 0 | S13: ='Revenue Forecast'!S12*PRODUCT(Assumptions!$E$122,Assumptions!$G$122) -> 0 | T13: ='Revenue Forecast'!T12*PRODUCT(Assumptions!$E$122,Assumptions!$G$122) -> 0 | U13: ='Revenue Forecast'!U12*PRODUCT(Assumptions!$E$122,Assumptions!$G$122) -> 0 | V13: ='Revenue Forecast'!V12*PRODUCT(Assumptions!$E$122,Assumptions!$G$122) -> 0 | W13: ='Revenue Forecast'!W12*PRODUCT(Assumptions!$E$122,Assumptions!$G$122) -> 0 | X13: ='Revenue Forecast'!X12*PRODUCT(Assumptions!$E$122,Assumptions!$G$122) -> 0 | ... AZ13: ='Revenue Forecast'!AZ12*PRODUCT(Assumptions!$E$122,Assumptions!$G$122) -> 17460 | BC13: =SUM(Q13:AB13) -> 0 | BD13: =SUM(AC13:AN13) -> 30000 | BE13: =SUM(AO13:AZ13) -> 120000 | BF13: ='Revenue Forecast'!BF12*PRODUCT(Assumptions!$E$122,Assumptions!$G$122) -> 240000
B14: Total Mini COGS | D14: € | Q14: =sum(Q12:Q13) -> 0 | R14: =sum(R12:R13) -> 0 | S14: =sum(S12:S13) -> 0 | T14: =sum(T12:T13) -> 0 | U14: =sum(U12:U13) -> 0 | V14: =sum(V12:V13) -> 0 | W14: =sum(W12:W13) -> 0 | X14: =sum(X12:X13) -> 0 | ... AZ14: =sum(AZ12:AZ13) -> 395760 | BB14: =SUM(E14:P14) -> 0 | BC14: =SUM(Q14:AB14) -> 0 | BD14: =SUM(AC14:AN14) -> 680000 | BE14: =SUM(AO14:AZ14) -> 2720000 | BF14: =sum(BF12:BF13) -> 4193400
B16: INSTALLATION
B17: Total COGS Mini & TTK | D17: € | Q17: ='Revenue Forecast'!Q34*Assumptions!$C$33 -> 0 | R17: ='Revenue Forecast'!R34*Assumptions!$C$33 -> 0 | S17: ='Revenue Forecast'!S34*Assumptions!$C$33 -> 0 | T17: ='Revenue Forecast'!T34*Assumptions!$C$33 -> 0 | U17: ='Revenue Forecast'!U34*Assumptions!$C$33 -> 0 | V17: ='Revenue Forecast'!V34*Assumptions!$C$33 -> 0 | W17: ='Revenue Forecast'!W34*Assumptions!$C$33 -> 0 | X17: ='Revenue Forecast'!X34*Assumptions!$C$33 -> 0 | ... AZ17: ='Revenue Forecast'!AZ34*Assumptions!$C$33 -> 2192000 | BC17: =SUM(Q17:AB17) -> 0 | BD17: =SUM(AC17:AN17) -> 4816000 | BE17: =SUM(AO17:AZ17) -> 16000000 | BF17: ='Revenue Forecast'!BF18*Assumptions!$C$33 -> 32000000
B19: SERVICE REVENUES
B20: Installed base (TTK) | D20: # | Q20: =Q4 | R20: =R4 | S20: =S4 | T20: =T4 | U20: =U4 | V20: =V4 | W20: =W4 | X20: =X4 | ... AB20: =AB4 | AC20: ='Revenue Forecast'!AC6 -> 48 | AD20: ='Revenue Forecast'!AD6+'Revenue Forecast'!AC22 -> 101 | AE20: ='Revenue Forecast'!AE6+'Revenue Forecast'!AD22 -> 159 | AF20: ='Revenue Forecast'!AF6+'Revenue Forecast'!AE22 -> 223 | AG20: ='Revenue Forecast'!AG6+'Revenue Forecast'!AF22 -> 293 | AH20: ='Revenue Forecast'!AH6+'Revenue Forecast'!AG22 -> 369 | AI20: ='Revenue Forecast'!AI6+'Revenue Forecast'!AH22 -> 452 | AJ20: ='Revenue Forecast'!AJ6+'Revenue Forecast'!AI22 -> 543 | AK20: ='Revenue Forecast'!AK6+'Revenue Forecast'!AJ22 -> 643 | ... AZ20: ='Revenue Forecast'!AZ6+'Revenue Forecast'!AY22 -> 4005 | BB20: =SUM(E20:P20) -> 0 | BC20: =SUM(Q20:AB20) -> 0 | BD20: =AN20 -> 1005 | BE20: =AZ20 -> 4005 | BF20: ='Revenue Forecast'!BF22 -> 5500
B21: Installed base (Mini) | D21: # | Q21: =Q10 | R21: =R10 | S21: =S10 | T21: =T10 | U21: =U10 | V21: =V10 | W21: =W10 | X21: =X10 | ... AB21: =AB10 | AC21: ='Revenue Forecast'!AC12 -> 20 | AD21: ='Revenue Forecast'!AD12+'Revenue Forecast'!AC23 -> 43 | AE21: ='Revenue Forecast'!AE12+'Revenue Forecast'!AD23 -> 69 | AF21: ='Revenue Forecast'!AF12+'Revenue Forecast'!AE23 -> 98 | AG21: ='Revenue Forecast'!AG12+'Revenue Forecast'!AF23 -> 130 | AH21: ='Revenue Forecast'!AH12+'Revenue Forecast'!AG23 -> 166 | AI21: ='Revenue Forecast'!AI12+'Revenue Forecast'!AH23 -> 207 | AJ21: ='Revenue Forecast'!AJ12+'Revenue Forecast'!AI23 -> 253 | AK21: ='Revenue Forecast'!AK12+'Revenue Forecast'!AJ23 -> 304 | ... AZ21: ='Revenue Forecast'!AZ12+'Revenue Forecast'!AY23 -> 2500 | BB21: =SUM(E21:P21) -> 0 | BC21: =SUM(Q21:AB21) -> 0 | BD21: =AN21 -> 500 | BE21: =AZ21 -> 2500 | BF21: ='Revenue Forecast'!BF23 -> 4500
B22: Total Service Revenue | D22: € | Q22: ='Revenue Forecast'!Q34*SUMPRODUCT(Assumptions!$E$126:$E$127,Assumptions!$G$126:$G$127)+E22 -> 0 | R22: ='Revenue Forecast'!R34*SUMPRODUCT(Assumptions!$E$126:$E$127,Assumptions!$G$126:$G$127)+F22 -> 0 | S22: ='Revenue Forecast'!S34*SUMPRODUCT(Assumptions!$E$126:$E$127,Assumptions!$G$126:$G$127)+G22 -> 0 | T22: ='Revenue Forecast'!T34*SUMPRODUCT(Assumptions!$E$126:$E$127,Assumptions!$G$126:$G$127)+H22 -> 0 | U22: ='Revenue Forecast'!U34*SUMPRODUCT(Assumptions!$E$126:$E$127,Assumptions!$G$126:$G$127)+I22 -> 0 | V22: ='Revenue Forecast'!V34*SUMPRODUCT(Assumptions!$E$126:$E$127,Assumptions!$G$126:$G$127)+J22 -> 0 | W22: ='Revenue Forecast'!W34*SUMPRODUCT(Assumptions!$E$126:$E$127,Assumptions!$G$126:$G$127)+K22 -> 0 | X22: ='Revenue Forecast'!X34*SUMPRODUCT(Assumptions!$E$126:$E$127,Assumptions!$G$126:$G$127)+L22 -> 0 | ... AZ22: ='Revenue Forecast'!AZ34*SUMPRODUCT(Assumptions!$E$126:$E$127,Assumptions!$G$126:$G$127)+AN22 -> 28302 | BB22: =SUM(E22:P22) -> 0 | BC22: =SUM(Q22:AB22) -> 0 | BD22: =sum(AC22:AN22) -> 47859 | BE22: =sum(AO22:AZ22)+BD22 -> 254718 | BF22: =(BE22*2)+BE22 -> 764154
B24: TOTAL COGS | M24: =M7+M12 -> 0 | N24: =N9+N14+N17+N22 -> 0 | O24: =O9+O14+O17+O22 -> 0 | P24: =P9+P14+P17+P22 -> 0 | Q24: =Q9+Q14+Q17+Q22 -> 0 | R24: =R9+R14+R17+R22 -> 0 | S24: =S9+S14+S17+S22 -> 0 | T24: =T9+T14+T17+T22 -> 0 | U24: =U9+U14+U17+U22 -> 0 | ... AZ24: =AZ9+AZ14+AZ17+AZ22 -> 5786676.1 | BB24: =SUM(BB7+BB12) -> 0 | BC24: =SUM(BC7+BC12) -> 0 | BD24: =sum(AC24:AN24) -> 16565413 | BE24: =sum(AO24:AZ24) -> 43068591 | BF24: =BF17+BF14+BF9+BF22 -> 72764354

Sheet OPEX
B1: Tarnoc B.V. — OPEX Forecast (€, negative = cost) | U1: Actual | V1: Projected
G2: 2025 | S2: 2026 | AE2: 2027 | AQ2: 2028
G3: 45658 | H3: 45689 | I3: 45717 | J3: 45748 | K3: 45778 | L3: 45809 | M3: 45839 | N3: 45870 | O3: 45901 | P3: 45931 | Q3: 45962 | R3: 45992 | S3: 46023 | T3: 46054 | U3: 46082 | V3: 46113 | W3: 46143 | X3: 46174 | Y3: 46204 | Z3: 46235 | AA3: 46266 | AB3: 46296 | AC3: 46327 | AD3: 46357 | AE3: 46388 | AF3: 46419 | AG3: 46447 | AH3: 46478 | AI3: 46508 | AJ3: 46539 | AK3: 46569 | AL3: 46600 | AM3: 46631 | AN3: 46661 | AO3: 46692 | AP3: 46722 | AQ3: 46753 | AR3: 46784 | AS3: 46813 | AT3: 46844 | AU3: 46874 | AV3: 46905 | AW3: 46935 | AX3: 46966 | AY3: 46997 | AZ3: 47027 | BA3: 47058 | BB3: 47088 | BD3: 2025 | BE3: 2026 | BF3: 2027 | BG3: 2028 | BH3: 2029
B5: PERSONNEL
B6: R&D | D6: € | O6: =Personnel!Q49 -> 47500 | P6: =Personnel!R49 -> 47500 | Q6: =Personnel!S49 -> 47500 | R6: =Personnel!T49 -> 47500 | S6: =Personnel!U49 -> 50700 | T6: =Personnel!V49 -> 50700 | U6: =Personnel!W49 -> 50700 | V6: =Personnel!X49 -> 50700 | ... BB6: =Personnel!BD49 -> 110364.77 | BD6: =SUM(G6:R6) -> 190000 | BE6: =SUM(S6:AD6) -> 705160 | BF6: =SUM(AE6:AP6) -> 1186575.2 | BG6: =SUM(AQ6:BB6) -> 1314001.2 | BH6: =BG6*('Financial Statements'!$BE$7/'Financial Statements'!$BD$7)^0.5 -> 2270248.3
B7: S&M | D7: € | O7: =Personnel!Q50 -> 0 | P7: =Personnel!R50 -> 0 | Q7: =Personnel!S50 -> 0 | R7: =Personnel!T50 -> 0 | S7: =Personnel!U50 -> 0 | T7: =Personnel!V50 -> 10800 | U7: =Personnel!W50 -> 10800 | V7: =Personnel!X50 -> 10800 | ... BB7: =Personnel!BD50 -> 53176.32 | BD7: =SUM(G7:R7) -> 0 | BE7: =SUM(S7:AD7) -> 183300 | BF7: =SUM(AE7:AP7) -> 331128 | BG7: =SUM(AQ7:BB7) -> 620118.24 | BH7: =BG7*('Financial Statements'!$BE$7/'Financial Statements'!$BD$7)^0.5 -> 1071401.1
B8: G&A | D8: € | O8: =Personnel!Q51 -> 11500 | P8: =Personnel!R51 -> 11500 | Q8: =Personnel!S51 -> 11500 | R8: =Personnel!T51 -> 11500 | S8: =Personnel!U51 -> 11820 | T8: =Personnel!V51 -> 11820 | U8: =Personnel!W51 -> 11820 | V8: =Personnel!X51 -> 11820 | ... BB8: =Personnel!BD51 -> 55445.088 | BD8: =SUM(G8:R8) -> 46000 | BE8: =SUM(S8:AD8) -> 222060 | BF8: =SUM(AE8:AP8) -> 520843.2 | BG8: =SUM(AQ8:BB8) -> 645010.66 | BH8: =BG8*('Financial Statements'!$BE$7/'Financial Statements'!$BD$7)^0.2 -> 802708.62
B9: Total Personnel | D9: € | G9: =SUM(G6:G8) -> 0 | H9: =SUM(H6:H8) -> 0 | I9: =SUM(I6:I8) -> 0 | J9: =SUM(J6:J8) -> 0 | K9: =SUM(K6:K8) -> 0 | L9: =SUM(L6:L8) -> 0 | M9: =SUM(M6:M8) -> 0 | N9: =SUM(N6:N8) -> 0 | O9: =sum(O6:O8) -> 59000 | P9: =sum(P6:P8) -> 59000 | Q9: =sum(Q6:Q8) -> 59000 | R9: =sum(R6:R8) -> 59000 | S9: =sum(S6:S8) -> 62520 | T9: =sum(T6:T8) -> 73320 | U9: =sum(U6:U8) -> 73320 | V9: =sum(V6:V8) -> 73320 | ... BB9: =sum(BB6:BB8) -> 218986.18 | BD9: =SUM(G9:R9) -> 236000 | BE9: =SUM(S9:AD9) -> 1110520 | BF9: =SUM(AE9:AP9) -> 2038546.4 | BG9: =SUM(AQ9:BB9) -> 2579130.1 | BH9: =sum(BH6:BH8) -> 4144358.1
B11: NON-PERSONNEL
B13: R&D COSTS
B14: Kicker Development Cost | D14: € | R14: =Assumptions!E95 -> 168933 | BD14: =SUM(G14:R14) -> 168933 | BE14: =SUM(S14:AD14) -> 0 | BF14: =SUM(AE14:AP14) -> 0 | BG14: =SUM(AQ14:BB14) -> 0 | BH14: 0
B15: Ongoing Development costs | D15: € | S15: {=INDEX(Assumptions!$E$93:$I$93,MATCH(YEAR(S$3),Assumptions!$E$88:$I$88,0))} -> 10000 | T15: {=INDEX(Assumptions!$E$93:$I$93,MATCH(YEAR(T$3),Assumptions!$E$88:$I$88,0))} -> 10000 | U15: {=INDEX(Assumptions!$E$93:$I$93,MATCH(YEAR(U$3),Assumptions!$E$88:$I$88,0))} -> 10000 | V15: {=INDEX(Assumptions!$E$93:$I$93,MATCH(YEAR(V$3),Assumptions!$E$88:$I$88,0))} -> 10000 | W15: {=INDEX(Assumptions!$E$93:$I$93,MATCH(YEAR(W$3),Assumptions!$E$88:$I$88,0))} -> 10000 | X15: {=INDEX(Assumptions!$E$93:$I$93,MATCH(YEAR(X$3),Assumptions!$E$88:$I$88,0))} -> 10000 | Y15: {=INDEX(Assumptions!$E$93:$I$93,MATCH(YEAR(Y$3),Assumptions!$E$88:$I$88,0))} -> 10000 | Z15: {=INDEX(Assumptions!$E$93:$I$93,MATCH(YEAR(Z$3),Assumptions!$E$88:$I$88,0))} -> 10000 | ... BB15: {=INDEX(Assumptions!$E$93:$I$93,MATCH(YEAR(BB$3),Assumptions!$E$88:$I$88,0))} -> 16900 | BD15: =SUM(G15:R15) -> 0 | BE15: =SUM(S15:AD15) -> 120000 | BF15: =SUM(AE15:AP15) -> 156000 | BG15: =SUM(AQ15:BB15) -> 202800 | BH15: =BG15*('Financial Statements'!$BE$7/'Financial Statements'!$BD$7)^0.4 -> 314087.05
B16: Assembly partner | D16: € | AB16: =Assumptions!E98 -> 100000 | BD16: =SUM(G16:R16) -> 0 | BE16: =SUM(S16:AC16) -> 100000 | BF16: =SUM(AE16:AP16) -> 0 | BG16: =SUM(AQ16:BB16) -> 0
B17: Third party cost product development | D17: € | S17: {=INDEX(Assumptions!$E$94:$I$94,MATCH(YEAR(S$3),Assumptions!$E$88:$I$88,0))} -> 15000 | T17: {=INDEX(Assumptions!$E$94:$I$94,MATCH(YEAR(T$3),Assumptions!$E$88:$I$88,0))} -> 15000 | U17: {=INDEX(Assumptions!$E$94:$I$94,MATCH(YEAR(U$3),Assumptions!$E$88:$I$88,0))} -> 15000 | V17: {=INDEX(Assumptions!$E$94:$I$94,MATCH(YEAR(V$3),Assumptions!$E$88:$I$88,0))} -> 15000 | W17: {=INDEX(Assumptions!$E$94:$I$94,MATCH(YEAR(W$3),Assumptions!$E$88:$I$88,0))} -> 15000 | X17: {=INDEX(Assumptions!$E$94:$I$94,MATCH(YEAR(X$3),Assumptions!$E$88:$I$88,0))} -> 15000 | Y17: {=INDEX(Assumptions!$E$94:$I$94,MATCH(YEAR(Y$3),Assumptions!$E$88:$I$88,0))} -> 15000 | Z17: {=INDEX(Assumptions!$E$94:$I$94,MATCH(YEAR(Z$3),Assumptions!$E$88:$I$88,0))} -> 15000 | ... BB17: {=INDEX(Assumptions!$E$94:$I$94,MATCH(YEAR(BB$3),Assumptions!$E$88:$I$88,0))} -> 25350 | BD17: =SUM(G17:R17) -> 0 | BE17: =SUM(S17:AD17) -> 180000 | BF17: =SUM(AE17:AP17) -> 234000 | BG17: =SUM(AQ17:BB17) -> 304200 | BH17: =BG17*('Financial Statements'!$BE$7/'Financial Statements'!$BD$7)^0.4 -> 471130.57
B18: Tooling Fisher (result: 2%-3%) | D18: € | AC18: =Assumptions!E99 -> 45000 | BD18: =SUM(G18:R18) -> 0 | BE18: =SUM(S18:AC18) -> 45000 | BF18: =SUM(AE18:AP18) -> 0 | BG18: =SUM(AQ18:BB18) -> 0 | BH18: 0
B19: Total R&D | R19: =R14+R15+R16 -> 168933 | S19: =sum(S14:S18) -> 25000 | T19: =sum(T14:T18) -> 25000 | U19: =sum(U14:U18) -> 25000 | V19: =sum(V14:V18) -> 25000 | W19: =sum(W14:W18) -> 25000 | X19: =sum(X14:X18) -> 25000 | Y19: =sum(Y14:Y18) -> 25000 | Z19: =sum(Z14:Z18) -> 25000 | ... BB19: =sum(BB14:BB18) -> 42250 | BD19: =SUM(G19:R19) -> 168933 | BE19: =SUM(S19:AD19) -> 445000 | BF19: =SUM(AE19:AP19) -> 390000 | BG19: =SUM(AQ19:BB19) -> 507000 | BH19: =sum(BH14:BH18) -> 785217.62
BE20: =BE19/BD19-1 -> 1.6341804 | BF20: =BF19/BE19-1 -> -0.12359551 | BG20: =BG19/BF19-1 -> 0.3 | BH20: =BH19/BG19-1 -> 0.5487527
B21: SALES & MARKETING
B22: Baseline Sales & Marketting | S22: {=INDEX(Assumptions!$E$91:$I$91,MATCH(YEAR(S$3),Assumptions!$E$88:$I$88,0))} -> 14000 | T22: {=INDEX(Assumptions!$E$91:$I$91,MATCH(YEAR(T$3),Assumptions!$E$88:$I$88,0))} -> 14000 | U22: {=INDEX(Assumptions!$E$91:$I$91,MATCH(YEAR(U$3),Assumptions!$E$88:$I$88,0))} -> 14000 | V22: {=INDEX(Assumptions!$E$91:$I$91,MATCH(YEAR(V$3),Assumptions!$E$88:$I$88,0))} -> 14000 | W22: {=INDEX(Assumptions!$E$91:$I$91,MATCH(YEAR(W$3),Assumptions!$E$88:$I$88,0))} -> 14000 | X22: {=INDEX(Assumptions!$E$91:$I$91,MATCH(YEAR(X$3),Assumptions!$E$88:$I$88,0))} -> 14000 | Y22: {=INDEX(Assumptions!$E$91:$I$91,MATCH(YEAR(Y$3),Assumptions!$E$88:$I$88,0))} -> 14000 | Z22: {=INDEX(Assumptions!$E$91:$I$91,MATCH(YEAR(Z$3),Assumptions!$E$88:$I$88,0))} -> 14000 | ... BB22: {=INDEX(Assumptions!$E$91:$I$91,MATCH(YEAR(BB$3),Assumptions!$E$88:$I$88,0))} -> 23660 | BD22: =SUM(G22:R22) -> 0 | BE22: =SUM(S22:AD22) -> 168000 | BF22: =SUM(AE22:AP22) -> 218400 | BG22: =SUM(AQ22:BB22) -> 283920 | BH22: =BG22*('Financial Statements'!$BE$7/'Financial Statements'!$BD$7)^0.5 -> 490539.05
B23: Sales & Marketing (3rd party) | D23: € | S23: 7000 | T23: 7000 | U23: 7000 | V23: 7000 | W23: 7000 | X23: 7000 | Y23: 7000 | Z23: 7000 | AA23: 7000 | AB23: 10000 | AC23: 10000 | AD23: 10000 | AE23: =('Revenue Forecast'!AC6+'Revenue Forecast'!AC12)*VLOOKUP('Revenue Forecast'!AC33,Assumptions!$G$103:$H$110,2,TRUE) -> 40800 | AF23: =('Revenue Forecast'!AD6+'Revenue Forecast'!AD12)*VLOOKUP('Revenue Forecast'!AD33,Assumptions!$G$103:$H$110,2,TRUE) -> 45600 | AG23: =('Revenue Forecast'!AE6+'Revenue Forecast'!AE12)*VLOOKUP('Revenue Forecast'!AE33,Assumptions!$G$103:$H$110,2,TRUE) -> 50400 | AH23: =('Revenue Forecast'!AF6+'Revenue Forecast'!AF12)*VLOOKUP('Revenue Forecast'!AF33,Assumptions!$G$103:$H$110,2,TRUE) -> 55800 | AI23: =('Revenue Forecast'!AG6+'Revenue Forecast'!AG12)*VLOOKUP('Revenue Forecast'!AG33,Assumptions!$G$103:$H$110,2,TRUE) -> 61200 | AJ23: =('Revenue Forecast'!AH6+'Revenue Forecast'!AH12)*VLOOKUP('Revenue Forecast'!AH33,Assumptions!$G$103:$H$110,2,TRUE) -> 67200 | AK23: =('Revenue Forecast'!AI6+'Revenue Forecast'!AI12)*VLOOKUP('Revenue Forecast'!AI33,Assumptions!$G$103:$H$110,2,TRUE) -> 74400 | AL23: =('Revenue Forecast'!AJ6+'Revenue Forecast'!AJ12)*VLOOKUP('Revenue Forecast'!AJ33,Assumptions!$G$103:$H$110,2,TRUE) -> 82200 | ... BB23: =('Revenue Forecast'!AZ6+'Revenue Forecast'!AZ12)*VLOOKUP('Revenue Forecast'!AZ33,Assumptions!$G$103:$H$110,2,TRUE) -> 168345.6 | BD23: =SUM(G23:R23) -> 0 | BE23: =SUM(S23:AD23) -> 93000 | BF23: =SUM(AE23:AP23) -> 817920 | BG23: =SUM(AQ23:BB23) -> 1600896 | BH23: =('Revenue Forecast'!BF6+'Revenue Forecast'!BF12)*VLOOKUP('Revenue Forecast'!BF33,Assumptions!$G$103:$H$110,2,TRUE) -> 2457600
B24: Customer journey (third party) | D24: € | R24: =Assumptions!$E$96 -> 10000 | X24: =Assumptions!E96 -> 10000 | BD24: =SUM(G24:R24) -> 10000 | BE24: =SUM(T24:AC24) -> 10000 | BF24: =SUM(AE24:AP24) -> 0 | BG24: =SUM(AQ24:BB24) -> 0 | BH24: =BG24*('Financial Statements'!$BE$7/'Financial Statements'!$BD$7)^0.5 -> 0
B25: Branding + Website (third party cost) | D25: € | R25: =Assumptions!$E$97 -> 10000 | W25: =Assumptions!E97 -> 10000 | BD25: =SUM(G25:R25) -> 10000 | BE25: =SUM(S25:AH25) -> 10000 | BF25: =SUM(AE25:AP25) -> 0 | BG25: =SUM(AQ25:BB25) -> 0 | BH25: =BG25*('Financial Statements'!$BE$7/'Financial Statements'!$BD$7)^0.5 -> 0
B26: Total S&M | G26: =SUM(G23:G25) -> 0 | H26: =SUM(H23:H25) -> 0 | I26: =SUM(I23:I25) -> 0 | J26: =SUM(J23:J25) -> 0 | K26: =SUM(K23:K25) -> 0 | L26: =SUM(L23:L25) -> 0 | M26: =SUM(M23:M25) -> 0 | N26: =SUM(N23:N25) -> 0 | ... R26: =SUM(R23:R25) -> 20000 | S26: =sum(S22:S25) -> 21000 | T26: =sum(T22:T25) -> 21000 | U26: =sum(U22:U25) -> 21000 | V26: =sum(V22:V25) -> 21000 | W26: =sum(W22:W25) -> 31000 | X26: =sum(X22:X25) -> 31000 | Y26: =sum(Y22:Y25) -> 21000 | Z26: =sum(Z22:Z25) -> 21000 | ... BB26: =sum(BB22:BB25) -> 192005.6 | BD26: =SUM(G26:R26) -> 20000 | BE26: =SUM(S26:AD26) -> 281000 | BF26: =SUM(AE26:AP26) -> 1036320 | BG26: =SUM(AQ26:BB26) -> 1884816 | BH26: =sum(BH22:BH25) -> 2948139
BE27: =BE26/BD26-1 -> 13.05 | BF27: =BF26/BE26-1 -> 2.6879715 | BG27: =BG26/BF26-1 -> 0.81875868 | BH27: =BH26/BG26-1 -> 0.56415218
B28: G&A (NON-LABOUR)
B29: Office rent (part of General) | D29: € | G29: =Assumptions!$E$89 -> 5000 | H29: =Assumptions!$E$89 -> 5000 | I29: =Assumptions!$E$89 -> 5000 | J29: =Assumptions!$E$89 -> 5000 | K29: =Assumptions!$E$89 -> 5000 | L29: =Assumptions!$E$89 -> 5000 | M29: =Assumptions!$E$89 -> 5000 | N29: =Assumptions!$E$89 -> 5000 | ... R29: =Assumptions!$E$89 -> 5000 | S29: {=INDEX(Assumptions!$E$89:$I$89,MATCH(YEAR(S$3),Assumptions!$E$88:$I$88,0))} -> 5000 | T29: {=INDEX(Assumptions!$E$89:$I$89,MATCH(YEAR(T$3),Assumptions!$E$88:$I$88,0))} -> 5000 | U29: {=INDEX(Assumptions!$E$89:$I$89,MATCH(YEAR(U$3),Assumptions!$E$88:$I$88,0))} -> 5000 | V29: {=INDEX(Assumptions!$E$89:$I$89,MATCH(YEAR(V$3),Assumptions!$E$88:$I$88,0))} -> 5000 | W29: {=INDEX(Assumptions!$E$89:$I$89,MATCH(YEAR(W$3),Assumptions!$E$88:$I$88,0))} -> 5000 | X29: {=INDEX(Assumptions!$E$89:$I$89,MATCH(YEAR(X$3),Assumptions!$E$88:$I$88,0))} -> 5000 | Y29: {=INDEX(Assumptions!$E$89:$I$89,MATCH(YEAR(Y$3),Assumptions!$E$88:$I$88,0))} -> 5000 | Z29: {=INDEX(Assumptions!$E$89:$I$89,MATCH(YEAR(Z$3),Assumptions!$E$88:$I$88,0))} -> 5000 | ... BB29: {=INDEX(Assumptions!$E$89:$I$89,MATCH(YEAR(BB$3),Assumptions!$E$88:$I$88,0))} -> 8450 | BD29: =SUM(G29:R29) -> 60000 | BE29: =SUM(S29:AD29) -> 60000 | BF29: =SUM(AE29:AP29) -> 78000 | BG29: =SUM(AQ29:BB29) -> 101400 | BH29: =BG29*('Financial Statements'!$BE$7/'Financial Statements'!$BD$7)^0.2 -> 126191.18
B30: Other General | D30: € | G30: =Assumptions!$E$90 -> 7000 | H30: =Assumptions!$E$90 -> 7000 | I30: =Assumptions!$E$90 -> 7000 | J30: =Assumptions!$E$90 -> 7000 | K30: =Assumptions!$E$90 -> 7000 | L30: =Assumptions!$E$90 -> 7000 | M30: =Assumptions!$E$90 -> 7000 | N30: =Assumptions!$E$90 -> 7000 | ... R30: =Assumptions!$E$90 -> 7000 | S30: {=INDEX(Assumptions!$E$90:$I$90,MATCH(YEAR(S$3),Assumptions!$E$88:$I$88,0))} -> 7000 | T30: {=INDEX(Assumptions!$E$90:$I$90,MATCH(YEAR(T$3),Assumptions!$E$88:$I$88,0))} -> 7000 | U30: {=INDEX(Assumptions!$E$90:$I$90,MATCH(YEAR(U$3),Assumptions!$E$88:$I$88,0))} -> 7000 | V30: {=INDEX(Assumptions!$E$90:$I$90,MATCH(YEAR(V$3),Assumptions!$E$88:$I$88,0))} -> 7000 | W30: {=INDEX(Assumptions!$E$90:$I$90,MATCH(YEAR(W$3),Assumptions!$E$88:$I$88,0))} -> 7000 | X30: {=INDEX(Assumptions!$E$90:$I$90,MATCH(YEAR(X$3),Assumptions!$E$88:$I$88,0))} -> 7000 | Y30: {=INDEX(Assumptions!$E$90:$I$90,MATCH(YEAR(Y$3),Assumptions!$E$88:$I$88,0))} -> 7000 | Z30: {=INDEX(Assumptions!$E$90:$I$90,MATCH(YEAR(Z$3),Assumptions!$E$88:$I$88,0))} -> 7000 | ... BB30: {=INDEX(Assumptions!$E$90:$I$90,MATCH(YEAR(BB$3),Assumptions!$E$88:$I$88,0))} -> 11830 | BD30: =SUM(G30:R30) -> 84000 | BE30: =SUM(S30:AD30) -> 84000 | BF30: =SUM(AE30:AP30) -> 109200 | BG30: =SUM(AQ30:BB30) -> 141960 | BH30: =BG30*('Financial Statements'!$BE$7/'Financial Statements'!$BD$7)^0.2 -> 176667.65
B31: Finance & Legal etc. | D31: € | G31: =Assumptions!$E$92 -> 8000 | H31: =Assumptions!$E$92 -> 8000 | I31: =Assumptions!$E$92 -> 8000 | J31: =Assumptions!$E$92 -> 8000 | K31: =Assumptions!$E$92 -> 8000 | L31: =Assumptions!$E$92 -> 8000 | M31: =Assumptions!$E$92 -> 8000 | N31: =Assumptions!$E$92 -> 8000 | ... R31: =Assumptions!$E$92 -> 8000 | S31: {=INDEX(Assumptions!$E$92:$I$92,MATCH(YEAR(S$3),Assumptions!$E$88:$I$88,0))} -> 8000 | T31: {=INDEX(Assumptions!$E$92:$I$92,MATCH(YEAR(T$3),Assumptions!$E$88:$I$88,0))} -> 8000 | U31: {=INDEX(Assumptions!$E$92:$I$92,MATCH(YEAR(U$3),Assumptions!$E$88:$I$88,0))} -> 8000 | V31: {=INDEX(Assumptions!$E$92:$I$92,MATCH(YEAR(V$3),Assumptions!$E$88:$I$88,0))} -> 8000 | W31: {=INDEX(Assumptions!$E$92:$I$92,MATCH(YEAR(W$3),Assumptions!$E$88:$I$88,0))} -> 8000 | X31: {=INDEX(Assumptions!$E$92:$I$92,MATCH(YEAR(X$3),Assumptions!$E$88:$I$88,0))} -> 8000 | Y31: {=INDEX(Assumptions!$E$92:$I$92,MATCH(YEAR(Y$3),Assumptions!$E$88:$I$88,0))} -> 8000 | Z31: {=INDEX(Assumptions!$E$92:$I$92,MATCH(YEAR(Z$3),Assumptions!$E$88:$I$88,0))} -> 8000 | ... BB31: {=INDEX(Assumptions!$E$92:$I$92,MATCH(YEAR(BB$3),Assumptions!$E$88:$I$88,0))} -> 13520 | BD31: =SUM(G31:R31) -> 96000 | BE31: =SUM(S31:AD31) -> 96000 | BF31: =SUM(AE31:AP31) -> 124800 | BG31: =SUM(AQ31:BB31) -> 162240 | BH31: =BG31*('Financial Statements'!$BE$7/'Financial Statements'!$BD$7)^0.2 -> 201905.88
B32: Total G&A | S32: =sum(S29:S31) -> 20000 | T32: =sum(T29:T31) -> 20000 | U32: =sum(U29:U31) -> 20000 | V32: =sum(V29:V31) -> 20000 | W32: =sum(W29:W31) -> 20000 | X32: =sum(X29:X31) -> 20000 | Y32: =sum(Y29:Y31) -> 20000 | Z32: =sum(Z29:Z31) -> 20000 | ... BB32: =sum(BB29:BB31) -> 33800 | BD32: =SUM(G32:R32) -> 0 | BE32: =SUM(S32:AD32) -> 240000 | BF32: =SUM(AE32:AP32) -> 312000 | BG32: =SUM(AQ32:BB32) -> 405600 | BH32: =sum(BH29:BH31) -> 504764.71
B34: Total non-personnell | D34: € | G34: =G32+G26+G19 -> 0 | H34: =H32+H26+H19 -> 0 | I34: =I32+I26+I19 -> 0 | J34: =J32+J26+J19 -> 0 | K34: =K32+K26+K19 -> 0 | L34: =L32+L26+L19 -> 0 | M34: =M32+M26+M19 -> 0 | N34: =N32+N26+N19 -> 0 | ... BB34: =BB32+BB26+BB19 -> 268055.6 | BD34: =SUM(G34:R34) -> 188933 | BE34: =SUM(S34:AD34) -> 966000 | BF34: =SUM(AE34:AP34) -> 1738320 | BG34: =SUM(AQ34:BB34) -> 2797416 | BH34: =BH32+BH26+BH19 -> 4238121.4
B36: TOTAL OPEX | D36: € | G36: =G34+G9 -> 0 | H36: =H34+H9 -> 0 | I36: =I34+I9 -> 0 | J36: =J34+J9 -> 0 | K36: =K34+K9 -> 0 | L36: =L34+L9 -> 0 | M36: =M34+M9 -> 0 | N36: =N34+N9 -> 0 | ... BB36: =BB34+BB9 -> 487041.78 | BD36: =SUM(G36:R36) -> 424933 | BE36: =SUM(S36:AD36) -> 2076520 | BF36: =SUM(AE36:AP36) -> 3776866.4 | BG36: =SUM(AQ36:BB36) -> 5376546.1 | BH36: =BH34+BH9 -> 8382479.5
B38: Total R&D | D38: € | G38: =G19+G6 -> 0 | H38: =H19+H6 -> 0 | I38: =I19+I6 -> 0 | J38: =J19+J6 -> 0 | K38: =K19+K6 -> 0 | L38: =L19+L6 -> 0 | M38: =M19+M6 -> 0 | N38: =N19+N6 -> 0 | ... BB38: =BB19+BB6 -> 152614.77 | BD38: =BD19+BD6 -> 358933 | BE38: =BE19+BE6 -> 1150160 | BF38: =BF19+BF6 -> 1576575.2 | BG38: =BG19+BG6 -> 1821001.2 | BH38: =BH19+BH6 -> 3055465.9
B39: Total S&M | D39: € | G39: =G26+G7 -> 0 | H39: =H26+H7 -> 0 | I39: =I26+I7 -> 0 | J39: =J26+J7 -> 0 | K39: =K26+K7 -> 0 | L39: =L26+L7 -> 0 | M39: =M26+M7 -> 0 | N39: =N26+N7 -> 0 | ... BB39: =BB26+BB7 -> 245181.92 | BD39: =BD26+BD7 -> 20000 | BE39: =BE26+BE7 -> 464300 | BF39: =BF26+BF7 -> 1367448 | BG39: =BG26+BG7 -> 2504934.2 | BH39: =BH26+BH7 -> 4019540.2
B40: Total G&A | D40: € | G40: =G32+G8 -> 0 | H40: =H32+H8 -> 0 | I40: =I32+I8 -> 0 | J40: =J32+J8 -> 0 | K40: =K32+K8 -> 0 | L40: =L32+L8 -> 0 | M40: =M32+M8 -> 0 | N40: =N32+N8 -> 0 | ... BB40: =BB32+BB8 -> 89245.088 | BD40: =BD32+BD8 -> 46000 | BE40: =BE32+BE8 -> 462060 | BF40: =BF32+BF8 -> 832843.2 | BG40: =BG32+BG8 -> 1050610.7 | BH40: =BH32+BH8 -> 1307473.3
B41: R&D % of Total OPEX | S41: =S38/S$36 -> 0.58901338 | T41: =T38/T$36 -> 0.54335343 | U41: =U38/U$36 -> 0.54335343 | V41: =V38/V$36 -> 0.54335343 | W41: =W38/W$36 -> 0.50696491 | X41: =X38/X$36 -> 0.50696491 | Y41: =Y38/Y$36 -> 0.56815096 | Z41: =Z38/Z$36 -> 0.5235816 | ... BB41: =BB38/BB$36 -> 0.31335047 | BD41: =BD38/BD$36 -> 0.8446814 | BE41: =BE38/BE$36 -> 0.55388824 | BF41: =BF38/BF$36 -> 0.41742943 | BG41: =BG38/BG$36 -> 0.3386935 | BH41: =BH38/BH$36 -> 0.36450623
B42: S&M % of Total OPEX | S42: =S39/S$36 -> 0.16339869 | T42: =T39/T$36 -> 0.22825151 | U42: =U39/U$36 -> 0.22825151 | V42: =V39/V$36 -> 0.22825151 | W42: =W39/W$36 -> 0.27993571 | X42: =X39/X$36 -> 0.27993571 | Y42: =Y39/Y$36 -> 0.21585664 | Z42: =Z39/Z$36 -> 0.23815083 | ... BB42: =BB39/BB$36 -> 0.50341045 | BD42: =BD39/BD$36 -> 0.047066243 | BE42: =BE39/BE$36 -> 0.22359525 | BF42: =BF39/BF$36 -> 0.36205888 | BG42: =BG39/BG$36 -> 0.46590026 | BH42: =BH39/BH$36 -> 0.47951685
B43: G&A % of Total OPEX | S43: =S40/S$36 -> 0.24758792 | T43: =T40/T$36 -> 0.22839506 | U43: =U40/U$36 -> 0.22839506 | V43: =V40/V$36 -> 0.22839506 | W43: =W40/W$36 -> 0.21309938 | X43: =X40/X$36 -> 0.21309938 | Y43: =Y40/Y$36 -> 0.2159924 | Z43: =Z40/Z$36 -> 0.23826757 | ... BB43: =BB40/BB$36 -> 0.18323908 | BD43: =BD40/BD$36 -> 0.10825236 | BE43: =BE40/BE$36 -> 0.22251652 | BF43: =BF40/BF$36 -> 0.22051169 | BG43: =BG40/BG$36 -> 0.19540624 | BH43: =BH40/BH$36 -> 0.15597692

Sheet Personnel
B1: PERSONNEL — Monthly Employer Cost (€)
A2: # | B2: Name | C2: Dept | D2: Role | E2: Type | F2: Start | G2: End | H2: Monthly Cost (€) | I2: 45658 | J2: 45689 | K2: 45717 | L2: 45748 | M2: 45778 | N2: 45809 | O2: 45839 | P2: 45870 | Q2: 45901 | R2: 45931 | S2: 45962 | T2: 45992 | U2: 46023 | V2: 46054 | W2: 46082 | X2: 46113 | Y2: 46143 | Z2: 46174 | AA2: 46204 | AB2: 46235 | AC2: 46266 | AD2: 46296 | AE2: 46327 | AF2: 46357 | AG2: 46388 | AH2: 46419 | AI2: 46447 | AJ2: 46478 | AK2: 46508 | AL2: 46539 | AM2: 46569 | AN2: 46600 | AO2: 46631 | AP2: 46661 | AQ2: 46692 | AR2: 46722 | AS2: 46753 | AT2: 46784 | AU2: 46813 | AV2: 46844 | AW2: 46874 | AX2: 46905 | AY2: 46935 | AZ2: 46966 | BA2: 46997 | BB2: 47027 | BC2: 47058 | BD2: 47088 | BE2: 47119 | BF2: 47150 | BG2: 47178 | BH2: 47209 | BI2: 47239 | BJ2: 47270 | BK2: 47300 | BL2: 47331 | BM2: 47362 | BN2: 47392 | BO2: 47423 | BP2: 47453
A3: 1 | B3: R&D Engineer | C3: R&D | D3: Field Engineer | E3: Current | F3: 45901 | H3: 5500 | I3: =IF(AND(F3<=DATE(2025,1,1),OR(G3="",G3>=DATE(2025,1,1))),H3*(1+Assumptions!$C$7)^0,0) -> 0 | J3: =IF(AND(F3<=DATE(2025,2,1),OR(G3="",G3>=DATE(2025,2,1))),H3*(1+Assumptions!$C$7)^0,0) -> 0 | K3: =IF(AND(F3<=DATE(2025,3,1),OR(G3="",G3>=DATE(2025,3,1))),H3*(1+Assumptions!$C$7)^0,0) -> 0 | L3: =IF(AND(F3<=DATE(2025,4,1),OR(G3="",G3>=DATE(2025,4,1))),H3*(1+Assumptions!$C$7)^0,0) -> 0 | M3: =IF(AND(F3<=DATE(2025,5,1),OR(G3="",G3>=DATE(2025,5,1))),H3*(1+Assumptions!$C$7)^0,0) -> 0 | N3: =IF(AND(F3<=DATE(2025,6,1),OR(G3="",G3>=DATE(2025,6,1))),H3*(1+Assumptions!$C$7)^0,0) -> 0 | O3: =IF(AND(F3<=DATE(2025,7,1),OR(G3="",G3>=DATE(2025,7,1))),H3*(1+Assumptions!$C$7)^0,0) -> 0 | P3: =IF(AND(F3<=DATE(2025,8,1),OR(G3="",G3>=DATE(2025,8,1))),H3*(1+Assumptions!$C$7)^0,0) -> 0 | Q3: =IF(AND(F3<=DATE(2025,9,1),OR(G3="",G3>=DATE(2025,9,1))),H3*(1+Assumptions!$C$7)^0,0) -> 5500 | R3: =IF(AND(F3<=DATE(2025,10,1),OR(G3="",G3>=DATE(2025,10,1))),H3*(1+Assumptions!$C$7)^0,0) -> 5500 | S3: =IF(AND(F3<=DATE(2025,11,1),OR(G3="",G3>=DATE(2025,11,1))),H3*(1+Assumptions!$C$7)^0,0) -> 5500 | T3: =IF(AND(F3<=DATE(2025,12,1),OR(G3="",G3>=DATE(2025,12,1))),H3*(1+Assumptions!$C$7)^0,0) -> 5500 | U3: =IF(AND(F3<=DATE(2026,1,1),OR(G3="",G3>=DATE(2026,1,1))),H3*(1+Assumptions!$C$7)^1,0) -> 5940 | V3: =IF(AND(F3<=DATE(2026,2,1),OR(G3="",G3>=DATE(2026,2,1))),H3*(1+Assumptions!$C$7)^1,0) -> 5940 | W3: =IF(AND(F3<=DATE(2026,3,1),OR(G3="",G3>=DATE(2026,3,1))),H3*(1+Assumptions!$C$7)^1,0) -> 5940 | X3: =IF(AND(F3<=DATE(2026,4,1),OR(G3="",G3>=DATE(2026,4,1))),H3*(1+Assumptions!$C$7)^1,0) -> 5940 | Y3: =IF(AND(F3<=DATE(2026,5,1),OR(G3="",G3>=DATE(2026,5,1))),H3*(1+Assumptions!$C$7)^1,0) -> 5940 | Z3: =IF(AND(F3<=DATE(2026,6,1),OR(G3="",G3>=DATE(2026,6,1))),H3*(1+Assumptions!$C$7)^1,0) -> 5940 | AA3: =IF(AND(F3<=DATE(2026,7,1),OR(G3="",G3>=DATE(2026,7,1))),H3*(1+Assumptions!$C$7)^1,0) -> 5940 | AB3: =IF(AND(F3<=DATE(2026,8,1),OR(G3="",G3>=DATE(2026,8,1))),H3*(1+Assumptions!$C$7)^1,0) -> 5940 | AC3: =IF(AND(F3<=DATE(2026,9,1),OR(G3="",G3>=DATE(2026,9,1))),H3*(1+Assumptions!$C$7)^1,0) -> 5940 | AD3: =IF(AND(F3<=DATE(2026,10,1),OR(G3="",G3>=DATE(2026,10,1))),H3*(1+Assumptions!$C$7)^1,0) -> 5940 | AE3: =IF(AND(F3<=DATE(2026,11,1),OR(G3="",G3>=DATE(2026,11,1))),H3*(1+Assumptions!$C$7)^1,0) -> 5940 | AF3: =IF(AND(F3<=DATE(2026,12,1),OR(G3="",G3>=DATE(2026,12,1))),H3*(1+Assumptions!$C$7)^1,0) -> 5940 | AG3: =IF(AND(F3<=DATE(2027,1,1),OR(G3="",G3>=DATE(2027,1,1))),H3*(1+Assumptions!$C$7)^2,0) -> 6415.2 | AH3: =IF(AND(F3<=DATE(2027,2,1),OR(G3="",G3>=DATE(2027,2,1))),H3*(1+Assumptions!$C$7)^2,0) -> 6415.2 | AI3: =IF(AND(F3<=DATE(2027,3,1),OR(G3="",G3>=DATE(2027,3,1))),H3*(1+Assumptions!$C$7)^2,0) -> 6415.2 | AJ3: =IF(AND(F3<=DATE(2027,4,1),OR(G3="",G3>=DATE(2027,4,1))),H3*(1+Assumptions!$C$7)^2,0) -> 6415.2 | AK3: =IF(AND(F3<=DATE(2027,5,1),OR(G3="",G3>=DATE(2027,5,1))),H3*(1+Assumptions!$C$7)^2,0) -> 6415.2 | AL3: =IF(AND(F3<=DATE(2027,6,1),OR(G3="",G3>=DATE(2027,6,1))),H3*(1+Assumptions!$C$7)^2,0) -> 6415.2 | AM3: =IF(AND(F3<=DATE(2027,7,1),OR(G3="",G3>=DATE(2027,7,1))),H3*(1+Assumptions!$C$7)^2,0) -> 6415.2 | AN3: =IF(AND(F3<=DATE(2027,8,1),OR(G3="",G3>=DATE(2027,8,1))),H3*(1+Assumptions!$C$7)^2,0) -> 6415.2 | AO3: =IF(AND(F3<=DATE(2027,9,1),OR(G3="",G3>=DATE(2027,9,1))),H3*(1+Assumptions!$C$7)^2,0) -> 6415.2 | AP3: =IF(AND(F3<=DATE(2027,10,1),OR(G3="",G3>=DATE(2027,10,1))),H3*(1+Assumptions!$C$7)^2,0) -> 6415.2 | AQ3: =IF(AND(F3<=DATE(2027,11,1),OR(G3="",G3>=DATE(2027,11,1))),H3*(1+Assumptions!$C$7)^2,0) -> 6415.2 | AR3: =IF(AND(F3<=DATE(2027,12,1),OR(G3="",G3>=DATE(2027,12,1))),H3*(1+Assumptions!$C$7)^2,0) -> 6415.2 | AS3: =IF(AND(F3<=DATE(2028,1,1),OR(G3="",G3>=DATE(2028,1,1))),H3*(1+Assumptions!$C$7)^3,0) -> 6928.416 | AT3: =IF(AND(F3<=DATE(2028,2,1),OR(G3="",G3>=DATE(2028,2,1))),H3*(1+Assumptions!$C$7)^3,0) -> 6928.416 | AU3: =IF(AND(F3<=DATE(2028,3,1),OR(G3="",G3>=DATE(2028,3,1))),H3*(1+Assumptions!$C$7)^3,0) -> 6928.416 | AV3: =IF(AND(F3<=DATE(2028,4,1),OR(G3="",G3>=DATE(2028,4,1))),H3*(1+Assumptions!$C$7)^3,0) -> 6928.416 | AW3: =IF(AND(F3<=DATE(2028,5,1),OR(G3="",G3>=DATE(2028,5,1))),H3*(1+Assumptions!$C$7)^3,0) -> 6928.416 | AX3: =IF(AND(F3<=DATE(2028,6,1),OR(G3="",G3>=DATE(2028,6,1))),H3*(1+Assumptions!$C$7)^3,0) -> 6928.416 | AY3: =IF(AND(F3<=DATE(2028,7,1),OR(G3="",G3>=DATE(2028,7,1))),H3*(1+Assumptions!$C$7)^3,0) -> 6928.416 | AZ3: =IF(AND(F3<=DATE(2028,8,1),OR(G3="",G3>=DATE(2028,8,1))),H3*(1+Assumptions!$C$7)^3,0) -> 6928.416 | BA3: =IF(AND(F3<=DATE(2028,9,1),OR(G3="",G3>=DATE(2028,9,1))),H3*(1+Assumptions!$C$7)^3,0) -> 6928.416 | BB3: =IF(AND(F3<=DATE(2028,10,1),OR(G3="",G3>=DATE(2028,10,1))),H3*(1+Assumptions!$C$7)^3,0) -> 6928.416 | BC3: =IF(AND(F3<=DATE(2028,11,1),OR(G3="",G3>=DATE(2028,11,1))),H3*(1+Assumptions!$C$7)^3,0) -> 6928.416 | BD3: =IF(AND(F3<=DATE(2028,12,1),OR(G3="",G3>=DATE(2028,12,1))),H3*(1+Assumptions!$C$7)^3,0) -> 6928.416 | BE3: =IF(AND(G3<=DATE(2028,12,1),OR(H3="",H3>=DATE(2028,12,1))),I3*(1+Assumptions!$C$7)^3,0) -> 0 | BF3: =IF(AND(H3<=DATE(2028,12,1),OR(I3="",I3>=DATE(2028,12,1))),J3*(1+Assumptions!$C$7)^3,0) -> 0 | BG3: =IF(AND(I3<=DATE(2028,12,1),OR(J3="",J3>=DATE(2028,12,1))),K3*(1+Assumptions!$C$7)^3,0) -> 0 | BH3: =IF(AND(J3<=DATE(2028,12,1),OR(K3="",K3>=DATE(2028,12,1))),L3*(1+Assumptions!$C$7)^3,0) -> 0 | BI3: =IF(AND(K3<=DATE(2028,12,1),OR(L3="",L3>=DATE(2028,12,1))),M3*(1+Assumptions!$C$7)^3,0) -> 0 | BJ3: =IF(AND(L3<=DATE(2028,12,1),OR(M3="",M3>=DATE(2028,12,1))),N3*(1+Assumptions!$C$7)^3,0) -> 0 | BK3: =IF(AND(M3<=DATE(2028,12,1),OR(N3="",N3>=DATE(2028,12,1))),O3*(1+Assumptions!$C$7)^3,0) -> 0 | ... BP3: =IF(AND(R3<=DATE(2028,12,1),OR(S3="",S3>=DATE(2028,12,1))),T3*(1+Assumptions!$C$7)^3,0) -> 0
A4: 2 | B4: Project manager | C4: R&D | D4: R&D Engineer | E4: Current | F4: 45901 | H4: 7500 | I4: =IF(AND(F4<=DATE(2025,1,1),OR(G4="",G4>=DATE(2025,1,1))),H4*(1+Assumptions!$C$7)^0,0) -> 0 | J4: =IF(AND(F4<=DATE(2025,2,1),OR(G4="",G4>=DATE(2025,2,1))),H4*(1+Assumptions!$C$7)^0,0) -> 0 | K4: =IF(AND(F4<=DATE(2025,3,1),OR(G4="",G4>=DATE(2025,3,1))),H4*(1+Assumptions!$C$7)^0,0) -> 0 | L4: =IF(AND(F4<=DATE(2025,4,1),OR(G4="",G4>=DATE(2025,4,1))),H4*(1+Assumptions!$C$7)^0,0) -> 0 | M4: =IF(AND(F4<=DATE(2025,5,1),OR(G4="",G4>=DATE(2025,5,1))),H4*(1+Assumptions!$C$7)^0,0) -> 0 | N4: =IF(AND(F4<=DATE(2025,6,1),OR(G4="",G4>=DATE(2025,6,1))),H4*(1+Assumptions!$C$7)^0,0) -> 0 | O4: =IF(AND(F4<=DATE(2025,7,1),OR(G4="",G4>=DATE(2025,7,1))),H4*(1+Assumptions!$C$7)^0,0) -> 0 | P4: =IF(AND(F4<=DATE(2025,8,1),OR(G4="",G4>=DATE(2025,8,1))),H4*(1+Assumptions!$C$7)^0,0) -> 0 | Q4: =IF(AND(F4<=DATE(2025,9,1),OR(G4="",G4>=DATE(2025,9,1))),H4*(1+Assumptions!$C$7)^0,0) -> 7500 | R4: =IF(AND(F4<=DATE(2025,10,1),OR(G4="",G4>=DATE(2025,10,1))),H4*(1+Assumptions!$C$7)^0,0) -> 7500 | S4: =IF(AND(F4<=DATE(2025,11,1),OR(G4="",G4>=DATE(2025,11,1))),H4*(1+Assumptions!$C$7)^0,0) -> 7500 | T4: =IF(AND(F4<=DATE(2025,12,1),OR(G4="",G4>=DATE(2025,12,1))),H4*(1+Assumptions!$C$7)^0,0) -> 7500 | U4: =IF(AND(F4<=DATE(2026,1,1),OR(G4="",G4>=DATE(2026,1,1))),H4*(1+Assumptions!$C$7)^1,0) -> 8100 | V4: =IF(AND(F4<=DATE(2026,2,1),OR(G4="",G4>=DATE(2026,2,1))),H4*(1+Assumptions!$C$7)^1,0) -> 8100 | W4: =IF(AND(F4<=DATE(2026,3,1),OR(G4="",G4>=DATE(2026,3,1))),H4*(1+Assumptions!$C$7)^1,0) -> 8100 | X4: =IF(AND(F4<=DATE(2026,4,1),OR(G4="",G4>=DATE(2026,4,1))),H4*(1+Assumptions!$C$7)^1,0) -> 8100 | Y4: =IF(AND(F4<=DATE(2026,5,1),OR(G4="",G4>=DATE(2026,5,1))),H4*(1+Assumptions!$C$7)^1,0) -> 8100 | Z4: =IF(AND(F4<=DATE(2026,6,1),OR(G4="",G4>=DATE(2026,6,1))),H4*(1+Assumptions!$C$7)^1,0) -> 8100 | AA4: =IF(AND(F4<=DATE(2026,7,1),OR(G4="",G4>=DATE(2026,7,1))),H4*(1+Assumptions!$C$7)^1,0) -> 8100 | AB4: =IF(AND(F4<=DATE(2026,8,1),OR(G4="",G4>=DATE(2026,8,1))),H4*(1+Assumptions!$C$7)^1,0) -> 8100 | AC4: =IF(AND(F4<=DATE(2026,9,1),OR(G4="",G4>=DATE(2026,9,1))),H4*(1+Assumptions!$C$7)^1,0) -> 8100 | AD4: =IF(AND(F4<=DATE(2026,10,1),OR(G4="",G4>=DATE(2026,10,1))),H4*(1+Assumptions!$C$7)^1,0) -> 8100 | AE4: =IF(AND(F4<=DATE(2026,11,1),OR(G4="",G4>=DATE(2026,11,1))),H4*(1+Assumptions!$C$7)^1,0) -> 8100 | AF4: =IF(AND(F4<=DATE(2026,12,1),OR(G4="",G4>=DATE(2026,12,1))),H4*(1+Assumptions!$C$7)^1,0) -> 8100 | AG4: =IF(AND(F4<=DATE(2027,1,1),OR(G4="",G4>=DATE(2027,1,1))),H4*(1+Assumptions!$C$7)^2,0) -> 8748 | AH4: =IF(AND(F4<=DATE(2027,2,1),OR(G4="",G4>=DATE(2027,2,1))),H4*(1+Assumptions!$C$7)^2,0) -> 8748 | AI4: =IF(AND(F4<=DATE(2027,3,1),OR(G4="",G4>=DATE(2027,3,1))),H4*(1+Assumptions!$C$7)^2,0) -> 8748 | AJ4: =IF(AND(F4<=DATE(2027,4,1),OR(G4="",G4>=DATE(2027,4,1))),H4*(1+Assumptions!$C$7)^2,0) -> 8748 | AK4: =IF(AND(F4<=DATE(2027,5,1),OR(G4="",G4>=DATE(2027,5,1))),H4*(1+Assumptions!$C$7)^2,0) -> 8748 | AL4: =IF(AND(F4<=DATE(2027,6,1),OR(G4="",G4>=DATE(2027,6,1))),H4*(1+Assumptions!$C$7)^2,0) -> 8748 | AM4: =IF(AND(F4<=DATE(2027,7,1),OR(G4="",G4>=DATE(2027,7,1))),H4*(1+Assumptions!$C$7)^2,0) -> 8748 | AN4: =IF(AND(F4<=DATE(2027,8,1),OR(G4="",G4>=DATE(2027,8,1))),H4*(1+Assumptions!$C$7)^2,0) -> 8748 | AO4: =IF(AND(F4<=DATE(2027,9,1),OR(G4="",G4>=DATE(2027,9,1))),H4*(1+Assumptions!$C$7)^2,0) -> 8748 | AP4: =IF(AND(F4<=DATE(2027,10,1),OR(G4="",G4>=DATE(2027,10,1))),H4*(1+Assumptions!$C$7)^2,0) -> 8748 | AQ4: =IF(AND(F4<=DATE(2027,11,1),OR(G4="",G4>=DATE(2027,11,1))),H4*(1+Assumptions!$C$7)^2,0) -> 8748 | AR4: =IF(AND(F4<=DATE(2027,12,1),OR(G4="",G4>=DATE(2027,12,1))),H4*(1+Assumptions!$C$7)^2,0) -> 8748 | AS4: =IF(AND(F4<=DATE(2028,1,1),OR(G4="",G4>=DATE(2028,1,1))),H4*(1+Assumptions!$C$7)^3,0) -> 9447.84 | AT4: =IF(AND(F4<=DATE(2028,2,1),OR(G4="",G4>=DATE(2028,2,1))),H4*(1+Assumptions!$C$7)^3,0) -> 9447.84 | AU4: =IF(AND(F4<=DATE(2028,3,1),OR(G4="",G4>=DATE(2028,3,1))),H4*(1+Assumptions!$C$7)^3,0) -> 9447.84 | AV4: =IF(AND(F4<=DATE(2028,4,1),OR(G4="",G4>=DATE(2028,4,1))),H4*(1+Assumptions!$C$7)^3,0) -> 9447.84 | AW4: =IF(AND(F4<=DATE(2028,5,1),OR(G4="",G4>=DATE(2028,5,1))),H4*(1+Assumptions!$C$7)^3,0) -> 9447.84 | AX4: =IF(AND(F4<=DATE(2028,6,1),OR(G4="",G4>=DATE(2028,6,1))),H4*(1+Assumptions!$C$7)^3,0) -> 9447.84 | AY4: =IF(AND(F4<=DATE(2028,7,1),OR(G4="",G4>=DATE(2028,7,1))),H4*(1+Assumptions!$C$7)^3,0) -> 9447.84 | AZ4: =IF(AND(F4<=DATE(2028,8,1),OR(G4="",G4>=DATE(2028,8,1))),H4*(1+Assumptions!$C$7)^3,0) -> 9447.84 | BA4: =IF(AND(F4<=DATE(2028,9,1),OR(G4="",G4>=DATE(2028,9,1))),H4*(1+Assumptions!$C$7)^3,0) -> 9447.84 | BB4: =IF(AND(F4<=DATE(2028,10,1),OR(G4="",G4>=DATE(2028,10,1))),H4*(1+Assumptions!$C$7)^3,0) -> 9447.84 | BC4: =IF(AND(F4<=DATE(2028,11,1),OR(G4="",G4>=DATE(2028,11,1))),H4*(1+Assumptions!$C$7)^3,0) -> 9447.84 | BD4: =IF(AND(F4<=DATE(2028,12,1),OR(G4="",G4>=DATE(2028,12,1))),H4*(1+Assumptions!$C$7)^3,0) -> 9447.84 | BE4: =IF(AND(G4<=DATE(2028,12,1),OR(H4="",H4>=DATE(2028,12,1))),I4*(1+Assumptions!$C$7)^3,0) -> 0 | BF4: =IF(AND(H4<=DATE(2028,12,1),OR(I4="",I4>=DATE(2028,12,1))),J4*(1+Assumptions!$C$7)^3,0) -> 0 | BG4: =IF(AND(I4<=DATE(2028,12,1),OR(J4="",J4>=DATE(2028,12,1))),K4*(1+Assumptions!$C$7)^3,0) -> 0 | BH4: =IF(AND(J4<=DATE(2028,12,1),OR(K4="",K4>=DATE(2028,12,1))),L4*(1+Assumptions!$C$7)^3,0) -> 0 | BI4: =IF(AND(K4<=DATE(2028,12,1),OR(L4="",L4>=DATE(2028,12,1))),M4*(1+Assumptions!$C$7)^3,0) -> 0 | BJ4: =IF(AND(L4<=DATE(2028,12,1),OR(M4="",M4>=DATE(2028,12,1))),N4*(1+Assumptions!$C$7)^3,0) -> 0 | BK4: =IF(AND(M4<=DATE(2028,12,1),OR(N4="",N4>=DATE(2028,12,1))),O4*(1+Assumptions!$C$7)^3,0) -> 0 | ... BP4: =IF(AND(R4<=DATE(2028,12,1),OR(S4="",S4>=DATE(2028,12,1))),T4*(1+Assumptions!$C$7)^3,0) -> 0
A5: 3 | B5: R&D Engineer | C5: R&D | D5: R&D Engineer | E5: Current | F5: 45901 | H5: 3000 | I5: =IF(AND(F5<=DATE(2025,1,1),OR(G5="",G5>=DATE(2025,1,1))),H5*(1+Assumptions!$C$7)^0,0) -> 0 | J5: =IF(AND(F5<=DATE(2025,2,1),OR(G5="",G5>=DATE(2025,2,1))),H5*(1+Assumptions!$C$7)^0,0) -> 0 | K5: =IF(AND(F5<=DATE(2025,3,1),OR(G5="",G5>=DATE(2025,3,1))),H5*(1+Assumptions!$C$7)^0,0) -> 0 | L5: =IF(AND(F5<=DATE(2025,4,1),OR(G5="",G5>=DATE(2025,4,1))),H5*(1+Assumptions!$C$7)^0,0) -> 0 | M5: =IF(AND(F5<=DATE(2025,5,1),OR(G5="",G5>=DATE(2025,5,1))),H5*(1+Assumptions!$C$7)^0,0) -> 0 | N5: =IF(AND(F5<=DATE(2025,6,1),OR(G5="",G5>=DATE(2025,6,1))),H5*(1+Assumptions!$C$7)^0,0) -> 0 | O5: =IF(AND(F5<=DATE(2025,7,1),OR(G5="",G5>=DATE(2025,7,1))),H5*(1+Assumptions!$C$7)^0,0) -> 0 | P5: =IF(AND(F5<=DATE(2025,8,1),OR(G5="",G5>=DATE(2025,8,1))),H5*(1+Assumptions!$C$7)^0,0) -> 0 | Q5: =IF(AND(F5<=DATE(2025,9,1),OR(G5="",G5>=DATE(2025,9,1))),H5*(1+Assumptions!$C$7)^0,0) -> 3000 | R5: =IF(AND(F5<=DATE(2025,10,1),OR(G5="",G5>=DATE(2025,10,1))),H5*(1+Assumptions!$C$7)^0,0) -> 3000 | S5: =IF(AND(F5<=DATE(2025,11,1),OR(G5="",G5>=DATE(2025,11,1))),H5*(1+Assumptions!$C$7)^0,0) -> 3000 | T5: =IF(AND(F5<=DATE(2025,12,1),OR(G5="",G5>=DATE(2025,12,1))),H5*(1+Assumptions!$C$7)^0,0) -> 3000 | U5: =IF(AND(F5<=DATE(2026,1,1),OR(G5="",G5>=DATE(2026,1,1))),H5*(1+Assumptions!$C$7)^1,0) -> 3240 | V5: =IF(AND(F5<=DATE(2026,2,1),OR(G5="",G5>=DATE(2026,2,1))),H5*(1+Assumptions!$C$7)^1,0) -> 3240 | W5: =IF(AND(F5<=DATE(2026,3,1),OR(G5="",G5>=DATE(2026,3,1))),H5*(1+Assumptions!$C$7)^1,0) -> 3240 | X5: =IF(AND(F5<=DATE(2026,4,1),OR(G5="",G5>=DATE(2026,4,1))),H5*(1+Assumptions!$C$7)^1,0) -> 3240 | Y5: =IF(AND(F5<=DATE(2026,5,1),OR(G5="",G5>=DATE(2026,5,1))),H5*(1+Assumptions!$C$7)^1,0) -> 3240 | Z5: =IF(AND(F5<=DATE(2026,6,1),OR(G5="",G5>=DATE(2026,6,1))),H5*(1+Assumptions!$C$7)^1,0) -> 3240 | AA5: =IF(AND(F5<=DATE(2026,7,1),OR(G5="",G5>=DATE(2026,7,1))),H5*(1+Assumptions!$C$7)^1,0) -> 3240 | AB5: =IF(AND(F5<=DATE(2026,8,1),OR(G5="",G5>=DATE(2026,8,1))),H5*(1+Assumptions!$C$7)^1,0) -> 3240 | AC5: =IF(AND(F5<=DATE(2026,9,1),OR(G5="",G5>=DATE(2026,9,1))),H5*(1+Assumptions!$C$7)^1,0) -> 3240 | AD5: =IF(AND(F5<=DATE(2026,10,1),OR(G5="",G5>=DATE(2026,10,1))),H5*(1+Assumptions!$C$7)^1,0) -> 3240 | AE5: =IF(AND(F5<=DATE(2026,11,1),OR(G5="",G5>=DATE(2026,11,1))),H5*(1+Assumptions!$C$7)^1,0) -> 3240 | AF5: =IF(AND(F5<=DATE(2026,12,1),OR(G5="",G5>=DATE(2026,12,1))),H5*(1+Assumptions!$C$7)^1,0) -> 3240 | AG5: =IF(AND(F5<=DATE(2027,1,1),OR(G5="",G5>=DATE(2027,1,1))),H5*(1+Assumptions!$C$7)^2,0) -> 3499.2 | AH5: =IF(AND(F5<=DATE(2027,2,1),OR(G5="",G5>=DATE(2027,2,1))),H5*(1+Assumptions!$C$7)^2,0) -> 3499.2 | AI5: =IF(AND(F5<=DATE(2027,3,1),OR(G5="",G5>=DATE(2027,3,1))),H5*(1+Assumptions!$C$7)^2,0) -> 3499.2 | AJ5: =IF(AND(F5<=DATE(2027,4,1),OR(G5="",G5>=DATE(2027,4,1))),H5*(1+Assumptions!$C$7)^2,0) -> 3499.2 | AK5: =IF(AND(F5<=DATE(2027,5,1),OR(G5="",G5>=DATE(2027,5,1))),H5*(1+Assumptions!$C$7)^2,0) -> 3499.2 | AL5: =IF(AND(F5<=DATE(2027,6,1),OR(G5="",G5>=DATE(2027,6,1))),H5*(1+Assumptions!$C$7)^2,0) -> 3499.2 | AM5: =IF(AND(F5<=DATE(2027,7,1),OR(G5="",G5>=DATE(2027,7,1))),H5*(1+Assumptions!$C$7)^2,0) -> 3499.2 | AN5: =IF(AND(F5<=DATE(2027,8,1),OR(G5="",G5>=DATE(2027,8,1))),H5*(1+Assumptions!$C$7)^2,0) -> 3499.2 | AO5: =IF(AND(F5<=DATE(2027,9,1),OR(G5="",G5>=DATE(2027,9,1))),H5*(1+Assumptions!$C$7)^2,0) -> 3499.2 | AP5: =IF(AND(F5<=DATE(2027,10,1),OR(G5="",G5>=DATE(2027,10,1))),H5*(1+Assumptions!$C$7)^2,0) -> 3499.2 | AQ5: =IF(AND(F5<=DATE(2027,11,1),OR(G5="",G5>=DATE(2027,11,1))),H5*(1+Assumptions!$C$7)^2,0) -> 3499.2 | AR5: =IF(AND(F5<=DATE(2027,12,1),OR(G5="",G5>=DATE(2027,12,1))),H5*(1+Assumptions!$C$7)^2,0) -> 3499.2 | AS5: =IF(AND(F5<=DATE(2028,1,1),OR(G5="",G5>=DATE(2028,1,1))),H5*(1+Assumptions!$C$7)^3,0) -> 3779.136 | AT5: =IF(AND(F5<=DATE(2028,2,1),OR(G5="",G5>=DATE(2028,2,1))),H5*(1+Assumptions!$C$7)^3,0) -> 3779.136 | AU5: =IF(AND(F5<=DATE(2028,3,1),OR(G5="",G5>=DATE(2028,3,1))),H5*(1+Assumptions!$C$7)^3,0) -> 3779.136 | AV5: =IF(AND(F5<=DATE(2028,4,1),OR(G5="",G5>=DATE(2028,4,1))),H5*(1+Assumptions!$C$7)^3,0) -> 3779.136 | AW5: =IF(AND(F5<=DATE(2028,5,1),OR(G5="",G5>=DATE(2028,5,1))),H5*(1+Assumptions!$C$7)^3,0) -> 3779.136 | AX5: =IF(AND(F5<=DATE(2028,6,1),OR(G5="",G5>=DATE(2028,6,1))),H5*(1+Assumptions!$C$7)^3,0) -> 3779.136 | AY5: =IF(AND(F5<=DATE(2028,7,1),OR(G5="",G5>=DATE(2028,7,1))),H5*(1+Assumptions!$C$7)^3,0) -> 3779.136 | AZ5: =IF(AND(F5<=DATE(2028,8,1),OR(G5="",G5>=DATE(2028,8,1))),H5*(1+Assumptions!$C$7)^3,0) -> 3779.136 | BA5: =IF(AND(F5<=DATE(2028,9,1),OR(G5="",G5>=DATE(2028,9,1))),H5*(1+Assumptions!$C$7)^3,0) -> 3779.136 | BB5: =IF(AND(F5<=DATE(2028,10,1),OR(G5="",G5>=DATE(2028,10,1))),H5*(1+Assumptions!$C$7)^3,0) -> 3779.136 | BC5: =IF(AND(F5<=DATE(2028,11,1),OR(G5="",G5>=DATE(2028,11,1))),H5*(1+Assumptions!$C$7)^3,0) -> 3779.136 | BD5: =IF(AND(F5<=DATE(2028,12,1),OR(G5="",G5>=DATE(2028,12,1))),H5*(1+Assumptions!$C$7)^3,0) -> 3779.136 | BE5: =IF(AND(G5<=DATE(2028,12,1),OR(H5="",H5>=DATE(2028,12,1))),I5*(1+Assumptions!$C$7)^3,0) -> 0 | BF5: =IF(AND(H5<=DATE(2028,12,1),OR(I5="",I5>=DATE(2028,12,1))),J5*(1+Assumptions!$C$7)^3,0) -> 0 | BG5: =IF(AND(I5<=DATE(2028,12,1),OR(J5="",J5>=DATE(2028,12,1))),K5*(1+Assumptions!$C$7)^3,0) -> 0 | BH5: =IF(AND(J5<=DATE(2028,12,1),OR(K5="",K5>=DATE(2028,12,1))),L5*(1+Assumptions!$C$7)^3,0) -> 0 | BI5: =IF(AND(K5<=DATE(2028,12,1),OR(L5="",L5>=DATE(2028,12,1))),M5*(1+Assumptions!$C$7)^3,0) -> 0 | BJ5: =IF(AND(L5<=DATE(2028,12,1),OR(M5="",M5>=DATE(2028,12,1))),N5*(1+Assumptions!$C$7)^3,0) -> 0 | BK5: =IF(AND(M5<=DATE(2028,12,1),OR(N5="",N5>=DATE(2028,12,1))),O5*(1+Assumptions!$C$7)^3,0) -> 0 | ... BP5: =IF(AND(R5<=DATE(2028,12,1),OR(S5="",S5>=DATE(2028,12,1))),T5*(1+Assumptions!$C$7)^3,0) -> 0
A6: 4 | B6: R&D Engineer | C6: R&D | D6: R&D Engineer | E6: Current | F6: 45901 | H6: 6000 | I6: =IF(AND(F6<=DATE(2025,1,1),OR(G6="",G6>=DATE(2025,1,1))),H6*(1+Assumptions!$C$7)^0,0) -> 0 | J6: =IF(AND(F6<=DATE(2025,2,1),OR(G6="",G6>=DATE(2025,2,1))),H6*(1+Assumptions!$C$7)^0,0) -> 0 | K6: =IF(AND(F6<=DATE(2025,3,1),OR(G6="",G6>=DATE(2025,3,1))),H6*(1+Assumptions!$C$7)^0,0) -> 0 | L6: =IF(AND(F6<=DATE(2025,4,1),OR(G6="",G6>=DATE(2025,4,1))),H6*(1+Assumptions!$C$7)^0,0) -> 0 | M6: =IF(AND(F6<=DATE(2025,5,1),OR(G6="",G6>=DATE(2025,5,1))),H6*(1+Assumptions!$C$7)^0,0) -> 0 | N6: =IF(AND(F6<=DATE(2025,6,1),OR(G6="",G6>=DATE(2025,6,1))),H6*(1+Assumptions!$C$7)^0,0) -> 0 | O6: =IF(AND(F6<=DATE(2025,7,1),OR(G6="",G6>=DATE(2025,7,1))),H6*(1+Assumptions!$C$7)^0,0) -> 0 | P6: =IF(AND(F6<=DATE(2025,8,1),OR(G6="",G6>=DATE(2025,8,1))),H6*(1+Assumptions!$C$7)^0,0) -> 0 | Q6: =IF(AND(F6<=DATE(2025,9,1),OR(G6="",G6>=DATE(2025,9,1))),H6*(1+Assumptions!$C$7)^0,0) -> 6000 | R6: =IF(AND(F6<=DATE(2025,10,1),OR(G6="",G6>=DATE(2025,10,1))),H6*(1+Assumptions!$C$7)^0,0) -> 6000 | S6: =IF(AND(F6<=DATE(2025,11,1),OR(G6="",G6>=DATE(2025,11,1))),H6*(1+Assumptions!$C$7)^0,0) -> 6000 | T6: =IF(AND(F6<=DATE(2025,12,1),OR(G6="",G6>=DATE(2025,12,1))),H6*(1+Assumptions!$C$7)^0,0) -> 6000 | U6: =IF(AND(F6<=DATE(2026,1,1),OR(G6="",G6>=DATE(2026,1,1))),H6*(1+Assumptions!$C$7)^1,0) -> 6480 | V6: =IF(AND(F6<=DATE(2026,2,1),OR(G6="",G6>=DATE(2026,2,1))),H6*(1+Assumptions!$C$7)^1,0) -> 6480 | W6: =IF(AND(F6<=DATE(2026,3,1),OR(G6="",G6>=DATE(2026,3,1))),H6*(1+Assumptions!$C$7)^1,0) -> 6480 | X6: =IF(AND(F6<=DATE(2026,4,1),OR(G6="",G6>=DATE(2026,4,1))),H6*(1+Assumptions!$C$7)^1,0) -> 6480 | Y6: =IF(AND(F6<=DATE(2026,5,1),OR(G6="",G6>=DATE(2026,5,1))),H6*(1+Assumptions!$C$7)^1,0) -> 6480 | Z6: =IF(AND(F6<=DATE(2026,6,1),OR(G6="",G6>=DATE(2026,6,1))),H6*(1+Assumptions!$C$7)^1,0) -> 6480 | AA6: =IF(AND(F6<=DATE(2026,7,1),OR(G6="",G6>=DATE(2026,7,1))),H6*(1+Assumptions!$C$7)^1,0) -> 6480 | AB6: =IF(AND(F6<=DATE(2026,8,1),OR(G6="",G6>=DATE(2026,8,1))),H6*(1+Assumptions!$C$7)^1,0) -> 6480 | AC6: =IF(AND(F6<=DATE(2026,9,1),OR(G6="",G6>=DATE(2026,9,1))),H6*(1+Assumptions!$C$7)^1,0) -> 6480 | AD6: =IF(AND(F6<=DATE(2026,10,1),OR(G6="",G6>=DATE(2026,10,1))),H6*(1+Assumptions!$C$7)^1,0) -> 6480 | AE6: =IF(AND(F6<=DATE(2026,11,1),OR(G6="",G6>=DATE(2026,11,1))),H6*(1+Assumptions!$C$7)^1,0) -> 6480 | AF6: =IF(AND(F6<=DATE(2026,12,1),OR(G6="",G6>=DATE(2026,12,1))),H6*(1+Assumptions!$C$7)^1,0) -> 6480 | AG6: =IF(AND(F6<=DATE(2027,1,1),OR(G6="",G6>=DATE(2027,1,1))),H6*(1+Assumptions!$C$7)^2,0) -> 6998.4 | AH6: =IF(AND(F6<=DATE(2027,2,1),OR(G6="",G6>=DATE(2027,2,1))),H6*(1+Assumptions!$C$7)^2,0) -> 6998.4 | AI6: =IF(AND(F6<=DATE(2027,3,1),OR(G6="",G6>=DATE(2027,3,1))),H6*(1+Assumptions!$C$7)^2,0) -> 6998.4 | AJ6: =IF(AND(F6<=DATE(2027,4,1),OR(G6="",G6>=DATE(2027,4,1))),H6*(1+Assumptions!$C$7)^2,0) -> 6998.4 | AK6: =IF(AND(F6<=DATE(2027,5,1),OR(G6="",G6>=DATE(2027,5,1))),H6*(1+Assumptions!$C$7)^2,0) -> 6998.4 | AL6: =IF(AND(F6<=DATE(2027,6,1),OR(G6="",G6>=DATE(2027,6,1))),H6*(1+Assumptions!$C$7)^2,0) -> 6998.4 | AM6: =IF(AND(F6<=DATE(2027,7,1),OR(G6="",G6>=DATE(2027,7,1))),H6*(1+Assumptions!$C$7)^2,0) -> 6998.4 | AN6: =IF(AND(F6<=DATE(2027,8,1),OR(G6="",G6>=DATE(2027,8,1))),H6*(1+Assumptions!$C$7)^2,0) -> 6998.4 | AO6: =IF(AND(F6<=DATE(2027,9,1),OR(G6="",G6>=DATE(2027,9,1))),H6*(1+Assumptions!$C$7)^2,0) -> 6998.4 | AP6: =IF(AND(F6<=DATE(2027,10,1),OR(G6="",G6>=DATE(2027,10,1))),H6*(1+Assumptions!$C$7)^2,0) -> 6998.4 | AQ6: =IF(AND(F6<=DATE(2027,11,1),OR(G6="",G6>=DATE(2027,11,1))),H6*(1+Assumptions!$C$7)^2,0) -> 6998.4 | AR6: =IF(AND(F6<=DATE(2027,12,1),OR(G6="",G6>=DATE(2027,12,1))),H6*(1+Assumptions!$C$7)^2,0) -> 6998.4 | AS6: =IF(AND(F6<=DATE(2028,1,1),OR(G6="",G6>=DATE(2028,1,1))),H6*(1+Assumptions!$C$7)^3,0) -> 7558.272 | AT6: =IF(AND(F6<=DATE(2028,2,1),OR(G6="",G6>=DATE(2028,2,1))),H6*(1+Assumptions!$C$7)^3,0) -> 7558.272 | AU6: =IF(AND(F6<=DATE(2028,3,1),OR(G6="",G6>=DATE(2028,3,1))),H6*(1+Assumptions!$C$7)^3,0) -> 7558.272 | AV6: =IF(AND(F6<=DATE(2028,4,1),OR(G6="",G6>=DATE(2028,4,1))),H6*(1+Assumptions!$C$7)^3,0) -> 7558.272 | AW6: =IF(AND(F6<=DATE(2028,5,1),OR(G6="",G6>=DATE(2028,5,1))),H6*(1+Assumptions!$C$7)^3,0) -> 7558.272 | AX6: =IF(AND(F6<=DATE(2028,6,1),OR(G6="",G6>=DATE(2028,6,1))),H6*(1+Assumptions!$C$7)^3,0) -> 7558.272 | AY6: =IF(AND(F6<=DATE(2028,7,1),OR(G6="",G6>=DATE(2028,7,1))),H6*(1+Assumptions!$C$7)^3,0) -> 7558.272 | AZ6: =IF(AND(F6<=DATE(2028,8,1),OR(G6="",G6>=DATE(2028,8,1))),H6*(1+Assumptions!$C$7)^3,0) -> 7558.272 | BA6: =IF(AND(F6<=DATE(2028,9,1),OR(G6="",G6>=DATE(2028,9,1))),H6*(1+Assumptions!$C$7)^3,0) -> 7558.272 | BB6: =IF(AND(F6<=DATE(2028,10,1),OR(G6="",G6>=DATE(2028,10,1))),H6*(1+Assumptions!$C$7)^3,0) -> 7558.272 | BC6: =IF(AND(F6<=DATE(2028,11,1),OR(G6="",G6>=DATE(2028,11,1))),H6*(1+Assumptions!$C$7)^3,0) -> 7558.272 | BD6: =IF(AND(F6<=DATE(2028,12,1),OR(G6="",G6>=DATE(2028,12,1))),H6*(1+Assumptions!$C$7)^3,0) -> 7558.272 | BE6: =IF(AND(G6<=DATE(2028,12,1),OR(H6="",H6>=DATE(2028,12,1))),I6*(1+Assumptions!$C$7)^3,0) -> 0 | BF6: =IF(AND(H6<=DATE(2028,12,1),OR(I6="",I6>=DATE(2028,12,1))),J6*(1+Assumptions!$C$7)^3,0) -> 0 | BG6: =IF(AND(I6<=DATE(2028,12,1),OR(J6="",J6>=DATE(2028,12,1))),K6*(1+Assumptions!$C$7)^3,0) -> 0 | BH6: =IF(AND(J6<=DATE(2028,12,1),OR(K6="",K6>=DATE(2028,12,1))),L6*(1+Assumptions!$C$7)^3,0) -> 0 | BI6: =IF(AND(K6<=DATE(2028,12,1),OR(L6="",L6>=DATE(2028,12,1))),M6*(1+Assumptions!$C$7)^3,0) -> 0 | BJ6: =IF(AND(L6<=DATE(2028,12,1),OR(M6="",M6>=DATE(2028,12,1))),N6*(1+Assumptions!$C$7)^3,0) -> 0 | BK6: =IF(AND(M6<=DATE(2028,12,1),OR(N6="",N6>=DATE(2028,12,1))),O6*(1+Assumptions!$C$7)^3,0) -> 0 | ... BP6: =IF(AND(R6<=DATE(2028,12,1),OR(S6="",S6>=DATE(2028,12,1))),T6*(1+Assumptions!$C$7)^3,0) -> 0
A7: 5 | B7: Firmware Engineer | C7: R&D | D7: R&D Engineer | E7: Current | F7: 45901 | H7: 7000 | I7: =IF(AND(F7<=DATE(2025,1,1),OR(G7="",G7>=DATE(2025,1,1))),H7*(1+Assumptions!$C$7)^0,0) -> 0 | J7: =IF(AND(F7<=DATE(2025,2,1),OR(G7="",G7>=DATE(2025,2,1))),H7*(1+Assumptions!$C$7)^0,0) -> 0 | K7: =IF(AND(F7<=DATE(2025,3,1),OR(G7="",G7>=DATE(2025,3,1))),H7*(1+Assumptions!$C$7)^0,0) -> 0 | L7: =IF(AND(F7<=DATE(2025,4,1),OR(G7="",G7>=DATE(2025,4,1))),H7*(1+Assumptions!$C$7)^0,0) -> 0 | M7: =IF(AND(F7<=DATE(2025,5,1),OR(G7="",G7>=DATE(2025,5,1))),H7*(1+Assumptions!$C$7)^0,0) -> 0 | N7: =IF(AND(F7<=DATE(2025,6,1),OR(G7="",G7>=DATE(2025,6,1))),H7*(1+Assumptions!$C$7)^0,0) -> 0 | O7: =IF(AND(F7<=DATE(2025,7,1),OR(G7="",G7>=DATE(2025,7,1))),H7*(1+Assumptions!$C$7)^0,0) -> 0 | P7: =IF(AND(F7<=DATE(2025,8,1),OR(G7="",G7>=DATE(2025,8,1))),H7*(1+Assumptions!$C$7)^0,0) -> 0 | Q7: =IF(AND(F7<=DATE(2025,9,1),OR(G7="",G7>=DATE(2025,9,1))),H7*(1+Assumptions!$C$7)^0,0) -> 7000 | R7: =IF(AND(F7<=DATE(2025,10,1),OR(G7="",G7>=DATE(2025,10,1))),H7*(1+Assumptions!$C$7)^0,0) -> 7000 | S7: =IF(AND(F7<=DATE(2025,11,1),OR(G7="",G7>=DATE(2025,11,1))),H7*(1+Assumptions!$C$7)^0,0) -> 7000 | T7: =IF(AND(F7<=DATE(2025,12,1),OR(G7="",G7>=DATE(2025,12,1))),H7*(1+Assumptions!$C$7)^0,0) -> 7000 | U7: =IF(AND(F7<=DATE(2026,1,1),OR(G7="",G7>=DATE(2026,1,1))),H7*(1+Assumptions!$C$7)^1,0) -> 7560 | V7: =IF(AND(F7<=DATE(2026,2,1),OR(G7="",G7>=DATE(2026,2,1))),H7*(1+Assumptions!$C$7)^1,0) -> 7560 | W7: =IF(AND(F7<=DATE(2026,3,1),OR(G7="",G7>=DATE(2026,3,1))),H7*(1+Assumptions!$C$7)^1,0) -> 7560 | X7: =IF(AND(F7<=DATE(2026,4,1),OR(G7="",G7>=DATE(2026,4,1))),H7*(1+Assumptions!$C$7)^1,0) -> 7560 | Y7: =IF(AND(F7<=DATE(2026,5,1),OR(G7="",G7>=DATE(2026,5,1))),H7*(1+Assumptions!$C$7)^1,0) -> 7560 | Z7: =IF(AND(F7<=DATE(2026,6,1),OR(G7="",G7>=DATE(2026,6,1))),H7*(1+Assumptions!$C$7)^1,0) -> 7560 | AA7: =IF(AND(F7<=DATE(2026,7,1),OR(G7="",G7>=DATE(2026,7,1))),H7*(1+Assumptions!$C$7)^1,0) -> 7560 | AB7: =IF(AND(F7<=DATE(2026,8,1),OR(G7="",G7>=DATE(2026,8,1))),H7*(1+Assumptions!$C$7)^1,0) -> 7560 | AC7: =IF(AND(F7<=DATE(2026,9,1),OR(G7="",G7>=DATE(2026,9,1))),H7*(1+Assumptions!$C$7)^1,0) -> 7560 | AD7: =IF(AND(F7<=DATE(2026,10,1),OR(G7="",G7>=DATE(2026,10,1))),H7*(1+Assumptions!$C$7)^1,0) -> 7560 | AE7: =IF(AND(F7<=DATE(2026,11,1),OR(G7="",G7>=DATE(2026,11,1))),H7*(1+Assumptions!$C$7)^1,0) -> 7560 | AF7: =IF(AND(F7<=DATE(2026,12,1),OR(G7="",G7>=DATE(2026,12,1))),H7*(1+Assumptions!$C$7)^1,0) -> 7560 | AG7: =IF(AND(F7<=DATE(2027,1,1),OR(G7="",G7>=DATE(2027,1,1))),H7*(1+Assumptions!$C$7)^2,0) -> 8164.8 | AH7: =IF(AND(F7<=DATE(2027,2,1),OR(G7="",G7>=DATE(2027,2,1))),H7*(1+Assumptions!$C$7)^2,0) -> 8164.8 | AI7: =IF(AND(F7<=DATE(2027,3,1),OR(G7="",G7>=DATE(2027,3,1))),H7*(1+Assumptions!$C$7)^2,0) -> 8164.8 | AJ7: =IF(AND(F7<=DATE(2027,4,1),OR(G7="",G7>=DATE(2027,4,1))),H7*(1+Assumptions!$C$7)^2,0) -> 8164.8 | AK7: =IF(AND(F7<=DATE(2027,5,1),OR(G7="",G7>=DATE(2027,5,1))),H7*(1+Assumptions!$C$7)^2,0) -> 8164.8 | AL7: =IF(AND(F7<=DATE(2027,6,1),OR(G7="",G7>=DATE(2027,6,1))),H7*(1+Assumptions!$C$7)^2,0) -> 8164.8 | AM7: =IF(AND(F7<=DATE(2027,7,1),OR(G7="",G7>=DATE(2027,7,1))),H7*(1+Assumptions!$C$7)^2,0) -> 8164.8 | AN7: =IF(AND(F7<=DATE(2027,8,1),OR(G7="",G7>=DATE(2027,8,1))),H7*(1+Assumptions!$C$7)^2,0) -> 8164.8 | AO7: =IF(AND(F7<=DATE(2027,9,1),OR(G7="",G7>=DATE(2027,9,1))),H7*(1+Assumptions!$C$7)^2,0) -> 8164.8 | AP7: =IF(AND(F7<=DATE(2027,10,1),OR(G7="",G7>=DATE(2027,10,1))),H7*(1+Assumptions!$C$7)^2,0) -> 8164.8 | AQ7: =IF(AND(F7<=DATE(2027,11,1),OR(G7="",G7>=DATE(2027,11,1))),H7*(1+Assumptions!$C$7)^2,0) -> 8164.8 | AR7: =IF(AND(F7<=DATE(2027,12,1),OR(G7="",G7>=DATE(2027,12,1))),H7*(1+Assumptions!$C$7)^2,0) -> 8164.8 | AS7: =IF(AND(F7<=DATE(2028,1,1),OR(G7="",G7>=DATE(2028,1,1))),H7*(1+Assumptions!$C$7)^3,0) -> 8817.984 | AT7: =IF(AND(F7<=DATE(2028,2,1),OR(G7="",G7>=DATE(2028,2,1))),H7*(1+Assumptions!$C$7)^3,0) -> 8817.984 | AU7: =IF(AND(F7<=DATE(2028,3,1),OR(G7="",G7>=DATE(2028,3,1))),H7*(1+Assumptions!$C$7)^3,0) -> 8817.984 | AV7: =IF(AND(F7<=DATE(2028,4,1),OR(G7="",G7>=DATE(2028,4,1))),H7*(1+Assumptions!$C$7)^3,0) -> 8817.984 | AW7: =IF(AND(F7<=DATE(2028,5,1),OR(G7="",G7>=DATE(2028,5,1))),H7*(1+Assumptions!$C$7)^3,0) -> 8817.984 | AX7: =IF(AND(F7<=DATE(2028,6,1),OR(G7="",G7>=DATE(2028,6,1))),H7*(1+Assumptions!$C$7)^3,0) -> 8817.984 | AY7: =IF(AND(F7<=DATE(2028,7,1),OR(G7="",G7>=DATE(2028,7,1))),H7*(1+Assumptions!$C$7)^3,0) -> 8817.984 | AZ7: =IF(AND(F7<=DATE(2028,8,1),OR(G7="",G7>=DATE(2028,8,1))),H7*(1+Assumptions!$C$7)^3,0) -> 8817.984 | BA7: =IF(AND(F7<=DATE(2028,9,1),OR(G7="",G7>=DATE(2028,9,1))),H7*(1+Assumptions!$C$7)^3,0) -> 8817.984 | BB7: =IF(AND(F7<=DATE(2028,10,1),OR(G7="",G7>=DATE(2028,10,1))),H7*(1+Assumptions!$C$7)^3,0) -> 8817.984 | BC7: =IF(AND(F7<=DATE(2028,11,1),OR(G7="",G7>=DATE(2028,11,1))),H7*(1+Assumptions!$C$7)^3,0) -> 8817.984 | BD7: =IF(AND(F7<=DATE(2028,12,1),OR(G7="",G7>=DATE(2028,12,1))),H7*(1+Assumptions!$C$7)^3,0) -> 8817.984 | BE7: =IF(AND(G7<=DATE(2028,12,1),OR(H7="",H7>=DATE(2028,12,1))),I7*(1+Assumptions!$C$7)^3,0) -> 0 | BF7: =IF(AND(H7<=DATE(2028,12,1),OR(I7="",I7>=DATE(2028,12,1))),J7*(1+Assumptions!$C$7)^3,0) -> 0 | BG7: =IF(AND(I7<=DATE(2028,12,1),OR(J7="",J7>=DATE(2028,12,1))),K7*(1+Assumptions!$C$7)^3,0) -> 0 | BH7: =IF(AND(J7<=DATE(2028,12,1),OR(K7="",K7>=DATE(2028,12,1))),L7*(1+Assumptions!$C$7)^3,0) -> 0 | BI7: =IF(AND(K7<=DATE(2028,12,1),OR(L7="",L7>=DATE(2028,12,1))),M7*(1+Assumptions!$C$7)^3,0) -> 0 | BJ7: =IF(AND(L7<=DATE(2028,12,1),OR(M7="",M7>=DATE(2028,12,1))),N7*(1+Assumptions!$C$7)^3,0) -> 0 | BK7: =IF(AND(M7<=DATE(2028,12,1),OR(N7="",N7>=DATE(2028,12,1))),O7*(1+Assumptions!$C$7)^3,0) -> 0 | ... BP7: =IF(AND(R7<=DATE(2028,12,1),OR(S7="",S7>=DATE(2028,12,1))),T7*(1+Assumptions!$C$7)^3,0) -> 0
A8: 6 | B8: Mechanical Engineer | C8: R&D | D8: R&D Engineer | E8: Current | F8: 45901 | H8: 5500 | I8: =IF(AND(F8<=DATE(2025,1,1),OR(G8="",G8>=DATE(2025,1,1))),H8*(1+Assumptions!$C$7)^0,0) -> 0 | J8: =IF(AND(F8<=DATE(2025,2,1),OR(G8="",G8>=DATE(2025,2,1))),H8*(1+Assumptions!$C$7)^0,0) -> 0 | K8: =IF(AND(F8<=DATE(2025,3,1),OR(G8="",G8>=DATE(2025,3,1))),H8*(1+Assumptions!$C$7)^0,0) -> 0 | L8: =IF(AND(F8<=DATE(2025,4,1),OR(G8="",G8>=DATE(2025,4,1))),H8*(1+Assumptions!$C$7)^0,0) -> 0 | M8: =IF(AND(F8<=DATE(2025,5,1),OR(G8="",G8>=DATE(2025,5,1))),H8*(1+Assumptions!$C$7)^0,0) -> 0 | N8: =IF(AND(F8<=DATE(2025,6,1),OR(G8="",G8>=DATE(2025,6,1))),H8*(1+Assumptions!$C$7)^0,0) -> 0 | O8: =IF(AND(F8<=DATE(2025,7,1),OR(G8="",G8>=DATE(2025,7,1))),H8*(1+Assumptions!$C$7)^0,0) -> 0 | P8: =IF(AND(F8<=DATE(2025,8,1),OR(G8="",G8>=DATE(2025,8,1))),H8*(1+Assumptions!$C$7)^0,0) -> 0 | Q8: =IF(AND(F8<=DATE(2025,9,1),OR(G8="",G8>=DATE(2025,9,1))),H8*(1+Assumptions!$C$7)^0,0) -> 5500 | R8: =IF(AND(F8<=DATE(2025,10,1),OR(G8="",G8>=DATE(2025,10,1))),H8*(1+Assumptions!$C$7)^0,0) -> 5500 | S8: =IF(AND(F8<=DATE(2025,11,1),OR(G8="",G8>=DATE(2025,11,1))),H8*(1+Assumptions!$C$7)^0,0) -> 5500 | T8: =IF(AND(F8<=DATE(2025,12,1),OR(G8="",G8>=DATE(2025,12,1))),H8*(1+Assumptions!$C$7)^0,0) -> 5500 | U8: =IF(AND(F8<=DATE(2026,1,1),OR(G8="",G8>=DATE(2026,1,1))),H8*(1+Assumptions!$C$7)^1,0) -> 5940 | V8: =IF(AND(F8<=DATE(2026,2,1),OR(G8="",G8>=DATE(2026,2,1))),H8*(1+Assumptions!$C$7)^1,0) -> 5940 | W8: =IF(AND(F8<=DATE(2026,3,1),OR(G8="",G8>=DATE(2026,3,1))),H8*(1+Assumptions!$C$7)^1,0) -> 5940 | X8: =IF(AND(F8<=DATE(2026,4,1),OR(G8="",G8>=DATE(2026,4,1))),H8*(1+Assumptions!$C$7)^1,0) -> 5940 | Y8: =IF(AND(F8<=DATE(2026,5,1),OR(G8="",G8>=DATE(2026,5,1))),H8*(1+Assumptions!$C$7)^1,0) -> 5940 | Z8: =IF(AND(F8<=DATE(2026,6,1),OR(G8="",G8>=DATE(2026,6,1))),H8*(1+Assumptions!$C$7)^1,0) -> 5940 | AA8: =IF(AND(F8<=DATE(2026,7,1),OR(G8="",G8>=DATE(2026,7,1))),H8*(1+Assumptions!$C$7)^1,0) -> 5940 | AB8: =IF(AND(F8<=DATE(2026,8,1),OR(G8="",G8>=DATE(2026,8,1))),H8*(1+Assumptions!$C$7)^1,0) -> 5940 | AC8: =IF(AND(F8<=DATE(2026,9,1),OR(G8="",G8>=DATE(2026,9,1))),H8*(1+Assumptions!$C$7)^1,0) -> 5940 | AD8: =IF(AND(F8<=DATE(2026,10,1),OR(G8="",G8>=DATE(2026,10,1))),H8*(1+Assumptions!$C$7)^1,0) -> 5940 | AE8: =IF(AND(F8<=DATE(2026,11,1),OR(G8="",G8>=DATE(2026,11,1))),H8*(1+Assumptions!$C$7)^1,0) -> 5940 | AF8: =IF(AND(F8<=DATE(2026,12,1),OR(G8="",G8>=DATE(2026,12,1))),H8*(1+Assumptions!$C$7)^1,0) -> 5940 | AG8: =IF(AND(F8<=DATE(2027,1,1),OR(G8="",G8>=DATE(2027,1,1))),H8*(1+Assumptions!$C$7)^2,0) -> 6415.2 | AH8: =IF(AND(F8<=DATE(2027,2,1),OR(G8="",G8>=DATE(2027,2,1))),H8*(1+Assumptions!$C$7)^2,0) -> 6415.2 | AI8: =IF(AND(F8<=DATE(2027,3,1),OR(G8="",G8>=DATE(2027,3,1))),H8*(1+Assumptions!$C$7)^2,0) -> 6415.2 | AJ8: =IF(AND(F8<=DATE(2027,4,1),OR(G8="",G8>=DATE(2027,4,1))),H8*(1+Assumptions!$C$7)^2,0) -> 6415.2 | AK8: =IF(AND(F8<=DATE(2027,5,1),OR(G8="",G8>=DATE(2027,5,1))),H8*(1+Assumptions!$C$7)^2,0) -> 6415.2 | AL8: =IF(AND(F8<=DATE(2027,6,1),OR(G8="",G8>=DATE(2027,6,1))),H8*(1+Assumptions!$C$7)^2,0) -> 6415.2 | AM8: =IF(AND(F8<=DATE(2027,7,1),OR(G8="",G8>=DATE(2027,7,1))),H8*(1+Assumptions!$C$7)^2,0) -> 6415.2 | AN8: =IF(AND(F8<=DATE(2027,8,1),OR(G8="",G8>=DATE(2027,8,1))),H8*(1+Assumptions!$C$7)^2,0) -> 6415.2 | AO8: =IF(AND(F8<=DATE(2027,9,1),OR(G8="",G8>=DATE(2027,9,1))),H8*(1+Assumptions!$C$7)^2,0) -> 6415.2 | AP8: =IF(AND(F8<=DATE(2027,10,1),OR(G8="",G8>=DATE(2027,10,1))),H8*(1+Assumptions!$C$7)^2,0) -> 6415.2 | AQ8: =IF(AND(F8<=DATE(2027,11,1),OR(G8="",G8>=DATE(2027,11,1))),H8*(1+Assumptions!$C$7)^2,0) -> 6415.2 | AR8: =IF(AND(F8<=DATE(2027,12,1),OR(G8="",G8>=DATE(2027,12,1))),H8*(1+Assumptions!$C$7)^2,0) -> 6415.2 | AS8: =IF(AND(F8<=DATE(2028,1,1),OR(G8="",G8>=DATE(2028,1,1))),H8*(1+Assumptions!$C$7)^3,0) -> 6928.416 | AT8: =IF(AND(F8<=DATE(2028,2,1),OR(G8="",G8>=DATE(2028,2,1))),H8*(1+Assumptions!$C$7)^3,0) -> 6928.416 | AU8: =IF(AND(F8<=DATE(2028,3,1),OR(G8="",G8>=DATE(2028,3,1))),H8*(1+Assumptions!$C$7)^3,0) -> 6928.416 | AV8: =IF(AND(F8<=DATE(2028,4,1),OR(G8="",G8>=DATE(2028,4,1))),H8*(1+Assumptions!$C$7)^3,0) -> 6928.416 | AW8: =IF(AND(F8<=DATE(2028,5,1),OR(G8="",G8>=DATE(2028,5,1))),H8*(1+Assumptions!$C$7)^3,0) -> 6928.416 | AX8: =IF(AND(F8<=DATE(2028,6,1),OR(G8="",G8>=DATE(2028,6,1))),H8*(1+Assumptions!$C$7)^3,0) -> 6928.416 | AY8: =IF(AND(F8<=DATE(2028,7,1),OR(G8="",G8>=DATE(2028,7,1))),H8*(1+Assumptions!$C$7)^3,0) -> 6928.416 | AZ8: =IF(AND(F8<=DATE(2028,8,1),OR(G8="",G8>=DATE(2028,8,1))),H8*(1+Assumptions!$C$7)^3,0) -> 6928.416 | BA8: =IF(AND(F8<=DATE(2028,9,1),OR(G8="",G8>=DATE(2028,9,1))),H8*(1+Assumptions!$C$7)^3,0) -> 6928.416 | BB8: =IF(AND(F8<=DATE(2028,10,1),OR(G8="",G8>=DATE(2028,10,1))),H8*(1+Assumptions!$C$7)^3,0) -> 6928.416 | BC8: =IF(AND(F8<=DATE(2028,11,1),OR(G8="",G8>=DATE(2028,11,1))),H8*(1+Assumptions!$C$7)^3,0) -> 6928.416 | BD8: =IF(AND(F8<=DATE(2028,12,1),OR(G8="",G8>=DATE(2028,12,1))),H8*(1+Assumptions!$C$7)^3,0) -> 6928.416 | BE8: =IF(AND(G8<=DATE(2028,12,1),OR(H8="",H8>=DATE(2028,12,1))),I8*(1+Assumptions!$C$7)^3,0) -> 0 | BF8: =IF(AND(H8<=DATE(2028,12,1),OR(I8="",I8>=DATE(2028,12,1))),J8*(1+Assumptions!$C$7)^3,0) -> 0 | BG8: =IF(AND(I8<=DATE(2028,12,1),OR(J8="",J8>=DATE(2028,12,1))),K8*(1+Assumptions!$C$7)^3,0) -> 0 | BH8: =IF(AND(J8<=DATE(2028,12,1),OR(K8="",K8>=DATE(2028,12,1))),L8*(1+Assumptions!$C$7)^3,0) -> 0 | BI8: =IF(AND(K8<=DATE(2028,12,1),OR(L8="",L8>=DATE(2028,12,1))),M8*(1+Assumptions!$C$7)^3,0) -> 0 | BJ8: =IF(AND(L8<=DATE(2028,12,1),OR(M8="",M8>=DATE(2028,12,1))),N8*(1+Assumptions!$C$7)^3,0) -> 0 | BK8: =IF(AND(M8<=DATE(2028,12,1),OR(N8="",N8>=DATE(2028,12,1))),O8*(1+Assumptions!$C$7)^3,0) -> 0 | ... BP8: =IF(AND(R8<=DATE(2028,12,1),OR(S8="",S8>=DATE(2028,12,1))),T8*(1+Assumptions!$C$7)^3,0) -> 0
A9: 7 | B9: Electrical Engineer | C9: R&D | D9: R&D Engineer | E9: Current | F9: 45901 | H9: 5500 | I9: =IF(AND(F9<=DATE(2025,1,1),OR(G9="",G9>=DATE(2025,1,1))),H9*(1+Assumptions!$C$7)^0,0) -> 0 | J9: =IF(AND(F9<=DATE(2025,2,1),OR(G9="",G9>=DATE(2025,2,1))),H9*(1+Assumptions!$C$7)^0,0) -> 0 | K9: =IF(AND(F9<=DATE(2025,3,1),OR(G9="",G9>=DATE(2025,3,1))),H9*(1+Assumptions!$C$7)^0,0) -> 0 | L9: =IF(AND(F9<=DATE(2025,4,1),OR(G9="",G9>=DATE(2025,4,1))),H9*(1+Assumptions!$C$7)^0,0) -> 0 | M9: =IF(AND(F9<=DATE(2025,5,1),OR(G9="",G9>=DATE(2025,5,1))),H9*(1+Assumptions!$C$7)^0,0) -> 0 | N9: =IF(AND(F9<=DATE(2025,6,1),OR(G9="",G9>=DATE(2025,6,1))),H9*(1+Assumptions!$C$7)^0,0) -> 0 | O9: =IF(AND(F9<=DATE(2025,7,1),OR(G9="",G9>=DATE(2025,7,1))),H9*(1+Assumptions!$C$7)^0,0) -> 0 | P9: =IF(AND(F9<=DATE(2025,8,1),OR(G9="",G9>=DATE(2025,8,1))),H9*(1+Assumptions!$C$7)^0,0) -> 0 | Q9: =IF(AND(F9<=DATE(2025,9,1),OR(G9="",G9>=DATE(2025,9,1))),H9*(1+Assumptions!$C$7)^0,0) -> 5500 | R9: =IF(AND(F9<=DATE(2025,10,1),OR(G9="",G9>=DATE(2025,10,1))),H9*(1+Assumptions!$C$7)^0,0) -> 5500 | S9: =IF(AND(F9<=DATE(2025,11,1),OR(G9="",G9>=DATE(2025,11,1))),H9*(1+Assumptions!$C$7)^0,0) -> 5500 | T9: =IF(AND(F9<=DATE(2025,12,1),OR(G9="",G9>=DATE(2025,12,1))),H9*(1+Assumptions!$C$7)^0,0) -> 5500 | U9: =IF(AND(F9<=DATE(2026,1,1),OR(G9="",G9>=DATE(2026,1,1))),H9*(1+Assumptions!$C$7)^1,0) -> 5940 | V9: =IF(AND(F9<=DATE(2026,2,1),OR(G9="",G9>=DATE(2026,2,1))),H9*(1+Assumptions!$C$7)^1,0) -> 5940 | W9: =IF(AND(F9<=DATE(2026,3,1),OR(G9="",G9>=DATE(2026,3,1))),H9*(1+Assumptions!$C$7)^1,0) -> 5940 | X9: =IF(AND(F9<=DATE(2026,4,1),OR(G9="",G9>=DATE(2026,4,1))),H9*(1+Assumptions!$C$7)^1,0) -> 5940 | Y9: =IF(AND(F9<=DATE(2026,5,1),OR(G9="",G9>=DATE(2026,5,1))),H9*(1+Assumptions!$C$7)^1,0) -> 5940 | Z9: =IF(AND(F9<=DATE(2026,6,1),OR(G9="",G9>=DATE(2026,6,1))),H9*(1+Assumptions!$C$7)^1,0) -> 5940 | AA9: =IF(AND(F9<=DATE(2026,7,1),OR(G9="",G9>=DATE(2026,7,1))),H9*(1+Assumptions!$C$7)^1,0) -> 5940 | AB9: =IF(AND(F9<=DATE(2026,8,1),OR(G9="",G9>=DATE(2026,8,1))),H9*(1+Assumptions!$C$7)^1,0) -> 5940 | AC9: =IF(AND(F9<=DATE(2026,9,1),OR(G9="",G9>=DATE(2026,9,1))),H9*(1+Assumptions!$C$7)^1,0) -> 5940 | AD9: =IF(AND(F9<=DATE(2026,10,1),OR(G9="",G9>=DATE(2026,10,1))),H9*(1+Assumptions!$C$7)^1,0) -> 5940 | AE9: =IF(AND(F9<=DATE(2026,11,1),OR(G9="",G9>=DATE(2026,11,1))),H9*(1+Assumptions!$C$7)^1,0) -> 5940 | AF9: =IF(AND(F9<=DATE(2026,12,1),OR(G9="",G9>=DATE(2026,12,1))),H9*(1+Assumptions!$C$7)^1,0) -> 5940 | AG9: =IF(AND(F9<=DATE(2027,1,1),OR(G9="",G9>=DATE(2027,1,1))),H9*(1+Assumptions!$C$7)^2,0) -> 6415.2 | AH9: =IF(AND(F9<=DATE(2027,2,1),OR(G9="",G9>=DATE(2027,2,1))),H9*(1+Assumptions!$C$7)^2,0) -> 6415.2 | AI9: =IF(AND(F9<=DATE(2027,3,1),OR(G9="",G9>=DATE(2027,3,1))),H9*(1+Assumptions!$C$7)^2,0) -> 6415.2 | AJ9: =IF(AND(F9<=DATE(2027,4,1),OR(G9="",G9>=DATE(2027,4,1))),H9*(1+Assumptions!$C$7)^2,0) -> 6415.2 | AK9: =IF(AND(F9<=DATE(2027,5,1),OR(G9="",G9>=DATE(2027,5,1))),H9*(1+Assumptions!$C$7)^2,0) -> 6415.2 | AL9: =IF(AND(F9<=DATE(2027,6,1),OR(G9="",G9>=DATE(2027,6,1))),H9*(1+Assumptions!$C$7)^2,0) -> 6415.2 | AM9: =IF(AND(F9<=DATE(2027,7,1),OR(G9="",G9>=DATE(2027,7,1))),H9*(1+Assumptions!$C$7)^2,0) -> 6415.2 | AN9: =IF(AND(F9<=DATE(2027,8,1),OR(G9="",G9>=DATE(2027,8,1))),H9*(1+Assumptions!$C$7)^2,0) -> 6415.2 | AO9: =IF(AND(F9<=DATE(2027,9,1),OR(G9="",G9>=DATE(2027,9,1))),H9*(1+Assumptions!$C$7)^2,0) -> 6415.2 | AP9: =IF(AND(F9<=DATE(2027,10,1),OR(G9="",G9>=DATE(2027,10,1))),H9*(1+Assumptions!$C$7)^2,0) -> 6415.2 | AQ9: =IF(AND(F9<=DATE(2027,11,1),OR(G9="",G9>=DATE(2027,11,1))),H9*(1+Assumptions!$C$7)^2,0) -> 6415.2 | AR9: =IF(AND(F9<=DATE(2027,12,1),OR(G9="",G9>=DATE(2027,12,1))),H9*(1+Assumptions!$C$7)^2,0) -> 6415.2 | AS9: =IF(AND(F9<=DATE(2028,1,1),OR(G9="",G9>=DATE(2028,1,1))),H9*(1+Assumptions!$C$7)^3,0) -> 6928.416 | AT9: =IF(AND(F9<=DATE(2028,2,1),OR(G9="",G9>=DATE(2028,2,1))),H9*(1+Assumptions!$C$7)^3,0) -> 6928.416 | AU9: =IF(AND(F9<=DATE(2028,3,1),OR(G9="",G9>=DATE(2028,3,1))),H9*(1+Assumptions!$C$7)^3,0) -> 6928.416 | AV9: =IF(AND(F9<=DATE(2028,4,1),OR(G9="",G9>=DATE(2028,4,1))),H9*(1+Assumptions!$C$7)^3,0) -> 6928.416 | AW9: =IF(AND(F9<=DATE(2028,5,1),OR(G9="",G9>=DATE(2028,5,1))),H9*(1+Assumptions!$C$7)^3,0) -> 6928.416 | AX9: =IF(AND(F9<=DATE(2028,6,1),OR(G9="",G9>=DATE(2028,6,1))),H9*(1+Assumptions!$C$7)^3,0) -> 6928.416 | AY9: =IF(AND(F9<=DATE(2028,7,1),OR(G9="",G9>=DATE(2028,7,1))),H9*(1+Assumptions!$C$7)^3,0) -> 6928.416 | AZ9: =IF(AND(F9<=DATE(2028,8,1),OR(G9="",G9>=DATE(2028,8,1))),H9*(1+Assumptions!$C$7)^3,0) -> 6928.416 | BA9: =IF(AND(F9<=DATE(2028,9,1),OR(G9="",G9>=DATE(2028,9,1))),H9*(1+Assumptions!$C$7)^3,0) -> 6928.416 | BB9: =IF(AND(F9<=DATE(2028,10,1),OR(G9="",G9>=DATE(2028,10,1))),H9*(1+Assumptions!$C$7)^3,0) -> 6928.416 | BC9: =IF(AND(F9<=DATE(2028,11,1),OR(G9="",G9>=DATE(2028,11,1))),H9*(1+Assumptions!$C$7)^3,0) -> 6928.416 | BD9: =IF(AND(F9<=DATE(2028,12,1),OR(G9="",G9>=DATE(2028,12,1))),H9*(1+Assumptions!$C$7)^3,0) -> 6928.416 | BE9: =IF(AND(G9<=DATE(2028,12,1),OR(H9="",H9>=DATE(2028,12,1))),I9*(1+Assumptions!$C$7)^3,0) -> 0 | BF9: =IF(AND(H9<=DATE(2028,12,1),OR(I9="",I9>=DATE(2028,12,1))),J9*(1+Assumptions!$C$7)^3,0) -> 0 | BG9: =IF(AND(I9<=DATE(2028,12,1),OR(J9="",J9>=DATE(2028,12,1))),K9*(1+Assumptions!$C$7)^3,0) -> 0 | BH9: =IF(AND(J9<=DATE(2028,12,1),OR(K9="",K9>=DATE(2028,12,1))),L9*(1+Assumptions!$C$7)^3,0) -> 0 | BI9: =IF(AND(K9<=DATE(2028,12,1),OR(L9="",L9>=DATE(2028,12,1))),M9*(1+Assumptions!$C$7)^3,0) -> 0 | BJ9: =IF(AND(L9<=DATE(2028,12,1),OR(M9="",M9>=DATE(2028,12,1))),N9*(1+Assumptions!$C$7)^3,0) -> 0 | BK9: =IF(AND(M9<=DATE(2028,12,1),OR(N9="",N9>=DATE(2028,12,1))),O9*(1+Assumptions!$C$7)^3,0) -> 0 | ... BP9: =IF(AND(R9<=DATE(2028,12,1),OR(S9="",S9>=DATE(2028,12,1))),T9*(1+Assumptions!$C$7)^3,0) -> 0
A10: 11 | B10: CFO (part time) | C10: G&A | D10: CFO | E10: Current | F10: 45901 | G10: 46266 | H10: 4000 | I10: =IF(AND(F10<=DATE(2025,1,1),OR(G10="",G10>=DATE(2025,1,1))),H10*(1+Assumptions!$C$7)^0,0) -> 0 | J10: =IF(AND(F10<=DATE(2025,2,1),OR(G10="",G10>=DATE(2025,2,1))),H10*(1+Assumptions!$C$7)^0,0) -> 0 | K10: =IF(AND(F10<=DATE(2025,3,1),OR(G10="",G10>=DATE(2025,3,1))),H10*(1+Assumptions!$C$7)^0,0) -> 0 | L10: =IF(AND(F10<=DATE(2025,4,1),OR(G10="",G10>=DATE(2025,4,1))),H10*(1+Assumptions!$C$7)^0,0) -> 0 | M10: =IF(AND(F10<=DATE(2025,5,1),OR(G10="",G10>=DATE(2025,5,1))),H10*(1+Assumptions!$C$7)^0,0) -> 0 | N10: =IF(AND(F10<=DATE(2025,6,1),OR(G10="",G10>=DATE(2025,6,1))),H10*(1+Assumptions!$C$7)^0,0) -> 0 | O10: =IF(AND(F10<=DATE(2025,7,1),OR(G10="",G10>=DATE(2025,7,1))),H10*(1+Assumptions!$C$7)^0,0) -> 0 | P10: =IF(AND(F10<=DATE(2025,8,1),OR(G10="",G10>=DATE(2025,8,1))),H10*(1+Assumptions!$C$7)^0,0) -> 0 | Q10: =IF(AND(F10<=DATE(2025,9,1),OR(G10="",G10>=DATE(2025,9,1))),H10*(1+Assumptions!$C$7)^0,0) -> 4000 | R10: =IF(AND(F10<=DATE(2025,10,1),OR(G10="",G10>=DATE(2025,10,1))),H10*(1+Assumptions!$C$7)^0,0) -> 4000 | S10: =IF(AND(F10<=DATE(2025,11,1),OR(G10="",G10>=DATE(2025,11,1))),H10*(1+Assumptions!$C$7)^0,0) -> 4000 | T10: =IF(AND(F10<=DATE(2025,12,1),OR(G10="",G10>=DATE(2025,12,1))),H10*(1+Assumptions!$C$7)^0,0) -> 4000 | U10: =IF(AND(F10<=DATE(2026,1,1),OR(G10="",G10>=DATE(2026,1,1))),H10*(1+Assumptions!$C$7)^1,0) -> 4320 | V10: =IF(AND(F10<=DATE(2026,2,1),OR(G10="",G10>=DATE(2026,2,1))),H10*(1+Assumptions!$C$7)^1,0) -> 4320 | W10: =IF(AND(F10<=DATE(2026,3,1),OR(G10="",G10>=DATE(2026,3,1))),H10*(1+Assumptions!$C$7)^1,0) -> 4320 | X10: =IF(AND(F10<=DATE(2026,4,1),OR(G10="",G10>=DATE(2026,4,1))),H10*(1+Assumptions!$C$7)^1,0) -> 4320 | Y10: =IF(AND(F10<=DATE(2026,5,1),OR(G10="",G10>=DATE(2026,5,1))),H10*(1+Assumptions!$C$7)^1,0) -> 4320 | Z10: =IF(AND(F10<=DATE(2026,6,1),OR(G10="",G10>=DATE(2026,6,1))),H10*(1+Assumptions!$C$7)^1,0) -> 4320 | AA10: =IF(AND(F10<=DATE(2026,7,1),OR(G10="",G10>=DATE(2026,7,1))),H10*(1+Assumptions!$C$7)^1,0) -> 4320 | AB10: =IF(AND(F10<=DATE(2026,8,1),OR(G10="",G10>=DATE(2026,8,1))),H10*(1+Assumptions!$C$7)^1,0) -> 4320 | AC10: =IF(AND(F10<=DATE(2026,9,1),OR(G10="",G10>=DATE(2026,9,1))),H10*(1+Assumptions!$C$7)^1,0) -> 4320 | AD10: =IF(AND(F10<=DATE(2026,10,1),OR(G10="",G10>=DATE(2026,10,1))),H10*(1+Assumptions!$C$7)^1,0) -> 0 | AE10: =IF(AND(F10<=DATE(2026,11,1),OR(G10="",G10>=DATE(2026,11,1))),H10*(1+Assumptions!$C$7)^1,0) -> 0 | AF10: =IF(AND(F10<=DATE(2026,12,1),OR(G10="",G10>=DATE(2026,12,1))),H10*(1+Assumptions!$C$7)^1,0) -> 0 | AG10: =IF(AND(F10<=DATE(2027,1,1),OR(G10="",G10>=DATE(2027,1,1))),H10*(1+Assumptions!$C$7)^2,0) -> 0 | AH10: =IF(AND(F10<=DATE(2027,2,1),OR(G10="",G10>=DATE(2027,2,1))),H10*(1+Assumptions!$C$7)^2,0) -> 0 | AI10: =IF(AND(F10<=DATE(2027,3,1),OR(G10="",G10>=DATE(2027,3,1))),H10*(1+Assumptions!$C$7)^2,0) -> 0 | AJ10: =IF(AND(F10<=DATE(2027,4,1),OR(G10="",G10>=DATE(2027,4,1))),H10*(1+Assumptions!$C$7)^2,0) -> 0 | AK10: =IF(AND(F10<=DATE(2027,5,1),OR(G10="",G10>=DATE(2027,5,1))),H10*(1+Assumptions!$C$7)^2,0) -> 0 | AL10: =IF(AND(F10<=DATE(2027,6,1),OR(G10="",G10>=DATE(2027,6,1))),H10*(1+Assumptions!$C$7)^2,0) -> 0 | AM10: =IF(AND(F10<=DATE(2027,7,1),OR(G10="",G10>=DATE(2027,7,1))),H10*(1+Assumptions!$C$7)^2,0) -> 0 | AN10: =IF(AND(F10<=DATE(2027,8,1),OR(G10="",G10>=DATE(2027,8,1))),H10*(1+Assumptions!$C$7)^2,0) -> 0 | AO10: =IF(AND(F10<=DATE(2027,9,1),OR(G10="",G10>=DATE(2027,9,1))),H10*(1+Assumptions!$C$7)^2,0) -> 0 | AP10: =IF(AND(F10<=DATE(2027,10,1),OR(G10="",G10>=DATE(2027,10,1))),H10*(1+Assumptions!$C$7)^2,0) -> 0 | AQ10: =IF(AND(F10<=DATE(2027,11,1),OR(G10="",G10>=DATE(2027,11,1))),H10*(1+Assumptions!$C$7)^2,0) -> 0 | AR10: =IF(AND(F10<=DATE(2027,12,1),OR(G10="",G10>=DATE(2027,12,1))),H10*(1+Assumptions!$C$7)^2,0) -> 0 | AS10: =IF(AND(F10<=DATE(2028,1,1),OR(G10="",G10>=DATE(2028,1,1))),H10*(1+Assumptions!$C$7)^3,0) -> 0 | AT10: =IF(AND(F10<=DATE(2028,2,1),OR(G10="",G10>=DATE(2028,2,1))),H10*(1+Assumptions!$C$7)^3,0) -> 0 | AU10: =IF(AND(F10<=DATE(2028,3,1),OR(G10="",G10>=DATE(2028,3,1))),H10*(1+Assumptions!$C$7)^3,0) -> 0 | AV10: =IF(AND(F10<=DATE(2028,4,1),OR(G10="",G10>=DATE(2028,4,1))),H10*(1+Assumptions!$C$7)^3,0) -> 0 | AW10: =IF(AND(F10<=DATE(2028,5,1),OR(G10="",G10>=DATE(2028,5,1))),H10*(1+Assumptions!$C$7)^3,0) -> 0 | AX10: =IF(AND(F10<=DATE(2028,6,1),OR(G10="",G10>=DATE(2028,6,1))),H10*(1+Assumptions!$C$7)^3,0) -> 0 | AY10: =IF(AND(F10<=DATE(2028,7,1),OR(G10="",G10>=DATE(2028,7,1))),H10*(1+Assumptions!$C$7)^3,0) -> 0 | AZ10: =IF(AND(F10<=DATE(2028,8,1),OR(G10="",G10>=DATE(2028,8,1))),H10*(1+Assumptions!$C$7)^3,0) -> 0 | BA10: =IF(AND(F10<=DATE(2028,9,1),OR(G10="",G10>=DATE(2028,9,1))),H10*(1+Assumptions!$C$7)^3,0) -> 0 | BB10: =IF(AND(F10<=DATE(2028,10,1),OR(G10="",G10>=DATE(2028,10,1))),H10*(1+Assumptions!$C$7)^3,0) -> 0 | BC10: =IF(AND(F10<=DATE(2028,11,1),OR(G10="",G10>=DATE(2028,11,1))),H10*(1+Assumptions!$C$7)^3,0) -> 0 | BD10: =IF(AND(F10<=DATE(2028,12,1),OR(G10="",G10>=DATE(2028,12,1))),H10*(1+Assumptions!$C$7)^3,0) -> 0 | BE10: =IF(AND(G10<=DATE(2028,12,1),OR(H10="",H10>=DATE(2028,12,1))),I10*(1+Assumptions!$C$7)^3,0) -> 0 | BF10: =IF(AND(H10<=DATE(2028,12,1),OR(I10="",I10>=DATE(2028,12,1))),J10*(1+Assumptions!$C$7)^3,0) -> 0 | BG10: =IF(AND(I10<=DATE(2028,12,1),OR(J10="",J10>=DATE(2028,12,1))),K10*(1+Assumptions!$C$7)^3,0) -> 0 | BH10: =IF(AND(J10<=DATE(2028,12,1),OR(K10="",K10>=DATE(2028,12,1))),L10*(1+Assumptions!$C$7)^3,0) -> 0 | BI10: =IF(AND(K10<=DATE(2028,12,1),OR(L10="",L10>=DATE(2028,12,1))),M10*(1+Assumptions!$C$7)^3,0) -> 0 | BJ10: =IF(AND(L10<=DATE(2028,12,1),OR(M10="",M10>=DATE(2028,12,1))),N10*(1+Assumptions!$C$7)^3,0) -> 0 | BK10: =IF(AND(M10<=DATE(2028,12,1),OR(N10="",N10>=DATE(2028,12,1))),O10*(1+Assumptions!$C$7)^3,0) -> 0 | ... BP10: =IF(AND(R10<=DATE(2028,12,1),OR(S10="",S10>=DATE(2028,12,1))),T10*(1+Assumptions!$C$7)^3,0) -> 0
A11: 8 | B11: CTO | C11: R&D | D11: CTO | E11: Current | F11: 46266 | H11: 11500 | I11: =IF(AND(F11<=DATE(2025,1,1),OR(G11="",G11>=DATE(2025,1,1))),H11*(1+Assumptions!$C$7)^0,0) -> 0 | J11: =IF(AND(F11<=DATE(2025,2,1),OR(G11="",G11>=DATE(2025,2,1))),H11*(1+Assumptions!$C$7)^0,0) -> 0 | K11: =IF(AND(F11<=DATE(2025,3,1),OR(G11="",G11>=DATE(2025,3,1))),H11*(1+Assumptions!$C$7)^0,0) -> 0 | L11: =IF(AND(F11<=DATE(2025,4,1),OR(G11="",G11>=DATE(2025,4,1))),H11*(1+Assumptions!$C$7)^0,0) -> 0 | M11: =IF(AND(F11<=DATE(2025,5,1),OR(G11="",G11>=DATE(2025,5,1))),H11*(1+Assumptions!$C$7)^0,0) -> 0 | N11: =IF(AND(F11<=DATE(2025,6,1),OR(G11="",G11>=DATE(2025,6,1))),H11*(1+Assumptions!$C$7)^0,0) -> 0 | O11: =IF(AND(F11<=DATE(2025,7,1),OR(G11="",G11>=DATE(2025,7,1))),H11*(1+Assumptions!$C$7)^0,0) -> 0 | P11: =IF(AND(F11<=DATE(2025,8,1),OR(G11="",G11>=DATE(2025,8,1))),H11*(1+Assumptions!$C$7)^0,0) -> 0 | Q11: 7500 | R11: 7500 | S11: 7500 | T11: 7500 | U11: 7500 | V11: 7500 | W11: 7500 | X11: 7500 | Y11: 7500 | Z11: 7500 | AA11: 7500 | AB11: 7500 | AC11: =IF(AND(F11<=DATE(2026,9,1),OR(G11="",G11>=DATE(2026,9,1))),H11) -> 11500 | AD11: =IF(AND(F11<=DATE(2026,10,1),OR(G11="",G11>=DATE(2026,10,1))),H11*(1+Assumptions!$C$7)^1,0) -> 12420 | AE11: =IF(AND(F11<=DATE(2026,11,1),OR(G11="",G11>=DATE(2026,11,1))),H11*(1+Assumptions!$C$7)^1,0) -> 12420 | AF11: =IF(AND(F11<=DATE(2026,12,1),OR(G11="",G11>=DATE(2026,12,1))),H11*(1+Assumptions!$C$7)^1,0) -> 12420 | AG11: =IF(AND(F11<=DATE(2027,1,1),OR(G11="",G11>=DATE(2027,1,1))),H11*(1+Assumptions!$C$7)^2,0) -> 13413.6 | AH11: =IF(AND(F11<=DATE(2027,2,1),OR(G11="",G11>=DATE(2027,2,1))),H11*(1+Assumptions!$C$7)^2,0) -> 13413.6 | AI11: =IF(AND(F11<=DATE(2027,3,1),OR(G11="",G11>=DATE(2027,3,1))),H11*(1+Assumptions!$C$7)^2,0) -> 13413.6 | AJ11: =IF(AND(F11<=DATE(2027,4,1),OR(G11="",G11>=DATE(2027,4,1))),H11*(1+Assumptions!$C$7)^2,0) -> 13413.6 | AK11: =IF(AND(F11<=DATE(2027,5,1),OR(G11="",G11>=DATE(2027,5,1))),H11*(1+Assumptions!$C$7)^2,0) -> 13413.6 | AL11: =IF(AND(F11<=DATE(2027,6,1),OR(G11="",G11>=DATE(2027,6,1))),H11*(1+Assumptions!$C$7)^2,0) -> 13413.6 | AM11: =IF(AND(F11<=DATE(2027,7,1),OR(G11="",G11>=DATE(2027,7,1))),H11*(1+Assumptions!$C$7)^2,0) -> 13413.6 | AN11: =IF(AND(F11<=DATE(2027,8,1),OR(G11="",G11>=DATE(2027,8,1))),H11*(1+Assumptions!$C$7)^2,0) -> 13413.6 | AO11: =IF(AND(F11<=DATE(2027,9,1),OR(G11="",G11>=DATE(2027,9,1))),H11*(1+Assumptions!$C$7)^2,0) -> 13413.6 | AP11: =IF(AND(F11<=DATE(2027,10,1),OR(G11="",G11>=DATE(2027,10,1))),H11*(1+Assumptions!$C$7)^2,0) -> 13413.6 | AQ11: =IF(AND(F11<=DATE(2027,11,1),OR(G11="",G11>=DATE(2027,11,1))),H11*(1+Assumptions!$C$7)^2,0) -> 13413.6 | AR11: =IF(AND(F11<=DATE(2027,12,1),OR(G11="",G11>=DATE(2027,12,1))),H11*(1+Assumptions!$C$7)^2,0) -> 13413.6 | AS11: =IF(AND(F11<=DATE(2028,1,1),OR(G11="",G11>=DATE(2028,1,1))),H11*(1+Assumptions!$C$7)^3,0) -> 14486.688 | AT11: =IF(AND(F11<=DATE(2028,2,1),OR(G11="",G11>=DATE(2028,2,1))),H11*(1+Assumptions!$C$7)^3,0) -> 14486.688 | AU11: =IF(AND(F11<=DATE(2028,3,1),OR(G11="",G11>=DATE(2028,3,1))),H11*(1+Assumptions!$C$7)^3,0) -> 14486.688 | AV11: =IF(AND(F11<=DATE(2028,4,1),OR(G11="",G11>=DATE(2028,4,1))),H11*(1+Assumptions!$C$7)^3,0) -> 14486.688 | AW11: =IF(AND(F11<=DATE(2028,5,1),OR(G11="",G11>=DATE(2028,5,1))),H11*(1+Assumptions!$C$7)^3,0) -> 14486.688 | AX11: =IF(AND(F11<=DATE(2028,6,1),OR(G11="",G11>=DATE(2028,6,1))),H11*(1+Assumptions!$C$7)^3,0) -> 14486.688 | AY11: =IF(AND(F11<=DATE(2028,7,1),OR(G11="",G11>=DATE(2028,7,1))),H11*(1+Assumptions!$C$7)^3,0) -> 14486.688 | AZ11: =IF(AND(F11<=DATE(2028,8,1),OR(G11="",G11>=DATE(2028,8,1))),H11*(1+Assumptions!$C$7)^3,0) -> 14486.688 | BA11: =IF(AND(F11<=DATE(2028,9,1),OR(G11="",G11>=DATE(2028,9,1))),H11*(1+Assumptions!$C$7)^3,0) -> 14486.688 | BB11: =IF(AND(F11<=DATE(2028,10,1),OR(G11="",G11>=DATE(2028,10,1))),H11*(1+Assumptions!$C$7)^3,0) -> 14486.688 | BC11: =IF(AND(F11<=DATE(2028,11,1),OR(G11="",G11>=DATE(2028,11,1))),H11*(1+Assumptions!$C$7)^3,0) -> 14486.688 | BD11: =IF(AND(F11<=DATE(2028,12,1),OR(G11="",G11>=DATE(2028,12,1))),H11*(1+Assumptions!$C$7)^3,0) -> 14486.688 | BE11: =IF(AND(G11<=DATE(2028,12,1),OR(H11="",H11>=DATE(2028,12,1))),I11*(1+Assumptions!$C$7)^3,0) -> 0 | BF11: =IF(AND(H11<=DATE(2028,12,1),OR(I11="",I11>=DATE(2028,12,1))),J11*(1+Assumptions!$C$7)^3,0) -> 0 | BG11: =IF(AND(I11<=DATE(2028,12,1),OR(J11="",J11>=DATE(2028,12,1))),K11*(1+Assumptions!$C$7)^3,0) -> 0 | BH11: =IF(AND(J11<=DATE(2028,12,1),OR(K11="",K11>=DATE(2028,12,1))),L11*(1+Assumptions!$C$7)^3,0) -> 0 | BI11: =IF(AND(K11<=DATE(2028,12,1),OR(L11="",L11>=DATE(2028,12,1))),M11*(1+Assumptions!$C$7)^3,0) -> 0 | BJ11: =IF(AND(L11<=DATE(2028,12,1),OR(M11="",M11>=DATE(2028,12,1))),N11*(1+Assumptions!$C$7)^3,0) -> 0 | BK11: =IF(AND(M11<=DATE(2028,12,1),OR(N11="",N11>=DATE(2028,12,1))),O11*(1+Assumptions!$C$7)^3,0) -> 0 | ... BP11: =IF(AND(R11<=DATE(2028,12,1),OR(S11="",S11>=DATE(2028,12,1))),T11*(1+Assumptions!$C$7)^3,0) -> 0
A12: 9 | B12: Head of Growth | C12: S&M | D12: Growth | E12: Current | F12: 46054 | H12: 10000 | I12: =IF(AND(F12<=DATE(2025,1,1),OR(G12="",G12>=DATE(2025,1,1))),H12*(1+Assumptions!$C$7)^0,0) -> 0 | J12: =IF(AND(F12<=DATE(2025,2,1),OR(G12="",G12>=DATE(2025,2,1))),H12*(1+Assumptions!$C$7)^0,0) -> 0 | K12: =IF(AND(F12<=DATE(2025,3,1),OR(G12="",G12>=DATE(2025,3,1))),H12*(1+Assumptions!$C$7)^0,0) -> 0 | L12: =IF(AND(F12<=DATE(2025,4,1),OR(G12="",G12>=DATE(2025,4,1))),H12*(1+Assumptions!$C$7)^0,0) -> 0 | M12: =IF(AND(F12<=DATE(2025,5,1),OR(G12="",G12>=DATE(2025,5,1))),H12*(1+Assumptions!$C$7)^0,0) -> 0 | N12: =IF(AND(F12<=DATE(2025,6,1),OR(G12="",G12>=DATE(2025,6,1))),H12*(1+Assumptions!$C$7)^0,0) -> 0 | O12: =IF(AND(F12<=DATE(2025,7,1),OR(G12="",G12>=DATE(2025,7,1))),H12*(1+Assumptions!$C$7)^0,0) -> 0 | P12: =IF(AND(F12<=DATE(2025,8,1),OR(G12="",G12>=DATE(2025,8,1))),H12*(1+Assumptions!$C$7)^0,0) -> 0 | Q12: =IF(AND(F12<=DATE(2025,9,1),OR(G12="",G12>=DATE(2025,9,1))),H12*(1+Assumptions!$C$7)^0,0) -> 0 | R12: =IF(AND(F12<=DATE(2025,10,1),OR(G12="",G12>=DATE(2025,10,1))),H12*(1+Assumptions!$C$7)^0,0) -> 0 | S12: =IF(AND(F12<=DATE(2025,11,1),OR(G12="",G12>=DATE(2025,11,1))),H12*(1+Assumptions!$C$7)^0,0) -> 0 | T12: =IF(AND(F12<=DATE(2025,12,1),OR(G12="",G12>=DATE(2025,12,1))),H12*(1+Assumptions!$C$7)^0,0) -> 0 | U12: =IF(AND(F12<=DATE(2026,1,1),OR(G12="",G12>=DATE(2026,1,1))),H12*(1+Assumptions!$C$7)^1,0) -> 0 | V12: =IF(AND(F12<=DATE(2026,2,1),OR(G12="",G12>=DATE(2026,2,1))),H12*(1+Assumptions!$C$7)^1,0) -> 10800 | W12: =IF(AND(F12<=DATE(2026,3,1),OR(G12="",G12>=DATE(2026,3,1))),H12*(1+Assumptions!$C$7)^1,0) -> 10800 | X12: =IF(AND(F12<=DATE(2026,4,1),OR(G12="",G12>=DATE(2026,4,1))),H12*(1+Assumptions!$C$7)^1,0) -> 10800 | Y12: =IF(AND(F12<=DATE(2026,5,1),OR(G12="",G12>=DATE(2026,5,1))),H12*(1+Assumptions!$C$7)^1,0) -> 10800 | Z12: =IF(AND(F12<=DATE(2026,6,1),OR(G12="",G12>=DATE(2026,6,1))),H12*(1+Assumptions!$C$7)^1,0) -> 10800 | AA12: =IF(AND(F12<=DATE(2026,7,1),OR(G12="",G12>=DATE(2026,7,1))),H12*(1+Assumptions!$C$7)^1,0) -> 10800 | AB12: =IF(AND(F12<=DATE(2026,8,1),OR(G12="",G12>=DATE(2026,8,1))),H12*(1+Assumptions!$C$7)^1,0) -> 10800 | AC12: =IF(AND(F12<=DATE(2026,9,1),OR(G12="",G12>=DATE(2026,9,1))),H12*(1+Assumptions!$C$7)^1,0) -> 10800 | AD12: =IF(AND(F12<=DATE(2026,10,1),OR(G12="",G12>=DATE(2026,10,1))),H12*(1+Assumptions!$C$7)^1,0) -> 10800 | AE12: =IF(AND(F12<=DATE(2026,11,1),OR(G12="",G12>=DATE(2026,11,1))),H12*(1+Assumptions!$C$7)^1,0) -> 10800 | AF12: =IF(AND(F12<=DATE(2026,12,1),OR(G12="",G12>=DATE(2026,12,1))),H12*(1+Assumptions!$C$7)^1,0) -> 10800 | AG12: =IF(AND(F12<=DATE(2027,1,1),OR(G12="",G12>=DATE(2027,1,1))),H12*(1+Assumptions!$C$7)^2,0) -> 11664 | AH12: =IF(AND(F12<=DATE(2027,2,1),OR(G12="",G12>=DATE(2027,2,1))),H12*(1+Assumptions!$C$7)^2,0) -> 11664 | AI12: =IF(AND(F12<=DATE(2027,3,1),OR(G12="",G12>=DATE(2027,3,1))),H12*(1+Assumptions!$C$7)^2,0) -> 11664 | AJ12: =IF(AND(F12<=DATE(2027,4,1),OR(G12="",G12>=DATE(2027,4,1))),H12*(1+Assumptions!$C$7)^2,0) -> 11664 | AK12: =IF(AND(F12<=DATE(2027,5,1),OR(G12="",G12>=DATE(2027,5,1))),H12*(1+Assumptions!$C$7)^2,0) -> 11664 | AL12: =IF(AND(F12<=DATE(2027,6,1),OR(G12="",G12>=DATE(2027,6,1))),H12*(1+Assumptions!$C$7)^2,0) -> 11664 | AM12: =IF(AND(F12<=DATE(2027,7,1),OR(G12="",G12>=DATE(2027,7,1))),H12*(1+Assumptions!$C$7)^2,0) -> 11664 | AN12: =IF(AND(F12<=DATE(2027,8,1),OR(G12="",G12>=DATE(2027,8,1))),H12*(1+Assumptions!$C$7)^2,0) -> 11664 | AO12: =IF(AND(F12<=DATE(2027,9,1),OR(G12="",G12>=DATE(2027,9,1))),H12*(1+Assumptions!$C$7)^2,0) -> 11664 | AP12: =IF(AND(F12<=DATE(2027,10,1),OR(G12="",G12>=DATE(2027,10,1))),H12*(1+Assumptions!$C$7)^2,0) -> 11664 | AQ12: =IF(AND(F12<=DATE(2027,11,1),OR(G12="",G12>=DATE(2027,11,1))),H12*(1+Assumptions!$C$7)^2,0) -> 11664 | AR12: =IF(AND(F12<=DATE(2027,12,1),OR(G12="",G12>=DATE(2027,12,1))),H12*(1+Assumptions!$C$7)^2,0) -> 11664 | AS12: =IF(AND(F12<=DATE(2028,1,1),OR(G12="",G12>=DATE(2028,1,1))),H12*(1+Assumptions!$C$7)^3,0) -> 12597.12 | AT12: =IF(AND(F12<=DATE(2028,2,1),OR(G12="",G12>=DATE(2028,2,1))),H12*(1+Assumptions!$C$7)^3,0) -> 12597.12 | AU12: =IF(AND(F12<=DATE(2028,3,1),OR(G12="",G12>=DATE(2028,3,1))),H12*(1+Assumptions!$C$7)^3,0) -> 12597.12 | AV12: =IF(AND(F12<=DATE(2028,4,1),OR(G12="",G12>=DATE(2028,4,1))),H12*(1+Assumptions!$C$7)^3,0) -> 12597.12 | AW12: =IF(AND(F12<=DATE(2028,5,1),OR(G12="",G12>=DATE(2028,5,1))),H12*(1+Assumptions!$C$7)^3,0) -> 12597.12 | AX12: =IF(AND(F12<=DATE(2028,6,1),OR(G12="",G12>=DATE(2028,6,1))),H12*(1+Assumptions!$C$7)^3,0) -> 12597.12 | AY12: =IF(AND(F12<=DATE(2028,7,1),OR(G12="",G12>=DATE(2028,7,1))),H12*(1+Assumptions!$C$7)^3,0) -> 12597.12 | AZ12: =IF(AND(F12<=DATE(2028,8,1),OR(G12="",G12>=DATE(2028,8,1))),H12*(1+Assumptions!$C$7)^3,0) -> 12597.12 | BA12: =IF(AND(F12<=DATE(2028,9,1),OR(G12="",G12>=DATE(2028,9,1))),H12*(1+Assumptions!$C$7)^3,0) -> 12597.12 | BB12: =IF(AND(F12<=DATE(2028,10,1),OR(G12="",G12>=DATE(2028,10,1))),H12*(1+Assumptions!$C$7)^3,0) -> 12597.12 | BC12: =IF(AND(F12<=DATE(2028,11,1),OR(G12="",G12>=DATE(2028,11,1))),H12*(1+Assumptions!$C$7)^3,0) -> 12597.12 | BD12: =IF(AND(F12<=DATE(2028,12,1),OR(G12="",G12>=DATE(2028,12,1))),H12*(1+Assumptions!$C$7)^3,0) -> 12597.12 | BE12: =IF(AND(G12<=DATE(2028,12,1),OR(H12="",H12>=DATE(2028,12,1))),I12*(1+Assumptions!$C$7)^3,0) -> 0 | BF12: =IF(AND(H12<=DATE(2028,12,1),OR(I12="",I12>=DATE(2028,12,1))),J12*(1+Assumptions!$C$7)^3,0) -> 0 | BG12: =IF(AND(I12<=DATE(2028,12,1),OR(J12="",J12>=DATE(2028,12,1))),K12*(1+Assumptions!$C$7)^3,0) -> 0 | BH12: =IF(AND(J12<=DATE(2028,12,1),OR(K12="",K12>=DATE(2028,12,1))),L12*(1+Assumptions!$C$7)^3,0) -> 0 | BI12: =IF(AND(K12<=DATE(2028,12,1),OR(L12="",L12>=DATE(2028,12,1))),M12*(1+Assumptions!$C$7)^3,0) -> 0 | BJ12: =IF(AND(L12<=DATE(2028,12,1),OR(M12="",M12>=DATE(2028,12,1))),N12*(1+Assumptions!$C$7)^3,0) -> 0 | BK12: =IF(AND(M12<=DATE(2028,12,1),OR(N12="",N12>=DATE(2028,12,1))),O12*(1+Assumptions!$C$7)^3,0) -> 0 | ... BP12: =IF(AND(R12<=DATE(2028,12,1),OR(S12="",S12>=DATE(2028,12,1))),T12*(1+Assumptions!$C$7)^3,0) -> 0
A13: 10 | B13: CEO | C13: G&A | D13: CEO | E13: Current | F13: 46266 | H13: 11500 | I13: =IF(AND(F13<=DATE(2025,1,1),OR(G13="",G13>=DATE(2025,1,1))),H13*(1+Assumptions!$C$7)^0,0) -> 0 | J13: =IF(AND(F13<=DATE(2025,2,1),OR(G13="",G13>=DATE(2025,2,1))),H13*(1+Assumptions!$C$7)^0,0) -> 0 | K13: =IF(AND(F13<=DATE(2025,3,1),OR(G13="",G13>=DATE(2025,3,1))),H13*(1+Assumptions!$C$7)^0,0) -> 0 | L13: =IF(AND(F13<=DATE(2025,4,1),OR(G13="",G13>=DATE(2025,4,1))),H13*(1+Assumptions!$C$7)^0,0) -> 0 | M13: =IF(AND(F13<=DATE(2025,5,1),OR(G13="",G13>=DATE(2025,5,1))),H13*(1+Assumptions!$C$7)^0,0) -> 0 | N13: =IF(AND(F13<=DATE(2025,6,1),OR(G13="",G13>=DATE(2025,6,1))),H13*(1+Assumptions!$C$7)^0,0) -> 0 | O13: =IF(AND(F13<=DATE(2025,7,1),OR(G13="",G13>=DATE(2025,7,1))),H13*(1+Assumptions!$C$7)^0,0) -> 0 | P13: =IF(AND(F13<=DATE(2025,8,1),OR(G13="",G13>=DATE(2025,8,1))),H13*(1+Assumptions!$C$7)^0,0) -> 0 | Q13: 7500 | R13: 7500 | S13: 7500 | T13: 7500 | U13: 7500 | V13: 7500 | W13: 7500 | X13: 7500 | Y13: 7500 | Z13: 7500 | AA13: 7500 | AB13: 7500 | AC13: =IF(AND(F13<=DATE(2026,9,1),OR(G13="",G13>=DATE(2026,9,1))),H13*(1+Assumptions!$C$7)^1,0) -> 12420 | AD13: =IF(AND(F13<=DATE(2026,10,1),OR(G13="",G13>=DATE(2026,10,1))),H13*(1+Assumptions!$C$7)^1,0) -> 12420 | AE13: =IF(AND(F13<=DATE(2026,11,1),OR(G13="",G13>=DATE(2026,11,1))),H13*(1+Assumptions!$C$7)^1,0) -> 12420 | AF13: =IF(AND(F13<=DATE(2026,12,1),OR(G13="",G13>=DATE(2026,12,1))),H13*(1+Assumptions!$C$7)^1,0) -> 12420 | AG13: =IF(AND(F13<=DATE(2027,1,1),OR(G13="",G13>=DATE(2027,1,1))),H13*(1+Assumptions!$C$7)^2,0) -> 13413.6 | AH13: =IF(AND(F13<=DATE(2027,2,1),OR(G13="",G13>=DATE(2027,2,1))),H13*(1+Assumptions!$C$7)^2,0) -> 13413.6 | AI13: =IF(AND(F13<=DATE(2027,3,1),OR(G13="",G13>=DATE(2027,3,1))),H13*(1+Assumptions!$C$7)^2,0) -> 13413.6 | AJ13: =IF(AND(F13<=DATE(2027,4,1),OR(G13="",G13>=DATE(2027,4,1))),H13*(1+Assumptions!$C$7)^2,0) -> 13413.6 | AK13: =IF(AND(F13<=DATE(2027,5,1),OR(G13="",G13>=DATE(2027,5,1))),H13*(1+Assumptions!$C$7)^2,0) -> 13413.6 | AL13: =IF(AND(F13<=DATE(2027,6,1),OR(G13="",G13>=DATE(2027,6,1))),H13*(1+Assumptions!$C$7)^2,0) -> 13413.6 | AM13: =IF(AND(F13<=DATE(2027,7,1),OR(G13="",G13>=DATE(2027,7,1))),H13*(1+Assumptions!$C$7)^2,0) -> 13413.6 | AN13: =IF(AND(F13<=DATE(2027,8,1),OR(G13="",G13>=DATE(2027,8,1))),H13*(1+Assumptions!$C$7)^2,0) -> 13413.6 | AO13: =IF(AND(F13<=DATE(2027,9,1),OR(G13="",G13>=DATE(2027,9,1))),H13*(1+Assumptions!$C$7)^2,0) -> 13413.6 | AP13: =IF(AND(F13<=DATE(2027,10,1),OR(G13="",G13>=DATE(2027,10,1))),H13*(1+Assumptions!$C$7)^2,0) -> 13413.6 | AQ13: =IF(AND(F13<=DATE(2027,11,1),OR(G13="",G13>=DATE(2027,11,1))),H13*(1+Assumptions!$C$7)^2,0) -> 13413.6 | AR13: =IF(AND(F13<=DATE(2027,12,1),OR(G13="",G13>=DATE(2027,12,1))),H13*(1+Assumptions!$C$7)^2,0) -> 13413.6 | AS13: =IF(AND(F13<=DATE(2028,1,1),OR(G13="",G13>=DATE(2028,1,1))),H13*(1+Assumptions!$C$7)^3,0) -> 14486.688 | AT13: =IF(AND(F13<=DATE(2028,2,1),OR(G13="",G13>=DATE(2028,2,1))),H13*(1+Assumptions!$C$7)^3,0) -> 14486.688 | AU13: =IF(AND(F13<=DATE(2028,3,1),OR(G13="",G13>=DATE(2028,3,1))),H13*(1+Assumptions!$C$7)^3,0) -> 14486.688 | AV13: =IF(AND(F13<=DATE(2028,4,1),OR(G13="",G13>=DATE(2028,4,1))),H13*(1+Assumptions!$C$7)^3,0) -> 14486.688 | AW13: =IF(AND(F13<=DATE(2028,5,1),OR(G13="",G13>=DATE(2028,5,1))),H13*(1+Assumptions!$C$7)^3,0) -> 14486.688 | AX13: =IF(AND(F13<=DATE(2028,6,1),OR(G13="",G13>=DATE(2028,6,1))),H13*(1+Assumptions!$C$7)^3,0) -> 14486.688 | AY13: =IF(AND(F13<=DATE(2028,7,1),OR(G13="",G13>=DATE(2028,7,1))),H13*(1+Assumptions!$C$7)^3,0) -> 14486.688 | AZ13: =IF(AND(F13<=DATE(2028,8,1),OR(G13="",G13>=DATE(2028,8,1))),H13*(1+Assumptions!$C$7)^3,0) -> 14486.688 | BA13: =IF(AND(F13<=DATE(2028,9,1),OR(G13="",G13>=DATE(2028,9,1))),H13*(1+Assumptions!$C$7)^3,0) -> 14486.688 | BB13: =IF(AND(F13<=DATE(2028,10,1),OR(G13="",G13>=DATE(2028,10,1))),H13*(1+Assumptions!$C$7)^3,0) -> 14486.688 | BC13: =IF(AND(F13<=DATE(2028,11,1),OR(G13="",G13>=DATE(2028,11,1))),H13*(1+Assumptions!$C$7)^3,0) -> 14486.688 | BD13: =IF(AND(F13<=DATE(2028,12,1),OR(G13="",G13>=DATE(2028,12,1))),H13*(1+Assumptions!$C$7)^3,0) -> 14486.688 | BE13: =IF(AND(G13<=DATE(2028,12,1),OR(H13="",H13>=DATE(2028,12,1))),I13*(1+Assumptions!$C$7)^3,0) -> 0 | BF13: =IF(AND(H13<=DATE(2028,12,1),OR(I13="",I13>=DATE(2028,12,1))),J13*(1+Assumptions!$C$7)^3,0) -> 0 | BG13: =IF(AND(I13<=DATE(2028,12,1),OR(J13="",J13>=DATE(2028,12,1))),K13*(1+Assumptions!$C$7)^3,0) -> 0 | BH13: =IF(AND(J13<=DATE(2028,12,1),OR(K13="",K13>=DATE(2028,12,1))),L13*(1+Assumptions!$C$7)^3,0) -> 0 | BI13: =IF(AND(K13<=DATE(2028,12,1),OR(L13="",L13>=DATE(2028,12,1))),M13*(1+Assumptions!$C$7)^3,0) -> 0 | BJ13: =IF(AND(L13<=DATE(2028,12,1),OR(M13="",M13>=DATE(2028,12,1))),N13*(1+Assumptions!$C$7)^3,0) -> 0 | BK13: =IF(AND(M13<=DATE(2028,12,1),OR(N13="",N13>=DATE(2028,12,1))),O13*(1+Assumptions!$C$7)^3,0) -> 0 | ... BP13: =IF(AND(R13<=DATE(2028,12,1),OR(S13="",S13>=DATE(2028,12,1))),T13*(1+Assumptions!$C$7)^3,0) -> 0
A15: # | B15: PLANNED HIRES
A16: 12 | B16: New hire | C16: R&D | D16: Software Engineer | E16: Planned | F16: 46204 | H16: 8000 | I16: =IF(AND($F16<=I$2, OR($G16="",$G16>=I$2)), $H16 * (1 + Assumptions!$C$7) ^ INT(((YEAR(I$2)-YEAR($F16))*12 + MONTH(I$2)-MONTH($F16)) / 12), 0) -> 0 | J16: =IF(AND($F16<=J$2, OR($G16="",$G16>=J$2)), $H16 * (1 + Assumptions!$C$7) ^ INT(((YEAR(J$2)-YEAR($F16))*12 + MONTH(J$2)-MONTH($F16)) / 12), 0) -> 0 | K16: =IF(AND($F16<=K$2, OR($G16="",$G16>=K$2)), $H16 * (1 + Assumptions!$C$7) ^ INT(((YEAR(K$2)-YEAR($F16))*12 + MONTH(K$2)-MONTH($F16)) / 12), 0) -> 0 | L16: =IF(AND($F16<=L$2, OR($G16="",$G16>=L$2)), $H16 * (1 + Assumptions!$C$7) ^ INT(((YEAR(L$2)-YEAR($F16))*12 + MONTH(L$2)-MONTH($F16)) / 12), 0) -> 0 | M16: =IF(AND($F16<=M$2, OR($G16="",$G16>=M$2)), $H16 * (1 + Assumptions!$C$7) ^ INT(((YEAR(M$2)-YEAR($F16))*12 + MONTH(M$2)-MONTH($F16)) / 12), 0) -> 0 | N16: =IF(AND($F16<=N$2, OR($G16="",$G16>=N$2)), $H16 * (1 + Assumptions!$C$7) ^ INT(((YEAR(N$2)-YEAR($F16))*12 + MONTH(N$2)-MONTH($F16)) / 12), 0) -> 0 | O16: =IF(AND($F16<=O$2, OR($G16="",$G16>=O$2)), $H16 * (1 + Assumptions!$C$7) ^ INT(((YEAR(O$2)-YEAR($F16))*12 + MONTH(O$2)-MONTH($F16)) / 12), 0) -> 0 | P16: =IF(AND($F16<=P$2, OR($G16="",$G16>=P$2)), $H16 * (1 + Assumptions!$C$7) ^ INT(((YEAR(P$2)-YEAR($F16))*12 + MONTH(P$2)-MONTH($F16)) / 12), 0) -> 0 | ... BP16: =IF(AND($F16<=BP$2, OR($G16="",$G16>=BP$2)), $H16 * (1 + Assumptions!$C$7) ^ INT(((YEAR(BP$2)-YEAR($F16))*12 + MONTH(BP$2)-MONTH($F16)) / 12), 0) -> 10077.696
A17: 13 | B17: New hire | C17: G&A | D17: COO | E17: Planned | F17: 46235 | H17: 9000 | I17: =IF(AND($F17<=I$2, OR($G17="",$G17>=I$2)), $H17 * (1 + Assumptions!$C$7) ^ INT(((YEAR(I$2)-YEAR($F17))*12 + MONTH(I$2)-MONTH($F17)) / 12), 0) -> 0 | J17: =IF(AND($F17<=J$2, OR($G17="",$G17>=J$2)), $H17 * (1 + Assumptions!$C$7) ^ INT(((YEAR(J$2)-YEAR($F17))*12 + MONTH(J$2)-MONTH($F17)) / 12), 0) -> 0 | K17: =IF(AND($F17<=K$2, OR($G17="",$G17>=K$2)), $H17 * (1 + Assumptions!$C$7) ^ INT(((YEAR(K$2)-YEAR($F17))*12 + MONTH(K$2)-MONTH($F17)) / 12), 0) -> 0 | L17: =IF(AND($F17<=L$2, OR($G17="",$G17>=L$2)), $H17 * (1 + Assumptions!$C$7) ^ INT(((YEAR(L$2)-YEAR($F17))*12 + MONTH(L$2)-MONTH($F17)) / 12), 0) -> 0 | M17: =IF(AND($F17<=M$2, OR($G17="",$G17>=M$2)), $H17 * (1 + Assumptions!$C$7) ^ INT(((YEAR(M$2)-YEAR($F17))*12 + MONTH(M$2)-MONTH($F17)) / 12), 0) -> 0 | N17: =IF(AND($F17<=N$2, OR($G17="",$G17>=N$2)), $H17 * (1 + Assumptions!$C$7) ^ INT(((YEAR(N$2)-YEAR($F17))*12 + MONTH(N$2)-MONTH($F17)) / 12), 0) -> 0 | O17: =IF(AND($F17<=O$2, OR($G17="",$G17>=O$2)), $H17 * (1 + Assumptions!$C$7) ^ INT(((YEAR(O$2)-YEAR($F17))*12 + MONTH(O$2)-MONTH($F17)) / 12), 0) -> 0 | P17: =IF(AND($F17<=P$2, OR($G17="",$G17>=P$2)), $H17 * (1 + Assumptions!$C$7) ^ INT(((YEAR(P$2)-YEAR($F17))*12 + MONTH(P$2)-MONTH($F17)) / 12), 0) -> 0 | ... BP17: =IF(AND($F17<=BP$2, OR($G17="",$G17>=BP$2)), $H17 * (1 + Assumptions!$C$7) ^ INT(((YEAR(BP$2)-YEAR($F17))*12 + MONTH(BP$2)-MONTH($F17)) / 12), 0) -> 11337.408
A18: 14 | B18: New hire | C18: R&D | D18: Maintenance Engineer | E18: Planned | F18: 46235 | H18: 6000 | I18: =IF(AND($F18<=I$2, OR($G18="",$G18>=I$2)), $H18 * (1 + Assumptions!$C$7) ^ INT(((YEAR(I$2)-YEAR($F18))*12 + MONTH(I$2)-MONTH($F18)) / 12), 0) -> 0 | J18: =IF(AND($F18<=J$2, OR($G18="",$G18>=J$2)), $H18 * (1 + Assumptions!$C$7) ^ INT(((YEAR(J$2)-YEAR($F18))*12 + MONTH(J$2)-MONTH($F18)) / 12), 0) -> 0 | K18: =IF(AND($F18<=K$2, OR($G18="",$G18>=K$2)), $H18 * (1 + Assumptions!$C$7) ^ INT(((YEAR(K$2)-YEAR($F18))*12 + MONTH(K$2)-MONTH($F18)) / 12), 0) -> 0 | L18: =IF(AND($F18<=L$2, OR($G18="",$G18>=L$2)), $H18 * (1 + Assumptions!$C$7) ^ INT(((YEAR(L$2)-YEAR($F18))*12 + MONTH(L$2)-MONTH($F18)) / 12), 0) -> 0 | M18: =IF(AND($F18<=M$2, OR($G18="",$G18>=M$2)), $H18 * (1 + Assumptions!$C$7) ^ INT(((YEAR(M$2)-YEAR($F18))*12 + MONTH(M$2)-MONTH($F18)) / 12), 0) -> 0 | N18: =IF(AND($F18<=N$2, OR($G18="",$G18>=N$2)), $H18 * (1 + Assumptions!$C$7) ^ INT(((YEAR(N$2)-YEAR($F18))*12 + MONTH(N$2)-MONTH($F18)) / 12), 0) -> 0 | O18: =IF(AND($F18<=O$2, OR($G18="",$G18>=O$2)), $H18 * (1 + Assumptions!$C$7) ^ INT(((YEAR(O$2)-YEAR($F18))*12 + MONTH(O$2)-MONTH($F18)) / 12), 0) -> 0 | P18: =IF(AND($F18<=P$2, OR($G18="",$G18>=P$2)), $H18 * (1 + Assumptions!$C$7) ^ INT(((YEAR(P$2)-YEAR($F18))*12 + MONTH(P$2)-MONTH($F18)) / 12), 0) -> 0 | ... BP18: =IF(AND($F18<=BP$2, OR($G18="",$G18>=BP$2)), $H18 * (1 + Assumptions!$C$7) ^ INT(((YEAR(BP$2)-YEAR($F18))*12 + MONTH(BP$2)-MONTH($F18)) / 12), 0) -> 7558.272
A19: 15 | B19: New hire | C19: S&M | D19: Marketing | E19: Planned | F19: 46235 | H19: 9000 | I19: =IF(AND($F19<=I$2, OR($G19="",$G19>=I$2)), $H19 * (1 + Assumptions!$C$7) ^ INT(((YEAR(I$2)-YEAR($F19))*12 + MONTH(I$2)-MONTH($F19)) / 12), 0) -> 0 | J19: =IF(AND($F19<=J$2, OR($G19="",$G19>=J$2)), $H19 * (1 + Assumptions!$C$7) ^ INT(((YEAR(J$2)-YEAR($F19))*12 + MONTH(J$2)-MONTH($F19)) / 12), 0) -> 0 | K19: =IF(AND($F19<=K$2, OR($G19="",$G19>=K$2)), $H19 * (1 + Assumptions!$C$7) ^ INT(((YEAR(K$2)-YEAR($F19))*12 + MONTH(K$2)-MONTH($F19)) / 12), 0) -> 0 | L19: =IF(AND($F19<=L$2, OR($G19="",$G19>=L$2)), $H19 * (1 + Assumptions!$C$7) ^ INT(((YEAR(L$2)-YEAR($F19))*12 + MONTH(L$2)-MONTH($F19)) / 12), 0) -> 0 | M19: =IF(AND($F19<=M$2, OR($G19="",$G19>=M$2)), $H19 * (1 + Assumptions!$C$7) ^ INT(((YEAR(M$2)-YEAR($F19))*12 + MONTH(M$2)-MONTH($F19)) / 12), 0) -> 0 | N19: =IF(AND($F19<=N$2, OR($G19="",$G19>=N$2)), $H19 * (1 + Assumptions!$C$7) ^ INT(((YEAR(N$2)-YEAR($F19))*12 + MONTH(N$2)-MONTH($F19)) / 12), 0) -> 0 | O19: =IF(AND($F19<=O$2, OR($G19="",$G19>=O$2)), $H19 * (1 + Assumptions!$C$7) ^ INT(((YEAR(O$2)-YEAR($F19))*12 + MONTH(O$2)-MONTH($F19)) / 12), 0) -> 0 | P19: =IF(AND($F19<=P$2, OR($G19="",$G19>=P$2)), $H19 * (1 + Assumptions!$C$7) ^ INT(((YEAR(P$2)-YEAR($F19))*12 + MONTH(P$2)-MONTH($F19)) / 12), 0) -> 0 | ... BP19: =IF(AND($F19<=BP$2, OR($G19="",$G19>=BP$2)), $H19 * (1 + Assumptions!$C$7) ^ INT(((YEAR(BP$2)-YEAR($F19))*12 + MONTH(BP$2)-MONTH($F19)) / 12), 0) -> 11337.408
A20: 16 | B20: New hire | C20: G&A | D20: CFO | E20: Planned | F20: 46296 | H20: 9500 | I20: =IF(AND($F20<=I$2, OR($G20="",$G20>=I$2)), $H20 * (1 + Assumptions!$C$7) ^ INT(((YEAR(I$2)-YEAR($F20))*12 + MONTH(I$2)-MONTH($F20)) / 12), 0) -> 0 | J20: =IF(AND($F20<=J$2, OR($G20="",$G20>=J$2)), $H20 * (1 + Assumptions!$C$7) ^ INT(((YEAR(J$2)-YEAR($F20))*12 + MONTH(J$2)-MONTH($F20)) / 12), 0) -> 0 | K20: =IF(AND($F20<=K$2, OR($G20="",$G20>=K$2)), $H20 * (1 + Assumptions!$C$7) ^ INT(((YEAR(K$2)-YEAR($F20))*12 + MONTH(K$2)-MONTH($F20)) / 12), 0) -> 0 | L20: =IF(AND($F20<=L$2, OR($G20="",$G20>=L$2)), $H20 * (1 + Assumptions!$C$7) ^ INT(((YEAR(L$2)-YEAR($F20))*12 + MONTH(L$2)-MONTH($F20)) / 12), 0) -> 0 | M20: =IF(AND($F20<=M$2, OR($G20="",$G20>=M$2)), $H20 * (1 + Assumptions!$C$7) ^ INT(((YEAR(M$2)-YEAR($F20))*12 + MONTH(M$2)-MONTH($F20)) / 12), 0) -> 0 | N20: =IF(AND($F20<=N$2, OR($G20="",$G20>=N$2)), $H20 * (1 + Assumptions!$C$7) ^ INT(((YEAR(N$2)-YEAR($F20))*12 + MONTH(N$2)-MONTH($F20)) / 12), 0) -> 0 | O20: =IF(AND($F20<=O$2, OR($G20="",$G20>=O$2)), $H20 * (1 + Assumptions!$C$7) ^ INT(((YEAR(O$2)-YEAR($F20))*12 + MONTH(O$2)-MONTH($F20)) / 12), 0) -> 0 | P20: =IF(AND($F20<=P$2, OR($G20="",$G20>=P$2)), $H20 * (1 + Assumptions!$C$7) ^ INT(((YEAR(P$2)-YEAR($F20))*12 + MONTH(P$2)-MONTH($F20)) / 12), 0) -> 0 | ... BP20: =IF(AND($F20<=BP$2, OR($G20="",$G20>=BP$2)), $H20 * (1 + Assumptions!$C$7) ^ INT(((YEAR(BP$2)-YEAR($F20))*12 + MONTH(BP$2)-MONTH($F20)) / 12), 0) -> 11967.264
A21: 17 | B21: New hire | C21: S&M | D21: Sales | E21: Planned | F21: 46296 | H21: 6500 | I21: =IF(AND($F21<=I$2, OR($G21="",$G21>=I$2)), $H21 * (1 + Assumptions!$C$7) ^ INT(((YEAR(I$2)-YEAR($F21))*12 + MONTH(I$2)-MONTH($F21)) / 12), 0) -> 0 | J21: =IF(AND($F21<=J$2, OR($G21="",$G21>=J$2)), $H21 * (1 + Assumptions!$C$7) ^ INT(((YEAR(J$2)-YEAR($F21))*12 + MONTH(J$2)-MONTH($F21)) / 12), 0) -> 0 | K21: =IF(AND($F21<=K$2, OR($G21="",$G21>=K$2)), $H21 * (1 + Assumptions!$C$7) ^ INT(((YEAR(K$2)-YEAR($F21))*12 + MONTH(K$2)-MONTH($F21)) / 12), 0) -> 0 | L21: =IF(AND($F21<=L$2, OR($G21="",$G21>=L$2)), $H21 * (1 + Assumptions!$C$7) ^ INT(((YEAR(L$2)-YEAR($F21))*12 + MONTH(L$2)-MONTH($F21)) / 12), 0) -> 0 | M21: =IF(AND($F21<=M$2, OR($G21="",$G21>=M$2)), $H21 * (1 + Assumptions!$C$7) ^ INT(((YEAR(M$2)-YEAR($F21))*12 + MONTH(M$2)-MONTH($F21)) / 12), 0) -> 0 | N21: =IF(AND($F21<=N$2, OR($G21="",$G21>=N$2)), $H21 * (1 + Assumptions!$C$7) ^ INT(((YEAR(N$2)-YEAR($F21))*12 + MONTH(N$2)-MONTH($F21)) / 12), 0) -> 0 | O21: =IF(AND($F21<=O$2, OR($G21="",$G21>=O$2)), $H21 * (1 + Assumptions!$C$7) ^ INT(((YEAR(O$2)-YEAR($F21))*12 + MONTH(O$2)-MONTH($F21)) / 12), 0) -> 0 | P21: =IF(AND($F21<=P$2, OR($G21="",$G21>=P$2)), $H21 * (1 + Assumptions!$C$7) ^ INT(((YEAR(P$2)-YEAR($F21))*12 + MONTH(P$2)-MONTH($F21)) / 12), 0) -> 0 | ... BP21: =IF(AND($F21<=BP$2, OR($G21="",$G21>=BP$2)), $H21 * (1 + Assumptions!$C$7) ^ INT(((YEAR(BP$2)-YEAR($F21))*12 + MONTH(BP$2)-MONTH($F21)) / 12), 0) -> 8188.128
A22: 18 | B22: New hire | C22: R&D | D22: R&D Engineer | E22: Planned | F22: 46388 | H22: 7500 | I22: =IF(AND($F22<=I$2, OR($G22="",$G22>=I$2)), $H22 * (1 + Assumptions!$C$7) ^ INT(((YEAR(I$2)-YEAR($F22))*12 + MONTH(I$2)-MONTH($F22)) / 12), 0) -> 0 | J22: =IF(AND($F22<=J$2, OR($G22="",$G22>=J$2)), $H22 * (1 + Assumptions!$C$7) ^ INT(((YEAR(J$2)-YEAR($F22))*12 + MONTH(J$2)-MONTH($F22)) / 12), 0) -> 0 | K22: =IF(AND($F22<=K$2, OR($G22="",$G22>=K$2)), $H22 * (1 + Assumptions!$C$7) ^ INT(((YEAR(K$2)-YEAR($F22))*12 + MONTH(K$2)-MONTH($F22)) / 12), 0) -> 0 | L22: =IF(AND($F22<=L$2, OR($G22="",$G22>=L$2)), $H22 * (1 + Assumptions!$C$7) ^ INT(((YEAR(L$2)-YEAR($F22))*12 + MONTH(L$2)-MONTH($F22)) / 12), 0) -> 0 | M22: =IF(AND($F22<=M$2, OR($G22="",$G22>=M$2)), $H22 * (1 + Assumptions!$C$7) ^ INT(((YEAR(M$2)-YEAR($F22))*12 + MONTH(M$2)-MONTH($F22)) / 12), 0) -> 0 | N22: =IF(AND($F22<=N$2, OR($G22="",$G22>=N$2)), $H22 * (1 + Assumptions!$C$7) ^ INT(((YEAR(N$2)-YEAR($F22))*12 + MONTH(N$2)-MONTH($F22)) / 12), 0) -> 0 | O22: =IF(AND($F22<=O$2, OR($G22="",$G22>=O$2)), $H22 * (1 + Assumptions!$C$7) ^ INT(((YEAR(O$2)-YEAR($F22))*12 + MONTH(O$2)-MONTH($F22)) / 12), 0) -> 0 | P22: =IF(AND($F22<=P$2, OR($G22="",$G22>=P$2)), $H22 * (1 + Assumptions!$C$7) ^ INT(((YEAR(P$2)-YEAR($F22))*12 + MONTH(P$2)-MONTH($F22)) / 12), 0) -> 0 | ... BP22: =IF(AND($F22<=BP$2, OR($G22="",$G22>=BP$2)), $H22 * (1 + Assumptions!$C$7) ^ INT(((YEAR(BP$2)-YEAR($F22))*12 + MONTH(BP$2)-MONTH($F22)) / 12), 0) -> 8748
A23: 19 | B23: New hire | C23: G&A | D23: Office Support | E23: Planned | F23: 46388 | H23: 4500 | I23: =IF(AND($F23<=I$2, OR($G23="",$G23>=I$2)), $H23 * (1 + Assumptions!$C$7) ^ INT(((YEAR(I$2)-YEAR($F23))*12 + MONTH(I$2)-MONTH($F23)) / 12), 0) -> 0 | J23: =IF(AND($F23<=J$2, OR($G23="",$G23>=J$2)), $H23 * (1 + Assumptions!$C$7) ^ INT(((YEAR(J$2)-YEAR($F23))*12 + MONTH(J$2)-MONTH($F23)) / 12), 0) -> 0 | K23: =IF(AND($F23<=K$2, OR($G23="",$G23>=K$2)), $H23 * (1 + Assumptions!$C$7) ^ INT(((YEAR(K$2)-YEAR($F23))*12 + MONTH(K$2)-MONTH($F23)) / 12), 0) -> 0 | L23: =IF(AND($F23<=L$2, OR($G23="",$G23>=L$2)), $H23 * (1 + Assumptions!$C$7) ^ INT(((YEAR(L$2)-YEAR($F23))*12 + MONTH(L$2)-MONTH($F23)) / 12), 0) -> 0 | M23: =IF(AND($F23<=M$2, OR($G23="",$G23>=M$2)), $H23 * (1 + Assumptions!$C$7) ^ INT(((YEAR(M$2)-YEAR($F23))*12 + MONTH(M$2)-MONTH($F23)) / 12), 0) -> 0 | N23: =IF(AND($F23<=N$2, OR($G23="",$G23>=N$2)), $H23 * (1 + Assumptions!$C$7) ^ INT(((YEAR(N$2)-YEAR($F23))*12 + MONTH(N$2)-MONTH($F23)) / 12), 0) -> 0 | O23: =IF(AND($F23<=O$2, OR($G23="",$G23>=O$2)), $H23 * (1 + Assumptions!$C$7) ^ INT(((YEAR(O$2)-YEAR($F23))*12 + MONTH(O$2)-MONTH($F23)) / 12), 0) -> 0 | P23: =IF(AND($F23<=P$2, OR($G23="",$G23>=P$2)), $H23 * (1 + Assumptions!$C$7) ^ INT(((YEAR(P$2)-YEAR($F23))*12 + MONTH(P$2)-MONTH($F23)) / 12), 0) -> 0 | ... BP23: =IF(AND($F23<=BP$2, OR($G23="",$G23>=BP$2)), $H23 * (1 + Assumptions!$C$7) ^ INT(((YEAR(BP$2)-YEAR($F23))*12 + MONTH(BP$2)-MONTH($F23)) / 12), 0) -> 5248.8
A24: 20 | B24: New hire | C24: R&D | D24: Product | E24: Planned | F24: 46388 | H24: 6500 | I24: =IF(AND($F24<=I$2, OR($G24="",$G24>=I$2)), $H24 * (1 + Assumptions!$C$7) ^ INT(((YEAR(I$2)-YEAR($F24))*12 + MONTH(I$2)-MONTH($F24)) / 12), 0) -> 0 | J24: =IF(AND($F24<=J$2, OR($G24="",$G24>=J$2)), $H24 * (1 + Assumptions!$C$7) ^ INT(((YEAR(J$2)-YEAR($F24))*12 + MONTH(J$2)-MONTH($F24)) / 12), 0) -> 0 | K24: =IF(AND($F24<=K$2, OR($G24="",$G24>=K$2)), $H24 * (1 + Assumptions!$C$7) ^ INT(((YEAR(K$2)-YEAR($F24))*12 + MONTH(K$2)-MONTH($F24)) / 12), 0) -> 0 | L24: =IF(AND($F24<=L$2, OR($G24="",$G24>=L$2)), $H24 * (1 + Assumptions!$C$7) ^ INT(((YEAR(L$2)-YEAR($F24))*12 + MONTH(L$2)-MONTH($F24)) / 12), 0) -> 0 | M24: =IF(AND($F24<=M$2, OR($G24="",$G24>=M$2)), $H24 * (1 + Assumptions!$C$7) ^ INT(((YEAR(M$2)-YEAR($F24))*12 + MONTH(M$2)-MONTH($F24)) / 12), 0) -> 0 | N24: =IF(AND($F24<=N$2, OR($G24="",$G24>=N$2)), $H24 * (1 + Assumptions!$C$7) ^ INT(((YEAR(N$2)-YEAR($F24))*12 + MONTH(N$2)-MONTH($F24)) / 12), 0) -> 0 | O24: =IF(AND($F24<=O$2, OR($G24="",$G24>=O$2)), $H24 * (1 + Assumptions!$C$7) ^ INT(((YEAR(O$2)-YEAR($F24))*12 + MONTH(O$2)-MONTH($F24)) / 12), 0) -> 0 | P24: =IF(AND($F24<=P$2, OR($G24="",$G24>=P$2)), $H24 * (1 + Assumptions!$C$7) ^ INT(((YEAR(P$2)-YEAR($F24))*12 + MONTH(P$2)-MONTH($F24)) / 12), 0) -> 0 | ... BP24: =IF(AND($F24<=BP$2, OR($G24="",$G24>=BP$2)), $H24 * (1 + Assumptions!$C$7) ^ INT(((YEAR(BP$2)-YEAR($F24))*12 + MONTH(BP$2)-MONTH($F24)) / 12), 0) -> 7581.6
A25: 21 | B25: New hire | C25: G&A | D25: Logistics | E25: Planned | F25: 46388 | H25: 6500 | I25: =IF(AND($F25<=I$2, OR($G25="",$G25>=I$2)), $H25 * (1 + Assumptions!$C$7) ^ INT(((YEAR(I$2)-YEAR($F25))*12 + MONTH(I$2)-MONTH($F25)) / 12), 0) -> 0 | J25: =IF(AND($F25<=J$2, OR($G25="",$G25>=J$2)), $H25 * (1 + Assumptions!$C$7) ^ INT(((YEAR(J$2)-YEAR($F25))*12 + MONTH(J$2)-MONTH($F25)) / 12), 0) -> 0 | K25: =IF(AND($F25<=K$2, OR($G25="",$G25>=K$2)), $H25 * (1 + Assumptions!$C$7) ^ INT(((YEAR(K$2)-YEAR($F25))*12 + MONTH(K$2)-MONTH($F25)) / 12), 0) -> 0 | L25: =IF(AND($F25<=L$2, OR($G25="",$G25>=L$2)), $H25 * (1 + Assumptions!$C$7) ^ INT(((YEAR(L$2)-YEAR($F25))*12 + MONTH(L$2)-MONTH($F25)) / 12), 0) -> 0 | M25: =IF(AND($F25<=M$2, OR($G25="",$G25>=M$2)), $H25 * (1 + Assumptions!$C$7) ^ INT(((YEAR(M$2)-YEAR($F25))*12 + MONTH(M$2)-MONTH($F25)) / 12), 0) -> 0 | N25: =IF(AND($F25<=N$2, OR($G25="",$G25>=N$2)), $H25 * (1 + Assumptions!$C$7) ^ INT(((YEAR(N$2)-YEAR($F25))*12 + MONTH(N$2)-MONTH($F25)) / 12), 0) -> 0 | O25: =IF(AND($F25<=O$2, OR($G25="",$G25>=O$2)), $H25 * (1 + Assumptions!$C$7) ^ INT(((YEAR(O$2)-YEAR($F25))*12 + MONTH(O$2)-MONTH($F25)) / 12), 0) -> 0 | P25: =IF(AND($F25<=P$2, OR($G25="",$G25>=P$2)), $H25 * (1 + Assumptions!$C$7) ^ INT(((YEAR(P$2)-YEAR($F25))*12 + MONTH(P$2)-MONTH($F25)) / 12), 0) -> 0 | ... BP25: =IF(AND($F25<=BP$2, OR($G25="",$G25>=BP$2)), $H25 * (1 + Assumptions!$C$7) ^ INT(((YEAR(BP$2)-YEAR($F25))*12 + MONTH(BP$2)-MONTH($F25)) / 12), 0) -> 7581.6
A26: 22 | B26: New hire | C26: R&D | D26: Field Engineer | E26: Planned | F26: 46388 | H26: 6500 | I26: =IF(AND($F26<=I$2, OR($G26="",$G26>=I$2)), $H26 * (1 + Assumptions!$C$7) ^ INT(((YEAR(I$2)-YEAR($F26))*12 + MONTH(I$2)-MONTH($F26)) / 12), 0) -> 0 | J26: =IF(AND($F26<=J$2, OR($G26="",$G26>=J$2)), $H26 * (1 + Assumptions!$C$7) ^ INT(((YEAR(J$2)-YEAR($F26))*12 + MONTH(J$2)-MONTH($F26)) / 12), 0) -> 0 | K26: =IF(AND($F26<=K$2, OR($G26="",$G26>=K$2)), $H26 * (1 + Assumptions!$C$7) ^ INT(((YEAR(K$2)-YEAR($F26))*12 + MONTH(K$2)-MONTH($F26)) / 12), 0) -> 0 | L26: =IF(AND($F26<=L$2, OR($G26="",$G26>=L$2)), $H26 * (1 + Assumptions!$C$7) ^ INT(((YEAR(L$2)-YEAR($F26))*12 + MONTH(L$2)-MONTH($F26)) / 12), 0) -> 0 | M26: =IF(AND($F26<=M$2, OR($G26="",$G26>=M$2)), $H26 * (1 + Assumptions!$C$7) ^ INT(((YEAR(M$2)-YEAR($F26))*12 + MONTH(M$2)-MONTH($F26)) / 12), 0) -> 0 | N26: =IF(AND($F26<=N$2, OR($G26="",$G26>=N$2)), $H26 * (1 + Assumptions!$C$7) ^ INT(((YEAR(N$2)-YEAR($F26))*12 + MONTH(N$2)-MONTH($F26)) / 12), 0) -> 0 | O26: =IF(AND($F26<=O$2, OR($G26="",$G26>=O$2)), $H26 * (1 + Assumptions!$C$7) ^ INT(((YEAR(O$2)-YEAR($F26))*12 + MONTH(O$2)-MONTH($F26)) / 12), 0) -> 0 | P26: =IF(AND($F26<=P$2, OR($G26="",$G26>=P$2)), $H26 * (1 + Assumptions!$C$7) ^ INT(((YEAR(P$2)-YEAR($F26))*12 + MONTH(P$2)-MONTH($F26)) / 12), 0) -> 0 | ... BP26: =IF(AND($F26<=BP$2, OR($G26="",$G26>=BP$2)), $H26 * (1 + Assumptions!$C$7) ^ INT(((YEAR(BP$2)-YEAR($F26))*12 + MONTH(BP$2)-MONTH($F26)) / 12), 0) -> 7581.6
A27: 23 | B27: New hire | C27: R&D | D27: Field Engineer | E27: Planned | F27: 46539 | H27: 6500 | I27: =IF(AND($F27<=I$2, OR($G27="",$G27>=I$2)), $H27 * (1 + Assumptions!$C$7) ^ INT(((YEAR(I$2)-YEAR($F27))*12 + MONTH(I$2)-MONTH($F27)) / 12), 0) -> 0 | J27: =IF(AND($F27<=J$2, OR($G27="",$G27>=J$2)), $H27 * (1 + Assumptions!$C$7) ^ INT(((YEAR(J$2)-YEAR($F27))*12 + MONTH(J$2)-MONTH($F27)) / 12), 0) -> 0 | K27: =IF(AND($F27<=K$2, OR($G27="",$G27>=K$2)), $H27 * (1 + Assumptions!$C$7) ^ INT(((YEAR(K$2)-YEAR($F27))*12 + MONTH(K$2)-MONTH($F27)) / 12), 0) -> 0 | L27: =IF(AND($F27<=L$2, OR($G27="",$G27>=L$2)), $H27 * (1 + Assumptions!$C$7) ^ INT(((YEAR(L$2)-YEAR($F27))*12 + MONTH(L$2)-MONTH($F27)) / 12), 0) -> 0 | M27: =IF(AND($F27<=M$2, OR($G27="",$G27>=M$2)), $H27 * (1 + Assumptions!$C$7) ^ INT(((YEAR(M$2)-YEAR($F27))*12 + MONTH(M$2)-MONTH($F27)) / 12), 0) -> 0 | N27: =IF(AND($F27<=N$2, OR($G27="",$G27>=N$2)), $H27 * (1 + Assumptions!$C$7) ^ INT(((YEAR(N$2)-YEAR($F27))*12 + MONTH(N$2)-MONTH($F27)) / 12), 0) -> 0 | O27: =IF(AND($F27<=O$2, OR($G27="",$G27>=O$2)), $H27 * (1 + Assumptions!$C$7) ^ INT(((YEAR(O$2)-YEAR($F27))*12 + MONTH(O$2)-MONTH($F27)) / 12), 0) -> 0 | P27: =IF(AND($F27<=P$2, OR($G27="",$G27>=P$2)), $H27 * (1 + Assumptions!$C$7) ^ INT(((YEAR(P$2)-YEAR($F27))*12 + MONTH(P$2)-MONTH($F27)) / 12), 0) -> 0 | ... BP27: =IF(AND($F27<=BP$2, OR($G27="",$G27>=BP$2)), $H27 * (1 + Assumptions!$C$7) ^ INT(((YEAR(BP$2)-YEAR($F27))*12 + MONTH(BP$2)-MONTH($F27)) / 12), 0) -> 7581.6
... A43: 39 | B43: New hire | C43: G&A | D43: Finance | E43: Planned | F43: 47394 | H43: 7500 | I43: =IF(AND($F43<=I$2, OR($G43="",$G43>=I$2)), $H43 * (1 + Assumptions!$C$7) ^ INT(((YEAR(I$2)-YEAR($F43))*12 + MONTH(I$2)-MONTH($F43)) / 12), 0) -> 0 | J43: =IF(AND($F43<=J$2, OR($G43="",$G43>=J$2)), $H43 * (1 + Assumptions!$C$7) ^ INT(((YEAR(J$2)-YEAR($F43))*12 + MONTH(J$2)-MONTH($F43)) / 12), 0) -> 0 | K43: =IF(AND($F43<=K$2, OR($G43="",$G43>=K$2)), $H43 * (1 + Assumptions!$C$7) ^ INT(((YEAR(K$2)-YEAR($F43))*12 + MONTH(K$2)-MONTH($F43)) / 12), 0) -> 0 | L43: =IF(AND($F43<=L$2, OR($G43="",$G43>=L$2)), $H43 * (1 + Assumptions!$C$7) ^ INT(((YEAR(L$2)-YEAR($F43))*12 + MONTH(L$2)-MONTH($F43)) / 12), 0) -> 0 | M43: =IF(AND($F43<=M$2, OR($G43="",$G43>=M$2)), $H43 * (1 + Assumptions!$C$7) ^ INT(((YEAR(M$2)-YEAR($F43))*12 + MONTH(M$2)-MONTH($F43)) / 12), 0) -> 0 | N43: =IF(AND($F43<=N$2, OR($G43="",$G43>=N$2)), $H43 * (1 + Assumptions!$C$7) ^ INT(((YEAR(N$2)-YEAR($F43))*12 + MONTH(N$2)-MONTH($F43)) / 12), 0) -> 0 | O43: =IF(AND($F43<=O$2, OR($G43="",$G43>=O$2)), $H43 * (1 + Assumptions!$C$7) ^ INT(((YEAR(O$2)-YEAR($F43))*12 + MONTH(O$2)-MONTH($F43)) / 12), 0) -> 0 | P43: =IF(AND($F43<=P$2, OR($G43="",$G43>=P$2)), $H43 * (1 + Assumptions!$C$7) ^ INT(((YEAR(P$2)-YEAR($F43))*12 + MONTH(P$2)-MONTH($F43)) / 12), 0) -> 0 | ... BP43: =IF(AND($F43<=BP$2, OR($G43="",$G43>=BP$2)), $H43 * (1 + Assumptions!$C$7) ^ INT(((YEAR(BP$2)-YEAR($F43))*12 + MONTH(BP$2)-MONTH($F43)) / 12), 0) -> 7500
B45: How to use this section:
B46: When adding an employee, follow the structure above, filling in columns A through H. Then drag the formula from the row above in column H down, and accross. Additionally, add a new employee above row 38, as the formulas below will not capture the new employee.
B48: SUMMARY BY DEPARTMENT
B49: R&D | I49: =SUMIF($C$2:$C$37,"R&D",I2:I37) -> 0 | J49: =SUMIF($C$2:$C$37,"R&D",J2:J37) -> 0 | K49: =SUMIF($C$2:$C$37,"R&D",K2:K37) -> 0 | L49: =SUMIF($C$2:$C$37,"R&D",L2:L37) -> 0 | M49: =SUMIF($C$2:$C$37,"R&D",M2:M37) -> 0 | N49: =SUMIF($C$2:$C$37,"R&D",N2:N37) -> 0 | O49: =SUMIF($C$2:$C$37,"R&D",O2:O37) -> 0 | P49: =SUMIF($C$2:$C$37,"R&D",P2:P37) -> 0 | ... BD49: =SUMIF($C$2:$C$37,"R&D",BD2:BD37) -> 110364.77
B50: S&M | I50: =SUMIF($C$3:$C$37,"S&M",I3:I37) -> 0 | J50: =SUMIF($C$3:$C$37,"S&M",J3:J37) -> 0 | K50: =SUMIF($C$3:$C$37,"S&M",K3:K37) -> 0 | L50: =SUMIF($C$3:$C$37,"S&M",L3:L37) -> 0 | M50: =SUMIF($C$3:$C$37,"S&M",M3:M37) -> 0 | N50: =SUMIF($C$3:$C$37,"S&M",N3:N37) -> 0 | O50: =SUMIF($C$3:$C$37,"S&M",O3:O37) -> 0 | P50: =SUMIF($C$3:$C$37,"S&M",P3:P37) -> 0 | ... BD50: =SUMIF($C$3:$C$37,"S&M",BD3:BD37) -> 53176.32
B51: G&A | I51: =SUMIF($C$3:$C$37,"G&A",I3:I37) -> 0 | J51: =SUMIF($C$3:$C$37,"G&A",J3:J37) -> 0 | K51: =SUMIF($C$3:$C$37,"G&A",K3:K37) -> 0 | L51: =SUMIF($C$3:$C$37,"G&A",L3:L37) -> 0 | M51: =SUMIF($C$3:$C$37,"G&A",M3:M37) -> 0 | N51: =SUMIF($C$3:$C$37,"G&A",N3:N37) -> 0 | O51: =SUMIF($C$3:$C$37,"G&A",O3:O37) -> 0 | P51: =SUMIF($C$3:$C$37,"G&A",P3:P37) -> 0 | ... BD51: =SUMIF($C$3:$C$37,"G&A",BD3:BD37) -> 55445.088
B52: TOTAL | I52: =SUM(I49:I51) -> 0 | J52: =SUM(J49:J51) -> 0 | K52: =SUM(K49:K51) -> 0 | L52: =SUM(L49:L51) -> 0 | M52: =SUM(M49:M51) -> 0 | N52: =SUM(N49:N51) -> 0 | O52: =SUM(O49:O51) -> 0 | P52: =SUM(P49:P51) -> 0 | ... BD52: =SUM(BD49:BD51) -> 218986.18
B54: HEADCOUNT BY DEPARTMENT
B55: R&D | I55: =COUNTIFS($C$3:$C$37,"R&D",I3:I37,">0") -> 0 | J55: =COUNTIFS($C$3:$C$37,"R&D",J3:J37,">0") -> 0 | K55: =COUNTIFS($C$3:$C$37,"R&D",K3:K37,">0") -> 0 | L55: =COUNTIFS($C$3:$C$37,"R&D",L3:L37,">0") -> 0 | M55: =COUNTIFS($C$3:$C$37,"R&D",M3:M37,">0") -> 0 | N55: =COUNTIFS($C$3:$C$37,"R&D",N3:N37,">0") -> 0 | O55: =COUNTIFS($C$3:$C$37,"R&D",O3:O37,">0") -> 0 | P55: =COUNTIFS($C$3:$C$37,"R&D",P3:P37,">0") -> 0 | ... BD55: =COUNTIFS($C$3:$C$37,"R&D",BD3:BD37,">0") -> 14
B56: S&M | I56: =COUNTIFS($C$3:$C$37,"S&M",I3:I37,">0") -> 0 | J56: =COUNTIFS($C$3:$C$37,"S&M",J3:J37,">0") -> 0 | K56: =COUNTIFS($C$3:$C$37,"S&M",K3:K37,">0") -> 0 | L56: =COUNTIFS($C$3:$C$37,"S&M",L3:L37,">0") -> 0 | M56: =COUNTIFS($C$3:$C$37,"S&M",M3:M37,">0") -> 0 | N56: =COUNTIFS($C$3:$C$37,"S&M",N3:N37,">0") -> 0 | O56: =COUNTIFS($C$3:$C$37,"S&M",O3:O37,">0") -> 0 | P56: =COUNTIFS($C$3:$C$37,"S&M",P3:P37,">0") -> 0 | ... BD56: =COUNTIFS($C$3:$C$37,"S&M",BD3:BD37,">0") -> 6
B57: G&A | I57: =COUNTIFS($C$3:$C$37,"G&A",I3:I37,">0") -> 0 | J57: =COUNTIFS($C$3:$C$37,"G&A",J3:J37,">0") -> 0 | K57: =COUNTIFS($C$3:$C$37,"G&A",K3:K37,">0") -> 0 | L57: =COUNTIFS($C$3:$C$37,"G&A",L3:L37,">0") -> 0 | M57: =COUNTIFS($C$3:$C$37,"G&A",M3:M37,">0") -> 0 | N57: =COUNTIFS($C$3:$C$37,"G&A",N3:N37,">0") -> 0 | O57: =COUNTIFS($C$3:$C$37,"G&A",O3:O37,">0") -> 0 | P57: =COUNTIFS($C$3:$C$37,"G&A",P3:P37,">0") -> 0 | ... BD57: =COUNTIFS($C$3:$C$37,"G&A",BD3:BD37,">0") -> 6
B58: TOTAL HEADCOUNT | I58: =SUM(I55:I57) -> 0 | J58: =SUM(J55:J57) -> 0 | K58: =SUM(K55:K57) -> 0 | L58: =SUM(L55:L57) -> 0 | M58: =SUM(M55:M57) -> 0 | N58: =SUM(N55:N57) -> 0 | O58: =SUM(O55:O57) -> 0 | P58: =SUM(P55:P57) -> 0 | ... BD58: =SUM(BD55:BD57) -> 26

Sheet Dasboard (FOR PITCHDECK)
B2: Financials | C2: 2025 | D2: 2026 | E2: 2027 | F2: 2028 | G2: 2029 | H2: 2030 | M2: Units & Revenues | N2: 2027 | O2: 2028 | P2: 2029 | T2: 2027 | U2: 2028 | V2: 2029
B3: Revenues (€) | C3: ='Financial Statements'!BB11 -> 97480 | D3: ='Financial Statements'!BC11 -> 106782 | E3: ='Financial Statements'!BD11 -> 16512760 | F3: ='Financial Statements'!BE11 -> 52529043 | G3: ='Financial Statements'!BF11 -> 1.0550693e+08 | H3: =#REF! -> #REF! | M3: TTK units sold | N3: ='Revenue Forecast'!BD6 -> 1005 | O3: ='Revenue Forecast'!BE6 -> 3000 | P3: ='Revenue Forecast'!BF6 -> 6000 | S3: TTK revenues | T3: 3035867.8 | U3: 11993554 | V3: 23987107
B4: COGS (€) | E4: =COGS!BD7 -> 10048915 | F4: =COGS!BE7 -> 21238332 | M4: Mini units sold | N4: ='Revenue Forecast'!BD12 -> 500 | O4: ='Revenue Forecast'!BE12 -> 2000 | P4: ='Revenue Forecast'!BF12 -> 4000 | S4: MIni revenues | T4: 332231.4 | U4: 2751983.5 | V4: 5503966.9
B5: OPEX (€) | D5: =OPEX!BE36 -> 2076520 | E5: =OPEX!BF36 -> 3776866.4 | F5: =OPEX!BG36 -> 5376546.1 | M5: TTK revenues (€) | N5: ='Revenue Forecast'!BD9 -> 10140118 | O5: ='Revenue Forecast'!BE9 -> 30269008 | P5: ='Revenue Forecast'!BF9 -> 60538017
M6: MIni revenues (€) | N6: ='Revenue Forecast'!BD15 -> 1452797.5 | O6: ='Revenue Forecast'!BE15 -> 5811190.1 | P6: ='Revenue Forecast'!BF15 -> 11622380 | S6: Distribution of funds | V6: Production/Aasembly | W6: Product development | X6: Sales & Marketing
V7: 0.6 | W7: 0.15 | X7: 0.25

Sheet Dashboard
B2: Financials | C2: 2025 | D2: 2026 | E2: 2027 | F2: 2028 | G2: 2029 | J2: Units & Revenues | L2: 2026 | M2: 2027 | N2: 2028 | O2: 2029 | U2: 2026 | V2: 2027 | W2: 2028 | X2: 2029
B3: REVENUES (€) | C3: ='Financial Statements'!BB11 -> 97480 | D3: ='Financial Statements'!BC11 -> 106782 | E3: ='Financial Statements'!BD11 -> 16512760 | F3: ='Financial Statements'!BE11 -> 52529043 | G3: ='Financial Statements'!BF11 -> 1.0550693e+08 | J3: TTK units sold | L3: ='Revenue Forecast'!BC6 -> 0 | M3: ='Revenue Forecast'!BD6 -> 1005 | N3: ='Revenue Forecast'!BE6 -> 3000 | O3: ='Revenue Forecast'!BF6 -> 6000 | S3: Headcount | U3: =count(Personnel!F3:F21) -> 17 | V3: =count(Personnel!F3:F27) -> 23 | W3: =COUNT(Personnel!F3:F31) -> 27 | X3: =COUNT(Personnel!F3:F33) -> 29
B4: COGS (€) | D4: ='Financial Statements'!BC17 -> 0 | E4: ='Financial Statements'!BD17 -> 16565413 | F4: ='Financial Statements'!BE17 -> 43068591 | G4: ='Financial Statements'!BF17 -> 72000200 | J4: Mini units sold | L4: ='Revenue Forecast'!BC12 -> 0 | M4: ='Revenue Forecast'!BD12 -> 500 | N4: ='Revenue Forecast'!BE12 -> 2000 | O4: ='Revenue Forecast'!BF12 -> 4000 | S4: Revenue/FTE | U4: =D3/U3 -> 6281.2941 | V4: =E3/V3 -> 717946.1 | W4: =F3/W3 -> 1945520.1 | X4: =G3/X3 -> 3638170.1
B5: OPEX (€) | D5: ='Financial Statements'!BC26 -> 2076520 | E5: ='Financial Statements'!BD26 -> 3776866.4 | F5: ='Financial Statements'!BE26 -> 5376546.1 | G5: ='Financial Statements'!BF26 -> 8382479.5 | J5: TTK revenues | L5: ='Revenue Forecast'!BC9 -> 0 | M5: ='Revenue Forecast'!BD9 -> 10140118 | N5: ='Revenue Forecast'!BE9 -> 30269008 | O5: ='Revenue Forecast'!BF9 -> 60538017 | S5: EBITDA/FTE | U5: =D6/U3 -> -115866.94 | V5: =E6/V3 -> -166500.81 | W5: =F6/W3 -> 151255.79 | X5: =G6/X3 -> 866353.53
B6: EBITDA (€) | D6: ='Financial Statements'!BC28 -> -1969738 | E6: ='Financial Statements'!BD28 -> -3829518.7 | F6: ='Financial Statements'!BE28 -> 4083906.2 | G6: ='Financial Statements'!BF28 -> 25124252 | J6: MIni revenues | L6: ='Revenue Forecast'!BC15 -> 0 | M6: ='Revenue Forecast'!BD15 -> 1452797.5 | N6: ='Revenue Forecast'!BE15 -> 5811190.1 | O6: ='Revenue Forecast'!BF15 -> 11622380 | S6: Seed Distribution of funds | X6: Production/Aasembly | Y6: Product development | Z6: Sales & Marketing
B7: EBT (€) | D7: ='Financial Statements'!BC33 -> -1969738 | E7: ='Financial Statements'!BD33 -> -3829518.7 | F7: ='Financial Statements'!BE33 -> 4083906.2 | G7: ='Financial Statements'!BF33 -> 25124252 | X7: 0.6 | Y7: 0.15 | Z7: 0.25
B8: NET INCOME (€) | D8: ='Financial Statements'!BC37 -> -1969738 | E8: ='Financial Statements'!BD37 -> -3829518.7 | F8: ='Financial Statements'!BE37 -> 4083906.2 | G8: ='Financial Statements'!BF37 -> 18802171
