Workbook

Sheet Summary
B1: Tarnoc B.V. Summary (Base case, EUR3m raise)
B2: Written 7 September 2026. The results table is live; the text is not. | D2: Case shown: | E2: Base case, EUR3m raise
D3: BOM priced on: | E3: two-year volume commitment
B5: WHAT THIS IS
B6: A monthly model of Tarnoc from January 2026 to December 2030. Every figure is calculated from the Assumptions tab.
B7: The only typed numbers are the assumptions, the committed 2026 plan (OPEX rows 38 to 43) and the back-office headcount (Personnel row 17).
B8: This workbook holds the base case only (EUR3m raise). The BOM is priced on two-year volume.
B9: Prices, BOM tiers, service and upsell tables, shipping, the 2026 plan, the subsidy, the raise amounts and working-capital days are the client's own figures.
B11: HOW UNITS SOLD ARE CALCULATED
B12: Units sold in a month is the lowest of three numbers:
B13: 1. Demand: marketing spend / EUR120 per lead x 50% qualified x 40% won, plus the orders installer partners bring in themselves (1 a month each in 2027, 4 by 2030).
B14: 2. Selling capacity: own reps x 20 a month for the direct share of sales, installer partners x 8 a month for the rest. Direct share 80% in 2027, 50% in 2028, 35%, then 30%.
B15: 3. Build capacity: the assembly partner's contracted volume. This case has no in-house production.
B17: WHAT FOLLOWS FROM UNITS
B18: Revenue: units x price, plus upsell, plus installation passed through to the installer at cost, plus service contracts on the installed base.
... B22: RESULTS
C23: 2026 | D23: 2027 | E23: 2028 | F23: 2029 | G23: 2030
B24: Units sold | C24: =Dashboard!D6 | D24: =Dashboard!E6 | E24: =Dashboard!F6 | F24: =Dashboard!G6 | G24: =Dashboard!H6
B25: Revenue | C25: =Dashboard!D14 | D25: =Dashboard!E14 | E25: =Dashboard!F14 | F25: =Dashboard!G14 | G25: =Dashboard!H14
B26: Gross margin | C26: =Dashboard!D16 | D26: =Dashboard!E16 | E26: =Dashboard!F16 | F26: =Dashboard!G16 | G26: =Dashboard!H16
B27: EBITDA | C27: =Dashboard!D18 | D27: =Dashboard!E18 | E27: =Dashboard!F18 | F27: =Dashboard!G18 | G27: =Dashboard!H18
B28: Total headcount at year end | C28: =Dashboard!D24 | D28: =Dashboard!E24 | E28: =Dashboard!F24 | F28: =Dashboard!G24 | G28: =Dashboard!H24
B29: Cash at year end | C29: =Dashboard!D31 | D29: =Dashboard!E31 | E29: =Dashboard!F31 | F29: =Dashboard!G31 | G29: =Dashboard!H31
B31: Lowest cash after the raise, and when | C31: =Dashboard!D37 | D31: =Dashboard!D38
B32: Months of operating cost that covers | C32: =Dashboard!D53
B33: Share of the raise the plan uses | C33: =Dashboard!D52
B34: Lowest cash before the raise | C34: =Dashboard!D39
B36: THIS CASE IN TWO LINES (typed on 7 September 2026; the table above is live)
B37: Base, EUR3m: 354 / 1,344 / 4,122 / 7,407 units in 2027 to 2030, EUR126m revenue in 2030. Gross margin 10%, 25%, 37%, 37%. EBITDA -2.5m, +0.9m, +17m, +34m. 95 people.
B38: Cash low EUR0.6m in December 2027, about two months of cost; 80% of the raise used.
B39: Gross margin steps from about 10% to 25% the year two-year volume passes 5,000 units (2028), and to 37% past 10,000 (2029).
B41: DOES IT MAKE SENSE
B42: Mechanically, yes. Both cases pass the full audit: no formula errors, balance sheet ties every month, funding received equals the inputs, 116 rows agree with an independent re-implementation.
B43: Commercially it holds on one condition: the supplier prices the BOM on two-year volume. Without that, 2027 and 2028 are priced at EUR9,984 a unit and base does not close on EUR3m.
B44: Soft spot 1. Base turns on about 500 units: 2028 plus 2029 volume is 5,500 against a 5,000 tier. Below 5,000, 2028 costs EUR2,900 more per unit and EBITDA goes back to about -3m.
B46: ASSUMPTIONS CHECKED AGAINST THE MARKET (research of 4 September 2026, sources in docs/tarnoc-assumptions-research-2026-09-04.md)
B47: Assumption | C47: In the model | D47: Verdict | E47: What the market evidence says
B48: Cost per marketing lead | C48: EUR120 | D48: supported | E48: Exclusive heat-pump leads EUR130-280 NL/BE, EUR50-350 DE; EUR90-180 is the range
B49: Lead to order (50% qualified x 40% won) | C49: 20%, EUR600 per order | D49: high | E49: Published 8-15% and EUR900-1,800 per order; the client's current number; stronger for a product priced below installed heat pumps
B50: Installer commission | C50: 10% of unit price | D50: supported as a fee | E50: Loyalty and referral schemes pay 4-10%; installers who buy and resell expect 20-30% trade margin
B51: Units a partner can sell per month | C51: 8 | D51: supported | E51: Certification norm about 80 installs a year per monteur; fits a mid-sized firm with one dedicated monteur
B52: Orders a partner brings in per month | C52: 1, 2, 3, 4 (2027-30) | D52: top of range | E52: Evidence: 0.5-1 in year one, 2-3 by year four; 4 only for top partners
B53: Partners per partner manager | C53: 18 | D53: low vs incumbents | E53: Remeha and Nefit account managers cover hundreds of firms; 15-25 is fine while onboarding, 40-80 at steady state
B54: Partners trained per trainer per year; cost | C54: 40; EUR3,500 | D54: throughput low, cost fine | E54: 40-80 a year; EUR1,500-2,500 plus a rotating demo pool
B55: Rep quota | C55: 20 closes a month | D55: high | E55: US HVAC comfort advisors 8-10 a month, top decile 11-17; solar reps 2-3 in year one
B56: Direct share path | C56: 80 / 50 / 35 / 30% | D56: no precedent | E56: Brands are installer-led from day one or stay mostly direct; those that shift still hold 40-60% direct in year four
B57: Marketing spend as share of revenue | C57: about 2-4% | D57: low | E57: HVAC 6% (10-15% in growth), NIBE selling costs 14.6%; 6-10% early and 3-5% later is typical
B58: Marketing team | C58: 2 + 1 per EUR1.5m of yearly spend | D58: supported | E58: Cross-industry: 1 marketer per EUR1-1.5m of media, or a 10-12% agency line
... B74: Back office | C74: 3 to 8 people | D74: supported | E74: Fine for 95 staff; for 300 staff 14-22, and HR alone needs 4-6
B76: The research briefs described the product as a gas boiler; it is a turbine heat pump. That weakens the "high" verdicts on the close rate and price, and does not affect the rest.
B78: WHERE THE PLAN IS VULNERABLE
B79: Base: the 5,000-unit cliff in 2028 (2028 plus 2029 volume is 5,500 against the 5,000 tier) and two months of cash cover in December 2027. A one-quarter delay in the 2029 ramp costs the margin step.
B80: Both: the turbineketel sells below its tier-1 BOM. A forced price cut makes the first tier worse.
B81: Turbineketel service prices (EUR60 and EUR90 a year) are below the Dutch market. Upside if raised.
B83: STILL NEEDED FROM THE CLIENT
B84: Supplier quotes behind the three BOM tiers, and confirmation the supplier will price on a two-year volume commitment.
B85: Confirmation of the installer deal: 10% of the unit price on top of the installation fee.
B86: A view on the direct-to-installer shift (80 / 50 / 35 / 30% direct).
B88: Detail: How to read me for the colour code, Dashboard for the year view, Assumptions for every input, docs/ in the repository for the research and the formula reviews.

Sheet Cover
B6: TARNOC B.V.
B8: Financial Model
B9: Built from scratch, September 2026
B10: Base case, EUR3m raise
B12: Currency | C12: EUR, ex VAT unless stated
B13: Period | C13: January 2026 to December 2030, monthly
B14: Fiscal year | C14: Calendar
B15: Units | C15: Whole euros
B18: Start with the Summary tab, then How to read me.
B21: STRICTLY CONFIDENTIAL

Sheet How to read me
B1: Tarnoc B.V. How to read this model
B3: COLOUR CODING
B4: Sample | C4: Hardcoded input. These are the only cells to change. They live on Assumptions, plus the back-office headcount row on Personnel.
B5: Sample | C5: Calculated cell. Do not type over these.
B6: Sample | C6: Subtotal or total row.
B7: Sample | C7: Section header.
B8: Sample | C8: Margin or ratio row.
B9: Sample | C9: Check row. Must read nil.
B12: HOW THE MODEL FITS TOGETHER
C13: Assumptions -> every other tab. The only other typed numbers are the back-office headcount on Personnel and the committed 2026 plan on OPEX.
C14: Revenue Forecast -> COGS, OPEX, Personnel, Financial Statements.
C15: Personnel -> OPEX -> Financial Statements.
C16: Everything -> Dashboard.
B18: THE CASE
C19: This workbook holds the base case only (EUR3m raise). The Value column on Assumptions is the plan; there is no case switch.
C20: The bill of materials is priced on two-year volume (this year plus next), which assumes a volume commitment to the supplier. There is no switch for this; it is how the COGS tab works.
B22: HOW UNITS SOLD IS DECIDED
C23: Units sold is not typed in. Three numbers are worked out for every month and the smallest one wins:
C24: 1. Demand. Marketing spend divided by cost per lead, through the two conversion rates, plus the orders installer partners bring in on their own jobs.
C25: 2. What we can sell. Our own reps times quota, plus installer partners times units each, capped by the direct and channel mix. No ramp-up: reps and partners sell at full rate from the month they join.
C26: 3. What we can build. The assembly partner's contracted volume.
C27: There is no market size or market share anywhere in the model.
B30: THINGS WORTH KNOWING
C31: Installation is a pass-through. It is charged to the customer at exactly what the installation partner is paid, so it adds revenue and an identical cost and no margin.
C32: Field service engineers are salaried staff on the Personnel tab. The service contract cost per unit in COGS covers parts, consumables and travel, not their salaries.
C33: Unit cost falls in steps, not smoothly. The turbineketel bill of materials is EUR9,984 below 5,000 units a year, EUR7,069 from 5,000 and EUR4,998 from 10,000. Almost all of the profit in the later years comes from crossing the second step, so that assumption carries more weight than any other in the model.
C34: Every month is a real column. There are no annual-only columns, so nothing can be hardcoded in a year that the monthly build does not see.

Sheet Assumptions
B1: Tarnoc B.V. Assumptions
B2: Every driver lives here. Pale yellow cells are inputs, everything else is calculated. This workbook is the base case, eur3m raise.
B4: GENERAL
D5: Value
B6: Opening cash at Jan-2026 | C6: EUR | D6: 853120 | J6: the actual balance carried into January 2026
B7: Base year for salary and cost inflation | C7: year | D7: 2026 | J7: costs are quoted in this year's money and inflated from here
B8: Annual salary increase | C8: % | D8: 0.05
B9: Corporate income tax rate | C9: % | D9: 0.258 | J9: losses are carried forward until profits absorb them
B10: Interest on the convertible loan | C10: % | D10: 0.05
B11: First month we can sell | C11: date | D11: 46388 | J11: nil units before this. Product, certification and supply have to be ready first
B12: Committed 2026 plan holds until | C12: date | D12: 46296 | J12: operating costs to this month are taken from the existing plan, not from the drivers
B13: Subsidy received | C13: EUR | D13: 106782
B14: Subsidy received in | C14: date | D14: 46235
B15: WORKING CAPITAL
B16: Days sales outstanding | C16: days | D16: 20
B17: Days payable outstanding | C17: days | D17: 45
B18: Days inventory outstanding | C18: days | D18: 0 | J18: the assembly partner holds the stock; nothing sits on our balance sheet
B19: PRICING (ex VAT)
B20: Turbineketel list price | C20: EUR/unit | D20: 8525.62
B21: Outdoor unit, Combi+ only | C21: EUR/unit | D21: 5309.92
B22: Combi+ price (ketel plus outdoor unit) | C22: EUR/unit | D22: =Assumptions!$D$20+Assumptions!$D$21
B23: Installation, TTK | C23: EUR/unit | D23: 2800 | J23: pass-through: the customer is charged what the installer is paid
B24: Installation, Combi+ | C24: EUR/unit | D24: 3800 | J24: pass-through, so it adds revenue and an identical cost
B25: TTK share of units | C25: % | D25: 0.2
B26: Combi+ share of units | C26: % | D26: =1-Assumptions!$D$25
B27: UPSELL BASKET (attached to every unit sold)
D28: Attach % | E28: Price | F28: Cost
B29: Boiler variant 50 | D29: 0.49 | E29: 165.29 | F29: 80
B30: Boiler variant 100 | D30: 0.19 | E30: 330.58 | F30: 150
B31: Sound reduction | D31: 0.79 | E31: 454.55 | F31: 190
B32: Upsell revenue per unit sold | C32: EUR/unit | D32: =SUMPRODUCT($D$29:$D$31,$E$29:$E$31)
B33: Upsell cost per unit sold | C33: EUR/unit | D33: =SUMPRODUCT($D$29:$D$31,$F$29:$F$31)
B34: SERVICE CONTRACTS (annual, charged on the installed base)
D35: Attach % | E35: Price/yr | F35: Cost/yr
B36: TTK, basic | D36: 0.34 | E36: 60 | F36: 30
B37: TTK, premium | D37: 0.54 | E37: 90 | F37: 40
B38: Combi+, basic | D38: 0.34 | E38: 150 | F38: 75
B39: Combi+, premium | D39: 0.54 | E39: 200 | F39: 100
B40: Service revenue per installed unit per year | C40: EUR/unit | D40: =Assumptions!$D$25*SUMPRODUCT($D$36:$D$37,$E$36:$E$37)+Assumptions!$D$26*SUMPRODUCT($D$38:$D$39,$E$38:$E$39)
B41: Service cost per installed unit per year | C41: EUR/unit | D41: =Assumptions!$D$25*SUMPRODUCT($D$36:$D$37,$F$36:$F$37)+Assumptions!$D$26*SUMPRODUCT($D$38:$D$39,$F$38:$F$39) | J41: parts, consumables and travel per contract; the field engineers themselves are salaried on the Personnel tab
B42: Share of the installed base on a contract | C42: % | D42: =$D$36+$D$37
B43: DEMAND (marketing spend runs the funnel)
B44: Marketing spend | C44: EUR/month | D44: 2026 | E44: 2027 | F44: 2028 | G44: 2029 | H44: 2030 | J44: generates orders through the funnel, on top of the orders installer partners bring in; nil before the first sellable month
B45: Value | D45: 0 | E45: 13000 | F45: 40000 | G45: 115000 | H45: 160000
D46: Value
B47: Cost per lead | C47: EUR | D47: 120 | J47: EUR120 a lead at a 20% close rate is EUR600 of marketing per customer
B48: Lead to qualified | C48: % | D48: 0.5
B49: Qualified to won | C49: % | D49: 0.4 | J49: 50% then 40% is a 20% lead to sale rate, in line with high-intent HVAC leads
B50: SELLING CAPACITY (own reps early, installer channel at scale)
B51: Share of units sold direct | C51: % | D51: 2026 | E51: 2027 | F51: 2028 | G51: 2029 | H51: 2030 | J51: direct to consumer first, installers brought in from 2027, half the volume by 2028 and installer-led from 2029
B52: Value | D52: 1 | E52: 0.8 | F52: 0.5 | G52: 0.35 | H52: 0.3
B53: Reps hired per month | C53: FTE/month | D53: 2026 | E53: 2027 | F53: 2028 | G53: 2029 | H53: 2030 | J53: sales hiring starts in the first month we can sell, so 2026 is nil
B54: Value | D54: 0 | E54: 0.5 | F54: 0.25 | G54: 0.25 | H54: 0.25
B55: Installer partners signed per month | C55: partners/month | D55: 2026 | E55: 2027 | F55: 2028 | G55: 2029 | H55: 2030 | J55: same gate: no partner intros before the first month we can sell; the network takes time to build
B56: Value | D56: 0 | E56: 1 | F56: 1.5 | G56: 3 | H56: 3.8
B57: Orders an installer partner brings in per month | C57: units/month | D57: 2026 | E57: 2027 | F57: 2028 | G57: 2029 | H57: 2030 | J57: customers the installer finds on their own jobs, rising as the brand becomes known; these add to demand
B58: Value | D58: 0 | E58: 1 | F58: 2 | G58: 3 | H58: 4
D59: Value
B60: Reps in post at Jan-2026 | C60: FTE | D60: 1
B61: Quota per rep | C61: units/month | D61: 20 | J61: a rep sells full quota from the month they are hired, no ramp and no attainment haircut
B62: Installer partners at Jan-2026 | C62: partners | D62: 1
B63: Units per partner per month | C63: units/month | D63: 8 | J63: a partner sells full volume from the month they are signed
B64: Installer partner commission, share of unit price | C64: % | D64: 0.1 | J64: paid on every unit sold through the channel, on the turbineketel or Combi+ system price only, not on installation, upsell or service
B65: Partners per partner manager | C65: partners | D65: 18
B66: BUILD CAPACITY (assembly partner only; this case has no in-house production)
D67: Value
B68: Assembly partner capacity | C68: units/month | D68: 650 | J68: what the partner has contracted to build for us
B69: BILL OF MATERIALS (unit cost falls as volume crosses each tier)
D70: From units/yr | E70: TTK cost | F70: Outdoor unit
B71: Tier 1 | D71: 0 | E71: 9984 | F71: 1402.6
B72: Tier 2 | D72: 5000 | E72: 7069 | F72: 1262.34
B73: Tier 3 | D73: 10000 | E73: 4998 | F73: 1136.1
D74: Value
B75: Inbound shipping, Combi+ outdoor unit | C75: EUR/unit | D75: 100
B76: ORGANISATION (headcount follows whatever creates the work)
B77: R&D engineers hired in the year | C77: FTE | D77: 2026 | E77: 2027 | F77: 2028 | G77: 2029 | H77: 2030 | J77: a novel turbine machine plus the Twincycle needs engineers, not a fixed team
B78: Value | D78: 0 | E78: 4 | F78: 3 | G78: 3 | H78: 4
D79: Value
B80: R&D engineers in post at Jan-2026 | C80: FTE | D80: 10 | J80: the founding engineering team; their cost sits inside the committed 2026 plan until November 2026
B81: Marketing team floor | C81: FTE | D81: 2
B82: Units per supply chain and logistics FTE | C82: units/yr | D82: 900 | J82: buying, planning, inbound quality and warehousing
B83: Installed units per support agent | C83: units | D83: 2500 | J83: a heating appliance peaks in winter and this is a first generation product
B84: Installed units per technical escalation FTE | C84: units | D84: 15000
B85: New partners per year per installer trainer | C85: partners | D85: 40
B86: Units per order desk FTE | C86: units/yr | D86: 3000
B87: Yearly marketing budget one marketer can run | C87: EUR/yr | D87: 1500000 | J87: sizes the marketing team only: the floor above plus one more person for every EUR1.5m of yearly spend. Not a spend. Benchmarks: one marketer per EUR1-1.5m of media
D88: Value
B89: Installed units one field engineer can look after | C89: units | D89: 600 | J89: sizes the field service team: units on a service contract divided by this number = engineers to hire. Each unit gets one visit a year plus breakdown cover; market range 600 to 900
B90: LOADED COST PER PERSON (employer cost, including taxes)
D91: Value
B92: Sales rep | C92: EUR/month | D92: 7500
B93: Partner manager | C93: EUR/month | D93: 8000
B94: Trainer, order desk, marketing | C94: EUR/month | D94: 7000
B95: Supply chain and production | C95: EUR/month | D95: 5000
B96: Support and escalation | C96: EUR/month | D96: 4800
B97: Leadership and back office | C97: EUR/month | D97: 7000
B98: R&D engineer | C98: EUR/month | D98: 5700 | J98: the blended cost of the engineers already in post
B99: Field service engineer | C99: EUR/month | D99: 6500
B100: OVERHEADS AND OTHER OPERATING COSTS
D101: Value
...

Sheet Financial Statements
B1: Tarnoc B.V. Financial Statements
B2: Three statements, monthly. The check on row 58 must read zero in every column.
E3: 46023 | F3: 46054 | G3: 46082 | H3: 46113 | I3: 46143 | J3: 46174 | K3: 46204 | L3: 46235 | M3: 46266 | N3: 46296 | O3: 46327 | P3: 46357 | Q3: 46388 | R3: 46419 | S3: 46447 | T3: 46478 | U3: 46508 | V3: 46539 | W3: 46569 | X3: 46600 | Y3: 46631 | Z3: 46661 | AA3: 46692 | AB3: 46722 | AC3: 46753 | AD3: 46784 | AE3: 46813 | AF3: 46844 | AG3: 46874 | AH3: 46905 | AI3: 46935 | AJ3: 46966 | AK3: 46997 | AL3: 47027 | AM3: 47058 | AN3: 47088 | AO3: 47119 | AP3: 47150 | AQ3: 47178 | AR3: 47209 | AS3: 47239 | AT3: 47270 | AU3: 47300 | AV3: 47331 | AW3: 47362 | AX3: 47392 | AY3: 47423 | AZ3: 47453 | BA3: 47484 | BB3: 47515 | BC3: 47543 | BD3: 47574 | BE3: 47604 | BF3: 47635 | BG3: 47665 | BH3: 47696 | BI3: 47727 | BJ3: 47757 | BK3: 47788 | BL3: 47818 | BN3: 2026 | BO3: 2027 | BP3: 2028 | BQ3: 2029 | BR3: 2030 | BT3: what this row does
B5: PROFIT AND LOSS
B6: Revenue | C6: EUR | E6: ='Revenue Forecast'!E50 | F6: ='Revenue Forecast'!F50 | G6: ='Revenue Forecast'!G50 | H6: ='Revenue Forecast'!H50 | I6: ='Revenue Forecast'!I50 | J6: ='Revenue Forecast'!J50 | K6: ='Revenue Forecast'!K50 | L6: ='Revenue Forecast'!L50 | ... BL6: ='Revenue Forecast'!BL50 | BN6: =SUM(E6:P6) | BO6: =SUM(Q6:AB6) | BP6: =SUM(AC6:AN6) | BQ6: =SUM(AO6:AZ6) | BR6: =SUM(BA6:BL6)
B7: Cost of goods sold | C7: EUR | E7: =-COGS!E19 | F7: =-COGS!F19 | G7: =-COGS!G19 | H7: =-COGS!H19 | I7: =-COGS!I19 | J7: =-COGS!J19 | K7: =-COGS!K19 | L7: =-COGS!L19 | ... BL7: =-COGS!BL19 | BN7: =SUM(E7:P7) | BO7: =SUM(Q7:AB7) | BP7: =SUM(AC7:AN7) | BQ7: =SUM(AO7:AZ7) | BR7: =SUM(BA7:BL7)
B8: Gross profit | C8: EUR | E8: =E6+E7 | F8: =F6+F7 | G8: =G6+G7 | H8: =H6+H7 | I8: =I6+I7 | J8: =J6+J7 | K8: =K6+K7 | L8: =L6+L7 | ... BL8: =BL6+BL7 | BN8: =SUM(E8:P8) | BO8: =SUM(Q8:AB8) | BP8: =SUM(AC8:AN8) | BQ8: =SUM(AO8:AZ8) | BR8: =SUM(BA8:BL8)
B9: Gross margin | C9: % | E9: =IFERROR(E8/E6,0) | F9: =IFERROR(F8/F6,0) | G9: =IFERROR(G8/G6,0) | H9: =IFERROR(H8/H6,0) | I9: =IFERROR(I8/I6,0) | J9: =IFERROR(J8/J6,0) | K9: =IFERROR(K8/K6,0) | L9: =IFERROR(L8/L6,0) | ... BL9: =IFERROR(BL8/BL6,0) | BN9: =IFERROR(BN8/BN6,0) | BO9: =IFERROR(BO8/BO6,0) | BP9: =IFERROR(BP8/BP6,0) | BQ9: =IFERROR(BQ8/BQ6,0) | BR9: =IFERROR(BR8/BR6,0)
B11: Research and development | C11: EUR | E11: =-OPEX!E30 | F11: =-OPEX!F30 | G11: =-OPEX!G30 | H11: =-OPEX!H30 | I11: =-OPEX!I30 | J11: =-OPEX!J30 | K11: =-OPEX!K30 | L11: =-OPEX!L30 | ... BL11: =-OPEX!BL30 | BN11: =SUM(E11:P11) | BO11: =SUM(Q11:AB11) | BP11: =SUM(AC11:AN11) | BQ11: =SUM(AO11:AZ11) | BR11: =SUM(BA11:BL11)
B12: Sales and marketing | C12: EUR | E12: =-OPEX!E31 | F12: =-OPEX!F31 | G12: =-OPEX!G31 | H12: =-OPEX!H31 | I12: =-OPEX!I31 | J12: =-OPEX!J31 | K12: =-OPEX!K31 | L12: =-OPEX!L31 | ... BL12: =-OPEX!BL31 | BN12: =SUM(E12:P12) | BO12: =SUM(Q12:AB12) | BP12: =SUM(AC12:AN12) | BQ12: =SUM(AO12:AZ12) | BR12: =SUM(BA12:BL12)
B13: General and administrative | C13: EUR | E13: =-OPEX!E32 | F13: =-OPEX!F32 | G13: =-OPEX!G32 | H13: =-OPEX!H32 | I13: =-OPEX!I32 | J13: =-OPEX!J32 | K13: =-OPEX!K32 | L13: =-OPEX!L32 | ... BL13: =-OPEX!BL32 | BN13: =SUM(E13:P13) | BO13: =SUM(Q13:AB13) | BP13: =SUM(AC13:AN13) | BQ13: =SUM(AO13:AZ13) | BR13: =SUM(BA13:BL13)
B14: Total operating expenses | C14: EUR | E14: =SUM(E11:E13) | F14: =SUM(F11:F13) | G14: =SUM(G11:G13) | H14: =SUM(H11:H13) | I14: =SUM(I11:I13) | J14: =SUM(J11:J13) | K14: =SUM(K11:K13) | L14: =SUM(L11:L13) | ... BL14: =SUM(BL11:BL13) | BN14: =SUM(E14:P14) | BO14: =SUM(Q14:AB14) | BP14: =SUM(AC14:AN14) | BQ14: =SUM(AO14:AZ14) | BR14: =SUM(BA14:BL14)
B16: EBITDA | C16: EUR | E16: =E8+E14 | F16: =F8+F14 | G16: =G8+G14 | H16: =H8+H14 | I16: =I8+I14 | J16: =J8+J14 | K16: =K8+K14 | L16: =L8+L14 | ... BL16: =BL8+BL14 | BN16: =SUM(E16:P16) | BO16: =SUM(Q16:AB16) | BP16: =SUM(AC16:AN16) | BQ16: =SUM(AO16:AZ16) | BR16: =SUM(BA16:BL16)
B17: EBITDA margin | C17: % | E17: =IFERROR(E16/E6,0) | F17: =IFERROR(F16/F6,0) | G17: =IFERROR(G16/G6,0) | H17: =IFERROR(H16/H6,0) | I17: =IFERROR(I16/I6,0) | J17: =IFERROR(J16/J6,0) | K17: =IFERROR(K16/K6,0) | L17: =IFERROR(L16/L6,0) | ... BL17: =IFERROR(BL16/BL6,0) | BN17: =IFERROR(BN16/BN6,0) | BO17: =IFERROR(BO16/BO6,0) | BP17: =IFERROR(BP16/BP6,0) | BQ17: =IFERROR(BQ16/BQ6,0) | BR17: =IFERROR(BR16/BR6,0)
B19: Depreciation | C19: EUR | E19: =0 | F19: =0 | G19: =0 | H19: =0 | I19: =0 | J19: =0 | K19: =0 | L19: =0 | ... BL19: =0 | BN19: =SUM(E19:P19) | BO19: =SUM(Q19:AB19) | BP19: =SUM(AC19:AN19) | BQ19: =SUM(AO19:AZ19) | BR19: =SUM(BA19:BL19) | BT19: no fixed assets in this case
B20: Interest on the loan | C20: EUR | E20: =0 | F20: =-E51*Assumptions!$D$10/12 | G20: =-F51*Assumptions!$D$10/12 | H20: =-G51*Assumptions!$D$10/12 | I20: =-H51*Assumptions!$D$10/12 | J20: =-I51*Assumptions!$D$10/12 | K20: =-J51*Assumptions!$D$10/12 | L20: =-K51*Assumptions!$D$10/12 | M20: =-L51*Assumptions!$D$10/12 | ... BL20: =-BK51*Assumptions!$D$10/12 | BN20: =SUM(E20:P20) | BO20: =SUM(Q20:AB20) | BP20: =SUM(AC20:AN20) | BQ20: =SUM(AO20:AZ20) | BR20: =SUM(BA20:BL20)
B21: Profit before tax | C21: EUR | E21: =E16+E19+E20 | F21: =F16+F19+F20 | G21: =G16+G19+G20 | H21: =H16+H19+H20 | I21: =I16+I19+I20 | J21: =J16+J19+J20 | K21: =K16+K19+K20 | L21: =L16+L19+L20 | ... BL21: =BL16+BL19+BL20 | BN21: =SUM(E21:P21) | BO21: =SUM(Q21:AB21) | BP21: =SUM(AC21:AN21) | BQ21: =SUM(AO21:AZ21) | BR21: =SUM(BA21:BL21)
B22: Tax | C22: EUR | E22: =-IF(E21>0,MAX(0,E21-0)*Assumptions!$D$9,0) | F22: =-IF(F21>0,MAX(0,F21-E64)*Assumptions!$D$9,0) | G22: =-IF(G21>0,MAX(0,G21-F64)*Assumptions!$D$9,0) | H22: =-IF(H21>0,MAX(0,H21-G64)*Assumptions!$D$9,0) | I22: =-IF(I21>0,MAX(0,I21-H64)*Assumptions!$D$9,0) | J22: =-IF(J21>0,MAX(0,J21-I64)*Assumptions!$D$9,0) | K22: =-IF(K21>0,MAX(0,K21-J64)*Assumptions!$D$9,0) | L22: =-IF(L21>0,MAX(0,L21-K64)*Assumptions!$D$9,0) | M22: =-IF(M21>0,MAX(0,M21-L64)*Assumptions!$D$9,0) | ... BL22: =-IF(BL21>0,MAX(0,BL21-BK64)*Assumptions!$D$9,0) | BN22: =SUM(E22:P22) | BO22: =SUM(Q22:AB22) | BP22: =SUM(AC22:AN22) | BQ22: =SUM(AO22:AZ22) | BR22: =SUM(BA22:BL22) | BT22: losses are carried forward and absorb profit before any tax is paid
B23: Net income | C23: EUR | E23: =E21+E22 | F23: =F21+F22 | G23: =G21+G22 | H23: =H21+H22 | I23: =I21+I22 | J23: =J21+J22 | K23: =K21+K22 | L23: =L21+L22 | ... BL23: =BL21+BL22 | BN23: =SUM(E23:P23) | BO23: =SUM(Q23:AB23) | BP23: =SUM(AC23:AN23) | BQ23: =SUM(AO23:AZ23) | BR23: =SUM(BA23:BL23)
B24: Net margin | C24: % | E24: =IFERROR(E23/E6,0) | F24: =IFERROR(F23/F6,0) | G24: =IFERROR(G23/G6,0) | H24: =IFERROR(H23/H6,0) | I24: =IFERROR(I23/I6,0) | J24: =IFERROR(J23/J6,0) | K24: =IFERROR(K23/K6,0) | L24: =IFERROR(L23/L6,0) | ... BL24: =IFERROR(BL23/BL6,0) | BN24: =IFERROR(BN23/BN6,0) | BO24: =IFERROR(BO23/BO6,0) | BP24: =IFERROR(BP23/BP6,0) | BQ24: =IFERROR(BQ23/BQ6,0) | BR24: =IFERROR(BR23/BR6,0)
B26: CASH FLOW
B27: Net income | C27: EUR | E27: =E23 | F27: =F23 | G27: =G23 | H27: =H23 | I27: =I23 | J27: =J23 | K27: =K23 | L27: =L23 | ... BL27: =BL23 | BN27: =SUM(E27:P27) | BO27: =SUM(Q27:AB27) | BP27: =SUM(AC27:AN27) | BQ27: =SUM(AO27:AZ27) | BR27: =SUM(BA27:BL27)
B28: Depreciation added back | C28: EUR | E28: =-E19 | F28: =-F19 | G28: =-G19 | H28: =-H19 | I28: =-I19 | J28: =-J19 | K28: =-K19 | L28: =-L19 | ... BL28: =-BL19 | BN28: =SUM(E28:P28) | BO28: =SUM(Q28:AB28) | BP28: =SUM(AC28:AN28) | BQ28: =SUM(AO28:AZ28) | BR28: =SUM(BA28:BL28)
B29: Movement in receivables | C29: EUR | E29: =-(E44-0) | F29: =-(F44-E44) | G29: =-(G44-F44) | H29: =-(H44-G44) | I29: =-(I44-H44) | J29: =-(J44-I44) | K29: =-(K44-J44) | L29: =-(L44-K44) | M29: =-(M44-L44) | ... BL29: =-(BL44-BK44) | BN29: =SUM(E29:P29) | BO29: =SUM(Q29:AB29) | BP29: =SUM(AC29:AN29) | BQ29: =SUM(AO29:AZ29) | BR29: =SUM(BA29:BL29)
B30: Movement in inventory | C30: EUR | E30: =-(E45-0) | F30: =-(F45-E45) | G30: =-(G45-F45) | H30: =-(H45-G45) | I30: =-(I45-H45) | J30: =-(J45-I45) | K30: =-(K45-J45) | L30: =-(L45-K45) | M30: =-(M45-L45) | ... BL30: =-(BL45-BK45) | BN30: =SUM(E30:P30) | BO30: =SUM(Q30:AB30) | BP30: =SUM(AC30:AN30) | BQ30: =SUM(AO30:AZ30) | BR30: =SUM(BA30:BL30)
B31: Movement in payables | C31: EUR | E31: =E50-0 | F31: =F50-E50 | G31: =G50-F50 | H31: =H50-G50 | I31: =I50-H50 | J31: =J50-I50 | K31: =K50-J50 | L31: =L50-K50 | M31: =M50-L50 | ... BL31: =BL50-BK50 | BN31: =SUM(E31:P31) | BO31: =SUM(Q31:AB31) | BP31: =SUM(AC31:AN31) | BQ31: =SUM(AO31:AZ31) | BR31: =SUM(BA31:BL31)
B32: Cash from operations | C32: EUR | E32: =SUM(E27:E31) | F32: =SUM(F27:F31) | G32: =SUM(G27:G31) | H32: =SUM(H27:H31) | I32: =SUM(I27:I31) | J32: =SUM(J27:J31) | K32: =SUM(K27:K31) | L32: =SUM(L27:L31) | ... BL32: =SUM(BL27:BL31) | BN32: =SUM(E32:P32) | BO32: =SUM(Q32:AB32) | BP32: =SUM(AC32:AN32) | BQ32: =SUM(AO32:AZ32) | BR32: =SUM(BA32:BL32)
B33: Capital expenditure | C33: EUR | E33: =-E61 | F33: =-F61 | G33: =-G61 | H33: =-H61 | I33: =-I61 | J33: =-J61 | K33: =-K61 | L33: =-L61 | ... BL33: =-BL61 | BN33: =SUM(E33:P33) | BO33: =SUM(Q33:AB33) | BP33: =SUM(AC33:AN33) | BQ33: =SUM(AO33:AZ33) | BR33: =SUM(BA33:BL33)
B34: Cash from investing | C34: EUR | E34: =E33 | F34: =F33 | G34: =G33 | H34: =H33 | I34: =I33 | J34: =J33 | K34: =K33 | L34: =L33 | ... BL34: =BL33 | BN34: =SUM(E34:P34) | BO34: =SUM(Q34:AB34) | BP34: =SUM(AC34:AN34) | BQ34: =SUM(AO34:AZ34) | BR34: =SUM(BA34:BL34)
B35: Equity raised | C35: EUR | E35: =IF(AND(YEAR(E$3)=YEAR(Assumptions!$D$114),MONTH(E$3)=MONTH(Assumptions!$D$114)),Assumptions!$D$115,0)+IF(AND(YEAR(E$3)=YEAR(Assumptions!$D$116),MONTH(E$3)=MONTH(Assumptions!$D$116)),Assumptions!$D$117,0) | F35: =IF(AND(YEAR(F$3)=YEAR(Assumptions!$D$114),MONTH(F$3)=MONTH(Assumptions!$D$114)),Assumptions!$D$115,0)+IF(AND(YEAR(F$3)=YEAR(Assumptions!$D$116),MONTH(F$3)=MONTH(Assumptions!$D$116)),Assumptions!$D$117,0) | G35: =IF(AND(YEAR(G$3)=YEAR(Assumptions!$D$114),MONTH(G$3)=MONTH(Assumptions!$D$114)),Assumptions!$D$115,0)+IF(AND(YEAR(G$3)=YEAR(Assumptions!$D$116),MONTH(G$3)=MONTH(Assumptions!$D$116)),Assumptions!$D$117,0) | H35: =IF(AND(YEAR(H$3)=YEAR(Assumptions!$D$114),MONTH(H$3)=MONTH(Assumptions!$D$114)),Assumptions!$D$115,0)+IF(AND(YEAR(H$3)=YEAR(Assumptions!$D$116),MONTH(H$3)=MONTH(Assumptions!$D$116)),Assumptions!$D$117,0) | I35: =IF(AND(YEAR(I$3)=YEAR(Assumptions!$D$114),MONTH(I$3)=MONTH(Assumptions!$D$114)),Assumptions!$D$115,0)+IF(AND(YEAR(I$3)=YEAR(Assumptions!$D$116),MONTH(I$3)=MONTH(Assumptions!$D$116)),Assumptions!$D$117,0) | J35: =IF(AND(YEAR(J$3)=YEAR(Assumptions!$D$114),MONTH(J$3)=MONTH(Assumptions!$D$114)),Assumptions!$D$115,0)+IF(AND(YEAR(J$3)=YEAR(Assumptions!$D$116),MONTH(J$3)=MONTH(Assumptions!$D$116)),Assumptions!$D$117,0) | K35: =IF(AND(YEAR(K$3)=YEAR(Assumptions!$D$114),MONTH(K$3)=MONTH(Assumptions!$D$114)),Assumptions!$D$115,0)+IF(AND(YEAR(K$3)=YEAR(Assumptions!$D$116),MONTH(K$3)=MONTH(Assumptions!$D$116)),Assumptions!$D$117,0) | L35: =IF(AND(YEAR(L$3)=YEAR(Assumptions!$D$114),MONTH(L$3)=MONTH(Assumptions!$D$114)),Assumptions!$D$115,0)+IF(AND(YEAR(L$3)=YEAR(Assumptions!$D$116),MONTH(L$3)=MONTH(Assumptions!$D$116)),Assumptions!$D$117,0) | ... BL35: =IF(AND(YEAR(BL$3)=YEAR(Assumptions!$D$114),MONTH(BL$3)=MONTH(Assumptions!$D$114)),Assumptions!$D$115,0)+IF(AND(YEAR(BL$3)=YEAR(Assumptions!$D$116),MONTH(BL$3)=MONTH(Assumptions!$D$116)),Assumptions!$D$117,0) | BN35: =SUM(E35:P35) | BO35: =SUM(Q35:AB35) | BP35: =SUM(AC35:AN35) | BQ35: =SUM(AO35:AZ35) | BR35: =SUM(BA35:BL35) | BT35: dates and amounts are on the Assumptions funding block; any day in the month counts
B36: Loan drawn | C36: EUR | E36: =IF(AND(YEAR(E$3)=YEAR(Assumptions!$D$119),MONTH(E$3)=MONTH(Assumptions!$D$119)),Assumptions!$D$118,0) | F36: =IF(AND(YEAR(F$3)=YEAR(Assumptions!$D$119),MONTH(F$3)=MONTH(Assumptions!$D$119)),Assumptions!$D$118,0) | G36: =IF(AND(YEAR(G$3)=YEAR(Assumptions!$D$119),MONTH(G$3)=MONTH(Assumptions!$D$119)),Assumptions!$D$118,0) | H36: =IF(AND(YEAR(H$3)=YEAR(Assumptions!$D$119),MONTH(H$3)=MONTH(Assumptions!$D$119)),Assumptions!$D$118,0) | I36: =IF(AND(YEAR(I$3)=YEAR(Assumptions!$D$119),MONTH(I$3)=MONTH(Assumptions!$D$119)),Assumptions!$D$118,0) | J36: =IF(AND(YEAR(J$3)=YEAR(Assumptions!$D$119),MONTH(J$3)=MONTH(Assumptions!$D$119)),Assumptions!$D$118,0) | K36: =IF(AND(YEAR(K$3)=YEAR(Assumptions!$D$119),MONTH(K$3)=MONTH(Assumptions!$D$119)),Assumptions!$D$118,0) | L36: =IF(AND(YEAR(L$3)=YEAR(Assumptions!$D$119),MONTH(L$3)=MONTH(Assumptions!$D$119)),Assumptions!$D$118,0) | ... BL36: =IF(AND(YEAR(BL$3)=YEAR(Assumptions!$D$119),MONTH(BL$3)=MONTH(Assumptions!$D$119)),Assumptions!$D$118,0) | BN36: =SUM(E36:P36) | BO36: =SUM(Q36:AB36) | BP36: =SUM(AC36:AN36) | BQ36: =SUM(AO36:AZ36) | BR36: =SUM(BA36:BL36)
B37: Cash from financing | C37: EUR | E37: =E35+E36 | F37: =F35+F36 | G37: =G35+G36 | H37: =H35+H36 | I37: =I35+I36 | J37: =J35+J36 | K37: =K35+K36 | L37: =L35+L36 | ... BL37: =BL35+BL36 | BN37: =SUM(E37:P37) | BO37: =SUM(Q37:AB37) | BP37: =SUM(AC37:AN37) | BQ37: =SUM(AO37:AZ37) | BR37: =SUM(BA37:BL37)
B38: Movement in cash | C38: EUR | E38: =E32+E34+E37 | F38: =F32+F34+F37 | G38: =G32+G34+G37 | H38: =H32+H34+H37 | I38: =I32+I34+I37 | J38: =J32+J34+J37 | K38: =K32+K34+K37 | L38: =L32+L34+L37 | ... BL38: =BL32+BL34+BL37 | BN38: =SUM(E38:P38) | BO38: =SUM(Q38:AB38) | BP38: =SUM(AC38:AN38) | BQ38: =SUM(AO38:AZ38) | BR38: =SUM(BA38:BL38)
B39: Cash at the start of the month | C39: EUR | E39: =Assumptions!$D$6 | F39: =E40 | G39: =F40 | H39: =G40 | I39: =H40 | J39: =I40 | K39: =J40 | L39: =K40 | M39: =L40 | ... BL39: =BK40 | BN39: =E39 | BO39: =Q39 | BP39: =AC39 | BQ39: =AO39 | BR39: =BA39
B40: Cash at the end of the month | C40: EUR | E40: =E39+E38 | F40: =F39+F38 | G40: =G39+G38 | H40: =H39+H38 | I40: =I39+I38 | J40: =J39+J38 | K40: =K39+K38 | L40: =L39+L38 | ... BL40: =BL39+BL38 | BN40: =P40 | BO40: =AB40 | BP40: =AN40 | BQ40: =AZ40 | BR40: =BL40
B42: BALANCE SHEET
B43: Cash | C43: EUR | E43: =E40 | F43: =F40 | G43: =G40 | H43: =H40 | I43: =I40 | J43: =J40 | K43: =K40 | L43: =L40 | ... BL43: =BL40 | BN43: =P43 | BO43: =AB43 | BP43: =AN43 | BQ43: =AZ43 | BR43: =BL43
B44: Receivables | C44: EUR | E44: =Assumptions!$D$16/30*(E6-'Revenue Forecast'!E49) | F44: =Assumptions!$D$16/30*(F6-'Revenue Forecast'!F49) | G44: =Assumptions!$D$16/30*(G6-'Revenue Forecast'!G49) | H44: =Assumptions!$D$16/30*(H6-'Revenue Forecast'!H49) | I44: =Assumptions!$D$16/30*(I6-'Revenue Forecast'!I49) | J44: =Assumptions!$D$16/30*(J6-'Revenue Forecast'!J49) | K44: =Assumptions!$D$16/30*(K6-'Revenue Forecast'!K49) | L44: =Assumptions!$D$16/30*(L6-'Revenue Forecast'!L49) | ... BL44: =Assumptions!$D$16/30*(BL6-'Revenue Forecast'!BL49) | BN44: =P44 | BO44: =AB44 | BP44: =AN44 | BQ44: =AZ44 | BR44: =BL44 | BT44: on trading revenue only; the subsidy is a cash receipt, not an invoice
B45: Inventory | C45: EUR | E45: =Assumptions!$D$18/30*-E7 | F45: =Assumptions!$D$18/30*-F7 | G45: =Assumptions!$D$18/30*-G7 | H45: =Assumptions!$D$18/30*-H7 | I45: =Assumptions!$D$18/30*-I7 | J45: =Assumptions!$D$18/30*-J7 | K45: =Assumptions!$D$18/30*-K7 | L45: =Assumptions!$D$18/30*-L7 | ... BL45: =Assumptions!$D$18/30*-BL7 | BN45: =P45 | BO45: =AB45 | BP45: =AN45 | BQ45: =AZ45 | BR45: =BL45
B46: Total current assets | C46: EUR | E46: =SUM(E43:E45) | F46: =SUM(F43:F45) | G46: =SUM(G43:G45) | H46: =SUM(H43:H45) | I46: =SUM(I43:I45) | J46: =SUM(J43:J45) | K46: =SUM(K43:K45) | L46: =SUM(L43:L45) | ... BL46: =SUM(BL43:BL45) | BN46: =P46 | BO46: =AB46 | BP46: =AN46 | BQ46: =AZ46 | BR46: =BL46
B47: Property, plant and equipment, net | C47: EUR | E47: =E63-E62 | F47: =F63-F62 | G47: =G63-G62 | H47: =H63-H62 | I47: =I63-I62 | J47: =J63-J62 | K47: =K63-K62 | L47: =L63-L62 | ... BL47: =BL63-BL62 | BN47: =P47 | BO47: =AB47 | BP47: =AN47 | BQ47: =AZ47 | BR47: =BL47
B48: Total assets | C48: EUR | E48: =E46+E47 | F48: =F46+F47 | G48: =G46+G47 | H48: =H46+H47 | I48: =I46+I47 | J48: =J46+J47 | K48: =K46+K47 | L48: =L46+L47 | ... BL48: =BL46+BL47 | BN48: =P48 | BO48: =AB48 | BP48: =AN48 | BQ48: =AZ48 | BR48: =BL48
B50: Payables | C50: EUR | E50: =Assumptions!$D$17/30*-E7 | F50: =Assumptions!$D$17/30*-F7 | G50: =Assumptions!$D$17/30*-G7 | H50: =Assumptions!$D$17/30*-H7 | I50: =Assumptions!$D$17/30*-I7 | J50: =Assumptions!$D$17/30*-J7 | K50: =Assumptions!$D$17/30*-K7 | L50: =Assumptions!$D$17/30*-L7 | ... BL50: =Assumptions!$D$17/30*-BL7 | BN50: =P50 | BO50: =AB50 | BP50: =AN50 | BQ50: =AZ50 | BR50: =BL50
B51: Loan outstanding | C51: EUR | E51: =E36 | F51: =E51+F36 | G51: =F51+G36 | H51: =G51+H36 | I51: =H51+I36 | J51: =I51+J36 | K51: =J51+K36 | L51: =K51+L36 | M51: =L51+M36 | ... BL51: =BK51+BL36 | BN51: =P51 | BO51: =AB51 | BP51: =AN51 | BQ51: =AZ51 | BR51: =BL51
B52: Total liabilities | C52: EUR | E52: =E50+E51 | F52: =F50+F51 | G52: =G50+G51 | H52: =H50+H51 | I52: =I50+I51 | J52: =J50+J51 | K52: =K50+K51 | L52: =L50+L51 | ... BL52: =BL50+BL51 | BN52: =P52 | BO52: =AB52 | BP52: =AN52 | BQ52: =AZ52 | BR52: =BL52
B53: Share capital and premium | C53: EUR | E53: =Assumptions!$D$6+E35 | F53: =E53+F35 | G53: =F53+G35 | H53: =G53+H35 | I53: =H53+I35 | J53: =I53+J35 | K53: =J53+K35 | L53: =K53+L35 | M53: =L53+M35 | ... BL53: =BK53+BL35 | BN53: =P53 | BO53: =AB53 | BP53: =AN53 | BQ53: =AZ53 | BR53: =BL53 | BT53: opening equity matches the opening cash brought forward
B54: Retained earnings | C54: EUR | E54: =E23 | F54: =E54+F23 | G54: =F54+G23 | H54: =G54+H23 | I54: =H54+I23 | J54: =I54+J23 | K54: =J54+K23 | L54: =K54+L23 | M54: =L54+M23 | ... BL54: =BK54+BL23 | BN54: =P54 | BO54: =AB54 | BP54: =AN54 | BQ54: =AZ54 | BR54: =BL54
B55: Total equity | C55: EUR | E55: =E53+E54 | F55: =F53+F54 | G55: =G53+G54 | H55: =H53+H54 | I55: =I53+I54 | J55: =J53+J54 | K55: =K53+K54 | L55: =L53+L54 | ... BL55: =BL53+BL54 | BN55: =P55 | BO55: =AB55 | BP55: =AN55 | BQ55: =AZ55 | BR55: =BL55
B56: Total liabilities and equity | C56: EUR | E56: =E52+E55 | F56: =F52+F55 | G56: =G52+G55 | H56: =H52+H55 | I56: =I52+I55 | J56: =J52+J55 | K56: =K52+K55 | L56: =L52+L55 | ... BL56: =BL52+BL55 | BN56: =P56 | BO56: =AB56 | BP56: =AN56 | BQ56: =AZ56 | BR56: =BL56
B58: Check assets less liabilities and equity, must be nil | C58: EUR | E58: =E48-E56 | F58: =F48-F56 | G58: =G48-G56 | H58: =H48-H56 | I58: =I48-I56 | J58: =J48-J56 | K58: =K48-K56 | L58: =L48-L56 | ... BL58: =BL48-BL56 | BN58: =P58 | BO58: =AB58 | BP58: =AN58 | BQ58: =AZ58 | BR58: =BL58
B59: Check funding received equals the funding inputs, must be nil | C59: EUR | E59: =SUM($E$35:E35)+SUM($E$36:E36)-(IF((YEAR(E$3)*12+MONTH(E$3))>=(YEAR(Assumptions!$D$114)*12+MONTH(Assumptions!$D$114)),Assumptions!$D$115,0)+IF((YEAR(E$3)*12+MONTH(E$3))>=(YEAR(Assumptions!$D$116)*12+MONTH(Assumptions!$D$116)),Assumptions!$D$117,0)+IF((YEAR(E$3)*12+MONTH(E$3))>=(YEAR(Assumptions!$D$119)*12+MONTH(Assumptions!$D$119)),Assumptions!$D$118,0)) | F59: =SUM($E$35:F35)+SUM($E$36:F36)-(IF((YEAR(F$3)*12+MONTH(F$3))>=(YEAR(Assumptions!$D$114)*12+MONTH(Assumptions!$D$114)),Assumptions!$D$115,0)+IF((YEAR(F$3)*12+MONTH(F$3))>=(YEAR(Assumptions!$D$116)*12+MONTH(Assumptions!$D$116)),Assumptions!$D$117,0)+IF((YEAR(F$3)*12+MONTH(F$3))>=(YEAR(Assumptions!$D$119)*12+MONTH(Assumptions!$D$119)),Assumptions!$D$118,0)) | G59: =SUM($E$35:G35)+SUM($E$36:G36)-(IF((YEAR(G$3)*12+MONTH(G$3))>=(YEAR(Assumptions!$D$114)*12+MONTH(Assumptions!$D$114)),Assumptions!$D$115,0)+IF((YEAR(G$3)*12+MONTH(G$3))>=(YEAR(Assumptions!$D$116)*12+MONTH(Assumptions!$D$116)),Assumptions!$D$117,0)+IF((YEAR(G$3)*12+MONTH(G$3))>=(YEAR(Assumptions!$D$119)*12+MONTH(Assumptions!$D$119)),Assumptions!$D$118,0)) | H59: =SUM($E$35:H35)+SUM($E$36:H36)-(IF((YEAR(H$3)*12+MONTH(H$3))>=(YEAR(Assumptions!$D$114)*12+MONTH(Assumptions!$D$114)),Assumptions!$D$115,0)+IF((YEAR(H$3)*12+MONTH(H$3))>=(YEAR(Assumptions!$D$116)*12+MONTH(Assumptions!$D$116)),Assumptions!$D$117,0)+IF((YEAR(H$3)*12+MONTH(H$3))>=(YEAR(Assumptions!$D$119)*12+MONTH(Assumptions!$D$119)),Assumptions!$D$118,0)) | I59: =SUM($E$35:I35)+SUM($E$36:I36)-(IF((YEAR(I$3)*12+MONTH(I$3))>=(YEAR(Assumptions!$D$114)*12+MONTH(Assumptions!$D$114)),Assumptions!$D$115,0)+IF((YEAR(I$3)*12+MONTH(I$3))>=(YEAR(Assumptions!$D$116)*12+MONTH(Assumptions!$D$116)),Assumptions!$D$117,0)+IF((YEAR(I$3)*12+MONTH(I$3))>=(YEAR(Assumptions!$D$119)*12+MONTH(Assumptions!$D$119)),Assumptions!$D$118,0)) | J59: =SUM($E$35:J35)+SUM($E$36:J36)-(IF((YEAR(J$3)*12+MONTH(J$3))>=(YEAR(Assumptions!$D$114)*12+MONTH(Assumptions!$D$114)),Assumptions!$D$115,0)+IF((YEAR(J$3)*12+MONTH(J$3))>=(YEAR(Assumptions!$D$116)*12+MONTH(Assumptions!$D$116)),Assumptions!$D$117,0)+IF((YEAR(J$3)*12+MONTH(J$3))>=(YEAR(Assumptions!$D$119)*12+MONTH(Assumptions!$D$119)),Assumptions!$D$118,0)) | K59: =SUM($E$35:K35)+SUM($E$36:K36)-(IF((YEAR(K$3)*12+MONTH(K$3))>=(YEAR(Assumptions!$D$114)*12+MONTH(Assumptions!$D$114)),Assumptions!$D$115,0)+IF((YEAR(K$3)*12+MONTH(K$3))>=(YEAR(Assumptions!$D$116)*12+MONTH(Assumptions!$D$116)),Assumptions!$D$117,0)+IF((YEAR(K$3)*12+MONTH(K$3))>=(YEAR(Assumptions!$D$119)*12+MONTH(Assumptions!$D$119)),Assumptions!$D$118,0)) | L59: =SUM($E$35:L35)+SUM($E$36:L36)-(IF((YEAR(L$3)*12+MONTH(L$3))>=(YEAR(Assumptions!$D$114)*12+MONTH(Assumptions!$D$114)),Assumptions!$D$115,0)+IF((YEAR(L$3)*12+MONTH(L$3))>=(YEAR(Assumptions!$D$116)*12+MONTH(Assumptions!$D$116)),Assumptions!$D$117,0)+IF((YEAR(L$3)*12+MONTH(L$3))>=(YEAR(Assumptions!$D$119)*12+MONTH(Assumptions!$D$119)),Assumptions!$D$118,0)) | ... BL59: =SUM($E$35:BL35)+SUM($E$36:BL36)-(IF((YEAR(BL$3)*12+MONTH(BL$3))>=(YEAR(Assumptions!$D$114)*12+MONTH(Assumptions!$D$114)),Assumptions!$D$115,0)+IF((YEAR(BL$3)*12+MONTH(BL$3))>=(YEAR(Assumptions!$D$116)*12+MONTH(Assumptions!$D$116)),Assumptions!$D$117,0)+IF((YEAR(BL$3)*12+MONTH(BL$3))>=(YEAR(Assumptions!$D$119)*12+MONTH(Assumptions!$D$119)),Assumptions!$D$118,0)) | BN59: =P59 | BO59: =AB59 | BP59: =AN59 | BQ59: =AZ59 | BR59: =BL59 | BT59: cumulative equity and loan received against what the funding block says should have arrived by now
B60: SUPPORTING SCHEDULES
B61: Capital expenditure in the month | C61: EUR | E61: =0 | F61: =0 | G61: =0 | H61: =0 | I61: =0 | J61: =0 | K61: =0 | L61: =0 | ... BL61: =0 | BN61: =SUM(E61:P61) | BO61: =SUM(Q61:AB61) | BP61: =SUM(AC61:AN61) | BQ61: =SUM(AO61:AZ61) | BR61: =SUM(BA61:BL61) | BT61: no in-house production in this case, so no capex
B62: Accumulated depreciation | C62: EUR | E62: =-E19 | F62: =E62-F19 | G62: =F62-G19 | H62: =G62-H19 | I62: =H62-I19 | J62: =I62-J19 | K62: =J62-K19 | L62: =K62-L19 | M62: =L62-M19 | ... BL62: =BK62-BL19 | BN62: =P62 | BO62: =AB62 | BP62: =AN62 | BQ62: =AZ62 | BR62: =BL62
B63: Gross book value | C63: EUR | E63: =E61 | F63: =E63+F61 | G63: =F63+G61 | H63: =G63+H61 | I63: =H63+I61 | J63: =I63+J61 | K63: =J63+K61 | L63: =K63+L61 | M63: =L63+M61 | ... BL63: =BK63+BL61 | BN63: =P63 | BO63: =AB63 | BP63: =AN63 | BQ63: =AZ63 | BR63: =BL63
B64: Tax losses carried forward | C64: EUR | E64: =MAX(0,-E21) | F64: =MAX(0,E64-MAX(0,F21))+MAX(0,-F21) | G64: =MAX(0,F64-MAX(0,G21))+MAX(0,-G21) | H64: =MAX(0,G64-MAX(0,H21))+MAX(0,-H21) | I64: =MAX(0,H64-MAX(0,I21))+MAX(0,-I21) | J64: =MAX(0,I64-MAX(0,J21))+MAX(0,-J21) | K64: =MAX(0,J64-MAX(0,K21))+MAX(0,-K21) | L64: =MAX(0,K64-MAX(0,L21))+MAX(0,-L21) | M64: =MAX(0,L64-MAX(0,M21))+MAX(0,-M21) | ... BL64: =MAX(0,BK64-MAX(0,BL21))+MAX(0,-BL21) | BN64: =P64 | BO64: =AB64 | BP64: =AN64 | BQ64: =AZ64 | BR64: =BL64

Sheet Revenue Forecast
B1: Tarnoc B.V. Revenue Forecast
B2: Units sold is an output: marketing spend generates orders, and selling and build capacity cap them.
E3: 46023 | F3: 46054 | G3: 46082 | H3: 46113 | I3: 46143 | J3: 46174 | K3: 46204 | L3: 46235 | M3: 46266 | N3: 46296 | O3: 46327 | P3: 46357 | Q3: 46388 | R3: 46419 | S3: 46447 | T3: 46478 | U3: 46508 | V3: 46539 | W3: 46569 | X3: 46600 | Y3: 46631 | Z3: 46661 | AA3: 46692 | AB3: 46722 | AC3: 46753 | AD3: 46784 | AE3: 46813 | AF3: 46844 | AG3: 46874 | AH3: 46905 | AI3: 46935 | AJ3: 46966 | AK3: 46997 | AL3: 47027 | AM3: 47058 | AN3: 47088 | AO3: 47119 | AP3: 47150 | AQ3: 47178 | AR3: 47209 | AS3: 47239 | AT3: 47270 | AU3: 47300 | AV3: 47331 | AW3: 47362 | AX3: 47392 | AY3: 47423 | AZ3: 47453 | BA3: 47484 | BB3: 47515 | BC3: 47543 | BD3: 47574 | BE3: 47604 | BF3: 47635 | BG3: 47665 | BH3: 47696 | BI3: 47727 | BJ3: 47757 | BK3: 47788 | BL3: 47818 | BN3: 2026 | BO3: 2027 | BP3: 2028 | BQ3: 2029 | BR3: 2030 | BT3: what this row does
B5: DEMAND
B6: Marketing spend | C6: EUR/mo | E6: =IF(E$3<Assumptions!$D$11,0,HLOOKUP(YEAR(E$3),Assumptions!$D$44:$H$45,2,FALSE)) | F6: =IF(F$3<Assumptions!$D$11,0,HLOOKUP(YEAR(F$3),Assumptions!$D$44:$H$45,2,FALSE)) | G6: =IF(G$3<Assumptions!$D$11,0,HLOOKUP(YEAR(G$3),Assumptions!$D$44:$H$45,2,FALSE)) | H6: =IF(H$3<Assumptions!$D$11,0,HLOOKUP(YEAR(H$3),Assumptions!$D$44:$H$45,2,FALSE)) | I6: =IF(I$3<Assumptions!$D$11,0,HLOOKUP(YEAR(I$3),Assumptions!$D$44:$H$45,2,FALSE)) | J6: =IF(J$3<Assumptions!$D$11,0,HLOOKUP(YEAR(J$3),Assumptions!$D$44:$H$45,2,FALSE)) | K6: =IF(K$3<Assumptions!$D$11,0,HLOOKUP(YEAR(K$3),Assumptions!$D$44:$H$45,2,FALSE)) | L6: =IF(L$3<Assumptions!$D$11,0,HLOOKUP(YEAR(L$3),Assumptions!$D$44:$H$45,2,FALSE)) | ... BL6: =IF(BL$3<Assumptions!$D$11,0,HLOOKUP(YEAR(BL$3),Assumptions!$D$44:$H$45,2,FALSE)) | BN6: =SUM(E6:P6) | BO6: =SUM(Q6:AB6) | BP6: =SUM(AC6:AN6) | BQ6: =SUM(AO6:AZ6) | BR6: =SUM(BA6:BL6) | BT6: from the Assumptions year table
B7: Installed base at start of month | C7: units | E7: =0 | F7: =E41 | G7: =F41 | H7: =G41 | I7: =H41 | J7: =I41 | K7: =J41 | L7: =K41 | M7: =L41 | ... BL7: =BK41 | BN7: =P7 | BO7: =AB7 | BP7: =AN7 | BQ7: =AZ7 | BR7: =BL7
B8: Cost per lead | C8: EUR | E8: =Assumptions!$D$47 | F8: =Assumptions!$D$47 | G8: =Assumptions!$D$47 | H8: =Assumptions!$D$47 | I8: =Assumptions!$D$47 | J8: =Assumptions!$D$47 | K8: =Assumptions!$D$47 | L8: =Assumptions!$D$47 | ... BL8: =Assumptions!$D$47 | BN8: =IFERROR(AVERAGE(E8:P8),0) | BO8: =IFERROR(AVERAGE(Q8:AB8),0) | BP8: =IFERROR(AVERAGE(AC8:AN8),0) | BQ8: =IFERROR(AVERAGE(AO8:AZ8),0) | BR8: =IFERROR(AVERAGE(BA8:BL8),0) | BT8: held flat: marketing per unit only falls as installers bring in more of the orders
B9: Qualified leads | C9: leads | E9: =IFERROR(E6/E8,0)*Assumptions!$D$48 | F9: =IFERROR(F6/F8,0)*Assumptions!$D$48 | G9: =IFERROR(G6/G8,0)*Assumptions!$D$48 | H9: =IFERROR(H6/H8,0)*Assumptions!$D$48 | I9: =IFERROR(I6/I8,0)*Assumptions!$D$48 | J9: =IFERROR(J6/J8,0)*Assumptions!$D$48 | K9: =IFERROR(K6/K8,0)*Assumptions!$D$48 | L9: =IFERROR(L6/L8,0)*Assumptions!$D$48 | ... BL9: =IFERROR(BL6/BL8,0)*Assumptions!$D$48 | BN9: =SUM(E9:P9) | BO9: =SUM(Q9:AB9) | BP9: =SUM(AC9:AN9) | BQ9: =SUM(AO9:AZ9) | BR9: =SUM(BA9:BL9) | BT9: marketing spend divided by cost per lead, then the lead to qualified rate
B10: Orders the funnel generates | C10: units | E10: =E9*Assumptions!$D$49 | F10: =F9*Assumptions!$D$49 | G10: =G9*Assumptions!$D$49 | H10: =H9*Assumptions!$D$49 | I10: =I9*Assumptions!$D$49 | J10: =J9*Assumptions!$D$49 | K10: =K9*Assumptions!$D$49 | L10: =L9*Assumptions!$D$49 | ... BL10: =BL9*Assumptions!$D$49 | BN10: =SUM(E10:P10) | BO10: =SUM(Q10:AB10) | BP10: =SUM(AC10:AN10) | BQ10: =SUM(AO10:AZ10) | BR10: =SUM(BA10:BL10)
B11: Orders installer partners bring in | C11: units | E11: =E20*HLOOKUP(YEAR(E$3),Assumptions!$D$57:$H$58,2,FALSE) | F11: =F20*HLOOKUP(YEAR(F$3),Assumptions!$D$57:$H$58,2,FALSE) | G11: =G20*HLOOKUP(YEAR(G$3),Assumptions!$D$57:$H$58,2,FALSE) | H11: =H20*HLOOKUP(YEAR(H$3),Assumptions!$D$57:$H$58,2,FALSE) | I11: =I20*HLOOKUP(YEAR(I$3),Assumptions!$D$57:$H$58,2,FALSE) | J11: =J20*HLOOKUP(YEAR(J$3),Assumptions!$D$57:$H$58,2,FALSE) | K11: =K20*HLOOKUP(YEAR(K$3),Assumptions!$D$57:$H$58,2,FALSE) | L11: =L20*HLOOKUP(YEAR(L$3),Assumptions!$D$57:$H$58,2,FALSE) | ... BL11: =BL20*HLOOKUP(YEAR(BL$3),Assumptions!$D$57:$H$58,2,FALSE) | BN11: =SUM(E11:P11) | BO11: =SUM(Q11:AB11) | BP11: =SUM(AC11:AN11) | BQ11: =SUM(AO11:AZ11) | BR11: =SUM(BA11:BL11) | BT11: partners on the books times the orders each finds on their own jobs
B12: Demand | C12: units | E12: =E10+E11 | F12: =F10+F11 | G12: =G10+G11 | H12: =H10+H11 | I12: =I10+I11 | J12: =J10+J11 | K12: =K10+K11 | L12: =L10+L11 | ... BL12: =BL10+BL11 | BN12: =SUM(E12:P12) | BO12: =SUM(Q12:AB12) | BP12: =SUM(AC12:AN12) | BQ12: =SUM(AO12:AZ12) | BR12: =SUM(BA12:BL12)
B14: SELLING CAPACITY
B15: Share sold direct | C15: % | E15: =HLOOKUP(YEAR(E$3),Assumptions!$D$51:$H$52,2,FALSE) | F15: =HLOOKUP(YEAR(F$3),Assumptions!$D$51:$H$52,2,FALSE) | G15: =HLOOKUP(YEAR(G$3),Assumptions!$D$51:$H$52,2,FALSE) | H15: =HLOOKUP(YEAR(H$3),Assumptions!$D$51:$H$52,2,FALSE) | I15: =HLOOKUP(YEAR(I$3),Assumptions!$D$51:$H$52,2,FALSE) | J15: =HLOOKUP(YEAR(J$3),Assumptions!$D$51:$H$52,2,FALSE) | K15: =HLOOKUP(YEAR(K$3),Assumptions!$D$51:$H$52,2,FALSE) | L15: =HLOOKUP(YEAR(L$3),Assumptions!$D$51:$H$52,2,FALSE) | ... BL15: =HLOOKUP(YEAR(BL$3),Assumptions!$D$51:$H$52,2,FALSE) | BN15: =IFERROR(AVERAGE(E15:P15),0) | BO15: =IFERROR(AVERAGE(Q15:AB15),0) | BP15: =IFERROR(AVERAGE(AC15:AN15),0) | BQ15: =IFERROR(AVERAGE(AO15:AZ15),0) | BR15: =IFERROR(AVERAGE(BA15:BL15),0) | BT15: the rest is sold by trained installer partners
B16: Rep hiring rate | C16: FTE/month | E16: =IF(E$3<Assumptions!$D$11,0,HLOOKUP(YEAR(E$3),Assumptions!$D$53:$H$54,2,FALSE)) | F16: =IF(F$3<Assumptions!$D$11,0,HLOOKUP(YEAR(F$3),Assumptions!$D$53:$H$54,2,FALSE)) | G16: =IF(G$3<Assumptions!$D$11,0,HLOOKUP(YEAR(G$3),Assumptions!$D$53:$H$54,2,FALSE)) | H16: =IF(H$3<Assumptions!$D$11,0,HLOOKUP(YEAR(H$3),Assumptions!$D$53:$H$54,2,FALSE)) | I16: =IF(I$3<Assumptions!$D$11,0,HLOOKUP(YEAR(I$3),Assumptions!$D$53:$H$54,2,FALSE)) | J16: =IF(J$3<Assumptions!$D$11,0,HLOOKUP(YEAR(J$3),Assumptions!$D$53:$H$54,2,FALSE)) | K16: =IF(K$3<Assumptions!$D$11,0,HLOOKUP(YEAR(K$3),Assumptions!$D$53:$H$54,2,FALSE)) | L16: =IF(L$3<Assumptions!$D$11,0,HLOOKUP(YEAR(L$3),Assumptions!$D$53:$H$54,2,FALSE)) | ... BL16: =IF(BL$3<Assumptions!$D$11,0,HLOOKUP(YEAR(BL$3),Assumptions!$D$53:$H$54,2,FALSE)) | BN16: =SUM(E16:P16) | BO16: =SUM(Q16:AB16) | BP16: =SUM(AC16:AN16) | BQ16: =SUM(AO16:AZ16) | BR16: =SUM(BA16:BL16) | BT16: the planned rate, which can be less than one a month
B17: Reps in post | C17: FTE | E17: =ROUNDDOWN(Assumptions!$D$60+SUM($E16:E16),0) | F17: =ROUNDDOWN(Assumptions!$D$60+SUM($E16:F16),0) | G17: =ROUNDDOWN(Assumptions!$D$60+SUM($E16:G16),0) | H17: =ROUNDDOWN(Assumptions!$D$60+SUM($E16:H16),0) | I17: =ROUNDDOWN(Assumptions!$D$60+SUM($E16:I16),0) | J17: =ROUNDDOWN(Assumptions!$D$60+SUM($E16:J16),0) | K17: =ROUNDDOWN(Assumptions!$D$60+SUM($E16:K16),0) | L17: =ROUNDDOWN(Assumptions!$D$60+SUM($E16:L16),0) | ... BL17: =ROUNDDOWN(Assumptions!$D$60+SUM($E16:BL16),0) | BN17: =P17 | BO17: =AB17 | BP17: =AN17 | BQ17: =AZ17 | BR17: =BL17 | BT17: whole people only, so half a rep a month means one every second month
B18: Capacity from our own reps | C18: units/mo | E18: =E17*Assumptions!$D$61 | F18: =F17*Assumptions!$D$61 | G18: =G17*Assumptions!$D$61 | H18: =H17*Assumptions!$D$61 | I18: =I17*Assumptions!$D$61 | J18: =J17*Assumptions!$D$61 | K18: =K17*Assumptions!$D$61 | L18: =L17*Assumptions!$D$61 | ... BL18: =BL17*Assumptions!$D$61 | BN18: =SUM(E18:P18) | BO18: =SUM(Q18:AB18) | BP18: =SUM(AC18:AN18) | BQ18: =SUM(AO18:AZ18) | BR18: =SUM(BA18:BL18) | BT18: every rep in post carries full quota from the month they are hired
B19: Partner signing rate | C19: partners/month | E19: =IF(E$3<Assumptions!$D$11,0,HLOOKUP(YEAR(E$3),Assumptions!$D$55:$H$56,2,FALSE)) | F19: =IF(F$3<Assumptions!$D$11,0,HLOOKUP(YEAR(F$3),Assumptions!$D$55:$H$56,2,FALSE)) | G19: =IF(G$3<Assumptions!$D$11,0,HLOOKUP(YEAR(G$3),Assumptions!$D$55:$H$56,2,FALSE)) | H19: =IF(H$3<Assumptions!$D$11,0,HLOOKUP(YEAR(H$3),Assumptions!$D$55:$H$56,2,FALSE)) | I19: =IF(I$3<Assumptions!$D$11,0,HLOOKUP(YEAR(I$3),Assumptions!$D$55:$H$56,2,FALSE)) | J19: =IF(J$3<Assumptions!$D$11,0,HLOOKUP(YEAR(J$3),Assumptions!$D$55:$H$56,2,FALSE)) | K19: =IF(K$3<Assumptions!$D$11,0,HLOOKUP(YEAR(K$3),Assumptions!$D$55:$H$56,2,FALSE)) | L19: =IF(L$3<Assumptions!$D$11,0,HLOOKUP(YEAR(L$3),Assumptions!$D$55:$H$56,2,FALSE)) | ... BL19: =IF(BL$3<Assumptions!$D$11,0,HLOOKUP(YEAR(BL$3),Assumptions!$D$55:$H$56,2,FALSE)) | BN19: =SUM(E19:P19) | BO19: =SUM(Q19:AB19) | BP19: =SUM(AC19:AN19) | BQ19: =SUM(AO19:AZ19) | BR19: =SUM(BA19:BL19) | BT19: the planned rate, which can be less than one a month
B20: Installer partners on the books | C20: partners | E20: =ROUNDDOWN(Assumptions!$D$62+SUM($E19:E19),0) | F20: =ROUNDDOWN(Assumptions!$D$62+SUM($E19:F19),0) | G20: =ROUNDDOWN(Assumptions!$D$62+SUM($E19:G19),0) | H20: =ROUNDDOWN(Assumptions!$D$62+SUM($E19:H19),0) | I20: =ROUNDDOWN(Assumptions!$D$62+SUM($E19:I19),0) | J20: =ROUNDDOWN(Assumptions!$D$62+SUM($E19:J19),0) | K20: =ROUNDDOWN(Assumptions!$D$62+SUM($E19:K19),0) | L20: =ROUNDDOWN(Assumptions!$D$62+SUM($E19:L19),0) | ... BL20: =ROUNDDOWN(Assumptions!$D$62+SUM($E19:BL19),0) | BN20: =P20 | BO20: =AB20 | BP20: =AN20 | BQ20: =AZ20 | BR20: =BL20 | BT20: whole partners only, signed as the running total passes each whole number
B21: Capacity from the installer channel | C21: units/mo | E21: =E20*Assumptions!$D$63 | F21: =F20*Assumptions!$D$63 | G21: =G20*Assumptions!$D$63 | H21: =H20*Assumptions!$D$63 | I21: =I20*Assumptions!$D$63 | J21: =J20*Assumptions!$D$63 | K21: =K20*Assumptions!$D$63 | L21: =L20*Assumptions!$D$63 | ... BL21: =BL20*Assumptions!$D$63 | BN21: =SUM(E21:P21) | BO21: =SUM(Q21:AB21) | BP21: =SUM(AC21:AN21) | BQ21: =SUM(AO21:AZ21) | BR21: =SUM(BA21:BL21) | BT21: every partner on the books sells full volume from the month they are signed
B22: Selling capacity | C22: units/mo | E22: =MIN(IFERROR(E18/E15,1000000),IFERROR(E21/(1-E15),1000000)) | F22: =MIN(IFERROR(F18/F15,1000000),IFERROR(F21/(1-F15),1000000)) | G22: =MIN(IFERROR(G18/G15,1000000),IFERROR(G21/(1-G15),1000000)) | H22: =MIN(IFERROR(H18/H15,1000000),IFERROR(H21/(1-H15),1000000)) | I22: =MIN(IFERROR(I18/I15,1000000),IFERROR(I21/(1-I15),1000000)) | J22: =MIN(IFERROR(J18/J15,1000000),IFERROR(J21/(1-J15),1000000)) | K22: =MIN(IFERROR(K18/K15,1000000),IFERROR(K21/(1-K15),1000000)) | L22: =MIN(IFERROR(L18/L15,1000000),IFERROR(L21/(1-L15),1000000)) | ... BL22: =MIN(IFERROR(BL18/BL15,1000000),IFERROR(BL21/(1-BL15),1000000)) | BN22: =SUM(E22:P22) | BO22: =SUM(Q22:AB22) | BP22: =SUM(AC22:AN22) | BQ22: =SUM(AO22:AZ22) | BR22: =SUM(BA22:BL22) | BT22: our reps must cover the direct share and the partners the rest, so the mix caps it
B23: Partner managers needed | C23: FTE | E23: =ROUND(E20/Assumptions!$D$65,0) | F23: =ROUND(F20/Assumptions!$D$65,0) | G23: =ROUND(G20/Assumptions!$D$65,0) | H23: =ROUND(H20/Assumptions!$D$65,0) | I23: =ROUND(I20/Assumptions!$D$65,0) | J23: =ROUND(J20/Assumptions!$D$65,0) | K23: =ROUND(K20/Assumptions!$D$65,0) | L23: =ROUND(L20/Assumptions!$D$65,0) | ... BL23: =ROUND(BL20/Assumptions!$D$65,0) | BN23: =P23 | BO23: =AB23 | BP23: =AN23 | BQ23: =AZ23 | BR23: =BL23
B24: Selling capacity used | C24: % | E24: =IFERROR(E34/E22,0) | F24: =IFERROR(F34/F22,0) | G24: =IFERROR(G34/G22,0) | H24: =IFERROR(H34/H22,0) | I24: =IFERROR(I34/I22,0) | J24: =IFERROR(J34/J22,0) | K24: =IFERROR(K34/K22,0) | L24: =IFERROR(L34/L22,0) | ... BL24: =IFERROR(BL34/BL22,0) | BN24: =IFERROR(BN34/BN22,0) | BO24: =IFERROR(BO34/BO22,0) | BP24: =IFERROR(BP34/BP22,0) | BQ24: =IFERROR(BQ34/BQ22,0) | BR24: =IFERROR(BR34/BR22,0)
B27: BUILD CAPACITY
B28: Assembly partner | C28: units/mo | E28: =Assumptions!$D$68 | F28: =Assumptions!$D$68 | G28: =Assumptions!$D$68 | H28: =Assumptions!$D$68 | I28: =Assumptions!$D$68 | J28: =Assumptions!$D$68 | K28: =Assumptions!$D$68 | L28: =Assumptions!$D$68 | ... BL28: =Assumptions!$D$68 | BN28: =SUM(E28:P28) | BO28: =SUM(Q28:AB28) | BP28: =SUM(AC28:AN28) | BQ28: =SUM(AO28:AZ28) | BR28: =SUM(BA28:BL28) | BT28: the partner builds every unit in this case
B31: Build capacity | C31: units/mo | E31: =E28 | F31: =F28 | G31: =G28 | H31: =H28 | I31: =I28 | J31: =J28 | K31: =K28 | L31: =L28 | ... BL31: =BL28 | BN31: =SUM(E31:P31) | BO31: =SUM(Q31:AB31) | BP31: =SUM(AC31:AN31) | BQ31: =SUM(AO31:AZ31) | BR31: =SUM(BA31:BL31)
B33: UNITS SOLD
B34: Units sold | C34: units | E34: =IF(E$3<Assumptions!$D$11,0,ROUND(MIN(E12,E22,E31),0)) | F34: =IF(F$3<Assumptions!$D$11,0,ROUND(MIN(F12,F22,F31),0)) | G34: =IF(G$3<Assumptions!$D$11,0,ROUND(MIN(G12,G22,G31),0)) | H34: =IF(H$3<Assumptions!$D$11,0,ROUND(MIN(H12,H22,H31),0)) | I34: =IF(I$3<Assumptions!$D$11,0,ROUND(MIN(I12,I22,I31),0)) | J34: =IF(J$3<Assumptions!$D$11,0,ROUND(MIN(J12,J22,J31),0)) | K34: =IF(K$3<Assumptions!$D$11,0,ROUND(MIN(K12,K22,K31),0)) | L34: =IF(L$3<Assumptions!$D$11,0,ROUND(MIN(L12,L22,L31),0)) | ... BL34: =IF(BL$3<Assumptions!$D$11,0,ROUND(MIN(BL12,BL22,BL31),0)) | BN34: =SUM(E34:P34) | BO34: =SUM(Q34:AB34) | BP34: =SUM(AC34:AN34) | BQ34: =SUM(AO34:AZ34) | BR34: =SUM(BA34:BL34) | BT34: nil until the first month we can sell, then the smallest of demand, selling and build capacity
B35: Build capacity used | C35: % | E35: =IFERROR(E34/E31,0) | F35: =IFERROR(F34/F31,0) | G35: =IFERROR(G34/G31,0) | H35: =IFERROR(H34/H31,0) | I35: =IFERROR(I34/I31,0) | J35: =IFERROR(J34/J31,0) | K35: =IFERROR(K34/K31,0) | L35: =IFERROR(L34/L31,0) | ... BL35: =IFERROR(BL34/BL31,0) | BN35: =IFERROR(BN34/BN31,0) | BO35: =IFERROR(BO34/BO31,0) | BP35: =IFERROR(BP34/BP31,0) | BQ35: =IFERROR(BQ34/BQ31,0) | BR35: =IFERROR(BR34/BR31,0)
B38: UNIT SPLIT AND INSTALLED BASE
B39: TTK units | C39: units | E39: =ROUND(E34*Assumptions!$D$25,0) | F39: =ROUND(F34*Assumptions!$D$25,0) | G39: =ROUND(G34*Assumptions!$D$25,0) | H39: =ROUND(H34*Assumptions!$D$25,0) | I39: =ROUND(I34*Assumptions!$D$25,0) | J39: =ROUND(J34*Assumptions!$D$25,0) | K39: =ROUND(K34*Assumptions!$D$25,0) | L39: =ROUND(L34*Assumptions!$D$25,0) | ... BL39: =ROUND(BL34*Assumptions!$D$25,0) | BN39: =SUM(E39:P39) | BO39: =SUM(Q39:AB39) | BP39: =SUM(AC39:AN39) | BQ39: =SUM(AO39:AZ39) | BR39: =SUM(BA39:BL39) | BT39: whole units, and the Combi+ row takes the remainder so the two add to units sold
B40: Combi+ units | C40: units | E40: =E34-E39 | F40: =F34-F39 | G40: =G34-G39 | H40: =H34-H39 | I40: =I34-I39 | J40: =J34-J39 | K40: =K34-K39 | L40: =L34-L39 | ... BL40: =BL34-BL39 | BN40: =SUM(E40:P40) | BO40: =SUM(Q40:AB40) | BP40: =SUM(AC40:AN40) | BQ40: =SUM(AO40:AZ40) | BR40: =SUM(BA40:BL40)
B41: Installed base at end of month | C41: units | E41: =E7+E34 | F41: =F7+F34 | G41: =G7+G34 | H41: =H7+H34 | I41: =I7+I34 | J41: =J7+J34 | K41: =K7+K34 | L41: =L7+L34 | ... BL41: =BL7+BL34 | BN41: =P41 | BO41: =AB41 | BP41: =AN41 | BQ41: =AZ41 | BR41: =BL41
B43: REVENUE
B44: Turbineketel | C44: EUR | E44: =E39*Assumptions!$D$20 | F44: =F39*Assumptions!$D$20 | G44: =G39*Assumptions!$D$20 | H44: =H39*Assumptions!$D$20 | I44: =I39*Assumptions!$D$20 | J44: =J39*Assumptions!$D$20 | K44: =K39*Assumptions!$D$20 | L44: =L39*Assumptions!$D$20 | ... BL44: =BL39*Assumptions!$D$20 | BN44: =SUM(E44:P44) | BO44: =SUM(Q44:AB44) | BP44: =SUM(AC44:AN44) | BQ44: =SUM(AO44:AZ44) | BR44: =SUM(BA44:BL44)
B45: Combi+ | C45: EUR | E45: =E40*Assumptions!$D$22 | F45: =F40*Assumptions!$D$22 | G45: =G40*Assumptions!$D$22 | H45: =H40*Assumptions!$D$22 | I45: =I40*Assumptions!$D$22 | J45: =J40*Assumptions!$D$22 | K45: =K40*Assumptions!$D$22 | L45: =L40*Assumptions!$D$22 | ... BL45: =BL40*Assumptions!$D$22 | BN45: =SUM(E45:P45) | BO45: =SUM(Q45:AB45) | BP45: =SUM(AC45:AN45) | BQ45: =SUM(AO45:AZ45) | BR45: =SUM(BA45:BL45)
B46: Upsell basket | C46: EUR | E46: =E34*Assumptions!$D$32 | F46: =F34*Assumptions!$D$32 | G46: =G34*Assumptions!$D$32 | H46: =H34*Assumptions!$D$32 | I46: =I34*Assumptions!$D$32 | J46: =J34*Assumptions!$D$32 | K46: =K34*Assumptions!$D$32 | L46: =L34*Assumptions!$D$32 | ... BL46: =BL34*Assumptions!$D$32 | BN46: =SUM(E46:P46) | BO46: =SUM(Q46:AB46) | BP46: =SUM(AC46:AN46) | BQ46: =SUM(AO46:AZ46) | BR46: =SUM(BA46:BL46)
B47: Installation (pass-through) | C47: EUR | E47: =E39*Assumptions!$D$23+E40*Assumptions!$D$24 | F47: =F39*Assumptions!$D$23+F40*Assumptions!$D$24 | G47: =G39*Assumptions!$D$23+G40*Assumptions!$D$24 | H47: =H39*Assumptions!$D$23+H40*Assumptions!$D$24 | I47: =I39*Assumptions!$D$23+I40*Assumptions!$D$24 | J47: =J39*Assumptions!$D$23+J40*Assumptions!$D$24 | K47: =K39*Assumptions!$D$23+K40*Assumptions!$D$24 | L47: =L39*Assumptions!$D$23+L40*Assumptions!$D$24 | ... BL47: =BL39*Assumptions!$D$23+BL40*Assumptions!$D$24 | BN47: =SUM(E47:P47) | BO47: =SUM(Q47:AB47) | BP47: =SUM(AC47:AN47) | BQ47: =SUM(AO47:AZ47) | BR47: =SUM(BA47:BL47) | BT47: revenue equals cost, so it adds no margin
B48: Service contracts | C48: EUR | E48: =E7*Assumptions!$D$40/12 | F48: =F7*Assumptions!$D$40/12 | G48: =G7*Assumptions!$D$40/12 | H48: =H7*Assumptions!$D$40/12 | I48: =I7*Assumptions!$D$40/12 | J48: =J7*Assumptions!$D$40/12 | K48: =K7*Assumptions!$D$40/12 | L48: =L7*Assumptions!$D$40/12 | ... BL48: =BL7*Assumptions!$D$40/12 | BN48: =SUM(E48:P48) | BO48: =SUM(Q48:AB48) | BP48: =SUM(AC48:AN48) | BQ48: =SUM(AO48:AZ48) | BR48: =SUM(BA48:BL48) | BT48: charged on the installed base at the start of the month
B49: Subsidies and grants | C49: EUR | E49: =IF(AND(YEAR(E$3)=YEAR(Assumptions!$D$14),MONTH(E$3)=MONTH(Assumptions!$D$14)),Assumptions!$D$13,0) | F49: =IF(AND(YEAR(F$3)=YEAR(Assumptions!$D$14),MONTH(F$3)=MONTH(Assumptions!$D$14)),Assumptions!$D$13,0) | G49: =IF(AND(YEAR(G$3)=YEAR(Assumptions!$D$14),MONTH(G$3)=MONTH(Assumptions!$D$14)),Assumptions!$D$13,0) | H49: =IF(AND(YEAR(H$3)=YEAR(Assumptions!$D$14),MONTH(H$3)=MONTH(Assumptions!$D$14)),Assumptions!$D$13,0) | I49: =IF(AND(YEAR(I$3)=YEAR(Assumptions!$D$14),MONTH(I$3)=MONTH(Assumptions!$D$14)),Assumptions!$D$13,0) | J49: =IF(AND(YEAR(J$3)=YEAR(Assumptions!$D$14),MONTH(J$3)=MONTH(Assumptions!$D$14)),Assumptions!$D$13,0) | K49: =IF(AND(YEAR(K$3)=YEAR(Assumptions!$D$14),MONTH(K$3)=MONTH(Assumptions!$D$14)),Assumptions!$D$13,0) | L49: =IF(AND(YEAR(L$3)=YEAR(Assumptions!$D$14),MONTH(L$3)=MONTH(Assumptions!$D$14)),Assumptions!$D$13,0) | ... BL49: =IF(AND(YEAR(BL$3)=YEAR(Assumptions!$D$14),MONTH(BL$3)=MONTH(Assumptions!$D$14)),Assumptions!$D$13,0) | BN49: =SUM(E49:P49) | BO49: =SUM(Q49:AB49) | BP49: =SUM(AC49:AN49) | BQ49: =SUM(AO49:AZ49) | BR49: =SUM(BA49:BL49) | BT49: the 2026 subsidy already in the committed plan
B50: Total revenue | C50: EUR | E50: =SUM(E44:E49) | F50: =SUM(F44:F49) | G50: =SUM(G44:G49) | H50: =SUM(H44:H49) | I50: =SUM(I44:I49) | J50: =SUM(J44:J49) | K50: =SUM(K44:K49) | L50: =SUM(L44:L49) | ... BL50: =SUM(BL44:BL49) | BN50: =SUM(E50:P50) | BO50: =SUM(Q50:AB50) | BP50: =SUM(AC50:AN50) | BQ50: =SUM(AO50:AZ50) | BR50: =SUM(BA50:BL50)
B51: Revenue per unit | C51: EUR/unit | E51: =IFERROR((E50-E49)/E34,0) | F51: =IFERROR((F50-F49)/F34,0) | G51: =IFERROR((G50-G49)/G34,0) | H51: =IFERROR((H50-H49)/H34,0) | I51: =IFERROR((I50-I49)/I34,0) | J51: =IFERROR((J50-J49)/J34,0) | K51: =IFERROR((K50-K49)/K34,0) | L51: =IFERROR((L50-L49)/L34,0) | ... BL51: =IFERROR((BL50-BL49)/BL34,0) | BN51: =IFERROR((BN50-BN49)/BN34,0) | BO51: =IFERROR((BO50-BO49)/BO34,0) | BP51: =IFERROR((BP50-BP49)/BP34,0) | BQ51: =IFERROR((BQ50-BQ49)/BQ34,0) | BR51: =IFERROR((BR50-BR49)/BR34,0)

Sheet COGS
B1: Tarnoc B.V. Cost of Goods Sold
B2: Unit cost falls as volume crosses each tier. The tier is set on this year plus next year's units, a two-year volume commitment to the supplier.
E3: 46023 | F3: 46054 | G3: 46082 | H3: 46113 | I3: 46143 | J3: 46174 | K3: 46204 | L3: 46235 | M3: 46266 | N3: 46296 | O3: 46327 | P3: 46357 | Q3: 46388 | R3: 46419 | S3: 46447 | T3: 46478 | U3: 46508 | V3: 46539 | W3: 46569 | X3: 46600 | Y3: 46631 | Z3: 46661 | AA3: 46692 | AB3: 46722 | AC3: 46753 | AD3: 46784 | AE3: 46813 | AF3: 46844 | AG3: 46874 | AH3: 46905 | AI3: 46935 | AJ3: 46966 | AK3: 46997 | AL3: 47027 | AM3: 47058 | AN3: 47088 | AO3: 47119 | AP3: 47150 | AQ3: 47178 | AR3: 47209 | AS3: 47239 | AT3: 47270 | AU3: 47300 | AV3: 47331 | AW3: 47362 | AX3: 47392 | AY3: 47423 | AZ3: 47453 | BA3: 47484 | BB3: 47515 | BC3: 47543 | BD3: 47574 | BE3: 47604 | BF3: 47635 | BG3: 47665 | BH3: 47696 | BI3: 47727 | BJ3: 47757 | BK3: 47788 | BL3: 47818 | BN3: 2026 | BO3: 2027 | BP3: 2028 | BQ3: 2029 | BR3: 2030 | BT3: what this row does
B5: VOLUME TIER
B6: Units sold this calendar year | C6: units | E6: =IFERROR(HLOOKUP(YEAR(E$3),'Revenue Forecast'!$BN$3:$BR$34,32,FALSE),0) | F6: =IFERROR(HLOOKUP(YEAR(F$3),'Revenue Forecast'!$BN$3:$BR$34,32,FALSE),0) | G6: =IFERROR(HLOOKUP(YEAR(G$3),'Revenue Forecast'!$BN$3:$BR$34,32,FALSE),0) | H6: =IFERROR(HLOOKUP(YEAR(H$3),'Revenue Forecast'!$BN$3:$BR$34,32,FALSE),0) | I6: =IFERROR(HLOOKUP(YEAR(I$3),'Revenue Forecast'!$BN$3:$BR$34,32,FALSE),0) | J6: =IFERROR(HLOOKUP(YEAR(J$3),'Revenue Forecast'!$BN$3:$BR$34,32,FALSE),0) | K6: =IFERROR(HLOOKUP(YEAR(K$3),'Revenue Forecast'!$BN$3:$BR$34,32,FALSE),0) | L6: =IFERROR(HLOOKUP(YEAR(L$3),'Revenue Forecast'!$BN$3:$BR$34,32,FALSE),0) | ... BL6: =IFERROR(HLOOKUP(YEAR(BL$3),'Revenue Forecast'!$BN$3:$BR$34,32,FALSE),0) | BN6: =P6 | BO6: =AB6 | BP6: =AN6 | BQ6: =AZ6 | BR6: =BL6
B7: Units sold next calendar year | C7: units | E7: =IFERROR(HLOOKUP(YEAR(E$3)+1,'Revenue Forecast'!$BN$3:$BR$34,32,FALSE),E6) | F7: =IFERROR(HLOOKUP(YEAR(F$3)+1,'Revenue Forecast'!$BN$3:$BR$34,32,FALSE),F6) | G7: =IFERROR(HLOOKUP(YEAR(G$3)+1,'Revenue Forecast'!$BN$3:$BR$34,32,FALSE),G6) | H7: =IFERROR(HLOOKUP(YEAR(H$3)+1,'Revenue Forecast'!$BN$3:$BR$34,32,FALSE),H6) | I7: =IFERROR(HLOOKUP(YEAR(I$3)+1,'Revenue Forecast'!$BN$3:$BR$34,32,FALSE),I6) | J7: =IFERROR(HLOOKUP(YEAR(J$3)+1,'Revenue Forecast'!$BN$3:$BR$34,32,FALSE),J6) | K7: =IFERROR(HLOOKUP(YEAR(K$3)+1,'Revenue Forecast'!$BN$3:$BR$34,32,FALSE),K6) | L7: =IFERROR(HLOOKUP(YEAR(L$3)+1,'Revenue Forecast'!$BN$3:$BR$34,32,FALSE),L6) | ... BL7: =IFERROR(HLOOKUP(YEAR(BL$3)+1,'Revenue Forecast'!$BN$3:$BR$34,32,FALSE),BL6) | BN7: =P7 | BO7: =AB7 | BP7: =AN7 | BQ7: =AZ7 | BR7: =BL7 | BT7: beyond the horizon, next year is taken as at least this year
B8: Two-year volume, sets the tier | C8: units | E8: =E6+E7 | F8: =F6+F7 | G8: =G6+G7 | H8: =H6+H7 | I8: =I6+I7 | J8: =J6+J7 | K8: =K6+K7 | L8: =L6+L7 | ... BL8: =BL6+BL7 | BN8: =P8 | BO8: =AB8 | BP8: =AN8 | BQ8: =AZ8 | BR8: =BL8 | BT8: the supplier prices on a two-year volume commitment: this year plus next
B9: Turbineketel cost per unit | C9: EUR/unit | E9: =VLOOKUP(E8,Assumptions!$D$71:$E$73,2,TRUE) | F9: =VLOOKUP(F8,Assumptions!$D$71:$E$73,2,TRUE) | G9: =VLOOKUP(G8,Assumptions!$D$71:$E$73,2,TRUE) | H9: =VLOOKUP(H8,Assumptions!$D$71:$E$73,2,TRUE) | I9: =VLOOKUP(I8,Assumptions!$D$71:$E$73,2,TRUE) | J9: =VLOOKUP(J8,Assumptions!$D$71:$E$73,2,TRUE) | K9: =VLOOKUP(K8,Assumptions!$D$71:$E$73,2,TRUE) | L9: =VLOOKUP(L8,Assumptions!$D$71:$E$73,2,TRUE) | ... BL9: =VLOOKUP(BL8,Assumptions!$D$71:$E$73,2,TRUE) | BN9: =IFERROR(AVERAGE(E9:P9),0) | BO9: =IFERROR(AVERAGE(Q9:AB9),0) | BP9: =IFERROR(AVERAGE(AC9:AN9),0) | BQ9: =IFERROR(AVERAGE(AO9:AZ9),0) | BR9: =IFERROR(AVERAGE(BA9:BL9),0) | BT9: EUR9,984 below 5,000 units, EUR7,069 from 5,000, EUR4,998 from 10,000
B10: Outdoor unit cost per unit | C10: EUR/unit | E10: =VLOOKUP(E8,Assumptions!$D$71:$F$73,3,TRUE) | F10: =VLOOKUP(F8,Assumptions!$D$71:$F$73,3,TRUE) | G10: =VLOOKUP(G8,Assumptions!$D$71:$F$73,3,TRUE) | H10: =VLOOKUP(H8,Assumptions!$D$71:$F$73,3,TRUE) | I10: =VLOOKUP(I8,Assumptions!$D$71:$F$73,3,TRUE) | J10: =VLOOKUP(J8,Assumptions!$D$71:$F$73,3,TRUE) | K10: =VLOOKUP(K8,Assumptions!$D$71:$F$73,3,TRUE) | L10: =VLOOKUP(L8,Assumptions!$D$71:$F$73,3,TRUE) | ... BL10: =VLOOKUP(BL8,Assumptions!$D$71:$F$73,3,TRUE) | BN10: =IFERROR(AVERAGE(E10:P10),0) | BO10: =IFERROR(AVERAGE(Q10:AB10),0) | BP10: =IFERROR(AVERAGE(AC10:AN10),0) | BQ10: =IFERROR(AVERAGE(AO10:AZ10),0) | BR10: =IFERROR(AVERAGE(BA10:BL10),0)
B12: COST OF GOODS SOLD
B13: Turbineketel | C13: EUR | E13: ='Revenue Forecast'!E39*E9 | F13: ='Revenue Forecast'!F39*F9 | G13: ='Revenue Forecast'!G39*G9 | H13: ='Revenue Forecast'!H39*H9 | I13: ='Revenue Forecast'!I39*I9 | J13: ='Revenue Forecast'!J39*J9 | K13: ='Revenue Forecast'!K39*K9 | L13: ='Revenue Forecast'!L39*L9 | ... BL13: ='Revenue Forecast'!BL39*BL9 | BN13: =SUM(E13:P13) | BO13: =SUM(Q13:AB13) | BP13: =SUM(AC13:AN13) | BQ13: =SUM(AO13:AZ13) | BR13: =SUM(BA13:BL13)
B14: Combi+ | C14: EUR | E14: ='Revenue Forecast'!E40*(E9+E10+Assumptions!$D$75) | F14: ='Revenue Forecast'!F40*(F9+F10+Assumptions!$D$75) | G14: ='Revenue Forecast'!G40*(G9+G10+Assumptions!$D$75) | H14: ='Revenue Forecast'!H40*(H9+H10+Assumptions!$D$75) | I14: ='Revenue Forecast'!I40*(I9+I10+Assumptions!$D$75) | J14: ='Revenue Forecast'!J40*(J9+J10+Assumptions!$D$75) | K14: ='Revenue Forecast'!K40*(K9+K10+Assumptions!$D$75) | L14: ='Revenue Forecast'!L40*(L9+L10+Assumptions!$D$75) | ... BL14: ='Revenue Forecast'!BL40*(BL9+BL10+Assumptions!$D$75) | BN14: =SUM(E14:P14) | BO14: =SUM(Q14:AB14) | BP14: =SUM(AC14:AN14) | BQ14: =SUM(AO14:AZ14) | BR14: =SUM(BA14:BL14) | BT14: ketel plus outdoor unit plus inbound shipping
B15: Upsell basket | C15: EUR | E15: ='Revenue Forecast'!E34*Assumptions!$D$33 | F15: ='Revenue Forecast'!F34*Assumptions!$D$33 | G15: ='Revenue Forecast'!G34*Assumptions!$D$33 | H15: ='Revenue Forecast'!H34*Assumptions!$D$33 | I15: ='Revenue Forecast'!I34*Assumptions!$D$33 | J15: ='Revenue Forecast'!J34*Assumptions!$D$33 | K15: ='Revenue Forecast'!K34*Assumptions!$D$33 | L15: ='Revenue Forecast'!L34*Assumptions!$D$33 | ... BL15: ='Revenue Forecast'!BL34*Assumptions!$D$33 | BN15: =SUM(E15:P15) | BO15: =SUM(Q15:AB15) | BP15: =SUM(AC15:AN15) | BQ15: =SUM(AO15:AZ15) | BR15: =SUM(BA15:BL15)
B16: Installation (pass-through) | C16: EUR | E16: ='Revenue Forecast'!E47 | F16: ='Revenue Forecast'!F47 | G16: ='Revenue Forecast'!G47 | H16: ='Revenue Forecast'!H47 | I16: ='Revenue Forecast'!I47 | J16: ='Revenue Forecast'!J47 | K16: ='Revenue Forecast'!K47 | L16: ='Revenue Forecast'!L47 | ... BL16: ='Revenue Forecast'!BL47 | BN16: =SUM(E16:P16) | BO16: =SUM(Q16:AB16) | BP16: =SUM(AC16:AN16) | BQ16: =SUM(AO16:AZ16) | BR16: =SUM(BA16:BL16) | BT16: identical to the installation revenue, so it nets to nil
B17: Service delivery | C17: EUR | E17: ='Revenue Forecast'!E7*Assumptions!$D$41/12 | F17: ='Revenue Forecast'!F7*Assumptions!$D$41/12 | G17: ='Revenue Forecast'!G7*Assumptions!$D$41/12 | H17: ='Revenue Forecast'!H7*Assumptions!$D$41/12 | I17: ='Revenue Forecast'!I7*Assumptions!$D$41/12 | J17: ='Revenue Forecast'!J7*Assumptions!$D$41/12 | K17: ='Revenue Forecast'!K7*Assumptions!$D$41/12 | L17: ='Revenue Forecast'!L7*Assumptions!$D$41/12 | ... BL17: ='Revenue Forecast'!BL7*Assumptions!$D$41/12 | BN17: =SUM(E17:P17) | BO17: =SUM(Q17:AB17) | BP17: =SUM(AC17:AN17) | BQ17: =SUM(AO17:AZ17) | BR17: =SUM(BA17:BL17) | BT17: parts, consumables and travel per contract, from the service table; the engineers are on Personnel
B18: Installer partner commission | C18: EUR | E18: =('Revenue Forecast'!E44+'Revenue Forecast'!E45)*(1-'Revenue Forecast'!E15)*Assumptions!$D$64 | F18: =('Revenue Forecast'!F44+'Revenue Forecast'!F45)*(1-'Revenue Forecast'!F15)*Assumptions!$D$64 | G18: =('Revenue Forecast'!G44+'Revenue Forecast'!G45)*(1-'Revenue Forecast'!G15)*Assumptions!$D$64 | H18: =('Revenue Forecast'!H44+'Revenue Forecast'!H45)*(1-'Revenue Forecast'!H15)*Assumptions!$D$64 | I18: =('Revenue Forecast'!I44+'Revenue Forecast'!I45)*(1-'Revenue Forecast'!I15)*Assumptions!$D$64 | J18: =('Revenue Forecast'!J44+'Revenue Forecast'!J45)*(1-'Revenue Forecast'!J15)*Assumptions!$D$64 | K18: =('Revenue Forecast'!K44+'Revenue Forecast'!K45)*(1-'Revenue Forecast'!K15)*Assumptions!$D$64 | L18: =('Revenue Forecast'!L44+'Revenue Forecast'!L45)*(1-'Revenue Forecast'!L15)*Assumptions!$D$64 | ... BL18: =('Revenue Forecast'!BL44+'Revenue Forecast'!BL45)*(1-'Revenue Forecast'!BL15)*Assumptions!$D$64 | BN18: =SUM(E18:P18) | BO18: =SUM(Q18:AB18) | BP18: =SUM(AC18:AN18) | BQ18: =SUM(AO18:AZ18) | BR18: =SUM(BA18:BL18) | BT18: turbineketel and Combi+ revenue on the channel share of units, times the commission rate
B19: Total cost of goods sold | C19: EUR | E19: =SUM(E13:E18) | F19: =SUM(F13:F18) | G19: =SUM(G13:G18) | H19: =SUM(H13:H18) | I19: =SUM(I13:I18) | J19: =SUM(J13:J18) | K19: =SUM(K13:K18) | L19: =SUM(L13:L18) | ... BL19: =SUM(BL13:BL18) | BN19: =SUM(E19:P19) | BO19: =SUM(Q19:AB19) | BP19: =SUM(AC19:AN19) | BQ19: =SUM(AO19:AZ19) | BR19: =SUM(BA19:BL19)
B21: Gross profit per unit | C21: EUR/unit | E21: =IFERROR(('Revenue Forecast'!E50-'Revenue Forecast'!E49-E19)/'Revenue Forecast'!E34,0) | F21: =IFERROR(('Revenue Forecast'!F50-'Revenue Forecast'!F49-F19)/'Revenue Forecast'!F34,0) | G21: =IFERROR(('Revenue Forecast'!G50-'Revenue Forecast'!G49-G19)/'Revenue Forecast'!G34,0) | H21: =IFERROR(('Revenue Forecast'!H50-'Revenue Forecast'!H49-H19)/'Revenue Forecast'!H34,0) | I21: =IFERROR(('Revenue Forecast'!I50-'Revenue Forecast'!I49-I19)/'Revenue Forecast'!I34,0) | J21: =IFERROR(('Revenue Forecast'!J50-'Revenue Forecast'!J49-J19)/'Revenue Forecast'!J34,0) | K21: =IFERROR(('Revenue Forecast'!K50-'Revenue Forecast'!K49-K19)/'Revenue Forecast'!K34,0) | L21: =IFERROR(('Revenue Forecast'!L50-'Revenue Forecast'!L49-L19)/'Revenue Forecast'!L34,0) | ... BL21: =IFERROR(('Revenue Forecast'!BL50-'Revenue Forecast'!BL49-BL19)/'Revenue Forecast'!BL34,0) | BN21: =IFERROR(('Revenue Forecast'!BN50-'Revenue Forecast'!BN49-BN19)/'Revenue Forecast'!BN34,0) | BO21: =IFERROR(('Revenue Forecast'!BO50-'Revenue Forecast'!BO49-BO19)/'Revenue Forecast'!BO34,0) | BP21: =IFERROR(('Revenue Forecast'!BP50-'Revenue Forecast'!BP49-BP19)/'Revenue Forecast'!BP34,0) | BQ21: =IFERROR(('Revenue Forecast'!BQ50-'Revenue Forecast'!BQ49-BQ19)/'Revenue Forecast'!BQ34,0) | BR21: =IFERROR(('Revenue Forecast'!BR50-'Revenue Forecast'!BR49-BR19)/'Revenue Forecast'!BR34,0) | BT21: trading revenue less cost of sales, per unit; the subsidy is left out

Sheet OPEX
B1: Tarnoc B.V. Operating Expenses
B2: People come from the Personnel tab. Everything else scales with headcount or partners signed.
E3: 46023 | F3: 46054 | G3: 46082 | H3: 46113 | I3: 46143 | J3: 46174 | K3: 46204 | L3: 46235 | M3: 46266 | N3: 46296 | O3: 46327 | P3: 46357 | Q3: 46388 | R3: 46419 | S3: 46447 | T3: 46478 | U3: 46508 | V3: 46539 | W3: 46569 | X3: 46600 | Y3: 46631 | Z3: 46661 | AA3: 46692 | AB3: 46722 | AC3: 46753 | AD3: 46784 | AE3: 46813 | AF3: 46844 | AG3: 46874 | AH3: 46905 | AI3: 46935 | AJ3: 46966 | AK3: 46997 | AL3: 47027 | AM3: 47058 | AN3: 47088 | AO3: 47119 | AP3: 47150 | AQ3: 47178 | AR3: 47209 | AS3: 47239 | AT3: 47270 | AU3: 47300 | AV3: 47331 | AW3: 47362 | AX3: 47392 | AY3: 47423 | AZ3: 47453 | BA3: 47484 | BB3: 47515 | BC3: 47543 | BD3: 47574 | BE3: 47604 | BF3: 47635 | BG3: 47665 | BH3: 47696 | BI3: 47727 | BJ3: 47757 | BK3: 47788 | BL3: 47818 | BN3: 2026 | BO3: 2027 | BP3: 2028 | BQ3: 2029 | BR3: 2030 | BT3: what this row does
B5: PEOPLE
B6: Research and development | C6: EUR | E6: =IF(E$3<=Assumptions!$D$12,E38,Personnel!E26) | F6: =IF(F$3<=Assumptions!$D$12,F38,Personnel!F26) | G6: =IF(G$3<=Assumptions!$D$12,G38,Personnel!G26) | H6: =IF(H$3<=Assumptions!$D$12,H38,Personnel!H26) | I6: =IF(I$3<=Assumptions!$D$12,I38,Personnel!I26) | J6: =IF(J$3<=Assumptions!$D$12,J38,Personnel!J26) | K6: =IF(K$3<=Assumptions!$D$12,K38,Personnel!K26) | L6: =IF(L$3<=Assumptions!$D$12,L38,Personnel!L26) | ... BL6: =IF(BL$3<=Assumptions!$D$12,BL38,Personnel!BL26) | BN6: =SUM(E6:P6) | BO6: =SUM(Q6:AB6) | BP6: =SUM(AC6:AN6) | BQ6: =SUM(AO6:AZ6) | BR6: =SUM(BA6:BL6)
B7: Sales and marketing | C7: EUR | E7: =IF(E$3<=Assumptions!$D$12,E39,Personnel!E27) | F7: =IF(F$3<=Assumptions!$D$12,F39,Personnel!F27) | G7: =IF(G$3<=Assumptions!$D$12,G39,Personnel!G27) | H7: =IF(H$3<=Assumptions!$D$12,H39,Personnel!H27) | I7: =IF(I$3<=Assumptions!$D$12,I39,Personnel!I27) | J7: =IF(J$3<=Assumptions!$D$12,J39,Personnel!J27) | K7: =IF(K$3<=Assumptions!$D$12,K39,Personnel!K27) | L7: =IF(L$3<=Assumptions!$D$12,L39,Personnel!L27) | ... BL7: =IF(BL$3<=Assumptions!$D$12,BL39,Personnel!BL27) | BN7: =SUM(E7:P7) | BO7: =SUM(Q7:AB7) | BP7: =SUM(AC7:AN7) | BQ7: =SUM(AO7:AZ7) | BR7: =SUM(BA7:BL7)
B8: General and administrative | C8: EUR | E8: =IF(E$3<=Assumptions!$D$12,E40,Personnel!E28) | F8: =IF(F$3<=Assumptions!$D$12,F40,Personnel!F28) | G8: =IF(G$3<=Assumptions!$D$12,G40,Personnel!G28) | H8: =IF(H$3<=Assumptions!$D$12,H40,Personnel!H28) | I8: =IF(I$3<=Assumptions!$D$12,I40,Personnel!I28) | J8: =IF(J$3<=Assumptions!$D$12,J40,Personnel!J28) | K8: =IF(K$3<=Assumptions!$D$12,K40,Personnel!K28) | L8: =IF(L$3<=Assumptions!$D$12,L40,Personnel!L28) | ... BL8: =IF(BL$3<=Assumptions!$D$12,BL40,Personnel!BL28) | BN8: =SUM(E8:P8) | BO8: =SUM(Q8:AB8) | BP8: =SUM(AC8:AN8) | BQ8: =SUM(AO8:AZ8) | BR8: =SUM(BA8:BL8)
B9: Total people cost | C9: EUR | E9: =SUM(E6:E8) | F9: =SUM(F6:F8) | G9: =SUM(G6:G8) | H9: =SUM(H6:H8) | I9: =SUM(I6:I8) | J9: =SUM(J6:J8) | K9: =SUM(K6:K8) | L9: =SUM(L6:L8) | ... BL9: =SUM(BL6:BL8) | BN9: =SUM(E9:P9) | BO9: =SUM(Q9:AB9) | BP9: =SUM(AC9:AN9) | BQ9: =SUM(AO9:AZ9) | BR9: =SUM(BA9:BL9)
B11: SALES AND MARKETING, EVERYTHING ELSE
B12: Performance marketing | C12: EUR | E12: ='Revenue Forecast'!E6 | F12: ='Revenue Forecast'!F6 | G12: ='Revenue Forecast'!G6 | H12: ='Revenue Forecast'!H6 | I12: ='Revenue Forecast'!I6 | J12: ='Revenue Forecast'!J6 | K12: ='Revenue Forecast'!K6 | L12: ='Revenue Forecast'!L6 | ... BL12: ='Revenue Forecast'!BL6 | BN12: =SUM(E12:P12) | BO12: =SUM(Q12:AB12) | BP12: =SUM(AC12:AN12) | BQ12: =SUM(AO12:AZ12) | BR12: =SUM(BA12:BL12) | BT12: the same spend that drives the funnel, so it can never be double counted
B13: Installer training and demo units | C13: EUR | E13: ='Revenue Forecast'!E19*Assumptions!$D$106*(1+Assumptions!$D$111)^(YEAR(E$3)-Assumptions!$D$7) | F13: ='Revenue Forecast'!F19*Assumptions!$D$106*(1+Assumptions!$D$111)^(YEAR(F$3)-Assumptions!$D$7) | G13: ='Revenue Forecast'!G19*Assumptions!$D$106*(1+Assumptions!$D$111)^(YEAR(G$3)-Assumptions!$D$7) | H13: ='Revenue Forecast'!H19*Assumptions!$D$106*(1+Assumptions!$D$111)^(YEAR(H$3)-Assumptions!$D$7) | I13: ='Revenue Forecast'!I19*Assumptions!$D$106*(1+Assumptions!$D$111)^(YEAR(I$3)-Assumptions!$D$7) | J13: ='Revenue Forecast'!J19*Assumptions!$D$106*(1+Assumptions!$D$111)^(YEAR(J$3)-Assumptions!$D$7) | K13: ='Revenue Forecast'!K19*Assumptions!$D$106*(1+Assumptions!$D$111)^(YEAR(K$3)-Assumptions!$D$7) | L13: ='Revenue Forecast'!L19*Assumptions!$D$106*(1+Assumptions!$D$111)^(YEAR(L$3)-Assumptions!$D$7) | ... BL13: ='Revenue Forecast'!BL19*Assumptions!$D$106*(1+Assumptions!$D$111)^(YEAR(BL$3)-Assumptions!$D$7) | BN13: =SUM(E13:P13) | BO13: =SUM(Q13:AB13) | BP13: =SUM(AC13:AN13) | BQ13: =SUM(AO13:AZ13) | BR13: =SUM(BA13:BL13)
B14: Total | C14: EUR | E14: =IF(E$3<=Assumptions!$D$12,E42,SUM(E12:E13)) | F14: =IF(F$3<=Assumptions!$D$12,F42,SUM(F12:F13)) | G14: =IF(G$3<=Assumptions!$D$12,G42,SUM(G12:G13)) | H14: =IF(H$3<=Assumptions!$D$12,H42,SUM(H12:H13)) | I14: =IF(I$3<=Assumptions!$D$12,I42,SUM(I12:I13)) | J14: =IF(J$3<=Assumptions!$D$12,J42,SUM(J12:J13)) | K14: =IF(K$3<=Assumptions!$D$12,K42,SUM(K12:K13)) | L14: =IF(L$3<=Assumptions!$D$12,L42,SUM(L12:L13)) | ... BL14: =IF(BL$3<=Assumptions!$D$12,BL42,SUM(BL12:BL13)) | BN14: =SUM(E14:P14) | BO14: =SUM(Q14:AB14) | BP14: =SUM(AC14:AN14) | BQ14: =SUM(AO14:AZ14) | BR14: =SUM(BA14:BL14)
B16: RESEARCH AND DEVELOPMENT, EVERYTHING ELSE
B17: Ongoing development | C17: EUR | E17: =Assumptions!$D$109*(1+Assumptions!$D$111)^(YEAR(E$3)-Assumptions!$D$7) | F17: =Assumptions!$D$109*(1+Assumptions!$D$111)^(YEAR(F$3)-Assumptions!$D$7) | G17: =Assumptions!$D$109*(1+Assumptions!$D$111)^(YEAR(G$3)-Assumptions!$D$7) | H17: =Assumptions!$D$109*(1+Assumptions!$D$111)^(YEAR(H$3)-Assumptions!$D$7) | I17: =Assumptions!$D$109*(1+Assumptions!$D$111)^(YEAR(I$3)-Assumptions!$D$7) | J17: =Assumptions!$D$109*(1+Assumptions!$D$111)^(YEAR(J$3)-Assumptions!$D$7) | K17: =Assumptions!$D$109*(1+Assumptions!$D$111)^(YEAR(K$3)-Assumptions!$D$7) | L17: =Assumptions!$D$109*(1+Assumptions!$D$111)^(YEAR(L$3)-Assumptions!$D$7) | ... BL17: =Assumptions!$D$109*(1+Assumptions!$D$111)^(YEAR(BL$3)-Assumptions!$D$7) | BN17: =SUM(E17:P17) | BO17: =SUM(Q17:AB17) | BP17: =SUM(AC17:AN17) | BQ17: =SUM(AO17:AZ17) | BR17: =SUM(BA17:BL17)
B18: Third party product development | C18: EUR | E18: =Assumptions!$D$110*(1+Assumptions!$D$111)^(YEAR(E$3)-Assumptions!$D$7) | F18: =Assumptions!$D$110*(1+Assumptions!$D$111)^(YEAR(F$3)-Assumptions!$D$7) | G18: =Assumptions!$D$110*(1+Assumptions!$D$111)^(YEAR(G$3)-Assumptions!$D$7) | H18: =Assumptions!$D$110*(1+Assumptions!$D$111)^(YEAR(H$3)-Assumptions!$D$7) | I18: =Assumptions!$D$110*(1+Assumptions!$D$111)^(YEAR(I$3)-Assumptions!$D$7) | J18: =Assumptions!$D$110*(1+Assumptions!$D$111)^(YEAR(J$3)-Assumptions!$D$7) | K18: =Assumptions!$D$110*(1+Assumptions!$D$111)^(YEAR(K$3)-Assumptions!$D$7) | L18: =Assumptions!$D$110*(1+Assumptions!$D$111)^(YEAR(L$3)-Assumptions!$D$7) | ... BL18: =Assumptions!$D$110*(1+Assumptions!$D$111)^(YEAR(BL$3)-Assumptions!$D$7) | BN18: =SUM(E18:P18) | BO18: =SUM(Q18:AB18) | BP18: =SUM(AC18:AN18) | BQ18: =SUM(AO18:AZ18) | BR18: =SUM(BA18:BL18)
B19: Total | C19: EUR | E19: =IF(E$3<=Assumptions!$D$12,E41,SUM(E17:E18)) | F19: =IF(F$3<=Assumptions!$D$12,F41,SUM(F17:F18)) | G19: =IF(G$3<=Assumptions!$D$12,G41,SUM(G17:G18)) | H19: =IF(H$3<=Assumptions!$D$12,H41,SUM(H17:H18)) | I19: =IF(I$3<=Assumptions!$D$12,I41,SUM(I17:I18)) | J19: =IF(J$3<=Assumptions!$D$12,J41,SUM(J17:J18)) | K19: =IF(K$3<=Assumptions!$D$12,K41,SUM(K17:K18)) | L19: =IF(L$3<=Assumptions!$D$12,L41,SUM(L17:L18)) | ... BL19: =IF(BL$3<=Assumptions!$D$12,BL41,SUM(BL17:BL18)) | BN19: =SUM(E19:P19) | BO19: =SUM(Q19:AB19) | BP19: =SUM(AC19:AN19) | BQ19: =SUM(AO19:AZ19) | BR19: =SUM(BA19:BL19)
B21: GENERAL AND ADMINISTRATIVE, EVERYTHING ELSE
B22: Offices, IT and travel | C22: EUR | E22: =Personnel!E20*(Assumptions!$D$102+Assumptions!$D$103+Assumptions!$D$104)*(1+Assumptions!$D$111)^(YEAR(E$3)-Assumptions!$D$7) | F22: =Personnel!F20*(Assumptions!$D$102+Assumptions!$D$103+Assumptions!$D$104)*(1+Assumptions!$D$111)^(YEAR(F$3)-Assumptions!$D$7) | G22: =Personnel!G20*(Assumptions!$D$102+Assumptions!$D$103+Assumptions!$D$104)*(1+Assumptions!$D$111)^(YEAR(G$3)-Assumptions!$D$7) | H22: =Personnel!H20*(Assumptions!$D$102+Assumptions!$D$103+Assumptions!$D$104)*(1+Assumptions!$D$111)^(YEAR(H$3)-Assumptions!$D$7) | I22: =Personnel!I20*(Assumptions!$D$102+Assumptions!$D$103+Assumptions!$D$104)*(1+Assumptions!$D$111)^(YEAR(I$3)-Assumptions!$D$7) | J22: =Personnel!J20*(Assumptions!$D$102+Assumptions!$D$103+Assumptions!$D$104)*(1+Assumptions!$D$111)^(YEAR(J$3)-Assumptions!$D$7) | K22: =Personnel!K20*(Assumptions!$D$102+Assumptions!$D$103+Assumptions!$D$104)*(1+Assumptions!$D$111)^(YEAR(K$3)-Assumptions!$D$7) | L22: =Personnel!L20*(Assumptions!$D$102+Assumptions!$D$103+Assumptions!$D$104)*(1+Assumptions!$D$111)^(YEAR(L$3)-Assumptions!$D$7) | ... BL22: =Personnel!BL20*(Assumptions!$D$102+Assumptions!$D$103+Assumptions!$D$104)*(1+Assumptions!$D$111)^(YEAR(BL$3)-Assumptions!$D$7) | BN22: =SUM(E22:P22) | BO22: =SUM(Q22:AB22) | BP22: =SUM(AC22:AN22) | BQ22: =SUM(AO22:AZ22) | BR22: =SUM(BA22:BL22) | BT22: scales with the number of people on the payroll, inflated like every other cost
B23: Recruitment | C23: EUR | E23: =0 | F23: =MAX(0,Personnel!F20-Personnel!E20)*Assumptions!$D$105*(1+Assumptions!$D$111)^(YEAR(F$3)-Assumptions!$D$7) | G23: =MAX(0,Personnel!G20-Personnel!F20)*Assumptions!$D$105*(1+Assumptions!$D$111)^(YEAR(G$3)-Assumptions!$D$7) | H23: =MAX(0,Personnel!H20-Personnel!G20)*Assumptions!$D$105*(1+Assumptions!$D$111)^(YEAR(H$3)-Assumptions!$D$7) | I23: =MAX(0,Personnel!I20-Personnel!H20)*Assumptions!$D$105*(1+Assumptions!$D$111)^(YEAR(I$3)-Assumptions!$D$7) | J23: =MAX(0,Personnel!J20-Personnel!I20)*Assumptions!$D$105*(1+Assumptions!$D$111)^(YEAR(J$3)-Assumptions!$D$7) | K23: =MAX(0,Personnel!K20-Personnel!J20)*Assumptions!$D$105*(1+Assumptions!$D$111)^(YEAR(K$3)-Assumptions!$D$7) | L23: =MAX(0,Personnel!L20-Personnel!K20)*Assumptions!$D$105*(1+Assumptions!$D$111)^(YEAR(L$3)-Assumptions!$D$7) | M23: =MAX(0,Personnel!M20-Personnel!L20)*Assumptions!$D$105*(1+Assumptions!$D$111)^(YEAR(M$3)-Assumptions!$D$7) | ... BL23: =MAX(0,Personnel!BL20-Personnel!BK20)*Assumptions!$D$105*(1+Assumptions!$D$111)^(YEAR(BL$3)-Assumptions!$D$7) | BN23: =SUM(E23:P23) | BO23: =SUM(Q23:AB23) | BP23: =SUM(AC23:AN23) | BQ23: =SUM(AO23:AZ23) | BR23: =SUM(BA23:BL23)
B25: Finance and legal | C25: EUR | E25: =Assumptions!$D$107*(1+Assumptions!$D$111)^(YEAR(E$3)-Assumptions!$D$7) | F25: =Assumptions!$D$107*(1+Assumptions!$D$111)^(YEAR(F$3)-Assumptions!$D$7) | G25: =Assumptions!$D$107*(1+Assumptions!$D$111)^(YEAR(G$3)-Assumptions!$D$7) | H25: =Assumptions!$D$107*(1+Assumptions!$D$111)^(YEAR(H$3)-Assumptions!$D$7) | I25: =Assumptions!$D$107*(1+Assumptions!$D$111)^(YEAR(I$3)-Assumptions!$D$7) | J25: =Assumptions!$D$107*(1+Assumptions!$D$111)^(YEAR(J$3)-Assumptions!$D$7) | K25: =Assumptions!$D$107*(1+Assumptions!$D$111)^(YEAR(K$3)-Assumptions!$D$7) | L25: =Assumptions!$D$107*(1+Assumptions!$D$111)^(YEAR(L$3)-Assumptions!$D$7) | ... BL25: =Assumptions!$D$107*(1+Assumptions!$D$111)^(YEAR(BL$3)-Assumptions!$D$7) | BN25: =SUM(E25:P25) | BO25: =SUM(Q25:AB25) | BP25: =SUM(AC25:AN25) | BQ25: =SUM(AO25:AZ25) | BR25: =SUM(BA25:BL25)
B26: Other general | C26: EUR | E26: =Assumptions!$D$108*(1+Assumptions!$D$111)^(YEAR(E$3)-Assumptions!$D$7) | F26: =Assumptions!$D$108*(1+Assumptions!$D$111)^(YEAR(F$3)-Assumptions!$D$7) | G26: =Assumptions!$D$108*(1+Assumptions!$D$111)^(YEAR(G$3)-Assumptions!$D$7) | H26: =Assumptions!$D$108*(1+Assumptions!$D$111)^(YEAR(H$3)-Assumptions!$D$7) | I26: =Assumptions!$D$108*(1+Assumptions!$D$111)^(YEAR(I$3)-Assumptions!$D$7) | J26: =Assumptions!$D$108*(1+Assumptions!$D$111)^(YEAR(J$3)-Assumptions!$D$7) | K26: =Assumptions!$D$108*(1+Assumptions!$D$111)^(YEAR(K$3)-Assumptions!$D$7) | L26: =Assumptions!$D$108*(1+Assumptions!$D$111)^(YEAR(L$3)-Assumptions!$D$7) | ... BL26: =Assumptions!$D$108*(1+Assumptions!$D$111)^(YEAR(BL$3)-Assumptions!$D$7) | BN26: =SUM(E26:P26) | BO26: =SUM(Q26:AB26) | BP26: =SUM(AC26:AN26) | BQ26: =SUM(AO26:AZ26) | BR26: =SUM(BA26:BL26)
B27: Total | C27: EUR | E27: =IF(E$3<=Assumptions!$D$12,E43,SUM(E22:E26)) | F27: =IF(F$3<=Assumptions!$D$12,F43,SUM(F22:F26)) | G27: =IF(G$3<=Assumptions!$D$12,G43,SUM(G22:G26)) | H27: =IF(H$3<=Assumptions!$D$12,H43,SUM(H22:H26)) | I27: =IF(I$3<=Assumptions!$D$12,I43,SUM(I22:I26)) | J27: =IF(J$3<=Assumptions!$D$12,J43,SUM(J22:J26)) | K27: =IF(K$3<=Assumptions!$D$12,K43,SUM(K22:K26)) | L27: =IF(L$3<=Assumptions!$D$12,L43,SUM(L22:L26)) | ... BL27: =IF(BL$3<=Assumptions!$D$12,BL43,SUM(BL22:BL26)) | BN27: =SUM(E27:P27) | BO27: =SUM(Q27:AB27) | BP27: =SUM(AC27:AN27) | BQ27: =SUM(AO27:AZ27) | BR27: =SUM(BA27:BL27)
B29: TOTAL OPERATING EXPENSES
B30: Research and development | C30: EUR | E30: =E6+E19 | F30: =F6+F19 | G30: =G6+G19 | H30: =H6+H19 | I30: =I6+I19 | J30: =J6+J19 | K30: =K6+K19 | L30: =L6+L19 | ... BL30: =BL6+BL19 | BN30: =SUM(E30:P30) | BO30: =SUM(Q30:AB30) | BP30: =SUM(AC30:AN30) | BQ30: =SUM(AO30:AZ30) | BR30: =SUM(BA30:BL30)
B31: Sales and marketing | C31: EUR | E31: =E7+E14 | F31: =F7+F14 | G31: =G7+G14 | H31: =H7+H14 | I31: =I7+I14 | J31: =J7+J14 | K31: =K7+K14 | L31: =L7+L14 | ... BL31: =BL7+BL14 | BN31: =SUM(E31:P31) | BO31: =SUM(Q31:AB31) | BP31: =SUM(AC31:AN31) | BQ31: =SUM(AO31:AZ31) | BR31: =SUM(BA31:BL31)
B32: General and administrative | C32: EUR | E32: =E8+E27 | F32: =F8+F27 | G32: =G8+G27 | H32: =H8+H27 | I32: =I8+I27 | J32: =J8+J27 | K32: =K8+K27 | L32: =L8+L27 | ... BL32: =BL8+BL27 | BN32: =SUM(E32:P32) | BO32: =SUM(Q32:AB32) | BP32: =SUM(AC32:AN32) | BQ32: =SUM(AO32:AZ32) | BR32: =SUM(BA32:BL32)
B33: Total operating expenses | C33: EUR | E33: =SUM(E30:E32) | F33: =SUM(F30:F32) | G33: =SUM(G30:G32) | H33: =SUM(H30:H32) | I33: =SUM(I30:I32) | J33: =SUM(J30:J32) | K33: =SUM(K30:K32) | L33: =SUM(L30:L32) | ... BL33: =SUM(BL30:BL32) | BN33: =SUM(E33:P33) | BO33: =SUM(Q33:AB33) | BP33: =SUM(AC33:AN33) | BQ33: =SUM(AO33:AZ33) | BR33: =SUM(BA33:BL33)
B35: Operating expenses as a share of revenue | C35: % | E35: =IFERROR(E33/'Revenue Forecast'!E50,0) | F35: =IFERROR(F33/'Revenue Forecast'!F50,0) | G35: =IFERROR(G33/'Revenue Forecast'!G50,0) | H35: =IFERROR(H33/'Revenue Forecast'!H50,0) | I35: =IFERROR(I33/'Revenue Forecast'!I50,0) | J35: =IFERROR(J33/'Revenue Forecast'!J50,0) | K35: =IFERROR(K33/'Revenue Forecast'!K50,0) | L35: =IFERROR(L33/'Revenue Forecast'!L50,0) | ... BL35: =IFERROR(BL33/'Revenue Forecast'!BL50,0) | BN35: =IFERROR(BN33/'Revenue Forecast'!BN50,0) | BO35: =IFERROR(BO33/'Revenue Forecast'!BO50,0) | BP35: =IFERROR(BP33/'Revenue Forecast'!BP50,0) | BQ35: =IFERROR(BQ33/'Revenue Forecast'!BQ50,0) | BR35: =IFERROR(BR33/'Revenue Forecast'!BR50,0)
B37: COMMITTED 2026 PLAN, HELD FIXED (January to October, from the existing model)
B38: People, research and development | C38: EUR | E38: 50700 | F38: 50700 | G38: 50700 | H38: 50700 | I38: 50700 | J38: 50700 | K38: 50700 | L38: 50700 | M38: 54700 | N38: 61620 | BN38: =SUM(E38:P38) | BO38: =SUM(Q38:AB38) | BP38: =SUM(AC38:AN38) | BQ38: =SUM(AO38:AZ38) | BR38: =SUM(BA38:BL38) | BT38: taken from the existing model and not recalculated
B39: People, sales and marketing | C39: EUR | E39: 0 | F39: 10800 | G39: 10800 | H39: 10800 | I39: 10800 | J39: 10800 | K39: 10800 | L39: 10800 | M39: 10800 | N39: 19800 | BN39: =SUM(E39:P39) | BO39: =SUM(Q39:AB39) | BP39: =SUM(AC39:AN39) | BQ39: =SUM(AO39:AZ39) | BR39: =SUM(BA39:BL39)
B40: People, general and administrative | C40: EUR | E40: 11820 | F40: 11820 | G40: 11820 | H40: 11820 | I40: 11820 | J40: 11820 | K40: 11820 | L40: 11820 | M40: 25740 | N40: 21420 | BN40: =SUM(E40:P40) | BO40: =SUM(Q40:AB40) | BP40: =SUM(AC40:AN40) | BQ40: =SUM(AO40:AZ40) | BR40: =SUM(BA40:BL40)
B41: Everything else, research and development | C41: EUR | E41: 25000 | F41: 25000 | G41: 25000 | H41: 25000 | I41: 25000 | J41: 25000 | K41: 25000 | L41: 25000 | M41: 25000 | N41: 125000 | BN41: =SUM(E41:P41) | BO41: =SUM(Q41:AB41) | BP41: =SUM(AC41:AN41) | BQ41: =SUM(AO41:AZ41) | BR41: =SUM(BA41:BL41)
B42: Everything else, sales and marketing | C42: EUR | E42: 21000 | F42: 21000 | G42: 21000 | H42: 21000 | I42: 31000 | J42: 31000 | K42: 21000 | L42: 21000 | M42: 21000 | N42: 24000 | BN42: =SUM(E42:P42) | BO42: =SUM(Q42:AB42) | BP42: =SUM(AC42:AN42) | BQ42: =SUM(AO42:AZ42) | BR42: =SUM(BA42:BL42)
B43: Everything else, general and administrative | C43: EUR | E43: 20000 | F43: 20000 | G43: 20000 | H43: 20000 | I43: 20000 | J43: 20000 | K43: 20000 | L43: 20000 | M43: 20000 | N43: 20000 | BN43: =SUM(E43:P43) | BO43: =SUM(Q43:AB43) | BP43: =SUM(AC43:AN43) | BQ43: =SUM(AO43:AZ43) | BR43: =SUM(BA43:BL43)
BT44: these ten months are committed. The drivers take over from November, the month after the raise lands.

Sheet Personnel
B1: Tarnoc B.V. Personnel
B2: Headcount by team. Every number is driven by whatever creates the work: units, installed base, partners signed or marketing spend. The back office is typed in directly.
E3: 46023 | F3: 46054 | G3: 46082 | H3: 46113 | I3: 46143 | J3: 46174 | K3: 46204 | L3: 46235 | M3: 46266 | N3: 46296 | O3: 46327 | P3: 46357 | Q3: 46388 | R3: 46419 | S3: 46447 | T3: 46478 | U3: 46508 | V3: 46539 | W3: 46569 | X3: 46600 | Y3: 46631 | Z3: 46661 | AA3: 46692 | AB3: 46722 | AC3: 46753 | AD3: 46784 | AE3: 46813 | AF3: 46844 | AG3: 46874 | AH3: 46905 | AI3: 46935 | AJ3: 46966 | AK3: 46997 | AL3: 47027 | AM3: 47058 | AN3: 47088 | AO3: 47119 | AP3: 47150 | AQ3: 47178 | AR3: 47209 | AS3: 47239 | AT3: 47270 | AU3: 47300 | AV3: 47331 | AW3: 47362 | AX3: 47392 | AY3: 47423 | AZ3: 47453 | BA3: 47484 | BB3: 47515 | BC3: 47543 | BD3: 47574 | BE3: 47604 | BF3: 47635 | BG3: 47665 | BH3: 47696 | BI3: 47727 | BJ3: 47757 | BK3: 47788 | BL3: 47818 | BN3: 2026 | BO3: 2027 | BP3: 2028 | BQ3: 2029 | BR3: 2030 | BT3: what this row does
B5: HEADCOUNT
B6: Sales reps | C6: FTE | E6: ='Revenue Forecast'!E17 | F6: ='Revenue Forecast'!F17 | G6: ='Revenue Forecast'!G17 | H6: ='Revenue Forecast'!H17 | I6: ='Revenue Forecast'!I17 | J6: ='Revenue Forecast'!J17 | K6: ='Revenue Forecast'!K17 | L6: ='Revenue Forecast'!L17 | ... BL6: ='Revenue Forecast'!BL17 | BN6: =P6 | BO6: =AB6 | BP6: =AN6 | BQ6: =AZ6 | BR6: =BL6
B7: Partner managers | C7: FTE | E7: ='Revenue Forecast'!E23 | F7: ='Revenue Forecast'!F23 | G7: ='Revenue Forecast'!G23 | H7: ='Revenue Forecast'!H23 | I7: ='Revenue Forecast'!I23 | J7: ='Revenue Forecast'!J23 | K7: ='Revenue Forecast'!K23 | L7: ='Revenue Forecast'!L23 | ... BL7: ='Revenue Forecast'!BL23 | BN7: =P7 | BO7: =AB7 | BP7: =AN7 | BQ7: =AZ7 | BR7: =BL7
B8: Installer trainers | C8: FTE | E8: =ROUND('Revenue Forecast'!E19*12/Assumptions!$D$85,0) | F8: =ROUND('Revenue Forecast'!F19*12/Assumptions!$D$85,0) | G8: =ROUND('Revenue Forecast'!G19*12/Assumptions!$D$85,0) | H8: =ROUND('Revenue Forecast'!H19*12/Assumptions!$D$85,0) | I8: =ROUND('Revenue Forecast'!I19*12/Assumptions!$D$85,0) | J8: =ROUND('Revenue Forecast'!J19*12/Assumptions!$D$85,0) | K8: =ROUND('Revenue Forecast'!K19*12/Assumptions!$D$85,0) | L8: =ROUND('Revenue Forecast'!L19*12/Assumptions!$D$85,0) | ... BL8: =ROUND('Revenue Forecast'!BL19*12/Assumptions!$D$85,0) | BN8: =P8 | BO8: =AB8 | BP8: =AN8 | BQ8: =AZ8 | BR8: =BL8 | BT8: every partner has to be trained and certified before selling anything
B9: Order desk | C9: FTE | E9: =ROUND('Revenue Forecast'!E34*12/Assumptions!$D$86,0) | F9: =ROUND('Revenue Forecast'!F34*12/Assumptions!$D$86,0) | G9: =ROUND('Revenue Forecast'!G34*12/Assumptions!$D$86,0) | H9: =ROUND('Revenue Forecast'!H34*12/Assumptions!$D$86,0) | I9: =ROUND('Revenue Forecast'!I34*12/Assumptions!$D$86,0) | J9: =ROUND('Revenue Forecast'!J34*12/Assumptions!$D$86,0) | K9: =ROUND('Revenue Forecast'!K34*12/Assumptions!$D$86,0) | L9: =ROUND('Revenue Forecast'!L34*12/Assumptions!$D$86,0) | ... BL9: =ROUND('Revenue Forecast'!BL34*12/Assumptions!$D$86,0) | BN9: =P9 | BO9: =AB9 | BP9: =AN9 | BQ9: =AZ9 | BR9: =BL9
B10: Marketing | C10: FTE | E10: =Assumptions!$D$81+ROUND('Revenue Forecast'!E6*12/Assumptions!$D$87,0) | F10: =Assumptions!$D$81+ROUND('Revenue Forecast'!F6*12/Assumptions!$D$87,0) | G10: =Assumptions!$D$81+ROUND('Revenue Forecast'!G6*12/Assumptions!$D$87,0) | H10: =Assumptions!$D$81+ROUND('Revenue Forecast'!H6*12/Assumptions!$D$87,0) | I10: =Assumptions!$D$81+ROUND('Revenue Forecast'!I6*12/Assumptions!$D$87,0) | J10: =Assumptions!$D$81+ROUND('Revenue Forecast'!J6*12/Assumptions!$D$87,0) | K10: =Assumptions!$D$81+ROUND('Revenue Forecast'!K6*12/Assumptions!$D$87,0) | L10: =Assumptions!$D$81+ROUND('Revenue Forecast'!L6*12/Assumptions!$D$87,0) | ... BL10: =Assumptions!$D$81+ROUND('Revenue Forecast'!BL6*12/Assumptions!$D$87,0) | BN10: =P10 | BO10: =AB10 | BP10: =AN10 | BQ10: =AZ10 | BR10: =BL10
B11: Sales and marketing | C11: FTE | E11: =SUM(E6:E10) | F11: =SUM(F6:F10) | G11: =SUM(G6:G10) | H11: =SUM(H6:H10) | I11: =SUM(I6:I10) | J11: =SUM(J6:J10) | K11: =SUM(K6:K10) | L11: =SUM(L6:L10) | ... BL11: =SUM(BL6:BL10) | BN11: =P11 | BO11: =AB11 | BP11: =AN11 | BQ11: =AZ11 | BR11: =BL11
B12: Supply chain and logistics | C12: FTE | E12: =ROUND('Revenue Forecast'!E34*12/Assumptions!$D$82,0) | F12: =ROUND('Revenue Forecast'!F34*12/Assumptions!$D$82,0) | G12: =ROUND('Revenue Forecast'!G34*12/Assumptions!$D$82,0) | H12: =ROUND('Revenue Forecast'!H34*12/Assumptions!$D$82,0) | I12: =ROUND('Revenue Forecast'!I34*12/Assumptions!$D$82,0) | J12: =ROUND('Revenue Forecast'!J34*12/Assumptions!$D$82,0) | K12: =ROUND('Revenue Forecast'!K34*12/Assumptions!$D$82,0) | L12: =ROUND('Revenue Forecast'!L34*12/Assumptions!$D$82,0) | ... BL12: =ROUND('Revenue Forecast'!BL34*12/Assumptions!$D$82,0) | BN12: =P12 | BO12: =AB12 | BP12: =AN12 | BQ12: =AZ12 | BR12: =BL12 | BT12: buying, planning, inbound quality and warehousing
B14: Customer support | C14: FTE | E14: =ROUND('Revenue Forecast'!E41/Assumptions!$D$83,0) | F14: =ROUND('Revenue Forecast'!F41/Assumptions!$D$83,0) | G14: =ROUND('Revenue Forecast'!G41/Assumptions!$D$83,0) | H14: =ROUND('Revenue Forecast'!H41/Assumptions!$D$83,0) | I14: =ROUND('Revenue Forecast'!I41/Assumptions!$D$83,0) | J14: =ROUND('Revenue Forecast'!J41/Assumptions!$D$83,0) | K14: =ROUND('Revenue Forecast'!K41/Assumptions!$D$83,0) | L14: =ROUND('Revenue Forecast'!L41/Assumptions!$D$83,0) | ... BL14: =ROUND('Revenue Forecast'!BL41/Assumptions!$D$83,0) | BN14: =P14 | BO14: =AB14 | BP14: =AN14 | BQ14: =AZ14 | BR14: =BL14 | BT14: inbound calls follow the installed base, not sales
B15: Technical escalation | C15: FTE | E15: =ROUND('Revenue Forecast'!E41/Assumptions!$D$84,0) | F15: =ROUND('Revenue Forecast'!F41/Assumptions!$D$84,0) | G15: =ROUND('Revenue Forecast'!G41/Assumptions!$D$84,0) | H15: =ROUND('Revenue Forecast'!H41/Assumptions!$D$84,0) | I15: =ROUND('Revenue Forecast'!I41/Assumptions!$D$84,0) | J15: =ROUND('Revenue Forecast'!J41/Assumptions!$D$84,0) | K15: =ROUND('Revenue Forecast'!K41/Assumptions!$D$84,0) | L15: =ROUND('Revenue Forecast'!L41/Assumptions!$D$84,0) | ... BL15: =ROUND('Revenue Forecast'!BL41/Assumptions!$D$84,0) | BN15: =P15 | BO15: =AB15 | BP15: =AN15 | BQ15: =AZ15 | BR15: =BL15
B16: R&D engineers | C16: FTE | E16: =Assumptions!$D$80+SUMIF(Assumptions!$D$77:$H$77,"<="&YEAR(E$3),Assumptions!$D$78:$H$78) | F16: =Assumptions!$D$80+SUMIF(Assumptions!$D$77:$H$77,"<="&YEAR(F$3),Assumptions!$D$78:$H$78) | G16: =Assumptions!$D$80+SUMIF(Assumptions!$D$77:$H$77,"<="&YEAR(G$3),Assumptions!$D$78:$H$78) | H16: =Assumptions!$D$80+SUMIF(Assumptions!$D$77:$H$77,"<="&YEAR(H$3),Assumptions!$D$78:$H$78) | I16: =Assumptions!$D$80+SUMIF(Assumptions!$D$77:$H$77,"<="&YEAR(I$3),Assumptions!$D$78:$H$78) | J16: =Assumptions!$D$80+SUMIF(Assumptions!$D$77:$H$77,"<="&YEAR(J$3),Assumptions!$D$78:$H$78) | K16: =Assumptions!$D$80+SUMIF(Assumptions!$D$77:$H$77,"<="&YEAR(K$3),Assumptions!$D$78:$H$78) | L16: =Assumptions!$D$80+SUMIF(Assumptions!$D$77:$H$77,"<="&YEAR(L$3),Assumptions!$D$78:$H$78) | ... BL16: =Assumptions!$D$80+SUMIF(Assumptions!$D$77:$H$77,"<="&YEAR(BL$3),Assumptions!$D$78:$H$78) | BN16: =P16 | BO16: =AB16 | BP16: =AN16 | BQ16: =AZ16 | BR16: =BL16 | BT16: the founding engineers plus everyone hired up to and including this year
B17: Leadership, finance, HR, IT and legal | C17: FTE | E17: 3 | F17: 3 | G17: 3 | H17: 3 | I17: 3 | J17: 3 | K17: 3 | L17: 3 | M17: 3 | N17: 3 | O17: 3 | P17: 3 | Q17: 4 | R17: 4 | S17: 4 | T17: 4 | U17: 4 | V17: 4 | W17: 4 | X17: 4 | Y17: 4 | Z17: 4 | AA17: 4 | AB17: 4 | AC17: 5 | AD17: 5 | AE17: 5 | AF17: 5 | AG17: 5 | AH17: 5 | AI17: 5 | AJ17: 5 | AK17: 5 | AL17: 5 | AM17: 5 | AN17: 5 | AO17: 6 | AP17: 6 | AQ17: 6 | AR17: 6 | AS17: 6 | AT17: 6 | AU17: 6 | AV17: 6 | AW17: 6 | AX17: 6 | AY17: 6 | AZ17: 6 | BA17: 8 | BB17: 8 | BC17: 8 | BD17: 8 | BE17: 8 | BF17: 8 | BG17: 8 | BH17: 8 | BI17: 8 | BJ17: 8 | BK17: 8 | BL17: 8 | BN17: =P17 | BO17: =AB17 | BP17: =AN17 | BQ17: =AZ17 | BR17: =BL17 | BT17: typed here, not driven: the leadership team, then finance, HR, IT and legal as the company grows. Same in both cases
B18: Field service engineers | C18: FTE | E18: =ROUND('Revenue Forecast'!E41*Assumptions!$D$42/Assumptions!$D$89,0) | F18: =ROUND('Revenue Forecast'!F41*Assumptions!$D$42/Assumptions!$D$89,0) | G18: =ROUND('Revenue Forecast'!G41*Assumptions!$D$42/Assumptions!$D$89,0) | H18: =ROUND('Revenue Forecast'!H41*Assumptions!$D$42/Assumptions!$D$89,0) | I18: =ROUND('Revenue Forecast'!I41*Assumptions!$D$42/Assumptions!$D$89,0) | J18: =ROUND('Revenue Forecast'!J41*Assumptions!$D$42/Assumptions!$D$89,0) | K18: =ROUND('Revenue Forecast'!K41*Assumptions!$D$42/Assumptions!$D$89,0) | L18: =ROUND('Revenue Forecast'!L41*Assumptions!$D$42/Assumptions!$D$89,0) | ... BL18: =ROUND('Revenue Forecast'!BL41*Assumptions!$D$42/Assumptions!$D$89,0) | BN18: =P18 | BO18: =AB18 | BP18: =AN18 | BQ18: =AZ18 | BR18: =BL18 | BT18: salaried staff: installed units on a service contract divided by the units one engineer can look after
B19: Operations, support and administration | C19: FTE | E19: =SUM(E12:E18) | F19: =SUM(F12:F18) | G19: =SUM(G12:G18) | H19: =SUM(H12:H18) | I19: =SUM(I12:I18) | J19: =SUM(J12:J18) | K19: =SUM(K12:K18) | L19: =SUM(L12:L18) | ... BL19: =SUM(BL12:BL18) | BN19: =P19 | BO19: =AB19 | BP19: =AN19 | BQ19: =AZ19 | BR19: =BL19
B20: Total headcount | C20: FTE | E20: =E11+E19 | F20: =F11+F19 | G20: =G11+G19 | H20: =H11+H19 | I20: =I11+I19 | J20: =J11+J19 | K20: =K11+K19 | L20: =L11+L19 | ... BL20: =BL11+BL19 | BN20: =P20 | BO20: =AB20 | BP20: =AN20 | BQ20: =AZ20 | BR20: =BL20
B25: COST BY DEPARTMENT
B26: Research and development | C26: EUR/mo | E26: =E16*Assumptions!$D$98*(1+Assumptions!$D$8)^(YEAR(E$3)-Assumptions!$D$7) | F26: =F16*Assumptions!$D$98*(1+Assumptions!$D$8)^(YEAR(F$3)-Assumptions!$D$7) | G26: =G16*Assumptions!$D$98*(1+Assumptions!$D$8)^(YEAR(G$3)-Assumptions!$D$7) | H26: =H16*Assumptions!$D$98*(1+Assumptions!$D$8)^(YEAR(H$3)-Assumptions!$D$7) | I26: =I16*Assumptions!$D$98*(1+Assumptions!$D$8)^(YEAR(I$3)-Assumptions!$D$7) | J26: =J16*Assumptions!$D$98*(1+Assumptions!$D$8)^(YEAR(J$3)-Assumptions!$D$7) | K26: =K16*Assumptions!$D$98*(1+Assumptions!$D$8)^(YEAR(K$3)-Assumptions!$D$7) | L26: =L16*Assumptions!$D$98*(1+Assumptions!$D$8)^(YEAR(L$3)-Assumptions!$D$7) | ... BL26: =BL16*Assumptions!$D$98*(1+Assumptions!$D$8)^(YEAR(BL$3)-Assumptions!$D$7) | BN26: =SUM(E26:P26) | BO26: =SUM(Q26:AB26) | BP26: =SUM(AC26:AN26) | BQ26: =SUM(AO26:AZ26) | BR26: =SUM(BA26:BL26)
B27: Sales and marketing | C27: EUR/mo | E27: =(E6*Assumptions!$D$92+E7*Assumptions!$D$93+(E8+E9+E10)*Assumptions!$D$94)*(1+Assumptions!$D$8)^(YEAR(E$3)-Assumptions!$D$7) | F27: =(F6*Assumptions!$D$92+F7*Assumptions!$D$93+(F8+F9+F10)*Assumptions!$D$94)*(1+Assumptions!$D$8)^(YEAR(F$3)-Assumptions!$D$7) | G27: =(G6*Assumptions!$D$92+G7*Assumptions!$D$93+(G8+G9+G10)*Assumptions!$D$94)*(1+Assumptions!$D$8)^(YEAR(G$3)-Assumptions!$D$7) | H27: =(H6*Assumptions!$D$92+H7*Assumptions!$D$93+(H8+H9+H10)*Assumptions!$D$94)*(1+Assumptions!$D$8)^(YEAR(H$3)-Assumptions!$D$7) | I27: =(I6*Assumptions!$D$92+I7*Assumptions!$D$93+(I8+I9+I10)*Assumptions!$D$94)*(1+Assumptions!$D$8)^(YEAR(I$3)-Assumptions!$D$7) | J27: =(J6*Assumptions!$D$92+J7*Assumptions!$D$93+(J8+J9+J10)*Assumptions!$D$94)*(1+Assumptions!$D$8)^(YEAR(J$3)-Assumptions!$D$7) | K27: =(K6*Assumptions!$D$92+K7*Assumptions!$D$93+(K8+K9+K10)*Assumptions!$D$94)*(1+Assumptions!$D$8)^(YEAR(K$3)-Assumptions!$D$7) | L27: =(L6*Assumptions!$D$92+L7*Assumptions!$D$93+(L8+L9+L10)*Assumptions!$D$94)*(1+Assumptions!$D$8)^(YEAR(L$3)-Assumptions!$D$7) | ... BL27: =(BL6*Assumptions!$D$92+BL7*Assumptions!$D$93+(BL8+BL9+BL10)*Assumptions!$D$94)*(1+Assumptions!$D$8)^(YEAR(BL$3)-Assumptions!$D$7) | BN27: =SUM(E27:P27) | BO27: =SUM(Q27:AB27) | BP27: =SUM(AC27:AN27) | BQ27: =SUM(AO27:AZ27) | BR27: =SUM(BA27:BL27)
B28: General and administrative | C28: EUR/mo | E28: =((E12+E13)*Assumptions!$D$95+(E14+E15)*Assumptions!$D$96+E17*Assumptions!$D$97+E18*Assumptions!$D$99)*(1+Assumptions!$D$8)^(YEAR(E$3)-Assumptions!$D$7) | F28: =((F12+F13)*Assumptions!$D$95+(F14+F15)*Assumptions!$D$96+F17*Assumptions!$D$97+F18*Assumptions!$D$99)*(1+Assumptions!$D$8)^(YEAR(F$3)-Assumptions!$D$7) | G28: =((G12+G13)*Assumptions!$D$95+(G14+G15)*Assumptions!$D$96+G17*Assumptions!$D$97+G18*Assumptions!$D$99)*(1+Assumptions!$D$8)^(YEAR(G$3)-Assumptions!$D$7) | H28: =((H12+H13)*Assumptions!$D$95+(H14+H15)*Assumptions!$D$96+H17*Assumptions!$D$97+H18*Assumptions!$D$99)*(1+Assumptions!$D$8)^(YEAR(H$3)-Assumptions!$D$7) | I28: =((I12+I13)*Assumptions!$D$95+(I14+I15)*Assumptions!$D$96+I17*Assumptions!$D$97+I18*Assumptions!$D$99)*(1+Assumptions!$D$8)^(YEAR(I$3)-Assumptions!$D$7) | J28: =((J12+J13)*Assumptions!$D$95+(J14+J15)*Assumptions!$D$96+J17*Assumptions!$D$97+J18*Assumptions!$D$99)*(1+Assumptions!$D$8)^(YEAR(J$3)-Assumptions!$D$7) | K28: =((K12+K13)*Assumptions!$D$95+(K14+K15)*Assumptions!$D$96+K17*Assumptions!$D$97+K18*Assumptions!$D$99)*(1+Assumptions!$D$8)^(YEAR(K$3)-Assumptions!$D$7) | L28: =((L12+L13)*Assumptions!$D$95+(L14+L15)*Assumptions!$D$96+L17*Assumptions!$D$97+L18*Assumptions!$D$99)*(1+Assumptions!$D$8)^(YEAR(L$3)-Assumptions!$D$7) | ... BL28: =((BL12+BL13)*Assumptions!$D$95+(BL14+BL15)*Assumptions!$D$96+BL17*Assumptions!$D$97+BL18*Assumptions!$D$99)*(1+Assumptions!$D$8)^(YEAR(BL$3)-Assumptions!$D$7) | BN28: =SUM(E28:P28) | BO28: =SUM(Q28:AB28) | BP28: =SUM(AC28:AN28) | BQ28: =SUM(AO28:AZ28) | BR28: =SUM(BA28:BL28)
B29: Total people cost | C29: EUR/mo | E29: =SUM(E26:E28) | F29: =SUM(F26:F28) | G29: =SUM(G26:G28) | H29: =SUM(H26:H28) | I29: =SUM(I26:I28) | J29: =SUM(J26:J28) | K29: =SUM(K26:K28) | L29: =SUM(L26:L28) | ... BL29: =SUM(BL26:BL28) | BN29: =SUM(E29:P29) | BO29: =SUM(Q29:AB29) | BP29: =SUM(AC29:AN29) | BQ29: =SUM(AO29:AZ29) | BR29: =SUM(BA29:BL29)
B31: Average cost per person | C31: EUR/mo | E31: =IFERROR(E29/E20,0) | F31: =IFERROR(F29/F20,0) | G31: =IFERROR(G29/G20,0) | H31: =IFERROR(H29/H20,0) | I31: =IFERROR(I29/I20,0) | J31: =IFERROR(J29/J20,0) | K31: =IFERROR(K29/K20,0) | L31: =IFERROR(L29/L20,0) | ... BL31: =IFERROR(BL29/BL20,0) | BN31: =IFERROR(SUM(E29:P29)/SUM(E20:P20),0) | BO31: =IFERROR(SUM(Q29:AB29)/SUM(Q20:AB20),0) | BP31: =IFERROR(SUM(AC29:AN29)/SUM(AC20:AN20),0) | BQ31: =IFERROR(SUM(AO29:AZ29)/SUM(AO20:AZ20),0) | BR31: =IFERROR(SUM(BA29:BL29)/SUM(BA20:BL20),0) | BT31: annual column: the year's people cost over the year's person-months

Sheet Dashboard
B1: Tarnoc B.V. Dashboard
B2: Every figure is a formula off the other tabs. Change a driver on Assumptions and this moves.
D3: 2026 | E3: 2027 | F3: 2028 | G3: 2029 | H3: 2030
B5: VOLUME AND CUSTOMERS
B6: Units sold | D6: ='Revenue Forecast'!BN34 | E6: ='Revenue Forecast'!BO34 | F6: ='Revenue Forecast'!BP34 | G6: ='Revenue Forecast'!BQ34 | H6: ='Revenue Forecast'!BR34
B7: Installed base at year end | D7: ='Revenue Forecast'!BN41 | E7: ='Revenue Forecast'!BO41 | F7: ='Revenue Forecast'!BP41 | G7: ='Revenue Forecast'!BQ41 | H7: ='Revenue Forecast'!BR41
B8: Build capacity used | D8: ='Revenue Forecast'!BN35 | E8: ='Revenue Forecast'!BO35 | F8: ='Revenue Forecast'!BP35 | G8: ='Revenue Forecast'!BQ35 | H8: ='Revenue Forecast'!BR35
B9: Installer partners at year end | D9: ='Revenue Forecast'!BN20 | E9: ='Revenue Forecast'!BO20 | F9: ='Revenue Forecast'!BP20 | G9: ='Revenue Forecast'!BQ20 | H9: ='Revenue Forecast'!BR20
B10: Marketing cost per unit sold | D10: =IFERROR('Revenue Forecast'!BN6/'Revenue Forecast'!BN34,0) | E10: =IFERROR('Revenue Forecast'!BO6/'Revenue Forecast'!BO34,0) | F10: =IFERROR('Revenue Forecast'!BP6/'Revenue Forecast'!BP34,0) | G10: =IFERROR('Revenue Forecast'!BQ6/'Revenue Forecast'!BQ34,0) | H10: =IFERROR('Revenue Forecast'!BR6/'Revenue Forecast'!BR34,0)
B13: PROFIT AND LOSS
B14: Revenue | D14: ='Financial Statements'!BN6 | E14: ='Financial Statements'!BO6 | F14: ='Financial Statements'!BP6 | G14: ='Financial Statements'!BQ6 | H14: ='Financial Statements'!BR6
B15: Gross profit | D15: ='Financial Statements'!BN8 | E15: ='Financial Statements'!BO8 | F15: ='Financial Statements'!BP8 | G15: ='Financial Statements'!BQ8 | H15: ='Financial Statements'!BR8
B16: Gross margin | D16: =IF('Revenue Forecast'!BN34=0,"n/a",'Financial Statements'!BN9) | E16: =IF('Revenue Forecast'!BO34=0,"n/a",'Financial Statements'!BO9) | F16: =IF('Revenue Forecast'!BP34=0,"n/a",'Financial Statements'!BP9) | G16: =IF('Revenue Forecast'!BQ34=0,"n/a",'Financial Statements'!BQ9) | H16: =IF('Revenue Forecast'!BR34=0,"n/a",'Financial Statements'!BR9) | J16: n/a in a year with no units sold
B17: Operating expenses | D17: ='Financial Statements'!BN14 | E17: ='Financial Statements'!BO14 | F17: ='Financial Statements'!BP14 | G17: ='Financial Statements'!BQ14 | H17: ='Financial Statements'!BR14
B18: EBITDA | D18: ='Financial Statements'!BN16 | E18: ='Financial Statements'!BO16 | F18: ='Financial Statements'!BP16 | G18: ='Financial Statements'!BQ16 | H18: ='Financial Statements'!BR16
B19: EBITDA margin | D19: =IF('Revenue Forecast'!BN34=0,"n/a",'Financial Statements'!BN17) | E19: =IF('Revenue Forecast'!BO34=0,"n/a",'Financial Statements'!BO17) | F19: =IF('Revenue Forecast'!BP34=0,"n/a",'Financial Statements'!BP17) | G19: =IF('Revenue Forecast'!BQ34=0,"n/a",'Financial Statements'!BQ17) | H19: =IF('Revenue Forecast'!BR34=0,"n/a",'Financial Statements'!BR17)
B20: Net income | D20: ='Financial Statements'!BN23 | E20: ='Financial Statements'!BO23 | F20: ='Financial Statements'!BP23 | G20: ='Financial Statements'!BQ23 | H20: ='Financial Statements'!BR23
B22: PEOPLE
B23: Field service engineers | D23: =Personnel!BN18 | E23: =Personnel!BO18 | F23: =Personnel!BP18 | G23: =Personnel!BQ18 | H23: =Personnel!BR18
B24: Total headcount | D24: =Personnel!BN20 | E24: =Personnel!BO20 | F24: =Personnel!BP20 | G24: =Personnel!BQ20 | H24: =Personnel!BR20
B26: Revenue per person | D26: =IFERROR(D14/D24,0) | E26: =IFERROR(E14/E24,0) | F26: =IFERROR(F14/F24,0) | G26: =IFERROR(G14/G24,0) | H26: =IFERROR(H14/H24,0) | J26: Viessmann runs at about EUR276k and Vaillant about EUR200k
B28: CASH AND FUNDING
B29: Equity raised in the year | D29: ='Financial Statements'!BN35 | E29: ='Financial Statements'!BO35 | F29: ='Financial Statements'!BP35 | G29: ='Financial Statements'!BQ35 | H29: ='Financial Statements'!BR35
B31: Cash at year end | D31: ='Financial Statements'!BN40 | E31: ='Financial Statements'!BO40 | F31: ='Financial Statements'!BP40 | G31: ='Financial Statements'!BQ40 | H31: ='Financial Statements'!BR40
B32: Lowest cash during the year | D32: =MIN('Financial Statements'!E40:'Financial Statements'!P40) | E32: =MIN('Financial Statements'!Q40:'Financial Statements'!AB40) | F32: =MIN('Financial Statements'!AC40:'Financial Statements'!AN40) | G32: =MIN('Financial Statements'!AO40:'Financial Statements'!AZ40) | H32: =MIN('Financial Statements'!BA40:'Financial Statements'!BL40) | J32: the number that decides whether the raise is big enough
B34: Balance sheet check, worst month across the whole model | D34: =MAX(ABS(MIN('Financial Statements'!$E$58:$BL$58)),ABS(MAX('Financial Statements'!$E$58:$BL$58))) | J34: must read nil
B36: WHERE THE MONEY GOES
B37: Lowest the cash balance ever gets, after the raise | D37: =MIN(INDEX('Financial Statements'!$E$40:$BL$40,MATCH(Assumptions!$D$116,'Financial Statements'!$E$3:$BL$3,0)):INDEX('Financial Statements'!$E$40:$BL$40,60)) | J37: the moment the plan is closest to running out
B38: The month it happens | D38: =INDEX('Financial Statements'!$E$3:$BL$3,MATCH(D37,INDEX('Financial Statements'!$E$40:$BL$40,MATCH(Assumptions!$D$116,'Financial Statements'!$E$3:$BL$3,0)):INDEX('Financial Statements'!$E$40:$BL$40,60),0)+MATCH(Assumptions!$D$116,'Financial Statements'!$E$3:$BL$3,0)-1)
B39: Lowest the cash balance gets before the raise | D39: =MIN(INDEX('Financial Statements'!$E$40:$BL$40,1):INDEX('Financial Statements'!$E$40:$BL$40,MATCH(Assumptions!$D$116,'Financial Statements'!$E$3:$BL$3,0)-1)) | J39: the committed 2026 plan has to survive to the raise on its own; negative here means it does not
B40: Cash at the start of January 2026 | D40: =Assumptions!$D$6
B41: Equity raised up to that month | D41: =SUMIF('Financial Statements'!$E$3:$BL$3,"<="&D38,'Financial Statements'!$E$35:$BL$35)
B42: Convertible loan drawn | D42: =SUMIF('Financial Statements'!$E$3:$BL$3,"<="&D38,'Financial Statements'!$E$36:$BL$36)
B43: Total money available | D43: =SUM(D40:D42)
B45: Absorbed by operations and working capital | D45: =-SUMIF('Financial Statements'!$E$3:$BL$3,"<="&D38,'Financial Statements'!$E$32:$BL$32) | J45: trading losses plus the receivables the ramp ties up, less the payables it creates
B46: Cash still in the bank at the low point | D46: =D37 | J46: negative means the plan has spent more than the money available
B47: Total | D47: =SUM(D44:D46) | J47: ties to total money available
B48: Check sources less uses, must be nil | D48: =D43-D47
B49: IS THE RAISE THE RIGHT SIZE
B50: Cash the moment the raise lands | D50: =INDEX('Financial Statements'!$E$40:$BL$40,MATCH(Assumptions!$D$116,'Financial Statements'!$E$3:$BL$3,0))
B51: Most of the raise ever drawn down | D51: =D50-D37
B52: Share of the raise the plan actually uses | D52: =IFERROR(D51/SUM(INDEX('Financial Statements'!$E$35:$BL$35,MATCH(Assumptions!$D$116,'Financial Statements'!$E$3:$BL$3,0)):INDEX('Financial Statements'!$E$35:$BL$35,60)),0) | J52: well under 100% means the raise is bigger than this plan needs; over 100% means the plan needs more than the raise
B53: Months of operating cost left at the low point | D53: =IFERROR(D37/(-HLOOKUP(YEAR(D38),'Financial Statements'!$BN$3:$BR$14,12,FALSE)/12),0) | J53: cash at the low point over that year's average monthly operating cost. Three or more is comfortable; negative means the cash has run out
