Workbook

Sheet Cover
B15: Financial Model
B19: Currency: EUR (€)
B21: STRICTLY CONFIDENTIAL

Sheet How to read me
B1: Tarnoc — How to Read This Model
B3: COLOR CODING
B4: Sample | C4: Assumptions are hardcoded inputs (sourced from documents)
B5: Sample | C5: Hardcoded historicalsis actual data from source documents
B6: Sample | C6: Formula cells are calculated, not hardcoded
B7: Sample | C7: Subtotal / total rows
B8: Sample | C8: Section headers / grand totals
B9: Sample | C9: Subsection headers
B10: Sample | C10: Margin / ratio rows (grey)
B11: Sample | C11: Balance sheet check rows (must = 0)
B14: FORMULA ARCHITECTURE
B15: Assumptions → Revenue Forecast, COGS, OPEX, CAPEX, Personnel (all drivers sourced here)
B16: Revenue Forecast → Financial Statements (revenue lines via cross-sheet links)
B17: COGS → Financial Statements (cost lines via cross-sheet links)
B18: OPEX → Financial Statements (opex lines via cross-sheet links)
B20: To change a number: ONLY edit cells in the Assumptions tab (yellow/orange).
B21: All other tabs will recalculate automatically.
B24: FURTHER EXPLANATIONS
B25: Subsidies: Tarnoc is and has been eligible for a number of subsidies. We will consider application for large projects, however this model excludes the forecast of any subsidy financing foing forward.
B26: Installation revenues: This is modelled fully as pass through revenue for now, as we plan to charge a customer exactly what we pay the installation partner for these services. This is subject to change in the future.
B27: Tarnoc's main products are the TTK (turbineketel) and the Combi+ (turbineketel + outdoor unit), plus the Twincycle (in development for 2027). Every unit contains a turbineketel; the Combi+ adds an outdoor unit and a heavier installation. We also plan to sell various add-ons such as boilers for hybrid setups and sound reduction units.
B28: Service Revenues: Service revenues are calculated relative to installed base. We assume a certain percentage (see assumptions) of customers will purchase our Service package, and are charged annually.
... B46: Market share is on the face of the model. The turbineketel replaces a gas boiler one-for-one, so the market is the ~400,000 gas boilers replaced in the Netherlands each year - not the ~125,000 heat pumps sold in 2024. Share is measured against that, plus Belgium and Germany once the expansion market opens.

Sheet Assumptions
B2: Drivers & Assumptions
B3: ASSUMPTIONS | L3: what this row does
B5: General Assumptions
B6: Opening Cash Balance (Jan 2024) | C6: 29538.9
B7: Annual salary increase (%) | C7: 0.08 | L7: salary raise applied every year on the Personnel tab
B8: Employer cost basis | C8: Werkgeverlasten (incl. taxes)
B9: Holiday pay (%) | C9: 0.08
B10: Income tax rate | C10: 0.258
B11: Interst on WC loan | C11: 0.05 | L11: interest rate charged on the CLA / working-capital loan
B13: Working Capital | H13: 20
B15: Days Sales Outstanding (DSO) | C15: days | D15: 20 | L15: days customers take to pay — sets receivables on the balance sheet
B16: Days Payable Outstanding (DPO) | C16: days | D16: 45 | L16: days we take to pay suppliers — sets payables
B17: Days Inventory Outstanding (DIO) | C17: days | D17: =IF($D$82=2,30,0) | L17: days of stock held. 0 in Base (as before); 30 in the Aggressive case
B18: Pre-payment | C18: % | L18: share paid up front. left blank, so no customer deposits assumed
B20: Revenue Build
B21: ~Units sold | D21: ='Growth Engine'!BC43 | E21: ='Growth Engine'!BD43 | F21: ='Growth Engine'!BE43 | G21: ='Growth Engine'!BF43 | L21: OUTPUT, not an input — units come from the Growth Engine tab (demand vs sales capacity vs build capacity)
C22: 2026 | D22: 2027 | E22: 2028 | F22: 2029 | G22: 2030
B23: TTK | C23: 0 | D23: =D$21*$H23 | E23: =E$21*$H23 | F23: =F$21*$H23 | G23: =G$21*$H23 | H23: 0.2 | L23: TTK units = total units x the mix % in column H
B24: Combi+ | C24: 0 | D24: =D$21*$H24 | E24: =E$21*$H24 | F24: =F$21*$H24 | G24: =G$21*$H24 | H24: =1-H23 | L24: Combi+ units = total units x the mix % in column H
B27: Pricing
B28: PRICING — build-up (turbineketel + outdoor unit) | D28: (inc VAT)
B29: Turbineketel base price (all products) | C29: 8525.62 | D29: =C29*1.21 | L29: column D is just the same price with VAT added, for reference
B30: Outdoor unit — Combi+ | C30: 5309.92 | D30: =C30*1.21 | L30: column D is the incl-VAT version, for reference
B31: Combi+ price (ketel + ODU) | C31: =C29+C30 | D31: =C31*1.21 | L31: Combi+ price = ketel + outdoor unit
B32: INSTALLATION (PASS-THROUGH; REV=COST)
B33: Installation — TTK | C33: 2800 | L33: charged at cost, no margin (pass-through)
B34: Installation — Combi+ | C34: 3800 | L34: charged at cost, no margin (pass-through)
B35: COGS
B36: TTK
B37: Bill of Materials TTK supplier 1
B38: # | C38: Category | D38: Component | E38: 1,000 units | F38: 5,000 units | G38: 10,000 units | H38: Unit | I38: Source
B39: B1 | C39: Supplier 1 | D39: Compressor + VFD | E39: 6314 | F39: 4500 | G39: 2692.44 | H39: €/unit | I39: Source: BOM data provided | L39: compressor prices typed in per tier, not a % step-down
B40: B2 | C40: Supplier 1 | D40: Heat exchangers (set) | E40: 805.5 | F40: =E40*0.7 | G40: =0.6*F40 | H40: €/unit | I40: Source: BOM data provided | L40: volume discount: 5k column = 70% of 1k, 10k = 60% of 5k
B41: B3 | C41: Supplier 1 | D41: Electronics & Power Electronics | E41: 632.92 | F41: =E41*0.7 | G41: =0.6*F41 | H41: €/unit | I41: Source: BOM data provided | L41: volume discount: 5k column = 70% of 1k, 10k = 60% of 5k
B42: B4 | C42: Supplier 1 | D42: Hydraulic Components (Pumps, Valves, etc.) | E42: 283.76 | F42: =E42*0.7 | G42: =0.6*F42 | H42: €/unit | I42: Source: BOM data provided | L42: volume discount: 5k column = 70% of 1k, 10k = 60% of 5k
B43: B5 | C43: Supplier 1 | D43: Silencer & Insulation | E43: 118.48 | F43: =E43*0.7 | G43: =0.6*F43 | H43: €/unit | I43: Source: BOM data provided | L43: volume discount: 5k column = 70% of 1k, 10k = 60% of 5k
B44: B6 | C44: Supplier 1 | D44: Enclosure (Sheet Metal & Coating) | E44: 653.03 | F44: =E44*0.7 | G44: =0.6*F44 | H44: €/unit | I44: Source: BOM data provided | L44: volume discount: 5k column = 70% of 1k, 10k = 60% of 5k
B45: B7 | C45: Supplier 1 | D45: Other Components | E45: 290 | F45: =E45*0.7 | G45: 126 | H45: €/unit | I45: Source: BOM data provided | L45: 5k = 70% of 1k; the 10k number is typed in by hand
B46: B8 | C46: Supplier 1 | D46: Assembly & Final Testing | E46: 200 | F46: =E46*0.7 | G46: =0.6*F46 | H46: €/unit | I46: Source: BOM data provided | L46: volume discount: 5k column = 70% of 1k, 10k = 60% of 5k
B47: B9 | C47: Supplier 1 | D47: Packaging & Inbound Logistics | E47: 395 | F47: =E47*0.7 | G47: =0.6*F47 | H47: €/unit | I47: Source: BOM data provided | L47: volume discount: 5k column = 70% of 1k, 10k = 60% of 5k
B48: B10 | C48: Supplier 1 | D48: Yield Loss & Warranty Provision (~3%) | E48: 291.23 | F48: =E48*0.7 | G48: =0.6*F48 | H48: €/unit | I48: Source: BOM data provided | L48: volume discount: 5k column = 70% of 1k, 10k = 60% of 5k
B49: B11 | C49: Contingency/risk | D49: Contingency & Risk Reserve | E49: 0 | F49: 0 | G49: 760 | H49: €/unit | I49: Source: No source, added for risk purposes | L49: risk buffer, added by hand at the 10k tier only
B50: B-T | C50: Supplier 1 total | D50: Total COGS / unit (BOM) | E50: =SUM(E39:E49) | F50: =SUM(F39:F49) | G50: =round(SUM(G39:G49),0) | H50: €/unit | L50: adds the BOM lines up: cost per ketel at each volume tier
B52: Bill of Materials TTK supplier 2
B53: D1 | C53: Supplier 2 | D53: Compressor + VFD | E53: 2568 | F53: 2311.2 | G53: 2080.08 | H53: €/unit | I53: Source: BOM data provided
B54: D2 | C54: Supplier 2 | D54: Heat exchangers (set) | E54: 805.5 | F54: =E54*0.7 | G54: =F54*0.6 | H54: €/unit | I54: Source: BOM data provided | L54: volume discount: 5k column = 70% of 1k, 10k = 60% of 5k
B55: D3 | C55: Supplier 2 | D55: Elektronica & vermogenselektronica | E55: 257.92 | F55: =E55*0.7 | G55: =F55*0.6 | H55: €/unit | I55: Source: BOM data provided | L55: volume discount: 5k column = 70% of 1k, 10k = 60% of 5k
B56: D4 | C56: Supplier 2 | D56: Hydraulisch (pompen/kleppen/etc.) | E56: 283.76 | F56: =E56*0.7 | G56: =F56*0.6 | H56: €/unit | I56: Source: BOM data provided | L56: volume discount: 5k column = 70% of 1k, 10k = 60% of 5k
B57: D5 | C57: Supplier 2 | D57: Silencer + isolatie | E57: 118.48 | F57: =E57*0.7 | G57: =F57*0.6 | H57: €/unit | I57: Source: BOM data provided | L57: volume discount: 5k column = 70% of 1k, 10k = 60% of 5k
B58: D6 | C58: Supplier 2 | D58: Enclosure (plaatwerk, coating) | E58: 653.03 | F58: =E58*0.7 | G58: =F58*0.6 | H58: €/unit | I58: Source: BOM data provided | L58: volume discount: 5k column = 70% of 1k, 10k = 60% of 5k
B59: D7 | C59: Supplier 2 | D59: Everything Else | E59: 300 | F59: =E59*0.7 | G59: =F59*0.6 | H59: €/unit | I59: Source: BOM data provided | L59: volume discount: 5k column = 70% of 1k, 10k = 60% of 5k
B60: D8 | C60: Supplier 2 | D60: Assemblage & eindtest | E60: 200 | F60: =E60*0.7 | G60: =F60*0.6 | H60: €/unit | I60: Source: BOM data provided | L60: volume discount: 5k column = 70% of 1k, 10k = 60% of 5k
B61: D9 | C61: Supplier 2 | D61: Verpakking & logistiek inkomend | E61: 400 | F61: =E61*0.7 | G61: =F61*0.6 | H61: €/unit | I61: Source: BOM data provided | L61: volume discount: 5k column = 70% of 1k, 10k = 60% of 5k
B62: D10 | C62: Supplier 2 | D62: Yield / garantie-reserve (~3%) | E62: 236.81 | F62: =E62*0.7 | G62: =F62*0.6 | H62: €/unit | I62: Source: BOM data provided | L62: volume discount: 5k column = 70% of 1k, 10k = 60% of 5k
C63: Supplier 2 total | D63: Total COGS / unit (BOM) | E63: =SUM(E53:E62) | F63: =SUM(F53:F62) | G63: =SUM(G53:G62) | L63: supplier 2's total cost per ketel at each tier, for comparison
B65: TTK Volume tier breakpoints
B66: Min Units (≥) | C66: Cost / unit | D66: Unit | E66: Note
B67: 0 | C67: =E50 | D67: €/unit | E67: Linked from BOM Total row above | L67: the sub-5,000 tier. cost pulled from the BOM total above
B68: 5000 | C68: =F50 | D68: €/unit | E68: Linked from BOM Total row above | L68: the 5,000+ tier. COGS looks up this little table
B69: 10000 | C69: =G50 | D69: €/unit | E69: Linked from BOM Total row above | L69: the 10,000+ tier. the tier key is two years of volume, not one
B71: OUTDOOR UNIT COGS (Combi+) — volume tiers
B72: Component | E72: 1,000 units | F72: 5,000 units | G72: 10,000 units | H72: Unit | I72: Unit | J72: Source
B73: Outdoor unit — Combi+ | E73: 1402.6 | F73: 1262.34 | G73: 1136.1 | H73: €/unit | I73: €/unit | J73: Source: BOM data
B74: Shipping (Combi+) | E74: 100 | F74: 100 | G74: 100 | H74: €/unit | I74: €/unit | J74: Source: BOM data
B76: Outdoor Unit tier breakpoints (for COGS VLOOKUP)
B77: Min Units (≥)
B78: 0 | C78: =E73 | L78: outdoor unit cost below 5,000 units, pulled from the table above
B79: 5000 | C79: =F73 | L79: outdoor unit cost at 5,000+
B80: 10000 | C80: =G73 | L80: outdoor unit cost at 10,000+
B81: SCENARIO & TIER BASIS
B82: Case (1 = Base €3m, 2 = Aggressive €10m) | D82: 2 | L82: the master switch. 2 = the 10m plan: bigger volumes, capex, 10m equity, faster sales hires
B83: BOM tier basis (1 = this year only, 2 = this year + next) | D83: 1 | L83: how the ketel cost tier is chosen. 1 = only the year's own volume (conservative)
B84: MEMO — previous hardcoded aggressive plan (no longer drives anything) | D84: 1800 | E84: 5200 | F84: 11000 | G84: 22000 | L84: superseded by the Growth Engine tab: units are now an output of the operating plan
B85: MEMO — previous hardcoded base plan (no longer drives anything) | D85: 600 | E85: 1600 | F85: 3600 | G85: 7200 | L85: the plan as it stands today — leave alone so Base stays comparable
B86: Other operating expenditures | F86: Yearly increase: | G86: 0.35
C87: Category | D87: Note | E87: 2026 | F87: 2027 | G87: 2028 | H87: 2029 | I87: 2030
B88: Office rent (part of General) | C88: G&A | D88: ongoing | E88: 5000 | F88: =$E88*(1+$G$86) | G88: =F88*(1+$G$86) | H88: =G88*(1+$G$86) | I88: =H88*(1+$G$86) | L88: 2026 is typed in; later years grow it by the rate above
B89: Other General | C89: G&A | D89: ongoing | E89: 7000 | F89: =$E89*(1+$G$86) | G89: =F89*(1+$G$86) | H89: =G89*(1+$G$86) | I89: =H89*(1+$G$86) | L89: 2026 is typed in; later years grow it by the rate above
B90: Baseline Sales & Marketing | C90: S&M | D90: ongoing | E90: 14000 | F90: =$E90*(1+$G$86) | G90: =F90*(1+$G$86) | H90: =G90*(1+$G$86) | I90: =H90*(1+$G$86) | L90: 2026 is typed in; later years grow it by the rate above
B91: Finance & Legal etc. | C91: G&A | D91: ongoing | E91: 8000 | F91: =$E91*(1+$G$86) | G91: =F91*(1+$G$86) | H91: =G91*(1+$G$86) | I91: =H91*(1+$G$86) | L91: 2026 is typed in; later years grow it by the rate above
B92: Ongoing Development costs | C92: R&D | D92: ongoing | E92: 10000 | F92: =$E92*(1+$G$86) | G92: =F92*(1+$G$86) | H92: =G92*(1+$G$86) | I92: =H92*(1+$G$86) | L92: 2026 is typed in; later years grow it by the rate above
B93: Third party cost product development | C93: R&D | D93: ongoing | E93: 15000 | F93: =$E93*(1+$G$86) | G93: =F93*(1+$G$86) | H93: =G93*(1+$G$86) | I93: =H93*(1+$G$86) | L93: 2026 is typed in; later years grow it by the rate above
B94: Kicker Development Cost | C94: R&D | D94: one-off | E94: 168933 | L94: one-off, lands in the single month it's booked on OPEX
B95: Customer journey (third party) | C95: S&M | D95: one-off | E95: 10000 | L95: one-off, lands in the single month it's booked on OPEX
B96: Branding + Website (third party cost) | C96: S&M | D96: one-off | E96: 10000 | L96: one-off, lands in the single month it's booked on OPEX
B97: Assembly partner | C97: R&D | D97: one-off | E97: 100000 | L97: one-off, lands in the single month it's booked on OPEX
B98: Tooling Fisher (result: 2%-3%) | C98: R&D | D98: one-off | E98: 45000 | L98: one-off, lands in the single month it's booked on OPEX
B101: Assumptions for costs per unit sold (3rd parties or expenses (NO personell) | G101: Units sold | H101: S&M cost per unit | I101: Decrease | J101: Yearly costs
B102: Marketing spend per Customer | C102: S&M | E102: 600 | F102: third party | G102: 0 | H102: =E106 | L102: top of the cost-down table: sales cost per unit at zero volume
B103: Closing costs per customer | C103: S&M | D103: (Calls, viewing location, etc) | E103: 150 | F103: third party | G103: 400 | H103: =E106 | J103: =G103*H103 | L103: same cost up to 400 units. column J = total spend there
B104: Aftersales and support | C104: S&M | E104: 50 | F104: third party | G104: =G103*2 | H104: =H103*I104 | I104: 0.9 | J104: =G104*H104 | L104: units double, cost per unit drops 10%. OPEX looks up this table
G105: =G104*2 | H105: =H104*I105 | I105: 0.9 | J105: =G105*H105 | L105: units double, cost per unit drops 10%
B106: Cost per unit sold (cost down driven by volume) | C106: S&M | D106: costdown: S(n)=S(1)*n^-b, where b=0,2 | E106: =SUM(E102:E104) | F106: S(1) | G106: =G105*2 | H106: =H105*I106 | I106: 0.9 | J106: =G106*H106 | L106: column E adds the three costs above = cost per unit at low volume
G107: =G106*2 | H107: =H106*I107 | I107: 0.9 | J107: =G107*H107 | L107: units double, cost per unit drops 10%
G108: =G107*2 | H108: =H107*I108 | I108: 0.9 | J108: =G108*H108 | L108: units double, cost per unit drops 10%
G109: =G108*2 | H109: =H108*I109 | I109: 0.9 | J109: =G109*H109 | L109: units double, cost per unit drops 10% (bottom of the table)
B111: Product | C111: Upsell item | D111: Type | E111: Attach % | F111: Unit rev. (EX VAT) | G111: Unit COGS | H111: Gross profit | I111: avg. Value | J111: avg. profit
B112: TTK / Combi+ | C112: Boiler variant 50 | D112: One-time | E112: 0.49 | F112: 165.29 | G112: 80 | H112: =F112-G112 | I112: =F112*E112 | J112: =H112*E112 | L112: profit per upsell, then the average per heat pump after attach %
B113: TTK / Combi+ | C113: Boiler variant 100 | D113: One-time | E113: 0.19 | F113: 330.58 | G113: 150 | H113: =F113-G113 | I113: =F113*E113 | J113: =H113*E113 | L113: profit per upsell, then the average per heat pump after attach %
B114: TTK / Combi+ | C114: Sound reduction | D114: One-time | E114: 0.79 | F114: 454.55 | G114: 190 | H114: =F114-G114 | I114: =F114*E114 | J114: =H114*E114 | L114: profit per upsell, then the average per heat pump after attach %
...

Sheet Growth Engine
B2: Tarnoc B.V. — Growth Engine
B3: Units sold are an OUTPUT of demand, sales capacity and build capacity — not an input. Every driver lives on the Assumptions tab (rows 130+). Case switch: Assumptions D82.
B5: Month | F5: 46388 | G5: 46419 | H5: 46447 | I5: 46478 | J5: 46508 | K5: 46539 | L5: 46569 | M5: 46600 | N5: 46631 | O5: 46661 | P5: 46692 | Q5: 46722 | R5: 46753 | S5: 46784 | T5: 46813 | U5: 46844 | V5: 46874 | W5: 46905 | X5: 46935 | Y5: 46966 | Z5: 46997 | AA5: 47027 | AB5: 47058 | AC5: 47088 | AD5: 47119 | AE5: 47150 | AF5: 47178 | AG5: 47209 | AH5: 47239 | AI5: 47270 | AJ5: 47300 | AK5: 47331 | AL5: 47362 | AM5: 47392 | AN5: 47423 | AO5: 47453 | AP5: 47484 | AQ5: 47515 | AR5: 47543 | AS5: 47574 | AT5: 47604 | AU5: 47635 | AV5: 47665 | AW5: 47696 | AX5: 47727 | AY5: 47757 | AZ5: 47788 | BA5: 47818 | BC5: 2027 | BD5: 2028 | BE5: 2029 | BF5: 2030 | BH5: what this row does
B7: MARKET — serviceable demand for a 1-for-1 gas-boiler replacement
B8: NL serviceable market | C8: units/mo | F8: =Assumptions!$F$134*Assumptions!$F$135/12 | G8: =Assumptions!$F$134*Assumptions!$F$135/12 | H8: =Assumptions!$F$134*Assumptions!$F$135/12 | I8: =Assumptions!$F$134*Assumptions!$F$135/12 | J8: =Assumptions!$F$134*Assumptions!$F$135/12 | K8: =Assumptions!$F$134*Assumptions!$F$135/12 | L8: =Assumptions!$F$134*Assumptions!$F$135/12 | M8: =Assumptions!$F$134*Assumptions!$F$135/12 | ... BA8: =Assumptions!$F$134*Assumptions!$F$135/12 | BC8: =SUM(F8:Q8) | BD8: =SUM(R8:AC8) | BE8: =SUM(AD8:AO8) | BF8: =SUM(AP8:BA8) | BH8: ~400k gas boilers replaced a year in NL x the share suitable for a 1-for-1 swap
B9: Expansion market (BE+DE) | C9: units/mo | F9: =IF(YEAR(F$5)>=Assumptions!$F$137,Assumptions!$F$136*Assumptions!$F$135/12,0) | G9: =IF(YEAR(G$5)>=Assumptions!$F$137,Assumptions!$F$136*Assumptions!$F$135/12,0) | H9: =IF(YEAR(H$5)>=Assumptions!$F$137,Assumptions!$F$136*Assumptions!$F$135/12,0) | I9: =IF(YEAR(I$5)>=Assumptions!$F$137,Assumptions!$F$136*Assumptions!$F$135/12,0) | J9: =IF(YEAR(J$5)>=Assumptions!$F$137,Assumptions!$F$136*Assumptions!$F$135/12,0) | K9: =IF(YEAR(K$5)>=Assumptions!$F$137,Assumptions!$F$136*Assumptions!$F$135/12,0) | L9: =IF(YEAR(L$5)>=Assumptions!$F$137,Assumptions!$F$136*Assumptions!$F$135/12,0) | M9: =IF(YEAR(M$5)>=Assumptions!$F$137,Assumptions!$F$136*Assumptions!$F$135/12,0) | ... BA9: =IF(YEAR(BA$5)>=Assumptions!$F$137,Assumptions!$F$136*Assumptions!$F$135/12,0) | BC9: =SUM(F9:Q9) | BD9: =SUM(R9:AC9) | BE9: =SUM(AD9:AO9) | BF9: =SUM(AP9:BA9) | BH9: opens in the entry year set on Assumptions
B10: Total serviceable market | C10: units/mo | F10: =F8+F9 | G10: =G8+G9 | H10: =H8+H9 | I10: =I8+I9 | J10: =J8+J9 | K10: =K8+K9 | L10: =L8+L9 | M10: =M8+M9 | ... BA10: =BA8+BA9 | BC10: =SUM(F10:Q10) | BD10: =SUM(R10:AC10) | BE10: =SUM(AD10:AO10) | BF10: =SUM(AP10:BA10)
B11: Share ceiling — max units allowed | C11: units/mo | F11: =F10*Assumptions!$F$138 | G11: =G10*Assumptions!$F$138 | H11: =H10*Assumptions!$F$138 | I11: =I10*Assumptions!$F$138 | J11: =J10*Assumptions!$F$138 | K11: =K10*Assumptions!$F$138 | L11: =L10*Assumptions!$F$138 | M11: =M10*Assumptions!$F$138 | ... BA11: =BA10*Assumptions!$F$138 | BC11: =SUM(F11:Q11) | BD11: =SUM(R11:AC11) | BE11: =SUM(AD11:AO11) | BF11: =SUM(AP11:BA11) | BH11: a hard ceiling, so the plan can never quietly assume we own an unrealistic slice of the market
B13: DEMAND GENERATION — marketing spend drives orders
B14: Marketing spend | C14: EUR/mo | F14: =IF(YEAR(F$5)=2027,Assumptions!$F$140,IF(YEAR(F$5)=2028,Assumptions!$F$141,IF(YEAR(F$5)=2029,Assumptions!$F$142,Assumptions!$F$143))) | G14: =IF(YEAR(G$5)=2027,Assumptions!$F$140,IF(YEAR(G$5)=2028,Assumptions!$F$141,IF(YEAR(G$5)=2029,Assumptions!$F$142,Assumptions!$F$143))) | H14: =IF(YEAR(H$5)=2027,Assumptions!$F$140,IF(YEAR(H$5)=2028,Assumptions!$F$141,IF(YEAR(H$5)=2029,Assumptions!$F$142,Assumptions!$F$143))) | I14: =IF(YEAR(I$5)=2027,Assumptions!$F$140,IF(YEAR(I$5)=2028,Assumptions!$F$141,IF(YEAR(I$5)=2029,Assumptions!$F$142,Assumptions!$F$143))) | J14: =IF(YEAR(J$5)=2027,Assumptions!$F$140,IF(YEAR(J$5)=2028,Assumptions!$F$141,IF(YEAR(J$5)=2029,Assumptions!$F$142,Assumptions!$F$143))) | K14: =IF(YEAR(K$5)=2027,Assumptions!$F$140,IF(YEAR(K$5)=2028,Assumptions!$F$141,IF(YEAR(K$5)=2029,Assumptions!$F$142,Assumptions!$F$143))) | L14: =IF(YEAR(L$5)=2027,Assumptions!$F$140,IF(YEAR(L$5)=2028,Assumptions!$F$141,IF(YEAR(L$5)=2029,Assumptions!$F$142,Assumptions!$F$143))) | M14: =IF(YEAR(M$5)=2027,Assumptions!$F$140,IF(YEAR(M$5)=2028,Assumptions!$F$141,IF(YEAR(M$5)=2029,Assumptions!$F$142,Assumptions!$F$143))) | ... BA14: =IF(YEAR(BA$5)=2027,Assumptions!$F$140,IF(YEAR(BA$5)=2028,Assumptions!$F$141,IF(YEAR(BA$5)=2029,Assumptions!$F$142,Assumptions!$F$143))) | BC14: =SUM(F14:Q14) | BD14: =SUM(R14:AC14) | BE14: =SUM(AD14:AO14) | BF14: =SUM(AP14:BA14)
B15: Installed base, start of month | C15: units | F15: =0 | G15: =F46 | H15: =G46 | I15: =H46 | J15: =I46 | K15: =J46 | L15: =K46 | M15: =L46 | N15: =M46 | ... BA15: =AZ46 | BC15: =Q15 | BD15: =AC15 | BE15: =AO15 | BF15: =BA15
B16: Effective CPL | C16: EUR | F16: =Assumptions!$F$144*(1-Assumptions!$F$145)^IF(F15<400,0,LOG(F15/400,2)) | G16: =Assumptions!$F$144*(1-Assumptions!$F$145)^IF(G15<400,0,LOG(G15/400,2)) | H16: =Assumptions!$F$144*(1-Assumptions!$F$145)^IF(H15<400,0,LOG(H15/400,2)) | I16: =Assumptions!$F$144*(1-Assumptions!$F$145)^IF(I15<400,0,LOG(I15/400,2)) | J16: =Assumptions!$F$144*(1-Assumptions!$F$145)^IF(J15<400,0,LOG(J15/400,2)) | K16: =Assumptions!$F$144*(1-Assumptions!$F$145)^IF(K15<400,0,LOG(K15/400,2)) | L16: =Assumptions!$F$144*(1-Assumptions!$F$145)^IF(L15<400,0,LOG(L15/400,2)) | M16: =Assumptions!$F$144*(1-Assumptions!$F$145)^IF(M15<400,0,LOG(M15/400,2)) | ... BA16: =Assumptions!$F$144*(1-Assumptions!$F$145)^IF(BA15<400,0,LOG(BA15/400,2)) | BC16: =AVERAGE(F16:Q16) | BD16: =AVERAGE(R16:AC16) | BE16: =AVERAGE(AD16:AO16) | BF16: =AVERAGE(AP16:BA16) | BH16: cost per lead falls 10% per doubling of installed base — brand, referral and channel pull
B17: Leads | C17: leads | F17: =IFERROR(F14/F16,0) | G17: =IFERROR(G14/G16,0) | H17: =IFERROR(H14/H16,0) | I17: =IFERROR(I14/I16,0) | J17: =IFERROR(J14/J16,0) | K17: =IFERROR(K14/K16,0) | L17: =IFERROR(L14/L16,0) | M17: =IFERROR(M14/M16,0) | ... BA17: =IFERROR(BA14/BA16,0) | BC17: =SUM(F17:Q17) | BD17: =SUM(R17:AC17) | BE17: =SUM(AD17:AO17) | BF17: =SUM(AP17:BA17)
B18: Qualified leads | C18: leads | F18: =F17*Assumptions!$F$146 | G18: =G17*Assumptions!$F$146 | H18: =H17*Assumptions!$F$146 | I18: =I17*Assumptions!$F$146 | J18: =J17*Assumptions!$F$146 | K18: =K17*Assumptions!$F$146 | L18: =L17*Assumptions!$F$146 | M18: =M17*Assumptions!$F$146 | ... BA18: =BA17*Assumptions!$F$146 | BC18: =SUM(F18:Q18) | BD18: =SUM(R18:AC18) | BE18: =SUM(AD18:AO18) | BF18: =SUM(AP18:BA18)
B19: DEMAND — orders generated | C19: units/mo | F19: =F18*Assumptions!$F$147 | G19: =G18*Assumptions!$F$147 | H19: =H18*Assumptions!$F$147 | I19: =I18*Assumptions!$F$147 | J19: =J18*Assumptions!$F$147 | K19: =K18*Assumptions!$F$147 | L19: =L18*Assumptions!$F$147 | M19: =M18*Assumptions!$F$147 | ... BA19: =BA18*Assumptions!$F$147 | BC19: =SUM(F19:Q19) | BD19: =SUM(R19:AC19) | BE19: =SUM(AD19:AO19) | BF19: =SUM(AP19:BA19)
B20: Implied CAC | C20: EUR/unit | F20: =IFERROR(F14/F19,0) | G20: =IFERROR(G14/G19,0) | H20: =IFERROR(H14/H19,0) | I20: =IFERROR(I14/I19,0) | J20: =IFERROR(J14/J19,0) | K20: =IFERROR(K14/K19,0) | L20: =IFERROR(L14/L19,0) | M20: =IFERROR(M14/M19,0) | ... BA20: =IFERROR(BA14/BA19,0) | BC20: =AVERAGE(F20:Q20) | BD20: =AVERAGE(R20:AC20) | BE20: =AVERAGE(AD20:AO20) | BF20: =AVERAGE(AP20:BA20) | BH20: reconciles to the EUR600/customer already assumed on Assumptions row 102
B22: SALES CAPACITY — direct reps early, enabled installer channel at scale
B23: Direct motion share | C23: % | F23: =IF(YEAR(F$5)=2027,Assumptions!$F$149,IF(YEAR(F$5)=2028,Assumptions!$F$150,IF(YEAR(F$5)=2029,Assumptions!$F$151,Assumptions!$F$152))) | G23: =IF(YEAR(G$5)=2027,Assumptions!$F$149,IF(YEAR(G$5)=2028,Assumptions!$F$150,IF(YEAR(G$5)=2029,Assumptions!$F$151,Assumptions!$F$152))) | H23: =IF(YEAR(H$5)=2027,Assumptions!$F$149,IF(YEAR(H$5)=2028,Assumptions!$F$150,IF(YEAR(H$5)=2029,Assumptions!$F$151,Assumptions!$F$152))) | I23: =IF(YEAR(I$5)=2027,Assumptions!$F$149,IF(YEAR(I$5)=2028,Assumptions!$F$150,IF(YEAR(I$5)=2029,Assumptions!$F$151,Assumptions!$F$152))) | J23: =IF(YEAR(J$5)=2027,Assumptions!$F$149,IF(YEAR(J$5)=2028,Assumptions!$F$150,IF(YEAR(J$5)=2029,Assumptions!$F$151,Assumptions!$F$152))) | K23: =IF(YEAR(K$5)=2027,Assumptions!$F$149,IF(YEAR(K$5)=2028,Assumptions!$F$150,IF(YEAR(K$5)=2029,Assumptions!$F$151,Assumptions!$F$152))) | L23: =IF(YEAR(L$5)=2027,Assumptions!$F$149,IF(YEAR(L$5)=2028,Assumptions!$F$150,IF(YEAR(L$5)=2029,Assumptions!$F$151,Assumptions!$F$152))) | M23: =IF(YEAR(M$5)=2027,Assumptions!$F$149,IF(YEAR(M$5)=2028,Assumptions!$F$150,IF(YEAR(M$5)=2029,Assumptions!$F$151,Assumptions!$F$152))) | ... BA23: =IF(YEAR(BA$5)=2027,Assumptions!$F$149,IF(YEAR(BA$5)=2028,Assumptions!$F$150,IF(YEAR(BA$5)=2029,Assumptions!$F$151,Assumptions!$F$152))) | BC23: =AVERAGE(F23:Q23) | BD23: =AVERAGE(R23:AC23) | BE23: =AVERAGE(AD23:AO23) | BF23: =AVERAGE(AP23:BA23)
B24: Reps hired in month | C24: FTE | F24: =IF(YEAR(F$5)=2027,Assumptions!$F$154,IF(YEAR(F$5)=2028,Assumptions!$F$155,IF(YEAR(F$5)=2029,Assumptions!$F$156,Assumptions!$F$157))) | G24: =IF(YEAR(G$5)=2027,Assumptions!$F$154,IF(YEAR(G$5)=2028,Assumptions!$F$155,IF(YEAR(G$5)=2029,Assumptions!$F$156,Assumptions!$F$157))) | H24: =IF(YEAR(H$5)=2027,Assumptions!$F$154,IF(YEAR(H$5)=2028,Assumptions!$F$155,IF(YEAR(H$5)=2029,Assumptions!$F$156,Assumptions!$F$157))) | I24: =IF(YEAR(I$5)=2027,Assumptions!$F$154,IF(YEAR(I$5)=2028,Assumptions!$F$155,IF(YEAR(I$5)=2029,Assumptions!$F$156,Assumptions!$F$157))) | J24: =IF(YEAR(J$5)=2027,Assumptions!$F$154,IF(YEAR(J$5)=2028,Assumptions!$F$155,IF(YEAR(J$5)=2029,Assumptions!$F$156,Assumptions!$F$157))) | K24: =IF(YEAR(K$5)=2027,Assumptions!$F$154,IF(YEAR(K$5)=2028,Assumptions!$F$155,IF(YEAR(K$5)=2029,Assumptions!$F$156,Assumptions!$F$157))) | L24: =IF(YEAR(L$5)=2027,Assumptions!$F$154,IF(YEAR(L$5)=2028,Assumptions!$F$155,IF(YEAR(L$5)=2029,Assumptions!$F$156,Assumptions!$F$157))) | M24: =IF(YEAR(M$5)=2027,Assumptions!$F$154,IF(YEAR(M$5)=2028,Assumptions!$F$155,IF(YEAR(M$5)=2029,Assumptions!$F$156,Assumptions!$F$157))) | ... BA24: =IF(YEAR(BA$5)=2027,Assumptions!$F$154,IF(YEAR(BA$5)=2028,Assumptions!$F$155,IF(YEAR(BA$5)=2029,Assumptions!$F$156,Assumptions!$F$157))) | BC24: =SUM(F24:Q24) | BD24: =SUM(R24:AC24) | BE24: =SUM(AD24:AO24) | BF24: =SUM(AP24:BA24)
B25: Reps on payroll | C25: FTE | F25: =Assumptions!$F$153+F24 | G25: =F25+G24 | H25: =G25+H24 | I25: =H25+I24 | J25: =I25+J24 | K25: =J25+K24 | L25: =K25+L24 | M25: =L25+M24 | N25: =M25+N24 | ... BA25: =AZ25+BA24 | BC25: =Q25 | BD25: =AC25 | BE25: =AO25 | BF25: =BA25
B26: Reps fully ramped | C26: FTE | F26: =Assumptions!$F$153 | G26: =IF(1<Assumptions!$F$159,Assumptions!$F$153,INDEX($F25:BA25,2-Assumptions!$F$159)) | H26: =IF(2<Assumptions!$F$159,Assumptions!$F$153,INDEX($F25:BA25,3-Assumptions!$F$159)) | I26: =IF(3<Assumptions!$F$159,Assumptions!$F$153,INDEX($F25:BA25,4-Assumptions!$F$159)) | J26: =IF(4<Assumptions!$F$159,Assumptions!$F$153,INDEX($F25:BA25,5-Assumptions!$F$159)) | K26: =IF(5<Assumptions!$F$159,Assumptions!$F$153,INDEX($F25:BA25,6-Assumptions!$F$159)) | L26: =IF(6<Assumptions!$F$159,Assumptions!$F$153,INDEX($F25:BA25,7-Assumptions!$F$159)) | M26: =IF(7<Assumptions!$F$159,Assumptions!$F$153,INDEX($F25:BA25,8-Assumptions!$F$159)) | N26: =IF(8<Assumptions!$F$159,Assumptions!$F$153,INDEX($F25:BA25,9-Assumptions!$F$159)) | O26: =IF(9<Assumptions!$F$159,Assumptions!$F$153,INDEX($F25:BA25,10-Assumptions!$F$159)) | P26: =IF(10<Assumptions!$F$159,Assumptions!$F$153,INDEX($F25:BA25,11-Assumptions!$F$159)) | Q26: =IF(11<Assumptions!$F$159,Assumptions!$F$153,INDEX($F25:BA25,12-Assumptions!$F$159)) | R26: =IF(12<Assumptions!$F$159,Assumptions!$F$153,INDEX($F25:BA25,13-Assumptions!$F$159)) | S26: =IF(13<Assumptions!$F$159,Assumptions!$F$153,INDEX($F25:BA25,14-Assumptions!$F$159)) | T26: =IF(14<Assumptions!$F$159,Assumptions!$F$153,INDEX($F25:BA25,15-Assumptions!$F$159)) | U26: =IF(15<Assumptions!$F$159,Assumptions!$F$153,INDEX($F25:BA25,16-Assumptions!$F$159)) | V26: =IF(16<Assumptions!$F$159,Assumptions!$F$153,INDEX($F25:BA25,17-Assumptions!$F$159)) | W26: =IF(17<Assumptions!$F$159,Assumptions!$F$153,INDEX($F25:BA25,18-Assumptions!$F$159)) | X26: =IF(18<Assumptions!$F$159,Assumptions!$F$153,INDEX($F25:BA25,19-Assumptions!$F$159)) | Y26: =IF(19<Assumptions!$F$159,Assumptions!$F$153,INDEX($F25:BA25,20-Assumptions!$F$159)) | Z26: =IF(20<Assumptions!$F$159,Assumptions!$F$153,INDEX($F25:BA25,21-Assumptions!$F$159)) | AA26: =IF(21<Assumptions!$F$159,Assumptions!$F$153,INDEX($F25:BA25,22-Assumptions!$F$159)) | AB26: =IF(22<Assumptions!$F$159,Assumptions!$F$153,INDEX($F25:BA25,23-Assumptions!$F$159)) | AC26: =IF(23<Assumptions!$F$159,Assumptions!$F$153,INDEX($F25:BA25,24-Assumptions!$F$159)) | AD26: =IF(24<Assumptions!$F$159,Assumptions!$F$153,INDEX($F25:BA25,25-Assumptions!$F$159)) | AE26: =IF(25<Assumptions!$F$159,Assumptions!$F$153,INDEX($F25:BA25,26-Assumptions!$F$159)) | AF26: =IF(26<Assumptions!$F$159,Assumptions!$F$153,INDEX($F25:BA25,27-Assumptions!$F$159)) | AG26: =IF(27<Assumptions!$F$159,Assumptions!$F$153,INDEX($F25:BA25,28-Assumptions!$F$159)) | AH26: =IF(28<Assumptions!$F$159,Assumptions!$F$153,INDEX($F25:BA25,29-Assumptions!$F$159)) | AI26: =IF(29<Assumptions!$F$159,Assumptions!$F$153,INDEX($F25:BA25,30-Assumptions!$F$159)) | AJ26: =IF(30<Assumptions!$F$159,Assumptions!$F$153,INDEX($F25:BA25,31-Assumptions!$F$159)) | AK26: =IF(31<Assumptions!$F$159,Assumptions!$F$153,INDEX($F25:BA25,32-Assumptions!$F$159)) | AL26: =IF(32<Assumptions!$F$159,Assumptions!$F$153,INDEX($F25:BA25,33-Assumptions!$F$159)) | AM26: =IF(33<Assumptions!$F$159,Assumptions!$F$153,INDEX($F25:BA25,34-Assumptions!$F$159)) | AN26: =IF(34<Assumptions!$F$159,Assumptions!$F$153,INDEX($F25:BA25,35-Assumptions!$F$159)) | AO26: =IF(35<Assumptions!$F$159,Assumptions!$F$153,INDEX($F25:BA25,36-Assumptions!$F$159)) | AP26: =IF(36<Assumptions!$F$159,Assumptions!$F$153,INDEX($F25:BA25,37-Assumptions!$F$159)) | AQ26: =IF(37<Assumptions!$F$159,Assumptions!$F$153,INDEX($F25:BA25,38-Assumptions!$F$159)) | AR26: =IF(38<Assumptions!$F$159,Assumptions!$F$153,INDEX($F25:BA25,39-Assumptions!$F$159)) | AS26: =IF(39<Assumptions!$F$159,Assumptions!$F$153,INDEX($F25:BA25,40-Assumptions!$F$159)) | AT26: =IF(40<Assumptions!$F$159,Assumptions!$F$153,INDEX($F25:BA25,41-Assumptions!$F$159)) | AU26: =IF(41<Assumptions!$F$159,Assumptions!$F$153,INDEX($F25:BA25,42-Assumptions!$F$159)) | AV26: =IF(42<Assumptions!$F$159,Assumptions!$F$153,INDEX($F25:BA25,43-Assumptions!$F$159)) | AW26: =IF(43<Assumptions!$F$159,Assumptions!$F$153,INDEX($F25:BA25,44-Assumptions!$F$159)) | AX26: =IF(44<Assumptions!$F$159,Assumptions!$F$153,INDEX($F25:BA25,45-Assumptions!$F$159)) | AY26: =IF(45<Assumptions!$F$159,Assumptions!$F$153,INDEX($F25:BA25,46-Assumptions!$F$159)) | AZ26: =IF(46<Assumptions!$F$159,Assumptions!$F$153,INDEX($F25:BA25,47-Assumptions!$F$159)) | BA26: =IF(47<Assumptions!$F$159,Assumptions!$F$153,INDEX($F25:BA25,48-Assumptions!$F$159)) | BC26: =Q26 | BD26: =AC26 | BE26: =AO26 | BF26: =BA26 | BH26: a rep carries no quota until fully ramped (6 months) — deliberately conservative
B27: Direct capacity | C27: units/mo | F27: =F26*Assumptions!$F$158*Assumptions!$F$160 | G27: =G26*Assumptions!$F$158*Assumptions!$F$160 | H27: =H26*Assumptions!$F$158*Assumptions!$F$160 | I27: =I26*Assumptions!$F$158*Assumptions!$F$160 | J27: =J26*Assumptions!$F$158*Assumptions!$F$160 | K27: =K26*Assumptions!$F$158*Assumptions!$F$160 | L27: =L26*Assumptions!$F$158*Assumptions!$F$160 | M27: =M26*Assumptions!$F$158*Assumptions!$F$160 | ... BA27: =BA26*Assumptions!$F$158*Assumptions!$F$160 | BC27: =SUM(F27:Q27) | BD27: =SUM(R27:AC27) | BE27: =SUM(AD27:AO27) | BF27: =SUM(AP27:BA27)
B28: Installer partners recruited | C28: partners | F28: =IF(YEAR(F$5)=2027,Assumptions!$F$162,IF(YEAR(F$5)=2028,Assumptions!$F$163,IF(YEAR(F$5)=2029,Assumptions!$F$164,Assumptions!$F$165))) | G28: =IF(YEAR(G$5)=2027,Assumptions!$F$162,IF(YEAR(G$5)=2028,Assumptions!$F$163,IF(YEAR(G$5)=2029,Assumptions!$F$164,Assumptions!$F$165))) | H28: =IF(YEAR(H$5)=2027,Assumptions!$F$162,IF(YEAR(H$5)=2028,Assumptions!$F$163,IF(YEAR(H$5)=2029,Assumptions!$F$164,Assumptions!$F$165))) | I28: =IF(YEAR(I$5)=2027,Assumptions!$F$162,IF(YEAR(I$5)=2028,Assumptions!$F$163,IF(YEAR(I$5)=2029,Assumptions!$F$164,Assumptions!$F$165))) | J28: =IF(YEAR(J$5)=2027,Assumptions!$F$162,IF(YEAR(J$5)=2028,Assumptions!$F$163,IF(YEAR(J$5)=2029,Assumptions!$F$164,Assumptions!$F$165))) | K28: =IF(YEAR(K$5)=2027,Assumptions!$F$162,IF(YEAR(K$5)=2028,Assumptions!$F$163,IF(YEAR(K$5)=2029,Assumptions!$F$164,Assumptions!$F$165))) | L28: =IF(YEAR(L$5)=2027,Assumptions!$F$162,IF(YEAR(L$5)=2028,Assumptions!$F$163,IF(YEAR(L$5)=2029,Assumptions!$F$164,Assumptions!$F$165))) | M28: =IF(YEAR(M$5)=2027,Assumptions!$F$162,IF(YEAR(M$5)=2028,Assumptions!$F$163,IF(YEAR(M$5)=2029,Assumptions!$F$164,Assumptions!$F$165))) | ... BA28: =IF(YEAR(BA$5)=2027,Assumptions!$F$162,IF(YEAR(BA$5)=2028,Assumptions!$F$163,IF(YEAR(BA$5)=2029,Assumptions!$F$164,Assumptions!$F$165))) | BC28: =SUM(F28:Q28) | BD28: =SUM(R28:AC28) | BE28: =SUM(AD28:AO28) | BF28: =SUM(AP28:BA28)
B29: Installer partners on books | C29: partners | F29: =Assumptions!$F$161+F28 | G29: =F29+G28 | H29: =G29+H28 | I29: =H29+I28 | J29: =I29+J28 | K29: =J29+K28 | L29: =K29+L28 | M29: =L29+M28 | N29: =M29+N28 | ... BA29: =AZ29+BA28 | BC29: =Q29 | BD29: =AC29 | BE29: =AO29 | BF29: =BA29
B30: Installer partners productive | C30: partners | F30: =Assumptions!$F$161 | G30: =IF(1<Assumptions!$F$166,Assumptions!$F$161,INDEX($F29:BA29,2-Assumptions!$F$166)) | H30: =IF(2<Assumptions!$F$166,Assumptions!$F$161,INDEX($F29:BA29,3-Assumptions!$F$166)) | I30: =IF(3<Assumptions!$F$166,Assumptions!$F$161,INDEX($F29:BA29,4-Assumptions!$F$166)) | J30: =IF(4<Assumptions!$F$166,Assumptions!$F$161,INDEX($F29:BA29,5-Assumptions!$F$166)) | K30: =IF(5<Assumptions!$F$166,Assumptions!$F$161,INDEX($F29:BA29,6-Assumptions!$F$166)) | L30: =IF(6<Assumptions!$F$166,Assumptions!$F$161,INDEX($F29:BA29,7-Assumptions!$F$166)) | M30: =IF(7<Assumptions!$F$166,Assumptions!$F$161,INDEX($F29:BA29,8-Assumptions!$F$166)) | N30: =IF(8<Assumptions!$F$166,Assumptions!$F$161,INDEX($F29:BA29,9-Assumptions!$F$166)) | O30: =IF(9<Assumptions!$F$166,Assumptions!$F$161,INDEX($F29:BA29,10-Assumptions!$F$166)) | P30: =IF(10<Assumptions!$F$166,Assumptions!$F$161,INDEX($F29:BA29,11-Assumptions!$F$166)) | Q30: =IF(11<Assumptions!$F$166,Assumptions!$F$161,INDEX($F29:BA29,12-Assumptions!$F$166)) | R30: =IF(12<Assumptions!$F$166,Assumptions!$F$161,INDEX($F29:BA29,13-Assumptions!$F$166)) | S30: =IF(13<Assumptions!$F$166,Assumptions!$F$161,INDEX($F29:BA29,14-Assumptions!$F$166)) | T30: =IF(14<Assumptions!$F$166,Assumptions!$F$161,INDEX($F29:BA29,15-Assumptions!$F$166)) | U30: =IF(15<Assumptions!$F$166,Assumptions!$F$161,INDEX($F29:BA29,16-Assumptions!$F$166)) | V30: =IF(16<Assumptions!$F$166,Assumptions!$F$161,INDEX($F29:BA29,17-Assumptions!$F$166)) | W30: =IF(17<Assumptions!$F$166,Assumptions!$F$161,INDEX($F29:BA29,18-Assumptions!$F$166)) | X30: =IF(18<Assumptions!$F$166,Assumptions!$F$161,INDEX($F29:BA29,19-Assumptions!$F$166)) | Y30: =IF(19<Assumptions!$F$166,Assumptions!$F$161,INDEX($F29:BA29,20-Assumptions!$F$166)) | Z30: =IF(20<Assumptions!$F$166,Assumptions!$F$161,INDEX($F29:BA29,21-Assumptions!$F$166)) | AA30: =IF(21<Assumptions!$F$166,Assumptions!$F$161,INDEX($F29:BA29,22-Assumptions!$F$166)) | AB30: =IF(22<Assumptions!$F$166,Assumptions!$F$161,INDEX($F29:BA29,23-Assumptions!$F$166)) | AC30: =IF(23<Assumptions!$F$166,Assumptions!$F$161,INDEX($F29:BA29,24-Assumptions!$F$166)) | AD30: =IF(24<Assumptions!$F$166,Assumptions!$F$161,INDEX($F29:BA29,25-Assumptions!$F$166)) | AE30: =IF(25<Assumptions!$F$166,Assumptions!$F$161,INDEX($F29:BA29,26-Assumptions!$F$166)) | AF30: =IF(26<Assumptions!$F$166,Assumptions!$F$161,INDEX($F29:BA29,27-Assumptions!$F$166)) | AG30: =IF(27<Assumptions!$F$166,Assumptions!$F$161,INDEX($F29:BA29,28-Assumptions!$F$166)) | AH30: =IF(28<Assumptions!$F$166,Assumptions!$F$161,INDEX($F29:BA29,29-Assumptions!$F$166)) | AI30: =IF(29<Assumptions!$F$166,Assumptions!$F$161,INDEX($F29:BA29,30-Assumptions!$F$166)) | AJ30: =IF(30<Assumptions!$F$166,Assumptions!$F$161,INDEX($F29:BA29,31-Assumptions!$F$166)) | AK30: =IF(31<Assumptions!$F$166,Assumptions!$F$161,INDEX($F29:BA29,32-Assumptions!$F$166)) | AL30: =IF(32<Assumptions!$F$166,Assumptions!$F$161,INDEX($F29:BA29,33-Assumptions!$F$166)) | AM30: =IF(33<Assumptions!$F$166,Assumptions!$F$161,INDEX($F29:BA29,34-Assumptions!$F$166)) | AN30: =IF(34<Assumptions!$F$166,Assumptions!$F$161,INDEX($F29:BA29,35-Assumptions!$F$166)) | AO30: =IF(35<Assumptions!$F$166,Assumptions!$F$161,INDEX($F29:BA29,36-Assumptions!$F$166)) | AP30: =IF(36<Assumptions!$F$166,Assumptions!$F$161,INDEX($F29:BA29,37-Assumptions!$F$166)) | AQ30: =IF(37<Assumptions!$F$166,Assumptions!$F$161,INDEX($F29:BA29,38-Assumptions!$F$166)) | AR30: =IF(38<Assumptions!$F$166,Assumptions!$F$161,INDEX($F29:BA29,39-Assumptions!$F$166)) | AS30: =IF(39<Assumptions!$F$166,Assumptions!$F$161,INDEX($F29:BA29,40-Assumptions!$F$166)) | AT30: =IF(40<Assumptions!$F$166,Assumptions!$F$161,INDEX($F29:BA29,41-Assumptions!$F$166)) | AU30: =IF(41<Assumptions!$F$166,Assumptions!$F$161,INDEX($F29:BA29,42-Assumptions!$F$166)) | AV30: =IF(42<Assumptions!$F$166,Assumptions!$F$161,INDEX($F29:BA29,43-Assumptions!$F$166)) | AW30: =IF(43<Assumptions!$F$166,Assumptions!$F$161,INDEX($F29:BA29,44-Assumptions!$F$166)) | AX30: =IF(44<Assumptions!$F$166,Assumptions!$F$161,INDEX($F29:BA29,45-Assumptions!$F$166)) | AY30: =IF(45<Assumptions!$F$166,Assumptions!$F$161,INDEX($F29:BA29,46-Assumptions!$F$166)) | AZ30: =IF(46<Assumptions!$F$166,Assumptions!$F$161,INDEX($F29:BA29,47-Assumptions!$F$166)) | BA30: =IF(47<Assumptions!$F$166,Assumptions!$F$161,INDEX($F29:BA29,48-Assumptions!$F$166)) | BC30: =Q30 | BD30: =AC30 | BE30: =AO30 | BF30: =BA30
B31: Channel capacity | C31: units/mo | F31: =F30*Assumptions!$F$167 | G31: =G30*Assumptions!$F$167 | H31: =H30*Assumptions!$F$167 | I31: =I30*Assumptions!$F$167 | J31: =J30*Assumptions!$F$167 | K31: =K30*Assumptions!$F$167 | L31: =L30*Assumptions!$F$167 | M31: =M30*Assumptions!$F$167 | ... BA31: =BA30*Assumptions!$F$167 | BC31: =SUM(F31:Q31) | BD31: =SUM(R31:AC31) | BE31: =SUM(AD31:AO31) | BF31: =SUM(AP31:BA31)
B32: TOTAL sales capacity | C32: units/mo | F32: =MIN(IFERROR(F27/F23,1000000),IFERROR(F31/(1-F23),1000000)) | G32: =MIN(IFERROR(G27/G23,1000000),IFERROR(G31/(1-G23),1000000)) | H32: =MIN(IFERROR(H27/H23,1000000),IFERROR(H31/(1-H23),1000000)) | I32: =MIN(IFERROR(I27/I23,1000000),IFERROR(I31/(1-I23),1000000)) | J32: =MIN(IFERROR(J27/J23,1000000),IFERROR(J31/(1-J23),1000000)) | K32: =MIN(IFERROR(K27/K23,1000000),IFERROR(K31/(1-K23),1000000)) | L32: =MIN(IFERROR(L27/L23,1000000),IFERROR(L31/(1-L23),1000000)) | M32: =MIN(IFERROR(M27/M23,1000000),IFERROR(M31/(1-M23),1000000)) | ... BA32: =MIN(IFERROR(BA27/BA23,1000000),IFERROR(BA31/(1-BA23),1000000)) | BC32: =SUM(F32:Q32) | BD32: =SUM(R32:AC32) | BE32: =SUM(AD32:AO32) | BF32: =SUM(AP32:BA32) | BH32: how many we can actually sell: our own reps have to cover the direct share, installers the rest
B33: Partner managers required | C33: FTE | F33: =ROUNDUP(F29/Assumptions!$F$168,0) | G33: =ROUNDUP(G29/Assumptions!$F$168,0) | H33: =ROUNDUP(H29/Assumptions!$F$168,0) | I33: =ROUNDUP(I29/Assumptions!$F$168,0) | J33: =ROUNDUP(J29/Assumptions!$F$168,0) | K33: =ROUNDUP(K29/Assumptions!$F$168,0) | L33: =ROUNDUP(L29/Assumptions!$F$168,0) | M33: =ROUNDUP(M29/Assumptions!$F$168,0) | ... BA33: =ROUNDUP(BA29/Assumptions!$F$168,0) | BC33: =Q33 | BD33: =AC33 | BE33: =AO33 | BF33: =BA33
B36: BUILD CAPACITY — assembly partner first, in-house lines take over
B37: Assembly partner capacity | C37: units/mo | F37: =Assumptions!$F$172 | G37: =Assumptions!$F$172 | H37: =Assumptions!$F$172 | I37: =Assumptions!$F$172 | J37: =Assumptions!$F$172 | K37: =Assumptions!$F$172 | L37: =Assumptions!$F$172 | M37: =Assumptions!$F$172 | ... BA37: =Assumptions!$F$172 | BC37: =SUM(F37:Q37) | BD37: =SUM(R37:AC37) | BE37: =SUM(AD37:AO37) | BF37: =SUM(AP37:BA37)
B38: In-house lines live | C38: lines | F38: =IF(F$5>=Assumptions!$F$173,1,0)+IF(F$5>=Assumptions!$F$174,1,0) | G38: =IF(G$5>=Assumptions!$F$173,1,0)+IF(G$5>=Assumptions!$F$174,1,0) | H38: =IF(H$5>=Assumptions!$F$173,1,0)+IF(H$5>=Assumptions!$F$174,1,0) | I38: =IF(I$5>=Assumptions!$F$173,1,0)+IF(I$5>=Assumptions!$F$174,1,0) | J38: =IF(J$5>=Assumptions!$F$173,1,0)+IF(J$5>=Assumptions!$F$174,1,0) | K38: =IF(K$5>=Assumptions!$F$173,1,0)+IF(K$5>=Assumptions!$F$174,1,0) | L38: =IF(L$5>=Assumptions!$F$173,1,0)+IF(L$5>=Assumptions!$F$174,1,0) | M38: =IF(M$5>=Assumptions!$F$173,1,0)+IF(M$5>=Assumptions!$F$174,1,0) | ... BA38: =IF(BA$5>=Assumptions!$F$173,1,0)+IF(BA$5>=Assumptions!$F$174,1,0) | BC38: =Q38 | BD38: =AC38 | BE38: =AO38 | BF38: =BA38
B39: In-house capacity | C39: units/mo | F39: =F38*Assumptions!$F$175 | G39: =G38*Assumptions!$F$175 | H39: =H38*Assumptions!$F$175 | I39: =I38*Assumptions!$F$175 | J39: =J38*Assumptions!$F$175 | K39: =K38*Assumptions!$F$175 | L39: =L38*Assumptions!$F$175 | M39: =M38*Assumptions!$F$175 | ... BA39: =BA38*Assumptions!$F$175 | BC39: =SUM(F39:Q39) | BD39: =SUM(R39:AC39) | BE39: =SUM(AD39:AO39) | BF39: =SUM(AP39:BA39)
B40: TOTAL build capacity | C40: units/mo | F40: =F37+F39 | G40: =G37+G39 | H40: =H37+H39 | I40: =I37+I39 | J40: =J37+J39 | K40: =K37+K39 | L40: =L37+L39 | M40: =M37+M39 | ... BA40: =BA37+BA39 | BC40: =SUM(F40:Q40) | BD40: =SUM(R40:AC40) | BE40: =SUM(AD40:AO40) | BF40: =SUM(AP40:BA40)
B42: UNITS SOLD — and what stopped us selling more, month by month
B43: UNITS SOLD | C43: units | F43: =ROUND(MIN(F19,F11,F32,F40),0) | G43: =ROUND(MIN(G19,G11,G32,G40),0) | H43: =ROUND(MIN(H19,H11,H32,H40),0) | I43: =ROUND(MIN(I19,I11,I32,I40),0) | J43: =ROUND(MIN(J19,J11,J32,J40),0) | K43: =ROUND(MIN(K19,K11,K32,K40),0) | L43: =ROUND(MIN(L19,L11,L32,L40),0) | M43: =ROUND(MIN(M19,M11,M32,M40),0) | ... BA43: =ROUND(MIN(BA19,BA11,BA32,BA40),0) | BC43: =SUM(F43:Q43) | BD43: =SUM(R43:AC43) | BE43: =SUM(AD43:AO43) | BF43: =SUM(AP43:BA43) | BH43: we sell the smallest of: what people want, what the market allows, what we can sell, what we can build
B44: Why we did not sell more | F44: =IF(F43>=F40-0.5,"Build capacity",IF(F43>=F32-0.5,"Sales capacity",IF(F43>=F11-0.5,"Market ceiling","Demand"))) | G44: =IF(G43>=G40-0.5,"Build capacity",IF(G43>=G32-0.5,"Sales capacity",IF(G43>=G11-0.5,"Market ceiling","Demand"))) | H44: =IF(H43>=H40-0.5,"Build capacity",IF(H43>=H32-0.5,"Sales capacity",IF(H43>=H11-0.5,"Market ceiling","Demand"))) | I44: =IF(I43>=I40-0.5,"Build capacity",IF(I43>=I32-0.5,"Sales capacity",IF(I43>=I11-0.5,"Market ceiling","Demand"))) | J44: =IF(J43>=J40-0.5,"Build capacity",IF(J43>=J32-0.5,"Sales capacity",IF(J43>=J11-0.5,"Market ceiling","Demand"))) | K44: =IF(K43>=K40-0.5,"Build capacity",IF(K43>=K32-0.5,"Sales capacity",IF(K43>=K11-0.5,"Market ceiling","Demand"))) | L44: =IF(L43>=L40-0.5,"Build capacity",IF(L43>=L32-0.5,"Sales capacity",IF(L43>=L11-0.5,"Market ceiling","Demand"))) | M44: =IF(M43>=M40-0.5,"Build capacity",IF(M43>=M32-0.5,"Sales capacity",IF(M43>=M11-0.5,"Market ceiling","Demand"))) | ... BA44: =IF(BA43>=BA40-0.5,"Build capacity",IF(BA43>=BA32-0.5,"Sales capacity",IF(BA43>=BA11-0.5,"Market ceiling","Demand")))
B45: Build capacity utilisation | C45: % | F45: =IFERROR(F43/F40,0) | G45: =IFERROR(G43/G40,0) | H45: =IFERROR(H43/H40,0) | I45: =IFERROR(I43/I40,0) | J45: =IFERROR(J43/J40,0) | K45: =IFERROR(K43/K40,0) | L45: =IFERROR(L43/L40,0) | M45: =IFERROR(M43/M40,0) | ... BA45: =IFERROR(BA43/BA40,0) | BC45: =AVERAGE(F45:Q45) | BD45: =AVERAGE(R45:AC45) | BE45: =AVERAGE(AD45:AO45) | BF45: =AVERAGE(AP45:BA45)
B46: Installed base, end of month | C46: units | F46: =F15+F43 | G46: =G15+G43 | H46: =H15+H43 | I46: =I15+I43 | J46: =J15+J43 | K46: =K15+K43 | L46: =L15+L43 | M46: =M15+M43 | ... BA46: =BA15+BA43 | BC46: =Q46 | BD46: =AC46 | BE46: =AO46 | BF46: =BA46
B47: CONSEQUENCES — market share, installed base, and the org the plan needs
B48: Implied share of serviceable market | C48: % | F48: =IFERROR(F43/F10,0) | G48: =IFERROR(G43/G10,0) | H48: =IFERROR(H43/H10,0) | I48: =IFERROR(I43/I10,0) | J48: =IFERROR(J43/J10,0) | K48: =IFERROR(K43/K10,0) | L48: =IFERROR(L43/L10,0) | M48: =IFERROR(M43/M10,0) | ... BA48: =IFERROR(BA43/BA10,0) | BC48: =AVERAGE(F48:Q48) | BD48: =AVERAGE(R48:AC48) | BE48: =AVERAGE(AD48:AO48) | BF48: =AVERAGE(AP48:BA48) | BH48: the first number a VC computes — kept on the face of the model
B49: Service technicians implied | C49: FTE | F49: =ROUNDUP(F46*(Assumptions!$E$117+Assumptions!$E$118)/Assumptions!$F$181,0) | G49: =ROUNDUP(G46*(Assumptions!$E$117+Assumptions!$E$118)/Assumptions!$F$181,0) | H49: =ROUNDUP(H46*(Assumptions!$E$117+Assumptions!$E$118)/Assumptions!$F$181,0) | I49: =ROUNDUP(I46*(Assumptions!$E$117+Assumptions!$E$118)/Assumptions!$F$181,0) | J49: =ROUNDUP(J46*(Assumptions!$E$117+Assumptions!$E$118)/Assumptions!$F$181,0) | K49: =ROUNDUP(K46*(Assumptions!$E$117+Assumptions!$E$118)/Assumptions!$F$181,0) | L49: =ROUNDUP(L46*(Assumptions!$E$117+Assumptions!$E$118)/Assumptions!$F$181,0) | M49: =ROUNDUP(M46*(Assumptions!$E$117+Assumptions!$E$118)/Assumptions!$F$181,0) | ... BA49: =ROUNDUP(BA46*(Assumptions!$E$117+Assumptions!$E$118)/Assumptions!$F$181,0) | BC49: =Q49 | BD49: =AC49 | BE49: =AO49 | BF49: =BA49 | BH49: check only — field labour is already inside the ~50% service COGS, so it is not charged twice
B56: ORGANISATION — the people this plan actually needs
B57: Sales reps | C57: FTE | F57: =F25 | G57: =G25 | H57: =H25 | I57: =I25 | J57: =J25 | K57: =K25 | L57: =L25 | M57: =M25 | ... BA57: =BA25 | BC57: =Q57 | BD57: =AC57 | BE57: =AO57 | BF57: =BA57
B58: Partner managers | C58: FTE | F58: =F33 | G58: =G33 | H58: =H33 | I58: =I33 | J58: =J33 | K58: =K33 | L58: =L33 | M58: =M33 | ... BA58: =BA33 | BC58: =Q58 | BD58: =AC58 | BE58: =AO58 | BF58: =BA58
B59: Installer trainers | C59: FTE | F59: =ROUNDUP(F28*12/Assumptions!$F$188,0) | G59: =ROUNDUP(G28*12/Assumptions!$F$188,0) | H59: =ROUNDUP(H28*12/Assumptions!$F$188,0) | I59: =ROUNDUP(I28*12/Assumptions!$F$188,0) | J59: =ROUNDUP(J28*12/Assumptions!$F$188,0) | K59: =ROUNDUP(K28*12/Assumptions!$F$188,0) | L59: =ROUNDUP(L28*12/Assumptions!$F$188,0) | M59: =ROUNDUP(M28*12/Assumptions!$F$188,0) | ... BA59: =ROUNDUP(BA28*12/Assumptions!$F$188,0) | BC59: =Q59 | BD59: =AC59 | BE59: =AO59 | BF59: =BA59 | BH59: 290 installer partners have to be trained and certified before they can sell anything
B60: Order desk / sales ops | C60: FTE | F60: =ROUNDUP(F43*12/Assumptions!$F$189,0) | G60: =ROUNDUP(G43*12/Assumptions!$F$189,0) | H60: =ROUNDUP(H43*12/Assumptions!$F$189,0) | I60: =ROUNDUP(I43*12/Assumptions!$F$189,0) | J60: =ROUNDUP(J43*12/Assumptions!$F$189,0) | K60: =ROUNDUP(K43*12/Assumptions!$F$189,0) | L60: =ROUNDUP(L43*12/Assumptions!$F$189,0) | M60: =ROUNDUP(M43*12/Assumptions!$F$189,0) | ... BA60: =ROUNDUP(BA43*12/Assumptions!$F$189,0) | BC60: =Q60 | BD60: =AC60 | BE60: =AO60 | BF60: =BA60
B61: Marketing team | C61: FTE | F61: =2+ROUNDUP(F14*12/Assumptions!$F$190,0) | G61: =2+ROUNDUP(G14*12/Assumptions!$F$190,0) | H61: =2+ROUNDUP(H14*12/Assumptions!$F$190,0) | I61: =2+ROUNDUP(I14*12/Assumptions!$F$190,0) | J61: =2+ROUNDUP(J14*12/Assumptions!$F$190,0) | K61: =2+ROUNDUP(K14*12/Assumptions!$F$190,0) | L61: =2+ROUNDUP(L14*12/Assumptions!$F$190,0) | M61: =2+ROUNDUP(M14*12/Assumptions!$F$190,0) | ... BA61: =2+ROUNDUP(BA14*12/Assumptions!$F$190,0) | BC61: =Q61 | BD61: =AC61 | BE61: =AO61 | BF61: =BA61
B62: Commercial team (S&M) | C62: FTE | F62: =SUM(F57:F61) | G62: =SUM(G57:G61) | H62: =SUM(H57:H61) | I62: =SUM(I57:I61) | J62: =SUM(J57:J61) | K62: =SUM(K57:K61) | L62: =SUM(L57:L61) | M62: =SUM(M57:M61) | ... BA62: =SUM(BA57:BA61) | BC62: =Q62 | BD62: =AC62 | BE62: =AO62 | BF62: =BA62
B63: Supply chain, planning & logistics | C63: FTE | F63: =ROUNDUP(F43*12/Assumptions!$F$184,0) | G63: =ROUNDUP(G43*12/Assumptions!$F$184,0) | H63: =ROUNDUP(H43*12/Assumptions!$F$184,0) | I63: =ROUNDUP(I43*12/Assumptions!$F$184,0) | J63: =ROUNDUP(J43*12/Assumptions!$F$184,0) | K63: =ROUNDUP(K43*12/Assumptions!$F$184,0) | L63: =ROUNDUP(L43*12/Assumptions!$F$184,0) | M63: =ROUNDUP(M43*12/Assumptions!$F$184,0) | ... BA63: =ROUNDUP(BA43*12/Assumptions!$F$184,0) | BC63: =Q63 | BD63: =AC63 | BE63: =AO63 | BF63: =BA63 | BH63: someone has to buy, plan and move EUR114m of components a year
B64: Production operators | C64: FTE | F64: =F38*Assumptions!$F$185 | G64: =G38*Assumptions!$F$185 | H64: =H38*Assumptions!$F$185 | I64: =I38*Assumptions!$F$185 | J64: =J38*Assumptions!$F$185 | K64: =K38*Assumptions!$F$185 | L64: =L38*Assumptions!$F$185 | M64: =M38*Assumptions!$F$185 | ... BA64: =BA38*Assumptions!$F$185 | BC64: =Q64 | BD64: =AC64 | BE64: =AO64 | BF64: =BA64
B65: Customer support | C65: FTE | F65: =ROUNDUP(F46/Assumptions!$F$186,0) | G65: =ROUNDUP(G46/Assumptions!$F$186,0) | H65: =ROUNDUP(H46/Assumptions!$F$186,0) | I65: =ROUNDUP(I46/Assumptions!$F$186,0) | J65: =ROUNDUP(J46/Assumptions!$F$186,0) | K65: =ROUNDUP(K46/Assumptions!$F$186,0) | L65: =ROUNDUP(L46/Assumptions!$F$186,0) | M65: =ROUNDUP(M46/Assumptions!$F$186,0) | ... BA65: =ROUNDUP(BA46/Assumptions!$F$186,0) | BC65: =Q65 | BD65: =AC65 | BE65: =AO65 | BF65: =BA65 | BH65: inbound calls scale with the installed base, not with sales
B66: Technical escalation | C66: FTE | F66: =ROUNDUP(F46/Assumptions!$F$187,0) | G66: =ROUNDUP(G46/Assumptions!$F$187,0) | H66: =ROUNDUP(H46/Assumptions!$F$187,0) | I66: =ROUNDUP(I46/Assumptions!$F$187,0) | J66: =ROUNDUP(J46/Assumptions!$F$187,0) | K66: =ROUNDUP(K46/Assumptions!$F$187,0) | L66: =ROUNDUP(L46/Assumptions!$F$187,0) | M66: =ROUNDUP(M46/Assumptions!$F$187,0) | ... BA66: =ROUNDUP(BA46/Assumptions!$F$187,0) | BC66: =Q66 | BD66: =AC66 | BE66: =AO66 | BF66: =BA66
B67: Quality & certification | C67: FTE | F67: =Assumptions!$F$191+Assumptions!$F$192*(1+IF(YEAR(F$5)>=Assumptions!$F$137,2,0))-Assumptions!$F$192 | G67: =Assumptions!$F$191+Assumptions!$F$192*(1+IF(YEAR(G$5)>=Assumptions!$F$137,2,0))-Assumptions!$F$192 | H67: =Assumptions!$F$191+Assumptions!$F$192*(1+IF(YEAR(H$5)>=Assumptions!$F$137,2,0))-Assumptions!$F$192 | I67: =Assumptions!$F$191+Assumptions!$F$192*(1+IF(YEAR(I$5)>=Assumptions!$F$137,2,0))-Assumptions!$F$192 | J67: =Assumptions!$F$191+Assumptions!$F$192*(1+IF(YEAR(J$5)>=Assumptions!$F$137,2,0))-Assumptions!$F$192 | K67: =Assumptions!$F$191+Assumptions!$F$192*(1+IF(YEAR(K$5)>=Assumptions!$F$137,2,0))-Assumptions!$F$192 | L67: =Assumptions!$F$191+Assumptions!$F$192*(1+IF(YEAR(L$5)>=Assumptions!$F$137,2,0))-Assumptions!$F$192 | M67: =Assumptions!$F$191+Assumptions!$F$192*(1+IF(YEAR(M$5)>=Assumptions!$F$137,2,0))-Assumptions!$F$192 | ... BA67: =Assumptions!$F$191+Assumptions!$F$192*(1+IF(YEAR(BA$5)>=Assumptions!$F$137,2,0))-Assumptions!$F$192 | BC67: =Q67 | BD67: =AC67 | BE67: =AO67 | BF67: =BA67 | BH67: every new country needs its own certification work
B68: R&D — from the Personnel roster | C68: FTE | F68: =Personnel!AG257 | G68: =Personnel!AH257 | H68: =Personnel!AI257 | I68: =Personnel!AJ257 | J68: =Personnel!AK257 | K68: =Personnel!AL257 | L68: =Personnel!AM257 | M68: =Personnel!AN257 | ... AO68: =Personnel!BP257 | AP68: =Personnel!BP257 | AQ68: =Personnel!BP257 | AR68: =Personnel!BP257 | AS68: =Personnel!BP257 | AT68: =Personnel!BP257 | AU68: =Personnel!BP257 | AV68: =Personnel!BP257 | AW68: =Personnel!BP257 | AX68: =Personnel!BP257 | AY68: =Personnel!BP257 | AZ68: =Personnel!BP257 | BA68: =Personnel!BP257 | BC68: =Q68 | BD68: =AC68 | BE68: =AO68 | BF68: =BA68 | BH68: a novel turbine product, the Twincycle, and certification for two new countries
B69: G&A — finance, HR, IT, legal, office | C69: FTE | F69: =ROUNDUP((F62+SUM(F63:F67)+F68)/Assumptions!$F$193,0) | G69: =ROUNDUP((G62+SUM(G63:G67)+G68)/Assumptions!$F$193,0) | H69: =ROUNDUP((H62+SUM(H63:H67)+H68)/Assumptions!$F$193,0) | I69: =ROUNDUP((I62+SUM(I63:I67)+I68)/Assumptions!$F$193,0) | J69: =ROUNDUP((J62+SUM(J63:J67)+J68)/Assumptions!$F$193,0) | K69: =ROUNDUP((K62+SUM(K63:K67)+K68)/Assumptions!$F$193,0) | L69: =ROUNDUP((L62+SUM(L63:L67)+L68)/Assumptions!$F$193,0) | M69: =ROUNDUP((M62+SUM(M63:M67)+M68)/Assumptions!$F$193,0) | ... BA69: =ROUNDUP((BA62+SUM(BA63:BA67)+BA68)/Assumptions!$F$193,0) | BC69: =Q69 | BD69: =AC69 | BE69: =AO69 | BF69: =BA69
B70: Operations, support & G&A | C70: FTE | F70: =SUM(F63:F67)+F69 | G70: =SUM(G63:G67)+G69 | H70: =SUM(H63:H67)+H69 | I70: =SUM(I63:I67)+I69 | J70: =SUM(J63:J67)+J69 | K70: =SUM(K63:K67)+K69 | L70: =SUM(L63:L67)+L69 | M70: =SUM(M63:M67)+M69 | ... BA70: =SUM(BA63:BA67)+BA69 | BC70: =Q70 | BD70: =AC70 | BE70: =AO70 | BF70: =BA70
B71: TOTAL PEOPLE ON PAYROLL | C71: FTE | F71: =F62+F70+F68 | G71: =G62+G70+G68 | H71: =H62+H70+H68 | I71: =I62+I70+I68 | J71: =J62+J70+J68 | K71: =K62+K70+K68 | L71: =L62+L70+L68 | M71: =M62+M70+M68 | ... BA71: =BA62+BA70+BA68 | BC71: =Q71 | BD71: =AC71 | BE71: =AO71 | BF71: =BA71
B72: Field service technicians | C72: FTE | F72: =F49 | G72: =G49 | H72: =H49 | I72: =I49 | J72: =J49 | K72: =K49 | L72: =L49 | M72: =M49 | ... BA72: =BA49 | BC72: =Q72 | BD72: =AC72 | BE72: =AO72 | BF72: =BA72 | BH72: counted here but NOT charged again — their cost is already inside the ~50% service COGS
B73: TOTAL HEADCOUNT | C73: FTE | F73: =F71+F72 | G73: =G71+G72 | H73: =H71+H72 | I73: =I71+I72 | J73: =J71+J72 | K73: =K71+K72 | L73: =L71+L72 | M73: =M71+M72 | ... BA73: =BA71+BA72 | BC73: =Q73 | BD73: =AC73 | BE73: =AO73 | BF73: =BA73
B74: People in the Personnel tab today | C74: FTE | F74: =Personnel!AG260 | G74: =Personnel!AH260 | H74: =Personnel!AI260 | I74: =Personnel!AJ260 | J74: =Personnel!AK260 | K74: =Personnel!AL260 | L74: =Personnel!AM260 | M74: =Personnel!AN260 | ... AO74: =Personnel!BP260 | AP74: =Personnel!BP260 | AQ74: =Personnel!BP260 | AR74: =Personnel!BP260 | AS74: =Personnel!BP260 | AT74: =Personnel!BP260 | AU74: =Personnel!BP260 | AV74: =Personnel!BP260 | AW74: =Personnel!BP260 | AX74: =Personnel!BP260 | AY74: =Personnel!BP260 | AZ74: =Personnel!BP260 | BA74: =Personnel!BP260 | BC74: =Q74 | BD74: =AC74 | BE74: =AO74 | BF74: =BA74
B75: Extra people the plan needs | C75: FTE | F75: =MAX(0,F71-F74) | G75: =MAX(0,G71-G74) | H75: =MAX(0,H71-H74) | I75: =MAX(0,I71-I74) | J75: =MAX(0,J71-J74) | K75: =MAX(0,K71-K74) | L75: =MAX(0,L71-L74) | M75: =MAX(0,M71-M74) | ... BA75: =MAX(0,BA71-BA74) | BC75: =Q75 | BD75: =AC75 | BE75: =AO75 | BF75: =BA75 | BH75: should now be at or near zero: the people are in the Personnel tab. Anything left is a genuine gap between the plan and the roster.
B77: COST — what that organisation costs, on top of the roster
B78: Commercial team cost required | C78: check | F78: =F57*Assumptions!$F$169+F58*Assumptions!$F$170+(F59+F60+F61)*Assumptions!$F$195 | G78: =G57*Assumptions!$F$169+G58*Assumptions!$F$170+(G59+G60+G61)*Assumptions!$F$195 | H78: =H57*Assumptions!$F$169+H58*Assumptions!$F$170+(H59+H60+H61)*Assumptions!$F$195 | I78: =I57*Assumptions!$F$169+I58*Assumptions!$F$170+(I59+I60+I61)*Assumptions!$F$195 | J78: =J57*Assumptions!$F$169+J58*Assumptions!$F$170+(J59+J60+J61)*Assumptions!$F$195 | K78: =K57*Assumptions!$F$169+K58*Assumptions!$F$170+(K59+K60+K61)*Assumptions!$F$195 | L78: =L57*Assumptions!$F$169+L58*Assumptions!$F$170+(L59+L60+L61)*Assumptions!$F$195 | M78: =M57*Assumptions!$F$169+M58*Assumptions!$F$170+(M59+M60+M61)*Assumptions!$F$195 | ... BA78: =BA57*Assumptions!$F$169+BA58*Assumptions!$F$170+(BA59+BA60+BA61)*Assumptions!$F$195 | BC78: =SUM(F78:Q78) | BD78: =SUM(R78:AC78) | BE78: =SUM(AD78:AO78) | BF78: =SUM(AP78:BA78) | BH78: required vs roster — a check on the Personnel tab, not a cost
B79: S&M cost already in the roster | C79: check | F79: =Personnel!AG252 | G79: =Personnel!AH252 | H79: =Personnel!AI252 | I79: =Personnel!AJ252 | J79: =Personnel!AK252 | K79: =Personnel!AL252 | L79: =Personnel!AM252 | M79: =Personnel!AN252 | ... AO79: =Personnel!BP252 | AP79: =Personnel!BP252 | AQ79: =Personnel!BP252 | AR79: =Personnel!BP252 | AS79: =Personnel!BP252 | AT79: =Personnel!BP252 | AU79: =Personnel!BP252 | AV79: =Personnel!BP252 | AW79: =Personnel!BP252 | AX79: =Personnel!BP252 | AY79: =Personnel!BP252 | AZ79: =Personnel!BP252 | BA79: =Personnel!BP252 | BC79: =SUM(F79:Q79) | BD79: =SUM(R79:AC79) | BE79: =SUM(AD79:AO79) | BF79: =SUM(AP79:BA79)
B80: S&M people — required vs roster (check only) | C80: check | F80: =MAX(0,F78-F79) | G80: =MAX(0,G78-G79) | H80: =MAX(0,H78-H79) | I80: =MAX(0,I78-I79) | J80: =MAX(0,J78-J79) | K80: =MAX(0,K78-K79) | L80: =MAX(0,L78-L79) | M80: =MAX(0,M78-M79) | ... BA80: =MAX(0,BA78-BA79) | BC80: =SUM(F80:Q80) | BD80: =SUM(R80:AC80) | BE80: =SUM(AD80:AO80) | BF80: =SUM(AP80:BA80)
B81: Operations, support & G&A cost required | C81: check | F81: =(F63+F64)*Assumptions!$F$196+(F65+F66)*Assumptions!$F$197+(F67+F69)*Assumptions!$F$198 | G81: =(G63+G64)*Assumptions!$F$196+(G65+G66)*Assumptions!$F$197+(G67+G69)*Assumptions!$F$198 | H81: =(H63+H64)*Assumptions!$F$196+(H65+H66)*Assumptions!$F$197+(H67+H69)*Assumptions!$F$198 | I81: =(I63+I64)*Assumptions!$F$196+(I65+I66)*Assumptions!$F$197+(I67+I69)*Assumptions!$F$198 | J81: =(J63+J64)*Assumptions!$F$196+(J65+J66)*Assumptions!$F$197+(J67+J69)*Assumptions!$F$198 | K81: =(K63+K64)*Assumptions!$F$196+(K65+K66)*Assumptions!$F$197+(K67+K69)*Assumptions!$F$198 | L81: =(L63+L64)*Assumptions!$F$196+(L65+L66)*Assumptions!$F$197+(L67+L69)*Assumptions!$F$198 | M81: =(M63+M64)*Assumptions!$F$196+(M65+M66)*Assumptions!$F$197+(M67+M69)*Assumptions!$F$198 | ... BA81: =(BA63+BA64)*Assumptions!$F$196+(BA65+BA66)*Assumptions!$F$197+(BA67+BA69)*Assumptions!$F$198 | BC81: =SUM(F81:Q81) | BD81: =SUM(R81:AC81) | BE81: =SUM(AD81:AO81) | BF81: =SUM(AP81:BA81)
B82: G&A cost already in the roster | C82: check | F82: =Personnel!AG253 | G82: =Personnel!AH253 | H82: =Personnel!AI253 | I82: =Personnel!AJ253 | J82: =Personnel!AK253 | K82: =Personnel!AL253 | L82: =Personnel!AM253 | M82: =Personnel!AN253 | ... AO82: =Personnel!BP253 | AP82: =Personnel!BP253 | AQ82: =Personnel!BP253 | AR82: =Personnel!BP253 | AS82: =Personnel!BP253 | AT82: =Personnel!BP253 | AU82: =Personnel!BP253 | AV82: =Personnel!BP253 | AW82: =Personnel!BP253 | AX82: =Personnel!BP253 | AY82: =Personnel!BP253 | AZ82: =Personnel!BP253 | BA82: =Personnel!BP253 | BC82: =SUM(F82:Q82) | BD82: =SUM(R82:AC82) | BE82: =SUM(AD82:AO82) | BF82: =SUM(AP82:BA82)
B83: Ops & G&A people — required vs roster (check only) | C83: check | F83: =MAX(0,F81-F82) | G83: =MAX(0,G81-G82) | H83: =MAX(0,H81-H82) | I83: =MAX(0,I81-I82) | J83: =MAX(0,J81-J82) | K83: =MAX(0,K81-K82) | L83: =MAX(0,L81-L82) | M83: =MAX(0,M81-M82) | ... BA83: =MAX(0,BA81-BA82) | BC83: =SUM(F83:Q83) | BD83: =SUM(R83:AC83) | BE83: =SUM(AD83:AO83) | BF83: =SUM(AP83:BA83)
B84: Facilities, IT & travel | C84: EUR/mo | F84: =F71*(Assumptions!$F$200+Assumptions!$F$201+Assumptions!$F$202) | G84: =G71*(Assumptions!$F$200+Assumptions!$F$201+Assumptions!$F$202) | H84: =H71*(Assumptions!$F$200+Assumptions!$F$201+Assumptions!$F$202) | I84: =I71*(Assumptions!$F$200+Assumptions!$F$201+Assumptions!$F$202) | J84: =J71*(Assumptions!$F$200+Assumptions!$F$201+Assumptions!$F$202) | K84: =K71*(Assumptions!$F$200+Assumptions!$F$201+Assumptions!$F$202) | L84: =L71*(Assumptions!$F$200+Assumptions!$F$201+Assumptions!$F$202) | M84: =M71*(Assumptions!$F$200+Assumptions!$F$201+Assumptions!$F$202) | ... BA84: =BA71*(Assumptions!$F$200+Assumptions!$F$201+Assumptions!$F$202) | BC84: =SUM(F84:Q84) | BD84: =SUM(R84:AC84) | BE84: =SUM(AD84:AO84) | BF84: =SUM(AP84:BA84)
B85: Recruitment | C85: EUR/mo | F85: =0 | G85: =MAX(0,G71-F71)*Assumptions!$F$203 | H85: =MAX(0,H71-G71)*Assumptions!$F$203 | I85: =MAX(0,I71-H71)*Assumptions!$F$203 | J85: =MAX(0,J71-I71)*Assumptions!$F$203 | K85: =MAX(0,K71-J71)*Assumptions!$F$203 | L85: =MAX(0,L71-K71)*Assumptions!$F$203 | M85: =MAX(0,M71-L71)*Assumptions!$F$203 | N85: =MAX(0,N71-M71)*Assumptions!$F$203 | ... BA85: =MAX(0,BA71-AZ71)*Assumptions!$F$203 | BC85: =SUM(F85:Q85) | BD85: =SUM(R85:AC85) | BE85: =SUM(AD85:AO85) | BF85: =SUM(AP85:BA85)
B86: Installer training & demo units | C86: EUR/mo | F86: =F28*Assumptions!$F$204 | G86: =G28*Assumptions!$F$204 | H86: =H28*Assumptions!$F$204 | I86: =I28*Assumptions!$F$204 | J86: =J28*Assumptions!$F$204 | K86: =K28*Assumptions!$F$204 | L86: =L28*Assumptions!$F$204 | M86: =M28*Assumptions!$F$204 | ... BA86: =BA28*Assumptions!$F$204 | BC86: =SUM(F86:Q86) | BD86: =SUM(R86:AC86) | BE86: =SUM(AD86:AO86) | BF86: =SUM(AP86:BA86)
B87: In-house line facility & maintenance | C87: EUR/mo | F87: =F38*Assumptions!$F$179 | G87: =G38*Assumptions!$F$179 | H87: =H38*Assumptions!$F$179 | I87: =I38*Assumptions!$F$179 | J87: =J38*Assumptions!$F$179 | K87: =K38*Assumptions!$F$179 | L87: =L38*Assumptions!$F$179 | M87: =M38*Assumptions!$F$179 | ... BA87: =BA38*Assumptions!$F$179 | BC87: =SUM(F87:Q87) | BD87: =SUM(R87:AC87) | BE87: =SUM(AD87:AO87) | BF87: =SUM(AP87:BA87)
B88: Entering a new country | C88: EUR/mo | F88: =IF(AND(YEAR(F$5)=Assumptions!$F$137,MONTH(F$5)=1),Assumptions!$F$206*2,0) | G88: =IF(AND(YEAR(G$5)=Assumptions!$F$137,MONTH(G$5)=1),Assumptions!$F$206*2,0) | H88: =IF(AND(YEAR(H$5)=Assumptions!$F$137,MONTH(H$5)=1),Assumptions!$F$206*2,0) | I88: =IF(AND(YEAR(I$5)=Assumptions!$F$137,MONTH(I$5)=1),Assumptions!$F$206*2,0) | J88: =IF(AND(YEAR(J$5)=Assumptions!$F$137,MONTH(J$5)=1),Assumptions!$F$206*2,0) | K88: =IF(AND(YEAR(K$5)=Assumptions!$F$137,MONTH(K$5)=1),Assumptions!$F$206*2,0) | L88: =IF(AND(YEAR(L$5)=Assumptions!$F$137,MONTH(L$5)=1),Assumptions!$F$206*2,0) | M88: =IF(AND(YEAR(M$5)=Assumptions!$F$137,MONTH(M$5)=1),Assumptions!$F$206*2,0) | ... BA88: =IF(AND(YEAR(BA$5)=Assumptions!$F$137,MONTH(BA$5)=1),Assumptions!$F$206*2,0) | BC88: =SUM(F88:Q88) | BD88: =SUM(R88:AC88) | BE88: =SUM(AD88:AO88) | BF88: =SUM(AP88:BA88)
B89: R&D engineers — now hired in the Personnel tab (check only) | C89: EUR/mo | F89: =(IF(YEAR(F$5)=2027,Assumptions!$F$208,IF(YEAR(F$5)=2028,Assumptions!$F$209,IF(YEAR(F$5)=2029,Assumptions!$F$210,Assumptions!$F$211))))*Assumptions!$F$207 | G89: =(IF(YEAR(G$5)=2027,Assumptions!$F$208,IF(YEAR(G$5)=2028,Assumptions!$F$209,IF(YEAR(G$5)=2029,Assumptions!$F$210,Assumptions!$F$211))))*Assumptions!$F$207 | H89: =(IF(YEAR(H$5)=2027,Assumptions!$F$208,IF(YEAR(H$5)=2028,Assumptions!$F$209,IF(YEAR(H$5)=2029,Assumptions!$F$210,Assumptions!$F$211))))*Assumptions!$F$207 | I89: =(IF(YEAR(I$5)=2027,Assumptions!$F$208,IF(YEAR(I$5)=2028,Assumptions!$F$209,IF(YEAR(I$5)=2029,Assumptions!$F$210,Assumptions!$F$211))))*Assumptions!$F$207 | J89: =(IF(YEAR(J$5)=2027,Assumptions!$F$208,IF(YEAR(J$5)=2028,Assumptions!$F$209,IF(YEAR(J$5)=2029,Assumptions!$F$210,Assumptions!$F$211))))*Assumptions!$F$207 | K89: =(IF(YEAR(K$5)=2027,Assumptions!$F$208,IF(YEAR(K$5)=2028,Assumptions!$F$209,IF(YEAR(K$5)=2029,Assumptions!$F$210,Assumptions!$F$211))))*Assumptions!$F$207 | L89: =(IF(YEAR(L$5)=2027,Assumptions!$F$208,IF(YEAR(L$5)=2028,Assumptions!$F$209,IF(YEAR(L$5)=2029,Assumptions!$F$210,Assumptions!$F$211))))*Assumptions!$F$207 | M89: =(IF(YEAR(M$5)=2027,Assumptions!$F$208,IF(YEAR(M$5)=2028,Assumptions!$F$209,IF(YEAR(M$5)=2029,Assumptions!$F$210,Assumptions!$F$211))))*Assumptions!$F$207 | ... BA89: =(IF(YEAR(BA$5)=2027,Assumptions!$F$208,IF(YEAR(BA$5)=2028,Assumptions!$F$209,IF(YEAR(BA$5)=2029,Assumptions!$F$210,Assumptions!$F$211))))*Assumptions!$F$207 | BC89: =SUM(F89:Q89) | BD89: =SUM(R89:AC89) | BE89: =SUM(AD89:AO89) | BF89: =SUM(AP89:BA89)
B90: TOTAL EXTRA NON-PEOPLE COST | C90: EUR/mo | F90: =F84+F85+F86+F87+F88 | G90: =G84+G85+G86+G87+G88 | H90: =H84+H85+H86+H87+H88 | I90: =I84+I85+I86+I87+I88 | J90: =J84+J85+J86+J87+J88 | K90: =K84+K85+K86+K87+K88 | L90: =L84+L85+L86+L87+L88 | M90: =M84+M85+M86+M87+M88 | ... BA90: =BA84+BA85+BA86+BA87+BA88 | BC90: =BC84+BC85+BC86+BC87+BC88 | BD90: =BD84+BD85+BD86+BD87+BD88 | BE90: =BE84+BE85+BE86+BE87+BE88 | BF90: =BF84+BF85+BF86+BF87+BF88 | BH90: people are costed in the Personnel tab; only these overheads are added here
B91: Warranty reserve above the BOM (goes to COGS) | C91: EUR/mo | F91: =F43*Assumptions!$F$205 | G91: =G43*Assumptions!$F$205 | H91: =H43*Assumptions!$F$205 | I91: =I43*Assumptions!$F$205 | J91: =J43*Assumptions!$F$205 | K91: =K43*Assumptions!$F$205 | L91: =L43*Assumptions!$F$205 | M91: =M43*Assumptions!$F$205 | ... BA91: =BA43*Assumptions!$F$205 | BC91: =SUM(F91:Q91) | BD91: =SUM(R91:AC91) | BE91: =SUM(AD91:AO91) | BF91: =SUM(AP91:BA91) | BH91: the BOM already carries a 3% yield/warranty provision; this is the reserve on top

Sheet Financial Statements
B1: Tarnoc B.V. — Financial Statements (€)
E2: 2025 | Q2: 2026 | AC2: 2027 | AO2: 2028
E3: 45658 | F3: 45689 | G3: 45717 | H3: 45748 | I3: 45778 | J3: 45809 | K3: 45839 | L3: 45870 | M3: 45901 | N3: 45931 | O3: 45962 | P3: 45992 | Q3: 46023 | R3: 46054 | S3: 46082 | T3: 46113 | U3: 46143 | V3: 46174 | W3: 46204 | X3: 46235 | Y3: 46266 | Z3: 46296 | AA3: 46327 | AB3: 46357 | AC3: 46388 | AD3: 46419 | AE3: 46447 | AF3: 46478 | AG3: 46508 | AH3: 46539 | AI3: 46569 | AJ3: 46600 | AK3: 46631 | AL3: 46661 | AM3: 46692 | AN3: 46722 | AO3: 46753 | AP3: 46784 | AQ3: 46813 | AR3: 46844 | AS3: 46874 | AT3: 46905 | AU3: 46935 | AV3: 46966 | AW3: 46997 | AX3: 47027 | AY3: 47058 | AZ3: 47088 | BB3: 2025 | BC3: 2026 | BD3: 2027 | BE3: 2028 | BF3: 2029 | BH3: what this row does
B5: PROFIT & LOSS STATEMENT
B6: Revenues
B7: TTK | D7: € | M7: ='Revenue Forecast'!M9 | N7: ='Revenue Forecast'!N9 | O7: ='Revenue Forecast'!O9 | P7: ='Revenue Forecast'!P9 | Q7: ='Revenue Forecast'!Q9 | R7: ='Revenue Forecast'!R9 | S7: ='Revenue Forecast'!S9 | T7: ='Revenue Forecast'!T9 | ... AZ7: ='Revenue Forecast'!AZ9 | BB7: =sum(E7:P7) | BC7: =sum(Q7:AB7) | BD7: =sum(AC7:AN7) | BE7: =sum(AO7:AZ7) | BF7: ='Revenue Forecast'!BF9 | BH7: TTK revenue, pulled from the Revenue Forecast
B8: Combi+ | D8: € | Q8: ='Revenue Forecast'!Q15 | R8: ='Revenue Forecast'!R15 | S8: ='Revenue Forecast'!S15 | T8: ='Revenue Forecast'!T15 | U8: ='Revenue Forecast'!U15 | V8: ='Revenue Forecast'!V15 | W8: ='Revenue Forecast'!W15 | X8: ='Revenue Forecast'!X15 | ... AZ8: ='Revenue Forecast'!AZ15 | BB8: ='Revenue Forecast'!BB15 | BC8: ='Revenue Forecast'!BC15 | BD8: ='Revenue Forecast'!BD15 | BE8: ='Revenue Forecast'!BE15 | BF8: ='Revenue Forecast'!BF15 | BH8: Combi+ revenue, pulled from the Revenue Forecast
B9: Other | D9: € | M9: ='Revenue Forecast'!M19+'Revenue Forecast'!M24 | N9: ='Revenue Forecast'!N19+'Revenue Forecast'!N24 | O9: ='Revenue Forecast'!O19+'Revenue Forecast'!O24 | P9: ='Revenue Forecast'!P19+'Revenue Forecast'!P24 | Q9: ='Revenue Forecast'!Q19+'Revenue Forecast'!Q24 | R9: ='Revenue Forecast'!R19+'Revenue Forecast'!R24 | S9: ='Revenue Forecast'!S19+'Revenue Forecast'!S24 | T9: ='Revenue Forecast'!T19+'Revenue Forecast'!T24 | ... AZ9: ='Revenue Forecast'!AZ19+'Revenue Forecast'!AZ24 | BB9: =sum(E9:P9) | BC9: =sum(Q9:AB9) | BD9: =sum(AC9:AN9) | BE9: =sum(AO9:AZ9) | BF9: ='Revenue Forecast'!BF19+'Revenue Forecast'!BF24 | BH9: installation + service revenue from the Revenue Forecast
B10: Subsidies & grants | D10: € | M10: ='Revenue Forecast'!M28 | N10: ='Revenue Forecast'!N28 | O10: ='Revenue Forecast'!O28 | P10: ='Revenue Forecast'!P28 | Q10: ='Revenue Forecast'!Q28 | R10: ='Revenue Forecast'!R28 | S10: ='Revenue Forecast'!S28 | T10: 0 | U10: ='Revenue Forecast'!U28 | V10: ='Revenue Forecast'!V28 | W10: ='Revenue Forecast'!W28 | X10: ='Revenue Forecast'!X28 | Y10: ='Revenue Forecast'!Y28 | Z10: ='Revenue Forecast'!Z28 | AA10: ='Revenue Forecast'!AA28 | AB10: ='Revenue Forecast'!AB28 | ... AZ10: ='Revenue Forecast'!AZ28 | BB10: =sum(E10:P10) | BC10: =sum(Q10:AB10) | BD10: pm | BE10: pm | BF10: pm | BH10: subsidies from the Revenue Forecast. nothing budgeted
B11: Total Revenue | D11: € | M11: ='Revenue Forecast'!M30 | N11: ='Revenue Forecast'!N30 | O11: ='Revenue Forecast'!O30 | P11: ='Revenue Forecast'!P30 | Q11: ='Revenue Forecast'!Q30 | R11: ='Revenue Forecast'!R30 | S11: ='Revenue Forecast'!S30 | T11: ='Revenue Forecast'!T30 | ... AZ11: ='Revenue Forecast'!AZ30 | BB11: =sum(E11:P11) | BC11: =sum(Q11:AB11) | BD11: =sum(AC11:AN11) | BE11: =sum(AO11:AZ11) | BF11: =sum(BF7:BF10) | BH11: all the revenue lines added
B13: Cost of goods sold
B14: TTK | D14: € | E14: =COGS!E9 | F14: =COGS!F9 | G14: =COGS!G9 | H14: =COGS!H9 | I14: =COGS!I9 | J14: =COGS!J9 | K14: =COGS!K9 | L14: =COGS!L9 | ... AZ14: =COGS!AZ9 | BB14: =sum(E14:P14) | BC14: =sum(Q14:AB14) | BD14: =sum(AC14:AN14) | BE14: =sum(AO14:AZ14) | BF14: =COGS!BF9 | BH14: TTK cost of sales, from the COGS tab
B15: Combi+ | D15: € | Q15: =COGS!Q14 | R15: =COGS!R14 | S15: =COGS!S14 | T15: =COGS!T14 | U15: =COGS!U14 | V15: =COGS!V14 | W15: =COGS!W14 | X15: =COGS!X14 | ... AZ15: =COGS!AZ14 | BB15: =COGS!BB14 | BC15: =COGS!BC14 | BD15: =COGS!BD14 | BE15: =COGS!BE14 | BF15: =COGS!BF14 | BH15: Combi+ cost of sales, from COGS
B16: Other | D16: € | E16: =COGS!E17 | F16: =COGS!F17 | G16: =COGS!G17 | H16: =COGS!H17 | I16: =COGS!I17 | J16: =COGS!J17 | K16: =COGS!K17 | L16: =COGS!L17 | ... P16: =COGS!P17 | Q16: =COGS!Q17+COGS!Q20 | R16: =COGS!R17+COGS!R20 | S16: =COGS!S17+COGS!S20 | T16: =COGS!T17+COGS!T20 | U16: =COGS!U17+COGS!U20 | V16: =COGS!V17+COGS!V20 | W16: =COGS!W17+COGS!W20 | X16: =COGS!X17+COGS!X20 | ... AZ16: =COGS!AZ17+COGS!AZ20 | BB16: =sum(E16:P16) | BC16: =sum(Q16:AB16) | BD16: =sum(AC16:AN16) | BE16: =sum(AO16:AZ16) | BF16: =COGS!BF17+COGS!BF20 | BH16: installation + service costs, from COGS
B17: Total COGS | D17: € | M17: =COGS!M22 | N17: =COGS!N22 | O17: =COGS!O22 | P17: =COGS!P22 | Q17: =COGS!Q22 | R17: =COGS!R22 | S17: =COGS!S22 | T17: =COGS!T22 | ... AZ17: =COGS!AZ22 | BB17: =sum(E17:P17) | BC17: =sum(Q17:AB17) | BD17: =sum(AC17:AN17) | BE17: =sum(AO17:AZ17) | BF17: =sum(BF14:BF16) | BH17: all the cost lines added
B19: Gross Profit
B20: TTK | D20: € | Q20: =Q7-Q14 | R20: =R7-R14 | S20: =S7-S14 | T20: =T7-T14 | U20: =U7-U14 | V20: =V7-V14 | W20: =W7-W14 | X20: =X7-X14 | ... AZ20: =AZ7-AZ14 | BC20: =BC7-BC14 | BD20: =BD7-BD14 | BE20: =BE7-BE14 | BF20: =BF7-BF14 | BH20: TTK revenue minus TTK cost
B21: Combi+ | D21: € | Q21: =Q8-Q15 | R21: =R8-R15 | S21: =S8-S15 | T21: =T8-T15 | U21: =U8-U15 | V21: =V8-V15 | W21: =W8-W15 | X21: =X8-X15 | ... AZ21: =AZ8-AZ15 | BC21: =BC8-BC15 | BD21: =BD8-BD15 | BE21: =BE8-BE15 | BF21: =BF8-BF15 | BH21: Combi+ revenue minus Combi+ cost
B22: Other | D22: € | Q22: =Q9-Q16 | R22: =R9-R16 | S22: =S9-S16 | T22: =T9-T16 | U22: =U9-U16 | V22: =V9-V16 | W22: =W9-W16 | X22: =X9-X16 | ... AZ22: =AZ9-AZ16 | BC22: =BC9-BC16 | BD22: =BD9-BD16 | BE22: =BE9-BE16 | BF22: =BF9-BF16 | BH22: installation + service revenue minus their cost
B23: Gross Profit | D23: € | M23: =M11-M17 | N23: =N11-N17 | O23: =O11-O17 | P23: =P11-P17 | Q23: =Q11-Q17 | R23: =R11-R17 | S23: =S11-S17 | T23: =T11-T17 | ... AZ23: =AZ11-AZ17 | BB23: =sum(E23:P23) | BC23: =sum(Q23:AB23) | BD23: =sum(AC23:AN23) | BE23: =sum(AO23:AZ23) | BF23: =BF11-BF17 | BH23: revenue minus cost of sales
B24: Gross margin % | D24: % | BD24: =BD23/BD11 | BE24: =BE23/BE11 | BF24: =BF23/BF11 | BH24: gross profit as a % of revenue (year columns only)
B26: Operational expenses
B27: R&D | D27: € | M27: =OPEX!O38 | N27: =OPEX!P38 | O27: =OPEX!Q38 | P27: =OPEX!R38 | Q27: =OPEX!S38 | R27: =OPEX!T38 | S27: =OPEX!U38 | T27: =OPEX!V38 | ... AZ27: =OPEX!BB38 | BB27: =sum(E27:P27) | BC27: =sum(Q27:AB27) | BD27: =sum(AC27:AN27) | BE27: =sum(AO27:AZ27) | BF27: =OPEX!BH38 | BH27: R&D spend, people and other, from OPEX
B28: S&M | D28: € | M28: =OPEX!O39 | N28: =OPEX!P39 | O28: =OPEX!Q39 | P28: =OPEX!R39 | Q28: =OPEX!S39 | R28: =OPEX!T39 | S28: =OPEX!U39 | T28: =OPEX!V39 | ... AZ28: =OPEX!BB39 | BB28: =sum(E28:P28) | BC28: =sum(Q28:AB28) | BD28: =sum(AC28:AN28) | BE28: =sum(AO28:AZ28) | BF28: =OPEX!BH39 | BH28: S&M spend from OPEX
B29: G&A | D29: € | M29: =OPEX!O40 | N29: =OPEX!P40 | O29: =OPEX!Q40 | P29: =OPEX!R40 | Q29: =OPEX!S40 | R29: =OPEX!T40 | S29: =OPEX!U40 | T29: =OPEX!V40 | ... AZ29: =OPEX!BB40 | BB29: =sum(E29:P29) | BC29: =sum(Q29:AB29) | BD29: =sum(AC29:AN29) | BE29: =sum(AO29:AZ29) | BF29: =OPEX!BH40 | BH29: G&A spend from OPEX
B30: Total OPEX | D30: € | M30: =(M29+M28+M27) | N30: =(N29+N28+N27) | O30: =(O29+O28+O27) | P30: =(P29+P28+P27) | Q30: =(Q29+Q28+Q27) | R30: =(R29+R28+R27) | S30: =(S29+S28+S27) | T30: =(T29+T28+T27) | ... AZ30: =(AZ29+AZ28+AZ27) | BB30: =sum(E30:P30) | BC30: =sum(Q30:AB30) | BD30: =sum(AC30:AN30) | BE30: =sum(AO30:AZ30) | BF30: =sum(BF27:BF29) | BH30: the three OPEX lines added
B32: EBITDA | D32: € | M32: =M23-M30 | N32: =N23-N30 | O32: =O23-O30 | P32: =P23-P30 | Q32: =Q23-Q30 | R32: =R23-R30 | S32: =S23-S30 | T32: =T23-T30 | ... AZ32: =AZ23-AZ30 | BB32: =sum(E32:P32) | BC32: =sum(Q32:AB32) | BD32: =sum(AC32:AN32) | BE32: =sum(AO32:AZ32) | BF32: =BF23-BF30 | BH32: gross profit minus operating costs
B33: EBITDA margin % | D33: % | BE33: =BE32/BE11 | BF33: =BF32/BF11 | BH33: EBITDA as a % of revenue
B35: Depreciation & Amortisation | D35: € | E35: =-SUM($E$53:E53)/(Assumptions!$D$128*12) | F35: =-SUM($E$53:F53)/(Assumptions!$D$128*12) | G35: =-SUM($E$53:G53)/(Assumptions!$D$128*12) | H35: =-SUM($E$53:H53)/(Assumptions!$D$128*12) | I35: =-SUM($E$53:I53)/(Assumptions!$D$128*12) | J35: =-SUM($E$53:J53)/(Assumptions!$D$128*12) | K35: =-SUM($E$53:K53)/(Assumptions!$D$128*12) | L35: =-SUM($E$53:L53)/(Assumptions!$D$128*12) | ... AZ35: =-SUM($E$53:AZ53)/(Assumptions!$D$128*12) | BB35: =sum(E35:P35) | BC35: =sum(Q35:AB35) | BD35: =sum(AC35:AN35) | BE35: =sum(AO35:AZ35) | BF35: =(-SUM($E$53:$AZ$53)+(-BF53)/2)/Assumptions!$D$128 | BH35: straight line on cumulative capex, blended life from Assumptions D128
B36: Interest payments | D36: € | M36: 0 | N36: 0 | O36: 0 | P36: 0 | Q36: =P82*Assumptions!$C$11/12 | R36: =Q82*Assumptions!$C$11/12 | S36: =R82*Assumptions!$C$11/12 | T36: =S82*Assumptions!$C$11/12 | U36: =T82*Assumptions!$C$11/12 | V36: =U82*Assumptions!$C$11/12 | W36: =V82*Assumptions!$C$11/12 | X36: =W82*Assumptions!$C$11/12 | ... AZ36: =AY82*Assumptions!$C$11/12 | BB36: =sum(E36:P36) | BC36: =sum(Q36:AB36) | BD36: =sum(AC36:AN36) | BE36: =sum(AO36:AZ36) | BF36: =BE82*Assumptions!$C$11/12 | BH36: interest on last month's loan balance, yearly rate divided by 12
B37: EBT | D37: € | M37: =M32-sum(M35:M36) | N37: =N32-sum(N35:N36) | O37: =O32-sum(O35:O36) | P37: =P32-sum(P35:P36) | Q37: =Q32-sum(Q35:Q36) | R37: =R32-sum(R35:R36) | S37: =S32-sum(S35:S36) | T37: =T32-sum(T35:T36) | ... AZ37: =AZ32-sum(AZ35:AZ36) | BB37: =sum(E37:P37) | BC37: =sum(Q37:AB37) | BD37: =sum(AC37:AN37) | BE37: =sum(AO37:AZ37) | BF37: =BF32-sum(BF35:BF36) | BH37: EBITDA minus depreciation and interest
BE38: =BE37/BE11 | BF38: =BF37/BF11 | BH38: profit before tax as a % of revenue
B40: Income tax | D40: € | M40: 0 | N40: 0 | O40: 0 | P40: 0 | Q40: 0 | R40: 0 | S40: 0 | T40: 0 | U40: 0 | V40: 0 | W40: 0 | X40: 0 | Y40: 0 | Z40: 0 | AA40: 0 | AB40: 0 | AC40: 0 | AD40: 0 | AE40: 0 | AF40: 0 | AG40: 0 | AH40: 0 | AI40: 0 | AJ40: 0 | AK40: 0 | AL40: 0 | AM40: 0 | AN40: 0 | AO40: 0 | AP40: 0 | AQ40: 0 | AR40: 0 | AS40: 0 | AT40: 0 | AU40: 0 | AV40: 0 | AW40: 0 | AX40: 0 | AY40: 0 | AZ40: 0 | BB40: =sum(E40:P40) | BC40: =sum(Q40:AB40) | BD40: =sum(AC40:AN40) | BE40: =sum(AO40:AZ40) | BF40: =(BF37-AZ44)*Assumptions!$C$10 | BH40: tax on profit, but only once the old losses below are used up
B41: NET INCOME | D41: € | M41: =M37-M40 | N41: =N37-N40 | O41: =O37-O40 | P41: =P37-P40 | Q41: =Q37-Q40 | R41: =R37-R40 | S41: =S37-S40 | T41: =T37-T40 | ... AZ41: =AZ37-AZ40 | BB41: =sum(E41:P41) | BC41: =sum(Q41:AB41) | BD41: =sum(AC41:AN41) | BE41: =sum(AO41:AZ41) | BF41: =BF37-BF40 | BH41: profit after tax
B42: Profit margin % | BE42: =BE41/BE11 | BF42: =BF41/BF11 | BH42: net profit as a % of revenue
B44: Tax carry over to be applied | M44: 108239 | N44: =M44+(-N41*Assumptions!$C$10) | O44: =N44+(-O41*Assumptions!$C$10) | P44: =O44+(-P41*Assumptions!$C$10) | Q44: =P44+(-Q41*Assumptions!$C$10) | R44: =Q44+(-R41*Assumptions!$C$10) | S44: =R44+(-S41*Assumptions!$C$10) | T44: =S44+(-T41*Assumptions!$C$10) | U44: =T44+(-U41*Assumptions!$C$10) | ... AZ44: =AY44+(-AZ41*Assumptions!$C$10) | BH44: running pot of unused tax losses: grows in loss months, gets eaten when profitable
B46: CASH FLOW STATEMENT
B47: Net income | D47: € | M47: =M41 | N47: =N41 | O47: =O41 | P47: =P41 | Q47: =Q41 | R47: =R41 | S47: =S41 | T47: =T41 | ... AZ47: =AZ41 | BB47: =sum(E47:P47) | BC47: =sum(Q47:AB47) | BD47: =sum(AC47:AN47) | BE47: =sum(AO47:AZ47) | BF47: =BF41 | BH47: cash flow starts from net income
B48: Depreciation & amortisation | D48: € | E48: =E35 | F48: =F35 | G48: =G35 | H48: =H35 | I48: =I35 | J48: =J35 | K48: =K35 | L48: =L35 | ... AZ48: =AZ35 | BB48: =sum(E48:P48) | BC48: =sum(Q48:AB48) | BD48: =sum(AC48:AN48) | BE48: =sum(AO48:AZ48) | BF48: =BF35 | BH48: adds depreciation back, it isn't cash
B49: Increase in accounts receivable (delta DSO) | D49: € | M49: 0 | N49: =-(N68-M68) | O49: =-(O68-N68) | P49: =-(P68-O68) | Q49: =-(Q68-P68) | R49: =-(R68-Q68) | S49: =-(S68-R68) | T49: =-(T68-S68) | U49: =-(U68-T68) | ... AZ49: =-(AZ68-AY68) | BB49: =sum(E49:P49) | BC49: =sum(Q49:AB49) | BD49: =sum(AC49:AN49) | BE49: =sum(AO49:AZ49) | BF49: =-(BF68-BE68) | BH49: cash tied up when receivables grow, freed when they shrink
B50: Increase in accounts payable (delta DPO) | D50: € | M50: 0 | N50: =(N77-M77) | O50: =(O77-N77) | P50: =(P77-O77) | Q50: =(Q77-P77) | R50: =(R77-Q77) | S50: =(S77-R77) | T50: =(T77-S77) | U50: =(U77-T77) | ... AZ50: =(AZ77-AY77) | BB50: =sum(E50:P50) | BC50: =sum(Q50:AB50) | BD50: =sum(AC50:AN50) | BE50: =sum(AO50:AZ50) | BF50: =BF77-BE77 | BH50: cash gained by paying suppliers later, used up when payables fall
B51: Change in inventory (delta DIO) | D51: € | M51: 0 | N51: =-(N69-M69) | O51: =-(O69-N69) | P51: =-(P69-O69) | Q51: =-(Q69-P69) | R51: =-(R69-Q69) | S51: =-(S69-R69) | T51: =-(T69-S69) | U51: =-(U69-T69) | ... AZ51: =-(AZ69-AY69) | BB51: =sum(E51:P51) | BC51: =sum(Q51:AB51) | BD51: =sum(AC51:AN51) | BE51: =sum(AO51:AZ51) | BF51: =-(BF69-BE69) | BH51: cash tied up in stock. days of stock is 0, so nothing moves
B52: Cash from Operations | D52: € | M52: =sum(M47:M51) | N52: =sum(N47:N51) | O52: =sum(O47:O51) | P52: =sum(P47:P51) | Q52: =sum(Q47:Q51) | R52: =sum(R47:R51) | S52: =sum(S47:S51) | T52: =sum(T47:T51) | ... AZ52: =sum(AZ47:AZ51) | BB52: =sum(E52:P52) | BC52: =sum(Q52:AB52) | BD52: =sum(AC52:AN52) | BE52: =sum(AO52:AZ52) | BF52: =sum(BF47:BF51) | BH52: net income plus all the working-capital swings
B53: CAPEX | D53: € | E53: =IFERROR(-HLOOKUP(YEAR(E$3),Assumptions!$D$124:$G$127,4,FALSE)/12,0) | F53: =IFERROR(-HLOOKUP(YEAR(F$3),Assumptions!$D$124:$G$127,4,FALSE)/12,0) | G53: =IFERROR(-HLOOKUP(YEAR(G$3),Assumptions!$D$124:$G$127,4,FALSE)/12,0) | H53: =IFERROR(-HLOOKUP(YEAR(H$3),Assumptions!$D$124:$G$127,4,FALSE)/12,0) | I53: =IFERROR(-HLOOKUP(YEAR(I$3),Assumptions!$D$124:$G$127,4,FALSE)/12,0) | J53: =IFERROR(-HLOOKUP(YEAR(J$3),Assumptions!$D$124:$G$127,4,FALSE)/12,0) | K53: =IFERROR(-HLOOKUP(YEAR(K$3),Assumptions!$D$124:$G$127,4,FALSE)/12,0) | L53: =IFERROR(-HLOOKUP(YEAR(L$3),Assumptions!$D$124:$G$127,4,FALSE)/12,0) | ... AZ53: =IFERROR(-HLOOKUP(YEAR(AZ$3),Assumptions!$D$124:$G$127,4,FALSE)/12,0) | BB53: =sum(E53:P53) | BC53: =sum(Q53:AB53) | BD53: =sum(AC53:AN53) | BE53: =sum(AO53:AZ53) | BF53: =-Assumptions!$F$127 | BH53: staged capex from Assumptions rows 125-127, spread evenly over each year
B54: Cash from Investing | M54: =M53 | N54: =N53 | O54: =O53 | P54: =P53 | Q54: =Q53 | R54: =R53 | S54: =S53 | T54: =T53 | ... AZ54: =AZ53 | BB54: =sum(E54:P54) | BC54: =sum(Q54:AB54) | BD54: =sum(AC54:AN54) | BE54: =sum(AO54:AZ54) | BF54: =BF53 | BH54: same as capex
B55: Equity injection | D55: € | S55: 0 | U55: 300000 | AA55: =IF(Assumptions!$D$82=2,10000000,3000000) | BB55: =sum(E55:P55) | BC55: =sum(Q55:AB55) | BD55: =sum(AC55:AN55) | BE55: =sum(AO55:AZ55) | BF55: 0 | BH55: money in from shares: 300k May-26, then 3.0m (Base) or 10.0m (Aggressive) Nov-26
B56: Loan (CLA) | D56: € | W56: 300000 | BB56: =sum(E56:P56) | BC56: =sum(Q56:AB56) | BD56: =sum(AC56:AN56) | BE56: =sum(AO56:AZ56) | BF56: 0 | BH56: CLA loan drawn, 300k in Jul-26
B58: Cash from Financing | D58: € | E58: =E55+E56+E57 | F58: =F55+F56+F57 | G58: =G55+G56+G57 | H58: =H55+H56+H57 | I58: =I55+I56+I57 | J58: =J55+J56+J57 | K58: =K55+K56+K57 | L58: =L55+L56+L57 | ... AZ58: =AZ55+AZ56+AZ57 | BB58: =sum(E58:P58) | BC58: =sum(Q58:AB58) | BD58: =sum(AC58:AN58) | BE58: =sum(AO58:AZ58) | BF58: =BF55+BF56+BF57 | BH58: equity plus loans in the month
B60: Total Change in Cash | D60: € | M60: =M52+M54+M58 | N60: =N52+N54+N58 | O60: =O52+O54+O58 | P60: =P52+P54+P58 | Q60: =Q52+Q54+Q58 | R60: =R52+R54+R58 | S60: =S52+S54+S58 | T60: =T52+T54+T58 | ... AZ60: =AZ52+AZ54+AZ58 | BB60: =BB58+BB54+BB52 | BC60: =BC58+BC54+BC52 | BD60: =BD58+BD54+BD52 | BE60: =BE58+BE54+BE52 | BF60: =BF58+BF54+BF52 | BH60: operating + investing + financing
B61: Beginning cash balance | D61: € | M61: =1111108+69465 | N61: =M62 | O61: =N62 | P61: =O62 | Q61: =P62 | R61: =Q62 | S61: =R62 | T61: =S62 | U61: =T62 | ... AZ61: =AY62 | BB61: =BB60+BB62 | BC61: =Q61 | BD61: =AC61 | BE61: =AO61 | BF61: =AZ62 | BH61: last month's closing cash
B62: Ending Cash Balance | D62: € | M62: =M60+M61 | N62: =N61+N60 | O62: =O61+O60 | P62: =P61+P60 | Q62: =Q61+Q60 | R62: =R61+R60 | S62: =S61+S60 | T62: =T61+T60 | U62: =U61+U60 | V62: =V61+V60 | W62: =V62+W60 | X62: =X61+X60 | Y62: =Y61+Y60 | Z62: =Z61+Z60 | AA62: =AA61+AA60 | AB62: =AB61+AB60 | AC62: =AC61+AC60 | AD62: =AD61+AD60 | AE62: =AE61+AE60 | ... AZ62: =AZ61+AZ60 | BB62: =P62 | BC62: =BC60+BC61 | BD62: =BD60+BD61 | BE62: =BE60+BE61 | BF62: =BF60+BF61 | BH62: cash in minus cash out. this is the runway line to watch
B64: BALANCE SHEET
B65: ASSETS
B66: Cash and cash equivalents | D66: € | M66: =M62 | N66: =N62 | O66: =O62 | P66: =P62 | Q66: =Q62 | R66: =R62 | S66: =S62 | T66: =T62 | ... AZ66: =AZ62 | BB66: =P66 | BC66: =AB66 | BD66: =AN66 | BE66: =AZ66 | BF66: =BF62 | BH66: the closing cash from the cash flow above
B67: Deferred tax assest ("carry forward") | D67: € | M67: =M44 | N67: =N44 | O67: =O44 | P67: =P44 | Q67: =Q44 | R67: =R44 | S67: =S44 | T67: =T44 | ... AZ67: =AZ44 | BB67: =P67 | BC67: =AB67 | BD67: =AN67 | BE67: =AZ67 | BF67: 0 | BH67: unused tax losses, parked as an asset
B68: Accounts receivable (DSO-based) | D68: € | M68: =ABS(Assumptions!$D$15*(M11/30)) | N68: =ABS(Assumptions!$D$15*(N11/30)) | O68: =ABS(Assumptions!$D$15*(O11/30)) | P68: =ABS(Assumptions!$D$15*(P11/30)) | Q68: =ABS(Assumptions!$D$15*(Q11/30)) | R68: =ABS(Assumptions!$D$15*(R11/30)) | S68: =ABS(Assumptions!$D$15*(S11/30)) | T68: =ABS(Assumptions!$D$15*(T11/30)) | ... AZ68: =ABS(Assumptions!$D$15*(AZ11/30)) | BB68: =P68 | BC68: =AB68 | BD68: =AN68 | BE68: =AZ68 | BF68: =Assumptions!$D$15/365*BF11 | BH68: receivables: DSO days' worth of revenue not collected yet
B69: Inventory (DIO-based) | D69: € | M69: =ABS(Assumptions!$D$17*(M17/30)) | N69: =ABS(Assumptions!$D$17*(N17/30)) | O69: =ABS(Assumptions!$D$17*(O17/30)) | P69: =ABS(Assumptions!$D$17*(P17/30)) | Q69: =ABS(Assumptions!$D$17*(Q17/30)) | R69: =ABS(Assumptions!$D$17*(R17/30)) | S69: =ABS(Assumptions!$D$17*(S17/30)) | T69: =ABS(Assumptions!$D$17*(T17/30)) | ... AZ69: =ABS(Assumptions!$D$17*(AZ17/30)) | BB69: =P69 | BC69: =AB69 | BD69: =AN69 | BE69: =AZ69 | BF69: =Assumptions!$D$17/365*BF17 | BH69: inventory: days of stock x cost of sales. 0 days, so zero
B70: Total Current Assets | D70: € | M70: =sum(M66:M69) | N70: =sum(N66:N69) | O70: =sum(O66:O69) | P70: =sum(P66:P69) | Q70: =sum(Q66:Q69) | R70: =sum(R66:R69) | S70: =sum(S66:S69) | T70: =sum(T66:T69) | ... AZ70: =sum(AZ66:AZ69) | BB70: =P70 | BC70: =AB70 | BD70: =AN70 | BE70: =AZ70 | BF70: =BF66+BF68+BF69 | BH70: cash + receivables + inventory
B72: Net PP&E | D72: € | E72: =-SUM($E$53:E53)-SUM($E$35:E35) | F72: =-SUM($E$53:F53)-SUM($E$35:F35) | G72: =-SUM($E$53:G53)-SUM($E$35:G35) | H72: =-SUM($E$53:H53)-SUM($E$35:H35) | I72: =-SUM($E$53:I53)-SUM($E$35:I35) | J72: =-SUM($E$53:J53)-SUM($E$35:J35) | K72: =-SUM($E$53:K53)-SUM($E$35:K35) | L72: =-SUM($E$53:L53)-SUM($E$35:L35) | ... AZ72: =-SUM($E$53:AZ53)-SUM($E$35:AZ35) | BB72: =P72 | BC72: =AB72 | BD72: =AN72 | BE72: =AZ72 | BF72: =BE72+(-BF53)-BF35 | BH72: cumulative capex less accumulated depreciation
B73: Total Fixed Assets | D73: € | M73: =M72 | N73: =N72 | O73: =O72 | P73: =P72 | Q73: =Q72 | R73: =R72 | S73: =S72 | T73: =T72 | ... AZ73: =AZ72 | BB73: =P73 | BC73: =AB73 | BD73: =AN73 | BE73: =AZ73 | BF73: =BF72 | BH73: same as net PP&E
B74: TOTAL ASSETS | D74: € | M74: =M70+M73 | N74: =N70+N73 | O74: =O70+O73 | P74: =P70+P73 | Q74: =Q70+Q73 | R74: =R70+R73 | S74: =S70+S73 | T74: =T70+T73 | ... AZ74: =AZ70+AZ73 | BB74: =P74 | BC74: =AB74 | BD74: =AN74 | BE74: =AZ74 | BF74: =BF70+BF73 | BH74: current assets + fixed assets
B76: EQUITY & LIABILITIES
B77: Accounts payable (DPO-based) | D77: € | M77: =ABS(Assumptions!$D$16*(M17/30)) | N77: =ABS(Assumptions!$D$16*(N17/30)) | O77: =ABS(Assumptions!$D$16*(O17/30)) | P77: =ABS(Assumptions!$D$16*(P17/30)) | Q77: =ABS(Assumptions!$D$16*(Q17/30)) | R77: =ABS(Assumptions!$D$16*(R17/30)) | S77: =ABS(Assumptions!$D$16*(S17/30)) | T77: =ABS(Assumptions!$D$16*(T17/30)) | ... AZ77: =ABS(Assumptions!$D$16*(AZ17/30)) | BB77: =P77 | BC77: =AB77 | BD77: =AN77 | BE77: =AZ77 | BF77: =Assumptions!$D$16/365*BF17 | BH77: payables: DPO days' worth of cost of sales not paid yet
B78: Total Current Liabilities | D78: € | M78: =sum(M77) | N78: =sum(N77) | O78: =sum(O77) | P78: =sum(P77) | Q78: =sum(Q77) | R78: =sum(R77) | S78: =sum(S77) | T78: =sum(T77) | ... AZ78: =sum(AZ77) | BB78: =P78 | BC78: =AB78 | BD78: =AN78 | BE78: =AZ78 | BF78: =BF77 | BH78: same as payables
B81: Loan (CLA) | D81: € | Q81: 0 | R81: 0 | S81: 0 | T81: 0 | U81: 0 | V81: =V56 | W81: =V81+W56 | X81: =W81 | Y81: =X81 | Z81: 0 | AA81: 0 | AB81: 0 | AC81: 0 | AD81: 0 | AE81: 0 | AF81: 0 | AG81: 0 | AH81: 0 | AI81: 0 | AJ81: 0 | AK81: 0 | AL81: 0 | AM81: 0 | AN81: 0 | AO81: 0 | AP81: 0 | AQ81: 0 | AR81: 0 | AS81: 0 | AT81: 0 | AU81: 0 | AV81: 0 | AW81: 0 | AX81: 0 | AY81: 0 | AZ81: 0 | BB81: 0 | BC81: =AB81 | BD81: =AN81 | BE81: =AZ81 | BF81: 0 | BH81: CLA balance: a liability Jul-Sep 26, then it converts to shares
B83: Total Long-Term Liabilities | D83: € | E83: =E80+E81+E82 | F83: =F80+F81+F82 | G83: =G80+G81+G82 | H83: =H80+H81+H82 | I83: =I80+I81+I82 | J83: =J80+J81+J82 | K83: =K80+K81+K82 | L83: =L80+L81+L82 | ... AZ83: =AZ80+AZ81+AZ82 | BB83: =P83 | BC83: =AB83 | BD83: =AN83 | BE83: =AZ83 | BF83: =sum(BF80:BF82) | BH83: all the long-term debt lines added
B85: Share capital + premium | D85: € | M85: =M61 | N85: =M85 | O85: =N85 | P85: =O85 | Q85: =P85 | R85: =Q85 | S85: =R85 | T85: =S85 | U85: =T85 | ... Y85: =X85 | Z85: =Y85+Y81 | AA85: =Z85 | AB85: =AA85 | AC85: =AB85 | AD85: =AC85 | AE85: =AD85 | AF85: =AE85 | AG85: =AF85 | AH85: =AG85 | ... AZ85: =AY85 | BB85: =P85 | BC85: =AB85 | BD85: =AN85 | BE85: =AZ85 | BF85: =BE85 | BH85: share capital, steps up when the CLA converts to shares
B86: Cumulative equity injections | D86: € | M86: =M55+M55 | N86: =M86+N55 | O86: =N86+O55 | P86: =O86+P55 | Q86: =P86+Q55 | R86: =Q86+R55 | S86: =R86+S55 | T86: =S86+T55 | U86: =T86+U55 | ... AZ86: =AY86+AZ55 | BB86: =P86 | BC86: =AB86 | BD86: =AN86 | BE86: =AZ86 | BF86: =BE86 | BH86: running total of cash put in by shareholders
B87: Retained earnings (cumulative net income) | D87: € | M87: =M47 | N87: =M87+N41 | O87: =N87+O41 | P87: =O87+P41 | Q87: =P87+Q41 | R87: =Q87+R41 | S87: =R87+S41 | T87: =S87+T41 | U87: =T87+U41 | ... AZ87: =AY87+AZ41 | BB87: =P87 | BC87: =AB87 | BD87: =AN87 | BE87: =AZ87 | BF87: =BE87+BF41 | BH87: retained earnings: last month's plus this month's profit
B88: Total Equity | D88: € | M88: =M85+M86+M87+M44 | N88: =N85+N86+N87+N44 | O88: =O85+O86+O87+O44 | P88: =P85+P86+P87+P44 | Q88: =Q85+Q86+Q87+Q44 | R88: =R85+R86+R87+R44 | S88: =S85+S86+S87+S44 | T88: =T85+T86+T87+T44 | ... AZ88: =AZ85+AZ86+AZ87+AZ44 | BB88: =P88 | BC88: =AB88 | BD88: =AN88 | BE88: =AZ88 | BF88: =sum(BF85:BF87) | BH88: share capital + injections + retained earnings
B89: TOTAL EQUITY & LIABILITIES | D89: € | M89: =M78+M83+M88 | N89: =N78+N83+N88 | O89: =O78+O83+O88 | P89: =P78+P83+P88 | Q89: =Q78+Q83+Q88 | R89: =R78+R83+R88 | S89: =S78+S83+S88 | T89: =T78+T83+T88 | ... AZ89: =AZ78+AZ83+AZ88 | BB89: =P89 | BC89: =AB89 | BD89: =AN89 | BE89: =AZ89 | BF89: =BF78+BF83+BF88 | BH89: liabilities plus equity
B91: CHECK (Total Assets − Total E&L = 0) | M91: =M74-M89 | N91: =N74-N89 | O91: =O74-O89 | P91: =P74-P89 | Q91: =Q74-Q89 | R91: =R74-R89 | S91: =S74-S89 | T91: =T74-T89 | ... AZ91: =AZ74-AZ89 | BB91: =BB74-BB89 | BC91: =BC74-BC89 | BD91: =BD74-BD89 | BE91: =BE74-BE89 | BF91: =BF74-BF89 | BH91: checks assets = liabilities + equity, must be 0
B93: Cumulative turbineketels (helper) | E93: ='Revenue Forecast'!E34 | F93: =E93+'Revenue Forecast'!F34 | G93: =F93+'Revenue Forecast'!G34 | H93: =G93+'Revenue Forecast'!H34 | I93: =H93+'Revenue Forecast'!I34 | J93: =I93+'Revenue Forecast'!J34 | K93: =J93+'Revenue Forecast'!K34 | L93: =K93+'Revenue Forecast'!L34 | M93: =L93+'Revenue Forecast'!M34 | ... AZ93: =AY93+'Revenue Forecast'!AZ34 | BH93: running count of ketels ever sold. feeds the COGS volume tiers

Sheet Revenue Forecast
B1: Tarnoc B.V. — Revenue Forecast (€, ex VAT unless noted)
E2: 2025 | Q2: 2026 | AC2: 2027 | AO2: 2028
E3: 45658 | F3: 45689 | G3: 45717 | H3: 45748 | I3: 45778 | J3: 45809 | K3: 45839 | L3: 45870 | M3: 45901 | N3: 45931 | O3: 45962 | P3: 45992 | Q3: 46023 | R3: 46054 | S3: 46082 | T3: 46113 | U3: 46143 | V3: 46174 | W3: 46204 | X3: 46235 | Y3: 46266 | Z3: 46296 | AA3: 46327 | AB3: 46357 | AC3: 46388 | AD3: 46419 | AE3: 46447 | AF3: 46478 | AG3: 46508 | AH3: 46539 | AI3: 46569 | AJ3: 46600 | AK3: 46631 | AL3: 46661 | AM3: 46692 | AN3: 46722 | AO3: 46753 | AP3: 46784 | AQ3: 46813 | AR3: 46844 | AS3: 46874 | AT3: 46905 | AU3: 46935 | AV3: 46966 | AW3: 46997 | AX3: 47027 | AY3: 47058 | AZ3: 47088 | BB3: 2025 | BC3: 2026 | BD3: 2027 | BE3: 2028 | BF3: 2029 | BH3: what this row does
AB4: 2 | AC4: 3 | AD4: 4 | AE4: 5 | AF4: 6 | AG4: 7 | AH4: 8 | AI4: 9 | AJ4: 10 | AK4: 11 | AL4: 12 | AM4: 13 | AN4: 14 | AO4: 15 | AP4: 16 | AQ4: 17 | AR4: 18 | AS4: 19 | AT4: 20 | AU4: 21 | AV4: 22 | AW4: 23 | AX4: 24 | AY4: 25 | AZ4: 26
B5: TURBINEKETEL (TTK)
B6: TTK units sold | D6: # | E6: 0 | F6: 0 | G6: 0 | H6: 0 | I6: 0 | J6: 0 | K6: 0 | L6: 0 | M6: 0 | N6: 0 | O6: 0 | P6: 0 | Q6: 0 | R6: 0 | S6: 0 | T6: 0 | U6: 0 | V6: 0 | W6: 0 | X6: 0 | Y6: 0 | Z6: 0 | AA6: 0 | AB6: 0 | AC6: ='Growth Engine'!F43*Assumptions!$H$23 | AD6: ='Growth Engine'!G43*Assumptions!$H$23 | AE6: ='Growth Engine'!H43*Assumptions!$H$23 | AF6: ='Growth Engine'!I43*Assumptions!$H$23 | AG6: ='Growth Engine'!J43*Assumptions!$H$23 | AH6: ='Growth Engine'!K43*Assumptions!$H$23 | AI6: ='Growth Engine'!L43*Assumptions!$H$23 | AJ6: ='Growth Engine'!M43*Assumptions!$H$23 | ... AZ6: ='Growth Engine'!AC43*Assumptions!$H$23 | BB6: =SUM(E6:P6) | BC6: =SUM(Q6:AB6) | BD6: =SUM(AC6:AN6) | BE6: =SUM(AO6:AZ6) | BF6: =Assumptions!$F$23 | BH6: units from the Growth Engine tab x the TTK share of the mix (Assumptions H23)
B7: TTK Revenue | D7: € | Q7: =Q6*Assumptions!$C$29 | R7: =R6*Assumptions!$C$29 | S7: =S6*Assumptions!$C$29 | T7: =T6*Assumptions!$C$29 | U7: =U6*Assumptions!$C$29 | V7: =V6*Assumptions!$C$29 | W7: =W6*Assumptions!$C$29 | X7: =X6*Assumptions!$C$29 | ... AZ7: =AZ6*Assumptions!$C$29 | BB7: =SUM(E7:P7) | BC7: =SUM(Q7:AB7) | BD7: =SUM(AC7:AN7) | BE7: =SUM(AO7:AZ7) | BF7: =BF6*Assumptions!$C$29 | BH7: units x TTK price
B8: TTK upsell | D8: € | Q8: =Q6*SUMPRODUCT(Assumptions!$E$112:$F$114) | R8: =R6*SUMPRODUCT(Assumptions!$E$112:$F$114) | S8: =S6*SUMPRODUCT(Assumptions!$E$112:$F$114) | T8: =T6*SUMPRODUCT(Assumptions!$E$112:$F$114) | U8: =U6*SUMPRODUCT(Assumptions!$E$112:$F$114) | V8: =V6*SUMPRODUCT(Assumptions!$E$112:$F$114) | W8: =W6*SUMPRODUCT(Assumptions!$E$112:$F$114) | X8: =X6*SUMPRODUCT(Assumptions!$E$112:$F$114) | ... AB8: =AB6*SUMPRODUCT(Assumptions!$E$112:$F$114) | AC8: =AC6*SUMPRODUCT(Assumptions!$E$112:$E$114,Assumptions!$F$112:$F$114) | AD8: =AD6*SUMPRODUCT(Assumptions!$E$112:$E$114,Assumptions!$F$112:$F$114) | AE8: =AE6*SUMPRODUCT(Assumptions!$E$112:$E$114,Assumptions!$F$112:$F$114) | AF8: =AF6*SUMPRODUCT(Assumptions!$E$112:$E$114,Assumptions!$F$112:$F$114) | AG8: =AG6*SUMPRODUCT(Assumptions!$E$112:$E$114,Assumptions!$F$112:$F$114) | AH8: =AH6*SUMPRODUCT(Assumptions!$E$112:$E$114,Assumptions!$F$112:$F$114) | AI8: =AI6*SUMPRODUCT(Assumptions!$E$112:$E$114,Assumptions!$F$112:$F$114) | AJ8: =AJ6*SUMPRODUCT(Assumptions!$E$112:$E$114,Assumptions!$F$112:$F$114) | ... AZ8: =AZ6*SUMPRODUCT(Assumptions!$E$112:$E$114,Assumptions!$F$112:$F$114) | BB8: =SUM(E8:P8) | BC8: =SUM(Q8:AB8) | BD8: =SUM(AC8:AN8) | BE8: =SUM(AO8:AZ8) | BF8: =BF6*SUMPRODUCT(Assumptions!$E$112:$E$114,Assumptions!$F$112:$F$114) | BH8: units x average upsell basket (attach % x price)
B9: Total TTK Revenue | D9: € | Q9: =sum(Q7:Q8) | R9: =sum(R7:R8) | S9: =sum(S7:S8) | T9: =sum(T7:T8) | U9: =sum(U7:U8) | V9: =sum(V7:V8) | W9: =sum(W7:W8) | X9: =sum(X7:X8) | ... AZ9: =sum(AZ7:AZ8) | BB9: =SUM(E9:P9) | BC9: =SUM(Q9:AB9) | BD9: =SUM(AC9:AN9) | BE9: =SUM(AO9:AZ9) | BF9: =SUM(BF7:BF8) | BH9: machine revenue + upsells
B11: COMBI+
B12: Combi+ units sold | D12: # | E12: 0 | F12: 0 | G12: 0 | H12: 0 | I12: 0 | J12: 0 | K12: 0 | L12: 0 | M12: 0 | N12: 0 | O12: 0 | P12: 0 | Q12: 0 | R12: 0 | S12: 0 | T12: 0 | U12: 0 | V12: 0 | W12: 0 | X12: 0 | Y12: 0 | Z12: 0 | AA12: 0 | AB12: 0 | AC12: ='Growth Engine'!F43*Assumptions!$H$24 | AD12: ='Growth Engine'!G43*Assumptions!$H$24 | AE12: ='Growth Engine'!H43*Assumptions!$H$24 | AF12: ='Growth Engine'!I43*Assumptions!$H$24 | AG12: ='Growth Engine'!J43*Assumptions!$H$24 | AH12: ='Growth Engine'!K43*Assumptions!$H$24 | AI12: ='Growth Engine'!L43*Assumptions!$H$24 | AJ12: ='Growth Engine'!M43*Assumptions!$H$24 | ... AZ12: ='Growth Engine'!AC43*Assumptions!$H$24 | BB12: =SUM(E12:P12) | BC12: =SUM(Q12:AB12) | BD12: =SUM(AC12:AN12) | BE12: =SUM(AO12:AZ12) | BF12: =Assumptions!$F$24 | BH12: units from the Growth Engine tab x the Combi+ share of the mix (Assumptions H24)
B13: Combi+ Revenue | D13: € | Q13: =Q12*Assumptions!$C$31 | R13: =R12*Assumptions!$C$31 | S13: =S12*Assumptions!$C$31 | T13: =T12*Assumptions!$C$31 | U13: =U12*Assumptions!$C$31 | V13: =V12*Assumptions!$C$31 | W13: =W12*Assumptions!$C$31 | X13: =X12*Assumptions!$C$31 | ... AZ13: =AZ12*Assumptions!$C$31 | BB13: =SUM(E13:P13) | BC13: =SUM(Q13:AB13) | BD13: =SUM(AC13:AN13) | BE13: =SUM(AO13:AZ13) | BF13: =BF12*Assumptions!$C$31 | BH13: units x Combi+ price (ketel + outdoor unit)
B14: Combi+ upsell | D14: € | Q14: =Q12*SUMPRODUCT(Assumptions!$E$112:$E$114,Assumptions!$F$112:$F$114) | R14: =R12*SUMPRODUCT(Assumptions!$E$112:$E$114,Assumptions!$F$112:$F$114) | S14: =S12*SUMPRODUCT(Assumptions!$E$112:$E$114,Assumptions!$F$112:$F$114) | T14: =T12*SUMPRODUCT(Assumptions!$E$112:$E$114,Assumptions!$F$112:$F$114) | U14: =U12*SUMPRODUCT(Assumptions!$E$112:$E$114,Assumptions!$F$112:$F$114) | V14: =V12*SUMPRODUCT(Assumptions!$E$112:$E$114,Assumptions!$F$112:$F$114) | W14: =W12*SUMPRODUCT(Assumptions!$E$112:$E$114,Assumptions!$F$112:$F$114) | X14: =X12*SUMPRODUCT(Assumptions!$E$112:$E$114,Assumptions!$F$112:$F$114) | ... AZ14: =AZ12*SUMPRODUCT(Assumptions!$E$112:$E$114,Assumptions!$F$112:$F$114) | BB14: =SUM(E14:P14) | BC14: =SUM(Q14:AB14) | BD14: =SUM(AC14:AN14) | BE14: =SUM(AO14:AZ14) | BF14: =BF12*SUMPRODUCT(Assumptions!$E$112:$E$114,Assumptions!$F$112:$F$114) | BH14: units x average upsell basket
B15: Total Combi+ Revenue | D15: € | Q15: =sum(Q13:Q14) | R15: =sum(R13:R14) | S15: =sum(S13:S14) | T15: =sum(T13:T14) | U15: =sum(U13:U14) | V15: =sum(V13:V14) | W15: =sum(W13:W14) | X15: =sum(X13:X14) | ... AZ15: =sum(AZ13:AZ14) | BB15: =SUM(E15:P15) | BC15: =SUM(Q15:AB15) | BD15: =SUM(AC15:AN15) | BE15: =SUM(AO15:AZ15) | BF15: =sum(BF13:BF14) | BH15: machine revenue + upsells
B17: INSTALLATION REVENUES | D17: €
B18: Units installed | D18: # | E18: =E6+E12 | F18: =F6+F12 | G18: =G6+G12 | H18: =H6+H12 | I18: =I6+I12 | J18: =J6+J12 | K18: =K6+K12 | L18: =L6+L12 | ... AZ18: =AZ6+AZ12 | BB18: =SUM(E18:P18) | BC18: =SUM(Q18:AB18) | BD18: =SUM(AC18:AN18) | BE18: =SUM(AO18:AZ18) | BF18: =BF6+BF12 | BH18: TTK + Combi+ units. every unit sold gets installed
B19: Total Installation Revenue | D19: € | E19: =E6*Assumptions!$C$33+E12*Assumptions!$C$34 | F19: =F6*Assumptions!$C$33+F12*Assumptions!$C$34 | G19: =G6*Assumptions!$C$33+G12*Assumptions!$C$34 | H19: =H6*Assumptions!$C$33+H12*Assumptions!$C$34 | I19: =I6*Assumptions!$C$33+I12*Assumptions!$C$34 | J19: =J6*Assumptions!$C$33+J12*Assumptions!$C$34 | K19: =K6*Assumptions!$C$33+K12*Assumptions!$C$34 | L19: =L6*Assumptions!$C$33+L12*Assumptions!$C$34 | ... AZ19: =AZ6*Assumptions!$C$33+AZ12*Assumptions!$C$34 | BB19: =SUM(E19:P19) | BC19: =SUM(Q19:AB19) | BD19: =SUM(AC19:AN19) | BE19: =SUM(AO19:AZ19) | BF19: =BF6*Assumptions!$C$33+BF12*Assumptions!$C$34 | BH19: units x installation price per product. pass-through, cost is the same
B21: SERVICE REVENUES
B22: Installed base (TTK) | D22: # | Q22: =Q6 | R22: =R6 | S22: =S6 | T22: =T6 | U22: =U6 | V22: =V6 | W22: =W6 | X22: =X6 | ... AC22: =AC6 | AD22: =AC22+AD6 | AE22: =AD22+AE6 | AF22: =AE22+AF6 | AG22: =AF22+AG6 | AH22: =AG22+AH6 | AI22: =AH22+AI6 | AJ22: =AI22+AJ6 | AK22: =AJ22+AK6 | ... AZ22: =AY22+AZ6 | BB22: =SUM(E22:P22) | BC22: =SUM(Q22:AB22) | BD22: =AN22 | BE22: =AZ22 | BF22: =BE22+($BF$18*Assumptions!$H$23) | BH22: TTK machines out in the field: last month's base + this month's sales
B23: Installed base (Combi+) | Q23: =Q12 | R23: =R12 | S23: =S12 | T23: =T12 | U23: =U12 | V23: =V12 | W23: =W12 | X23: =X12 | ... AC23: =AC12 | AD23: =AC23+AD12 | AE23: =AD23+AE12 | AF23: =AE23+AF12 | AG23: =AF23+AG12 | AH23: =AG23+AH12 | AI23: =AH23+AI12 | AJ23: =AI23+AJ12 | AK23: =AJ23+AK12 | ... AZ23: =AY23+AZ12 | BB23: =SUM(E23:P23) | BC23: =SUM(Q23:AB23) | BD23: =AN23 | BE23: =AZ23 | BF23: =BE23+($BF$18*Assumptions!$H$24) | BH23: Combi+ machines out in the field, same running total
B24: Total Service Revenue | D24: € | Q24: =Q34*SUMPRODUCT(Assumptions!$E$120:$E$121,Assumptions!$F$120:$F$121) | R24: =R34*SUMPRODUCT(Assumptions!$E$120:$E$121,Assumptions!$F$120:$F$121) | S24: =S34*SUMPRODUCT(Assumptions!$E$120:$E$121,Assumptions!$F$120:$F$121) | T24: =T34*SUMPRODUCT(Assumptions!$E$120:$E$121,Assumptions!$F$120:$F$121) | U24: =U34*SUMPRODUCT(Assumptions!$E$120:$E$121,Assumptions!$F$120:$F$121) | V24: =V34*SUMPRODUCT(Assumptions!$E$120:$E$121,Assumptions!$F$120:$F$121) | W24: =W34*SUMPRODUCT(Assumptions!$E$120:$E$121,Assumptions!$F$120:$F$121) | X24: =X34*SUMPRODUCT(Assumptions!$E$120:$E$121,Assumptions!$F$120:$F$121) | ... AB24: =AB34*SUMPRODUCT(Assumptions!$E$120:$E$121,Assumptions!$F$120:$F$121) | AC24: =AC34*SUMPRODUCT(Assumptions!$E$120:$E$121,Assumptions!$F$120:$F$121)+Q24 | AD24: =AD34*SUMPRODUCT(Assumptions!$E$120:$E$121,Assumptions!$F$120:$F$121)+R24 | AE24: =AE34*SUMPRODUCT(Assumptions!$E$120:$E$121,Assumptions!$F$120:$F$121)+S24 | AF24: =AF34*SUMPRODUCT(Assumptions!$E$120:$E$121,Assumptions!$F$120:$F$121)+T24 | AG24: =AG34*SUMPRODUCT(Assumptions!$E$120:$E$121,Assumptions!$F$120:$F$121)+U24 | AH24: =AH34*SUMPRODUCT(Assumptions!$E$120:$E$121,Assumptions!$F$120:$F$121)+V24 | AI24: =AI34*SUMPRODUCT(Assumptions!$E$120:$E$121,Assumptions!$F$120:$F$121)+W24 | AJ24: =AJ34*SUMPRODUCT(Assumptions!$E$120:$E$121,Assumptions!$F$120:$F$121)+X24 | ... AZ24: =AZ34*SUMPRODUCT(Assumptions!$E$120:$E$121,Assumptions!$F$120:$F$121)+AN24 | BB24: =SUM(E24:P24) | BC24: =SUM(Q24:AB24) | BD24: =SUM(AC24:AN24) | BE24: =SUM(AO24:AZ24) | BF24: =BF34*SUMPRODUCT(Assumptions!$E$120:$E$121,Assumptions!$F$120:$F$121)+BE24 | BH24: this month's units x service rate + the same month last year, so contracts keep stacking as the base grows. 2029 adds all of 2028 on top
B26: SUBSIDIES & GRANTS
B27: All other | D27: € | E27: 0 | F27: 0 | G27: 0 | H27: 0 | I27: 0 | J27: 0 | K27: 0 | L27: 0 | M27: 0 | N27: 19480 | O27: 78000 | P27: 0 | Q27: 0 | R27: 0 | S27: 0 | T27: 0 | U27: 0 | V27: 0 | W27: 0 | X27: 106782 | Y27: 0 | Z27: 0 | AA27: 0 | AB27: 0 | AC27: 0 | AD27: 0 | AE27: 0 | AF27: 0 | AG27: 0 | AH27: 0 | AI27: 0 | AJ27: 0 | AK27: 0 | AL27: 0 | AM27: 0 | AN27: 0 | AO27: 0 | AP27: 0 | AQ27: 0 | AR27: 0 | AS27: 0 | AT27: 0 | AU27: 0 | AV27: 0 | AW27: 0 | AX27: 0 | AY27: 0 | AZ27: 0 | BB27: =SUM(E27:P27) | BC27: =SUM(Q27:AB27) | BD27: =SUM(AC27:AN27) | BE27: =SUM(AO27:AZ27) | BF27: 0 | BH27: nothing budgeted. the year columns just add the months up
B28: Total Subsidies & Grants | D28: € | E28: =sum(E27) | F28: =sum(F27) | G28: =sum(G27) | H28: =sum(H27) | I28: =sum(I27) | J28: =sum(J27) | K28: =sum(K27) | L28: =sum(L27) | ... AZ28: =sum(AZ27) | BB28: =SUM(E28:P28) | BC28: =SUM(Q28:AB28) | BD28: =BD27 | BE28: =BE27 | BF28: =BF27 | BH28: same as the line above
B30: TOTAL REVENUE | E30: =E9+E15+E19+E24+E28 | F30: =F9+F15+F19+F24+F28 | G30: =G9+G15+G19+G24+G28 | H30: =H9+H15+H19+H24+H28 | I30: =I9+I15+I19+I24+I28 | J30: =J9+J15+J19+J24+J28 | K30: =K9+K15+K19+K24+K28 | L30: =L9+L15+L19+L24+L28 | ... AZ30: =AZ9+AZ15+AZ19+AZ24+AZ28 | BB30: =BB9+BB15+BB19+BB24+BB28 | BC30: =BC9+BC15+BC19+BC24+BC28 | BD30: =SUM(AC30:AN30) | BE30: =SUM(AO30:AZ30) | BF30: =BF9+BF15+BF19+BF24+BF28 | BH30: everything added: TTK + Combi+ + installation + service + subsidies
B33: Installed Base | E33: =sum(E22:E23) | F33: =sum(F22:F23) | G33: =sum(G22:G23) | H33: =sum(H22:H23) | I33: =sum(I22:I23) | J33: =sum(J22:J23) | K33: =sum(K22:K23) | L33: =sum(L22:L23) | ... AZ33: =sum(AZ22:AZ23) | BB33: =sum(BB22:BB23) | BC33: =sum(BC22:BC23) | BD33: =sum(BD22:BD23) | BE33: =sum(BE22:BE23) | BF33: =sum(BF22:BF23) | BH33: total machines in the field (TTK + Combi+)
B34: Units sold | D34: # | E34: =E6+E12 | F34: =F6+F12 | G34: =G6+G12 | H34: =H6+H12 | I34: =I6+I12 | J34: =J6+J12 | K34: =K6+K12 | L34: =L6+L12 | ... AZ34: =AZ6+AZ12 | BB34: 0 | BC34: 0 | BD34: =SUM(AC34:AN34) | BE34: =SUM(AO34:AZ34) | BF34: =BF18 | BH34: units sold this period. the COGS volume tiers look at this row

Sheet COGS
B1: Tarnoc B.V. — COGS Schedule (€)
E2: 2025 | Q2: 2026 | AC2: 2027 | AO2: 2028
E3: 45658 | F3: 45689 | G3: 45717 | H3: 45748 | I3: 45778 | J3: 45809 | K3: 45839 | L3: 45870 | M3: 45901 | N3: 45931 | O3: 45962 | P3: 45992 | Q3: 46023 | R3: 46054 | S3: 46082 | T3: 46113 | U3: 46143 | V3: 46174 | W3: 46204 | X3: 46235 | Y3: 46266 | Z3: 46296 | AA3: 46327 | AB3: 46357 | AC3: 46388 | AD3: 46419 | AE3: 46447 | AF3: 46478 | AG3: 46508 | AH3: 46539 | AI3: 46569 | AJ3: 46600 | AK3: 46631 | AL3: 46661 | AM3: 46692 | AN3: 46722 | AO3: 46753 | AP3: 46784 | AQ3: 46813 | AR3: 46844 | AS3: 46874 | AT3: 46905 | AU3: 46935 | AV3: 46966 | AW3: 46997 | AX3: 47027 | AY3: 47058 | AZ3: 47088 | BB3: 2025 | BC3: 2026 | BD3: 2027 | BE3: 2028 | BF3: 2029
B6: TTK
B7: TTK | D7: € | Q7: =IFERROR('Revenue Forecast'!Q6*VLOOKUP('Revenue Forecast'!$BC$34,Assumptions!$B$67:$C$69,2,TRUE),0) | R7: =IFERROR('Revenue Forecast'!R6*VLOOKUP('Revenue Forecast'!$BC$34,Assumptions!$B$67:$C$69,2,TRUE),0) | S7: =IFERROR('Revenue Forecast'!S6*VLOOKUP('Revenue Forecast'!$BC$34,Assumptions!$B$67:$C$69,2,TRUE),0) | T7: =IFERROR('Revenue Forecast'!T6*VLOOKUP('Revenue Forecast'!$BC$34,Assumptions!$B$67:$C$69,2,TRUE),0) | U7: =IFERROR('Revenue Forecast'!U6*VLOOKUP('Revenue Forecast'!$BC$34,Assumptions!$B$67:$C$69,2,TRUE),0) | V7: =IFERROR('Revenue Forecast'!V6*VLOOKUP('Revenue Forecast'!$BC$34,Assumptions!$B$67:$C$69,2,TRUE),0) | W7: =IFERROR('Revenue Forecast'!W6*VLOOKUP('Revenue Forecast'!$BC$34,Assumptions!$B$67:$C$69,2,TRUE),0) | X7: =IFERROR('Revenue Forecast'!X6*VLOOKUP('Revenue Forecast'!$BC$34,Assumptions!$B$67:$C$69,2,TRUE),0) | ... AB7: =IFERROR('Revenue Forecast'!AB6*VLOOKUP('Revenue Forecast'!$BC$34,Assumptions!$B$67:$C$69,2,TRUE),0) | AC7: =IFERROR('Revenue Forecast'!AC6*VLOOKUP(IF(Assumptions!$D$83=2,'Revenue Forecast'!$BD$34+'Revenue Forecast'!$BE$34,'Revenue Forecast'!$BD$34),Assumptions!$B$67:$C$69,2,TRUE),0) | AD7: =IFERROR('Revenue Forecast'!AD6*VLOOKUP(IF(Assumptions!$D$83=2,'Revenue Forecast'!$BD$34+'Revenue Forecast'!$BE$34,'Revenue Forecast'!$BD$34),Assumptions!$B$67:$C$69,2,TRUE),0) | AE7: =IFERROR('Revenue Forecast'!AE6*VLOOKUP(IF(Assumptions!$D$83=2,'Revenue Forecast'!$BD$34+'Revenue Forecast'!$BE$34,'Revenue Forecast'!$BD$34),Assumptions!$B$67:$C$69,2,TRUE),0) | AF7: =IFERROR('Revenue Forecast'!AF6*VLOOKUP(IF(Assumptions!$D$83=2,'Revenue Forecast'!$BD$34+'Revenue Forecast'!$BE$34,'Revenue Forecast'!$BD$34),Assumptions!$B$67:$C$69,2,TRUE),0) | AG7: =IFERROR('Revenue Forecast'!AG6*VLOOKUP(IF(Assumptions!$D$83=2,'Revenue Forecast'!$BD$34+'Revenue Forecast'!$BE$34,'Revenue Forecast'!$BD$34),Assumptions!$B$67:$C$69,2,TRUE),0) | AH7: =IFERROR('Revenue Forecast'!AH6*VLOOKUP(IF(Assumptions!$D$83=2,'Revenue Forecast'!$BD$34+'Revenue Forecast'!$BE$34,'Revenue Forecast'!$BD$34),Assumptions!$B$67:$C$69,2,TRUE),0) | AI7: =IFERROR('Revenue Forecast'!AI6*VLOOKUP(IF(Assumptions!$D$83=2,'Revenue Forecast'!$BD$34+'Revenue Forecast'!$BE$34,'Revenue Forecast'!$BD$34),Assumptions!$B$67:$C$69,2,TRUE),0) | AJ7: =IFERROR('Revenue Forecast'!AJ6*VLOOKUP(IF(Assumptions!$D$83=2,'Revenue Forecast'!$BD$34+'Revenue Forecast'!$BE$34,'Revenue Forecast'!$BD$34),Assumptions!$B$67:$C$69,2,TRUE),0) | ... AN7: =IFERROR('Revenue Forecast'!AN6*VLOOKUP(IF(Assumptions!$D$83=2,'Revenue Forecast'!$BD$34+'Revenue Forecast'!$BE$34,'Revenue Forecast'!$BD$34),Assumptions!$B$67:$C$69,2,TRUE),0) | AO7: =IFERROR('Revenue Forecast'!AO6*VLOOKUP(IF(Assumptions!$D$83=2,'Revenue Forecast'!$BE$34+'Revenue Forecast'!$BF$34,'Revenue Forecast'!$BE$34),Assumptions!$B$67:$C$69,2,TRUE),0) | AP7: =IFERROR('Revenue Forecast'!AP6*VLOOKUP(IF(Assumptions!$D$83=2,'Revenue Forecast'!$BE$34+'Revenue Forecast'!$BF$34,'Revenue Forecast'!$BE$34),Assumptions!$B$67:$C$69,2,TRUE),0) | AQ7: =IFERROR('Revenue Forecast'!AQ6*VLOOKUP(IF(Assumptions!$D$83=2,'Revenue Forecast'!$BE$34+'Revenue Forecast'!$BF$34,'Revenue Forecast'!$BE$34),Assumptions!$B$67:$C$69,2,TRUE),0) | AR7: =IFERROR('Revenue Forecast'!AR6*VLOOKUP(IF(Assumptions!$D$83=2,'Revenue Forecast'!$BE$34+'Revenue Forecast'!$BF$34,'Revenue Forecast'!$BE$34),Assumptions!$B$67:$C$69,2,TRUE),0) | AS7: =IFERROR('Revenue Forecast'!AS6*VLOOKUP(IF(Assumptions!$D$83=2,'Revenue Forecast'!$BE$34+'Revenue Forecast'!$BF$34,'Revenue Forecast'!$BE$34),Assumptions!$B$67:$C$69,2,TRUE),0) | AT7: =IFERROR('Revenue Forecast'!AT6*VLOOKUP(IF(Assumptions!$D$83=2,'Revenue Forecast'!$BE$34+'Revenue Forecast'!$BF$34,'Revenue Forecast'!$BE$34),Assumptions!$B$67:$C$69,2,TRUE),0) | AU7: =IFERROR('Revenue Forecast'!AU6*VLOOKUP(IF(Assumptions!$D$83=2,'Revenue Forecast'!$BE$34+'Revenue Forecast'!$BF$34,'Revenue Forecast'!$BE$34),Assumptions!$B$67:$C$69,2,TRUE),0) | AV7: =IFERROR('Revenue Forecast'!AV6*VLOOKUP(IF(Assumptions!$D$83=2,'Revenue Forecast'!$BE$34+'Revenue Forecast'!$BF$34,'Revenue Forecast'!$BE$34),Assumptions!$B$67:$C$69,2,TRUE),0) | ... AZ7: =IFERROR('Revenue Forecast'!AZ6*VLOOKUP(IF(Assumptions!$D$83=2,'Revenue Forecast'!$BE$34+'Revenue Forecast'!$BF$34,'Revenue Forecast'!$BE$34),Assumptions!$B$67:$C$69,2,TRUE),0) | BC7: =SUM(Q7:AB7) | BD7: =SUM(AC7:AN7) | BE7: =SUM(AO7:AZ7) | BF7: ='Revenue Forecast'!BF6*VLOOKUP(IF(Assumptions!$D$83=2,'Revenue Forecast'!$BF$34+Assumptions!$G$21,'Revenue Forecast'!$BF$34),Assumptions!$B$67:$C$69,2,TRUE) | BH7: units x ketel build cost. the tier basis is set by the switch on Assumptions row 83
B8: Upsell | D8: € | Q8: ='Revenue Forecast'!Q6*SUMPRODUCT(Assumptions!$E$112:$E$114,Assumptions!$G$112:$G$114) | R8: ='Revenue Forecast'!R6*SUMPRODUCT(Assumptions!$E$112:$E$114,Assumptions!$G$112:$G$114) | S8: ='Revenue Forecast'!S6*SUMPRODUCT(Assumptions!$E$112:$E$114,Assumptions!$G$112:$G$114) | T8: ='Revenue Forecast'!T6*SUMPRODUCT(Assumptions!$E$112:$E$114,Assumptions!$G$112:$G$114) | U8: ='Revenue Forecast'!U6*SUMPRODUCT(Assumptions!$E$112:$E$114,Assumptions!$G$112:$G$114) | V8: ='Revenue Forecast'!V6*SUMPRODUCT(Assumptions!$E$112:$E$114,Assumptions!$G$112:$G$114) | W8: ='Revenue Forecast'!W6*SUMPRODUCT(Assumptions!$E$112:$E$114,Assumptions!$G$112:$G$114) | X8: ='Revenue Forecast'!X6*SUMPRODUCT(Assumptions!$E$112:$E$114,Assumptions!$G$112:$G$114) | ... AZ8: ='Revenue Forecast'!AZ6*SUMPRODUCT(Assumptions!$E$112:$E$114,Assumptions!$G$112:$G$114) | BC8: =SUM(Q8:AB8) | BD8: =SUM(AC8:AN8) | BE8: =SUM(AO8:AZ8) | BF8: ='Revenue Forecast'!BF6*SUMPRODUCT(Assumptions!$E$112:$E$114,Assumptions!$G$112:$G$114) | BH8: units x upsell cost (attach % x cost of each item)
B9: Total TTK COGS | D9: € | Q9: =sum(Q7:Q8) | R9: =sum(R7:R8) | S9: =sum(S7:S8) | T9: =sum(T7:T8) | U9: =sum(U7:U8) | V9: =sum(V7:V8) | W9: =sum(W7:W8) | X9: =sum(X7:X8) | ... AZ9: =sum(AZ7:AZ8) | BB9: =SUM(E9:P9) | BC9: =SUM(Q9:AB9) | BD9: =SUM(AC9:AN9) | BE9: =SUM(AO9:AZ9) | BF9: =sum(BF7:BF8) | BH9: machine cost + upsell cost
B11: COMBI+
B12: Combi+ | Q12: =IFERROR('Revenue Forecast'!Q12*(VLOOKUP('Revenue Forecast'!$BC$34,Assumptions!$B$67:$C$69,2,TRUE)+VLOOKUP('Revenue Forecast'!$BC$12,Assumptions!$B$78:$C$80,2,TRUE)+Assumptions!$E$74),0) | R12: =IFERROR('Revenue Forecast'!R12*(VLOOKUP('Revenue Forecast'!$BC$34,Assumptions!$B$67:$C$69,2,TRUE)+VLOOKUP('Revenue Forecast'!$BC$12,Assumptions!$B$78:$C$80,2,TRUE)+Assumptions!$E$74),0) | S12: =IFERROR('Revenue Forecast'!S12*(VLOOKUP('Revenue Forecast'!$BC$34,Assumptions!$B$67:$C$69,2,TRUE)+VLOOKUP('Revenue Forecast'!$BC$12,Assumptions!$B$78:$C$80,2,TRUE)+Assumptions!$E$74),0) | T12: =IFERROR('Revenue Forecast'!T12*(VLOOKUP('Revenue Forecast'!$BC$34,Assumptions!$B$67:$C$69,2,TRUE)+VLOOKUP('Revenue Forecast'!$BC$12,Assumptions!$B$78:$C$80,2,TRUE)+Assumptions!$E$74),0) | U12: =IFERROR('Revenue Forecast'!U12*(VLOOKUP('Revenue Forecast'!$BC$34,Assumptions!$B$67:$C$69,2,TRUE)+VLOOKUP('Revenue Forecast'!$BC$12,Assumptions!$B$78:$C$80,2,TRUE)+Assumptions!$E$74),0) | V12: =IFERROR('Revenue Forecast'!V12*(VLOOKUP('Revenue Forecast'!$BC$34,Assumptions!$B$67:$C$69,2,TRUE)+VLOOKUP('Revenue Forecast'!$BC$12,Assumptions!$B$78:$C$80,2,TRUE)+Assumptions!$E$74),0) | W12: =IFERROR('Revenue Forecast'!W12*(VLOOKUP('Revenue Forecast'!$BC$34,Assumptions!$B$67:$C$69,2,TRUE)+VLOOKUP('Revenue Forecast'!$BC$12,Assumptions!$B$78:$C$80,2,TRUE)+Assumptions!$E$74),0) | X12: =IFERROR('Revenue Forecast'!X12*(VLOOKUP('Revenue Forecast'!$BC$34,Assumptions!$B$67:$C$69,2,TRUE)+VLOOKUP('Revenue Forecast'!$BC$12,Assumptions!$B$78:$C$80,2,TRUE)+Assumptions!$E$74),0) | ... AB12: =IFERROR('Revenue Forecast'!AB12*(VLOOKUP('Revenue Forecast'!$BC$34,Assumptions!$B$67:$C$69,2,TRUE)+VLOOKUP('Revenue Forecast'!$BC$12,Assumptions!$B$78:$C$80,2,TRUE)+Assumptions!$E$74),0) | AC12: =IFERROR('Revenue Forecast'!AC12*(VLOOKUP(IF(Assumptions!$D$83=2,'Revenue Forecast'!$BD$34+'Revenue Forecast'!$BE$34,'Revenue Forecast'!$BD$34),Assumptions!$B$67:$C$69,2,TRUE)+VLOOKUP(IF(Assumptions!$D$83=2,'Revenue Forecast'!$BD$12+'Revenue Forecast'!$BE$12,'Revenue Forecast'!$BD$12),Assumptions!$B$78:$C$80,2,TRUE)+Assumptions!$E$74),0) | AD12: =IFERROR('Revenue Forecast'!AD12*(VLOOKUP(IF(Assumptions!$D$83=2,'Revenue Forecast'!$BD$34+'Revenue Forecast'!$BE$34,'Revenue Forecast'!$BD$34),Assumptions!$B$67:$C$69,2,TRUE)+VLOOKUP(IF(Assumptions!$D$83=2,'Revenue Forecast'!$BD$12+'Revenue Forecast'!$BE$12,'Revenue Forecast'!$BD$12),Assumptions!$B$78:$C$80,2,TRUE)+Assumptions!$E$74),0) | AE12: =IFERROR('Revenue Forecast'!AE12*(VLOOKUP(IF(Assumptions!$D$83=2,'Revenue Forecast'!$BD$34+'Revenue Forecast'!$BE$34,'Revenue Forecast'!$BD$34),Assumptions!$B$67:$C$69,2,TRUE)+VLOOKUP(IF(Assumptions!$D$83=2,'Revenue Forecast'!$BD$12+'Revenue Forecast'!$BE$12,'Revenue Forecast'!$BD$12),Assumptions!$B$78:$C$80,2,TRUE)+Assumptions!$E$74),0) | AF12: =IFERROR('Revenue Forecast'!AF12*(VLOOKUP(IF(Assumptions!$D$83=2,'Revenue Forecast'!$BD$34+'Revenue Forecast'!$BE$34,'Revenue Forecast'!$BD$34),Assumptions!$B$67:$C$69,2,TRUE)+VLOOKUP(IF(Assumptions!$D$83=2,'Revenue Forecast'!$BD$12+'Revenue Forecast'!$BE$12,'Revenue Forecast'!$BD$12),Assumptions!$B$78:$C$80,2,TRUE)+Assumptions!$E$74),0) | AG12: =IFERROR('Revenue Forecast'!AG12*(VLOOKUP(IF(Assumptions!$D$83=2,'Revenue Forecast'!$BD$34+'Revenue Forecast'!$BE$34,'Revenue Forecast'!$BD$34),Assumptions!$B$67:$C$69,2,TRUE)+VLOOKUP(IF(Assumptions!$D$83=2,'Revenue Forecast'!$BD$12+'Revenue Forecast'!$BE$12,'Revenue Forecast'!$BD$12),Assumptions!$B$78:$C$80,2,TRUE)+Assumptions!$E$74),0) | AH12: =IFERROR('Revenue Forecast'!AH12*(VLOOKUP(IF(Assumptions!$D$83=2,'Revenue Forecast'!$BD$34+'Revenue Forecast'!$BE$34,'Revenue Forecast'!$BD$34),Assumptions!$B$67:$C$69,2,TRUE)+VLOOKUP(IF(Assumptions!$D$83=2,'Revenue Forecast'!$BD$12+'Revenue Forecast'!$BE$12,'Revenue Forecast'!$BD$12),Assumptions!$B$78:$C$80,2,TRUE)+Assumptions!$E$74),0) | AI12: =IFERROR('Revenue Forecast'!AI12*(VLOOKUP(IF(Assumptions!$D$83=2,'Revenue Forecast'!$BD$34+'Revenue Forecast'!$BE$34,'Revenue Forecast'!$BD$34),Assumptions!$B$67:$C$69,2,TRUE)+VLOOKUP(IF(Assumptions!$D$83=2,'Revenue Forecast'!$BD$12+'Revenue Forecast'!$BE$12,'Revenue Forecast'!$BD$12),Assumptions!$B$78:$C$80,2,TRUE)+Assumptions!$E$74),0) | AJ12: =IFERROR('Revenue Forecast'!AJ12*(VLOOKUP(IF(Assumptions!$D$83=2,'Revenue Forecast'!$BD$34+'Revenue Forecast'!$BE$34,'Revenue Forecast'!$BD$34),Assumptions!$B$67:$C$69,2,TRUE)+VLOOKUP(IF(Assumptions!$D$83=2,'Revenue Forecast'!$BD$12+'Revenue Forecast'!$BE$12,'Revenue Forecast'!$BD$12),Assumptions!$B$78:$C$80,2,TRUE)+Assumptions!$E$74),0) | ... AN12: =IFERROR('Revenue Forecast'!AN12*(VLOOKUP(IF(Assumptions!$D$83=2,'Revenue Forecast'!$BD$34+'Revenue Forecast'!$BE$34,'Revenue Forecast'!$BD$34),Assumptions!$B$67:$C$69,2,TRUE)+VLOOKUP(IF(Assumptions!$D$83=2,'Revenue Forecast'!$BD$12+'Revenue Forecast'!$BE$12,'Revenue Forecast'!$BD$12),Assumptions!$B$78:$C$80,2,TRUE)+Assumptions!$E$74),0) | AO12: =IFERROR('Revenue Forecast'!AO12*(VLOOKUP(IF(Assumptions!$D$83=2,'Revenue Forecast'!$BE$34+'Revenue Forecast'!$BF$34,'Revenue Forecast'!$BE$34),Assumptions!$B$67:$C$69,2,TRUE)+VLOOKUP(IF(Assumptions!$D$83=2,'Revenue Forecast'!$BE$12+'Revenue Forecast'!$BF$12,'Revenue Forecast'!$BE$12),Assumptions!$B$78:$C$80,2,TRUE)+Assumptions!$E$74),0) | AP12: =IFERROR('Revenue Forecast'!AP12*(VLOOKUP(IF(Assumptions!$D$83=2,'Revenue Forecast'!$BE$34+'Revenue Forecast'!$BF$34,'Revenue Forecast'!$BE$34),Assumptions!$B$67:$C$69,2,TRUE)+VLOOKUP(IF(Assumptions!$D$83=2,'Revenue Forecast'!$BE$12+'Revenue Forecast'!$BF$12,'Revenue Forecast'!$BE$12),Assumptions!$B$78:$C$80,2,TRUE)+Assumptions!$E$74),0) | AQ12: =IFERROR('Revenue Forecast'!AQ12*(VLOOKUP(IF(Assumptions!$D$83=2,'Revenue Forecast'!$BE$34+'Revenue Forecast'!$BF$34,'Revenue Forecast'!$BE$34),Assumptions!$B$67:$C$69,2,TRUE)+VLOOKUP(IF(Assumptions!$D$83=2,'Revenue Forecast'!$BE$12+'Revenue Forecast'!$BF$12,'Revenue Forecast'!$BE$12),Assumptions!$B$78:$C$80,2,TRUE)+Assumptions!$E$74),0) | AR12: =IFERROR('Revenue Forecast'!AR12*(VLOOKUP(IF(Assumptions!$D$83=2,'Revenue Forecast'!$BE$34+'Revenue Forecast'!$BF$34,'Revenue Forecast'!$BE$34),Assumptions!$B$67:$C$69,2,TRUE)+VLOOKUP(IF(Assumptions!$D$83=2,'Revenue Forecast'!$BE$12+'Revenue Forecast'!$BF$12,'Revenue Forecast'!$BE$12),Assumptions!$B$78:$C$80,2,TRUE)+Assumptions!$E$74),0) | AS12: =IFERROR('Revenue Forecast'!AS12*(VLOOKUP(IF(Assumptions!$D$83=2,'Revenue Forecast'!$BE$34+'Revenue Forecast'!$BF$34,'Revenue Forecast'!$BE$34),Assumptions!$B$67:$C$69,2,TRUE)+VLOOKUP(IF(Assumptions!$D$83=2,'Revenue Forecast'!$BE$12+'Revenue Forecast'!$BF$12,'Revenue Forecast'!$BE$12),Assumptions!$B$78:$C$80,2,TRUE)+Assumptions!$E$74),0) | AT12: =IFERROR('Revenue Forecast'!AT12*(VLOOKUP(IF(Assumptions!$D$83=2,'Revenue Forecast'!$BE$34+'Revenue Forecast'!$BF$34,'Revenue Forecast'!$BE$34),Assumptions!$B$67:$C$69,2,TRUE)+VLOOKUP(IF(Assumptions!$D$83=2,'Revenue Forecast'!$BE$12+'Revenue Forecast'!$BF$12,'Revenue Forecast'!$BE$12),Assumptions!$B$78:$C$80,2,TRUE)+Assumptions!$E$74),0) | AU12: =IFERROR('Revenue Forecast'!AU12*(VLOOKUP(IF(Assumptions!$D$83=2,'Revenue Forecast'!$BE$34+'Revenue Forecast'!$BF$34,'Revenue Forecast'!$BE$34),Assumptions!$B$67:$C$69,2,TRUE)+VLOOKUP(IF(Assumptions!$D$83=2,'Revenue Forecast'!$BE$12+'Revenue Forecast'!$BF$12,'Revenue Forecast'!$BE$12),Assumptions!$B$78:$C$80,2,TRUE)+Assumptions!$E$74),0) | AV12: =IFERROR('Revenue Forecast'!AV12*(VLOOKUP(IF(Assumptions!$D$83=2,'Revenue Forecast'!$BE$34+'Revenue Forecast'!$BF$34,'Revenue Forecast'!$BE$34),Assumptions!$B$67:$C$69,2,TRUE)+VLOOKUP(IF(Assumptions!$D$83=2,'Revenue Forecast'!$BE$12+'Revenue Forecast'!$BF$12,'Revenue Forecast'!$BE$12),Assumptions!$B$78:$C$80,2,TRUE)+Assumptions!$E$74),0) | ... AZ12: =IFERROR('Revenue Forecast'!AZ12*(VLOOKUP(IF(Assumptions!$D$83=2,'Revenue Forecast'!$BE$34+'Revenue Forecast'!$BF$34,'Revenue Forecast'!$BE$34),Assumptions!$B$67:$C$69,2,TRUE)+VLOOKUP(IF(Assumptions!$D$83=2,'Revenue Forecast'!$BE$12+'Revenue Forecast'!$BF$12,'Revenue Forecast'!$BE$12),Assumptions!$B$78:$C$80,2,TRUE)+Assumptions!$E$74),0) | BC12: =SUM(Q12:AB12) | BD12: =SUM(AC12:AN12) | BE12: =SUM(AO12:AZ12) | BF12: ='Revenue Forecast'!BF12*(VLOOKUP(IF(Assumptions!$D$83=2,'Revenue Forecast'!$BF$34+Assumptions!$G$21,'Revenue Forecast'!$BF$34),Assumptions!$B$67:$C$69,2,TRUE)+VLOOKUP(IF(Assumptions!$D$83=2,'Revenue Forecast'!$BF$12+Assumptions!$G$24,'Revenue Forecast'!$BF$12),Assumptions!$B$78:$C$80,2,TRUE)+Assumptions!$E$74) | BH12: units x (ketel tier + outdoor unit tier + shipping), ketel tier per the row-83 switch
B13: Upsell | Q13: ='Revenue Forecast'!Q12*SUMPRODUCT(Assumptions!$E$112:$E$114,Assumptions!$G$112:$G$114) | R13: ='Revenue Forecast'!R12*SUMPRODUCT(Assumptions!$E$112:$E$114,Assumptions!$G$112:$G$114) | S13: ='Revenue Forecast'!S12*SUMPRODUCT(Assumptions!$E$112:$E$114,Assumptions!$G$112:$G$114) | T13: ='Revenue Forecast'!T12*SUMPRODUCT(Assumptions!$E$112:$E$114,Assumptions!$G$112:$G$114) | U13: ='Revenue Forecast'!U12*SUMPRODUCT(Assumptions!$E$112:$E$114,Assumptions!$G$112:$G$114) | V13: ='Revenue Forecast'!V12*SUMPRODUCT(Assumptions!$E$112:$E$114,Assumptions!$G$112:$G$114) | W13: ='Revenue Forecast'!W12*SUMPRODUCT(Assumptions!$E$112:$E$114,Assumptions!$G$112:$G$114) | X13: ='Revenue Forecast'!X12*SUMPRODUCT(Assumptions!$E$112:$E$114,Assumptions!$G$112:$G$114) | ... AZ13: ='Revenue Forecast'!AZ12*SUMPRODUCT(Assumptions!$E$112:$E$114,Assumptions!$G$112:$G$114) | BC13: =SUM(Q13:AB13) | BD13: =SUM(AC13:AN13) | BE13: =SUM(AO13:AZ13) | BF13: ='Revenue Forecast'!BF12*SUMPRODUCT(Assumptions!$E$112:$E$114,Assumptions!$G$112:$G$114) | BH13: units x upsell cost
B14: Total Combi+ COGS | Q14: =sum(Q12:Q13) | R14: =sum(R12:R13) | S14: =sum(S12:S13) | T14: =sum(T12:T13) | U14: =sum(U12:U13) | V14: =sum(V12:V13) | W14: =sum(W12:W13) | X14: =sum(X12:X13) | ... AZ14: =sum(AZ12:AZ13) | BC14: =sum(BC12:BC13) | BD14: =sum(BD12:BD13) | BE14: =sum(BE12:BE13) | BF14: =sum(BF12:BF13) | BH14: machine cost + upsell cost
B16: INSTALLATION
B17: Installation COGS (pass-through, = installation revenue) | D17: € | Q17: ='Revenue Forecast'!Q19 | R17: ='Revenue Forecast'!R19 | S17: ='Revenue Forecast'!S19 | T17: ='Revenue Forecast'!T19 | U17: ='Revenue Forecast'!U19 | V17: ='Revenue Forecast'!V19 | W17: ='Revenue Forecast'!W19 | X17: ='Revenue Forecast'!X19 | ... AZ17: ='Revenue Forecast'!AZ19 | BB17: ='Revenue Forecast'!BB19 | BC17: ='Revenue Forecast'!BC19 | BD17: ='Revenue Forecast'!BD19 | BE17: ='Revenue Forecast'!BE19 | BF17: ='Revenue Forecast'!BF19 | BH17: same number as installation revenue. pass-through, zero margin
B19: SERVICE REVENUES
B20: Total Service Revenue | D20: € | Q20: ='Revenue Forecast'!Q34*SUMPRODUCT(Assumptions!$E$120:$E$121,Assumptions!$G$120:$G$121)+E20 | R20: ='Revenue Forecast'!R34*SUMPRODUCT(Assumptions!$E$120:$E$121,Assumptions!$G$120:$G$121)+F20 | S20: ='Revenue Forecast'!S34*SUMPRODUCT(Assumptions!$E$120:$E$121,Assumptions!$G$120:$G$121)+G20 | T20: ='Revenue Forecast'!T34*SUMPRODUCT(Assumptions!$E$120:$E$121,Assumptions!$G$120:$G$121)+H20 | U20: ='Revenue Forecast'!U34*SUMPRODUCT(Assumptions!$E$120:$E$121,Assumptions!$G$120:$G$121)+I20 | V20: ='Revenue Forecast'!V34*SUMPRODUCT(Assumptions!$E$120:$E$121,Assumptions!$G$120:$G$121)+J20 | W20: ='Revenue Forecast'!W34*SUMPRODUCT(Assumptions!$E$120:$E$121,Assumptions!$G$120:$G$121)+K20 | X20: ='Revenue Forecast'!X34*SUMPRODUCT(Assumptions!$E$120:$E$121,Assumptions!$G$120:$G$121)+L20 | ... AZ20: ='Revenue Forecast'!AZ34*SUMPRODUCT(Assumptions!$E$120:$E$121,Assumptions!$G$120:$G$121)+AN20 | BB20: =SUM(E20:P20) | BC20: =SUM(Q20:AB20) | BD20: =sum(AC20:AN20) | BE20: =sum(AO20:AZ20)+BD20 | BF20: ='Revenue Forecast'!BF34*SUMPRODUCT(Assumptions!$E$120:$E$121,Assumptions!$G$120:$G$121)+BE20 | BH20: units x cost per service contract + last year's, stacks like the revenue
B21: Warranty reserve (above the 3% in the BOM) | E21: 0 | F21: 0 | G21: 0 | H21: 0 | I21: 0 | J21: 0 | K21: 0 | L21: 0 | M21: 0 | N21: 0 | O21: 0 | P21: 0 | Q21: 0 | R21: 0 | S21: 0 | T21: 0 | U21: 0 | V21: 0 | W21: 0 | X21: 0 | Y21: 0 | Z21: 0 | AA21: 0 | AB21: 0 | AC21: ='Growth Engine'!F91 | AD21: ='Growth Engine'!G91 | AE21: ='Growth Engine'!H91 | AF21: ='Growth Engine'!I91 | AG21: ='Growth Engine'!J91 | AH21: ='Growth Engine'!K91 | AI21: ='Growth Engine'!L91 | AJ21: ='Growth Engine'!M91 | ... AZ21: ='Growth Engine'!AC91 | BB21: 0 | BC21: 0 | BD21: =SUM(AC21:AN21) | BE21: =SUM(AO21:AZ21) | BF21: ='Growth Engine'!BE91 | BH21: a real warranty reserve on a first-generation turbine machine, on top of the BOM provision
B22: TOTAL COGS | E22: =E9+E14+E17+E20+E21 | F22: =F9+F14+F17+F20+F21 | G22: =G9+G14+G17+G20+G21 | H22: =H9+H14+H17+H20+H21 | I22: =I9+I14+I17+I20+I21 | J22: =J9+J14+J17+J20+J21 | K22: =K9+K14+K17+K20+K21 | L22: =L9+L14+L17+L20+L21 | ... AZ22: =AZ9+AZ14+AZ17+AZ20+AZ21 | BB22: =BB9+BB14+BB17+BB20+BB21 | BC22: =BC9+BC14+BC17+BC20+BC21 | BD22: =BD9+BD14+BD17+BD20+BD21 | BE22: =BE9+BE14+BE17+BE20+BE21 | BF22: =BF9+BF14+BF17+BF20+BF21 | BH22: TTK + Combi+ + installation + service costs

Sheet OPEX
B1: Tarnoc B.V. — OPEX Forecast (€, negative = cost) | U1: Actual | V1: Projected
G2: 2025 | S2: 2026 | AE2: 2027 | AQ2: 2028
G3: 45658 | H3: 45689 | I3: 45717 | J3: 45748 | K3: 45778 | L3: 45809 | M3: 45839 | N3: 45870 | O3: 45901 | P3: 45931 | Q3: 45962 | R3: 45992 | S3: 46023 | T3: 46054 | U3: 46082 | V3: 46113 | W3: 46143 | X3: 46174 | Y3: 46204 | Z3: 46235 | AA3: 46266 | AB3: 46296 | AC3: 46327 | AD3: 46357 | AE3: 46388 | AF3: 46419 | AG3: 46447 | AH3: 46478 | AI3: 46508 | AJ3: 46539 | AK3: 46569 | AL3: 46600 | AM3: 46631 | AN3: 46661 | AO3: 46692 | AP3: 46722 | AQ3: 46753 | AR3: 46784 | AS3: 46813 | AT3: 46844 | AU3: 46874 | AV3: 46905 | AW3: 46935 | AX3: 46966 | AY3: 46997 | AZ3: 47027 | BA3: 47058 | BB3: 47088 | BD3: 2025 | BE3: 2026 | BF3: 2027 | BG3: 2028 | BH3: 2029 | BK3: what this row does
B5: PERSONNEL
B6: R&D | D6: € | O6: =Personnel!Q251 | P6: =Personnel!R251 | Q6: =Personnel!S251 | R6: =Personnel!T251 | S6: =Personnel!U251 | T6: =Personnel!V251 | U6: =Personnel!W251 | V6: =Personnel!X251 | ... BB6: =Personnel!BD251 | BD6: =SUM(G6:R6) | BE6: =SUM(S6:AD6) | BF6: =SUM(AE6:AP6) | BG6: =SUM(AQ6:BB6) | BH6: =sum(Personnel!BE251:BP251) | BI6: =BH6*('Financial Statements'!$BE$7/'Financial Statements'!$BD$7)^0.5 | BK6: R&D salary bill, pulled from the Personnel tab
B7: S&M | D7: € | O7: =Personnel!Q252 | P7: =Personnel!R252 | Q7: =Personnel!S252 | R7: =Personnel!T252 | S7: =Personnel!U252 | T7: =Personnel!V252 | U7: =Personnel!W252 | V7: =Personnel!X252 | ... BB7: =Personnel!BD252 | BD7: =SUM(G7:R7) | BE7: =SUM(S7:AD7) | BF7: =SUM(AE7:AP7) | BG7: =SUM(AQ7:BB7) | BH7: =sum(Personnel!BE252:BP252) | BI7: =BH7*('Financial Statements'!$BE$7/'Financial Statements'!$BD$7)^0.5 | BK7: S&M salary bill, pulled from Personnel
B8: G&A | D8: € | O8: =Personnel!Q253 | P8: =Personnel!R253 | Q8: =Personnel!S253 | R8: =Personnel!T253 | S8: =Personnel!U253 | T8: =Personnel!V253 | U8: =Personnel!W253 | V8: =Personnel!X253 | ... BB8: =Personnel!BD253 | BD8: =SUM(G8:R8) | BE8: =SUM(S8:AD8) | BF8: =SUM(AE8:AP8) | BG8: =SUM(AQ8:BB8) | BH8: =sum(Personnel!BE253:BP253) | BI8: =BH8*('Financial Statements'!$BE$7/'Financial Statements'!$BD$7)^0.2 | BK8: G&A salary bill, pulled from Personnel
B9: Total Personnel | D9: € | G9: =SUM(G6:G8) | H9: =SUM(H6:H8) | I9: =SUM(I6:I8) | J9: =SUM(J6:J8) | K9: =SUM(K6:K8) | L9: =SUM(L6:L8) | M9: =SUM(M6:M8) | N9: =SUM(N6:N8) | O9: =sum(O6:O8) | P9: =sum(P6:P8) | Q9: =sum(Q6:Q8) | R9: =sum(R6:R8) | S9: =sum(S6:S8) | T9: =sum(T6:T8) | U9: =sum(U6:U8) | V9: =sum(V6:V8) | ... BB9: =sum(BB6:BB8) | BD9: =SUM(G9:R9) | BE9: =SUM(S9:AD9) | BF9: =SUM(AE9:AP9) | BG9: =SUM(AQ9:BB9) | BH9: =sum(BH6:BH8) | BK9: the three salary lines added
B11: NON-PERSONNEL
B13: R&D COSTS
B14: Kicker Development Cost | D14: € | R14: =Assumptions!E94 | BD14: =SUM(G14:R14) | BE14: =SUM(S14:AD14) | BF14: =SUM(AE14:AP14) | BG14: =SUM(AQ14:BB14) | BH14: 0 | BK14: one-off from Assumptions, booked in its month
B15: Ongoing Development costs | D15: € | S15: {=INDEX(Assumptions!$E$92:$I$92,MATCH(YEAR(S$3),Assumptions!$E$87:$I$87,0))} | T15: {=INDEX(Assumptions!$E$92:$I$92,MATCH(YEAR(T$3),Assumptions!$E$87:$I$87,0))} | U15: {=INDEX(Assumptions!$E$92:$I$92,MATCH(YEAR(U$3),Assumptions!$E$87:$I$87,0))} | V15: {=INDEX(Assumptions!$E$92:$I$92,MATCH(YEAR(V$3),Assumptions!$E$87:$I$87,0))} | W15: {=INDEX(Assumptions!$E$92:$I$92,MATCH(YEAR(W$3),Assumptions!$E$87:$I$87,0))} | X15: {=INDEX(Assumptions!$E$92:$I$92,MATCH(YEAR(X$3),Assumptions!$E$87:$I$87,0))} | Y15: {=INDEX(Assumptions!$E$92:$I$92,MATCH(YEAR(Y$3),Assumptions!$E$87:$I$87,0))} | Z15: {=INDEX(Assumptions!$E$92:$I$92,MATCH(YEAR(Z$3),Assumptions!$E$87:$I$87,0))} | ... BB15: {=INDEX(Assumptions!$E$92:$I$92,MATCH(YEAR(BB$3),Assumptions!$E$87:$I$87,0))} | BD15: =SUM(G15:R15) | BE15: =SUM(S15:AD15) | BF15: =SUM(AE15:AP15) | BG15: =SUM(AQ15:BB15) | BH15: =BG15*('Financial Statements'!$BE$7/'Financial Statements'!$BD$7)^0.4 | BK15: from Assumptions; 2029 scaled off 2028 by revenue growth
B16: Assembly partner | D16: € | AB16: =Assumptions!E97 | BD16: =SUM(G16:R16) | BE16: =SUM(S16:AC16) | BF16: =SUM(AE16:AP16) | BG16: =SUM(AQ16:BB16) | BH16: 0 | BK16: one-off from Assumptions, booked in its month
B17: Third party cost product development | D17: € | S17: {=INDEX(Assumptions!$E$93:$I$93,MATCH(YEAR(S$3),Assumptions!$E$87:$I$87,0))} | T17: {=INDEX(Assumptions!$E$93:$I$93,MATCH(YEAR(T$3),Assumptions!$E$87:$I$87,0))} | U17: {=INDEX(Assumptions!$E$93:$I$93,MATCH(YEAR(U$3),Assumptions!$E$87:$I$87,0))} | V17: {=INDEX(Assumptions!$E$93:$I$93,MATCH(YEAR(V$3),Assumptions!$E$87:$I$87,0))} | W17: {=INDEX(Assumptions!$E$93:$I$93,MATCH(YEAR(W$3),Assumptions!$E$87:$I$87,0))} | X17: {=INDEX(Assumptions!$E$93:$I$93,MATCH(YEAR(X$3),Assumptions!$E$87:$I$87,0))} | Y17: {=INDEX(Assumptions!$E$93:$I$93,MATCH(YEAR(Y$3),Assumptions!$E$87:$I$87,0))} | Z17: {=INDEX(Assumptions!$E$93:$I$93,MATCH(YEAR(Z$3),Assumptions!$E$87:$I$87,0))} | ... BB17: {=INDEX(Assumptions!$E$93:$I$93,MATCH(YEAR(BB$3),Assumptions!$E$87:$I$87,0))} | BD17: =SUM(G17:R17) | BE17: =SUM(S17:AD17) | BF17: =SUM(AE17:AP17) | BG17: =SUM(AQ17:BB17) | BH17: =BG17*('Financial Statements'!$BE$7/'Financial Statements'!$BD$7)^0.4 | BK17: from Assumptions; 2029 scaled off 2028 by revenue growth
B18: Tooling Fisher (result: 2%-3%) | D18: € | AC18: =Assumptions!E98 | BD18: =SUM(G18:R18) | BE18: =SUM(S18:AC18) | BF18: =SUM(AE18:AP18) | BG18: =SUM(AQ18:BB18) | BH18: 0 | BK18: one-off from Assumptions, booked in its month
B19: Total R&D | R19: =R14+R15+R16 | S19: =sum(S14:S18) | T19: =sum(T14:T18) | U19: =sum(U14:U18) | V19: =sum(V14:V18) | W19: =sum(W14:W18) | X19: =sum(X14:X18) | Y19: =sum(Y14:Y18) | Z19: =sum(Z14:Z18) | ... BB19: =sum(BB14:BB18) | BD19: =SUM(G19:R19) | BE19: =SUM(S19:AD19) | BF19: =SUM(AE19:AP19) | BG19: =SUM(AQ19:BB19) | BH19: =sum(BH14:BH18) | BK19: all the non-people R&D lines added
BE20: =BE19/BD19-1 | BF20: =BF19/BE19-1 | BG20: =BG19/BF19-1 | BH20: =BH19/BG19-1 | BK20: year-on-year change in R&D spend
B21: SALES & MARKETING
B22: Baseline Sales & Marketting | S22: {=INDEX(Assumptions!$E$90:$I$90,MATCH(YEAR(S$3),Assumptions!$E$87:$I$87,0))} | T22: {=INDEX(Assumptions!$E$90:$I$90,MATCH(YEAR(T$3),Assumptions!$E$87:$I$87,0))} | U22: {=INDEX(Assumptions!$E$90:$I$90,MATCH(YEAR(U$3),Assumptions!$E$87:$I$87,0))} | V22: {=INDEX(Assumptions!$E$90:$I$90,MATCH(YEAR(V$3),Assumptions!$E$87:$I$87,0))} | W22: {=INDEX(Assumptions!$E$90:$I$90,MATCH(YEAR(W$3),Assumptions!$E$87:$I$87,0))} | X22: {=INDEX(Assumptions!$E$90:$I$90,MATCH(YEAR(X$3),Assumptions!$E$87:$I$87,0))} | Y22: {=INDEX(Assumptions!$E$90:$I$90,MATCH(YEAR(Y$3),Assumptions!$E$87:$I$87,0))} | Z22: {=INDEX(Assumptions!$E$90:$I$90,MATCH(YEAR(Z$3),Assumptions!$E$87:$I$87,0))} | ... BB22: {=INDEX(Assumptions!$E$90:$I$90,MATCH(YEAR(BB$3),Assumptions!$E$87:$I$87,0))} | BD22: =SUM(G22:R22) | BE22: =SUM(S22:AD22) | BF22: =SUM(AE22:AP22) | BG22: =SUM(AQ22:BB22) | BH22: =BG22*('Financial Statements'!$BE$7/'Financial Statements'!$BD$7)^0.5 | BK22: baseline marketing from Assumptions; 2029 scaled off revenue growth
B23: Sales & Marketing (3rd party) | D23: € | S23: 7000 | T23: 7000 | U23: 7000 | V23: 7000 | W23: 7000 | X23: 7000 | Y23: 7000 | Z23: 7000 | AA23: 7000 | AB23: 10000 | AC23: 10000 | AD23: 10000 | AE23: =('Revenue Forecast'!AC6+'Revenue Forecast'!AC12)*VLOOKUP('Revenue Forecast'!AC33,Assumptions!$G$102:$H$109,2,TRUE) | AF23: =('Revenue Forecast'!AD6+'Revenue Forecast'!AD12)*VLOOKUP('Revenue Forecast'!AD33,Assumptions!$G$102:$H$109,2,TRUE) | AG23: =('Revenue Forecast'!AE6+'Revenue Forecast'!AE12)*VLOOKUP('Revenue Forecast'!AE33,Assumptions!$G$102:$H$109,2,TRUE) | AH23: =('Revenue Forecast'!AF6+'Revenue Forecast'!AF12)*VLOOKUP('Revenue Forecast'!AF33,Assumptions!$G$102:$H$109,2,TRUE) | AI23: =('Revenue Forecast'!AG6+'Revenue Forecast'!AG12)*VLOOKUP('Revenue Forecast'!AG33,Assumptions!$G$102:$H$109,2,TRUE) | AJ23: =('Revenue Forecast'!AH6+'Revenue Forecast'!AH12)*VLOOKUP('Revenue Forecast'!AH33,Assumptions!$G$102:$H$109,2,TRUE) | AK23: =('Revenue Forecast'!AI6+'Revenue Forecast'!AI12)*VLOOKUP('Revenue Forecast'!AI33,Assumptions!$G$102:$H$109,2,TRUE) | AL23: =('Revenue Forecast'!AJ6+'Revenue Forecast'!AJ12)*VLOOKUP('Revenue Forecast'!AJ33,Assumptions!$G$102:$H$109,2,TRUE) | ... BB23: =('Revenue Forecast'!AZ6+'Revenue Forecast'!AZ12)*VLOOKUP('Revenue Forecast'!AZ33,Assumptions!$G$102:$H$109,2,TRUE) | BD23: =SUM(G23:R23) | BE23: =SUM(S23:AD23) | BF23: =SUM(AE23:AP23) | BG23: =SUM(AQ23:BB23) | BH23: =('Revenue Forecast'!BF6+'Revenue Forecast'!BF12)*VLOOKUP('Revenue Forecast'!BF33,Assumptions!$G$102:$H$109,2,TRUE) | BK23: units sold x sales cost per unit, which falls as volume grows
B24: Customer journey (third party) | D24: € | R24: =Assumptions!$E$95 | X24: =Assumptions!E95 | BD24: =SUM(G24:R24) | BE24: =SUM(T24:AC24) | BF24: =SUM(AE24:AP24) | BG24: =SUM(AQ24:BB24) | BH24: =BG24*('Financial Statements'!$BE$7/'Financial Statements'!$BD$7)^0.5 | BK24: one-off from Assumptions; 2029 scaled off revenue growth
B25: Branding + Website (third party cost) | D25: € | R25: =Assumptions!$E$96 | W25: =Assumptions!E96 | BD25: =SUM(G25:R25) | BE25: =SUM(S25:AH25) | BF25: =SUM(AE25:AP25) | BG25: =SUM(AQ25:BB25) | BH25: =BG25*('Financial Statements'!$BE$7/'Financial Statements'!$BD$7)^0.5 | BK25: one-off from Assumptions; 2029 scaled off revenue growth
B26: Total S&M | G26: =SUM(G23:G25) | H26: =SUM(H23:H25) | I26: =SUM(I23:I25) | J26: =SUM(J23:J25) | K26: =SUM(K23:K25) | L26: =SUM(L23:L25) | M26: =SUM(M23:M25) | N26: =SUM(N23:N25) | ... R26: =SUM(R23:R25) | S26: =sum(S22:S25) | T26: =sum(T22:T25) | U26: =sum(U22:U25) | V26: =sum(V22:V25) | W26: =sum(W22:W25) | X26: =sum(X22:X25) | Y26: =sum(Y22:Y25) | Z26: =sum(Z22:Z25) | ... BB26: =sum(BB22:BB25) | BD26: =SUM(G26:R26) | BE26: =SUM(S26:AD26) | BF26: =SUM(AE26:AP26) | BG26: =SUM(AQ26:BB26) | BH26: =sum(BH22:BH25) | BK26: all the non-people sales & marketing lines added
BE27: =BE26/BD26-1 | BF27: =BF26/BE26-1 | BG27: =BG26/BF26-1 | BH27: =BH26/BG26-1 | BK27: year-on-year change in S&M spend
B28: G&A (NON-LABOUR)
B29: Office rent (part of General) | D29: € | G29: =Assumptions!$E$88 | H29: =Assumptions!$E$88 | I29: =Assumptions!$E$88 | J29: =Assumptions!$E$88 | K29: =Assumptions!$E$88 | L29: =Assumptions!$E$88 | M29: =Assumptions!$E$88 | N29: =Assumptions!$E$88 | ... R29: =Assumptions!$E$88 | S29: {=INDEX(Assumptions!$E$88:$I$88,MATCH(YEAR(S$3),Assumptions!$E$87:$I$87,0))} | T29: {=INDEX(Assumptions!$E$88:$I$88,MATCH(YEAR(T$3),Assumptions!$E$87:$I$87,0))} | U29: {=INDEX(Assumptions!$E$88:$I$88,MATCH(YEAR(U$3),Assumptions!$E$87:$I$87,0))} | V29: {=INDEX(Assumptions!$E$88:$I$88,MATCH(YEAR(V$3),Assumptions!$E$87:$I$87,0))} | W29: {=INDEX(Assumptions!$E$88:$I$88,MATCH(YEAR(W$3),Assumptions!$E$87:$I$87,0))} | X29: {=INDEX(Assumptions!$E$88:$I$88,MATCH(YEAR(X$3),Assumptions!$E$87:$I$87,0))} | Y29: {=INDEX(Assumptions!$E$88:$I$88,MATCH(YEAR(Y$3),Assumptions!$E$87:$I$87,0))} | Z29: {=INDEX(Assumptions!$E$88:$I$88,MATCH(YEAR(Z$3),Assumptions!$E$87:$I$87,0))} | ... BB29: {=INDEX(Assumptions!$E$88:$I$88,MATCH(YEAR(BB$3),Assumptions!$E$87:$I$87,0))} | BD29: =SUM(G29:R29) | BE29: =SUM(S29:AD29) | BF29: =SUM(AE29:AP29) | BG29: =SUM(AQ29:BB29) | BH29: =BG29*('Financial Statements'!$BE$7/'Financial Statements'!$BD$7)^0.2 | BK29: rent from Assumptions, growing each year
B30: Other General | D30: € | G30: =Assumptions!$E$89 | H30: =Assumptions!$E$89 | I30: =Assumptions!$E$89 | J30: =Assumptions!$E$89 | K30: =Assumptions!$E$89 | L30: =Assumptions!$E$89 | M30: =Assumptions!$E$89 | N30: =Assumptions!$E$89 | ... R30: =Assumptions!$E$89 | S30: {=INDEX(Assumptions!$E$89:$I$89,MATCH(YEAR(S$3),Assumptions!$E$87:$I$87,0))} | T30: {=INDEX(Assumptions!$E$89:$I$89,MATCH(YEAR(T$3),Assumptions!$E$87:$I$87,0))} | U30: {=INDEX(Assumptions!$E$89:$I$89,MATCH(YEAR(U$3),Assumptions!$E$87:$I$87,0))} | V30: {=INDEX(Assumptions!$E$89:$I$89,MATCH(YEAR(V$3),Assumptions!$E$87:$I$87,0))} | W30: {=INDEX(Assumptions!$E$89:$I$89,MATCH(YEAR(W$3),Assumptions!$E$87:$I$87,0))} | X30: {=INDEX(Assumptions!$E$89:$I$89,MATCH(YEAR(X$3),Assumptions!$E$87:$I$87,0))} | Y30: {=INDEX(Assumptions!$E$89:$I$89,MATCH(YEAR(Y$3),Assumptions!$E$87:$I$87,0))} | Z30: {=INDEX(Assumptions!$E$89:$I$89,MATCH(YEAR(Z$3),Assumptions!$E$87:$I$87,0))} | ... BB30: {=INDEX(Assumptions!$E$89:$I$89,MATCH(YEAR(BB$3),Assumptions!$E$87:$I$87,0))} | BD30: =SUM(G30:R30) | BE30: =SUM(S30:AD30) | BF30: =SUM(AE30:AP30) | BG30: =SUM(AQ30:BB30) | BH30: =BG30*('Financial Statements'!$BE$7/'Financial Statements'!$BD$7)^0.2 | BK30: other general costs from Assumptions, growing each year
B31: Finance & Legal etc. | D31: € | G31: =Assumptions!$E$91 | H31: =Assumptions!$E$91 | I31: =Assumptions!$E$91 | J31: =Assumptions!$E$91 | K31: =Assumptions!$E$91 | L31: =Assumptions!$E$91 | M31: =Assumptions!$E$91 | N31: =Assumptions!$E$91 | ... R31: =Assumptions!$E$91 | S31: {=INDEX(Assumptions!$E$91:$I$91,MATCH(YEAR(S$3),Assumptions!$E$87:$I$87,0))} | T31: {=INDEX(Assumptions!$E$91:$I$91,MATCH(YEAR(T$3),Assumptions!$E$87:$I$87,0))} | U31: {=INDEX(Assumptions!$E$91:$I$91,MATCH(YEAR(U$3),Assumptions!$E$87:$I$87,0))} | V31: {=INDEX(Assumptions!$E$91:$I$91,MATCH(YEAR(V$3),Assumptions!$E$87:$I$87,0))} | W31: {=INDEX(Assumptions!$E$91:$I$91,MATCH(YEAR(W$3),Assumptions!$E$87:$I$87,0))} | X31: {=INDEX(Assumptions!$E$91:$I$91,MATCH(YEAR(X$3),Assumptions!$E$87:$I$87,0))} | Y31: {=INDEX(Assumptions!$E$91:$I$91,MATCH(YEAR(Y$3),Assumptions!$E$87:$I$87,0))} | Z31: {=INDEX(Assumptions!$E$91:$I$91,MATCH(YEAR(Z$3),Assumptions!$E$87:$I$87,0))} | ... BB31: {=INDEX(Assumptions!$E$91:$I$91,MATCH(YEAR(BB$3),Assumptions!$E$87:$I$87,0))} | BD31: =SUM(G31:R31) | BE31: =SUM(S31:AD31) | BF31: =SUM(AE31:AP31) | BG31: =SUM(AQ31:BB31) | BH31: =BG31*('Financial Statements'!$BE$7/'Financial Statements'!$BD$7)^0.2 | BK31: finance & legal from Assumptions, growing each year
B32: Total G&A | S32: =sum(S29:S31) | T32: =sum(T29:T31) | U32: =sum(U29:U31) | V32: =sum(V29:V31) | W32: =sum(W29:W31) | X32: =sum(X29:X31) | Y32: =sum(Y29:Y31) | Z32: =sum(Z29:Z31) | ... BB32: =sum(BB29:BB31) | BD32: =SUM(G32:R32) | BE32: =SUM(S32:AD32) | BF32: =SUM(AE32:AP32) | BG32: =SUM(AQ32:BB32) | BH32: =sum(BH29:BH31) | BK32: the three G&A lines added
B34: Total non-personnell | D34: € | G34: =G32+G26+G19 | H34: =H32+H26+H19 | I34: =I32+I26+I19 | J34: =J32+J26+J19 | K34: =K32+K26+K19 | L34: =L32+L26+L19 | M34: =M32+M26+M19 | N34: =N32+N26+N19 | ... BB34: =BB32+BB26+BB19 | BD34: =SUM(G34:R34) | BE34: =SUM(S34:AD34) | BF34: =SUM(AE34:AP34) | BG34: =SUM(AQ34:BB34) | BH34: =BH32+BH26+BH19 | BK34: R&D + S&M + G&A, everything except salaries
B36: TOTAL OPEX | D36: € | G36: =G34+G9+G48 | H36: =H34+H9+H48 | I36: =I34+I9+I48 | J36: =J34+J9+J48 | K36: =K34+K9+K48 | L36: =L34+L9+L48 | M36: =M34+M9+M48 | N36: =N34+N9+N48 | ... BB36: =BB34+BB9+BB48 | BD36: =BD34+BD9+BD48 | BE36: =BE34+BE9+BE48 | BF36: =BF34+BF9+BF48 | BG36: =BG34+BG9+BG48 | BH36: =BH34+BH9+BH48 | BK36: salaries + all other operating costs
B38: Total R&D | D38: € | G38: =G19+G6+G49 | H38: =H19+H6+H49 | I38: =I19+I6+I49 | J38: =J19+J6+J49 | K38: =K19+K6+K49 | L38: =L19+L6+L49 | M38: =M19+M6+M49 | N38: =N19+N6+N49 | ... BB38: =BB19+BB6+BB49 | BD38: =BD19+BD6+BD49 | BE38: =BE19+BE6+BE49 | BF38: =BF19+BF6+BF49 | BG38: =BG19+BG6+BG49 | BH38: =BH19+BH6+BH49 | BK38: R&D people + R&D other. this is the line the P&L reads
B39: Total S&M | D39: € | G39: =G26+G7+G46 | H39: =H26+H7+H46 | I39: =I26+I7+I46 | J39: =J26+J7+J46 | K39: =K26+K7+K46 | L39: =L26+L7+L46 | M39: =M26+M7+M46 | N39: =N26+N7+N46 | ... BB39: =BB26+BB7+BB46 | BD39: =BD26+BD7+BD46 | BE39: =BE26+BE7+BE46 | BF39: =BF26+BF7+BF46 | BG39: =BG26+BG7+BG46 | BH39: =BH26+BH7+BH46 | BK39: S&M people + S&M other. this is the line the P&L reads
B40: Total G&A | D40: € | G40: =G32+G8+G47 | H40: =H32+H8+H47 | I40: =I32+I8+I47 | J40: =J32+J8+J47 | K40: =K32+K8+K47 | L40: =L32+L8+L47 | M40: =M32+M8+M47 | N40: =N32+N8+N47 | ... BB40: =BB32+BB8+BB47 | BD40: =BD32+BD8+BD47 | BE40: =BE32+BE8+BE47 | BF40: =BF32+BF8+BF47 | BG40: =BG32+BG8+BG47 | BH40: =BH32+BH8+BH47 | BK40: G&A people + G&A other. this is the line the P&L reads
B41: R&D % of Total OPEX | S41: =S38/S$36 | T41: =T38/T$36 | U41: =U38/U$36 | V41: =V38/V$36 | W41: =W38/W$36 | X41: =X38/X$36 | Y41: =Y38/Y$36 | Z41: =Z38/Z$36 | ... BB41: =BB38/BB$36 | BD41: =BD38/BD$36 | BE41: =BE38/BE$36 | BF41: =BF38/BF$36 | BG41: =BG38/BG$36 | BH41: =BH38/BH$36 | BK41: R&D share of total operating costs
B42: S&M % of Total OPEX | S42: =S39/S$36 | T42: =T39/T$36 | U42: =U39/U$36 | V42: =V39/V$36 | W42: =W39/W$36 | X42: =X39/X$36 | Y42: =Y39/Y$36 | Z42: =Z39/Z$36 | ... BB42: =BB39/BB$36 | BD42: =BD39/BD$36 | BE42: =BE39/BE$36 | BF42: =BF39/BF$36 | BG42: =BG39/BG$36 | BH42: =BH39/BH$36 | BK42: S&M share of total operating costs
B43: G&A % of Total OPEX | S43: =S40/S$36 | T43: =T40/T$36 | U43: =U40/U$36 | V43: =V40/V$36 | W43: =W40/W$36 | X43: =X40/X$36 | Y43: =Y40/Y$36 | Z43: =Z40/Z$36 | ... BB43: =BB40/BB$36 | BD43: =BD40/BD$36 | BE43: =BE40/BE$36 | BF43: =BF40/BF$36 | BG43: =BG40/BG$36 | BH43: =BH40/BH$36 | BK43: G&A share of total operating costs
B45: GROWTH ENGINE — THE ORGANISATION THIS PLAN NEEDS (case-driven)
B46: S&M — installer training & demo units | G46: 0 | H46: 0 | I46: 0 | J46: 0 | K46: 0 | L46: 0 | M46: 0 | N46: 0 | O46: 0 | P46: 0 | Q46: 0 | R46: 0 | S46: 0 | T46: 0 | U46: 0 | V46: 0 | W46: 0 | X46: 0 | Y46: 0 | Z46: 0 | AA46: 0 | AB46: 0 | AC46: 0 | AD46: 0 | AE46: ='Growth Engine'!F86 | AF46: ='Growth Engine'!G86 | AG46: ='Growth Engine'!H86 | AH46: ='Growth Engine'!I86 | AI46: ='Growth Engine'!J86 | AJ46: ='Growth Engine'!K86 | AK46: ='Growth Engine'!L86 | AL46: ='Growth Engine'!M86 | ... BB46: ='Growth Engine'!AC86 | BD46: 0 | BE46: 0 | BF46: =SUM(AE46:AP46) | BG46: =SUM(AQ46:BB46) | BH46: ='Growth Engine'!BE86 | BK46: people are NOT here — they are rows in the Personnel tab, like every other employee
B47: G&A — facilities, IT, travel, recruitment, plant, new countries | G47: 0 | H47: 0 | I47: 0 | J47: 0 | K47: 0 | L47: 0 | M47: 0 | N47: 0 | O47: 0 | P47: 0 | Q47: 0 | R47: 0 | S47: 0 | T47: 0 | U47: 0 | V47: 0 | W47: 0 | X47: 0 | Y47: 0 | Z47: 0 | AA47: 0 | AB47: 0 | AC47: 0 | AD47: 0 | AE47: ='Growth Engine'!F84+'Growth Engine'!F85+'Growth Engine'!F87+'Growth Engine'!F88 | AF47: ='Growth Engine'!G84+'Growth Engine'!G85+'Growth Engine'!G87+'Growth Engine'!G88 | AG47: ='Growth Engine'!H84+'Growth Engine'!H85+'Growth Engine'!H87+'Growth Engine'!H88 | AH47: ='Growth Engine'!I84+'Growth Engine'!I85+'Growth Engine'!I87+'Growth Engine'!I88 | AI47: ='Growth Engine'!J84+'Growth Engine'!J85+'Growth Engine'!J87+'Growth Engine'!J88 | AJ47: ='Growth Engine'!K84+'Growth Engine'!K85+'Growth Engine'!K87+'Growth Engine'!K88 | AK47: ='Growth Engine'!L84+'Growth Engine'!L85+'Growth Engine'!L87+'Growth Engine'!L88 | AL47: ='Growth Engine'!M84+'Growth Engine'!M85+'Growth Engine'!M87+'Growth Engine'!M88 | ... BB47: ='Growth Engine'!AC84+'Growth Engine'!AC85+'Growth Engine'!AC87+'Growth Engine'!AC88 | BD47: 0 | BE47: 0 | BF47: =SUM(AE47:AP47) | BG47: =SUM(AQ47:BB47) | BH47: ='Growth Engine'!BE84+'Growth Engine'!BE85+'Growth Engine'!BE87+'Growth Engine'!BE88 | BK47: overheads scale with headcount; plant and country-entry costs come off the capacity plan
B48: Total growth-engine OPEX | G48: =G46+G47+G49 | H48: =H46+H47+H49 | I48: =I46+I47+I49 | J48: =J46+J47+J49 | K48: =K46+K47+K49 | L48: =L46+L47+L49 | M48: =M46+M47+M49 | N48: =N46+N47+N49 | ... BB48: =BB46+BB47+BB49 | BD48: =BD46+BD47+BD49 | BE48: =BE46+BE47+BE49 | BF48: =BF46+BF47+BF49 | BG48: =BG46+BG47+BG49 | BH48: =BH46+BH47+BH49
B49: (people are in the Personnel tab) | G49: 0 | H49: 0 | I49: 0 | J49: 0 | K49: 0 | L49: 0 | M49: 0 | N49: 0 | O49: 0 | P49: 0 | Q49: 0 | R49: 0 | S49: 0 | T49: 0 | U49: 0 | V49: 0 | W49: 0 | X49: 0 | Y49: 0 | Z49: 0 | AA49: 0 | AB49: 0 | AC49: 0 | AD49: 0 | AE49: 0 | AF49: 0 | AG49: 0 | AH49: 0 | AI49: 0 | AJ49: 0 | AK49: 0 | AL49: 0 | AM49: 0 | AN49: 0 | AO49: 0 | AP49: 0 | AQ49: 0 | AR49: 0 | AS49: 0 | AT49: 0 | AU49: 0 | AV49: 0 | AW49: 0 | AX49: 0 | AY49: 0 | AZ49: 0 | BA49: 0 | BB49: 0 | BD49: 0 | BE49: 0 | BF49: =SUM(AE49:AP49) | BG49: =SUM(AQ49:BB49) | BH49: 0

Sheet Personnel
B1: PERSONNEL — Monthly Employer Cost (€)
A2: # | B2: Name | C2: Dept | D2: Role | E2: Type | F2: Start | G2: End | H2: Monthly Cost (€) | I2: 45658 | J2: 45689 | K2: 45717 | L2: 45748 | M2: 45778 | N2: 45809 | O2: 45839 | P2: 45870 | Q2: 45901 | R2: 45931 | S2: 45962 | T2: 45992 | U2: 46023 | V2: 46054 | W2: 46082 | X2: 46113 | Y2: 46143 | Z2: 46174 | AA2: 46204 | AB2: 46235 | AC2: 46266 | AD2: 46296 | AE2: 46327 | AF2: 46357 | AG2: 46388 | AH2: 46419 | AI2: 46447 | AJ2: 46478 | AK2: 46508 | AL2: 46539 | AM2: 46569 | AN2: 46600 | AO2: 46631 | AP2: 46661 | AQ2: 46692 | AR2: 46722 | AS2: 46753 | AT2: 46784 | AU2: 46813 | AV2: 46844 | AW2: 46874 | AX2: 46905 | AY2: 46935 | AZ2: 46966 | BA2: 46997 | BB2: 47027 | BC2: 47058 | BD2: 47088 | BE2: 47119 | BF2: 47150 | BG2: 47178 | BH2: 47209 | BI2: 47239 | BJ2: 47270 | BK2: 47300 | BL2: 47331 | BM2: 47362 | BN2: 47392 | BO2: 47423 | BP2: 47453 | BR2: what this row does
A3: 1 | B3: R&D Engineer | C3: R&D | D3: Field Engineer | E3: Current | F3: 45901 | H3: 5500 | I3: =IF(AND(F3<=DATE(2025,1,1),OR(G3="",G3>=DATE(2025,1,1))),H3*(1+Assumptions!$C$7)^0,0) | J3: =IF(AND(F3<=DATE(2025,2,1),OR(G3="",G3>=DATE(2025,2,1))),H3*(1+Assumptions!$C$7)^0,0) | K3: =IF(AND(F3<=DATE(2025,3,1),OR(G3="",G3>=DATE(2025,3,1))),H3*(1+Assumptions!$C$7)^0,0) | L3: =IF(AND(F3<=DATE(2025,4,1),OR(G3="",G3>=DATE(2025,4,1))),H3*(1+Assumptions!$C$7)^0,0) | M3: =IF(AND(F3<=DATE(2025,5,1),OR(G3="",G3>=DATE(2025,5,1))),H3*(1+Assumptions!$C$7)^0,0) | N3: =IF(AND(F3<=DATE(2025,6,1),OR(G3="",G3>=DATE(2025,6,1))),H3*(1+Assumptions!$C$7)^0,0) | O3: =IF(AND(F3<=DATE(2025,7,1),OR(G3="",G3>=DATE(2025,7,1))),H3*(1+Assumptions!$C$7)^0,0) | P3: =IF(AND(F3<=DATE(2025,8,1),OR(G3="",G3>=DATE(2025,8,1))),H3*(1+Assumptions!$C$7)^0,0) | Q3: =IF(AND(F3<=DATE(2025,9,1),OR(G3="",G3>=DATE(2025,9,1))),H3*(1+Assumptions!$C$7)^0,0) | R3: =IF(AND(F3<=DATE(2025,10,1),OR(G3="",G3>=DATE(2025,10,1))),H3*(1+Assumptions!$C$7)^0,0) | S3: =IF(AND(F3<=DATE(2025,11,1),OR(G3="",G3>=DATE(2025,11,1))),H3*(1+Assumptions!$C$7)^0,0) | T3: =IF(AND(F3<=DATE(2025,12,1),OR(G3="",G3>=DATE(2025,12,1))),H3*(1+Assumptions!$C$7)^0,0) | U3: =IF(AND(F3<=DATE(2026,1,1),OR(G3="",G3>=DATE(2026,1,1))),H3*(1+Assumptions!$C$7)^1,0) | V3: =IF(AND(F3<=DATE(2026,2,1),OR(G3="",G3>=DATE(2026,2,1))),H3*(1+Assumptions!$C$7)^1,0) | W3: =IF(AND(F3<=DATE(2026,3,1),OR(G3="",G3>=DATE(2026,3,1))),H3*(1+Assumptions!$C$7)^1,0) | X3: =IF(AND(F3<=DATE(2026,4,1),OR(G3="",G3>=DATE(2026,4,1))),H3*(1+Assumptions!$C$7)^1,0) | Y3: =IF(AND(F3<=DATE(2026,5,1),OR(G3="",G3>=DATE(2026,5,1))),H3*(1+Assumptions!$C$7)^1,0) | Z3: =IF(AND(F3<=DATE(2026,6,1),OR(G3="",G3>=DATE(2026,6,1))),H3*(1+Assumptions!$C$7)^1,0) | AA3: =IF(AND(F3<=DATE(2026,7,1),OR(G3="",G3>=DATE(2026,7,1))),H3*(1+Assumptions!$C$7)^1,0) | AB3: =IF(AND(F3<=DATE(2026,8,1),OR(G3="",G3>=DATE(2026,8,1))),H3*(1+Assumptions!$C$7)^1,0) | AC3: =IF(AND(F3<=DATE(2026,9,1),OR(G3="",G3>=DATE(2026,9,1))),H3*(1+Assumptions!$C$7)^1,0) | AD3: =IF(AND(F3<=DATE(2026,10,1),OR(G3="",G3>=DATE(2026,10,1))),H3*(1+Assumptions!$C$7)^1,0) | AE3: =IF(AND(F3<=DATE(2026,11,1),OR(G3="",G3>=DATE(2026,11,1))),H3*(1+Assumptions!$C$7)^1,0) | AF3: =IF(AND(F3<=DATE(2026,12,1),OR(G3="",G3>=DATE(2026,12,1))),H3*(1+Assumptions!$C$7)^1,0) | AG3: =IF(AND(F3<=DATE(2027,1,1),OR(G3="",G3>=DATE(2027,1,1))),H3*(1+Assumptions!$C$7)^2,0) | AH3: =IF(AND(F3<=DATE(2027,2,1),OR(G3="",G3>=DATE(2027,2,1))),H3*(1+Assumptions!$C$7)^2,0) | AI3: =IF(AND(F3<=DATE(2027,3,1),OR(G3="",G3>=DATE(2027,3,1))),H3*(1+Assumptions!$C$7)^2,0) | AJ3: =IF(AND(F3<=DATE(2027,4,1),OR(G3="",G3>=DATE(2027,4,1))),H3*(1+Assumptions!$C$7)^2,0) | AK3: =IF(AND(F3<=DATE(2027,5,1),OR(G3="",G3>=DATE(2027,5,1))),H3*(1+Assumptions!$C$7)^2,0) | AL3: =IF(AND(F3<=DATE(2027,6,1),OR(G3="",G3>=DATE(2027,6,1))),H3*(1+Assumptions!$C$7)^2,0) | AM3: =IF(AND(F3<=DATE(2027,7,1),OR(G3="",G3>=DATE(2027,7,1))),H3*(1+Assumptions!$C$7)^2,0) | AN3: =IF(AND(F3<=DATE(2027,8,1),OR(G3="",G3>=DATE(2027,8,1))),H3*(1+Assumptions!$C$7)^2,0) | AO3: =IF(AND(F3<=DATE(2027,9,1),OR(G3="",G3>=DATE(2027,9,1))),H3*(1+Assumptions!$C$7)^2,0) | AP3: =IF(AND(F3<=DATE(2027,10,1),OR(G3="",G3>=DATE(2027,10,1))),H3*(1+Assumptions!$C$7)^2,0) | AQ3: =IF(AND(F3<=DATE(2027,11,1),OR(G3="",G3>=DATE(2027,11,1))),H3*(1+Assumptions!$C$7)^2,0) | AR3: =IF(AND(F3<=DATE(2027,12,1),OR(G3="",G3>=DATE(2027,12,1))),H3*(1+Assumptions!$C$7)^2,0) | AS3: =IF(AND(F3<=DATE(2028,1,1),OR(G3="",G3>=DATE(2028,1,1))),H3*(1+Assumptions!$C$7)^3,0) | AT3: =IF(AND(F3<=DATE(2028,2,1),OR(G3="",G3>=DATE(2028,2,1))),H3*(1+Assumptions!$C$7)^3,0) | AU3: =IF(AND(F3<=DATE(2028,3,1),OR(G3="",G3>=DATE(2028,3,1))),H3*(1+Assumptions!$C$7)^3,0) | AV3: =IF(AND(F3<=DATE(2028,4,1),OR(G3="",G3>=DATE(2028,4,1))),H3*(1+Assumptions!$C$7)^3,0) | AW3: =IF(AND(F3<=DATE(2028,5,1),OR(G3="",G3>=DATE(2028,5,1))),H3*(1+Assumptions!$C$7)^3,0) | AX3: =IF(AND(F3<=DATE(2028,6,1),OR(G3="",G3>=DATE(2028,6,1))),H3*(1+Assumptions!$C$7)^3,0) | AY3: =IF(AND(F3<=DATE(2028,7,1),OR(G3="",G3>=DATE(2028,7,1))),H3*(1+Assumptions!$C$7)^3,0) | AZ3: =IF(AND(F3<=DATE(2028,8,1),OR(G3="",G3>=DATE(2028,8,1))),H3*(1+Assumptions!$C$7)^3,0) | BA3: =IF(AND(F3<=DATE(2028,9,1),OR(G3="",G3>=DATE(2028,9,1))),H3*(1+Assumptions!$C$7)^3,0) | BB3: =IF(AND(F3<=DATE(2028,10,1),OR(G3="",G3>=DATE(2028,10,1))),H3*(1+Assumptions!$C$7)^3,0) | BC3: =IF(AND(F3<=DATE(2028,11,1),OR(G3="",G3>=DATE(2028,11,1))),H3*(1+Assumptions!$C$7)^3,0) | BD3: =IF(AND(F3<=DATE(2028,12,1),OR(G3="",G3>=DATE(2028,12,1))),H3*(1+Assumptions!$C$7)^3,0) | BE3: =IF(AND(F3<=DATE(2029,1,1),OR(G3="",G3>=DATE(2029,1,1))),H3*(1+Assumptions!$C$7)^4,0) | BF3: =IF(AND(F3<=DATE(2029,2,1),OR(G3="",G3>=DATE(2029,2,1))),H3*(1+Assumptions!$C$7)^4,0) | BG3: =IF(AND(F3<=DATE(2029,3,1),OR(G3="",G3>=DATE(2029,3,1))),H3*(1+Assumptions!$C$7)^4,0) | BH3: =IF(AND(F3<=DATE(2029,4,1),OR(G3="",G3>=DATE(2029,4,1))),H3*(1+Assumptions!$C$7)^4,0) | BI3: =IF(AND(F3<=DATE(2029,5,1),OR(G3="",G3>=DATE(2029,5,1))),H3*(1+Assumptions!$C$7)^4,0) | BJ3: =IF(AND(F3<=DATE(2029,6,1),OR(G3="",G3>=DATE(2029,6,1))),H3*(1+Assumptions!$C$7)^4,0) | BK3: =IF(AND(F3<=DATE(2029,7,1),OR(G3="",G3>=DATE(2029,7,1))),H3*(1+Assumptions!$C$7)^4,0) | BL3: =IF(AND(F3<=DATE(2029,8,1),OR(G3="",G3>=DATE(2029,8,1))),H3*(1+Assumptions!$C$7)^4,0) | BM3: =IF(AND(F3<=DATE(2029,9,1),OR(G3="",G3>=DATE(2029,9,1))),H3*(1+Assumptions!$C$7)^4,0) | BN3: =IF(AND(F3<=DATE(2029,10,1),OR(G3="",G3>=DATE(2029,10,1))),H3*(1+Assumptions!$C$7)^4,0) | BO3: =IF(AND(F3<=DATE(2029,11,1),OR(G3="",G3>=DATE(2029,11,1))),H3*(1+Assumptions!$C$7)^4,0) | BP3: =IF(AND(F3<=DATE(2029,12,1),OR(G3="",G3>=DATE(2029,12,1))),H3*(1+Assumptions!$C$7)^4,0) | BR3: paid this month if started and not yet left; +8% each calendar year
A4: 2 | B4: Project manager | C4: R&D | D4: R&D Engineer | E4: Current | F4: 45901 | H4: 7500 | I4: =IF(AND(F4<=DATE(2025,1,1),OR(G4="",G4>=DATE(2025,1,1))),H4*(1+Assumptions!$C$7)^0,0) | J4: =IF(AND(F4<=DATE(2025,2,1),OR(G4="",G4>=DATE(2025,2,1))),H4*(1+Assumptions!$C$7)^0,0) | K4: =IF(AND(F4<=DATE(2025,3,1),OR(G4="",G4>=DATE(2025,3,1))),H4*(1+Assumptions!$C$7)^0,0) | L4: =IF(AND(F4<=DATE(2025,4,1),OR(G4="",G4>=DATE(2025,4,1))),H4*(1+Assumptions!$C$7)^0,0) | M4: =IF(AND(F4<=DATE(2025,5,1),OR(G4="",G4>=DATE(2025,5,1))),H4*(1+Assumptions!$C$7)^0,0) | N4: =IF(AND(F4<=DATE(2025,6,1),OR(G4="",G4>=DATE(2025,6,1))),H4*(1+Assumptions!$C$7)^0,0) | O4: =IF(AND(F4<=DATE(2025,7,1),OR(G4="",G4>=DATE(2025,7,1))),H4*(1+Assumptions!$C$7)^0,0) | P4: =IF(AND(F4<=DATE(2025,8,1),OR(G4="",G4>=DATE(2025,8,1))),H4*(1+Assumptions!$C$7)^0,0) | Q4: =IF(AND(F4<=DATE(2025,9,1),OR(G4="",G4>=DATE(2025,9,1))),H4*(1+Assumptions!$C$7)^0,0) | R4: =IF(AND(F4<=DATE(2025,10,1),OR(G4="",G4>=DATE(2025,10,1))),H4*(1+Assumptions!$C$7)^0,0) | S4: =IF(AND(F4<=DATE(2025,11,1),OR(G4="",G4>=DATE(2025,11,1))),H4*(1+Assumptions!$C$7)^0,0) | T4: =IF(AND(F4<=DATE(2025,12,1),OR(G4="",G4>=DATE(2025,12,1))),H4*(1+Assumptions!$C$7)^0,0) | U4: =IF(AND(F4<=DATE(2026,1,1),OR(G4="",G4>=DATE(2026,1,1))),H4*(1+Assumptions!$C$7)^1,0) | V4: =IF(AND(F4<=DATE(2026,2,1),OR(G4="",G4>=DATE(2026,2,1))),H4*(1+Assumptions!$C$7)^1,0) | W4: =IF(AND(F4<=DATE(2026,3,1),OR(G4="",G4>=DATE(2026,3,1))),H4*(1+Assumptions!$C$7)^1,0) | X4: =IF(AND(F4<=DATE(2026,4,1),OR(G4="",G4>=DATE(2026,4,1))),H4*(1+Assumptions!$C$7)^1,0) | Y4: =IF(AND(F4<=DATE(2026,5,1),OR(G4="",G4>=DATE(2026,5,1))),H4*(1+Assumptions!$C$7)^1,0) | Z4: =IF(AND(F4<=DATE(2026,6,1),OR(G4="",G4>=DATE(2026,6,1))),H4*(1+Assumptions!$C$7)^1,0) | AA4: =IF(AND(F4<=DATE(2026,7,1),OR(G4="",G4>=DATE(2026,7,1))),H4*(1+Assumptions!$C$7)^1,0) | AB4: =IF(AND(F4<=DATE(2026,8,1),OR(G4="",G4>=DATE(2026,8,1))),H4*(1+Assumptions!$C$7)^1,0) | AC4: =IF(AND(F4<=DATE(2026,9,1),OR(G4="",G4>=DATE(2026,9,1))),H4*(1+Assumptions!$C$7)^1,0) | AD4: =IF(AND(F4<=DATE(2026,10,1),OR(G4="",G4>=DATE(2026,10,1))),H4*(1+Assumptions!$C$7)^1,0) | AE4: =IF(AND(F4<=DATE(2026,11,1),OR(G4="",G4>=DATE(2026,11,1))),H4*(1+Assumptions!$C$7)^1,0) | AF4: =IF(AND(F4<=DATE(2026,12,1),OR(G4="",G4>=DATE(2026,12,1))),H4*(1+Assumptions!$C$7)^1,0) | AG4: =IF(AND(F4<=DATE(2027,1,1),OR(G4="",G4>=DATE(2027,1,1))),H4*(1+Assumptions!$C$7)^2,0) | AH4: =IF(AND(F4<=DATE(2027,2,1),OR(G4="",G4>=DATE(2027,2,1))),H4*(1+Assumptions!$C$7)^2,0) | AI4: =IF(AND(F4<=DATE(2027,3,1),OR(G4="",G4>=DATE(2027,3,1))),H4*(1+Assumptions!$C$7)^2,0) | AJ4: =IF(AND(F4<=DATE(2027,4,1),OR(G4="",G4>=DATE(2027,4,1))),H4*(1+Assumptions!$C$7)^2,0) | AK4: =IF(AND(F4<=DATE(2027,5,1),OR(G4="",G4>=DATE(2027,5,1))),H4*(1+Assumptions!$C$7)^2,0) | AL4: =IF(AND(F4<=DATE(2027,6,1),OR(G4="",G4>=DATE(2027,6,1))),H4*(1+Assumptions!$C$7)^2,0) | AM4: =IF(AND(F4<=DATE(2027,7,1),OR(G4="",G4>=DATE(2027,7,1))),H4*(1+Assumptions!$C$7)^2,0) | AN4: =IF(AND(F4<=DATE(2027,8,1),OR(G4="",G4>=DATE(2027,8,1))),H4*(1+Assumptions!$C$7)^2,0) | AO4: =IF(AND(F4<=DATE(2027,9,1),OR(G4="",G4>=DATE(2027,9,1))),H4*(1+Assumptions!$C$7)^2,0) | AP4: =IF(AND(F4<=DATE(2027,10,1),OR(G4="",G4>=DATE(2027,10,1))),H4*(1+Assumptions!$C$7)^2,0) | AQ4: =IF(AND(F4<=DATE(2027,11,1),OR(G4="",G4>=DATE(2027,11,1))),H4*(1+Assumptions!$C$7)^2,0) | AR4: =IF(AND(F4<=DATE(2027,12,1),OR(G4="",G4>=DATE(2027,12,1))),H4*(1+Assumptions!$C$7)^2,0) | AS4: =IF(AND(F4<=DATE(2028,1,1),OR(G4="",G4>=DATE(2028,1,1))),H4*(1+Assumptions!$C$7)^3,0) | AT4: =IF(AND(F4<=DATE(2028,2,1),OR(G4="",G4>=DATE(2028,2,1))),H4*(1+Assumptions!$C$7)^3,0) | AU4: =IF(AND(F4<=DATE(2028,3,1),OR(G4="",G4>=DATE(2028,3,1))),H4*(1+Assumptions!$C$7)^3,0) | AV4: =IF(AND(F4<=DATE(2028,4,1),OR(G4="",G4>=DATE(2028,4,1))),H4*(1+Assumptions!$C$7)^3,0) | AW4: =IF(AND(F4<=DATE(2028,5,1),OR(G4="",G4>=DATE(2028,5,1))),H4*(1+Assumptions!$C$7)^3,0) | AX4: =IF(AND(F4<=DATE(2028,6,1),OR(G4="",G4>=DATE(2028,6,1))),H4*(1+Assumptions!$C$7)^3,0) | AY4: =IF(AND(F4<=DATE(2028,7,1),OR(G4="",G4>=DATE(2028,7,1))),H4*(1+Assumptions!$C$7)^3,0) | AZ4: =IF(AND(F4<=DATE(2028,8,1),OR(G4="",G4>=DATE(2028,8,1))),H4*(1+Assumptions!$C$7)^3,0) | BA4: =IF(AND(F4<=DATE(2028,9,1),OR(G4="",G4>=DATE(2028,9,1))),H4*(1+Assumptions!$C$7)^3,0) | BB4: =IF(AND(F4<=DATE(2028,10,1),OR(G4="",G4>=DATE(2028,10,1))),H4*(1+Assumptions!$C$7)^3,0) | BC4: =IF(AND(F4<=DATE(2028,11,1),OR(G4="",G4>=DATE(2028,11,1))),H4*(1+Assumptions!$C$7)^3,0) | BD4: =IF(AND(F4<=DATE(2028,12,1),OR(G4="",G4>=DATE(2028,12,1))),H4*(1+Assumptions!$C$7)^3,0) | BE4: =IF(AND(F4<=DATE(2029,1,1),OR(G4="",G4>=DATE(2029,1,1))),H4*(1+Assumptions!$C$7)^4,0) | BF4: =IF(AND(F4<=DATE(2029,2,1),OR(G4="",G4>=DATE(2029,2,1))),H4*(1+Assumptions!$C$7)^4,0) | BG4: =IF(AND(F4<=DATE(2029,3,1),OR(G4="",G4>=DATE(2029,3,1))),H4*(1+Assumptions!$C$7)^4,0) | BH4: =IF(AND(F4<=DATE(2029,4,1),OR(G4="",G4>=DATE(2029,4,1))),H4*(1+Assumptions!$C$7)^4,0) | BI4: =IF(AND(F4<=DATE(2029,5,1),OR(G4="",G4>=DATE(2029,5,1))),H4*(1+Assumptions!$C$7)^4,0) | BJ4: =IF(AND(F4<=DATE(2029,6,1),OR(G4="",G4>=DATE(2029,6,1))),H4*(1+Assumptions!$C$7)^4,0) | BK4: =IF(AND(F4<=DATE(2029,7,1),OR(G4="",G4>=DATE(2029,7,1))),H4*(1+Assumptions!$C$7)^4,0) | BL4: =IF(AND(F4<=DATE(2029,8,1),OR(G4="",G4>=DATE(2029,8,1))),H4*(1+Assumptions!$C$7)^4,0) | BM4: =IF(AND(F4<=DATE(2029,9,1),OR(G4="",G4>=DATE(2029,9,1))),H4*(1+Assumptions!$C$7)^4,0) | BN4: =IF(AND(F4<=DATE(2029,10,1),OR(G4="",G4>=DATE(2029,10,1))),H4*(1+Assumptions!$C$7)^4,0) | BO4: =IF(AND(F4<=DATE(2029,11,1),OR(G4="",G4>=DATE(2029,11,1))),H4*(1+Assumptions!$C$7)^4,0) | BP4: =IF(AND(F4<=DATE(2029,12,1),OR(G4="",G4>=DATE(2029,12,1))),H4*(1+Assumptions!$C$7)^4,0) | BR4: paid this month if started and not yet left; +8% each calendar year
A5: 3 | B5: R&D Engineer | C5: R&D | D5: R&D Engineer | E5: Current | F5: 45901 | H5: 3000 | I5: =IF(AND(F5<=DATE(2025,1,1),OR(G5="",G5>=DATE(2025,1,1))),H5*(1+Assumptions!$C$7)^0,0) | J5: =IF(AND(F5<=DATE(2025,2,1),OR(G5="",G5>=DATE(2025,2,1))),H5*(1+Assumptions!$C$7)^0,0) | K5: =IF(AND(F5<=DATE(2025,3,1),OR(G5="",G5>=DATE(2025,3,1))),H5*(1+Assumptions!$C$7)^0,0) | L5: =IF(AND(F5<=DATE(2025,4,1),OR(G5="",G5>=DATE(2025,4,1))),H5*(1+Assumptions!$C$7)^0,0) | M5: =IF(AND(F5<=DATE(2025,5,1),OR(G5="",G5>=DATE(2025,5,1))),H5*(1+Assumptions!$C$7)^0,0) | N5: =IF(AND(F5<=DATE(2025,6,1),OR(G5="",G5>=DATE(2025,6,1))),H5*(1+Assumptions!$C$7)^0,0) | O5: =IF(AND(F5<=DATE(2025,7,1),OR(G5="",G5>=DATE(2025,7,1))),H5*(1+Assumptions!$C$7)^0,0) | P5: =IF(AND(F5<=DATE(2025,8,1),OR(G5="",G5>=DATE(2025,8,1))),H5*(1+Assumptions!$C$7)^0,0) | Q5: =IF(AND(F5<=DATE(2025,9,1),OR(G5="",G5>=DATE(2025,9,1))),H5*(1+Assumptions!$C$7)^0,0) | R5: =IF(AND(F5<=DATE(2025,10,1),OR(G5="",G5>=DATE(2025,10,1))),H5*(1+Assumptions!$C$7)^0,0) | S5: =IF(AND(F5<=DATE(2025,11,1),OR(G5="",G5>=DATE(2025,11,1))),H5*(1+Assumptions!$C$7)^0,0) | T5: =IF(AND(F5<=DATE(2025,12,1),OR(G5="",G5>=DATE(2025,12,1))),H5*(1+Assumptions!$C$7)^0,0) | U5: =IF(AND(F5<=DATE(2026,1,1),OR(G5="",G5>=DATE(2026,1,1))),H5*(1+Assumptions!$C$7)^1,0) | V5: =IF(AND(F5<=DATE(2026,2,1),OR(G5="",G5>=DATE(2026,2,1))),H5*(1+Assumptions!$C$7)^1,0) | W5: =IF(AND(F5<=DATE(2026,3,1),OR(G5="",G5>=DATE(2026,3,1))),H5*(1+Assumptions!$C$7)^1,0) | X5: =IF(AND(F5<=DATE(2026,4,1),OR(G5="",G5>=DATE(2026,4,1))),H5*(1+Assumptions!$C$7)^1,0) | Y5: =IF(AND(F5<=DATE(2026,5,1),OR(G5="",G5>=DATE(2026,5,1))),H5*(1+Assumptions!$C$7)^1,0) | Z5: =IF(AND(F5<=DATE(2026,6,1),OR(G5="",G5>=DATE(2026,6,1))),H5*(1+Assumptions!$C$7)^1,0) | AA5: =IF(AND(F5<=DATE(2026,7,1),OR(G5="",G5>=DATE(2026,7,1))),H5*(1+Assumptions!$C$7)^1,0) | AB5: =IF(AND(F5<=DATE(2026,8,1),OR(G5="",G5>=DATE(2026,8,1))),H5*(1+Assumptions!$C$7)^1,0) | AC5: =IF(AND(F5<=DATE(2026,9,1),OR(G5="",G5>=DATE(2026,9,1))),H5*(1+Assumptions!$C$7)^1,0) | AD5: =IF(AND(F5<=DATE(2026,10,1),OR(G5="",G5>=DATE(2026,10,1))),H5*(1+Assumptions!$C$7)^1,0) | AE5: =IF(AND(F5<=DATE(2026,11,1),OR(G5="",G5>=DATE(2026,11,1))),H5*(1+Assumptions!$C$7)^1,0) | AF5: =IF(AND(F5<=DATE(2026,12,1),OR(G5="",G5>=DATE(2026,12,1))),H5*(1+Assumptions!$C$7)^1,0) | AG5: =IF(AND(F5<=DATE(2027,1,1),OR(G5="",G5>=DATE(2027,1,1))),H5*(1+Assumptions!$C$7)^2,0) | AH5: =IF(AND(F5<=DATE(2027,2,1),OR(G5="",G5>=DATE(2027,2,1))),H5*(1+Assumptions!$C$7)^2,0) | AI5: =IF(AND(F5<=DATE(2027,3,1),OR(G5="",G5>=DATE(2027,3,1))),H5*(1+Assumptions!$C$7)^2,0) | AJ5: =IF(AND(F5<=DATE(2027,4,1),OR(G5="",G5>=DATE(2027,4,1))),H5*(1+Assumptions!$C$7)^2,0) | AK5: =IF(AND(F5<=DATE(2027,5,1),OR(G5="",G5>=DATE(2027,5,1))),H5*(1+Assumptions!$C$7)^2,0) | AL5: =IF(AND(F5<=DATE(2027,6,1),OR(G5="",G5>=DATE(2027,6,1))),H5*(1+Assumptions!$C$7)^2,0) | AM5: =IF(AND(F5<=DATE(2027,7,1),OR(G5="",G5>=DATE(2027,7,1))),H5*(1+Assumptions!$C$7)^2,0) | AN5: =IF(AND(F5<=DATE(2027,8,1),OR(G5="",G5>=DATE(2027,8,1))),H5*(1+Assumptions!$C$7)^2,0) | AO5: =IF(AND(F5<=DATE(2027,9,1),OR(G5="",G5>=DATE(2027,9,1))),H5*(1+Assumptions!$C$7)^2,0) | AP5: =IF(AND(F5<=DATE(2027,10,1),OR(G5="",G5>=DATE(2027,10,1))),H5*(1+Assumptions!$C$7)^2,0) | AQ5: =IF(AND(F5<=DATE(2027,11,1),OR(G5="",G5>=DATE(2027,11,1))),H5*(1+Assumptions!$C$7)^2,0) | AR5: =IF(AND(F5<=DATE(2027,12,1),OR(G5="",G5>=DATE(2027,12,1))),H5*(1+Assumptions!$C$7)^2,0) | AS5: =IF(AND(F5<=DATE(2028,1,1),OR(G5="",G5>=DATE(2028,1,1))),H5*(1+Assumptions!$C$7)^3,0) | AT5: =IF(AND(F5<=DATE(2028,2,1),OR(G5="",G5>=DATE(2028,2,1))),H5*(1+Assumptions!$C$7)^3,0) | AU5: =IF(AND(F5<=DATE(2028,3,1),OR(G5="",G5>=DATE(2028,3,1))),H5*(1+Assumptions!$C$7)^3,0) | AV5: =IF(AND(F5<=DATE(2028,4,1),OR(G5="",G5>=DATE(2028,4,1))),H5*(1+Assumptions!$C$7)^3,0) | AW5: =IF(AND(F5<=DATE(2028,5,1),OR(G5="",G5>=DATE(2028,5,1))),H5*(1+Assumptions!$C$7)^3,0) | AX5: =IF(AND(F5<=DATE(2028,6,1),OR(G5="",G5>=DATE(2028,6,1))),H5*(1+Assumptions!$C$7)^3,0) | AY5: =IF(AND(F5<=DATE(2028,7,1),OR(G5="",G5>=DATE(2028,7,1))),H5*(1+Assumptions!$C$7)^3,0) | AZ5: =IF(AND(F5<=DATE(2028,8,1),OR(G5="",G5>=DATE(2028,8,1))),H5*(1+Assumptions!$C$7)^3,0) | BA5: =IF(AND(F5<=DATE(2028,9,1),OR(G5="",G5>=DATE(2028,9,1))),H5*(1+Assumptions!$C$7)^3,0) | BB5: =IF(AND(F5<=DATE(2028,10,1),OR(G5="",G5>=DATE(2028,10,1))),H5*(1+Assumptions!$C$7)^3,0) | BC5: =IF(AND(F5<=DATE(2028,11,1),OR(G5="",G5>=DATE(2028,11,1))),H5*(1+Assumptions!$C$7)^3,0) | BD5: =IF(AND(F5<=DATE(2028,12,1),OR(G5="",G5>=DATE(2028,12,1))),H5*(1+Assumptions!$C$7)^3,0) | BE5: =IF(AND(F5<=DATE(2029,1,1),OR(G5="",G5>=DATE(2029,1,1))),H5*(1+Assumptions!$C$7)^4,0) | BF5: =IF(AND(F5<=DATE(2029,2,1),OR(G5="",G5>=DATE(2029,2,1))),H5*(1+Assumptions!$C$7)^4,0) | BG5: =IF(AND(F5<=DATE(2029,3,1),OR(G5="",G5>=DATE(2029,3,1))),H5*(1+Assumptions!$C$7)^4,0) | BH5: =IF(AND(F5<=DATE(2029,4,1),OR(G5="",G5>=DATE(2029,4,1))),H5*(1+Assumptions!$C$7)^4,0) | BI5: =IF(AND(F5<=DATE(2029,5,1),OR(G5="",G5>=DATE(2029,5,1))),H5*(1+Assumptions!$C$7)^4,0) | BJ5: =IF(AND(F5<=DATE(2029,6,1),OR(G5="",G5>=DATE(2029,6,1))),H5*(1+Assumptions!$C$7)^4,0) | BK5: =IF(AND(F5<=DATE(2029,7,1),OR(G5="",G5>=DATE(2029,7,1))),H5*(1+Assumptions!$C$7)^4,0) | BL5: =IF(AND(F5<=DATE(2029,8,1),OR(G5="",G5>=DATE(2029,8,1))),H5*(1+Assumptions!$C$7)^4,0) | BM5: =IF(AND(F5<=DATE(2029,9,1),OR(G5="",G5>=DATE(2029,9,1))),H5*(1+Assumptions!$C$7)^4,0) | BN5: =IF(AND(F5<=DATE(2029,10,1),OR(G5="",G5>=DATE(2029,10,1))),H5*(1+Assumptions!$C$7)^4,0) | BO5: =IF(AND(F5<=DATE(2029,11,1),OR(G5="",G5>=DATE(2029,11,1))),H5*(1+Assumptions!$C$7)^4,0) | BP5: =IF(AND(F5<=DATE(2029,12,1),OR(G5="",G5>=DATE(2029,12,1))),H5*(1+Assumptions!$C$7)^4,0) | BR5: paid this month if started and not yet left; +8% each calendar year
A6: 4 | B6: R&D Engineer | C6: R&D | D6: R&D Engineer | E6: Current | F6: 45901 | H6: 6000 | I6: =IF(AND(F6<=DATE(2025,1,1),OR(G6="",G6>=DATE(2025,1,1))),H6*(1+Assumptions!$C$7)^0,0) | J6: =IF(AND(F6<=DATE(2025,2,1),OR(G6="",G6>=DATE(2025,2,1))),H6*(1+Assumptions!$C$7)^0,0) | K6: =IF(AND(F6<=DATE(2025,3,1),OR(G6="",G6>=DATE(2025,3,1))),H6*(1+Assumptions!$C$7)^0,0) | L6: =IF(AND(F6<=DATE(2025,4,1),OR(G6="",G6>=DATE(2025,4,1))),H6*(1+Assumptions!$C$7)^0,0) | M6: =IF(AND(F6<=DATE(2025,5,1),OR(G6="",G6>=DATE(2025,5,1))),H6*(1+Assumptions!$C$7)^0,0) | N6: =IF(AND(F6<=DATE(2025,6,1),OR(G6="",G6>=DATE(2025,6,1))),H6*(1+Assumptions!$C$7)^0,0) | O6: =IF(AND(F6<=DATE(2025,7,1),OR(G6="",G6>=DATE(2025,7,1))),H6*(1+Assumptions!$C$7)^0,0) | P6: =IF(AND(F6<=DATE(2025,8,1),OR(G6="",G6>=DATE(2025,8,1))),H6*(1+Assumptions!$C$7)^0,0) | Q6: =IF(AND(F6<=DATE(2025,9,1),OR(G6="",G6>=DATE(2025,9,1))),H6*(1+Assumptions!$C$7)^0,0) | R6: =IF(AND(F6<=DATE(2025,10,1),OR(G6="",G6>=DATE(2025,10,1))),H6*(1+Assumptions!$C$7)^0,0) | S6: =IF(AND(F6<=DATE(2025,11,1),OR(G6="",G6>=DATE(2025,11,1))),H6*(1+Assumptions!$C$7)^0,0) | T6: =IF(AND(F6<=DATE(2025,12,1),OR(G6="",G6>=DATE(2025,12,1))),H6*(1+Assumptions!$C$7)^0,0) | U6: =IF(AND(F6<=DATE(2026,1,1),OR(G6="",G6>=DATE(2026,1,1))),H6*(1+Assumptions!$C$7)^1,0) | V6: =IF(AND(F6<=DATE(2026,2,1),OR(G6="",G6>=DATE(2026,2,1))),H6*(1+Assumptions!$C$7)^1,0) | W6: =IF(AND(F6<=DATE(2026,3,1),OR(G6="",G6>=DATE(2026,3,1))),H6*(1+Assumptions!$C$7)^1,0) | X6: =IF(AND(F6<=DATE(2026,4,1),OR(G6="",G6>=DATE(2026,4,1))),H6*(1+Assumptions!$C$7)^1,0) | Y6: =IF(AND(F6<=DATE(2026,5,1),OR(G6="",G6>=DATE(2026,5,1))),H6*(1+Assumptions!$C$7)^1,0) | Z6: =IF(AND(F6<=DATE(2026,6,1),OR(G6="",G6>=DATE(2026,6,1))),H6*(1+Assumptions!$C$7)^1,0) | AA6: =IF(AND(F6<=DATE(2026,7,1),OR(G6="",G6>=DATE(2026,7,1))),H6*(1+Assumptions!$C$7)^1,0) | AB6: =IF(AND(F6<=DATE(2026,8,1),OR(G6="",G6>=DATE(2026,8,1))),H6*(1+Assumptions!$C$7)^1,0) | AC6: =IF(AND(F6<=DATE(2026,9,1),OR(G6="",G6>=DATE(2026,9,1))),H6*(1+Assumptions!$C$7)^1,0) | AD6: =IF(AND(F6<=DATE(2026,10,1),OR(G6="",G6>=DATE(2026,10,1))),H6*(1+Assumptions!$C$7)^1,0) | AE6: =IF(AND(F6<=DATE(2026,11,1),OR(G6="",G6>=DATE(2026,11,1))),H6*(1+Assumptions!$C$7)^1,0) | AF6: =IF(AND(F6<=DATE(2026,12,1),OR(G6="",G6>=DATE(2026,12,1))),H6*(1+Assumptions!$C$7)^1,0) | AG6: =IF(AND(F6<=DATE(2027,1,1),OR(G6="",G6>=DATE(2027,1,1))),H6*(1+Assumptions!$C$7)^2,0) | AH6: =IF(AND(F6<=DATE(2027,2,1),OR(G6="",G6>=DATE(2027,2,1))),H6*(1+Assumptions!$C$7)^2,0) | AI6: =IF(AND(F6<=DATE(2027,3,1),OR(G6="",G6>=DATE(2027,3,1))),H6*(1+Assumptions!$C$7)^2,0) | AJ6: =IF(AND(F6<=DATE(2027,4,1),OR(G6="",G6>=DATE(2027,4,1))),H6*(1+Assumptions!$C$7)^2,0) | AK6: =IF(AND(F6<=DATE(2027,5,1),OR(G6="",G6>=DATE(2027,5,1))),H6*(1+Assumptions!$C$7)^2,0) | AL6: =IF(AND(F6<=DATE(2027,6,1),OR(G6="",G6>=DATE(2027,6,1))),H6*(1+Assumptions!$C$7)^2,0) | AM6: =IF(AND(F6<=DATE(2027,7,1),OR(G6="",G6>=DATE(2027,7,1))),H6*(1+Assumptions!$C$7)^2,0) | AN6: =IF(AND(F6<=DATE(2027,8,1),OR(G6="",G6>=DATE(2027,8,1))),H6*(1+Assumptions!$C$7)^2,0) | AO6: =IF(AND(F6<=DATE(2027,9,1),OR(G6="",G6>=DATE(2027,9,1))),H6*(1+Assumptions!$C$7)^2,0) | AP6: =IF(AND(F6<=DATE(2027,10,1),OR(G6="",G6>=DATE(2027,10,1))),H6*(1+Assumptions!$C$7)^2,0) | AQ6: =IF(AND(F6<=DATE(2027,11,1),OR(G6="",G6>=DATE(2027,11,1))),H6*(1+Assumptions!$C$7)^2,0) | AR6: =IF(AND(F6<=DATE(2027,12,1),OR(G6="",G6>=DATE(2027,12,1))),H6*(1+Assumptions!$C$7)^2,0) | AS6: =IF(AND(F6<=DATE(2028,1,1),OR(G6="",G6>=DATE(2028,1,1))),H6*(1+Assumptions!$C$7)^3,0) | AT6: =IF(AND(F6<=DATE(2028,2,1),OR(G6="",G6>=DATE(2028,2,1))),H6*(1+Assumptions!$C$7)^3,0) | AU6: =IF(AND(F6<=DATE(2028,3,1),OR(G6="",G6>=DATE(2028,3,1))),H6*(1+Assumptions!$C$7)^3,0) | AV6: =IF(AND(F6<=DATE(2028,4,1),OR(G6="",G6>=DATE(2028,4,1))),H6*(1+Assumptions!$C$7)^3,0) | AW6: =IF(AND(F6<=DATE(2028,5,1),OR(G6="",G6>=DATE(2028,5,1))),H6*(1+Assumptions!$C$7)^3,0) | AX6: =IF(AND(F6<=DATE(2028,6,1),OR(G6="",G6>=DATE(2028,6,1))),H6*(1+Assumptions!$C$7)^3,0) | AY6: =IF(AND(F6<=DATE(2028,7,1),OR(G6="",G6>=DATE(2028,7,1))),H6*(1+Assumptions!$C$7)^3,0) | AZ6: =IF(AND(F6<=DATE(2028,8,1),OR(G6="",G6>=DATE(2028,8,1))),H6*(1+Assumptions!$C$7)^3,0) | BA6: =IF(AND(F6<=DATE(2028,9,1),OR(G6="",G6>=DATE(2028,9,1))),H6*(1+Assumptions!$C$7)^3,0) | BB6: =IF(AND(F6<=DATE(2028,10,1),OR(G6="",G6>=DATE(2028,10,1))),H6*(1+Assumptions!$C$7)^3,0) | BC6: =IF(AND(F6<=DATE(2028,11,1),OR(G6="",G6>=DATE(2028,11,1))),H6*(1+Assumptions!$C$7)^3,0) | BD6: =IF(AND(F6<=DATE(2028,12,1),OR(G6="",G6>=DATE(2028,12,1))),H6*(1+Assumptions!$C$7)^3,0) | BE6: =IF(AND(F6<=DATE(2029,1,1),OR(G6="",G6>=DATE(2029,1,1))),H6*(1+Assumptions!$C$7)^4,0) | BF6: =IF(AND(F6<=DATE(2029,2,1),OR(G6="",G6>=DATE(2029,2,1))),H6*(1+Assumptions!$C$7)^4,0) | BG6: =IF(AND(F6<=DATE(2029,3,1),OR(G6="",G6>=DATE(2029,3,1))),H6*(1+Assumptions!$C$7)^4,0) | BH6: =IF(AND(F6<=DATE(2029,4,1),OR(G6="",G6>=DATE(2029,4,1))),H6*(1+Assumptions!$C$7)^4,0) | BI6: =IF(AND(F6<=DATE(2029,5,1),OR(G6="",G6>=DATE(2029,5,1))),H6*(1+Assumptions!$C$7)^4,0) | BJ6: =IF(AND(F6<=DATE(2029,6,1),OR(G6="",G6>=DATE(2029,6,1))),H6*(1+Assumptions!$C$7)^4,0) | BK6: =IF(AND(F6<=DATE(2029,7,1),OR(G6="",G6>=DATE(2029,7,1))),H6*(1+Assumptions!$C$7)^4,0) | BL6: =IF(AND(F6<=DATE(2029,8,1),OR(G6="",G6>=DATE(2029,8,1))),H6*(1+Assumptions!$C$7)^4,0) | BM6: =IF(AND(F6<=DATE(2029,9,1),OR(G6="",G6>=DATE(2029,9,1))),H6*(1+Assumptions!$C$7)^4,0) | BN6: =IF(AND(F6<=DATE(2029,10,1),OR(G6="",G6>=DATE(2029,10,1))),H6*(1+Assumptions!$C$7)^4,0) | BO6: =IF(AND(F6<=DATE(2029,11,1),OR(G6="",G6>=DATE(2029,11,1))),H6*(1+Assumptions!$C$7)^4,0) | BP6: =IF(AND(F6<=DATE(2029,12,1),OR(G6="",G6>=DATE(2029,12,1))),H6*(1+Assumptions!$C$7)^4,0) | BR6: paid this month if started and not yet left; +8% each calendar year
A7: 5 | B7: Firmware Engineer | C7: R&D | D7: R&D Engineer | E7: Current | F7: 45901 | H7: 7000 | I7: =IF(AND(F7<=DATE(2025,1,1),OR(G7="",G7>=DATE(2025,1,1))),H7*(1+Assumptions!$C$7)^0,0) | J7: =IF(AND(F7<=DATE(2025,2,1),OR(G7="",G7>=DATE(2025,2,1))),H7*(1+Assumptions!$C$7)^0,0) | K7: =IF(AND(F7<=DATE(2025,3,1),OR(G7="",G7>=DATE(2025,3,1))),H7*(1+Assumptions!$C$7)^0,0) | L7: =IF(AND(F7<=DATE(2025,4,1),OR(G7="",G7>=DATE(2025,4,1))),H7*(1+Assumptions!$C$7)^0,0) | M7: =IF(AND(F7<=DATE(2025,5,1),OR(G7="",G7>=DATE(2025,5,1))),H7*(1+Assumptions!$C$7)^0,0) | N7: =IF(AND(F7<=DATE(2025,6,1),OR(G7="",G7>=DATE(2025,6,1))),H7*(1+Assumptions!$C$7)^0,0) | O7: =IF(AND(F7<=DATE(2025,7,1),OR(G7="",G7>=DATE(2025,7,1))),H7*(1+Assumptions!$C$7)^0,0) | P7: =IF(AND(F7<=DATE(2025,8,1),OR(G7="",G7>=DATE(2025,8,1))),H7*(1+Assumptions!$C$7)^0,0) | Q7: =IF(AND(F7<=DATE(2025,9,1),OR(G7="",G7>=DATE(2025,9,1))),H7*(1+Assumptions!$C$7)^0,0) | R7: =IF(AND(F7<=DATE(2025,10,1),OR(G7="",G7>=DATE(2025,10,1))),H7*(1+Assumptions!$C$7)^0,0) | S7: =IF(AND(F7<=DATE(2025,11,1),OR(G7="",G7>=DATE(2025,11,1))),H7*(1+Assumptions!$C$7)^0,0) | T7: =IF(AND(F7<=DATE(2025,12,1),OR(G7="",G7>=DATE(2025,12,1))),H7*(1+Assumptions!$C$7)^0,0) | U7: =IF(AND(F7<=DATE(2026,1,1),OR(G7="",G7>=DATE(2026,1,1))),H7*(1+Assumptions!$C$7)^1,0) | V7: =IF(AND(F7<=DATE(2026,2,1),OR(G7="",G7>=DATE(2026,2,1))),H7*(1+Assumptions!$C$7)^1,0) | W7: =IF(AND(F7<=DATE(2026,3,1),OR(G7="",G7>=DATE(2026,3,1))),H7*(1+Assumptions!$C$7)^1,0) | X7: =IF(AND(F7<=DATE(2026,4,1),OR(G7="",G7>=DATE(2026,4,1))),H7*(1+Assumptions!$C$7)^1,0) | Y7: =IF(AND(F7<=DATE(2026,5,1),OR(G7="",G7>=DATE(2026,5,1))),H7*(1+Assumptions!$C$7)^1,0) | Z7: =IF(AND(F7<=DATE(2026,6,1),OR(G7="",G7>=DATE(2026,6,1))),H7*(1+Assumptions!$C$7)^1,0) | AA7: =IF(AND(F7<=DATE(2026,7,1),OR(G7="",G7>=DATE(2026,7,1))),H7*(1+Assumptions!$C$7)^1,0) | AB7: =IF(AND(F7<=DATE(2026,8,1),OR(G7="",G7>=DATE(2026,8,1))),H7*(1+Assumptions!$C$7)^1,0) | AC7: =IF(AND(F7<=DATE(2026,9,1),OR(G7="",G7>=DATE(2026,9,1))),H7*(1+Assumptions!$C$7)^1,0) | AD7: =IF(AND(F7<=DATE(2026,10,1),OR(G7="",G7>=DATE(2026,10,1))),H7*(1+Assumptions!$C$7)^1,0) | AE7: =IF(AND(F7<=DATE(2026,11,1),OR(G7="",G7>=DATE(2026,11,1))),H7*(1+Assumptions!$C$7)^1,0) | AF7: =IF(AND(F7<=DATE(2026,12,1),OR(G7="",G7>=DATE(2026,12,1))),H7*(1+Assumptions!$C$7)^1,0) | AG7: =IF(AND(F7<=DATE(2027,1,1),OR(G7="",G7>=DATE(2027,1,1))),H7*(1+Assumptions!$C$7)^2,0) | AH7: =IF(AND(F7<=DATE(2027,2,1),OR(G7="",G7>=DATE(2027,2,1))),H7*(1+Assumptions!$C$7)^2,0) | AI7: =IF(AND(F7<=DATE(2027,3,1),OR(G7="",G7>=DATE(2027,3,1))),H7*(1+Assumptions!$C$7)^2,0) | AJ7: =IF(AND(F7<=DATE(2027,4,1),OR(G7="",G7>=DATE(2027,4,1))),H7*(1+Assumptions!$C$7)^2,0) | AK7: =IF(AND(F7<=DATE(2027,5,1),OR(G7="",G7>=DATE(2027,5,1))),H7*(1+Assumptions!$C$7)^2,0) | AL7: =IF(AND(F7<=DATE(2027,6,1),OR(G7="",G7>=DATE(2027,6,1))),H7*(1+Assumptions!$C$7)^2,0) | AM7: =IF(AND(F7<=DATE(2027,7,1),OR(G7="",G7>=DATE(2027,7,1))),H7*(1+Assumptions!$C$7)^2,0) | AN7: =IF(AND(F7<=DATE(2027,8,1),OR(G7="",G7>=DATE(2027,8,1))),H7*(1+Assumptions!$C$7)^2,0) | AO7: =IF(AND(F7<=DATE(2027,9,1),OR(G7="",G7>=DATE(2027,9,1))),H7*(1+Assumptions!$C$7)^2,0) | AP7: =IF(AND(F7<=DATE(2027,10,1),OR(G7="",G7>=DATE(2027,10,1))),H7*(1+Assumptions!$C$7)^2,0) | AQ7: =IF(AND(F7<=DATE(2027,11,1),OR(G7="",G7>=DATE(2027,11,1))),H7*(1+Assumptions!$C$7)^2,0) | AR7: =IF(AND(F7<=DATE(2027,12,1),OR(G7="",G7>=DATE(2027,12,1))),H7*(1+Assumptions!$C$7)^2,0) | AS7: =IF(AND(F7<=DATE(2028,1,1),OR(G7="",G7>=DATE(2028,1,1))),H7*(1+Assumptions!$C$7)^3,0) | AT7: =IF(AND(F7<=DATE(2028,2,1),OR(G7="",G7>=DATE(2028,2,1))),H7*(1+Assumptions!$C$7)^3,0) | AU7: =IF(AND(F7<=DATE(2028,3,1),OR(G7="",G7>=DATE(2028,3,1))),H7*(1+Assumptions!$C$7)^3,0) | AV7: =IF(AND(F7<=DATE(2028,4,1),OR(G7="",G7>=DATE(2028,4,1))),H7*(1+Assumptions!$C$7)^3,0) | AW7: =IF(AND(F7<=DATE(2028,5,1),OR(G7="",G7>=DATE(2028,5,1))),H7*(1+Assumptions!$C$7)^3,0) | AX7: =IF(AND(F7<=DATE(2028,6,1),OR(G7="",G7>=DATE(2028,6,1))),H7*(1+Assumptions!$C$7)^3,0) | AY7: =IF(AND(F7<=DATE(2028,7,1),OR(G7="",G7>=DATE(2028,7,1))),H7*(1+Assumptions!$C$7)^3,0) | AZ7: =IF(AND(F7<=DATE(2028,8,1),OR(G7="",G7>=DATE(2028,8,1))),H7*(1+Assumptions!$C$7)^3,0) | BA7: =IF(AND(F7<=DATE(2028,9,1),OR(G7="",G7>=DATE(2028,9,1))),H7*(1+Assumptions!$C$7)^3,0) | BB7: =IF(AND(F7<=DATE(2028,10,1),OR(G7="",G7>=DATE(2028,10,1))),H7*(1+Assumptions!$C$7)^3,0) | BC7: =IF(AND(F7<=DATE(2028,11,1),OR(G7="",G7>=DATE(2028,11,1))),H7*(1+Assumptions!$C$7)^3,0) | BD7: =IF(AND(F7<=DATE(2028,12,1),OR(G7="",G7>=DATE(2028,12,1))),H7*(1+Assumptions!$C$7)^3,0) | BE7: =IF(AND(F7<=DATE(2029,1,1),OR(G7="",G7>=DATE(2029,1,1))),H7*(1+Assumptions!$C$7)^4,0) | BF7: =IF(AND(F7<=DATE(2029,2,1),OR(G7="",G7>=DATE(2029,2,1))),H7*(1+Assumptions!$C$7)^4,0) | BG7: =IF(AND(F7<=DATE(2029,3,1),OR(G7="",G7>=DATE(2029,3,1))),H7*(1+Assumptions!$C$7)^4,0) | BH7: =IF(AND(F7<=DATE(2029,4,1),OR(G7="",G7>=DATE(2029,4,1))),H7*(1+Assumptions!$C$7)^4,0) | BI7: =IF(AND(F7<=DATE(2029,5,1),OR(G7="",G7>=DATE(2029,5,1))),H7*(1+Assumptions!$C$7)^4,0) | BJ7: =IF(AND(F7<=DATE(2029,6,1),OR(G7="",G7>=DATE(2029,6,1))),H7*(1+Assumptions!$C$7)^4,0) | BK7: =IF(AND(F7<=DATE(2029,7,1),OR(G7="",G7>=DATE(2029,7,1))),H7*(1+Assumptions!$C$7)^4,0) | BL7: =IF(AND(F7<=DATE(2029,8,1),OR(G7="",G7>=DATE(2029,8,1))),H7*(1+Assumptions!$C$7)^4,0) | BM7: =IF(AND(F7<=DATE(2029,9,1),OR(G7="",G7>=DATE(2029,9,1))),H7*(1+Assumptions!$C$7)^4,0) | BN7: =IF(AND(F7<=DATE(2029,10,1),OR(G7="",G7>=DATE(2029,10,1))),H7*(1+Assumptions!$C$7)^4,0) | BO7: =IF(AND(F7<=DATE(2029,11,1),OR(G7="",G7>=DATE(2029,11,1))),H7*(1+Assumptions!$C$7)^4,0) | BP7: =IF(AND(F7<=DATE(2029,12,1),OR(G7="",G7>=DATE(2029,12,1))),H7*(1+Assumptions!$C$7)^4,0) | BR7: paid this month if started and not yet left; +8% each calendar year
A8: 6 | B8: Mechanical Engineer | C8: R&D | D8: R&D Engineer | E8: Current | F8: 45901 | H8: 5500 | I8: =IF(AND(F8<=DATE(2025,1,1),OR(G8="",G8>=DATE(2025,1,1))),H8*(1+Assumptions!$C$7)^0,0) | J8: =IF(AND(F8<=DATE(2025,2,1),OR(G8="",G8>=DATE(2025,2,1))),H8*(1+Assumptions!$C$7)^0,0) | K8: =IF(AND(F8<=DATE(2025,3,1),OR(G8="",G8>=DATE(2025,3,1))),H8*(1+Assumptions!$C$7)^0,0) | L8: =IF(AND(F8<=DATE(2025,4,1),OR(G8="",G8>=DATE(2025,4,1))),H8*(1+Assumptions!$C$7)^0,0) | M8: =IF(AND(F8<=DATE(2025,5,1),OR(G8="",G8>=DATE(2025,5,1))),H8*(1+Assumptions!$C$7)^0,0) | N8: =IF(AND(F8<=DATE(2025,6,1),OR(G8="",G8>=DATE(2025,6,1))),H8*(1+Assumptions!$C$7)^0,0) | O8: =IF(AND(F8<=DATE(2025,7,1),OR(G8="",G8>=DATE(2025,7,1))),H8*(1+Assumptions!$C$7)^0,0) | P8: =IF(AND(F8<=DATE(2025,8,1),OR(G8="",G8>=DATE(2025,8,1))),H8*(1+Assumptions!$C$7)^0,0) | Q8: =IF(AND(F8<=DATE(2025,9,1),OR(G8="",G8>=DATE(2025,9,1))),H8*(1+Assumptions!$C$7)^0,0) | R8: =IF(AND(F8<=DATE(2025,10,1),OR(G8="",G8>=DATE(2025,10,1))),H8*(1+Assumptions!$C$7)^0,0) | S8: =IF(AND(F8<=DATE(2025,11,1),OR(G8="",G8>=DATE(2025,11,1))),H8*(1+Assumptions!$C$7)^0,0) | T8: =IF(AND(F8<=DATE(2025,12,1),OR(G8="",G8>=DATE(2025,12,1))),H8*(1+Assumptions!$C$7)^0,0) | U8: =IF(AND(F8<=DATE(2026,1,1),OR(G8="",G8>=DATE(2026,1,1))),H8*(1+Assumptions!$C$7)^1,0) | V8: =IF(AND(F8<=DATE(2026,2,1),OR(G8="",G8>=DATE(2026,2,1))),H8*(1+Assumptions!$C$7)^1,0) | W8: =IF(AND(F8<=DATE(2026,3,1),OR(G8="",G8>=DATE(2026,3,1))),H8*(1+Assumptions!$C$7)^1,0) | X8: =IF(AND(F8<=DATE(2026,4,1),OR(G8="",G8>=DATE(2026,4,1))),H8*(1+Assumptions!$C$7)^1,0) | Y8: =IF(AND(F8<=DATE(2026,5,1),OR(G8="",G8>=DATE(2026,5,1))),H8*(1+Assumptions!$C$7)^1,0) | Z8: =IF(AND(F8<=DATE(2026,6,1),OR(G8="",G8>=DATE(2026,6,1))),H8*(1+Assumptions!$C$7)^1,0) | AA8: =IF(AND(F8<=DATE(2026,7,1),OR(G8="",G8>=DATE(2026,7,1))),H8*(1+Assumptions!$C$7)^1,0) | AB8: =IF(AND(F8<=DATE(2026,8,1),OR(G8="",G8>=DATE(2026,8,1))),H8*(1+Assumptions!$C$7)^1,0) | AC8: =IF(AND(F8<=DATE(2026,9,1),OR(G8="",G8>=DATE(2026,9,1))),H8*(1+Assumptions!$C$7)^1,0) | AD8: =IF(AND(F8<=DATE(2026,10,1),OR(G8="",G8>=DATE(2026,10,1))),H8*(1+Assumptions!$C$7)^1,0) | AE8: =IF(AND(F8<=DATE(2026,11,1),OR(G8="",G8>=DATE(2026,11,1))),H8*(1+Assumptions!$C$7)^1,0) | AF8: =IF(AND(F8<=DATE(2026,12,1),OR(G8="",G8>=DATE(2026,12,1))),H8*(1+Assumptions!$C$7)^1,0) | AG8: =IF(AND(F8<=DATE(2027,1,1),OR(G8="",G8>=DATE(2027,1,1))),H8*(1+Assumptions!$C$7)^2,0) | AH8: =IF(AND(F8<=DATE(2027,2,1),OR(G8="",G8>=DATE(2027,2,1))),H8*(1+Assumptions!$C$7)^2,0) | AI8: =IF(AND(F8<=DATE(2027,3,1),OR(G8="",G8>=DATE(2027,3,1))),H8*(1+Assumptions!$C$7)^2,0) | AJ8: =IF(AND(F8<=DATE(2027,4,1),OR(G8="",G8>=DATE(2027,4,1))),H8*(1+Assumptions!$C$7)^2,0) | AK8: =IF(AND(F8<=DATE(2027,5,1),OR(G8="",G8>=DATE(2027,5,1))),H8*(1+Assumptions!$C$7)^2,0) | AL8: =IF(AND(F8<=DATE(2027,6,1),OR(G8="",G8>=DATE(2027,6,1))),H8*(1+Assumptions!$C$7)^2,0) | AM8: =IF(AND(F8<=DATE(2027,7,1),OR(G8="",G8>=DATE(2027,7,1))),H8*(1+Assumptions!$C$7)^2,0) | AN8: =IF(AND(F8<=DATE(2027,8,1),OR(G8="",G8>=DATE(2027,8,1))),H8*(1+Assumptions!$C$7)^2,0) | AO8: =IF(AND(F8<=DATE(2027,9,1),OR(G8="",G8>=DATE(2027,9,1))),H8*(1+Assumptions!$C$7)^2,0) | AP8: =IF(AND(F8<=DATE(2027,10,1),OR(G8="",G8>=DATE(2027,10,1))),H8*(1+Assumptions!$C$7)^2,0) | AQ8: =IF(AND(F8<=DATE(2027,11,1),OR(G8="",G8>=DATE(2027,11,1))),H8*(1+Assumptions!$C$7)^2,0) | AR8: =IF(AND(F8<=DATE(2027,12,1),OR(G8="",G8>=DATE(2027,12,1))),H8*(1+Assumptions!$C$7)^2,0) | AS8: =IF(AND(F8<=DATE(2028,1,1),OR(G8="",G8>=DATE(2028,1,1))),H8*(1+Assumptions!$C$7)^3,0) | AT8: =IF(AND(F8<=DATE(2028,2,1),OR(G8="",G8>=DATE(2028,2,1))),H8*(1+Assumptions!$C$7)^3,0) | AU8: =IF(AND(F8<=DATE(2028,3,1),OR(G8="",G8>=DATE(2028,3,1))),H8*(1+Assumptions!$C$7)^3,0) | AV8: =IF(AND(F8<=DATE(2028,4,1),OR(G8="",G8>=DATE(2028,4,1))),H8*(1+Assumptions!$C$7)^3,0) | AW8: =IF(AND(F8<=DATE(2028,5,1),OR(G8="",G8>=DATE(2028,5,1))),H8*(1+Assumptions!$C$7)^3,0) | AX8: =IF(AND(F8<=DATE(2028,6,1),OR(G8="",G8>=DATE(2028,6,1))),H8*(1+Assumptions!$C$7)^3,0) | AY8: =IF(AND(F8<=DATE(2028,7,1),OR(G8="",G8>=DATE(2028,7,1))),H8*(1+Assumptions!$C$7)^3,0) | AZ8: =IF(AND(F8<=DATE(2028,8,1),OR(G8="",G8>=DATE(2028,8,1))),H8*(1+Assumptions!$C$7)^3,0) | BA8: =IF(AND(F8<=DATE(2028,9,1),OR(G8="",G8>=DATE(2028,9,1))),H8*(1+Assumptions!$C$7)^3,0) | BB8: =IF(AND(F8<=DATE(2028,10,1),OR(G8="",G8>=DATE(2028,10,1))),H8*(1+Assumptions!$C$7)^3,0) | BC8: =IF(AND(F8<=DATE(2028,11,1),OR(G8="",G8>=DATE(2028,11,1))),H8*(1+Assumptions!$C$7)^3,0) | BD8: =IF(AND(F8<=DATE(2028,12,1),OR(G8="",G8>=DATE(2028,12,1))),H8*(1+Assumptions!$C$7)^3,0) | BE8: =IF(AND(F8<=DATE(2029,1,1),OR(G8="",G8>=DATE(2029,1,1))),H8*(1+Assumptions!$C$7)^4,0) | BF8: =IF(AND(F8<=DATE(2029,2,1),OR(G8="",G8>=DATE(2029,2,1))),H8*(1+Assumptions!$C$7)^4,0) | BG8: =IF(AND(F8<=DATE(2029,3,1),OR(G8="",G8>=DATE(2029,3,1))),H8*(1+Assumptions!$C$7)^4,0) | BH8: =IF(AND(F8<=DATE(2029,4,1),OR(G8="",G8>=DATE(2029,4,1))),H8*(1+Assumptions!$C$7)^4,0) | BI8: =IF(AND(F8<=DATE(2029,5,1),OR(G8="",G8>=DATE(2029,5,1))),H8*(1+Assumptions!$C$7)^4,0) | BJ8: =IF(AND(F8<=DATE(2029,6,1),OR(G8="",G8>=DATE(2029,6,1))),H8*(1+Assumptions!$C$7)^4,0) | BK8: =IF(AND(F8<=DATE(2029,7,1),OR(G8="",G8>=DATE(2029,7,1))),H8*(1+Assumptions!$C$7)^4,0) | BL8: =IF(AND(F8<=DATE(2029,8,1),OR(G8="",G8>=DATE(2029,8,1))),H8*(1+Assumptions!$C$7)^4,0) | BM8: =IF(AND(F8<=DATE(2029,9,1),OR(G8="",G8>=DATE(2029,9,1))),H8*(1+Assumptions!$C$7)^4,0) | BN8: =IF(AND(F8<=DATE(2029,10,1),OR(G8="",G8>=DATE(2029,10,1))),H8*(1+Assumptions!$C$7)^4,0) | BO8: =IF(AND(F8<=DATE(2029,11,1),OR(G8="",G8>=DATE(2029,11,1))),H8*(1+Assumptions!$C$7)^4,0) | BP8: =IF(AND(F8<=DATE(2029,12,1),OR(G8="",G8>=DATE(2029,12,1))),H8*(1+Assumptions!$C$7)^4,0) | BR8: paid this month if started and not yet left; +8% each calendar year
A9: 7 | B9: Electrical Engineer | C9: R&D | D9: R&D Engineer | E9: Current | F9: 45901 | H9: 5500 | I9: =IF(AND(F9<=DATE(2025,1,1),OR(G9="",G9>=DATE(2025,1,1))),H9*(1+Assumptions!$C$7)^0,0) | J9: =IF(AND(F9<=DATE(2025,2,1),OR(G9="",G9>=DATE(2025,2,1))),H9*(1+Assumptions!$C$7)^0,0) | K9: =IF(AND(F9<=DATE(2025,3,1),OR(G9="",G9>=DATE(2025,3,1))),H9*(1+Assumptions!$C$7)^0,0) | L9: =IF(AND(F9<=DATE(2025,4,1),OR(G9="",G9>=DATE(2025,4,1))),H9*(1+Assumptions!$C$7)^0,0) | M9: =IF(AND(F9<=DATE(2025,5,1),OR(G9="",G9>=DATE(2025,5,1))),H9*(1+Assumptions!$C$7)^0,0) | N9: =IF(AND(F9<=DATE(2025,6,1),OR(G9="",G9>=DATE(2025,6,1))),H9*(1+Assumptions!$C$7)^0,0) | O9: =IF(AND(F9<=DATE(2025,7,1),OR(G9="",G9>=DATE(2025,7,1))),H9*(1+Assumptions!$C$7)^0,0) | P9: =IF(AND(F9<=DATE(2025,8,1),OR(G9="",G9>=DATE(2025,8,1))),H9*(1+Assumptions!$C$7)^0,0) | Q9: =IF(AND(F9<=DATE(2025,9,1),OR(G9="",G9>=DATE(2025,9,1))),H9*(1+Assumptions!$C$7)^0,0) | R9: =IF(AND(F9<=DATE(2025,10,1),OR(G9="",G9>=DATE(2025,10,1))),H9*(1+Assumptions!$C$7)^0,0) | S9: =IF(AND(F9<=DATE(2025,11,1),OR(G9="",G9>=DATE(2025,11,1))),H9*(1+Assumptions!$C$7)^0,0) | T9: =IF(AND(F9<=DATE(2025,12,1),OR(G9="",G9>=DATE(2025,12,1))),H9*(1+Assumptions!$C$7)^0,0) | U9: =IF(AND(F9<=DATE(2026,1,1),OR(G9="",G9>=DATE(2026,1,1))),H9*(1+Assumptions!$C$7)^1,0) | V9: =IF(AND(F9<=DATE(2026,2,1),OR(G9="",G9>=DATE(2026,2,1))),H9*(1+Assumptions!$C$7)^1,0) | W9: =IF(AND(F9<=DATE(2026,3,1),OR(G9="",G9>=DATE(2026,3,1))),H9*(1+Assumptions!$C$7)^1,0) | X9: =IF(AND(F9<=DATE(2026,4,1),OR(G9="",G9>=DATE(2026,4,1))),H9*(1+Assumptions!$C$7)^1,0) | Y9: =IF(AND(F9<=DATE(2026,5,1),OR(G9="",G9>=DATE(2026,5,1))),H9*(1+Assumptions!$C$7)^1,0) | Z9: =IF(AND(F9<=DATE(2026,6,1),OR(G9="",G9>=DATE(2026,6,1))),H9*(1+Assumptions!$C$7)^1,0) | AA9: =IF(AND(F9<=DATE(2026,7,1),OR(G9="",G9>=DATE(2026,7,1))),H9*(1+Assumptions!$C$7)^1,0) | AB9: =IF(AND(F9<=DATE(2026,8,1),OR(G9="",G9>=DATE(2026,8,1))),H9*(1+Assumptions!$C$7)^1,0) | AC9: =IF(AND(F9<=DATE(2026,9,1),OR(G9="",G9>=DATE(2026,9,1))),H9*(1+Assumptions!$C$7)^1,0) | AD9: =IF(AND(F9<=DATE(2026,10,1),OR(G9="",G9>=DATE(2026,10,1))),H9*(1+Assumptions!$C$7)^1,0) | AE9: =IF(AND(F9<=DATE(2026,11,1),OR(G9="",G9>=DATE(2026,11,1))),H9*(1+Assumptions!$C$7)^1,0) | AF9: =IF(AND(F9<=DATE(2026,12,1),OR(G9="",G9>=DATE(2026,12,1))),H9*(1+Assumptions!$C$7)^1,0) | AG9: =IF(AND(F9<=DATE(2027,1,1),OR(G9="",G9>=DATE(2027,1,1))),H9*(1+Assumptions!$C$7)^2,0) | AH9: =IF(AND(F9<=DATE(2027,2,1),OR(G9="",G9>=DATE(2027,2,1))),H9*(1+Assumptions!$C$7)^2,0) | AI9: =IF(AND(F9<=DATE(2027,3,1),OR(G9="",G9>=DATE(2027,3,1))),H9*(1+Assumptions!$C$7)^2,0) | AJ9: =IF(AND(F9<=DATE(2027,4,1),OR(G9="",G9>=DATE(2027,4,1))),H9*(1+Assumptions!$C$7)^2,0) | AK9: =IF(AND(F9<=DATE(2027,5,1),OR(G9="",G9>=DATE(2027,5,1))),H9*(1+Assumptions!$C$7)^2,0) | AL9: =IF(AND(F9<=DATE(2027,6,1),OR(G9="",G9>=DATE(2027,6,1))),H9*(1+Assumptions!$C$7)^2,0) | AM9: =IF(AND(F9<=DATE(2027,7,1),OR(G9="",G9>=DATE(2027,7,1))),H9*(1+Assumptions!$C$7)^2,0) | AN9: =IF(AND(F9<=DATE(2027,8,1),OR(G9="",G9>=DATE(2027,8,1))),H9*(1+Assumptions!$C$7)^2,0) | AO9: =IF(AND(F9<=DATE(2027,9,1),OR(G9="",G9>=DATE(2027,9,1))),H9*(1+Assumptions!$C$7)^2,0) | AP9: =IF(AND(F9<=DATE(2027,10,1),OR(G9="",G9>=DATE(2027,10,1))),H9*(1+Assumptions!$C$7)^2,0) | AQ9: =IF(AND(F9<=DATE(2027,11,1),OR(G9="",G9>=DATE(2027,11,1))),H9*(1+Assumptions!$C$7)^2,0) | AR9: =IF(AND(F9<=DATE(2027,12,1),OR(G9="",G9>=DATE(2027,12,1))),H9*(1+Assumptions!$C$7)^2,0) | AS9: =IF(AND(F9<=DATE(2028,1,1),OR(G9="",G9>=DATE(2028,1,1))),H9*(1+Assumptions!$C$7)^3,0) | AT9: =IF(AND(F9<=DATE(2028,2,1),OR(G9="",G9>=DATE(2028,2,1))),H9*(1+Assumptions!$C$7)^3,0) | AU9: =IF(AND(F9<=DATE(2028,3,1),OR(G9="",G9>=DATE(2028,3,1))),H9*(1+Assumptions!$C$7)^3,0) | AV9: =IF(AND(F9<=DATE(2028,4,1),OR(G9="",G9>=DATE(2028,4,1))),H9*(1+Assumptions!$C$7)^3,0) | AW9: =IF(AND(F9<=DATE(2028,5,1),OR(G9="",G9>=DATE(2028,5,1))),H9*(1+Assumptions!$C$7)^3,0) | AX9: =IF(AND(F9<=DATE(2028,6,1),OR(G9="",G9>=DATE(2028,6,1))),H9*(1+Assumptions!$C$7)^3,0) | AY9: =IF(AND(F9<=DATE(2028,7,1),OR(G9="",G9>=DATE(2028,7,1))),H9*(1+Assumptions!$C$7)^3,0) | AZ9: =IF(AND(F9<=DATE(2028,8,1),OR(G9="",G9>=DATE(2028,8,1))),H9*(1+Assumptions!$C$7)^3,0) | BA9: =IF(AND(F9<=DATE(2028,9,1),OR(G9="",G9>=DATE(2028,9,1))),H9*(1+Assumptions!$C$7)^3,0) | BB9: =IF(AND(F9<=DATE(2028,10,1),OR(G9="",G9>=DATE(2028,10,1))),H9*(1+Assumptions!$C$7)^3,0) | BC9: =IF(AND(F9<=DATE(2028,11,1),OR(G9="",G9>=DATE(2028,11,1))),H9*(1+Assumptions!$C$7)^3,0) | BD9: =IF(AND(F9<=DATE(2028,12,1),OR(G9="",G9>=DATE(2028,12,1))),H9*(1+Assumptions!$C$7)^3,0) | BE9: =IF(AND(F9<=DATE(2029,1,1),OR(G9="",G9>=DATE(2029,1,1))),H9*(1+Assumptions!$C$7)^4,0) | BF9: =IF(AND(F9<=DATE(2029,2,1),OR(G9="",G9>=DATE(2029,2,1))),H9*(1+Assumptions!$C$7)^4,0) | BG9: =IF(AND(F9<=DATE(2029,3,1),OR(G9="",G9>=DATE(2029,3,1))),H9*(1+Assumptions!$C$7)^4,0) | BH9: =IF(AND(F9<=DATE(2029,4,1),OR(G9="",G9>=DATE(2029,4,1))),H9*(1+Assumptions!$C$7)^4,0) | BI9: =IF(AND(F9<=DATE(2029,5,1),OR(G9="",G9>=DATE(2029,5,1))),H9*(1+Assumptions!$C$7)^4,0) | BJ9: =IF(AND(F9<=DATE(2029,6,1),OR(G9="",G9>=DATE(2029,6,1))),H9*(1+Assumptions!$C$7)^4,0) | BK9: =IF(AND(F9<=DATE(2029,7,1),OR(G9="",G9>=DATE(2029,7,1))),H9*(1+Assumptions!$C$7)^4,0) | BL9: =IF(AND(F9<=DATE(2029,8,1),OR(G9="",G9>=DATE(2029,8,1))),H9*(1+Assumptions!$C$7)^4,0) | BM9: =IF(AND(F9<=DATE(2029,9,1),OR(G9="",G9>=DATE(2029,9,1))),H9*(1+Assumptions!$C$7)^4,0) | BN9: =IF(AND(F9<=DATE(2029,10,1),OR(G9="",G9>=DATE(2029,10,1))),H9*(1+Assumptions!$C$7)^4,0) | BO9: =IF(AND(F9<=DATE(2029,11,1),OR(G9="",G9>=DATE(2029,11,1))),H9*(1+Assumptions!$C$7)^4,0) | BP9: =IF(AND(F9<=DATE(2029,12,1),OR(G9="",G9>=DATE(2029,12,1))),H9*(1+Assumptions!$C$7)^4,0) | BR9: paid this month if started and not yet left; +8% each calendar year
A10: 11 | B10: CFO (part time) | C10: G&A | D10: CFO | E10: Current | F10: 45901 | G10: 46266 | H10: 4000 | I10: =IF(AND(F10<=DATE(2025,1,1),OR(G10="",G10>=DATE(2025,1,1))),H10*(1+Assumptions!$C$7)^0,0) | J10: =IF(AND(F10<=DATE(2025,2,1),OR(G10="",G10>=DATE(2025,2,1))),H10*(1+Assumptions!$C$7)^0,0) | K10: =IF(AND(F10<=DATE(2025,3,1),OR(G10="",G10>=DATE(2025,3,1))),H10*(1+Assumptions!$C$7)^0,0) | L10: =IF(AND(F10<=DATE(2025,4,1),OR(G10="",G10>=DATE(2025,4,1))),H10*(1+Assumptions!$C$7)^0,0) | M10: =IF(AND(F10<=DATE(2025,5,1),OR(G10="",G10>=DATE(2025,5,1))),H10*(1+Assumptions!$C$7)^0,0) | N10: =IF(AND(F10<=DATE(2025,6,1),OR(G10="",G10>=DATE(2025,6,1))),H10*(1+Assumptions!$C$7)^0,0) | O10: =IF(AND(F10<=DATE(2025,7,1),OR(G10="",G10>=DATE(2025,7,1))),H10*(1+Assumptions!$C$7)^0,0) | P10: =IF(AND(F10<=DATE(2025,8,1),OR(G10="",G10>=DATE(2025,8,1))),H10*(1+Assumptions!$C$7)^0,0) | Q10: =IF(AND(F10<=DATE(2025,9,1),OR(G10="",G10>=DATE(2025,9,1))),H10*(1+Assumptions!$C$7)^0,0) | R10: =IF(AND(F10<=DATE(2025,10,1),OR(G10="",G10>=DATE(2025,10,1))),H10*(1+Assumptions!$C$7)^0,0) | S10: =IF(AND(F10<=DATE(2025,11,1),OR(G10="",G10>=DATE(2025,11,1))),H10*(1+Assumptions!$C$7)^0,0) | T10: =IF(AND(F10<=DATE(2025,12,1),OR(G10="",G10>=DATE(2025,12,1))),H10*(1+Assumptions!$C$7)^0,0) | U10: =IF(AND(F10<=DATE(2026,1,1),OR(G10="",G10>=DATE(2026,1,1))),H10*(1+Assumptions!$C$7)^1,0) | V10: =IF(AND(F10<=DATE(2026,2,1),OR(G10="",G10>=DATE(2026,2,1))),H10*(1+Assumptions!$C$7)^1,0) | W10: =IF(AND(F10<=DATE(2026,3,1),OR(G10="",G10>=DATE(2026,3,1))),H10*(1+Assumptions!$C$7)^1,0) | X10: =IF(AND(F10<=DATE(2026,4,1),OR(G10="",G10>=DATE(2026,4,1))),H10*(1+Assumptions!$C$7)^1,0) | Y10: =IF(AND(F10<=DATE(2026,5,1),OR(G10="",G10>=DATE(2026,5,1))),H10*(1+Assumptions!$C$7)^1,0) | Z10: =IF(AND(F10<=DATE(2026,6,1),OR(G10="",G10>=DATE(2026,6,1))),H10*(1+Assumptions!$C$7)^1,0) | AA10: =IF(AND(F10<=DATE(2026,7,1),OR(G10="",G10>=DATE(2026,7,1))),H10*(1+Assumptions!$C$7)^1,0) | AB10: =IF(AND(F10<=DATE(2026,8,1),OR(G10="",G10>=DATE(2026,8,1))),H10*(1+Assumptions!$C$7)^1,0) | AC10: =IF(AND(F10<=DATE(2026,9,1),OR(G10="",G10>=DATE(2026,9,1))),H10*(1+Assumptions!$C$7)^1,0) | AD10: =IF(AND(F10<=DATE(2026,10,1),OR(G10="",G10>=DATE(2026,10,1))),H10*(1+Assumptions!$C$7)^1,0) | AE10: =IF(AND(F10<=DATE(2026,11,1),OR(G10="",G10>=DATE(2026,11,1))),H10*(1+Assumptions!$C$7)^1,0) | AF10: =IF(AND(F10<=DATE(2026,12,1),OR(G10="",G10>=DATE(2026,12,1))),H10*(1+Assumptions!$C$7)^1,0) | AG10: =IF(AND(F10<=DATE(2027,1,1),OR(G10="",G10>=DATE(2027,1,1))),H10*(1+Assumptions!$C$7)^2,0) | AH10: =IF(AND(F10<=DATE(2027,2,1),OR(G10="",G10>=DATE(2027,2,1))),H10*(1+Assumptions!$C$7)^2,0) | AI10: =IF(AND(F10<=DATE(2027,3,1),OR(G10="",G10>=DATE(2027,3,1))),H10*(1+Assumptions!$C$7)^2,0) | AJ10: =IF(AND(F10<=DATE(2027,4,1),OR(G10="",G10>=DATE(2027,4,1))),H10*(1+Assumptions!$C$7)^2,0) | AK10: =IF(AND(F10<=DATE(2027,5,1),OR(G10="",G10>=DATE(2027,5,1))),H10*(1+Assumptions!$C$7)^2,0) | AL10: =IF(AND(F10<=DATE(2027,6,1),OR(G10="",G10>=DATE(2027,6,1))),H10*(1+Assumptions!$C$7)^2,0) | AM10: =IF(AND(F10<=DATE(2027,7,1),OR(G10="",G10>=DATE(2027,7,1))),H10*(1+Assumptions!$C$7)^2,0) | AN10: =IF(AND(F10<=DATE(2027,8,1),OR(G10="",G10>=DATE(2027,8,1))),H10*(1+Assumptions!$C$7)^2,0) | AO10: =IF(AND(F10<=DATE(2027,9,1),OR(G10="",G10>=DATE(2027,9,1))),H10*(1+Assumptions!$C$7)^2,0) | AP10: =IF(AND(F10<=DATE(2027,10,1),OR(G10="",G10>=DATE(2027,10,1))),H10*(1+Assumptions!$C$7)^2,0) | AQ10: =IF(AND(F10<=DATE(2027,11,1),OR(G10="",G10>=DATE(2027,11,1))),H10*(1+Assumptions!$C$7)^2,0) | AR10: =IF(AND(F10<=DATE(2027,12,1),OR(G10="",G10>=DATE(2027,12,1))),H10*(1+Assumptions!$C$7)^2,0) | AS10: =IF(AND(F10<=DATE(2028,1,1),OR(G10="",G10>=DATE(2028,1,1))),H10*(1+Assumptions!$C$7)^3,0) | AT10: =IF(AND(F10<=DATE(2028,2,1),OR(G10="",G10>=DATE(2028,2,1))),H10*(1+Assumptions!$C$7)^3,0) | AU10: =IF(AND(F10<=DATE(2028,3,1),OR(G10="",G10>=DATE(2028,3,1))),H10*(1+Assumptions!$C$7)^3,0) | AV10: =IF(AND(F10<=DATE(2028,4,1),OR(G10="",G10>=DATE(2028,4,1))),H10*(1+Assumptions!$C$7)^3,0) | AW10: =IF(AND(F10<=DATE(2028,5,1),OR(G10="",G10>=DATE(2028,5,1))),H10*(1+Assumptions!$C$7)^3,0) | AX10: =IF(AND(F10<=DATE(2028,6,1),OR(G10="",G10>=DATE(2028,6,1))),H10*(1+Assumptions!$C$7)^3,0) | AY10: =IF(AND(F10<=DATE(2028,7,1),OR(G10="",G10>=DATE(2028,7,1))),H10*(1+Assumptions!$C$7)^3,0) | AZ10: =IF(AND(F10<=DATE(2028,8,1),OR(G10="",G10>=DATE(2028,8,1))),H10*(1+Assumptions!$C$7)^3,0) | BA10: =IF(AND(F10<=DATE(2028,9,1),OR(G10="",G10>=DATE(2028,9,1))),H10*(1+Assumptions!$C$7)^3,0) | BB10: =IF(AND(F10<=DATE(2028,10,1),OR(G10="",G10>=DATE(2028,10,1))),H10*(1+Assumptions!$C$7)^3,0) | BC10: =IF(AND(F10<=DATE(2028,11,1),OR(G10="",G10>=DATE(2028,11,1))),H10*(1+Assumptions!$C$7)^3,0) | BD10: =IF(AND(F10<=DATE(2028,12,1),OR(G10="",G10>=DATE(2028,12,1))),H10*(1+Assumptions!$C$7)^3,0) | BE10: =IF(AND(F10<=DATE(2029,1,1),OR(G10="",G10>=DATE(2029,1,1))),H10*(1+Assumptions!$C$7)^4,0) | BF10: =IF(AND(F10<=DATE(2029,2,1),OR(G10="",G10>=DATE(2029,2,1))),H10*(1+Assumptions!$C$7)^4,0) | BG10: =IF(AND(F10<=DATE(2029,3,1),OR(G10="",G10>=DATE(2029,3,1))),H10*(1+Assumptions!$C$7)^4,0) | BH10: =IF(AND(F10<=DATE(2029,4,1),OR(G10="",G10>=DATE(2029,4,1))),H10*(1+Assumptions!$C$7)^4,0) | BI10: =IF(AND(F10<=DATE(2029,5,1),OR(G10="",G10>=DATE(2029,5,1))),H10*(1+Assumptions!$C$7)^4,0) | BJ10: =IF(AND(F10<=DATE(2029,6,1),OR(G10="",G10>=DATE(2029,6,1))),H10*(1+Assumptions!$C$7)^4,0) | BK10: =IF(AND(F10<=DATE(2029,7,1),OR(G10="",G10>=DATE(2029,7,1))),H10*(1+Assumptions!$C$7)^4,0) | BL10: =IF(AND(F10<=DATE(2029,8,1),OR(G10="",G10>=DATE(2029,8,1))),H10*(1+Assumptions!$C$7)^4,0) | BM10: =IF(AND(F10<=DATE(2029,9,1),OR(G10="",G10>=DATE(2029,9,1))),H10*(1+Assumptions!$C$7)^4,0) | BN10: =IF(AND(F10<=DATE(2029,10,1),OR(G10="",G10>=DATE(2029,10,1))),H10*(1+Assumptions!$C$7)^4,0) | BO10: =IF(AND(F10<=DATE(2029,11,1),OR(G10="",G10>=DATE(2029,11,1))),H10*(1+Assumptions!$C$7)^4,0) | BP10: =IF(AND(F10<=DATE(2029,12,1),OR(G10="",G10>=DATE(2029,12,1))),H10*(1+Assumptions!$C$7)^4,0) | BR10: paid this month if started and not yet left; +8% each calendar year
A11: 8 | B11: CTO | C11: R&D | D11: CTO | E11: Current | F11: 46266 | H11: 11500 | I11: =IF(AND(F11<=DATE(2025,1,1),OR(G11="",G11>=DATE(2025,1,1))),H11*(1+Assumptions!$C$7)^0,0) | J11: =IF(AND(F11<=DATE(2025,2,1),OR(G11="",G11>=DATE(2025,2,1))),H11*(1+Assumptions!$C$7)^0,0) | K11: =IF(AND(F11<=DATE(2025,3,1),OR(G11="",G11>=DATE(2025,3,1))),H11*(1+Assumptions!$C$7)^0,0) | L11: =IF(AND(F11<=DATE(2025,4,1),OR(G11="",G11>=DATE(2025,4,1))),H11*(1+Assumptions!$C$7)^0,0) | M11: =IF(AND(F11<=DATE(2025,5,1),OR(G11="",G11>=DATE(2025,5,1))),H11*(1+Assumptions!$C$7)^0,0) | N11: =IF(AND(F11<=DATE(2025,6,1),OR(G11="",G11>=DATE(2025,6,1))),H11*(1+Assumptions!$C$7)^0,0) | O11: =IF(AND(F11<=DATE(2025,7,1),OR(G11="",G11>=DATE(2025,7,1))),H11*(1+Assumptions!$C$7)^0,0) | P11: =IF(AND(F11<=DATE(2025,8,1),OR(G11="",G11>=DATE(2025,8,1))),H11*(1+Assumptions!$C$7)^0,0) | Q11: 7500 | R11: 7500 | S11: 7500 | T11: 7500 | U11: 7500 | V11: 7500 | W11: 7500 | X11: 7500 | Y11: 7500 | Z11: 7500 | AA11: 7500 | AB11: 7500 | AC11: =IF(AND(F11<=DATE(2026,9,1),OR(G11="",G11>=DATE(2026,9,1))),H11) | AD11: =IF(AND(F11<=DATE(2026,10,1),OR(G11="",G11>=DATE(2026,10,1))),H11*(1+Assumptions!$C$7)^1,0) | AE11: =IF(AND(F11<=DATE(2026,11,1),OR(G11="",G11>=DATE(2026,11,1))),H11*(1+Assumptions!$C$7)^1,0) | AF11: =IF(AND(F11<=DATE(2026,12,1),OR(G11="",G11>=DATE(2026,12,1))),H11*(1+Assumptions!$C$7)^1,0) | AG11: =IF(AND(F11<=DATE(2027,1,1),OR(G11="",G11>=DATE(2027,1,1))),H11*(1+Assumptions!$C$7)^2,0) | AH11: =IF(AND(F11<=DATE(2027,2,1),OR(G11="",G11>=DATE(2027,2,1))),H11*(1+Assumptions!$C$7)^2,0) | AI11: =IF(AND(F11<=DATE(2027,3,1),OR(G11="",G11>=DATE(2027,3,1))),H11*(1+Assumptions!$C$7)^2,0) | AJ11: =IF(AND(F11<=DATE(2027,4,1),OR(G11="",G11>=DATE(2027,4,1))),H11*(1+Assumptions!$C$7)^2,0) | AK11: =IF(AND(F11<=DATE(2027,5,1),OR(G11="",G11>=DATE(2027,5,1))),H11*(1+Assumptions!$C$7)^2,0) | AL11: =IF(AND(F11<=DATE(2027,6,1),OR(G11="",G11>=DATE(2027,6,1))),H11*(1+Assumptions!$C$7)^2,0) | AM11: =IF(AND(F11<=DATE(2027,7,1),OR(G11="",G11>=DATE(2027,7,1))),H11*(1+Assumptions!$C$7)^2,0) | AN11: =IF(AND(F11<=DATE(2027,8,1),OR(G11="",G11>=DATE(2027,8,1))),H11*(1+Assumptions!$C$7)^2,0) | AO11: =IF(AND(F11<=DATE(2027,9,1),OR(G11="",G11>=DATE(2027,9,1))),H11*(1+Assumptions!$C$7)^2,0) | AP11: =IF(AND(F11<=DATE(2027,10,1),OR(G11="",G11>=DATE(2027,10,1))),H11*(1+Assumptions!$C$7)^2,0) | AQ11: =IF(AND(F11<=DATE(2027,11,1),OR(G11="",G11>=DATE(2027,11,1))),H11*(1+Assumptions!$C$7)^2,0) | AR11: =IF(AND(F11<=DATE(2027,12,1),OR(G11="",G11>=DATE(2027,12,1))),H11*(1+Assumptions!$C$7)^2,0) | AS11: =IF(AND(F11<=DATE(2028,1,1),OR(G11="",G11>=DATE(2028,1,1))),H11*(1+Assumptions!$C$7)^3,0) | AT11: =IF(AND(F11<=DATE(2028,2,1),OR(G11="",G11>=DATE(2028,2,1))),H11*(1+Assumptions!$C$7)^3,0) | AU11: =IF(AND(F11<=DATE(2028,3,1),OR(G11="",G11>=DATE(2028,3,1))),H11*(1+Assumptions!$C$7)^3,0) | AV11: =IF(AND(F11<=DATE(2028,4,1),OR(G11="",G11>=DATE(2028,4,1))),H11*(1+Assumptions!$C$7)^3,0) | AW11: =IF(AND(F11<=DATE(2028,5,1),OR(G11="",G11>=DATE(2028,5,1))),H11*(1+Assumptions!$C$7)^3,0) | AX11: =IF(AND(F11<=DATE(2028,6,1),OR(G11="",G11>=DATE(2028,6,1))),H11*(1+Assumptions!$C$7)^3,0) | AY11: =IF(AND(F11<=DATE(2028,7,1),OR(G11="",G11>=DATE(2028,7,1))),H11*(1+Assumptions!$C$7)^3,0) | AZ11: =IF(AND(F11<=DATE(2028,8,1),OR(G11="",G11>=DATE(2028,8,1))),H11*(1+Assumptions!$C$7)^3,0) | BA11: =IF(AND(F11<=DATE(2028,9,1),OR(G11="",G11>=DATE(2028,9,1))),H11*(1+Assumptions!$C$7)^3,0) | BB11: =IF(AND(F11<=DATE(2028,10,1),OR(G11="",G11>=DATE(2028,10,1))),H11*(1+Assumptions!$C$7)^3,0) | BC11: =IF(AND(F11<=DATE(2028,11,1),OR(G11="",G11>=DATE(2028,11,1))),H11*(1+Assumptions!$C$7)^3,0) | BD11: =IF(AND(F11<=DATE(2028,12,1),OR(G11="",G11>=DATE(2028,12,1))),H11*(1+Assumptions!$C$7)^3,0) | BE11: =IF(AND(F11<=DATE(2029,1,1),OR(G11="",G11>=DATE(2029,1,1))),H11*(1+Assumptions!$C$7)^4,0) | BF11: =IF(AND(F11<=DATE(2029,2,1),OR(G11="",G11>=DATE(2029,2,1))),H11*(1+Assumptions!$C$7)^4,0) | BG11: =IF(AND(F11<=DATE(2029,3,1),OR(G11="",G11>=DATE(2029,3,1))),H11*(1+Assumptions!$C$7)^4,0) | BH11: =IF(AND(F11<=DATE(2029,4,1),OR(G11="",G11>=DATE(2029,4,1))),H11*(1+Assumptions!$C$7)^4,0) | BI11: =IF(AND(F11<=DATE(2029,5,1),OR(G11="",G11>=DATE(2029,5,1))),H11*(1+Assumptions!$C$7)^4,0) | BJ11: =IF(AND(F11<=DATE(2029,6,1),OR(G11="",G11>=DATE(2029,6,1))),H11*(1+Assumptions!$C$7)^4,0) | BK11: =IF(AND(F11<=DATE(2029,7,1),OR(G11="",G11>=DATE(2029,7,1))),H11*(1+Assumptions!$C$7)^4,0) | BL11: =IF(AND(F11<=DATE(2029,8,1),OR(G11="",G11>=DATE(2029,8,1))),H11*(1+Assumptions!$C$7)^4,0) | BM11: =IF(AND(F11<=DATE(2029,9,1),OR(G11="",G11>=DATE(2029,9,1))),H11*(1+Assumptions!$C$7)^4,0) | BN11: =IF(AND(F11<=DATE(2029,10,1),OR(G11="",G11>=DATE(2029,10,1))),H11*(1+Assumptions!$C$7)^4,0) | BO11: =IF(AND(F11<=DATE(2029,11,1),OR(G11="",G11>=DATE(2029,11,1))),H11*(1+Assumptions!$C$7)^4,0) | BP11: =IF(AND(F11<=DATE(2029,12,1),OR(G11="",G11>=DATE(2029,12,1))),H11*(1+Assumptions!$C$7)^4,0) | BR11: paid this month if started and not yet left; +8% each calendar year
