Workbook

Sheet Cover
B15: Financial Model
B19: Currency: EUR (€)
B21: STRICTLY CONFIDENTIAL

Sheet How to read me
B1: Tarnoc — How to Read This Model
B3: COLOR CODING
B4: Sample | C4: Assumptions are hardcoded inputs (sourced from documents)
B5: Sample | C5: Hardcoded historicalsis actual data from source documents
B6: Sample | C6: Formula cells are calculated, not hardcoded
B7: Sample | C7: Subtotal / total rows
B8: Sample | C8: Section headers / grand totals
B9: Sample | C9: Subsection headers
B10: Sample | C10: Margin / ratio rows (grey)
B11: Sample | C11: Balance sheet check rows (must = 0)
B14: FORMULA ARCHITECTURE
B15: Assumptions → Revenue Forecast, COGS, OPEX, CAPEX, Personnel (all drivers sourced here)
B16: Revenue Forecast → Financial Statements (revenue lines via cross-sheet links)
B17: COGS → Financial Statements (cost lines via cross-sheet links)
B18: OPEX → Financial Statements (opex lines via cross-sheet links)
B20: To change a number: ONLY edit cells in the Assumptions tab (yellow/orange).
B21: All other tabs will recalculate automatically.
B24: FURTHER EXPLANATIONS
B25: Subsidies: Tarnoc is and has been eligible for a number of subsidies. We will consider application for large projects, however this model excludes the forecast of any subsidy financing foing forward.
B26: Installation revenues: This is modelled fully as pass through revenue for now, as we plan to charge a customer exactly what we pay the installation partner for these services. This is subject to change in the future.
B27: Tarnoc's main products are the TTK (turbineketel) and the Combi+ (turbineketel + outdoor unit), plus the Twincycle (in development for 2027). Every unit contains a turbineketel; the Combi+ adds an outdoor unit and a heavier installation. We also plan to sell various add-ons such as boilers for hybrid setups and sound reduction units.
B28: Service Revenues: Service revenues are calculated relative to installed base. We assume a certain percentage (see assumptions) of customers will purchase our Service package, and are charged annually.
... B45: 2) bill of materials, is all of that inclusive of VAT? because if not

Sheet Assumptions
B2: Drivers & Assumptions
B3: ASSUMPTIONS | L3: what this row does
B5: General Assumptions
B6: Opening Cash Balance (Jan 2024) | C6: 29538.9
B7: Annual salary increase (%) | C7: 0.08 | L7: salary raise applied every year on the Personnel tab
B8: Employer cost basis | C8: Werkgeverlasten (incl. taxes)
B9: Holiday pay (%) | C9: 0.08
B10: Income tax rate | C10: 0.258
B11: Interst on WC loan | C11: 0.05 | L11: interest rate charged on the CLA / working-capital loan
B13: Working Capital | H13: 20
B15: Days Sales Outstanding (DSO) | C15: days | D15: 20 | L15: days customers take to pay — sets receivables on the balance sheet
B16: Days Payable Outstanding (DPO) | C16: days | D16: 45 | L16: days we take to pay suppliers — sets payables
B17: Days Inventory Outstanding (DIO) | C17: days | D17: =IF($D$82=2,30,0) | L17: days of stock held. 0 in Base (as before); 30 in the Aggressive case
B18: Pre-payment | C18: % | L18: share paid up front. left blank, so no customer deposits assumed
B20: Revenue Build
B21: ~Units sold | D21: =IF($D$82=2,D84,D85) | E21: =IF($D$82=2,E84,E85) | F21: =IF($D$82=2,F84,F85) | G21: =IF($D$82=2,G84,G85) | L21: the main dial: total units a year, picked from the Case switch in row 82
C22: 2026 | D22: 2027 | E22: 2028 | F22: 2029 | G22: 2030
B23: TTK | C23: 0 | D23: =D$21*$H23 | E23: =E$21*$H23 | F23: =F$21*$H23 | G23: =G$21*$H23 | H23: 0.2 | L23: TTK units = total units x the mix % in column H
B24: Combi+ | C24: 0 | D24: =D$21*$H24 | E24: =E$21*$H24 | F24: =F$21*$H24 | G24: =G$21*$H24 | H24: =1-H23 | L24: Combi+ units = total units x the mix % in column H
B27: Pricing
B28: PRICING — build-up (turbineketel + outdoor unit) | D28: (inc VAT)
B29: Turbineketel base price (all products) | C29: 8525.62 | D29: =C29*1.21 | L29: column D is just the same price with VAT added, for reference
B30: Outdoor unit — Combi+ | C30: 5309.92 | D30: =C30*1.21 | L30: column D is the incl-VAT version, for reference
B31: Combi+ price (ketel + ODU) | C31: =C29+C30 | D31: =C31*1.21 | L31: Combi+ price = ketel + outdoor unit
B32: INSTALLATION (PASS-THROUGH; REV=COST)
B33: Installation — TTK | C33: 2800 | L33: charged at cost, no margin (pass-through)
B34: Installation — Combi+ | C34: 3800 | L34: charged at cost, no margin (pass-through)
B35: COGS
B36: TTK
B37: Bill of Materials TTK supplier 1
B38: # | C38: Category | D38: Component | E38: 1,000 units | F38: 5,000 units | G38: 10,000 units | H38: Unit | I38: Source
B39: B1 | C39: Supplier 1 | D39: Compressor + VFD | E39: 6314 | F39: 4500 | G39: 2692.44 | H39: €/unit | I39: Source: BOM data provided | L39: compressor prices typed in per tier, not a % step-down
B40: B2 | C40: Supplier 1 | D40: Heat exchangers (set) | E40: 805.5 | F40: =E40*0.7 | G40: =0.6*F40 | H40: €/unit | I40: Source: BOM data provided | L40: volume discount: 5k column = 70% of 1k, 10k = 60% of 5k
B41: B3 | C41: Supplier 1 | D41: Electronics & Power Electronics | E41: 632.92 | F41: =E41*0.7 | G41: =0.6*F41 | H41: €/unit | I41: Source: BOM data provided | L41: volume discount: 5k column = 70% of 1k, 10k = 60% of 5k
B42: B4 | C42: Supplier 1 | D42: Hydraulic Components (Pumps, Valves, etc.) | E42: 283.76 | F42: =E42*0.7 | G42: =0.6*F42 | H42: €/unit | I42: Source: BOM data provided | L42: volume discount: 5k column = 70% of 1k, 10k = 60% of 5k
B43: B5 | C43: Supplier 1 | D43: Silencer & Insulation | E43: 118.48 | F43: =E43*0.7 | G43: =0.6*F43 | H43: €/unit | I43: Source: BOM data provided | L43: volume discount: 5k column = 70% of 1k, 10k = 60% of 5k
B44: B6 | C44: Supplier 1 | D44: Enclosure (Sheet Metal & Coating) | E44: 653.03 | F44: =E44*0.7 | G44: =0.6*F44 | H44: €/unit | I44: Source: BOM data provided | L44: volume discount: 5k column = 70% of 1k, 10k = 60% of 5k
B45: B7 | C45: Supplier 1 | D45: Other Components | E45: 290 | F45: =E45*0.7 | G45: 126 | H45: €/unit | I45: Source: BOM data provided | L45: 5k = 70% of 1k; the 10k number is typed in by hand
B46: B8 | C46: Supplier 1 | D46: Assembly & Final Testing | E46: 200 | F46: =E46*0.7 | G46: =0.6*F46 | H46: €/unit | I46: Source: BOM data provided | L46: volume discount: 5k column = 70% of 1k, 10k = 60% of 5k
B47: B9 | C47: Supplier 1 | D47: Packaging & Inbound Logistics | E47: 395 | F47: =E47*0.7 | G47: =0.6*F47 | H47: €/unit | I47: Source: BOM data provided | L47: volume discount: 5k column = 70% of 1k, 10k = 60% of 5k
B48: B10 | C48: Supplier 1 | D48: Yield Loss & Warranty Provision (~3%) | E48: 291.23 | F48: =E48*0.7 | G48: =0.6*F48 | H48: €/unit | I48: Source: BOM data provided | L48: volume discount: 5k column = 70% of 1k, 10k = 60% of 5k
B49: B11 | C49: Contingency/risk | D49: Contingency & Risk Reserve | E49: 0 | F49: 0 | G49: 760 | H49: €/unit | I49: Source: No source, added for risk purposes | L49: risk buffer, added by hand at the 10k tier only
B50: B-T | C50: Supplier 1 total | D50: Total COGS / unit (BOM) | E50: =SUM(E39:E49) | F50: =SUM(F39:F49) | G50: =round(SUM(G39:G49),0) | H50: €/unit | L50: adds the BOM lines up: cost per ketel at each volume tier
B52: Bill of Materials TTK supplier 2
B53: D1 | C53: Supplier 2 | D53: Compressor + VFD | E53: 2568 | F53: 2311.2 | G53: 2080.08 | H53: €/unit | I53: Source: BOM data provided
B54: D2 | C54: Supplier 2 | D54: Heat exchangers (set) | E54: 805.5 | F54: =E54*0.7 | G54: =F54*0.6 | H54: €/unit | I54: Source: BOM data provided | L54: volume discount: 5k column = 70% of 1k, 10k = 60% of 5k
B55: D3 | C55: Supplier 2 | D55: Elektronica & vermogenselektronica | E55: 257.92 | F55: =E55*0.7 | G55: =F55*0.6 | H55: €/unit | I55: Source: BOM data provided | L55: volume discount: 5k column = 70% of 1k, 10k = 60% of 5k
B56: D4 | C56: Supplier 2 | D56: Hydraulisch (pompen/kleppen/etc.) | E56: 283.76 | F56: =E56*0.7 | G56: =F56*0.6 | H56: €/unit | I56: Source: BOM data provided | L56: volume discount: 5k column = 70% of 1k, 10k = 60% of 5k
B57: D5 | C57: Supplier 2 | D57: Silencer + isolatie | E57: 118.48 | F57: =E57*0.7 | G57: =F57*0.6 | H57: €/unit | I57: Source: BOM data provided | L57: volume discount: 5k column = 70% of 1k, 10k = 60% of 5k
B58: D6 | C58: Supplier 2 | D58: Enclosure (plaatwerk, coating) | E58: 653.03 | F58: =E58*0.7 | G58: =F58*0.6 | H58: €/unit | I58: Source: BOM data provided | L58: volume discount: 5k column = 70% of 1k, 10k = 60% of 5k
B59: D7 | C59: Supplier 2 | D59: Everything Else | E59: 300 | F59: =E59*0.7 | G59: =F59*0.6 | H59: €/unit | I59: Source: BOM data provided | L59: volume discount: 5k column = 70% of 1k, 10k = 60% of 5k
B60: D8 | C60: Supplier 2 | D60: Assemblage & eindtest | E60: 200 | F60: =E60*0.7 | G60: =F60*0.6 | H60: €/unit | I60: Source: BOM data provided | L60: volume discount: 5k column = 70% of 1k, 10k = 60% of 5k
B61: D9 | C61: Supplier 2 | D61: Verpakking & logistiek inkomend | E61: 400 | F61: =E61*0.7 | G61: =F61*0.6 | H61: €/unit | I61: Source: BOM data provided | L61: volume discount: 5k column = 70% of 1k, 10k = 60% of 5k
B62: D10 | C62: Supplier 2 | D62: Yield / garantie-reserve (~3%) | E62: 236.81 | F62: =E62*0.7 | G62: =F62*0.6 | H62: €/unit | I62: Source: BOM data provided | L62: volume discount: 5k column = 70% of 1k, 10k = 60% of 5k
C63: Supplier 2 total | D63: Total COGS / unit (BOM) | E63: =SUM(E53:E62) | F63: =SUM(F53:F62) | G63: =SUM(G53:G62) | L63: supplier 2's total cost per ketel at each tier, for comparison
B65: TTK Volume tier breakpoints
B66: Min Units (≥) | C66: Cost / unit | D66: Unit | E66: Note
B67: 0 | C67: =E50 | D67: €/unit | E67: Linked from BOM Total row above | L67: the sub-5,000 tier. cost pulled from the BOM total above
B68: 5000 | C68: =F50 | D68: €/unit | E68: Linked from BOM Total row above | L68: the 5,000+ tier. COGS looks up this little table
B69: 10000 | C69: =G50 | D69: €/unit | E69: Linked from BOM Total row above | L69: the 10,000+ tier. the tier key is two years of volume, not one
B71: OUTDOOR UNIT COGS (Combi+) — volume tiers
B72: Component | E72: 1,000 units | F72: 5,000 units | G72: 10,000 units | H72: Unit | I72: Unit | J72: Source
B73: Outdoor unit — Combi+ | E73: 1402.6 | F73: 1262.34 | G73: 1136.1 | H73: €/unit | I73: €/unit | J73: Source: BOM data
B74: Shipping (Combi+) | E74: 100 | F74: 100 | G74: 100 | H74: €/unit | I74: €/unit | J74: Source: BOM data
B76: Outdoor Unit tier breakpoints (for COGS VLOOKUP)
B77: Min Units (≥)
B78: 0 | C78: =E73 | L78: outdoor unit cost below 5,000 units, pulled from the table above
B79: 5000 | C79: =F73 | L79: outdoor unit cost at 5,000+
B80: 10000 | C80: =G73 | L80: outdoor unit cost at 10,000+
B81: SCENARIO & TIER BASIS
B82: Case (1 = Base €3m, 2 = Aggressive €10m) | D82: 2 | L82: the master switch. 2 = the 10m plan: bigger volumes, capex, 10m equity, faster sales hires
B83: BOM tier basis (1 = this year only, 2 = this year + next) | D83: 1 | L83: how the ketel cost tier is chosen. 1 = only the year's own volume (conservative)
B84: Aggressive case — units sold | D84: 1800 | E84: 5200 | F84: 11000 | G84: 22000 | L84: 2028 is set to clear the 5,000-unit tier, 2029 to clear 10,000
B85: Base case — units sold | D85: 600 | E85: 1600 | F85: 3600 | G85: 7200 | L85: the plan as it stands today — leave alone so Base stays comparable
B86: Other operating expenditures | F86: Yearly increase: | G86: 0.35
C87: Category | D87: Note | E87: 2026 | F87: 2027 | G87: 2028 | H87: 2029 | I87: 2030
B88: Office rent (part of General) | C88: G&A | D88: ongoing | E88: 5000 | F88: =$E88*(1+$G$86) | G88: =F88*(1+$G$86) | H88: =G88*(1+$G$86) | I88: =H88*(1+$G$86) | L88: 2026 is typed in; later years grow it by the rate above
B89: Other General | C89: G&A | D89: ongoing | E89: 7000 | F89: =$E89*(1+$G$86) | G89: =F89*(1+$G$86) | H89: =G89*(1+$G$86) | I89: =H89*(1+$G$86) | L89: 2026 is typed in; later years grow it by the rate above
B90: Baseline Sales & Marketing | C90: S&M | D90: ongoing | E90: 14000 | F90: =$E90*(1+$G$86) | G90: =F90*(1+$G$86) | H90: =G90*(1+$G$86) | I90: =H90*(1+$G$86) | L90: 2026 is typed in; later years grow it by the rate above
B91: Finance & Legal etc. | C91: G&A | D91: ongoing | E91: 8000 | F91: =$E91*(1+$G$86) | G91: =F91*(1+$G$86) | H91: =G91*(1+$G$86) | I91: =H91*(1+$G$86) | L91: 2026 is typed in; later years grow it by the rate above
B92: Ongoing Development costs | C92: R&D | D92: ongoing | E92: 10000 | F92: =$E92*(1+$G$86) | G92: =F92*(1+$G$86) | H92: =G92*(1+$G$86) | I92: =H92*(1+$G$86) | L92: 2026 is typed in; later years grow it by the rate above
B93: Third party cost product development | C93: R&D | D93: ongoing | E93: 15000 | F93: =$E93*(1+$G$86) | G93: =F93*(1+$G$86) | H93: =G93*(1+$G$86) | I93: =H93*(1+$G$86) | L93: 2026 is typed in; later years grow it by the rate above
B94: Kicker Development Cost | C94: R&D | D94: one-off | E94: 168933 | L94: one-off, lands in the single month it's booked on OPEX
B95: Customer journey (third party) | C95: S&M | D95: one-off | E95: 10000 | L95: one-off, lands in the single month it's booked on OPEX
B96: Branding + Website (third party cost) | C96: S&M | D96: one-off | E96: 10000 | L96: one-off, lands in the single month it's booked on OPEX
B97: Assembly partner | C97: R&D | D97: one-off | E97: 100000 | L97: one-off, lands in the single month it's booked on OPEX
B98: Tooling Fisher (result: 2%-3%) | C98: R&D | D98: one-off | E98: 45000 | L98: one-off, lands in the single month it's booked on OPEX
B101: Assumptions for costs per unit sold (3rd parties or expenses (NO personell) | G101: Units sold | H101: S&M cost per unit | I101: Decrease | J101: Yearly costs
B102: Marketing spend per Customer | C102: S&M | E102: 600 | F102: third party | G102: 0 | H102: =E106 | L102: top of the cost-down table: sales cost per unit at zero volume
B103: Closing costs per customer | C103: S&M | D103: (Calls, viewing location, etc) | E103: 150 | F103: third party | G103: 400 | H103: =E106 | J103: =G103*H103 | L103: same cost up to 400 units. column J = total spend there
B104: Aftersales and support | C104: S&M | E104: 50 | F104: third party | G104: =G103*2 | H104: =H103*I104 | I104: 0.9 | J104: =G104*H104 | L104: units double, cost per unit drops 10%. OPEX looks up this table
G105: =G104*2 | H105: =H104*I105 | I105: 0.9 | J105: =G105*H105 | L105: units double, cost per unit drops 10%
B106: Cost per unit sold (cost down driven by volume) | C106: S&M | D106: costdown: S(n)=S(1)*n^-b, where b=0,2 | E106: =SUM(E102:E104) | F106: S(1) | G106: =G105*2 | H106: =H105*I106 | I106: 0.9 | J106: =G106*H106 | L106: column E adds the three costs above = cost per unit at low volume
G107: =G106*2 | H107: =H106*I107 | I107: 0.9 | J107: =G107*H107 | L107: units double, cost per unit drops 10%
G108: =G107*2 | H108: =H107*I108 | I108: 0.9 | J108: =G108*H108 | L108: units double, cost per unit drops 10%
G109: =G108*2 | H109: =H108*I109 | I109: 0.9 | J109: =G109*H109 | L109: units double, cost per unit drops 10% (bottom of the table)
B111: Product | C111: Upsell item | D111: Type | E111: Attach % | F111: Unit rev. (EX VAT) | G111: Unit COGS | H111: Gross profit | I111: avg. Value | J111: avg. profit
B112: TTK / Combi+ | C112: Boiler variant 50 | D112: One-time | E112: 0.49 | F112: 165.29 | G112: 80 | H112: =F112-G112 | I112: =F112*E112 | J112: =H112*E112 | L112: profit per upsell, then the average per heat pump after attach %
B113: TTK / Combi+ | C113: Boiler variant 100 | D113: One-time | E113: 0.19 | F113: 330.58 | G113: 150 | H113: =F113-G113 | I113: =F113*E113 | J113: =H113*E113 | L113: profit per upsell, then the average per heat pump after attach %
B114: TTK / Combi+ | C114: Sound reduction | D114: One-time | E114: 0.79 | F114: 454.55 | G114: 190 | H114: =F114-G114 | I114: =F114*E114 | J114: =H114*E114 | L114: profit per upsell, then the average per heat pump after attach %
...

Sheet Financial Statements
B1: Tarnoc B.V. — Financial Statements (€)
E2: 2025 | Q2: 2026 | AC2: 2027 | AO2: 2028
E3: 45658 | F3: 45689 | G3: 45717 | H3: 45748 | I3: 45778 | J3: 45809 | K3: 45839 | L3: 45870 | M3: 45901 | N3: 45931 | O3: 45962 | P3: 45992 | Q3: 46023 | R3: 46054 | S3: 46082 | T3: 46113 | U3: 46143 | V3: 46174 | W3: 46204 | X3: 46235 | Y3: 46266 | Z3: 46296 | AA3: 46327 | AB3: 46357 | AC3: 46388 | AD3: 46419 | AE3: 46447 | AF3: 46478 | AG3: 46508 | AH3: 46539 | AI3: 46569 | AJ3: 46600 | AK3: 46631 | AL3: 46661 | AM3: 46692 | AN3: 46722 | AO3: 46753 | AP3: 46784 | AQ3: 46813 | AR3: 46844 | AS3: 46874 | AT3: 46905 | AU3: 46935 | AV3: 46966 | AW3: 46997 | AX3: 47027 | AY3: 47058 | AZ3: 47088 | BB3: 2025 | BC3: 2026 | BD3: 2027 | BE3: 2028 | BF3: 2029 | BH3: what this row does
B5: PROFIT & LOSS STATEMENT
B6: Revenues
B7: TTK | D7: € | M7: ='Revenue Forecast'!M9 | N7: ='Revenue Forecast'!N9 | O7: ='Revenue Forecast'!O9 | P7: ='Revenue Forecast'!P9 | Q7: ='Revenue Forecast'!Q9 | R7: ='Revenue Forecast'!R9 | S7: ='Revenue Forecast'!S9 | T7: ='Revenue Forecast'!T9 | ... AZ7: ='Revenue Forecast'!AZ9 | BB7: =sum(E7:P7) | BC7: =sum(Q7:AB7) | BD7: =sum(AC7:AN7) | BE7: =sum(AO7:AZ7) | BF7: ='Revenue Forecast'!BF9 | BH7: TTK revenue, pulled from the Revenue Forecast
B8: Combi+ | D8: € | Q8: ='Revenue Forecast'!Q15 | R8: ='Revenue Forecast'!R15 | S8: ='Revenue Forecast'!S15 | T8: ='Revenue Forecast'!T15 | U8: ='Revenue Forecast'!U15 | V8: ='Revenue Forecast'!V15 | W8: ='Revenue Forecast'!W15 | X8: ='Revenue Forecast'!X15 | ... AZ8: ='Revenue Forecast'!AZ15 | BB8: ='Revenue Forecast'!BB15 | BC8: ='Revenue Forecast'!BC15 | BD8: ='Revenue Forecast'!BD15 | BE8: ='Revenue Forecast'!BE15 | BF8: ='Revenue Forecast'!BF15 | BH8: Combi+ revenue, pulled from the Revenue Forecast
B9: Other | D9: € | M9: ='Revenue Forecast'!M19+'Revenue Forecast'!M24 | N9: ='Revenue Forecast'!N19+'Revenue Forecast'!N24 | O9: ='Revenue Forecast'!O19+'Revenue Forecast'!O24 | P9: ='Revenue Forecast'!P19+'Revenue Forecast'!P24 | Q9: ='Revenue Forecast'!Q19+'Revenue Forecast'!Q24 | R9: ='Revenue Forecast'!R19+'Revenue Forecast'!R24 | S9: ='Revenue Forecast'!S19+'Revenue Forecast'!S24 | T9: ='Revenue Forecast'!T19+'Revenue Forecast'!T24 | ... AZ9: ='Revenue Forecast'!AZ19+'Revenue Forecast'!AZ24 | BB9: =sum(E9:P9) | BC9: =sum(Q9:AB9) | BD9: =sum(AC9:AN9) | BE9: =sum(AO9:AZ9) | BF9: ='Revenue Forecast'!BF19+'Revenue Forecast'!BF24 | BH9: installation + service revenue from the Revenue Forecast
B10: Subsidies & grants | D10: € | M10: ='Revenue Forecast'!M28 | N10: ='Revenue Forecast'!N28 | O10: ='Revenue Forecast'!O28 | P10: ='Revenue Forecast'!P28 | Q10: ='Revenue Forecast'!Q28 | R10: ='Revenue Forecast'!R28 | S10: ='Revenue Forecast'!S28 | T10: 0 | U10: ='Revenue Forecast'!U28 | V10: ='Revenue Forecast'!V28 | W10: ='Revenue Forecast'!W28 | X10: ='Revenue Forecast'!X28 | Y10: ='Revenue Forecast'!Y28 | Z10: ='Revenue Forecast'!Z28 | AA10: ='Revenue Forecast'!AA28 | AB10: ='Revenue Forecast'!AB28 | ... AZ10: ='Revenue Forecast'!AZ28 | BB10: =sum(E10:P10) | BC10: =sum(Q10:AB10) | BD10: pm | BE10: pm | BF10: pm | BH10: subsidies from the Revenue Forecast. nothing budgeted
B11: Total Revenue | D11: € | M11: ='Revenue Forecast'!M30 | N11: ='Revenue Forecast'!N30 | O11: ='Revenue Forecast'!O30 | P11: ='Revenue Forecast'!P30 | Q11: ='Revenue Forecast'!Q30 | R11: ='Revenue Forecast'!R30 | S11: ='Revenue Forecast'!S30 | T11: ='Revenue Forecast'!T30 | ... AZ11: ='Revenue Forecast'!AZ30 | BB11: =sum(E11:P11) | BC11: =sum(Q11:AB11) | BD11: =sum(AC11:AN11) | BE11: =sum(AO11:AZ11) | BF11: =sum(BF7:BF10) | BH11: all the revenue lines added
B13: Cost of goods sold
B14: TTK | D14: € | E14: =COGS!E9 | F14: =COGS!F9 | G14: =COGS!G9 | H14: =COGS!H9 | I14: =COGS!I9 | J14: =COGS!J9 | K14: =COGS!K9 | L14: =COGS!L9 | ... AZ14: =COGS!AZ9 | BB14: =sum(E14:P14) | BC14: =sum(Q14:AB14) | BD14: =sum(AC14:AN14) | BE14: =sum(AO14:AZ14) | BF14: =COGS!BF9 | BH14: TTK cost of sales, from the COGS tab
B15: Combi+ | D15: € | Q15: =COGS!Q14 | R15: =COGS!R14 | S15: =COGS!S14 | T15: =COGS!T14 | U15: =COGS!U14 | V15: =COGS!V14 | W15: =COGS!W14 | X15: =COGS!X14 | ... AZ15: =COGS!AZ14 | BB15: =COGS!BB14 | BC15: =COGS!BC14 | BD15: =COGS!BD14 | BE15: =COGS!BE14 | BF15: =COGS!BF14 | BH15: Combi+ cost of sales, from COGS
B16: Other | D16: € | E16: =COGS!E17 | F16: =COGS!F17 | G16: =COGS!G17 | H16: =COGS!H17 | I16: =COGS!I17 | J16: =COGS!J17 | K16: =COGS!K17 | L16: =COGS!L17 | ... P16: =COGS!P17 | Q16: =COGS!Q17+COGS!Q20 | R16: =COGS!R17+COGS!R20 | S16: =COGS!S17+COGS!S20 | T16: =COGS!T17+COGS!T20 | U16: =COGS!U17+COGS!U20 | V16: =COGS!V17+COGS!V20 | W16: =COGS!W17+COGS!W20 | X16: =COGS!X17+COGS!X20 | ... AZ16: =COGS!AZ17+COGS!AZ20 | BB16: =sum(E16:P16) | BC16: =sum(Q16:AB16) | BD16: =sum(AC16:AN16) | BE16: =sum(AO16:AZ16) | BF16: =COGS!BF17+COGS!BF20 | BH16: installation + service costs, from COGS
B17: Total COGS | D17: € | M17: =COGS!M22 | N17: =COGS!N22 | O17: =COGS!O22 | P17: =COGS!P22 | Q17: =COGS!Q22 | R17: =COGS!R22 | S17: =COGS!S22 | T17: =COGS!T22 | ... AZ17: =COGS!AZ22 | BB17: =sum(E17:P17) | BC17: =sum(Q17:AB17) | BD17: =sum(AC17:AN17) | BE17: =sum(AO17:AZ17) | BF17: =sum(BF14:BF16) | BH17: all the cost lines added
B19: Gross Profit
B20: TTK | D20: € | Q20: =Q7-Q14 | R20: =R7-R14 | S20: =S7-S14 | T20: =T7-T14 | U20: =U7-U14 | V20: =V7-V14 | W20: =W7-W14 | X20: =X7-X14 | ... AZ20: =AZ7-AZ14 | BC20: =BC7-BC14 | BD20: =BD7-BD14 | BE20: =BE7-BE14 | BF20: =BF7-BF14 | BH20: TTK revenue minus TTK cost
B21: Combi+ | D21: € | Q21: =Q8-Q15 | R21: =R8-R15 | S21: =S8-S15 | T21: =T8-T15 | U21: =U8-U15 | V21: =V8-V15 | W21: =W8-W15 | X21: =X8-X15 | ... AZ21: =AZ8-AZ15 | BC21: =BC8-BC15 | BD21: =BD8-BD15 | BE21: =BE8-BE15 | BF21: =BF8-BF15 | BH21: Combi+ revenue minus Combi+ cost
B22: Other | D22: € | Q22: =Q9-Q16 | R22: =R9-R16 | S22: =S9-S16 | T22: =T9-T16 | U22: =U9-U16 | V22: =V9-V16 | W22: =W9-W16 | X22: =X9-X16 | ... AZ22: =AZ9-AZ16 | BC22: =BC9-BC16 | BD22: =BD9-BD16 | BE22: =BE9-BE16 | BF22: =BF9-BF16 | BH22: installation + service revenue minus their cost
B23: Gross Profit | D23: € | M23: =M11-M17 | N23: =N11-N17 | O23: =O11-O17 | P23: =P11-P17 | Q23: =Q11-Q17 | R23: =R11-R17 | S23: =S11-S17 | T23: =T11-T17 | ... AZ23: =AZ11-AZ17 | BB23: =sum(E23:P23) | BC23: =sum(Q23:AB23) | BD23: =sum(AC23:AN23) | BE23: =sum(AO23:AZ23) | BF23: =BF11-BF17 | BH23: revenue minus cost of sales
B24: Gross margin % | D24: % | BD24: =BD23/BD11 | BE24: =BE23/BE11 | BF24: =BF23/BF11 | BH24: gross profit as a % of revenue (year columns only)
B26: Operational expenses
B27: R&D | D27: € | M27: =OPEX!O38 | N27: =OPEX!P38 | O27: =OPEX!Q38 | P27: =OPEX!R38 | Q27: =OPEX!S38 | R27: =OPEX!T38 | S27: =OPEX!U38 | T27: =OPEX!V38 | ... AZ27: =OPEX!BB38 | BB27: =sum(E27:P27) | BC27: =sum(Q27:AB27) | BD27: =sum(AC27:AN27) | BE27: =sum(AO27:AZ27) | BF27: =OPEX!BH38 | BH27: R&D spend, people and other, from OPEX
B28: S&M | D28: € | M28: =OPEX!O39 | N28: =OPEX!P39 | O28: =OPEX!Q39 | P28: =OPEX!R39 | Q28: =OPEX!S39 | R28: =OPEX!T39 | S28: =OPEX!U39 | T28: =OPEX!V39 | ... AZ28: =OPEX!BB39 | BB28: =sum(E28:P28) | BC28: =sum(Q28:AB28) | BD28: =sum(AC28:AN28) | BE28: =sum(AO28:AZ28) | BF28: =OPEX!BH39 | BH28: S&M spend from OPEX
B29: G&A | D29: € | M29: =OPEX!O40 | N29: =OPEX!P40 | O29: =OPEX!Q40 | P29: =OPEX!R40 | Q29: =OPEX!S40 | R29: =OPEX!T40 | S29: =OPEX!U40 | T29: =OPEX!V40 | ... AZ29: =OPEX!BB40 | BB29: =sum(E29:P29) | BC29: =sum(Q29:AB29) | BD29: =sum(AC29:AN29) | BE29: =sum(AO29:AZ29) | BF29: =OPEX!BH40 | BH29: G&A spend from OPEX
B30: Total OPEX | D30: € | M30: =(M29+M28+M27) | N30: =(N29+N28+N27) | O30: =(O29+O28+O27) | P30: =(P29+P28+P27) | Q30: =(Q29+Q28+Q27) | R30: =(R29+R28+R27) | S30: =(S29+S28+S27) | T30: =(T29+T28+T27) | ... AZ30: =(AZ29+AZ28+AZ27) | BB30: =sum(E30:P30) | BC30: =sum(Q30:AB30) | BD30: =sum(AC30:AN30) | BE30: =sum(AO30:AZ30) | BF30: =sum(BF27:BF29) | BH30: the three OPEX lines added
B32: EBITDA | D32: € | M32: =M23-M30 | N32: =N23-N30 | O32: =O23-O30 | P32: =P23-P30 | Q32: =Q23-Q30 | R32: =R23-R30 | S32: =S23-S30 | T32: =T23-T30 | ... AZ32: =AZ23-AZ30 | BB32: =sum(E32:P32) | BC32: =sum(Q32:AB32) | BD32: =sum(AC32:AN32) | BE32: =sum(AO32:AZ32) | BF32: =BF23-BF30 | BH32: gross profit minus operating costs
B33: EBITDA margin % | D33: % | BE33: =BE32/BE11 | BF33: =BF32/BF11 | BH33: EBITDA as a % of revenue
B35: Depreciation & Amortisation | D35: € | E35: =-SUM($E$53:E53)/(Assumptions!$D$128*12) | F35: =-SUM($E$53:F53)/(Assumptions!$D$128*12) | G35: =-SUM($E$53:G53)/(Assumptions!$D$128*12) | H35: =-SUM($E$53:H53)/(Assumptions!$D$128*12) | I35: =-SUM($E$53:I53)/(Assumptions!$D$128*12) | J35: =-SUM($E$53:J53)/(Assumptions!$D$128*12) | K35: =-SUM($E$53:K53)/(Assumptions!$D$128*12) | L35: =-SUM($E$53:L53)/(Assumptions!$D$128*12) | ... AZ35: =-SUM($E$53:AZ53)/(Assumptions!$D$128*12) | BB35: =sum(E35:P35) | BC35: =sum(Q35:AB35) | BD35: =sum(AC35:AN35) | BE35: =sum(AO35:AZ35) | BF35: =(-SUM($E$53:$AZ$53)+(-BF53)/2)/Assumptions!$D$128 | BH35: straight line on cumulative capex, blended life from Assumptions D128
B36: Interest payments | D36: € | M36: 0 | N36: 0 | O36: 0 | P36: 0 | Q36: =P82*Assumptions!$C$11/12 | R36: =Q82*Assumptions!$C$11/12 | S36: =R82*Assumptions!$C$11/12 | T36: =S82*Assumptions!$C$11/12 | U36: =T82*Assumptions!$C$11/12 | V36: =U82*Assumptions!$C$11/12 | W36: =V82*Assumptions!$C$11/12 | X36: =W82*Assumptions!$C$11/12 | ... AZ36: =AY82*Assumptions!$C$11/12 | BB36: =sum(E36:P36) | BC36: =sum(Q36:AB36) | BD36: =sum(AC36:AN36) | BE36: =sum(AO36:AZ36) | BF36: =BE82*Assumptions!$C$11/12 | BH36: interest on last month's loan balance, yearly rate divided by 12
B37: EBT | D37: € | M37: =M32-sum(M35:M36) | N37: =N32-sum(N35:N36) | O37: =O32-sum(O35:O36) | P37: =P32-sum(P35:P36) | Q37: =Q32-sum(Q35:Q36) | R37: =R32-sum(R35:R36) | S37: =S32-sum(S35:S36) | T37: =T32-sum(T35:T36) | ... AZ37: =AZ32-sum(AZ35:AZ36) | BB37: =sum(E37:P37) | BC37: =sum(Q37:AB37) | BD37: =sum(AC37:AN37) | BE37: =sum(AO37:AZ37) | BF37: =BF32-sum(BF35:BF36) | BH37: EBITDA minus depreciation and interest
BE38: =BE37/BE11 | BF38: =BF37/BF11 | BH38: profit before tax as a % of revenue
B40: Income tax | D40: € | M40: 0 | N40: 0 | O40: 0 | P40: 0 | Q40: 0 | R40: 0 | S40: 0 | T40: 0 | U40: 0 | V40: 0 | W40: 0 | X40: 0 | Y40: 0 | Z40: 0 | AA40: 0 | AB40: 0 | AC40: 0 | AD40: 0 | AE40: 0 | AF40: 0 | AG40: 0 | AH40: 0 | AI40: 0 | AJ40: 0 | AK40: 0 | AL40: 0 | AM40: 0 | AN40: 0 | AO40: 0 | AP40: 0 | AQ40: 0 | AR40: 0 | AS40: 0 | AT40: 0 | AU40: 0 | AV40: 0 | AW40: 0 | AX40: 0 | AY40: 0 | AZ40: 0 | BB40: =sum(E40:P40) | BC40: =sum(Q40:AB40) | BD40: =sum(AC40:AN40) | BE40: =sum(AO40:AZ40) | BF40: =(BF37-AZ44)*Assumptions!$C$10 | BH40: tax on profit, but only once the old losses below are used up
B41: NET INCOME | D41: € | M41: =M37-M40 | N41: =N37-N40 | O41: =O37-O40 | P41: =P37-P40 | Q41: =Q37-Q40 | R41: =R37-R40 | S41: =S37-S40 | T41: =T37-T40 | ... AZ41: =AZ37-AZ40 | BB41: =sum(E41:P41) | BC41: =sum(Q41:AB41) | BD41: =sum(AC41:AN41) | BE41: =sum(AO41:AZ41) | BF41: =BF37-BF40 | BH41: profit after tax
B42: Profit margin % | BE42: =BE41/BE11 | BF42: =BF41/BF11 | BH42: net profit as a % of revenue
B44: Tax carry over to be applied | M44: 108239 | N44: =M44+(-N41*Assumptions!$C$10) | O44: =N44+(-O41*Assumptions!$C$10) | P44: =O44+(-P41*Assumptions!$C$10) | Q44: =P44+(-Q41*Assumptions!$C$10) | R44: =Q44+(-R41*Assumptions!$C$10) | S44: =R44+(-S41*Assumptions!$C$10) | T44: =S44+(-T41*Assumptions!$C$10) | U44: =T44+(-U41*Assumptions!$C$10) | ... AZ44: =AY44+(-AZ41*Assumptions!$C$10) | BH44: running pot of unused tax losses: grows in loss months, gets eaten when profitable
B46: CASH FLOW STATEMENT
B47: Net income | D47: € | M47: =M41 | N47: =N41 | O47: =O41 | P47: =P41 | Q47: =Q41 | R47: =R41 | S47: =S41 | T47: =T41 | ... AZ47: =AZ41 | BB47: =sum(E47:P47) | BC47: =sum(Q47:AB47) | BD47: =sum(AC47:AN47) | BE47: =sum(AO47:AZ47) | BF47: =BF41 | BH47: cash flow starts from net income
B48: Depreciation & amortisation | D48: € | E48: =E35 | F48: =F35 | G48: =G35 | H48: =H35 | I48: =I35 | J48: =J35 | K48: =K35 | L48: =L35 | ... AZ48: =AZ35 | BB48: =sum(E48:P48) | BC48: =sum(Q48:AB48) | BD48: =sum(AC48:AN48) | BE48: =sum(AO48:AZ48) | BF48: =BF35 | BH48: adds depreciation back, it isn't cash
B49: Increase in accounts receivable (delta DSO) | D49: € | M49: 0 | N49: =-(N68-M68) | O49: =-(O68-N68) | P49: =-(P68-O68) | Q49: =-(Q68-P68) | R49: =-(R68-Q68) | S49: =-(S68-R68) | T49: =-(T68-S68) | U49: =-(U68-T68) | ... AZ49: =-(AZ68-AY68) | BB49: =sum(E49:P49) | BC49: =sum(Q49:AB49) | BD49: =sum(AC49:AN49) | BE49: =sum(AO49:AZ49) | BF49: =-(BF68-BE68) | BH49: cash tied up when receivables grow, freed when they shrink
B50: Increase in accounts payable (delta DPO) | D50: € | M50: 0 | N50: =(N77-M77) | O50: =(O77-N77) | P50: =(P77-O77) | Q50: =(Q77-P77) | R50: =(R77-Q77) | S50: =(S77-R77) | T50: =(T77-S77) | U50: =(U77-T77) | ... AZ50: =(AZ77-AY77) | BB50: =sum(E50:P50) | BC50: =sum(Q50:AB50) | BD50: =sum(AC50:AN50) | BE50: =sum(AO50:AZ50) | BF50: =BF77-BE77 | BH50: cash gained by paying suppliers later, used up when payables fall
B51: Change in inventory (delta DIO) | D51: € | M51: 0 | N51: =-(N69-M69) | O51: =-(O69-N69) | P51: =-(P69-O69) | Q51: =-(Q69-P69) | R51: =-(R69-Q69) | S51: =-(S69-R69) | T51: =-(T69-S69) | U51: =-(U69-T69) | ... AZ51: =-(AZ69-AY69) | BB51: =sum(E51:P51) | BC51: =sum(Q51:AB51) | BD51: =sum(AC51:AN51) | BE51: =sum(AO51:AZ51) | BF51: =-(BF69-BE69) | BH51: cash tied up in stock. days of stock is 0, so nothing moves
B52: Cash from Operations | D52: € | M52: =sum(M47:M51) | N52: =sum(N47:N51) | O52: =sum(O47:O51) | P52: =sum(P47:P51) | Q52: =sum(Q47:Q51) | R52: =sum(R47:R51) | S52: =sum(S47:S51) | T52: =sum(T47:T51) | ... AZ52: =sum(AZ47:AZ51) | BB52: =sum(E52:P52) | BC52: =sum(Q52:AB52) | BD52: =sum(AC52:AN52) | BE52: =sum(AO52:AZ52) | BF52: =sum(BF47:BF51) | BH52: net income plus all the working-capital swings
B53: CAPEX | D53: € | E53: =IFERROR(-HLOOKUP(YEAR(E$3),Assumptions!$D$124:$G$127,4,FALSE)/12,0) | F53: =IFERROR(-HLOOKUP(YEAR(F$3),Assumptions!$D$124:$G$127,4,FALSE)/12,0) | G53: =IFERROR(-HLOOKUP(YEAR(G$3),Assumptions!$D$124:$G$127,4,FALSE)/12,0) | H53: =IFERROR(-HLOOKUP(YEAR(H$3),Assumptions!$D$124:$G$127,4,FALSE)/12,0) | I53: =IFERROR(-HLOOKUP(YEAR(I$3),Assumptions!$D$124:$G$127,4,FALSE)/12,0) | J53: =IFERROR(-HLOOKUP(YEAR(J$3),Assumptions!$D$124:$G$127,4,FALSE)/12,0) | K53: =IFERROR(-HLOOKUP(YEAR(K$3),Assumptions!$D$124:$G$127,4,FALSE)/12,0) | L53: =IFERROR(-HLOOKUP(YEAR(L$3),Assumptions!$D$124:$G$127,4,FALSE)/12,0) | ... AZ53: =IFERROR(-HLOOKUP(YEAR(AZ$3),Assumptions!$D$124:$G$127,4,FALSE)/12,0) | BB53: =sum(E53:P53) | BC53: =sum(Q53:AB53) | BD53: =sum(AC53:AN53) | BE53: =sum(AO53:AZ53) | BF53: =-Assumptions!$F$127 | BH53: staged capex from Assumptions rows 125-127, spread evenly over each year
B54: Cash from Investing | M54: =M53 | N54: =N53 | O54: =O53 | P54: =P53 | Q54: =Q53 | R54: =R53 | S54: =S53 | T54: =T53 | ... AZ54: =AZ53 | BB54: =sum(E54:P54) | BC54: =sum(Q54:AB54) | BD54: =sum(AC54:AN54) | BE54: =sum(AO54:AZ54) | BF54: =BF53 | BH54: same as capex
B55: Equity injection | D55: € | S55: 0 | U55: 300000 | AA55: =IF(Assumptions!$D$82=2,10000000,3000000) | BB55: =sum(E55:P55) | BC55: =sum(Q55:AB55) | BD55: =sum(AC55:AN55) | BE55: =sum(AO55:AZ55) | BF55: 0 | BH55: money in from shares: 300k May-26, then 3.0m (Base) or 10.0m (Aggressive) Nov-26
B56: Loan (CLA) | D56: € | W56: 300000 | BB56: =sum(E56:P56) | BC56: =sum(Q56:AB56) | BD56: =sum(AC56:AN56) | BE56: =sum(AO56:AZ56) | BF56: 0 | BH56: CLA loan drawn, 300k in Jul-26
B58: Cash from Financing | D58: € | E58: =E55+E56+E57 | F58: =F55+F56+F57 | G58: =G55+G56+G57 | H58: =H55+H56+H57 | I58: =I55+I56+I57 | J58: =J55+J56+J57 | K58: =K55+K56+K57 | L58: =L55+L56+L57 | ... AZ58: =AZ55+AZ56+AZ57 | BB58: =sum(E58:P58) | BC58: =sum(Q58:AB58) | BD58: =sum(AC58:AN58) | BE58: =sum(AO58:AZ58) | BF58: =BF55+BF56+BF57 | BH58: equity plus loans in the month
B60: Total Change in Cash | D60: € | M60: =M52+M54+M58 | N60: =N52+N54+N58 | O60: =O52+O54+O58 | P60: =P52+P54+P58 | Q60: =Q52+Q54+Q58 | R60: =R52+R54+R58 | S60: =S52+S54+S58 | T60: =T52+T54+T58 | ... AZ60: =AZ52+AZ54+AZ58 | BB60: =BB58+BB54+BB52 | BC60: =BC58+BC54+BC52 | BD60: =BD58+BD54+BD52 | BE60: =BE58+BE54+BE52 | BF60: =BF58+BF54+BF52 | BH60: operating + investing + financing
B61: Beginning cash balance | D61: € | M61: =1111108+69465 | N61: =M62 | O61: =N62 | P61: =O62 | Q61: =P62 | R61: =Q62 | S61: =R62 | T61: =S62 | U61: =T62 | ... AZ61: =AY62 | BB61: =BB60+BB62 | BC61: =Q61 | BD61: =AC61 | BE61: =AO61 | BF61: =AZ62 | BH61: last month's closing cash
B62: Ending Cash Balance | D62: € | M62: =M60+M61 | N62: =N61+N60 | O62: =O61+O60 | P62: =P61+P60 | Q62: =Q61+Q60 | R62: =R61+R60 | S62: =S61+S60 | T62: =T61+T60 | U62: =U61+U60 | V62: =V61+V60 | W62: =V62+W60 | X62: =X61+X60 | Y62: =Y61+Y60 | Z62: =Z61+Z60 | AA62: =AA61+AA60 | AB62: =AB61+AB60 | AC62: =AC61+AC60 | AD62: =AD61+AD60 | AE62: =AE61+AE60 | ... AZ62: =AZ61+AZ60 | BB62: =P62 | BC62: =BC60+BC61 | BD62: =BD60+BD61 | BE62: =BE60+BE61 | BF62: =BF60+BF61 | BH62: cash in minus cash out. this is the runway line to watch
B64: BALANCE SHEET
B65: ASSETS
B66: Cash and cash equivalents | D66: € | M66: =M62 | N66: =N62 | O66: =O62 | P66: =P62 | Q66: =Q62 | R66: =R62 | S66: =S62 | T66: =T62 | ... AZ66: =AZ62 | BB66: =P66 | BC66: =AB66 | BD66: =AN66 | BE66: =AZ66 | BF66: =BF62 | BH66: the closing cash from the cash flow above
B67: Deferred tax assest ("carry forward") | D67: € | M67: =M44 | N67: =N44 | O67: =O44 | P67: =P44 | Q67: =Q44 | R67: =R44 | S67: =S44 | T67: =T44 | ... AZ67: =AZ44 | BB67: =P67 | BC67: =AB67 | BD67: =AN67 | BE67: =AZ67 | BF67: 0 | BH67: unused tax losses, parked as an asset
B68: Accounts receivable (DSO-based) | D68: € | M68: =ABS(Assumptions!$D$15*(M11/30)) | N68: =ABS(Assumptions!$D$15*(N11/30)) | O68: =ABS(Assumptions!$D$15*(O11/30)) | P68: =ABS(Assumptions!$D$15*(P11/30)) | Q68: =ABS(Assumptions!$D$15*(Q11/30)) | R68: =ABS(Assumptions!$D$15*(R11/30)) | S68: =ABS(Assumptions!$D$15*(S11/30)) | T68: =ABS(Assumptions!$D$15*(T11/30)) | ... AZ68: =ABS(Assumptions!$D$15*(AZ11/30)) | BB68: =P68 | BC68: =AB68 | BD68: =AN68 | BE68: =AZ68 | BF68: =Assumptions!$D$15/365*BF11 | BH68: receivables: DSO days' worth of revenue not collected yet
B69: Inventory (DIO-based) | D69: € | M69: =ABS(Assumptions!$D$17*(M17/30)) | N69: =ABS(Assumptions!$D$17*(N17/30)) | O69: =ABS(Assumptions!$D$17*(O17/30)) | P69: =ABS(Assumptions!$D$17*(P17/30)) | Q69: =ABS(Assumptions!$D$17*(Q17/30)) | R69: =ABS(Assumptions!$D$17*(R17/30)) | S69: =ABS(Assumptions!$D$17*(S17/30)) | T69: =ABS(Assumptions!$D$17*(T17/30)) | ... AZ69: =ABS(Assumptions!$D$17*(AZ17/30)) | BB69: =P69 | BC69: =AB69 | BD69: =AN69 | BE69: =AZ69 | BF69: =Assumptions!$D$17/365*BF17 | BH69: inventory: days of stock x cost of sales. 0 days, so zero
B70: Total Current Assets | D70: € | M70: =sum(M66:M69) | N70: =sum(N66:N69) | O70: =sum(O66:O69) | P70: =sum(P66:P69) | Q70: =sum(Q66:Q69) | R70: =sum(R66:R69) | S70: =sum(S66:S69) | T70: =sum(T66:T69) | ... AZ70: =sum(AZ66:AZ69) | BB70: =P70 | BC70: =AB70 | BD70: =AN70 | BE70: =AZ70 | BF70: =BF66+BF68+BF69 | BH70: cash + receivables + inventory
B72: Net PP&E | D72: € | E72: =-SUM($E$53:E53)-SUM($E$35:E35) | F72: =-SUM($E$53:F53)-SUM($E$35:F35) | G72: =-SUM($E$53:G53)-SUM($E$35:G35) | H72: =-SUM($E$53:H53)-SUM($E$35:H35) | I72: =-SUM($E$53:I53)-SUM($E$35:I35) | J72: =-SUM($E$53:J53)-SUM($E$35:J35) | K72: =-SUM($E$53:K53)-SUM($E$35:K35) | L72: =-SUM($E$53:L53)-SUM($E$35:L35) | ... AZ72: =-SUM($E$53:AZ53)-SUM($E$35:AZ35) | BB72: =P72 | BC72: =AB72 | BD72: =AN72 | BE72: =AZ72 | BF72: =BE72+(-BF53)-BF35 | BH72: cumulative capex less accumulated depreciation
B73: Total Fixed Assets | D73: € | M73: =M72 | N73: =N72 | O73: =O72 | P73: =P72 | Q73: =Q72 | R73: =R72 | S73: =S72 | T73: =T72 | ... AZ73: =AZ72 | BB73: =P73 | BC73: =AB73 | BD73: =AN73 | BE73: =AZ73 | BF73: =BF72 | BH73: same as net PP&E
B74: TOTAL ASSETS | D74: € | M74: =M70+M73 | N74: =N70+N73 | O74: =O70+O73 | P74: =P70+P73 | Q74: =Q70+Q73 | R74: =R70+R73 | S74: =S70+S73 | T74: =T70+T73 | ... AZ74: =AZ70+AZ73 | BB74: =P74 | BC74: =AB74 | BD74: =AN74 | BE74: =AZ74 | BF74: =BF70+BF73 | BH74: current assets + fixed assets
B76: EQUITY & LIABILITIES
B77: Accounts payable (DPO-based) | D77: € | M77: =ABS(Assumptions!$D$16*(M17/30)) | N77: =ABS(Assumptions!$D$16*(N17/30)) | O77: =ABS(Assumptions!$D$16*(O17/30)) | P77: =ABS(Assumptions!$D$16*(P17/30)) | Q77: =ABS(Assumptions!$D$16*(Q17/30)) | R77: =ABS(Assumptions!$D$16*(R17/30)) | S77: =ABS(Assumptions!$D$16*(S17/30)) | T77: =ABS(Assumptions!$D$16*(T17/30)) | ... AZ77: =ABS(Assumptions!$D$16*(AZ17/30)) | BB77: =P77 | BC77: =AB77 | BD77: =AN77 | BE77: =AZ77 | BF77: =Assumptions!$D$16/365*BF17 | BH77: payables: DPO days' worth of cost of sales not paid yet
B78: Total Current Liabilities | D78: € | M78: =sum(M77) | N78: =sum(N77) | O78: =sum(O77) | P78: =sum(P77) | Q78: =sum(Q77) | R78: =sum(R77) | S78: =sum(S77) | T78: =sum(T77) | ... AZ78: =sum(AZ77) | BB78: =P78 | BC78: =AB78 | BD78: =AN78 | BE78: =AZ78 | BF78: =BF77 | BH78: same as payables
B81: Loan (CLA) | D81: € | Q81: 0 | R81: 0 | S81: 0 | T81: 0 | U81: 0 | V81: =V56 | W81: =V81+W56 | X81: =W81 | Y81: =X81 | Z81: 0 | AA81: 0 | AB81: 0 | AC81: 0 | AD81: 0 | AE81: 0 | AF81: 0 | AG81: 0 | AH81: 0 | AI81: 0 | AJ81: 0 | AK81: 0 | AL81: 0 | AM81: 0 | AN81: 0 | AO81: 0 | AP81: 0 | AQ81: 0 | AR81: 0 | AS81: 0 | AT81: 0 | AU81: 0 | AV81: 0 | AW81: 0 | AX81: 0 | AY81: 0 | AZ81: 0 | BB81: 0 | BC81: =AB81 | BD81: =AN81 | BE81: =AZ81 | BF81: 0 | BH81: CLA balance: a liability Jul-Sep 26, then it converts to shares
B83: Total Long-Term Liabilities | D83: € | E83: =E80+E81+E82 | F83: =F80+F81+F82 | G83: =G80+G81+G82 | H83: =H80+H81+H82 | I83: =I80+I81+I82 | J83: =J80+J81+J82 | K83: =K80+K81+K82 | L83: =L80+L81+L82 | ... AZ83: =AZ80+AZ81+AZ82 | BB83: =P83 | BC83: =AB83 | BD83: =AN83 | BE83: =AZ83 | BF83: =sum(BF80:BF82) | BH83: all the long-term debt lines added
B85: Share capital + premium | D85: € | M85: =M61 | N85: =M85 | O85: =N85 | P85: =O85 | Q85: =P85 | R85: =Q85 | S85: =R85 | T85: =S85 | U85: =T85 | ... Y85: =X85 | Z85: =Y85+Y81 | AA85: =Z85 | AB85: =AA85 | AC85: =AB85 | AD85: =AC85 | AE85: =AD85 | AF85: =AE85 | AG85: =AF85 | AH85: =AG85 | ... AZ85: =AY85 | BB85: =P85 | BC85: =AB85 | BD85: =AN85 | BE85: =AZ85 | BF85: =BE85 | BH85: share capital, steps up when the CLA converts to shares
B86: Cumulative equity injections | D86: € | M86: =M55+M55 | N86: =M86+N55 | O86: =N86+O55 | P86: =O86+P55 | Q86: =P86+Q55 | R86: =Q86+R55 | S86: =R86+S55 | T86: =S86+T55 | U86: =T86+U55 | ... AZ86: =AY86+AZ55 | BB86: =P86 | BC86: =AB86 | BD86: =AN86 | BE86: =AZ86 | BF86: =BE86 | BH86: running total of cash put in by shareholders
B87: Retained earnings (cumulative net income) | D87: € | M87: =M47 | N87: =M87+N41 | O87: =N87+O41 | P87: =O87+P41 | Q87: =P87+Q41 | R87: =Q87+R41 | S87: =R87+S41 | T87: =S87+T41 | U87: =T87+U41 | ... AZ87: =AY87+AZ41 | BB87: =P87 | BC87: =AB87 | BD87: =AN87 | BE87: =AZ87 | BF87: =BE87+BF41 | BH87: retained earnings: last month's plus this month's profit
B88: Total Equity | D88: € | M88: =M85+M86+M87+M44 | N88: =N85+N86+N87+N44 | O88: =O85+O86+O87+O44 | P88: =P85+P86+P87+P44 | Q88: =Q85+Q86+Q87+Q44 | R88: =R85+R86+R87+R44 | S88: =S85+S86+S87+S44 | T88: =T85+T86+T87+T44 | ... AZ88: =AZ85+AZ86+AZ87+AZ44 | BB88: =P88 | BC88: =AB88 | BD88: =AN88 | BE88: =AZ88 | BF88: =sum(BF85:BF87) | BH88: share capital + injections + retained earnings
B89: TOTAL EQUITY & LIABILITIES | D89: € | M89: =M78+M83+M88 | N89: =N78+N83+N88 | O89: =O78+O83+O88 | P89: =P78+P83+P88 | Q89: =Q78+Q83+Q88 | R89: =R78+R83+R88 | S89: =S78+S83+S88 | T89: =T78+T83+T88 | ... AZ89: =AZ78+AZ83+AZ88 | BB89: =P89 | BC89: =AB89 | BD89: =AN89 | BE89: =AZ89 | BF89: =BF78+BF83+BF88 | BH89: liabilities plus equity
B91: CHECK (Total Assets − Total E&L = 0) | M91: =M74-M89 | N91: =N74-N89 | O91: =O74-O89 | P91: =P74-P89 | Q91: =Q74-Q89 | R91: =R74-R89 | S91: =S74-S89 | T91: =T74-T89 | ... AZ91: =AZ74-AZ89 | BB91: =BB74-BB89 | BC91: =BC74-BC89 | BD91: =BD74-BD89 | BE91: =BE74-BE89 | BF91: =BF74-BF89 | BH91: checks assets = liabilities + equity, must be 0
B93: Cumulative turbineketels (helper) | E93: ='Revenue Forecast'!E34 | F93: =E93+'Revenue Forecast'!F34 | G93: =F93+'Revenue Forecast'!G34 | H93: =G93+'Revenue Forecast'!H34 | I93: =H93+'Revenue Forecast'!I34 | J93: =I93+'Revenue Forecast'!J34 | K93: =J93+'Revenue Forecast'!K34 | L93: =K93+'Revenue Forecast'!L34 | M93: =L93+'Revenue Forecast'!M34 | ... AZ93: =AY93+'Revenue Forecast'!AZ34 | BH93: running count of ketels ever sold. feeds the COGS volume tiers

Sheet Revenue Forecast
B1: Tarnoc B.V. — Revenue Forecast (€, ex VAT unless noted)
E2: 2025 | Q2: 2026 | AC2: 2027 | AO2: 2028
E3: 45658 | F3: 45689 | G3: 45717 | H3: 45748 | I3: 45778 | J3: 45809 | K3: 45839 | L3: 45870 | M3: 45901 | N3: 45931 | O3: 45962 | P3: 45992 | Q3: 46023 | R3: 46054 | S3: 46082 | T3: 46113 | U3: 46143 | V3: 46174 | W3: 46204 | X3: 46235 | Y3: 46266 | Z3: 46296 | AA3: 46327 | AB3: 46357 | AC3: 46388 | AD3: 46419 | AE3: 46447 | AF3: 46478 | AG3: 46508 | AH3: 46539 | AI3: 46569 | AJ3: 46600 | AK3: 46631 | AL3: 46661 | AM3: 46692 | AN3: 46722 | AO3: 46753 | AP3: 46784 | AQ3: 46813 | AR3: 46844 | AS3: 46874 | AT3: 46905 | AU3: 46935 | AV3: 46966 | AW3: 46997 | AX3: 47027 | AY3: 47058 | AZ3: 47088 | BB3: 2025 | BC3: 2026 | BD3: 2027 | BE3: 2028 | BF3: 2029 | BH3: what this row does
AB4: 2 | AC4: 3 | AD4: 4 | AE4: 5 | AF4: 6 | AG4: 7 | AH4: 8 | AI4: 9 | AJ4: 10 | AK4: 11 | AL4: 12 | AM4: 13 | AN4: 14 | AO4: 15 | AP4: 16 | AQ4: 17 | AR4: 18 | AS4: 19 | AT4: 20 | AU4: 21 | AV4: 22 | AW4: 23 | AX4: 24 | AY4: 25 | AZ4: 26
B5: TURBINEKETEL (TTK)
B6: TTK units sold | D6: # | Q6: {=IF(YEAR(Q$3)=2026,0,ROUND(EXP((LN(Assumptions!$E$23/Assumptions!$D$23)/12)*((YEAR(Q$3)-2027)*12+MONTH(Q$3)-1))/SUMPRODUCT(EXP((LN(Assumptions!$E$23/Assumptions!$D$23)/12)*(ROW(INDIRECT("1:24"))-1)))*SUM(Assumptions!$D$23:$E$23),0))} | R6: {=IF(YEAR(R$3)=2026,0,ROUND(EXP((LN(Assumptions!$E$23/Assumptions!$D$23)/12)*((YEAR(R$3)-2027)*12+MONTH(R$3)-1))/SUMPRODUCT(EXP((LN(Assumptions!$E$23/Assumptions!$D$23)/12)*(ROW(INDIRECT("1:24"))-1)))*SUM(Assumptions!$D$23:$E$23),0))} | S6: {=IF(YEAR(S$3)=2026,0,ROUND(EXP((LN(Assumptions!$E$23/Assumptions!$D$23)/12)*((YEAR(S$3)-2027)*12+MONTH(S$3)-1))/SUMPRODUCT(EXP((LN(Assumptions!$E$23/Assumptions!$D$23)/12)*(ROW(INDIRECT("1:24"))-1)))*SUM(Assumptions!$D$23:$E$23),0))} | T6: {=IF(YEAR(T$3)=2026,0,ROUND(EXP((LN(Assumptions!$E$23/Assumptions!$D$23)/12)*((YEAR(T$3)-2027)*12+MONTH(T$3)-1))/SUMPRODUCT(EXP((LN(Assumptions!$E$23/Assumptions!$D$23)/12)*(ROW(INDIRECT("1:24"))-1)))*SUM(Assumptions!$D$23:$E$23),0))} | U6: {=IF(YEAR(U$3)=2026,0,ROUND(EXP((LN(Assumptions!$E$23/Assumptions!$D$23)/12)*((YEAR(U$3)-2027)*12+MONTH(U$3)-1))/SUMPRODUCT(EXP((LN(Assumptions!$E$23/Assumptions!$D$23)/12)*(ROW(INDIRECT("1:24"))-1)))*SUM(Assumptions!$D$23:$E$23),0))} | V6: {=IF(YEAR(V$3)=2026,0,ROUND(EXP((LN(Assumptions!$E$23/Assumptions!$D$23)/12)*((YEAR(V$3)-2027)*12+MONTH(V$3)-1))/SUMPRODUCT(EXP((LN(Assumptions!$E$23/Assumptions!$D$23)/12)*(ROW(INDIRECT("1:24"))-1)))*SUM(Assumptions!$D$23:$E$23),0))} | W6: {=IF(YEAR(W$3)=2026,0,ROUND(EXP((LN(Assumptions!$E$23/Assumptions!$D$23)/12)*((YEAR(W$3)-2027)*12+MONTH(W$3)-1))/SUMPRODUCT(EXP((LN(Assumptions!$E$23/Assumptions!$D$23)/12)*(ROW(INDIRECT("1:24"))-1)))*SUM(Assumptions!$D$23:$E$23),0))} | X6: {=IF(YEAR(X$3)=2026,0,ROUND(EXP((LN(Assumptions!$E$23/Assumptions!$D$23)/12)*((YEAR(X$3)-2027)*12+MONTH(X$3)-1))/SUMPRODUCT(EXP((LN(Assumptions!$E$23/Assumptions!$D$23)/12)*(ROW(INDIRECT("1:24"))-1)))*SUM(Assumptions!$D$23:$E$23),0))} | ... AM6: {=IF(YEAR(AM$3)=2026,0,ROUND(EXP((LN(Assumptions!$E$23/Assumptions!$D$23)/12)*((YEAR(AM$3)-2027)*12+MONTH(AM$3)-1))/SUMPRODUCT(EXP((LN(Assumptions!$E$23/Assumptions!$D$23)/12)*(ROW(INDIRECT("1:24"))-1)))*SUM(Assumptions!$D$23:$E$23),0))} | AN6: =Assumptions!$D$23-SUM(AC6:AM6) | AO6: {=IF(YEAR(AO$3)=2026,0,ROUND(EXP((LN(Assumptions!$E$23/Assumptions!$D$23)/12)*((YEAR(AO$3)-2027)*12+MONTH(AO$3)-1))/SUMPRODUCT(EXP((LN(Assumptions!$E$23/Assumptions!$D$23)/12)*(ROW(INDIRECT("1:24"))-1)))*SUM(Assumptions!$D$23:$E$23),0))} | AP6: {=IF(YEAR(AP$3)=2026,0,ROUND(EXP((LN(Assumptions!$E$23/Assumptions!$D$23)/12)*((YEAR(AP$3)-2027)*12+MONTH(AP$3)-1))/SUMPRODUCT(EXP((LN(Assumptions!$E$23/Assumptions!$D$23)/12)*(ROW(INDIRECT("1:24"))-1)))*SUM(Assumptions!$D$23:$E$23),0))} | AQ6: {=IF(YEAR(AQ$3)=2026,0,ROUND(EXP((LN(Assumptions!$E$23/Assumptions!$D$23)/12)*((YEAR(AQ$3)-2027)*12+MONTH(AQ$3)-1))/SUMPRODUCT(EXP((LN(Assumptions!$E$23/Assumptions!$D$23)/12)*(ROW(INDIRECT("1:24"))-1)))*SUM(Assumptions!$D$23:$E$23),0))} | AR6: {=IF(YEAR(AR$3)=2026,0,ROUND(EXP((LN(Assumptions!$E$23/Assumptions!$D$23)/12)*((YEAR(AR$3)-2027)*12+MONTH(AR$3)-1))/SUMPRODUCT(EXP((LN(Assumptions!$E$23/Assumptions!$D$23)/12)*(ROW(INDIRECT("1:24"))-1)))*SUM(Assumptions!$D$23:$E$23),0))} | AS6: {=IF(YEAR(AS$3)=2026,0,ROUND(EXP((LN(Assumptions!$E$23/Assumptions!$D$23)/12)*((YEAR(AS$3)-2027)*12+MONTH(AS$3)-1))/SUMPRODUCT(EXP((LN(Assumptions!$E$23/Assumptions!$D$23)/12)*(ROW(INDIRECT("1:24"))-1)))*SUM(Assumptions!$D$23:$E$23),0))} | AT6: {=IF(YEAR(AT$3)=2026,0,ROUND(EXP((LN(Assumptions!$E$23/Assumptions!$D$23)/12)*((YEAR(AT$3)-2027)*12+MONTH(AT$3)-1))/SUMPRODUCT(EXP((LN(Assumptions!$E$23/Assumptions!$D$23)/12)*(ROW(INDIRECT("1:24"))-1)))*SUM(Assumptions!$D$23:$E$23),0))} | AU6: {=IF(YEAR(AU$3)=2026,0,ROUND(EXP((LN(Assumptions!$E$23/Assumptions!$D$23)/12)*((YEAR(AU$3)-2027)*12+MONTH(AU$3)-1))/SUMPRODUCT(EXP((LN(Assumptions!$E$23/Assumptions!$D$23)/12)*(ROW(INDIRECT("1:24"))-1)))*SUM(Assumptions!$D$23:$E$23),0))} | AV6: {=IF(YEAR(AV$3)=2026,0,ROUND(EXP((LN(Assumptions!$E$23/Assumptions!$D$23)/12)*((YEAR(AV$3)-2027)*12+MONTH(AV$3)-1))/SUMPRODUCT(EXP((LN(Assumptions!$E$23/Assumptions!$D$23)/12)*(ROW(INDIRECT("1:24"))-1)))*SUM(Assumptions!$D$23:$E$23),0))} | ... AY6: {=IF(YEAR(AY$3)=2026,0,ROUND(EXP((LN(Assumptions!$E$23/Assumptions!$D$23)/12)*((YEAR(AY$3)-2027)*12+MONTH(AY$3)-1))/SUMPRODUCT(EXP((LN(Assumptions!$E$23/Assumptions!$D$23)/12)*(ROW(INDIRECT("1:24"))-1)))*SUM(Assumptions!$D$23:$E$23),0))} | AZ6: =Assumptions!$E$23-SUM(AO6:AY6) | BB6: =SUM(E6:P6) | BC6: =SUM(Q6:AB6) | BD6: =SUM(AC6:AN6) | BE6: =SUM(AO6:AZ6) | BF6: =Assumptions!$F$23 | BH6: monthly units on an S-curve ramp; December tops up so the year hits the target exactly. 2029 has no monthly detail, it reads the annual number
B7: TTK Revenue | D7: € | Q7: =Q6*Assumptions!$C$29 | R7: =R6*Assumptions!$C$29 | S7: =S6*Assumptions!$C$29 | T7: =T6*Assumptions!$C$29 | U7: =U6*Assumptions!$C$29 | V7: =V6*Assumptions!$C$29 | W7: =W6*Assumptions!$C$29 | X7: =X6*Assumptions!$C$29 | ... AZ7: =AZ6*Assumptions!$C$29 | BB7: =SUM(E7:P7) | BC7: =SUM(Q7:AB7) | BD7: =SUM(AC7:AN7) | BE7: =SUM(AO7:AZ7) | BF7: =BF6*Assumptions!$C$29 | BH7: units x TTK price
B8: TTK upsell | D8: € | Q8: =Q6*SUMPRODUCT(Assumptions!$E$112:$F$114) | R8: =R6*SUMPRODUCT(Assumptions!$E$112:$F$114) | S8: =S6*SUMPRODUCT(Assumptions!$E$112:$F$114) | T8: =T6*SUMPRODUCT(Assumptions!$E$112:$F$114) | U8: =U6*SUMPRODUCT(Assumptions!$E$112:$F$114) | V8: =V6*SUMPRODUCT(Assumptions!$E$112:$F$114) | W8: =W6*SUMPRODUCT(Assumptions!$E$112:$F$114) | X8: =X6*SUMPRODUCT(Assumptions!$E$112:$F$114) | ... AB8: =AB6*SUMPRODUCT(Assumptions!$E$112:$F$114) | AC8: =AC6*SUMPRODUCT(Assumptions!$E$112:$E$114,Assumptions!$F$112:$F$114) | AD8: =AD6*SUMPRODUCT(Assumptions!$E$112:$E$114,Assumptions!$F$112:$F$114) | AE8: =AE6*SUMPRODUCT(Assumptions!$E$112:$E$114,Assumptions!$F$112:$F$114) | AF8: =AF6*SUMPRODUCT(Assumptions!$E$112:$E$114,Assumptions!$F$112:$F$114) | AG8: =AG6*SUMPRODUCT(Assumptions!$E$112:$E$114,Assumptions!$F$112:$F$114) | AH8: =AH6*SUMPRODUCT(Assumptions!$E$112:$E$114,Assumptions!$F$112:$F$114) | AI8: =AI6*SUMPRODUCT(Assumptions!$E$112:$E$114,Assumptions!$F$112:$F$114) | AJ8: =AJ6*SUMPRODUCT(Assumptions!$E$112:$E$114,Assumptions!$F$112:$F$114) | ... AZ8: =AZ6*SUMPRODUCT(Assumptions!$E$112:$E$114,Assumptions!$F$112:$F$114) | BB8: =SUM(E8:P8) | BC8: =SUM(Q8:AB8) | BD8: =SUM(AC8:AN8) | BE8: =SUM(AO8:AZ8) | BF8: =BF6*SUMPRODUCT(Assumptions!$E$112:$E$114,Assumptions!$F$112:$F$114) | BH8: units x average upsell basket (attach % x price)
B9: Total TTK Revenue | D9: € | Q9: =sum(Q7:Q8) | R9: =sum(R7:R8) | S9: =sum(S7:S8) | T9: =sum(T7:T8) | U9: =sum(U7:U8) | V9: =sum(V7:V8) | W9: =sum(W7:W8) | X9: =sum(X7:X8) | ... AZ9: =sum(AZ7:AZ8) | BB9: =SUM(E9:P9) | BC9: =SUM(Q9:AB9) | BD9: =SUM(AC9:AN9) | BE9: =SUM(AO9:AZ9) | BF9: =SUM(BF7:BF8) | BH9: machine revenue + upsells
B11: COMBI+
B12: Combi+ units sold | D12: # | Q12: {=IF(YEAR(Q$3)=2026,0,ROUND(EXP((LN(Assumptions!$E$24/Assumptions!$D$24)/12)*((YEAR(Q$3)-2027)*12+MONTH(Q$3)-1))/SUMPRODUCT(EXP((LN(Assumptions!$E$24/Assumptions!$D$24)/12)*(ROW(INDIRECT("1:24"))-1)))*SUM(Assumptions!$D$24:$E$24),0))} | R12: {=IF(YEAR(R$3)=2026,0,ROUND(EXP((LN(Assumptions!$E$24/Assumptions!$D$24)/12)*((YEAR(R$3)-2027)*12+MONTH(R$3)-1))/SUMPRODUCT(EXP((LN(Assumptions!$E$24/Assumptions!$D$24)/12)*(ROW(INDIRECT("1:24"))-1)))*SUM(Assumptions!$D$24:$E$24),0))} | S12: {=IF(YEAR(S$3)=2026,0,ROUND(EXP((LN(Assumptions!$E$24/Assumptions!$D$24)/12)*((YEAR(S$3)-2027)*12+MONTH(S$3)-1))/SUMPRODUCT(EXP((LN(Assumptions!$E$24/Assumptions!$D$24)/12)*(ROW(INDIRECT("1:24"))-1)))*SUM(Assumptions!$D$24:$E$24),0))} | T12: {=IF(YEAR(T$3)=2026,0,ROUND(EXP((LN(Assumptions!$E$24/Assumptions!$D$24)/12)*((YEAR(T$3)-2027)*12+MONTH(T$3)-1))/SUMPRODUCT(EXP((LN(Assumptions!$E$24/Assumptions!$D$24)/12)*(ROW(INDIRECT("1:24"))-1)))*SUM(Assumptions!$D$24:$E$24),0))} | U12: {=IF(YEAR(U$3)=2026,0,ROUND(EXP((LN(Assumptions!$E$24/Assumptions!$D$24)/12)*((YEAR(U$3)-2027)*12+MONTH(U$3)-1))/SUMPRODUCT(EXP((LN(Assumptions!$E$24/Assumptions!$D$24)/12)*(ROW(INDIRECT("1:24"))-1)))*SUM(Assumptions!$D$24:$E$24),0))} | V12: {=IF(YEAR(V$3)=2026,0,ROUND(EXP((LN(Assumptions!$E$24/Assumptions!$D$24)/12)*((YEAR(V$3)-2027)*12+MONTH(V$3)-1))/SUMPRODUCT(EXP((LN(Assumptions!$E$24/Assumptions!$D$24)/12)*(ROW(INDIRECT("1:24"))-1)))*SUM(Assumptions!$D$24:$E$24),0))} | W12: {=IF(YEAR(W$3)=2026,0,ROUND(EXP((LN(Assumptions!$E$24/Assumptions!$D$24)/12)*((YEAR(W$3)-2027)*12+MONTH(W$3)-1))/SUMPRODUCT(EXP((LN(Assumptions!$E$24/Assumptions!$D$24)/12)*(ROW(INDIRECT("1:24"))-1)))*SUM(Assumptions!$D$24:$E$24),0))} | X12: {=IF(YEAR(X$3)=2026,0,ROUND(EXP((LN(Assumptions!$E$24/Assumptions!$D$24)/12)*((YEAR(X$3)-2027)*12+MONTH(X$3)-1))/SUMPRODUCT(EXP((LN(Assumptions!$E$24/Assumptions!$D$24)/12)*(ROW(INDIRECT("1:24"))-1)))*SUM(Assumptions!$D$24:$E$24),0))} | ... AM12: {=IF(YEAR(AM$3)=2026,0,ROUND(EXP((LN(Assumptions!$E$24/Assumptions!$D$24)/12)*((YEAR(AM$3)-2027)*12+MONTH(AM$3)-1))/SUMPRODUCT(EXP((LN(Assumptions!$E$24/Assumptions!$D$24)/12)*(ROW(INDIRECT("1:24"))-1)))*SUM(Assumptions!$D$24:$E$24),0))} | AN12: =Assumptions!$D$24-SUM(AC12:AM12) | AO12: {=IF(YEAR(AO$3)=2026,0,ROUND(EXP((LN(Assumptions!$E$24/Assumptions!$D$24)/12)*((YEAR(AO$3)-2027)*12+MONTH(AO$3)-1))/SUMPRODUCT(EXP((LN(Assumptions!$E$24/Assumptions!$D$24)/12)*(ROW(INDIRECT("1:24"))-1)))*SUM(Assumptions!$D$24:$E$24),0))} | AP12: {=IF(YEAR(AP$3)=2026,0,ROUND(EXP((LN(Assumptions!$E$24/Assumptions!$D$24)/12)*((YEAR(AP$3)-2027)*12+MONTH(AP$3)-1))/SUMPRODUCT(EXP((LN(Assumptions!$E$24/Assumptions!$D$24)/12)*(ROW(INDIRECT("1:24"))-1)))*SUM(Assumptions!$D$24:$E$24),0))} | AQ12: {=IF(YEAR(AQ$3)=2026,0,ROUND(EXP((LN(Assumptions!$E$24/Assumptions!$D$24)/12)*((YEAR(AQ$3)-2027)*12+MONTH(AQ$3)-1))/SUMPRODUCT(EXP((LN(Assumptions!$E$24/Assumptions!$D$24)/12)*(ROW(INDIRECT("1:24"))-1)))*SUM(Assumptions!$D$24:$E$24),0))} | AR12: {=IF(YEAR(AR$3)=2026,0,ROUND(EXP((LN(Assumptions!$E$24/Assumptions!$D$24)/12)*((YEAR(AR$3)-2027)*12+MONTH(AR$3)-1))/SUMPRODUCT(EXP((LN(Assumptions!$E$24/Assumptions!$D$24)/12)*(ROW(INDIRECT("1:24"))-1)))*SUM(Assumptions!$D$24:$E$24),0))} | AS12: {=IF(YEAR(AS$3)=2026,0,ROUND(EXP((LN(Assumptions!$E$24/Assumptions!$D$24)/12)*((YEAR(AS$3)-2027)*12+MONTH(AS$3)-1))/SUMPRODUCT(EXP((LN(Assumptions!$E$24/Assumptions!$D$24)/12)*(ROW(INDIRECT("1:24"))-1)))*SUM(Assumptions!$D$24:$E$24),0))} | AT12: {=IF(YEAR(AT$3)=2026,0,ROUND(EXP((LN(Assumptions!$E$24/Assumptions!$D$24)/12)*((YEAR(AT$3)-2027)*12+MONTH(AT$3)-1))/SUMPRODUCT(EXP((LN(Assumptions!$E$24/Assumptions!$D$24)/12)*(ROW(INDIRECT("1:24"))-1)))*SUM(Assumptions!$D$24:$E$24),0))} | AU12: {=IF(YEAR(AU$3)=2026,0,ROUND(EXP((LN(Assumptions!$E$24/Assumptions!$D$24)/12)*((YEAR(AU$3)-2027)*12+MONTH(AU$3)-1))/SUMPRODUCT(EXP((LN(Assumptions!$E$24/Assumptions!$D$24)/12)*(ROW(INDIRECT("1:24"))-1)))*SUM(Assumptions!$D$24:$E$24),0))} | AV12: {=IF(YEAR(AV$3)=2026,0,ROUND(EXP((LN(Assumptions!$E$24/Assumptions!$D$24)/12)*((YEAR(AV$3)-2027)*12+MONTH(AV$3)-1))/SUMPRODUCT(EXP((LN(Assumptions!$E$24/Assumptions!$D$24)/12)*(ROW(INDIRECT("1:24"))-1)))*SUM(Assumptions!$D$24:$E$24),0))} | ... AY12: {=IF(YEAR(AY$3)=2026,0,ROUND(EXP((LN(Assumptions!$E$24/Assumptions!$D$24)/12)*((YEAR(AY$3)-2027)*12+MONTH(AY$3)-1))/SUMPRODUCT(EXP((LN(Assumptions!$E$24/Assumptions!$D$24)/12)*(ROW(INDIRECT("1:24"))-1)))*SUM(Assumptions!$D$24:$E$24),0))} | AZ12: =Assumptions!$E$24-SUM(AO12:AY12) | BB12: =SUM(E12:P12) | BC12: =SUM(Q12:AB12) | BD12: =SUM(AC12:AN12) | BE12: =SUM(AO12:AZ12) | BF12: =Assumptions!$F$24 | BH12: same S-curve as TTK, on the Combi+ volume; December is the top-up. 2029 comes straight off the annual assumption
B13: Combi+ Revenue | D13: € | Q13: =Q12*Assumptions!$C$31 | R13: =R12*Assumptions!$C$31 | S13: =S12*Assumptions!$C$31 | T13: =T12*Assumptions!$C$31 | U13: =U12*Assumptions!$C$31 | V13: =V12*Assumptions!$C$31 | W13: =W12*Assumptions!$C$31 | X13: =X12*Assumptions!$C$31 | ... AZ13: =AZ12*Assumptions!$C$31 | BB13: =SUM(E13:P13) | BC13: =SUM(Q13:AB13) | BD13: =SUM(AC13:AN13) | BE13: =SUM(AO13:AZ13) | BF13: =BF12*Assumptions!$C$31 | BH13: units x Combi+ price (ketel + outdoor unit)
B14: Combi+ upsell | D14: € | Q14: =Q12*SUMPRODUCT(Assumptions!$E$112:$E$114,Assumptions!$F$112:$F$114) | R14: =R12*SUMPRODUCT(Assumptions!$E$112:$E$114,Assumptions!$F$112:$F$114) | S14: =S12*SUMPRODUCT(Assumptions!$E$112:$E$114,Assumptions!$F$112:$F$114) | T14: =T12*SUMPRODUCT(Assumptions!$E$112:$E$114,Assumptions!$F$112:$F$114) | U14: =U12*SUMPRODUCT(Assumptions!$E$112:$E$114,Assumptions!$F$112:$F$114) | V14: =V12*SUMPRODUCT(Assumptions!$E$112:$E$114,Assumptions!$F$112:$F$114) | W14: =W12*SUMPRODUCT(Assumptions!$E$112:$E$114,Assumptions!$F$112:$F$114) | X14: =X12*SUMPRODUCT(Assumptions!$E$112:$E$114,Assumptions!$F$112:$F$114) | ... AZ14: =AZ12*SUMPRODUCT(Assumptions!$E$112:$E$114,Assumptions!$F$112:$F$114) | BB14: =SUM(E14:P14) | BC14: =SUM(Q14:AB14) | BD14: =SUM(AC14:AN14) | BE14: =SUM(AO14:AZ14) | BF14: =BF12*SUMPRODUCT(Assumptions!$E$112:$E$114,Assumptions!$F$112:$F$114) | BH14: units x average upsell basket
B15: Total Combi+ Revenue | D15: € | Q15: =sum(Q13:Q14) | R15: =sum(R13:R14) | S15: =sum(S13:S14) | T15: =sum(T13:T14) | U15: =sum(U13:U14) | V15: =sum(V13:V14) | W15: =sum(W13:W14) | X15: =sum(X13:X14) | ... AZ15: =sum(AZ13:AZ14) | BB15: =SUM(E15:P15) | BC15: =SUM(Q15:AB15) | BD15: =SUM(AC15:AN15) | BE15: =SUM(AO15:AZ15) | BF15: =sum(BF13:BF14) | BH15: machine revenue + upsells
B17: INSTALLATION REVENUES | D17: €
B18: Units installed | D18: # | E18: =E6+E12 | F18: =F6+F12 | G18: =G6+G12 | H18: =H6+H12 | I18: =I6+I12 | J18: =J6+J12 | K18: =K6+K12 | L18: =L6+L12 | ... AZ18: =AZ6+AZ12 | BB18: =SUM(E18:P18) | BC18: =SUM(Q18:AB18) | BD18: =SUM(AC18:AN18) | BE18: =SUM(AO18:AZ18) | BF18: =BF6+BF12 | BH18: TTK + Combi+ units. every unit sold gets installed
B19: Total Installation Revenue | D19: € | E19: =E6*Assumptions!$C$33+E12*Assumptions!$C$34 | F19: =F6*Assumptions!$C$33+F12*Assumptions!$C$34 | G19: =G6*Assumptions!$C$33+G12*Assumptions!$C$34 | H19: =H6*Assumptions!$C$33+H12*Assumptions!$C$34 | I19: =I6*Assumptions!$C$33+I12*Assumptions!$C$34 | J19: =J6*Assumptions!$C$33+J12*Assumptions!$C$34 | K19: =K6*Assumptions!$C$33+K12*Assumptions!$C$34 | L19: =L6*Assumptions!$C$33+L12*Assumptions!$C$34 | ... AZ19: =AZ6*Assumptions!$C$33+AZ12*Assumptions!$C$34 | BB19: =SUM(E19:P19) | BC19: =SUM(Q19:AB19) | BD19: =SUM(AC19:AN19) | BE19: =SUM(AO19:AZ19) | BF19: =BF6*Assumptions!$C$33+BF12*Assumptions!$C$34 | BH19: units x installation price per product. pass-through, cost is the same
B21: SERVICE REVENUES
B22: Installed base (TTK) | D22: # | Q22: =Q6 | R22: =R6 | S22: =S6 | T22: =T6 | U22: =U6 | V22: =V6 | W22: =W6 | X22: =X6 | ... AC22: =AC6 | AD22: =AC22+AD6 | AE22: =AD22+AE6 | AF22: =AE22+AF6 | AG22: =AF22+AG6 | AH22: =AG22+AH6 | AI22: =AH22+AI6 | AJ22: =AI22+AJ6 | AK22: =AJ22+AK6 | ... AZ22: =AY22+AZ6 | BB22: =SUM(E22:P22) | BC22: =SUM(Q22:AB22) | BD22: =AN22 | BE22: =AZ22 | BF22: =BE22+($BF$18*Assumptions!$H$23) | BH22: TTK machines out in the field: last month's base + this month's sales
B23: Installed base (Combi+) | Q23: =Q12 | R23: =R12 | S23: =S12 | T23: =T12 | U23: =U12 | V23: =V12 | W23: =W12 | X23: =X12 | ... AC23: =AC12 | AD23: =AC23+AD12 | AE23: =AD23+AE12 | AF23: =AE23+AF12 | AG23: =AF23+AG12 | AH23: =AG23+AH12 | AI23: =AH23+AI12 | AJ23: =AI23+AJ12 | AK23: =AJ23+AK12 | ... AZ23: =AY23+AZ12 | BB23: =SUM(E23:P23) | BC23: =SUM(Q23:AB23) | BD23: =AN23 | BE23: =AZ23 | BF23: =BE23+($BF$18*Assumptions!$H$24) | BH23: Combi+ machines out in the field, same running total
B24: Total Service Revenue | D24: € | Q24: =Q34*SUMPRODUCT(Assumptions!$E$120:$E$121,Assumptions!$F$120:$F$121) | R24: =R34*SUMPRODUCT(Assumptions!$E$120:$E$121,Assumptions!$F$120:$F$121) | S24: =S34*SUMPRODUCT(Assumptions!$E$120:$E$121,Assumptions!$F$120:$F$121) | T24: =T34*SUMPRODUCT(Assumptions!$E$120:$E$121,Assumptions!$F$120:$F$121) | U24: =U34*SUMPRODUCT(Assumptions!$E$120:$E$121,Assumptions!$F$120:$F$121) | V24: =V34*SUMPRODUCT(Assumptions!$E$120:$E$121,Assumptions!$F$120:$F$121) | W24: =W34*SUMPRODUCT(Assumptions!$E$120:$E$121,Assumptions!$F$120:$F$121) | X24: =X34*SUMPRODUCT(Assumptions!$E$120:$E$121,Assumptions!$F$120:$F$121) | ... AB24: =AB34*SUMPRODUCT(Assumptions!$E$120:$E$121,Assumptions!$F$120:$F$121) | AC24: =AC34*SUMPRODUCT(Assumptions!$E$120:$E$121,Assumptions!$F$120:$F$121)+Q24 | AD24: =AD34*SUMPRODUCT(Assumptions!$E$120:$E$121,Assumptions!$F$120:$F$121)+R24 | AE24: =AE34*SUMPRODUCT(Assumptions!$E$120:$E$121,Assumptions!$F$120:$F$121)+S24 | AF24: =AF34*SUMPRODUCT(Assumptions!$E$120:$E$121,Assumptions!$F$120:$F$121)+T24 | AG24: =AG34*SUMPRODUCT(Assumptions!$E$120:$E$121,Assumptions!$F$120:$F$121)+U24 | AH24: =AH34*SUMPRODUCT(Assumptions!$E$120:$E$121,Assumptions!$F$120:$F$121)+V24 | AI24: =AI34*SUMPRODUCT(Assumptions!$E$120:$E$121,Assumptions!$F$120:$F$121)+W24 | AJ24: =AJ34*SUMPRODUCT(Assumptions!$E$120:$E$121,Assumptions!$F$120:$F$121)+X24 | ... AZ24: =AZ34*SUMPRODUCT(Assumptions!$E$120:$E$121,Assumptions!$F$120:$F$121)+AN24 | BB24: =SUM(E24:P24) | BC24: =SUM(Q24:AB24) | BD24: =SUM(AC24:AN24) | BE24: =SUM(AO24:AZ24) | BF24: =BF34*SUMPRODUCT(Assumptions!$E$120:$E$121,Assumptions!$F$120:$F$121)+BE24 | BH24: this month's units x service rate + the same month last year, so contracts keep stacking as the base grows. 2029 adds all of 2028 on top
B26: SUBSIDIES & GRANTS
B27: All other | D27: € | E27: 0 | F27: 0 | G27: 0 | H27: 0 | I27: 0 | J27: 0 | K27: 0 | L27: 0 | M27: 0 | N27: 19480 | O27: 78000 | P27: 0 | Q27: 0 | R27: 0 | S27: 0 | T27: 0 | U27: 0 | V27: 0 | W27: 0 | X27: 106782 | Y27: 0 | Z27: 0 | AA27: 0 | AB27: 0 | AC27: 0 | AD27: 0 | AE27: 0 | AF27: 0 | AG27: 0 | AH27: 0 | AI27: 0 | AJ27: 0 | AK27: 0 | AL27: 0 | AM27: 0 | AN27: 0 | AO27: 0 | AP27: 0 | AQ27: 0 | AR27: 0 | AS27: 0 | AT27: 0 | AU27: 0 | AV27: 0 | AW27: 0 | AX27: 0 | AY27: 0 | AZ27: 0 | BB27: =SUM(E27:P27) | BC27: =SUM(Q27:AB27) | BD27: =SUM(AC27:AN27) | BE27: =SUM(AO27:AZ27) | BF27: 0 | BH27: nothing budgeted. the year columns just add the months up
B28: Total Subsidies & Grants | D28: € | E28: =sum(E27) | F28: =sum(F27) | G28: =sum(G27) | H28: =sum(H27) | I28: =sum(I27) | J28: =sum(J27) | K28: =sum(K27) | L28: =sum(L27) | ... AZ28: =sum(AZ27) | BB28: =SUM(E28:P28) | BC28: =SUM(Q28:AB28) | BD28: =BD27 | BE28: =BE27 | BF28: =BF27 | BH28: same as the line above
B30: TOTAL REVENUE | E30: =E9+E15+E19+E24+E28 | F30: =F9+F15+F19+F24+F28 | G30: =G9+G15+G19+G24+G28 | H30: =H9+H15+H19+H24+H28 | I30: =I9+I15+I19+I24+I28 | J30: =J9+J15+J19+J24+J28 | K30: =K9+K15+K19+K24+K28 | L30: =L9+L15+L19+L24+L28 | ... AZ30: =AZ9+AZ15+AZ19+AZ24+AZ28 | BB30: =BB9+BB15+BB19+BB24+BB28 | BC30: =BC9+BC15+BC19+BC24+BC28 | BD30: =SUM(AC30:AN30) | BE30: =SUM(AO30:AZ30) | BF30: =BF9+BF15+BF19+BF24+BF28 | BH30: everything added: TTK + Combi+ + installation + service + subsidies
B33: Installed Base | E33: =sum(E22:E23) | F33: =sum(F22:F23) | G33: =sum(G22:G23) | H33: =sum(H22:H23) | I33: =sum(I22:I23) | J33: =sum(J22:J23) | K33: =sum(K22:K23) | L33: =sum(L22:L23) | ... AZ33: =sum(AZ22:AZ23) | BB33: =sum(BB22:BB23) | BC33: =sum(BC22:BC23) | BD33: =sum(BD22:BD23) | BE33: =sum(BE22:BE23) | BF33: =sum(BF22:BF23) | BH33: total machines in the field (TTK + Combi+)
B34: Units sold | D34: # | E34: =E6+E12 | F34: =F6+F12 | G34: =G6+G12 | H34: =H6+H12 | I34: =I6+I12 | J34: =J6+J12 | K34: =K6+K12 | L34: =L6+L12 | ... AZ34: =AZ6+AZ12 | BB34: 0 | BC34: 0 | BD34: =SUM(AC34:AN34) | BE34: =SUM(AO34:AZ34) | BF34: =BF18 | BH34: units sold this period. the COGS volume tiers look at this row

Sheet COGS
B1: Tarnoc B.V. — COGS Schedule (€)
E2: 2025 | Q2: 2026 | AC2: 2027 | AO2: 2028
E3: 45658 | F3: 45689 | G3: 45717 | H3: 45748 | I3: 45778 | J3: 45809 | K3: 45839 | L3: 45870 | M3: 45901 | N3: 45931 | O3: 45962 | P3: 45992 | Q3: 46023 | R3: 46054 | S3: 46082 | T3: 46113 | U3: 46143 | V3: 46174 | W3: 46204 | X3: 46235 | Y3: 46266 | Z3: 46296 | AA3: 46327 | AB3: 46357 | AC3: 46388 | AD3: 46419 | AE3: 46447 | AF3: 46478 | AG3: 46508 | AH3: 46539 | AI3: 46569 | AJ3: 46600 | AK3: 46631 | AL3: 46661 | AM3: 46692 | AN3: 46722 | AO3: 46753 | AP3: 46784 | AQ3: 46813 | AR3: 46844 | AS3: 46874 | AT3: 46905 | AU3: 46935 | AV3: 46966 | AW3: 46997 | AX3: 47027 | AY3: 47058 | AZ3: 47088 | BB3: 2025 | BC3: 2026 | BD3: 2027 | BE3: 2028 | BF3: 2029
B6: TTK
B7: TTK | D7: € | Q7: =IFNA('Revenue Forecast'!Q6*VLOOKUP('Revenue Forecast'!$BC$34,Assumptions!$B$67:$C$69,2,TRUE),0) | R7: =IFNA('Revenue Forecast'!R6*VLOOKUP('Revenue Forecast'!$BC$34,Assumptions!$B$67:$C$69,2,TRUE),0) | S7: =IFNA('Revenue Forecast'!S6*VLOOKUP('Revenue Forecast'!$BC$34,Assumptions!$B$67:$C$69,2,TRUE),0) | T7: =IFNA('Revenue Forecast'!T6*VLOOKUP('Revenue Forecast'!$BC$34,Assumptions!$B$67:$C$69,2,TRUE),0) | U7: =IFNA('Revenue Forecast'!U6*VLOOKUP('Revenue Forecast'!$BC$34,Assumptions!$B$67:$C$69,2,TRUE),0) | V7: =IFNA('Revenue Forecast'!V6*VLOOKUP('Revenue Forecast'!$BC$34,Assumptions!$B$67:$C$69,2,TRUE),0) | W7: =IFNA('Revenue Forecast'!W6*VLOOKUP('Revenue Forecast'!$BC$34,Assumptions!$B$67:$C$69,2,TRUE),0) | X7: =IFNA('Revenue Forecast'!X6*VLOOKUP('Revenue Forecast'!$BC$34,Assumptions!$B$67:$C$69,2,TRUE),0) | ... AB7: =IFNA('Revenue Forecast'!AB6*VLOOKUP('Revenue Forecast'!$BC$34,Assumptions!$B$67:$C$69,2,TRUE),0) | AC7: =IFNA('Revenue Forecast'!AC6*VLOOKUP(IF(Assumptions!$D$83=2,'Revenue Forecast'!$BD$34+'Revenue Forecast'!$BE$34,'Revenue Forecast'!$BD$34),Assumptions!$B$67:$C$69,2,TRUE),0) | AD7: =IFNA('Revenue Forecast'!AD6*VLOOKUP(IF(Assumptions!$D$83=2,'Revenue Forecast'!$BD$34+'Revenue Forecast'!$BE$34,'Revenue Forecast'!$BD$34),Assumptions!$B$67:$C$69,2,TRUE),0) | AE7: =IFNA('Revenue Forecast'!AE6*VLOOKUP(IF(Assumptions!$D$83=2,'Revenue Forecast'!$BD$34+'Revenue Forecast'!$BE$34,'Revenue Forecast'!$BD$34),Assumptions!$B$67:$C$69,2,TRUE),0) | AF7: =IFNA('Revenue Forecast'!AF6*VLOOKUP(IF(Assumptions!$D$83=2,'Revenue Forecast'!$BD$34+'Revenue Forecast'!$BE$34,'Revenue Forecast'!$BD$34),Assumptions!$B$67:$C$69,2,TRUE),0) | AG7: =IFNA('Revenue Forecast'!AG6*VLOOKUP(IF(Assumptions!$D$83=2,'Revenue Forecast'!$BD$34+'Revenue Forecast'!$BE$34,'Revenue Forecast'!$BD$34),Assumptions!$B$67:$C$69,2,TRUE),0) | AH7: =IFNA('Revenue Forecast'!AH6*VLOOKUP(IF(Assumptions!$D$83=2,'Revenue Forecast'!$BD$34+'Revenue Forecast'!$BE$34,'Revenue Forecast'!$BD$34),Assumptions!$B$67:$C$69,2,TRUE),0) | AI7: =IFNA('Revenue Forecast'!AI6*VLOOKUP(IF(Assumptions!$D$83=2,'Revenue Forecast'!$BD$34+'Revenue Forecast'!$BE$34,'Revenue Forecast'!$BD$34),Assumptions!$B$67:$C$69,2,TRUE),0) | AJ7: =IFNA('Revenue Forecast'!AJ6*VLOOKUP(IF(Assumptions!$D$83=2,'Revenue Forecast'!$BD$34+'Revenue Forecast'!$BE$34,'Revenue Forecast'!$BD$34),Assumptions!$B$67:$C$69,2,TRUE),0) | ... AN7: =IFNA('Revenue Forecast'!AN6*VLOOKUP(IF(Assumptions!$D$83=2,'Revenue Forecast'!$BD$34+'Revenue Forecast'!$BE$34,'Revenue Forecast'!$BD$34),Assumptions!$B$67:$C$69,2,TRUE),0) | AO7: =IFNA('Revenue Forecast'!AO6*VLOOKUP(IF(Assumptions!$D$83=2,'Revenue Forecast'!$BE$34+'Revenue Forecast'!$BF$34,'Revenue Forecast'!$BE$34),Assumptions!$B$67:$C$69,2,TRUE),0) | AP7: =IFNA('Revenue Forecast'!AP6*VLOOKUP(IF(Assumptions!$D$83=2,'Revenue Forecast'!$BE$34+'Revenue Forecast'!$BF$34,'Revenue Forecast'!$BE$34),Assumptions!$B$67:$C$69,2,TRUE),0) | AQ7: =IFNA('Revenue Forecast'!AQ6*VLOOKUP(IF(Assumptions!$D$83=2,'Revenue Forecast'!$BE$34+'Revenue Forecast'!$BF$34,'Revenue Forecast'!$BE$34),Assumptions!$B$67:$C$69,2,TRUE),0) | AR7: =IFNA('Revenue Forecast'!AR6*VLOOKUP(IF(Assumptions!$D$83=2,'Revenue Forecast'!$BE$34+'Revenue Forecast'!$BF$34,'Revenue Forecast'!$BE$34),Assumptions!$B$67:$C$69,2,TRUE),0) | AS7: =IFNA('Revenue Forecast'!AS6*VLOOKUP(IF(Assumptions!$D$83=2,'Revenue Forecast'!$BE$34+'Revenue Forecast'!$BF$34,'Revenue Forecast'!$BE$34),Assumptions!$B$67:$C$69,2,TRUE),0) | AT7: =IFNA('Revenue Forecast'!AT6*VLOOKUP(IF(Assumptions!$D$83=2,'Revenue Forecast'!$BE$34+'Revenue Forecast'!$BF$34,'Revenue Forecast'!$BE$34),Assumptions!$B$67:$C$69,2,TRUE),0) | AU7: =IFNA('Revenue Forecast'!AU6*VLOOKUP(IF(Assumptions!$D$83=2,'Revenue Forecast'!$BE$34+'Revenue Forecast'!$BF$34,'Revenue Forecast'!$BE$34),Assumptions!$B$67:$C$69,2,TRUE),0) | AV7: =IFNA('Revenue Forecast'!AV6*VLOOKUP(IF(Assumptions!$D$83=2,'Revenue Forecast'!$BE$34+'Revenue Forecast'!$BF$34,'Revenue Forecast'!$BE$34),Assumptions!$B$67:$C$69,2,TRUE),0) | ... AZ7: =IFNA('Revenue Forecast'!AZ6*VLOOKUP(IF(Assumptions!$D$83=2,'Revenue Forecast'!$BE$34+'Revenue Forecast'!$BF$34,'Revenue Forecast'!$BE$34),Assumptions!$B$67:$C$69,2,TRUE),0) | BC7: =SUM(Q7:AB7) | BD7: =SUM(AC7:AN7) | BE7: =SUM(AO7:AZ7) | BF7: ='Revenue Forecast'!BF6*VLOOKUP(IF(Assumptions!$D$83=2,'Revenue Forecast'!$BF$34+Assumptions!$G$21,'Revenue Forecast'!$BF$34),Assumptions!$B$67:$C$69,2,TRUE) | BH7: units x ketel build cost. the tier basis is set by the switch on Assumptions row 83
B8: Upsell | D8: € | Q8: ='Revenue Forecast'!Q6*SUMPRODUCT(Assumptions!$E$112:$E$114,Assumptions!$G$112:$G$114) | R8: ='Revenue Forecast'!R6*SUMPRODUCT(Assumptions!$E$112:$E$114,Assumptions!$G$112:$G$114) | S8: ='Revenue Forecast'!S6*SUMPRODUCT(Assumptions!$E$112:$E$114,Assumptions!$G$112:$G$114) | T8: ='Revenue Forecast'!T6*SUMPRODUCT(Assumptions!$E$112:$E$114,Assumptions!$G$112:$G$114) | U8: ='Revenue Forecast'!U6*SUMPRODUCT(Assumptions!$E$112:$E$114,Assumptions!$G$112:$G$114) | V8: ='Revenue Forecast'!V6*SUMPRODUCT(Assumptions!$E$112:$E$114,Assumptions!$G$112:$G$114) | W8: ='Revenue Forecast'!W6*SUMPRODUCT(Assumptions!$E$112:$E$114,Assumptions!$G$112:$G$114) | X8: ='Revenue Forecast'!X6*SUMPRODUCT(Assumptions!$E$112:$E$114,Assumptions!$G$112:$G$114) | ... AZ8: ='Revenue Forecast'!AZ6*SUMPRODUCT(Assumptions!$E$112:$E$114,Assumptions!$G$112:$G$114) | BC8: =SUM(Q8:AB8) | BD8: =SUM(AC8:AN8) | BE8: =SUM(AO8:AZ8) | BF8: ='Revenue Forecast'!BF6*SUMPRODUCT(Assumptions!$E$112:$E$114,Assumptions!$G$112:$G$114) | BH8: units x upsell cost (attach % x cost of each item)
B9: Total TTK COGS | D9: € | Q9: =sum(Q7:Q8) | R9: =sum(R7:R8) | S9: =sum(S7:S8) | T9: =sum(T7:T8) | U9: =sum(U7:U8) | V9: =sum(V7:V8) | W9: =sum(W7:W8) | X9: =sum(X7:X8) | ... AZ9: =sum(AZ7:AZ8) | BB9: =SUM(E9:P9) | BC9: =SUM(Q9:AB9) | BD9: =SUM(AC9:AN9) | BE9: =SUM(AO9:AZ9) | BF9: =sum(BF7:BF8) | BH9: machine cost + upsell cost
B11: COMBI+
B12: Combi+ | Q12: =IFNA('Revenue Forecast'!Q12*(VLOOKUP('Revenue Forecast'!$BC$34,Assumptions!$B$67:$C$69,2,TRUE)+VLOOKUP('Revenue Forecast'!$BC$12,Assumptions!$B$78:$C$80,2,TRUE)+Assumptions!$E$74),0) | R12: =IFNA('Revenue Forecast'!R12*(VLOOKUP('Revenue Forecast'!$BC$34,Assumptions!$B$67:$C$69,2,TRUE)+VLOOKUP('Revenue Forecast'!$BC$12,Assumptions!$B$78:$C$80,2,TRUE)+Assumptions!$E$74),0) | S12: =IFNA('Revenue Forecast'!S12*(VLOOKUP('Revenue Forecast'!$BC$34,Assumptions!$B$67:$C$69,2,TRUE)+VLOOKUP('Revenue Forecast'!$BC$12,Assumptions!$B$78:$C$80,2,TRUE)+Assumptions!$E$74),0) | T12: =IFNA('Revenue Forecast'!T12*(VLOOKUP('Revenue Forecast'!$BC$34,Assumptions!$B$67:$C$69,2,TRUE)+VLOOKUP('Revenue Forecast'!$BC$12,Assumptions!$B$78:$C$80,2,TRUE)+Assumptions!$E$74),0) | U12: =IFNA('Revenue Forecast'!U12*(VLOOKUP('Revenue Forecast'!$BC$34,Assumptions!$B$67:$C$69,2,TRUE)+VLOOKUP('Revenue Forecast'!$BC$12,Assumptions!$B$78:$C$80,2,TRUE)+Assumptions!$E$74),0) | V12: =IFNA('Revenue Forecast'!V12*(VLOOKUP('Revenue Forecast'!$BC$34,Assumptions!$B$67:$C$69,2,TRUE)+VLOOKUP('Revenue Forecast'!$BC$12,Assumptions!$B$78:$C$80,2,TRUE)+Assumptions!$E$74),0) | W12: =IFNA('Revenue Forecast'!W12*(VLOOKUP('Revenue Forecast'!$BC$34,Assumptions!$B$67:$C$69,2,TRUE)+VLOOKUP('Revenue Forecast'!$BC$12,Assumptions!$B$78:$C$80,2,TRUE)+Assumptions!$E$74),0) | X12: =IFNA('Revenue Forecast'!X12*(VLOOKUP('Revenue Forecast'!$BC$34,Assumptions!$B$67:$C$69,2,TRUE)+VLOOKUP('Revenue Forecast'!$BC$12,Assumptions!$B$78:$C$80,2,TRUE)+Assumptions!$E$74),0) | ... AB12: =IFNA('Revenue Forecast'!AB12*(VLOOKUP('Revenue Forecast'!$BC$34,Assumptions!$B$67:$C$69,2,TRUE)+VLOOKUP('Revenue Forecast'!$BC$12,Assumptions!$B$78:$C$80,2,TRUE)+Assumptions!$E$74),0) | AC12: =IFNA('Revenue Forecast'!AC12*(VLOOKUP(IF(Assumptions!$D$83=2,'Revenue Forecast'!$BD$34+'Revenue Forecast'!$BE$34,'Revenue Forecast'!$BD$34),Assumptions!$B$67:$C$69,2,TRUE)+VLOOKUP(IF(Assumptions!$D$83=2,'Revenue Forecast'!$BD$12+'Revenue Forecast'!$BE$12,'Revenue Forecast'!$BD$12),Assumptions!$B$78:$C$80,2,TRUE)+Assumptions!$E$74),0) | AD12: =IFNA('Revenue Forecast'!AD12*(VLOOKUP(IF(Assumptions!$D$83=2,'Revenue Forecast'!$BD$34+'Revenue Forecast'!$BE$34,'Revenue Forecast'!$BD$34),Assumptions!$B$67:$C$69,2,TRUE)+VLOOKUP(IF(Assumptions!$D$83=2,'Revenue Forecast'!$BD$12+'Revenue Forecast'!$BE$12,'Revenue Forecast'!$BD$12),Assumptions!$B$78:$C$80,2,TRUE)+Assumptions!$E$74),0) | AE12: =IFNA('Revenue Forecast'!AE12*(VLOOKUP(IF(Assumptions!$D$83=2,'Revenue Forecast'!$BD$34+'Revenue Forecast'!$BE$34,'Revenue Forecast'!$BD$34),Assumptions!$B$67:$C$69,2,TRUE)+VLOOKUP(IF(Assumptions!$D$83=2,'Revenue Forecast'!$BD$12+'Revenue Forecast'!$BE$12,'Revenue Forecast'!$BD$12),Assumptions!$B$78:$C$80,2,TRUE)+Assumptions!$E$74),0) | AF12: =IFNA('Revenue Forecast'!AF12*(VLOOKUP(IF(Assumptions!$D$83=2,'Revenue Forecast'!$BD$34+'Revenue Forecast'!$BE$34,'Revenue Forecast'!$BD$34),Assumptions!$B$67:$C$69,2,TRUE)+VLOOKUP(IF(Assumptions!$D$83=2,'Revenue Forecast'!$BD$12+'Revenue Forecast'!$BE$12,'Revenue Forecast'!$BD$12),Assumptions!$B$78:$C$80,2,TRUE)+Assumptions!$E$74),0) | AG12: =IFNA('Revenue Forecast'!AG12*(VLOOKUP(IF(Assumptions!$D$83=2,'Revenue Forecast'!$BD$34+'Revenue Forecast'!$BE$34,'Revenue Forecast'!$BD$34),Assumptions!$B$67:$C$69,2,TRUE)+VLOOKUP(IF(Assumptions!$D$83=2,'Revenue Forecast'!$BD$12+'Revenue Forecast'!$BE$12,'Revenue Forecast'!$BD$12),Assumptions!$B$78:$C$80,2,TRUE)+Assumptions!$E$74),0) | AH12: =IFNA('Revenue Forecast'!AH12*(VLOOKUP(IF(Assumptions!$D$83=2,'Revenue Forecast'!$BD$34+'Revenue Forecast'!$BE$34,'Revenue Forecast'!$BD$34),Assumptions!$B$67:$C$69,2,TRUE)+VLOOKUP(IF(Assumptions!$D$83=2,'Revenue Forecast'!$BD$12+'Revenue Forecast'!$BE$12,'Revenue Forecast'!$BD$12),Assumptions!$B$78:$C$80,2,TRUE)+Assumptions!$E$74),0) | AI12: =IFNA('Revenue Forecast'!AI12*(VLOOKUP(IF(Assumptions!$D$83=2,'Revenue Forecast'!$BD$34+'Revenue Forecast'!$BE$34,'Revenue Forecast'!$BD$34),Assumptions!$B$67:$C$69,2,TRUE)+VLOOKUP(IF(Assumptions!$D$83=2,'Revenue Forecast'!$BD$12+'Revenue Forecast'!$BE$12,'Revenue Forecast'!$BD$12),Assumptions!$B$78:$C$80,2,TRUE)+Assumptions!$E$74),0) | AJ12: =IFNA('Revenue Forecast'!AJ12*(VLOOKUP(IF(Assumptions!$D$83=2,'Revenue Forecast'!$BD$34+'Revenue Forecast'!$BE$34,'Revenue Forecast'!$BD$34),Assumptions!$B$67:$C$69,2,TRUE)+VLOOKUP(IF(Assumptions!$D$83=2,'Revenue Forecast'!$BD$12+'Revenue Forecast'!$BE$12,'Revenue Forecast'!$BD$12),Assumptions!$B$78:$C$80,2,TRUE)+Assumptions!$E$74),0) | ... AN12: =IFNA('Revenue Forecast'!AN12*(VLOOKUP(IF(Assumptions!$D$83=2,'Revenue Forecast'!$BD$34+'Revenue Forecast'!$BE$34,'Revenue Forecast'!$BD$34),Assumptions!$B$67:$C$69,2,TRUE)+VLOOKUP(IF(Assumptions!$D$83=2,'Revenue Forecast'!$BD$12+'Revenue Forecast'!$BE$12,'Revenue Forecast'!$BD$12),Assumptions!$B$78:$C$80,2,TRUE)+Assumptions!$E$74),0) | AO12: =IFNA('Revenue Forecast'!AO12*(VLOOKUP(IF(Assumptions!$D$83=2,'Revenue Forecast'!$BE$34+'Revenue Forecast'!$BF$34,'Revenue Forecast'!$BE$34),Assumptions!$B$67:$C$69,2,TRUE)+VLOOKUP(IF(Assumptions!$D$83=2,'Revenue Forecast'!$BE$12+'Revenue Forecast'!$BF$12,'Revenue Forecast'!$BE$12),Assumptions!$B$78:$C$80,2,TRUE)+Assumptions!$E$74),0) | AP12: =IFNA('Revenue Forecast'!AP12*(VLOOKUP(IF(Assumptions!$D$83=2,'Revenue Forecast'!$BE$34+'Revenue Forecast'!$BF$34,'Revenue Forecast'!$BE$34),Assumptions!$B$67:$C$69,2,TRUE)+VLOOKUP(IF(Assumptions!$D$83=2,'Revenue Forecast'!$BE$12+'Revenue Forecast'!$BF$12,'Revenue Forecast'!$BE$12),Assumptions!$B$78:$C$80,2,TRUE)+Assumptions!$E$74),0) | AQ12: =IFNA('Revenue Forecast'!AQ12*(VLOOKUP(IF(Assumptions!$D$83=2,'Revenue Forecast'!$BE$34+'Revenue Forecast'!$BF$34,'Revenue Forecast'!$BE$34),Assumptions!$B$67:$C$69,2,TRUE)+VLOOKUP(IF(Assumptions!$D$83=2,'Revenue Forecast'!$BE$12+'Revenue Forecast'!$BF$12,'Revenue Forecast'!$BE$12),Assumptions!$B$78:$C$80,2,TRUE)+Assumptions!$E$74),0) | AR12: =IFNA('Revenue Forecast'!AR12*(VLOOKUP(IF(Assumptions!$D$83=2,'Revenue Forecast'!$BE$34+'Revenue Forecast'!$BF$34,'Revenue Forecast'!$BE$34),Assumptions!$B$67:$C$69,2,TRUE)+VLOOKUP(IF(Assumptions!$D$83=2,'Revenue Forecast'!$BE$12+'Revenue Forecast'!$BF$12,'Revenue Forecast'!$BE$12),Assumptions!$B$78:$C$80,2,TRUE)+Assumptions!$E$74),0) | AS12: =IFNA('Revenue Forecast'!AS12*(VLOOKUP(IF(Assumptions!$D$83=2,'Revenue Forecast'!$BE$34+'Revenue Forecast'!$BF$34,'Revenue Forecast'!$BE$34),Assumptions!$B$67:$C$69,2,TRUE)+VLOOKUP(IF(Assumptions!$D$83=2,'Revenue Forecast'!$BE$12+'Revenue Forecast'!$BF$12,'Revenue Forecast'!$BE$12),Assumptions!$B$78:$C$80,2,TRUE)+Assumptions!$E$74),0) | AT12: =IFNA('Revenue Forecast'!AT12*(VLOOKUP(IF(Assumptions!$D$83=2,'Revenue Forecast'!$BE$34+'Revenue Forecast'!$BF$34,'Revenue Forecast'!$BE$34),Assumptions!$B$67:$C$69,2,TRUE)+VLOOKUP(IF(Assumptions!$D$83=2,'Revenue Forecast'!$BE$12+'Revenue Forecast'!$BF$12,'Revenue Forecast'!$BE$12),Assumptions!$B$78:$C$80,2,TRUE)+Assumptions!$E$74),0) | AU12: =IFNA('Revenue Forecast'!AU12*(VLOOKUP(IF(Assumptions!$D$83=2,'Revenue Forecast'!$BE$34+'Revenue Forecast'!$BF$34,'Revenue Forecast'!$BE$34),Assumptions!$B$67:$C$69,2,TRUE)+VLOOKUP(IF(Assumptions!$D$83=2,'Revenue Forecast'!$BE$12+'Revenue Forecast'!$BF$12,'Revenue Forecast'!$BE$12),Assumptions!$B$78:$C$80,2,TRUE)+Assumptions!$E$74),0) | AV12: =IFNA('Revenue Forecast'!AV12*(VLOOKUP(IF(Assumptions!$D$83=2,'Revenue Forecast'!$BE$34+'Revenue Forecast'!$BF$34,'Revenue Forecast'!$BE$34),Assumptions!$B$67:$C$69,2,TRUE)+VLOOKUP(IF(Assumptions!$D$83=2,'Revenue Forecast'!$BE$12+'Revenue Forecast'!$BF$12,'Revenue Forecast'!$BE$12),Assumptions!$B$78:$C$80,2,TRUE)+Assumptions!$E$74),0) | ... AZ12: =IFNA('Revenue Forecast'!AZ12*(VLOOKUP(IF(Assumptions!$D$83=2,'Revenue Forecast'!$BE$34+'Revenue Forecast'!$BF$34,'Revenue Forecast'!$BE$34),Assumptions!$B$67:$C$69,2,TRUE)+VLOOKUP(IF(Assumptions!$D$83=2,'Revenue Forecast'!$BE$12+'Revenue Forecast'!$BF$12,'Revenue Forecast'!$BE$12),Assumptions!$B$78:$C$80,2,TRUE)+Assumptions!$E$74),0) | BC12: =SUM(Q12:AB12) | BD12: =SUM(AC12:AN12) | BE12: =SUM(AO12:AZ12) | BF12: ='Revenue Forecast'!BF12*(VLOOKUP(IF(Assumptions!$D$83=2,'Revenue Forecast'!$BF$34+Assumptions!$G$21,'Revenue Forecast'!$BF$34),Assumptions!$B$67:$C$69,2,TRUE)+VLOOKUP(IF(Assumptions!$D$83=2,'Revenue Forecast'!$BF$12+Assumptions!$G$24,'Revenue Forecast'!$BF$12),Assumptions!$B$78:$C$80,2,TRUE)+Assumptions!$E$74) | BH12: units x (ketel tier + outdoor unit tier + shipping), ketel tier per the row-83 switch
B13: Upsell | Q13: ='Revenue Forecast'!Q12*SUMPRODUCT(Assumptions!$E$112:$E$114,Assumptions!$G$112:$G$114) | R13: ='Revenue Forecast'!R12*SUMPRODUCT(Assumptions!$E$112:$E$114,Assumptions!$G$112:$G$114) | S13: ='Revenue Forecast'!S12*SUMPRODUCT(Assumptions!$E$112:$E$114,Assumptions!$G$112:$G$114) | T13: ='Revenue Forecast'!T12*SUMPRODUCT(Assumptions!$E$112:$E$114,Assumptions!$G$112:$G$114) | U13: ='Revenue Forecast'!U12*SUMPRODUCT(Assumptions!$E$112:$E$114,Assumptions!$G$112:$G$114) | V13: ='Revenue Forecast'!V12*SUMPRODUCT(Assumptions!$E$112:$E$114,Assumptions!$G$112:$G$114) | W13: ='Revenue Forecast'!W12*SUMPRODUCT(Assumptions!$E$112:$E$114,Assumptions!$G$112:$G$114) | X13: ='Revenue Forecast'!X12*SUMPRODUCT(Assumptions!$E$112:$E$114,Assumptions!$G$112:$G$114) | ... AZ13: ='Revenue Forecast'!AZ12*SUMPRODUCT(Assumptions!$E$112:$E$114,Assumptions!$G$112:$G$114) | BC13: =SUM(Q13:AB13) | BD13: =SUM(AC13:AN13) | BE13: =SUM(AO13:AZ13) | BF13: ='Revenue Forecast'!BF12*SUMPRODUCT(Assumptions!$E$112:$E$114,Assumptions!$G$112:$G$114) | BH13: units x upsell cost
B14: Total Combi+ COGS | Q14: =sum(Q12:Q13) | R14: =sum(R12:R13) | S14: =sum(S12:S13) | T14: =sum(T12:T13) | U14: =sum(U12:U13) | V14: =sum(V12:V13) | W14: =sum(W12:W13) | X14: =sum(X12:X13) | ... AZ14: =sum(AZ12:AZ13) | BC14: =sum(BC12:BC13) | BD14: =sum(BD12:BD13) | BE14: =sum(BE12:BE13) | BF14: =sum(BF12:BF13) | BH14: machine cost + upsell cost
B16: INSTALLATION
B17: Installation COGS (pass-through, = installation revenue) | D17: € | Q17: ='Revenue Forecast'!Q19 | R17: ='Revenue Forecast'!R19 | S17: ='Revenue Forecast'!S19 | T17: ='Revenue Forecast'!T19 | U17: ='Revenue Forecast'!U19 | V17: ='Revenue Forecast'!V19 | W17: ='Revenue Forecast'!W19 | X17: ='Revenue Forecast'!X19 | ... AZ17: ='Revenue Forecast'!AZ19 | BB17: ='Revenue Forecast'!BB19 | BC17: ='Revenue Forecast'!BC19 | BD17: ='Revenue Forecast'!BD19 | BE17: ='Revenue Forecast'!BE19 | BF17: ='Revenue Forecast'!BF19 | BH17: same number as installation revenue. pass-through, zero margin
B19: SERVICE REVENUES
B20: Total Service Revenue | D20: € | Q20: ='Revenue Forecast'!Q34*SUMPRODUCT(Assumptions!$E$120:$E$121,Assumptions!$G$120:$G$121)+E20 | R20: ='Revenue Forecast'!R34*SUMPRODUCT(Assumptions!$E$120:$E$121,Assumptions!$G$120:$G$121)+F20 | S20: ='Revenue Forecast'!S34*SUMPRODUCT(Assumptions!$E$120:$E$121,Assumptions!$G$120:$G$121)+G20 | T20: ='Revenue Forecast'!T34*SUMPRODUCT(Assumptions!$E$120:$E$121,Assumptions!$G$120:$G$121)+H20 | U20: ='Revenue Forecast'!U34*SUMPRODUCT(Assumptions!$E$120:$E$121,Assumptions!$G$120:$G$121)+I20 | V20: ='Revenue Forecast'!V34*SUMPRODUCT(Assumptions!$E$120:$E$121,Assumptions!$G$120:$G$121)+J20 | W20: ='Revenue Forecast'!W34*SUMPRODUCT(Assumptions!$E$120:$E$121,Assumptions!$G$120:$G$121)+K20 | X20: ='Revenue Forecast'!X34*SUMPRODUCT(Assumptions!$E$120:$E$121,Assumptions!$G$120:$G$121)+L20 | ... AZ20: ='Revenue Forecast'!AZ34*SUMPRODUCT(Assumptions!$E$120:$E$121,Assumptions!$G$120:$G$121)+AN20 | BB20: =SUM(E20:P20) | BC20: =SUM(Q20:AB20) | BD20: =sum(AC20:AN20) | BE20: =sum(AO20:AZ20)+BD20 | BF20: ='Revenue Forecast'!BF34*SUMPRODUCT(Assumptions!$E$120:$E$121,Assumptions!$G$120:$G$121)+BE20 | BH20: units x cost per service contract + last year's, stacks like the revenue
B22: TOTAL COGS | M22: =M7 | N22: =N9+N17+N20 | O22: =O9+O17+O20 | P22: =P9+P17+P20 | Q22: =Q9+Q14+Q17+Q20 | R22: =R9+R14+R17+R20 | S22: =S9+S14+S17+S20 | T22: =T9+T14+T17+T20 | U22: =U9+U14+U17+U20 | V22: =V9+V14+V17+V20 | W22: =W9+W14+W17+W20 | X22: =X9+X14+X17+X20 | ... AZ22: =AZ9+AZ14+AZ17+AZ20 | BB22: =BB9+BB14+BB17+BB20 | BC22: =BC9+BC14+BC17+BC20 | BD22: =BD9+BD14+BD17+BD20 | BE22: =BE9+BE14+BE17+BE20 | BF22: =BF9+BF14+BF17+BF20 | BH22: TTK + Combi+ + installation + service costs

Sheet OPEX
B1: Tarnoc B.V. — OPEX Forecast (€, negative = cost) | U1: Actual | V1: Projected
G2: 2025 | S2: 2026 | AE2: 2027 | AQ2: 2028
G3: 45658 | H3: 45689 | I3: 45717 | J3: 45748 | K3: 45778 | L3: 45809 | M3: 45839 | N3: 45870 | O3: 45901 | P3: 45931 | Q3: 45962 | R3: 45992 | S3: 46023 | T3: 46054 | U3: 46082 | V3: 46113 | W3: 46143 | X3: 46174 | Y3: 46204 | Z3: 46235 | AA3: 46266 | AB3: 46296 | AC3: 46327 | AD3: 46357 | AE3: 46388 | AF3: 46419 | AG3: 46447 | AH3: 46478 | AI3: 46508 | AJ3: 46539 | AK3: 46569 | AL3: 46600 | AM3: 46631 | AN3: 46661 | AO3: 46692 | AP3: 46722 | AQ3: 46753 | AR3: 46784 | AS3: 46813 | AT3: 46844 | AU3: 46874 | AV3: 46905 | AW3: 46935 | AX3: 46966 | AY3: 46997 | AZ3: 47027 | BA3: 47058 | BB3: 47088 | BD3: 2025 | BE3: 2026 | BF3: 2027 | BG3: 2028 | BH3: 2029 | BK3: what this row does
B5: PERSONNEL
B6: R&D | D6: € | O6: =Personnel!Q62 | P6: =Personnel!R62 | Q6: =Personnel!S62 | R6: =Personnel!T62 | S6: =Personnel!U62 | T6: =Personnel!V62 | U6: =Personnel!W62 | V6: =Personnel!X62 | ... BB6: =Personnel!BD62 | BD6: =SUM(G6:R6) | BE6: =SUM(S6:AD6) | BF6: =SUM(AE6:AP6) | BG6: =SUM(AQ6:BB6) | BH6: =sum(Personnel!BE62:BP62) | BI6: =BH6*('Financial Statements'!$BE$7/'Financial Statements'!$BD$7)^0.5 | BK6: R&D salary bill, pulled from the Personnel tab
B7: S&M | D7: € | O7: =Personnel!Q63 | P7: =Personnel!R63 | Q7: =Personnel!S63 | R7: =Personnel!T63 | S7: =Personnel!U63 | T7: =Personnel!V63 | U7: =Personnel!W63 | V7: =Personnel!X63 | ... BB7: =Personnel!BD63 | BD7: =SUM(G7:R7) | BE7: =SUM(S7:AD7) | BF7: =SUM(AE7:AP7) | BG7: =SUM(AQ7:BB7) | BH7: =sum(Personnel!BE63:BP63) | BI7: =BH7*('Financial Statements'!$BE$7/'Financial Statements'!$BD$7)^0.5 | BK7: S&M salary bill, pulled from Personnel
B8: G&A | D8: € | O8: =Personnel!Q64 | P8: =Personnel!R64 | Q8: =Personnel!S64 | R8: =Personnel!T64 | S8: =Personnel!U64 | T8: =Personnel!V64 | U8: =Personnel!W64 | V8: =Personnel!X64 | ... BB8: =Personnel!BD64 | BD8: =SUM(G8:R8) | BE8: =SUM(S8:AD8) | BF8: =SUM(AE8:AP8) | BG8: =SUM(AQ8:BB8) | BH8: =sum(Personnel!BE64:BP64) | BI8: =BH8*('Financial Statements'!$BE$7/'Financial Statements'!$BD$7)^0.2 | BK8: G&A salary bill, pulled from Personnel
B9: Total Personnel | D9: € | G9: =SUM(G6:G8) | H9: =SUM(H6:H8) | I9: =SUM(I6:I8) | J9: =SUM(J6:J8) | K9: =SUM(K6:K8) | L9: =SUM(L6:L8) | M9: =SUM(M6:M8) | N9: =SUM(N6:N8) | O9: =sum(O6:O8) | P9: =sum(P6:P8) | Q9: =sum(Q6:Q8) | R9: =sum(R6:R8) | S9: =sum(S6:S8) | T9: =sum(T6:T8) | U9: =sum(U6:U8) | V9: =sum(V6:V8) | ... BB9: =sum(BB6:BB8) | BD9: =SUM(G9:R9) | BE9: =SUM(S9:AD9) | BF9: =SUM(AE9:AP9) | BG9: =SUM(AQ9:BB9) | BH9: =sum(BH6:BH8) | BK9: the three salary lines added
B11: NON-PERSONNEL
B13: R&D COSTS
B14: Kicker Development Cost | D14: € | R14: =Assumptions!E94 | BD14: =SUM(G14:R14) | BE14: =SUM(S14:AD14) | BF14: =SUM(AE14:AP14) | BG14: =SUM(AQ14:BB14) | BH14: 0 | BK14: one-off from Assumptions, booked in its month
B15: Ongoing Development costs | D15: € | S15: {=INDEX(Assumptions!$E$92:$I$92,MATCH(YEAR(S$3),Assumptions!$E$87:$I$87,0))} | T15: {=INDEX(Assumptions!$E$92:$I$92,MATCH(YEAR(T$3),Assumptions!$E$87:$I$87,0))} | U15: {=INDEX(Assumptions!$E$92:$I$92,MATCH(YEAR(U$3),Assumptions!$E$87:$I$87,0))} | V15: {=INDEX(Assumptions!$E$92:$I$92,MATCH(YEAR(V$3),Assumptions!$E$87:$I$87,0))} | W15: {=INDEX(Assumptions!$E$92:$I$92,MATCH(YEAR(W$3),Assumptions!$E$87:$I$87,0))} | X15: {=INDEX(Assumptions!$E$92:$I$92,MATCH(YEAR(X$3),Assumptions!$E$87:$I$87,0))} | Y15: {=INDEX(Assumptions!$E$92:$I$92,MATCH(YEAR(Y$3),Assumptions!$E$87:$I$87,0))} | Z15: {=INDEX(Assumptions!$E$92:$I$92,MATCH(YEAR(Z$3),Assumptions!$E$87:$I$87,0))} | ... BB15: {=INDEX(Assumptions!$E$92:$I$92,MATCH(YEAR(BB$3),Assumptions!$E$87:$I$87,0))} | BD15: =SUM(G15:R15) | BE15: =SUM(S15:AD15) | BF15: =SUM(AE15:AP15) | BG15: =SUM(AQ15:BB15) | BH15: =BG15*('Financial Statements'!$BE$7/'Financial Statements'!$BD$7)^0.4 | BK15: from Assumptions; 2029 scaled off 2028 by revenue growth
B16: Assembly partner | D16: € | AB16: =Assumptions!E97 | BD16: =SUM(G16:R16) | BE16: =SUM(S16:AC16) | BF16: =SUM(AE16:AP16) | BG16: =SUM(AQ16:BB16) | BH16: 0 | BK16: one-off from Assumptions, booked in its month
B17: Third party cost product development | D17: € | S17: {=INDEX(Assumptions!$E$93:$I$93,MATCH(YEAR(S$3),Assumptions!$E$87:$I$87,0))} | T17: {=INDEX(Assumptions!$E$93:$I$93,MATCH(YEAR(T$3),Assumptions!$E$87:$I$87,0))} | U17: {=INDEX(Assumptions!$E$93:$I$93,MATCH(YEAR(U$3),Assumptions!$E$87:$I$87,0))} | V17: {=INDEX(Assumptions!$E$93:$I$93,MATCH(YEAR(V$3),Assumptions!$E$87:$I$87,0))} | W17: {=INDEX(Assumptions!$E$93:$I$93,MATCH(YEAR(W$3),Assumptions!$E$87:$I$87,0))} | X17: {=INDEX(Assumptions!$E$93:$I$93,MATCH(YEAR(X$3),Assumptions!$E$87:$I$87,0))} | Y17: {=INDEX(Assumptions!$E$93:$I$93,MATCH(YEAR(Y$3),Assumptions!$E$87:$I$87,0))} | Z17: {=INDEX(Assumptions!$E$93:$I$93,MATCH(YEAR(Z$3),Assumptions!$E$87:$I$87,0))} | ... BB17: {=INDEX(Assumptions!$E$93:$I$93,MATCH(YEAR(BB$3),Assumptions!$E$87:$I$87,0))} | BD17: =SUM(G17:R17) | BE17: =SUM(S17:AD17) | BF17: =SUM(AE17:AP17) | BG17: =SUM(AQ17:BB17) | BH17: =BG17*('Financial Statements'!$BE$7/'Financial Statements'!$BD$7)^0.4 | BK17: from Assumptions; 2029 scaled off 2028 by revenue growth
B18: Tooling Fisher (result: 2%-3%) | D18: € | AC18: =Assumptions!E98 | BD18: =SUM(G18:R18) | BE18: =SUM(S18:AC18) | BF18: =SUM(AE18:AP18) | BG18: =SUM(AQ18:BB18) | BH18: 0 | BK18: one-off from Assumptions, booked in its month
B19: Total R&D | R19: =R14+R15+R16 | S19: =sum(S14:S18) | T19: =sum(T14:T18) | U19: =sum(U14:U18) | V19: =sum(V14:V18) | W19: =sum(W14:W18) | X19: =sum(X14:X18) | Y19: =sum(Y14:Y18) | Z19: =sum(Z14:Z18) | ... BB19: =sum(BB14:BB18) | BD19: =SUM(G19:R19) | BE19: =SUM(S19:AD19) | BF19: =SUM(AE19:AP19) | BG19: =SUM(AQ19:BB19) | BH19: =sum(BH14:BH18) | BK19: all the non-people R&D lines added
BE20: =BE19/BD19-1 | BF20: =BF19/BE19-1 | BG20: =BG19/BF19-1 | BH20: =BH19/BG19-1 | BK20: year-on-year change in R&D spend
B21: SALES & MARKETING
B22: Baseline Sales & Marketting | S22: {=INDEX(Assumptions!$E$90:$I$90,MATCH(YEAR(S$3),Assumptions!$E$87:$I$87,0))} | T22: {=INDEX(Assumptions!$E$90:$I$90,MATCH(YEAR(T$3),Assumptions!$E$87:$I$87,0))} | U22: {=INDEX(Assumptions!$E$90:$I$90,MATCH(YEAR(U$3),Assumptions!$E$87:$I$87,0))} | V22: {=INDEX(Assumptions!$E$90:$I$90,MATCH(YEAR(V$3),Assumptions!$E$87:$I$87,0))} | W22: {=INDEX(Assumptions!$E$90:$I$90,MATCH(YEAR(W$3),Assumptions!$E$87:$I$87,0))} | X22: {=INDEX(Assumptions!$E$90:$I$90,MATCH(YEAR(X$3),Assumptions!$E$87:$I$87,0))} | Y22: {=INDEX(Assumptions!$E$90:$I$90,MATCH(YEAR(Y$3),Assumptions!$E$87:$I$87,0))} | Z22: {=INDEX(Assumptions!$E$90:$I$90,MATCH(YEAR(Z$3),Assumptions!$E$87:$I$87,0))} | ... BB22: {=INDEX(Assumptions!$E$90:$I$90,MATCH(YEAR(BB$3),Assumptions!$E$87:$I$87,0))} | BD22: =SUM(G22:R22) | BE22: =SUM(S22:AD22) | BF22: =SUM(AE22:AP22) | BG22: =SUM(AQ22:BB22) | BH22: =BG22*('Financial Statements'!$BE$7/'Financial Statements'!$BD$7)^0.5 | BK22: baseline marketing from Assumptions; 2029 scaled off revenue growth
B23: Sales & Marketing (3rd party) | D23: € | S23: 7000 | T23: 7000 | U23: 7000 | V23: 7000 | W23: 7000 | X23: 7000 | Y23: 7000 | Z23: 7000 | AA23: 7000 | AB23: 10000 | AC23: 10000 | AD23: 10000 | AE23: =('Revenue Forecast'!AC6+'Revenue Forecast'!AC12)*VLOOKUP('Revenue Forecast'!AC33,Assumptions!$G$102:$H$109,2,TRUE) | AF23: =('Revenue Forecast'!AD6+'Revenue Forecast'!AD12)*VLOOKUP('Revenue Forecast'!AD33,Assumptions!$G$102:$H$109,2,TRUE) | AG23: =('Revenue Forecast'!AE6+'Revenue Forecast'!AE12)*VLOOKUP('Revenue Forecast'!AE33,Assumptions!$G$102:$H$109,2,TRUE) | AH23: =('Revenue Forecast'!AF6+'Revenue Forecast'!AF12)*VLOOKUP('Revenue Forecast'!AF33,Assumptions!$G$102:$H$109,2,TRUE) | AI23: =('Revenue Forecast'!AG6+'Revenue Forecast'!AG12)*VLOOKUP('Revenue Forecast'!AG33,Assumptions!$G$102:$H$109,2,TRUE) | AJ23: =('Revenue Forecast'!AH6+'Revenue Forecast'!AH12)*VLOOKUP('Revenue Forecast'!AH33,Assumptions!$G$102:$H$109,2,TRUE) | AK23: =('Revenue Forecast'!AI6+'Revenue Forecast'!AI12)*VLOOKUP('Revenue Forecast'!AI33,Assumptions!$G$102:$H$109,2,TRUE) | AL23: =('Revenue Forecast'!AJ6+'Revenue Forecast'!AJ12)*VLOOKUP('Revenue Forecast'!AJ33,Assumptions!$G$102:$H$109,2,TRUE) | ... BB23: =('Revenue Forecast'!AZ6+'Revenue Forecast'!AZ12)*VLOOKUP('Revenue Forecast'!AZ33,Assumptions!$G$102:$H$109,2,TRUE) | BD23: =SUM(G23:R23) | BE23: =SUM(S23:AD23) | BF23: =SUM(AE23:AP23) | BG23: =SUM(AQ23:BB23) | BH23: =('Revenue Forecast'!BF6+'Revenue Forecast'!BF12)*VLOOKUP('Revenue Forecast'!BF33,Assumptions!$G$102:$H$109,2,TRUE) | BK23: units sold x sales cost per unit, which falls as volume grows
B24: Customer journey (third party) | D24: € | R24: =Assumptions!$E$95 | X24: =Assumptions!E95 | BD24: =SUM(G24:R24) | BE24: =SUM(T24:AC24) | BF24: =SUM(AE24:AP24) | BG24: =SUM(AQ24:BB24) | BH24: =BG24*('Financial Statements'!$BE$7/'Financial Statements'!$BD$7)^0.5 | BK24: one-off from Assumptions; 2029 scaled off revenue growth
B25: Branding + Website (third party cost) | D25: € | R25: =Assumptions!$E$96 | W25: =Assumptions!E96 | BD25: =SUM(G25:R25) | BE25: =SUM(S25:AH25) | BF25: =SUM(AE25:AP25) | BG25: =SUM(AQ25:BB25) | BH25: =BG25*('Financial Statements'!$BE$7/'Financial Statements'!$BD$7)^0.5 | BK25: one-off from Assumptions; 2029 scaled off revenue growth
B26: Total S&M | G26: =SUM(G23:G25) | H26: =SUM(H23:H25) | I26: =SUM(I23:I25) | J26: =SUM(J23:J25) | K26: =SUM(K23:K25) | L26: =SUM(L23:L25) | M26: =SUM(M23:M25) | N26: =SUM(N23:N25) | ... R26: =SUM(R23:R25) | S26: =sum(S22:S25) | T26: =sum(T22:T25) | U26: =sum(U22:U25) | V26: =sum(V22:V25) | W26: =sum(W22:W25) | X26: =sum(X22:X25) | Y26: =sum(Y22:Y25) | Z26: =sum(Z22:Z25) | ... BB26: =sum(BB22:BB25) | BD26: =SUM(G26:R26) | BE26: =SUM(S26:AD26) | BF26: =SUM(AE26:AP26) | BG26: =SUM(AQ26:BB26) | BH26: =sum(BH22:BH25) | BK26: all the non-people sales & marketing lines added
BE27: =BE26/BD26-1 | BF27: =BF26/BE26-1 | BG27: =BG26/BF26-1 | BH27: =BH26/BG26-1 | BK27: year-on-year change in S&M spend
B28: G&A (NON-LABOUR)
B29: Office rent (part of General) | D29: € | G29: =Assumptions!$E$88 | H29: =Assumptions!$E$88 | I29: =Assumptions!$E$88 | J29: =Assumptions!$E$88 | K29: =Assumptions!$E$88 | L29: =Assumptions!$E$88 | M29: =Assumptions!$E$88 | N29: =Assumptions!$E$88 | ... R29: =Assumptions!$E$88 | S29: {=INDEX(Assumptions!$E$88:$I$88,MATCH(YEAR(S$3),Assumptions!$E$87:$I$87,0))} | T29: {=INDEX(Assumptions!$E$88:$I$88,MATCH(YEAR(T$3),Assumptions!$E$87:$I$87,0))} | U29: {=INDEX(Assumptions!$E$88:$I$88,MATCH(YEAR(U$3),Assumptions!$E$87:$I$87,0))} | V29: {=INDEX(Assumptions!$E$88:$I$88,MATCH(YEAR(V$3),Assumptions!$E$87:$I$87,0))} | W29: {=INDEX(Assumptions!$E$88:$I$88,MATCH(YEAR(W$3),Assumptions!$E$87:$I$87,0))} | X29: {=INDEX(Assumptions!$E$88:$I$88,MATCH(YEAR(X$3),Assumptions!$E$87:$I$87,0))} | Y29: {=INDEX(Assumptions!$E$88:$I$88,MATCH(YEAR(Y$3),Assumptions!$E$87:$I$87,0))} | Z29: {=INDEX(Assumptions!$E$88:$I$88,MATCH(YEAR(Z$3),Assumptions!$E$87:$I$87,0))} | ... BB29: {=INDEX(Assumptions!$E$88:$I$88,MATCH(YEAR(BB$3),Assumptions!$E$87:$I$87,0))} | BD29: =SUM(G29:R29) | BE29: =SUM(S29:AD29) | BF29: =SUM(AE29:AP29) | BG29: =SUM(AQ29:BB29) | BH29: =BG29*('Financial Statements'!$BE$7/'Financial Statements'!$BD$7)^0.2 | BK29: rent from Assumptions, growing each year
B30: Other General | D30: € | G30: =Assumptions!$E$89 | H30: =Assumptions!$E$89 | I30: =Assumptions!$E$89 | J30: =Assumptions!$E$89 | K30: =Assumptions!$E$89 | L30: =Assumptions!$E$89 | M30: =Assumptions!$E$89 | N30: =Assumptions!$E$89 | ... R30: =Assumptions!$E$89 | S30: {=INDEX(Assumptions!$E$89:$I$89,MATCH(YEAR(S$3),Assumptions!$E$87:$I$87,0))} | T30: {=INDEX(Assumptions!$E$89:$I$89,MATCH(YEAR(T$3),Assumptions!$E$87:$I$87,0))} | U30: {=INDEX(Assumptions!$E$89:$I$89,MATCH(YEAR(U$3),Assumptions!$E$87:$I$87,0))} | V30: {=INDEX(Assumptions!$E$89:$I$89,MATCH(YEAR(V$3),Assumptions!$E$87:$I$87,0))} | W30: {=INDEX(Assumptions!$E$89:$I$89,MATCH(YEAR(W$3),Assumptions!$E$87:$I$87,0))} | X30: {=INDEX(Assumptions!$E$89:$I$89,MATCH(YEAR(X$3),Assumptions!$E$87:$I$87,0))} | Y30: {=INDEX(Assumptions!$E$89:$I$89,MATCH(YEAR(Y$3),Assumptions!$E$87:$I$87,0))} | Z30: {=INDEX(Assumptions!$E$89:$I$89,MATCH(YEAR(Z$3),Assumptions!$E$87:$I$87,0))} | ... BB30: {=INDEX(Assumptions!$E$89:$I$89,MATCH(YEAR(BB$3),Assumptions!$E$87:$I$87,0))} | BD30: =SUM(G30:R30) | BE30: =SUM(S30:AD30) | BF30: =SUM(AE30:AP30) | BG30: =SUM(AQ30:BB30) | BH30: =BG30*('Financial Statements'!$BE$7/'Financial Statements'!$BD$7)^0.2 | BK30: other general costs from Assumptions, growing each year
B31: Finance & Legal etc. | D31: € | G31: =Assumptions!$E$91 | H31: =Assumptions!$E$91 | I31: =Assumptions!$E$91 | J31: =Assumptions!$E$91 | K31: =Assumptions!$E$91 | L31: =Assumptions!$E$91 | M31: =Assumptions!$E$91 | N31: =Assumptions!$E$91 | ... R31: =Assumptions!$E$91 | S31: {=INDEX(Assumptions!$E$91:$I$91,MATCH(YEAR(S$3),Assumptions!$E$87:$I$87,0))} | T31: {=INDEX(Assumptions!$E$91:$I$91,MATCH(YEAR(T$3),Assumptions!$E$87:$I$87,0))} | U31: {=INDEX(Assumptions!$E$91:$I$91,MATCH(YEAR(U$3),Assumptions!$E$87:$I$87,0))} | V31: {=INDEX(Assumptions!$E$91:$I$91,MATCH(YEAR(V$3),Assumptions!$E$87:$I$87,0))} | W31: {=INDEX(Assumptions!$E$91:$I$91,MATCH(YEAR(W$3),Assumptions!$E$87:$I$87,0))} | X31: {=INDEX(Assumptions!$E$91:$I$91,MATCH(YEAR(X$3),Assumptions!$E$87:$I$87,0))} | Y31: {=INDEX(Assumptions!$E$91:$I$91,MATCH(YEAR(Y$3),Assumptions!$E$87:$I$87,0))} | Z31: {=INDEX(Assumptions!$E$91:$I$91,MATCH(YEAR(Z$3),Assumptions!$E$87:$I$87,0))} | ... BB31: {=INDEX(Assumptions!$E$91:$I$91,MATCH(YEAR(BB$3),Assumptions!$E$87:$I$87,0))} | BD31: =SUM(G31:R31) | BE31: =SUM(S31:AD31) | BF31: =SUM(AE31:AP31) | BG31: =SUM(AQ31:BB31) | BH31: =BG31*('Financial Statements'!$BE$7/'Financial Statements'!$BD$7)^0.2 | BK31: finance & legal from Assumptions, growing each year
B32: Total G&A | S32: =sum(S29:S31) | T32: =sum(T29:T31) | U32: =sum(U29:U31) | V32: =sum(V29:V31) | W32: =sum(W29:W31) | X32: =sum(X29:X31) | Y32: =sum(Y29:Y31) | Z32: =sum(Z29:Z31) | ... BB32: =sum(BB29:BB31) | BD32: =SUM(G32:R32) | BE32: =SUM(S32:AD32) | BF32: =SUM(AE32:AP32) | BG32: =SUM(AQ32:BB32) | BH32: =sum(BH29:BH31) | BK32: the three G&A lines added
B34: Total non-personnell | D34: € | G34: =G32+G26+G19 | H34: =H32+H26+H19 | I34: =I32+I26+I19 | J34: =J32+J26+J19 | K34: =K32+K26+K19 | L34: =L32+L26+L19 | M34: =M32+M26+M19 | N34: =N32+N26+N19 | ... BB34: =BB32+BB26+BB19 | BD34: =SUM(G34:R34) | BE34: =SUM(S34:AD34) | BF34: =SUM(AE34:AP34) | BG34: =SUM(AQ34:BB34) | BH34: =BH32+BH26+BH19 | BK34: R&D + S&M + G&A, everything except salaries
B36: TOTAL OPEX | D36: € | G36: =G34+G9 | H36: =H34+H9 | I36: =I34+I9 | J36: =J34+J9 | K36: =K34+K9 | L36: =L34+L9 | M36: =M34+M9 | N36: =N34+N9 | ... BB36: =BB34+BB9 | BD36: =SUM(G36:R36) | BE36: =SUM(S36:AD36) | BF36: =SUM(AE36:AP36) | BG36: =SUM(AQ36:BB36) | BH36: =BH34+BH9 | BK36: salaries + all other operating costs
B38: Total R&D | D38: € | G38: =G19+G6 | H38: =H19+H6 | I38: =I19+I6 | J38: =J19+J6 | K38: =K19+K6 | L38: =L19+L6 | M38: =M19+M6 | N38: =N19+N6 | ... BB38: =BB19+BB6 | BD38: =BD19+BD6 | BE38: =BE19+BE6 | BF38: =BF19+BF6 | BG38: =BG19+BG6 | BH38: =BH19+BH6 | BK38: R&D people + R&D other. this is the line the P&L reads
B39: Total S&M | D39: € | G39: =G26+G7 | H39: =H26+H7 | I39: =I26+I7 | J39: =J26+J7 | K39: =K26+K7 | L39: =L26+L7 | M39: =M26+M7 | N39: =N26+N7 | ... BB39: =BB26+BB7 | BD39: =BD26+BD7 | BE39: =BE26+BE7 | BF39: =BF26+BF7 | BG39: =BG26+BG7 | BH39: =BH26+BH7 | BK39: S&M people + S&M other. this is the line the P&L reads
B40: Total G&A | D40: € | G40: =G32+G8 | H40: =H32+H8 | I40: =I32+I8 | J40: =J32+J8 | K40: =K32+K8 | L40: =L32+L8 | M40: =M32+M8 | N40: =N32+N8 | ... BB40: =BB32+BB8 | BD40: =BD32+BD8 | BE40: =BE32+BE8 | BF40: =BF32+BF8 | BG40: =BG32+BG8 | BH40: =BH32+BH8 | BK40: G&A people + G&A other. this is the line the P&L reads
B41: R&D % of Total OPEX | S41: =S38/S$36 | T41: =T38/T$36 | U41: =U38/U$36 | V41: =V38/V$36 | W41: =W38/W$36 | X41: =X38/X$36 | Y41: =Y38/Y$36 | Z41: =Z38/Z$36 | ... BB41: =BB38/BB$36 | BD41: =BD38/BD$36 | BE41: =BE38/BE$36 | BF41: =BF38/BF$36 | BG41: =BG38/BG$36 | BH41: =BH38/BH$36 | BK41: R&D share of total operating costs
B42: S&M % of Total OPEX | S42: =S39/S$36 | T42: =T39/T$36 | U42: =U39/U$36 | V42: =V39/V$36 | W42: =W39/W$36 | X42: =X39/X$36 | Y42: =Y39/Y$36 | Z42: =Z39/Z$36 | ... BB42: =BB39/BB$36 | BD42: =BD39/BD$36 | BE42: =BE39/BE$36 | BF42: =BF39/BF$36 | BG42: =BG39/BG$36 | BH42: =BH39/BH$36 | BK42: S&M share of total operating costs
B43: G&A % of Total OPEX | S43: =S40/S$36 | T43: =T40/T$36 | U43: =U40/U$36 | V43: =V40/V$36 | W43: =W40/W$36 | X43: =X40/X$36 | Y43: =Y40/Y$36 | Z43: =Z40/Z$36 | ... BB43: =BB40/BB$36 | BD43: =BD40/BD$36 | BE43: =BE40/BE$36 | BF43: =BF40/BF$36 | BG43: =BG40/BG$36 | BH43: =BH40/BH$36 | BK43: G&A share of total operating costs

Sheet Personnel
B1: PERSONNEL — Monthly Employer Cost (€)
A2: # | B2: Name | C2: Dept | D2: Role | E2: Type | F2: Start | G2: End | H2: Monthly Cost (€) | I2: 45658 | J2: 45689 | K2: 45717 | L2: 45748 | M2: 45778 | N2: 45809 | O2: 45839 | P2: 45870 | Q2: 45901 | R2: 45931 | S2: 45962 | T2: 45992 | U2: 46023 | V2: 46054 | W2: 46082 | X2: 46113 | Y2: 46143 | Z2: 46174 | AA2: 46204 | AB2: 46235 | AC2: 46266 | AD2: 46296 | AE2: 46327 | AF2: 46357 | AG2: 46388 | AH2: 46419 | AI2: 46447 | AJ2: 46478 | AK2: 46508 | AL2: 46539 | AM2: 46569 | AN2: 46600 | AO2: 46631 | AP2: 46661 | AQ2: 46692 | AR2: 46722 | AS2: 46753 | AT2: 46784 | AU2: 46813 | AV2: 46844 | AW2: 46874 | AX2: 46905 | AY2: 46935 | AZ2: 46966 | BA2: 46997 | BB2: 47027 | BC2: 47058 | BD2: 47088 | BE2: 47119 | BF2: 47150 | BG2: 47178 | BH2: 47209 | BI2: 47239 | BJ2: 47270 | BK2: 47300 | BL2: 47331 | BM2: 47362 | BN2: 47392 | BO2: 47423 | BP2: 47453 | BR2: what this row does
A3: 1 | B3: R&D Engineer | C3: R&D | D3: Field Engineer | E3: Current | F3: 45901 | H3: 5500 | I3: =IF(AND(F3<=DATE(2025,1,1),OR(G3="",G3>=DATE(2025,1,1))),H3*(1+Assumptions!$C$7)^0,0) | J3: =IF(AND(F3<=DATE(2025,2,1),OR(G3="",G3>=DATE(2025,2,1))),H3*(1+Assumptions!$C$7)^0,0) | K3: =IF(AND(F3<=DATE(2025,3,1),OR(G3="",G3>=DATE(2025,3,1))),H3*(1+Assumptions!$C$7)^0,0) | L3: =IF(AND(F3<=DATE(2025,4,1),OR(G3="",G3>=DATE(2025,4,1))),H3*(1+Assumptions!$C$7)^0,0) | M3: =IF(AND(F3<=DATE(2025,5,1),OR(G3="",G3>=DATE(2025,5,1))),H3*(1+Assumptions!$C$7)^0,0) | N3: =IF(AND(F3<=DATE(2025,6,1),OR(G3="",G3>=DATE(2025,6,1))),H3*(1+Assumptions!$C$7)^0,0) | O3: =IF(AND(F3<=DATE(2025,7,1),OR(G3="",G3>=DATE(2025,7,1))),H3*(1+Assumptions!$C$7)^0,0) | P3: =IF(AND(F3<=DATE(2025,8,1),OR(G3="",G3>=DATE(2025,8,1))),H3*(1+Assumptions!$C$7)^0,0) | Q3: =IF(AND(F3<=DATE(2025,9,1),OR(G3="",G3>=DATE(2025,9,1))),H3*(1+Assumptions!$C$7)^0,0) | R3: =IF(AND(F3<=DATE(2025,10,1),OR(G3="",G3>=DATE(2025,10,1))),H3*(1+Assumptions!$C$7)^0,0) | S3: =IF(AND(F3<=DATE(2025,11,1),OR(G3="",G3>=DATE(2025,11,1))),H3*(1+Assumptions!$C$7)^0,0) | T3: =IF(AND(F3<=DATE(2025,12,1),OR(G3="",G3>=DATE(2025,12,1))),H3*(1+Assumptions!$C$7)^0,0) | U3: =IF(AND(F3<=DATE(2026,1,1),OR(G3="",G3>=DATE(2026,1,1))),H3*(1+Assumptions!$C$7)^1,0) | V3: =IF(AND(F3<=DATE(2026,2,1),OR(G3="",G3>=DATE(2026,2,1))),H3*(1+Assumptions!$C$7)^1,0) | W3: =IF(AND(F3<=DATE(2026,3,1),OR(G3="",G3>=DATE(2026,3,1))),H3*(1+Assumptions!$C$7)^1,0) | X3: =IF(AND(F3<=DATE(2026,4,1),OR(G3="",G3>=DATE(2026,4,1))),H3*(1+Assumptions!$C$7)^1,0) | Y3: =IF(AND(F3<=DATE(2026,5,1),OR(G3="",G3>=DATE(2026,5,1))),H3*(1+Assumptions!$C$7)^1,0) | Z3: =IF(AND(F3<=DATE(2026,6,1),OR(G3="",G3>=DATE(2026,6,1))),H3*(1+Assumptions!$C$7)^1,0) | AA3: =IF(AND(F3<=DATE(2026,7,1),OR(G3="",G3>=DATE(2026,7,1))),H3*(1+Assumptions!$C$7)^1,0) | AB3: =IF(AND(F3<=DATE(2026,8,1),OR(G3="",G3>=DATE(2026,8,1))),H3*(1+Assumptions!$C$7)^1,0) | AC3: =IF(AND(F3<=DATE(2026,9,1),OR(G3="",G3>=DATE(2026,9,1))),H3*(1+Assumptions!$C$7)^1,0) | AD3: =IF(AND(F3<=DATE(2026,10,1),OR(G3="",G3>=DATE(2026,10,1))),H3*(1+Assumptions!$C$7)^1,0) | AE3: =IF(AND(F3<=DATE(2026,11,1),OR(G3="",G3>=DATE(2026,11,1))),H3*(1+Assumptions!$C$7)^1,0) | AF3: =IF(AND(F3<=DATE(2026,12,1),OR(G3="",G3>=DATE(2026,12,1))),H3*(1+Assumptions!$C$7)^1,0) | AG3: =IF(AND(F3<=DATE(2027,1,1),OR(G3="",G3>=DATE(2027,1,1))),H3*(1+Assumptions!$C$7)^2,0) | AH3: =IF(AND(F3<=DATE(2027,2,1),OR(G3="",G3>=DATE(2027,2,1))),H3*(1+Assumptions!$C$7)^2,0) | AI3: =IF(AND(F3<=DATE(2027,3,1),OR(G3="",G3>=DATE(2027,3,1))),H3*(1+Assumptions!$C$7)^2,0) | AJ3: =IF(AND(F3<=DATE(2027,4,1),OR(G3="",G3>=DATE(2027,4,1))),H3*(1+Assumptions!$C$7)^2,0) | AK3: =IF(AND(F3<=DATE(2027,5,1),OR(G3="",G3>=DATE(2027,5,1))),H3*(1+Assumptions!$C$7)^2,0) | AL3: =IF(AND(F3<=DATE(2027,6,1),OR(G3="",G3>=DATE(2027,6,1))),H3*(1+Assumptions!$C$7)^2,0) | AM3: =IF(AND(F3<=DATE(2027,7,1),OR(G3="",G3>=DATE(2027,7,1))),H3*(1+Assumptions!$C$7)^2,0) | AN3: =IF(AND(F3<=DATE(2027,8,1),OR(G3="",G3>=DATE(2027,8,1))),H3*(1+Assumptions!$C$7)^2,0) | AO3: =IF(AND(F3<=DATE(2027,9,1),OR(G3="",G3>=DATE(2027,9,1))),H3*(1+Assumptions!$C$7)^2,0) | AP3: =IF(AND(F3<=DATE(2027,10,1),OR(G3="",G3>=DATE(2027,10,1))),H3*(1+Assumptions!$C$7)^2,0) | AQ3: =IF(AND(F3<=DATE(2027,11,1),OR(G3="",G3>=DATE(2027,11,1))),H3*(1+Assumptions!$C$7)^2,0) | AR3: =IF(AND(F3<=DATE(2027,12,1),OR(G3="",G3>=DATE(2027,12,1))),H3*(1+Assumptions!$C$7)^2,0) | AS3: =IF(AND(F3<=DATE(2028,1,1),OR(G3="",G3>=DATE(2028,1,1))),H3*(1+Assumptions!$C$7)^3,0) | AT3: =IF(AND(F3<=DATE(2028,2,1),OR(G3="",G3>=DATE(2028,2,1))),H3*(1+Assumptions!$C$7)^3,0) | AU3: =IF(AND(F3<=DATE(2028,3,1),OR(G3="",G3>=DATE(2028,3,1))),H3*(1+Assumptions!$C$7)^3,0) | AV3: =IF(AND(F3<=DATE(2028,4,1),OR(G3="",G3>=DATE(2028,4,1))),H3*(1+Assumptions!$C$7)^3,0) | AW3: =IF(AND(F3<=DATE(2028,5,1),OR(G3="",G3>=DATE(2028,5,1))),H3*(1+Assumptions!$C$7)^3,0) | AX3: =IF(AND(F3<=DATE(2028,6,1),OR(G3="",G3>=DATE(2028,6,1))),H3*(1+Assumptions!$C$7)^3,0) | AY3: =IF(AND(F3<=DATE(2028,7,1),OR(G3="",G3>=DATE(2028,7,1))),H3*(1+Assumptions!$C$7)^3,0) | AZ3: =IF(AND(F3<=DATE(2028,8,1),OR(G3="",G3>=DATE(2028,8,1))),H3*(1+Assumptions!$C$7)^3,0) | BA3: =IF(AND(F3<=DATE(2028,9,1),OR(G3="",G3>=DATE(2028,9,1))),H3*(1+Assumptions!$C$7)^3,0) | BB3: =IF(AND(F3<=DATE(2028,10,1),OR(G3="",G3>=DATE(2028,10,1))),H3*(1+Assumptions!$C$7)^3,0) | BC3: =IF(AND(F3<=DATE(2028,11,1),OR(G3="",G3>=DATE(2028,11,1))),H3*(1+Assumptions!$C$7)^3,0) | BD3: =IF(AND(F3<=DATE(2028,12,1),OR(G3="",G3>=DATE(2028,12,1))),H3*(1+Assumptions!$C$7)^3,0) | BE3: =IF(AND(F3<=DATE(2029,1,1),OR(G3="",G3>=DATE(2029,1,1))),H3*(1+Assumptions!$C$7)^4,0) | BF3: =IF(AND(F3<=DATE(2029,2,1),OR(G3="",G3>=DATE(2029,2,1))),H3*(1+Assumptions!$C$7)^4,0) | BG3: =IF(AND(F3<=DATE(2029,3,1),OR(G3="",G3>=DATE(2029,3,1))),H3*(1+Assumptions!$C$7)^4,0) | BH3: =IF(AND(F3<=DATE(2029,4,1),OR(G3="",G3>=DATE(2029,4,1))),H3*(1+Assumptions!$C$7)^4,0) | BI3: =IF(AND(F3<=DATE(2029,5,1),OR(G3="",G3>=DATE(2029,5,1))),H3*(1+Assumptions!$C$7)^4,0) | BJ3: =IF(AND(F3<=DATE(2029,6,1),OR(G3="",G3>=DATE(2029,6,1))),H3*(1+Assumptions!$C$7)^4,0) | BK3: =IF(AND(F3<=DATE(2029,7,1),OR(G3="",G3>=DATE(2029,7,1))),H3*(1+Assumptions!$C$7)^4,0) | BL3: =IF(AND(F3<=DATE(2029,8,1),OR(G3="",G3>=DATE(2029,8,1))),H3*(1+Assumptions!$C$7)^4,0) | BM3: =IF(AND(F3<=DATE(2029,9,1),OR(G3="",G3>=DATE(2029,9,1))),H3*(1+Assumptions!$C$7)^4,0) | BN3: =IF(AND(F3<=DATE(2029,10,1),OR(G3="",G3>=DATE(2029,10,1))),H3*(1+Assumptions!$C$7)^4,0) | BO3: =IF(AND(F3<=DATE(2029,11,1),OR(G3="",G3>=DATE(2029,11,1))),H3*(1+Assumptions!$C$7)^4,0) | BP3: =IF(AND(F3<=DATE(2029,12,1),OR(G3="",G3>=DATE(2029,12,1))),H3*(1+Assumptions!$C$7)^4,0) | BR3: paid this month if started and not yet left; +8% each calendar year
A4: 2 | B4: Project manager | C4: R&D | D4: R&D Engineer | E4: Current | F4: 45901 | H4: 7500 | I4: =IF(AND(F4<=DATE(2025,1,1),OR(G4="",G4>=DATE(2025,1,1))),H4*(1+Assumptions!$C$7)^0,0) | J4: =IF(AND(F4<=DATE(2025,2,1),OR(G4="",G4>=DATE(2025,2,1))),H4*(1+Assumptions!$C$7)^0,0) | K4: =IF(AND(F4<=DATE(2025,3,1),OR(G4="",G4>=DATE(2025,3,1))),H4*(1+Assumptions!$C$7)^0,0) | L4: =IF(AND(F4<=DATE(2025,4,1),OR(G4="",G4>=DATE(2025,4,1))),H4*(1+Assumptions!$C$7)^0,0) | M4: =IF(AND(F4<=DATE(2025,5,1),OR(G4="",G4>=DATE(2025,5,1))),H4*(1+Assumptions!$C$7)^0,0) | N4: =IF(AND(F4<=DATE(2025,6,1),OR(G4="",G4>=DATE(2025,6,1))),H4*(1+Assumptions!$C$7)^0,0) | O4: =IF(AND(F4<=DATE(2025,7,1),OR(G4="",G4>=DATE(2025,7,1))),H4*(1+Assumptions!$C$7)^0,0) | P4: =IF(AND(F4<=DATE(2025,8,1),OR(G4="",G4>=DATE(2025,8,1))),H4*(1+Assumptions!$C$7)^0,0) | Q4: =IF(AND(F4<=DATE(2025,9,1),OR(G4="",G4>=DATE(2025,9,1))),H4*(1+Assumptions!$C$7)^0,0) | R4: =IF(AND(F4<=DATE(2025,10,1),OR(G4="",G4>=DATE(2025,10,1))),H4*(1+Assumptions!$C$7)^0,0) | S4: =IF(AND(F4<=DATE(2025,11,1),OR(G4="",G4>=DATE(2025,11,1))),H4*(1+Assumptions!$C$7)^0,0) | T4: =IF(AND(F4<=DATE(2025,12,1),OR(G4="",G4>=DATE(2025,12,1))),H4*(1+Assumptions!$C$7)^0,0) | U4: =IF(AND(F4<=DATE(2026,1,1),OR(G4="",G4>=DATE(2026,1,1))),H4*(1+Assumptions!$C$7)^1,0) | V4: =IF(AND(F4<=DATE(2026,2,1),OR(G4="",G4>=DATE(2026,2,1))),H4*(1+Assumptions!$C$7)^1,0) | W4: =IF(AND(F4<=DATE(2026,3,1),OR(G4="",G4>=DATE(2026,3,1))),H4*(1+Assumptions!$C$7)^1,0) | X4: =IF(AND(F4<=DATE(2026,4,1),OR(G4="",G4>=DATE(2026,4,1))),H4*(1+Assumptions!$C$7)^1,0) | Y4: =IF(AND(F4<=DATE(2026,5,1),OR(G4="",G4>=DATE(2026,5,1))),H4*(1+Assumptions!$C$7)^1,0) | Z4: =IF(AND(F4<=DATE(2026,6,1),OR(G4="",G4>=DATE(2026,6,1))),H4*(1+Assumptions!$C$7)^1,0) | AA4: =IF(AND(F4<=DATE(2026,7,1),OR(G4="",G4>=DATE(2026,7,1))),H4*(1+Assumptions!$C$7)^1,0) | AB4: =IF(AND(F4<=DATE(2026,8,1),OR(G4="",G4>=DATE(2026,8,1))),H4*(1+Assumptions!$C$7)^1,0) | AC4: =IF(AND(F4<=DATE(2026,9,1),OR(G4="",G4>=DATE(2026,9,1))),H4*(1+Assumptions!$C$7)^1,0) | AD4: =IF(AND(F4<=DATE(2026,10,1),OR(G4="",G4>=DATE(2026,10,1))),H4*(1+Assumptions!$C$7)^1,0) | AE4: =IF(AND(F4<=DATE(2026,11,1),OR(G4="",G4>=DATE(2026,11,1))),H4*(1+Assumptions!$C$7)^1,0) | AF4: =IF(AND(F4<=DATE(2026,12,1),OR(G4="",G4>=DATE(2026,12,1))),H4*(1+Assumptions!$C$7)^1,0) | AG4: =IF(AND(F4<=DATE(2027,1,1),OR(G4="",G4>=DATE(2027,1,1))),H4*(1+Assumptions!$C$7)^2,0) | AH4: =IF(AND(F4<=DATE(2027,2,1),OR(G4="",G4>=DATE(2027,2,1))),H4*(1+Assumptions!$C$7)^2,0) | AI4: =IF(AND(F4<=DATE(2027,3,1),OR(G4="",G4>=DATE(2027,3,1))),H4*(1+Assumptions!$C$7)^2,0) | AJ4: =IF(AND(F4<=DATE(2027,4,1),OR(G4="",G4>=DATE(2027,4,1))),H4*(1+Assumptions!$C$7)^2,0) | AK4: =IF(AND(F4<=DATE(2027,5,1),OR(G4="",G4>=DATE(2027,5,1))),H4*(1+Assumptions!$C$7)^2,0) | AL4: =IF(AND(F4<=DATE(2027,6,1),OR(G4="",G4>=DATE(2027,6,1))),H4*(1+Assumptions!$C$7)^2,0) | AM4: =IF(AND(F4<=DATE(2027,7,1),OR(G4="",G4>=DATE(2027,7,1))),H4*(1+Assumptions!$C$7)^2,0) | AN4: =IF(AND(F4<=DATE(2027,8,1),OR(G4="",G4>=DATE(2027,8,1))),H4*(1+Assumptions!$C$7)^2,0) | AO4: =IF(AND(F4<=DATE(2027,9,1),OR(G4="",G4>=DATE(2027,9,1))),H4*(1+Assumptions!$C$7)^2,0) | AP4: =IF(AND(F4<=DATE(2027,10,1),OR(G4="",G4>=DATE(2027,10,1))),H4*(1+Assumptions!$C$7)^2,0) | AQ4: =IF(AND(F4<=DATE(2027,11,1),OR(G4="",G4>=DATE(2027,11,1))),H4*(1+Assumptions!$C$7)^2,0) | AR4: =IF(AND(F4<=DATE(2027,12,1),OR(G4="",G4>=DATE(2027,12,1))),H4*(1+Assumptions!$C$7)^2,0) | AS4: =IF(AND(F4<=DATE(2028,1,1),OR(G4="",G4>=DATE(2028,1,1))),H4*(1+Assumptions!$C$7)^3,0) | AT4: =IF(AND(F4<=DATE(2028,2,1),OR(G4="",G4>=DATE(2028,2,1))),H4*(1+Assumptions!$C$7)^3,0) | AU4: =IF(AND(F4<=DATE(2028,3,1),OR(G4="",G4>=DATE(2028,3,1))),H4*(1+Assumptions!$C$7)^3,0) | AV4: =IF(AND(F4<=DATE(2028,4,1),OR(G4="",G4>=DATE(2028,4,1))),H4*(1+Assumptions!$C$7)^3,0) | AW4: =IF(AND(F4<=DATE(2028,5,1),OR(G4="",G4>=DATE(2028,5,1))),H4*(1+Assumptions!$C$7)^3,0) | AX4: =IF(AND(F4<=DATE(2028,6,1),OR(G4="",G4>=DATE(2028,6,1))),H4*(1+Assumptions!$C$7)^3,0) | AY4: =IF(AND(F4<=DATE(2028,7,1),OR(G4="",G4>=DATE(2028,7,1))),H4*(1+Assumptions!$C$7)^3,0) | AZ4: =IF(AND(F4<=DATE(2028,8,1),OR(G4="",G4>=DATE(2028,8,1))),H4*(1+Assumptions!$C$7)^3,0) | BA4: =IF(AND(F4<=DATE(2028,9,1),OR(G4="",G4>=DATE(2028,9,1))),H4*(1+Assumptions!$C$7)^3,0) | BB4: =IF(AND(F4<=DATE(2028,10,1),OR(G4="",G4>=DATE(2028,10,1))),H4*(1+Assumptions!$C$7)^3,0) | BC4: =IF(AND(F4<=DATE(2028,11,1),OR(G4="",G4>=DATE(2028,11,1))),H4*(1+Assumptions!$C$7)^3,0) | BD4: =IF(AND(F4<=DATE(2028,12,1),OR(G4="",G4>=DATE(2028,12,1))),H4*(1+Assumptions!$C$7)^3,0) | BE4: =IF(AND(F4<=DATE(2029,1,1),OR(G4="",G4>=DATE(2029,1,1))),H4*(1+Assumptions!$C$7)^4,0) | BF4: =IF(AND(F4<=DATE(2029,2,1),OR(G4="",G4>=DATE(2029,2,1))),H4*(1+Assumptions!$C$7)^4,0) | BG4: =IF(AND(F4<=DATE(2029,3,1),OR(G4="",G4>=DATE(2029,3,1))),H4*(1+Assumptions!$C$7)^4,0) | BH4: =IF(AND(F4<=DATE(2029,4,1),OR(G4="",G4>=DATE(2029,4,1))),H4*(1+Assumptions!$C$7)^4,0) | BI4: =IF(AND(F4<=DATE(2029,5,1),OR(G4="",G4>=DATE(2029,5,1))),H4*(1+Assumptions!$C$7)^4,0) | BJ4: =IF(AND(F4<=DATE(2029,6,1),OR(G4="",G4>=DATE(2029,6,1))),H4*(1+Assumptions!$C$7)^4,0) | BK4: =IF(AND(F4<=DATE(2029,7,1),OR(G4="",G4>=DATE(2029,7,1))),H4*(1+Assumptions!$C$7)^4,0) | BL4: =IF(AND(F4<=DATE(2029,8,1),OR(G4="",G4>=DATE(2029,8,1))),H4*(1+Assumptions!$C$7)^4,0) | BM4: =IF(AND(F4<=DATE(2029,9,1),OR(G4="",G4>=DATE(2029,9,1))),H4*(1+Assumptions!$C$7)^4,0) | BN4: =IF(AND(F4<=DATE(2029,10,1),OR(G4="",G4>=DATE(2029,10,1))),H4*(1+Assumptions!$C$7)^4,0) | BO4: =IF(AND(F4<=DATE(2029,11,1),OR(G4="",G4>=DATE(2029,11,1))),H4*(1+Assumptions!$C$7)^4,0) | BP4: =IF(AND(F4<=DATE(2029,12,1),OR(G4="",G4>=DATE(2029,12,1))),H4*(1+Assumptions!$C$7)^4,0) | BR4: paid this month if started and not yet left; +8% each calendar year
A5: 3 | B5: R&D Engineer | C5: R&D | D5: R&D Engineer | E5: Current | F5: 45901 | H5: 3000 | I5: =IF(AND(F5<=DATE(2025,1,1),OR(G5="",G5>=DATE(2025,1,1))),H5*(1+Assumptions!$C$7)^0,0) | J5: =IF(AND(F5<=DATE(2025,2,1),OR(G5="",G5>=DATE(2025,2,1))),H5*(1+Assumptions!$C$7)^0,0) | K5: =IF(AND(F5<=DATE(2025,3,1),OR(G5="",G5>=DATE(2025,3,1))),H5*(1+Assumptions!$C$7)^0,0) | L5: =IF(AND(F5<=DATE(2025,4,1),OR(G5="",G5>=DATE(2025,4,1))),H5*(1+Assumptions!$C$7)^0,0) | M5: =IF(AND(F5<=DATE(2025,5,1),OR(G5="",G5>=DATE(2025,5,1))),H5*(1+Assumptions!$C$7)^0,0) | N5: =IF(AND(F5<=DATE(2025,6,1),OR(G5="",G5>=DATE(2025,6,1))),H5*(1+Assumptions!$C$7)^0,0) | O5: =IF(AND(F5<=DATE(2025,7,1),OR(G5="",G5>=DATE(2025,7,1))),H5*(1+Assumptions!$C$7)^0,0) | P5: =IF(AND(F5<=DATE(2025,8,1),OR(G5="",G5>=DATE(2025,8,1))),H5*(1+Assumptions!$C$7)^0,0) | Q5: =IF(AND(F5<=DATE(2025,9,1),OR(G5="",G5>=DATE(2025,9,1))),H5*(1+Assumptions!$C$7)^0,0) | R5: =IF(AND(F5<=DATE(2025,10,1),OR(G5="",G5>=DATE(2025,10,1))),H5*(1+Assumptions!$C$7)^0,0) | S5: =IF(AND(F5<=DATE(2025,11,1),OR(G5="",G5>=DATE(2025,11,1))),H5*(1+Assumptions!$C$7)^0,0) | T5: =IF(AND(F5<=DATE(2025,12,1),OR(G5="",G5>=DATE(2025,12,1))),H5*(1+Assumptions!$C$7)^0,0) | U5: =IF(AND(F5<=DATE(2026,1,1),OR(G5="",G5>=DATE(2026,1,1))),H5*(1+Assumptions!$C$7)^1,0) | V5: =IF(AND(F5<=DATE(2026,2,1),OR(G5="",G5>=DATE(2026,2,1))),H5*(1+Assumptions!$C$7)^1,0) | W5: =IF(AND(F5<=DATE(2026,3,1),OR(G5="",G5>=DATE(2026,3,1))),H5*(1+Assumptions!$C$7)^1,0) | X5: =IF(AND(F5<=DATE(2026,4,1),OR(G5="",G5>=DATE(2026,4,1))),H5*(1+Assumptions!$C$7)^1,0) | Y5: =IF(AND(F5<=DATE(2026,5,1),OR(G5="",G5>=DATE(2026,5,1))),H5*(1+Assumptions!$C$7)^1,0) | Z5: =IF(AND(F5<=DATE(2026,6,1),OR(G5="",G5>=DATE(2026,6,1))),H5*(1+Assumptions!$C$7)^1,0) | AA5: =IF(AND(F5<=DATE(2026,7,1),OR(G5="",G5>=DATE(2026,7,1))),H5*(1+Assumptions!$C$7)^1,0) | AB5: =IF(AND(F5<=DATE(2026,8,1),OR(G5="",G5>=DATE(2026,8,1))),H5*(1+Assumptions!$C$7)^1,0) | AC5: =IF(AND(F5<=DATE(2026,9,1),OR(G5="",G5>=DATE(2026,9,1))),H5*(1+Assumptions!$C$7)^1,0) | AD5: =IF(AND(F5<=DATE(2026,10,1),OR(G5="",G5>=DATE(2026,10,1))),H5*(1+Assumptions!$C$7)^1,0) | AE5: =IF(AND(F5<=DATE(2026,11,1),OR(G5="",G5>=DATE(2026,11,1))),H5*(1+Assumptions!$C$7)^1,0) | AF5: =IF(AND(F5<=DATE(2026,12,1),OR(G5="",G5>=DATE(2026,12,1))),H5*(1+Assumptions!$C$7)^1,0) | AG5: =IF(AND(F5<=DATE(2027,1,1),OR(G5="",G5>=DATE(2027,1,1))),H5*(1+Assumptions!$C$7)^2,0) | AH5: =IF(AND(F5<=DATE(2027,2,1),OR(G5="",G5>=DATE(2027,2,1))),H5*(1+Assumptions!$C$7)^2,0) | AI5: =IF(AND(F5<=DATE(2027,3,1),OR(G5="",G5>=DATE(2027,3,1))),H5*(1+Assumptions!$C$7)^2,0) | AJ5: =IF(AND(F5<=DATE(2027,4,1),OR(G5="",G5>=DATE(2027,4,1))),H5*(1+Assumptions!$C$7)^2,0) | AK5: =IF(AND(F5<=DATE(2027,5,1),OR(G5="",G5>=DATE(2027,5,1))),H5*(1+Assumptions!$C$7)^2,0) | AL5: =IF(AND(F5<=DATE(2027,6,1),OR(G5="",G5>=DATE(2027,6,1))),H5*(1+Assumptions!$C$7)^2,0) | AM5: =IF(AND(F5<=DATE(2027,7,1),OR(G5="",G5>=DATE(2027,7,1))),H5*(1+Assumptions!$C$7)^2,0) | AN5: =IF(AND(F5<=DATE(2027,8,1),OR(G5="",G5>=DATE(2027,8,1))),H5*(1+Assumptions!$C$7)^2,0) | AO5: =IF(AND(F5<=DATE(2027,9,1),OR(G5="",G5>=DATE(2027,9,1))),H5*(1+Assumptions!$C$7)^2,0) | AP5: =IF(AND(F5<=DATE(2027,10,1),OR(G5="",G5>=DATE(2027,10,1))),H5*(1+Assumptions!$C$7)^2,0) | AQ5: =IF(AND(F5<=DATE(2027,11,1),OR(G5="",G5>=DATE(2027,11,1))),H5*(1+Assumptions!$C$7)^2,0) | AR5: =IF(AND(F5<=DATE(2027,12,1),OR(G5="",G5>=DATE(2027,12,1))),H5*(1+Assumptions!$C$7)^2,0) | AS5: =IF(AND(F5<=DATE(2028,1,1),OR(G5="",G5>=DATE(2028,1,1))),H5*(1+Assumptions!$C$7)^3,0) | AT5: =IF(AND(F5<=DATE(2028,2,1),OR(G5="",G5>=DATE(2028,2,1))),H5*(1+Assumptions!$C$7)^3,0) | AU5: =IF(AND(F5<=DATE(2028,3,1),OR(G5="",G5>=DATE(2028,3,1))),H5*(1+Assumptions!$C$7)^3,0) | AV5: =IF(AND(F5<=DATE(2028,4,1),OR(G5="",G5>=DATE(2028,4,1))),H5*(1+Assumptions!$C$7)^3,0) | AW5: =IF(AND(F5<=DATE(2028,5,1),OR(G5="",G5>=DATE(2028,5,1))),H5*(1+Assumptions!$C$7)^3,0) | AX5: =IF(AND(F5<=DATE(2028,6,1),OR(G5="",G5>=DATE(2028,6,1))),H5*(1+Assumptions!$C$7)^3,0) | AY5: =IF(AND(F5<=DATE(2028,7,1),OR(G5="",G5>=DATE(2028,7,1))),H5*(1+Assumptions!$C$7)^3,0) | AZ5: =IF(AND(F5<=DATE(2028,8,1),OR(G5="",G5>=DATE(2028,8,1))),H5*(1+Assumptions!$C$7)^3,0) | BA5: =IF(AND(F5<=DATE(2028,9,1),OR(G5="",G5>=DATE(2028,9,1))),H5*(1+Assumptions!$C$7)^3,0) | BB5: =IF(AND(F5<=DATE(2028,10,1),OR(G5="",G5>=DATE(2028,10,1))),H5*(1+Assumptions!$C$7)^3,0) | BC5: =IF(AND(F5<=DATE(2028,11,1),OR(G5="",G5>=DATE(2028,11,1))),H5*(1+Assumptions!$C$7)^3,0) | BD5: =IF(AND(F5<=DATE(2028,12,1),OR(G5="",G5>=DATE(2028,12,1))),H5*(1+Assumptions!$C$7)^3,0) | BE5: =IF(AND(F5<=DATE(2029,1,1),OR(G5="",G5>=DATE(2029,1,1))),H5*(1+Assumptions!$C$7)^4,0) | BF5: =IF(AND(F5<=DATE(2029,2,1),OR(G5="",G5>=DATE(2029,2,1))),H5*(1+Assumptions!$C$7)^4,0) | BG5: =IF(AND(F5<=DATE(2029,3,1),OR(G5="",G5>=DATE(2029,3,1))),H5*(1+Assumptions!$C$7)^4,0) | BH5: =IF(AND(F5<=DATE(2029,4,1),OR(G5="",G5>=DATE(2029,4,1))),H5*(1+Assumptions!$C$7)^4,0) | BI5: =IF(AND(F5<=DATE(2029,5,1),OR(G5="",G5>=DATE(2029,5,1))),H5*(1+Assumptions!$C$7)^4,0) | BJ5: =IF(AND(F5<=DATE(2029,6,1),OR(G5="",G5>=DATE(2029,6,1))),H5*(1+Assumptions!$C$7)^4,0) | BK5: =IF(AND(F5<=DATE(2029,7,1),OR(G5="",G5>=DATE(2029,7,1))),H5*(1+Assumptions!$C$7)^4,0) | BL5: =IF(AND(F5<=DATE(2029,8,1),OR(G5="",G5>=DATE(2029,8,1))),H5*(1+Assumptions!$C$7)^4,0) | BM5: =IF(AND(F5<=DATE(2029,9,1),OR(G5="",G5>=DATE(2029,9,1))),H5*(1+Assumptions!$C$7)^4,0) | BN5: =IF(AND(F5<=DATE(2029,10,1),OR(G5="",G5>=DATE(2029,10,1))),H5*(1+Assumptions!$C$7)^4,0) | BO5: =IF(AND(F5<=DATE(2029,11,1),OR(G5="",G5>=DATE(2029,11,1))),H5*(1+Assumptions!$C$7)^4,0) | BP5: =IF(AND(F5<=DATE(2029,12,1),OR(G5="",G5>=DATE(2029,12,1))),H5*(1+Assumptions!$C$7)^4,0) | BR5: paid this month if started and not yet left; +8% each calendar year
A6: 4 | B6: R&D Engineer | C6: R&D | D6: R&D Engineer | E6: Current | F6: 45901 | H6: 6000 | I6: =IF(AND(F6<=DATE(2025,1,1),OR(G6="",G6>=DATE(2025,1,1))),H6*(1+Assumptions!$C$7)^0,0) | J6: =IF(AND(F6<=DATE(2025,2,1),OR(G6="",G6>=DATE(2025,2,1))),H6*(1+Assumptions!$C$7)^0,0) | K6: =IF(AND(F6<=DATE(2025,3,1),OR(G6="",G6>=DATE(2025,3,1))),H6*(1+Assumptions!$C$7)^0,0) | L6: =IF(AND(F6<=DATE(2025,4,1),OR(G6="",G6>=DATE(2025,4,1))),H6*(1+Assumptions!$C$7)^0,0) | M6: =IF(AND(F6<=DATE(2025,5,1),OR(G6="",G6>=DATE(2025,5,1))),H6*(1+Assumptions!$C$7)^0,0) | N6: =IF(AND(F6<=DATE(2025,6,1),OR(G6="",G6>=DATE(2025,6,1))),H6*(1+Assumptions!$C$7)^0,0) | O6: =IF(AND(F6<=DATE(2025,7,1),OR(G6="",G6>=DATE(2025,7,1))),H6*(1+Assumptions!$C$7)^0,0) | P6: =IF(AND(F6<=DATE(2025,8,1),OR(G6="",G6>=DATE(2025,8,1))),H6*(1+Assumptions!$C$7)^0,0) | Q6: =IF(AND(F6<=DATE(2025,9,1),OR(G6="",G6>=DATE(2025,9,1))),H6*(1+Assumptions!$C$7)^0,0) | R6: =IF(AND(F6<=DATE(2025,10,1),OR(G6="",G6>=DATE(2025,10,1))),H6*(1+Assumptions!$C$7)^0,0) | S6: =IF(AND(F6<=DATE(2025,11,1),OR(G6="",G6>=DATE(2025,11,1))),H6*(1+Assumptions!$C$7)^0,0) | T6: =IF(AND(F6<=DATE(2025,12,1),OR(G6="",G6>=DATE(2025,12,1))),H6*(1+Assumptions!$C$7)^0,0) | U6: =IF(AND(F6<=DATE(2026,1,1),OR(G6="",G6>=DATE(2026,1,1))),H6*(1+Assumptions!$C$7)^1,0) | V6: =IF(AND(F6<=DATE(2026,2,1),OR(G6="",G6>=DATE(2026,2,1))),H6*(1+Assumptions!$C$7)^1,0) | W6: =IF(AND(F6<=DATE(2026,3,1),OR(G6="",G6>=DATE(2026,3,1))),H6*(1+Assumptions!$C$7)^1,0) | X6: =IF(AND(F6<=DATE(2026,4,1),OR(G6="",G6>=DATE(2026,4,1))),H6*(1+Assumptions!$C$7)^1,0) | Y6: =IF(AND(F6<=DATE(2026,5,1),OR(G6="",G6>=DATE(2026,5,1))),H6*(1+Assumptions!$C$7)^1,0) | Z6: =IF(AND(F6<=DATE(2026,6,1),OR(G6="",G6>=DATE(2026,6,1))),H6*(1+Assumptions!$C$7)^1,0) | AA6: =IF(AND(F6<=DATE(2026,7,1),OR(G6="",G6>=DATE(2026,7,1))),H6*(1+Assumptions!$C$7)^1,0) | AB6: =IF(AND(F6<=DATE(2026,8,1),OR(G6="",G6>=DATE(2026,8,1))),H6*(1+Assumptions!$C$7)^1,0) | AC6: =IF(AND(F6<=DATE(2026,9,1),OR(G6="",G6>=DATE(2026,9,1))),H6*(1+Assumptions!$C$7)^1,0) | AD6: =IF(AND(F6<=DATE(2026,10,1),OR(G6="",G6>=DATE(2026,10,1))),H6*(1+Assumptions!$C$7)^1,0) | AE6: =IF(AND(F6<=DATE(2026,11,1),OR(G6="",G6>=DATE(2026,11,1))),H6*(1+Assumptions!$C$7)^1,0) | AF6: =IF(AND(F6<=DATE(2026,12,1),OR(G6="",G6>=DATE(2026,12,1))),H6*(1+Assumptions!$C$7)^1,0) | AG6: =IF(AND(F6<=DATE(2027,1,1),OR(G6="",G6>=DATE(2027,1,1))),H6*(1+Assumptions!$C$7)^2,0) | AH6: =IF(AND(F6<=DATE(2027,2,1),OR(G6="",G6>=DATE(2027,2,1))),H6*(1+Assumptions!$C$7)^2,0) | AI6: =IF(AND(F6<=DATE(2027,3,1),OR(G6="",G6>=DATE(2027,3,1))),H6*(1+Assumptions!$C$7)^2,0) | AJ6: =IF(AND(F6<=DATE(2027,4,1),OR(G6="",G6>=DATE(2027,4,1))),H6*(1+Assumptions!$C$7)^2,0) | AK6: =IF(AND(F6<=DATE(2027,5,1),OR(G6="",G6>=DATE(2027,5,1))),H6*(1+Assumptions!$C$7)^2,0) | AL6: =IF(AND(F6<=DATE(2027,6,1),OR(G6="",G6>=DATE(2027,6,1))),H6*(1+Assumptions!$C$7)^2,0) | AM6: =IF(AND(F6<=DATE(2027,7,1),OR(G6="",G6>=DATE(2027,7,1))),H6*(1+Assumptions!$C$7)^2,0) | AN6: =IF(AND(F6<=DATE(2027,8,1),OR(G6="",G6>=DATE(2027,8,1))),H6*(1+Assumptions!$C$7)^2,0) | AO6: =IF(AND(F6<=DATE(2027,9,1),OR(G6="",G6>=DATE(2027,9,1))),H6*(1+Assumptions!$C$7)^2,0) | AP6: =IF(AND(F6<=DATE(2027,10,1),OR(G6="",G6>=DATE(2027,10,1))),H6*(1+Assumptions!$C$7)^2,0) | AQ6: =IF(AND(F6<=DATE(2027,11,1),OR(G6="",G6>=DATE(2027,11,1))),H6*(1+Assumptions!$C$7)^2,0) | AR6: =IF(AND(F6<=DATE(2027,12,1),OR(G6="",G6>=DATE(2027,12,1))),H6*(1+Assumptions!$C$7)^2,0) | AS6: =IF(AND(F6<=DATE(2028,1,1),OR(G6="",G6>=DATE(2028,1,1))),H6*(1+Assumptions!$C$7)^3,0) | AT6: =IF(AND(F6<=DATE(2028,2,1),OR(G6="",G6>=DATE(2028,2,1))),H6*(1+Assumptions!$C$7)^3,0) | AU6: =IF(AND(F6<=DATE(2028,3,1),OR(G6="",G6>=DATE(2028,3,1))),H6*(1+Assumptions!$C$7)^3,0) | AV6: =IF(AND(F6<=DATE(2028,4,1),OR(G6="",G6>=DATE(2028,4,1))),H6*(1+Assumptions!$C$7)^3,0) | AW6: =IF(AND(F6<=DATE(2028,5,1),OR(G6="",G6>=DATE(2028,5,1))),H6*(1+Assumptions!$C$7)^3,0) | AX6: =IF(AND(F6<=DATE(2028,6,1),OR(G6="",G6>=DATE(2028,6,1))),H6*(1+Assumptions!$C$7)^3,0) | AY6: =IF(AND(F6<=DATE(2028,7,1),OR(G6="",G6>=DATE(2028,7,1))),H6*(1+Assumptions!$C$7)^3,0) | AZ6: =IF(AND(F6<=DATE(2028,8,1),OR(G6="",G6>=DATE(2028,8,1))),H6*(1+Assumptions!$C$7)^3,0) | BA6: =IF(AND(F6<=DATE(2028,9,1),OR(G6="",G6>=DATE(2028,9,1))),H6*(1+Assumptions!$C$7)^3,0) | BB6: =IF(AND(F6<=DATE(2028,10,1),OR(G6="",G6>=DATE(2028,10,1))),H6*(1+Assumptions!$C$7)^3,0) | BC6: =IF(AND(F6<=DATE(2028,11,1),OR(G6="",G6>=DATE(2028,11,1))),H6*(1+Assumptions!$C$7)^3,0) | BD6: =IF(AND(F6<=DATE(2028,12,1),OR(G6="",G6>=DATE(2028,12,1))),H6*(1+Assumptions!$C$7)^3,0) | BE6: =IF(AND(F6<=DATE(2029,1,1),OR(G6="",G6>=DATE(2029,1,1))),H6*(1+Assumptions!$C$7)^4,0) | BF6: =IF(AND(F6<=DATE(2029,2,1),OR(G6="",G6>=DATE(2029,2,1))),H6*(1+Assumptions!$C$7)^4,0) | BG6: =IF(AND(F6<=DATE(2029,3,1),OR(G6="",G6>=DATE(2029,3,1))),H6*(1+Assumptions!$C$7)^4,0) | BH6: =IF(AND(F6<=DATE(2029,4,1),OR(G6="",G6>=DATE(2029,4,1))),H6*(1+Assumptions!$C$7)^4,0) | BI6: =IF(AND(F6<=DATE(2029,5,1),OR(G6="",G6>=DATE(2029,5,1))),H6*(1+Assumptions!$C$7)^4,0) | BJ6: =IF(AND(F6<=DATE(2029,6,1),OR(G6="",G6>=DATE(2029,6,1))),H6*(1+Assumptions!$C$7)^4,0) | BK6: =IF(AND(F6<=DATE(2029,7,1),OR(G6="",G6>=DATE(2029,7,1))),H6*(1+Assumptions!$C$7)^4,0) | BL6: =IF(AND(F6<=DATE(2029,8,1),OR(G6="",G6>=DATE(2029,8,1))),H6*(1+Assumptions!$C$7)^4,0) | BM6: =IF(AND(F6<=DATE(2029,9,1),OR(G6="",G6>=DATE(2029,9,1))),H6*(1+Assumptions!$C$7)^4,0) | BN6: =IF(AND(F6<=DATE(2029,10,1),OR(G6="",G6>=DATE(2029,10,1))),H6*(1+Assumptions!$C$7)^4,0) | BO6: =IF(AND(F6<=DATE(2029,11,1),OR(G6="",G6>=DATE(2029,11,1))),H6*(1+Assumptions!$C$7)^4,0) | BP6: =IF(AND(F6<=DATE(2029,12,1),OR(G6="",G6>=DATE(2029,12,1))),H6*(1+Assumptions!$C$7)^4,0) | BR6: paid this month if started and not yet left; +8% each calendar year
A7: 5 | B7: Firmware Engineer | C7: R&D | D7: R&D Engineer | E7: Current | F7: 45901 | H7: 7000 | I7: =IF(AND(F7<=DATE(2025,1,1),OR(G7="",G7>=DATE(2025,1,1))),H7*(1+Assumptions!$C$7)^0,0) | J7: =IF(AND(F7<=DATE(2025,2,1),OR(G7="",G7>=DATE(2025,2,1))),H7*(1+Assumptions!$C$7)^0,0) | K7: =IF(AND(F7<=DATE(2025,3,1),OR(G7="",G7>=DATE(2025,3,1))),H7*(1+Assumptions!$C$7)^0,0) | L7: =IF(AND(F7<=DATE(2025,4,1),OR(G7="",G7>=DATE(2025,4,1))),H7*(1+Assumptions!$C$7)^0,0) | M7: =IF(AND(F7<=DATE(2025,5,1),OR(G7="",G7>=DATE(2025,5,1))),H7*(1+Assumptions!$C$7)^0,0) | N7: =IF(AND(F7<=DATE(2025,6,1),OR(G7="",G7>=DATE(2025,6,1))),H7*(1+Assumptions!$C$7)^0,0) | O7: =IF(AND(F7<=DATE(2025,7,1),OR(G7="",G7>=DATE(2025,7,1))),H7*(1+Assumptions!$C$7)^0,0) | P7: =IF(AND(F7<=DATE(2025,8,1),OR(G7="",G7>=DATE(2025,8,1))),H7*(1+Assumptions!$C$7)^0,0) | Q7: =IF(AND(F7<=DATE(2025,9,1),OR(G7="",G7>=DATE(2025,9,1))),H7*(1+Assumptions!$C$7)^0,0) | R7: =IF(AND(F7<=DATE(2025,10,1),OR(G7="",G7>=DATE(2025,10,1))),H7*(1+Assumptions!$C$7)^0,0) | S7: =IF(AND(F7<=DATE(2025,11,1),OR(G7="",G7>=DATE(2025,11,1))),H7*(1+Assumptions!$C$7)^0,0) | T7: =IF(AND(F7<=DATE(2025,12,1),OR(G7="",G7>=DATE(2025,12,1))),H7*(1+Assumptions!$C$7)^0,0) | U7: =IF(AND(F7<=DATE(2026,1,1),OR(G7="",G7>=DATE(2026,1,1))),H7*(1+Assumptions!$C$7)^1,0) | V7: =IF(AND(F7<=DATE(2026,2,1),OR(G7="",G7>=DATE(2026,2,1))),H7*(1+Assumptions!$C$7)^1,0) | W7: =IF(AND(F7<=DATE(2026,3,1),OR(G7="",G7>=DATE(2026,3,1))),H7*(1+Assumptions!$C$7)^1,0) | X7: =IF(AND(F7<=DATE(2026,4,1),OR(G7="",G7>=DATE(2026,4,1))),H7*(1+Assumptions!$C$7)^1,0) | Y7: =IF(AND(F7<=DATE(2026,5,1),OR(G7="",G7>=DATE(2026,5,1))),H7*(1+Assumptions!$C$7)^1,0) | Z7: =IF(AND(F7<=DATE(2026,6,1),OR(G7="",G7>=DATE(2026,6,1))),H7*(1+Assumptions!$C$7)^1,0) | AA7: =IF(AND(F7<=DATE(2026,7,1),OR(G7="",G7>=DATE(2026,7,1))),H7*(1+Assumptions!$C$7)^1,0) | AB7: =IF(AND(F7<=DATE(2026,8,1),OR(G7="",G7>=DATE(2026,8,1))),H7*(1+Assumptions!$C$7)^1,0) | AC7: =IF(AND(F7<=DATE(2026,9,1),OR(G7="",G7>=DATE(2026,9,1))),H7*(1+Assumptions!$C$7)^1,0) | AD7: =IF(AND(F7<=DATE(2026,10,1),OR(G7="",G7>=DATE(2026,10,1))),H7*(1+Assumptions!$C$7)^1,0) | AE7: =IF(AND(F7<=DATE(2026,11,1),OR(G7="",G7>=DATE(2026,11,1))),H7*(1+Assumptions!$C$7)^1,0) | AF7: =IF(AND(F7<=DATE(2026,12,1),OR(G7="",G7>=DATE(2026,12,1))),H7*(1+Assumptions!$C$7)^1,0) | AG7: =IF(AND(F7<=DATE(2027,1,1),OR(G7="",G7>=DATE(2027,1,1))),H7*(1+Assumptions!$C$7)^2,0) | AH7: =IF(AND(F7<=DATE(2027,2,1),OR(G7="",G7>=DATE(2027,2,1))),H7*(1+Assumptions!$C$7)^2,0) | AI7: =IF(AND(F7<=DATE(2027,3,1),OR(G7="",G7>=DATE(2027,3,1))),H7*(1+Assumptions!$C$7)^2,0) | AJ7: =IF(AND(F7<=DATE(2027,4,1),OR(G7="",G7>=DATE(2027,4,1))),H7*(1+Assumptions!$C$7)^2,0) | AK7: =IF(AND(F7<=DATE(2027,5,1),OR(G7="",G7>=DATE(2027,5,1))),H7*(1+Assumptions!$C$7)^2,0) | AL7: =IF(AND(F7<=DATE(2027,6,1),OR(G7="",G7>=DATE(2027,6,1))),H7*(1+Assumptions!$C$7)^2,0) | AM7: =IF(AND(F7<=DATE(2027,7,1),OR(G7="",G7>=DATE(2027,7,1))),H7*(1+Assumptions!$C$7)^2,0) | AN7: =IF(AND(F7<=DATE(2027,8,1),OR(G7="",G7>=DATE(2027,8,1))),H7*(1+Assumptions!$C$7)^2,0) | AO7: =IF(AND(F7<=DATE(2027,9,1),OR(G7="",G7>=DATE(2027,9,1))),H7*(1+Assumptions!$C$7)^2,0) | AP7: =IF(AND(F7<=DATE(2027,10,1),OR(G7="",G7>=DATE(2027,10,1))),H7*(1+Assumptions!$C$7)^2,0) | AQ7: =IF(AND(F7<=DATE(2027,11,1),OR(G7="",G7>=DATE(2027,11,1))),H7*(1+Assumptions!$C$7)^2,0) | AR7: =IF(AND(F7<=DATE(2027,12,1),OR(G7="",G7>=DATE(2027,12,1))),H7*(1+Assumptions!$C$7)^2,0) | AS7: =IF(AND(F7<=DATE(2028,1,1),OR(G7="",G7>=DATE(2028,1,1))),H7*(1+Assumptions!$C$7)^3,0) | AT7: =IF(AND(F7<=DATE(2028,2,1),OR(G7="",G7>=DATE(2028,2,1))),H7*(1+Assumptions!$C$7)^3,0) | AU7: =IF(AND(F7<=DATE(2028,3,1),OR(G7="",G7>=DATE(2028,3,1))),H7*(1+Assumptions!$C$7)^3,0) | AV7: =IF(AND(F7<=DATE(2028,4,1),OR(G7="",G7>=DATE(2028,4,1))),H7*(1+Assumptions!$C$7)^3,0) | AW7: =IF(AND(F7<=DATE(2028,5,1),OR(G7="",G7>=DATE(2028,5,1))),H7*(1+Assumptions!$C$7)^3,0) | AX7: =IF(AND(F7<=DATE(2028,6,1),OR(G7="",G7>=DATE(2028,6,1))),H7*(1+Assumptions!$C$7)^3,0) | AY7: =IF(AND(F7<=DATE(2028,7,1),OR(G7="",G7>=DATE(2028,7,1))),H7*(1+Assumptions!$C$7)^3,0) | AZ7: =IF(AND(F7<=DATE(2028,8,1),OR(G7="",G7>=DATE(2028,8,1))),H7*(1+Assumptions!$C$7)^3,0) | BA7: =IF(AND(F7<=DATE(2028,9,1),OR(G7="",G7>=DATE(2028,9,1))),H7*(1+Assumptions!$C$7)^3,0) | BB7: =IF(AND(F7<=DATE(2028,10,1),OR(G7="",G7>=DATE(2028,10,1))),H7*(1+Assumptions!$C$7)^3,0) | BC7: =IF(AND(F7<=DATE(2028,11,1),OR(G7="",G7>=DATE(2028,11,1))),H7*(1+Assumptions!$C$7)^3,0) | BD7: =IF(AND(F7<=DATE(2028,12,1),OR(G7="",G7>=DATE(2028,12,1))),H7*(1+Assumptions!$C$7)^3,0) | BE7: =IF(AND(F7<=DATE(2029,1,1),OR(G7="",G7>=DATE(2029,1,1))),H7*(1+Assumptions!$C$7)^4,0) | BF7: =IF(AND(F7<=DATE(2029,2,1),OR(G7="",G7>=DATE(2029,2,1))),H7*(1+Assumptions!$C$7)^4,0) | BG7: =IF(AND(F7<=DATE(2029,3,1),OR(G7="",G7>=DATE(2029,3,1))),H7*(1+Assumptions!$C$7)^4,0) | BH7: =IF(AND(F7<=DATE(2029,4,1),OR(G7="",G7>=DATE(2029,4,1))),H7*(1+Assumptions!$C$7)^4,0) | BI7: =IF(AND(F7<=DATE(2029,5,1),OR(G7="",G7>=DATE(2029,5,1))),H7*(1+Assumptions!$C$7)^4,0) | BJ7: =IF(AND(F7<=DATE(2029,6,1),OR(G7="",G7>=DATE(2029,6,1))),H7*(1+Assumptions!$C$7)^4,0) | BK7: =IF(AND(F7<=DATE(2029,7,1),OR(G7="",G7>=DATE(2029,7,1))),H7*(1+Assumptions!$C$7)^4,0) | BL7: =IF(AND(F7<=DATE(2029,8,1),OR(G7="",G7>=DATE(2029,8,1))),H7*(1+Assumptions!$C$7)^4,0) | BM7: =IF(AND(F7<=DATE(2029,9,1),OR(G7="",G7>=DATE(2029,9,1))),H7*(1+Assumptions!$C$7)^4,0) | BN7: =IF(AND(F7<=DATE(2029,10,1),OR(G7="",G7>=DATE(2029,10,1))),H7*(1+Assumptions!$C$7)^4,0) | BO7: =IF(AND(F7<=DATE(2029,11,1),OR(G7="",G7>=DATE(2029,11,1))),H7*(1+Assumptions!$C$7)^4,0) | BP7: =IF(AND(F7<=DATE(2029,12,1),OR(G7="",G7>=DATE(2029,12,1))),H7*(1+Assumptions!$C$7)^4,0) | BR7: paid this month if started and not yet left; +8% each calendar year
A8: 6 | B8: Mechanical Engineer | C8: R&D | D8: R&D Engineer | E8: Current | F8: 45901 | H8: 5500 | I8: =IF(AND(F8<=DATE(2025,1,1),OR(G8="",G8>=DATE(2025,1,1))),H8*(1+Assumptions!$C$7)^0,0) | J8: =IF(AND(F8<=DATE(2025,2,1),OR(G8="",G8>=DATE(2025,2,1))),H8*(1+Assumptions!$C$7)^0,0) | K8: =IF(AND(F8<=DATE(2025,3,1),OR(G8="",G8>=DATE(2025,3,1))),H8*(1+Assumptions!$C$7)^0,0) | L8: =IF(AND(F8<=DATE(2025,4,1),OR(G8="",G8>=DATE(2025,4,1))),H8*(1+Assumptions!$C$7)^0,0) | M8: =IF(AND(F8<=DATE(2025,5,1),OR(G8="",G8>=DATE(2025,5,1))),H8*(1+Assumptions!$C$7)^0,0) | N8: =IF(AND(F8<=DATE(2025,6,1),OR(G8="",G8>=DATE(2025,6,1))),H8*(1+Assumptions!$C$7)^0,0) | O8: =IF(AND(F8<=DATE(2025,7,1),OR(G8="",G8>=DATE(2025,7,1))),H8*(1+Assumptions!$C$7)^0,0) | P8: =IF(AND(F8<=DATE(2025,8,1),OR(G8="",G8>=DATE(2025,8,1))),H8*(1+Assumptions!$C$7)^0,0) | Q8: =IF(AND(F8<=DATE(2025,9,1),OR(G8="",G8>=DATE(2025,9,1))),H8*(1+Assumptions!$C$7)^0,0) | R8: =IF(AND(F8<=DATE(2025,10,1),OR(G8="",G8>=DATE(2025,10,1))),H8*(1+Assumptions!$C$7)^0,0) | S8: =IF(AND(F8<=DATE(2025,11,1),OR(G8="",G8>=DATE(2025,11,1))),H8*(1+Assumptions!$C$7)^0,0) | T8: =IF(AND(F8<=DATE(2025,12,1),OR(G8="",G8>=DATE(2025,12,1))),H8*(1+Assumptions!$C$7)^0,0) | U8: =IF(AND(F8<=DATE(2026,1,1),OR(G8="",G8>=DATE(2026,1,1))),H8*(1+Assumptions!$C$7)^1,0) | V8: =IF(AND(F8<=DATE(2026,2,1),OR(G8="",G8>=DATE(2026,2,1))),H8*(1+Assumptions!$C$7)^1,0) | W8: =IF(AND(F8<=DATE(2026,3,1),OR(G8="",G8>=DATE(2026,3,1))),H8*(1+Assumptions!$C$7)^1,0) | X8: =IF(AND(F8<=DATE(2026,4,1),OR(G8="",G8>=DATE(2026,4,1))),H8*(1+Assumptions!$C$7)^1,0) | Y8: =IF(AND(F8<=DATE(2026,5,1),OR(G8="",G8>=DATE(2026,5,1))),H8*(1+Assumptions!$C$7)^1,0) | Z8: =IF(AND(F8<=DATE(2026,6,1),OR(G8="",G8>=DATE(2026,6,1))),H8*(1+Assumptions!$C$7)^1,0) | AA8: =IF(AND(F8<=DATE(2026,7,1),OR(G8="",G8>=DATE(2026,7,1))),H8*(1+Assumptions!$C$7)^1,0) | AB8: =IF(AND(F8<=DATE(2026,8,1),OR(G8="",G8>=DATE(2026,8,1))),H8*(1+Assumptions!$C$7)^1,0) | AC8: =IF(AND(F8<=DATE(2026,9,1),OR(G8="",G8>=DATE(2026,9,1))),H8*(1+Assumptions!$C$7)^1,0) | AD8: =IF(AND(F8<=DATE(2026,10,1),OR(G8="",G8>=DATE(2026,10,1))),H8*(1+Assumptions!$C$7)^1,0) | AE8: =IF(AND(F8<=DATE(2026,11,1),OR(G8="",G8>=DATE(2026,11,1))),H8*(1+Assumptions!$C$7)^1,0) | AF8: =IF(AND(F8<=DATE(2026,12,1),OR(G8="",G8>=DATE(2026,12,1))),H8*(1+Assumptions!$C$7)^1,0) | AG8: =IF(AND(F8<=DATE(2027,1,1),OR(G8="",G8>=DATE(2027,1,1))),H8*(1+Assumptions!$C$7)^2,0) | AH8: =IF(AND(F8<=DATE(2027,2,1),OR(G8="",G8>=DATE(2027,2,1))),H8*(1+Assumptions!$C$7)^2,0) | AI8: =IF(AND(F8<=DATE(2027,3,1),OR(G8="",G8>=DATE(2027,3,1))),H8*(1+Assumptions!$C$7)^2,0) | AJ8: =IF(AND(F8<=DATE(2027,4,1),OR(G8="",G8>=DATE(2027,4,1))),H8*(1+Assumptions!$C$7)^2,0) | AK8: =IF(AND(F8<=DATE(2027,5,1),OR(G8="",G8>=DATE(2027,5,1))),H8*(1+Assumptions!$C$7)^2,0) | AL8: =IF(AND(F8<=DATE(2027,6,1),OR(G8="",G8>=DATE(2027,6,1))),H8*(1+Assumptions!$C$7)^2,0) | AM8: =IF(AND(F8<=DATE(2027,7,1),OR(G8="",G8>=DATE(2027,7,1))),H8*(1+Assumptions!$C$7)^2,0) | AN8: =IF(AND(F8<=DATE(2027,8,1),OR(G8="",G8>=DATE(2027,8,1))),H8*(1+Assumptions!$C$7)^2,0) | AO8: =IF(AND(F8<=DATE(2027,9,1),OR(G8="",G8>=DATE(2027,9,1))),H8*(1+Assumptions!$C$7)^2,0) | AP8: =IF(AND(F8<=DATE(2027,10,1),OR(G8="",G8>=DATE(2027,10,1))),H8*(1+Assumptions!$C$7)^2,0) | AQ8: =IF(AND(F8<=DATE(2027,11,1),OR(G8="",G8>=DATE(2027,11,1))),H8*(1+Assumptions!$C$7)^2,0) | AR8: =IF(AND(F8<=DATE(2027,12,1),OR(G8="",G8>=DATE(2027,12,1))),H8*(1+Assumptions!$C$7)^2,0) | AS8: =IF(AND(F8<=DATE(2028,1,1),OR(G8="",G8>=DATE(2028,1,1))),H8*(1+Assumptions!$C$7)^3,0) | AT8: =IF(AND(F8<=DATE(2028,2,1),OR(G8="",G8>=DATE(2028,2,1))),H8*(1+Assumptions!$C$7)^3,0) | AU8: =IF(AND(F8<=DATE(2028,3,1),OR(G8="",G8>=DATE(2028,3,1))),H8*(1+Assumptions!$C$7)^3,0) | AV8: =IF(AND(F8<=DATE(2028,4,1),OR(G8="",G8>=DATE(2028,4,1))),H8*(1+Assumptions!$C$7)^3,0) | AW8: =IF(AND(F8<=DATE(2028,5,1),OR(G8="",G8>=DATE(2028,5,1))),H8*(1+Assumptions!$C$7)^3,0) | AX8: =IF(AND(F8<=DATE(2028,6,1),OR(G8="",G8>=DATE(2028,6,1))),H8*(1+Assumptions!$C$7)^3,0) | AY8: =IF(AND(F8<=DATE(2028,7,1),OR(G8="",G8>=DATE(2028,7,1))),H8*(1+Assumptions!$C$7)^3,0) | AZ8: =IF(AND(F8<=DATE(2028,8,1),OR(G8="",G8>=DATE(2028,8,1))),H8*(1+Assumptions!$C$7)^3,0) | BA8: =IF(AND(F8<=DATE(2028,9,1),OR(G8="",G8>=DATE(2028,9,1))),H8*(1+Assumptions!$C$7)^3,0) | BB8: =IF(AND(F8<=DATE(2028,10,1),OR(G8="",G8>=DATE(2028,10,1))),H8*(1+Assumptions!$C$7)^3,0) | BC8: =IF(AND(F8<=DATE(2028,11,1),OR(G8="",G8>=DATE(2028,11,1))),H8*(1+Assumptions!$C$7)^3,0) | BD8: =IF(AND(F8<=DATE(2028,12,1),OR(G8="",G8>=DATE(2028,12,1))),H8*(1+Assumptions!$C$7)^3,0) | BE8: =IF(AND(F8<=DATE(2029,1,1),OR(G8="",G8>=DATE(2029,1,1))),H8*(1+Assumptions!$C$7)^4,0) | BF8: =IF(AND(F8<=DATE(2029,2,1),OR(G8="",G8>=DATE(2029,2,1))),H8*(1+Assumptions!$C$7)^4,0) | BG8: =IF(AND(F8<=DATE(2029,3,1),OR(G8="",G8>=DATE(2029,3,1))),H8*(1+Assumptions!$C$7)^4,0) | BH8: =IF(AND(F8<=DATE(2029,4,1),OR(G8="",G8>=DATE(2029,4,1))),H8*(1+Assumptions!$C$7)^4,0) | BI8: =IF(AND(F8<=DATE(2029,5,1),OR(G8="",G8>=DATE(2029,5,1))),H8*(1+Assumptions!$C$7)^4,0) | BJ8: =IF(AND(F8<=DATE(2029,6,1),OR(G8="",G8>=DATE(2029,6,1))),H8*(1+Assumptions!$C$7)^4,0) | BK8: =IF(AND(F8<=DATE(2029,7,1),OR(G8="",G8>=DATE(2029,7,1))),H8*(1+Assumptions!$C$7)^4,0) | BL8: =IF(AND(F8<=DATE(2029,8,1),OR(G8="",G8>=DATE(2029,8,1))),H8*(1+Assumptions!$C$7)^4,0) | BM8: =IF(AND(F8<=DATE(2029,9,1),OR(G8="",G8>=DATE(2029,9,1))),H8*(1+Assumptions!$C$7)^4,0) | BN8: =IF(AND(F8<=DATE(2029,10,1),OR(G8="",G8>=DATE(2029,10,1))),H8*(1+Assumptions!$C$7)^4,0) | BO8: =IF(AND(F8<=DATE(2029,11,1),OR(G8="",G8>=DATE(2029,11,1))),H8*(1+Assumptions!$C$7)^4,0) | BP8: =IF(AND(F8<=DATE(2029,12,1),OR(G8="",G8>=DATE(2029,12,1))),H8*(1+Assumptions!$C$7)^4,0) | BR8: paid this month if started and not yet left; +8% each calendar year
A9: 7 | B9: Electrical Engineer | C9: R&D | D9: R&D Engineer | E9: Current | F9: 45901 | H9: 5500 | I9: =IF(AND(F9<=DATE(2025,1,1),OR(G9="",G9>=DATE(2025,1,1))),H9*(1+Assumptions!$C$7)^0,0) | J9: =IF(AND(F9<=DATE(2025,2,1),OR(G9="",G9>=DATE(2025,2,1))),H9*(1+Assumptions!$C$7)^0,0) | K9: =IF(AND(F9<=DATE(2025,3,1),OR(G9="",G9>=DATE(2025,3,1))),H9*(1+Assumptions!$C$7)^0,0) | L9: =IF(AND(F9<=DATE(2025,4,1),OR(G9="",G9>=DATE(2025,4,1))),H9*(1+Assumptions!$C$7)^0,0) | M9: =IF(AND(F9<=DATE(2025,5,1),OR(G9="",G9>=DATE(2025,5,1))),H9*(1+Assumptions!$C$7)^0,0) | N9: =IF(AND(F9<=DATE(2025,6,1),OR(G9="",G9>=DATE(2025,6,1))),H9*(1+Assumptions!$C$7)^0,0) | O9: =IF(AND(F9<=DATE(2025,7,1),OR(G9="",G9>=DATE(2025,7,1))),H9*(1+Assumptions!$C$7)^0,0) | P9: =IF(AND(F9<=DATE(2025,8,1),OR(G9="",G9>=DATE(2025,8,1))),H9*(1+Assumptions!$C$7)^0,0) | Q9: =IF(AND(F9<=DATE(2025,9,1),OR(G9="",G9>=DATE(2025,9,1))),H9*(1+Assumptions!$C$7)^0,0) | R9: =IF(AND(F9<=DATE(2025,10,1),OR(G9="",G9>=DATE(2025,10,1))),H9*(1+Assumptions!$C$7)^0,0) | S9: =IF(AND(F9<=DATE(2025,11,1),OR(G9="",G9>=DATE(2025,11,1))),H9*(1+Assumptions!$C$7)^0,0) | T9: =IF(AND(F9<=DATE(2025,12,1),OR(G9="",G9>=DATE(2025,12,1))),H9*(1+Assumptions!$C$7)^0,0) | U9: =IF(AND(F9<=DATE(2026,1,1),OR(G9="",G9>=DATE(2026,1,1))),H9*(1+Assumptions!$C$7)^1,0) | V9: =IF(AND(F9<=DATE(2026,2,1),OR(G9="",G9>=DATE(2026,2,1))),H9*(1+Assumptions!$C$7)^1,0) | W9: =IF(AND(F9<=DATE(2026,3,1),OR(G9="",G9>=DATE(2026,3,1))),H9*(1+Assumptions!$C$7)^1,0) | X9: =IF(AND(F9<=DATE(2026,4,1),OR(G9="",G9>=DATE(2026,4,1))),H9*(1+Assumptions!$C$7)^1,0) | Y9: =IF(AND(F9<=DATE(2026,5,1),OR(G9="",G9>=DATE(2026,5,1))),H9*(1+Assumptions!$C$7)^1,0) | Z9: =IF(AND(F9<=DATE(2026,6,1),OR(G9="",G9>=DATE(2026,6,1))),H9*(1+Assumptions!$C$7)^1,0) | AA9: =IF(AND(F9<=DATE(2026,7,1),OR(G9="",G9>=DATE(2026,7,1))),H9*(1+Assumptions!$C$7)^1,0) | AB9: =IF(AND(F9<=DATE(2026,8,1),OR(G9="",G9>=DATE(2026,8,1))),H9*(1+Assumptions!$C$7)^1,0) | AC9: =IF(AND(F9<=DATE(2026,9,1),OR(G9="",G9>=DATE(2026,9,1))),H9*(1+Assumptions!$C$7)^1,0) | AD9: =IF(AND(F9<=DATE(2026,10,1),OR(G9="",G9>=DATE(2026,10,1))),H9*(1+Assumptions!$C$7)^1,0) | AE9: =IF(AND(F9<=DATE(2026,11,1),OR(G9="",G9>=DATE(2026,11,1))),H9*(1+Assumptions!$C$7)^1,0) | AF9: =IF(AND(F9<=DATE(2026,12,1),OR(G9="",G9>=DATE(2026,12,1))),H9*(1+Assumptions!$C$7)^1,0) | AG9: =IF(AND(F9<=DATE(2027,1,1),OR(G9="",G9>=DATE(2027,1,1))),H9*(1+Assumptions!$C$7)^2,0) | AH9: =IF(AND(F9<=DATE(2027,2,1),OR(G9="",G9>=DATE(2027,2,1))),H9*(1+Assumptions!$C$7)^2,0) | AI9: =IF(AND(F9<=DATE(2027,3,1),OR(G9="",G9>=DATE(2027,3,1))),H9*(1+Assumptions!$C$7)^2,0) | AJ9: =IF(AND(F9<=DATE(2027,4,1),OR(G9="",G9>=DATE(2027,4,1))),H9*(1+Assumptions!$C$7)^2,0) | AK9: =IF(AND(F9<=DATE(2027,5,1),OR(G9="",G9>=DATE(2027,5,1))),H9*(1+Assumptions!$C$7)^2,0) | AL9: =IF(AND(F9<=DATE(2027,6,1),OR(G9="",G9>=DATE(2027,6,1))),H9*(1+Assumptions!$C$7)^2,0) | AM9: =IF(AND(F9<=DATE(2027,7,1),OR(G9="",G9>=DATE(2027,7,1))),H9*(1+Assumptions!$C$7)^2,0) | AN9: =IF(AND(F9<=DATE(2027,8,1),OR(G9="",G9>=DATE(2027,8,1))),H9*(1+Assumptions!$C$7)^2,0) | AO9: =IF(AND(F9<=DATE(2027,9,1),OR(G9="",G9>=DATE(2027,9,1))),H9*(1+Assumptions!$C$7)^2,0) | AP9: =IF(AND(F9<=DATE(2027,10,1),OR(G9="",G9>=DATE(2027,10,1))),H9*(1+Assumptions!$C$7)^2,0) | AQ9: =IF(AND(F9<=DATE(2027,11,1),OR(G9="",G9>=DATE(2027,11,1))),H9*(1+Assumptions!$C$7)^2,0) | AR9: =IF(AND(F9<=DATE(2027,12,1),OR(G9="",G9>=DATE(2027,12,1))),H9*(1+Assumptions!$C$7)^2,0) | AS9: =IF(AND(F9<=DATE(2028,1,1),OR(G9="",G9>=DATE(2028,1,1))),H9*(1+Assumptions!$C$7)^3,0) | AT9: =IF(AND(F9<=DATE(2028,2,1),OR(G9="",G9>=DATE(2028,2,1))),H9*(1+Assumptions!$C$7)^3,0) | AU9: =IF(AND(F9<=DATE(2028,3,1),OR(G9="",G9>=DATE(2028,3,1))),H9*(1+Assumptions!$C$7)^3,0) | AV9: =IF(AND(F9<=DATE(2028,4,1),OR(G9="",G9>=DATE(2028,4,1))),H9*(1+Assumptions!$C$7)^3,0) | AW9: =IF(AND(F9<=DATE(2028,5,1),OR(G9="",G9>=DATE(2028,5,1))),H9*(1+Assumptions!$C$7)^3,0) | AX9: =IF(AND(F9<=DATE(2028,6,1),OR(G9="",G9>=DATE(2028,6,1))),H9*(1+Assumptions!$C$7)^3,0) | AY9: =IF(AND(F9<=DATE(2028,7,1),OR(G9="",G9>=DATE(2028,7,1))),H9*(1+Assumptions!$C$7)^3,0) | AZ9: =IF(AND(F9<=DATE(2028,8,1),OR(G9="",G9>=DATE(2028,8,1))),H9*(1+Assumptions!$C$7)^3,0) | BA9: =IF(AND(F9<=DATE(2028,9,1),OR(G9="",G9>=DATE(2028,9,1))),H9*(1+Assumptions!$C$7)^3,0) | BB9: =IF(AND(F9<=DATE(2028,10,1),OR(G9="",G9>=DATE(2028,10,1))),H9*(1+Assumptions!$C$7)^3,0) | BC9: =IF(AND(F9<=DATE(2028,11,1),OR(G9="",G9>=DATE(2028,11,1))),H9*(1+Assumptions!$C$7)^3,0) | BD9: =IF(AND(F9<=DATE(2028,12,1),OR(G9="",G9>=DATE(2028,12,1))),H9*(1+Assumptions!$C$7)^3,0) | BE9: =IF(AND(F9<=DATE(2029,1,1),OR(G9="",G9>=DATE(2029,1,1))),H9*(1+Assumptions!$C$7)^4,0) | BF9: =IF(AND(F9<=DATE(2029,2,1),OR(G9="",G9>=DATE(2029,2,1))),H9*(1+Assumptions!$C$7)^4,0) | BG9: =IF(AND(F9<=DATE(2029,3,1),OR(G9="",G9>=DATE(2029,3,1))),H9*(1+Assumptions!$C$7)^4,0) | BH9: =IF(AND(F9<=DATE(2029,4,1),OR(G9="",G9>=DATE(2029,4,1))),H9*(1+Assumptions!$C$7)^4,0) | BI9: =IF(AND(F9<=DATE(2029,5,1),OR(G9="",G9>=DATE(2029,5,1))),H9*(1+Assumptions!$C$7)^4,0) | BJ9: =IF(AND(F9<=DATE(2029,6,1),OR(G9="",G9>=DATE(2029,6,1))),H9*(1+Assumptions!$C$7)^4,0) | BK9: =IF(AND(F9<=DATE(2029,7,1),OR(G9="",G9>=DATE(2029,7,1))),H9*(1+Assumptions!$C$7)^4,0) | BL9: =IF(AND(F9<=DATE(2029,8,1),OR(G9="",G9>=DATE(2029,8,1))),H9*(1+Assumptions!$C$7)^4,0) | BM9: =IF(AND(F9<=DATE(2029,9,1),OR(G9="",G9>=DATE(2029,9,1))),H9*(1+Assumptions!$C$7)^4,0) | BN9: =IF(AND(F9<=DATE(2029,10,1),OR(G9="",G9>=DATE(2029,10,1))),H9*(1+Assumptions!$C$7)^4,0) | BO9: =IF(AND(F9<=DATE(2029,11,1),OR(G9="",G9>=DATE(2029,11,1))),H9*(1+Assumptions!$C$7)^4,0) | BP9: =IF(AND(F9<=DATE(2029,12,1),OR(G9="",G9>=DATE(2029,12,1))),H9*(1+Assumptions!$C$7)^4,0) | BR9: paid this month if started and not yet left; +8% each calendar year
A10: 11 | B10: CFO (part time) | C10: G&A | D10: CFO | E10: Current | F10: 45901 | G10: 46266 | H10: 4000 | I10: =IF(AND(F10<=DATE(2025,1,1),OR(G10="",G10>=DATE(2025,1,1))),H10*(1+Assumptions!$C$7)^0,0) | J10: =IF(AND(F10<=DATE(2025,2,1),OR(G10="",G10>=DATE(2025,2,1))),H10*(1+Assumptions!$C$7)^0,0) | K10: =IF(AND(F10<=DATE(2025,3,1),OR(G10="",G10>=DATE(2025,3,1))),H10*(1+Assumptions!$C$7)^0,0) | L10: =IF(AND(F10<=DATE(2025,4,1),OR(G10="",G10>=DATE(2025,4,1))),H10*(1+Assumptions!$C$7)^0,0) | M10: =IF(AND(F10<=DATE(2025,5,1),OR(G10="",G10>=DATE(2025,5,1))),H10*(1+Assumptions!$C$7)^0,0) | N10: =IF(AND(F10<=DATE(2025,6,1),OR(G10="",G10>=DATE(2025,6,1))),H10*(1+Assumptions!$C$7)^0,0) | O10: =IF(AND(F10<=DATE(2025,7,1),OR(G10="",G10>=DATE(2025,7,1))),H10*(1+Assumptions!$C$7)^0,0) | P10: =IF(AND(F10<=DATE(2025,8,1),OR(G10="",G10>=DATE(2025,8,1))),H10*(1+Assumptions!$C$7)^0,0) | Q10: =IF(AND(F10<=DATE(2025,9,1),OR(G10="",G10>=DATE(2025,9,1))),H10*(1+Assumptions!$C$7)^0,0) | R10: =IF(AND(F10<=DATE(2025,10,1),OR(G10="",G10>=DATE(2025,10,1))),H10*(1+Assumptions!$C$7)^0,0) | S10: =IF(AND(F10<=DATE(2025,11,1),OR(G10="",G10>=DATE(2025,11,1))),H10*(1+Assumptions!$C$7)^0,0) | T10: =IF(AND(F10<=DATE(2025,12,1),OR(G10="",G10>=DATE(2025,12,1))),H10*(1+Assumptions!$C$7)^0,0) | U10: =IF(AND(F10<=DATE(2026,1,1),OR(G10="",G10>=DATE(2026,1,1))),H10*(1+Assumptions!$C$7)^1,0) | V10: =IF(AND(F10<=DATE(2026,2,1),OR(G10="",G10>=DATE(2026,2,1))),H10*(1+Assumptions!$C$7)^1,0) | W10: =IF(AND(F10<=DATE(2026,3,1),OR(G10="",G10>=DATE(2026,3,1))),H10*(1+Assumptions!$C$7)^1,0) | X10: =IF(AND(F10<=DATE(2026,4,1),OR(G10="",G10>=DATE(2026,4,1))),H10*(1+Assumptions!$C$7)^1,0) | Y10: =IF(AND(F10<=DATE(2026,5,1),OR(G10="",G10>=DATE(2026,5,1))),H10*(1+Assumptions!$C$7)^1,0) | Z10: =IF(AND(F10<=DATE(2026,6,1),OR(G10="",G10>=DATE(2026,6,1))),H10*(1+Assumptions!$C$7)^1,0) | AA10: =IF(AND(F10<=DATE(2026,7,1),OR(G10="",G10>=DATE(2026,7,1))),H10*(1+Assumptions!$C$7)^1,0) | AB10: =IF(AND(F10<=DATE(2026,8,1),OR(G10="",G10>=DATE(2026,8,1))),H10*(1+Assumptions!$C$7)^1,0) | AC10: =IF(AND(F10<=DATE(2026,9,1),OR(G10="",G10>=DATE(2026,9,1))),H10*(1+Assumptions!$C$7)^1,0) | AD10: =IF(AND(F10<=DATE(2026,10,1),OR(G10="",G10>=DATE(2026,10,1))),H10*(1+Assumptions!$C$7)^1,0) | AE10: =IF(AND(F10<=DATE(2026,11,1),OR(G10="",G10>=DATE(2026,11,1))),H10*(1+Assumptions!$C$7)^1,0) | AF10: =IF(AND(F10<=DATE(2026,12,1),OR(G10="",G10>=DATE(2026,12,1))),H10*(1+Assumptions!$C$7)^1,0) | AG10: =IF(AND(F10<=DATE(2027,1,1),OR(G10="",G10>=DATE(2027,1,1))),H10*(1+Assumptions!$C$7)^2,0) | AH10: =IF(AND(F10<=DATE(2027,2,1),OR(G10="",G10>=DATE(2027,2,1))),H10*(1+Assumptions!$C$7)^2,0) | AI10: =IF(AND(F10<=DATE(2027,3,1),OR(G10="",G10>=DATE(2027,3,1))),H10*(1+Assumptions!$C$7)^2,0) | AJ10: =IF(AND(F10<=DATE(2027,4,1),OR(G10="",G10>=DATE(2027,4,1))),H10*(1+Assumptions!$C$7)^2,0) | AK10: =IF(AND(F10<=DATE(2027,5,1),OR(G10="",G10>=DATE(2027,5,1))),H10*(1+Assumptions!$C$7)^2,0) | AL10: =IF(AND(F10<=DATE(2027,6,1),OR(G10="",G10>=DATE(2027,6,1))),H10*(1+Assumptions!$C$7)^2,0) | AM10: =IF(AND(F10<=DATE(2027,7,1),OR(G10="",G10>=DATE(2027,7,1))),H10*(1+Assumptions!$C$7)^2,0) | AN10: =IF(AND(F10<=DATE(2027,8,1),OR(G10="",G10>=DATE(2027,8,1))),H10*(1+Assumptions!$C$7)^2,0) | AO10: =IF(AND(F10<=DATE(2027,9,1),OR(G10="",G10>=DATE(2027,9,1))),H10*(1+Assumptions!$C$7)^2,0) | AP10: =IF(AND(F10<=DATE(2027,10,1),OR(G10="",G10>=DATE(2027,10,1))),H10*(1+Assumptions!$C$7)^2,0) | AQ10: =IF(AND(F10<=DATE(2027,11,1),OR(G10="",G10>=DATE(2027,11,1))),H10*(1+Assumptions!$C$7)^2,0) | AR10: =IF(AND(F10<=DATE(2027,12,1),OR(G10="",G10>=DATE(2027,12,1))),H10*(1+Assumptions!$C$7)^2,0) | AS10: =IF(AND(F10<=DATE(2028,1,1),OR(G10="",G10>=DATE(2028,1,1))),H10*(1+Assumptions!$C$7)^3,0) | AT10: =IF(AND(F10<=DATE(2028,2,1),OR(G10="",G10>=DATE(2028,2,1))),H10*(1+Assumptions!$C$7)^3,0) | AU10: =IF(AND(F10<=DATE(2028,3,1),OR(G10="",G10>=DATE(2028,3,1))),H10*(1+Assumptions!$C$7)^3,0) | AV10: =IF(AND(F10<=DATE(2028,4,1),OR(G10="",G10>=DATE(2028,4,1))),H10*(1+Assumptions!$C$7)^3,0) | AW10: =IF(AND(F10<=DATE(2028,5,1),OR(G10="",G10>=DATE(2028,5,1))),H10*(1+Assumptions!$C$7)^3,0) | AX10: =IF(AND(F10<=DATE(2028,6,1),OR(G10="",G10>=DATE(2028,6,1))),H10*(1+Assumptions!$C$7)^3,0) | AY10: =IF(AND(F10<=DATE(2028,7,1),OR(G10="",G10>=DATE(2028,7,1))),H10*(1+Assumptions!$C$7)^3,0) | AZ10: =IF(AND(F10<=DATE(2028,8,1),OR(G10="",G10>=DATE(2028,8,1))),H10*(1+Assumptions!$C$7)^3,0) | BA10: =IF(AND(F10<=DATE(2028,9,1),OR(G10="",G10>=DATE(2028,9,1))),H10*(1+Assumptions!$C$7)^3,0) | BB10: =IF(AND(F10<=DATE(2028,10,1),OR(G10="",G10>=DATE(2028,10,1))),H10*(1+Assumptions!$C$7)^3,0) | BC10: =IF(AND(F10<=DATE(2028,11,1),OR(G10="",G10>=DATE(2028,11,1))),H10*(1+Assumptions!$C$7)^3,0) | BD10: =IF(AND(F10<=DATE(2028,12,1),OR(G10="",G10>=DATE(2028,12,1))),H10*(1+Assumptions!$C$7)^3,0) | BE10: =IF(AND(F10<=DATE(2029,1,1),OR(G10="",G10>=DATE(2029,1,1))),H10*(1+Assumptions!$C$7)^4,0) | BF10: =IF(AND(F10<=DATE(2029,2,1),OR(G10="",G10>=DATE(2029,2,1))),H10*(1+Assumptions!$C$7)^4,0) | BG10: =IF(AND(F10<=DATE(2029,3,1),OR(G10="",G10>=DATE(2029,3,1))),H10*(1+Assumptions!$C$7)^4,0) | BH10: =IF(AND(F10<=DATE(2029,4,1),OR(G10="",G10>=DATE(2029,4,1))),H10*(1+Assumptions!$C$7)^4,0) | BI10: =IF(AND(F10<=DATE(2029,5,1),OR(G10="",G10>=DATE(2029,5,1))),H10*(1+Assumptions!$C$7)^4,0) | BJ10: =IF(AND(F10<=DATE(2029,6,1),OR(G10="",G10>=DATE(2029,6,1))),H10*(1+Assumptions!$C$7)^4,0) | BK10: =IF(AND(F10<=DATE(2029,7,1),OR(G10="",G10>=DATE(2029,7,1))),H10*(1+Assumptions!$C$7)^4,0) | BL10: =IF(AND(F10<=DATE(2029,8,1),OR(G10="",G10>=DATE(2029,8,1))),H10*(1+Assumptions!$C$7)^4,0) | BM10: =IF(AND(F10<=DATE(2029,9,1),OR(G10="",G10>=DATE(2029,9,1))),H10*(1+Assumptions!$C$7)^4,0) | BN10: =IF(AND(F10<=DATE(2029,10,1),OR(G10="",G10>=DATE(2029,10,1))),H10*(1+Assumptions!$C$7)^4,0) | BO10: =IF(AND(F10<=DATE(2029,11,1),OR(G10="",G10>=DATE(2029,11,1))),H10*(1+Assumptions!$C$7)^4,0) | BP10: =IF(AND(F10<=DATE(2029,12,1),OR(G10="",G10>=DATE(2029,12,1))),H10*(1+Assumptions!$C$7)^4,0) | BR10: paid this month if started and not yet left; +8% each calendar year
A11: 8 | B11: CTO | C11: R&D | D11: CTO | E11: Current | F11: 46266 | H11: 11500 | I11: =IF(AND(F11<=DATE(2025,1,1),OR(G11="",G11>=DATE(2025,1,1))),H11*(1+Assumptions!$C$7)^0,0) | J11: =IF(AND(F11<=DATE(2025,2,1),OR(G11="",G11>=DATE(2025,2,1))),H11*(1+Assumptions!$C$7)^0,0) | K11: =IF(AND(F11<=DATE(2025,3,1),OR(G11="",G11>=DATE(2025,3,1))),H11*(1+Assumptions!$C$7)^0,0) | L11: =IF(AND(F11<=DATE(2025,4,1),OR(G11="",G11>=DATE(2025,4,1))),H11*(1+Assumptions!$C$7)^0,0) | M11: =IF(AND(F11<=DATE(2025,5,1),OR(G11="",G11>=DATE(2025,5,1))),H11*(1+Assumptions!$C$7)^0,0) | N11: =IF(AND(F11<=DATE(2025,6,1),OR(G11="",G11>=DATE(2025,6,1))),H11*(1+Assumptions!$C$7)^0,0) | O11: =IF(AND(F11<=DATE(2025,7,1),OR(G11="",G11>=DATE(2025,7,1))),H11*(1+Assumptions!$C$7)^0,0) | P11: =IF(AND(F11<=DATE(2025,8,1),OR(G11="",G11>=DATE(2025,8,1))),H11*(1+Assumptions!$C$7)^0,0) | Q11: 7500 | R11: 7500 | S11: 7500 | T11: 7500 | U11: 7500 | V11: 7500 | W11: 7500 | X11: 7500 | Y11: 7500 | Z11: 7500 | AA11: 7500 | AB11: 7500 | AC11: =IF(AND(F11<=DATE(2026,9,1),OR(G11="",G11>=DATE(2026,9,1))),H11) | AD11: =IF(AND(F11<=DATE(2026,10,1),OR(G11="",G11>=DATE(2026,10,1))),H11*(1+Assumptions!$C$7)^1,0) | AE11: =IF(AND(F11<=DATE(2026,11,1),OR(G11="",G11>=DATE(2026,11,1))),H11*(1+Assumptions!$C$7)^1,0) | AF11: =IF(AND(F11<=DATE(2026,12,1),OR(G11="",G11>=DATE(2026,12,1))),H11*(1+Assumptions!$C$7)^1,0) | AG11: =IF(AND(F11<=DATE(2027,1,1),OR(G11="",G11>=DATE(2027,1,1))),H11*(1+Assumptions!$C$7)^2,0) | AH11: =IF(AND(F11<=DATE(2027,2,1),OR(G11="",G11>=DATE(2027,2,1))),H11*(1+Assumptions!$C$7)^2,0) | AI11: =IF(AND(F11<=DATE(2027,3,1),OR(G11="",G11>=DATE(2027,3,1))),H11*(1+Assumptions!$C$7)^2,0) | AJ11: =IF(AND(F11<=DATE(2027,4,1),OR(G11="",G11>=DATE(2027,4,1))),H11*(1+Assumptions!$C$7)^2,0) | AK11: =IF(AND(F11<=DATE(2027,5,1),OR(G11="",G11>=DATE(2027,5,1))),H11*(1+Assumptions!$C$7)^2,0) | AL11: =IF(AND(F11<=DATE(2027,6,1),OR(G11="",G11>=DATE(2027,6,1))),H11*(1+Assumptions!$C$7)^2,0) | AM11: =IF(AND(F11<=DATE(2027,7,1),OR(G11="",G11>=DATE(2027,7,1))),H11*(1+Assumptions!$C$7)^2,0) | AN11: =IF(AND(F11<=DATE(2027,8,1),OR(G11="",G11>=DATE(2027,8,1))),H11*(1+Assumptions!$C$7)^2,0) | AO11: =IF(AND(F11<=DATE(2027,9,1),OR(G11="",G11>=DATE(2027,9,1))),H11*(1+Assumptions!$C$7)^2,0) | AP11: =IF(AND(F11<=DATE(2027,10,1),OR(G11="",G11>=DATE(2027,10,1))),H11*(1+Assumptions!$C$7)^2,0) | AQ11: =IF(AND(F11<=DATE(2027,11,1),OR(G11="",G11>=DATE(2027,11,1))),H11*(1+Assumptions!$C$7)^2,0) | AR11: =IF(AND(F11<=DATE(2027,12,1),OR(G11="",G11>=DATE(2027,12,1))),H11*(1+Assumptions!$C$7)^2,0) | AS11: =IF(AND(F11<=DATE(2028,1,1),OR(G11="",G11>=DATE(2028,1,1))),H11*(1+Assumptions!$C$7)^3,0) | AT11: =IF(AND(F11<=DATE(2028,2,1),OR(G11="",G11>=DATE(2028,2,1))),H11*(1+Assumptions!$C$7)^3,0) | AU11: =IF(AND(F11<=DATE(2028,3,1),OR(G11="",G11>=DATE(2028,3,1))),H11*(1+Assumptions!$C$7)^3,0) | AV11: =IF(AND(F11<=DATE(2028,4,1),OR(G11="",G11>=DATE(2028,4,1))),H11*(1+Assumptions!$C$7)^3,0) | AW11: =IF(AND(F11<=DATE(2028,5,1),OR(G11="",G11>=DATE(2028,5,1))),H11*(1+Assumptions!$C$7)^3,0) | AX11: =IF(AND(F11<=DATE(2028,6,1),OR(G11="",G11>=DATE(2028,6,1))),H11*(1+Assumptions!$C$7)^3,0) | AY11: =IF(AND(F11<=DATE(2028,7,1),OR(G11="",G11>=DATE(2028,7,1))),H11*(1+Assumptions!$C$7)^3,0) | AZ11: =IF(AND(F11<=DATE(2028,8,1),OR(G11="",G11>=DATE(2028,8,1))),H11*(1+Assumptions!$C$7)^3,0) | BA11: =IF(AND(F11<=DATE(2028,9,1),OR(G11="",G11>=DATE(2028,9,1))),H11*(1+Assumptions!$C$7)^3,0) | BB11: =IF(AND(F11<=DATE(2028,10,1),OR(G11="",G11>=DATE(2028,10,1))),H11*(1+Assumptions!$C$7)^3,0) | BC11: =IF(AND(F11<=DATE(2028,11,1),OR(G11="",G11>=DATE(2028,11,1))),H11*(1+Assumptions!$C$7)^3,0) | BD11: =IF(AND(F11<=DATE(2028,12,1),OR(G11="",G11>=DATE(2028,12,1))),H11*(1+Assumptions!$C$7)^3,0) | BE11: =IF(AND(F11<=DATE(2029,1,1),OR(G11="",G11>=DATE(2029,1,1))),H11*(1+Assumptions!$C$7)^4,0) | BF11: =IF(AND(F11<=DATE(2029,2,1),OR(G11="",G11>=DATE(2029,2,1))),H11*(1+Assumptions!$C$7)^4,0) | BG11: =IF(AND(F11<=DATE(2029,3,1),OR(G11="",G11>=DATE(2029,3,1))),H11*(1+Assumptions!$C$7)^4,0) | BH11: =IF(AND(F11<=DATE(2029,4,1),OR(G11="",G11>=DATE(2029,4,1))),H11*(1+Assumptions!$C$7)^4,0) | BI11: =IF(AND(F11<=DATE(2029,5,1),OR(G11="",G11>=DATE(2029,5,1))),H11*(1+Assumptions!$C$7)^4,0) | BJ11: =IF(AND(F11<=DATE(2029,6,1),OR(G11="",G11>=DATE(2029,6,1))),H11*(1+Assumptions!$C$7)^4,0) | BK11: =IF(AND(F11<=DATE(2029,7,1),OR(G11="",G11>=DATE(2029,7,1))),H11*(1+Assumptions!$C$7)^4,0) | BL11: =IF(AND(F11<=DATE(2029,8,1),OR(G11="",G11>=DATE(2029,8,1))),H11*(1+Assumptions!$C$7)^4,0) | BM11: =IF(AND(F11<=DATE(2029,9,1),OR(G11="",G11>=DATE(2029,9,1))),H11*(1+Assumptions!$C$7)^4,0) | BN11: =IF(AND(F11<=DATE(2029,10,1),OR(G11="",G11>=DATE(2029,10,1))),H11*(1+Assumptions!$C$7)^4,0) | BO11: =IF(AND(F11<=DATE(2029,11,1),OR(G11="",G11>=DATE(2029,11,1))),H11*(1+Assumptions!$C$7)^4,0) | BP11: =IF(AND(F11<=DATE(2029,12,1),OR(G11="",G11>=DATE(2029,12,1))),H11*(1+Assumptions!$C$7)^4,0) | BR11: paid this month if started and not yet left; +8% each calendar year
A12: 9 | B12: Head of Growth | C12: S&M | D12: Growth | E12: Current | F12: 46054 | H12: 10000 | I12: =IF(AND(F12<=DATE(2025,1,1),OR(G12="",G12>=DATE(2025,1,1))),H12*(1+Assumptions!$C$7)^0,0) | J12: =IF(AND(F12<=DATE(2025,2,1),OR(G12="",G12>=DATE(2025,2,1))),H12*(1+Assumptions!$C$7)^0,0) | K12: =IF(AND(F12<=DATE(2025,3,1),OR(G12="",G12>=DATE(2025,3,1))),H12*(1+Assumptions!$C$7)^0,0) | L12: =IF(AND(F12<=DATE(2025,4,1),OR(G12="",G12>=DATE(2025,4,1))),H12*(1+Assumptions!$C$7)^0,0) | M12: =IF(AND(F12<=DATE(2025,5,1),OR(G12="",G12>=DATE(2025,5,1))),H12*(1+Assumptions!$C$7)^0,0) | N12: =IF(AND(F12<=DATE(2025,6,1),OR(G12="",G12>=DATE(2025,6,1))),H12*(1+Assumptions!$C$7)^0,0) | O12: =IF(AND(F12<=DATE(2025,7,1),OR(G12="",G12>=DATE(2025,7,1))),H12*(1+Assumptions!$C$7)^0,0) | P12: =IF(AND(F12<=DATE(2025,8,1),OR(G12="",G12>=DATE(2025,8,1))),H12*(1+Assumptions!$C$7)^0,0) | Q12: =IF(AND(F12<=DATE(2025,9,1),OR(G12="",G12>=DATE(2025,9,1))),H12*(1+Assumptions!$C$7)^0,0) | R12: =IF(AND(F12<=DATE(2025,10,1),OR(G12="",G12>=DATE(2025,10,1))),H12*(1+Assumptions!$C$7)^0,0) | S12: =IF(AND(F12<=DATE(2025,11,1),OR(G12="",G12>=DATE(2025,11,1))),H12*(1+Assumptions!$C$7)^0,0) | T12: =IF(AND(F12<=DATE(2025,12,1),OR(G12="",G12>=DATE(2025,12,1))),H12*(1+Assumptions!$C$7)^0,0) | U12: =IF(AND(F12<=DATE(2026,1,1),OR(G12="",G12>=DATE(2026,1,1))),H12*(1+Assumptions!$C$7)^1,0) | V12: =IF(AND(F12<=DATE(2026,2,1),OR(G12="",G12>=DATE(2026,2,1))),H12*(1+Assumptions!$C$7)^1,0) | W12: =IF(AND(F12<=DATE(2026,3,1),OR(G12="",G12>=DATE(2026,3,1))),H12*(1+Assumptions!$C$7)^1,0) | X12: =IF(AND(F12<=DATE(2026,4,1),OR(G12="",G12>=DATE(2026,4,1))),H12*(1+Assumptions!$C$7)^1,0) | Y12: =IF(AND(F12<=DATE(2026,5,1),OR(G12="",G12>=DATE(2026,5,1))),H12*(1+Assumptions!$C$7)^1,0) | Z12: =IF(AND(F12<=DATE(2026,6,1),OR(G12="",G12>=DATE(2026,6,1))),H12*(1+Assumptions!$C$7)^1,0) | AA12: =IF(AND(F12<=DATE(2026,7,1),OR(G12="",G12>=DATE(2026,7,1))),H12*(1+Assumptions!$C$7)^1,0) | AB12: =IF(AND(F12<=DATE(2026,8,1),OR(G12="",G12>=DATE(2026,8,1))),H12*(1+Assumptions!$C$7)^1,0) | AC12: =IF(AND(F12<=DATE(2026,9,1),OR(G12="",G12>=DATE(2026,9,1))),H12*(1+Assumptions!$C$7)^1,0) | AD12: =IF(AND(F12<=DATE(2026,10,1),OR(G12="",G12>=DATE(2026,10,1))),H12*(1+Assumptions!$C$7)^1,0) | AE12: =IF(AND(F12<=DATE(2026,11,1),OR(G12="",G12>=DATE(2026,11,1))),H12*(1+Assumptions!$C$7)^1,0) | AF12: =IF(AND(F12<=DATE(2026,12,1),OR(G12="",G12>=DATE(2026,12,1))),H12*(1+Assumptions!$C$7)^1,0) | AG12: =IF(AND(F12<=DATE(2027,1,1),OR(G12="",G12>=DATE(2027,1,1))),H12*(1+Assumptions!$C$7)^2,0) | AH12: =IF(AND(F12<=DATE(2027,2,1),OR(G12="",G12>=DATE(2027,2,1))),H12*(1+Assumptions!$C$7)^2,0) | AI12: =IF(AND(F12<=DATE(2027,3,1),OR(G12="",G12>=DATE(2027,3,1))),H12*(1+Assumptions!$C$7)^2,0) | AJ12: =IF(AND(F12<=DATE(2027,4,1),OR(G12="",G12>=DATE(2027,4,1))),H12*(1+Assumptions!$C$7)^2,0) | AK12: =IF(AND(F12<=DATE(2027,5,1),OR(G12="",G12>=DATE(2027,5,1))),H12*(1+Assumptions!$C$7)^2,0) | AL12: =IF(AND(F12<=DATE(2027,6,1),OR(G12="",G12>=DATE(2027,6,1))),H12*(1+Assumptions!$C$7)^2,0) | AM12: =IF(AND(F12<=DATE(2027,7,1),OR(G12="",G12>=DATE(2027,7,1))),H12*(1+Assumptions!$C$7)^2,0) | AN12: =IF(AND(F12<=DATE(2027,8,1),OR(G12="",G12>=DATE(2027,8,1))),H12*(1+Assumptions!$C$7)^2,0) | AO12: =IF(AND(F12<=DATE(2027,9,1),OR(G12="",G12>=DATE(2027,9,1))),H12*(1+Assumptions!$C$7)^2,0) | AP12: =IF(AND(F12<=DATE(2027,10,1),OR(G12="",G12>=DATE(2027,10,1))),H12*(1+Assumptions!$C$7)^2,0) | AQ12: =IF(AND(F12<=DATE(2027,11,1),OR(G12="",G12>=DATE(2027,11,1))),H12*(1+Assumptions!$C$7)^2,0) | AR12: =IF(AND(F12<=DATE(2027,12,1),OR(G12="",G12>=DATE(2027,12,1))),H12*(1+Assumptions!$C$7)^2,0) | AS12: =IF(AND(F12<=DATE(2028,1,1),OR(G12="",G12>=DATE(2028,1,1))),H12*(1+Assumptions!$C$7)^3,0) | AT12: =IF(AND(F12<=DATE(2028,2,1),OR(G12="",G12>=DATE(2028,2,1))),H12*(1+Assumptions!$C$7)^3,0) | AU12: =IF(AND(F12<=DATE(2028,3,1),OR(G12="",G12>=DATE(2028,3,1))),H12*(1+Assumptions!$C$7)^3,0) | AV12: =IF(AND(F12<=DATE(2028,4,1),OR(G12="",G12>=DATE(2028,4,1))),H12*(1+Assumptions!$C$7)^3,0) | AW12: =IF(AND(F12<=DATE(2028,5,1),OR(G12="",G12>=DATE(2028,5,1))),H12*(1+Assumptions!$C$7)^3,0) | AX12: =IF(AND(F12<=DATE(2028,6,1),OR(G12="",G12>=DATE(2028,6,1))),H12*(1+Assumptions!$C$7)^3,0) | AY12: =IF(AND(F12<=DATE(2028,7,1),OR(G12="",G12>=DATE(2028,7,1))),H12*(1+Assumptions!$C$7)^3,0) | AZ12: =IF(AND(F12<=DATE(2028,8,1),OR(G12="",G12>=DATE(2028,8,1))),H12*(1+Assumptions!$C$7)^3,0) | BA12: =IF(AND(F12<=DATE(2028,9,1),OR(G12="",G12>=DATE(2028,9,1))),H12*(1+Assumptions!$C$7)^3,0) | BB12: =IF(AND(F12<=DATE(2028,10,1),OR(G12="",G12>=DATE(2028,10,1))),H12*(1+Assumptions!$C$7)^3,0) | BC12: =IF(AND(F12<=DATE(2028,11,1),OR(G12="",G12>=DATE(2028,11,1))),H12*(1+Assumptions!$C$7)^3,0) | BD12: =IF(AND(F12<=DATE(2028,12,1),OR(G12="",G12>=DATE(2028,12,1))),H12*(1+Assumptions!$C$7)^3,0) | BE12: =IF(AND(F12<=DATE(2029,1,1),OR(G12="",G12>=DATE(2029,1,1))),H12*(1+Assumptions!$C$7)^4,0) | BF12: =IF(AND(F12<=DATE(2029,2,1),OR(G12="",G12>=DATE(2029,2,1))),H12*(1+Assumptions!$C$7)^4,0) | BG12: =IF(AND(F12<=DATE(2029,3,1),OR(G12="",G12>=DATE(2029,3,1))),H12*(1+Assumptions!$C$7)^4,0) | BH12: =IF(AND(F12<=DATE(2029,4,1),OR(G12="",G12>=DATE(2029,4,1))),H12*(1+Assumptions!$C$7)^4,0) | BI12: =IF(AND(F12<=DATE(2029,5,1),OR(G12="",G12>=DATE(2029,5,1))),H12*(1+Assumptions!$C$7)^4,0) | BJ12: =IF(AND(F12<=DATE(2029,6,1),OR(G12="",G12>=DATE(2029,6,1))),H12*(1+Assumptions!$C$7)^4,0) | BK12: =IF(AND(F12<=DATE(2029,7,1),OR(G12="",G12>=DATE(2029,7,1))),H12*(1+Assumptions!$C$7)^4,0) | BL12: =IF(AND(F12<=DATE(2029,8,1),OR(G12="",G12>=DATE(2029,8,1))),H12*(1+Assumptions!$C$7)^4,0) | BM12: =IF(AND(F12<=DATE(2029,9,1),OR(G12="",G12>=DATE(2029,9,1))),H12*(1+Assumptions!$C$7)^4,0) | BN12: =IF(AND(F12<=DATE(2029,10,1),OR(G12="",G12>=DATE(2029,10,1))),H12*(1+Assumptions!$C$7)^4,0) | BO12: =IF(AND(F12<=DATE(2029,11,1),OR(G12="",G12>=DATE(2029,11,1))),H12*(1+Assumptions!$C$7)^4,0) | BP12: =IF(AND(F12<=DATE(2029,12,1),OR(G12="",G12>=DATE(2029,12,1))),H12*(1+Assumptions!$C$7)^4,0) | BR12: paid this month if started and not yet left; +8% each calendar year
A13: 10 | B13: CEO | C13: G&A | D13: CEO | E13: Current | F13: 46266 | H13: 11500 | I13: =IF(AND(F13<=DATE(2025,1,1),OR(G13="",G13>=DATE(2025,1,1))),H13*(1+Assumptions!$C$7)^0,0) | J13: =IF(AND(F13<=DATE(2025,2,1),OR(G13="",G13>=DATE(2025,2,1))),H13*(1+Assumptions!$C$7)^0,0) | K13: =IF(AND(F13<=DATE(2025,3,1),OR(G13="",G13>=DATE(2025,3,1))),H13*(1+Assumptions!$C$7)^0,0) | L13: =IF(AND(F13<=DATE(2025,4,1),OR(G13="",G13>=DATE(2025,4,1))),H13*(1+Assumptions!$C$7)^0,0) | M13: =IF(AND(F13<=DATE(2025,5,1),OR(G13="",G13>=DATE(2025,5,1))),H13*(1+Assumptions!$C$7)^0,0) | N13: =IF(AND(F13<=DATE(2025,6,1),OR(G13="",G13>=DATE(2025,6,1))),H13*(1+Assumptions!$C$7)^0,0) | O13: =IF(AND(F13<=DATE(2025,7,1),OR(G13="",G13>=DATE(2025,7,1))),H13*(1+Assumptions!$C$7)^0,0) | P13: =IF(AND(F13<=DATE(2025,8,1),OR(G13="",G13>=DATE(2025,8,1))),H13*(1+Assumptions!$C$7)^0,0) | Q13: 7500 | R13: 7500 | S13: 7500 | T13: 7500 | U13: 7500 | V13: 7500 | W13: 7500 | X13: 7500 | Y13: 7500 | Z13: 7500 | AA13: 7500 | AB13: 7500 | AC13: =IF(AND(F13<=DATE(2026,9,1),OR(G13="",G13>=DATE(2026,9,1))),H13*(1+Assumptions!$C$7)^1,0) | AD13: =IF(AND(F13<=DATE(2026,10,1),OR(G13="",G13>=DATE(2026,10,1))),H13*(1+Assumptions!$C$7)^1,0) | AE13: =IF(AND(F13<=DATE(2026,11,1),OR(G13="",G13>=DATE(2026,11,1))),H13*(1+Assumptions!$C$7)^1,0) | AF13: =IF(AND(F13<=DATE(2026,12,1),OR(G13="",G13>=DATE(2026,12,1))),H13*(1+Assumptions!$C$7)^1,0) | AG13: =IF(AND(F13<=DATE(2027,1,1),OR(G13="",G13>=DATE(2027,1,1))),H13*(1+Assumptions!$C$7)^2,0) | AH13: =IF(AND(F13<=DATE(2027,2,1),OR(G13="",G13>=DATE(2027,2,1))),H13*(1+Assumptions!$C$7)^2,0) | AI13: =IF(AND(F13<=DATE(2027,3,1),OR(G13="",G13>=DATE(2027,3,1))),H13*(1+Assumptions!$C$7)^2,0) | AJ13: =IF(AND(F13<=DATE(2027,4,1),OR(G13="",G13>=DATE(2027,4,1))),H13*(1+Assumptions!$C$7)^2,0) | AK13: =IF(AND(F13<=DATE(2027,5,1),OR(G13="",G13>=DATE(2027,5,1))),H13*(1+Assumptions!$C$7)^2,0) | AL13: =IF(AND(F13<=DATE(2027,6,1),OR(G13="",G13>=DATE(2027,6,1))),H13*(1+Assumptions!$C$7)^2,0) | AM13: =IF(AND(F13<=DATE(2027,7,1),OR(G13="",G13>=DATE(2027,7,1))),H13*(1+Assumptions!$C$7)^2,0) | AN13: =IF(AND(F13<=DATE(2027,8,1),OR(G13="",G13>=DATE(2027,8,1))),H13*(1+Assumptions!$C$7)^2,0) | AO13: =IF(AND(F13<=DATE(2027,9,1),OR(G13="",G13>=DATE(2027,9,1))),H13*(1+Assumptions!$C$7)^2,0) | AP13: =IF(AND(F13<=DATE(2027,10,1),OR(G13="",G13>=DATE(2027,10,1))),H13*(1+Assumptions!$C$7)^2,0) | AQ13: =IF(AND(F13<=DATE(2027,11,1),OR(G13="",G13>=DATE(2027,11,1))),H13*(1+Assumptions!$C$7)^2,0) | AR13: =IF(AND(F13<=DATE(2027,12,1),OR(G13="",G13>=DATE(2027,12,1))),H13*(1+Assumptions!$C$7)^2,0) | AS13: =IF(AND(F13<=DATE(2028,1,1),OR(G13="",G13>=DATE(2028,1,1))),H13*(1+Assumptions!$C$7)^3,0) | AT13: =IF(AND(F13<=DATE(2028,2,1),OR(G13="",G13>=DATE(2028,2,1))),H13*(1+Assumptions!$C$7)^3,0) | AU13: =IF(AND(F13<=DATE(2028,3,1),OR(G13="",G13>=DATE(2028,3,1))),H13*(1+Assumptions!$C$7)^3,0) | AV13: =IF(AND(F13<=DATE(2028,4,1),OR(G13="",G13>=DATE(2028,4,1))),H13*(1+Assumptions!$C$7)^3,0) | AW13: =IF(AND(F13<=DATE(2028,5,1),OR(G13="",G13>=DATE(2028,5,1))),H13*(1+Assumptions!$C$7)^3,0) | AX13: =IF(AND(F13<=DATE(2028,6,1),OR(G13="",G13>=DATE(2028,6,1))),H13*(1+Assumptions!$C$7)^3,0) | AY13: =IF(AND(F13<=DATE(2028,7,1),OR(G13="",G13>=DATE(2028,7,1))),H13*(1+Assumptions!$C$7)^3,0) | AZ13: =IF(AND(F13<=DATE(2028,8,1),OR(G13="",G13>=DATE(2028,8,1))),H13*(1+Assumptions!$C$7)^3,0) | BA13: =IF(AND(F13<=DATE(2028,9,1),OR(G13="",G13>=DATE(2028,9,1))),H13*(1+Assumptions!$C$7)^3,0) | BB13: =IF(AND(F13<=DATE(2028,10,1),OR(G13="",G13>=DATE(2028,10,1))),H13*(1+Assumptions!$C$7)^3,0) | BC13: =IF(AND(F13<=DATE(2028,11,1),OR(G13="",G13>=DATE(2028,11,1))),H13*(1+Assumptions!$C$7)^3,0) | BD13: =IF(AND(F13<=DATE(2028,12,1),OR(G13="",G13>=DATE(2028,12,1))),H13*(1+Assumptions!$C$7)^3,0) | BE13: =IF(AND(F13<=DATE(2029,1,1),OR(G13="",G13>=DATE(2029,1,1))),H13*(1+Assumptions!$C$7)^4,0) | BF13: =IF(AND(F13<=DATE(2029,2,1),OR(G13="",G13>=DATE(2029,2,1))),H13*(1+Assumptions!$C$7)^4,0) | BG13: =IF(AND(F13<=DATE(2029,3,1),OR(G13="",G13>=DATE(2029,3,1))),H13*(1+Assumptions!$C$7)^4,0) | BH13: =IF(AND(F13<=DATE(2029,4,1),OR(G13="",G13>=DATE(2029,4,1))),H13*(1+Assumptions!$C$7)^4,0) | BI13: =IF(AND(F13<=DATE(2029,5,1),OR(G13="",G13>=DATE(2029,5,1))),H13*(1+Assumptions!$C$7)^4,0) | BJ13: =IF(AND(F13<=DATE(2029,6,1),OR(G13="",G13>=DATE(2029,6,1))),H13*(1+Assumptions!$C$7)^4,0) | BK13: =IF(AND(F13<=DATE(2029,7,1),OR(G13="",G13>=DATE(2029,7,1))),H13*(1+Assumptions!$C$7)^4,0) | BL13: =IF(AND(F13<=DATE(2029,8,1),OR(G13="",G13>=DATE(2029,8,1))),H13*(1+Assumptions!$C$7)^4,0) | BM13: =IF(AND(F13<=DATE(2029,9,1),OR(G13="",G13>=DATE(2029,9,1))),H13*(1+Assumptions!$C$7)^4,0) | BN13: =IF(AND(F13<=DATE(2029,10,1),OR(G13="",G13>=DATE(2029,10,1))),H13*(1+Assumptions!$C$7)^4,0) | BO13: =IF(AND(F13<=DATE(2029,11,1),OR(G13="",G13>=DATE(2029,11,1))),H13*(1+Assumptions!$C$7)^4,0) | BP13: =IF(AND(F13<=DATE(2029,12,1),OR(G13="",G13>=DATE(2029,12,1))),H13*(1+Assumptions!$C$7)^4,0) | BR13: paid this month if started and not yet left; +8% each calendar year
A15: # | B15: PLANNED HIRES
A16: 11 | B16: New hire | C16: R&D | D16: Software Engineer | E16: Planned | F16: 46327 | H16: 8000 | I16: =IF(AND($F16<=I$2, OR($G16="",$G16>=I$2)), $H16 * (1 + Assumptions!$C$7) ^ INT(((YEAR(I$2)-YEAR($F16))*12 + MONTH(I$2)-MONTH($F16)) / 12), 0) | J16: =IF(AND($F16<=J$2, OR($G16="",$G16>=J$2)), $H16 * (1 + Assumptions!$C$7) ^ INT(((YEAR(J$2)-YEAR($F16))*12 + MONTH(J$2)-MONTH($F16)) / 12), 0) | K16: =IF(AND($F16<=K$2, OR($G16="",$G16>=K$2)), $H16 * (1 + Assumptions!$C$7) ^ INT(((YEAR(K$2)-YEAR($F16))*12 + MONTH(K$2)-MONTH($F16)) / 12), 0) | L16: =IF(AND($F16<=L$2, OR($G16="",$G16>=L$2)), $H16 * (1 + Assumptions!$C$7) ^ INT(((YEAR(L$2)-YEAR($F16))*12 + MONTH(L$2)-MONTH($F16)) / 12), 0) | M16: =IF(AND($F16<=M$2, OR($G16="",$G16>=M$2)), $H16 * (1 + Assumptions!$C$7) ^ INT(((YEAR(M$2)-YEAR($F16))*12 + MONTH(M$2)-MONTH($F16)) / 12), 0) | N16: =IF(AND($F16<=N$2, OR($G16="",$G16>=N$2)), $H16 * (1 + Assumptions!$C$7) ^ INT(((YEAR(N$2)-YEAR($F16))*12 + MONTH(N$2)-MONTH($F16)) / 12), 0) | O16: =IF(AND($F16<=O$2, OR($G16="",$G16>=O$2)), $H16 * (1 + Assumptions!$C$7) ^ INT(((YEAR(O$2)-YEAR($F16))*12 + MONTH(O$2)-MONTH($F16)) / 12), 0) | P16: =IF(AND($F16<=P$2, OR($G16="",$G16>=P$2)), $H16 * (1 + Assumptions!$C$7) ^ INT(((YEAR(P$2)-YEAR($F16))*12 + MONTH(P$2)-MONTH($F16)) / 12), 0) | ... BP16: =IF(AND($F16<=BP$2, OR($G16="",$G16>=BP$2)), $H16 * (1 + Assumptions!$C$7) ^ INT(((YEAR(BP$2)-YEAR($F16))*12 + MONTH(BP$2)-MONTH($F16)) / 12), 0) | BR16: paid this month if started and not yet left; +8% on each work anniversary
A17: 12 | B17: New hire | C17: G&A | D17: COO | E17: Planned | F17: 46266 | H17: 9000 | I17: =IF(AND($F17<=I$2, OR($G17="",$G17>=I$2)), $H17 * (1 + Assumptions!$C$7) ^ INT(((YEAR(I$2)-YEAR($F17))*12 + MONTH(I$2)-MONTH($F17)) / 12), 0) | J17: =IF(AND($F17<=J$2, OR($G17="",$G17>=J$2)), $H17 * (1 + Assumptions!$C$7) ^ INT(((YEAR(J$2)-YEAR($F17))*12 + MONTH(J$2)-MONTH($F17)) / 12), 0) | K17: =IF(AND($F17<=K$2, OR($G17="",$G17>=K$2)), $H17 * (1 + Assumptions!$C$7) ^ INT(((YEAR(K$2)-YEAR($F17))*12 + MONTH(K$2)-MONTH($F17)) / 12), 0) | L17: =IF(AND($F17<=L$2, OR($G17="",$G17>=L$2)), $H17 * (1 + Assumptions!$C$7) ^ INT(((YEAR(L$2)-YEAR($F17))*12 + MONTH(L$2)-MONTH($F17)) / 12), 0) | M17: =IF(AND($F17<=M$2, OR($G17="",$G17>=M$2)), $H17 * (1 + Assumptions!$C$7) ^ INT(((YEAR(M$2)-YEAR($F17))*12 + MONTH(M$2)-MONTH($F17)) / 12), 0) | N17: =IF(AND($F17<=N$2, OR($G17="",$G17>=N$2)), $H17 * (1 + Assumptions!$C$7) ^ INT(((YEAR(N$2)-YEAR($F17))*12 + MONTH(N$2)-MONTH($F17)) / 12), 0) | O17: =IF(AND($F17<=O$2, OR($G17="",$G17>=O$2)), $H17 * (1 + Assumptions!$C$7) ^ INT(((YEAR(O$2)-YEAR($F17))*12 + MONTH(O$2)-MONTH($F17)) / 12), 0) | P17: =IF(AND($F17<=P$2, OR($G17="",$G17>=P$2)), $H17 * (1 + Assumptions!$C$7) ^ INT(((YEAR(P$2)-YEAR($F17))*12 + MONTH(P$2)-MONTH($F17)) / 12), 0) | ... BP17: =IF(AND($F17<=BP$2, OR($G17="",$G17>=BP$2)), $H17 * (1 + Assumptions!$C$7) ^ INT(((YEAR(BP$2)-YEAR($F17))*12 + MONTH(BP$2)-MONTH($F17)) / 12), 0) | BR17: paid this month if started and not yet left; +8% on each work anniversary
A18: 13 | B18: New hire | C18: R&D | D18: Maintenance Engineer | E18: Planned | F18: 46267 | H18: 6000 | I18: =IF(AND($F18<=I$2, OR($G18="",$G18>=I$2)), $H18 * (1 + Assumptions!$C$7) ^ INT(((YEAR(I$2)-YEAR($F18))*12 + MONTH(I$2)-MONTH($F18)) / 12), 0) | J18: =IF(AND($F18<=J$2, OR($G18="",$G18>=J$2)), $H18 * (1 + Assumptions!$C$7) ^ INT(((YEAR(J$2)-YEAR($F18))*12 + MONTH(J$2)-MONTH($F18)) / 12), 0) | K18: =IF(AND($F18<=K$2, OR($G18="",$G18>=K$2)), $H18 * (1 + Assumptions!$C$7) ^ INT(((YEAR(K$2)-YEAR($F18))*12 + MONTH(K$2)-MONTH($F18)) / 12), 0) | L18: =IF(AND($F18<=L$2, OR($G18="",$G18>=L$2)), $H18 * (1 + Assumptions!$C$7) ^ INT(((YEAR(L$2)-YEAR($F18))*12 + MONTH(L$2)-MONTH($F18)) / 12), 0) | M18: =IF(AND($F18<=M$2, OR($G18="",$G18>=M$2)), $H18 * (1 + Assumptions!$C$7) ^ INT(((YEAR(M$2)-YEAR($F18))*12 + MONTH(M$2)-MONTH($F18)) / 12), 0) | N18: =IF(AND($F18<=N$2, OR($G18="",$G18>=N$2)), $H18 * (1 + Assumptions!$C$7) ^ INT(((YEAR(N$2)-YEAR($F18))*12 + MONTH(N$2)-MONTH($F18)) / 12), 0) | O18: =IF(AND($F18<=O$2, OR($G18="",$G18>=O$2)), $H18 * (1 + Assumptions!$C$7) ^ INT(((YEAR(O$2)-YEAR($F18))*12 + MONTH(O$2)-MONTH($F18)) / 12), 0) | P18: =IF(AND($F18<=P$2, OR($G18="",$G18>=P$2)), $H18 * (1 + Assumptions!$C$7) ^ INT(((YEAR(P$2)-YEAR($F18))*12 + MONTH(P$2)-MONTH($F18)) / 12), 0) | ... BP18: =IF(AND($F18<=BP$2, OR($G18="",$G18>=BP$2)), $H18 * (1 + Assumptions!$C$7) ^ INT(((YEAR(BP$2)-YEAR($F18))*12 + MONTH(BP$2)-MONTH($F18)) / 12), 0) | BR18: paid this month if started and not yet left; +8% on each work anniversary
A19: 14 | B19: New hire | C19: S&M | D19: Marketing | E19: Planned | F19: 46268 | H19: 9000 | I19: =IF(AND($F19<=I$2, OR($G19="",$G19>=I$2)), $H19 * (1 + Assumptions!$C$7) ^ INT(((YEAR(I$2)-YEAR($F19))*12 + MONTH(I$2)-MONTH($F19)) / 12), 0) | J19: =IF(AND($F19<=J$2, OR($G19="",$G19>=J$2)), $H19 * (1 + Assumptions!$C$7) ^ INT(((YEAR(J$2)-YEAR($F19))*12 + MONTH(J$2)-MONTH($F19)) / 12), 0) | K19: =IF(AND($F19<=K$2, OR($G19="",$G19>=K$2)), $H19 * (1 + Assumptions!$C$7) ^ INT(((YEAR(K$2)-YEAR($F19))*12 + MONTH(K$2)-MONTH($F19)) / 12), 0) | L19: =IF(AND($F19<=L$2, OR($G19="",$G19>=L$2)), $H19 * (1 + Assumptions!$C$7) ^ INT(((YEAR(L$2)-YEAR($F19))*12 + MONTH(L$2)-MONTH($F19)) / 12), 0) | M19: =IF(AND($F19<=M$2, OR($G19="",$G19>=M$2)), $H19 * (1 + Assumptions!$C$7) ^ INT(((YEAR(M$2)-YEAR($F19))*12 + MONTH(M$2)-MONTH($F19)) / 12), 0) | N19: =IF(AND($F19<=N$2, OR($G19="",$G19>=N$2)), $H19 * (1 + Assumptions!$C$7) ^ INT(((YEAR(N$2)-YEAR($F19))*12 + MONTH(N$2)-MONTH($F19)) / 12), 0) | O19: =IF(AND($F19<=O$2, OR($G19="",$G19>=O$2)), $H19 * (1 + Assumptions!$C$7) ^ INT(((YEAR(O$2)-YEAR($F19))*12 + MONTH(O$2)-MONTH($F19)) / 12), 0) | P19: =IF(AND($F19<=P$2, OR($G19="",$G19>=P$2)), $H19 * (1 + Assumptions!$C$7) ^ INT(((YEAR(P$2)-YEAR($F19))*12 + MONTH(P$2)-MONTH($F19)) / 12), 0) | ... BP19: =IF(AND($F19<=BP$2, OR($G19="",$G19>=BP$2)), $H19 * (1 + Assumptions!$C$7) ^ INT(((YEAR(BP$2)-YEAR($F19))*12 + MONTH(BP$2)-MONTH($F19)) / 12), 0) | BR19: paid this month if started and not yet left; +8% on each work anniversary
A20: 15 | B20: New hire | C20: G&A | D20: CFO | E20: Planned | F20: 46327 | H20: 9500 | I20: =IF(AND($F20<=I$2, OR($G20="",$G20>=I$2)), $H20 * (1 + Assumptions!$C$7) ^ INT(((YEAR(I$2)-YEAR($F20))*12 + MONTH(I$2)-MONTH($F20)) / 12), 0) | J20: =IF(AND($F20<=J$2, OR($G20="",$G20>=J$2)), $H20 * (1 + Assumptions!$C$7) ^ INT(((YEAR(J$2)-YEAR($F20))*12 + MONTH(J$2)-MONTH($F20)) / 12), 0) | K20: =IF(AND($F20<=K$2, OR($G20="",$G20>=K$2)), $H20 * (1 + Assumptions!$C$7) ^ INT(((YEAR(K$2)-YEAR($F20))*12 + MONTH(K$2)-MONTH($F20)) / 12), 0) | L20: =IF(AND($F20<=L$2, OR($G20="",$G20>=L$2)), $H20 * (1 + Assumptions!$C$7) ^ INT(((YEAR(L$2)-YEAR($F20))*12 + MONTH(L$2)-MONTH($F20)) / 12), 0) | M20: =IF(AND($F20<=M$2, OR($G20="",$G20>=M$2)), $H20 * (1 + Assumptions!$C$7) ^ INT(((YEAR(M$2)-YEAR($F20))*12 + MONTH(M$2)-MONTH($F20)) / 12), 0) | N20: =IF(AND($F20<=N$2, OR($G20="",$G20>=N$2)), $H20 * (1 + Assumptions!$C$7) ^ INT(((YEAR(N$2)-YEAR($F20))*12 + MONTH(N$2)-MONTH($F20)) / 12), 0) | O20: =IF(AND($F20<=O$2, OR($G20="",$G20>=O$2)), $H20 * (1 + Assumptions!$C$7) ^ INT(((YEAR(O$2)-YEAR($F20))*12 + MONTH(O$2)-MONTH($F20)) / 12), 0) | P20: =IF(AND($F20<=P$2, OR($G20="",$G20>=P$2)), $H20 * (1 + Assumptions!$C$7) ^ INT(((YEAR(P$2)-YEAR($F20))*12 + MONTH(P$2)-MONTH($F20)) / 12), 0) | ... BP20: =IF(AND($F20<=BP$2, OR($G20="",$G20>=BP$2)), $H20 * (1 + Assumptions!$C$7) ^ INT(((YEAR(BP$2)-YEAR($F20))*12 + MONTH(BP$2)-MONTH($F20)) / 12), 0) | BR20: paid this month if started and not yet left; +8% on each work anniversary
A21: 16 | B21: New hire | C21: S&M | D21: Sales | E21: Planned | F21: 46327 | H21: 6500 | I21: =IF(AND($F21<=I$2, OR($G21="",$G21>=I$2)), $H21 * (1 + Assumptions!$C$7) ^ INT(((YEAR(I$2)-YEAR($F21))*12 + MONTH(I$2)-MONTH($F21)) / 12), 0) | J21: =IF(AND($F21<=J$2, OR($G21="",$G21>=J$2)), $H21 * (1 + Assumptions!$C$7) ^ INT(((YEAR(J$2)-YEAR($F21))*12 + MONTH(J$2)-MONTH($F21)) / 12), 0) | K21: =IF(AND($F21<=K$2, OR($G21="",$G21>=K$2)), $H21 * (1 + Assumptions!$C$7) ^ INT(((YEAR(K$2)-YEAR($F21))*12 + MONTH(K$2)-MONTH($F21)) / 12), 0) | L21: =IF(AND($F21<=L$2, OR($G21="",$G21>=L$2)), $H21 * (1 + Assumptions!$C$7) ^ INT(((YEAR(L$2)-YEAR($F21))*12 + MONTH(L$2)-MONTH($F21)) / 12), 0) | M21: =IF(AND($F21<=M$2, OR($G21="",$G21>=M$2)), $H21 * (1 + Assumptions!$C$7) ^ INT(((YEAR(M$2)-YEAR($F21))*12 + MONTH(M$2)-MONTH($F21)) / 12), 0) | N21: =IF(AND($F21<=N$2, OR($G21="",$G21>=N$2)), $H21 * (1 + Assumptions!$C$7) ^ INT(((YEAR(N$2)-YEAR($F21))*12 + MONTH(N$2)-MONTH($F21)) / 12), 0) | O21: =IF(AND($F21<=O$2, OR($G21="",$G21>=O$2)), $H21 * (1 + Assumptions!$C$7) ^ INT(((YEAR(O$2)-YEAR($F21))*12 + MONTH(O$2)-MONTH($F21)) / 12), 0) | P21: =IF(AND($F21<=P$2, OR($G21="",$G21>=P$2)), $H21 * (1 + Assumptions!$C$7) ^ INT(((YEAR(P$2)-YEAR($F21))*12 + MONTH(P$2)-MONTH($F21)) / 12), 0) | ... BP21: =IF(AND($F21<=BP$2, OR($G21="",$G21>=BP$2)), $H21 * (1 + Assumptions!$C$7) ^ INT(((YEAR(BP$2)-YEAR($F21))*12 + MONTH(BP$2)-MONTH($F21)) / 12), 0) | BR21: paid this month if started and not yet left; +8% on each work anniversary
A22: 17 | B22: New hire | C22: R&D | D22: R&D Engineer | E22: Planned | F22: 46388 | H22: 7500 | I22: =IF(AND($F22<=I$2, OR($G22="",$G22>=I$2)), $H22 * (1 + Assumptions!$C$7) ^ INT(((YEAR(I$2)-YEAR($F22))*12 + MONTH(I$2)-MONTH($F22)) / 12), 0) | J22: =IF(AND($F22<=J$2, OR($G22="",$G22>=J$2)), $H22 * (1 + Assumptions!$C$7) ^ INT(((YEAR(J$2)-YEAR($F22))*12 + MONTH(J$2)-MONTH($F22)) / 12), 0) | K22: =IF(AND($F22<=K$2, OR($G22="",$G22>=K$2)), $H22 * (1 + Assumptions!$C$7) ^ INT(((YEAR(K$2)-YEAR($F22))*12 + MONTH(K$2)-MONTH($F22)) / 12), 0) | L22: =IF(AND($F22<=L$2, OR($G22="",$G22>=L$2)), $H22 * (1 + Assumptions!$C$7) ^ INT(((YEAR(L$2)-YEAR($F22))*12 + MONTH(L$2)-MONTH($F22)) / 12), 0) | M22: =IF(AND($F22<=M$2, OR($G22="",$G22>=M$2)), $H22 * (1 + Assumptions!$C$7) ^ INT(((YEAR(M$2)-YEAR($F22))*12 + MONTH(M$2)-MONTH($F22)) / 12), 0) | N22: =IF(AND($F22<=N$2, OR($G22="",$G22>=N$2)), $H22 * (1 + Assumptions!$C$7) ^ INT(((YEAR(N$2)-YEAR($F22))*12 + MONTH(N$2)-MONTH($F22)) / 12), 0) | O22: =IF(AND($F22<=O$2, OR($G22="",$G22>=O$2)), $H22 * (1 + Assumptions!$C$7) ^ INT(((YEAR(O$2)-YEAR($F22))*12 + MONTH(O$2)-MONTH($F22)) / 12), 0) | P22: =IF(AND($F22<=P$2, OR($G22="",$G22>=P$2)), $H22 * (1 + Assumptions!$C$7) ^ INT(((YEAR(P$2)-YEAR($F22))*12 + MONTH(P$2)-MONTH($F22)) / 12), 0) | ... BP22: =IF(AND($F22<=BP$2, OR($G22="",$G22>=BP$2)), $H22 * (1 + Assumptions!$C$7) ^ INT(((YEAR(BP$2)-YEAR($F22))*12 + MONTH(BP$2)-MONTH($F22)) / 12), 0) | BR22: paid this month if started and not yet left; +8% on each work anniversary
A23: 18 | B23: New hire | C23: G&A | D23: Office Support | E23: Planned | F23: 46388 | H23: 4500 | I23: =IF(AND($F23<=I$2, OR($G23="",$G23>=I$2)), $H23 * (1 + Assumptions!$C$7) ^ INT(((YEAR(I$2)-YEAR($F23))*12 + MONTH(I$2)-MONTH($F23)) / 12), 0) | J23: =IF(AND($F23<=J$2, OR($G23="",$G23>=J$2)), $H23 * (1 + Assumptions!$C$7) ^ INT(((YEAR(J$2)-YEAR($F23))*12 + MONTH(J$2)-MONTH($F23)) / 12), 0) | K23: =IF(AND($F23<=K$2, OR($G23="",$G23>=K$2)), $H23 * (1 + Assumptions!$C$7) ^ INT(((YEAR(K$2)-YEAR($F23))*12 + MONTH(K$2)-MONTH($F23)) / 12), 0) | L23: =IF(AND($F23<=L$2, OR($G23="",$G23>=L$2)), $H23 * (1 + Assumptions!$C$7) ^ INT(((YEAR(L$2)-YEAR($F23))*12 + MONTH(L$2)-MONTH($F23)) / 12), 0) | M23: =IF(AND($F23<=M$2, OR($G23="",$G23>=M$2)), $H23 * (1 + Assumptions!$C$7) ^ INT(((YEAR(M$2)-YEAR($F23))*12 + MONTH(M$2)-MONTH($F23)) / 12), 0) | N23: =IF(AND($F23<=N$2, OR($G23="",$G23>=N$2)), $H23 * (1 + Assumptions!$C$7) ^ INT(((YEAR(N$2)-YEAR($F23))*12 + MONTH(N$2)-MONTH($F23)) / 12), 0) | O23: =IF(AND($F23<=O$2, OR($G23="",$G23>=O$2)), $H23 * (1 + Assumptions!$C$7) ^ INT(((YEAR(O$2)-YEAR($F23))*12 + MONTH(O$2)-MONTH($F23)) / 12), 0) | P23: =IF(AND($F23<=P$2, OR($G23="",$G23>=P$2)), $H23 * (1 + Assumptions!$C$7) ^ INT(((YEAR(P$2)-YEAR($F23))*12 + MONTH(P$2)-MONTH($F23)) / 12), 0) | ... BP23: =IF(AND($F23<=BP$2, OR($G23="",$G23>=BP$2)), $H23 * (1 + Assumptions!$C$7) ^ INT(((YEAR(BP$2)-YEAR($F23))*12 + MONTH(BP$2)-MONTH($F23)) / 12), 0) | BR23: paid this month if started and not yet left; +8% on each work anniversary
A24: 19 | B24: New hire | C24: R&D | D24: Product | E24: Planned | F24: 46388 | H24: 6500 | I24: =IF(AND($F24<=I$2, OR($G24="",$G24>=I$2)), $H24 * (1 + Assumptions!$C$7) ^ INT(((YEAR(I$2)-YEAR($F24))*12 + MONTH(I$2)-MONTH($F24)) / 12), 0) | J24: =IF(AND($F24<=J$2, OR($G24="",$G24>=J$2)), $H24 * (1 + Assumptions!$C$7) ^ INT(((YEAR(J$2)-YEAR($F24))*12 + MONTH(J$2)-MONTH($F24)) / 12), 0) | K24: =IF(AND($F24<=K$2, OR($G24="",$G24>=K$2)), $H24 * (1 + Assumptions!$C$7) ^ INT(((YEAR(K$2)-YEAR($F24))*12 + MONTH(K$2)-MONTH($F24)) / 12), 0) | L24: =IF(AND($F24<=L$2, OR($G24="",$G24>=L$2)), $H24 * (1 + Assumptions!$C$7) ^ INT(((YEAR(L$2)-YEAR($F24))*12 + MONTH(L$2)-MONTH($F24)) / 12), 0) | M24: =IF(AND($F24<=M$2, OR($G24="",$G24>=M$2)), $H24 * (1 + Assumptions!$C$7) ^ INT(((YEAR(M$2)-YEAR($F24))*12 + MONTH(M$2)-MONTH($F24)) / 12), 0) | N24: =IF(AND($F24<=N$2, OR($G24="",$G24>=N$2)), $H24 * (1 + Assumptions!$C$7) ^ INT(((YEAR(N$2)-YEAR($F24))*12 + MONTH(N$2)-MONTH($F24)) / 12), 0) | O24: =IF(AND($F24<=O$2, OR($G24="",$G24>=O$2)), $H24 * (1 + Assumptions!$C$7) ^ INT(((YEAR(O$2)-YEAR($F24))*12 + MONTH(O$2)-MONTH($F24)) / 12), 0) | P24: =IF(AND($F24<=P$2, OR($G24="",$G24>=P$2)), $H24 * (1 + Assumptions!$C$7) ^ INT(((YEAR(P$2)-YEAR($F24))*12 + MONTH(P$2)-MONTH($F24)) / 12), 0) | ... BP24: =IF(AND($F24<=BP$2, OR($G24="",$G24>=BP$2)), $H24 * (1 + Assumptions!$C$7) ^ INT(((YEAR(BP$2)-YEAR($F24))*12 + MONTH(BP$2)-MONTH($F24)) / 12), 0) | BR24: paid this month if started and not yet left; +8% on each work anniversary
A25: 20 | B25: New hire | C25: G&A | D25: Logistics | E25: Planned | F25: 46388 | H25: 6500 | I25: =IF(AND($F25<=I$2, OR($G25="",$G25>=I$2)), $H25 * (1 + Assumptions!$C$7) ^ INT(((YEAR(I$2)-YEAR($F25))*12 + MONTH(I$2)-MONTH($F25)) / 12), 0) | J25: =IF(AND($F25<=J$2, OR($G25="",$G25>=J$2)), $H25 * (1 + Assumptions!$C$7) ^ INT(((YEAR(J$2)-YEAR($F25))*12 + MONTH(J$2)-MONTH($F25)) / 12), 0) | K25: =IF(AND($F25<=K$2, OR($G25="",$G25>=K$2)), $H25 * (1 + Assumptions!$C$7) ^ INT(((YEAR(K$2)-YEAR($F25))*12 + MONTH(K$2)-MONTH($F25)) / 12), 0) | L25: =IF(AND($F25<=L$2, OR($G25="",$G25>=L$2)), $H25 * (1 + Assumptions!$C$7) ^ INT(((YEAR(L$2)-YEAR($F25))*12 + MONTH(L$2)-MONTH($F25)) / 12), 0) | M25: =IF(AND($F25<=M$2, OR($G25="",$G25>=M$2)), $H25 * (1 + Assumptions!$C$7) ^ INT(((YEAR(M$2)-YEAR($F25))*12 + MONTH(M$2)-MONTH($F25)) / 12), 0) | N25: =IF(AND($F25<=N$2, OR($G25="",$G25>=N$2)), $H25 * (1 + Assumptions!$C$7) ^ INT(((YEAR(N$2)-YEAR($F25))*12 + MONTH(N$2)-MONTH($F25)) / 12), 0) | O25: =IF(AND($F25<=O$2, OR($G25="",$G25>=O$2)), $H25 * (1 + Assumptions!$C$7) ^ INT(((YEAR(O$2)-YEAR($F25))*12 + MONTH(O$2)-MONTH($F25)) / 12), 0) | P25: =IF(AND($F25<=P$2, OR($G25="",$G25>=P$2)), $H25 * (1 + Assumptions!$C$7) ^ INT(((YEAR(P$2)-YEAR($F25))*12 + MONTH(P$2)-MONTH($F25)) / 12), 0) | ... BP25: =IF(AND($F25<=BP$2, OR($G25="",$G25>=BP$2)), $H25 * (1 + Assumptions!$C$7) ^ INT(((YEAR(BP$2)-YEAR($F25))*12 + MONTH(BP$2)-MONTH($F25)) / 12), 0) | BR25: paid this month if started and not yet left; +8% on each work anniversary
A26: 21 | B26: New hire | C26: R&D | D26: Field Engineer | E26: Planned | F26: 46388 | H26: 6500 | I26: =IF(AND($F26<=I$2, OR($G26="",$G26>=I$2)), $H26 * (1 + Assumptions!$C$7) ^ INT(((YEAR(I$2)-YEAR($F26))*12 + MONTH(I$2)-MONTH($F26)) / 12), 0) | J26: =IF(AND($F26<=J$2, OR($G26="",$G26>=J$2)), $H26 * (1 + Assumptions!$C$7) ^ INT(((YEAR(J$2)-YEAR($F26))*12 + MONTH(J$2)-MONTH($F26)) / 12), 0) | K26: =IF(AND($F26<=K$2, OR($G26="",$G26>=K$2)), $H26 * (1 + Assumptions!$C$7) ^ INT(((YEAR(K$2)-YEAR($F26))*12 + MONTH(K$2)-MONTH($F26)) / 12), 0) | L26: =IF(AND($F26<=L$2, OR($G26="",$G26>=L$2)), $H26 * (1 + Assumptions!$C$7) ^ INT(((YEAR(L$2)-YEAR($F26))*12 + MONTH(L$2)-MONTH($F26)) / 12), 0) | M26: =IF(AND($F26<=M$2, OR($G26="",$G26>=M$2)), $H26 * (1 + Assumptions!$C$7) ^ INT(((YEAR(M$2)-YEAR($F26))*12 + MONTH(M$2)-MONTH($F26)) / 12), 0) | N26: =IF(AND($F26<=N$2, OR($G26="",$G26>=N$2)), $H26 * (1 + Assumptions!$C$7) ^ INT(((YEAR(N$2)-YEAR($F26))*12 + MONTH(N$2)-MONTH($F26)) / 12), 0) | O26: =IF(AND($F26<=O$2, OR($G26="",$G26>=O$2)), $H26 * (1 + Assumptions!$C$7) ^ INT(((YEAR(O$2)-YEAR($F26))*12 + MONTH(O$2)-MONTH($F26)) / 12), 0) | P26: =IF(AND($F26<=P$2, OR($G26="",$G26>=P$2)), $H26 * (1 + Assumptions!$C$7) ^ INT(((YEAR(P$2)-YEAR($F26))*12 + MONTH(P$2)-MONTH($F26)) / 12), 0) | ... BP26: =IF(AND($F26<=BP$2, OR($G26="",$G26>=BP$2)), $H26 * (1 + Assumptions!$C$7) ^ INT(((YEAR(BP$2)-YEAR($F26))*12 + MONTH(BP$2)-MONTH($F26)) / 12), 0) | BR26: paid this month if started and not yet left; +8% on each work anniversary
A27: 22 | B27: New hire | C27: R&D | D27: Field Engineer | E27: Planned | F27: 46539 | H27: 6500 | I27: =IF(AND($F27<=I$2, OR($G27="",$G27>=I$2)), $H27 * (1 + Assumptions!$C$7) ^ INT(((YEAR(I$2)-YEAR($F27))*12 + MONTH(I$2)-MONTH($F27)) / 12), 0) | J27: =IF(AND($F27<=J$2, OR($G27="",$G27>=J$2)), $H27 * (1 + Assumptions!$C$7) ^ INT(((YEAR(J$2)-YEAR($F27))*12 + MONTH(J$2)-MONTH($F27)) / 12), 0) | K27: =IF(AND($F27<=K$2, OR($G27="",$G27>=K$2)), $H27 * (1 + Assumptions!$C$7) ^ INT(((YEAR(K$2)-YEAR($F27))*12 + MONTH(K$2)-MONTH($F27)) / 12), 0) | L27: =IF(AND($F27<=L$2, OR($G27="",$G27>=L$2)), $H27 * (1 + Assumptions!$C$7) ^ INT(((YEAR(L$2)-YEAR($F27))*12 + MONTH(L$2)-MONTH($F27)) / 12), 0) | M27: =IF(AND($F27<=M$2, OR($G27="",$G27>=M$2)), $H27 * (1 + Assumptions!$C$7) ^ INT(((YEAR(M$2)-YEAR($F27))*12 + MONTH(M$2)-MONTH($F27)) / 12), 0) | N27: =IF(AND($F27<=N$2, OR($G27="",$G27>=N$2)), $H27 * (1 + Assumptions!$C$7) ^ INT(((YEAR(N$2)-YEAR($F27))*12 + MONTH(N$2)-MONTH($F27)) / 12), 0) | O27: =IF(AND($F27<=O$2, OR($G27="",$G27>=O$2)), $H27 * (1 + Assumptions!$C$7) ^ INT(((YEAR(O$2)-YEAR($F27))*12 + MONTH(O$2)-MONTH($F27)) / 12), 0) | P27: =IF(AND($F27<=P$2, OR($G27="",$G27>=P$2)), $H27 * (1 + Assumptions!$C$7) ^ INT(((YEAR(P$2)-YEAR($F27))*12 + MONTH(P$2)-MONTH($F27)) / 12), 0) | ... BP27: =IF(AND($F27<=BP$2, OR($G27="",$G27>=BP$2)), $H27 * (1 + Assumptions!$C$7) ^ INT(((YEAR(BP$2)-YEAR($F27))*12 + MONTH(BP$2)-MONTH($F27)) / 12), 0) | BR27: paid this month if started and not yet left; +8% on each work anniversary
A28: 23 | B28: New hire | C28: S&M | D28: Partner Manager | E28: Planned | F28: =IF(Assumptions!$D$82=2,DATE(2027,2,1),DATE(2027,6,1)) | H28: 7500 | I28: =IF(AND($F28<=I$2, OR($G28="",$G28>=I$2)), $H28 * (1 + Assumptions!$C$7) ^ INT(((YEAR(I$2)-YEAR($F28))*12 + MONTH(I$2)-MONTH($F28)) / 12), 0) | J28: =IF(AND($F28<=J$2, OR($G28="",$G28>=J$2)), $H28 * (1 + Assumptions!$C$7) ^ INT(((YEAR(J$2)-YEAR($F28))*12 + MONTH(J$2)-MONTH($F28)) / 12), 0) | K28: =IF(AND($F28<=K$2, OR($G28="",$G28>=K$2)), $H28 * (1 + Assumptions!$C$7) ^ INT(((YEAR(K$2)-YEAR($F28))*12 + MONTH(K$2)-MONTH($F28)) / 12), 0) | L28: =IF(AND($F28<=L$2, OR($G28="",$G28>=L$2)), $H28 * (1 + Assumptions!$C$7) ^ INT(((YEAR(L$2)-YEAR($F28))*12 + MONTH(L$2)-MONTH($F28)) / 12), 0) | M28: =IF(AND($F28<=M$2, OR($G28="",$G28>=M$2)), $H28 * (1 + Assumptions!$C$7) ^ INT(((YEAR(M$2)-YEAR($F28))*12 + MONTH(M$2)-MONTH($F28)) / 12), 0) | N28: =IF(AND($F28<=N$2, OR($G28="",$G28>=N$2)), $H28 * (1 + Assumptions!$C$7) ^ INT(((YEAR(N$2)-YEAR($F28))*12 + MONTH(N$2)-MONTH($F28)) / 12), 0) | O28: =IF(AND($F28<=O$2, OR($G28="",$G28>=O$2)), $H28 * (1 + Assumptions!$C$7) ^ INT(((YEAR(O$2)-YEAR($F28))*12 + MONTH(O$2)-MONTH($F28)) / 12), 0) | P28: =IF(AND($F28<=P$2, OR($G28="",$G28>=P$2)), $H28 * (1 + Assumptions!$C$7) ^ INT(((YEAR(P$2)-YEAR($F28))*12 + MONTH(P$2)-MONTH($F28)) / 12), 0) | ... BP28: =IF(AND($F28<=BP$2, OR($G28="",$G28>=BP$2)), $H28 * (1 + Assumptions!$C$7) ^ INT(((YEAR(BP$2)-YEAR($F28))*12 + MONTH(BP$2)-MONTH($F28)) / 12), 0) | BR28: paid this month if started and not yet left; +8% on each work anniversary
A29: 24 | B29: New hire | C29: S&M | D29: Marketing | E29: Planned | F29: 46539 | H29: 7500 | I29: =IF(AND($F29<=I$2, OR($G29="",$G29>=I$2)), $H29 * (1 + Assumptions!$C$7) ^ INT(((YEAR(I$2)-YEAR($F29))*12 + MONTH(I$2)-MONTH($F29)) / 12), 0) | J29: =IF(AND($F29<=J$2, OR($G29="",$G29>=J$2)), $H29 * (1 + Assumptions!$C$7) ^ INT(((YEAR(J$2)-YEAR($F29))*12 + MONTH(J$2)-MONTH($F29)) / 12), 0) | K29: =IF(AND($F29<=K$2, OR($G29="",$G29>=K$2)), $H29 * (1 + Assumptions!$C$7) ^ INT(((YEAR(K$2)-YEAR($F29))*12 + MONTH(K$2)-MONTH($F29)) / 12), 0) | L29: =IF(AND($F29<=L$2, OR($G29="",$G29>=L$2)), $H29 * (1 + Assumptions!$C$7) ^ INT(((YEAR(L$2)-YEAR($F29))*12 + MONTH(L$2)-MONTH($F29)) / 12), 0) | M29: =IF(AND($F29<=M$2, OR($G29="",$G29>=M$2)), $H29 * (1 + Assumptions!$C$7) ^ INT(((YEAR(M$2)-YEAR($F29))*12 + MONTH(M$2)-MONTH($F29)) / 12), 0) | N29: =IF(AND($F29<=N$2, OR($G29="",$G29>=N$2)), $H29 * (1 + Assumptions!$C$7) ^ INT(((YEAR(N$2)-YEAR($F29))*12 + MONTH(N$2)-MONTH($F29)) / 12), 0) | O29: =IF(AND($F29<=O$2, OR($G29="",$G29>=O$2)), $H29 * (1 + Assumptions!$C$7) ^ INT(((YEAR(O$2)-YEAR($F29))*12 + MONTH(O$2)-MONTH($F29)) / 12), 0) | P29: =IF(AND($F29<=P$2, OR($G29="",$G29>=P$2)), $H29 * (1 + Assumptions!$C$7) ^ INT(((YEAR(P$2)-YEAR($F29))*12 + MONTH(P$2)-MONTH($F29)) / 12), 0) | ... BP29: =IF(AND($F29<=BP$2, OR($G29="",$G29>=BP$2)), $H29 * (1 + Assumptions!$C$7) ^ INT(((YEAR(BP$2)-YEAR($F29))*12 + MONTH(BP$2)-MONTH($F29)) / 12), 0) | BR29: paid this month if started and not yet left; +8% on each work anniversary
A30: 25 | B30: New hire | C30: S&M | D30: Sales | E30: Planned | F30: =IF(Assumptions!$D$82=2,DATE(2027,1,1),DATE(2027,6,1)) | H30: 7500 | I30: =IF(AND($F30<=I$2, OR($G30="",$G30>=I$2)), $H30 * (1 + Assumptions!$C$7) ^ INT(((YEAR(I$2)-YEAR($F30))*12 + MONTH(I$2)-MONTH($F30)) / 12), 0) | J30: =IF(AND($F30<=J$2, OR($G30="",$G30>=J$2)), $H30 * (1 + Assumptions!$C$7) ^ INT(((YEAR(J$2)-YEAR($F30))*12 + MONTH(J$2)-MONTH($F30)) / 12), 0) | K30: =IF(AND($F30<=K$2, OR($G30="",$G30>=K$2)), $H30 * (1 + Assumptions!$C$7) ^ INT(((YEAR(K$2)-YEAR($F30))*12 + MONTH(K$2)-MONTH($F30)) / 12), 0) | L30: =IF(AND($F30<=L$2, OR($G30="",$G30>=L$2)), $H30 * (1 + Assumptions!$C$7) ^ INT(((YEAR(L$2)-YEAR($F30))*12 + MONTH(L$2)-MONTH($F30)) / 12), 0) | M30: =IF(AND($F30<=M$2, OR($G30="",$G30>=M$2)), $H30 * (1 + Assumptions!$C$7) ^ INT(((YEAR(M$2)-YEAR($F30))*12 + MONTH(M$2)-MONTH($F30)) / 12), 0) | N30: =IF(AND($F30<=N$2, OR($G30="",$G30>=N$2)), $H30 * (1 + Assumptions!$C$7) ^ INT(((YEAR(N$2)-YEAR($F30))*12 + MONTH(N$2)-MONTH($F30)) / 12), 0) | O30: =IF(AND($F30<=O$2, OR($G30="",$G30>=O$2)), $H30 * (1 + Assumptions!$C$7) ^ INT(((YEAR(O$2)-YEAR($F30))*12 + MONTH(O$2)-MONTH($F30)) / 12), 0) | P30: =IF(AND($F30<=P$2, OR($G30="",$G30>=P$2)), $H30 * (1 + Assumptions!$C$7) ^ INT(((YEAR(P$2)-YEAR($F30))*12 + MONTH(P$2)-MONTH($F30)) / 12), 0) | ... BP30: =IF(AND($F30<=BP$2, OR($G30="",$G30>=BP$2)), $H30 * (1 + Assumptions!$C$7) ^ INT(((YEAR(BP$2)-YEAR($F30))*12 + MONTH(BP$2)-MONTH($F30)) / 12), 0) | BR30: paid this month if started and not yet left; +8% on each work anniversary
A31: 26 | B31: New hire | C31: G&A | D31: Finance | E31: Planned | F31: 46753 | H31: 7500 | I31: =IF(AND($F31<=I$2, OR($G31="",$G31>=I$2)), $H31 * (1 + Assumptions!$C$7) ^ INT(((YEAR(I$2)-YEAR($F31))*12 + MONTH(I$2)-MONTH($F31)) / 12), 0) | J31: =IF(AND($F31<=J$2, OR($G31="",$G31>=J$2)), $H31 * (1 + Assumptions!$C$7) ^ INT(((YEAR(J$2)-YEAR($F31))*12 + MONTH(J$2)-MONTH($F31)) / 12), 0) | K31: =IF(AND($F31<=K$2, OR($G31="",$G31>=K$2)), $H31 * (1 + Assumptions!$C$7) ^ INT(((YEAR(K$2)-YEAR($F31))*12 + MONTH(K$2)-MONTH($F31)) / 12), 0) | L31: =IF(AND($F31<=L$2, OR($G31="",$G31>=L$2)), $H31 * (1 + Assumptions!$C$7) ^ INT(((YEAR(L$2)-YEAR($F31))*12 + MONTH(L$2)-MONTH($F31)) / 12), 0) | M31: =IF(AND($F31<=M$2, OR($G31="",$G31>=M$2)), $H31 * (1 + Assumptions!$C$7) ^ INT(((YEAR(M$2)-YEAR($F31))*12 + MONTH(M$2)-MONTH($F31)) / 12), 0) | N31: =IF(AND($F31<=N$2, OR($G31="",$G31>=N$2)), $H31 * (1 + Assumptions!$C$7) ^ INT(((YEAR(N$2)-YEAR($F31))*12 + MONTH(N$2)-MONTH($F31)) / 12), 0) | O31: =IF(AND($F31<=O$2, OR($G31="",$G31>=O$2)), $H31 * (1 + Assumptions!$C$7) ^ INT(((YEAR(O$2)-YEAR($F31))*12 + MONTH(O$2)-MONTH($F31)) / 12), 0) | P31: =IF(AND($F31<=P$2, OR($G31="",$G31>=P$2)), $H31 * (1 + Assumptions!$C$7) ^ INT(((YEAR(P$2)-YEAR($F31))*12 + MONTH(P$2)-MONTH($F31)) / 12), 0) | ... BP31: =IF(AND($F31<=BP$2, OR($G31="",$G31>=BP$2)), $H31 * (1 + Assumptions!$C$7) ^ INT(((YEAR(BP$2)-YEAR($F31))*12 + MONTH(BP$2)-MONTH($F31)) / 12), 0) | BR31: paid this month if started and not yet left; +8% on each work anniversary
A32: 27 | B32: New hire | C32: S&M | D32: R&D Engineer | E32: Planned | F32: 46753 | H32: 7500 | I32: =IF(AND($F32<=I$2, OR($G32="",$G32>=I$2)), $H32 * (1 + Assumptions!$C$7) ^ INT(((YEAR(I$2)-YEAR($F32))*12 + MONTH(I$2)-MONTH($F32)) / 12), 0) | J32: =IF(AND($F32<=J$2, OR($G32="",$G32>=J$2)), $H32 * (1 + Assumptions!$C$7) ^ INT(((YEAR(J$2)-YEAR($F32))*12 + MONTH(J$2)-MONTH($F32)) / 12), 0) | K32: =IF(AND($F32<=K$2, OR($G32="",$G32>=K$2)), $H32 * (1 + Assumptions!$C$7) ^ INT(((YEAR(K$2)-YEAR($F32))*12 + MONTH(K$2)-MONTH($F32)) / 12), 0) | L32: =IF(AND($F32<=L$2, OR($G32="",$G32>=L$2)), $H32 * (1 + Assumptions!$C$7) ^ INT(((YEAR(L$2)-YEAR($F32))*12 + MONTH(L$2)-MONTH($F32)) / 12), 0) | M32: =IF(AND($F32<=M$2, OR($G32="",$G32>=M$2)), $H32 * (1 + Assumptions!$C$7) ^ INT(((YEAR(M$2)-YEAR($F32))*12 + MONTH(M$2)-MONTH($F32)) / 12), 0) | N32: =IF(AND($F32<=N$2, OR($G32="",$G32>=N$2)), $H32 * (1 + Assumptions!$C$7) ^ INT(((YEAR(N$2)-YEAR($F32))*12 + MONTH(N$2)-MONTH($F32)) / 12), 0) | O32: =IF(AND($F32<=O$2, OR($G32="",$G32>=O$2)), $H32 * (1 + Assumptions!$C$7) ^ INT(((YEAR(O$2)-YEAR($F32))*12 + MONTH(O$2)-MONTH($F32)) / 12), 0) | P32: =IF(AND($F32<=P$2, OR($G32="",$G32>=P$2)), $H32 * (1 + Assumptions!$C$7) ^ INT(((YEAR(P$2)-YEAR($F32))*12 + MONTH(P$2)-MONTH($F32)) / 12), 0) | ... BP32: =IF(AND($F32<=BP$2, OR($G32="",$G32>=BP$2)), $H32 * (1 + Assumptions!$C$7) ^ INT(((YEAR(BP$2)-YEAR($F32))*12 + MONTH(BP$2)-MONTH($F32)) / 12), 0) | BR32: paid this month if started and not yet left; +8% on each work anniversary
A33: 28 | B33: New hire | C33: S&M | D33: Partner Manager | E33: Planned | F33: 46753 | H33: 7500 | I33: =IF(AND($F33<=I$2, OR($G33="",$G33>=I$2)), $H33 * (1 + Assumptions!$C$7) ^ INT(((YEAR(I$2)-YEAR($F33))*12 + MONTH(I$2)-MONTH($F33)) / 12), 0) | J33: =IF(AND($F33<=J$2, OR($G33="",$G33>=J$2)), $H33 * (1 + Assumptions!$C$7) ^ INT(((YEAR(J$2)-YEAR($F33))*12 + MONTH(J$2)-MONTH($F33)) / 12), 0) | K33: =IF(AND($F33<=K$2, OR($G33="",$G33>=K$2)), $H33 * (1 + Assumptions!$C$7) ^ INT(((YEAR(K$2)-YEAR($F33))*12 + MONTH(K$2)-MONTH($F33)) / 12), 0) | L33: =IF(AND($F33<=L$2, OR($G33="",$G33>=L$2)), $H33 * (1 + Assumptions!$C$7) ^ INT(((YEAR(L$2)-YEAR($F33))*12 + MONTH(L$2)-MONTH($F33)) / 12), 0) | M33: =IF(AND($F33<=M$2, OR($G33="",$G33>=M$2)), $H33 * (1 + Assumptions!$C$7) ^ INT(((YEAR(M$2)-YEAR($F33))*12 + MONTH(M$2)-MONTH($F33)) / 12), 0) | N33: =IF(AND($F33<=N$2, OR($G33="",$G33>=N$2)), $H33 * (1 + Assumptions!$C$7) ^ INT(((YEAR(N$2)-YEAR($F33))*12 + MONTH(N$2)-MONTH($F33)) / 12), 0) | O33: =IF(AND($F33<=O$2, OR($G33="",$G33>=O$2)), $H33 * (1 + Assumptions!$C$7) ^ INT(((YEAR(O$2)-YEAR($F33))*12 + MONTH(O$2)-MONTH($F33)) / 12), 0) | P33: =IF(AND($F33<=P$2, OR($G33="",$G33>=P$2)), $H33 * (1 + Assumptions!$C$7) ^ INT(((YEAR(P$2)-YEAR($F33))*12 + MONTH(P$2)-MONTH($F33)) / 12), 0) | ... BP33: =IF(AND($F33<=BP$2, OR($G33="",$G33>=BP$2)), $H33 * (1 + Assumptions!$C$7) ^ INT(((YEAR(BP$2)-YEAR($F33))*12 + MONTH(BP$2)-MONTH($F33)) / 12), 0) | BR33: paid this month if started and not yet left; +8% on each work anniversary
A34: 29 | B34: New hire | C34: S&M | D34: Partner Manager | E34: Planned | F34: =IF(Assumptions!$D$82=2,DATE(2027,8,1),DATE(2028,6,2)) | H34: 7500 | I34: =IF(AND($F34<=I$2, OR($G34="",$G34>=I$2)), $H34 * (1 + Assumptions!$C$7) ^ INT(((YEAR(I$2)-YEAR($F34))*12 + MONTH(I$2)-MONTH($F34)) / 12), 0) | J34: =IF(AND($F34<=J$2, OR($G34="",$G34>=J$2)), $H34 * (1 + Assumptions!$C$7) ^ INT(((YEAR(J$2)-YEAR($F34))*12 + MONTH(J$2)-MONTH($F34)) / 12), 0) | K34: =IF(AND($F34<=K$2, OR($G34="",$G34>=K$2)), $H34 * (1 + Assumptions!$C$7) ^ INT(((YEAR(K$2)-YEAR($F34))*12 + MONTH(K$2)-MONTH($F34)) / 12), 0) | L34: =IF(AND($F34<=L$2, OR($G34="",$G34>=L$2)), $H34 * (1 + Assumptions!$C$7) ^ INT(((YEAR(L$2)-YEAR($F34))*12 + MONTH(L$2)-MONTH($F34)) / 12), 0) | M34: =IF(AND($F34<=M$2, OR($G34="",$G34>=M$2)), $H34 * (1 + Assumptions!$C$7) ^ INT(((YEAR(M$2)-YEAR($F34))*12 + MONTH(M$2)-MONTH($F34)) / 12), 0) | N34: =IF(AND($F34<=N$2, OR($G34="",$G34>=N$2)), $H34 * (1 + Assumptions!$C$7) ^ INT(((YEAR(N$2)-YEAR($F34))*12 + MONTH(N$2)-MONTH($F34)) / 12), 0) | O34: =IF(AND($F34<=O$2, OR($G34="",$G34>=O$2)), $H34 * (1 + Assumptions!$C$7) ^ INT(((YEAR(O$2)-YEAR($F34))*12 + MONTH(O$2)-MONTH($F34)) / 12), 0) | P34: =IF(AND($F34<=P$2, OR($G34="",$G34>=P$2)), $H34 * (1 + Assumptions!$C$7) ^ INT(((YEAR(P$2)-YEAR($F34))*12 + MONTH(P$2)-MONTH($F34)) / 12), 0) | ... BP34: =IF(AND($F34<=BP$2, OR($G34="",$G34>=BP$2)), $H34 * (1 + Assumptions!$C$7) ^ INT(((YEAR(BP$2)-YEAR($F34))*12 + MONTH(BP$2)-MONTH($F34)) / 12), 0) | BR34: paid this month if started and not yet left; +8% on each work anniversary
A35: 30 | B35: New hire | C35: S&M | D35: Account Manager | E35: Planned | F35: =IF(Assumptions!$D$82=2,DATE(2027,10,1),DATE(2028,6,3)) | H35: 8000 | I35: =IF(AND($F35<=I$2, OR($G35="",$G35>=I$2)), $H35 * (1 + Assumptions!$C$7) ^ INT(((YEAR(I$2)-YEAR($F35))*12 + MONTH(I$2)-MONTH($F35)) / 12), 0) | J35: =IF(AND($F35<=J$2, OR($G35="",$G35>=J$2)), $H35 * (1 + Assumptions!$C$7) ^ INT(((YEAR(J$2)-YEAR($F35))*12 + MONTH(J$2)-MONTH($F35)) / 12), 0) | K35: =IF(AND($F35<=K$2, OR($G35="",$G35>=K$2)), $H35 * (1 + Assumptions!$C$7) ^ INT(((YEAR(K$2)-YEAR($F35))*12 + MONTH(K$2)-MONTH($F35)) / 12), 0) | L35: =IF(AND($F35<=L$2, OR($G35="",$G35>=L$2)), $H35 * (1 + Assumptions!$C$7) ^ INT(((YEAR(L$2)-YEAR($F35))*12 + MONTH(L$2)-MONTH($F35)) / 12), 0) | M35: =IF(AND($F35<=M$2, OR($G35="",$G35>=M$2)), $H35 * (1 + Assumptions!$C$7) ^ INT(((YEAR(M$2)-YEAR($F35))*12 + MONTH(M$2)-MONTH($F35)) / 12), 0) | N35: =IF(AND($F35<=N$2, OR($G35="",$G35>=N$2)), $H35 * (1 + Assumptions!$C$7) ^ INT(((YEAR(N$2)-YEAR($F35))*12 + MONTH(N$2)-MONTH($F35)) / 12), 0) | O35: =IF(AND($F35<=O$2, OR($G35="",$G35>=O$2)), $H35 * (1 + Assumptions!$C$7) ^ INT(((YEAR(O$2)-YEAR($F35))*12 + MONTH(O$2)-MONTH($F35)) / 12), 0) | P35: =IF(AND($F35<=P$2, OR($G35="",$G35>=P$2)), $H35 * (1 + Assumptions!$C$7) ^ INT(((YEAR(P$2)-YEAR($F35))*12 + MONTH(P$2)-MONTH($F35)) / 12), 0) | ... BP35: =IF(AND($F35<=BP$2, OR($G35="",$G35>=BP$2)), $H35 * (1 + Assumptions!$C$7) ^ INT(((YEAR(BP$2)-YEAR($F35))*12 + MONTH(BP$2)-MONTH($F35)) / 12), 0) | BR35: paid this month if started and not yet left; +8% on each work anniversary
A36: 31 | B36: New hire | C36: S&M | D36: Account Manager | E36: Planned | F36: =IF(Assumptions!$D$82=2,DATE(2028,1,3),DATE(2028,6,4)) | H36: 8000 | I36: =IF(AND($F36<=I$2, OR($G36="",$G36>=I$2)), $H36 * (1 + Assumptions!$C$7) ^ INT(((YEAR(I$2)-YEAR($F36))*12 + MONTH(I$2)-MONTH($F36)) / 12), 0) | J36: =IF(AND($F36<=J$2, OR($G36="",$G36>=J$2)), $H36 * (1 + Assumptions!$C$7) ^ INT(((YEAR(J$2)-YEAR($F36))*12 + MONTH(J$2)-MONTH($F36)) / 12), 0) | K36: =IF(AND($F36<=K$2, OR($G36="",$G36>=K$2)), $H36 * (1 + Assumptions!$C$7) ^ INT(((YEAR(K$2)-YEAR($F36))*12 + MONTH(K$2)-MONTH($F36)) / 12), 0) | L36: =IF(AND($F36<=L$2, OR($G36="",$G36>=L$2)), $H36 * (1 + Assumptions!$C$7) ^ INT(((YEAR(L$2)-YEAR($F36))*12 + MONTH(L$2)-MONTH($F36)) / 12), 0) | M36: =IF(AND($F36<=M$2, OR($G36="",$G36>=M$2)), $H36 * (1 + Assumptions!$C$7) ^ INT(((YEAR(M$2)-YEAR($F36))*12 + MONTH(M$2)-MONTH($F36)) / 12), 0) | N36: =IF(AND($F36<=N$2, OR($G36="",$G36>=N$2)), $H36 * (1 + Assumptions!$C$7) ^ INT(((YEAR(N$2)-YEAR($F36))*12 + MONTH(N$2)-MONTH($F36)) / 12), 0) | O36: =IF(AND($F36<=O$2, OR($G36="",$G36>=O$2)), $H36 * (1 + Assumptions!$C$7) ^ INT(((YEAR(O$2)-YEAR($F36))*12 + MONTH(O$2)-MONTH($F36)) / 12), 0) | P36: =IF(AND($F36<=P$2, OR($G36="",$G36>=P$2)), $H36 * (1 + Assumptions!$C$7) ^ INT(((YEAR(P$2)-YEAR($F36))*12 + MONTH(P$2)-MONTH($F36)) / 12), 0) | ... BP36: =IF(AND($F36<=BP$2, OR($G36="",$G36>=BP$2)), $H36 * (1 + Assumptions!$C$7) ^ INT(((YEAR(BP$2)-YEAR($F36))*12 + MONTH(BP$2)-MONTH($F36)) / 12), 0) | BR36: paid this month if started and not yet left; +8% on each work anniversary
A37: 32 | B37: New hire | C37: G&A | D37: Logistics | E37: Planned | F37: =IF(Assumptions!$D$82=2,DATE(2028,1,1),DATE(2028,10,1)) | H37: 6500 | I37: =IF(AND($F37<=I$2, OR($G37="",$G37>=I$2)), $H37 * (1 + Assumptions!$C$7) ^ INT(((YEAR(I$2)-YEAR($F37))*12 + MONTH(I$2)-MONTH($F37)) / 12), 0) | J37: =IF(AND($F37<=J$2, OR($G37="",$G37>=J$2)), $H37 * (1 + Assumptions!$C$7) ^ INT(((YEAR(J$2)-YEAR($F37))*12 + MONTH(J$2)-MONTH($F37)) / 12), 0) | K37: =IF(AND($F37<=K$2, OR($G37="",$G37>=K$2)), $H37 * (1 + Assumptions!$C$7) ^ INT(((YEAR(K$2)-YEAR($F37))*12 + MONTH(K$2)-MONTH($F37)) / 12), 0) | L37: =IF(AND($F37<=L$2, OR($G37="",$G37>=L$2)), $H37 * (1 + Assumptions!$C$7) ^ INT(((YEAR(L$2)-YEAR($F37))*12 + MONTH(L$2)-MONTH($F37)) / 12), 0) | M37: =IF(AND($F37<=M$2, OR($G37="",$G37>=M$2)), $H37 * (1 + Assumptions!$C$7) ^ INT(((YEAR(M$2)-YEAR($F37))*12 + MONTH(M$2)-MONTH($F37)) / 12), 0) | N37: =IF(AND($F37<=N$2, OR($G37="",$G37>=N$2)), $H37 * (1 + Assumptions!$C$7) ^ INT(((YEAR(N$2)-YEAR($F37))*12 + MONTH(N$2)-MONTH($F37)) / 12), 0) | O37: =IF(AND($F37<=O$2, OR($G37="",$G37>=O$2)), $H37 * (1 + Assumptions!$C$7) ^ INT(((YEAR(O$2)-YEAR($F37))*12 + MONTH(O$2)-MONTH($F37)) / 12), 0) | P37: =IF(AND($F37<=P$2, OR($G37="",$G37>=P$2)), $H37 * (1 + Assumptions!$C$7) ^ INT(((YEAR(P$2)-YEAR($F37))*12 + MONTH(P$2)-MONTH($F37)) / 12), 0) | ... BP37: =IF(AND($F37<=BP$2, OR($G37="",$G37>=BP$2)), $H37 * (1 + Assumptions!$C$7) ^ INT(((YEAR(BP$2)-YEAR($F37))*12 + MONTH(BP$2)-MONTH($F37)) / 12), 0) | BR37: paid this month if started and not yet left; +8% on each work anniversary
A38: 33 | B38: New hire | C38: S&M | D38: Account Manager | E38: Planned | F38: 47027 | H38: 8000 | I38: =IF(AND($F38<=I$2, OR($G38="",$G38>=I$2)), $H38 * (1 + Assumptions!$C$7) ^ INT(((YEAR(I$2)-YEAR($F38))*12 + MONTH(I$2)-MONTH($F38)) / 12), 0) | J38: =IF(AND($F38<=J$2, OR($G38="",$G38>=J$2)), $H38 * (1 + Assumptions!$C$7) ^ INT(((YEAR(J$2)-YEAR($F38))*12 + MONTH(J$2)-MONTH($F38)) / 12), 0) | K38: =IF(AND($F38<=K$2, OR($G38="",$G38>=K$2)), $H38 * (1 + Assumptions!$C$7) ^ INT(((YEAR(K$2)-YEAR($F38))*12 + MONTH(K$2)-MONTH($F38)) / 12), 0) | L38: =IF(AND($F38<=L$2, OR($G38="",$G38>=L$2)), $H38 * (1 + Assumptions!$C$7) ^ INT(((YEAR(L$2)-YEAR($F38))*12 + MONTH(L$2)-MONTH($F38)) / 12), 0) | M38: =IF(AND($F38<=M$2, OR($G38="",$G38>=M$2)), $H38 * (1 + Assumptions!$C$7) ^ INT(((YEAR(M$2)-YEAR($F38))*12 + MONTH(M$2)-MONTH($F38)) / 12), 0) | N38: =IF(AND($F38<=N$2, OR($G38="",$G38>=N$2)), $H38 * (1 + Assumptions!$C$7) ^ INT(((YEAR(N$2)-YEAR($F38))*12 + MONTH(N$2)-MONTH($F38)) / 12), 0) | O38: =IF(AND($F38<=O$2, OR($G38="",$G38>=O$2)), $H38 * (1 + Assumptions!$C$7) ^ INT(((YEAR(O$2)-YEAR($F38))*12 + MONTH(O$2)-MONTH($F38)) / 12), 0) | P38: =IF(AND($F38<=P$2, OR($G38="",$G38>=P$2)), $H38 * (1 + Assumptions!$C$7) ^ INT(((YEAR(P$2)-YEAR($F38))*12 + MONTH(P$2)-MONTH($F38)) / 12), 0) | ... BP38: =IF(AND($F38<=BP$2, OR($G38="",$G38>=BP$2)), $H38 * (1 + Assumptions!$C$7) ^ INT(((YEAR(BP$2)-YEAR($F38))*12 + MONTH(BP$2)-MONTH($F38)) / 12), 0) | BR38: paid this month if started and not yet left; +8% on each work anniversary
A39: 34 | B39: New hire | C39: S&M | D39: Sales | E39: Planned | F39: =IF(Assumptions!$D$82=2,DATE(2027,3,1),DATE(2028,10,1)) | H39: 6500 | I39: =IF(AND($F39<=I$2, OR($G39="",$G39>=I$2)), $H39 * (1 + Assumptions!$C$7) ^ INT(((YEAR(I$2)-YEAR($F39))*12 + MONTH(I$2)-MONTH($F39)) / 12), 0) | J39: =IF(AND($F39<=J$2, OR($G39="",$G39>=J$2)), $H39 * (1 + Assumptions!$C$7) ^ INT(((YEAR(J$2)-YEAR($F39))*12 + MONTH(J$2)-MONTH($F39)) / 12), 0) | K39: =IF(AND($F39<=K$2, OR($G39="",$G39>=K$2)), $H39 * (1 + Assumptions!$C$7) ^ INT(((YEAR(K$2)-YEAR($F39))*12 + MONTH(K$2)-MONTH($F39)) / 12), 0) | L39: =IF(AND($F39<=L$2, OR($G39="",$G39>=L$2)), $H39 * (1 + Assumptions!$C$7) ^ INT(((YEAR(L$2)-YEAR($F39))*12 + MONTH(L$2)-MONTH($F39)) / 12), 0) | M39: =IF(AND($F39<=M$2, OR($G39="",$G39>=M$2)), $H39 * (1 + Assumptions!$C$7) ^ INT(((YEAR(M$2)-YEAR($F39))*12 + MONTH(M$2)-MONTH($F39)) / 12), 0) | N39: =IF(AND($F39<=N$2, OR($G39="",$G39>=N$2)), $H39 * (1 + Assumptions!$C$7) ^ INT(((YEAR(N$2)-YEAR($F39))*12 + MONTH(N$2)-MONTH($F39)) / 12), 0) | O39: =IF(AND($F39<=O$2, OR($G39="",$G39>=O$2)), $H39 * (1 + Assumptions!$C$7) ^ INT(((YEAR(O$2)-YEAR($F39))*12 + MONTH(O$2)-MONTH($F39)) / 12), 0) | P39: =IF(AND($F39<=P$2, OR($G39="",$G39>=P$2)), $H39 * (1 + Assumptions!$C$7) ^ INT(((YEAR(P$2)-YEAR($F39))*12 + MONTH(P$2)-MONTH($F39)) / 12), 0) | ... BP39: =IF(AND($F39<=BP$2, OR($G39="",$G39>=BP$2)), $H39 * (1 + Assumptions!$C$7) ^ INT(((YEAR(BP$2)-YEAR($F39))*12 + MONTH(BP$2)-MONTH($F39)) / 12), 0) | BR39: paid this month if started and not yet left; +8% on each work anniversary
A40: 35 | B40: New hire | C40: S&M | D40: Sales | E40: Planned | F40: =IF(Assumptions!$D$82=2,DATE(2027,4,1),DATE(2028,10,2)) | H40: 6500 | I40: =IF(AND($F40<=I$2, OR($G40="",$G40>=I$2)), $H40 * (1 + Assumptions!$C$7) ^ INT(((YEAR(I$2)-YEAR($F40))*12 + MONTH(I$2)-MONTH($F40)) / 12), 0) | J40: =IF(AND($F40<=J$2, OR($G40="",$G40>=J$2)), $H40 * (1 + Assumptions!$C$7) ^ INT(((YEAR(J$2)-YEAR($F40))*12 + MONTH(J$2)-MONTH($F40)) / 12), 0) | K40: =IF(AND($F40<=K$2, OR($G40="",$G40>=K$2)), $H40 * (1 + Assumptions!$C$7) ^ INT(((YEAR(K$2)-YEAR($F40))*12 + MONTH(K$2)-MONTH($F40)) / 12), 0) | L40: =IF(AND($F40<=L$2, OR($G40="",$G40>=L$2)), $H40 * (1 + Assumptions!$C$7) ^ INT(((YEAR(L$2)-YEAR($F40))*12 + MONTH(L$2)-MONTH($F40)) / 12), 0) | M40: =IF(AND($F40<=M$2, OR($G40="",$G40>=M$2)), $H40 * (1 + Assumptions!$C$7) ^ INT(((YEAR(M$2)-YEAR($F40))*12 + MONTH(M$2)-MONTH($F40)) / 12), 0) | N40: =IF(AND($F40<=N$2, OR($G40="",$G40>=N$2)), $H40 * (1 + Assumptions!$C$7) ^ INT(((YEAR(N$2)-YEAR($F40))*12 + MONTH(N$2)-MONTH($F40)) / 12), 0) | O40: =IF(AND($F40<=O$2, OR($G40="",$G40>=O$2)), $H40 * (1 + Assumptions!$C$7) ^ INT(((YEAR(O$2)-YEAR($F40))*12 + MONTH(O$2)-MONTH($F40)) / 12), 0) | P40: =IF(AND($F40<=P$2, OR($G40="",$G40>=P$2)), $H40 * (1 + Assumptions!$C$7) ^ INT(((YEAR(P$2)-YEAR($F40))*12 + MONTH(P$2)-MONTH($F40)) / 12), 0) | ... BP40: =IF(AND($F40<=BP$2, OR($G40="",$G40>=BP$2)), $H40 * (1 + Assumptions!$C$7) ^ INT(((YEAR(BP$2)-YEAR($F40))*12 + MONTH(BP$2)-MONTH($F40)) / 12), 0) | BR40: paid this month if started and not yet left; +8% on each work anniversary
